Compiled from "Lcs.java"
public class net.oneandone.sushi.util.Lcs {
  private static final java.util.List<?> EMPTY;

  public static <T> java.util.List<T> compute(java.util.List<T>, java.util.List<T>);
    Code:
       0: aload_1
       1: invokeinterface #1,  1            // InterfaceMethod java/util/List.size:()I
       6: iconst_1
       7: iadd
       8: anewarray     #2                  // class java/util/List
      11: astore_2
      12: iconst_0
      13: istore        4
      15: iload         4
      17: aload_2
      18: arraylength
      19: if_icmpge     35
      22: aload_2
      23: iload         4
      25: getstatic     #3                  // Field EMPTY:Ljava/util/List;
      28: aastore
      29: iinc          4, 1
      32: goto          15
      35: aload_0
      36: invokeinterface #4,  1            // InterfaceMethod java/util/List.iterator:()Ljava/util/Iterator;
      41: astore        4
      43: aload         4
      45: invokeinterface #5,  1            // InterfaceMethod java/util/Iterator.hasNext:()Z
      50: ifeq          154
      53: aload         4
      55: invokeinterface #6,  1            // InterfaceMethod java/util/Iterator.next:()Ljava/lang/Object;
      60: astore        5
      62: aload_1
      63: invokeinterface #1,  1            // InterfaceMethod java/util/List.size:()I
      68: iconst_1
      69: iadd
      70: anewarray     #2                  // class java/util/List
      73: astore_3
      74: aload_3
      75: iconst_0
      76: getstatic     #3                  // Field EMPTY:Ljava/util/List;
      79: aastore
      80: iconst_1
      81: istore        6
      83: iload         6
      85: aload_3
      86: arraylength
      87: if_icmpge     149
      90: aload         5
      92: aload_1
      93: iload         6
      95: iconst_1
      96: isub
      97: invokeinterface #7,  2            // InterfaceMethod java/util/List.get:(I)Ljava/lang/Object;
     102: invokevirtual #8                  // Method java/lang/Object.equals:(Ljava/lang/Object;)Z
     105: ifeq          126
     108: aload_3
     109: iload         6
     111: aload_2
     112: iload         6
     114: iconst_1
     115: isub
     116: aaload
     117: aload         5
     119: invokestatic  #9                  // Method append:(Ljava/util/List;Ljava/lang/Object;)Ljava/util/List;
     122: aastore
     123: goto          143
     126: aload_3
     127: iload         6
     129: aload_3
     130: iload         6
     132: iconst_1
     133: isub
     134: aaload
     135: aload_2
     136: iload         6
     138: aaload
     139: invokestatic  #10                 // Method longest:(Ljava/util/List;Ljava/util/List;)Ljava/util/List;
     142: aastore
     143: iinc          6, 1
     146: goto          83
     149: aload_3
     150: astore_2
     151: goto          43
     154: aload_2
     155: aload_2
     156: arraylength
     157: iconst_1
     158: isub
     159: aaload
     160: areturn

  private static <T> java.util.List<T> append(java.util.List<T>, T);
    Code:
       0: new           #11                 // class java/util/ArrayList
       3: dup
       4: aload_0
       5: invokeinterface #1,  1            // InterfaceMethod java/util/List.size:()I
      10: iconst_1
      11: iadd
      12: invokespecial #12                 // Method java/util/ArrayList."<init>":(I)V
      15: astore_2
      16: aload_2
      17: aload_0
      18: invokeinterface #13,  2           // InterfaceMethod java/util/List.addAll:(Ljava/util/Collection;)Z
      23: pop
      24: aload_2
      25: aload_1
      26: invokeinterface #14,  2           // InterfaceMethod java/util/List.add:(Ljava/lang/Object;)Z
      31: pop
      32: aload_2
      33: areturn

  private static <T> java.util.List<T> longest(java.util.List<T>, java.util.List<T>);
    Code:
       0: new           #11                 // class java/util/ArrayList
       3: dup
       4: aload_0
       5: invokeinterface #1,  1            // InterfaceMethod java/util/List.size:()I
      10: aload_1
      11: invokeinterface #1,  1            // InterfaceMethod java/util/List.size:()I
      16: if_icmplt     23
      19: aload_0
      20: goto          24
      23: aload_1
      24: invokespecial #15                 // Method java/util/ArrayList."<init>":(Ljava/util/Collection;)V
      27: areturn

  private net.oneandone.sushi.util.Lcs();
    Code:
       0: aload_0
       1: invokespecial #16                 // Method java/lang/Object."<init>":()V
       4: return

  static {};
    Code:
       0: new           #11                 // class java/util/ArrayList
       3: dup
       4: iconst_0
       5: invokespecial #12                 // Method java/util/ArrayList."<init>":(I)V
       8: putstatic     #3                  // Field EMPTY:Ljava/util/List;
      11: return
}
