Compiled from "NetRc.java"
public class net.oneandone.sushi.util.NetRc$Authenticator {
  private final java.lang.String user;

  private final java.lang.String pass;

  public net.oneandone.sushi.util.NetRc$Authenticator(java.lang.String, java.lang.String);
    Code:
       0: aload_0
       1: invokespecial #1                  // Method java/lang/Object."<init>":()V
       4: aload_0
       5: aload_1
       6: putfield      #2                  // Field user:Ljava/lang/String;
       9: aload_0
      10: aload_2
      11: putfield      #3                  // Field pass:Ljava/lang/String;
      14: return

  public java.lang.String getUser();
    Code:
       0: aload_0
       1: getfield      #2                  // Field user:Ljava/lang/String;
       4: areturn

  public java.lang.String getPass();
    Code:
       0: aload_0
       1: getfield      #3                  // Field pass:Ljava/lang/String;
       4: areturn

  public int hashCode();
    Code:
       0: iconst_5
       1: istore_1
       2: bipush        17
       4: iload_1
       5: imul
       6: aload_0
       7: getfield      #2                  // Field user:Ljava/lang/String;
      10: invokestatic  #4                  // Method java/util/Objects.hashCode:(Ljava/lang/Object;)I
      13: iadd
      14: istore_1
      15: bipush        17
      17: iload_1
      18: imul
      19: aload_0
      20: getfield      #3                  // Field pass:Ljava/lang/String;
      23: invokestatic  #4                  // Method java/util/Objects.hashCode:(Ljava/lang/Object;)I
      26: iadd
      27: istore_1
      28: iload_1
      29: ireturn

  public boolean equals(java.lang.Object);
    Code:
       0: aload_1
       1: ifnonnull     6
       4: iconst_0
       5: ireturn
       6: aload_0
       7: invokevirtual #5                  // Method java/lang/Object.getClass:()Ljava/lang/Class;
      10: aload_1
      11: invokevirtual #5                  // Method java/lang/Object.getClass:()Ljava/lang/Class;
      14: if_acmpeq     19
      17: iconst_0
      18: ireturn
      19: aload_1
      20: checkcast     #6                  // class net/oneandone/sushi/util/NetRc$Authenticator
      23: astore_2
      24: aload_0
      25: getfield      #2                  // Field user:Ljava/lang/String;
      28: aload_2
      29: getfield      #2                  // Field user:Ljava/lang/String;
      32: invokestatic  #7                  // Method java/util/Objects.equals:(Ljava/lang/Object;Ljava/lang/Object;)Z
      35: ifne          40
      38: iconst_0
      39: ireturn
      40: aload_0
      41: getfield      #3                  // Field pass:Ljava/lang/String;
      44: aload_2
      45: getfield      #3                  // Field pass:Ljava/lang/String;
      48: invokestatic  #7                  // Method java/util/Objects.equals:(Ljava/lang/Object;Ljava/lang/Object;)Z
      51: ireturn

  public java.lang.String toString();
    Code:
       0: new           #8                  // class java/lang/StringBuilder
       3: dup
       4: invokespecial #9                  // Method java/lang/StringBuilder."<init>":()V
       7: ldc           #10                 // String NetRc.Authenticator{user=
       9: invokevirtual #11                 // Method java/lang/StringBuilder.append:(Ljava/lang/String;)Ljava/lang/StringBuilder;
      12: aload_0
      13: getfield      #2                  // Field user:Ljava/lang/String;
      16: invokevirtual #11                 // Method java/lang/StringBuilder.append:(Ljava/lang/String;)Ljava/lang/StringBuilder;
      19: ldc           #12                 // String , pass=
      21: invokevirtual #11                 // Method java/lang/StringBuilder.append:(Ljava/lang/String;)Ljava/lang/StringBuilder;
      24: aload_0
      25: getfield      #3                  // Field pass:Ljava/lang/String;
      28: invokevirtual #11                 // Method java/lang/StringBuilder.append:(Ljava/lang/String;)Ljava/lang/StringBuilder;
      31: bipush        125
      33: invokevirtual #13                 // Method java/lang/StringBuilder.append:(C)Ljava/lang/StringBuilder;
      36: invokevirtual #14                 // Method java/lang/StringBuilder.toString:()Ljava/lang/String;
      39: areturn
}
