Compiled from "GetPublicKeyResponse.kt"
public final class aws.sdk.kotlin.services.kms.model.GetPublicKeyResponse$Builder {
  private aws.sdk.kotlin.services.kms.model.CustomerMasterKeySpec customerMasterKeySpec;

  private java.util.List<? extends aws.sdk.kotlin.services.kms.model.EncryptionAlgorithmSpec> encryptionAlgorithms;

  private java.lang.String keyId;

  private aws.sdk.kotlin.services.kms.model.KeySpec keySpec;

  private aws.sdk.kotlin.services.kms.model.KeyUsageType keyUsage;

  private byte[] publicKey;

  private java.util.List<? extends aws.sdk.kotlin.services.kms.model.SigningAlgorithmSpec> signingAlgorithms;

  public final aws.sdk.kotlin.services.kms.model.CustomerMasterKeySpec getCustomerMasterKeySpec();
    Code:
       0: aload_0
       1: getfield      #11                 // Field customerMasterKeySpec:Laws/sdk/kotlin/services/kms/model/CustomerMasterKeySpec;
       4: areturn

  public final void setCustomerMasterKeySpec(aws.sdk.kotlin.services.kms.model.CustomerMasterKeySpec);
    Code:
       0: aload_0
       1: aload_1
       2: putfield      #11                 // Field customerMasterKeySpec:Laws/sdk/kotlin/services/kms/model/CustomerMasterKeySpec;
       5: return

  public static void getCustomerMasterKeySpec$annotations();
    Code:
       0: return

  public final java.util.List<aws.sdk.kotlin.services.kms.model.EncryptionAlgorithmSpec> getEncryptionAlgorithms();
    Code:
       0: aload_0
       1: getfield      #28                 // Field encryptionAlgorithms:Ljava/util/List;
       4: areturn

  public final void setEncryptionAlgorithms(java.util.List<? extends aws.sdk.kotlin.services.kms.model.EncryptionAlgorithmSpec>);
    Code:
       0: aload_0
       1: aload_1
       2: putfield      #28                 // Field encryptionAlgorithms:Ljava/util/List;
       5: return

  public final java.lang.String getKeyId();
    Code:
       0: aload_0
       1: getfield      #37                 // Field keyId:Ljava/lang/String;
       4: areturn

  public final void setKeyId(java.lang.String);
    Code:
       0: aload_0
       1: aload_1
       2: putfield      #37                 // Field keyId:Ljava/lang/String;
       5: return

  public final aws.sdk.kotlin.services.kms.model.KeySpec getKeySpec();
    Code:
       0: aload_0
       1: getfield      #45                 // Field keySpec:Laws/sdk/kotlin/services/kms/model/KeySpec;
       4: areturn

  public final void setKeySpec(aws.sdk.kotlin.services.kms.model.KeySpec);
    Code:
       0: aload_0
       1: aload_1
       2: putfield      #45                 // Field keySpec:Laws/sdk/kotlin/services/kms/model/KeySpec;
       5: return

  public final aws.sdk.kotlin.services.kms.model.KeyUsageType getKeyUsage();
    Code:
       0: aload_0
       1: getfield      #53                 // Field keyUsage:Laws/sdk/kotlin/services/kms/model/KeyUsageType;
       4: areturn

  public final void setKeyUsage(aws.sdk.kotlin.services.kms.model.KeyUsageType);
    Code:
       0: aload_0
       1: aload_1
       2: putfield      #53                 // Field keyUsage:Laws/sdk/kotlin/services/kms/model/KeyUsageType;
       5: return

  public final byte[] getPublicKey();
    Code:
       0: aload_0
       1: getfield      #61                 // Field publicKey:[B
       4: areturn

  public final void setPublicKey(byte[]);
    Code:
       0: aload_0
       1: aload_1
       2: putfield      #61                 // Field publicKey:[B
       5: return

  public final java.util.List<aws.sdk.kotlin.services.kms.model.SigningAlgorithmSpec> getSigningAlgorithms();
    Code:
       0: aload_0
       1: getfield      #68                 // Field signingAlgorithms:Ljava/util/List;
       4: areturn

  public final void setSigningAlgorithms(java.util.List<? extends aws.sdk.kotlin.services.kms.model.SigningAlgorithmSpec>);
    Code:
       0: aload_0
       1: aload_1
       2: putfield      #68                 // Field signingAlgorithms:Ljava/util/List;
       5: return

  public aws.sdk.kotlin.services.kms.model.GetPublicKeyResponse$Builder();
    Code:
       0: aload_0
       1: invokespecial #73                 // Method java/lang/Object."<init>":()V
       4: return

  public aws.sdk.kotlin.services.kms.model.GetPublicKeyResponse$Builder(aws.sdk.kotlin.services.kms.model.GetPublicKeyResponse);
    Code:
       0: aload_1
       1: ldc           #78                 // String x
       3: invokestatic  #84                 // Method kotlin/jvm/internal/Intrinsics.checkNotNullParameter:(Ljava/lang/Object;Ljava/lang/String;)V
       6: aload_0
       7: invokespecial #85                 // Method "<init>":()V
      10: aload_0
      11: aload_1
      12: invokevirtual #89                 // Method aws/sdk/kotlin/services/kms/model/GetPublicKeyResponse.getCustomerMasterKeySpec:()Laws/sdk/kotlin/services/kms/model/CustomerMasterKeySpec;
      15: putfield      #11                 // Field customerMasterKeySpec:Laws/sdk/kotlin/services/kms/model/CustomerMasterKeySpec;
      18: aload_0
      19: aload_1
      20: invokevirtual #91                 // Method aws/sdk/kotlin/services/kms/model/GetPublicKeyResponse.getEncryptionAlgorithms:()Ljava/util/List;
      23: putfield      #28                 // Field encryptionAlgorithms:Ljava/util/List;
      26: aload_0
      27: aload_1
      28: invokevirtual #93                 // Method aws/sdk/kotlin/services/kms/model/GetPublicKeyResponse.getKeyId:()Ljava/lang/String;
      31: putfield      #37                 // Field keyId:Ljava/lang/String;
      34: aload_0
      35: aload_1
      36: invokevirtual #95                 // Method aws/sdk/kotlin/services/kms/model/GetPublicKeyResponse.getKeySpec:()Laws/sdk/kotlin/services/kms/model/KeySpec;
      39: putfield      #45                 // Field keySpec:Laws/sdk/kotlin/services/kms/model/KeySpec;
      42: aload_0
      43: aload_1
      44: invokevirtual #97                 // Method aws/sdk/kotlin/services/kms/model/GetPublicKeyResponse.getKeyUsage:()Laws/sdk/kotlin/services/kms/model/KeyUsageType;
      47: putfield      #53                 // Field keyUsage:Laws/sdk/kotlin/services/kms/model/KeyUsageType;
      50: aload_0
      51: aload_1
      52: invokevirtual #99                 // Method aws/sdk/kotlin/services/kms/model/GetPublicKeyResponse.getPublicKey:()[B
      55: putfield      #61                 // Field publicKey:[B
      58: aload_0
      59: aload_1
      60: invokevirtual #101                // Method aws/sdk/kotlin/services/kms/model/GetPublicKeyResponse.getSigningAlgorithms:()Ljava/util/List;
      63: putfield      #68                 // Field signingAlgorithms:Ljava/util/List;
      66: return

  public final aws.sdk.kotlin.services.kms.model.GetPublicKeyResponse build();
    Code:
       0: new           #87                 // class aws/sdk/kotlin/services/kms/model/GetPublicKeyResponse
       3: dup
       4: aload_0
       5: aconst_null
       6: invokespecial #107                // Method aws/sdk/kotlin/services/kms/model/GetPublicKeyResponse."<init>":(Laws/sdk/kotlin/services/kms/model/GetPublicKeyResponse$Builder;Lkotlin/jvm/internal/DefaultConstructorMarker;)V
       9: areturn
}
