Compiled from "KeyMetadata.kt"
public final class aws.sdk.kotlin.services.kms.model.KeyMetadata$Builder {
  private java.lang.String arn;

  private java.lang.String awsAccountId;

  private java.lang.String cloudHsmClusterId;

  private aws.smithy.kotlin.runtime.time.Instant creationDate;

  private java.lang.String customKeyStoreId;

  private aws.sdk.kotlin.services.kms.model.CustomerMasterKeySpec customerMasterKeySpec;

  private aws.smithy.kotlin.runtime.time.Instant deletionDate;

  private java.lang.String description;

  private boolean enabled;

  private java.util.List<? extends aws.sdk.kotlin.services.kms.model.EncryptionAlgorithmSpec> encryptionAlgorithms;

  private aws.sdk.kotlin.services.kms.model.ExpirationModelType expirationModel;

  private java.lang.String keyId;

  private aws.sdk.kotlin.services.kms.model.KeyManagerType keyManager;

  private aws.sdk.kotlin.services.kms.model.KeySpec keySpec;

  private aws.sdk.kotlin.services.kms.model.KeyState keyState;

  private aws.sdk.kotlin.services.kms.model.KeyUsageType keyUsage;

  private java.util.List<? extends aws.sdk.kotlin.services.kms.model.MacAlgorithmSpec> macAlgorithms;

  private java.lang.Boolean multiRegion;

  private aws.sdk.kotlin.services.kms.model.MultiRegionConfiguration multiRegionConfiguration;

  private aws.sdk.kotlin.services.kms.model.OriginType origin;

  private java.lang.Integer pendingDeletionWindowInDays;

  private java.util.List<? extends aws.sdk.kotlin.services.kms.model.SigningAlgorithmSpec> signingAlgorithms;

  private aws.smithy.kotlin.runtime.time.Instant validTo;

  public final java.lang.String getArn();
    Code:
       0: aload_0
       1: getfield      #11                 // Field arn:Ljava/lang/String;
       4: areturn

  public final void setArn(java.lang.String);
    Code:
       0: aload_0
       1: aload_1
       2: putfield      #11                 // Field arn:Ljava/lang/String;
       5: return

  public final java.lang.String getAwsAccountId();
    Code:
       0: aload_0
       1: getfield      #20                 // Field awsAccountId:Ljava/lang/String;
       4: areturn

  public final void setAwsAccountId(java.lang.String);
    Code:
       0: aload_0
       1: aload_1
       2: putfield      #20                 // Field awsAccountId:Ljava/lang/String;
       5: return

  public final java.lang.String getCloudHsmClusterId();
    Code:
       0: aload_0
       1: getfield      #25                 // Field cloudHsmClusterId:Ljava/lang/String;
       4: areturn

  public final void setCloudHsmClusterId(java.lang.String);
    Code:
       0: aload_0
       1: aload_1
       2: putfield      #25                 // Field cloudHsmClusterId:Ljava/lang/String;
       5: return

  public final aws.smithy.kotlin.runtime.time.Instant getCreationDate();
    Code:
       0: aload_0
       1: getfield      #32                 // Field creationDate:Laws/smithy/kotlin/runtime/time/Instant;
       4: areturn

  public final void setCreationDate(aws.smithy.kotlin.runtime.time.Instant);
    Code:
       0: aload_0
       1: aload_1
       2: putfield      #32                 // Field creationDate:Laws/smithy/kotlin/runtime/time/Instant;
       5: return

  public final java.lang.String getCustomKeyStoreId();
    Code:
       0: aload_0
       1: getfield      #38                 // Field customKeyStoreId:Ljava/lang/String;
       4: areturn

  public final void setCustomKeyStoreId(java.lang.String);
    Code:
       0: aload_0
       1: aload_1
       2: putfield      #38                 // Field customKeyStoreId:Ljava/lang/String;
       5: return

  public final aws.sdk.kotlin.services.kms.model.CustomerMasterKeySpec getCustomerMasterKeySpec();
    Code:
       0: aload_0
       1: getfield      #45                 // Field customerMasterKeySpec:Laws/sdk/kotlin/services/kms/model/CustomerMasterKeySpec;
       4: areturn

  public final void setCustomerMasterKeySpec(aws.sdk.kotlin.services.kms.model.CustomerMasterKeySpec);
    Code:
       0: aload_0
       1: aload_1
       2: putfield      #45                 // Field customerMasterKeySpec:Laws/sdk/kotlin/services/kms/model/CustomerMasterKeySpec;
       5: return

  public static void getCustomerMasterKeySpec$annotations();
    Code:
       0: return

  public final aws.smithy.kotlin.runtime.time.Instant getDeletionDate();
    Code:
       0: aload_0
       1: getfield      #56                 // Field deletionDate:Laws/smithy/kotlin/runtime/time/Instant;
       4: areturn

  public final void setDeletionDate(aws.smithy.kotlin.runtime.time.Instant);
    Code:
       0: aload_0
       1: aload_1
       2: putfield      #56                 // Field deletionDate:Laws/smithy/kotlin/runtime/time/Instant;
       5: return

  public final java.lang.String getDescription();
    Code:
       0: aload_0
       1: getfield      #61                 // Field description:Ljava/lang/String;
       4: areturn

  public final void setDescription(java.lang.String);
    Code:
       0: aload_0
       1: aload_1
       2: putfield      #61                 // Field description:Ljava/lang/String;
       5: return

  public final boolean getEnabled();
    Code:
       0: aload_0
       1: getfield      #68                 // Field enabled:Z
       4: ireturn

  public final void setEnabled(boolean);
    Code:
       0: aload_0
       1: iload_1
       2: putfield      #68                 // Field enabled:Z
       5: return

  public final java.util.List<aws.sdk.kotlin.services.kms.model.EncryptionAlgorithmSpec> getEncryptionAlgorithms();
    Code:
       0: aload_0
       1: getfield      #77                 // Field encryptionAlgorithms:Ljava/util/List;
       4: areturn

  public final void setEncryptionAlgorithms(java.util.List<? extends aws.sdk.kotlin.services.kms.model.EncryptionAlgorithmSpec>);
    Code:
       0: aload_0
       1: aload_1
       2: putfield      #77                 // Field encryptionAlgorithms:Ljava/util/List;
       5: return

  public final aws.sdk.kotlin.services.kms.model.ExpirationModelType getExpirationModel();
    Code:
       0: aload_0
       1: getfield      #86                 // Field expirationModel:Laws/sdk/kotlin/services/kms/model/ExpirationModelType;
       4: areturn

  public final void setExpirationModel(aws.sdk.kotlin.services.kms.model.ExpirationModelType);
    Code:
       0: aload_0
       1: aload_1
       2: putfield      #86                 // Field expirationModel:Laws/sdk/kotlin/services/kms/model/ExpirationModelType;
       5: return

  public final java.lang.String getKeyId();
    Code:
       0: aload_0
       1: getfield      #92                 // Field keyId:Ljava/lang/String;
       4: areturn

  public final void setKeyId(java.lang.String);
    Code:
       0: aload_0
       1: aload_1
       2: putfield      #92                 // Field keyId:Ljava/lang/String;
       5: return

  public final aws.sdk.kotlin.services.kms.model.KeyManagerType getKeyManager();
    Code:
       0: aload_0
       1: getfield      #99                 // Field keyManager:Laws/sdk/kotlin/services/kms/model/KeyManagerType;
       4: areturn

  public final void setKeyManager(aws.sdk.kotlin.services.kms.model.KeyManagerType);
    Code:
       0: aload_0
       1: aload_1
       2: putfield      #99                 // Field keyManager:Laws/sdk/kotlin/services/kms/model/KeyManagerType;
       5: return

  public final aws.sdk.kotlin.services.kms.model.KeySpec getKeySpec();
    Code:
       0: aload_0
       1: getfield      #107                // Field keySpec:Laws/sdk/kotlin/services/kms/model/KeySpec;
       4: areturn

  public final void setKeySpec(aws.sdk.kotlin.services.kms.model.KeySpec);
    Code:
       0: aload_0
       1: aload_1
       2: putfield      #107                // Field keySpec:Laws/sdk/kotlin/services/kms/model/KeySpec;
       5: return

  public final aws.sdk.kotlin.services.kms.model.KeyState getKeyState();
    Code:
       0: aload_0
       1: getfield      #115                // Field keyState:Laws/sdk/kotlin/services/kms/model/KeyState;
       4: areturn

  public final void setKeyState(aws.sdk.kotlin.services.kms.model.KeyState);
    Code:
       0: aload_0
       1: aload_1
       2: putfield      #115                // Field keyState:Laws/sdk/kotlin/services/kms/model/KeyState;
       5: return

  public final aws.sdk.kotlin.services.kms.model.KeyUsageType getKeyUsage();
    Code:
       0: aload_0
       1: getfield      #123                // Field keyUsage:Laws/sdk/kotlin/services/kms/model/KeyUsageType;
       4: areturn

  public final void setKeyUsage(aws.sdk.kotlin.services.kms.model.KeyUsageType);
    Code:
       0: aload_0
       1: aload_1
       2: putfield      #123                // Field keyUsage:Laws/sdk/kotlin/services/kms/model/KeyUsageType;
       5: return

  public final java.util.List<aws.sdk.kotlin.services.kms.model.MacAlgorithmSpec> getMacAlgorithms();
    Code:
       0: aload_0
       1: getfield      #130                // Field macAlgorithms:Ljava/util/List;
       4: areturn

  public final void setMacAlgorithms(java.util.List<? extends aws.sdk.kotlin.services.kms.model.MacAlgorithmSpec>);
    Code:
       0: aload_0
       1: aload_1
       2: putfield      #130                // Field macAlgorithms:Ljava/util/List;
       5: return

  public final java.lang.Boolean getMultiRegion();
    Code:
       0: aload_0
       1: getfield      #138                // Field multiRegion:Ljava/lang/Boolean;
       4: areturn

  public final void setMultiRegion(java.lang.Boolean);
    Code:
       0: aload_0
       1: aload_1
       2: putfield      #138                // Field multiRegion:Ljava/lang/Boolean;
       5: return

  public final aws.sdk.kotlin.services.kms.model.MultiRegionConfiguration getMultiRegionConfiguration();
    Code:
       0: aload_0
       1: getfield      #146                // Field multiRegionConfiguration:Laws/sdk/kotlin/services/kms/model/MultiRegionConfiguration;
       4: areturn

  public final void setMultiRegionConfiguration(aws.sdk.kotlin.services.kms.model.MultiRegionConfiguration);
    Code:
       0: aload_0
       1: aload_1
       2: putfield      #146                // Field multiRegionConfiguration:Laws/sdk/kotlin/services/kms/model/MultiRegionConfiguration;
       5: return

  public final aws.sdk.kotlin.services.kms.model.OriginType getOrigin();
    Code:
       0: aload_0
       1: getfield      #154                // Field origin:Laws/sdk/kotlin/services/kms/model/OriginType;
       4: areturn

  public final void setOrigin(aws.sdk.kotlin.services.kms.model.OriginType);
    Code:
       0: aload_0
       1: aload_1
       2: putfield      #154                // Field origin:Laws/sdk/kotlin/services/kms/model/OriginType;
       5: return

  public final java.lang.Integer getPendingDeletionWindowInDays();
    Code:
       0: aload_0
       1: getfield      #162                // Field pendingDeletionWindowInDays:Ljava/lang/Integer;
       4: areturn

  public final void setPendingDeletionWindowInDays(java.lang.Integer);
    Code:
       0: aload_0
       1: aload_1
       2: putfield      #162                // Field pendingDeletionWindowInDays:Ljava/lang/Integer;
       5: return

  public final java.util.List<aws.sdk.kotlin.services.kms.model.SigningAlgorithmSpec> getSigningAlgorithms();
    Code:
       0: aload_0
       1: getfield      #169                // Field signingAlgorithms:Ljava/util/List;
       4: areturn

  public final void setSigningAlgorithms(java.util.List<? extends aws.sdk.kotlin.services.kms.model.SigningAlgorithmSpec>);
    Code:
       0: aload_0
       1: aload_1
       2: putfield      #169                // Field signingAlgorithms:Ljava/util/List;
       5: return

  public final aws.smithy.kotlin.runtime.time.Instant getValidTo();
    Code:
       0: aload_0
       1: getfield      #175                // Field validTo:Laws/smithy/kotlin/runtime/time/Instant;
       4: areturn

  public final void setValidTo(aws.smithy.kotlin.runtime.time.Instant);
    Code:
       0: aload_0
       1: aload_1
       2: putfield      #175                // Field validTo:Laws/smithy/kotlin/runtime/time/Instant;
       5: return

  public aws.sdk.kotlin.services.kms.model.KeyMetadata$Builder();
    Code:
       0: aload_0
       1: invokespecial #179                // Method java/lang/Object."<init>":()V
       4: return

  public aws.sdk.kotlin.services.kms.model.KeyMetadata$Builder(aws.sdk.kotlin.services.kms.model.KeyMetadata);
    Code:
       0: aload_1
       1: ldc           #184                // String x
       3: invokestatic  #190                // Method kotlin/jvm/internal/Intrinsics.checkNotNullParameter:(Ljava/lang/Object;Ljava/lang/String;)V
       6: aload_0
       7: invokespecial #191                // Method "<init>":()V
      10: aload_0
      11: aload_1
      12: invokevirtual #195                // Method aws/sdk/kotlin/services/kms/model/KeyMetadata.getArn:()Ljava/lang/String;
      15: putfield      #11                 // Field arn:Ljava/lang/String;
      18: aload_0
      19: aload_1
      20: invokevirtual #197                // Method aws/sdk/kotlin/services/kms/model/KeyMetadata.getAwsAccountId:()Ljava/lang/String;
      23: putfield      #20                 // Field awsAccountId:Ljava/lang/String;
      26: aload_0
      27: aload_1
      28: invokevirtual #199                // Method aws/sdk/kotlin/services/kms/model/KeyMetadata.getCloudHsmClusterId:()Ljava/lang/String;
      31: putfield      #25                 // Field cloudHsmClusterId:Ljava/lang/String;
      34: aload_0
      35: aload_1
      36: invokevirtual #201                // Method aws/sdk/kotlin/services/kms/model/KeyMetadata.getCreationDate:()Laws/smithy/kotlin/runtime/time/Instant;
      39: putfield      #32                 // Field creationDate:Laws/smithy/kotlin/runtime/time/Instant;
      42: aload_0
      43: aload_1
      44: invokevirtual #203                // Method aws/sdk/kotlin/services/kms/model/KeyMetadata.getCustomKeyStoreId:()Ljava/lang/String;
      47: putfield      #38                 // Field customKeyStoreId:Ljava/lang/String;
      50: aload_0
      51: aload_1
      52: invokevirtual #205                // Method aws/sdk/kotlin/services/kms/model/KeyMetadata.getCustomerMasterKeySpec:()Laws/sdk/kotlin/services/kms/model/CustomerMasterKeySpec;
      55: putfield      #45                 // Field customerMasterKeySpec:Laws/sdk/kotlin/services/kms/model/CustomerMasterKeySpec;
      58: aload_0
      59: aload_1
      60: invokevirtual #207                // Method aws/sdk/kotlin/services/kms/model/KeyMetadata.getDeletionDate:()Laws/smithy/kotlin/runtime/time/Instant;
      63: putfield      #56                 // Field deletionDate:Laws/smithy/kotlin/runtime/time/Instant;
      66: aload_0
      67: aload_1
      68: invokevirtual #209                // Method aws/sdk/kotlin/services/kms/model/KeyMetadata.getDescription:()Ljava/lang/String;
      71: putfield      #61                 // Field description:Ljava/lang/String;
      74: aload_0
      75: aload_1
      76: invokevirtual #211                // Method aws/sdk/kotlin/services/kms/model/KeyMetadata.getEnabled:()Z
      79: putfield      #68                 // Field enabled:Z
      82: aload_0
      83: aload_1
      84: invokevirtual #213                // Method aws/sdk/kotlin/services/kms/model/KeyMetadata.getEncryptionAlgorithms:()Ljava/util/List;
      87: putfield      #77                 // Field encryptionAlgorithms:Ljava/util/List;
      90: aload_0
      91: aload_1
      92: invokevirtual #215                // Method aws/sdk/kotlin/services/kms/model/KeyMetadata.getExpirationModel:()Laws/sdk/kotlin/services/kms/model/ExpirationModelType;
      95: putfield      #86                 // Field expirationModel:Laws/sdk/kotlin/services/kms/model/ExpirationModelType;
      98: aload_0
      99: aload_1
     100: invokevirtual #217                // Method aws/sdk/kotlin/services/kms/model/KeyMetadata.getKeyId:()Ljava/lang/String;
     103: putfield      #92                 // Field keyId:Ljava/lang/String;
     106: aload_0
     107: aload_1
     108: invokevirtual #219                // Method aws/sdk/kotlin/services/kms/model/KeyMetadata.getKeyManager:()Laws/sdk/kotlin/services/kms/model/KeyManagerType;
     111: putfield      #99                 // Field keyManager:Laws/sdk/kotlin/services/kms/model/KeyManagerType;
     114: aload_0
     115: aload_1
     116: invokevirtual #221                // Method aws/sdk/kotlin/services/kms/model/KeyMetadata.getKeySpec:()Laws/sdk/kotlin/services/kms/model/KeySpec;
     119: putfield      #107                // Field keySpec:Laws/sdk/kotlin/services/kms/model/KeySpec;
     122: aload_0
     123: aload_1
     124: invokevirtual #223                // Method aws/sdk/kotlin/services/kms/model/KeyMetadata.getKeyState:()Laws/sdk/kotlin/services/kms/model/KeyState;
     127: putfield      #115                // Field keyState:Laws/sdk/kotlin/services/kms/model/KeyState;
     130: aload_0
     131: aload_1
     132: invokevirtual #225                // Method aws/sdk/kotlin/services/kms/model/KeyMetadata.getKeyUsage:()Laws/sdk/kotlin/services/kms/model/KeyUsageType;
     135: putfield      #123                // Field keyUsage:Laws/sdk/kotlin/services/kms/model/KeyUsageType;
     138: aload_0
     139: aload_1
     140: invokevirtual #227                // Method aws/sdk/kotlin/services/kms/model/KeyMetadata.getMacAlgorithms:()Ljava/util/List;
     143: putfield      #130                // Field macAlgorithms:Ljava/util/List;
     146: aload_0
     147: aload_1
     148: invokevirtual #229                // Method aws/sdk/kotlin/services/kms/model/KeyMetadata.getMultiRegion:()Ljava/lang/Boolean;
     151: putfield      #138                // Field multiRegion:Ljava/lang/Boolean;
     154: aload_0
     155: aload_1
     156: invokevirtual #231                // Method aws/sdk/kotlin/services/kms/model/KeyMetadata.getMultiRegionConfiguration:()Laws/sdk/kotlin/services/kms/model/MultiRegionConfiguration;
     159: putfield      #146                // Field multiRegionConfiguration:Laws/sdk/kotlin/services/kms/model/MultiRegionConfiguration;
     162: aload_0
     163: aload_1
     164: invokevirtual #233                // Method aws/sdk/kotlin/services/kms/model/KeyMetadata.getOrigin:()Laws/sdk/kotlin/services/kms/model/OriginType;
     167: putfield      #154                // Field origin:Laws/sdk/kotlin/services/kms/model/OriginType;
     170: aload_0
     171: aload_1
     172: invokevirtual #235                // Method aws/sdk/kotlin/services/kms/model/KeyMetadata.getPendingDeletionWindowInDays:()Ljava/lang/Integer;
     175: putfield      #162                // Field pendingDeletionWindowInDays:Ljava/lang/Integer;
     178: aload_0
     179: aload_1
     180: invokevirtual #237                // Method aws/sdk/kotlin/services/kms/model/KeyMetadata.getSigningAlgorithms:()Ljava/util/List;
     183: putfield      #169                // Field signingAlgorithms:Ljava/util/List;
     186: aload_0
     187: aload_1
     188: invokevirtual #239                // Method aws/sdk/kotlin/services/kms/model/KeyMetadata.getValidTo:()Laws/smithy/kotlin/runtime/time/Instant;
     191: putfield      #175                // Field validTo:Laws/smithy/kotlin/runtime/time/Instant;
     194: return

  public final aws.sdk.kotlin.services.kms.model.KeyMetadata build();
    Code:
       0: new           #193                // class aws/sdk/kotlin/services/kms/model/KeyMetadata
       3: dup
       4: aload_0
       5: aconst_null
       6: invokespecial #245                // Method aws/sdk/kotlin/services/kms/model/KeyMetadata."<init>":(Laws/sdk/kotlin/services/kms/model/KeyMetadata$Builder;Lkotlin/jvm/internal/DefaultConstructorMarker;)V
       9: areturn

  public final void multiRegionConfiguration(kotlin.jvm.functions.Function1<? super aws.sdk.kotlin.services.kms.model.MultiRegionConfiguration$Builder, kotlin.Unit>);
    Code:
       0: aload_1
       1: ldc           #249                // String block
       3: invokestatic  #190                // Method kotlin/jvm/internal/Intrinsics.checkNotNullParameter:(Ljava/lang/Object;Ljava/lang/String;)V
       6: aload_0
       7: getstatic     #255                // Field aws/sdk/kotlin/services/kms/model/MultiRegionConfiguration.Companion:Laws/sdk/kotlin/services/kms/model/MultiRegionConfiguration$Companion;
      10: aload_1
      11: invokevirtual #261                // Method aws/sdk/kotlin/services/kms/model/MultiRegionConfiguration$Companion.invoke:(Lkotlin/jvm/functions/Function1;)Laws/sdk/kotlin/services/kms/model/MultiRegionConfiguration;
      14: putfield      #146                // Field multiRegionConfiguration:Laws/sdk/kotlin/services/kms/model/MultiRegionConfiguration;
      17: return
}
