Compiled from "BindingBeanTestCase.java"
public class juzu.impl.plugin.binding.BindingBeanTestCase extends juzu.test.AbstractInjectTestCase {
  public juzu.impl.plugin.binding.BindingBeanTestCase(juzu.impl.inject.spi.InjectorProvider);
    Code:
       0: aload_0
       1: aload_1
       2: invokespecial #1                  // Method juzu/test/AbstractInjectTestCase."<init>":(Ljuzu/impl/inject/spi/InjectorProvider;)V
       5: return

  public void testCreate() throws java.lang.Exception;
    Code:
       0: aload_0
       1: ldc           #2                  // String plugin.binding.create
       3: invokevirtual #3                  // Method application:(Ljava/lang/String;)Ljuzu/test/protocol/mock/MockApplication;
       6: invokevirtual #4                  // Method juzu/test/protocol/mock/MockApplication.init:()Ljuzu/test/protocol/mock/MockApplication;
       9: astore_1
      10: aload_1
      11: invokevirtual #5                  // Method juzu/test/protocol/mock/MockApplication.client:()Ljuzu/test/protocol/mock/MockClient;
      14: astore_2
      15: aload_2
      16: invokevirtual #6                  // Method juzu/test/protocol/mock/MockClient.render:()Ljuzu/test/protocol/mock/MockRenderBridge;
      19: astore_3
      20: ldc           #7                  // String pass
      22: aload_3
      23: invokevirtual #8                  // Method juzu/test/protocol/mock/MockRenderBridge.assertStringResult:()Ljava/lang/String;
      26: invokestatic  #9                  // Method assertEquals:(Ljava/lang/String;Ljava/lang/String;)V
      29: return

  public void testScope() throws java.lang.Exception;
    Code:
       0: aload_0
       1: ldc           #10                 // String plugin.binding.scope
       3: invokevirtual #3                  // Method application:(Ljava/lang/String;)Ljuzu/test/protocol/mock/MockApplication;
       6: invokevirtual #4                  // Method juzu/test/protocol/mock/MockApplication.init:()Ljuzu/test/protocol/mock/MockApplication;
       9: astore_1
      10: aload_1
      11: invokevirtual #5                  // Method juzu/test/protocol/mock/MockApplication.client:()Ljuzu/test/protocol/mock/MockClient;
      14: astore_2
      15: aload_2
      16: invokevirtual #6                  // Method juzu/test/protocol/mock/MockClient.render:()Ljuzu/test/protocol/mock/MockRenderBridge;
      19: astore_3
      20: aload_3
      21: invokevirtual #8                  // Method juzu/test/protocol/mock/MockRenderBridge.assertStringResult:()Ljava/lang/String;
      24: astore        4
      26: ldc           #11                 // String
      28: aload         4
      30: invokestatic  #12                 // Method assertNotSame:(Ljava/lang/Object;Ljava/lang/Object;)V
      33: aload_2
      34: aload         4
      36: invokevirtual #13                 // Method juzu/test/protocol/mock/MockClient.invoke:(Ljava/lang/String;)Ljuzu/test/protocol/mock/MockRequestBridge;
      39: checkcast     #14                 // class juzu/test/protocol/mock/MockRenderBridge
      42: astore_3
      43: aload_3
      44: invokevirtual #8                  // Method juzu/test/protocol/mock/MockRenderBridge.assertStringResult:()Ljava/lang/String;
      47: astore        5
      49: ldc           #7                  // String pass
      51: aload         5
      53: invokestatic  #9                  // Method assertEquals:(Ljava/lang/String;Ljava/lang/String;)V
      56: return
}
