Compiled from "ObjectCodec.java"
public class org.fusesource.hawtbuf.codec.ObjectCodec<T> extends org.fusesource.hawtbuf.codec.VariableCodec<T> {
  public org.fusesource.hawtbuf.codec.ObjectCodec();
    Code:
       0: aload_0
       1: invokespecial #1                  // Method org/fusesource/hawtbuf/codec/VariableCodec."<init>":()V
       4: return

  public void encode(java.lang.Object, java.io.DataOutput) throws java.io.IOException;
    Code:
       0: new           #2                  // class java/io/ByteArrayOutputStream
       3: dup
       4: invokespecial #3                  // Method java/io/ByteArrayOutputStream."<init>":()V
       7: astore_3
       8: new           #4                  // class java/io/ObjectOutputStream
      11: dup
      12: aload_3
      13: invokespecial #5                  // Method java/io/ObjectOutputStream."<init>":(Ljava/io/OutputStream;)V
      16: astore        4
      18: aload         4
      20: aload_1
      21: invokevirtual #6                  // Method java/io/ObjectOutputStream.writeObject:(Ljava/lang/Object;)V
      24: aload         4
      26: invokevirtual #7                  // Method java/io/ObjectOutputStream.close:()V
      29: aload_3
      30: invokevirtual #8                  // Method java/io/ByteArrayOutputStream.toByteArray:()[B
      33: astore        5
      35: aload_2
      36: aload         5
      38: arraylength
      39: invokeinterface #9,  2            // InterfaceMethod java/io/DataOutput.writeInt:(I)V
      44: aload_2
      45: aload         5
      47: invokeinterface #10,  2           // InterfaceMethod java/io/DataOutput.write:([B)V
      52: return

  public T decode(java.io.DataInput) throws java.io.IOException;
    Code:
       0: aload_1
       1: invokeinterface #11,  1           // InterfaceMethod java/io/DataInput.readInt:()I
       6: istore_2
       7: iload_2
       8: newarray       byte
      10: astore_3
      11: aload_1
      12: aload_3
      13: invokeinterface #12,  2           // InterfaceMethod java/io/DataInput.readFully:([B)V
      18: new           #13                 // class java/io/ByteArrayInputStream
      21: dup
      22: aload_3
      23: invokespecial #14                 // Method java/io/ByteArrayInputStream."<init>":([B)V
      26: astore        4
      28: new           #15                 // class java/io/ObjectInputStream
      31: dup
      32: aload         4
      34: invokespecial #16                 // Method java/io/ObjectInputStream."<init>":(Ljava/io/InputStream;)V
      37: astore        5
      39: aload         5
      41: invokevirtual #17                 // Method java/io/ObjectInputStream.readObject:()Ljava/lang/Object;
      44: areturn
      45: astore        6
      47: aload         6
      49: invokevirtual #19                 // Method java/lang/ClassNotFoundException.getMessage:()Ljava/lang/String;
      52: aload         6
      54: invokestatic  #20                 // Method createIOException:(Ljava/lang/String;Ljava/lang/Throwable;)Ljava/io/IOException;
      57: athrow
    Exception table:
       from    to  target type
          39    44    45   Class java/lang/ClassNotFoundException

  private static java.io.IOException createIOException(java.lang.String, java.lang.Throwable);
    Code:
       0: new           #21                 // class java/io/IOException
       3: dup
       4: aload_0
       5: invokespecial #22                 // Method java/io/IOException."<init>":(Ljava/lang/String;)V
       8: astore_2
       9: aload_2
      10: aload_1
      11: invokevirtual #23                 // Method java/io/IOException.initCause:(Ljava/lang/Throwable;)Ljava/lang/Throwable;
      14: pop
      15: aload_2
      16: areturn
}
