Compiled from "UTF8BufferCodec.java"
public class org.fusesource.hawtbuf.codec.UTF8BufferCodec extends org.fusesource.hawtbuf.codec.AbstractBufferCodec<org.fusesource.hawtbuf.UTF8Buffer> {
  public static final org.fusesource.hawtbuf.codec.UTF8BufferCodec INSTANCE;

  public org.fusesource.hawtbuf.codec.UTF8BufferCodec();
    Code:
       0: aload_0
       1: invokespecial #1                  // Method org/fusesource/hawtbuf/codec/AbstractBufferCodec."<init>":()V
       4: return

  protected org.fusesource.hawtbuf.UTF8Buffer createBuffer(byte[]);
    Code:
       0: new           #2                  // class org/fusesource/hawtbuf/UTF8Buffer
       3: dup
       4: aload_1
       5: invokespecial #3                  // Method org/fusesource/hawtbuf/UTF8Buffer."<init>":([B)V
       8: areturn

  protected org.fusesource.hawtbuf.Buffer createBuffer(byte[]);
    Code:
       0: aload_0
       1: aload_1
       2: invokevirtual #4                  // Method createBuffer:([B)Lorg/fusesource/hawtbuf/UTF8Buffer;
       5: areturn

  static {};
    Code:
       0: new           #5                  // class org/fusesource/hawtbuf/codec/UTF8BufferCodec
       3: dup
       4: invokespecial #6                  // Method "<init>":()V
       7: putstatic     #7                  // Field INSTANCE:Lorg/fusesource/hawtbuf/codec/UTF8BufferCodec;
      10: return
}
