Compiled from "CsvEscape.java"
public final class org.unbescape.csv.CsvEscape {
  public static java.lang.String escapeCsv(java.lang.String);
    Code:
       0: aload_0
       1: invokestatic  #1                  // Method org/unbescape/csv/CsvEscapeUtil.escape:(Ljava/lang/String;)Ljava/lang/String;
       4: areturn

  public static void escapeCsv(java.lang.String, java.io.Writer) throws java.io.IOException;
    Code:
       0: aload_1
       1: ifnonnull     14
       4: new           #2                  // class java/lang/IllegalArgumentException
       7: dup
       8: ldc           #3                  // String Argument \'writer\' cannot be null
      10: invokespecial #4                  // Method java/lang/IllegalArgumentException."<init>":(Ljava/lang/String;)V
      13: athrow
      14: new           #5                  // class org/unbescape/csv/CsvEscape$InternalStringReader
      17: dup
      18: aload_0
      19: invokespecial #6                  // Method org/unbescape/csv/CsvEscape$InternalStringReader."<init>":(Ljava/lang/String;)V
      22: aload_1
      23: invokestatic  #7                  // Method org/unbescape/csv/CsvEscapeUtil.escape:(Ljava/io/Reader;Ljava/io/Writer;)V
      26: return

  public static void escapeCsv(java.io.Reader, java.io.Writer) throws java.io.IOException;
    Code:
       0: aload_1
       1: ifnonnull     14
       4: new           #2                  // class java/lang/IllegalArgumentException
       7: dup
       8: ldc           #3                  // String Argument \'writer\' cannot be null
      10: invokespecial #4                  // Method java/lang/IllegalArgumentException."<init>":(Ljava/lang/String;)V
      13: athrow
      14: aload_0
      15: aload_1
      16: invokestatic  #7                  // Method org/unbescape/csv/CsvEscapeUtil.escape:(Ljava/io/Reader;Ljava/io/Writer;)V
      19: return

  public static void escapeCsv(char[], int, int, java.io.Writer) throws java.io.IOException;
    Code:
       0: aload_3
       1: ifnonnull     14
       4: new           #2                  // class java/lang/IllegalArgumentException
       7: dup
       8: ldc           #3                  // String Argument \'writer\' cannot be null
      10: invokespecial #4                  // Method java/lang/IllegalArgumentException."<init>":(Ljava/lang/String;)V
      13: athrow
      14: aload_0
      15: ifnonnull     22
      18: iconst_0
      19: goto          24
      22: aload_0
      23: arraylength
      24: istore        4
      26: iload_1
      27: iflt          36
      30: iload_1
      31: iload         4
      33: if_icmple     82
      36: new           #2                  // class java/lang/IllegalArgumentException
      39: dup
      40: new           #8                  // class java/lang/StringBuilder
      43: dup
      44: invokespecial #9                  // Method java/lang/StringBuilder."<init>":()V
      47: ldc           #10                 // String Invalid (offset, len). offset=
      49: invokevirtual #11                 // Method java/lang/StringBuilder.append:(Ljava/lang/String;)Ljava/lang/StringBuilder;
      52: iload_1
      53: invokevirtual #12                 // Method java/lang/StringBuilder.append:(I)Ljava/lang/StringBuilder;
      56: ldc           #13                 // String , len=
      58: invokevirtual #11                 // Method java/lang/StringBuilder.append:(Ljava/lang/String;)Ljava/lang/StringBuilder;
      61: iload_2
      62: invokevirtual #12                 // Method java/lang/StringBuilder.append:(I)Ljava/lang/StringBuilder;
      65: ldc           #14                 // String , text.length=
      67: invokevirtual #11                 // Method java/lang/StringBuilder.append:(Ljava/lang/String;)Ljava/lang/StringBuilder;
      70: iload         4
      72: invokevirtual #12                 // Method java/lang/StringBuilder.append:(I)Ljava/lang/StringBuilder;
      75: invokevirtual #15                 // Method java/lang/StringBuilder.toString:()Ljava/lang/String;
      78: invokespecial #4                  // Method java/lang/IllegalArgumentException."<init>":(Ljava/lang/String;)V
      81: athrow
      82: iload_2
      83: iflt          94
      86: iload_1
      87: iload_2
      88: iadd
      89: iload         4
      91: if_icmple     140
      94: new           #2                  // class java/lang/IllegalArgumentException
      97: dup
      98: new           #8                  // class java/lang/StringBuilder
     101: dup
     102: invokespecial #9                  // Method java/lang/StringBuilder."<init>":()V
     105: ldc           #10                 // String Invalid (offset, len). offset=
     107: invokevirtual #11                 // Method java/lang/StringBuilder.append:(Ljava/lang/String;)Ljava/lang/StringBuilder;
     110: iload_1
     111: invokevirtual #12                 // Method java/lang/StringBuilder.append:(I)Ljava/lang/StringBuilder;
     114: ldc           #13                 // String , len=
     116: invokevirtual #11                 // Method java/lang/StringBuilder.append:(Ljava/lang/String;)Ljava/lang/StringBuilder;
     119: iload_2
     120: invokevirtual #12                 // Method java/lang/StringBuilder.append:(I)Ljava/lang/StringBuilder;
     123: ldc           #14                 // String , text.length=
     125: invokevirtual #11                 // Method java/lang/StringBuilder.append:(Ljava/lang/String;)Ljava/lang/StringBuilder;
     128: iload         4
     130: invokevirtual #12                 // Method java/lang/StringBuilder.append:(I)Ljava/lang/StringBuilder;
     133: invokevirtual #15                 // Method java/lang/StringBuilder.toString:()Ljava/lang/String;
     136: invokespecial #4                  // Method java/lang/IllegalArgumentException."<init>":(Ljava/lang/String;)V
     139: athrow
     140: aload_0
     141: iload_1
     142: iload_2
     143: aload_3
     144: invokestatic  #16                 // Method org/unbescape/csv/CsvEscapeUtil.escape:([CIILjava/io/Writer;)V
     147: return

  public static java.lang.String unescapeCsv(java.lang.String);
    Code:
       0: aload_0
       1: invokestatic  #17                 // Method org/unbescape/csv/CsvEscapeUtil.unescape:(Ljava/lang/String;)Ljava/lang/String;
       4: areturn

  public static void unescapeCsv(java.lang.String, java.io.Writer) throws java.io.IOException;
    Code:
       0: aload_1
       1: ifnonnull     14
       4: new           #2                  // class java/lang/IllegalArgumentException
       7: dup
       8: ldc           #3                  // String Argument \'writer\' cannot be null
      10: invokespecial #4                  // Method java/lang/IllegalArgumentException."<init>":(Ljava/lang/String;)V
      13: athrow
      14: new           #5                  // class org/unbescape/csv/CsvEscape$InternalStringReader
      17: dup
      18: aload_0
      19: invokespecial #6                  // Method org/unbescape/csv/CsvEscape$InternalStringReader."<init>":(Ljava/lang/String;)V
      22: aload_1
      23: invokestatic  #18                 // Method org/unbescape/csv/CsvEscapeUtil.unescape:(Ljava/io/Reader;Ljava/io/Writer;)V
      26: return

  public static void unescapeCsv(java.io.Reader, java.io.Writer) throws java.io.IOException;
    Code:
       0: aload_1
       1: ifnonnull     14
       4: new           #2                  // class java/lang/IllegalArgumentException
       7: dup
       8: ldc           #3                  // String Argument \'writer\' cannot be null
      10: invokespecial #4                  // Method java/lang/IllegalArgumentException."<init>":(Ljava/lang/String;)V
      13: athrow
      14: aload_0
      15: aload_1
      16: invokestatic  #18                 // Method org/unbescape/csv/CsvEscapeUtil.unescape:(Ljava/io/Reader;Ljava/io/Writer;)V
      19: return

  public static void unescapeCsv(char[], int, int, java.io.Writer) throws java.io.IOException;
    Code:
       0: aload_3
       1: ifnonnull     14
       4: new           #2                  // class java/lang/IllegalArgumentException
       7: dup
       8: ldc           #3                  // String Argument \'writer\' cannot be null
      10: invokespecial #4                  // Method java/lang/IllegalArgumentException."<init>":(Ljava/lang/String;)V
      13: athrow
      14: aload_0
      15: ifnonnull     22
      18: iconst_0
      19: goto          24
      22: aload_0
      23: arraylength
      24: istore        4
      26: iload_1
      27: iflt          36
      30: iload_1
      31: iload         4
      33: if_icmple     82
      36: new           #2                  // class java/lang/IllegalArgumentException
      39: dup
      40: new           #8                  // class java/lang/StringBuilder
      43: dup
      44: invokespecial #9                  // Method java/lang/StringBuilder."<init>":()V
      47: ldc           #10                 // String Invalid (offset, len). offset=
      49: invokevirtual #11                 // Method java/lang/StringBuilder.append:(Ljava/lang/String;)Ljava/lang/StringBuilder;
      52: iload_1
      53: invokevirtual #12                 // Method java/lang/StringBuilder.append:(I)Ljava/lang/StringBuilder;
      56: ldc           #13                 // String , len=
      58: invokevirtual #11                 // Method java/lang/StringBuilder.append:(Ljava/lang/String;)Ljava/lang/StringBuilder;
      61: iload_2
      62: invokevirtual #12                 // Method java/lang/StringBuilder.append:(I)Ljava/lang/StringBuilder;
      65: ldc           #14                 // String , text.length=
      67: invokevirtual #11                 // Method java/lang/StringBuilder.append:(Ljava/lang/String;)Ljava/lang/StringBuilder;
      70: iload         4
      72: invokevirtual #12                 // Method java/lang/StringBuilder.append:(I)Ljava/lang/StringBuilder;
      75: invokevirtual #15                 // Method java/lang/StringBuilder.toString:()Ljava/lang/String;
      78: invokespecial #4                  // Method java/lang/IllegalArgumentException."<init>":(Ljava/lang/String;)V
      81: athrow
      82: iload_2
      83: iflt          94
      86: iload_1
      87: iload_2
      88: iadd
      89: iload         4
      91: if_icmple     140
      94: new           #2                  // class java/lang/IllegalArgumentException
      97: dup
      98: new           #8                  // class java/lang/StringBuilder
     101: dup
     102: invokespecial #9                  // Method java/lang/StringBuilder."<init>":()V
     105: ldc           #10                 // String Invalid (offset, len). offset=
     107: invokevirtual #11                 // Method java/lang/StringBuilder.append:(Ljava/lang/String;)Ljava/lang/StringBuilder;
     110: iload_1
     111: invokevirtual #12                 // Method java/lang/StringBuilder.append:(I)Ljava/lang/StringBuilder;
     114: ldc           #13                 // String , len=
     116: invokevirtual #11                 // Method java/lang/StringBuilder.append:(Ljava/lang/String;)Ljava/lang/StringBuilder;
     119: iload_2
     120: invokevirtual #12                 // Method java/lang/StringBuilder.append:(I)Ljava/lang/StringBuilder;
     123: ldc           #14                 // String , text.length=
     125: invokevirtual #11                 // Method java/lang/StringBuilder.append:(Ljava/lang/String;)Ljava/lang/StringBuilder;
     128: iload         4
     130: invokevirtual #12                 // Method java/lang/StringBuilder.append:(I)Ljava/lang/StringBuilder;
     133: invokevirtual #15                 // Method java/lang/StringBuilder.toString:()Ljava/lang/String;
     136: invokespecial #4                  // Method java/lang/IllegalArgumentException."<init>":(Ljava/lang/String;)V
     139: athrow
     140: aload_0
     141: iload_1
     142: iload_2
     143: aload_3
     144: invokestatic  #19                 // Method org/unbescape/csv/CsvEscapeUtil.unescape:([CIILjava/io/Writer;)V
     147: return

  private org.unbescape.csv.CsvEscape();
    Code:
       0: aload_0
       1: invokespecial #20                 // Method java/lang/Object."<init>":()V
       4: return
}
