Compiled from "IntTreePMap.java"
final class kotlin.reflect.jvm.internal.pcollections.IntTreePMap<V> {
  private static final kotlin.reflect.jvm.internal.pcollections.IntTreePMap<java.lang.Object> EMPTY;

  private final kotlin.reflect.jvm.internal.pcollections.IntTree<V> root;

  public static <V> kotlin.reflect.jvm.internal.pcollections.IntTreePMap<V> empty();
    Code:
       0: getstatic     #5                  // Field EMPTY:Lkotlin/reflect/jvm/internal/pcollections/IntTreePMap;
       3: areturn

  private kotlin.reflect.jvm.internal.pcollections.IntTreePMap(kotlin.reflect.jvm.internal.pcollections.IntTree<V>);
    Code:
       0: aload_0
       1: invokespecial #7                  // Method java/lang/Object."<init>":()V
       4: aload_0
       5: aload_1
       6: putfield      #6                  // Field root:Lkotlin/reflect/jvm/internal/pcollections/IntTree;
       9: return

  private kotlin.reflect.jvm.internal.pcollections.IntTreePMap<V> withRoot(kotlin.reflect.jvm.internal.pcollections.IntTree<V>);
    Code:
       0: aload_1
       1: aload_0
       2: getfield      #6                  // Field root:Lkotlin/reflect/jvm/internal/pcollections/IntTree;
       5: if_acmpne     10
       8: aload_0
       9: areturn
      10: new           #3                  // class kotlin/reflect/jvm/internal/pcollections/IntTreePMap
      13: dup
      14: aload_1
      15: invokespecial #11                 // Method "<init>":(Lkotlin/reflect/jvm/internal/pcollections/IntTree;)V
      18: areturn

  public V get(int);
    Code:
       0: aload_0
       1: getfield      #6                  // Field root:Lkotlin/reflect/jvm/internal/pcollections/IntTree;
       4: iload_1
       5: i2l
       6: invokevirtual #8                  // Method kotlin/reflect/jvm/internal/pcollections/IntTree.get:(J)Ljava/lang/Object;
       9: areturn

  public kotlin.reflect.jvm.internal.pcollections.IntTreePMap<V> plus(int, V);
    Code:
       0: aload_0
       1: aload_0
       2: getfield      #6                  // Field root:Lkotlin/reflect/jvm/internal/pcollections/IntTree;
       5: iload_1
       6: i2l
       7: aload_2
       8: invokevirtual #10                 // Method kotlin/reflect/jvm/internal/pcollections/IntTree.plus:(JLjava/lang/Object;)Lkotlin/reflect/jvm/internal/pcollections/IntTree;
      11: invokespecial #12                 // Method withRoot:(Lkotlin/reflect/jvm/internal/pcollections/IntTree;)Lkotlin/reflect/jvm/internal/pcollections/IntTreePMap;
      14: areturn

  public kotlin.reflect.jvm.internal.pcollections.IntTreePMap<V> minus(int);
    Code:
       0: aload_0
       1: aload_0
       2: getfield      #6                  // Field root:Lkotlin/reflect/jvm/internal/pcollections/IntTree;
       5: iload_1
       6: i2l
       7: invokevirtual #9                  // Method kotlin/reflect/jvm/internal/pcollections/IntTree.minus:(J)Lkotlin/reflect/jvm/internal/pcollections/IntTree;
      10: invokespecial #12                 // Method withRoot:(Lkotlin/reflect/jvm/internal/pcollections/IntTree;)Lkotlin/reflect/jvm/internal/pcollections/IntTreePMap;
      13: areturn

  static {};
    Code:
       0: new           #3                  // class kotlin/reflect/jvm/internal/pcollections/IntTreePMap
       3: dup
       4: getstatic     #4                  // Field kotlin/reflect/jvm/internal/pcollections/IntTree.EMPTYNODE:Lkotlin/reflect/jvm/internal/pcollections/IntTree;
       7: invokespecial #11                 // Method "<init>":(Lkotlin/reflect/jvm/internal/pcollections/IntTree;)V
      10: putstatic     #5                  // Field EMPTY:Lkotlin/reflect/jvm/internal/pcollections/IntTreePMap;
      13: return
}
