Compiled from "AtomicFieldUpdaterUtil.java"
final class org.jboss.netty.util.internal.AtomicFieldUpdaterUtil {
  private static final boolean AVAILABLE;

  static <T, V> java.util.concurrent.atomic.AtomicReferenceFieldUpdater<T, V> newRefUpdater(java.lang.Class<T>, java.lang.Class<V>, java.lang.String);
    Code:
       0: getstatic     #1                  // Field AVAILABLE:Z
       3: ifeq          13
       6: aload_0
       7: aload_1
       8: aload_2
       9: invokestatic  #2                  // Method java/util/concurrent/atomic/AtomicReferenceFieldUpdater.newUpdater:(Ljava/lang/Class;Ljava/lang/Class;Ljava/lang/String;)Ljava/util/concurrent/atomic/AtomicReferenceFieldUpdater;
      12: areturn
      13: aconst_null
      14: areturn

  static <T> java.util.concurrent.atomic.AtomicIntegerFieldUpdater<T> newIntUpdater(java.lang.Class<T>, java.lang.String);
    Code:
       0: getstatic     #1                  // Field AVAILABLE:Z
       3: ifeq          12
       6: aload_0
       7: aload_1
       8: invokestatic  #3                  // Method java/util/concurrent/atomic/AtomicIntegerFieldUpdater.newUpdater:(Ljava/lang/Class;Ljava/lang/String;)Ljava/util/concurrent/atomic/AtomicIntegerFieldUpdater;
      11: areturn
      12: aconst_null
      13: areturn

  static boolean isAvailable();
    Code:
       0: getstatic     #1                  // Field AVAILABLE:Z
       3: ireturn

  private org.jboss.netty.util.internal.AtomicFieldUpdaterUtil();
    Code:
       0: aload_0
       1: invokespecial #4                  // Method java/lang/Object."<init>":()V
       4: return

  static {};
    Code:
       0: iconst_0
       1: istore_0
       2: ldc_w         #5                  // class org/jboss/netty/util/internal/AtomicFieldUpdaterUtil$Node
       5: ldc_w         #5                  // class org/jboss/netty/util/internal/AtomicFieldUpdaterUtil$Node
       8: ldc           #6                  // String next
      10: invokestatic  #2                  // Method java/util/concurrent/atomic/AtomicReferenceFieldUpdater.newUpdater:(Ljava/lang/Class;Ljava/lang/Class;Ljava/lang/String;)Ljava/util/concurrent/atomic/AtomicReferenceFieldUpdater;
      13: astore_1
      14: new           #5                  // class org/jboss/netty/util/internal/AtomicFieldUpdaterUtil$Node
      17: dup
      18: invokespecial #7                  // Method org/jboss/netty/util/internal/AtomicFieldUpdaterUtil$Node."<init>":()V
      21: astore_2
      22: aload_1
      23: aload_2
      24: aload_2
      25: invokevirtual #8                  // Method java/util/concurrent/atomic/AtomicReferenceFieldUpdater.set:(Ljava/lang/Object;Ljava/lang/Object;)V
      28: aload_2
      29: getfield      #9                  // Field org/jboss/netty/util/internal/AtomicFieldUpdaterUtil$Node.next:Lorg/jboss/netty/util/internal/AtomicFieldUpdaterUtil$Node;
      32: aload_2
      33: if_acmpeq     44
      36: new           #10                 // class java/lang/Exception
      39: dup
      40: invokespecial #11                 // Method java/lang/Exception."<init>":()V
      43: athrow
      44: iconst_1
      45: istore_0
      46: goto          50
      49: astore_1
      50: iload_0
      51: putstatic     #1                  // Field AVAILABLE:Z
      54: return
    Exception table:
       from    to  target type
           2    46    49   Class java/lang/Throwable
}
