Compiled from "ConcurrentIdentityHashMap.java"
final class org.jboss.netty.util.internal.ConcurrentIdentityHashMap$WriteThroughEntry extends org.jboss.netty.util.internal.ConcurrentIdentityHashMap$SimpleEntry<K, V> {
  final org.jboss.netty.util.internal.ConcurrentIdentityHashMap this$0;

  org.jboss.netty.util.internal.ConcurrentIdentityHashMap$WriteThroughEntry(K, V);
    Code:
       0: aload_0
       1: aload_1
       2: putfield      #1                  // Field this$0:Lorg/jboss/netty/util/internal/ConcurrentIdentityHashMap;
       5: aload_0
       6: aload_2
       7: aload_3
       8: invokespecial #2                  // Method org/jboss/netty/util/internal/ConcurrentIdentityHashMap$SimpleEntry."<init>":(Ljava/lang/Object;Ljava/lang/Object;)V
      11: return

  public V setValue(V);
    Code:
       0: aload_1
       1: ifnonnull     12
       4: new           #3                  // class java/lang/NullPointerException
       7: dup
       8: invokespecial #4                  // Method java/lang/NullPointerException."<init>":()V
      11: athrow
      12: aload_0
      13: aload_1
      14: invokespecial #5                  // Method org/jboss/netty/util/internal/ConcurrentIdentityHashMap$SimpleEntry.setValue:(Ljava/lang/Object;)Ljava/lang/Object;
      17: astore_2
      18: aload_0
      19: getfield      #1                  // Field this$0:Lorg/jboss/netty/util/internal/ConcurrentIdentityHashMap;
      22: aload_0
      23: invokevirtual #6                  // Method getKey:()Ljava/lang/Object;
      26: aload_1
      27: invokevirtual #7                  // Method org/jboss/netty/util/internal/ConcurrentIdentityHashMap.put:(Ljava/lang/Object;Ljava/lang/Object;)Ljava/lang/Object;
      30: pop
      31: aload_2
      32: areturn
}
