Compiled from "ErasureCodeConstants.java"
public final class org.apache.hadoop.io.erasurecode.ErasureCodeConstants {
  public static final java.lang.String DUMMY_CODEC_NAME;

  public static final java.lang.String RS_CODEC_NAME;

  public static final java.lang.String RS_LEGACY_CODEC_NAME;

  public static final java.lang.String XOR_CODEC_NAME;

  public static final java.lang.String HHXOR_CODEC_NAME;

  public static final java.lang.String REPLICATION_CODEC_NAME;

  public static final org.apache.hadoop.io.erasurecode.ECSchema RS_6_3_SCHEMA;

  public static final org.apache.hadoop.io.erasurecode.ECSchema RS_3_2_SCHEMA;

  public static final org.apache.hadoop.io.erasurecode.ECSchema RS_6_3_LEGACY_SCHEMA;

  public static final org.apache.hadoop.io.erasurecode.ECSchema XOR_2_1_SCHEMA;

  public static final org.apache.hadoop.io.erasurecode.ECSchema RS_10_4_SCHEMA;

  public static final org.apache.hadoop.io.erasurecode.ECSchema REPLICATION_1_2_SCHEMA;

  public static final byte MAX_POLICY_ID;

  public static final byte USER_DEFINED_POLICY_START_ID;

  public static final byte REPLICATION_POLICY_ID;

  public static final java.lang.String REPLICATION_POLICY_NAME;

  private org.apache.hadoop.io.erasurecode.ErasureCodeConstants();
    Code:
       0: aload_0
       1: invokespecial #3                  // Method java/lang/Object."<init>":()V
       4: return

  static {};
    Code:
       0: new           #4                  // class org/apache/hadoop/io/erasurecode/ECSchema
       3: dup
       4: ldc           #5                  // String rs
       6: bipush        6
       8: iconst_3
       9: invokespecial #6                  // Method org/apache/hadoop/io/erasurecode/ECSchema."<init>":(Ljava/lang/String;II)V
      12: putstatic     #7                  // Field RS_6_3_SCHEMA:Lorg/apache/hadoop/io/erasurecode/ECSchema;
      15: new           #4                  // class org/apache/hadoop/io/erasurecode/ECSchema
      18: dup
      19: ldc           #5                  // String rs
      21: iconst_3
      22: iconst_2
      23: invokespecial #6                  // Method org/apache/hadoop/io/erasurecode/ECSchema."<init>":(Ljava/lang/String;II)V
      26: putstatic     #8                  // Field RS_3_2_SCHEMA:Lorg/apache/hadoop/io/erasurecode/ECSchema;
      29: new           #4                  // class org/apache/hadoop/io/erasurecode/ECSchema
      32: dup
      33: ldc           #9                  // String rs-legacy
      35: bipush        6
      37: iconst_3
      38: invokespecial #6                  // Method org/apache/hadoop/io/erasurecode/ECSchema."<init>":(Ljava/lang/String;II)V
      41: putstatic     #10                 // Field RS_6_3_LEGACY_SCHEMA:Lorg/apache/hadoop/io/erasurecode/ECSchema;
      44: new           #4                  // class org/apache/hadoop/io/erasurecode/ECSchema
      47: dup
      48: ldc           #11                 // String xor
      50: iconst_2
      51: iconst_1
      52: invokespecial #6                  // Method org/apache/hadoop/io/erasurecode/ECSchema."<init>":(Ljava/lang/String;II)V
      55: putstatic     #12                 // Field XOR_2_1_SCHEMA:Lorg/apache/hadoop/io/erasurecode/ECSchema;
      58: new           #4                  // class org/apache/hadoop/io/erasurecode/ECSchema
      61: dup
      62: ldc           #5                  // String rs
      64: bipush        10
      66: iconst_4
      67: invokespecial #6                  // Method org/apache/hadoop/io/erasurecode/ECSchema."<init>":(Ljava/lang/String;II)V
      70: putstatic     #13                 // Field RS_10_4_SCHEMA:Lorg/apache/hadoop/io/erasurecode/ECSchema;
      73: new           #4                  // class org/apache/hadoop/io/erasurecode/ECSchema
      76: dup
      77: ldc           #14                 // String replication
      79: iconst_1
      80: iconst_2
      81: invokespecial #6                  // Method org/apache/hadoop/io/erasurecode/ECSchema."<init>":(Ljava/lang/String;II)V
      84: putstatic     #15                 // Field REPLICATION_1_2_SCHEMA:Lorg/apache/hadoop/io/erasurecode/ECSchema;
      87: return
}
