Compiled from "DateTimeFormat.java"
public final class org.springframework.format.annotation.DateTimeFormat$ISO extends java.lang.Enum<org.springframework.format.annotation.DateTimeFormat$ISO> {
  public static final org.springframework.format.annotation.DateTimeFormat$ISO DATE;

  public static final org.springframework.format.annotation.DateTimeFormat$ISO TIME;

  public static final org.springframework.format.annotation.DateTimeFormat$ISO DATE_TIME;

  public static final org.springframework.format.annotation.DateTimeFormat$ISO NONE;

  private static final org.springframework.format.annotation.DateTimeFormat$ISO[] $VALUES;

  public static org.springframework.format.annotation.DateTimeFormat$ISO[] values();
    Code:
       0: getstatic     #1                  // Field $VALUES:[Lorg/springframework/format/annotation/DateTimeFormat$ISO;
       3: invokevirtual #2                  // Method "[Lorg/springframework/format/annotation/DateTimeFormat$ISO;".clone:()Ljava/lang/Object;
       6: checkcast     #3                  // class "[Lorg/springframework/format/annotation/DateTimeFormat$ISO;"
       9: areturn

  public static org.springframework.format.annotation.DateTimeFormat$ISO valueOf(java.lang.String);
    Code:
       0: ldc           #4                  // class org/springframework/format/annotation/DateTimeFormat$ISO
       2: aload_0
       3: invokestatic  #5                  // Method java/lang/Enum.valueOf:(Ljava/lang/Class;Ljava/lang/String;)Ljava/lang/Enum;
       6: checkcast     #4                  // class org/springframework/format/annotation/DateTimeFormat$ISO
       9: areturn

  private org.springframework.format.annotation.DateTimeFormat$ISO();
    Code:
       0: aload_0
       1: aload_1
       2: iload_2
       3: invokespecial #6                  // Method java/lang/Enum."<init>":(Ljava/lang/String;I)V
       6: return

  static {};
    Code:
       0: new           #4                  // class org/springframework/format/annotation/DateTimeFormat$ISO
       3: dup
       4: ldc           #7                  // String DATE
       6: iconst_0
       7: invokespecial #8                  // Method "<init>":(Ljava/lang/String;I)V
      10: putstatic     #9                  // Field DATE:Lorg/springframework/format/annotation/DateTimeFormat$ISO;
      13: new           #4                  // class org/springframework/format/annotation/DateTimeFormat$ISO
      16: dup
      17: ldc           #10                 // String TIME
      19: iconst_1
      20: invokespecial #8                  // Method "<init>":(Ljava/lang/String;I)V
      23: putstatic     #11                 // Field TIME:Lorg/springframework/format/annotation/DateTimeFormat$ISO;
      26: new           #4                  // class org/springframework/format/annotation/DateTimeFormat$ISO
      29: dup
      30: ldc           #12                 // String DATE_TIME
      32: iconst_2
      33: invokespecial #8                  // Method "<init>":(Ljava/lang/String;I)V
      36: putstatic     #13                 // Field DATE_TIME:Lorg/springframework/format/annotation/DateTimeFormat$ISO;
      39: new           #4                  // class org/springframework/format/annotation/DateTimeFormat$ISO
      42: dup
      43: ldc           #14                 // String NONE
      45: iconst_3
      46: invokespecial #8                  // Method "<init>":(Ljava/lang/String;I)V
      49: putstatic     #15                 // Field NONE:Lorg/springframework/format/annotation/DateTimeFormat$ISO;
      52: iconst_4
      53: anewarray     #4                  // class org/springframework/format/annotation/DateTimeFormat$ISO
      56: dup
      57: iconst_0
      58: getstatic     #9                  // Field DATE:Lorg/springframework/format/annotation/DateTimeFormat$ISO;
      61: aastore
      62: dup
      63: iconst_1
      64: getstatic     #11                 // Field TIME:Lorg/springframework/format/annotation/DateTimeFormat$ISO;
      67: aastore
      68: dup
      69: iconst_2
      70: getstatic     #13                 // Field DATE_TIME:Lorg/springframework/format/annotation/DateTimeFormat$ISO;
      73: aastore
      74: dup
      75: iconst_3
      76: getstatic     #15                 // Field NONE:Lorg/springframework/format/annotation/DateTimeFormat$ISO;
      79: aastore
      80: putstatic     #1                  // Field $VALUES:[Lorg/springframework/format/annotation/DateTimeFormat$ISO;
      83: return
}
