Compiled from "DataColumnImpl.kt"
final class org.jetbrains.kotlinx.dataframe.impl.columns.DataColumnImpl$hashCode$2 extends kotlin.jvm.internal.Lambda implements kotlin.jvm.functions.Function0<java.lang.Integer> {
  final org.jetbrains.kotlinx.dataframe.impl.columns.DataColumnImpl<T> this$0;

  org.jetbrains.kotlinx.dataframe.impl.columns.DataColumnImpl$hashCode$2(org.jetbrains.kotlinx.dataframe.impl.columns.DataColumnImpl<T>);
    Code:
       0: aload_0
       1: aload_1
       2: putfield      #14                 // Field this$0:Lorg/jetbrains/kotlinx/dataframe/impl/columns/DataColumnImpl;
       5: aload_0
       6: iconst_0
       7: invokespecial #17                 // Method kotlin/jvm/internal/Lambda."<init>":(I)V
      10: return

  public final java.lang.Integer invoke();
    Code:
       0: aload_0
       1: getfield      #14                 // Field this$0:Lorg/jetbrains/kotlinx/dataframe/impl/columns/DataColumnImpl;
       4: checkcast     #25                 // class org/jetbrains/kotlinx/dataframe/DataColumn
       7: invokestatic  #31                 // Method org/jetbrains/kotlinx/dataframe/impl/columns/UtilsKt.getHashCode:(Lorg/jetbrains/kotlinx/dataframe/DataColumn;)I
      10: invokestatic  #37                 // Method java/lang/Integer.valueOf:(I)Ljava/lang/Integer;
      13: areturn

  public java.lang.Object invoke();
    Code:
       0: aload_0
       1: invokevirtual #40                 // Method invoke:()Ljava/lang/Integer;
       4: areturn
}
