Compiled from "ServletSecurityMetaDataParser.java"
public class org.jboss.metadata.parser.jbossweb.ServletSecurityMetaDataParser extends org.jboss.metadata.parser.util.MetaDataElementParser {
  public org.jboss.metadata.parser.jbossweb.ServletSecurityMetaDataParser();
    Code:
       0: aload_0
       1: invokespecial #1                  // Method org/jboss/metadata/parser/util/MetaDataElementParser."<init>":()V
       4: return

  public static org.jboss.metadata.web.spec.ServletSecurityMetaData parse(javax.xml.stream.XMLStreamReader, org.jboss.metadata.property.PropertyReplacer) throws javax.xml.stream.XMLStreamException;
    Code:
       0: new           #2                  // class org/jboss/metadata/web/spec/ServletSecurityMetaData
       3: dup
       4: invokespecial #3                  // Method org/jboss/metadata/web/spec/ServletSecurityMetaData."<init>":()V
       7: astore_2
       8: aload_0
       9: invokeinterface #4,  1            // InterfaceMethod javax/xml/stream/XMLStreamReader.hasNext:()Z
      14: ifeq          216
      17: aload_0
      18: invokeinterface #5,  1            // InterfaceMethod javax/xml/stream/XMLStreamReader.nextTag:()I
      23: iconst_2
      24: if_icmpeq     216
      27: aload_0
      28: invokeinterface #7,  1            // InterfaceMethod javax/xml/stream/XMLStreamReader.getLocalName:()Ljava/lang/String;
      33: invokestatic  #8                  // Method org/jboss/metadata/parser/jbossweb/Element.forName:(Ljava/lang/String;)Lorg/jboss/metadata/parser/jbossweb/Element;
      36: astore_3
      37: getstatic     #9                  // Field org/jboss/metadata/parser/jbossweb/ServletSecurityMetaDataParser$1.$SwitchMap$org$jboss$metadata$parser$jbossweb$Element:[I
      40: aload_3
      41: invokevirtual #10                 // Method org/jboss/metadata/parser/jbossweb/Element.ordinal:()I
      44: iaload
      45: tableswitch   { // 1 to 4
                     1: 76
                     2: 118
                     3: 142
                     4: 166
               default: 208
          }
      76: aload_2
      77: invokevirtual #11                 // Method org/jboss/metadata/web/spec/ServletSecurityMetaData.getHttpMethodConstraints:()Ljava/util/List;
      80: astore        4
      82: aload         4
      84: ifnonnull     102
      87: new           #12                 // class java/util/ArrayList
      90: dup
      91: invokespecial #13                 // Method java/util/ArrayList."<init>":()V
      94: astore        4
      96: aload_2
      97: aload         4
      99: invokevirtual #14                 // Method org/jboss/metadata/web/spec/ServletSecurityMetaData.setHttpMethodConstraints:(Ljava/util/List;)V
     102: aload         4
     104: aload_0
     105: aload_1
     106: invokestatic  #15                 // Method org/jboss/metadata/parser/jbossweb/HttpMethodConstraintMetaDataParser.parse:(Ljavax/xml/stream/XMLStreamReader;Lorg/jboss/metadata/property/PropertyReplacer;)Lorg/jboss/metadata/web/spec/HttpMethodConstraintMetaData;
     109: invokeinterface #16,  2           // InterfaceMethod java/util/List.add:(Ljava/lang/Object;)Z
     114: pop
     115: goto          213
     118: aload_2
     119: aload_0
     120: aload_1
     121: invokestatic  #17                 // Method getElementText:(Ljavax/xml/stream/XMLStreamReader;Lorg/jboss/metadata/property/PropertyReplacer;)Ljava/lang/String;
     124: invokestatic  #18                 // Method org/jboss/metadata/web/spec/EmptyRoleSemanticType.valueOf:(Ljava/lang/String;)Lorg/jboss/metadata/web/spec/EmptyRoleSemanticType;
     127: invokevirtual #19                 // Method org/jboss/metadata/web/spec/ServletSecurityMetaData.setEmptyRoleSemantic:(Lorg/jboss/metadata/web/spec/EmptyRoleSemanticType;)V
     130: goto          213
     133: astore        5
     135: aload_0
     136: aload         5
     138: invokestatic  #21                 // Method unexpectedValue:(Ljavax/xml/stream/XMLStreamReader;Ljava/lang/Throwable;)Ljavax/xml/stream/XMLStreamException;
     141: athrow
     142: aload_2
     143: aload_0
     144: aload_1
     145: invokestatic  #17                 // Method getElementText:(Ljavax/xml/stream/XMLStreamReader;Lorg/jboss/metadata/property/PropertyReplacer;)Ljava/lang/String;
     148: invokestatic  #22                 // Method org/jboss/metadata/web/spec/TransportGuaranteeType.valueOf:(Ljava/lang/String;)Lorg/jboss/metadata/web/spec/TransportGuaranteeType;
     151: invokevirtual #23                 // Method org/jboss/metadata/web/spec/ServletSecurityMetaData.setTransportGuarantee:(Lorg/jboss/metadata/web/spec/TransportGuaranteeType;)V
     154: goto          213
     157: astore        5
     159: aload_0
     160: aload         5
     162: invokestatic  #21                 // Method unexpectedValue:(Ljavax/xml/stream/XMLStreamReader;Ljava/lang/Throwable;)Ljavax/xml/stream/XMLStreamException;
     165: athrow
     166: aload_2
     167: invokevirtual #24                 // Method org/jboss/metadata/web/spec/ServletSecurityMetaData.getRolesAllowed:()Ljava/util/List;
     170: astore        5
     172: aload         5
     174: ifnonnull     192
     177: new           #12                 // class java/util/ArrayList
     180: dup
     181: invokespecial #13                 // Method java/util/ArrayList."<init>":()V
     184: astore        5
     186: aload_2
     187: aload         5
     189: invokevirtual #25                 // Method org/jboss/metadata/web/spec/ServletSecurityMetaData.setRolesAllowed:(Ljava/util/List;)V
     192: aload         5
     194: aload_0
     195: aload_1
     196: invokestatic  #17                 // Method getElementText:(Ljavax/xml/stream/XMLStreamReader;Lorg/jboss/metadata/property/PropertyReplacer;)Ljava/lang/String;
     199: invokeinterface #16,  2           // InterfaceMethod java/util/List.add:(Ljava/lang/Object;)Z
     204: pop
     205: goto          213
     208: aload_0
     209: invokestatic  #26                 // Method unexpectedElement:(Ljavax/xml/stream/XMLStreamReader;)Ljavax/xml/stream/XMLStreamException;
     212: athrow
     213: goto          8
     216: aload_2
     217: areturn
    Exception table:
       from    to  target type
         118   130   133   Class java/lang/IllegalArgumentException
         142   154   157   Class java/lang/IllegalArgumentException
}
