Compiled from "CommentImpl.java"
public class org.apache.axis2.saaj.CommentImpl extends org.apache.axis2.saaj.TextImplEx implements org.w3c.dom.Comment {
  public org.apache.axis2.saaj.CommentImpl(org.apache.axiom.om.OMComment);
    Code:
       0: aload_0
       1: aload_1
       2: invokespecial #1                  // Method org/apache/axis2/saaj/TextImplEx."<init>":(Lorg/apache/axiom/om/OMNode;)V
       5: return

  public org.apache.axis2.saaj.CommentImpl(java.lang.String);
    Code:
       0: aload_0
       1: aload_1
       2: invokespecial #2                  // Method org/apache/axis2/saaj/TextImplEx."<init>":(Ljava/lang/String;)V
       5: return

  public boolean isComment();
    Code:
       0: iconst_1
       1: ireturn
}
