Compiled from "NodeImpl.java"
public abstract class org.apache.axis2.saaj.NodeImpl<T extends org.w3c.dom.Node, S extends org.apache.axiom.om.OMNode> extends org.apache.axis2.saaj.ProxyNode<T, S> implements javax.xml.soap.Node {
  public org.apache.axis2.saaj.NodeImpl(T, S);
    Code:
       0: aload_0
       1: aload_1
       2: aload_2
       3: invokespecial #1                  // Method org/apache/axis2/saaj/ProxyNode."<init>":(Lorg/w3c/dom/Node;Lorg/apache/axiom/om/OMInformationItem;)V
       6: return

  public final void detachNode();
    Code:
       0: aload_0
       1: getfield      #2                  // Field omTarget:Lorg/apache/axiom/om/OMInformationItem;
       4: checkcast     #3                  // class org/apache/axiom/om/OMNode
       7: invokeinterface #4,  1            // InterfaceMethod org/apache/axiom/om/OMNode.detach:()Lorg/apache/axiom/om/OMNode;
      12: pop
      13: return

  public final javax.xml.soap.SOAPElement getParentElement();
    Code:
       0: aload_0
       1: invokevirtual #5                  // Method getParentNode:()Lorg/w3c/dom/Node;
       4: checkcast     #6                  // class javax/xml/soap/SOAPElement
       7: areturn

  public void setParentElement(javax.xml.soap.SOAPElement) throws javax.xml.soap.SOAPException;
    Code:
       0: aload_1
       1: checkcast     #7                  // class org/apache/axis2/saaj/SOAPElementImpl
       4: getfield      #8                  // Field org/apache/axis2/saaj/SOAPElementImpl.omTarget:Lorg/apache/axiom/om/OMInformationItem;
       7: checkcast     #9                  // class org/apache/axiom/om/OMElement
      10: aload_0
      11: getfield      #2                  // Field omTarget:Lorg/apache/axiom/om/OMInformationItem;
      14: checkcast     #3                  // class org/apache/axiom/om/OMNode
      17: invokeinterface #10,  2           // InterfaceMethod org/apache/axiom/om/OMElement.addChild:(Lorg/apache/axiom/om/OMNode;)V
      22: return
}
