Compiled from "SOAPFactoryImpl.java"
public class org.apache.axis2.saaj.SOAPFactoryImpl extends javax.xml.soap.SOAPFactory {
  private final org.apache.axiom.om.dom.DOMMetaFactory metaFactory;

  protected java.lang.String soapVersion;

  public org.apache.axis2.saaj.SOAPFactoryImpl();
    Code:
       0: aload_0
       1: invokespecial #1                  // Method javax/xml/soap/SOAPFactory."<init>":()V
       4: aload_0
       5: ldc           #3                  // String dom
       7: invokestatic  #4                  // Method org/apache/axiom/om/OMAbstractFactory.getMetaFactory:(Ljava/lang/String;)Lorg/apache/axiom/om/OMMetaFactory;
      10: checkcast     #5                  // class org/apache/axiom/om/dom/DOMMetaFactory
      13: putfield      #6                  // Field metaFactory:Lorg/apache/axiom/om/dom/DOMMetaFactory;
      16: aload_0
      17: ldc           #8                  // String SOAP 1.1 Protocol
      19: putfield      #9                  // Field soapVersion:Ljava/lang/String;
      22: return

  public javax.xml.soap.SOAPElement createElement(javax.xml.soap.Name) throws javax.xml.soap.SOAPException;
    Code:
       0: aload_1
       1: invokeinterface #10,  1           // InterfaceMethod javax/xml/soap/Name.getLocalName:()Ljava/lang/String;
       6: astore_2
       7: aload_1
       8: invokeinterface #11,  1           // InterfaceMethod javax/xml/soap/Name.getPrefix:()Ljava/lang/String;
      13: astore_3
      14: aload_1
      15: invokeinterface #12,  1           // InterfaceMethod javax/xml/soap/Name.getURI:()Ljava/lang/String;
      20: astore        4
      22: aconst_null
      23: astore        5
      25: aload_0
      26: getfield      #9                  // Field soapVersion:Ljava/lang/String;
      29: ldc           #13                 // String SOAP 1.2 Protocol
      31: invokevirtual #14                 // Method java/lang/String.equals:(Ljava/lang/Object;)Z
      34: ifeq          60
      37: aload_0
      38: getfield      #6                  // Field metaFactory:Lorg/apache/axiom/om/dom/DOMMetaFactory;
      41: invokeinterface #15,  1           // InterfaceMethod org/apache/axiom/om/dom/DOMMetaFactory.getSOAP12Factory:()Lorg/apache/axiom/soap/SOAPFactory;
      46: aload_2
      47: aload         4
      49: aload_3
      50: invokeinterface #16,  4           // InterfaceMethod org/apache/axiom/soap/SOAPFactory.createOMElement:(Ljava/lang/String;Ljava/lang/String;Ljava/lang/String;)Lorg/apache/axiom/om/OMElement;
      55: astore        5
      57: goto          80
      60: aload_0
      61: getfield      #6                  // Field metaFactory:Lorg/apache/axiom/om/dom/DOMMetaFactory;
      64: invokeinterface #17,  1           // InterfaceMethod org/apache/axiom/om/dom/DOMMetaFactory.getSOAP11Factory:()Lorg/apache/axiom/soap/SOAPFactory;
      69: aload_2
      70: aload         4
      72: aload_3
      73: invokeinterface #16,  4           // InterfaceMethod org/apache/axiom/soap/SOAPFactory.createOMElement:(Ljava/lang/String;Ljava/lang/String;Ljava/lang/String;)Lorg/apache/axiom/om/OMElement;
      78: astore        5
      80: aload_0
      81: getfield      #6                  // Field metaFactory:Lorg/apache/axiom/om/dom/DOMMetaFactory;
      84: invokeinterface #18,  1           // InterfaceMethod org/apache/axiom/om/dom/DOMMetaFactory.getOMFactory:()Lorg/apache/axiom/om/OMFactory;
      89: aload_2
      90: aload         4
      92: aload_3
      93: invokeinterface #19,  4           // InterfaceMethod org/apache/axiom/om/OMFactory.createOMElement:(Ljava/lang/String;Ljava/lang/String;Ljava/lang/String;)Lorg/apache/axiom/om/OMElement;
      98: pop
      99: new           #20                 // class org/apache/axis2/saaj/SOAPElementImpl
     102: dup
     103: aload         5
     105: invokespecial #21                 // Method org/apache/axis2/saaj/SOAPElementImpl."<init>":(Lorg/apache/axiom/om/OMElement;)V
     108: areturn

  public javax.xml.soap.SOAPElement createElement(java.lang.String) throws javax.xml.soap.SOAPException;
    Code:
       0: aconst_null
       1: astore_2
       2: aload_0
       3: getfield      #9                  // Field soapVersion:Ljava/lang/String;
       6: ldc           #13                 // String SOAP 1.2 Protocol
       8: invokevirtual #14                 // Method java/lang/String.equals:(Ljava/lang/Object;)Z
      11: ifeq          27
      14: aload_0
      15: getfield      #6                  // Field metaFactory:Lorg/apache/axiom/om/dom/DOMMetaFactory;
      18: invokeinterface #15,  1           // InterfaceMethod org/apache/axiom/om/dom/DOMMetaFactory.getSOAP12Factory:()Lorg/apache/axiom/soap/SOAPFactory;
      23: astore_2
      24: goto          37
      27: aload_0
      28: getfield      #6                  // Field metaFactory:Lorg/apache/axiom/om/dom/DOMMetaFactory;
      31: invokeinterface #17,  1           // InterfaceMethod org/apache/axiom/om/dom/DOMMetaFactory.getSOAP11Factory:()Lorg/apache/axiom/soap/SOAPFactory;
      36: astore_2
      37: aload_2
      38: new           #22                 // class javax/xml/namespace/QName
      41: dup
      42: aload_1
      43: invokespecial #23                 // Method javax/xml/namespace/QName."<init>":(Ljava/lang/String;)V
      46: invokeinterface #24,  2           // InterfaceMethod org/apache/axiom/om/OMFactory.createOMElement:(Ljavax/xml/namespace/QName;)Lorg/apache/axiom/om/OMElement;
      51: astore_3
      52: new           #20                 // class org/apache/axis2/saaj/SOAPElementImpl
      55: dup
      56: aload_3
      57: invokespecial #21                 // Method org/apache/axis2/saaj/SOAPElementImpl."<init>":(Lorg/apache/axiom/om/OMElement;)V
      60: areturn

  public javax.xml.soap.SOAPElement createElement(java.lang.String, java.lang.String, java.lang.String) throws javax.xml.soap.SOAPException;
    Code:
       0: aconst_null
       1: astore        4
       3: aload_0
       4: getfield      #9                  // Field soapVersion:Ljava/lang/String;
       7: ldc           #13                 // String SOAP 1.2 Protocol
       9: invokevirtual #14                 // Method java/lang/String.equals:(Ljava/lang/Object;)Z
      12: ifeq          37
      15: aload_0
      16: getfield      #6                  // Field metaFactory:Lorg/apache/axiom/om/dom/DOMMetaFactory;
      19: invokeinterface #15,  1           // InterfaceMethod org/apache/axiom/om/dom/DOMMetaFactory.getSOAP12Factory:()Lorg/apache/axiom/soap/SOAPFactory;
      24: aload_1
      25: aload_3
      26: aload_2
      27: invokeinterface #16,  4           // InterfaceMethod org/apache/axiom/soap/SOAPFactory.createOMElement:(Ljava/lang/String;Ljava/lang/String;Ljava/lang/String;)Lorg/apache/axiom/om/OMElement;
      32: astore        4
      34: goto          56
      37: aload_0
      38: getfield      #6                  // Field metaFactory:Lorg/apache/axiom/om/dom/DOMMetaFactory;
      41: invokeinterface #17,  1           // InterfaceMethod org/apache/axiom/om/dom/DOMMetaFactory.getSOAP11Factory:()Lorg/apache/axiom/soap/SOAPFactory;
      46: aload_1
      47: aload_3
      48: aload_2
      49: invokeinterface #16,  4           // InterfaceMethod org/apache/axiom/soap/SOAPFactory.createOMElement:(Ljava/lang/String;Ljava/lang/String;Ljava/lang/String;)Lorg/apache/axiom/om/OMElement;
      54: astore        4
      56: new           #20                 // class org/apache/axis2/saaj/SOAPElementImpl
      59: dup
      60: aload         4
      62: invokespecial #21                 // Method org/apache/axis2/saaj/SOAPElementImpl."<init>":(Lorg/apache/axiom/om/OMElement;)V
      65: areturn

  public javax.xml.soap.Detail createDetail() throws javax.xml.soap.SOAPException;
    Code:
       0: aload_0
       1: getfield      #9                  // Field soapVersion:Ljava/lang/String;
       4: ldc           #13                 // String SOAP 1.2 Protocol
       6: invokevirtual #14                 // Method java/lang/String.equals:(Ljava/lang/Object;)Z
       9: ifeq          34
      12: new           #25                 // class org/apache/axis2/saaj/DetailImpl
      15: dup
      16: aload_0
      17: getfield      #6                  // Field metaFactory:Lorg/apache/axiom/om/dom/DOMMetaFactory;
      20: invokeinterface #15,  1           // InterfaceMethod org/apache/axiom/om/dom/DOMMetaFactory.getSOAP12Factory:()Lorg/apache/axiom/soap/SOAPFactory;
      25: invokeinterface #26,  1           // InterfaceMethod org/apache/axiom/soap/SOAPFactory.createSOAPFaultDetail:()Lorg/apache/axiom/soap/SOAPFaultDetail;
      30: invokespecial #27                 // Method org/apache/axis2/saaj/DetailImpl."<init>":(Lorg/apache/axiom/soap/SOAPFaultDetail;)V
      33: areturn
      34: new           #25                 // class org/apache/axis2/saaj/DetailImpl
      37: dup
      38: aload_0
      39: getfield      #6                  // Field metaFactory:Lorg/apache/axiom/om/dom/DOMMetaFactory;
      42: invokeinterface #17,  1           // InterfaceMethod org/apache/axiom/om/dom/DOMMetaFactory.getSOAP11Factory:()Lorg/apache/axiom/soap/SOAPFactory;
      47: invokeinterface #26,  1           // InterfaceMethod org/apache/axiom/soap/SOAPFactory.createSOAPFaultDetail:()Lorg/apache/axiom/soap/SOAPFaultDetail;
      52: invokespecial #27                 // Method org/apache/axis2/saaj/DetailImpl."<init>":(Lorg/apache/axiom/soap/SOAPFaultDetail;)V
      55: areturn

  public javax.xml.soap.Name createName(java.lang.String, java.lang.String, java.lang.String) throws javax.xml.soap.SOAPException;
    Code:
       0: new           #28                 // class org/apache/axis2/saaj/PrefixedQName
       3: dup
       4: aload_3
       5: aload_1
       6: aload_2
       7: invokespecial #29                 // Method org/apache/axis2/saaj/PrefixedQName."<init>":(Ljava/lang/String;Ljava/lang/String;Ljava/lang/String;)V
      10: areturn

  public javax.xml.soap.Name createName(java.lang.String) throws javax.xml.soap.SOAPException;
    Code:
       0: new           #28                 // class org/apache/axis2/saaj/PrefixedQName
       3: dup
       4: aconst_null
       5: aload_1
       6: aconst_null
       7: invokespecial #29                 // Method org/apache/axis2/saaj/PrefixedQName."<init>":(Ljava/lang/String;Ljava/lang/String;Ljava/lang/String;)V
      10: areturn

  public javax.xml.soap.SOAPFault createFault() throws javax.xml.soap.SOAPException;
    Code:
       0: aload_0
       1: getfield      #9                  // Field soapVersion:Ljava/lang/String;
       4: ldc           #13                 // String SOAP 1.2 Protocol
       6: invokevirtual #14                 // Method java/lang/String.equals:(Ljava/lang/Object;)Z
       9: ifeq          36
      12: aload_0
      13: getfield      #6                  // Field metaFactory:Lorg/apache/axiom/om/dom/DOMMetaFactory;
      16: invokeinterface #15,  1           // InterfaceMethod org/apache/axiom/om/dom/DOMMetaFactory.getSOAP12Factory:()Lorg/apache/axiom/soap/SOAPFactory;
      21: astore_1
      22: new           #30                 // class org/apache/axis2/saaj/SOAPFaultImpl
      25: dup
      26: aload_1
      27: invokeinterface #31,  1           // InterfaceMethod org/apache/axiom/soap/SOAPFactory.createSOAPFault:()Lorg/apache/axiom/soap/SOAPFault;
      32: invokespecial #32                 // Method org/apache/axis2/saaj/SOAPFaultImpl."<init>":(Lorg/apache/axiom/soap/SOAPFault;)V
      35: areturn
      36: aload_0
      37: getfield      #6                  // Field metaFactory:Lorg/apache/axiom/om/dom/DOMMetaFactory;
      40: invokeinterface #17,  1           // InterfaceMethod org/apache/axiom/om/dom/DOMMetaFactory.getSOAP11Factory:()Lorg/apache/axiom/soap/SOAPFactory;
      45: astore_1
      46: new           #30                 // class org/apache/axis2/saaj/SOAPFaultImpl
      49: dup
      50: aload_1
      51: invokeinterface #31,  1           // InterfaceMethod org/apache/axiom/soap/SOAPFactory.createSOAPFault:()Lorg/apache/axiom/soap/SOAPFault;
      56: invokespecial #32                 // Method org/apache/axis2/saaj/SOAPFaultImpl."<init>":(Lorg/apache/axiom/soap/SOAPFault;)V
      59: areturn

  public javax.xml.soap.SOAPFault createFault(java.lang.String, javax.xml.namespace.QName) throws javax.xml.soap.SOAPException;
    Code:
       0: aload_0
       1: getfield      #9                  // Field soapVersion:Ljava/lang/String;
       4: ldc           #13                 // String SOAP 1.2 Protocol
       6: invokevirtual #14                 // Method java/lang/String.equals:(Ljava/lang/Object;)Z
       9: ifeq          37
      12: new           #30                 // class org/apache/axis2/saaj/SOAPFaultImpl
      15: dup
      16: aload_0
      17: getfield      #6                  // Field metaFactory:Lorg/apache/axiom/om/dom/DOMMetaFactory;
      20: invokeinterface #15,  1           // InterfaceMethod org/apache/axiom/om/dom/DOMMetaFactory.getSOAP12Factory:()Lorg/apache/axiom/soap/SOAPFactory;
      25: invokeinterface #31,  1           // InterfaceMethod org/apache/axiom/soap/SOAPFactory.createSOAPFault:()Lorg/apache/axiom/soap/SOAPFault;
      30: invokespecial #32                 // Method org/apache/axis2/saaj/SOAPFaultImpl."<init>":(Lorg/apache/axiom/soap/SOAPFault;)V
      33: astore_3
      34: goto          59
      37: new           #30                 // class org/apache/axis2/saaj/SOAPFaultImpl
      40: dup
      41: aload_0
      42: getfield      #6                  // Field metaFactory:Lorg/apache/axiom/om/dom/DOMMetaFactory;
      45: invokeinterface #17,  1           // InterfaceMethod org/apache/axiom/om/dom/DOMMetaFactory.getSOAP11Factory:()Lorg/apache/axiom/soap/SOAPFactory;
      50: invokeinterface #31,  1           // InterfaceMethod org/apache/axiom/soap/SOAPFactory.createSOAPFault:()Lorg/apache/axiom/soap/SOAPFault;
      55: invokespecial #32                 // Method org/apache/axis2/saaj/SOAPFaultImpl."<init>":(Lorg/apache/axiom/soap/SOAPFault;)V
      58: astore_3
      59: aload_3
      60: aload_2
      61: invokeinterface #33,  2           // InterfaceMethod javax/xml/soap/SOAPFault.setFaultCode:(Ljavax/xml/namespace/QName;)V
      66: aload_3
      67: aload_1
      68: invokestatic  #34                 // Method java/util/Locale.getDefault:()Ljava/util/Locale;
      71: invokeinterface #35,  3           // InterfaceMethod javax/xml/soap/SOAPFault.addFaultReasonText:(Ljava/lang/String;Ljava/util/Locale;)V
      76: goto          94
      79: astore        4
      81: new           #37                 // class javax/xml/soap/SOAPException
      84: dup
      85: aload         4
      87: invokevirtual #38                 // Method java/lang/UnsupportedOperationException.getMessage:()Ljava/lang/String;
      90: invokespecial #39                 // Method javax/xml/soap/SOAPException."<init>":(Ljava/lang/String;)V
      93: athrow
      94: aload_3
      95: areturn
    Exception table:
       from    to  target type
          66    76    79   Class java/lang/UnsupportedOperationException

  public void setSOAPVersion(java.lang.String);
    Code:
       0: aload_0
       1: aload_1
       2: putfield      #9                  // Field soapVersion:Ljava/lang/String;
       5: return

  public javax.xml.soap.SOAPElement createElement(javax.xml.namespace.QName) throws javax.xml.soap.SOAPException;
    Code:
       0: aload_1
       1: invokevirtual #40                 // Method javax/xml/namespace/QName.getLocalPart:()Ljava/lang/String;
       4: astore_2
       5: aload_1
       6: invokevirtual #41                 // Method javax/xml/namespace/QName.getPrefix:()Ljava/lang/String;
       9: astore_3
      10: aload_1
      11: invokevirtual #42                 // Method javax/xml/namespace/QName.getNamespaceURI:()Ljava/lang/String;
      14: astore        4
      16: aload_0
      17: getfield      #6                  // Field metaFactory:Lorg/apache/axiom/om/dom/DOMMetaFactory;
      20: invokeinterface #18,  1           // InterfaceMethod org/apache/axiom/om/dom/DOMMetaFactory.getOMFactory:()Lorg/apache/axiom/om/OMFactory;
      25: aload_2
      26: aload         4
      28: aload_3
      29: invokeinterface #19,  4           // InterfaceMethod org/apache/axiom/om/OMFactory.createOMElement:(Ljava/lang/String;Ljava/lang/String;Ljava/lang/String;)Lorg/apache/axiom/om/OMElement;
      34: astore        5
      36: new           #20                 // class org/apache/axis2/saaj/SOAPElementImpl
      39: dup
      40: aload         5
      42: invokespecial #21                 // Method org/apache/axis2/saaj/SOAPElementImpl."<init>":(Lorg/apache/axiom/om/OMElement;)V
      45: areturn

  public javax.xml.soap.SOAPElement createElement(org.w3c.dom.Element) throws javax.xml.soap.SOAPException;
    Code:
       0: aconst_null
       1: astore_2
       2: aload_0
       3: getfield      #9                  // Field soapVersion:Ljava/lang/String;
       6: ldc           #13                 // String SOAP 1.2 Protocol
       8: invokevirtual #14                 // Method java/lang/String.equals:(Ljava/lang/Object;)Z
      11: ifeq          27
      14: aload_0
      15: getfield      #6                  // Field metaFactory:Lorg/apache/axiom/om/dom/DOMMetaFactory;
      18: invokeinterface #15,  1           // InterfaceMethod org/apache/axiom/om/dom/DOMMetaFactory.getSOAP12Factory:()Lorg/apache/axiom/soap/SOAPFactory;
      23: astore_2
      24: goto          37
      27: aload_0
      28: getfield      #6                  // Field metaFactory:Lorg/apache/axiom/om/dom/DOMMetaFactory;
      31: invokeinterface #17,  1           // InterfaceMethod org/apache/axiom/om/dom/DOMMetaFactory.getSOAP11Factory:()Lorg/apache/axiom/soap/SOAPFactory;
      36: astore_2
      37: aload_1
      38: invokeinterface #43,  1           // InterfaceMethod org/w3c/dom/Element.getPrefix:()Ljava/lang/String;
      43: astore_3
      44: aload_3
      45: ifnonnull     51
      48: ldc           #44                 // String
      50: astore_3
      51: aload_2
      52: aload_1
      53: invokeinterface #45,  1           // InterfaceMethod org/w3c/dom/Element.getNamespaceURI:()Ljava/lang/String;
      58: aload_3
      59: invokeinterface #46,  3           // InterfaceMethod org/apache/axiom/om/OMFactory.createOMNamespace:(Ljava/lang/String;Ljava/lang/String;)Lorg/apache/axiom/om/OMNamespace;
      64: astore        4
      66: aload_2
      67: aload_1
      68: invokeinterface #47,  1           // InterfaceMethod org/w3c/dom/Element.getLocalName:()Ljava/lang/String;
      73: aload         4
      75: invokeinterface #48,  3           // InterfaceMethod org/apache/axiom/om/OMFactory.createOMElement:(Ljava/lang/String;Lorg/apache/axiom/om/OMNamespace;)Lorg/apache/axiom/om/OMElement;
      80: astore        5
      82: new           #20                 // class org/apache/axis2/saaj/SOAPElementImpl
      85: dup
      86: aload         5
      88: invokespecial #21                 // Method org/apache/axis2/saaj/SOAPElementImpl."<init>":(Lorg/apache/axiom/om/OMElement;)V
      91: areturn
}
