Compiled from "AspspProfileRestConfig.java"
public class de.adorsys.psd2.aspsp.profile.config.AspspProfileRestConfig {
  private final de.adorsys.psd2.logger.web.LoggingContextInterceptor loggingContextInterceptor;

  private int readTimeout;

  private int connectionTimeout;

  public org.springframework.web.client.RestTemplate aspspProfileRestTemplate();
    Code:
       0: new           #1                  // class org/springframework/web/client/RestTemplate
       3: dup
       4: aload_0
       5: invokevirtual #2                  // Method clientHttpRequestFactory:()Lorg/springframework/http/client/ClientHttpRequestFactory;
       8: invokespecial #3                  // Method org/springframework/web/client/RestTemplate."<init>":(Lorg/springframework/http/client/ClientHttpRequestFactory;)V
      11: astore_1
      12: aload_1
      13: invokevirtual #4                  // Method org/springframework/web/client/RestTemplate.getMessageConverters:()Ljava/util/List;
      16: invokedynamic #5,  0              // InvokeDynamic #0:test:()Ljava/util/function/Predicate;
      21: invokeinterface #6,  2            // InterfaceMethod java/util/List.removeIf:(Ljava/util/function/Predicate;)Z
      26: pop
      27: aload_1
      28: new           #7                  // class de/adorsys/psd2/aspsp/profile/config/AspspProfileRestErrorHandler
      31: dup
      32: invokespecial #8                  // Method de/adorsys/psd2/aspsp/profile/config/AspspProfileRestErrorHandler."<init>":()V
      35: invokevirtual #9                  // Method org/springframework/web/client/RestTemplate.setErrorHandler:(Lorg/springframework/web/client/ResponseErrorHandler;)V
      38: aload_1
      39: invokevirtual #10                 // Method org/springframework/web/client/RestTemplate.getInterceptors:()Ljava/util/List;
      42: aload_0
      43: getfield      #11                 // Field loggingContextInterceptor:Lde/adorsys/psd2/logger/web/LoggingContextInterceptor;
      46: invokeinterface #12,  2           // InterfaceMethod java/util/List.add:(Ljava/lang/Object;)Z
      51: pop
      52: aload_1
      53: areturn

  private org.springframework.http.client.ClientHttpRequestFactory clientHttpRequestFactory();
    Code:
       0: new           #13                 // class org/springframework/http/client/SimpleClientHttpRequestFactory
       3: dup
       4: invokespecial #14                 // Method org/springframework/http/client/SimpleClientHttpRequestFactory."<init>":()V
       7: astore_1
       8: aload_1
       9: aload_0
      10: getfield      #15                 // Field readTimeout:I
      13: invokevirtual #16                 // Method org/springframework/http/client/SimpleClientHttpRequestFactory.setReadTimeout:(I)V
      16: aload_1
      17: aload_0
      18: getfield      #17                 // Field connectionTimeout:I
      21: invokevirtual #18                 // Method org/springframework/http/client/SimpleClientHttpRequestFactory.setConnectTimeout:(I)V
      24: aload_1
      25: areturn

  public de.adorsys.psd2.aspsp.profile.config.AspspProfileRestConfig(de.adorsys.psd2.logger.web.LoggingContextInterceptor);
    Code:
       0: aload_0
       1: invokespecial #19                 // Method java/lang/Object."<init>":()V
       4: aload_0
       5: aload_1
       6: putfield      #11                 // Field loggingContextInterceptor:Lde/adorsys/psd2/logger/web/LoggingContextInterceptor;
       9: return

  private static boolean lambda$aspspProfileRestTemplate$0(org.springframework.http.converter.HttpMessageConverter);
    Code:
       0: aload_0
       1: invokevirtual #20                 // Method java/lang/Object.getClass:()Ljava/lang/Class;
       4: ldc           #21                 // class org/springframework/http/converter/xml/MappingJackson2XmlHttpMessageConverter
       6: invokevirtual #22                 // Method java/lang/Class.isAssignableFrom:(Ljava/lang/Class;)Z
       9: ireturn
}
