Compiled from "DefinitionInformation.java"
final class software.amazon.awssdk.services.greengrass.model.DefinitionInformation$BuilderImpl implements software.amazon.awssdk.services.greengrass.model.DefinitionInformation$Builder {
  private java.lang.String arn;

  private java.lang.String creationTimestamp;

  private java.lang.String id;

  private java.lang.String lastUpdatedTimestamp;

  private java.lang.String latestVersion;

  private java.lang.String latestVersionArn;

  private java.lang.String name;

  private java.util.Map<java.lang.String, java.lang.String> tags;

  private software.amazon.awssdk.services.greengrass.model.DefinitionInformation$BuilderImpl();
    Code:
       0: aload_0
       1: invokespecial #11                 // Method java/lang/Object."<init>":()V
       4: aload_0
       5: invokestatic  #12                 // Method software/amazon/awssdk/core/util/DefaultSdkAutoConstructMap.getInstance:()Lsoftware/amazon/awssdk/core/util/DefaultSdkAutoConstructMap;
       8: putfield      #3                  // Field tags:Ljava/util/Map;
      11: return

  private software.amazon.awssdk.services.greengrass.model.DefinitionInformation$BuilderImpl(software.amazon.awssdk.services.greengrass.model.DefinitionInformation);
    Code:
       0: aload_0
       1: invokespecial #11                 // Method java/lang/Object."<init>":()V
       4: aload_0
       5: invokestatic  #12                 // Method software/amazon/awssdk/core/util/DefaultSdkAutoConstructMap.getInstance:()Lsoftware/amazon/awssdk/core/util/DefaultSdkAutoConstructMap;
       8: putfield      #3                  // Field tags:Ljava/util/Map;
      11: aload_0
      12: aload_1
      13: invokestatic  #13                 // Method software/amazon/awssdk/services/greengrass/model/DefinitionInformation.access$1000:(Lsoftware/amazon/awssdk/services/greengrass/model/DefinitionInformation;)Ljava/lang/String;
      16: invokevirtual #14                 // Method arn:(Ljava/lang/String;)Lsoftware/amazon/awssdk/services/greengrass/model/DefinitionInformation$Builder;
      19: pop
      20: aload_0
      21: aload_1
      22: invokestatic  #15                 // Method software/amazon/awssdk/services/greengrass/model/DefinitionInformation.access$1100:(Lsoftware/amazon/awssdk/services/greengrass/model/DefinitionInformation;)Ljava/lang/String;
      25: invokevirtual #16                 // Method creationTimestamp:(Ljava/lang/String;)Lsoftware/amazon/awssdk/services/greengrass/model/DefinitionInformation$Builder;
      28: pop
      29: aload_0
      30: aload_1
      31: invokestatic  #17                 // Method software/amazon/awssdk/services/greengrass/model/DefinitionInformation.access$1200:(Lsoftware/amazon/awssdk/services/greengrass/model/DefinitionInformation;)Ljava/lang/String;
      34: invokevirtual #18                 // Method id:(Ljava/lang/String;)Lsoftware/amazon/awssdk/services/greengrass/model/DefinitionInformation$Builder;
      37: pop
      38: aload_0
      39: aload_1
      40: invokestatic  #19                 // Method software/amazon/awssdk/services/greengrass/model/DefinitionInformation.access$1300:(Lsoftware/amazon/awssdk/services/greengrass/model/DefinitionInformation;)Ljava/lang/String;
      43: invokevirtual #20                 // Method lastUpdatedTimestamp:(Ljava/lang/String;)Lsoftware/amazon/awssdk/services/greengrass/model/DefinitionInformation$Builder;
      46: pop
      47: aload_0
      48: aload_1
      49: invokestatic  #21                 // Method software/amazon/awssdk/services/greengrass/model/DefinitionInformation.access$1400:(Lsoftware/amazon/awssdk/services/greengrass/model/DefinitionInformation;)Ljava/lang/String;
      52: invokevirtual #22                 // Method latestVersion:(Ljava/lang/String;)Lsoftware/amazon/awssdk/services/greengrass/model/DefinitionInformation$Builder;
      55: pop
      56: aload_0
      57: aload_1
      58: invokestatic  #23                 // Method software/amazon/awssdk/services/greengrass/model/DefinitionInformation.access$1500:(Lsoftware/amazon/awssdk/services/greengrass/model/DefinitionInformation;)Ljava/lang/String;
      61: invokevirtual #24                 // Method latestVersionArn:(Ljava/lang/String;)Lsoftware/amazon/awssdk/services/greengrass/model/DefinitionInformation$Builder;
      64: pop
      65: aload_0
      66: aload_1
      67: invokestatic  #25                 // Method software/amazon/awssdk/services/greengrass/model/DefinitionInformation.access$1600:(Lsoftware/amazon/awssdk/services/greengrass/model/DefinitionInformation;)Ljava/lang/String;
      70: invokevirtual #26                 // Method name:(Ljava/lang/String;)Lsoftware/amazon/awssdk/services/greengrass/model/DefinitionInformation$Builder;
      73: pop
      74: aload_0
      75: aload_1
      76: invokestatic  #27                 // Method software/amazon/awssdk/services/greengrass/model/DefinitionInformation.access$1700:(Lsoftware/amazon/awssdk/services/greengrass/model/DefinitionInformation;)Ljava/util/Map;
      79: invokevirtual #28                 // Method tags:(Ljava/util/Map;)Lsoftware/amazon/awssdk/services/greengrass/model/DefinitionInformation$Builder;
      82: pop
      83: return

  public final java.lang.String getArn();
    Code:
       0: aload_0
       1: getfield      #10                 // Field arn:Ljava/lang/String;
       4: areturn

  public final software.amazon.awssdk.services.greengrass.model.DefinitionInformation$Builder arn(java.lang.String);
    Code:
       0: aload_0
       1: aload_1
       2: putfield      #10                 // Field arn:Ljava/lang/String;
       5: aload_0
       6: areturn

  public final void setArn(java.lang.String);
    Code:
       0: aload_0
       1: aload_1
       2: putfield      #10                 // Field arn:Ljava/lang/String;
       5: return

  public final java.lang.String getCreationTimestamp();
    Code:
       0: aload_0
       1: getfield      #9                  // Field creationTimestamp:Ljava/lang/String;
       4: areturn

  public final software.amazon.awssdk.services.greengrass.model.DefinitionInformation$Builder creationTimestamp(java.lang.String);
    Code:
       0: aload_0
       1: aload_1
       2: putfield      #9                  // Field creationTimestamp:Ljava/lang/String;
       5: aload_0
       6: areturn

  public final void setCreationTimestamp(java.lang.String);
    Code:
       0: aload_0
       1: aload_1
       2: putfield      #9                  // Field creationTimestamp:Ljava/lang/String;
       5: return

  public final java.lang.String getId();
    Code:
       0: aload_0
       1: getfield      #8                  // Field id:Ljava/lang/String;
       4: areturn

  public final software.amazon.awssdk.services.greengrass.model.DefinitionInformation$Builder id(java.lang.String);
    Code:
       0: aload_0
       1: aload_1
       2: putfield      #8                  // Field id:Ljava/lang/String;
       5: aload_0
       6: areturn

  public final void setId(java.lang.String);
    Code:
       0: aload_0
       1: aload_1
       2: putfield      #8                  // Field id:Ljava/lang/String;
       5: return

  public final java.lang.String getLastUpdatedTimestamp();
    Code:
       0: aload_0
       1: getfield      #7                  // Field lastUpdatedTimestamp:Ljava/lang/String;
       4: areturn

  public final software.amazon.awssdk.services.greengrass.model.DefinitionInformation$Builder lastUpdatedTimestamp(java.lang.String);
    Code:
       0: aload_0
       1: aload_1
       2: putfield      #7                  // Field lastUpdatedTimestamp:Ljava/lang/String;
       5: aload_0
       6: areturn

  public final void setLastUpdatedTimestamp(java.lang.String);
    Code:
       0: aload_0
       1: aload_1
       2: putfield      #7                  // Field lastUpdatedTimestamp:Ljava/lang/String;
       5: return

  public final java.lang.String getLatestVersion();
    Code:
       0: aload_0
       1: getfield      #6                  // Field latestVersion:Ljava/lang/String;
       4: areturn

  public final software.amazon.awssdk.services.greengrass.model.DefinitionInformation$Builder latestVersion(java.lang.String);
    Code:
       0: aload_0
       1: aload_1
       2: putfield      #6                  // Field latestVersion:Ljava/lang/String;
       5: aload_0
       6: areturn

  public final void setLatestVersion(java.lang.String);
    Code:
       0: aload_0
       1: aload_1
       2: putfield      #6                  // Field latestVersion:Ljava/lang/String;
       5: return

  public final java.lang.String getLatestVersionArn();
    Code:
       0: aload_0
       1: getfield      #5                  // Field latestVersionArn:Ljava/lang/String;
       4: areturn

  public final software.amazon.awssdk.services.greengrass.model.DefinitionInformation$Builder latestVersionArn(java.lang.String);
    Code:
       0: aload_0
       1: aload_1
       2: putfield      #5                  // Field latestVersionArn:Ljava/lang/String;
       5: aload_0
       6: areturn

  public final void setLatestVersionArn(java.lang.String);
    Code:
       0: aload_0
       1: aload_1
       2: putfield      #5                  // Field latestVersionArn:Ljava/lang/String;
       5: return

  public final java.lang.String getName();
    Code:
       0: aload_0
       1: getfield      #4                  // Field name:Ljava/lang/String;
       4: areturn

  public final software.amazon.awssdk.services.greengrass.model.DefinitionInformation$Builder name(java.lang.String);
    Code:
       0: aload_0
       1: aload_1
       2: putfield      #4                  // Field name:Ljava/lang/String;
       5: aload_0
       6: areturn

  public final void setName(java.lang.String);
    Code:
       0: aload_0
       1: aload_1
       2: putfield      #4                  // Field name:Ljava/lang/String;
       5: return

  public final java.util.Map<java.lang.String, java.lang.String> getTags();
    Code:
       0: aload_0
       1: getfield      #3                  // Field tags:Ljava/util/Map;
       4: areturn

  public final software.amazon.awssdk.services.greengrass.model.DefinitionInformation$Builder tags(java.util.Map<java.lang.String, java.lang.String>);
    Code:
       0: aload_0
       1: aload_1
       2: invokestatic  #29                 // Method software/amazon/awssdk/services/greengrass/model/TagsCopier.copy:(Ljava/util/Map;)Ljava/util/Map;
       5: putfield      #3                  // Field tags:Ljava/util/Map;
       8: aload_0
       9: areturn

  public final void setTags(java.util.Map<java.lang.String, java.lang.String>);
    Code:
       0: aload_0
       1: aload_1
       2: invokestatic  #29                 // Method software/amazon/awssdk/services/greengrass/model/TagsCopier.copy:(Ljava/util/Map;)Ljava/util/Map;
       5: putfield      #3                  // Field tags:Ljava/util/Map;
       8: return

  public software.amazon.awssdk.services.greengrass.model.DefinitionInformation build();
    Code:
       0: new           #30                 // class software/amazon/awssdk/services/greengrass/model/DefinitionInformation
       3: dup
       4: aload_0
       5: aconst_null
       6: invokespecial #31                 // Method software/amazon/awssdk/services/greengrass/model/DefinitionInformation."<init>":(Lsoftware/amazon/awssdk/services/greengrass/model/DefinitionInformation$BuilderImpl;Lsoftware/amazon/awssdk/services/greengrass/model/DefinitionInformation$1;)V
       9: areturn

  public java.util.List<software.amazon.awssdk.core.SdkField<?>> sdkFields();
    Code:
       0: invokestatic  #32                 // Method software/amazon/awssdk/services/greengrass/model/DefinitionInformation.access$1900:()Ljava/util/List;
       3: areturn

  public java.lang.Object build();
    Code:
       0: aload_0
       1: invokevirtual #33                 // Method build:()Lsoftware/amazon/awssdk/services/greengrass/model/DefinitionInformation;
       4: areturn

  static java.lang.String access$000(software.amazon.awssdk.services.greengrass.model.DefinitionInformation$BuilderImpl);
    Code:
       0: aload_0
       1: getfield      #10                 // Field arn:Ljava/lang/String;
       4: areturn

  static java.lang.String access$100(software.amazon.awssdk.services.greengrass.model.DefinitionInformation$BuilderImpl);
    Code:
       0: aload_0
       1: getfield      #9                  // Field creationTimestamp:Ljava/lang/String;
       4: areturn

  static java.lang.String access$200(software.amazon.awssdk.services.greengrass.model.DefinitionInformation$BuilderImpl);
    Code:
       0: aload_0
       1: getfield      #8                  // Field id:Ljava/lang/String;
       4: areturn

  static java.lang.String access$300(software.amazon.awssdk.services.greengrass.model.DefinitionInformation$BuilderImpl);
    Code:
       0: aload_0
       1: getfield      #7                  // Field lastUpdatedTimestamp:Ljava/lang/String;
       4: areturn

  static java.lang.String access$400(software.amazon.awssdk.services.greengrass.model.DefinitionInformation$BuilderImpl);
    Code:
       0: aload_0
       1: getfield      #6                  // Field latestVersion:Ljava/lang/String;
       4: areturn

  static java.lang.String access$500(software.amazon.awssdk.services.greengrass.model.DefinitionInformation$BuilderImpl);
    Code:
       0: aload_0
       1: getfield      #5                  // Field latestVersionArn:Ljava/lang/String;
       4: areturn

  static java.lang.String access$600(software.amazon.awssdk.services.greengrass.model.DefinitionInformation$BuilderImpl);
    Code:
       0: aload_0
       1: getfield      #4                  // Field name:Ljava/lang/String;
       4: areturn

  static java.util.Map access$700(software.amazon.awssdk.services.greengrass.model.DefinitionInformation$BuilderImpl);
    Code:
       0: aload_0
       1: getfield      #3                  // Field tags:Ljava/util/Map;
       4: areturn

  software.amazon.awssdk.services.greengrass.model.DefinitionInformation$BuilderImpl(software.amazon.awssdk.services.greengrass.model.DefinitionInformation, software.amazon.awssdk.services.greengrass.model.DefinitionInformation$1);
    Code:
       0: aload_0
       1: aload_1
       2: invokespecial #2                  // Method "<init>":(Lsoftware/amazon/awssdk/services/greengrass/model/DefinitionInformation;)V
       5: return

  software.amazon.awssdk.services.greengrass.model.DefinitionInformation$BuilderImpl(software.amazon.awssdk.services.greengrass.model.DefinitionInformation$1);
    Code:
       0: aload_0
       1: invokespecial #1                  // Method "<init>":()V
       4: return
}
