Compiled from "FunctionConfigurationEnvironment.java"
public interface software.amazon.awssdk.services.greengrass.model.FunctionConfigurationEnvironment$Builder extends software.amazon.awssdk.core.SdkPojo, software.amazon.awssdk.utils.builder.CopyableBuilder<software.amazon.awssdk.services.greengrass.model.FunctionConfigurationEnvironment$Builder, software.amazon.awssdk.services.greengrass.model.FunctionConfigurationEnvironment> {
  public abstract software.amazon.awssdk.services.greengrass.model.FunctionConfigurationEnvironment$Builder accessSysfs(java.lang.Boolean);

  public abstract software.amazon.awssdk.services.greengrass.model.FunctionConfigurationEnvironment$Builder execution(software.amazon.awssdk.services.greengrass.model.FunctionExecutionConfig);

  public default software.amazon.awssdk.services.greengrass.model.FunctionConfigurationEnvironment$Builder execution(java.util.function.Consumer<software.amazon.awssdk.services.greengrass.model.FunctionExecutionConfig$Builder>);
    Code:
       0: aload_0
       1: invokestatic  #1                  // Method software/amazon/awssdk/services/greengrass/model/FunctionExecutionConfig.builder:()Lsoftware/amazon/awssdk/services/greengrass/model/FunctionExecutionConfig$Builder;
       4: aload_1
       5: invokeinterface #2,  2            // InterfaceMethod software/amazon/awssdk/services/greengrass/model/FunctionExecutionConfig$Builder.applyMutation:(Ljava/util/function/Consumer;)Lsoftware/amazon/awssdk/utils/builder/SdkBuilder;
      10: checkcast     #3                  // class software/amazon/awssdk/services/greengrass/model/FunctionExecutionConfig$Builder
      13: invokeinterface #4,  1            // InterfaceMethod software/amazon/awssdk/services/greengrass/model/FunctionExecutionConfig$Builder.build:()Ljava/lang/Object;
      18: checkcast     #5                  // class software/amazon/awssdk/services/greengrass/model/FunctionExecutionConfig
      21: invokeinterface #6,  2            // InterfaceMethod execution:(Lsoftware/amazon/awssdk/services/greengrass/model/FunctionExecutionConfig;)Lsoftware/amazon/awssdk/services/greengrass/model/FunctionConfigurationEnvironment$Builder;
      26: areturn

  public abstract software.amazon.awssdk.services.greengrass.model.FunctionConfigurationEnvironment$Builder resourceAccessPolicies(java.util.Collection<software.amazon.awssdk.services.greengrass.model.ResourceAccessPolicy>);

  public abstract software.amazon.awssdk.services.greengrass.model.FunctionConfigurationEnvironment$Builder resourceAccessPolicies(software.amazon.awssdk.services.greengrass.model.ResourceAccessPolicy...);

  public abstract software.amazon.awssdk.services.greengrass.model.FunctionConfigurationEnvironment$Builder resourceAccessPolicies(java.util.function.Consumer<software.amazon.awssdk.services.greengrass.model.ResourceAccessPolicy$Builder>...);

  public abstract software.amazon.awssdk.services.greengrass.model.FunctionConfigurationEnvironment$Builder variables(java.util.Map<java.lang.String, java.lang.String>);
}
