Compiled from "UpdateSubscriptionDefinitionResponse.java"
final class software.amazon.awssdk.services.greengrass.model.UpdateSubscriptionDefinitionResponse$BuilderImpl extends software.amazon.awssdk.services.greengrass.model.GreengrassResponse$BuilderImpl implements software.amazon.awssdk.services.greengrass.model.UpdateSubscriptionDefinitionResponse$Builder {
  private software.amazon.awssdk.services.greengrass.model.UpdateSubscriptionDefinitionResponse$BuilderImpl();
    Code:
       0: aload_0
       1: invokespecial #3                  // Method software/amazon/awssdk/services/greengrass/model/GreengrassResponse$BuilderImpl."<init>":()V
       4: return

  private software.amazon.awssdk.services.greengrass.model.UpdateSubscriptionDefinitionResponse$BuilderImpl(software.amazon.awssdk.services.greengrass.model.UpdateSubscriptionDefinitionResponse);
    Code:
       0: aload_0
       1: aload_1
       2: invokespecial #4                  // Method software/amazon/awssdk/services/greengrass/model/GreengrassResponse$BuilderImpl."<init>":(Lsoftware/amazon/awssdk/services/greengrass/model/GreengrassResponse;)V
       5: return

  public software.amazon.awssdk.services.greengrass.model.UpdateSubscriptionDefinitionResponse build();
    Code:
       0: new           #5                  // class software/amazon/awssdk/services/greengrass/model/UpdateSubscriptionDefinitionResponse
       3: dup
       4: aload_0
       5: aconst_null
       6: invokespecial #6                  // Method software/amazon/awssdk/services/greengrass/model/UpdateSubscriptionDefinitionResponse."<init>":(Lsoftware/amazon/awssdk/services/greengrass/model/UpdateSubscriptionDefinitionResponse$BuilderImpl;Lsoftware/amazon/awssdk/services/greengrass/model/UpdateSubscriptionDefinitionResponse$1;)V
       9: areturn

  public java.util.List<software.amazon.awssdk.core.SdkField<?>> sdkFields();
    Code:
       0: invokestatic  #7                  // Method software/amazon/awssdk/services/greengrass/model/UpdateSubscriptionDefinitionResponse.access$300:()Ljava/util/List;
       3: areturn

  public software.amazon.awssdk.services.greengrass.model.GreengrassResponse build();
    Code:
       0: aload_0
       1: invokevirtual #8                  // Method build:()Lsoftware/amazon/awssdk/services/greengrass/model/UpdateSubscriptionDefinitionResponse;
       4: areturn

  public software.amazon.awssdk.awscore.AwsResponse build();
    Code:
       0: aload_0
       1: invokevirtual #8                  // Method build:()Lsoftware/amazon/awssdk/services/greengrass/model/UpdateSubscriptionDefinitionResponse;
       4: areturn

  public software.amazon.awssdk.core.SdkResponse build();
    Code:
       0: aload_0
       1: invokevirtual #8                  // Method build:()Lsoftware/amazon/awssdk/services/greengrass/model/UpdateSubscriptionDefinitionResponse;
       4: areturn

  public java.lang.Object build();
    Code:
       0: aload_0
       1: invokevirtual #8                  // Method build:()Lsoftware/amazon/awssdk/services/greengrass/model/UpdateSubscriptionDefinitionResponse;
       4: areturn

  software.amazon.awssdk.services.greengrass.model.UpdateSubscriptionDefinitionResponse$BuilderImpl(software.amazon.awssdk.services.greengrass.model.UpdateSubscriptionDefinitionResponse, software.amazon.awssdk.services.greengrass.model.UpdateSubscriptionDefinitionResponse$1);
    Code:
       0: aload_0
       1: aload_1
       2: invokespecial #2                  // Method "<init>":(Lsoftware/amazon/awssdk/services/greengrass/model/UpdateSubscriptionDefinitionResponse;)V
       5: return

  software.amazon.awssdk.services.greengrass.model.UpdateSubscriptionDefinitionResponse$BuilderImpl(software.amazon.awssdk.services.greengrass.model.UpdateSubscriptionDefinitionResponse$1);
    Code:
       0: aload_0
       1: invokespecial #1                  // Method "<init>":()V
       4: return
}
