Compiled from "SimpleTypeStaxUnmarshallers.java"
public class com.amazonaws.transform.SimpleTypeStaxUnmarshallers$DateStaxUnmarshaller implements com.amazonaws.transform.Unmarshaller<java.util.Date, com.amazonaws.transform.StaxUnmarshallerContext> {
  private static final com.amazonaws.transform.SimpleTypeStaxUnmarshallers$DateStaxUnmarshaller instance;

  public com.amazonaws.transform.SimpleTypeStaxUnmarshallers$DateStaxUnmarshaller();
    Code:
       0: aload_0
       1: invokespecial #1                  // Method java/lang/Object."<init>":()V
       4: return

  public java.util.Date unmarshall(com.amazonaws.transform.StaxUnmarshallerContext) throws java.lang.Exception;
    Code:
       0: aload_1
       1: invokevirtual #2                  // Method com/amazonaws/transform/StaxUnmarshallerContext.readText:()Ljava/lang/String;
       4: astore_2
       5: aload_2
       6: ifnonnull     11
       9: aconst_null
      10: areturn
      11: aload_2
      12: invokestatic  #3                  // Method com/amazonaws/util/DateUtils.parseISO8601Date:(Ljava/lang/String;)Ljava/util/Date;
      15: areturn
      16: astore_3
      17: invokestatic  #5                  // Method com/amazonaws/transform/SimpleTypeStaxUnmarshallers.access$000:()Lorg/apache/commons/logging/Log;
      20: new           #6                  // class java/lang/StringBuilder
      23: dup
      24: invokespecial #7                  // Method java/lang/StringBuilder."<init>":()V
      27: ldc           #8                  // String Unable to parse date \'
      29: invokevirtual #9                  // Method java/lang/StringBuilder.append:(Ljava/lang/String;)Ljava/lang/StringBuilder;
      32: aload_2
      33: invokevirtual #9                  // Method java/lang/StringBuilder.append:(Ljava/lang/String;)Ljava/lang/StringBuilder;
      36: ldc           #10                 // String \':
      38: invokevirtual #9                  // Method java/lang/StringBuilder.append:(Ljava/lang/String;)Ljava/lang/StringBuilder;
      41: aload_3
      42: invokevirtual #11                 // Method java/lang/Exception.getMessage:()Ljava/lang/String;
      45: invokevirtual #9                  // Method java/lang/StringBuilder.append:(Ljava/lang/String;)Ljava/lang/StringBuilder;
      48: invokevirtual #12                 // Method java/lang/StringBuilder.toString:()Ljava/lang/String;
      51: aload_3
      52: invokeinterface #13,  3           // InterfaceMethod org/apache/commons/logging/Log.warn:(Ljava/lang/Object;Ljava/lang/Throwable;)V
      57: aconst_null
      58: areturn
    Exception table:
       from    to  target type
          11    15    16   Class java/lang/Exception

  public static com.amazonaws.transform.SimpleTypeStaxUnmarshallers$DateStaxUnmarshaller getInstance();
    Code:
       0: getstatic     #14                 // Field instance:Lcom/amazonaws/transform/SimpleTypeStaxUnmarshallers$DateStaxUnmarshaller;
       3: areturn

  public java.lang.Object unmarshall(java.lang.Object) throws java.lang.Exception;
    Code:
       0: aload_0
       1: aload_1
       2: checkcast     #15                 // class com/amazonaws/transform/StaxUnmarshallerContext
       5: invokevirtual #16                 // Method unmarshall:(Lcom/amazonaws/transform/StaxUnmarshallerContext;)Ljava/util/Date;
       8: areturn

  static {};
    Code:
       0: new           #17                 // class com/amazonaws/transform/SimpleTypeStaxUnmarshallers$DateStaxUnmarshaller
       3: dup
       4: invokespecial #18                 // Method "<init>":()V
       7: putstatic     #14                 // Field instance:Lcom/amazonaws/transform/SimpleTypeStaxUnmarshallers$DateStaxUnmarshaller;
      10: return
}
