Compiled from "UserConsumer.java"
public interface org.wildfly.swarm.config.management.security_realm.authentication.UserConsumer<T extends org.wildfly.swarm.config.management.security_realm.authentication.User<T>> {
  public abstract void accept(T);

  public default org.wildfly.swarm.config.management.security_realm.authentication.UserConsumer<T> andThen(org.wildfly.swarm.config.management.security_realm.authentication.UserConsumer<T>);
    Code:
       0: aload_0
       1: aload_1
       2: invokedynamic #1,  0              // InvokeDynamic #0:accept:(Lorg/wildfly/swarm/config/management/security_realm/authentication/UserConsumer;Lorg/wildfly/swarm/config/management/security_realm/authentication/UserConsumer;)Lorg/wildfly/swarm/config/management/security_realm/authentication/UserConsumer;
       7: areturn

  private void lambda$andThen$124(org.wildfly.swarm.config.management.security_realm.authentication.UserConsumer, org.wildfly.swarm.config.management.security_realm.authentication.User);
    Code:
       0: aload_0
       1: aload_2
       2: invokeinterface #2,  2            // InterfaceMethod accept:(Lorg/wildfly/swarm/config/management/security_realm/authentication/User;)V
       7: aload_1
       8: aload_2
       9: invokeinterface #2,  2            // InterfaceMethod accept:(Lorg/wildfly/swarm/config/management/security_realm/authentication/User;)V
      14: return
}
