Compiled from "ApplicationAttemptReport.java"
public abstract class org.apache.hadoop.yarn.api.records.ApplicationAttemptReport {
  public org.apache.hadoop.yarn.api.records.ApplicationAttemptReport();
    Code:
       0: aload_0
       1: invokespecial #1                  // Method java/lang/Object."<init>":()V
       4: return

  public static org.apache.hadoop.yarn.api.records.ApplicationAttemptReport newInstance(org.apache.hadoop.yarn.api.records.ApplicationAttemptId, java.lang.String, int, java.lang.String, java.lang.String, java.lang.String, org.apache.hadoop.yarn.api.records.YarnApplicationAttemptState, org.apache.hadoop.yarn.api.records.ContainerId, long, long);
    Code:
       0: ldc           #2                  // class org/apache/hadoop/yarn/api/records/ApplicationAttemptReport
       2: invokestatic  #3                  // Method org/apache/hadoop/yarn/util/Records.newRecord:(Ljava/lang/Class;)Ljava/lang/Object;
       5: checkcast     #2                  // class org/apache/hadoop/yarn/api/records/ApplicationAttemptReport
       8: astore        12
      10: aload         12
      12: aload_0
      13: invokevirtual #4                  // Method setApplicationAttemptId:(Lorg/apache/hadoop/yarn/api/records/ApplicationAttemptId;)V
      16: aload         12
      18: aload_1
      19: invokevirtual #5                  // Method setHost:(Ljava/lang/String;)V
      22: aload         12
      24: iload_2
      25: invokevirtual #6                  // Method setRpcPort:(I)V
      28: aload         12
      30: aload_3
      31: invokevirtual #7                  // Method setTrackingUrl:(Ljava/lang/String;)V
      34: aload         12
      36: aload         4
      38: invokevirtual #8                  // Method setOriginalTrackingUrl:(Ljava/lang/String;)V
      41: aload         12
      43: aload         5
      45: invokevirtual #9                  // Method setDiagnostics:(Ljava/lang/String;)V
      48: aload         12
      50: aload         6
      52: invokevirtual #10                 // Method setYarnApplicationAttemptState:(Lorg/apache/hadoop/yarn/api/records/YarnApplicationAttemptState;)V
      55: aload         12
      57: aload         7
      59: invokevirtual #11                 // Method setAMContainerId:(Lorg/apache/hadoop/yarn/api/records/ContainerId;)V
      62: aload         12
      64: lload         8
      66: invokevirtual #12                 // Method setStartTime:(J)V
      69: aload         12
      71: lload         10
      73: invokevirtual #13                 // Method setFinishTime:(J)V
      76: aload         12
      78: areturn

  public static org.apache.hadoop.yarn.api.records.ApplicationAttemptReport newInstance(org.apache.hadoop.yarn.api.records.ApplicationAttemptId, java.lang.String, int, java.lang.String, java.lang.String, java.lang.String, org.apache.hadoop.yarn.api.records.YarnApplicationAttemptState, org.apache.hadoop.yarn.api.records.ContainerId);
    Code:
       0: aload_0
       1: aload_1
       2: iload_2
       3: aload_3
       4: aload         4
       6: aload         5
       8: aload         6
      10: aload         7
      12: lconst_0
      13: lconst_0
      14: invokestatic  #14                 // Method newInstance:(Lorg/apache/hadoop/yarn/api/records/ApplicationAttemptId;Ljava/lang/String;ILjava/lang/String;Ljava/lang/String;Ljava/lang/String;Lorg/apache/hadoop/yarn/api/records/YarnApplicationAttemptState;Lorg/apache/hadoop/yarn/api/records/ContainerId;JJ)Lorg/apache/hadoop/yarn/api/records/ApplicationAttemptReport;
      17: areturn

  public abstract org.apache.hadoop.yarn.api.records.YarnApplicationAttemptState getYarnApplicationAttemptState();

  public abstract void setYarnApplicationAttemptState(org.apache.hadoop.yarn.api.records.YarnApplicationAttemptState);

  public abstract int getRpcPort();

  public abstract void setRpcPort(int);

  public abstract java.lang.String getHost();

  public abstract void setHost(java.lang.String);

  public abstract java.lang.String getDiagnostics();

  public abstract void setDiagnostics(java.lang.String);

  public abstract java.lang.String getTrackingUrl();

  public abstract void setTrackingUrl(java.lang.String);

  public abstract java.lang.String getOriginalTrackingUrl();

  public abstract void setOriginalTrackingUrl(java.lang.String);

  public abstract org.apache.hadoop.yarn.api.records.ApplicationAttemptId getApplicationAttemptId();

  public abstract void setApplicationAttemptId(org.apache.hadoop.yarn.api.records.ApplicationAttemptId);

  public abstract org.apache.hadoop.yarn.api.records.ContainerId getAMContainerId();

  public abstract void setAMContainerId(org.apache.hadoop.yarn.api.records.ContainerId);

  public abstract long getStartTime();

  public abstract void setStartTime(long);

  public abstract long getFinishTime();

  public abstract void setFinishTime(long);
}
