Compiled from "NodeAttributeInfo.java"
public abstract class org.apache.hadoop.yarn.api.records.NodeAttributeInfo {
  public org.apache.hadoop.yarn.api.records.NodeAttributeInfo();
    Code:
       0: aload_0
       1: invokespecial #1                  // Method java/lang/Object."<init>":()V
       4: return

  public static org.apache.hadoop.yarn.api.records.NodeAttributeInfo newInstance(org.apache.hadoop.yarn.api.records.NodeAttribute);
    Code:
       0: aload_0
       1: invokevirtual #2                  // Method org/apache/hadoop/yarn/api/records/NodeAttribute.getAttributeKey:()Lorg/apache/hadoop/yarn/api/records/NodeAttributeKey;
       4: aload_0
       5: invokevirtual #3                  // Method org/apache/hadoop/yarn/api/records/NodeAttribute.getAttributeType:()Lorg/apache/hadoop/yarn/api/records/NodeAttributeType;
       8: invokestatic  #4                  // Method newInstance:(Lorg/apache/hadoop/yarn/api/records/NodeAttributeKey;Lorg/apache/hadoop/yarn/api/records/NodeAttributeType;)Lorg/apache/hadoop/yarn/api/records/NodeAttributeInfo;
      11: areturn

  public static org.apache.hadoop.yarn.api.records.NodeAttributeInfo newInstance(org.apache.hadoop.yarn.api.records.NodeAttributeKey, org.apache.hadoop.yarn.api.records.NodeAttributeType);
    Code:
       0: ldc           #5                  // class org/apache/hadoop/yarn/api/records/NodeAttributeInfo
       2: invokestatic  #6                  // Method org/apache/hadoop/yarn/util/Records.newRecord:(Ljava/lang/Class;)Ljava/lang/Object;
       5: checkcast     #5                  // class org/apache/hadoop/yarn/api/records/NodeAttributeInfo
       8: astore_2
       9: aload_2
      10: aload_0
      11: invokevirtual #7                  // Method setAttributeKey:(Lorg/apache/hadoop/yarn/api/records/NodeAttributeKey;)V
      14: aload_2
      15: aload_1
      16: invokevirtual #8                  // Method setAttributeType:(Lorg/apache/hadoop/yarn/api/records/NodeAttributeType;)V
      19: aload_2
      20: areturn

  public abstract org.apache.hadoop.yarn.api.records.NodeAttributeKey getAttributeKey();

  public abstract void setAttributeKey(org.apache.hadoop.yarn.api.records.NodeAttributeKey);

  public abstract org.apache.hadoop.yarn.api.records.NodeAttributeType getAttributeType();

  public abstract void setAttributeType(org.apache.hadoop.yarn.api.records.NodeAttributeType);
}
