Compiled from "UpdateContainerRequest.java"
public abstract class org.apache.hadoop.yarn.api.records.UpdateContainerRequest {
  public org.apache.hadoop.yarn.api.records.UpdateContainerRequest();
    Code:
       0: aload_0
       1: invokespecial #1                  // Method java/lang/Object."<init>":()V
       4: return

  public static org.apache.hadoop.yarn.api.records.UpdateContainerRequest newInstance(int, org.apache.hadoop.yarn.api.records.ContainerId, org.apache.hadoop.yarn.api.records.ContainerUpdateType, org.apache.hadoop.yarn.api.records.Resource, org.apache.hadoop.yarn.api.records.ExecutionType);
    Code:
       0: ldc           #2                  // class org/apache/hadoop/yarn/api/records/UpdateContainerRequest
       2: invokestatic  #3                  // Method org/apache/hadoop/yarn/util/Records.newRecord:(Ljava/lang/Class;)Ljava/lang/Object;
       5: checkcast     #2                  // class org/apache/hadoop/yarn/api/records/UpdateContainerRequest
       8: astore        5
      10: aload         5
      12: iload_0
      13: invokevirtual #4                  // Method setContainerVersion:(I)V
      16: aload         5
      18: aload_1
      19: invokevirtual #5                  // Method setContainerId:(Lorg/apache/hadoop/yarn/api/records/ContainerId;)V
      22: aload         5
      24: aload_2
      25: invokevirtual #6                  // Method setContainerUpdateType:(Lorg/apache/hadoop/yarn/api/records/ContainerUpdateType;)V
      28: aload         5
      30: aload         4
      32: invokevirtual #7                  // Method setExecutionType:(Lorg/apache/hadoop/yarn/api/records/ExecutionType;)V
      35: aload         5
      37: aload_3
      38: invokevirtual #8                  // Method setCapability:(Lorg/apache/hadoop/yarn/api/records/Resource;)V
      41: aload         5
      43: areturn

  public abstract int getContainerVersion();

  public abstract void setContainerVersion(int);

  public abstract org.apache.hadoop.yarn.api.records.ContainerUpdateType getContainerUpdateType();

  public abstract void setContainerUpdateType(org.apache.hadoop.yarn.api.records.ContainerUpdateType);

  public abstract org.apache.hadoop.yarn.api.records.ContainerId getContainerId();

  public abstract void setContainerId(org.apache.hadoop.yarn.api.records.ContainerId);

  public abstract org.apache.hadoop.yarn.api.records.ExecutionType getExecutionType();

  public abstract void setExecutionType(org.apache.hadoop.yarn.api.records.ExecutionType);

  public abstract void setCapability(org.apache.hadoop.yarn.api.records.Resource);

  public abstract org.apache.hadoop.yarn.api.records.Resource getCapability();

  public int hashCode();
    Code:
       0: sipush        2153
       3: istore_1
       4: sipush        2459
       7: istore_2
       8: aload_0
       9: invokevirtual #9                  // Method getContainerId:()Lorg/apache/hadoop/yarn/api/records/ContainerId;
      12: astore_3
      13: aload_0
      14: invokevirtual #10                 // Method getExecutionType:()Lorg/apache/hadoop/yarn/api/records/ExecutionType;
      17: astore        4
      19: aload_0
      20: invokevirtual #11                 // Method getCapability:()Lorg/apache/hadoop/yarn/api/records/Resource;
      23: astore        5
      25: aload_0
      26: invokevirtual #12                 // Method getContainerUpdateType:()Lorg/apache/hadoop/yarn/api/records/ContainerUpdateType;
      29: astore        6
      31: sipush        2153
      34: iload_2
      35: imul
      36: aload         5
      38: ifnonnull     45
      41: iconst_0
      42: goto          50
      45: aload         5
      47: invokevirtual #13                 // Method org/apache/hadoop/yarn/api/records/Resource.hashCode:()I
      50: iadd
      51: istore_2
      52: sipush        2153
      55: iload_2
      56: imul
      57: aload_3
      58: ifnonnull     65
      61: iconst_0
      62: goto          69
      65: aload_3
      66: invokevirtual #14                 // Method org/apache/hadoop/yarn/api/records/ContainerId.hashCode:()I
      69: iadd
      70: istore_2
      71: sipush        2153
      74: iload_2
      75: imul
      76: aload_0
      77: invokevirtual #15                 // Method getContainerVersion:()I
      80: iadd
      81: istore_2
      82: sipush        2153
      85: iload_2
      86: imul
      87: aload         4
      89: ifnonnull     96
      92: iconst_0
      93: goto          101
      96: aload         4
      98: invokevirtual #16                 // Method org/apache/hadoop/yarn/api/records/ExecutionType.hashCode:()I
     101: iadd
     102: istore_2
     103: sipush        2153
     106: iload_2
     107: imul
     108: aload         6
     110: ifnonnull     117
     113: iconst_0
     114: goto          122
     117: aload         6
     119: invokevirtual #17                 // Method org/apache/hadoop/yarn/api/records/ContainerUpdateType.hashCode:()I
     122: iadd
     123: istore_2
     124: iload_2
     125: ireturn

  public java.lang.String toString();
    Code:
       0: new           #18                 // class java/lang/StringBuilder
       3: dup
       4: invokespecial #19                 // Method java/lang/StringBuilder."<init>":()V
       7: ldc           #20                 // String UpdateReq{containerId=
       9: invokevirtual #21                 // Method java/lang/StringBuilder.append:(Ljava/lang/String;)Ljava/lang/StringBuilder;
      12: aload_0
      13: invokevirtual #9                  // Method getContainerId:()Lorg/apache/hadoop/yarn/api/records/ContainerId;
      16: invokevirtual #22                 // Method java/lang/StringBuilder.append:(Ljava/lang/Object;)Ljava/lang/StringBuilder;
      19: ldc           #23                 // String , containerVersion=
      21: invokevirtual #21                 // Method java/lang/StringBuilder.append:(Ljava/lang/String;)Ljava/lang/StringBuilder;
      24: aload_0
      25: invokevirtual #15                 // Method getContainerVersion:()I
      28: invokevirtual #24                 // Method java/lang/StringBuilder.append:(I)Ljava/lang/StringBuilder;
      31: ldc           #25                 // String , targetExecType=
      33: invokevirtual #21                 // Method java/lang/StringBuilder.append:(Ljava/lang/String;)Ljava/lang/StringBuilder;
      36: aload_0
      37: invokevirtual #10                 // Method getExecutionType:()Lorg/apache/hadoop/yarn/api/records/ExecutionType;
      40: invokevirtual #22                 // Method java/lang/StringBuilder.append:(Ljava/lang/Object;)Ljava/lang/StringBuilder;
      43: ldc           #26                 // String , targetCapability=
      45: invokevirtual #21                 // Method java/lang/StringBuilder.append:(Ljava/lang/String;)Ljava/lang/StringBuilder;
      48: aload_0
      49: invokevirtual #11                 // Method getCapability:()Lorg/apache/hadoop/yarn/api/records/Resource;
      52: invokevirtual #22                 // Method java/lang/StringBuilder.append:(Ljava/lang/Object;)Ljava/lang/StringBuilder;
      55: ldc           #27                 // String , updateType=
      57: invokevirtual #21                 // Method java/lang/StringBuilder.append:(Ljava/lang/String;)Ljava/lang/StringBuilder;
      60: aload_0
      61: invokevirtual #12                 // Method getContainerUpdateType:()Lorg/apache/hadoop/yarn/api/records/ContainerUpdateType;
      64: invokevirtual #22                 // Method java/lang/StringBuilder.append:(Ljava/lang/Object;)Ljava/lang/StringBuilder;
      67: ldc           #28                 // String , }
      69: invokevirtual #21                 // Method java/lang/StringBuilder.append:(Ljava/lang/String;)Ljava/lang/StringBuilder;
      72: invokevirtual #29                 // Method java/lang/StringBuilder.toString:()Ljava/lang/String;
      75: areturn

  public boolean equals(java.lang.Object);
    Code:
       0: aload_0
       1: aload_1
       2: if_acmpne     7
       5: iconst_1
       6: ireturn
       7: aload_1
       8: ifnonnull     13
      11: iconst_0
      12: ireturn
      13: aload_0
      14: invokevirtual #30                 // Method java/lang/Object.getClass:()Ljava/lang/Class;
      17: aload_1
      18: invokevirtual #30                 // Method java/lang/Object.getClass:()Ljava/lang/Class;
      21: if_acmpeq     26
      24: iconst_0
      25: ireturn
      26: aload_1
      27: checkcast     #2                  // class org/apache/hadoop/yarn/api/records/UpdateContainerRequest
      30: astore_2
      31: aload_0
      32: invokevirtual #11                 // Method getCapability:()Lorg/apache/hadoop/yarn/api/records/Resource;
      35: astore_3
      36: aload_3
      37: ifnonnull     49
      40: aload_2
      41: invokevirtual #11                 // Method getCapability:()Lorg/apache/hadoop/yarn/api/records/Resource;
      44: ifnull        62
      47: iconst_0
      48: ireturn
      49: aload_3
      50: aload_2
      51: invokevirtual #11                 // Method getCapability:()Lorg/apache/hadoop/yarn/api/records/Resource;
      54: invokevirtual #31                 // Method org/apache/hadoop/yarn/api/records/Resource.equals:(Ljava/lang/Object;)Z
      57: ifne          62
      60: iconst_0
      61: ireturn
      62: aload_0
      63: invokevirtual #9                  // Method getContainerId:()Lorg/apache/hadoop/yarn/api/records/ContainerId;
      66: astore        4
      68: aload         4
      70: ifnonnull     82
      73: aload_2
      74: invokevirtual #9                  // Method getContainerId:()Lorg/apache/hadoop/yarn/api/records/ContainerId;
      77: ifnull        96
      80: iconst_0
      81: ireturn
      82: aload         4
      84: aload_2
      85: invokevirtual #9                  // Method getContainerId:()Lorg/apache/hadoop/yarn/api/records/ContainerId;
      88: invokevirtual #32                 // Method org/apache/hadoop/yarn/api/records/ContainerId.equals:(Ljava/lang/Object;)Z
      91: ifne          96
      94: iconst_0
      95: ireturn
      96: aload_0
      97: invokevirtual #15                 // Method getContainerVersion:()I
     100: aload_2
     101: invokevirtual #15                 // Method getContainerVersion:()I
     104: if_icmpeq     109
     107: iconst_0
     108: ireturn
     109: aload_0
     110: invokevirtual #10                 // Method getExecutionType:()Lorg/apache/hadoop/yarn/api/records/ExecutionType;
     113: astore        5
     115: aload         5
     117: ifnonnull     129
     120: aload_2
     121: invokevirtual #10                 // Method getExecutionType:()Lorg/apache/hadoop/yarn/api/records/ExecutionType;
     124: ifnull        143
     127: iconst_0
     128: ireturn
     129: aload         5
     131: aload_2
     132: invokevirtual #10                 // Method getExecutionType:()Lorg/apache/hadoop/yarn/api/records/ExecutionType;
     135: invokevirtual #33                 // Method org/apache/hadoop/yarn/api/records/ExecutionType.equals:(Ljava/lang/Object;)Z
     138: ifne          143
     141: iconst_0
     142: ireturn
     143: aload_0
     144: invokevirtual #12                 // Method getContainerUpdateType:()Lorg/apache/hadoop/yarn/api/records/ContainerUpdateType;
     147: astore        6
     149: aload         6
     151: ifnonnull     163
     154: aload_2
     155: invokevirtual #12                 // Method getContainerUpdateType:()Lorg/apache/hadoop/yarn/api/records/ContainerUpdateType;
     158: ifnull        177
     161: iconst_0
     162: ireturn
     163: aload         6
     165: aload_2
     166: invokevirtual #12                 // Method getContainerUpdateType:()Lorg/apache/hadoop/yarn/api/records/ContainerUpdateType;
     169: invokevirtual #34                 // Method org/apache/hadoop/yarn/api/records/ContainerUpdateType.equals:(Ljava/lang/Object;)Z
     172: ifne          177
     175: iconst_0
     176: ireturn
     177: iconst_1
     178: ireturn
}
