Compiled from "DSCompiler.java"
public class org.apache.commons.math3.analysis.differentiation.DSCompiler {
  private static java.util.concurrent.atomic.AtomicReference<org.apache.commons.math3.analysis.differentiation.DSCompiler[][]> compilers;

  private final int parameters;

  private final int order;

  private final int[][] sizes;

  private final int[][] derivativesIndirection;

  private final int[] lowerIndirection;

  private final int[][][] multIndirection;

  private final int[][][] compIndirection;

  private org.apache.commons.math3.analysis.differentiation.DSCompiler(int, int, org.apache.commons.math3.analysis.differentiation.DSCompiler, org.apache.commons.math3.analysis.differentiation.DSCompiler);
    Code:
       0: aload_0
       1: invokespecial #1                  // Method java/lang/Object."<init>":()V
       4: aload_0
       5: iload_1
       6: putfield      #2                  // Field parameters:I
       9: aload_0
      10: iload_2
      11: putfield      #3                  // Field order:I
      14: aload_0
      15: iload_1
      16: iload_2
      17: aload_3
      18: invokestatic  #4                  // Method compileSizes:(IILorg/apache/commons/math3/analysis/differentiation/DSCompiler;)[[I
      21: putfield      #5                  // Field sizes:[[I
      24: aload_0
      25: iload_1
      26: iload_2
      27: aload_3
      28: aload         4
      30: invokestatic  #6                  // Method compileDerivativesIndirection:(IILorg/apache/commons/math3/analysis/differentiation/DSCompiler;Lorg/apache/commons/math3/analysis/differentiation/DSCompiler;)[[I
      33: putfield      #7                  // Field derivativesIndirection:[[I
      36: aload_0
      37: iload_1
      38: iload_2
      39: aload_3
      40: aload         4
      42: invokestatic  #8                  // Method compileLowerIndirection:(IILorg/apache/commons/math3/analysis/differentiation/DSCompiler;Lorg/apache/commons/math3/analysis/differentiation/DSCompiler;)[I
      45: putfield      #9                  // Field lowerIndirection:[I
      48: aload_0
      49: iload_1
      50: iload_2
      51: aload_3
      52: aload         4
      54: aload_0
      55: getfield      #9                  // Field lowerIndirection:[I
      58: invokestatic  #10                 // Method compileMultiplicationIndirection:(IILorg/apache/commons/math3/analysis/differentiation/DSCompiler;Lorg/apache/commons/math3/analysis/differentiation/DSCompiler;[I)[[[I
      61: putfield      #11                 // Field multIndirection:[[[I
      64: aload_0
      65: iload_1
      66: iload_2
      67: aload_3
      68: aload         4
      70: aload_0
      71: getfield      #5                  // Field sizes:[[I
      74: aload_0
      75: getfield      #7                  // Field derivativesIndirection:[[I
      78: invokestatic  #12                 // Method compileCompositionIndirection:(IILorg/apache/commons/math3/analysis/differentiation/DSCompiler;Lorg/apache/commons/math3/analysis/differentiation/DSCompiler;[[I[[I)[[[I
      81: putfield      #13                 // Field compIndirection:[[[I
      84: return

  public static org.apache.commons.math3.analysis.differentiation.DSCompiler getCompiler(int, int);
    Code:
       0: getstatic     #14                 // Field compilers:Ljava/util/concurrent/atomic/AtomicReference;
       3: invokevirtual #15                 // Method java/util/concurrent/atomic/AtomicReference.get:()Ljava/lang/Object;
       6: checkcast     #16                 // class "[[Lorg/apache/commons/math3/analysis/differentiation/DSCompiler;"
       9: astore_2
      10: aload_2
      11: ifnull        42
      14: aload_2
      15: arraylength
      16: iload_0
      17: if_icmple     42
      20: aload_2
      21: iload_0
      22: aaload
      23: arraylength
      24: iload_1
      25: if_icmple     42
      28: aload_2
      29: iload_0
      30: aaload
      31: iload_1
      32: aaload
      33: ifnull        42
      36: aload_2
      37: iload_0
      38: aaload
      39: iload_1
      40: aaload
      41: areturn
      42: iload_0
      43: aload_2
      44: ifnonnull     51
      47: iconst_0
      48: goto          53
      51: aload_2
      52: arraylength
      53: invokestatic  #17                 // Method org/apache/commons/math3/util/FastMath.max:(II)I
      56: istore_3
      57: iload_1
      58: aload_2
      59: ifnonnull     66
      62: iconst_0
      63: goto          70
      66: aload_2
      67: iconst_0
      68: aaload
      69: arraylength
      70: invokestatic  #17                 // Method org/apache/commons/math3/util/FastMath.max:(II)I
      73: istore        4
      75: iload_3
      76: iconst_1
      77: iadd
      78: iload         4
      80: iconst_1
      81: iadd
      82: multianewarray #16,  2            // class "[[Lorg/apache/commons/math3/analysis/differentiation/DSCompiler;"
      86: astore        5
      88: aload_2
      89: ifnull        127
      92: iconst_0
      93: istore        6
      95: iload         6
      97: aload_2
      98: arraylength
      99: if_icmpge     127
     102: aload_2
     103: iload         6
     105: aaload
     106: iconst_0
     107: aload         5
     109: iload         6
     111: aaload
     112: iconst_0
     113: aload_2
     114: iload         6
     116: aaload
     117: arraylength
     118: invokestatic  #18                 // Method java/lang/System.arraycopy:(Ljava/lang/Object;ILjava/lang/Object;II)V
     121: iinc          6, 1
     124: goto          95
     127: iconst_0
     128: istore        6
     130: iload         6
     132: iload_0
     133: iload_1
     134: iadd
     135: if_icmpgt     254
     138: iconst_0
     139: iload         6
     141: iload_0
     142: isub
     143: invokestatic  #17                 // Method org/apache/commons/math3/util/FastMath.max:(II)I
     146: istore        7
     148: iload         7
     150: iload_1
     151: iload         6
     153: invokestatic  #19                 // Method org/apache/commons/math3/util/FastMath.min:(II)I
     156: if_icmpgt     248
     159: iload         6
     161: iload         7
     163: isub
     164: istore        8
     166: aload         5
     168: iload         8
     170: aaload
     171: iload         7
     173: aaload
     174: ifnonnull     242
     177: iload         8
     179: ifne          186
     182: aconst_null
     183: goto          196
     186: aload         5
     188: iload         8
     190: iconst_1
     191: isub
     192: aaload
     193: iload         7
     195: aaload
     196: astore        9
     198: iload         7
     200: ifne          207
     203: aconst_null
     204: goto          217
     207: aload         5
     209: iload         8
     211: aaload
     212: iload         7
     214: iconst_1
     215: isub
     216: aaload
     217: astore        10
     219: aload         5
     221: iload         8
     223: aaload
     224: iload         7
     226: new           #20                 // class org/apache/commons/math3/analysis/differentiation/DSCompiler
     229: dup
     230: iload         8
     232: iload         7
     234: aload         9
     236: aload         10
     238: invokespecial #21                 // Method "<init>":(IILorg/apache/commons/math3/analysis/differentiation/DSCompiler;Lorg/apache/commons/math3/analysis/differentiation/DSCompiler;)V
     241: aastore
     242: iinc          7, 1
     245: goto          148
     248: iinc          6, 1
     251: goto          130
     254: getstatic     #14                 // Field compilers:Ljava/util/concurrent/atomic/AtomicReference;
     257: aload_2
     258: aload         5
     260: invokevirtual #22                 // Method java/util/concurrent/atomic/AtomicReference.compareAndSet:(Ljava/lang/Object;Ljava/lang/Object;)Z
     263: pop
     264: aload         5
     266: iload_0
     267: aaload
     268: iload_1
     269: aaload
     270: areturn

  private static int[][] compileSizes(int, int, org.apache.commons.math3.analysis.differentiation.DSCompiler);
    Code:
       0: iload_0
       1: iconst_1
       2: iadd
       3: iload_1
       4: iconst_1
       5: iadd
       6: multianewarray #23,  2            // class "[[I"
      10: astore_3
      11: iload_0
      12: ifne          25
      15: aload_3
      16: iconst_0
      17: aaload
      18: iconst_1
      19: invokestatic  #24                 // Method java/util/Arrays.fill:([II)V
      22: goto          82
      25: aload_2
      26: getfield      #5                  // Field sizes:[[I
      29: iconst_0
      30: aload_3
      31: iconst_0
      32: iload_0
      33: invokestatic  #18                 // Method java/lang/System.arraycopy:(Ljava/lang/Object;ILjava/lang/Object;II)V
      36: aload_3
      37: iload_0
      38: aaload
      39: iconst_0
      40: iconst_1
      41: iastore
      42: iconst_0
      43: istore        4
      45: iload         4
      47: iload_1
      48: if_icmpge     82
      51: aload_3
      52: iload_0
      53: aaload
      54: iload         4
      56: iconst_1
      57: iadd
      58: aload_3
      59: iload_0
      60: aaload
      61: iload         4
      63: iaload
      64: aload_3
      65: iload_0
      66: iconst_1
      67: isub
      68: aaload
      69: iload         4
      71: iconst_1
      72: iadd
      73: iaload
      74: iadd
      75: iastore
      76: iinc          4, 1
      79: goto          45
      82: aload_3
      83: areturn

  private static int[][] compileDerivativesIndirection(int, int, org.apache.commons.math3.analysis.differentiation.DSCompiler, org.apache.commons.math3.analysis.differentiation.DSCompiler);
    Code:
       0: iload_0
       1: ifeq          8
       4: iload_1
       5: ifne          15
       8: iconst_1
       9: iload_0
      10: multianewarray #23,  2            // class "[[I"
      14: areturn
      15: aload_2
      16: getfield      #7                  // Field derivativesIndirection:[[I
      19: arraylength
      20: istore        4
      22: aload_3
      23: getfield      #7                  // Field derivativesIndirection:[[I
      26: arraylength
      27: istore        5
      29: iload         4
      31: iload         5
      33: iadd
      34: iload_0
      35: multianewarray #23,  2            // class "[[I"
      39: astore        6
      41: iconst_0
      42: istore        7
      44: iload         7
      46: iload         4
      48: if_icmpge     77
      51: aload_2
      52: getfield      #7                  // Field derivativesIndirection:[[I
      55: iload         7
      57: aaload
      58: iconst_0
      59: aload         6
      61: iload         7
      63: aaload
      64: iconst_0
      65: iload_0
      66: iconst_1
      67: isub
      68: invokestatic  #18                 // Method java/lang/System.arraycopy:(Ljava/lang/Object;ILjava/lang/Object;II)V
      71: iinc          7, 1
      74: goto          44
      77: iconst_0
      78: istore        7
      80: iload         7
      82: iload         5
      84: if_icmpge     130
      87: aload_3
      88: getfield      #7                  // Field derivativesIndirection:[[I
      91: iload         7
      93: aaload
      94: iconst_0
      95: aload         6
      97: iload         4
      99: iload         7
     101: iadd
     102: aaload
     103: iconst_0
     104: iload_0
     105: invokestatic  #18                 // Method java/lang/System.arraycopy:(Ljava/lang/Object;ILjava/lang/Object;II)V
     108: aload         6
     110: iload         4
     112: iload         7
     114: iadd
     115: aaload
     116: iload_0
     117: iconst_1
     118: isub
     119: dup2
     120: iaload
     121: iconst_1
     122: iadd
     123: iastore
     124: iinc          7, 1
     127: goto          80
     130: aload         6
     132: areturn

  private static int[] compileLowerIndirection(int, int, org.apache.commons.math3.analysis.differentiation.DSCompiler, org.apache.commons.math3.analysis.differentiation.DSCompiler);
    Code:
       0: iload_0
       1: ifeq          9
       4: iload_1
       5: iconst_1
       6: if_icmpgt     17
       9: iconst_1
      10: newarray       int
      12: dup
      13: iconst_0
      14: iconst_0
      15: iastore
      16: areturn
      17: aload_2
      18: getfield      #9                  // Field lowerIndirection:[I
      21: arraylength
      22: istore        4
      24: aload_3
      25: getfield      #9                  // Field lowerIndirection:[I
      28: arraylength
      29: istore        5
      31: iload         4
      33: iload         5
      35: iadd
      36: newarray       int
      38: astore        6
      40: aload_2
      41: getfield      #9                  // Field lowerIndirection:[I
      44: iconst_0
      45: aload         6
      47: iconst_0
      48: iload         4
      50: invokestatic  #18                 // Method java/lang/System.arraycopy:(Ljava/lang/Object;ILjava/lang/Object;II)V
      53: iconst_0
      54: istore        7
      56: iload         7
      58: iload         5
      60: if_icmpge     89
      63: aload         6
      65: iload         4
      67: iload         7
      69: iadd
      70: aload_2
      71: invokevirtual #25                 // Method getSize:()I
      74: aload_3
      75: getfield      #9                  // Field lowerIndirection:[I
      78: iload         7
      80: iaload
      81: iadd
      82: iastore
      83: iinc          7, 1
      86: goto          56
      89: aload         6
      91: areturn

  private static int[][][] compileMultiplicationIndirection(int, int, org.apache.commons.math3.analysis.differentiation.DSCompiler, org.apache.commons.math3.analysis.differentiation.DSCompiler, int[]);
    Code:
       0: iload_0
       1: ifeq          8
       4: iload_1
       5: ifne          38
       8: iconst_1
       9: anewarray     #23                 // class "[[I"
      12: dup
      13: iconst_0
      14: iconst_1
      15: anewarray     #26                 // class "[I"
      18: dup
      19: iconst_0
      20: iconst_3
      21: newarray       int
      23: dup
      24: iconst_0
      25: iconst_1
      26: iastore
      27: dup
      28: iconst_1
      29: iconst_0
      30: iastore
      31: dup
      32: iconst_2
      33: iconst_0
      34: iastore
      35: aastore
      36: aastore
      37: areturn
      38: aload_2
      39: getfield      #11                 // Field multIndirection:[[[I
      42: arraylength
      43: istore        5
      45: aload_3
      46: getfield      #11                 // Field multIndirection:[[[I
      49: arraylength
      50: istore        6
      52: iload         5
      54: iload         6
      56: iadd
      57: anewarray     #23                 // class "[[I"
      60: astore        7
      62: aload_2
      63: getfield      #11                 // Field multIndirection:[[[I
      66: iconst_0
      67: aload         7
      69: iconst_0
      70: iload         5
      72: invokestatic  #18                 // Method java/lang/System.arraycopy:(Ljava/lang/Object;ILjava/lang/Object;II)V
      75: iconst_0
      76: istore        8
      78: iload         8
      80: iload         6
      82: if_icmpge     392
      85: aload_3
      86: getfield      #11                 // Field multIndirection:[[[I
      89: iload         8
      91: aaload
      92: astore        9
      94: new           #27                 // class java/util/ArrayList
      97: dup
      98: invokespecial #28                 // Method java/util/ArrayList."<init>":()V
     101: astore        10
     103: iconst_0
     104: istore        11
     106: iload         11
     108: aload         9
     110: arraylength
     111: if_icmpge     214
     114: aload         10
     116: iconst_3
     117: newarray       int
     119: dup
     120: iconst_0
     121: aload         9
     123: iload         11
     125: aaload
     126: iconst_0
     127: iaload
     128: iastore
     129: dup
     130: iconst_1
     131: aload         4
     133: aload         9
     135: iload         11
     137: aaload
     138: iconst_1
     139: iaload
     140: iaload
     141: iastore
     142: dup
     143: iconst_2
     144: iload         5
     146: aload         9
     148: iload         11
     150: aaload
     151: iconst_2
     152: iaload
     153: iadd
     154: iastore
     155: invokeinterface #29,  2           // InterfaceMethod java/util/List.add:(Ljava/lang/Object;)Z
     160: pop
     161: aload         10
     163: iconst_3
     164: newarray       int
     166: dup
     167: iconst_0
     168: aload         9
     170: iload         11
     172: aaload
     173: iconst_0
     174: iaload
     175: iastore
     176: dup
     177: iconst_1
     178: iload         5
     180: aload         9
     182: iload         11
     184: aaload
     185: iconst_1
     186: iaload
     187: iadd
     188: iastore
     189: dup
     190: iconst_2
     191: aload         4
     193: aload         9
     195: iload         11
     197: aaload
     198: iconst_2
     199: iaload
     200: iaload
     201: iastore
     202: invokeinterface #29,  2           // InterfaceMethod java/util/List.add:(Ljava/lang/Object;)Z
     207: pop
     208: iinc          11, 1
     211: goto          106
     214: new           #27                 // class java/util/ArrayList
     217: dup
     218: aload         10
     220: invokeinterface #30,  1           // InterfaceMethod java/util/List.size:()I
     225: invokespecial #31                 // Method java/util/ArrayList."<init>":(I)V
     228: astore        11
     230: iconst_0
     231: istore        12
     233: iload         12
     235: aload         10
     237: invokeinterface #30,  1           // InterfaceMethod java/util/List.size:()I
     242: if_icmpge     358
     245: aload         10
     247: iload         12
     249: invokeinterface #32,  2           // InterfaceMethod java/util/List.get:(I)Ljava/lang/Object;
     254: checkcast     #26                 // class "[I"
     257: astore        13
     259: aload         13
     261: iconst_0
     262: iaload
     263: ifle          352
     266: iload         12
     268: iconst_1
     269: iadd
     270: istore        14
     272: iload         14
     274: aload         10
     276: invokeinterface #30,  1           // InterfaceMethod java/util/List.size:()I
     281: if_icmpge     342
     284: aload         10
     286: iload         14
     288: invokeinterface #32,  2           // InterfaceMethod java/util/List.get:(I)Ljava/lang/Object;
     293: checkcast     #26                 // class "[I"
     296: astore        15
     298: aload         13
     300: iconst_1
     301: iaload
     302: aload         15
     304: iconst_1
     305: iaload
     306: if_icmpne     336
     309: aload         13
     311: iconst_2
     312: iaload
     313: aload         15
     315: iconst_2
     316: iaload
     317: if_icmpne     336
     320: aload         13
     322: iconst_0
     323: dup2
     324: iaload
     325: aload         15
     327: iconst_0
     328: iaload
     329: iadd
     330: iastore
     331: aload         15
     333: iconst_0
     334: iconst_0
     335: iastore
     336: iinc          14, 1
     339: goto          272
     342: aload         11
     344: aload         13
     346: invokeinterface #29,  2           // InterfaceMethod java/util/List.add:(Ljava/lang/Object;)Z
     351: pop
     352: iinc          12, 1
     355: goto          233
     358: aload         7
     360: iload         5
     362: iload         8
     364: iadd
     365: aload         11
     367: aload         11
     369: invokeinterface #30,  1           // InterfaceMethod java/util/List.size:()I
     374: anewarray     #26                 // class "[I"
     377: invokeinterface #33,  2           // InterfaceMethod java/util/List.toArray:([Ljava/lang/Object;)[Ljava/lang/Object;
     382: checkcast     #23                 // class "[[I"
     385: aastore
     386: iinc          8, 1
     389: goto          78
     392: aload         7
     394: areturn

  private static int[][][] compileCompositionIndirection(int, int, org.apache.commons.math3.analysis.differentiation.DSCompiler, org.apache.commons.math3.analysis.differentiation.DSCompiler, int[][], int[][]);
    Code:
       0: iload_0
       1: ifeq          8
       4: iload_1
       5: ifne          34
       8: iconst_1
       9: anewarray     #23                 // class "[[I"
      12: dup
      13: iconst_0
      14: iconst_1
      15: anewarray     #26                 // class "[I"
      18: dup
      19: iconst_0
      20: iconst_2
      21: newarray       int
      23: dup
      24: iconst_0
      25: iconst_1
      26: iastore
      27: dup
      28: iconst_1
      29: iconst_0
      30: iastore
      31: aastore
      32: aastore
      33: areturn
      34: aload_2
      35: getfield      #13                 // Field compIndirection:[[[I
      38: arraylength
      39: istore        6
      41: aload_3
      42: getfield      #13                 // Field compIndirection:[[[I
      45: arraylength
      46: istore        7
      48: iload         6
      50: iload         7
      52: iadd
      53: anewarray     #23                 // class "[[I"
      56: astore        8
      58: aload_2
      59: getfield      #13                 // Field compIndirection:[[[I
      62: iconst_0
      63: aload         8
      65: iconst_0
      66: iload         6
      68: invokestatic  #18                 // Method java/lang/System.arraycopy:(Ljava/lang/Object;ILjava/lang/Object;II)V
      71: iconst_0
      72: istore        9
      74: iload         9
      76: iload         7
      78: if_icmpge     606
      81: new           #27                 // class java/util/ArrayList
      84: dup
      85: invokespecial #28                 // Method java/util/ArrayList."<init>":()V
      88: astore        10
      90: aload_3
      91: getfield      #13                 // Field compIndirection:[[[I
      94: iload         9
      96: aaload
      97: astore        11
      99: aload         11
     101: arraylength
     102: istore        12
     104: iconst_0
     105: istore        13
     107: iload         13
     109: iload         12
     111: if_icmpge     384
     114: aload         11
     116: iload         13
     118: aaload
     119: astore        14
     121: aload         14
     123: arraylength
     124: iconst_1
     125: iadd
     126: newarray       int
     128: astore        15
     130: aload         15
     132: iconst_0
     133: aload         14
     135: iconst_0
     136: iaload
     137: iastore
     138: aload         15
     140: iconst_1
     141: aload         14
     143: iconst_1
     144: iaload
     145: iconst_1
     146: iadd
     147: iastore
     148: iload_0
     149: newarray       int
     151: astore        16
     153: aload         16
     155: iload_0
     156: iconst_1
     157: isub
     158: iconst_1
     159: iastore
     160: aload         15
     162: aload         14
     164: arraylength
     165: iload_0
     166: iload_1
     167: aload         4
     169: aload         16
     171: invokestatic  #34                 // Method getPartialDerivativeIndex:(II[[I[I)I
     174: iastore
     175: iconst_2
     176: istore        17
     178: iload         17
     180: aload         14
     182: arraylength
     183: if_icmpge     214
     186: aload         15
     188: iload         17
     190: aload         14
     192: iload         17
     194: iaload
     195: iload_0
     196: aload_3
     197: getfield      #7                  // Field derivativesIndirection:[[I
     200: iload_0
     201: iload_1
     202: aload         4
     204: invokestatic  #35                 // Method convertIndex:(II[[III[[I)I
     207: iastore
     208: iinc          17, 1
     211: goto          178
     214: aload         15
     216: iconst_2
     217: aload         15
     219: arraylength
     220: invokestatic  #36                 // Method java/util/Arrays.sort:([III)V
     223: aload         10
     225: aload         15
     227: invokeinterface #29,  2           // InterfaceMethod java/util/List.add:(Ljava/lang/Object;)Z
     232: pop
     233: iconst_2
     234: istore        17
     236: iload         17
     238: aload         14
     240: arraylength
     241: if_icmpge     378
     244: aload         14
     246: arraylength
     247: newarray       int
     249: astore        18
     251: aload         18
     253: iconst_0
     254: aload         14
     256: iconst_0
     257: iaload
     258: iastore
     259: aload         18
     261: iconst_1
     262: aload         14
     264: iconst_1
     265: iaload
     266: iastore
     267: iconst_2
     268: istore        19
     270: iload         19
     272: aload         14
     274: arraylength
     275: if_icmpge     353
     278: aload         18
     280: iload         19
     282: aload         14
     284: iload         19
     286: iaload
     287: iload_0
     288: aload_3
     289: getfield      #7                  // Field derivativesIndirection:[[I
     292: iload_0
     293: iload_1
     294: aload         4
     296: invokestatic  #35                 // Method convertIndex:(II[[III[[I)I
     299: iastore
     300: iload         19
     302: iload         17
     304: if_icmpne     347
     307: aload         5
     309: aload         18
     311: iload         19
     313: iaload
     314: aaload
     315: iconst_0
     316: aload         16
     318: iconst_0
     319: iload_0
     320: invokestatic  #18                 // Method java/lang/System.arraycopy:(Ljava/lang/Object;ILjava/lang/Object;II)V
     323: aload         16
     325: iload_0
     326: iconst_1
     327: isub
     328: dup2
     329: iaload
     330: iconst_1
     331: iadd
     332: iastore
     333: aload         18
     335: iload         19
     337: iload_0
     338: iload_1
     339: aload         4
     341: aload         16
     343: invokestatic  #34                 // Method getPartialDerivativeIndex:(II[[I[I)I
     346: iastore
     347: iinc          19, 1
     350: goto          270
     353: aload         18
     355: iconst_2
     356: aload         18
     358: arraylength
     359: invokestatic  #36                 // Method java/util/Arrays.sort:([III)V
     362: aload         10
     364: aload         18
     366: invokeinterface #29,  2           // InterfaceMethod java/util/List.add:(Ljava/lang/Object;)Z
     371: pop
     372: iinc          17, 1
     375: goto          236
     378: iinc          13, 1
     381: goto          107
     384: new           #27                 // class java/util/ArrayList
     387: dup
     388: aload         10
     390: invokeinterface #30,  1           // InterfaceMethod java/util/List.size:()I
     395: invokespecial #31                 // Method java/util/ArrayList."<init>":(I)V
     398: astore        11
     400: iconst_0
     401: istore        12
     403: iload         12
     405: aload         10
     407: invokeinterface #30,  1           // InterfaceMethod java/util/List.size:()I
     412: if_icmpge     572
     415: aload         10
     417: iload         12
     419: invokeinterface #32,  2           // InterfaceMethod java/util/List.get:(I)Ljava/lang/Object;
     424: checkcast     #26                 // class "[I"
     427: astore        13
     429: aload         13
     431: iconst_0
     432: iaload
     433: ifle          566
     436: iload         12
     438: iconst_1
     439: iadd
     440: istore        14
     442: iload         14
     444: aload         10
     446: invokeinterface #30,  1           // InterfaceMethod java/util/List.size:()I
     451: if_icmpge     556
     454: aload         10
     456: iload         14
     458: invokeinterface #32,  2           // InterfaceMethod java/util/List.get:(I)Ljava/lang/Object;
     463: checkcast     #26                 // class "[I"
     466: astore        15
     468: aload         13
     470: arraylength
     471: aload         15
     473: arraylength
     474: if_icmpne     481
     477: iconst_1
     478: goto          482
     481: iconst_0
     482: istore        16
     484: iconst_1
     485: istore        17
     487: iload         16
     489: ifeq          529
     492: iload         17
     494: aload         13
     496: arraylength
     497: if_icmpge     529
     500: iload         16
     502: aload         13
     504: iload         17
     506: iaload
     507: aload         15
     509: iload         17
     511: iaload
     512: if_icmpne     519
     515: iconst_1
     516: goto          520
     519: iconst_0
     520: iand
     521: istore        16
     523: iinc          17, 1
     526: goto          487
     529: iload         16
     531: ifeq          550
     534: aload         13
     536: iconst_0
     537: dup2
     538: iaload
     539: aload         15
     541: iconst_0
     542: iaload
     543: iadd
     544: iastore
     545: aload         15
     547: iconst_0
     548: iconst_0
     549: iastore
     550: iinc          14, 1
     553: goto          442
     556: aload         11
     558: aload         13
     560: invokeinterface #29,  2           // InterfaceMethod java/util/List.add:(Ljava/lang/Object;)Z
     565: pop
     566: iinc          12, 1
     569: goto          403
     572: aload         8
     574: iload         6
     576: iload         9
     578: iadd
     579: aload         11
     581: aload         11
     583: invokeinterface #30,  1           // InterfaceMethod java/util/List.size:()I
     588: anewarray     #26                 // class "[I"
     591: invokeinterface #33,  2           // InterfaceMethod java/util/List.toArray:([Ljava/lang/Object;)[Ljava/lang/Object;
     596: checkcast     #23                 // class "[[I"
     599: aastore
     600: iinc          9, 1
     603: goto          74
     606: aload         8
     608: areturn

  public int getPartialDerivativeIndex(int...) throws org.apache.commons.math3.exception.DimensionMismatchException, org.apache.commons.math3.exception.NumberIsTooLargeException;
    Code:
       0: aload_1
       1: arraylength
       2: aload_0
       3: invokevirtual #37                 // Method getFreeParameters:()I
       6: if_icmpeq     23
       9: new           #38                 // class org/apache/commons/math3/exception/DimensionMismatchException
      12: dup
      13: aload_1
      14: arraylength
      15: aload_0
      16: invokevirtual #37                 // Method getFreeParameters:()I
      19: invokespecial #39                 // Method org/apache/commons/math3/exception/DimensionMismatchException."<init>":(II)V
      22: athrow
      23: aload_0
      24: getfield      #2                  // Field parameters:I
      27: aload_0
      28: getfield      #3                  // Field order:I
      31: aload_0
      32: getfield      #5                  // Field sizes:[[I
      35: aload_1
      36: invokestatic  #34                 // Method getPartialDerivativeIndex:(II[[I[I)I
      39: ireturn

  private static int getPartialDerivativeIndex(int, int, int[][], int...) throws org.apache.commons.math3.exception.NumberIsTooLargeException;
    Code:
       0: iconst_0
       1: istore        4
       3: iload_1
       4: istore        5
       6: iconst_0
       7: istore        6
       9: iload_0
      10: iconst_1
      11: isub
      12: istore        7
      14: iload         7
      16: iflt          88
      19: aload_3
      20: iload         7
      22: iaload
      23: istore        8
      25: iload         6
      27: iload         8
      29: iadd
      30: istore        6
      32: iload         6
      34: iload_1
      35: if_icmple     56
      38: new           #40                 // class org/apache/commons/math3/exception/NumberIsTooLargeException
      41: dup
      42: iload         6
      44: invokestatic  #41                 // Method java/lang/Integer.valueOf:(I)Ljava/lang/Integer;
      47: iload_1
      48: invokestatic  #41                 // Method java/lang/Integer.valueOf:(I)Ljava/lang/Integer;
      51: iconst_1
      52: invokespecial #42                 // Method org/apache/commons/math3/exception/NumberIsTooLargeException."<init>":(Ljava/lang/Number;Ljava/lang/Number;Z)V
      55: athrow
      56: iload         8
      58: iinc          8, -1
      61: ifle          82
      64: iload         4
      66: aload_2
      67: iload         7
      69: aaload
      70: iload         5
      72: iinc          5, -1
      75: iaload
      76: iadd
      77: istore        4
      79: goto          56
      82: iinc          7, -1
      85: goto          14
      88: iload         4
      90: ireturn

  private static int convertIndex(int, int, int[][], int, int, int[][]);
    Code:
       0: iload_3
       1: newarray       int
       3: astore        6
       5: aload_2
       6: iload_0
       7: aaload
       8: iconst_0
       9: aload         6
      11: iconst_0
      12: iload_1
      13: iload_3
      14: invokestatic  #19                 // Method org/apache/commons/math3/util/FastMath.min:(II)I
      17: invokestatic  #18                 // Method java/lang/System.arraycopy:(Ljava/lang/Object;ILjava/lang/Object;II)V
      20: iload_3
      21: iload         4
      23: aload         5
      25: aload         6
      27: invokestatic  #34                 // Method getPartialDerivativeIndex:(II[[I[I)I
      30: ireturn

  public int[] getPartialDerivativeOrders(int);
    Code:
       0: aload_0
       1: getfield      #7                  // Field derivativesIndirection:[[I
       4: iload_1
       5: aaload
       6: areturn

  public int getFreeParameters();
    Code:
       0: aload_0
       1: getfield      #2                  // Field parameters:I
       4: ireturn

  public int getOrder();
    Code:
       0: aload_0
       1: getfield      #3                  // Field order:I
       4: ireturn

  public int getSize();
    Code:
       0: aload_0
       1: getfield      #5                  // Field sizes:[[I
       4: aload_0
       5: getfield      #2                  // Field parameters:I
       8: aaload
       9: aload_0
      10: getfield      #3                  // Field order:I
      13: iaload
      14: ireturn

  public void linearCombination(double, double[], int, double, double[], int, double[], int);
    Code:
       0: iconst_0
       1: istore        11
       3: iload         11
       5: aload_0
       6: invokevirtual #25                 // Method getSize:()I
       9: if_icmpge     47
      12: aload         9
      14: iload         10
      16: iload         11
      18: iadd
      19: dload_1
      20: aload_3
      21: iload         4
      23: iload         11
      25: iadd
      26: daload
      27: dload         5
      29: aload         7
      31: iload         8
      33: iload         11
      35: iadd
      36: daload
      37: invokestatic  #43                 // Method org/apache/commons/math3/util/MathArrays.linearCombination:(DDDD)D
      40: dastore
      41: iinc          11, 1
      44: goto          3
      47: return

  public void linearCombination(double, double[], int, double, double[], int, double, double[], int, double[], int);
    Code:
       0: iconst_0
       1: istore        15
       3: iload         15
       5: aload_0
       6: invokevirtual #25                 // Method getSize:()I
       9: if_icmpge     57
      12: aload         13
      14: iload         14
      16: iload         15
      18: iadd
      19: dload_1
      20: aload_3
      21: iload         4
      23: iload         15
      25: iadd
      26: daload
      27: dload         5
      29: aload         7
      31: iload         8
      33: iload         15
      35: iadd
      36: daload
      37: dload         9
      39: aload         11
      41: iload         12
      43: iload         15
      45: iadd
      46: daload
      47: invokestatic  #44                 // Method org/apache/commons/math3/util/MathArrays.linearCombination:(DDDDDD)D
      50: dastore
      51: iinc          15, 1
      54: goto          3
      57: return

  public void linearCombination(double, double[], int, double, double[], int, double, double[], int, double, double[], int, double[], int);
    Code:
       0: iconst_0
       1: istore        19
       3: iload         19
       5: aload_0
       6: invokevirtual #25                 // Method getSize:()I
       9: if_icmpge     67
      12: aload         17
      14: iload         18
      16: iload         19
      18: iadd
      19: dload_1
      20: aload_3
      21: iload         4
      23: iload         19
      25: iadd
      26: daload
      27: dload         5
      29: aload         7
      31: iload         8
      33: iload         19
      35: iadd
      36: daload
      37: dload         9
      39: aload         11
      41: iload         12
      43: iload         19
      45: iadd
      46: daload
      47: dload         13
      49: aload         15
      51: iload         16
      53: iload         19
      55: iadd
      56: daload
      57: invokestatic  #45                 // Method org/apache/commons/math3/util/MathArrays.linearCombination:(DDDDDDDD)D
      60: dastore
      61: iinc          19, 1
      64: goto          3
      67: return

  public void add(double[], int, double[], int, double[], int);
    Code:
       0: iconst_0
       1: istore        7
       3: iload         7
       5: aload_0
       6: invokevirtual #25                 // Method getSize:()I
       9: if_icmpge     40
      12: aload         5
      14: iload         6
      16: iload         7
      18: iadd
      19: aload_1
      20: iload_2
      21: iload         7
      23: iadd
      24: daload
      25: aload_3
      26: iload         4
      28: iload         7
      30: iadd
      31: daload
      32: dadd
      33: dastore
      34: iinc          7, 1
      37: goto          3
      40: return

  public void subtract(double[], int, double[], int, double[], int);
    Code:
       0: iconst_0
       1: istore        7
       3: iload         7
       5: aload_0
       6: invokevirtual #25                 // Method getSize:()I
       9: if_icmpge     40
      12: aload         5
      14: iload         6
      16: iload         7
      18: iadd
      19: aload_1
      20: iload_2
      21: iload         7
      23: iadd
      24: daload
      25: aload_3
      26: iload         4
      28: iload         7
      30: iadd
      31: daload
      32: dsub
      33: dastore
      34: iinc          7, 1
      37: goto          3
      40: return

  public void multiply(double[], int, double[], int, double[], int);
    Code:
       0: iconst_0
       1: istore        7
       3: iload         7
       5: aload_0
       6: getfield      #11                 // Field multIndirection:[[[I
       9: arraylength
      10: if_icmpge     96
      13: aload_0
      14: getfield      #11                 // Field multIndirection:[[[I
      17: iload         7
      19: aaload
      20: astore        8
      22: dconst_0
      23: dstore        9
      25: iconst_0
      26: istore        11
      28: iload         11
      30: aload         8
      32: arraylength
      33: if_icmpge     80
      36: dload         9
      38: aload         8
      40: iload         11
      42: aaload
      43: iconst_0
      44: iaload
      45: i2d
      46: aload_1
      47: iload_2
      48: aload         8
      50: iload         11
      52: aaload
      53: iconst_1
      54: iaload
      55: iadd
      56: daload
      57: dmul
      58: aload_3
      59: iload         4
      61: aload         8
      63: iload         11
      65: aaload
      66: iconst_2
      67: iaload
      68: iadd
      69: daload
      70: dmul
      71: dadd
      72: dstore        9
      74: iinc          11, 1
      77: goto          28
      80: aload         5
      82: iload         6
      84: iload         7
      86: iadd
      87: dload         9
      89: dastore
      90: iinc          7, 1
      93: goto          3
      96: return

  public void divide(double[], int, double[], int, double[], int);
    Code:
       0: aload_0
       1: invokevirtual #25                 // Method getSize:()I
       4: newarray       double
       6: astore        7
       8: aload_0
       9: aload_3
      10: iload_2
      11: iconst_m1
      12: aload         7
      14: iconst_0
      15: invokevirtual #46                 // Method pow:([DII[DI)V
      18: aload_0
      19: aload_1
      20: iload_2
      21: aload         7
      23: iconst_0
      24: aload         5
      26: iload         6
      28: invokevirtual #47                 // Method multiply:([DI[DI[DI)V
      31: return

  public void remainder(double[], int, double[], int, double[], int);
    Code:
       0: aload_1
       1: iload_2
       2: daload
       3: aload_3
       4: iload         4
       6: daload
       7: drem
       8: dstore        7
      10: aload_1
      11: iload_2
      12: daload
      13: dload         7
      15: dsub
      16: aload_3
      17: iload         4
      19: daload
      20: ddiv
      21: invokestatic  #48                 // Method org/apache/commons/math3/util/FastMath.rint:(D)D
      24: dstore        9
      26: aload         5
      28: iload         6
      30: dload         7
      32: dastore
      33: iconst_1
      34: istore        11
      36: iload         11
      38: aload_0
      39: invokevirtual #25                 // Method getSize:()I
      42: if_icmpge     76
      45: aload         5
      47: iload         6
      49: iload         11
      51: iadd
      52: aload_1
      53: iload_2
      54: iload         11
      56: iadd
      57: daload
      58: dload         9
      60: aload_3
      61: iload         4
      63: iload         11
      65: iadd
      66: daload
      67: dmul
      68: dsub
      69: dastore
      70: iinc          11, 1
      73: goto          36
      76: return

  public void pow(double[], int, double, double[], int);
    Code:
       0: iconst_1
       1: aload_0
       2: getfield      #3                  // Field order:I
       5: iadd
       6: newarray       double
       8: astore        7
      10: aload_1
      11: iload_2
      12: daload
      13: dload_3
      14: aload_0
      15: getfield      #3                  // Field order:I
      18: i2d
      19: dsub
      20: invokestatic  #49                 // Method org/apache/commons/math3/util/FastMath.pow:(DD)D
      23: dstore        8
      25: aload_0
      26: getfield      #3                  // Field order:I
      29: istore        10
      31: iload         10
      33: ifle          57
      36: aload         7
      38: iload         10
      40: dload         8
      42: dastore
      43: dload         8
      45: aload_1
      46: iload_2
      47: daload
      48: dmul
      49: dstore        8
      51: iinc          10, -1
      54: goto          31
      57: aload         7
      59: iconst_0
      60: dload         8
      62: dastore
      63: dload_3
      64: dstore        10
      66: iconst_1
      67: istore        12
      69: iload         12
      71: aload_0
      72: getfield      #3                  // Field order:I
      75: if_icmpgt     104
      78: aload         7
      80: iload         12
      82: dup2
      83: daload
      84: dload         10
      86: dmul
      87: dastore
      88: dload         10
      90: dload_3
      91: iload         12
      93: i2d
      94: dsub
      95: dmul
      96: dstore        10
      98: iinc          12, 1
     101: goto          69
     104: aload_0
     105: aload_1
     106: iload_2
     107: aload         7
     109: aload         5
     111: iload         6
     113: invokevirtual #50                 // Method compose:([DI[D[DI)V
     116: return

  public void pow(double[], int, int, double[], int);
    Code:
       0: iload_3
       1: ifne          28
       4: aload         4
       6: iload         5
       8: dconst_1
       9: dastore
      10: aload         4
      12: iload         5
      14: iconst_1
      15: iadd
      16: iload         5
      18: aload_0
      19: invokevirtual #25                 // Method getSize:()I
      22: iadd
      23: dconst_0
      24: invokestatic  #51                 // Method java/util/Arrays.fill:([DIID)V
      27: return
      28: iconst_1
      29: aload_0
      30: getfield      #3                  // Field order:I
      33: iadd
      34: newarray       double
      36: astore        6
      38: iload_3
      39: ifle          103
      42: aload_0
      43: getfield      #3                  // Field order:I
      46: iload_3
      47: invokestatic  #19                 // Method org/apache/commons/math3/util/FastMath.min:(II)I
      50: istore        7
      52: aload_1
      53: iload_2
      54: daload
      55: iload_3
      56: iload         7
      58: isub
      59: invokestatic  #52                 // Method org/apache/commons/math3/util/FastMath.pow:(DI)D
      62: dstore        8
      64: iload         7
      66: istore        10
      68: iload         10
      70: ifle          94
      73: aload         6
      75: iload         10
      77: dload         8
      79: dastore
      80: dload         8
      82: aload_1
      83: iload_2
      84: daload
      85: dmul
      86: dstore        8
      88: iinc          10, -1
      91: goto          68
      94: aload         6
      96: iconst_0
      97: dload         8
      99: dastore
     100: goto          151
     103: dconst_1
     104: aload_1
     105: iload_2
     106: daload
     107: ddiv
     108: dstore        7
     110: dload         7
     112: iload_3
     113: ineg
     114: invokestatic  #52                 // Method org/apache/commons/math3/util/FastMath.pow:(DI)D
     117: dstore        9
     119: iconst_0
     120: istore        11
     122: iload         11
     124: aload_0
     125: getfield      #3                  // Field order:I
     128: if_icmpgt     151
     131: aload         6
     133: iload         11
     135: dload         9
     137: dastore
     138: dload         9
     140: dload         7
     142: dmul
     143: dstore        9
     145: iinc          11, 1
     148: goto          122
     151: iload_3
     152: i2d
     153: dstore        7
     155: iconst_1
     156: istore        9
     158: iload         9
     160: aload_0
     161: getfield      #3                  // Field order:I
     164: if_icmpgt     193
     167: aload         6
     169: iload         9
     171: dup2
     172: daload
     173: dload         7
     175: dmul
     176: dastore
     177: dload         7
     179: iload_3
     180: iload         9
     182: isub
     183: i2d
     184: dmul
     185: dstore        7
     187: iinc          9, 1
     190: goto          158
     193: aload_0
     194: aload_1
     195: iload_2
     196: aload         6
     198: aload         4
     200: iload         5
     202: invokevirtual #50                 // Method compose:([DI[D[DI)V
     205: return

  public void pow(double[], int, double[], int, double[], int);
    Code:
       0: aload_0
       1: invokevirtual #25                 // Method getSize:()I
       4: newarray       double
       6: astore        7
       8: aload_0
       9: aload_1
      10: iload_2
      11: aload         7
      13: iconst_0
      14: invokevirtual #53                 // Method log:([DI[DI)V
      17: aload_0
      18: invokevirtual #25                 // Method getSize:()I
      21: newarray       double
      23: astore        8
      25: aload_0
      26: aload         7
      28: iconst_0
      29: aload_3
      30: iload         4
      32: aload         8
      34: iconst_0
      35: invokevirtual #47                 // Method multiply:([DI[DI[DI)V
      38: aload_0
      39: aload         8
      41: iconst_0
      42: aload         5
      44: iload         6
      46: invokevirtual #54                 // Method exp:([DI[DI)V
      49: return

  public void rootN(double[], int, int, double[], int);
    Code:
       0: iconst_1
       1: aload_0
       2: getfield      #3                  // Field order:I
       5: iadd
       6: newarray       double
       8: astore        6
      10: iload_3
      11: iconst_2
      12: if_icmpne     38
      15: aload         6
      17: iconst_0
      18: aload_1
      19: iload_2
      20: daload
      21: invokestatic  #55                 // Method org/apache/commons/math3/util/FastMath.sqrt:(D)D
      24: dastore
      25: ldc2_w        #56                 // double 0.5d
      28: aload         6
      30: iconst_0
      31: daload
      32: ddiv
      33: dstore        7
      35: goto          104
      38: iload_3
      39: iconst_3
      40: if_icmpne     73
      43: aload         6
      45: iconst_0
      46: aload_1
      47: iload_2
      48: daload
      49: invokestatic  #58                 // Method org/apache/commons/math3/util/FastMath.cbrt:(D)D
      52: dastore
      53: dconst_1
      54: ldc2_w        #59                 // double 3.0d
      57: aload         6
      59: iconst_0
      60: daload
      61: dmul
      62: aload         6
      64: iconst_0
      65: daload
      66: dmul
      67: ddiv
      68: dstore        7
      70: goto          104
      73: aload         6
      75: iconst_0
      76: aload_1
      77: iload_2
      78: daload
      79: dconst_1
      80: iload_3
      81: i2d
      82: ddiv
      83: invokestatic  #49                 // Method org/apache/commons/math3/util/FastMath.pow:(DD)D
      86: dastore
      87: dconst_1
      88: iload_3
      89: i2d
      90: aload         6
      92: iconst_0
      93: daload
      94: iload_3
      95: iconst_1
      96: isub
      97: invokestatic  #52                 // Method org/apache/commons/math3/util/FastMath.pow:(DI)D
     100: dmul
     101: ddiv
     102: dstore        7
     104: dconst_1
     105: iload_3
     106: i2d
     107: ddiv
     108: dstore        9
     110: dconst_1
     111: aload_1
     112: iload_2
     113: daload
     114: ddiv
     115: dstore        11
     117: iconst_1
     118: istore        13
     120: iload         13
     122: aload_0
     123: getfield      #3                  // Field order:I
     126: if_icmpgt     156
     129: aload         6
     131: iload         13
     133: dload         7
     135: dastore
     136: dload         7
     138: dload         11
     140: dload         9
     142: iload         13
     144: i2d
     145: dsub
     146: dmul
     147: dmul
     148: dstore        7
     150: iinc          13, 1
     153: goto          120
     156: aload_0
     157: aload_1
     158: iload_2
     159: aload         6
     161: aload         4
     163: iload         5
     165: invokevirtual #50                 // Method compose:([DI[D[DI)V
     168: return

  public void exp(double[], int, double[], int);
    Code:
       0: iconst_1
       1: aload_0
       2: getfield      #3                  // Field order:I
       5: iadd
       6: newarray       double
       8: astore        5
      10: aload         5
      12: aload_1
      13: iload_2
      14: daload
      15: invokestatic  #61                 // Method org/apache/commons/math3/util/FastMath.exp:(D)D
      18: invokestatic  #62                 // Method java/util/Arrays.fill:([DD)V
      21: aload_0
      22: aload_1
      23: iload_2
      24: aload         5
      26: aload_3
      27: iload         4
      29: invokevirtual #50                 // Method compose:([DI[D[DI)V
      32: return

  public void expm1(double[], int, double[], int);
    Code:
       0: iconst_1
       1: aload_0
       2: getfield      #3                  // Field order:I
       5: iadd
       6: newarray       double
       8: astore        5
      10: aload         5
      12: iconst_0
      13: aload_1
      14: iload_2
      15: daload
      16: invokestatic  #63                 // Method org/apache/commons/math3/util/FastMath.expm1:(D)D
      19: dastore
      20: aload         5
      22: iconst_1
      23: iconst_1
      24: aload_0
      25: getfield      #3                  // Field order:I
      28: iadd
      29: aload_1
      30: iload_2
      31: daload
      32: invokestatic  #61                 // Method org/apache/commons/math3/util/FastMath.exp:(D)D
      35: invokestatic  #51                 // Method java/util/Arrays.fill:([DIID)V
      38: aload_0
      39: aload_1
      40: iload_2
      41: aload         5
      43: aload_3
      44: iload         4
      46: invokevirtual #50                 // Method compose:([DI[D[DI)V
      49: return

  public void log(double[], int, double[], int);
    Code:
       0: iconst_1
       1: aload_0
       2: getfield      #3                  // Field order:I
       5: iadd
       6: newarray       double
       8: astore        5
      10: aload         5
      12: iconst_0
      13: aload_1
      14: iload_2
      15: daload
      16: invokestatic  #64                 // Method org/apache/commons/math3/util/FastMath.log:(D)D
      19: dastore
      20: aload_0
      21: getfield      #3                  // Field order:I
      24: ifle          75
      27: dconst_1
      28: aload_1
      29: iload_2
      30: daload
      31: ddiv
      32: dstore        6
      34: dload         6
      36: dstore        8
      38: iconst_1
      39: istore        10
      41: iload         10
      43: aload_0
      44: getfield      #3                  // Field order:I
      47: if_icmpgt     75
      50: aload         5
      52: iload         10
      54: dload         8
      56: dastore
      57: dload         8
      59: iload         10
      61: ineg
      62: i2d
      63: dload         6
      65: dmul
      66: dmul
      67: dstore        8
      69: iinc          10, 1
      72: goto          41
      75: aload_0
      76: aload_1
      77: iload_2
      78: aload         5
      80: aload_3
      81: iload         4
      83: invokevirtual #50                 // Method compose:([DI[D[DI)V
      86: return

  public void log1p(double[], int, double[], int);
    Code:
       0: iconst_1
       1: aload_0
       2: getfield      #3                  // Field order:I
       5: iadd
       6: newarray       double
       8: astore        5
      10: aload         5
      12: iconst_0
      13: aload_1
      14: iload_2
      15: daload
      16: invokestatic  #65                 // Method org/apache/commons/math3/util/FastMath.log1p:(D)D
      19: dastore
      20: aload_0
      21: getfield      #3                  // Field order:I
      24: ifle          77
      27: dconst_1
      28: dconst_1
      29: aload_1
      30: iload_2
      31: daload
      32: dadd
      33: ddiv
      34: dstore        6
      36: dload         6
      38: dstore        8
      40: iconst_1
      41: istore        10
      43: iload         10
      45: aload_0
      46: getfield      #3                  // Field order:I
      49: if_icmpgt     77
      52: aload         5
      54: iload         10
      56: dload         8
      58: dastore
      59: dload         8
      61: iload         10
      63: ineg
      64: i2d
      65: dload         6
      67: dmul
      68: dmul
      69: dstore        8
      71: iinc          10, 1
      74: goto          43
      77: aload_0
      78: aload_1
      79: iload_2
      80: aload         5
      82: aload_3
      83: iload         4
      85: invokevirtual #50                 // Method compose:([DI[D[DI)V
      88: return

  public void log10(double[], int, double[], int);
    Code:
       0: iconst_1
       1: aload_0
       2: getfield      #3                  // Field order:I
       5: iadd
       6: newarray       double
       8: astore        5
      10: aload         5
      12: iconst_0
      13: aload_1
      14: iload_2
      15: daload
      16: invokestatic  #66                 // Method org/apache/commons/math3/util/FastMath.log10:(D)D
      19: dastore
      20: aload_0
      21: getfield      #3                  // Field order:I
      24: ifle          82
      27: dconst_1
      28: aload_1
      29: iload_2
      30: daload
      31: ddiv
      32: dstore        6
      34: dload         6
      36: ldc2_w        #67                 // double 10.0d
      39: invokestatic  #64                 // Method org/apache/commons/math3/util/FastMath.log:(D)D
      42: ddiv
      43: dstore        8
      45: iconst_1
      46: istore        10
      48: iload         10
      50: aload_0
      51: getfield      #3                  // Field order:I
      54: if_icmpgt     82
      57: aload         5
      59: iload         10
      61: dload         8
      63: dastore
      64: dload         8
      66: iload         10
      68: ineg
      69: i2d
      70: dload         6
      72: dmul
      73: dmul
      74: dstore        8
      76: iinc          10, 1
      79: goto          48
      82: aload_0
      83: aload_1
      84: iload_2
      85: aload         5
      87: aload_3
      88: iload         4
      90: invokevirtual #50                 // Method compose:([DI[D[DI)V
      93: return

  public void cos(double[], int, double[], int);
    Code:
       0: iconst_1
       1: aload_0
       2: getfield      #3                  // Field order:I
       5: iadd
       6: newarray       double
       8: astore        5
      10: aload         5
      12: iconst_0
      13: aload_1
      14: iload_2
      15: daload
      16: invokestatic  #69                 // Method org/apache/commons/math3/util/FastMath.cos:(D)D
      19: dastore
      20: aload_0
      21: getfield      #3                  // Field order:I
      24: ifle          69
      27: aload         5
      29: iconst_1
      30: aload_1
      31: iload_2
      32: daload
      33: invokestatic  #70                 // Method org/apache/commons/math3/util/FastMath.sin:(D)D
      36: dneg
      37: dastore
      38: iconst_2
      39: istore        6
      41: iload         6
      43: aload_0
      44: getfield      #3                  // Field order:I
      47: if_icmpgt     69
      50: aload         5
      52: iload         6
      54: aload         5
      56: iload         6
      58: iconst_2
      59: isub
      60: daload
      61: dneg
      62: dastore
      63: iinc          6, 1
      66: goto          41
      69: aload_0
      70: aload_1
      71: iload_2
      72: aload         5
      74: aload_3
      75: iload         4
      77: invokevirtual #50                 // Method compose:([DI[D[DI)V
      80: return

  public void sin(double[], int, double[], int);
    Code:
       0: iconst_1
       1: aload_0
       2: getfield      #3                  // Field order:I
       5: iadd
       6: newarray       double
       8: astore        5
      10: aload         5
      12: iconst_0
      13: aload_1
      14: iload_2
      15: daload
      16: invokestatic  #70                 // Method org/apache/commons/math3/util/FastMath.sin:(D)D
      19: dastore
      20: aload_0
      21: getfield      #3                  // Field order:I
      24: ifle          68
      27: aload         5
      29: iconst_1
      30: aload_1
      31: iload_2
      32: daload
      33: invokestatic  #69                 // Method org/apache/commons/math3/util/FastMath.cos:(D)D
      36: dastore
      37: iconst_2
      38: istore        6
      40: iload         6
      42: aload_0
      43: getfield      #3                  // Field order:I
      46: if_icmpgt     68
      49: aload         5
      51: iload         6
      53: aload         5
      55: iload         6
      57: iconst_2
      58: isub
      59: daload
      60: dneg
      61: dastore
      62: iinc          6, 1
      65: goto          40
      68: aload_0
      69: aload_1
      70: iload_2
      71: aload         5
      73: aload_3
      74: iload         4
      76: invokevirtual #50                 // Method compose:([DI[D[DI)V
      79: return

  public void tan(double[], int, double[], int);
    Code:
       0: iconst_1
       1: aload_0
       2: getfield      #3                  // Field order:I
       5: iadd
       6: newarray       double
       8: astore        5
      10: aload_1
      11: iload_2
      12: daload
      13: invokestatic  #71                 // Method org/apache/commons/math3/util/FastMath.tan:(D)D
      16: dstore        6
      18: aload         5
      20: iconst_0
      21: dload         6
      23: dastore
      24: aload_0
      25: getfield      #3                  // Field order:I
      28: ifle          198
      31: aload_0
      32: getfield      #3                  // Field order:I
      35: iconst_2
      36: iadd
      37: newarray       double
      39: astore        8
      41: aload         8
      43: iconst_1
      44: dconst_1
      45: dastore
      46: dload         6
      48: dload         6
      50: dmul
      51: dstore        9
      53: iconst_1
      54: istore        11
      56: iload         11
      58: aload_0
      59: getfield      #3                  // Field order:I
      62: if_icmpgt     198
      65: dconst_0
      66: dstore        12
      68: aload         8
      70: iload         11
      72: iconst_1
      73: iadd
      74: iload         11
      76: i2d
      77: aload         8
      79: iload         11
      81: daload
      82: dmul
      83: dastore
      84: iload         11
      86: iconst_1
      87: iadd
      88: istore        14
      90: iload         14
      92: iflt          171
      95: dload         12
      97: dload         9
      99: dmul
     100: aload         8
     102: iload         14
     104: daload
     105: dadd
     106: dstore        12
     108: iload         14
     110: iconst_2
     111: if_icmple     151
     114: aload         8
     116: iload         14
     118: iconst_2
     119: isub
     120: iload         14
     122: iconst_1
     123: isub
     124: i2d
     125: aload         8
     127: iload         14
     129: iconst_1
     130: isub
     131: daload
     132: dmul
     133: iload         14
     135: iconst_3
     136: isub
     137: i2d
     138: aload         8
     140: iload         14
     142: iconst_3
     143: isub
     144: daload
     145: dmul
     146: dadd
     147: dastore
     148: goto          165
     151: iload         14
     153: iconst_2
     154: if_icmpne     165
     157: aload         8
     159: iconst_0
     160: aload         8
     162: iconst_1
     163: daload
     164: dastore
     165: iinc          14, -2
     168: goto          90
     171: iload         11
     173: iconst_1
     174: iand
     175: ifne          185
     178: dload         12
     180: dload         6
     182: dmul
     183: dstore        12
     185: aload         5
     187: iload         11
     189: dload         12
     191: dastore
     192: iinc          11, 1
     195: goto          56
     198: aload_0
     199: aload_1
     200: iload_2
     201: aload         5
     203: aload_3
     204: iload         4
     206: invokevirtual #50                 // Method compose:([DI[D[DI)V
     209: return

  public void acos(double[], int, double[], int);
    Code:
       0: iconst_1
       1: aload_0
       2: getfield      #3                  // Field order:I
       5: iadd
       6: newarray       double
       8: astore        5
      10: aload_1
      11: iload_2
      12: daload
      13: dstore        6
      15: aload         5
      17: iconst_0
      18: dload         6
      20: invokestatic  #72                 // Method org/apache/commons/math3/util/FastMath.acos:(D)D
      23: dastore
      24: aload_0
      25: getfield      #3                  // Field order:I
      28: ifle          241
      31: aload_0
      32: getfield      #3                  // Field order:I
      35: newarray       double
      37: astore        8
      39: aload         8
      41: iconst_0
      42: ldc2_w        #73                 // double -1.0d
      45: dastore
      46: dload         6
      48: dload         6
      50: dmul
      51: dstore        9
      53: dconst_1
      54: dconst_1
      55: dload         9
      57: dsub
      58: ddiv
      59: dstore        11
      61: dload         11
      63: invokestatic  #55                 // Method org/apache/commons/math3/util/FastMath.sqrt:(D)D
      66: dstore        13
      68: aload         5
      70: iconst_1
      71: dload         13
      73: aload         8
      75: iconst_0
      76: daload
      77: dmul
      78: dastore
      79: iconst_2
      80: istore        15
      82: iload         15
      84: aload_0
      85: getfield      #3                  // Field order:I
      88: if_icmpgt     241
      91: dconst_0
      92: dstore        16
      94: aload         8
      96: iload         15
      98: iconst_1
      99: isub
     100: iload         15
     102: iconst_1
     103: isub
     104: i2d
     105: aload         8
     107: iload         15
     109: iconst_2
     110: isub
     111: daload
     112: dmul
     113: dastore
     114: iload         15
     116: iconst_1
     117: isub
     118: istore        18
     120: iload         18
     122: iflt          204
     125: dload         16
     127: dload         9
     129: dmul
     130: aload         8
     132: iload         18
     134: daload
     135: dadd
     136: dstore        16
     138: iload         18
     140: iconst_2
     141: if_icmple     184
     144: aload         8
     146: iload         18
     148: iconst_2
     149: isub
     150: iload         18
     152: iconst_1
     153: isub
     154: i2d
     155: aload         8
     157: iload         18
     159: iconst_1
     160: isub
     161: daload
     162: dmul
     163: iconst_2
     164: iload         15
     166: imul
     167: iload         18
     169: isub
     170: i2d
     171: aload         8
     173: iload         18
     175: iconst_3
     176: isub
     177: daload
     178: dmul
     179: dadd
     180: dastore
     181: goto          198
     184: iload         18
     186: iconst_2
     187: if_icmpne     198
     190: aload         8
     192: iconst_0
     193: aload         8
     195: iconst_1
     196: daload
     197: dastore
     198: iinc          18, -2
     201: goto          120
     204: iload         15
     206: iconst_1
     207: iand
     208: ifne          218
     211: dload         16
     213: dload         6
     215: dmul
     216: dstore        16
     218: dload         13
     220: dload         11
     222: dmul
     223: dstore        13
     225: aload         5
     227: iload         15
     229: dload         13
     231: dload         16
     233: dmul
     234: dastore
     235: iinc          15, 1
     238: goto          82
     241: aload_0
     242: aload_1
     243: iload_2
     244: aload         5
     246: aload_3
     247: iload         4
     249: invokevirtual #50                 // Method compose:([DI[D[DI)V
     252: return

  public void asin(double[], int, double[], int);
    Code:
       0: iconst_1
       1: aload_0
       2: getfield      #3                  // Field order:I
       5: iadd
       6: newarray       double
       8: astore        5
      10: aload_1
      11: iload_2
      12: daload
      13: dstore        6
      15: aload         5
      17: iconst_0
      18: dload         6
      20: invokestatic  #75                 // Method org/apache/commons/math3/util/FastMath.asin:(D)D
      23: dastore
      24: aload_0
      25: getfield      #3                  // Field order:I
      28: ifle          239
      31: aload_0
      32: getfield      #3                  // Field order:I
      35: newarray       double
      37: astore        8
      39: aload         8
      41: iconst_0
      42: dconst_1
      43: dastore
      44: dload         6
      46: dload         6
      48: dmul
      49: dstore        9
      51: dconst_1
      52: dconst_1
      53: dload         9
      55: dsub
      56: ddiv
      57: dstore        11
      59: dload         11
      61: invokestatic  #55                 // Method org/apache/commons/math3/util/FastMath.sqrt:(D)D
      64: dstore        13
      66: aload         5
      68: iconst_1
      69: dload         13
      71: aload         8
      73: iconst_0
      74: daload
      75: dmul
      76: dastore
      77: iconst_2
      78: istore        15
      80: iload         15
      82: aload_0
      83: getfield      #3                  // Field order:I
      86: if_icmpgt     239
      89: dconst_0
      90: dstore        16
      92: aload         8
      94: iload         15
      96: iconst_1
      97: isub
      98: iload         15
     100: iconst_1
     101: isub
     102: i2d
     103: aload         8
     105: iload         15
     107: iconst_2
     108: isub
     109: daload
     110: dmul
     111: dastore
     112: iload         15
     114: iconst_1
     115: isub
     116: istore        18
     118: iload         18
     120: iflt          202
     123: dload         16
     125: dload         9
     127: dmul
     128: aload         8
     130: iload         18
     132: daload
     133: dadd
     134: dstore        16
     136: iload         18
     138: iconst_2
     139: if_icmple     182
     142: aload         8
     144: iload         18
     146: iconst_2
     147: isub
     148: iload         18
     150: iconst_1
     151: isub
     152: i2d
     153: aload         8
     155: iload         18
     157: iconst_1
     158: isub
     159: daload
     160: dmul
     161: iconst_2
     162: iload         15
     164: imul
     165: iload         18
     167: isub
     168: i2d
     169: aload         8
     171: iload         18
     173: iconst_3
     174: isub
     175: daload
     176: dmul
     177: dadd
     178: dastore
     179: goto          196
     182: iload         18
     184: iconst_2
     185: if_icmpne     196
     188: aload         8
     190: iconst_0
     191: aload         8
     193: iconst_1
     194: daload
     195: dastore
     196: iinc          18, -2
     199: goto          118
     202: iload         15
     204: iconst_1
     205: iand
     206: ifne          216
     209: dload         16
     211: dload         6
     213: dmul
     214: dstore        16
     216: dload         13
     218: dload         11
     220: dmul
     221: dstore        13
     223: aload         5
     225: iload         15
     227: dload         13
     229: dload         16
     231: dmul
     232: dastore
     233: iinc          15, 1
     236: goto          80
     239: aload_0
     240: aload_1
     241: iload_2
     242: aload         5
     244: aload_3
     245: iload         4
     247: invokevirtual #50                 // Method compose:([DI[D[DI)V
     250: return

  public void atan(double[], int, double[], int);
    Code:
       0: iconst_1
       1: aload_0
       2: getfield      #3                  // Field order:I
       5: iadd
       6: newarray       double
       8: astore        5
      10: aload_1
      11: iload_2
      12: daload
      13: dstore        6
      15: aload         5
      17: iconst_0
      18: dload         6
      20: invokestatic  #76                 // Method org/apache/commons/math3/util/FastMath.atan:(D)D
      23: dastore
      24: aload_0
      25: getfield      #3                  // Field order:I
      28: ifle          237
      31: aload_0
      32: getfield      #3                  // Field order:I
      35: newarray       double
      37: astore        8
      39: aload         8
      41: iconst_0
      42: dconst_1
      43: dastore
      44: dload         6
      46: dload         6
      48: dmul
      49: dstore        9
      51: dconst_1
      52: dconst_1
      53: dload         9
      55: dadd
      56: ddiv
      57: dstore        11
      59: dload         11
      61: dstore        13
      63: aload         5
      65: iconst_1
      66: dload         13
      68: aload         8
      70: iconst_0
      71: daload
      72: dmul
      73: dastore
      74: iconst_2
      75: istore        15
      77: iload         15
      79: aload_0
      80: getfield      #3                  // Field order:I
      83: if_icmpgt     237
      86: dconst_0
      87: dstore        16
      89: aload         8
      91: iload         15
      93: iconst_1
      94: isub
      95: iload         15
      97: ineg
      98: i2d
      99: aload         8
     101: iload         15
     103: iconst_2
     104: isub
     105: daload
     106: dmul
     107: dastore
     108: iload         15
     110: iconst_1
     111: isub
     112: istore        18
     114: iload         18
     116: iflt          200
     119: dload         16
     121: dload         9
     123: dmul
     124: aload         8
     126: iload         18
     128: daload
     129: dadd
     130: dstore        16
     132: iload         18
     134: iconst_2
     135: if_icmple     180
     138: aload         8
     140: iload         18
     142: iconst_2
     143: isub
     144: iload         18
     146: iconst_1
     147: isub
     148: i2d
     149: aload         8
     151: iload         18
     153: iconst_1
     154: isub
     155: daload
     156: dmul
     157: iload         18
     159: iconst_1
     160: isub
     161: iconst_2
     162: iload         15
     164: imul
     165: isub
     166: i2d
     167: aload         8
     169: iload         18
     171: iconst_3
     172: isub
     173: daload
     174: dmul
     175: dadd
     176: dastore
     177: goto          194
     180: iload         18
     182: iconst_2
     183: if_icmpne     194
     186: aload         8
     188: iconst_0
     189: aload         8
     191: iconst_1
     192: daload
     193: dastore
     194: iinc          18, -2
     197: goto          114
     200: iload         15
     202: iconst_1
     203: iand
     204: ifne          214
     207: dload         16
     209: dload         6
     211: dmul
     212: dstore        16
     214: dload         13
     216: dload         11
     218: dmul
     219: dstore        13
     221: aload         5
     223: iload         15
     225: dload         13
     227: dload         16
     229: dmul
     230: dastore
     231: iinc          15, 1
     234: goto          77
     237: aload_0
     238: aload_1
     239: iload_2
     240: aload         5
     242: aload_3
     243: iload         4
     245: invokevirtual #50                 // Method compose:([DI[D[DI)V
     248: return

  public void atan2(double[], int, double[], int, double[], int);
    Code:
       0: aload_0
       1: invokevirtual #25                 // Method getSize:()I
       4: newarray       double
       6: astore        7
       8: aload_0
       9: aload_3
      10: iload         4
      12: aload_3
      13: iload         4
      15: aload         7
      17: iconst_0
      18: invokevirtual #47                 // Method multiply:([DI[DI[DI)V
      21: aload_0
      22: invokevirtual #25                 // Method getSize:()I
      25: newarray       double
      27: astore        8
      29: aload_0
      30: aload_1
      31: iload_2
      32: aload_1
      33: iload_2
      34: aload         8
      36: iconst_0
      37: invokevirtual #47                 // Method multiply:([DI[DI[DI)V
      40: aload_0
      41: aload         7
      43: iconst_0
      44: aload         8
      46: iconst_0
      47: aload         8
      49: iconst_0
      50: invokevirtual #77                 // Method add:([DI[DI[DI)V
      53: aload_0
      54: aload         8
      56: iconst_0
      57: iconst_2
      58: aload         7
      60: iconst_0
      61: invokevirtual #78                 // Method rootN:([DII[DI)V
      64: aload_3
      65: iload         4
      67: daload
      68: dconst_0
      69: dcmpl
      70: iflt          145
      73: aload_0
      74: aload         7
      76: iconst_0
      77: aload_3
      78: iload         4
      80: aload         8
      82: iconst_0
      83: invokevirtual #77                 // Method add:([DI[DI[DI)V
      86: aload_0
      87: aload_1
      88: iload_2
      89: aload         8
      91: iconst_0
      92: aload         7
      94: iconst_0
      95: invokevirtual #79                 // Method divide:([DI[DI[DI)V
      98: aload_0
      99: aload         7
     101: iconst_0
     102: aload         8
     104: iconst_0
     105: invokevirtual #80                 // Method atan:([DI[DI)V
     108: iconst_0
     109: istore        9
     111: iload         9
     113: aload         8
     115: arraylength
     116: if_icmpge     142
     119: aload         5
     121: iload         6
     123: iload         9
     125: iadd
     126: ldc2_w        #81                 // double 2.0d
     129: aload         8
     131: iload         9
     133: daload
     134: dmul
     135: dastore
     136: iinc          9, 1
     139: goto          111
     142: goto          246
     145: aload_0
     146: aload         7
     148: iconst_0
     149: aload_3
     150: iload         4
     152: aload         8
     154: iconst_0
     155: invokevirtual #83                 // Method subtract:([DI[DI[DI)V
     158: aload_0
     159: aload_1
     160: iload_2
     161: aload         8
     163: iconst_0
     164: aload         7
     166: iconst_0
     167: invokevirtual #79                 // Method divide:([DI[DI[DI)V
     170: aload_0
     171: aload         7
     173: iconst_0
     174: aload         8
     176: iconst_0
     177: invokevirtual #80                 // Method atan:([DI[DI)V
     180: aload         5
     182: iload         6
     184: aload         8
     186: iconst_0
     187: daload
     188: dconst_0
     189: dcmpg
     190: ifgt          199
     193: ldc2_w        #84                 // double -3.141592653589793d
     196: goto          202
     199: ldc2_w        #86                 // double 3.141592653589793d
     202: ldc2_w        #81                 // double 2.0d
     205: aload         8
     207: iconst_0
     208: daload
     209: dmul
     210: dsub
     211: dastore
     212: iconst_1
     213: istore        9
     215: iload         9
     217: aload         8
     219: arraylength
     220: if_icmpge     246
     223: aload         5
     225: iload         6
     227: iload         9
     229: iadd
     230: ldc2_w        #88                 // double -2.0d
     233: aload         8
     235: iload         9
     237: daload
     238: dmul
     239: dastore
     240: iinc          9, 1
     243: goto          215
     246: return

  public void cosh(double[], int, double[], int);
    Code:
       0: iconst_1
       1: aload_0
       2: getfield      #3                  // Field order:I
       5: iadd
       6: newarray       double
       8: astore        5
      10: aload         5
      12: iconst_0
      13: aload_1
      14: iload_2
      15: daload
      16: invokestatic  #90                 // Method org/apache/commons/math3/util/FastMath.cosh:(D)D
      19: dastore
      20: aload_0
      21: getfield      #3                  // Field order:I
      24: ifle          67
      27: aload         5
      29: iconst_1
      30: aload_1
      31: iload_2
      32: daload
      33: invokestatic  #91                 // Method org/apache/commons/math3/util/FastMath.sinh:(D)D
      36: dastore
      37: iconst_2
      38: istore        6
      40: iload         6
      42: aload_0
      43: getfield      #3                  // Field order:I
      46: if_icmpgt     67
      49: aload         5
      51: iload         6
      53: aload         5
      55: iload         6
      57: iconst_2
      58: isub
      59: daload
      60: dastore
      61: iinc          6, 1
      64: goto          40
      67: aload_0
      68: aload_1
      69: iload_2
      70: aload         5
      72: aload_3
      73: iload         4
      75: invokevirtual #50                 // Method compose:([DI[D[DI)V
      78: return

  public void sinh(double[], int, double[], int);
    Code:
       0: iconst_1
       1: aload_0
       2: getfield      #3                  // Field order:I
       5: iadd
       6: newarray       double
       8: astore        5
      10: aload         5
      12: iconst_0
      13: aload_1
      14: iload_2
      15: daload
      16: invokestatic  #91                 // Method org/apache/commons/math3/util/FastMath.sinh:(D)D
      19: dastore
      20: aload_0
      21: getfield      #3                  // Field order:I
      24: ifle          67
      27: aload         5
      29: iconst_1
      30: aload_1
      31: iload_2
      32: daload
      33: invokestatic  #90                 // Method org/apache/commons/math3/util/FastMath.cosh:(D)D
      36: dastore
      37: iconst_2
      38: istore        6
      40: iload         6
      42: aload_0
      43: getfield      #3                  // Field order:I
      46: if_icmpgt     67
      49: aload         5
      51: iload         6
      53: aload         5
      55: iload         6
      57: iconst_2
      58: isub
      59: daload
      60: dastore
      61: iinc          6, 1
      64: goto          40
      67: aload_0
      68: aload_1
      69: iload_2
      70: aload         5
      72: aload_3
      73: iload         4
      75: invokevirtual #50                 // Method compose:([DI[D[DI)V
      78: return

  public void tanh(double[], int, double[], int);
    Code:
       0: iconst_1
       1: aload_0
       2: getfield      #3                  // Field order:I
       5: iadd
       6: newarray       double
       8: astore        5
      10: aload_1
      11: iload_2
      12: daload
      13: invokestatic  #92                 // Method org/apache/commons/math3/util/FastMath.tanh:(D)D
      16: dstore        6
      18: aload         5
      20: iconst_0
      21: dload         6
      23: dastore
      24: aload_0
      25: getfield      #3                  // Field order:I
      28: ifle          199
      31: aload_0
      32: getfield      #3                  // Field order:I
      35: iconst_2
      36: iadd
      37: newarray       double
      39: astore        8
      41: aload         8
      43: iconst_1
      44: dconst_1
      45: dastore
      46: dload         6
      48: dload         6
      50: dmul
      51: dstore        9
      53: iconst_1
      54: istore        11
      56: iload         11
      58: aload_0
      59: getfield      #3                  // Field order:I
      62: if_icmpgt     199
      65: dconst_0
      66: dstore        12
      68: aload         8
      70: iload         11
      72: iconst_1
      73: iadd
      74: iload         11
      76: ineg
      77: i2d
      78: aload         8
      80: iload         11
      82: daload
      83: dmul
      84: dastore
      85: iload         11
      87: iconst_1
      88: iadd
      89: istore        14
      91: iload         14
      93: iflt          172
      96: dload         12
      98: dload         9
     100: dmul
     101: aload         8
     103: iload         14
     105: daload
     106: dadd
     107: dstore        12
     109: iload         14
     111: iconst_2
     112: if_icmple     152
     115: aload         8
     117: iload         14
     119: iconst_2
     120: isub
     121: iload         14
     123: iconst_1
     124: isub
     125: i2d
     126: aload         8
     128: iload         14
     130: iconst_1
     131: isub
     132: daload
     133: dmul
     134: iload         14
     136: iconst_3
     137: isub
     138: i2d
     139: aload         8
     141: iload         14
     143: iconst_3
     144: isub
     145: daload
     146: dmul
     147: dsub
     148: dastore
     149: goto          166
     152: iload         14
     154: iconst_2
     155: if_icmpne     166
     158: aload         8
     160: iconst_0
     161: aload         8
     163: iconst_1
     164: daload
     165: dastore
     166: iinc          14, -2
     169: goto          91
     172: iload         11
     174: iconst_1
     175: iand
     176: ifne          186
     179: dload         12
     181: dload         6
     183: dmul
     184: dstore        12
     186: aload         5
     188: iload         11
     190: dload         12
     192: dastore
     193: iinc          11, 1
     196: goto          56
     199: aload_0
     200: aload_1
     201: iload_2
     202: aload         5
     204: aload_3
     205: iload         4
     207: invokevirtual #50                 // Method compose:([DI[D[DI)V
     210: return

  public void acosh(double[], int, double[], int);
    Code:
       0: iconst_1
       1: aload_0
       2: getfield      #3                  // Field order:I
       5: iadd
       6: newarray       double
       8: astore        5
      10: aload_1
      11: iload_2
      12: daload
      13: dstore        6
      15: aload         5
      17: iconst_0
      18: dload         6
      20: invokestatic  #93                 // Method org/apache/commons/math3/util/FastMath.acosh:(D)D
      23: dastore
      24: aload_0
      25: getfield      #3                  // Field order:I
      28: ifle          240
      31: aload_0
      32: getfield      #3                  // Field order:I
      35: newarray       double
      37: astore        8
      39: aload         8
      41: iconst_0
      42: dconst_1
      43: dastore
      44: dload         6
      46: dload         6
      48: dmul
      49: dstore        9
      51: dconst_1
      52: dload         9
      54: dconst_1
      55: dsub
      56: ddiv
      57: dstore        11
      59: dload         11
      61: invokestatic  #55                 // Method org/apache/commons/math3/util/FastMath.sqrt:(D)D
      64: dstore        13
      66: aload         5
      68: iconst_1
      69: dload         13
      71: aload         8
      73: iconst_0
      74: daload
      75: dmul
      76: dastore
      77: iconst_2
      78: istore        15
      80: iload         15
      82: aload_0
      83: getfield      #3                  // Field order:I
      86: if_icmpgt     240
      89: dconst_0
      90: dstore        16
      92: aload         8
      94: iload         15
      96: iconst_1
      97: isub
      98: iconst_1
      99: iload         15
     101: isub
     102: i2d
     103: aload         8
     105: iload         15
     107: iconst_2
     108: isub
     109: daload
     110: dmul
     111: dastore
     112: iload         15
     114: iconst_1
     115: isub
     116: istore        18
     118: iload         18
     120: iflt          203
     123: dload         16
     125: dload         9
     127: dmul
     128: aload         8
     130: iload         18
     132: daload
     133: dadd
     134: dstore        16
     136: iload         18
     138: iconst_2
     139: if_icmple     182
     142: aload         8
     144: iload         18
     146: iconst_2
     147: isub
     148: iconst_1
     149: iload         18
     151: isub
     152: i2d
     153: aload         8
     155: iload         18
     157: iconst_1
     158: isub
     159: daload
     160: dmul
     161: iload         18
     163: iconst_2
     164: iload         15
     166: imul
     167: isub
     168: i2d
     169: aload         8
     171: iload         18
     173: iconst_3
     174: isub
     175: daload
     176: dmul
     177: dadd
     178: dastore
     179: goto          197
     182: iload         18
     184: iconst_2
     185: if_icmpne     197
     188: aload         8
     190: iconst_0
     191: aload         8
     193: iconst_1
     194: daload
     195: dneg
     196: dastore
     197: iinc          18, -2
     200: goto          118
     203: iload         15
     205: iconst_1
     206: iand
     207: ifne          217
     210: dload         16
     212: dload         6
     214: dmul
     215: dstore        16
     217: dload         13
     219: dload         11
     221: dmul
     222: dstore        13
     224: aload         5
     226: iload         15
     228: dload         13
     230: dload         16
     232: dmul
     233: dastore
     234: iinc          15, 1
     237: goto          80
     240: aload_0
     241: aload_1
     242: iload_2
     243: aload         5
     245: aload_3
     246: iload         4
     248: invokevirtual #50                 // Method compose:([DI[D[DI)V
     251: return

  public void asinh(double[], int, double[], int);
    Code:
       0: iconst_1
       1: aload_0
       2: getfield      #3                  // Field order:I
       5: iadd
       6: newarray       double
       8: astore        5
      10: aload_1
      11: iload_2
      12: daload
      13: dstore        6
      15: aload         5
      17: iconst_0
      18: dload         6
      20: invokestatic  #94                 // Method org/apache/commons/math3/util/FastMath.asinh:(D)D
      23: dastore
      24: aload_0
      25: getfield      #3                  // Field order:I
      28: ifle          239
      31: aload_0
      32: getfield      #3                  // Field order:I
      35: newarray       double
      37: astore        8
      39: aload         8
      41: iconst_0
      42: dconst_1
      43: dastore
      44: dload         6
      46: dload         6
      48: dmul
      49: dstore        9
      51: dconst_1
      52: dconst_1
      53: dload         9
      55: dadd
      56: ddiv
      57: dstore        11
      59: dload         11
      61: invokestatic  #55                 // Method org/apache/commons/math3/util/FastMath.sqrt:(D)D
      64: dstore        13
      66: aload         5
      68: iconst_1
      69: dload         13
      71: aload         8
      73: iconst_0
      74: daload
      75: dmul
      76: dastore
      77: iconst_2
      78: istore        15
      80: iload         15
      82: aload_0
      83: getfield      #3                  // Field order:I
      86: if_icmpgt     239
      89: dconst_0
      90: dstore        16
      92: aload         8
      94: iload         15
      96: iconst_1
      97: isub
      98: iconst_1
      99: iload         15
     101: isub
     102: i2d
     103: aload         8
     105: iload         15
     107: iconst_2
     108: isub
     109: daload
     110: dmul
     111: dastore
     112: iload         15
     114: iconst_1
     115: isub
     116: istore        18
     118: iload         18
     120: iflt          202
     123: dload         16
     125: dload         9
     127: dmul
     128: aload         8
     130: iload         18
     132: daload
     133: dadd
     134: dstore        16
     136: iload         18
     138: iconst_2
     139: if_icmple     182
     142: aload         8
     144: iload         18
     146: iconst_2
     147: isub
     148: iload         18
     150: iconst_1
     151: isub
     152: i2d
     153: aload         8
     155: iload         18
     157: iconst_1
     158: isub
     159: daload
     160: dmul
     161: iload         18
     163: iconst_2
     164: iload         15
     166: imul
     167: isub
     168: i2d
     169: aload         8
     171: iload         18
     173: iconst_3
     174: isub
     175: daload
     176: dmul
     177: dadd
     178: dastore
     179: goto          196
     182: iload         18
     184: iconst_2
     185: if_icmpne     196
     188: aload         8
     190: iconst_0
     191: aload         8
     193: iconst_1
     194: daload
     195: dastore
     196: iinc          18, -2
     199: goto          118
     202: iload         15
     204: iconst_1
     205: iand
     206: ifne          216
     209: dload         16
     211: dload         6
     213: dmul
     214: dstore        16
     216: dload         13
     218: dload         11
     220: dmul
     221: dstore        13
     223: aload         5
     225: iload         15
     227: dload         13
     229: dload         16
     231: dmul
     232: dastore
     233: iinc          15, 1
     236: goto          80
     239: aload_0
     240: aload_1
     241: iload_2
     242: aload         5
     244: aload_3
     245: iload         4
     247: invokevirtual #50                 // Method compose:([DI[D[DI)V
     250: return

  public void atanh(double[], int, double[], int);
    Code:
       0: iconst_1
       1: aload_0
       2: getfield      #3                  // Field order:I
       5: iadd
       6: newarray       double
       8: astore        5
      10: aload_1
      11: iload_2
      12: daload
      13: dstore        6
      15: aload         5
      17: iconst_0
      18: dload         6
      20: invokestatic  #95                 // Method org/apache/commons/math3/util/FastMath.atanh:(D)D
      23: dastore
      24: aload_0
      25: getfield      #3                  // Field order:I
      28: ifle          236
      31: aload_0
      32: getfield      #3                  // Field order:I
      35: newarray       double
      37: astore        8
      39: aload         8
      41: iconst_0
      42: dconst_1
      43: dastore
      44: dload         6
      46: dload         6
      48: dmul
      49: dstore        9
      51: dconst_1
      52: dconst_1
      53: dload         9
      55: dsub
      56: ddiv
      57: dstore        11
      59: dload         11
      61: dstore        13
      63: aload         5
      65: iconst_1
      66: dload         13
      68: aload         8
      70: iconst_0
      71: daload
      72: dmul
      73: dastore
      74: iconst_2
      75: istore        15
      77: iload         15
      79: aload_0
      80: getfield      #3                  // Field order:I
      83: if_icmpgt     236
      86: dconst_0
      87: dstore        16
      89: aload         8
      91: iload         15
      93: iconst_1
      94: isub
      95: iload         15
      97: i2d
      98: aload         8
     100: iload         15
     102: iconst_2
     103: isub
     104: daload
     105: dmul
     106: dastore
     107: iload         15
     109: iconst_1
     110: isub
     111: istore        18
     113: iload         18
     115: iflt          199
     118: dload         16
     120: dload         9
     122: dmul
     123: aload         8
     125: iload         18
     127: daload
     128: dadd
     129: dstore        16
     131: iload         18
     133: iconst_2
     134: if_icmple     179
     137: aload         8
     139: iload         18
     141: iconst_2
     142: isub
     143: iload         18
     145: iconst_1
     146: isub
     147: i2d
     148: aload         8
     150: iload         18
     152: iconst_1
     153: isub
     154: daload
     155: dmul
     156: iconst_2
     157: iload         15
     159: imul
     160: iload         18
     162: isub
     163: iconst_1
     164: iadd
     165: i2d
     166: aload         8
     168: iload         18
     170: iconst_3
     171: isub
     172: daload
     173: dmul
     174: dadd
     175: dastore
     176: goto          193
     179: iload         18
     181: iconst_2
     182: if_icmpne     193
     185: aload         8
     187: iconst_0
     188: aload         8
     190: iconst_1
     191: daload
     192: dastore
     193: iinc          18, -2
     196: goto          113
     199: iload         15
     201: iconst_1
     202: iand
     203: ifne          213
     206: dload         16
     208: dload         6
     210: dmul
     211: dstore        16
     213: dload         13
     215: dload         11
     217: dmul
     218: dstore        13
     220: aload         5
     222: iload         15
     224: dload         13
     226: dload         16
     228: dmul
     229: dastore
     230: iinc          15, 1
     233: goto          77
     236: aload_0
     237: aload_1
     238: iload_2
     239: aload         5
     241: aload_3
     242: iload         4
     244: invokevirtual #50                 // Method compose:([DI[D[DI)V
     247: return

  public void compose(double[], int, double[], double[], int);
    Code:
       0: iconst_0
       1: istore        6
       3: iload         6
       5: aload_0
       6: getfield      #13                 // Field compIndirection:[[[I
       9: arraylength
      10: if_icmpge     117
      13: aload_0
      14: getfield      #13                 // Field compIndirection:[[[I
      17: iload         6
      19: aaload
      20: astore        7
      22: dconst_0
      23: dstore        8
      25: iconst_0
      26: istore        10
      28: iload         10
      30: aload         7
      32: arraylength
      33: if_icmpge     101
      36: aload         7
      38: iload         10
      40: aaload
      41: astore        11
      43: aload         11
      45: iconst_0
      46: iaload
      47: i2d
      48: aload_3
      49: aload         11
      51: iconst_1
      52: iaload
      53: daload
      54: dmul
      55: dstore        12
      57: iconst_2
      58: istore        14
      60: iload         14
      62: aload         11
      64: arraylength
      65: if_icmpge     88
      68: dload         12
      70: aload_1
      71: iload_2
      72: aload         11
      74: iload         14
      76: iaload
      77: iadd
      78: daload
      79: dmul
      80: dstore        12
      82: iinc          14, 1
      85: goto          60
      88: dload         8
      90: dload         12
      92: dadd
      93: dstore        8
      95: iinc          10, 1
      98: goto          28
     101: aload         4
     103: iload         5
     105: iload         6
     107: iadd
     108: dload         8
     110: dastore
     111: iinc          6, 1
     114: goto          3
     117: return

  public double taylor(double[], int, double...);
    Code:
       0: dconst_0
       1: dstore        4
       3: aload_0
       4: invokevirtual #25                 // Method getSize:()I
       7: iconst_1
       8: isub
       9: istore        6
      11: iload         6
      13: iflt          97
      16: aload_0
      17: iload         6
      19: invokevirtual #96                 // Method getPartialDerivativeOrders:(I)[I
      22: astore        7
      24: aload_1
      25: iload_2
      26: iload         6
      28: iadd
      29: daload
      30: dstore        8
      32: iconst_0
      33: istore        10
      35: iload         10
      37: aload         7
      39: arraylength
      40: if_icmpge     84
      43: aload         7
      45: iload         10
      47: iaload
      48: ifle          78
      51: dload         8
      53: aload_3
      54: iload         10
      56: daload
      57: aload         7
      59: iload         10
      61: iaload
      62: invokestatic  #52                 // Method org/apache/commons/math3/util/FastMath.pow:(DI)D
      65: aload         7
      67: iload         10
      69: iaload
      70: invokestatic  #97                 // Method org/apache/commons/math3/util/ArithmeticUtils.factorial:(I)J
      73: l2d
      74: ddiv
      75: dmul
      76: dstore        8
      78: iinc          10, 1
      81: goto          35
      84: dload         4
      86: dload         8
      88: dadd
      89: dstore        4
      91: iinc          6, -1
      94: goto          11
      97: dload         4
      99: dreturn

  public void checkCompatibility(org.apache.commons.math3.analysis.differentiation.DSCompiler) throws org.apache.commons.math3.exception.DimensionMismatchException;
    Code:
       0: aload_0
       1: getfield      #2                  // Field parameters:I
       4: aload_1
       5: getfield      #2                  // Field parameters:I
       8: if_icmpeq     27
      11: new           #38                 // class org/apache/commons/math3/exception/DimensionMismatchException
      14: dup
      15: aload_0
      16: getfield      #2                  // Field parameters:I
      19: aload_1
      20: getfield      #2                  // Field parameters:I
      23: invokespecial #39                 // Method org/apache/commons/math3/exception/DimensionMismatchException."<init>":(II)V
      26: athrow
      27: aload_0
      28: getfield      #3                  // Field order:I
      31: aload_1
      32: getfield      #3                  // Field order:I
      35: if_icmpeq     54
      38: new           #38                 // class org/apache/commons/math3/exception/DimensionMismatchException
      41: dup
      42: aload_0
      43: getfield      #3                  // Field order:I
      46: aload_1
      47: getfield      #3                  // Field order:I
      50: invokespecial #39                 // Method org/apache/commons/math3/exception/DimensionMismatchException."<init>":(II)V
      53: athrow
      54: return

  static {};
    Code:
       0: new           #98                 // class java/util/concurrent/atomic/AtomicReference
       3: dup
       4: aconst_null
       5: invokespecial #99                 // Method java/util/concurrent/atomic/AtomicReference."<init>":(Ljava/lang/Object;)V
       8: putstatic     #14                 // Field compilers:Ljava/util/concurrent/atomic/AtomicReference;
      11: return
}
