Compiled from "AbstractSignatureParts.kt"
final class kotlin.reflect.jvm.internal.impl.load.java.typeEnhancement.AbstractSignatureParts$computeIndexedQualifiers$1 extends kotlin.jvm.internal.Lambda implements kotlin.jvm.functions.Function1<java.lang.Integer, kotlin.reflect.jvm.internal.impl.load.java.typeEnhancement.JavaTypeQualifiers> {
  final kotlin.reflect.jvm.internal.impl.load.java.typeEnhancement.TypeEnhancementInfo $predefined;

  final kotlin.reflect.jvm.internal.impl.load.java.typeEnhancement.JavaTypeQualifiers[] $computedResult;

  kotlin.reflect.jvm.internal.impl.load.java.typeEnhancement.AbstractSignatureParts$computeIndexedQualifiers$1(kotlin.reflect.jvm.internal.impl.load.java.typeEnhancement.TypeEnhancementInfo, kotlin.reflect.jvm.internal.impl.load.java.typeEnhancement.JavaTypeQualifiers[]);
    Code:
       0: aload_0
       1: aload_1
       2: putfield      #14                 // Field $predefined:Lkotlin/reflect/jvm/internal/impl/load/java/typeEnhancement/TypeEnhancementInfo;
       5: aload_0
       6: aload_2
       7: putfield      #13                 // Field $computedResult:[Lkotlin/reflect/jvm/internal/impl/load/java/typeEnhancement/JavaTypeQualifiers;
      10: aload_0
      11: iconst_1
      12: invokespecial #19                 // Method kotlin/jvm/internal/Lambda."<init>":(I)V
      15: return

  public final kotlin.reflect.jvm.internal.impl.load.java.typeEnhancement.JavaTypeQualifiers invoke(int);
    Code:
       0: aload_0
       1: getfield      #14                 // Field $predefined:Lkotlin/reflect/jvm/internal/impl/load/java/typeEnhancement/TypeEnhancementInfo;
       4: dup
       5: ifnull        31
       8: invokevirtual #22                 // Method kotlin/reflect/jvm/internal/impl/load/java/typeEnhancement/TypeEnhancementInfo.getMap:()Ljava/util/Map;
      11: dup
      12: ifnull        31
      15: iload_1
      16: invokestatic  #16                 // Method java/lang/Integer.valueOf:(I)Ljava/lang/Integer;
      19: invokeinterface #23,  2           // InterfaceMethod java/util/Map.get:(Ljava/lang/Object;)Ljava/lang/Object;
      24: checkcast     #10                 // class kotlin/reflect/jvm/internal/impl/load/java/typeEnhancement/JavaTypeQualifiers
      27: dup
      28: ifnonnull     67
      31: pop
      32: aload_0
      33: getfield      #13                 // Field $computedResult:[Lkotlin/reflect/jvm/internal/impl/load/java/typeEnhancement/JavaTypeQualifiers;
      36: astore_2
      37: iload_1
      38: iflt          55
      41: iload_1
      42: aload_2
      43: invokestatic  #18                 // Method kotlin/collections/ArraysKt.getLastIndex:([Ljava/lang/Object;)I
      46: if_icmpgt     55
      49: aload_2
      50: iload_1
      51: aaload
      52: goto          67
      55: iload_1
      56: istore_3
      57: iconst_0
      58: istore        4
      60: getstatic     #15                 // Field kotlin/reflect/jvm/internal/impl/load/java/typeEnhancement/JavaTypeQualifiers.Companion:Lkotlin/reflect/jvm/internal/impl/load/java/typeEnhancement/JavaTypeQualifiers$Companion;
      63: invokevirtual #21                 // Method kotlin/reflect/jvm/internal/impl/load/java/typeEnhancement/JavaTypeQualifiers$Companion.getNONE:()Lkotlin/reflect/jvm/internal/impl/load/java/typeEnhancement/JavaTypeQualifiers;
      66: nop
      67: areturn

  public java.lang.Object invoke(java.lang.Object);
    Code:
       0: aload_0
       1: aload_1
       2: checkcast     #2                  // class java/lang/Number
       5: invokevirtual #17                 // Method java/lang/Number.intValue:()I
       8: invokevirtual #20                 // Method invoke:(I)Lkotlin/reflect/jvm/internal/impl/load/java/typeEnhancement/JavaTypeQualifiers;
      11: areturn
}
