Compiled from "AbstractSignatureParts.kt"
final class kotlin.reflect.jvm.internal.impl.load.java.typeEnhancement.AbstractSignatureParts$toIndexed$1$1 extends kotlin.jvm.internal.Lambda implements kotlin.jvm.functions.Function1<kotlin.reflect.jvm.internal.impl.load.java.typeEnhancement.AbstractSignatureParts$TypeAndDefaultQualifiers, java.lang.Iterable<? extends kotlin.reflect.jvm.internal.impl.load.java.typeEnhancement.AbstractSignatureParts$TypeAndDefaultQualifiers>> {
  final kotlin.reflect.jvm.internal.impl.load.java.typeEnhancement.AbstractSignatureParts<TAnnotation> this$0;

  final kotlin.reflect.jvm.internal.impl.types.model.TypeSystemContext $this_with;

  kotlin.reflect.jvm.internal.impl.load.java.typeEnhancement.AbstractSignatureParts$toIndexed$1$1(kotlin.reflect.jvm.internal.impl.load.java.typeEnhancement.AbstractSignatureParts<TAnnotation>, kotlin.reflect.jvm.internal.impl.types.model.TypeSystemContext);
    Code:
       0: aload_0
       1: aload_1
       2: putfield      #18                 // Field this$0:Lkotlin/reflect/jvm/internal/impl/load/java/typeEnhancement/AbstractSignatureParts;
       5: aload_0
       6: aload_2
       7: putfield      #17                 // Field $this_with:Lkotlin/reflect/jvm/internal/impl/types/model/TypeSystemContext;
      10: aload_0
      11: iconst_1
      12: invokespecial #24                 // Method kotlin/jvm/internal/Lambda."<init>":(I)V
      15: return

  public final java.lang.Iterable<kotlin.reflect.jvm.internal.impl.load.java.typeEnhancement.AbstractSignatureParts$TypeAndDefaultQualifiers> invoke(kotlin.reflect.jvm.internal.impl.load.java.typeEnhancement.AbstractSignatureParts$TypeAndDefaultQualifiers);
    Code:
       0: aload_1
       1: ldc           #1                  // String it
       3: invokestatic  #23                 // Method kotlin/jvm/internal/Intrinsics.checkNotNullParameter:(Ljava/lang/Object;Ljava/lang/String;)V
       6: aload_0
       7: getfield      #18                 // Field this$0:Lkotlin/reflect/jvm/internal/impl/load/java/typeEnhancement/AbstractSignatureParts;
      10: invokevirtual #26                 // Method kotlin/reflect/jvm/internal/impl/load/java/typeEnhancement/AbstractSignatureParts.getSkipRawTypeArguments:()Z
      13: ifeq          53
      16: aload_1
      17: invokevirtual #29                 // Method kotlin/reflect/jvm/internal/impl/load/java/typeEnhancement/AbstractSignatureParts$TypeAndDefaultQualifiers.getType:()Lkotlin/reflect/jvm/internal/impl/types/model/KotlinTypeMarker;
      20: astore_2
      21: aload_2
      22: ifnull        47
      25: aload_0
      26: getfield      #17                 // Field $this_with:Lkotlin/reflect/jvm/internal/impl/types/model/TypeSystemContext;
      29: aload_2
      30: invokeinterface #37,  2           // InterfaceMethod kotlin/reflect/jvm/internal/impl/types/model/TypeSystemContext.isRawType:(Lkotlin/reflect/jvm/internal/impl/types/model/KotlinTypeMarker;)Z
      35: iconst_1
      36: if_icmpne     43
      39: iconst_1
      40: goto          48
      43: iconst_0
      44: goto          48
      47: iconst_0
      48: ifeq          53
      51: aconst_null
      52: areturn
      53: aload_1
      54: invokevirtual #29                 // Method kotlin/reflect/jvm/internal/impl/load/java/typeEnhancement/AbstractSignatureParts$TypeAndDefaultQualifiers.getType:()Lkotlin/reflect/jvm/internal/impl/types/model/KotlinTypeMarker;
      57: astore_2
      58: aload_2
      59: ifnull        310
      62: aload_0
      63: getfield      #17                 // Field $this_with:Lkotlin/reflect/jvm/internal/impl/types/model/TypeSystemContext;
      66: aload_2
      67: invokeinterface #39,  2           // InterfaceMethod kotlin/reflect/jvm/internal/impl/types/model/TypeSystemContext.typeConstructor:(Lkotlin/reflect/jvm/internal/impl/types/model/KotlinTypeMarker;)Lkotlin/reflect/jvm/internal/impl/types/model/TypeConstructorMarker;
      72: astore_3
      73: aload_3
      74: ifnull        310
      77: aload_0
      78: getfield      #17                 // Field $this_with:Lkotlin/reflect/jvm/internal/impl/types/model/TypeSystemContext;
      81: aload_3
      82: invokeinterface #35,  2           // InterfaceMethod kotlin/reflect/jvm/internal/impl/types/model/TypeSystemContext.getParameters:(Lkotlin/reflect/jvm/internal/impl/types/model/TypeConstructorMarker;)Ljava/util/List;
      87: astore        4
      89: aload         4
      91: ifnull        310
      94: aload         4
      96: checkcast     #2                  // class java/lang/Iterable
      99: astore        5
     101: aload_0
     102: getfield      #17                 // Field $this_with:Lkotlin/reflect/jvm/internal/impl/types/model/TypeSystemContext;
     105: aload_1
     106: invokevirtual #29                 // Method kotlin/reflect/jvm/internal/impl/load/java/typeEnhancement/AbstractSignatureParts$TypeAndDefaultQualifiers.getType:()Lkotlin/reflect/jvm/internal/impl/types/model/KotlinTypeMarker;
     109: invokeinterface #34,  2           // InterfaceMethod kotlin/reflect/jvm/internal/impl/types/model/TypeSystemContext.getArguments:(Lkotlin/reflect/jvm/internal/impl/types/model/KotlinTypeMarker;)Ljava/util/List;
     114: checkcast     #2                  // class java/lang/Iterable
     117: astore        6
     119: aload_0
     120: getfield      #17                 // Field $this_with:Lkotlin/reflect/jvm/internal/impl/types/model/TypeSystemContext;
     123: astore        7
     125: aload_0
     126: getfield      #18                 // Field this$0:Lkotlin/reflect/jvm/internal/impl/load/java/typeEnhancement/AbstractSignatureParts;
     129: astore        8
     131: iconst_0
     132: istore        9
     134: aload         5
     136: invokeinterface #31,  1           // InterfaceMethod java/lang/Iterable.iterator:()Ljava/util/Iterator;
     141: astore        10
     143: aload         6
     145: invokeinterface #31,  1           // InterfaceMethod java/lang/Iterable.iterator:()Ljava/util/Iterator;
     150: astore        11
     152: new           #4                  // class java/util/ArrayList
     155: dup
     156: aload         5
     158: bipush        10
     160: invokestatic  #22                 // Method kotlin/collections/CollectionsKt.collectionSizeOrDefault:(Ljava/lang/Iterable;I)I
     163: aload         6
     165: bipush        10
     167: invokestatic  #22                 // Method kotlin/collections/CollectionsKt.collectionSizeOrDefault:(Ljava/lang/Iterable;I)I
     170: invokestatic  #19                 // Method java/lang/Math.min:(II)I
     173: invokespecial #20                 // Method java/util/ArrayList."<init>":(I)V
     176: astore        12
     178: aload         10
     180: invokeinterface #32,  1           // InterfaceMethod java/util/Iterator.hasNext:()Z
     185: ifeq          302
     188: aload         11
     190: invokeinterface #32,  1           // InterfaceMethod java/util/Iterator.hasNext:()Z
     195: ifeq          302
     198: aload         12
     200: aload         10
     202: invokeinterface #33,  1           // InterfaceMethod java/util/Iterator.next:()Ljava/lang/Object;
     207: aload         11
     209: invokeinterface #33,  1           // InterfaceMethod java/util/Iterator.next:()Ljava/lang/Object;
     214: checkcast     #14                 // class kotlin/reflect/jvm/internal/impl/types/model/TypeArgumentMarker
     217: astore        13
     219: checkcast     #15                 // class kotlin/reflect/jvm/internal/impl/types/model/TypeParameterMarker
     222: astore        14
     224: astore        17
     226: iconst_0
     227: istore        15
     229: aload         7
     231: aload         13
     233: invokeinterface #38,  2           // InterfaceMethod kotlin/reflect/jvm/internal/impl/types/model/TypeSystemContext.isStarProjection:(Lkotlin/reflect/jvm/internal/impl/types/model/TypeArgumentMarker;)Z
     238: ifeq          258
     241: new           #12                 // class kotlin/reflect/jvm/internal/impl/load/java/typeEnhancement/AbstractSignatureParts$TypeAndDefaultQualifiers
     244: dup
     245: aconst_null
     246: aload_1
     247: invokevirtual #28                 // Method kotlin/reflect/jvm/internal/impl/load/java/typeEnhancement/AbstractSignatureParts$TypeAndDefaultQualifiers.getDefaultQualifiers:()Lkotlin/reflect/jvm/internal/impl/load/java/JavaTypeQualifiersByElementType;
     250: aload         14
     252: invokespecial #27                 // Method kotlin/reflect/jvm/internal/impl/load/java/typeEnhancement/AbstractSignatureParts$TypeAndDefaultQualifiers."<init>":(Lkotlin/reflect/jvm/internal/impl/types/model/KotlinTypeMarker;Lkotlin/reflect/jvm/internal/impl/load/java/JavaTypeQualifiersByElementType;Lkotlin/reflect/jvm/internal/impl/types/model/TypeParameterMarker;)V
     255: goto          291
     258: aload         7
     260: aload         13
     262: invokeinterface #36,  2           // InterfaceMethod kotlin/reflect/jvm/internal/impl/types/model/TypeSystemContext.getType:(Lkotlin/reflect/jvm/internal/impl/types/model/TypeArgumentMarker;)Lkotlin/reflect/jvm/internal/impl/types/model/KotlinTypeMarker;
     267: astore        16
     269: new           #12                 // class kotlin/reflect/jvm/internal/impl/load/java/typeEnhancement/AbstractSignatureParts$TypeAndDefaultQualifiers
     272: dup
     273: aload         16
     275: aload         8
     277: aload         16
     279: aload_1
     280: invokevirtual #28                 // Method kotlin/reflect/jvm/internal/impl/load/java/typeEnhancement/AbstractSignatureParts$TypeAndDefaultQualifiers.getDefaultQualifiers:()Lkotlin/reflect/jvm/internal/impl/load/java/JavaTypeQualifiersByElementType;
     283: invokestatic  #25                 // Method kotlin/reflect/jvm/internal/impl/load/java/typeEnhancement/AbstractSignatureParts.access$extractAndMergeDefaultQualifiers:(Lkotlin/reflect/jvm/internal/impl/load/java/typeEnhancement/AbstractSignatureParts;Lkotlin/reflect/jvm/internal/impl/types/model/KotlinTypeMarker;Lkotlin/reflect/jvm/internal/impl/load/java/JavaTypeQualifiersByElementType;)Lkotlin/reflect/jvm/internal/impl/load/java/JavaTypeQualifiersByElementType;
     286: aload         14
     288: invokespecial #27                 // Method kotlin/reflect/jvm/internal/impl/load/java/typeEnhancement/AbstractSignatureParts$TypeAndDefaultQualifiers."<init>":(Lkotlin/reflect/jvm/internal/impl/types/model/KotlinTypeMarker;Lkotlin/reflect/jvm/internal/impl/load/java/JavaTypeQualifiersByElementType;Lkotlin/reflect/jvm/internal/impl/types/model/TypeParameterMarker;)V
     291: nop
     292: aload         17
     294: swap
     295: invokevirtual #21                 // Method java/util/ArrayList.add:(Ljava/lang/Object;)Z
     298: pop
     299: goto          178
     302: aload         12
     304: checkcast     #6                  // class java/util/List
     307: goto          311
     310: aconst_null
     311: checkcast     #2                  // class java/lang/Iterable
     314: areturn

  public java.lang.Object invoke(java.lang.Object);
    Code:
       0: aload_0
       1: aload_1
       2: checkcast     #12                 // class kotlin/reflect/jvm/internal/impl/load/java/typeEnhancement/AbstractSignatureParts$TypeAndDefaultQualifiers
       5: invokevirtual #30                 // Method invoke:(Lkotlin/reflect/jvm/internal/impl/load/java/typeEnhancement/AbstractSignatureParts$TypeAndDefaultQualifiers;)Ljava/lang/Iterable;
       8: areturn
}
