Compiled from "typeEnhancementUtils.kt"
public final class kotlin.reflect.jvm.internal.impl.load.java.typeEnhancement.TypeEnhancementUtilsKt {
  private static final <T> T select(java.util.Set<? extends T>, T, T, T, boolean);
    Code:
       0: iload         4
       2: ifeq          66
       5: aload_0
       6: aload_1
       7: invokeinterface #47,  2           // InterfaceMethod java/util/Set.contains:(Ljava/lang/Object;)Z
      12: ifeq          19
      15: aload_1
      16: goto          34
      19: aload_0
      20: aload_2
      21: invokeinterface #47,  2           // InterfaceMethod java/util/Set.contains:(Ljava/lang/Object;)Z
      26: ifeq          33
      29: aload_2
      30: goto          34
      33: aconst_null
      34: astore        5
      36: aload         5
      38: aload_1
      39: invokestatic  #31                 // Method kotlin/jvm/internal/Intrinsics.areEqual:(Ljava/lang/Object;Ljava/lang/Object;)Z
      42: ifeq          57
      45: aload_3
      46: aload_2
      47: invokestatic  #31                 // Method kotlin/jvm/internal/Intrinsics.areEqual:(Ljava/lang/Object;Ljava/lang/Object;)Z
      50: ifeq          57
      53: aconst_null
      54: goto          65
      57: aload_3
      58: dup
      59: ifnonnull     65
      62: pop
      63: aload         5
      65: areturn
      66: aload_3
      67: dup
      68: ifnull        92
      71: astore        6
      73: iconst_0
      74: istore        7
      76: aload_0
      77: aload_3
      78: invokestatic  #30                 // Method kotlin/collections/SetsKt.plus:(Ljava/util/Set;Ljava/lang/Object;)Ljava/util/Set;
      81: checkcast     #5                  // class java/lang/Iterable
      84: invokestatic  #29                 // Method kotlin/collections/CollectionsKt.toSet:(Ljava/lang/Iterable;)Ljava/util/Set;
      87: nop
      88: dup
      89: ifnonnull     94
      92: pop
      93: aload_0
      94: astore        5
      96: aload         5
      98: checkcast     #5                  // class java/lang/Iterable
     101: invokestatic  #28                 // Method kotlin/collections/CollectionsKt.singleOrNull:(Ljava/lang/Iterable;)Ljava/lang/Object;
     104: areturn

  private static final kotlin.reflect.jvm.internal.impl.load.java.typeEnhancement.NullabilityQualifier select(java.util.Set<? extends kotlin.reflect.jvm.internal.impl.load.java.typeEnhancement.NullabilityQualifier>, kotlin.reflect.jvm.internal.impl.load.java.typeEnhancement.NullabilityQualifier, boolean);
    Code:
       0: aload_1
       1: getstatic     #24                 // Field kotlin/reflect/jvm/internal/impl/load/java/typeEnhancement/NullabilityQualifier.FORCE_FLEXIBILITY:Lkotlin/reflect/jvm/internal/impl/load/java/typeEnhancement/NullabilityQualifier;
       4: if_acmpne     13
       7: getstatic     #24                 // Field kotlin/reflect/jvm/internal/impl/load/java/typeEnhancement/NullabilityQualifier.FORCE_FLEXIBILITY:Lkotlin/reflect/jvm/internal/impl/load/java/typeEnhancement/NullabilityQualifier;
      10: goto          28
      13: aload_0
      14: getstatic     #25                 // Field kotlin/reflect/jvm/internal/impl/load/java/typeEnhancement/NullabilityQualifier.NOT_NULL:Lkotlin/reflect/jvm/internal/impl/load/java/typeEnhancement/NullabilityQualifier;
      17: getstatic     #26                 // Field kotlin/reflect/jvm/internal/impl/load/java/typeEnhancement/NullabilityQualifier.NULLABLE:Lkotlin/reflect/jvm/internal/impl/load/java/typeEnhancement/NullabilityQualifier;
      20: aload_1
      21: iload_2
      22: invokestatic  #40                 // Method select:(Ljava/util/Set;Ljava/lang/Object;Ljava/lang/Object;Ljava/lang/Object;Z)Ljava/lang/Object;
      25: checkcast     #18                 // class kotlin/reflect/jvm/internal/impl/load/java/typeEnhancement/NullabilityQualifier
      28: areturn

  private static final kotlin.reflect.jvm.internal.impl.load.java.typeEnhancement.NullabilityQualifier getNullabilityForErrors(kotlin.reflect.jvm.internal.impl.load.java.typeEnhancement.JavaTypeQualifiers);
    Code:
       0: aload_0
       1: invokevirtual #38                 // Method kotlin/reflect/jvm/internal/impl/load/java/typeEnhancement/JavaTypeQualifiers.isNullabilityQualifierForWarning:()Z
       4: ifeq          11
       7: aconst_null
       8: goto          15
      11: aload_0
      12: invokevirtual #37                 // Method kotlin/reflect/jvm/internal/impl/load/java/typeEnhancement/JavaTypeQualifiers.getNullability:()Lkotlin/reflect/jvm/internal/impl/load/java/typeEnhancement/NullabilityQualifier;
      15: areturn

  public static final kotlin.reflect.jvm.internal.impl.load.java.typeEnhancement.JavaTypeQualifiers computeQualifiersForOverride(kotlin.reflect.jvm.internal.impl.load.java.typeEnhancement.JavaTypeQualifiers, java.util.Collection<kotlin.reflect.jvm.internal.impl.load.java.typeEnhancement.JavaTypeQualifiers>, boolean, boolean, boolean);
    Code:
       0: aload_0
       1: ldc           #1                  // String <this>
       3: invokestatic  #33                 // Method kotlin/jvm/internal/Intrinsics.checkNotNullParameter:(Ljava/lang/Object;Ljava/lang/String;)V
       6: aload_1
       7: ldc           #3                  // String superQualifiers
       9: invokestatic  #33                 // Method kotlin/jvm/internal/Intrinsics.checkNotNullParameter:(Ljava/lang/Object;Ljava/lang/String;)V
      12: aload_1
      13: checkcast     #5                  // class java/lang/Iterable
      16: astore        6
      18: iconst_0
      19: istore        7
      21: aload         6
      23: astore        8
      25: new           #7                  // class java/util/ArrayList
      28: dup
      29: invokespecial #27                 // Method java/util/ArrayList."<init>":()V
      32: checkcast     #8                  // class java/util/Collection
      35: astore        9
      37: iconst_0
      38: istore        10
      40: aload         8
      42: astore        11
      44: iconst_0
      45: istore        12
      47: aload         11
      49: invokeinterface #42,  1           // InterfaceMethod java/lang/Iterable.iterator:()Ljava/util/Iterator;
      54: astore        13
      56: aload         13
      58: invokeinterface #45,  1           // InterfaceMethod java/util/Iterator.hasNext:()Z
      63: ifeq          124
      66: aload         13
      68: invokeinterface #46,  1           // InterfaceMethod java/util/Iterator.next:()Ljava/lang/Object;
      73: astore        14
      75: aload         14
      77: astore        15
      79: iconst_0
      80: istore        16
      82: aload         15
      84: checkcast     #16                 // class kotlin/reflect/jvm/internal/impl/load/java/typeEnhancement/JavaTypeQualifiers
      87: astore        17
      89: iconst_0
      90: istore        18
      92: aload         17
      94: invokestatic  #39                 // Method getNullabilityForErrors:(Lkotlin/reflect/jvm/internal/impl/load/java/typeEnhancement/JavaTypeQualifiers;)Lkotlin/reflect/jvm/internal/impl/load/java/typeEnhancement/NullabilityQualifier;
      97: dup
      98: ifnull        119
     101: astore        19
     103: iconst_0
     104: istore        20
     106: aload         9
     108: aload         19
     110: invokeinterface #43,  2           // InterfaceMethod java/util/Collection.add:(Ljava/lang/Object;)Z
     115: pop
     116: goto          120
     119: pop
     120: nop
     121: goto          56
     124: nop
     125: aload         9
     127: checkcast     #10                 // class java/util/List
     130: nop
     131: checkcast     #5                  // class java/lang/Iterable
     134: invokestatic  #29                 // Method kotlin/collections/CollectionsKt.toSet:(Ljava/lang/Iterable;)Ljava/util/Set;
     137: aload_0
     138: invokestatic  #39                 // Method getNullabilityForErrors:(Lkotlin/reflect/jvm/internal/impl/load/java/typeEnhancement/JavaTypeQualifiers;)Lkotlin/reflect/jvm/internal/impl/load/java/typeEnhancement/NullabilityQualifier;
     141: iload_2
     142: invokestatic  #41                 // Method select:(Ljava/util/Set;Lkotlin/reflect/jvm/internal/impl/load/java/typeEnhancement/NullabilityQualifier;Z)Lkotlin/reflect/jvm/internal/impl/load/java/typeEnhancement/NullabilityQualifier;
     145: astore        5
     147: aload         5
     149: dup
     150: ifnonnull     287
     153: pop
     154: aload_1
     155: checkcast     #5                  // class java/lang/Iterable
     158: astore        7
     160: iconst_0
     161: istore        8
     163: aload         7
     165: astore        9
     167: new           #7                  // class java/util/ArrayList
     170: dup
     171: invokespecial #27                 // Method java/util/ArrayList."<init>":()V
     174: checkcast     #8                  // class java/util/Collection
     177: astore        10
     179: iconst_0
     180: istore        11
     182: aload         9
     184: astore        12
     186: iconst_0
     187: istore        13
     189: aload         12
     191: invokeinterface #42,  1           // InterfaceMethod java/lang/Iterable.iterator:()Ljava/util/Iterator;
     196: astore        14
     198: aload         14
     200: invokeinterface #45,  1           // InterfaceMethod java/util/Iterator.hasNext:()Z
     205: ifeq          266
     208: aload         14
     210: invokeinterface #46,  1           // InterfaceMethod java/util/Iterator.next:()Ljava/lang/Object;
     215: astore        15
     217: aload         15
     219: astore        16
     221: iconst_0
     222: istore        17
     224: aload         16
     226: checkcast     #16                 // class kotlin/reflect/jvm/internal/impl/load/java/typeEnhancement/JavaTypeQualifiers
     229: astore        18
     231: iconst_0
     232: istore        19
     234: aload         18
     236: invokevirtual #37                 // Method kotlin/reflect/jvm/internal/impl/load/java/typeEnhancement/JavaTypeQualifiers.getNullability:()Lkotlin/reflect/jvm/internal/impl/load/java/typeEnhancement/NullabilityQualifier;
     239: dup
     240: ifnull        261
     243: astore        20
     245: iconst_0
     246: istore        21
     248: aload         10
     250: aload         20
     252: invokeinterface #43,  2           // InterfaceMethod java/util/Collection.add:(Ljava/lang/Object;)Z
     257: pop
     258: goto          262
     261: pop
     262: nop
     263: goto          198
     266: nop
     267: aload         10
     269: checkcast     #10                 // class java/util/List
     272: nop
     273: checkcast     #5                  // class java/lang/Iterable
     276: invokestatic  #29                 // Method kotlin/collections/CollectionsKt.toSet:(Ljava/lang/Iterable;)Ljava/util/Set;
     279: aload_0
     280: invokevirtual #37                 // Method kotlin/reflect/jvm/internal/impl/load/java/typeEnhancement/JavaTypeQualifiers.getNullability:()Lkotlin/reflect/jvm/internal/impl/load/java/typeEnhancement/NullabilityQualifier;
     283: iload_2
     284: invokestatic  #41                 // Method select:(Ljava/util/Set;Lkotlin/reflect/jvm/internal/impl/load/java/typeEnhancement/NullabilityQualifier;Z)Lkotlin/reflect/jvm/internal/impl/load/java/typeEnhancement/NullabilityQualifier;
     287: astore        6
     289: aload_1
     290: checkcast     #5                  // class java/lang/Iterable
     293: astore        8
     295: iconst_0
     296: istore        9
     298: aload         8
     300: astore        10
     302: new           #7                  // class java/util/ArrayList
     305: dup
     306: invokespecial #27                 // Method java/util/ArrayList."<init>":()V
     309: checkcast     #8                  // class java/util/Collection
     312: astore        11
     314: iconst_0
     315: istore        12
     317: aload         10
     319: astore        13
     321: iconst_0
     322: istore        14
     324: aload         13
     326: invokeinterface #42,  1           // InterfaceMethod java/lang/Iterable.iterator:()Ljava/util/Iterator;
     331: astore        15
     333: aload         15
     335: invokeinterface #45,  1           // InterfaceMethod java/util/Iterator.hasNext:()Z
     340: ifeq          401
     343: aload         15
     345: invokeinterface #46,  1           // InterfaceMethod java/util/Iterator.next:()Ljava/lang/Object;
     350: astore        16
     352: aload         16
     354: astore        17
     356: iconst_0
     357: istore        18
     359: aload         17
     361: checkcast     #16                 // class kotlin/reflect/jvm/internal/impl/load/java/typeEnhancement/JavaTypeQualifiers
     364: astore        19
     366: iconst_0
     367: istore        20
     369: aload         19
     371: invokevirtual #36                 // Method kotlin/reflect/jvm/internal/impl/load/java/typeEnhancement/JavaTypeQualifiers.getMutability:()Lkotlin/reflect/jvm/internal/impl/load/java/typeEnhancement/MutabilityQualifier;
     374: dup
     375: ifnull        396
     378: astore        21
     380: iconst_0
     381: istore        22
     383: aload         11
     385: aload         21
     387: invokeinterface #43,  2           // InterfaceMethod java/util/Collection.add:(Ljava/lang/Object;)Z
     392: pop
     393: goto          397
     396: pop
     397: nop
     398: goto          333
     401: nop
     402: aload         11
     404: checkcast     #10                 // class java/util/List
     407: nop
     408: checkcast     #5                  // class java/lang/Iterable
     411: invokestatic  #29                 // Method kotlin/collections/CollectionsKt.toSet:(Ljava/lang/Iterable;)Ljava/util/Set;
     414: getstatic     #22                 // Field kotlin/reflect/jvm/internal/impl/load/java/typeEnhancement/MutabilityQualifier.MUTABLE:Lkotlin/reflect/jvm/internal/impl/load/java/typeEnhancement/MutabilityQualifier;
     417: getstatic     #23                 // Field kotlin/reflect/jvm/internal/impl/load/java/typeEnhancement/MutabilityQualifier.READ_ONLY:Lkotlin/reflect/jvm/internal/impl/load/java/typeEnhancement/MutabilityQualifier;
     420: aload_0
     421: invokevirtual #36                 // Method kotlin/reflect/jvm/internal/impl/load/java/typeEnhancement/JavaTypeQualifiers.getMutability:()Lkotlin/reflect/jvm/internal/impl/load/java/typeEnhancement/MutabilityQualifier;
     424: iload_2
     425: invokestatic  #40                 // Method select:(Ljava/util/Set;Ljava/lang/Object;Ljava/lang/Object;Ljava/lang/Object;Z)Ljava/lang/Object;
     428: checkcast     #17                 // class kotlin/reflect/jvm/internal/impl/load/java/typeEnhancement/MutabilityQualifier
     431: astore        7
     433: aload         6
     435: dup
     436: ifnull        482
     439: astore        9
     441: aload         9
     443: astore        10
     445: iconst_0
     446: istore        11
     448: iload         4
     450: ifne          465
     453: iload_3
     454: ifeq          469
     457: aload         10
     459: getstatic     #26                 // Field kotlin/reflect/jvm/internal/impl/load/java/typeEnhancement/NullabilityQualifier.NULLABLE:Lkotlin/reflect/jvm/internal/impl/load/java/typeEnhancement/NullabilityQualifier;
     462: if_acmpne     469
     465: iconst_1
     466: goto          470
     469: iconst_0
     470: ifne          478
     473: aload         9
     475: goto          484
     478: aconst_null
     479: goto          484
     482: pop
     483: aconst_null
     484: astore        8
     486: aload         8
     488: aload         7
     490: aload         8
     492: getstatic     #25                 // Field kotlin/reflect/jvm/internal/impl/load/java/typeEnhancement/NullabilityQualifier.NOT_NULL:Lkotlin/reflect/jvm/internal/impl/load/java/typeEnhancement/NullabilityQualifier;
     495: if_acmpne     601
     498: aload_0
     499: invokevirtual #35                 // Method kotlin/reflect/jvm/internal/impl/load/java/typeEnhancement/JavaTypeQualifiers.getDefinitelyNotNull:()Z
     502: ifne          597
     505: aload_1
     506: checkcast     #5                  // class java/lang/Iterable
     509: astore        9
     511: astore        24
     513: astore        23
     515: iconst_0
     516: istore        10
     518: aload         9
     520: checkcast     #8                  // class java/util/Collection
     523: invokeinterface #44,  1           // InterfaceMethod java/util/Collection.isEmpty:()Z
     528: ifeq          535
     531: iconst_0
     532: goto          586
     535: aload         9
     537: invokeinterface #42,  1           // InterfaceMethod java/lang/Iterable.iterator:()Ljava/util/Iterator;
     542: astore        11
     544: aload         11
     546: invokeinterface #45,  1           // InterfaceMethod java/util/Iterator.hasNext:()Z
     551: ifeq          585
     554: aload         11
     556: invokeinterface #46,  1           // InterfaceMethod java/util/Iterator.next:()Ljava/lang/Object;
     561: astore        12
     563: aload         12
     565: checkcast     #16                 // class kotlin/reflect/jvm/internal/impl/load/java/typeEnhancement/JavaTypeQualifiers
     568: astore        13
     570: iconst_0
     571: istore        14
     573: aload         13
     575: invokevirtual #35                 // Method kotlin/reflect/jvm/internal/impl/load/java/typeEnhancement/JavaTypeQualifiers.getDefinitelyNotNull:()Z
     578: ifeq          544
     581: iconst_1
     582: goto          586
     585: iconst_0
     586: istore        25
     588: aload         23
     590: aload         24
     592: iload         25
     594: ifeq          601
     597: iconst_1
     598: goto          602
     601: iconst_0
     602: aload         8
     604: ifnull        618
     607: aload         5
     609: aload         6
     611: if_acmpeq     618
     614: iconst_1
     615: goto          619
     618: iconst_0
     619: istore        26
     621: istore        27
     623: astore        28
     625: astore        29
     627: new           #16                 // class kotlin/reflect/jvm/internal/impl/load/java/typeEnhancement/JavaTypeQualifiers
     630: dup
     631: aload         29
     633: aload         28
     635: iload         27
     637: iload         26
     639: invokespecial #34                 // Method kotlin/reflect/jvm/internal/impl/load/java/typeEnhancement/JavaTypeQualifiers."<init>":(Lkotlin/reflect/jvm/internal/impl/load/java/typeEnhancement/NullabilityQualifier;Lkotlin/reflect/jvm/internal/impl/load/java/typeEnhancement/MutabilityQualifier;ZZ)V
     642: areturn

  public static final boolean hasEnhancedNullability(kotlin.reflect.jvm.internal.impl.types.TypeSystemCommonBackendContext, kotlin.reflect.jvm.internal.impl.types.model.KotlinTypeMarker);
    Code:
       0: aload_0
       1: ldc           #1                  // String <this>
       3: invokestatic  #33                 // Method kotlin/jvm/internal/Intrinsics.checkNotNullParameter:(Ljava/lang/Object;Ljava/lang/String;)V
       6: aload_1
       7: ldc           #4                  // String type
       9: invokestatic  #33                 // Method kotlin/jvm/internal/Intrinsics.checkNotNullParameter:(Ljava/lang/Object;Ljava/lang/String;)V
      12: aload_0
      13: aload_1
      14: getstatic     #21                 // Field kotlin/reflect/jvm/internal/impl/load/java/JvmAnnotationNames.ENHANCED_NULLABILITY_ANNOTATION:Lkotlin/reflect/jvm/internal/impl/name/FqName;
      17: dup
      18: ldc           #2                  // String ENHANCED_NULLABILITY_ANNOTATION
      20: invokestatic  #32                 // Method kotlin/jvm/internal/Intrinsics.checkNotNullExpressionValue:(Ljava/lang/Object;Ljava/lang/String;)V
      23: invokeinterface #48,  3           // InterfaceMethod kotlin/reflect/jvm/internal/impl/types/TypeSystemCommonBackendContext.hasAnnotation:(Lkotlin/reflect/jvm/internal/impl/types/model/KotlinTypeMarker;Lkotlin/reflect/jvm/internal/impl/name/FqName;)Z
      28: ireturn
}
