Compiled from "ELProcessor.java"
public class jakarta.el.ELProcessor {
  private jakarta.el.ELManager elManager;

  private jakarta.el.ExpressionFactory factory;

  public jakarta.el.ELProcessor();
    Code:
       0: aload_0
       1: invokespecial #1                  // Method java/lang/Object."<init>":()V
       4: aload_0
       5: new           #2                  // class jakarta/el/ELManager
       8: dup
       9: invokespecial #3                  // Method jakarta/el/ELManager."<init>":()V
      12: putfield      #4                  // Field elManager:Ljakarta/el/ELManager;
      15: aload_0
      16: invokestatic  #5                  // Method jakarta/el/ELManager.getExpressionFactory:()Ljakarta/el/ExpressionFactory;
      19: putfield      #6                  // Field factory:Ljakarta/el/ExpressionFactory;
      22: return

  public jakarta.el.ELManager getELManager();
    Code:
       0: aload_0
       1: getfield      #4                  // Field elManager:Ljakarta/el/ELManager;
       4: areturn

  public java.lang.Object eval(java.lang.String);
    Code:
       0: aload_0
       1: aload_1
       2: ldc           #7                  // class java/lang/Object
       4: invokevirtual #8                  // Method getValue:(Ljava/lang/String;Ljava/lang/Class;)Ljava/lang/Object;
       7: areturn

  public java.lang.Object getValue(java.lang.String, java.lang.Class<?>);
    Code:
       0: aload_0
       1: getfield      #6                  // Field factory:Ljakarta/el/ExpressionFactory;
       4: aload_0
       5: getfield      #4                  // Field elManager:Ljakarta/el/ELManager;
       8: invokevirtual #9                  // Method jakarta/el/ELManager.getELContext:()Ljakarta/el/StandardELContext;
      11: aload_0
      12: aload_1
      13: invokespecial #10                 // Method bracket:(Ljava/lang/String;)Ljava/lang/String;
      16: aload_2
      17: invokevirtual #11                 // Method jakarta/el/ExpressionFactory.createValueExpression:(Ljakarta/el/ELContext;Ljava/lang/String;Ljava/lang/Class;)Ljakarta/el/ValueExpression;
      20: astore_3
      21: aload_3
      22: aload_0
      23: getfield      #4                  // Field elManager:Ljakarta/el/ELManager;
      26: invokevirtual #9                  // Method jakarta/el/ELManager.getELContext:()Ljakarta/el/StandardELContext;
      29: invokevirtual #12                 // Method jakarta/el/ValueExpression.getValue:(Ljakarta/el/ELContext;)Ljava/lang/Object;
      32: areturn

  public void setValue(java.lang.String, java.lang.Object);
    Code:
       0: aload_0
       1: getfield      #6                  // Field factory:Ljakarta/el/ExpressionFactory;
       4: aload_0
       5: getfield      #4                  // Field elManager:Ljakarta/el/ELManager;
       8: invokevirtual #9                  // Method jakarta/el/ELManager.getELContext:()Ljakarta/el/StandardELContext;
      11: aload_0
      12: aload_1
      13: invokespecial #10                 // Method bracket:(Ljava/lang/String;)Ljava/lang/String;
      16: ldc           #7                  // class java/lang/Object
      18: invokevirtual #11                 // Method jakarta/el/ExpressionFactory.createValueExpression:(Ljakarta/el/ELContext;Ljava/lang/String;Ljava/lang/Class;)Ljakarta/el/ValueExpression;
      21: astore_3
      22: aload_3
      23: aload_0
      24: getfield      #4                  // Field elManager:Ljakarta/el/ELManager;
      27: invokevirtual #9                  // Method jakarta/el/ELManager.getELContext:()Ljakarta/el/StandardELContext;
      30: aload_2
      31: invokevirtual #13                 // Method jakarta/el/ValueExpression.setValue:(Ljakarta/el/ELContext;Ljava/lang/Object;)V
      34: return

  public void setVariable(java.lang.String, java.lang.String);
    Code:
       0: aload_0
       1: getfield      #6                  // Field factory:Ljakarta/el/ExpressionFactory;
       4: aload_0
       5: getfield      #4                  // Field elManager:Ljakarta/el/ELManager;
       8: invokevirtual #9                  // Method jakarta/el/ELManager.getELContext:()Ljakarta/el/StandardELContext;
      11: aload_0
      12: aload_2
      13: invokespecial #10                 // Method bracket:(Ljava/lang/String;)Ljava/lang/String;
      16: ldc           #7                  // class java/lang/Object
      18: invokevirtual #11                 // Method jakarta/el/ExpressionFactory.createValueExpression:(Ljakarta/el/ELContext;Ljava/lang/String;Ljava/lang/Class;)Ljakarta/el/ValueExpression;
      21: astore_3
      22: aload_0
      23: getfield      #4                  // Field elManager:Ljakarta/el/ELManager;
      26: aload_1
      27: aload_3
      28: invokevirtual #14                 // Method jakarta/el/ELManager.setVariable:(Ljava/lang/String;Ljakarta/el/ValueExpression;)V
      31: return

  public void defineFunction(java.lang.String, java.lang.String, java.lang.String, java.lang.String) throws java.lang.ClassNotFoundException, java.lang.NoSuchMethodException;
    Code:
       0: aload_1
       1: ifnull        17
       4: aload_2
       5: ifnull        17
       8: aload_3
       9: ifnull        17
      12: aload         4
      14: ifnonnull     27
      17: new           #15                 // class java/lang/NullPointerException
      20: dup
      21: ldc           #16                 // String Null argument for defineFunction
      23: invokespecial #17                 // Method java/lang/NullPointerException."<init>":(Ljava/lang/String;)V
      26: athrow
      27: aconst_null
      28: astore        5
      30: invokestatic  #18                 // Method java/lang/Thread.currentThread:()Ljava/lang/Thread;
      33: invokevirtual #19                 // Method java/lang/Thread.getContextClassLoader:()Ljava/lang/ClassLoader;
      36: astore        6
      38: aload         6
      40: ifnonnull     52
      43: aload_0
      44: invokevirtual #20                 // Method java/lang/Object.getClass:()Ljava/lang/Class;
      47: invokevirtual #21                 // Method java/lang/Class.getClassLoader:()Ljava/lang/ClassLoader;
      50: astore        6
      52: aload_3
      53: iconst_0
      54: aload         6
      56: invokestatic  #22                 // Method java/lang/Class.forName:(Ljava/lang/String;ZLjava/lang/ClassLoader;)Ljava/lang/Class;
      59: astore        7
      61: aload         4
      63: bipush        40
      65: invokevirtual #23                 // Method java/lang/String.indexOf:(I)I
      68: istore        8
      70: iload         8
      72: ifge          160
      75: aload         7
      77: invokevirtual #24                 // Method java/lang/Class.getDeclaredMethods:()[Ljava/lang/reflect/Method;
      80: astore        9
      82: aload         9
      84: arraylength
      85: istore        10
      87: iconst_0
      88: istore        11
      90: iload         11
      92: iload         10
      94: if_icmpge     127
      97: aload         9
      99: iload         11
     101: aaload
     102: astore        12
     104: aload         12
     106: invokevirtual #25                 // Method java/lang/reflect/Method.getName:()Ljava/lang/String;
     109: aload         4
     111: invokevirtual #26                 // Method java/lang/String.equals:(Ljava/lang/Object;)Z
     114: ifeq          121
     117: aload         12
     119: astore        5
     121: iinc          11, 1
     124: goto          90
     127: aload         5
     129: ifnonnull     333
     132: new           #27                 // class java/lang/NoSuchMethodException
     135: dup
     136: new           #28                 // class java/lang/StringBuilder
     139: dup
     140: invokespecial #29                 // Method java/lang/StringBuilder."<init>":()V
     143: ldc           #30                 // String Bad method name:
     145: invokevirtual #31                 // Method java/lang/StringBuilder.append:(Ljava/lang/String;)Ljava/lang/StringBuilder;
     148: aload         4
     150: invokevirtual #31                 // Method java/lang/StringBuilder.append:(Ljava/lang/String;)Ljava/lang/StringBuilder;
     153: invokevirtual #32                 // Method java/lang/StringBuilder.toString:()Ljava/lang/String;
     156: invokespecial #33                 // Method java/lang/NoSuchMethodException."<init>":(Ljava/lang/String;)V
     159: athrow
     160: aload         4
     162: bipush        32
     164: invokevirtual #23                 // Method java/lang/String.indexOf:(I)I
     167: istore        9
     169: iload         9
     171: ifge          202
     174: new           #27                 // class java/lang/NoSuchMethodException
     177: dup
     178: new           #28                 // class java/lang/StringBuilder
     181: dup
     182: invokespecial #29                 // Method java/lang/StringBuilder."<init>":()V
     185: ldc           #34                 // String Bad method signature:
     187: invokevirtual #31                 // Method java/lang/StringBuilder.append:(Ljava/lang/String;)Ljava/lang/StringBuilder;
     190: aload         4
     192: invokevirtual #31                 // Method java/lang/StringBuilder.append:(Ljava/lang/String;)Ljava/lang/StringBuilder;
     195: invokevirtual #32                 // Method java/lang/StringBuilder.toString:()Ljava/lang/String;
     198: invokespecial #33                 // Method java/lang/NoSuchMethodException."<init>":(Ljava/lang/String;)V
     201: athrow
     202: aload         4
     204: iload         9
     206: iconst_1
     207: iadd
     208: iload         8
     210: invokevirtual #35                 // Method java/lang/String.substring:(II)Ljava/lang/String;
     213: invokevirtual #36                 // Method java/lang/String.trim:()Ljava/lang/String;
     216: astore        10
     218: aload         4
     220: bipush        41
     222: iload         8
     224: iconst_1
     225: iadd
     226: invokevirtual #37                 // Method java/lang/String.indexOf:(II)I
     229: istore        9
     231: iload         9
     233: ifge          264
     236: new           #27                 // class java/lang/NoSuchMethodException
     239: dup
     240: new           #28                 // class java/lang/StringBuilder
     243: dup
     244: invokespecial #29                 // Method java/lang/StringBuilder."<init>":()V
     247: ldc           #34                 // String Bad method signature:
     249: invokevirtual #31                 // Method java/lang/StringBuilder.append:(Ljava/lang/String;)Ljava/lang/StringBuilder;
     252: aload         4
     254: invokevirtual #31                 // Method java/lang/StringBuilder.append:(Ljava/lang/String;)Ljava/lang/StringBuilder;
     257: invokevirtual #32                 // Method java/lang/StringBuilder.toString:()Ljava/lang/String;
     260: invokespecial #33                 // Method java/lang/NoSuchMethodException."<init>":(Ljava/lang/String;)V
     263: athrow
     264: aload         4
     266: iload         8
     268: iconst_1
     269: iadd
     270: iload         9
     272: invokevirtual #35                 // Method java/lang/String.substring:(II)Ljava/lang/String;
     275: ldc           #38                 // String ,
     277: invokevirtual #39                 // Method java/lang/String.split:(Ljava/lang/String;)[Ljava/lang/String;
     280: astore        11
     282: aload         11
     284: arraylength
     285: anewarray     #40                 // class java/lang/Class
     288: astore        12
     290: iconst_0
     291: istore        13
     293: iload         13
     295: aload         11
     297: arraylength
     298: if_icmpge     322
     301: aload         12
     303: iload         13
     305: aload         11
     307: iload         13
     309: aaload
     310: aload         6
     312: invokestatic  #41                 // Method toClass:(Ljava/lang/String;Ljava/lang/ClassLoader;)Ljava/lang/Class;
     315: aastore
     316: iinc          13, 1
     319: goto          293
     322: aload         7
     324: aload         10
     326: aload         12
     328: invokevirtual #42                 // Method java/lang/Class.getDeclaredMethod:(Ljava/lang/String;[Ljava/lang/Class;)Ljava/lang/reflect/Method;
     331: astore        5
     333: aload         5
     335: invokevirtual #43                 // Method java/lang/reflect/Method.getModifiers:()I
     338: invokestatic  #44                 // Method java/lang/reflect/Modifier.isStatic:(I)Z
     341: ifne          372
     344: new           #27                 // class java/lang/NoSuchMethodException
     347: dup
     348: new           #28                 // class java/lang/StringBuilder
     351: dup
     352: invokespecial #29                 // Method java/lang/StringBuilder."<init>":()V
     355: ldc           #45                 // String The method specified in defineFunction must be static:
     357: invokevirtual #31                 // Method java/lang/StringBuilder.append:(Ljava/lang/String;)Ljava/lang/StringBuilder;
     360: aload         5
     362: invokevirtual #46                 // Method java/lang/StringBuilder.append:(Ljava/lang/Object;)Ljava/lang/StringBuilder;
     365: invokevirtual #32                 // Method java/lang/StringBuilder.toString:()Ljava/lang/String;
     368: invokespecial #33                 // Method java/lang/NoSuchMethodException."<init>":(Ljava/lang/String;)V
     371: athrow
     372: aload_2
     373: ldc           #47                 // String
     375: invokevirtual #26                 // Method java/lang/String.equals:(Ljava/lang/Object;)Z
     378: ifeq          384
     381: aload         4
     383: astore_2
     384: aload_0
     385: getfield      #4                  // Field elManager:Ljakarta/el/ELManager;
     388: aload_1
     389: aload_2
     390: aload         5
     392: invokevirtual #48                 // Method jakarta/el/ELManager.mapFunction:(Ljava/lang/String;Ljava/lang/String;Ljava/lang/reflect/Method;)V
     395: return

  public void defineFunction(java.lang.String, java.lang.String, java.lang.reflect.Method) throws java.lang.NoSuchMethodException;
    Code:
       0: aload_1
       1: ifnull        12
       4: aload_2
       5: ifnull        12
       8: aload_3
       9: ifnonnull     22
      12: new           #15                 // class java/lang/NullPointerException
      15: dup
      16: ldc           #16                 // String Null argument for defineFunction
      18: invokespecial #17                 // Method java/lang/NullPointerException."<init>":(Ljava/lang/String;)V
      21: athrow
      22: aload_3
      23: invokevirtual #43                 // Method java/lang/reflect/Method.getModifiers:()I
      26: invokestatic  #44                 // Method java/lang/reflect/Modifier.isStatic:(I)Z
      29: ifne          59
      32: new           #27                 // class java/lang/NoSuchMethodException
      35: dup
      36: new           #28                 // class java/lang/StringBuilder
      39: dup
      40: invokespecial #29                 // Method java/lang/StringBuilder."<init>":()V
      43: ldc           #45                 // String The method specified in defineFunction must be static:
      45: invokevirtual #31                 // Method java/lang/StringBuilder.append:(Ljava/lang/String;)Ljava/lang/StringBuilder;
      48: aload_3
      49: invokevirtual #46                 // Method java/lang/StringBuilder.append:(Ljava/lang/Object;)Ljava/lang/StringBuilder;
      52: invokevirtual #32                 // Method java/lang/StringBuilder.toString:()Ljava/lang/String;
      55: invokespecial #33                 // Method java/lang/NoSuchMethodException."<init>":(Ljava/lang/String;)V
      58: athrow
      59: aload_2
      60: ldc           #47                 // String
      62: invokevirtual #26                 // Method java/lang/String.equals:(Ljava/lang/Object;)Z
      65: ifeq          73
      68: aload_3
      69: invokevirtual #25                 // Method java/lang/reflect/Method.getName:()Ljava/lang/String;
      72: astore_2
      73: aload_0
      74: getfield      #4                  // Field elManager:Ljakarta/el/ELManager;
      77: aload_1
      78: aload_2
      79: aload_3
      80: invokevirtual #48                 // Method jakarta/el/ELManager.mapFunction:(Ljava/lang/String;Ljava/lang/String;Ljava/lang/reflect/Method;)V
      83: return

  public void defineBean(java.lang.String, java.lang.Object);
    Code:
       0: aload_0
       1: getfield      #4                  // Field elManager:Ljakarta/el/ELManager;
       4: aload_1
       5: aload_2
       6: invokevirtual #49                 // Method jakarta/el/ELManager.defineBean:(Ljava/lang/String;Ljava/lang/Object;)Ljava/lang/Object;
       9: pop
      10: return

  private static java.lang.Class<?> toClass(java.lang.String, java.lang.ClassLoader) throws java.lang.ClassNotFoundException;
    Code:
       0: aconst_null
       1: astore_2
       2: aload_0
       3: bipush        91
       5: invokevirtual #23                 // Method java/lang/String.indexOf:(I)I
       8: istore_3
       9: iconst_0
      10: istore        4
      12: iload_3
      13: ifle          55
      16: iconst_0
      17: istore        5
      19: iload         5
      21: aload_0
      22: invokevirtual #50                 // Method java/lang/String.length:()I
      25: if_icmpge     48
      28: aload_0
      29: iload         5
      31: invokevirtual #51                 // Method java/lang/String.charAt:(I)C
      34: bipush        91
      36: if_icmpne     42
      39: iinc          4, 1
      42: iinc          5, 1
      45: goto          19
      48: aload_0
      49: iconst_0
      50: iload_3
      51: invokevirtual #35                 // Method java/lang/String.substring:(II)Ljava/lang/String;
      54: astore_0
      55: ldc           #52                 // String boolean
      57: aload_0
      58: invokevirtual #26                 // Method java/lang/String.equals:(Ljava/lang/Object;)Z
      61: ifeq          71
      64: getstatic     #53                 // Field java/lang/Boolean.TYPE:Ljava/lang/Class;
      67: astore_2
      68: goto          189
      71: ldc           #54                 // String char
      73: aload_0
      74: invokevirtual #26                 // Method java/lang/String.equals:(Ljava/lang/Object;)Z
      77: ifeq          87
      80: getstatic     #55                 // Field java/lang/Character.TYPE:Ljava/lang/Class;
      83: astore_2
      84: goto          189
      87: ldc           #56                 // String byte
      89: aload_0
      90: invokevirtual #26                 // Method java/lang/String.equals:(Ljava/lang/Object;)Z
      93: ifeq          103
      96: getstatic     #57                 // Field java/lang/Byte.TYPE:Ljava/lang/Class;
      99: astore_2
     100: goto          189
     103: ldc           #58                 // String short
     105: aload_0
     106: invokevirtual #26                 // Method java/lang/String.equals:(Ljava/lang/Object;)Z
     109: ifeq          119
     112: getstatic     #59                 // Field java/lang/Short.TYPE:Ljava/lang/Class;
     115: astore_2
     116: goto          189
     119: ldc           #60                 // String int
     121: aload_0
     122: invokevirtual #26                 // Method java/lang/String.equals:(Ljava/lang/Object;)Z
     125: ifeq          135
     128: getstatic     #61                 // Field java/lang/Integer.TYPE:Ljava/lang/Class;
     131: astore_2
     132: goto          189
     135: ldc           #62                 // String long
     137: aload_0
     138: invokevirtual #26                 // Method java/lang/String.equals:(Ljava/lang/Object;)Z
     141: ifeq          151
     144: getstatic     #63                 // Field java/lang/Long.TYPE:Ljava/lang/Class;
     147: astore_2
     148: goto          189
     151: ldc           #64                 // String float
     153: aload_0
     154: invokevirtual #26                 // Method java/lang/String.equals:(Ljava/lang/Object;)Z
     157: ifeq          167
     160: getstatic     #65                 // Field java/lang/Float.TYPE:Ljava/lang/Class;
     163: astore_2
     164: goto          189
     167: ldc           #66                 // String double
     169: aload_0
     170: invokevirtual #26                 // Method java/lang/String.equals:(Ljava/lang/Object;)Z
     173: ifeq          183
     176: getstatic     #67                 // Field java/lang/Double.TYPE:Ljava/lang/Class;
     179: astore_2
     180: goto          189
     183: aload_1
     184: aload_0
     185: invokevirtual #68                 // Method java/lang/ClassLoader.loadClass:(Ljava/lang/String;)Ljava/lang/Class;
     188: astore_2
     189: iload         4
     191: ifne          196
     194: aload_2
     195: areturn
     196: iload         4
     198: iconst_1
     199: if_icmpne     211
     202: aload_2
     203: iconst_1
     204: invokestatic  #69                 // Method java/lang/reflect/Array.newInstance:(Ljava/lang/Class;I)Ljava/lang/Object;
     207: invokevirtual #20                 // Method java/lang/Object.getClass:()Ljava/lang/Class;
     210: areturn
     211: aload_2
     212: iload         4
     214: newarray       int
     216: invokestatic  #70                 // Method java/lang/reflect/Array.newInstance:(Ljava/lang/Class;[I)Ljava/lang/Object;
     219: invokevirtual #20                 // Method java/lang/Object.getClass:()Ljava/lang/Class;
     222: areturn

  private java.lang.String bracket(java.lang.String);
    Code:
       0: new           #28                 // class java/lang/StringBuilder
       3: dup
       4: invokespecial #29                 // Method java/lang/StringBuilder."<init>":()V
       7: ldc           #71                 // String ${
       9: invokevirtual #31                 // Method java/lang/StringBuilder.append:(Ljava/lang/String;)Ljava/lang/StringBuilder;
      12: aload_1
      13: invokevirtual #31                 // Method java/lang/StringBuilder.append:(Ljava/lang/String;)Ljava/lang/StringBuilder;
      16: bipush        125
      18: invokevirtual #72                 // Method java/lang/StringBuilder.append:(C)Ljava/lang/StringBuilder;
      21: invokevirtual #32                 // Method java/lang/StringBuilder.toString:()Ljava/lang/String;
      24: areturn
}
