Compiled from "StandardELContext.java"
public class jakarta.el.StandardELContext extends jakarta.el.ELContext {
  private jakarta.el.ELResolver elResolver;

  private jakarta.el.CompositeELResolver customResolvers;

  private jakarta.el.ELResolver streamELResolver;

  private jakarta.el.FunctionMapper functionMapper;

  private java.util.Map<java.lang.String, java.lang.reflect.Method> initFunctionMap;

  private jakarta.el.VariableMapper variableMapper;

  private jakarta.el.ELContext delegate;

  private java.util.Map<java.lang.String, java.lang.Object> beans;

  public jakarta.el.StandardELContext(jakarta.el.ExpressionFactory);
    Code:
       0: aload_0
       1: invokespecial #2                  // Method jakarta/el/ELContext."<init>":()V
       4: aload_0
       5: new           #3                  // class java/util/HashMap
       8: dup
       9: invokespecial #4                  // Method java/util/HashMap."<init>":()V
      12: putfield      #1                  // Field beans:Ljava/util/Map;
      15: aload_0
      16: aload_1
      17: invokevirtual #5                  // Method jakarta/el/ExpressionFactory.getStreamELResolver:()Ljakarta/el/ELResolver;
      20: putfield      #6                  // Field streamELResolver:Ljakarta/el/ELResolver;
      23: aload_0
      24: aload_1
      25: invokevirtual #7                  // Method jakarta/el/ExpressionFactory.getInitFunctionMap:()Ljava/util/Map;
      28: putfield      #8                  // Field initFunctionMap:Ljava/util/Map;
      31: return

  public jakarta.el.StandardELContext(jakarta.el.ELContext);
    Code:
       0: aload_0
       1: invokespecial #2                  // Method jakarta/el/ELContext."<init>":()V
       4: aload_0
       5: new           #3                  // class java/util/HashMap
       8: dup
       9: invokespecial #4                  // Method java/util/HashMap."<init>":()V
      12: putfield      #1                  // Field beans:Ljava/util/Map;
      15: aload_0
      16: aload_1
      17: putfield      #9                  // Field delegate:Ljakarta/el/ELContext;
      20: new           #10                 // class jakarta/el/CompositeELResolver
      23: dup
      24: invokespecial #11                 // Method jakarta/el/CompositeELResolver."<init>":()V
      27: astore_2
      28: aload_2
      29: new           #12                 // class jakarta/el/BeanNameELResolver
      32: dup
      33: new           #13                 // class jakarta/el/StandardELContext$LocalBeanNameResolver
      36: dup
      37: aload_0
      38: aconst_null
      39: invokespecial #14                 // Method jakarta/el/StandardELContext$LocalBeanNameResolver."<init>":(Ljakarta/el/StandardELContext;Ljakarta/el/StandardELContext$1;)V
      42: invokespecial #15                 // Method jakarta/el/BeanNameELResolver."<init>":(Ljakarta/el/BeanNameResolver;)V
      45: invokevirtual #16                 // Method jakarta/el/CompositeELResolver.add:(Ljakarta/el/ELResolver;)V
      48: aload_0
      49: new           #10                 // class jakarta/el/CompositeELResolver
      52: dup
      53: invokespecial #11                 // Method jakarta/el/CompositeELResolver."<init>":()V
      56: putfield      #17                 // Field customResolvers:Ljakarta/el/CompositeELResolver;
      59: aload_2
      60: aload_0
      61: getfield      #17                 // Field customResolvers:Ljakarta/el/CompositeELResolver;
      64: invokevirtual #16                 // Method jakarta/el/CompositeELResolver.add:(Ljakarta/el/ELResolver;)V
      67: aload_2
      68: aload_1
      69: invokevirtual #18                 // Method jakarta/el/ELContext.getELResolver:()Ljakarta/el/ELResolver;
      72: invokevirtual #16                 // Method jakarta/el/CompositeELResolver.add:(Ljakarta/el/ELResolver;)V
      75: aload_0
      76: aload_2
      77: putfield      #19                 // Field elResolver:Ljakarta/el/ELResolver;
      80: aload_0
      81: aload_1
      82: invokevirtual #20                 // Method jakarta/el/ELContext.getFunctionMapper:()Ljakarta/el/FunctionMapper;
      85: putfield      #21                 // Field functionMapper:Ljakarta/el/FunctionMapper;
      88: aload_0
      89: aload_1
      90: invokevirtual #22                 // Method jakarta/el/ELContext.getVariableMapper:()Ljakarta/el/VariableMapper;
      93: putfield      #23                 // Field variableMapper:Ljakarta/el/VariableMapper;
      96: aload_0
      97: aload_1
      98: invokevirtual #24                 // Method jakarta/el/ELContext.getLocale:()Ljava/util/Locale;
     101: invokevirtual #25                 // Method setLocale:(Ljava/util/Locale;)V
     104: return

  public void putContext(java.lang.Class<?>, java.lang.Object);
    Code:
       0: aload_0
       1: getfield      #9                  // Field delegate:Ljakarta/el/ELContext;
       4: ifnull        19
       7: aload_0
       8: getfield      #9                  // Field delegate:Ljakarta/el/ELContext;
      11: aload_1
      12: aload_2
      13: invokevirtual #26                 // Method jakarta/el/ELContext.putContext:(Ljava/lang/Class;Ljava/lang/Object;)V
      16: goto          25
      19: aload_0
      20: aload_1
      21: aload_2
      22: invokespecial #26                 // Method jakarta/el/ELContext.putContext:(Ljava/lang/Class;Ljava/lang/Object;)V
      25: return

  public java.lang.Object getContext(java.lang.Class<?>);
    Code:
       0: aload_0
       1: getfield      #9                  // Field delegate:Ljakarta/el/ELContext;
       4: ifnonnull     13
       7: aload_0
       8: aload_1
       9: invokespecial #27                 // Method jakarta/el/ELContext.getContext:(Ljava/lang/Class;)Ljava/lang/Object;
      12: areturn
      13: aload_0
      14: getfield      #9                  // Field delegate:Ljakarta/el/ELContext;
      17: aload_1
      18: invokevirtual #27                 // Method jakarta/el/ELContext.getContext:(Ljava/lang/Class;)Ljava/lang/Object;
      21: areturn

  public jakarta.el.ELResolver getELResolver();
    Code:
       0: aload_0
       1: getfield      #19                 // Field elResolver:Ljakarta/el/ELResolver;
       4: ifnonnull     140
       7: new           #10                 // class jakarta/el/CompositeELResolver
      10: dup
      11: invokespecial #11                 // Method jakarta/el/CompositeELResolver."<init>":()V
      14: astore_1
      15: aload_1
      16: new           #12                 // class jakarta/el/BeanNameELResolver
      19: dup
      20: new           #13                 // class jakarta/el/StandardELContext$LocalBeanNameResolver
      23: dup
      24: aload_0
      25: aconst_null
      26: invokespecial #14                 // Method jakarta/el/StandardELContext$LocalBeanNameResolver."<init>":(Ljakarta/el/StandardELContext;Ljakarta/el/StandardELContext$1;)V
      29: invokespecial #15                 // Method jakarta/el/BeanNameELResolver."<init>":(Ljakarta/el/BeanNameResolver;)V
      32: invokevirtual #16                 // Method jakarta/el/CompositeELResolver.add:(Ljakarta/el/ELResolver;)V
      35: aload_0
      36: new           #10                 // class jakarta/el/CompositeELResolver
      39: dup
      40: invokespecial #11                 // Method jakarta/el/CompositeELResolver."<init>":()V
      43: putfield      #17                 // Field customResolvers:Ljakarta/el/CompositeELResolver;
      46: aload_1
      47: aload_0
      48: getfield      #17                 // Field customResolvers:Ljakarta/el/CompositeELResolver;
      51: invokevirtual #16                 // Method jakarta/el/CompositeELResolver.add:(Ljakarta/el/ELResolver;)V
      54: aload_0
      55: getfield      #6                  // Field streamELResolver:Ljakarta/el/ELResolver;
      58: ifnull        69
      61: aload_1
      62: aload_0
      63: getfield      #6                  // Field streamELResolver:Ljakarta/el/ELResolver;
      66: invokevirtual #16                 // Method jakarta/el/CompositeELResolver.add:(Ljakarta/el/ELResolver;)V
      69: aload_1
      70: new           #28                 // class jakarta/el/StaticFieldELResolver
      73: dup
      74: invokespecial #29                 // Method jakarta/el/StaticFieldELResolver."<init>":()V
      77: invokevirtual #16                 // Method jakarta/el/CompositeELResolver.add:(Ljakarta/el/ELResolver;)V
      80: aload_1
      81: new           #30                 // class jakarta/el/MapELResolver
      84: dup
      85: invokespecial #31                 // Method jakarta/el/MapELResolver."<init>":()V
      88: invokevirtual #16                 // Method jakarta/el/CompositeELResolver.add:(Ljakarta/el/ELResolver;)V
      91: aload_1
      92: new           #32                 // class jakarta/el/ResourceBundleELResolver
      95: dup
      96: invokespecial #33                 // Method jakarta/el/ResourceBundleELResolver."<init>":()V
      99: invokevirtual #16                 // Method jakarta/el/CompositeELResolver.add:(Ljakarta/el/ELResolver;)V
     102: aload_1
     103: new           #34                 // class jakarta/el/ListELResolver
     106: dup
     107: invokespecial #35                 // Method jakarta/el/ListELResolver."<init>":()V
     110: invokevirtual #16                 // Method jakarta/el/CompositeELResolver.add:(Ljakarta/el/ELResolver;)V
     113: aload_1
     114: new           #36                 // class jakarta/el/ArrayELResolver
     117: dup
     118: invokespecial #37                 // Method jakarta/el/ArrayELResolver."<init>":()V
     121: invokevirtual #16                 // Method jakarta/el/CompositeELResolver.add:(Ljakarta/el/ELResolver;)V
     124: aload_1
     125: new           #38                 // class jakarta/el/BeanELResolver
     128: dup
     129: invokespecial #39                 // Method jakarta/el/BeanELResolver."<init>":()V
     132: invokevirtual #16                 // Method jakarta/el/CompositeELResolver.add:(Ljakarta/el/ELResolver;)V
     135: aload_0
     136: aload_1
     137: putfield      #19                 // Field elResolver:Ljakarta/el/ELResolver;
     140: aload_0
     141: getfield      #19                 // Field elResolver:Ljakarta/el/ELResolver;
     144: areturn

  public void addELResolver(jakarta.el.ELResolver);
    Code:
       0: aload_0
       1: invokevirtual #40                 // Method getELResolver:()Ljakarta/el/ELResolver;
       4: pop
       5: aload_0
       6: getfield      #17                 // Field customResolvers:Ljakarta/el/CompositeELResolver;
       9: aload_1
      10: invokevirtual #16                 // Method jakarta/el/CompositeELResolver.add:(Ljakarta/el/ELResolver;)V
      13: return

  java.util.Map<java.lang.String, java.lang.Object> getBeans();
    Code:
       0: aload_0
       1: getfield      #1                  // Field beans:Ljava/util/Map;
       4: areturn

  public jakarta.el.FunctionMapper getFunctionMapper();
    Code:
       0: aload_0
       1: getfield      #21                 // Field functionMapper:Ljakarta/el/FunctionMapper;
       4: ifnonnull     22
       7: aload_0
       8: new           #41                 // class jakarta/el/StandardELContext$DefaultFunctionMapper
      11: dup
      12: aload_0
      13: getfield      #8                  // Field initFunctionMap:Ljava/util/Map;
      16: invokespecial #42                 // Method jakarta/el/StandardELContext$DefaultFunctionMapper."<init>":(Ljava/util/Map;)V
      19: putfield      #21                 // Field functionMapper:Ljakarta/el/FunctionMapper;
      22: aload_0
      23: getfield      #21                 // Field functionMapper:Ljakarta/el/FunctionMapper;
      26: areturn

  public jakarta.el.VariableMapper getVariableMapper();
    Code:
       0: aload_0
       1: getfield      #23                 // Field variableMapper:Ljakarta/el/VariableMapper;
       4: ifnonnull     19
       7: aload_0
       8: new           #43                 // class jakarta/el/StandardELContext$DefaultVariableMapper
      11: dup
      12: aconst_null
      13: invokespecial #44                 // Method jakarta/el/StandardELContext$DefaultVariableMapper."<init>":(Ljakarta/el/StandardELContext$1;)V
      16: putfield      #23                 // Field variableMapper:Ljakarta/el/VariableMapper;
      19: aload_0
      20: getfield      #23                 // Field variableMapper:Ljakarta/el/VariableMapper;
      23: areturn

  static java.util.Map access$200(jakarta.el.StandardELContext);
    Code:
       0: aload_0
       1: getfield      #1                  // Field beans:Ljava/util/Map;
       4: areturn
}
