Compiled from "UriUtils.java"
public abstract class org.springframework.data.rest.webmvc.util.UriUtils {
  private static org.springframework.hateoas.core.AnnotationMappingDiscoverer DISCOVERER;

  private org.springframework.data.rest.webmvc.util.UriUtils();
    Code:
       0: aload_0
       1: invokespecial #1                  // Method java/lang/Object."<init>":()V
       4: return

  public static java.lang.String findMappingVariable(java.lang.String, java.lang.reflect.Method, java.lang.String);
    Code:
       0: aload_0
       1: ldc           #2                  // String Variable name must not be null or empty!
       3: invokestatic  #3                  // Method org/springframework/util/Assert.hasText:(Ljava/lang/String;Ljava/lang/String;)V
       6: aload_1
       7: ldc           #4                  // String Method must not be null!
       9: invokestatic  #5                  // Method org/springframework/util/Assert.notNull:(Ljava/lang/Object;Ljava/lang/String;)V
      12: getstatic     #6                  // Field DISCOVERER:Lorg/springframework/hateoas/core/AnnotationMappingDiscoverer;
      15: aload_1
      16: invokevirtual #7                  // Method org/springframework/hateoas/core/AnnotationMappingDiscoverer.getMapping:(Ljava/lang/reflect/Method;)Ljava/lang/String;
      19: astore_3
      20: new           #8                  // class org/springframework/web/util/UriTemplate
      23: dup
      24: aload_3
      25: invokespecial #9                  // Method org/springframework/web/util/UriTemplate."<init>":(Ljava/lang/String;)V
      28: aload_2
      29: invokevirtual #10                 // Method org/springframework/web/util/UriTemplate.match:(Ljava/lang/String;)Ljava/util/Map;
      32: astore        4
      34: aload         4
      36: aload_0
      37: invokeinterface #11,  2           // InterfaceMethod java/util/Map.get:(Ljava/lang/Object;)Ljava/lang/Object;
      42: checkcast     #12                 // class java/lang/String
      45: astore        5
      47: aload         5
      49: ifnull        55
      52: aload         5
      54: areturn
      55: aconst_null
      56: areturn

  public static java.util.List<java.lang.String> getPathSegments(java.lang.reflect.Method);
    Code:
       0: aload_0
       1: ldc           #4                  // String Method must not be null!
       3: invokestatic  #5                  // Method org/springframework/util/Assert.notNull:(Ljava/lang/Object;Ljava/lang/String;)V
       6: getstatic     #6                  // Field DISCOVERER:Lorg/springframework/hateoas/core/AnnotationMappingDiscoverer;
       9: aload_0
      10: invokevirtual #13                 // Method java/lang/reflect/Method.getDeclaringClass:()Ljava/lang/Class;
      13: aload_0
      14: invokevirtual #14                 // Method org/springframework/hateoas/core/AnnotationMappingDiscoverer.getMapping:(Ljava/lang/Class;Ljava/lang/reflect/Method;)Ljava/lang/String;
      17: astore_1
      18: aload_1
      19: invokestatic  #15                 // Method org/springframework/web/util/UriComponentsBuilder.fromPath:(Ljava/lang/String;)Lorg/springframework/web/util/UriComponentsBuilder;
      22: invokevirtual #16                 // Method org/springframework/web/util/UriComponentsBuilder.build:()Lorg/springframework/web/util/UriComponents;
      25: invokevirtual #17                 // Method org/springframework/web/util/UriComponents.getPathSegments:()Ljava/util/List;
      28: areturn

  static {};
    Code:
       0: new           #18                 // class org/springframework/hateoas/core/AnnotationMappingDiscoverer
       3: dup
       4: ldc           #19                 // class org/springframework/web/bind/annotation/RequestMapping
       6: invokespecial #20                 // Method org/springframework/hateoas/core/AnnotationMappingDiscoverer."<init>":(Ljava/lang/Class;)V
       9: putstatic     #6                  // Field DISCOVERER:Lorg/springframework/hateoas/core/AnnotationMappingDiscoverer;
      12: return
}
