Compiled from "SchemaBuilderImpl.java"
class org.kohsuke.rngom.binary.SchemaBuilderImpl$ValidationContextImpl implements org.relaxng.datatype.ValidationContext {
  private org.relaxng.datatype.ValidationContext vc;

  private java.lang.String ns;

  org.kohsuke.rngom.binary.SchemaBuilderImpl$ValidationContextImpl(org.relaxng.datatype.ValidationContext, java.lang.String);
    Code:
       0: aload_0
       1: invokespecial #1                  // Method java/lang/Object."<init>":()V
       4: aload_0
       5: aload_1
       6: putfield      #2                  // Field vc:Lorg/relaxng/datatype/ValidationContext;
       9: aload_0
      10: aload_2
      11: invokevirtual #3                  // Method java/lang/String.length:()I
      14: ifne          21
      17: aconst_null
      18: goto          22
      21: aload_2
      22: putfield      #4                  // Field ns:Ljava/lang/String;
      25: return

  public java.lang.String resolveNamespacePrefix(java.lang.String);
    Code:
       0: aload_1
       1: invokevirtual #3                  // Method java/lang/String.length:()I
       4: ifne          14
       7: aload_0
       8: getfield      #4                  // Field ns:Ljava/lang/String;
      11: goto          24
      14: aload_0
      15: getfield      #2                  // Field vc:Lorg/relaxng/datatype/ValidationContext;
      18: aload_1
      19: invokeinterface #5,  2            // InterfaceMethod org/relaxng/datatype/ValidationContext.resolveNamespacePrefix:(Ljava/lang/String;)Ljava/lang/String;
      24: areturn

  public java.lang.String getBaseUri();
    Code:
       0: aload_0
       1: getfield      #2                  // Field vc:Lorg/relaxng/datatype/ValidationContext;
       4: invokeinterface #6,  1            // InterfaceMethod org/relaxng/datatype/ValidationContext.getBaseUri:()Ljava/lang/String;
       9: areturn

  public boolean isUnparsedEntity(java.lang.String);
    Code:
       0: aload_0
       1: getfield      #2                  // Field vc:Lorg/relaxng/datatype/ValidationContext;
       4: aload_1
       5: invokeinterface #7,  2            // InterfaceMethod org/relaxng/datatype/ValidationContext.isUnparsedEntity:(Ljava/lang/String;)Z
      10: ireturn

  public boolean isNotation(java.lang.String);
    Code:
       0: aload_0
       1: getfield      #2                  // Field vc:Lorg/relaxng/datatype/ValidationContext;
       4: aload_1
       5: invokeinterface #8,  2            // InterfaceMethod org/relaxng/datatype/ValidationContext.isNotation:(Ljava/lang/String;)Z
      10: ireturn
}
