Compiled from "LatencyMinimizingServerSelector.java"
public class com.mongodb.selector.LatencyMinimizingServerSelector implements com.mongodb.selector.ServerSelector {
  private final long acceptableLatencyDifferenceNanos;

  public com.mongodb.selector.LatencyMinimizingServerSelector(long, java.util.concurrent.TimeUnit);
    Code:
       0: aload_0
       1: invokespecial #1                  // Method java/lang/Object."<init>":()V
       4: aload_0
       5: getstatic     #2                  // Field java/util/concurrent/TimeUnit.NANOSECONDS:Ljava/util/concurrent/TimeUnit;
       8: lload_1
       9: aload_3
      10: invokevirtual #3                  // Method java/util/concurrent/TimeUnit.convert:(JLjava/util/concurrent/TimeUnit;)J
      13: putfield      #4                  // Field acceptableLatencyDifferenceNanos:J
      16: return

  public long getAcceptableLatencyDifference(java.util.concurrent.TimeUnit);
    Code:
       0: aload_1
       1: aload_0
       2: getfield      #4                  // Field acceptableLatencyDifferenceNanos:J
       5: getstatic     #2                  // Field java/util/concurrent/TimeUnit.NANOSECONDS:Ljava/util/concurrent/TimeUnit;
       8: invokevirtual #3                  // Method java/util/concurrent/TimeUnit.convert:(JLjava/util/concurrent/TimeUnit;)J
      11: lreturn

  public java.util.List<com.mongodb.connection.ServerDescription> select(com.mongodb.connection.ClusterDescription);
    Code:
       0: aload_1
       1: invokevirtual #5                  // Method com/mongodb/connection/ClusterDescription.getConnectionMode:()Lcom/mongodb/connection/ClusterConnectionMode;
       4: getstatic     #6                  // Field com/mongodb/connection/ClusterConnectionMode.MULTIPLE:Lcom/mongodb/connection/ClusterConnectionMode;
       7: if_acmpeq     15
      10: aload_1
      11: invokevirtual #7                  // Method com/mongodb/connection/ClusterDescription.getAny:()Ljava/util/List;
      14: areturn
      15: aload_0
      16: aload_1
      17: invokevirtual #7                  // Method com/mongodb/connection/ClusterDescription.getAny:()Ljava/util/List;
      20: aload_0
      21: aload_1
      22: invokevirtual #8                  // Method com/mongodb/connection/ClusterDescription.getServerDescriptions:()Ljava/util/List;
      25: invokespecial #9                  // Method getFastestRoundTripTimeNanos:(Ljava/util/List;)J
      28: invokespecial #10                 // Method getServersWithAcceptableLatencyDifference:(Ljava/util/List;J)Ljava/util/List;
      31: areturn

  public java.lang.String toString();
    Code:
       0: new           #11                 // class java/lang/StringBuilder
       3: dup
       4: invokespecial #12                 // Method java/lang/StringBuilder."<init>":()V
       7: ldc           #13                 // String LatencyMinimizingServerSelector{acceptableLatencyDifference=
       9: invokevirtual #14                 // Method java/lang/StringBuilder.append:(Ljava/lang/String;)Ljava/lang/StringBuilder;
      12: getstatic     #15                 // Field java/util/concurrent/TimeUnit.MILLISECONDS:Ljava/util/concurrent/TimeUnit;
      15: aload_0
      16: getfield      #4                  // Field acceptableLatencyDifferenceNanos:J
      19: getstatic     #2                  // Field java/util/concurrent/TimeUnit.NANOSECONDS:Ljava/util/concurrent/TimeUnit;
      22: invokevirtual #3                  // Method java/util/concurrent/TimeUnit.convert:(JLjava/util/concurrent/TimeUnit;)J
      25: invokevirtual #16                 // Method java/lang/StringBuilder.append:(J)Ljava/lang/StringBuilder;
      28: ldc           #17                 // String  ms
      30: invokevirtual #14                 // Method java/lang/StringBuilder.append:(Ljava/lang/String;)Ljava/lang/StringBuilder;
      33: bipush        125
      35: invokevirtual #18                 // Method java/lang/StringBuilder.append:(C)Ljava/lang/StringBuilder;
      38: invokevirtual #19                 // Method java/lang/StringBuilder.toString:()Ljava/lang/String;
      41: areturn

  private long getFastestRoundTripTimeNanos(java.util.List<com.mongodb.connection.ServerDescription>);
    Code:
       0: ldc2_w        #21                 // long 9223372036854775807l
       3: lstore_2
       4: aload_1
       5: invokeinterface #23,  1           // InterfaceMethod java/util/List.iterator:()Ljava/util/Iterator;
      10: astore        4
      12: aload         4
      14: invokeinterface #24,  1           // InterfaceMethod java/util/Iterator.hasNext:()Z
      19: ifeq          64
      22: aload         4
      24: invokeinterface #25,  1           // InterfaceMethod java/util/Iterator.next:()Ljava/lang/Object;
      29: checkcast     #26                 // class com/mongodb/connection/ServerDescription
      32: astore        5
      34: aload         5
      36: invokevirtual #27                 // Method com/mongodb/connection/ServerDescription.isOk:()Z
      39: ifne          45
      42: goto          12
      45: aload         5
      47: invokevirtual #28                 // Method com/mongodb/connection/ServerDescription.getRoundTripTimeNanos:()J
      50: lload_2
      51: lcmp
      52: ifge          61
      55: aload         5
      57: invokevirtual #28                 // Method com/mongodb/connection/ServerDescription.getRoundTripTimeNanos:()J
      60: lstore_2
      61: goto          12
      64: lload_2
      65: lreturn

  private java.util.List<com.mongodb.connection.ServerDescription> getServersWithAcceptableLatencyDifference(java.util.List<com.mongodb.connection.ServerDescription>, long);
    Code:
       0: new           #29                 // class java/util/ArrayList
       3: dup
       4: aload_1
       5: invokeinterface #30,  1           // InterfaceMethod java/util/List.size:()I
      10: invokespecial #31                 // Method java/util/ArrayList."<init>":(I)V
      13: astore        4
      15: aload_1
      16: invokeinterface #23,  1           // InterfaceMethod java/util/List.iterator:()Ljava/util/Iterator;
      21: astore        5
      23: aload         5
      25: invokeinterface #24,  1           // InterfaceMethod java/util/Iterator.hasNext:()Z
      30: ifeq          84
      33: aload         5
      35: invokeinterface #25,  1           // InterfaceMethod java/util/Iterator.next:()Ljava/lang/Object;
      40: checkcast     #26                 // class com/mongodb/connection/ServerDescription
      43: astore        6
      45: aload         6
      47: invokevirtual #27                 // Method com/mongodb/connection/ServerDescription.isOk:()Z
      50: ifne          56
      53: goto          23
      56: aload         6
      58: invokevirtual #28                 // Method com/mongodb/connection/ServerDescription.getRoundTripTimeNanos:()J
      61: aload_0
      62: getfield      #4                  // Field acceptableLatencyDifferenceNanos:J
      65: lsub
      66: lload_2
      67: lcmp
      68: ifgt          81
      71: aload         4
      73: aload         6
      75: invokeinterface #32,  2           // InterfaceMethod java/util/List.add:(Ljava/lang/Object;)Z
      80: pop
      81: goto          23
      84: aload         4
      86: areturn
}
