Compiled from "HttpRequestWrapper.java"
public class org.springframework.http.client.support.HttpRequestWrapper implements org.springframework.http.HttpRequest {
  private final org.springframework.http.HttpRequest request;

  public org.springframework.http.client.support.HttpRequestWrapper(org.springframework.http.HttpRequest);
    Code:
       0: aload_0
       1: invokespecial #1                  // Method java/lang/Object."<init>":()V
       4: aload_1
       5: ldc           #2                  // String HttpRequest must not be null
       7: invokestatic  #3                  // Method org/springframework/util/Assert.notNull:(Ljava/lang/Object;Ljava/lang/String;)V
      10: aload_0
      11: aload_1
      12: putfield      #4                  // Field request:Lorg/springframework/http/HttpRequest;
      15: return

  public org.springframework.http.HttpRequest getRequest();
    Code:
       0: aload_0
       1: getfield      #4                  // Field request:Lorg/springframework/http/HttpRequest;
       4: areturn

  public org.springframework.http.HttpMethod getMethod();
    Code:
       0: aload_0
       1: getfield      #4                  // Field request:Lorg/springframework/http/HttpRequest;
       4: invokeinterface #5,  1            // InterfaceMethod org/springframework/http/HttpRequest.getMethod:()Lorg/springframework/http/HttpMethod;
       9: areturn

  public java.net.URI getURI();
    Code:
       0: aload_0
       1: getfield      #4                  // Field request:Lorg/springframework/http/HttpRequest;
       4: invokeinterface #6,  1            // InterfaceMethod org/springframework/http/HttpRequest.getURI:()Ljava/net/URI;
       9: areturn

  public org.springframework.http.HttpHeaders getHeaders();
    Code:
       0: aload_0
       1: getfield      #4                  // Field request:Lorg/springframework/http/HttpRequest;
       4: invokeinterface #7,  1            // InterfaceMethod org/springframework/http/HttpRequest.getHeaders:()Lorg/springframework/http/HttpHeaders;
       9: areturn
}
