Compiled from "ZipCentralDir.java"
public class sbt.internal.inc.zip.ZipCentralDir {
  private final byte[] cen;

  private sbt.internal.inc.zip.ZipCentralDir$END end;

  private final java.nio.channels.SeekableByteChannel ch;

  private java.util.LinkedHashMap<sbt.internal.inc.zip.ZipCentralDir$IndexNode, sbt.internal.inc.zip.ZipCentralDir$IndexNode> inodes;

  private static byte[] ROOTPATH;

  private final sbt.internal.inc.zip.ZipCentralDir$IndexNode LOOKUPKEY;

  private java.util.List<sbt.internal.inc.zip.ZipCentralDir$Entry> elist;

  private static final boolean isWindows;

  public sbt.internal.inc.zip.ZipCentralDir(java.nio.file.Path) throws java.io.IOException;
    Code:
       0: aload_0
       1: invokespecial #6                  // Method java/lang/Object."<init>":()V
       4: aload_0
       5: aconst_null
       6: invokestatic  #7                  // Method sbt/internal/inc/zip/ZipCentralDir$IndexNode.keyOf:([B)Lsbt/internal/inc/zip/ZipCentralDir$IndexNode;
       9: putfield      #8                  // Field LOOKUPKEY:Lsbt/internal/inc/zip/ZipCentralDir$IndexNode;
      12: aload_0
      13: aload_1
      14: iconst_1
      15: anewarray     #9                  // class java/nio/file/OpenOption
      18: dup
      19: iconst_0
      20: getstatic     #10                 // Field java/nio/file/StandardOpenOption.READ:Ljava/nio/file/StandardOpenOption;
      23: aastore
      24: invokestatic  #11                 // Method java/nio/file/Files.newByteChannel:(Ljava/nio/file/Path;[Ljava/nio/file/OpenOption;)Ljava/nio/channels/SeekableByteChannel;
      27: putfield      #12                 // Field ch:Ljava/nio/channels/SeekableByteChannel;
      30: aload_0
      31: aload_0
      32: invokespecial #13                 // Method initCEN:()[B
      35: putfield      #5                  // Field cen:[B
      38: aload_0
      39: aload_0
      40: invokespecial #14                 // Method readEntries:()Ljava/util/List;
      43: putfield      #15                 // Field elist:Ljava/util/List;
      46: aload_0
      47: getfield      #12                 // Field ch:Ljava/nio/channels/SeekableByteChannel;
      50: invokeinterface #16,  1           // InterfaceMethod java/nio/channels/SeekableByteChannel.close:()V
      55: return

  public long getCentralDirStart();
    Code:
       0: aload_0
       1: getfield      #17                 // Field end:Lsbt/internal/inc/zip/ZipCentralDir$END;
       4: getfield      #18                 // Field sbt/internal/inc/zip/ZipCentralDir$END.cenoff:J
       7: lreturn

  public void setCentralDirStart(long);
    Code:
       0: aload_0
       1: getfield      #17                 // Field end:Lsbt/internal/inc/zip/ZipCentralDir$END;
       4: lload_1
       5: putfield      #18                 // Field sbt/internal/inc/zip/ZipCentralDir$END.cenoff:J
       8: return

  public java.util.List<sbt.internal.inc.zip.ZipCentralDir$Entry> getHeaders();
    Code:
       0: aload_0
       1: getfield      #15                 // Field elist:Ljava/util/List;
       4: areturn

  public void setHeaders(java.util.List<sbt.internal.inc.zip.ZipCentralDir$Entry>);
    Code:
       0: aload_0
       1: aload_1
       2: putfield      #15                 // Field elist:Ljava/util/List;
       5: return

  public void dump(java.io.OutputStream) throws java.io.IOException;
    Code:
       0: lconst_0
       1: lstore_2
       2: aload_0
       3: getfield      #15                 // Field elist:Ljava/util/List;
       6: invokeinterface #19,  1           // InterfaceMethod java/util/List.iterator:()Ljava/util/Iterator;
      11: astore        4
      13: aload         4
      15: invokeinterface #20,  1           // InterfaceMethod java/util/Iterator.hasNext:()Z
      20: ifeq          48
      23: aload         4
      25: invokeinterface #21,  1           // InterfaceMethod java/util/Iterator.next:()Ljava/lang/Object;
      30: checkcast     #22                 // class sbt/internal/inc/zip/ZipCentralDir$Entry
      33: astore        5
      35: lload_2
      36: aload         5
      38: aload_1
      39: invokevirtual #23                 // Method sbt/internal/inc/zip/ZipCentralDir$Entry.writeCEN:(Ljava/io/OutputStream;)I
      42: i2l
      43: ladd
      44: lstore_2
      45: goto          13
      48: aload_0
      49: getfield      #17                 // Field end:Lsbt/internal/inc/zip/ZipCentralDir$END;
      52: aload_0
      53: getfield      #15                 // Field elist:Ljava/util/List;
      56: invokeinterface #24,  1           // InterfaceMethod java/util/List.size:()I
      61: putfield      #25                 // Field sbt/internal/inc/zip/ZipCentralDir$END.centot:I
      64: aload_0
      65: getfield      #17                 // Field end:Lsbt/internal/inc/zip/ZipCentralDir$END;
      68: lload_2
      69: putfield      #26                 // Field sbt/internal/inc/zip/ZipCentralDir$END.cenlen:J
      72: aload_0
      73: getfield      #17                 // Field end:Lsbt/internal/inc/zip/ZipCentralDir$END;
      76: aload_1
      77: lload_2
      78: invokevirtual #27                 // Method sbt/internal/inc/zip/ZipCentralDir$END.write:(Ljava/io/OutputStream;J)V
      81: return

  private java.util.List<sbt.internal.inc.zip.ZipCentralDir$Entry> readEntries() throws java.io.IOException;
    Code:
       0: new           #28                 // class java/util/ArrayList
       3: dup
       4: invokespecial #29                 // Method java/util/ArrayList."<init>":()V
       7: astore_1
       8: aload_0
       9: getfield      #30                 // Field inodes:Ljava/util/LinkedHashMap;
      12: invokevirtual #31                 // Method java/util/LinkedHashMap.values:()Ljava/util/Collection;
      15: invokeinterface #32,  1           // InterfaceMethod java/util/Collection.iterator:()Ljava/util/Iterator;
      20: astore_2
      21: aload_2
      22: invokeinterface #20,  1           // InterfaceMethod java/util/Iterator.hasNext:()Z
      27: ifeq          73
      30: aload_2
      31: invokeinterface #21,  1           // InterfaceMethod java/util/Iterator.next:()Ljava/lang/Object;
      36: checkcast     #33                 // class sbt/internal/inc/zip/ZipCentralDir$IndexNode
      39: astore_3
      40: aload_3
      41: getfield      #34                 // Field sbt/internal/inc/zip/ZipCentralDir$IndexNode.pos:I
      44: iconst_m1
      45: if_icmpne     51
      48: goto          21
      51: aload_0
      52: aload_3
      53: getfield      #34                 // Field sbt/internal/inc/zip/ZipCentralDir$IndexNode.pos:I
      56: invokestatic  #35                 // Method sbt/internal/inc/zip/ZipCentralDir$Entry.readCEN:(Lsbt/internal/inc/zip/ZipCentralDir;I)Lsbt/internal/inc/zip/ZipCentralDir$Entry;
      59: astore        4
      61: aload_1
      62: aload         4
      64: invokeinterface #36,  2           // InterfaceMethod java/util/List.add:(Ljava/lang/Object;)Z
      69: pop
      70: goto          21
      73: aload_1
      74: areturn

  private byte[] initCEN() throws java.io.IOException;
    Code:
       0: aload_0
       1: aload_0
       2: invokespecial #37                 // Method findEND:()Lsbt/internal/inc/zip/ZipCentralDir$END;
       5: putfield      #17                 // Field end:Lsbt/internal/inc/zip/ZipCentralDir$END;
       8: aload_0
       9: getfield      #17                 // Field end:Lsbt/internal/inc/zip/ZipCentralDir$END;
      12: getfield      #38                 // Field sbt/internal/inc/zip/ZipCentralDir$END.endpos:J
      15: lconst_0
      16: lcmp
      17: ifne          41
      20: aload_0
      21: new           #39                 // class java/util/LinkedHashMap
      24: dup
      25: bipush        10
      27: invokespecial #40                 // Method java/util/LinkedHashMap."<init>":(I)V
      30: putfield      #30                 // Field inodes:Ljava/util/LinkedHashMap;
      33: lconst_0
      34: lstore_1
      35: aload_0
      36: invokespecial #41                 // Method buildNodeTree:()V
      39: aconst_null
      40: areturn
      41: aload_0
      42: getfield      #17                 // Field end:Lsbt/internal/inc/zip/ZipCentralDir$END;
      45: getfield      #26                 // Field sbt/internal/inc/zip/ZipCentralDir$END.cenlen:J
      48: aload_0
      49: getfield      #17                 // Field end:Lsbt/internal/inc/zip/ZipCentralDir$END;
      52: getfield      #38                 // Field sbt/internal/inc/zip/ZipCentralDir$END.endpos:J
      55: lcmp
      56: ifle          64
      59: ldc           #42                 // String invalid END header (bad central directory size)
      61: invokestatic  #4                  // Method zerror:(Ljava/lang/String;)V
      64: aload_0
      65: getfield      #17                 // Field end:Lsbt/internal/inc/zip/ZipCentralDir$END;
      68: getfield      #38                 // Field sbt/internal/inc/zip/ZipCentralDir$END.endpos:J
      71: aload_0
      72: getfield      #17                 // Field end:Lsbt/internal/inc/zip/ZipCentralDir$END;
      75: getfield      #26                 // Field sbt/internal/inc/zip/ZipCentralDir$END.cenlen:J
      78: lsub
      79: lstore_3
      80: lload_3
      81: aload_0
      82: getfield      #17                 // Field end:Lsbt/internal/inc/zip/ZipCentralDir$END;
      85: getfield      #18                 // Field sbt/internal/inc/zip/ZipCentralDir$END.cenoff:J
      88: lsub
      89: lstore_1
      90: lload_1
      91: lconst_0
      92: lcmp
      93: ifge          101
      96: ldc           #43                 // String invalid END header (bad central directory offset)
      98: invokestatic  #4                  // Method zerror:(Ljava/lang/String;)V
     101: aload_0
     102: getfield      #17                 // Field end:Lsbt/internal/inc/zip/ZipCentralDir$END;
     105: getfield      #26                 // Field sbt/internal/inc/zip/ZipCentralDir$END.cenlen:J
     108: ldc2_w        #44                 // long 22l
     111: ladd
     112: l2i
     113: newarray       byte
     115: astore        5
     117: aload_0
     118: aload         5
     120: iconst_0
     121: aload         5
     123: arraylength
     124: i2l
     125: lload_3
     126: invokespecial #2                  // Method readFullyAt:([BIJJ)J
     129: aload_0
     130: getfield      #17                 // Field end:Lsbt/internal/inc/zip/ZipCentralDir$END;
     133: getfield      #26                 // Field sbt/internal/inc/zip/ZipCentralDir$END.cenlen:J
     136: ldc2_w        #44                 // long 22l
     139: ladd
     140: lcmp
     141: ifeq          149
     144: ldc           #46                 // String read CEN tables failed
     146: invokestatic  #4                  // Method zerror:(Ljava/lang/String;)V
     149: aload_0
     150: new           #39                 // class java/util/LinkedHashMap
     153: dup
     154: aload_0
     155: getfield      #17                 // Field end:Lsbt/internal/inc/zip/ZipCentralDir$END;
     158: getfield      #25                 // Field sbt/internal/inc/zip/ZipCentralDir$END.centot:I
     161: iconst_1
     162: iadd
     163: invokespecial #40                 // Method java/util/LinkedHashMap."<init>":(I)V
     166: putfield      #30                 // Field inodes:Ljava/util/LinkedHashMap;
     169: iconst_0
     170: istore        6
     172: aload         5
     174: arraylength
     175: bipush        22
     177: isub
     178: istore        7
     180: iload         6
     182: iload         7
     184: if_icmpge     381
     187: aload         5
     189: iload         6
     191: invokestatic  #47                 // Method sbt/internal/inc/zip/ZipConstants.CENSIG:([BI)J
     194: getstatic     #48                 // Field sbt/internal/inc/zip/ZipConstants.CENSIG:J
     197: lcmp
     198: ifeq          206
     201: ldc           #49                 // String invalid CEN header (bad signature)
     203: invokestatic  #4                  // Method zerror:(Ljava/lang/String;)V
     206: aload         5
     208: iload         6
     210: invokestatic  #50                 // Method sbt/internal/inc/zip/ZipConstants.CENHOW:([BI)I
     213: istore        8
     215: aload         5
     217: iload         6
     219: invokestatic  #51                 // Method sbt/internal/inc/zip/ZipConstants.CENNAM:([BI)I
     222: istore        9
     224: aload         5
     226: iload         6
     228: invokestatic  #52                 // Method sbt/internal/inc/zip/ZipConstants.CENEXT:([BI)I
     231: istore        10
     233: aload         5
     235: iload         6
     237: invokestatic  #53                 // Method sbt/internal/inc/zip/ZipConstants.CENCOM:([BI)I
     240: istore        11
     242: aload         5
     244: iload         6
     246: invokestatic  #54                 // Method sbt/internal/inc/zip/ZipConstants.CENFLG:([BI)I
     249: iconst_1
     250: iand
     251: ifeq          259
     254: ldc           #55                 // String invalid CEN header (encrypted entry)
     256: invokestatic  #4                  // Method zerror:(Ljava/lang/String;)V
     259: iload         8
     261: ifeq          299
     264: iload         8
     266: bipush        8
     268: if_icmpeq     299
     271: new           #56                 // class java/lang/StringBuilder
     274: dup
     275: invokespecial #57                 // Method java/lang/StringBuilder."<init>":()V
     278: ldc           #58                 // String invalid CEN header (unsupported compression method:
     280: invokevirtual #59                 // Method java/lang/StringBuilder.append:(Ljava/lang/String;)Ljava/lang/StringBuilder;
     283: iload         8
     285: invokevirtual #60                 // Method java/lang/StringBuilder.append:(I)Ljava/lang/StringBuilder;
     288: ldc           #61                 // String )
     290: invokevirtual #59                 // Method java/lang/StringBuilder.append:(Ljava/lang/String;)Ljava/lang/StringBuilder;
     293: invokevirtual #62                 // Method java/lang/StringBuilder.toString:()Ljava/lang/String;
     296: invokestatic  #4                  // Method zerror:(Ljava/lang/String;)V
     299: iload         6
     301: bipush        46
     303: iadd
     304: iload         9
     306: iadd
     307: iload         7
     309: if_icmple     317
     312: ldc           #63                 // String invalid CEN header (bad header size)
     314: invokestatic  #4                  // Method zerror:(Ljava/lang/String;)V
     317: aload         5
     319: iload         6
     321: bipush        46
     323: iadd
     324: iload         6
     326: bipush        46
     328: iadd
     329: iload         9
     331: iadd
     332: invokestatic  #64                 // Method java/util/Arrays.copyOfRange:([BII)[B
     335: astore        12
     337: new           #33                 // class sbt/internal/inc/zip/ZipCentralDir$IndexNode
     340: dup
     341: aload         12
     343: iload         6
     345: invokespecial #65                 // Method sbt/internal/inc/zip/ZipCentralDir$IndexNode."<init>":([BI)V
     348: astore        13
     350: aload_0
     351: getfield      #30                 // Field inodes:Ljava/util/LinkedHashMap;
     354: aload         13
     356: aload         13
     358: invokevirtual #66                 // Method java/util/LinkedHashMap.put:(Ljava/lang/Object;Ljava/lang/Object;)Ljava/lang/Object;
     361: pop
     362: iload         6
     364: bipush        46
     366: iload         9
     368: iadd
     369: iload         10
     371: iadd
     372: iload         11
     374: iadd
     375: iadd
     376: istore        6
     378: goto          180
     381: iload         6
     383: bipush        22
     385: iadd
     386: aload         5
     388: arraylength
     389: if_icmpeq     397
     392: ldc           #63                 // String invalid CEN header (bad header size)
     394: invokestatic  #4                  // Method zerror:(Ljava/lang/String;)V
     397: aload_0
     398: invokespecial #41                 // Method buildNodeTree:()V
     401: aload         5
     403: areturn

  private sbt.internal.inc.zip.ZipCentralDir$END findEND() throws java.io.IOException;
    Code:
       0: sipush        128
       3: newarray       byte
       5: astore_1
       6: aload_0
       7: getfield      #12                 // Field ch:Ljava/nio/channels/SeekableByteChannel;
      10: invokeinterface #67,  1           // InterfaceMethod java/nio/channels/SeekableByteChannel.size:()J
      15: lstore_2
      16: lload_2
      17: ldc2_w        #68                 // long 65557l
      20: lsub
      21: lconst_0
      22: lcmp
      23: ifle          34
      26: lload_2
      27: ldc2_w        #68                 // long 65557l
      30: lsub
      31: goto          35
      34: lconst_0
      35: lstore        4
      37: lload         4
      39: aload_1
      40: arraylength
      41: bipush        22
      43: isub
      44: i2l
      45: lsub
      46: lstore        6
      48: lload_2
      49: aload_1
      50: arraylength
      51: i2l
      52: lsub
      53: lstore        8
      55: lload         8
      57: lload         6
      59: lcmp
      60: iflt          446
      63: iconst_0
      64: istore        10
      66: lload         8
      68: lconst_0
      69: lcmp
      70: ifge          87
      73: lload         8
      75: lneg
      76: l2i
      77: istore        10
      79: aload_1
      80: iconst_0
      81: iload         10
      83: iconst_0
      84: invokestatic  #70                 // Method java/util/Arrays.fill:([BIIB)V
      87: aload_1
      88: arraylength
      89: iload         10
      91: isub
      92: istore        11
      94: aload_0
      95: aload_1
      96: iload         10
      98: iload         11
     100: i2l
     101: lload         8
     103: iload         10
     105: i2l
     106: ladd
     107: invokespecial #2                  // Method readFullyAt:([BIJJ)J
     110: iload         11
     112: i2l
     113: lcmp
     114: ifeq          122
     117: ldc           #71                 // String zip END header not found
     119: invokestatic  #4                  // Method zerror:(Ljava/lang/String;)V
     122: aload_1
     123: arraylength
     124: bipush        22
     126: isub
     127: istore        12
     129: iload         12
     131: iflt          432
     134: aload_1
     135: iload         12
     137: iconst_0
     138: iadd
     139: baload
     140: bipush        80
     142: if_icmpne     426
     145: aload_1
     146: iload         12
     148: iconst_1
     149: iadd
     150: baload
     151: bipush        75
     153: if_icmpne     426
     156: aload_1
     157: iload         12
     159: iconst_2
     160: iadd
     161: baload
     162: iconst_5
     163: if_icmpne     426
     166: aload_1
     167: iload         12
     169: iconst_3
     170: iadd
     171: baload
     172: bipush        6
     174: if_icmpne     426
     177: lload         8
     179: iload         12
     181: i2l
     182: ladd
     183: ldc2_w        #44                 // long 22l
     186: ladd
     187: aload_1
     188: iload         12
     190: invokestatic  #72                 // Method sbt/internal/inc/zip/ZipConstants.ENDCOM:([BI)I
     193: i2l
     194: ladd
     195: lload_2
     196: lcmp
     197: ifne          426
     200: aload_1
     201: iload         12
     203: iload         12
     205: bipush        22
     207: iadd
     208: invokestatic  #64                 // Method java/util/Arrays.copyOfRange:([BII)[B
     211: astore_1
     212: new           #73                 // class sbt/internal/inc/zip/ZipCentralDir$END
     215: dup
     216: invokespecial #74                 // Method sbt/internal/inc/zip/ZipCentralDir$END."<init>":()V
     219: astore        13
     221: aload         13
     223: aload_1
     224: invokestatic  #75                 // Method sbt/internal/inc/zip/ZipConstants.ENDSUB:([B)I
     227: putfield      #76                 // Field sbt/internal/inc/zip/ZipCentralDir$END.endsub:I
     230: aload         13
     232: aload_1
     233: invokestatic  #77                 // Method sbt/internal/inc/zip/ZipConstants.ENDTOT:([B)I
     236: putfield      #25                 // Field sbt/internal/inc/zip/ZipCentralDir$END.centot:I
     239: aload         13
     241: aload_1
     242: invokestatic  #78                 // Method sbt/internal/inc/zip/ZipConstants.ENDSIZ:([B)J
     245: putfield      #26                 // Field sbt/internal/inc/zip/ZipCentralDir$END.cenlen:J
     248: aload         13
     250: aload_1
     251: invokestatic  #79                 // Method sbt/internal/inc/zip/ZipConstants.ENDOFF:([B)J
     254: putfield      #18                 // Field sbt/internal/inc/zip/ZipCentralDir$END.cenoff:J
     257: aload         13
     259: aload_1
     260: invokestatic  #80                 // Method sbt/internal/inc/zip/ZipConstants.ENDCOM:([B)I
     263: putfield      #81                 // Field sbt/internal/inc/zip/ZipCentralDir$END.comlen:I
     266: aload         13
     268: lload         8
     270: iload         12
     272: i2l
     273: ladd
     274: putfield      #38                 // Field sbt/internal/inc/zip/ZipCentralDir$END.endpos:J
     277: aload         13
     279: getfield      #26                 // Field sbt/internal/inc/zip/ZipCentralDir$END.cenlen:J
     282: ldc2_w        #82                 // long 4294967295l
     285: lcmp
     286: ifeq          311
     289: aload         13
     291: getfield      #18                 // Field sbt/internal/inc/zip/ZipCentralDir$END.cenoff:J
     294: ldc2_w        #82                 // long 4294967295l
     297: lcmp
     298: ifeq          311
     301: aload         13
     303: getfield      #25                 // Field sbt/internal/inc/zip/ZipCentralDir$END.centot:I
     306: ldc           #84                 // int 65535
     308: if_icmpne     423
     311: bipush        20
     313: newarray       byte
     315: astore        14
     317: aload_0
     318: aload         14
     320: iconst_0
     321: aload         14
     323: arraylength
     324: i2l
     325: aload         13
     327: getfield      #38                 // Field sbt/internal/inc/zip/ZipCentralDir$END.endpos:J
     330: ldc2_w        #85                 // long 20l
     333: lsub
     334: invokespecial #2                  // Method readFullyAt:([BIJJ)J
     337: aload         14
     339: arraylength
     340: i2l
     341: lcmp
     342: ifeq          348
     345: aload         13
     347: areturn
     348: aload         14
     350: invokestatic  #87                 // Method sbt/internal/inc/zip/ZipConstants.ZIP64_LOCOFF:([B)J
     353: lstore        15
     355: bipush        56
     357: newarray       byte
     359: astore        17
     361: aload_0
     362: aload         17
     364: iconst_0
     365: aload         17
     367: arraylength
     368: i2l
     369: lload         15
     371: invokespecial #2                  // Method readFullyAt:([BIJJ)J
     374: aload         17
     376: arraylength
     377: i2l
     378: lcmp
     379: ifeq          385
     382: aload         13
     384: areturn
     385: aload         13
     387: aload         17
     389: invokestatic  #88                 // Method sbt/internal/inc/zip/ZipConstants.ZIP64_ENDSIZ:([B)J
     392: putfield      #26                 // Field sbt/internal/inc/zip/ZipCentralDir$END.cenlen:J
     395: aload         13
     397: aload         17
     399: invokestatic  #89                 // Method sbt/internal/inc/zip/ZipConstants.ZIP64_ENDOFF:([B)J
     402: putfield      #18                 // Field sbt/internal/inc/zip/ZipCentralDir$END.cenoff:J
     405: aload         13
     407: aload         17
     409: invokestatic  #90                 // Method sbt/internal/inc/zip/ZipConstants.ZIP64_ENDTOT:([B)J
     412: l2i
     413: putfield      #25                 // Field sbt/internal/inc/zip/ZipCentralDir$END.centot:I
     416: aload         13
     418: lload         15
     420: putfield      #38                 // Field sbt/internal/inc/zip/ZipCentralDir$END.endpos:J
     423: aload         13
     425: areturn
     426: iinc          12, -1
     429: goto          129
     432: lload         8
     434: aload_1
     435: arraylength
     436: bipush        22
     438: isub
     439: i2l
     440: lsub
     441: lstore        8
     443: goto          55
     446: ldc           #71                 // String zip END header not found
     448: invokestatic  #4                  // Method zerror:(Ljava/lang/String;)V
     451: aconst_null
     452: areturn

  private static void zerror(java.lang.String);
    Code:
       0: new           #91                 // class java/util/zip/ZipError
       3: dup
       4: aload_0
       5: invokespecial #92                 // Method java/util/zip/ZipError."<init>":(Ljava/lang/String;)V
       8: athrow

  private void buildNodeTree();
    Code:
       0: new           #93                 // class java/util/HashSet
       3: dup
       4: invokespecial #94                 // Method java/util/HashSet."<init>":()V
       7: astore_1
       8: new           #33                 // class sbt/internal/inc/zip/ZipCentralDir$IndexNode
      11: dup
      12: getstatic     #95                 // Field ROOTPATH:[B
      15: iconst_m1
      16: invokespecial #65                 // Method sbt/internal/inc/zip/ZipCentralDir$IndexNode."<init>":([BI)V
      19: astore_2
      20: aload_0
      21: getfield      #30                 // Field inodes:Ljava/util/LinkedHashMap;
      24: aload_2
      25: aload_2
      26: invokevirtual #66                 // Method java/util/LinkedHashMap.put:(Ljava/lang/Object;Ljava/lang/Object;)Ljava/lang/Object;
      29: pop
      30: aload_1
      31: aload_2
      32: invokevirtual #96                 // Method java/util/HashSet.add:(Ljava/lang/Object;)Z
      35: pop
      36: aload_0
      37: getfield      #30                 // Field inodes:Ljava/util/LinkedHashMap;
      40: invokevirtual #97                 // Method java/util/LinkedHashMap.keySet:()Ljava/util/Set;
      43: iconst_0
      44: anewarray     #33                 // class sbt/internal/inc/zip/ZipCentralDir$IndexNode
      47: invokeinterface #98,  2           // InterfaceMethod java/util/Set.toArray:([Ljava/lang/Object;)[Ljava/lang/Object;
      52: checkcast     #99                 // class "[Lsbt/internal/inc/zip/ZipCentralDir$IndexNode;"
      55: astore_3
      56: aload_3
      57: arraylength
      58: istore        4
      60: iconst_0
      61: istore        5
      63: iload         5
      65: iload         4
      67: if_icmpge     89
      70: aload_3
      71: iload         5
      73: aaload
      74: astore        6
      76: aload_0
      77: aload         6
      79: aload_1
      80: invokespecial #100                // Method addToTree:(Lsbt/internal/inc/zip/ZipCentralDir$IndexNode;Ljava/util/HashSet;)V
      83: iinc          5, 1
      86: goto          63
      89: return

  private void addToTree(sbt.internal.inc.zip.ZipCentralDir$IndexNode, java.util.HashSet<sbt.internal.inc.zip.ZipCentralDir$IndexNode>);
    Code:
       0: aload_2
       1: aload_1
       2: invokevirtual #101                // Method java/util/HashSet.contains:(Ljava/lang/Object;)Z
       5: ifeq          9
       8: return
       9: aload_1
      10: getfield      #102                // Field sbt/internal/inc/zip/ZipCentralDir$IndexNode.name:[B
      13: astore        4
      15: aload         4
      17: invokestatic  #103                // Method getParent:([B)[B
      20: astore        5
      22: aload_0
      23: getfield      #30                 // Field inodes:Ljava/util/LinkedHashMap;
      26: aload_0
      27: getfield      #8                  // Field LOOKUPKEY:Lsbt/internal/inc/zip/ZipCentralDir$IndexNode;
      30: aload         5
      32: invokevirtual #104                // Method sbt/internal/inc/zip/ZipCentralDir$IndexNode.as:([B)Lsbt/internal/inc/zip/ZipCentralDir$IndexNode;
      35: invokevirtual #105                // Method java/util/LinkedHashMap.containsKey:(Ljava/lang/Object;)Z
      38: ifeq          59
      41: aload_0
      42: getfield      #30                 // Field inodes:Ljava/util/LinkedHashMap;
      45: aload_0
      46: getfield      #8                  // Field LOOKUPKEY:Lsbt/internal/inc/zip/ZipCentralDir$IndexNode;
      49: invokevirtual #106                // Method java/util/LinkedHashMap.get:(Ljava/lang/Object;)Ljava/lang/Object;
      52: checkcast     #33                 // class sbt/internal/inc/zip/ZipCentralDir$IndexNode
      55: astore_3
      56: goto          80
      59: new           #33                 // class sbt/internal/inc/zip/ZipCentralDir$IndexNode
      62: dup
      63: aload         5
      65: iconst_m1
      66: invokespecial #65                 // Method sbt/internal/inc/zip/ZipCentralDir$IndexNode."<init>":([BI)V
      69: astore_3
      70: aload_0
      71: getfield      #30                 // Field inodes:Ljava/util/LinkedHashMap;
      74: aload_3
      75: aload_3
      76: invokevirtual #66                 // Method java/util/LinkedHashMap.put:(Ljava/lang/Object;Ljava/lang/Object;)Ljava/lang/Object;
      79: pop
      80: aload_0
      81: aload_3
      82: aload_2
      83: invokespecial #100                // Method addToTree:(Lsbt/internal/inc/zip/ZipCentralDir$IndexNode;Ljava/util/HashSet;)V
      86: aload_1
      87: aload_3
      88: getfield      #107                // Field sbt/internal/inc/zip/ZipCentralDir$IndexNode.child:Lsbt/internal/inc/zip/ZipCentralDir$IndexNode;
      91: putfield      #108                // Field sbt/internal/inc/zip/ZipCentralDir$IndexNode.sibling:Lsbt/internal/inc/zip/ZipCentralDir$IndexNode;
      94: aload_3
      95: aload_1
      96: putfield      #107                // Field sbt/internal/inc/zip/ZipCentralDir$IndexNode.child:Lsbt/internal/inc/zip/ZipCentralDir$IndexNode;
      99: aload         4
     101: aload         4
     103: arraylength
     104: iconst_1
     105: isub
     106: baload
     107: bipush        47
     109: if_icmpne     118
     112: aload_2
     113: aload_1
     114: invokevirtual #96                 // Method java/util/HashSet.add:(Ljava/lang/Object;)Z
     117: pop
     118: return

  private static byte[] getParent(byte[]);
    Code:
       0: aload_0
       1: arraylength
       2: iconst_1
       3: isub
       4: istore_1
       5: iload_1
       6: ifle          20
       9: aload_0
      10: iload_1
      11: baload
      12: bipush        47
      14: if_icmpne     20
      17: iinc          1, -1
      20: iload_1
      21: ifle          38
      24: aload_0
      25: iload_1
      26: baload
      27: bipush        47
      29: if_icmpeq     38
      32: iinc          1, -1
      35: goto          20
      38: iload_1
      39: ifgt          46
      42: getstatic     #95                 // Field ROOTPATH:[B
      45: areturn
      46: aload_0
      47: iload_1
      48: iconst_1
      49: iadd
      50: invokestatic  #109                // Method java/util/Arrays.copyOf:([BI)[B
      53: areturn

  private long readFullyAt(byte[], int, long, long) throws java.io.IOException;
    Code:
       0: aload_1
       1: invokestatic  #110                // Method java/nio/ByteBuffer.wrap:([B)Ljava/nio/ByteBuffer;
       4: astore        7
       6: aload         7
       8: iload_2
       9: invokevirtual #111                // Method java/nio/ByteBuffer.position:(I)Ljava/nio/Buffer;
      12: pop
      13: aload         7
      15: iload_2
      16: i2l
      17: lload_3
      18: ladd
      19: l2i
      20: invokevirtual #112                // Method java/nio/ByteBuffer.limit:(I)Ljava/nio/Buffer;
      23: pop
      24: aload_0
      25: aload         7
      27: lload         5
      29: invokespecial #113                // Method readFullyAt:(Ljava/nio/ByteBuffer;J)J
      32: lreturn

  private long readFullyAt(java.nio.ByteBuffer, long) throws java.io.IOException;
    Code:
       0: aload_0
       1: getfield      #12                 // Field ch:Ljava/nio/channels/SeekableByteChannel;
       4: lload_2
       5: invokeinterface #114,  3          // InterfaceMethod java/nio/channels/SeekableByteChannel.position:(J)Ljava/nio/channels/SeekableByteChannel;
      10: aload_1
      11: invokeinterface #115,  2          // InterfaceMethod java/nio/channels/SeekableByteChannel.read:(Ljava/nio/ByteBuffer;)I
      16: i2l
      17: lreturn

  static byte[] access$000(sbt.internal.inc.zip.ZipCentralDir);
    Code:
       0: aload_0
       1: getfield      #5                  // Field cen:[B
       4: areturn

  static void access$100(java.lang.String);
    Code:
       0: aload_0
       1: invokestatic  #4                  // Method zerror:(Ljava/lang/String;)V
       4: return

  static boolean access$200();
    Code:
       0: getstatic     #3                  // Field isWindows:Z
       3: ireturn

  static long access$300(sbt.internal.inc.zip.ZipCentralDir, byte[], int, long, long) throws java.io.IOException;
    Code:
       0: aload_0
       1: aload_1
       2: iload_2
       3: lload_3
       4: lload         5
       6: invokespecial #2                  // Method readFullyAt:([BIJJ)J
       9: lreturn

  static {};
    Code:
       0: iconst_0
       1: newarray       byte
       3: putstatic     #95                 // Field ROOTPATH:[B
       6: ldc           #116                // String os.name
       8: invokestatic  #117                // Method java/lang/System.getProperty:(Ljava/lang/String;)Ljava/lang/String;
      11: ldc           #118                // String Windows
      13: invokevirtual #119                // Method java/lang/String.startsWith:(Ljava/lang/String;)Z
      16: putstatic     #3                  // Field isWindows:Z
      19: return
}
