Compiled from "Endpoint.java"
public class org.hawkular.bus.common.Endpoint {
  public static final org.hawkular.bus.common.Endpoint TEMPORARY_QUEUE;

  public static final org.hawkular.bus.common.Endpoint TEMPORARY_TOPIC;

  private final org.hawkular.bus.common.Endpoint$Type type;

  private final java.lang.String name;

  private final boolean isTemp;

  public org.hawkular.bus.common.Endpoint(java.lang.String) throws java.lang.IllegalArgumentException;
    Code:
       0: aload_0
       1: invokespecial #1                  // Method java/lang/Object."<init>":()V
       4: aload_1
       5: ifnonnull     18
       8: new           #2                  // class java/lang/IllegalArgumentException
      11: dup
      12: ldc           #3                  // String destination must not be null
      14: invokespecial #4                  // Method java/lang/IllegalArgumentException."<init>":(Ljava/lang/String;)V
      17: athrow
      18: new           #5                  // class java/net/URI
      21: dup
      22: aload_1
      23: invokespecial #6                  // Method java/net/URI."<init>":(Ljava/lang/String;)V
      26: astore_2
      27: goto          58
      30: astore_3
      31: new           #2                  // class java/lang/IllegalArgumentException
      34: dup
      35: new           #8                  // class java/lang/StringBuilder
      38: dup
      39: invokespecial #9                  // Method java/lang/StringBuilder."<init>":()V
      42: ldc           #10                 // String Not a valid destination URI:
      44: invokevirtual #11                 // Method java/lang/StringBuilder.append:(Ljava/lang/String;)Ljava/lang/StringBuilder;
      47: aload_1
      48: invokevirtual #11                 // Method java/lang/StringBuilder.append:(Ljava/lang/String;)Ljava/lang/StringBuilder;
      51: invokevirtual #12                 // Method java/lang/StringBuilder.toString:()Ljava/lang/String;
      54: invokespecial #4                  // Method java/lang/IllegalArgumentException."<init>":(Ljava/lang/String;)V
      57: athrow
      58: aload_2
      59: invokevirtual #13                 // Method java/net/URI.getScheme:()Ljava/lang/String;
      62: invokevirtual #14                 // Method java/lang/String.toUpperCase:()Ljava/lang/String;
      65: astore_3
      66: aload_3
      67: invokestatic  #15                 // Method org/hawkular/bus/common/Endpoint$Type.valueOf:(Ljava/lang/String;)Lorg/hawkular/bus/common/Endpoint$Type;
      70: astore        4
      72: goto          113
      75: astore        5
      77: new           #2                  // class java/lang/IllegalArgumentException
      80: dup
      81: new           #8                  // class java/lang/StringBuilder
      84: dup
      85: invokespecial #9                  // Method java/lang/StringBuilder."<init>":()V
      88: ldc           #16                 // String Not a valid destination URI [
      90: invokevirtual #11                 // Method java/lang/StringBuilder.append:(Ljava/lang/String;)Ljava/lang/StringBuilder;
      93: aload_1
      94: invokevirtual #11                 // Method java/lang/StringBuilder.append:(Ljava/lang/String;)Ljava/lang/StringBuilder;
      97: ldc           #17                 // String ]; the endpoint type must be either QUEUE or TOPIC:
      99: invokevirtual #11                 // Method java/lang/StringBuilder.append:(Ljava/lang/String;)Ljava/lang/StringBuilder;
     102: aload_3
     103: invokevirtual #11                 // Method java/lang/StringBuilder.append:(Ljava/lang/String;)Ljava/lang/StringBuilder;
     106: invokevirtual #12                 // Method java/lang/StringBuilder.toString:()Ljava/lang/String;
     109: invokespecial #4                  // Method java/lang/IllegalArgumentException."<init>":(Ljava/lang/String;)V
     112: athrow
     113: aload_2
     114: invokevirtual #18                 // Method java/net/URI.getHost:()Ljava/lang/String;
     117: astore        5
     119: aload_0
     120: aload         4
     122: putfield      #19                 // Field type:Lorg/hawkular/bus/common/Endpoint$Type;
     125: aload_0
     126: aload         5
     128: putfield      #20                 // Field name:Ljava/lang/String;
     131: aload_0
     132: iconst_0
     133: putfield      #21                 // Field isTemp:Z
     136: return
    Exception table:
       from    to  target type
          18    27    30   Class java/lang/Exception
          66    72    75   Class java/lang/Exception

  public org.hawkular.bus.common.Endpoint(org.hawkular.bus.common.Endpoint$Type, java.lang.String);
    Code:
       0: aload_0
       1: aload_1
       2: aload_2
       3: iconst_0
       4: invokespecial #22                 // Method "<init>":(Lorg/hawkular/bus/common/Endpoint$Type;Ljava/lang/String;Z)V
       7: return

  public org.hawkular.bus.common.Endpoint(org.hawkular.bus.common.Endpoint$Type, java.lang.String, boolean);
    Code:
       0: aload_0
       1: invokespecial #1                  // Method java/lang/Object."<init>":()V
       4: aload_1
       5: ifnonnull     18
       8: new           #2                  // class java/lang/IllegalArgumentException
      11: dup
      12: ldc           #23                 // String type must not be null
      14: invokespecial #4                  // Method java/lang/IllegalArgumentException."<init>":(Ljava/lang/String;)V
      17: athrow
      18: aload_2
      19: ifnonnull     32
      22: new           #2                  // class java/lang/IllegalArgumentException
      25: dup
      26: ldc           #24                 // String name must not be null
      28: invokespecial #4                  // Method java/lang/IllegalArgumentException."<init>":(Ljava/lang/String;)V
      31: athrow
      32: aload_0
      33: aload_1
      34: putfield      #19                 // Field type:Lorg/hawkular/bus/common/Endpoint$Type;
      37: aload_0
      38: aload_2
      39: putfield      #20                 // Field name:Ljava/lang/String;
      42: aload_0
      43: iload_3
      44: putfield      #21                 // Field isTemp:Z
      47: return

  public org.hawkular.bus.common.Endpoint$Type getType();
    Code:
       0: aload_0
       1: getfield      #19                 // Field type:Lorg/hawkular/bus/common/Endpoint$Type;
       4: areturn

  public java.lang.String getName();
    Code:
       0: aload_0
       1: getfield      #20                 // Field name:Ljava/lang/String;
       4: areturn

  public boolean isTemporary();
    Code:
       0: aload_0
       1: getfield      #21                 // Field isTemp:Z
       4: ireturn

  public java.lang.String toString();
    Code:
       0: aload_0
       1: invokevirtual #25                 // Method isTemporary:()Z
       4: ifeq          38
       7: new           #8                  // class java/lang/StringBuilder
      10: dup
      11: invokespecial #9                  // Method java/lang/StringBuilder."<init>":()V
      14: ldc           #26                 // String {
      16: invokevirtual #11                 // Method java/lang/StringBuilder.append:(Ljava/lang/String;)Ljava/lang/StringBuilder;
      19: aload_0
      20: getfield      #19                 // Field type:Lorg/hawkular/bus/common/Endpoint$Type;
      23: invokevirtual #27                 // Method org/hawkular/bus/common/Endpoint$Type.name:()Ljava/lang/String;
      26: invokevirtual #11                 // Method java/lang/StringBuilder.append:(Ljava/lang/String;)Ljava/lang/StringBuilder;
      29: ldc           #28                 // String }$TEMPORARY$
      31: invokevirtual #11                 // Method java/lang/StringBuilder.append:(Ljava/lang/String;)Ljava/lang/StringBuilder;
      34: invokevirtual #12                 // Method java/lang/StringBuilder.toString:()Ljava/lang/String;
      37: areturn
      38: new           #8                  // class java/lang/StringBuilder
      41: dup
      42: invokespecial #9                  // Method java/lang/StringBuilder."<init>":()V
      45: ldc           #26                 // String {
      47: invokevirtual #11                 // Method java/lang/StringBuilder.append:(Ljava/lang/String;)Ljava/lang/StringBuilder;
      50: aload_0
      51: getfield      #19                 // Field type:Lorg/hawkular/bus/common/Endpoint$Type;
      54: invokevirtual #27                 // Method org/hawkular/bus/common/Endpoint$Type.name:()Ljava/lang/String;
      57: invokevirtual #11                 // Method java/lang/StringBuilder.append:(Ljava/lang/String;)Ljava/lang/StringBuilder;
      60: ldc           #29                 // String }
      62: invokevirtual #11                 // Method java/lang/StringBuilder.append:(Ljava/lang/String;)Ljava/lang/StringBuilder;
      65: aload_0
      66: getfield      #20                 // Field name:Ljava/lang/String;
      69: invokevirtual #11                 // Method java/lang/StringBuilder.append:(Ljava/lang/String;)Ljava/lang/StringBuilder;
      72: invokevirtual #12                 // Method java/lang/StringBuilder.toString:()Ljava/lang/String;
      75: areturn

  public int hashCode();
    Code:
       0: iconst_1
       1: istore_1
       2: bipush        31
       4: iload_1
       5: imul
       6: aload_0
       7: getfield      #20                 // Field name:Ljava/lang/String;
      10: invokevirtual #30                 // Method java/lang/String.hashCode:()I
      13: iadd
      14: istore_1
      15: bipush        31
      17: iload_1
      18: imul
      19: aload_0
      20: getfield      #19                 // Field type:Lorg/hawkular/bus/common/Endpoint$Type;
      23: invokevirtual #31                 // Method org/hawkular/bus/common/Endpoint$Type.hashCode:()I
      26: iadd
      27: istore_1
      28: bipush        31
      30: iload_1
      31: imul
      32: aload_0
      33: getfield      #21                 // Field isTemp:Z
      36: ifeq          45
      39: sipush        1231
      42: goto          48
      45: sipush        1237
      48: iadd
      49: istore_1
      50: iload_1
      51: ireturn

  public boolean equals(java.lang.Object);
    Code:
       0: aload_0
       1: aload_1
       2: if_acmpne     7
       5: iconst_1
       6: ireturn
       7: aload_1
       8: instanceof    #32                 // class org/hawkular/bus/common/Endpoint
      11: ifne          16
      14: iconst_0
      15: ireturn
      16: aload_1
      17: checkcast     #32                 // class org/hawkular/bus/common/Endpoint
      20: astore_2
      21: aload_0
      22: getfield      #19                 // Field type:Lorg/hawkular/bus/common/Endpoint$Type;
      25: aload_2
      26: getfield      #19                 // Field type:Lorg/hawkular/bus/common/Endpoint$Type;
      29: if_acmpeq     34
      32: iconst_0
      33: ireturn
      34: aload_0
      35: getfield      #20                 // Field name:Ljava/lang/String;
      38: aload_2
      39: getfield      #20                 // Field name:Ljava/lang/String;
      42: invokevirtual #33                 // Method java/lang/String.equals:(Ljava/lang/Object;)Z
      45: ifne          50
      48: iconst_0
      49: ireturn
      50: aload_0
      51: getfield      #21                 // Field isTemp:Z
      54: aload_2
      55: getfield      #21                 // Field isTemp:Z
      58: if_icmpeq     63
      61: iconst_0
      62: ireturn
      63: iconst_1
      64: ireturn

  static {};
    Code:
       0: new           #32                 // class org/hawkular/bus/common/Endpoint
       3: dup
       4: getstatic     #34                 // Field org/hawkular/bus/common/Endpoint$Type.QUEUE:Lorg/hawkular/bus/common/Endpoint$Type;
       7: ldc           #35                 // String __tmpQueue__
       9: iconst_1
      10: invokespecial #22                 // Method "<init>":(Lorg/hawkular/bus/common/Endpoint$Type;Ljava/lang/String;Z)V
      13: putstatic     #36                 // Field TEMPORARY_QUEUE:Lorg/hawkular/bus/common/Endpoint;
      16: new           #32                 // class org/hawkular/bus/common/Endpoint
      19: dup
      20: getstatic     #37                 // Field org/hawkular/bus/common/Endpoint$Type.TOPIC:Lorg/hawkular/bus/common/Endpoint$Type;
      23: ldc           #38                 // String __tmpTopic__
      25: iconst_1
      26: invokespecial #22                 // Method "<init>":(Lorg/hawkular/bus/common/Endpoint$Type;Ljava/lang/String;Z)V
      29: putstatic     #39                 // Field TEMPORARY_TOPIC:Lorg/hawkular/bus/common/Endpoint;
      32: return
}
