Compiled from "Http2Protocol.java"
public class org.apache.coyote.http2.Http2Protocol implements org.apache.coyote.UpgradeProtocol {
  static final long DEFAULT_READ_TIMEOUT;

  static final long DEFAULT_WRITE_TIMEOUT;

  static final long DEFAULT_KEEP_ALIVE_TIMEOUT;

  static final long DEFAULT_STREAM_READ_TIMEOUT;

  static final long DEFAULT_STREAM_WRITE_TIMEOUT;

  static final long DEFAULT_MAX_CONCURRENT_STREAMS;

  static final int DEFAULT_MAX_CONCURRENT_STREAM_EXECUTION;

  static final int DEFAULT_OVERHEAD_COUNT_FACTOR;

  static final int DEFAULT_OVERHEAD_CONTINUATION_THRESHOLD;

  static final int DEFAULT_OVERHEAD_DATA_THRESHOLD;

  static final int DEFAULT_OVERHEAD_WINDOW_UPDATE_THRESHOLD;

  private static final java.lang.String HTTP_UPGRADE_NAME;

  private static final java.lang.String ALPN_NAME;

  private static final byte[] ALPN_IDENTIFIER;

  private long readTimeout;

  private long writeTimeout;

  private long keepAliveTimeout;

  private long streamReadTimeout;

  private long streamWriteTimeout;

  private long maxConcurrentStreams;

  private int maxConcurrentStreamExecution;

  private int initialWindowSize;

  private java.util.Set<java.lang.String> allowedTrailerHeaders;

  private int maxHeaderCount;

  private int maxHeaderSize;

  private int maxTrailerCount;

  private int maxTrailerSize;

  private int overheadCountFactor;

  private int overheadContinuationThreshold;

  private int overheadDataThreshold;

  private int overheadWindowUpdateThreshold;

  private boolean initiatePingDisabled;

  private final org.apache.coyote.CompressionConfig compressionConfig;

  private org.apache.coyote.http11.AbstractHttp11Protocol<?> http11Protocol;

  public org.apache.coyote.http2.Http2Protocol();
    Code:
       0: aload_0
       1: invokespecial #1                  // Method java/lang/Object."<init>":()V
       4: aload_0
       5: ldc2_w        #2                  // long 5000l
       8: putfield      #4                  // Field readTimeout:J
      11: aload_0
      12: ldc2_w        #2                  // long 5000l
      15: putfield      #5                  // Field writeTimeout:J
      18: aload_0
      19: ldc2_w        #6                  // long 20000l
      22: putfield      #8                  // Field keepAliveTimeout:J
      25: aload_0
      26: ldc2_w        #6                  // long 20000l
      29: putfield      #9                  // Field streamReadTimeout:J
      32: aload_0
      33: ldc2_w        #6                  // long 20000l
      36: putfield      #10                 // Field streamWriteTimeout:J
      39: aload_0
      40: ldc2_w        #11                 // long 100l
      43: putfield      #13                 // Field maxConcurrentStreams:J
      46: aload_0
      47: bipush        20
      49: putfield      #14                 // Field maxConcurrentStreamExecution:I
      52: aload_0
      53: ldc           #15                 // int 65535
      55: putfield      #16                 // Field initialWindowSize:I
      58: aload_0
      59: new           #17                 // class java/util/concurrent/ConcurrentHashMap
      62: dup
      63: invokespecial #18                 // Method java/util/concurrent/ConcurrentHashMap."<init>":()V
      66: invokestatic  #19                 // Method java/util/Collections.newSetFromMap:(Ljava/util/Map;)Ljava/util/Set;
      69: putfield      #20                 // Field allowedTrailerHeaders:Ljava/util/Set;
      72: aload_0
      73: bipush        100
      75: putfield      #21                 // Field maxHeaderCount:I
      78: aload_0
      79: sipush        8192
      82: putfield      #22                 // Field maxHeaderSize:I
      85: aload_0
      86: bipush        100
      88: putfield      #23                 // Field maxTrailerCount:I
      91: aload_0
      92: sipush        8192
      95: putfield      #24                 // Field maxTrailerSize:I
      98: aload_0
      99: iconst_1
     100: putfield      #25                 // Field overheadCountFactor:I
     103: aload_0
     104: sipush        1024
     107: putfield      #26                 // Field overheadContinuationThreshold:I
     110: aload_0
     111: sipush        1024
     114: putfield      #27                 // Field overheadDataThreshold:I
     117: aload_0
     118: sipush        1024
     121: putfield      #28                 // Field overheadWindowUpdateThreshold:I
     124: aload_0
     125: iconst_0
     126: putfield      #29                 // Field initiatePingDisabled:Z
     129: aload_0
     130: new           #30                 // class org/apache/coyote/CompressionConfig
     133: dup
     134: invokespecial #31                 // Method org/apache/coyote/CompressionConfig."<init>":()V
     137: putfield      #32                 // Field compressionConfig:Lorg/apache/coyote/CompressionConfig;
     140: aload_0
     141: aconst_null
     142: putfield      #33                 // Field http11Protocol:Lorg/apache/coyote/http11/AbstractHttp11Protocol;
     145: return

  public java.lang.String getHttpUpgradeName(boolean);
    Code:
       0: iload_1
       1: ifeq          6
       4: aconst_null
       5: areturn
       6: ldc           #34                 // String h2c
       8: areturn

  public byte[] getAlpnIdentifier();
    Code:
       0: getstatic     #35                 // Field ALPN_IDENTIFIER:[B
       3: areturn

  public java.lang.String getAlpnName();
    Code:
       0: ldc           #36                 // String h2
       2: areturn

  public org.apache.coyote.Processor getProcessor(org.apache.tomcat.util.net.SocketWrapperBase<?>, org.apache.coyote.Adapter);
    Code:
       0: new           #37                 // class org/apache/coyote/http11/upgrade/UpgradeProcessorInternal
       3: dup
       4: aload_1
       5: new           #38                 // class org/apache/coyote/UpgradeToken
       8: dup
       9: aload_0
      10: aload_2
      11: aconst_null
      12: invokevirtual #39                 // Method getInternalUpgradeHandler:(Lorg/apache/coyote/Adapter;Lorg/apache/coyote/Request;)Lorg/apache/coyote/http11/upgrade/InternalHttpUpgradeHandler;
      15: aconst_null
      16: aconst_null
      17: invokespecial #40                 // Method org/apache/coyote/UpgradeToken."<init>":(Ljavax/servlet/http/HttpUpgradeHandler;Lorg/apache/tomcat/ContextBind;Lorg/apache/tomcat/InstanceManager;)V
      20: invokespecial #41                 // Method org/apache/coyote/http11/upgrade/UpgradeProcessorInternal."<init>":(Lorg/apache/tomcat/util/net/SocketWrapperBase;Lorg/apache/coyote/UpgradeToken;)V
      23: astore_3
      24: aload_3
      25: areturn

  public org.apache.coyote.http11.upgrade.InternalHttpUpgradeHandler getInternalUpgradeHandler(org.apache.coyote.Adapter, org.apache.coyote.Request);
    Code:
       0: new           #42                 // class org/apache/coyote/http2/Http2UpgradeHandler
       3: dup
       4: aload_0
       5: aload_1
       6: aload_2
       7: invokespecial #43                 // Method org/apache/coyote/http2/Http2UpgradeHandler."<init>":(Lorg/apache/coyote/http2/Http2Protocol;Lorg/apache/coyote/Adapter;Lorg/apache/coyote/Request;)V
      10: astore_3
      11: aload_3
      12: aload_0
      13: invokevirtual #44                 // Method getReadTimeout:()J
      16: invokevirtual #45                 // Method org/apache/coyote/http2/Http2UpgradeHandler.setReadTimeout:(J)V
      19: aload_3
      20: aload_0
      21: invokevirtual #46                 // Method getKeepAliveTimeout:()J
      24: invokevirtual #47                 // Method org/apache/coyote/http2/Http2UpgradeHandler.setKeepAliveTimeout:(J)V
      27: aload_3
      28: aload_0
      29: invokevirtual #48                 // Method getWriteTimeout:()J
      32: invokevirtual #49                 // Method org/apache/coyote/http2/Http2UpgradeHandler.setWriteTimeout:(J)V
      35: aload_3
      36: aload_0
      37: invokevirtual #50                 // Method getMaxConcurrentStreams:()J
      40: invokevirtual #51                 // Method org/apache/coyote/http2/Http2UpgradeHandler.setMaxConcurrentStreams:(J)V
      43: aload_3
      44: aload_0
      45: invokevirtual #52                 // Method getMaxConcurrentStreamExecution:()I
      48: invokevirtual #53                 // Method org/apache/coyote/http2/Http2UpgradeHandler.setMaxConcurrentStreamExecution:(I)V
      51: aload_3
      52: aload_0
      53: invokevirtual #54                 // Method getInitialWindowSize:()I
      56: invokevirtual #55                 // Method org/apache/coyote/http2/Http2UpgradeHandler.setInitialWindowSize:(I)V
      59: aload_3
      60: aload_0
      61: getfield      #20                 // Field allowedTrailerHeaders:Ljava/util/Set;
      64: invokevirtual #56                 // Method org/apache/coyote/http2/Http2UpgradeHandler.setAllowedTrailerHeaders:(Ljava/util/Set;)V
      67: aload_3
      68: aload_0
      69: invokevirtual #57                 // Method getMaxHeaderCount:()I
      72: invokevirtual #58                 // Method org/apache/coyote/http2/Http2UpgradeHandler.setMaxHeaderCount:(I)V
      75: aload_3
      76: aload_0
      77: invokevirtual #59                 // Method getMaxHeaderSize:()I
      80: invokevirtual #60                 // Method org/apache/coyote/http2/Http2UpgradeHandler.setMaxHeaderSize:(I)V
      83: aload_3
      84: aload_0
      85: invokevirtual #61                 // Method getMaxTrailerCount:()I
      88: invokevirtual #62                 // Method org/apache/coyote/http2/Http2UpgradeHandler.setMaxTrailerCount:(I)V
      91: aload_3
      92: aload_0
      93: invokevirtual #63                 // Method getMaxTrailerSize:()I
      96: invokevirtual #64                 // Method org/apache/coyote/http2/Http2UpgradeHandler.setMaxTrailerSize:(I)V
      99: aload_3
     100: aload_0
     101: getfield      #29                 // Field initiatePingDisabled:Z
     104: invokevirtual #65                 // Method org/apache/coyote/http2/Http2UpgradeHandler.setInitiatePingDisabled:(Z)V
     107: aload_3
     108: areturn

  public boolean accept(org.apache.coyote.Request);
    Code:
       0: aload_1
       1: invokevirtual #66                 // Method org/apache/coyote/Request.getMimeHeaders:()Lorg/apache/tomcat/util/http/MimeHeaders;
       4: ldc           #67                 // String HTTP2-Settings
       6: invokevirtual #68                 // Method org/apache/tomcat/util/http/MimeHeaders.values:(Ljava/lang/String;)Ljava/util/Enumeration;
       9: astore_2
      10: iconst_0
      11: istore_3
      12: aload_2
      13: invokeinterface #69,  1           // InterfaceMethod java/util/Enumeration.hasMoreElements:()Z
      18: ifeq          34
      21: iinc          3, 1
      24: aload_2
      25: invokeinterface #70,  1           // InterfaceMethod java/util/Enumeration.nextElement:()Ljava/lang/Object;
      30: pop
      31: goto          12
      34: iload_3
      35: iconst_1
      36: if_icmpeq     41
      39: iconst_0
      40: ireturn
      41: aload_1
      42: invokevirtual #66                 // Method org/apache/coyote/Request.getMimeHeaders:()Lorg/apache/tomcat/util/http/MimeHeaders;
      45: ldc           #71                 // String Connection
      47: invokevirtual #68                 // Method org/apache/tomcat/util/http/MimeHeaders.values:(Ljava/lang/String;)Ljava/util/Enumeration;
      50: astore        4
      52: iconst_0
      53: istore        5
      55: aload         4
      57: invokeinterface #69,  1           // InterfaceMethod java/util/Enumeration.hasMoreElements:()Z
      62: ifeq          90
      65: iload         5
      67: ifne          90
      70: aload         4
      72: invokeinterface #70,  1           // InterfaceMethod java/util/Enumeration.nextElement:()Ljava/lang/Object;
      77: checkcast     #72                 // class java/lang/String
      80: ldc           #67                 // String HTTP2-Settings
      82: invokevirtual #73                 // Method java/lang/String.contains:(Ljava/lang/CharSequence;)Z
      85: istore        5
      87: goto          55
      90: iload         5
      92: ireturn

  public long getReadTimeout();
    Code:
       0: aload_0
       1: getfield      #4                  // Field readTimeout:J
       4: lreturn

  public void setReadTimeout(long);
    Code:
       0: aload_0
       1: lload_1
       2: putfield      #4                  // Field readTimeout:J
       5: return

  public long getWriteTimeout();
    Code:
       0: aload_0
       1: getfield      #5                  // Field writeTimeout:J
       4: lreturn

  public void setWriteTimeout(long);
    Code:
       0: aload_0
       1: lload_1
       2: putfield      #5                  // Field writeTimeout:J
       5: return

  public long getKeepAliveTimeout();
    Code:
       0: aload_0
       1: getfield      #8                  // Field keepAliveTimeout:J
       4: lreturn

  public void setKeepAliveTimeout(long);
    Code:
       0: aload_0
       1: lload_1
       2: putfield      #8                  // Field keepAliveTimeout:J
       5: return

  public long getStreamReadTimeout();
    Code:
       0: aload_0
       1: getfield      #9                  // Field streamReadTimeout:J
       4: lreturn

  public void setStreamReadTimeout(long);
    Code:
       0: aload_0
       1: lload_1
       2: putfield      #9                  // Field streamReadTimeout:J
       5: return

  public long getStreamWriteTimeout();
    Code:
       0: aload_0
       1: getfield      #10                 // Field streamWriteTimeout:J
       4: lreturn

  public void setStreamWriteTimeout(long);
    Code:
       0: aload_0
       1: lload_1
       2: putfield      #10                 // Field streamWriteTimeout:J
       5: return

  public long getMaxConcurrentStreams();
    Code:
       0: aload_0
       1: getfield      #13                 // Field maxConcurrentStreams:J
       4: lreturn

  public void setMaxConcurrentStreams(long);
    Code:
       0: aload_0
       1: lload_1
       2: putfield      #13                 // Field maxConcurrentStreams:J
       5: return

  public int getMaxConcurrentStreamExecution();
    Code:
       0: aload_0
       1: getfield      #14                 // Field maxConcurrentStreamExecution:I
       4: ireturn

  public void setMaxConcurrentStreamExecution(int);
    Code:
       0: aload_0
       1: iload_1
       2: putfield      #14                 // Field maxConcurrentStreamExecution:I
       5: return

  public int getInitialWindowSize();
    Code:
       0: aload_0
       1: getfield      #16                 // Field initialWindowSize:I
       4: ireturn

  public void setInitialWindowSize(int);
    Code:
       0: aload_0
       1: iload_1
       2: putfield      #16                 // Field initialWindowSize:I
       5: return

  public void setAllowedTrailerHeaders(java.lang.String);
    Code:
       0: new           #74                 // class java/util/HashSet
       3: dup
       4: invokespecial #75                 // Method java/util/HashSet."<init>":()V
       7: astore_2
       8: aload_2
       9: aload_0
      10: getfield      #20                 // Field allowedTrailerHeaders:Ljava/util/Set;
      13: invokeinterface #76,  2           // InterfaceMethod java/util/Set.addAll:(Ljava/util/Collection;)Z
      18: pop
      19: aload_1
      20: ifnull        120
      23: aload_1
      24: ldc           #77                 // String ,
      26: invokevirtual #78                 // Method java/lang/String.split:(Ljava/lang/String;)[Ljava/lang/String;
      29: astore_3
      30: aload_3
      31: astore        4
      33: aload         4
      35: arraylength
      36: istore        5
      38: iconst_0
      39: istore        6
      41: iload         6
      43: iload         5
      45: if_icmpge     109
      48: aload         4
      50: iload         6
      52: aaload
      53: astore        7
      55: aload         7
      57: invokevirtual #79                 // Method java/lang/String.trim:()Ljava/lang/String;
      60: getstatic     #80                 // Field java/util/Locale.ENGLISH:Ljava/util/Locale;
      63: invokevirtual #81                 // Method java/lang/String.toLowerCase:(Ljava/util/Locale;)Ljava/lang/String;
      66: astore        8
      68: aload_2
      69: aload         8
      71: invokeinterface #82,  2           // InterfaceMethod java/util/Set.contains:(Ljava/lang/Object;)Z
      76: ifeq          91
      79: aload_2
      80: aload         8
      82: invokeinterface #83,  2           // InterfaceMethod java/util/Set.remove:(Ljava/lang/Object;)Z
      87: pop
      88: goto          103
      91: aload_0
      92: getfield      #20                 // Field allowedTrailerHeaders:Ljava/util/Set;
      95: aload         8
      97: invokeinterface #84,  2           // InterfaceMethod java/util/Set.add:(Ljava/lang/Object;)Z
     102: pop
     103: iinc          6, 1
     106: goto          41
     109: aload_0
     110: getfield      #20                 // Field allowedTrailerHeaders:Ljava/util/Set;
     113: aload_2
     114: invokeinterface #85,  2           // InterfaceMethod java/util/Set.removeAll:(Ljava/util/Collection;)Z
     119: pop
     120: return

  public java.lang.String getAllowedTrailerHeaders();
    Code:
       0: new           #86                 // class java/util/ArrayList
       3: dup
       4: aload_0
       5: getfield      #20                 // Field allowedTrailerHeaders:Ljava/util/Set;
       8: invokeinterface #87,  1           // InterfaceMethod java/util/Set.size:()I
      13: invokespecial #88                 // Method java/util/ArrayList."<init>":(I)V
      16: astore_1
      17: aload_1
      18: aload_0
      19: getfield      #20                 // Field allowedTrailerHeaders:Ljava/util/Set;
      22: invokeinterface #89,  2           // InterfaceMethod java/util/List.addAll:(Ljava/util/Collection;)Z
      27: pop
      28: aload_1
      29: invokestatic  #90                 // Method org/apache/tomcat/util/buf/StringUtils.join:(Ljava/util/Collection;)Ljava/lang/String;
      32: areturn

  public void setMaxHeaderCount(int);
    Code:
       0: aload_0
       1: iload_1
       2: putfield      #21                 // Field maxHeaderCount:I
       5: return

  public int getMaxHeaderCount();
    Code:
       0: aload_0
       1: getfield      #21                 // Field maxHeaderCount:I
       4: ireturn

  public void setMaxHeaderSize(int);
    Code:
       0: aload_0
       1: iload_1
       2: putfield      #22                 // Field maxHeaderSize:I
       5: return

  public int getMaxHeaderSize();
    Code:
       0: aload_0
       1: getfield      #22                 // Field maxHeaderSize:I
       4: ireturn

  public void setMaxTrailerCount(int);
    Code:
       0: aload_0
       1: iload_1
       2: putfield      #23                 // Field maxTrailerCount:I
       5: return

  public int getMaxTrailerCount();
    Code:
       0: aload_0
       1: getfield      #23                 // Field maxTrailerCount:I
       4: ireturn

  public void setMaxTrailerSize(int);
    Code:
       0: aload_0
       1: iload_1
       2: putfield      #24                 // Field maxTrailerSize:I
       5: return

  public int getMaxTrailerSize();
    Code:
       0: aload_0
       1: getfield      #24                 // Field maxTrailerSize:I
       4: ireturn

  public int getOverheadCountFactor();
    Code:
       0: aload_0
       1: getfield      #25                 // Field overheadCountFactor:I
       4: ireturn

  public void setOverheadCountFactor(int);
    Code:
       0: aload_0
       1: iload_1
       2: putfield      #25                 // Field overheadCountFactor:I
       5: return

  public int getOverheadContinuationThreshold();
    Code:
       0: aload_0
       1: getfield      #26                 // Field overheadContinuationThreshold:I
       4: ireturn

  public void setOverheadContinuationThreshold(int);
    Code:
       0: aload_0
       1: iload_1
       2: putfield      #26                 // Field overheadContinuationThreshold:I
       5: return

  public int getOverheadDataThreshold();
    Code:
       0: aload_0
       1: getfield      #27                 // Field overheadDataThreshold:I
       4: ireturn

  public void setOverheadDataThreshold(int);
    Code:
       0: aload_0
       1: iload_1
       2: putfield      #27                 // Field overheadDataThreshold:I
       5: return

  public int getOverheadWindowUpdateThreshold();
    Code:
       0: aload_0
       1: getfield      #28                 // Field overheadWindowUpdateThreshold:I
       4: ireturn

  public void setOverheadWindowUpdateThreshold(int);
    Code:
       0: aload_0
       1: iload_1
       2: putfield      #28                 // Field overheadWindowUpdateThreshold:I
       5: return

  public void setInitiatePingDisabled(boolean);
    Code:
       0: aload_0
       1: iload_1
       2: putfield      #29                 // Field initiatePingDisabled:Z
       5: return

  public void setCompression(java.lang.String);
    Code:
       0: aload_0
       1: getfield      #32                 // Field compressionConfig:Lorg/apache/coyote/CompressionConfig;
       4: aload_1
       5: invokevirtual #91                 // Method org/apache/coyote/CompressionConfig.setCompression:(Ljava/lang/String;)V
       8: return

  public java.lang.String getCompression();
    Code:
       0: aload_0
       1: getfield      #32                 // Field compressionConfig:Lorg/apache/coyote/CompressionConfig;
       4: invokevirtual #92                 // Method org/apache/coyote/CompressionConfig.getCompression:()Ljava/lang/String;
       7: areturn

  protected int getCompressionLevel();
    Code:
       0: aload_0
       1: getfield      #32                 // Field compressionConfig:Lorg/apache/coyote/CompressionConfig;
       4: invokevirtual #93                 // Method org/apache/coyote/CompressionConfig.getCompressionLevel:()I
       7: ireturn

  public java.lang.String getNoCompressionUserAgents();
    Code:
       0: aload_0
       1: getfield      #32                 // Field compressionConfig:Lorg/apache/coyote/CompressionConfig;
       4: invokevirtual #94                 // Method org/apache/coyote/CompressionConfig.getNoCompressionUserAgents:()Ljava/lang/String;
       7: areturn

  protected java.util.regex.Pattern getNoCompressionUserAgentsPattern();
    Code:
       0: aload_0
       1: getfield      #32                 // Field compressionConfig:Lorg/apache/coyote/CompressionConfig;
       4: invokevirtual #95                 // Method org/apache/coyote/CompressionConfig.getNoCompressionUserAgentsPattern:()Ljava/util/regex/Pattern;
       7: areturn

  public void setNoCompressionUserAgents(java.lang.String);
    Code:
       0: aload_0
       1: getfield      #32                 // Field compressionConfig:Lorg/apache/coyote/CompressionConfig;
       4: aload_1
       5: invokevirtual #96                 // Method org/apache/coyote/CompressionConfig.setNoCompressionUserAgents:(Ljava/lang/String;)V
       8: return

  public java.lang.String getCompressibleMimeType();
    Code:
       0: aload_0
       1: getfield      #32                 // Field compressionConfig:Lorg/apache/coyote/CompressionConfig;
       4: invokevirtual #97                 // Method org/apache/coyote/CompressionConfig.getCompressibleMimeType:()Ljava/lang/String;
       7: areturn

  public void setCompressibleMimeType(java.lang.String);
    Code:
       0: aload_0
       1: getfield      #32                 // Field compressionConfig:Lorg/apache/coyote/CompressionConfig;
       4: aload_1
       5: invokevirtual #98                 // Method org/apache/coyote/CompressionConfig.setCompressibleMimeType:(Ljava/lang/String;)V
       8: return

  public java.lang.String[] getCompressibleMimeTypes();
    Code:
       0: aload_0
       1: getfield      #32                 // Field compressionConfig:Lorg/apache/coyote/CompressionConfig;
       4: invokevirtual #99                 // Method org/apache/coyote/CompressionConfig.getCompressibleMimeTypes:()[Ljava/lang/String;
       7: areturn

  public int getCompressionMinSize();
    Code:
       0: aload_0
       1: getfield      #32                 // Field compressionConfig:Lorg/apache/coyote/CompressionConfig;
       4: invokevirtual #100                // Method org/apache/coyote/CompressionConfig.getCompressionMinSize:()I
       7: ireturn

  public void setCompressionMinSize(int);
    Code:
       0: aload_0
       1: getfield      #32                 // Field compressionConfig:Lorg/apache/coyote/CompressionConfig;
       4: iload_1
       5: invokevirtual #101                // Method org/apache/coyote/CompressionConfig.setCompressionMinSize:(I)V
       8: return

  public boolean getNoCompressionStrongETag();
    Code:
       0: aload_0
       1: getfield      #32                 // Field compressionConfig:Lorg/apache/coyote/CompressionConfig;
       4: invokevirtual #102                // Method org/apache/coyote/CompressionConfig.getNoCompressionStrongETag:()Z
       7: ireturn

  public void setNoCompressionStrongETag(boolean);
    Code:
       0: aload_0
       1: getfield      #32                 // Field compressionConfig:Lorg/apache/coyote/CompressionConfig;
       4: iload_1
       5: invokevirtual #103                // Method org/apache/coyote/CompressionConfig.setNoCompressionStrongETag:(Z)V
       8: return

  public boolean useCompression(org.apache.coyote.Request, org.apache.coyote.Response);
    Code:
       0: aload_0
       1: getfield      #32                 // Field compressionConfig:Lorg/apache/coyote/CompressionConfig;
       4: aload_1
       5: aload_2
       6: invokevirtual #104                // Method org/apache/coyote/CompressionConfig.useCompression:(Lorg/apache/coyote/Request;Lorg/apache/coyote/Response;)Z
       9: ireturn

  public org.apache.coyote.http11.AbstractHttp11Protocol<?> getHttp11Protocol();
    Code:
       0: aload_0
       1: getfield      #33                 // Field http11Protocol:Lorg/apache/coyote/http11/AbstractHttp11Protocol;
       4: areturn

  public void setHttp11Protocol(org.apache.coyote.http11.AbstractHttp11Protocol<?>);
    Code:
       0: aload_0
       1: aload_1
       2: putfield      #33                 // Field http11Protocol:Lorg/apache/coyote/http11/AbstractHttp11Protocol;
       5: return

  static {};
    Code:
       0: ldc           #36                 // String h2
       2: getstatic     #105                // Field java/nio/charset/StandardCharsets.UTF_8:Ljava/nio/charset/Charset;
       5: invokevirtual #106                // Method java/lang/String.getBytes:(Ljava/nio/charset/Charset;)[B
       8: putstatic     #35                 // Field ALPN_IDENTIFIER:[B
      11: return
}
