Compiled from "OpenCensusUtils.java"
final class com.google.api.client.http.OpenCensusUtils$1 extends io.opencensus.trace.propagation.TextFormat$Setter<com.google.api.client.http.HttpHeaders> {
  com.google.api.client.http.OpenCensusUtils$1();
    Code:
       0: aload_0
       1: invokespecial #1                  // Method io/opencensus/trace/propagation/TextFormat$Setter."<init>":()V
       4: return

  public void put(com.google.api.client.http.HttpHeaders, java.lang.String, java.lang.String);
    Code:
       0: aload_1
       1: aload_2
       2: aload_3
       3: invokevirtual #2                  // Method com/google/api/client/http/HttpHeaders.set:(Ljava/lang/String;Ljava/lang/Object;)Lcom/google/api/client/http/HttpHeaders;
       6: pop
       7: return

  public void put(java.lang.Object, java.lang.String, java.lang.String);
    Code:
       0: aload_0
       1: aload_1
       2: checkcast     #3                  // class com/google/api/client/http/HttpHeaders
       5: aload_2
       6: aload_3
       7: invokevirtual #4                  // Method put:(Lcom/google/api/client/http/HttpHeaders;Ljava/lang/String;Ljava/lang/String;)V
      10: return
}
