Compiled from "FieldAccess.java"
public final class net.bytebuddy.implementation.bytecode.member.FieldAccess extends java.lang.Enum<net.bytebuddy.implementation.bytecode.member.FieldAccess> {
  public static final net.bytebuddy.implementation.bytecode.member.FieldAccess STATIC;

  public static final net.bytebuddy.implementation.bytecode.member.FieldAccess INSTANCE;

  private final int putterOpcode;

  private final int getterOpcode;

  private final int targetSizeChange;

  private static final net.bytebuddy.implementation.bytecode.member.FieldAccess[] $VALUES;

  public static net.bytebuddy.implementation.bytecode.member.FieldAccess[] values();
    Code:
       0: getstatic     #55                 // Field $VALUES:[Lnet/bytebuddy/implementation/bytecode/member/FieldAccess;
       3: invokevirtual #60                 // Method "[Lnet/bytebuddy/implementation/bytecode/member/FieldAccess;".clone:()Ljava/lang/Object;
       6: checkcast     #56                 // class "[Lnet/bytebuddy/implementation/bytecode/member/FieldAccess;"
       9: areturn

  public static net.bytebuddy.implementation.bytecode.member.FieldAccess valueOf(java.lang.String);
    Code:
       0: ldc           #2                  // class net/bytebuddy/implementation/bytecode/member/FieldAccess
       2: aload_0
       3: invokestatic  #65                 // Method java/lang/Enum.valueOf:(Ljava/lang/Class;Ljava/lang/String;)Ljava/lang/Enum;
       6: checkcast     #2                  // class net/bytebuddy/implementation/bytecode/member/FieldAccess
       9: areturn

  private net.bytebuddy.implementation.bytecode.member.FieldAccess(int, int, net.bytebuddy.implementation.bytecode.StackSize);
    Code:
       0: aload_0
       1: aload_1
       2: iload_2
       3: invokespecial #73                 // Method java/lang/Enum."<init>":(Ljava/lang/String;I)V
       6: aload_0
       7: iload_3
       8: putfield      #75                 // Field putterOpcode:I
      11: aload_0
      12: iload         4
      14: putfield      #77                 // Field getterOpcode:I
      17: aload_0
      18: aload         5
      20: invokevirtual #83                 // Method net/bytebuddy/implementation/bytecode/StackSize.getSize:()I
      23: putfield      #85                 // Field targetSizeChange:I
      26: return

  public static net.bytebuddy.implementation.bytecode.StackManipulation forEnumeration(net.bytebuddy.description.enumeration.EnumerationDescription);
    Code:
       0: aload_0
       1: invokeinterface #95,  1           // InterfaceMethod net/bytebuddy/description/enumeration/EnumerationDescription.getEnumerationType:()Lnet/bytebuddy/description/type/TypeDescription;
       6: invokeinterface #99,  1           // InterfaceMethod net/bytebuddy/description/type/TypeDescription.getDeclaredFields:()Lnet/bytebuddy/description/field/FieldList;
      11: aload_0
      12: invokeinterface #103,  1          // InterfaceMethod net/bytebuddy/description/enumeration/EnumerationDescription.getValue:()Ljava/lang/String;
      17: invokestatic  #109                // Method net/bytebuddy/matcher/ElementMatchers.named:(Ljava/lang/String;)Lnet/bytebuddy/matcher/ElementMatcher$Junction;
      20: invokeinterface #115,  2          // InterfaceMethod net/bytebuddy/description/field/FieldList.filter:(Lnet/bytebuddy/matcher/ElementMatcher;)Lnet/bytebuddy/matcher/FilterableList;
      25: checkcast     #111                // class net/bytebuddy/description/field/FieldList
      28: astore_1
      29: aload_1
      30: invokeinterface #118,  1          // InterfaceMethod net/bytebuddy/description/field/FieldList.size:()I
      35: iconst_1
      36: if_icmpne     90
      39: aload_1
      40: invokeinterface #121,  1          // InterfaceMethod net/bytebuddy/description/field/FieldList.getOnly:()Ljava/lang/Object;
      45: checkcast     #19                 // class net/bytebuddy/description/field/FieldDescription$InDefinedShape
      48: invokeinterface #125,  1          // InterfaceMethod net/bytebuddy/description/field/FieldDescription$InDefinedShape.isStatic:()Z
      53: ifeq          90
      56: aload_1
      57: invokeinterface #121,  1          // InterfaceMethod net/bytebuddy/description/field/FieldList.getOnly:()Ljava/lang/Object;
      62: checkcast     #19                 // class net/bytebuddy/description/field/FieldDescription$InDefinedShape
      65: invokeinterface #128,  1          // InterfaceMethod net/bytebuddy/description/field/FieldDescription$InDefinedShape.isPublic:()Z
      70: ifeq          90
      73: aload_1
      74: invokeinterface #121,  1          // InterfaceMethod net/bytebuddy/description/field/FieldList.getOnly:()Ljava/lang/Object;
      79: checkcast     #19                 // class net/bytebuddy/description/field/FieldDescription$InDefinedShape
      82: invokeinterface #131,  1          // InterfaceMethod net/bytebuddy/description/field/FieldDescription$InDefinedShape.isEnum:()Z
      87: ifne          96
      90: getstatic     #134                // Field net/bytebuddy/implementation/bytecode/StackManipulation$Illegal.INSTANCE:Lnet/bytebuddy/implementation/bytecode/StackManipulation$Illegal;
      93: goto          123
      96: new           #10                 // class net/bytebuddy/implementation/bytecode/member/FieldAccess$AccessDispatcher
      99: dup
     100: getstatic     #136                // Field STATIC:Lnet/bytebuddy/implementation/bytecode/member/FieldAccess;
     103: dup
     104: invokevirtual #142                // Method java/lang/Object.getClass:()Ljava/lang/Class;
     107: pop
     108: aload_1
     109: invokeinterface #121,  1          // InterfaceMethod net/bytebuddy/description/field/FieldList.getOnly:()Ljava/lang/Object;
     114: checkcast     #19                 // class net/bytebuddy/description/field/FieldDescription$InDefinedShape
     117: invokespecial #145                // Method net/bytebuddy/implementation/bytecode/member/FieldAccess$AccessDispatcher."<init>":(Lnet/bytebuddy/implementation/bytecode/member/FieldAccess;Lnet/bytebuddy/description/field/FieldDescription$InDefinedShape;)V
     120: invokevirtual #149                // Method net/bytebuddy/implementation/bytecode/member/FieldAccess$AccessDispatcher.read:()Lnet/bytebuddy/implementation/bytecode/StackManipulation;
     123: areturn

  public static net.bytebuddy.implementation.bytecode.member.FieldAccess$Defined forField(net.bytebuddy.description.field.FieldDescription$InDefinedShape);
    Code:
       0: aload_0
       1: invokeinterface #125,  1          // InterfaceMethod net/bytebuddy/description/field/FieldDescription$InDefinedShape.isStatic:()Z
       6: ifeq          28
       9: new           #10                 // class net/bytebuddy/implementation/bytecode/member/FieldAccess$AccessDispatcher
      12: dup
      13: getstatic     #136                // Field STATIC:Lnet/bytebuddy/implementation/bytecode/member/FieldAccess;
      16: dup
      17: invokevirtual #142                // Method java/lang/Object.getClass:()Ljava/lang/Class;
      20: pop
      21: aload_0
      22: invokespecial #145                // Method net/bytebuddy/implementation/bytecode/member/FieldAccess$AccessDispatcher."<init>":(Lnet/bytebuddy/implementation/bytecode/member/FieldAccess;Lnet/bytebuddy/description/field/FieldDescription$InDefinedShape;)V
      25: goto          44
      28: new           #10                 // class net/bytebuddy/implementation/bytecode/member/FieldAccess$AccessDispatcher
      31: dup
      32: getstatic     #158                // Field INSTANCE:Lnet/bytebuddy/implementation/bytecode/member/FieldAccess;
      35: dup
      36: invokevirtual #142                // Method java/lang/Object.getClass:()Ljava/lang/Class;
      39: pop
      40: aload_0
      41: invokespecial #145                // Method net/bytebuddy/implementation/bytecode/member/FieldAccess$AccessDispatcher."<init>":(Lnet/bytebuddy/implementation/bytecode/member/FieldAccess;Lnet/bytebuddy/description/field/FieldDescription$InDefinedShape;)V
      44: areturn

  public static net.bytebuddy.implementation.bytecode.member.FieldAccess$Defined forField(net.bytebuddy.description.field.FieldDescription);
    Code:
       0: aload_0
       1: invokeinterface #165,  1          // InterfaceMethod net/bytebuddy/description/field/FieldDescription.asDefined:()Lnet/bytebuddy/description/ByteCodeElement$TypeDependant;
       6: checkcast     #19                 // class net/bytebuddy/description/field/FieldDescription$InDefinedShape
       9: astore_1
      10: aload_0
      11: invokeinterface #169,  1          // InterfaceMethod net/bytebuddy/description/field/FieldDescription.getType:()Lnet/bytebuddy/description/type/TypeDescription$Generic;
      16: invokeinterface #172,  1          // InterfaceMethod net/bytebuddy/description/type/TypeDescription$Generic.asErasure:()Lnet/bytebuddy/description/type/TypeDescription;
      21: aload_1
      22: invokeinterface #173,  1          // InterfaceMethod net/bytebuddy/description/field/FieldDescription$InDefinedShape.getType:()Lnet/bytebuddy/description/type/TypeDescription$Generic;
      27: invokeinterface #172,  1          // InterfaceMethod net/bytebuddy/description/type/TypeDescription$Generic.asErasure:()Lnet/bytebuddy/description/type/TypeDescription;
      32: invokevirtual #177                // Method java/lang/Object.equals:(Ljava/lang/Object;)Z
      35: ifeq          45
      38: aload_1
      39: invokestatic  #179                // Method forField:(Lnet/bytebuddy/description/field/FieldDescription$InDefinedShape;)Lnet/bytebuddy/implementation/bytecode/member/FieldAccess$Defined;
      42: goto          53
      45: aload_0
      46: aload_1
      47: invokestatic  #179                // Method forField:(Lnet/bytebuddy/description/field/FieldDescription$InDefinedShape;)Lnet/bytebuddy/implementation/bytecode/member/FieldAccess$Defined;
      50: invokestatic  #183                // Method net/bytebuddy/implementation/bytecode/member/FieldAccess$OfGenericField.of:(Lnet/bytebuddy/description/field/FieldDescription;Lnet/bytebuddy/implementation/bytecode/member/FieldAccess$Defined;)Lnet/bytebuddy/implementation/bytecode/member/FieldAccess$Defined;
      53: areturn

  static int access$200(net.bytebuddy.implementation.bytecode.member.FieldAccess);
    Code:
       0: aload_0
       1: getfield      #77                 // Field getterOpcode:I
       4: ireturn

  static int access$300(net.bytebuddy.implementation.bytecode.member.FieldAccess);
    Code:
       0: aload_0
       1: getfield      #85                 // Field targetSizeChange:I
       4: ireturn

  static int access$400(net.bytebuddy.implementation.bytecode.member.FieldAccess);
    Code:
       0: aload_0
       1: getfield      #75                 // Field putterOpcode:I
       4: ireturn

  static {};
    Code:
       0: new           #2                  // class net/bytebuddy/implementation/bytecode/member/FieldAccess
       3: dup
       4: ldc           #193                // String STATIC
       6: iconst_0
       7: sipush        179
      10: sipush        178
      13: getstatic     #196                // Field net/bytebuddy/implementation/bytecode/StackSize.ZERO:Lnet/bytebuddy/implementation/bytecode/StackSize;
      16: invokespecial #198                // Method "<init>":(Ljava/lang/String;IIILnet/bytebuddy/implementation/bytecode/StackSize;)V
      19: putstatic     #136                // Field STATIC:Lnet/bytebuddy/implementation/bytecode/member/FieldAccess;
      22: new           #2                  // class net/bytebuddy/implementation/bytecode/member/FieldAccess
      25: dup
      26: ldc           #199                // String INSTANCE
      28: iconst_1
      29: sipush        181
      32: sipush        180
      35: getstatic     #202                // Field net/bytebuddy/implementation/bytecode/StackSize.SINGLE:Lnet/bytebuddy/implementation/bytecode/StackSize;
      38: invokespecial #198                // Method "<init>":(Ljava/lang/String;IIILnet/bytebuddy/implementation/bytecode/StackSize;)V
      41: putstatic     #158                // Field INSTANCE:Lnet/bytebuddy/implementation/bytecode/member/FieldAccess;
      44: iconst_2
      45: anewarray     #2                  // class net/bytebuddy/implementation/bytecode/member/FieldAccess
      48: dup
      49: iconst_0
      50: getstatic     #136                // Field STATIC:Lnet/bytebuddy/implementation/bytecode/member/FieldAccess;
      53: aastore
      54: dup
      55: iconst_1
      56: getstatic     #158                // Field INSTANCE:Lnet/bytebuddy/implementation/bytecode/member/FieldAccess;
      59: aastore
      60: putstatic     #55                 // Field $VALUES:[Lnet/bytebuddy/implementation/bytecode/member/FieldAccess;
      63: return
}
