Compiled from "MethodVariableAccess.java"
public class net.bytebuddy.implementation.bytecode.member.MethodVariableAccess$MethodLoading implements net.bytebuddy.implementation.bytecode.StackManipulation {
  private final net.bytebuddy.description.method.MethodDescription methodDescription;

  private final net.bytebuddy.implementation.bytecode.member.MethodVariableAccess$MethodLoading$TypeCastingHandler typeCastingHandler;

  protected net.bytebuddy.implementation.bytecode.member.MethodVariableAccess$MethodLoading(net.bytebuddy.description.method.MethodDescription, net.bytebuddy.implementation.bytecode.member.MethodVariableAccess$MethodLoading$TypeCastingHandler);
    Code:
       0: aload_0
       1: invokespecial #47                 // Method java/lang/Object."<init>":()V
       4: aload_0
       5: aload_1
       6: putfield      #49                 // Field methodDescription:Lnet/bytebuddy/description/method/MethodDescription;
       9: aload_0
      10: aload_2
      11: putfield      #51                 // Field typeCastingHandler:Lnet/bytebuddy/implementation/bytecode/member/MethodVariableAccess$MethodLoading$TypeCastingHandler;
      14: return

  public boolean isValid();
    Code:
       0: iconst_1
       1: ireturn

  public net.bytebuddy.implementation.bytecode.StackManipulation$Size apply(net.bytebuddy.jar.asm.MethodVisitor, net.bytebuddy.implementation.Implementation$Context);
    Code:
       0: new           #59                 // class java/util/ArrayList
       3: dup
       4: invokespecial #60                 // Method java/util/ArrayList."<init>":()V
       7: astore_3
       8: aload_0
       9: getfield      #49                 // Field methodDescription:Lnet/bytebuddy/description/method/MethodDescription;
      12: invokeinterface #66,  1           // InterfaceMethod net/bytebuddy/description/method/MethodDescription.getParameters:()Lnet/bytebuddy/description/method/ParameterList;
      17: invokeinterface #72,  1           // InterfaceMethod net/bytebuddy/description/method/ParameterList.iterator:()Ljava/util/Iterator;
      22: astore        4
      24: aload         4
      26: invokeinterface #77,  1           // InterfaceMethod java/util/Iterator.hasNext:()Z
      31: ifeq          110
      34: aload         4
      36: invokeinterface #81,  1           // InterfaceMethod java/util/Iterator.next:()Ljava/lang/Object;
      41: checkcast     #83                 // class net/bytebuddy/description/method/ParameterDescription
      44: astore        5
      46: aload         5
      48: invokeinterface #87,  1           // InterfaceMethod net/bytebuddy/description/method/ParameterDescription.getType:()Lnet/bytebuddy/description/type/TypeDescription$Generic;
      53: invokeinterface #91,  1           // InterfaceMethod net/bytebuddy/description/type/TypeDescription$Generic.asErasure:()Lnet/bytebuddy/description/type/TypeDescription;
      58: astore        6
      60: aload_3
      61: aload         6
      63: invokestatic  #95                 // Method net/bytebuddy/implementation/bytecode/member/MethodVariableAccess.of:(Lnet/bytebuddy/description/type/TypeDefinition;)Lnet/bytebuddy/implementation/bytecode/member/MethodVariableAccess;
      66: aload         5
      68: invokeinterface #99,  1           // InterfaceMethod net/bytebuddy/description/method/ParameterDescription.getOffset:()I
      73: invokevirtual #103                // Method net/bytebuddy/implementation/bytecode/member/MethodVariableAccess.loadFrom:(I)Lnet/bytebuddy/implementation/bytecode/StackManipulation;
      76: invokeinterface #109,  2          // InterfaceMethod java/util/List.add:(Ljava/lang/Object;)Z
      81: pop
      82: aload_3
      83: aload_0
      84: getfield      #51                 // Field typeCastingHandler:Lnet/bytebuddy/implementation/bytecode/member/MethodVariableAccess$MethodLoading$TypeCastingHandler;
      87: aload         6
      89: aload         5
      91: invokeinterface #112,  1          // InterfaceMethod net/bytebuddy/description/method/ParameterDescription.getIndex:()I
      96: invokeinterface #116,  3          // InterfaceMethod net/bytebuddy/implementation/bytecode/member/MethodVariableAccess$MethodLoading$TypeCastingHandler.ofIndex:(Lnet/bytebuddy/description/type/TypeDescription;I)Lnet/bytebuddy/implementation/bytecode/StackManipulation;
     101: invokeinterface #109,  2          // InterfaceMethod java/util/List.add:(Ljava/lang/Object;)Z
     106: pop
     107: goto          24
     110: new           #26                 // class net/bytebuddy/implementation/bytecode/StackManipulation$Compound
     113: dup
     114: aload_3
     115: invokespecial #119                // Method net/bytebuddy/implementation/bytecode/StackManipulation$Compound."<init>":(Ljava/util/List;)V
     118: aload_1
     119: aload_2
     120: invokevirtual #121                // Method net/bytebuddy/implementation/bytecode/StackManipulation$Compound.apply:(Lnet/bytebuddy/jar/asm/MethodVisitor;Lnet/bytebuddy/implementation/Implementation$Context;)Lnet/bytebuddy/implementation/bytecode/StackManipulation$Size;
     123: areturn

  public net.bytebuddy.implementation.bytecode.StackManipulation prependThisReference();
    Code:
       0: aload_0
       1: getfield      #49                 // Field methodDescription:Lnet/bytebuddy/description/method/MethodDescription;
       4: invokeinterface #137,  1          // InterfaceMethod net/bytebuddy/description/method/MethodDescription.isStatic:()Z
       9: ifeq          16
      12: aload_0
      13: goto          37
      16: new           #26                 // class net/bytebuddy/implementation/bytecode/StackManipulation$Compound
      19: dup
      20: iconst_2
      21: anewarray     #6                  // class net/bytebuddy/implementation/bytecode/StackManipulation
      24: dup
      25: iconst_0
      26: invokestatic  #140                // Method net/bytebuddy/implementation/bytecode/member/MethodVariableAccess.loadThis:()Lnet/bytebuddy/implementation/bytecode/StackManipulation;
      29: aastore
      30: dup
      31: iconst_1
      32: aload_0
      33: aastore
      34: invokespecial #143                // Method net/bytebuddy/implementation/bytecode/StackManipulation$Compound."<init>":([Lnet/bytebuddy/implementation/bytecode/StackManipulation;)V
      37: areturn

  public net.bytebuddy.implementation.bytecode.member.MethodVariableAccess$MethodLoading asBridgeOf(net.bytebuddy.description.method.MethodDescription);
    Code:
       0: new           #2                  // class net/bytebuddy/implementation/bytecode/member/MethodVariableAccess$MethodLoading
       3: dup
       4: aload_0
       5: getfield      #49                 // Field methodDescription:Lnet/bytebuddy/description/method/MethodDescription;
       8: new           #29                 // class net/bytebuddy/implementation/bytecode/member/MethodVariableAccess$MethodLoading$TypeCastingHandler$ForBridgeTarget
      11: dup
      12: aload_1
      13: invokespecial #148                // Method net/bytebuddy/implementation/bytecode/member/MethodVariableAccess$MethodLoading$TypeCastingHandler$ForBridgeTarget."<init>":(Lnet/bytebuddy/description/method/MethodDescription;)V
      16: invokespecial #150                // Method "<init>":(Lnet/bytebuddy/description/method/MethodDescription;Lnet/bytebuddy/implementation/bytecode/member/MethodVariableAccess$MethodLoading$TypeCastingHandler;)V
      19: areturn

  public boolean equals(java.lang.Object);
    Code:
       0: aload_0
       1: aload_1
       2: if_acmpne     7
       5: iconst_1
       6: ireturn
       7: aload_1
       8: ifnonnull     13
      11: iconst_0
      12: ireturn
      13: aload_0
      14: invokevirtual #156                // Method java/lang/Object.getClass:()Ljava/lang/Class;
      17: aload_1
      18: invokevirtual #156                // Method java/lang/Object.getClass:()Ljava/lang/Class;
      21: if_acmpeq     26
      24: iconst_0
      25: ireturn
      26: aload_0
      27: getfield      #49                 // Field methodDescription:Lnet/bytebuddy/description/method/MethodDescription;
      30: aload_1
      31: checkcast     #2                  // class net/bytebuddy/implementation/bytecode/member/MethodVariableAccess$MethodLoading
      34: getfield      #49                 // Field methodDescription:Lnet/bytebuddy/description/method/MethodDescription;
      37: invokevirtual #158                // Method java/lang/Object.equals:(Ljava/lang/Object;)Z
      40: ifne          45
      43: iconst_0
      44: ireturn
      45: aload_0
      46: getfield      #51                 // Field typeCastingHandler:Lnet/bytebuddy/implementation/bytecode/member/MethodVariableAccess$MethodLoading$TypeCastingHandler;
      49: aload_1
      50: checkcast     #2                  // class net/bytebuddy/implementation/bytecode/member/MethodVariableAccess$MethodLoading
      53: getfield      #51                 // Field typeCastingHandler:Lnet/bytebuddy/implementation/bytecode/member/MethodVariableAccess$MethodLoading$TypeCastingHandler;
      56: invokevirtual #158                // Method java/lang/Object.equals:(Ljava/lang/Object;)Z
      59: ifne          64
      62: iconst_0
      63: ireturn
      64: iconst_1
      65: ireturn

  public int hashCode();
    Code:
       0: bipush        17
       2: bipush        31
       4: imul
       5: aload_0
       6: getfield      #49                 // Field methodDescription:Lnet/bytebuddy/description/method/MethodDescription;
       9: invokevirtual #161                // Method java/lang/Object.hashCode:()I
      12: iadd
      13: bipush        31
      15: imul
      16: aload_0
      17: getfield      #51                 // Field typeCastingHandler:Lnet/bytebuddy/implementation/bytecode/member/MethodVariableAccess$MethodLoading$TypeCastingHandler;
      20: invokevirtual #161                // Method java/lang/Object.hashCode:()I
      23: iadd
      24: ireturn
}
