Compiled from "PatternParseException.java"
public class org.springframework.web.util.pattern.PatternParseException extends java.lang.IllegalArgumentException {
  private final int position;

  private final char[] pattern;

  private final org.springframework.web.util.pattern.PatternParseException$PatternMessage messageType;

  private final java.lang.Object[] inserts;

  org.springframework.web.util.pattern.PatternParseException(int, char[], org.springframework.web.util.pattern.PatternParseException$PatternMessage, java.lang.Object...);
    Code:
       0: aload_0
       1: aload_3
       2: aload         4
       4: invokevirtual #1                  // Method org/springframework/web/util/pattern/PatternParseException$PatternMessage.formatMessage:([Ljava/lang/Object;)Ljava/lang/String;
       7: invokespecial #2                  // Method java/lang/IllegalArgumentException."<init>":(Ljava/lang/String;)V
      10: aload_0
      11: iload_1
      12: putfield      #3                  // Field position:I
      15: aload_0
      16: aload_2
      17: putfield      #4                  // Field pattern:[C
      20: aload_0
      21: aload_3
      22: putfield      #5                  // Field messageType:Lorg/springframework/web/util/pattern/PatternParseException$PatternMessage;
      25: aload_0
      26: aload         4
      28: putfield      #6                  // Field inserts:[Ljava/lang/Object;
      31: return

  org.springframework.web.util.pattern.PatternParseException(java.lang.Throwable, int, char[], org.springframework.web.util.pattern.PatternParseException$PatternMessage, java.lang.Object...);
    Code:
       0: aload_0
       1: aload         4
       3: aload         5
       5: invokevirtual #1                  // Method org/springframework/web/util/pattern/PatternParseException$PatternMessage.formatMessage:([Ljava/lang/Object;)Ljava/lang/String;
       8: aload_1
       9: invokespecial #7                  // Method java/lang/IllegalArgumentException."<init>":(Ljava/lang/String;Ljava/lang/Throwable;)V
      12: aload_0
      13: iload_2
      14: putfield      #3                  // Field position:I
      17: aload_0
      18: aload_3
      19: putfield      #4                  // Field pattern:[C
      22: aload_0
      23: aload         4
      25: putfield      #5                  // Field messageType:Lorg/springframework/web/util/pattern/PatternParseException$PatternMessage;
      28: aload_0
      29: aload         5
      31: putfield      #6                  // Field inserts:[Ljava/lang/Object;
      34: return

  public java.lang.String getMessage();
    Code:
       0: aload_0
       1: getfield      #5                  // Field messageType:Lorg/springframework/web/util/pattern/PatternParseException$PatternMessage;
       4: aload_0
       5: getfield      #6                  // Field inserts:[Ljava/lang/Object;
       8: invokevirtual #1                  // Method org/springframework/web/util/pattern/PatternParseException$PatternMessage.formatMessage:([Ljava/lang/Object;)Ljava/lang/String;
      11: areturn

  public java.lang.String toDetailedString();
    Code:
       0: new           #8                  // class java/lang/StringBuilder
       3: dup
       4: invokespecial #9                  // Method java/lang/StringBuilder."<init>":()V
       7: astore_1
       8: aload_1
       9: aload_0
      10: getfield      #4                  // Field pattern:[C
      13: invokevirtual #10                 // Method java/lang/StringBuilder.append:([C)Ljava/lang/StringBuilder;
      16: bipush        10
      18: invokevirtual #11                 // Method java/lang/StringBuilder.append:(C)Ljava/lang/StringBuilder;
      21: pop
      22: iconst_0
      23: istore_2
      24: iload_2
      25: aload_0
      26: getfield      #3                  // Field position:I
      29: if_icmpge     45
      32: aload_1
      33: bipush        32
      35: invokevirtual #11                 // Method java/lang/StringBuilder.append:(C)Ljava/lang/StringBuilder;
      38: pop
      39: iinc          2, 1
      42: goto          24
      45: aload_1
      46: ldc           #12                 // String ^\n
      48: invokevirtual #13                 // Method java/lang/StringBuilder.append:(Ljava/lang/String;)Ljava/lang/StringBuilder;
      51: pop
      52: aload_1
      53: aload_0
      54: invokevirtual #14                 // Method getMessage:()Ljava/lang/String;
      57: invokevirtual #13                 // Method java/lang/StringBuilder.append:(Ljava/lang/String;)Ljava/lang/StringBuilder;
      60: pop
      61: aload_1
      62: invokevirtual #15                 // Method java/lang/StringBuilder.toString:()Ljava/lang/String;
      65: areturn

  public int getPosition();
    Code:
       0: aload_0
       1: getfield      #3                  // Field position:I
       4: ireturn

  public org.springframework.web.util.pattern.PatternParseException$PatternMessage getMessageType();
    Code:
       0: aload_0
       1: getfield      #5                  // Field messageType:Lorg/springframework/web/util/pattern/PatternParseException$PatternMessage;
       4: areturn

  public java.lang.Object[] getInserts();
    Code:
       0: aload_0
       1: getfield      #6                  // Field inserts:[Ljava/lang/Object;
       4: areturn
}
