Compiled from "AbstractRangeSet.java"
abstract class com.google.common.collect.AbstractRangeSet<C extends java.lang.Comparable> implements com.google.common.collect.RangeSet<C> {
  com.google.common.collect.AbstractRangeSet();
    Code:
       0: aload_0
       1: invokespecial #1                  // Method java/lang/Object."<init>":()V
       4: return

  public boolean contains(C);
    Code:
       0: aload_0
       1: aload_1
       2: invokevirtual #2                  // Method rangeContaining:(Ljava/lang/Comparable;)Lcom/google/common/collect/Range;
       5: ifnull        12
       8: iconst_1
       9: goto          13
      12: iconst_0
      13: ireturn

  public abstract com.google.common.collect.Range<C> rangeContaining(C);

  public boolean isEmpty();
    Code:
       0: aload_0
       1: invokevirtual #3                  // Method asRanges:()Ljava/util/Set;
       4: invokeinterface #4,  1            // InterfaceMethod java/util/Set.isEmpty:()Z
       9: ireturn

  public void add(com.google.common.collect.Range<C>);
    Code:
       0: new           #5                  // class java/lang/UnsupportedOperationException
       3: dup
       4: invokespecial #6                  // Method java/lang/UnsupportedOperationException."<init>":()V
       7: athrow

  public void remove(com.google.common.collect.Range<C>);
    Code:
       0: new           #5                  // class java/lang/UnsupportedOperationException
       3: dup
       4: invokespecial #6                  // Method java/lang/UnsupportedOperationException."<init>":()V
       7: athrow

  public void clear();
    Code:
       0: aload_0
       1: invokestatic  #7                  // Method com/google/common/collect/Range.all:()Lcom/google/common/collect/Range;
       4: invokevirtual #8                  // Method remove:(Lcom/google/common/collect/Range;)V
       7: return

  public boolean enclosesAll(com.google.common.collect.RangeSet<C>);
    Code:
       0: aload_1
       1: invokeinterface #9,  1            // InterfaceMethod com/google/common/collect/RangeSet.asRanges:()Ljava/util/Set;
       6: invokeinterface #10,  1           // InterfaceMethod java/util/Set.iterator:()Ljava/util/Iterator;
      11: astore_2
      12: aload_2
      13: invokeinterface #11,  1           // InterfaceMethod java/util/Iterator.hasNext:()Z
      18: ifeq          44
      21: aload_2
      22: invokeinterface #12,  1           // InterfaceMethod java/util/Iterator.next:()Ljava/lang/Object;
      27: checkcast     #13                 // class com/google/common/collect/Range
      30: astore_3
      31: aload_0
      32: aload_3
      33: invokevirtual #14                 // Method encloses:(Lcom/google/common/collect/Range;)Z
      36: ifne          41
      39: iconst_0
      40: ireturn
      41: goto          12
      44: iconst_1
      45: ireturn

  public void addAll(com.google.common.collect.RangeSet<C>);
    Code:
       0: aload_1
       1: invokeinterface #9,  1            // InterfaceMethod com/google/common/collect/RangeSet.asRanges:()Ljava/util/Set;
       6: invokeinterface #10,  1           // InterfaceMethod java/util/Set.iterator:()Ljava/util/Iterator;
      11: astore_2
      12: aload_2
      13: invokeinterface #11,  1           // InterfaceMethod java/util/Iterator.hasNext:()Z
      18: ifeq          39
      21: aload_2
      22: invokeinterface #12,  1           // InterfaceMethod java/util/Iterator.next:()Ljava/lang/Object;
      27: checkcast     #13                 // class com/google/common/collect/Range
      30: astore_3
      31: aload_0
      32: aload_3
      33: invokevirtual #15                 // Method add:(Lcom/google/common/collect/Range;)V
      36: goto          12
      39: return

  public void removeAll(com.google.common.collect.RangeSet<C>);
    Code:
       0: aload_1
       1: invokeinterface #9,  1            // InterfaceMethod com/google/common/collect/RangeSet.asRanges:()Ljava/util/Set;
       6: invokeinterface #10,  1           // InterfaceMethod java/util/Set.iterator:()Ljava/util/Iterator;
      11: astore_2
      12: aload_2
      13: invokeinterface #11,  1           // InterfaceMethod java/util/Iterator.hasNext:()Z
      18: ifeq          39
      21: aload_2
      22: invokeinterface #12,  1           // InterfaceMethod java/util/Iterator.next:()Ljava/lang/Object;
      27: checkcast     #13                 // class com/google/common/collect/Range
      30: astore_3
      31: aload_0
      32: aload_3
      33: invokevirtual #8                  // Method remove:(Lcom/google/common/collect/Range;)V
      36: goto          12
      39: return

  public abstract boolean encloses(com.google.common.collect.Range<C>);

  public boolean equals(java.lang.Object);
    Code:
       0: aload_1
       1: aload_0
       2: if_acmpne     7
       5: iconst_1
       6: ireturn
       7: aload_1
       8: instanceof    #16                 // class com/google/common/collect/RangeSet
      11: ifeq          35
      14: aload_1
      15: checkcast     #16                 // class com/google/common/collect/RangeSet
      18: astore_2
      19: aload_0
      20: invokevirtual #3                  // Method asRanges:()Ljava/util/Set;
      23: aload_2
      24: invokeinterface #9,  1            // InterfaceMethod com/google/common/collect/RangeSet.asRanges:()Ljava/util/Set;
      29: invokeinterface #17,  2           // InterfaceMethod java/util/Set.equals:(Ljava/lang/Object;)Z
      34: ireturn
      35: iconst_0
      36: ireturn

  public final int hashCode();
    Code:
       0: aload_0
       1: invokevirtual #3                  // Method asRanges:()Ljava/util/Set;
       4: invokeinterface #18,  1           // InterfaceMethod java/util/Set.hashCode:()I
       9: ireturn

  public final java.lang.String toString();
    Code:
       0: aload_0
       1: invokevirtual #3                  // Method asRanges:()Ljava/util/Set;
       4: invokevirtual #19                 // Method java/lang/Object.toString:()Ljava/lang/String;
       7: areturn
}
