Compiled from "JsonTestersAutoConfiguration.java"
class org.springframework.boot.test.autoconfigure.json.JsonTestersAutoConfiguration$JsonTesterFactoryBean<T, M> implements org.springframework.beans.factory.FactoryBean<T> {
  private final java.lang.Class<?> objectType;

  private final M marshaller;

  org.springframework.boot.test.autoconfigure.json.JsonTestersAutoConfiguration$JsonTesterFactoryBean(java.lang.Class<?>, M);
    Code:
       0: aload_0
       1: invokespecial #1                  // Method java/lang/Object."<init>":()V
       4: aload_0
       5: aload_1
       6: putfield      #2                  // Field objectType:Ljava/lang/Class;
       9: aload_0
      10: aload_2
      11: putfield      #3                  // Field marshaller:Ljava/lang/Object;
      14: return

  public boolean isSingleton();
    Code:
       0: iconst_0
       1: ireturn

  public T getObject() throws java.lang.Exception;
    Code:
       0: aload_0
       1: getfield      #3                  // Field marshaller:Ljava/lang/Object;
       4: ifnonnull     32
       7: aload_0
       8: getfield      #2                  // Field objectType:Ljava/lang/Class;
      11: iconst_0
      12: anewarray     #4                  // class java/lang/Class
      15: invokevirtual #5                  // Method java/lang/Class.getDeclaredConstructor:([Ljava/lang/Class;)Ljava/lang/reflect/Constructor;
      18: astore_1
      19: aload_1
      20: invokestatic  #6                  // Method org/springframework/util/ReflectionUtils.makeAccessible:(Ljava/lang/reflect/Constructor;)V
      23: aload_1
      24: iconst_0
      25: anewarray     #7                  // class java/lang/Object
      28: invokestatic  #8                  // Method org/springframework/beans/BeanUtils.instantiateClass:(Ljava/lang/reflect/Constructor;[Ljava/lang/Object;)Ljava/lang/Object;
      31: areturn
      32: aload_0
      33: getfield      #2                  // Field objectType:Ljava/lang/Class;
      36: invokevirtual #9                  // Method java/lang/Class.getDeclaredConstructors:()[Ljava/lang/reflect/Constructor;
      39: astore_1
      40: aload_1
      41: astore_2
      42: aload_2
      43: arraylength
      44: istore_3
      45: iconst_0
      46: istore        4
      48: iload         4
      50: iload_3
      51: if_icmpge     115
      54: aload_2
      55: iload         4
      57: aaload
      58: astore        5
      60: aload         5
      62: invokevirtual #10                 // Method java/lang/reflect/Constructor.getParameterTypes:()[Ljava/lang/Class;
      65: arraylength
      66: iconst_1
      67: if_icmpne     109
      70: aload         5
      72: invokevirtual #10                 // Method java/lang/reflect/Constructor.getParameterTypes:()[Ljava/lang/Class;
      75: iconst_0
      76: aaload
      77: aload_0
      78: getfield      #3                  // Field marshaller:Ljava/lang/Object;
      81: invokevirtual #11                 // Method java/lang/Class.isInstance:(Ljava/lang/Object;)Z
      84: ifeq          109
      87: aload         5
      89: invokestatic  #6                  // Method org/springframework/util/ReflectionUtils.makeAccessible:(Ljava/lang/reflect/Constructor;)V
      92: aload         5
      94: iconst_1
      95: anewarray     #7                  // class java/lang/Object
      98: dup
      99: iconst_0
     100: aload_0
     101: getfield      #3                  // Field marshaller:Ljava/lang/Object;
     104: aastore
     105: invokestatic  #8                  // Method org/springframework/beans/BeanUtils.instantiateClass:(Ljava/lang/reflect/Constructor;[Ljava/lang/Object;)Ljava/lang/Object;
     108: areturn
     109: iinc          4, 1
     112: goto          48
     115: new           #12                 // class java/lang/IllegalStateException
     118: dup
     119: new           #13                 // class java/lang/StringBuilder
     122: dup
     123: invokespecial #14                 // Method java/lang/StringBuilder."<init>":()V
     126: aload_0
     127: getfield      #2                  // Field objectType:Ljava/lang/Class;
     130: invokevirtual #15                 // Method java/lang/StringBuilder.append:(Ljava/lang/Object;)Ljava/lang/StringBuilder;
     133: ldc           #16                 // String  does not have a usable constructor
     135: invokevirtual #17                 // Method java/lang/StringBuilder.append:(Ljava/lang/String;)Ljava/lang/StringBuilder;
     138: invokevirtual #18                 // Method java/lang/StringBuilder.toString:()Ljava/lang/String;
     141: invokespecial #19                 // Method java/lang/IllegalStateException."<init>":(Ljava/lang/String;)V
     144: athrow

  public java.lang.Class<?> getObjectType();
    Code:
       0: aload_0
       1: getfield      #2                  // Field objectType:Ljava/lang/Class;
       4: areturn
}
