Compiled from "PasswdUserDatabase.java"
public final class org.apache.catalina.startup.PasswdUserDatabase implements org.apache.catalina.startup.UserDatabase {
  private static final org.apache.juli.logging.Log log;

  private static final org.apache.naming.StringManager sm;

  private static final java.lang.String PASSWORD_FILE;

  private final java.util.Hashtable<java.lang.String, java.lang.String> homes;

  private org.apache.catalina.startup.UserConfig userConfig;

  public org.apache.catalina.startup.PasswdUserDatabase();
    Code:
       0: aload_0
       1: invokespecial #1                  // Method java/lang/Object."<init>":()V
       4: aload_0
       5: new           #2                  // class java/util/Hashtable
       8: dup
       9: invokespecial #3                  // Method java/util/Hashtable."<init>":()V
      12: putfield      #4                  // Field homes:Ljava/util/Hashtable;
      15: aload_0
      16: aconst_null
      17: putfield      #5                  // Field userConfig:Lorg/apache/catalina/startup/UserConfig;
      20: return

  public org.apache.catalina.startup.UserConfig getUserConfig();
    Code:
       0: aload_0
       1: getfield      #5                  // Field userConfig:Lorg/apache/catalina/startup/UserConfig;
       4: areturn

  public void setUserConfig(org.apache.catalina.startup.UserConfig);
    Code:
       0: aload_0
       1: aload_1
       2: putfield      #5                  // Field userConfig:Lorg/apache/catalina/startup/UserConfig;
       5: aload_0
       6: invokespecial #6                  // Method init:()V
       9: return

  public java.lang.String getHome(java.lang.String);
    Code:
       0: aload_0
       1: getfield      #4                  // Field homes:Ljava/util/Hashtable;
       4: aload_1
       5: invokevirtual #7                  // Method java/util/Hashtable.get:(Ljava/lang/Object;)Ljava/lang/Object;
       8: checkcast     #8                  // class java/lang/String
      11: areturn

  public java.util.Enumeration<java.lang.String> getUsers();
    Code:
       0: aload_0
       1: getfield      #4                  // Field homes:Ljava/util/Hashtable;
       4: invokevirtual #9                  // Method java/util/Hashtable.keys:()Ljava/util/Enumeration;
       7: areturn

  private void init();
    Code:
       0: new           #10                 // class java/io/BufferedReader
       3: dup
       4: new           #11                 // class java/io/FileReader
       7: dup
       8: ldc           #12                 // String /etc/passwd
      10: invokespecial #13                 // Method java/io/FileReader."<init>":(Ljava/lang/String;)V
      13: invokespecial #14                 // Method java/io/BufferedReader."<init>":(Ljava/io/Reader;)V
      16: astore_1
      17: aconst_null
      18: astore_2
      19: aload_1
      20: invokevirtual #15                 // Method java/io/BufferedReader.readLine:()Ljava/lang/String;
      23: astore_3
      24: aload_3
      25: ifnull        87
      28: aload_3
      29: ldc           #16                 // String :
      31: invokevirtual #17                 // Method java/lang/String.split:(Ljava/lang/String;)[Ljava/lang/String;
      34: astore        4
      36: aload         4
      38: arraylength
      39: iconst_5
      40: if_icmple     79
      43: aload         4
      45: iconst_0
      46: aaload
      47: invokevirtual #18                 // Method java/lang/String.length:()I
      50: ifle          79
      53: aload         4
      55: iconst_5
      56: aaload
      57: invokevirtual #18                 // Method java/lang/String.length:()I
      60: ifle          79
      63: aload_0
      64: getfield      #4                  // Field homes:Ljava/util/Hashtable;
      67: aload         4
      69: iconst_0
      70: aaload
      71: aload         4
      73: iconst_5
      74: aaload
      75: invokevirtual #19                 // Method java/util/Hashtable.put:(Ljava/lang/Object;Ljava/lang/Object;)Ljava/lang/Object;
      78: pop
      79: aload_1
      80: invokevirtual #15                 // Method java/io/BufferedReader.readLine:()Ljava/lang/String;
      83: astore_3
      84: goto          24
      87: aload_1
      88: ifnull        158
      91: aload_2
      92: ifnull        111
      95: aload_1
      96: invokevirtual #20                 // Method java/io/BufferedReader.close:()V
      99: goto          158
     102: astore_3
     103: aload_2
     104: aload_3
     105: invokevirtual #22                 // Method java/lang/Throwable.addSuppressed:(Ljava/lang/Throwable;)V
     108: goto          158
     111: aload_1
     112: invokevirtual #20                 // Method java/io/BufferedReader.close:()V
     115: goto          158
     118: astore_3
     119: aload_3
     120: astore_2
     121: aload_3
     122: athrow
     123: astore        5
     125: aload_1
     126: ifnull        155
     129: aload_2
     130: ifnull        151
     133: aload_1
     134: invokevirtual #20                 // Method java/io/BufferedReader.close:()V
     137: goto          155
     140: astore        6
     142: aload_2
     143: aload         6
     145: invokevirtual #22                 // Method java/lang/Throwable.addSuppressed:(Ljava/lang/Throwable;)V
     148: goto          155
     151: aload_1
     152: invokevirtual #20                 // Method java/io/BufferedReader.close:()V
     155: aload         5
     157: athrow
     158: goto          179
     161: astore_1
     162: getstatic     #24                 // Field log:Lorg/apache/juli/logging/Log;
     165: getstatic     #25                 // Field sm:Lorg/apache/naming/StringManager;
     168: ldc           #26                 // String passwdUserDatabase.readFail
     170: invokevirtual #27                 // Method org/apache/naming/StringManager.getString:(Ljava/lang/String;)Ljava/lang/String;
     173: aload_1
     174: invokeinterface #28,  3           // InterfaceMethod org/apache/juli/logging/Log.warn:(Ljava/lang/Object;Ljava/lang/Throwable;)V
     179: return
    Exception table:
       from    to  target type
          95    99   102   Class java/lang/Throwable
          19    87   118   Class java/lang/Throwable
          19    87   123   any
         133   137   140   Class java/lang/Throwable
         118   125   123   any
           0   158   161   Class java/lang/Exception

  static {};
    Code:
       0: ldc_w         #29                 // class org/apache/catalina/startup/PasswdUserDatabase
       3: invokestatic  #30                 // Method org/apache/juli/logging/LogFactory.getLog:(Ljava/lang/Class;)Lorg/apache/juli/logging/Log;
       6: putstatic     #24                 // Field log:Lorg/apache/juli/logging/Log;
       9: ldc_w         #29                 // class org/apache/catalina/startup/PasswdUserDatabase
      12: invokestatic  #31                 // Method org/apache/naming/StringManager.getManager:(Ljava/lang/Class;)Lorg/apache/naming/StringManager;
      15: putstatic     #25                 // Field sm:Lorg/apache/naming/StringManager;
      18: return
}
