Compiled from "WildFlyLogContextSelectorImpl.java"
class org.jboss.as.logging.logmanager.WildFlyLogContextSelectorImpl implements org.jboss.as.logging.logmanager.WildFlyLogContextSelector {
  private final org.jboss.logmanager.ClassLoaderLogContextSelector contextSelector;

  private final org.jboss.logmanager.ThreadLocalLogContextSelector threadLocalContextSelector;

  private final java.util.concurrent.atomic.AtomicInteger counter;

  public org.jboss.as.logging.logmanager.WildFlyLogContextSelectorImpl();
    Code:
       0: aload_0
       1: invokespecial #1                  // Method java/lang/Object."<init>":()V
       4: aload_0
       5: new           #2                  // class java/util/concurrent/atomic/AtomicInteger
       8: dup
       9: iconst_0
      10: invokespecial #3                  // Method java/util/concurrent/atomic/AtomicInteger."<init>":(I)V
      13: putfield      #4                  // Field counter:Ljava/util/concurrent/atomic/AtomicInteger;
      16: invokestatic  #5                  // Method org/jboss/logmanager/LogContext.getLogContext:()Lorg/jboss/logmanager/LogContext;
      19: astore_1
      20: aload_0
      21: new           #6                  // class org/jboss/logmanager/ClassLoaderLogContextSelector
      24: dup
      25: new           #7                  // class org/jboss/as/logging/logmanager/WildFlyLogContextSelectorImpl$1
      28: dup
      29: aload_0
      30: aload_1
      31: invokespecial #8                  // Method org/jboss/as/logging/logmanager/WildFlyLogContextSelectorImpl$1."<init>":(Lorg/jboss/as/logging/logmanager/WildFlyLogContextSelectorImpl;Lorg/jboss/logmanager/LogContext;)V
      34: iconst_1
      35: invokespecial #9                  // Method org/jboss/logmanager/ClassLoaderLogContextSelector."<init>":(Lorg/jboss/logmanager/LogContextSelector;Z)V
      38: putfield      #10                 // Field contextSelector:Lorg/jboss/logmanager/ClassLoaderLogContextSelector;
      41: aload_0
      42: new           #11                 // class org/jboss/logmanager/ThreadLocalLogContextSelector
      45: dup
      46: aload_0
      47: getfield      #10                 // Field contextSelector:Lorg/jboss/logmanager/ClassLoaderLogContextSelector;
      50: invokespecial #12                 // Method org/jboss/logmanager/ThreadLocalLogContextSelector."<init>":(Lorg/jboss/logmanager/LogContextSelector;)V
      53: putfield      #13                 // Field threadLocalContextSelector:Lorg/jboss/logmanager/ThreadLocalLogContextSelector;
      56: return

  public org.jboss.logmanager.LogContext getLogContext();
    Code:
       0: aload_0
       1: getfield      #13                 // Field threadLocalContextSelector:Lorg/jboss/logmanager/ThreadLocalLogContextSelector;
       4: invokevirtual #14                 // Method org/jboss/logmanager/ThreadLocalLogContextSelector.getLogContext:()Lorg/jboss/logmanager/LogContext;
       7: areturn

  public org.jboss.logmanager.LogContext getAndSet(java.lang.Object, org.jboss.logmanager.LogContext);
    Code:
       0: aload_0
       1: getfield      #13                 // Field threadLocalContextSelector:Lorg/jboss/logmanager/ThreadLocalLogContextSelector;
       4: aload_1
       5: aload_2
       6: invokevirtual #15                 // Method org/jboss/logmanager/ThreadLocalLogContextSelector.getAndSet:(Ljava/lang/Object;Lorg/jboss/logmanager/LogContext;)Lorg/jboss/logmanager/LogContext;
       9: areturn

  public void registerLogContext(java.lang.ClassLoader, org.jboss.logmanager.LogContext);
    Code:
       0: aload_0
       1: getfield      #10                 // Field contextSelector:Lorg/jboss/logmanager/ClassLoaderLogContextSelector;
       4: aload_1
       5: aload_2
       6: invokevirtual #16                 // Method org/jboss/logmanager/ClassLoaderLogContextSelector.registerLogContext:(Ljava/lang/ClassLoader;Lorg/jboss/logmanager/LogContext;)V
       9: aload_0
      10: getfield      #4                  // Field counter:Ljava/util/concurrent/atomic/AtomicInteger;
      13: invokevirtual #17                 // Method java/util/concurrent/atomic/AtomicInteger.incrementAndGet:()I
      16: pop
      17: return

  public boolean unregisterLogContext(java.lang.ClassLoader, org.jboss.logmanager.LogContext);
    Code:
       0: aload_0
       1: getfield      #10                 // Field contextSelector:Lorg/jboss/logmanager/ClassLoaderLogContextSelector;
       4: aload_1
       5: aload_2
       6: invokevirtual #18                 // Method org/jboss/logmanager/ClassLoaderLogContextSelector.unregisterLogContext:(Ljava/lang/ClassLoader;Lorg/jboss/logmanager/LogContext;)Z
       9: ifeq          22
      12: aload_0
      13: getfield      #4                  // Field counter:Ljava/util/concurrent/atomic/AtomicInteger;
      16: invokevirtual #19                 // Method java/util/concurrent/atomic/AtomicInteger.decrementAndGet:()I
      19: pop
      20: iconst_1
      21: ireturn
      22: iconst_0
      23: ireturn

  public boolean addLogApiClassLoader(java.lang.ClassLoader);
    Code:
       0: aload_0
       1: getfield      #10                 // Field contextSelector:Lorg/jboss/logmanager/ClassLoaderLogContextSelector;
       4: aload_1
       5: invokevirtual #20                 // Method org/jboss/logmanager/ClassLoaderLogContextSelector.addLogApiClassLoader:(Ljava/lang/ClassLoader;)Z
       8: ireturn

  public boolean removeLogApiClassLoader(java.lang.ClassLoader);
    Code:
       0: aload_0
       1: getfield      #10                 // Field contextSelector:Lorg/jboss/logmanager/ClassLoaderLogContextSelector;
       4: aload_1
       5: invokevirtual #21                 // Method org/jboss/logmanager/ClassLoaderLogContextSelector.removeLogApiClassLoader:(Ljava/lang/ClassLoader;)Z
       8: ireturn

  public int registeredCount();
    Code:
       0: aload_0
       1: getfield      #4                  // Field counter:Ljava/util/concurrent/atomic/AtomicInteger;
       4: invokevirtual #22                 // Method java/util/concurrent/atomic/AtomicInteger.get:()I
       7: ireturn
}
