Compiled from "MemoryStoreEvictionPolicy.java"
public final class net.sf.ehcache.store.MemoryStoreEvictionPolicy$MemoryStoreEvictionPolicyEnum extends java.lang.Enum<net.sf.ehcache.store.MemoryStoreEvictionPolicy$MemoryStoreEvictionPolicyEnum> {
  public static final net.sf.ehcache.store.MemoryStoreEvictionPolicy$MemoryStoreEvictionPolicyEnum LFU;

  public static final net.sf.ehcache.store.MemoryStoreEvictionPolicy$MemoryStoreEvictionPolicyEnum LRU;

  public static final net.sf.ehcache.store.MemoryStoreEvictionPolicy$MemoryStoreEvictionPolicyEnum FIFO;

  private static final net.sf.ehcache.store.MemoryStoreEvictionPolicy$MemoryStoreEvictionPolicyEnum[] $VALUES;

  public static net.sf.ehcache.store.MemoryStoreEvictionPolicy$MemoryStoreEvictionPolicyEnum[] values();
    Code:
       0: getstatic     #1                  // Field $VALUES:[Lnet/sf/ehcache/store/MemoryStoreEvictionPolicy$MemoryStoreEvictionPolicyEnum;
       3: invokevirtual #2                  // Method "[Lnet/sf/ehcache/store/MemoryStoreEvictionPolicy$MemoryStoreEvictionPolicyEnum;".clone:()Ljava/lang/Object;
       6: checkcast     #3                  // class "[Lnet/sf/ehcache/store/MemoryStoreEvictionPolicy$MemoryStoreEvictionPolicyEnum;"
       9: areturn

  public static net.sf.ehcache.store.MemoryStoreEvictionPolicy$MemoryStoreEvictionPolicyEnum valueOf(java.lang.String);
    Code:
       0: ldc_w         #4                  // class net/sf/ehcache/store/MemoryStoreEvictionPolicy$MemoryStoreEvictionPolicyEnum
       3: aload_0
       4: invokestatic  #5                  // Method java/lang/Enum.valueOf:(Ljava/lang/Class;Ljava/lang/String;)Ljava/lang/Enum;
       7: checkcast     #4                  // class net/sf/ehcache/store/MemoryStoreEvictionPolicy$MemoryStoreEvictionPolicyEnum
      10: areturn

  private net.sf.ehcache.store.MemoryStoreEvictionPolicy$MemoryStoreEvictionPolicyEnum();
    Code:
       0: aload_0
       1: aload_1
       2: iload_2
       3: invokespecial #6                  // Method java/lang/Enum."<init>":(Ljava/lang/String;I)V
       6: return

  static {};
    Code:
       0: new           #4                  // class net/sf/ehcache/store/MemoryStoreEvictionPolicy$MemoryStoreEvictionPolicyEnum
       3: dup
       4: ldc           #7                  // String LFU
       6: iconst_0
       7: invokespecial #8                  // Method "<init>":(Ljava/lang/String;I)V
      10: putstatic     #9                  // Field LFU:Lnet/sf/ehcache/store/MemoryStoreEvictionPolicy$MemoryStoreEvictionPolicyEnum;
      13: new           #4                  // class net/sf/ehcache/store/MemoryStoreEvictionPolicy$MemoryStoreEvictionPolicyEnum
      16: dup
      17: ldc           #10                 // String LRU
      19: iconst_1
      20: invokespecial #8                  // Method "<init>":(Ljava/lang/String;I)V
      23: putstatic     #11                 // Field LRU:Lnet/sf/ehcache/store/MemoryStoreEvictionPolicy$MemoryStoreEvictionPolicyEnum;
      26: new           #4                  // class net/sf/ehcache/store/MemoryStoreEvictionPolicy$MemoryStoreEvictionPolicyEnum
      29: dup
      30: ldc           #12                 // String FIFO
      32: iconst_2
      33: invokespecial #8                  // Method "<init>":(Ljava/lang/String;I)V
      36: putstatic     #13                 // Field FIFO:Lnet/sf/ehcache/store/MemoryStoreEvictionPolicy$MemoryStoreEvictionPolicyEnum;
      39: iconst_3
      40: anewarray     #4                  // class net/sf/ehcache/store/MemoryStoreEvictionPolicy$MemoryStoreEvictionPolicyEnum
      43: dup
      44: iconst_0
      45: getstatic     #9                  // Field LFU:Lnet/sf/ehcache/store/MemoryStoreEvictionPolicy$MemoryStoreEvictionPolicyEnum;
      48: aastore
      49: dup
      50: iconst_1
      51: getstatic     #11                 // Field LRU:Lnet/sf/ehcache/store/MemoryStoreEvictionPolicy$MemoryStoreEvictionPolicyEnum;
      54: aastore
      55: dup
      56: iconst_2
      57: getstatic     #13                 // Field FIFO:Lnet/sf/ehcache/store/MemoryStoreEvictionPolicy$MemoryStoreEvictionPolicyEnum;
      60: aastore
      61: putstatic     #1                  // Field $VALUES:[Lnet/sf/ehcache/store/MemoryStoreEvictionPolicy$MemoryStoreEvictionPolicyEnum;
      64: return
}
