Compiled from "UTF8Checker.java"
public class io.undertow.websockets.core.protocol.version07.UTF8Checker implements io.undertow.websockets.core.function.ChannelFunction {
  private static final int UTF8_ACCEPT;

  private static final int UTF8_REJECT;

  private static final byte[] TYPES;

  private static final byte[] STATES;

  private int state;

  public io.undertow.websockets.core.protocol.version07.UTF8Checker();
    Code:
       0: aload_0
       1: invokespecial #1                  // Method java/lang/Object."<init>":()V
       4: aload_0
       5: iconst_0
       6: putfield      #3                  // Field state:I
       9: return

  private void checkUTF8(int) throws java.io.UnsupportedEncodingException;
    Code:
       0: getstatic     #4                  // Field TYPES:[B
       3: iload_1
       4: sipush        255
       7: iand
       8: baload
       9: istore_2
      10: aload_0
      11: getstatic     #5                  // Field STATES:[B
      14: aload_0
      15: getfield      #3                  // Field state:I
      18: iload_2
      19: iadd
      20: baload
      21: putfield      #3                  // Field state:I
      24: aload_0
      25: getfield      #3                  // Field state:I
      28: bipush        12
      30: if_icmpne     42
      33: getstatic     #6                  // Field io/undertow/websockets/core/WebSocketMessages.MESSAGES:Lio/undertow/websockets/core/WebSocketMessages;
      36: invokeinterface #7,  1            // InterfaceMethod io/undertow/websockets/core/WebSocketMessages.invalidTextFrameEncoding:()Ljava/io/UnsupportedEncodingException;
      41: athrow
      42: return

  private void checkUTF8(java.nio.ByteBuffer, int, int) throws java.io.UnsupportedEncodingException;
    Code:
       0: iload_2
       1: iload_3
       2: iadd
       3: istore        4
       5: iload_2
       6: istore        5
       8: iload         5
      10: iload         4
      12: if_icmpge     31
      15: aload_0
      16: aload_1
      17: iload         5
      19: invokevirtual #8                  // Method java/nio/ByteBuffer.get:(I)B
      22: invokespecial #9                  // Method checkUTF8:(I)V
      25: iinc          5, 1
      28: goto          8
      31: return

  public void newFrame(io.undertow.server.protocol.framed.FrameHeaderData);
    Code:
       0: return

  public void afterRead(java.nio.ByteBuffer, int, int) throws java.io.IOException;
    Code:
       0: aload_0
       1: aload_1
       2: iload_2
       3: iload_3
       4: invokespecial #10                 // Method checkUTF8:(Ljava/nio/ByteBuffer;II)V
       7: return

  public void beforeWrite(java.nio.ByteBuffer, int, int) throws java.io.UnsupportedEncodingException;
    Code:
       0: aload_0
       1: aload_1
       2: iload_2
       3: iload_3
       4: invokespecial #10                 // Method checkUTF8:(Ljava/nio/ByteBuffer;II)V
       7: return

  public void complete() throws java.io.UnsupportedEncodingException;
    Code:
       0: aload_0
       1: getfield      #3                  // Field state:I
       4: ifeq          16
       7: getstatic     #6                  // Field io/undertow/websockets/core/WebSocketMessages.MESSAGES:Lio/undertow/websockets/core/WebSocketMessages;
      10: invokeinterface #7,  1            // InterfaceMethod io/undertow/websockets/core/WebSocketMessages.invalidTextFrameEncoding:()Ljava/io/UnsupportedEncodingException;
      15: athrow
      16: return

  static {};
    Code:
       0: sipush        256
       3: newarray       byte
       5: dup
       6: iconst_0
       7: iconst_0
       8: bastore
       9: dup
      10: iconst_1
      11: iconst_0
      12: bastore
      13: dup
      14: iconst_2
      15: iconst_0
      16: bastore
      17: dup
      18: iconst_3
      19: iconst_0
      20: bastore
      21: dup
      22: iconst_4
      23: iconst_0
      24: bastore
      25: dup
      26: iconst_5
      27: iconst_0
      28: bastore
      29: dup
      30: bipush        6
      32: iconst_0
      33: bastore
      34: dup
      35: bipush        7
      37: iconst_0
      38: bastore
      39: dup
      40: bipush        8
      42: iconst_0
      43: bastore
      44: dup
      45: bipush        9
      47: iconst_0
      48: bastore
      49: dup
      50: bipush        10
      52: iconst_0
      53: bastore
      54: dup
      55: bipush        11
      57: iconst_0
      58: bastore
      59: dup
      60: bipush        12
      62: iconst_0
      63: bastore
      64: dup
      65: bipush        13
      67: iconst_0
      68: bastore
      69: dup
      70: bipush        14
      72: iconst_0
      73: bastore
      74: dup
      75: bipush        15
      77: iconst_0
      78: bastore
      79: dup
      80: bipush        16
      82: iconst_0
      83: bastore
      84: dup
      85: bipush        17
      87: iconst_0
      88: bastore
      89: dup
      90: bipush        18
      92: iconst_0
      93: bastore
      94: dup
      95: bipush        19
      97: iconst_0
      98: bastore
      99: dup
     100: bipush        20
     102: iconst_0
     103: bastore
     104: dup
     105: bipush        21
     107: iconst_0
     108: bastore
     109: dup
     110: bipush        22
     112: iconst_0
     113: bastore
     114: dup
     115: bipush        23
     117: iconst_0
     118: bastore
     119: dup
     120: bipush        24
     122: iconst_0
     123: bastore
     124: dup
     125: bipush        25
     127: iconst_0
     128: bastore
     129: dup
     130: bipush        26
     132: iconst_0
     133: bastore
     134: dup
     135: bipush        27
     137: iconst_0
     138: bastore
     139: dup
     140: bipush        28
     142: iconst_0
     143: bastore
     144: dup
     145: bipush        29
     147: iconst_0
     148: bastore
     149: dup
     150: bipush        30
     152: iconst_0
     153: bastore
     154: dup
     155: bipush        31
     157: iconst_0
     158: bastore
     159: dup
     160: bipush        32
     162: iconst_0
     163: bastore
     164: dup
     165: bipush        33
     167: iconst_0
     168: bastore
     169: dup
     170: bipush        34
     172: iconst_0
     173: bastore
     174: dup
     175: bipush        35
     177: iconst_0
     178: bastore
     179: dup
     180: bipush        36
     182: iconst_0
     183: bastore
     184: dup
     185: bipush        37
     187: iconst_0
     188: bastore
     189: dup
     190: bipush        38
     192: iconst_0
     193: bastore
     194: dup
     195: bipush        39
     197: iconst_0
     198: bastore
     199: dup
     200: bipush        40
     202: iconst_0
     203: bastore
     204: dup
     205: bipush        41
     207: iconst_0
     208: bastore
     209: dup
     210: bipush        42
     212: iconst_0
     213: bastore
     214: dup
     215: bipush        43
     217: iconst_0
     218: bastore
     219: dup
     220: bipush        44
     222: iconst_0
     223: bastore
     224: dup
     225: bipush        45
     227: iconst_0
     228: bastore
     229: dup
     230: bipush        46
     232: iconst_0
     233: bastore
     234: dup
     235: bipush        47
     237: iconst_0
     238: bastore
     239: dup
     240: bipush        48
     242: iconst_0
     243: bastore
     244: dup
     245: bipush        49
     247: iconst_0
     248: bastore
     249: dup
     250: bipush        50
     252: iconst_0
     253: bastore
     254: dup
     255: bipush        51
     257: iconst_0
     258: bastore
     259: dup
     260: bipush        52
     262: iconst_0
     263: bastore
     264: dup
     265: bipush        53
     267: iconst_0
     268: bastore
     269: dup
     270: bipush        54
     272: iconst_0
     273: bastore
     274: dup
     275: bipush        55
     277: iconst_0
     278: bastore
     279: dup
     280: bipush        56
     282: iconst_0
     283: bastore
     284: dup
     285: bipush        57
     287: iconst_0
     288: bastore
     289: dup
     290: bipush        58
     292: iconst_0
     293: bastore
     294: dup
     295: bipush        59
     297: iconst_0
     298: bastore
     299: dup
     300: bipush        60
     302: iconst_0
     303: bastore
     304: dup
     305: bipush        61
     307: iconst_0
     308: bastore
     309: dup
     310: bipush        62
     312: iconst_0
     313: bastore
     314: dup
     315: bipush        63
     317: iconst_0
     318: bastore
     319: dup
     320: bipush        64
     322: iconst_0
     323: bastore
     324: dup
     325: bipush        65
     327: iconst_0
     328: bastore
     329: dup
     330: bipush        66
     332: iconst_0
     333: bastore
     334: dup
     335: bipush        67
     337: iconst_0
     338: bastore
     339: dup
     340: bipush        68
     342: iconst_0
     343: bastore
     344: dup
     345: bipush        69
     347: iconst_0
     348: bastore
     349: dup
     350: bipush        70
     352: iconst_0
     353: bastore
     354: dup
     355: bipush        71
     357: iconst_0
     358: bastore
     359: dup
     360: bipush        72
     362: iconst_0
     363: bastore
     364: dup
     365: bipush        73
     367: iconst_0
     368: bastore
     369: dup
     370: bipush        74
     372: iconst_0
     373: bastore
     374: dup
     375: bipush        75
     377: iconst_0
     378: bastore
     379: dup
     380: bipush        76
     382: iconst_0
     383: bastore
     384: dup
     385: bipush        77
     387: iconst_0
     388: bastore
     389: dup
     390: bipush        78
     392: iconst_0
     393: bastore
     394: dup
     395: bipush        79
     397: iconst_0
     398: bastore
     399: dup
     400: bipush        80
     402: iconst_0
     403: bastore
     404: dup
     405: bipush        81
     407: iconst_0
     408: bastore
     409: dup
     410: bipush        82
     412: iconst_0
     413: bastore
     414: dup
     415: bipush        83
     417: iconst_0
     418: bastore
     419: dup
     420: bipush        84
     422: iconst_0
     423: bastore
     424: dup
     425: bipush        85
     427: iconst_0
     428: bastore
     429: dup
     430: bipush        86
     432: iconst_0
     433: bastore
     434: dup
     435: bipush        87
     437: iconst_0
     438: bastore
     439: dup
     440: bipush        88
     442: iconst_0
     443: bastore
     444: dup
     445: bipush        89
     447: iconst_0
     448: bastore
     449: dup
     450: bipush        90
     452: iconst_0
     453: bastore
     454: dup
     455: bipush        91
     457: iconst_0
     458: bastore
     459: dup
     460: bipush        92
     462: iconst_0
     463: bastore
     464: dup
     465: bipush        93
     467: iconst_0
     468: bastore
     469: dup
     470: bipush        94
     472: iconst_0
     473: bastore
     474: dup
     475: bipush        95
     477: iconst_0
     478: bastore
     479: dup
     480: bipush        96
     482: iconst_0
     483: bastore
     484: dup
     485: bipush        97
     487: iconst_0
     488: bastore
     489: dup
     490: bipush        98
     492: iconst_0
     493: bastore
     494: dup
     495: bipush        99
     497: iconst_0
     498: bastore
     499: dup
     500: bipush        100
     502: iconst_0
     503: bastore
     504: dup
     505: bipush        101
     507: iconst_0
     508: bastore
     509: dup
     510: bipush        102
     512: iconst_0
     513: bastore
     514: dup
     515: bipush        103
     517: iconst_0
     518: bastore
     519: dup
     520: bipush        104
     522: iconst_0
     523: bastore
     524: dup
     525: bipush        105
     527: iconst_0
     528: bastore
     529: dup
     530: bipush        106
     532: iconst_0
     533: bastore
     534: dup
     535: bipush        107
     537: iconst_0
     538: bastore
     539: dup
     540: bipush        108
     542: iconst_0
     543: bastore
     544: dup
     545: bipush        109
     547: iconst_0
     548: bastore
     549: dup
     550: bipush        110
     552: iconst_0
     553: bastore
     554: dup
     555: bipush        111
     557: iconst_0
     558: bastore
     559: dup
     560: bipush        112
     562: iconst_0
     563: bastore
     564: dup
     565: bipush        113
     567: iconst_0
     568: bastore
     569: dup
     570: bipush        114
     572: iconst_0
     573: bastore
     574: dup
     575: bipush        115
     577: iconst_0
     578: bastore
     579: dup
     580: bipush        116
     582: iconst_0
     583: bastore
     584: dup
     585: bipush        117
     587: iconst_0
     588: bastore
     589: dup
     590: bipush        118
     592: iconst_0
     593: bastore
     594: dup
     595: bipush        119
     597: iconst_0
     598: bastore
     599: dup
     600: bipush        120
     602: iconst_0
     603: bastore
     604: dup
     605: bipush        121
     607: iconst_0
     608: bastore
     609: dup
     610: bipush        122
     612: iconst_0
     613: bastore
     614: dup
     615: bipush        123
     617: iconst_0
     618: bastore
     619: dup
     620: bipush        124
     622: iconst_0
     623: bastore
     624: dup
     625: bipush        125
     627: iconst_0
     628: bastore
     629: dup
     630: bipush        126
     632: iconst_0
     633: bastore
     634: dup
     635: bipush        127
     637: iconst_0
     638: bastore
     639: dup
     640: sipush        128
     643: iconst_1
     644: bastore
     645: dup
     646: sipush        129
     649: iconst_1
     650: bastore
     651: dup
     652: sipush        130
     655: iconst_1
     656: bastore
     657: dup
     658: sipush        131
     661: iconst_1
     662: bastore
     663: dup
     664: sipush        132
     667: iconst_1
     668: bastore
     669: dup
     670: sipush        133
     673: iconst_1
     674: bastore
     675: dup
     676: sipush        134
     679: iconst_1
     680: bastore
     681: dup
     682: sipush        135
     685: iconst_1
     686: bastore
     687: dup
     688: sipush        136
     691: iconst_1
     692: bastore
     693: dup
     694: sipush        137
     697: iconst_1
     698: bastore
     699: dup
     700: sipush        138
     703: iconst_1
     704: bastore
     705: dup
     706: sipush        139
     709: iconst_1
     710: bastore
     711: dup
     712: sipush        140
     715: iconst_1
     716: bastore
     717: dup
     718: sipush        141
     721: iconst_1
     722: bastore
     723: dup
     724: sipush        142
     727: iconst_1
     728: bastore
     729: dup
     730: sipush        143
     733: iconst_1
     734: bastore
     735: dup
     736: sipush        144
     739: bipush        9
     741: bastore
     742: dup
     743: sipush        145
     746: bipush        9
     748: bastore
     749: dup
     750: sipush        146
     753: bipush        9
     755: bastore
     756: dup
     757: sipush        147
     760: bipush        9
     762: bastore
     763: dup
     764: sipush        148
     767: bipush        9
     769: bastore
     770: dup
     771: sipush        149
     774: bipush        9
     776: bastore
     777: dup
     778: sipush        150
     781: bipush        9
     783: bastore
     784: dup
     785: sipush        151
     788: bipush        9
     790: bastore
     791: dup
     792: sipush        152
     795: bipush        9
     797: bastore
     798: dup
     799: sipush        153
     802: bipush        9
     804: bastore
     805: dup
     806: sipush        154
     809: bipush        9
     811: bastore
     812: dup
     813: sipush        155
     816: bipush        9
     818: bastore
     819: dup
     820: sipush        156
     823: bipush        9
     825: bastore
     826: dup
     827: sipush        157
     830: bipush        9
     832: bastore
     833: dup
     834: sipush        158
     837: bipush        9
     839: bastore
     840: dup
     841: sipush        159
     844: bipush        9
     846: bastore
     847: dup
     848: sipush        160
     851: bipush        7
     853: bastore
     854: dup
     855: sipush        161
     858: bipush        7
     860: bastore
     861: dup
     862: sipush        162
     865: bipush        7
     867: bastore
     868: dup
     869: sipush        163
     872: bipush        7
     874: bastore
     875: dup
     876: sipush        164
     879: bipush        7
     881: bastore
     882: dup
     883: sipush        165
     886: bipush        7
     888: bastore
     889: dup
     890: sipush        166
     893: bipush        7
     895: bastore
     896: dup
     897: sipush        167
     900: bipush        7
     902: bastore
     903: dup
     904: sipush        168
     907: bipush        7
     909: bastore
     910: dup
     911: sipush        169
     914: bipush        7
     916: bastore
     917: dup
     918: sipush        170
     921: bipush        7
     923: bastore
     924: dup
     925: sipush        171
     928: bipush        7
     930: bastore
     931: dup
     932: sipush        172
     935: bipush        7
     937: bastore
     938: dup
     939: sipush        173
     942: bipush        7
     944: bastore
     945: dup
     946: sipush        174
     949: bipush        7
     951: bastore
     952: dup
     953: sipush        175
     956: bipush        7
     958: bastore
     959: dup
     960: sipush        176
     963: bipush        7
     965: bastore
     966: dup
     967: sipush        177
     970: bipush        7
     972: bastore
     973: dup
     974: sipush        178
     977: bipush        7
     979: bastore
     980: dup
     981: sipush        179
     984: bipush        7
     986: bastore
     987: dup
     988: sipush        180
     991: bipush        7
     993: bastore
     994: dup
     995: sipush        181
     998: bipush        7
    1000: bastore
    1001: dup
    1002: sipush        182
    1005: bipush        7
    1007: bastore
    1008: dup
    1009: sipush        183
    1012: bipush        7
    1014: bastore
    1015: dup
    1016: sipush        184
    1019: bipush        7
    1021: bastore
    1022: dup
    1023: sipush        185
    1026: bipush        7
    1028: bastore
    1029: dup
    1030: sipush        186
    1033: bipush        7
    1035: bastore
    1036: dup
    1037: sipush        187
    1040: bipush        7
    1042: bastore
    1043: dup
    1044: sipush        188
    1047: bipush        7
    1049: bastore
    1050: dup
    1051: sipush        189
    1054: bipush        7
    1056: bastore
    1057: dup
    1058: sipush        190
    1061: bipush        7
    1063: bastore
    1064: dup
    1065: sipush        191
    1068: bipush        7
    1070: bastore
    1071: dup
    1072: sipush        192
    1075: bipush        8
    1077: bastore
    1078: dup
    1079: sipush        193
    1082: bipush        8
    1084: bastore
    1085: dup
    1086: sipush        194
    1089: iconst_2
    1090: bastore
    1091: dup
    1092: sipush        195
    1095: iconst_2
    1096: bastore
    1097: dup
    1098: sipush        196
    1101: iconst_2
    1102: bastore
    1103: dup
    1104: sipush        197
    1107: iconst_2
    1108: bastore
    1109: dup
    1110: sipush        198
    1113: iconst_2
    1114: bastore
    1115: dup
    1116: sipush        199
    1119: iconst_2
    1120: bastore
    1121: dup
    1122: sipush        200
    1125: iconst_2
    1126: bastore
    1127: dup
    1128: sipush        201
    1131: iconst_2
    1132: bastore
    1133: dup
    1134: sipush        202
    1137: iconst_2
    1138: bastore
    1139: dup
    1140: sipush        203
    1143: iconst_2
    1144: bastore
    1145: dup
    1146: sipush        204
    1149: iconst_2
    1150: bastore
    1151: dup
    1152: sipush        205
    1155: iconst_2
    1156: bastore
    1157: dup
    1158: sipush        206
    1161: iconst_2
    1162: bastore
    1163: dup
    1164: sipush        207
    1167: iconst_2
    1168: bastore
    1169: dup
    1170: sipush        208
    1173: iconst_2
    1174: bastore
    1175: dup
    1176: sipush        209
    1179: iconst_2
    1180: bastore
    1181: dup
    1182: sipush        210
    1185: iconst_2
    1186: bastore
    1187: dup
    1188: sipush        211
    1191: iconst_2
    1192: bastore
    1193: dup
    1194: sipush        212
    1197: iconst_2
    1198: bastore
    1199: dup
    1200: sipush        213
    1203: iconst_2
    1204: bastore
    1205: dup
    1206: sipush        214
    1209: iconst_2
    1210: bastore
    1211: dup
    1212: sipush        215
    1215: iconst_2
    1216: bastore
    1217: dup
    1218: sipush        216
    1221: iconst_2
    1222: bastore
    1223: dup
    1224: sipush        217
    1227: iconst_2
    1228: bastore
    1229: dup
    1230: sipush        218
    1233: iconst_2
    1234: bastore
    1235: dup
    1236: sipush        219
    1239: iconst_2
    1240: bastore
    1241: dup
    1242: sipush        220
    1245: iconst_2
    1246: bastore
    1247: dup
    1248: sipush        221
    1251: iconst_2
    1252: bastore
    1253: dup
    1254: sipush        222
    1257: iconst_2
    1258: bastore
    1259: dup
    1260: sipush        223
    1263: iconst_2
    1264: bastore
    1265: dup
    1266: sipush        224
    1269: bipush        10
    1271: bastore
    1272: dup
    1273: sipush        225
    1276: iconst_3
    1277: bastore
    1278: dup
    1279: sipush        226
    1282: iconst_3
    1283: bastore
    1284: dup
    1285: sipush        227
    1288: iconst_3
    1289: bastore
    1290: dup
    1291: sipush        228
    1294: iconst_3
    1295: bastore
    1296: dup
    1297: sipush        229
    1300: iconst_3
    1301: bastore
    1302: dup
    1303: sipush        230
    1306: iconst_3
    1307: bastore
    1308: dup
    1309: sipush        231
    1312: iconst_3
    1313: bastore
    1314: dup
    1315: sipush        232
    1318: iconst_3
    1319: bastore
    1320: dup
    1321: sipush        233
    1324: iconst_3
    1325: bastore
    1326: dup
    1327: sipush        234
    1330: iconst_3
    1331: bastore
    1332: dup
    1333: sipush        235
    1336: iconst_3
    1337: bastore
    1338: dup
    1339: sipush        236
    1342: iconst_3
    1343: bastore
    1344: dup
    1345: sipush        237
    1348: iconst_4
    1349: bastore
    1350: dup
    1351: sipush        238
    1354: iconst_3
    1355: bastore
    1356: dup
    1357: sipush        239
    1360: iconst_3
    1361: bastore
    1362: dup
    1363: sipush        240
    1366: bipush        11
    1368: bastore
    1369: dup
    1370: sipush        241
    1373: bipush        6
    1375: bastore
    1376: dup
    1377: sipush        242
    1380: bipush        6
    1382: bastore
    1383: dup
    1384: sipush        243
    1387: bipush        6
    1389: bastore
    1390: dup
    1391: sipush        244
    1394: iconst_5
    1395: bastore
    1396: dup
    1397: sipush        245
    1400: bipush        8
    1402: bastore
    1403: dup
    1404: sipush        246
    1407: bipush        8
    1409: bastore
    1410: dup
    1411: sipush        247
    1414: bipush        8
    1416: bastore
    1417: dup
    1418: sipush        248
    1421: bipush        8
    1423: bastore
    1424: dup
    1425: sipush        249
    1428: bipush        8
    1430: bastore
    1431: dup
    1432: sipush        250
    1435: bipush        8
    1437: bastore
    1438: dup
    1439: sipush        251
    1442: bipush        8
    1444: bastore
    1445: dup
    1446: sipush        252
    1449: bipush        8
    1451: bastore
    1452: dup
    1453: sipush        253
    1456: bipush        8
    1458: bastore
    1459: dup
    1460: sipush        254
    1463: bipush        8
    1465: bastore
    1466: dup
    1467: sipush        255
    1470: bipush        8
    1472: bastore
    1473: putstatic     #4                  // Field TYPES:[B
    1476: bipush        108
    1478: newarray       byte
    1480: dup
    1481: iconst_0
    1482: iconst_0
    1483: bastore
    1484: dup
    1485: iconst_1
    1486: bipush        12
    1488: bastore
    1489: dup
    1490: iconst_2
    1491: bipush        24
    1493: bastore
    1494: dup
    1495: iconst_3
    1496: bipush        36
    1498: bastore
    1499: dup
    1500: iconst_4
    1501: bipush        60
    1503: bastore
    1504: dup
    1505: iconst_5
    1506: bipush        96
    1508: bastore
    1509: dup
    1510: bipush        6
    1512: bipush        84
    1514: bastore
    1515: dup
    1516: bipush        7
    1518: bipush        12
    1520: bastore
    1521: dup
    1522: bipush        8
    1524: bipush        12
    1526: bastore
    1527: dup
    1528: bipush        9
    1530: bipush        12
    1532: bastore
    1533: dup
    1534: bipush        10
    1536: bipush        48
    1538: bastore
    1539: dup
    1540: bipush        11
    1542: bipush        72
    1544: bastore
    1545: dup
    1546: bipush        12
    1548: bipush        12
    1550: bastore
    1551: dup
    1552: bipush        13
    1554: bipush        12
    1556: bastore
    1557: dup
    1558: bipush        14
    1560: bipush        12
    1562: bastore
    1563: dup
    1564: bipush        15
    1566: bipush        12
    1568: bastore
    1569: dup
    1570: bipush        16
    1572: bipush        12
    1574: bastore
    1575: dup
    1576: bipush        17
    1578: bipush        12
    1580: bastore
    1581: dup
    1582: bipush        18
    1584: bipush        12
    1586: bastore
    1587: dup
    1588: bipush        19
    1590: bipush        12
    1592: bastore
    1593: dup
    1594: bipush        20
    1596: bipush        12
    1598: bastore
    1599: dup
    1600: bipush        21
    1602: bipush        12
    1604: bastore
    1605: dup
    1606: bipush        22
    1608: bipush        12
    1610: bastore
    1611: dup
    1612: bipush        23
    1614: bipush        12
    1616: bastore
    1617: dup
    1618: bipush        24
    1620: bipush        12
    1622: bastore
    1623: dup
    1624: bipush        25
    1626: iconst_0
    1627: bastore
    1628: dup
    1629: bipush        26
    1631: bipush        12
    1633: bastore
    1634: dup
    1635: bipush        27
    1637: bipush        12
    1639: bastore
    1640: dup
    1641: bipush        28
    1643: bipush        12
    1645: bastore
    1646: dup
    1647: bipush        29
    1649: bipush        12
    1651: bastore
    1652: dup
    1653: bipush        30
    1655: bipush        12
    1657: bastore
    1658: dup
    1659: bipush        31
    1661: iconst_0
    1662: bastore
    1663: dup
    1664: bipush        32
    1666: bipush        12
    1668: bastore
    1669: dup
    1670: bipush        33
    1672: iconst_0
    1673: bastore
    1674: dup
    1675: bipush        34
    1677: bipush        12
    1679: bastore
    1680: dup
    1681: bipush        35
    1683: bipush        12
    1685: bastore
    1686: dup
    1687: bipush        36
    1689: bipush        12
    1691: bastore
    1692: dup
    1693: bipush        37
    1695: bipush        24
    1697: bastore
    1698: dup
    1699: bipush        38
    1701: bipush        12
    1703: bastore
    1704: dup
    1705: bipush        39
    1707: bipush        12
    1709: bastore
    1710: dup
    1711: bipush        40
    1713: bipush        12
    1715: bastore
    1716: dup
    1717: bipush        41
    1719: bipush        12
    1721: bastore
    1722: dup
    1723: bipush        42
    1725: bipush        12
    1727: bastore
    1728: dup
    1729: bipush        43
    1731: bipush        24
    1733: bastore
    1734: dup
    1735: bipush        44
    1737: bipush        12
    1739: bastore
    1740: dup
    1741: bipush        45
    1743: bipush        24
    1745: bastore
    1746: dup
    1747: bipush        46
    1749: bipush        12
    1751: bastore
    1752: dup
    1753: bipush        47
    1755: bipush        12
    1757: bastore
    1758: dup
    1759: bipush        48
    1761: bipush        12
    1763: bastore
    1764: dup
    1765: bipush        49
    1767: bipush        12
    1769: bastore
    1770: dup
    1771: bipush        50
    1773: bipush        12
    1775: bastore
    1776: dup
    1777: bipush        51
    1779: bipush        12
    1781: bastore
    1782: dup
    1783: bipush        52
    1785: bipush        12
    1787: bastore
    1788: dup
    1789: bipush        53
    1791: bipush        12
    1793: bastore
    1794: dup
    1795: bipush        54
    1797: bipush        12
    1799: bastore
    1800: dup
    1801: bipush        55
    1803: bipush        24
    1805: bastore
    1806: dup
    1807: bipush        56
    1809: bipush        12
    1811: bastore
    1812: dup
    1813: bipush        57
    1815: bipush        12
    1817: bastore
    1818: dup
    1819: bipush        58
    1821: bipush        12
    1823: bastore
    1824: dup
    1825: bipush        59
    1827: bipush        12
    1829: bastore
    1830: dup
    1831: bipush        60
    1833: bipush        12
    1835: bastore
    1836: dup
    1837: bipush        61
    1839: bipush        24
    1841: bastore
    1842: dup
    1843: bipush        62
    1845: bipush        12
    1847: bastore
    1848: dup
    1849: bipush        63
    1851: bipush        12
    1853: bastore
    1854: dup
    1855: bipush        64
    1857: bipush        12
    1859: bastore
    1860: dup
    1861: bipush        65
    1863: bipush        12
    1865: bastore
    1866: dup
    1867: bipush        66
    1869: bipush        12
    1871: bastore
    1872: dup
    1873: bipush        67
    1875: bipush        12
    1877: bastore
    1878: dup
    1879: bipush        68
    1881: bipush        12
    1883: bastore
    1884: dup
    1885: bipush        69
    1887: bipush        24
    1889: bastore
    1890: dup
    1891: bipush        70
    1893: bipush        12
    1895: bastore
    1896: dup
    1897: bipush        71
    1899: bipush        12
    1901: bastore
    1902: dup
    1903: bipush        72
    1905: bipush        12
    1907: bastore
    1908: dup
    1909: bipush        73
    1911: bipush        12
    1913: bastore
    1914: dup
    1915: bipush        74
    1917: bipush        12
    1919: bastore
    1920: dup
    1921: bipush        75
    1923: bipush        12
    1925: bastore
    1926: dup
    1927: bipush        76
    1929: bipush        12
    1931: bastore
    1932: dup
    1933: bipush        77
    1935: bipush        12
    1937: bastore
    1938: dup
    1939: bipush        78
    1941: bipush        12
    1943: bastore
    1944: dup
    1945: bipush        79
    1947: bipush        36
    1949: bastore
    1950: dup
    1951: bipush        80
    1953: bipush        12
    1955: bastore
    1956: dup
    1957: bipush        81
    1959: bipush        36
    1961: bastore
    1962: dup
    1963: bipush        82
    1965: bipush        12
    1967: bastore
    1968: dup
    1969: bipush        83
    1971: bipush        12
    1973: bastore
    1974: dup
    1975: bipush        84
    1977: bipush        12
    1979: bastore
    1980: dup
    1981: bipush        85
    1983: bipush        36
    1985: bastore
    1986: dup
    1987: bipush        86
    1989: bipush        12
    1991: bastore
    1992: dup
    1993: bipush        87
    1995: bipush        12
    1997: bastore
    1998: dup
    1999: bipush        88
    2001: bipush        12
    2003: bastore
    2004: dup
    2005: bipush        89
    2007: bipush        12
    2009: bastore
    2010: dup
    2011: bipush        90
    2013: bipush        12
    2015: bastore
    2016: dup
    2017: bipush        91
    2019: bipush        36
    2021: bastore
    2022: dup
    2023: bipush        92
    2025: bipush        12
    2027: bastore
    2028: dup
    2029: bipush        93
    2031: bipush        36
    2033: bastore
    2034: dup
    2035: bipush        94
    2037: bipush        12
    2039: bastore
    2040: dup
    2041: bipush        95
    2043: bipush        12
    2045: bastore
    2046: dup
    2047: bipush        96
    2049: bipush        12
    2051: bastore
    2052: dup
    2053: bipush        97
    2055: bipush        36
    2057: bastore
    2058: dup
    2059: bipush        98
    2061: bipush        12
    2063: bastore
    2064: dup
    2065: bipush        99
    2067: bipush        12
    2069: bastore
    2070: dup
    2071: bipush        100
    2073: bipush        12
    2075: bastore
    2076: dup
    2077: bipush        101
    2079: bipush        12
    2081: bastore
    2082: dup
    2083: bipush        102
    2085: bipush        12
    2087: bastore
    2088: dup
    2089: bipush        103
    2091: bipush        12
    2093: bastore
    2094: dup
    2095: bipush        104
    2097: bipush        12
    2099: bastore
    2100: dup
    2101: bipush        105
    2103: bipush        12
    2105: bastore
    2106: dup
    2107: bipush        106
    2109: bipush        12
    2111: bastore
    2112: dup
    2113: bipush        107
    2115: bipush        12
    2117: bastore
    2118: putstatic     #5                  // Field STATES:[B
    2121: return
}
