Compiled from "Uid.java"
public class com.arjuna.ats.arjuna.common.Uid implements java.lang.Cloneable,java.io.Serializable {
  private static final long serialVersionUID;

  private static final int MAX_SEQ_VALUE;

  protected volatile long[] hostAddr;

  protected volatile int process;

  protected volatile int sec;

  protected volatile int other;

  private volatile int _hashValue;

  private volatile boolean _valid;

  private volatile java.lang.String _stringForm;

  private volatile byte[] _byteForm;

  private static final java.util.concurrent.atomic.AtomicInteger uidsCreated;

  private static volatile int initTime;

  private static final char breakChar;

  private static final char fileBreakChar;

  private static final com.arjuna.ats.arjuna.common.Uid NIL_UID;

  private static final com.arjuna.ats.arjuna.common.Uid LAST_RESOURCE_UID;

  private static final com.arjuna.ats.arjuna.common.Uid MAX_UID;

  private static final com.arjuna.ats.arjuna.common.Uid MIN_UID;

  public static final int UID_SIZE;

  public com.arjuna.ats.arjuna.common.Uid();
    Code:
       0: aload_0
       1: invokespecial #1                  // Method java/lang/Object."<init>":()V
       4: aload_0
       5: aconst_null
       6: putfield      #2                  // Field hostAddr:[J
       9: aload_0
      10: iconst_0
      11: putfield      #3                  // Field process:I
      14: aload_0
      15: iconst_0
      16: putfield      #4                  // Field sec:I
      19: aload_0
      20: iconst_0
      21: putfield      #5                  // Field other:I
      24: aload_0
      25: iconst_m1
      26: putfield      #6                  // Field _hashValue:I
      29: aload_0
      30: iconst_0
      31: putfield      #7                  // Field _valid:Z
      34: aload_0
      35: aconst_null
      36: putfield      #8                  // Field _stringForm:Ljava/lang/String;
      39: aload_0
      40: aconst_null
      41: putfield      #9                  // Field _byteForm:[B
      44: aload_0
      45: invokestatic  #10                 // Method com/arjuna/ats/arjuna/utils/Utility.hostInetAddr:()[J
      48: putfield      #2                  // Field hostAddr:[J
      51: aload_0
      52: invokestatic  #11                 // Method com/arjuna/ats/arjuna/utils/Utility.getpid:()I
      55: putfield      #3                  // Field process:I
      58: getstatic     #12                 // Field initTime:I
      61: ifne          75
      64: invokestatic  #13                 // Method java/lang/System.currentTimeMillis:()J
      67: ldc2_w        #14                 // long 1000l
      70: ldiv
      71: l2i
      72: putstatic     #12                 // Field initTime:I
      75: aload_0
      76: getstatic     #12                 // Field initTime:I
      79: putfield      #4                  // Field sec:I
      82: aload_0
      83: invokestatic  #16                 // Method getValue:()I
      86: putfield      #5                  // Field other:I
      89: aload_0
      90: iconst_1
      91: putfield      #7                  // Field _valid:Z
      94: aload_0
      95: invokespecial #17                 // Method generateHash:()V
      98: goto          115
     101: astore_1
     102: getstatic     #19                 // Field com/arjuna/ats/arjuna/logging/tsLogger.i18NLogger:Lcom/arjuna/ats/arjuna/logging/arjunaI18NLogger;
     105: invokeinterface #20,  1           // InterfaceMethod com/arjuna/ats/arjuna/logging/arjunaI18NLogger.warn_common_Uid_1:()V
     110: aload_0
     111: iconst_0
     112: putfield      #7                  // Field _valid:Z
     115: return
    Exception table:
       from    to  target type
          44    98   101   Class java/net/UnknownHostException

  public com.arjuna.ats.arjuna.common.Uid(com.arjuna.ats.arjuna.common.Uid);
    Code:
       0: aload_0
       1: invokespecial #1                  // Method java/lang/Object."<init>":()V
       4: aload_0
       5: aload_1
       6: invokespecial #21                 // Method copy:(Lcom/arjuna/ats/arjuna/common/Uid;)V
       9: return

  public com.arjuna.ats.arjuna.common.Uid(byte[]);
    Code:
       0: aload_0
       1: invokespecial #1                  // Method java/lang/Object."<init>":()V
       4: aload_1
       5: ifnonnull     16
       8: new           #22                 // class java/lang/IllegalArgumentException
      11: dup
      12: invokespecial #23                 // Method java/lang/IllegalArgumentException."<init>":()V
      15: athrow
      16: aload_0
      17: iconst_2
      18: newarray       long
      20: putfield      #2                  // Field hostAddr:[J
      23: aload_0
      24: iconst_m1
      25: putfield      #6                  // Field _hashValue:I
      28: aload_0
      29: aconst_null
      30: putfield      #8                  // Field _stringForm:Ljava/lang/String;
      33: aload_0
      34: aconst_null
      35: putfield      #9                  // Field _byteForm:[B
      38: new           #24                 // class java/io/ByteArrayInputStream
      41: dup
      42: aload_1
      43: invokespecial #25                 // Method java/io/ByteArrayInputStream."<init>":([B)V
      46: astore_2
      47: new           #26                 // class java/io/DataInputStream
      50: dup
      51: aload_2
      52: invokespecial #27                 // Method java/io/DataInputStream."<init>":(Ljava/io/InputStream;)V
      55: astore_3
      56: aload_0
      57: getfield      #2                  // Field hostAddr:[J
      60: iconst_0
      61: aload_3
      62: invokevirtual #28                 // Method java/io/DataInputStream.readLong:()J
      65: lastore
      66: aload_0
      67: getfield      #2                  // Field hostAddr:[J
      70: iconst_1
      71: aload_3
      72: invokevirtual #28                 // Method java/io/DataInputStream.readLong:()J
      75: lastore
      76: aload_0
      77: aload_3
      78: invokevirtual #29                 // Method java/io/DataInputStream.readInt:()I
      81: putfield      #3                  // Field process:I
      84: aload_0
      85: aload_3
      86: invokevirtual #29                 // Method java/io/DataInputStream.readInt:()I
      89: putfield      #4                  // Field sec:I
      92: aload_0
      93: aload_3
      94: invokevirtual #29                 // Method java/io/DataInputStream.readInt:()I
      97: putfield      #5                  // Field other:I
     100: aload_0
     101: iconst_1
     102: putfield      #7                  // Field _valid:Z
     105: goto          123
     108: astore_2
     109: getstatic     #19                 // Field com/arjuna/ats/arjuna/logging/tsLogger.i18NLogger:Lcom/arjuna/ats/arjuna/logging/arjunaI18NLogger;
     112: aload_2
     113: invokeinterface #31,  2           // InterfaceMethod com/arjuna/ats/arjuna/logging/arjunaI18NLogger.warn_common_Uid_bytes:(Ljava/lang/Throwable;)V
     118: aload_0
     119: iconst_0
     120: putfield      #7                  // Field _valid:Z
     123: aload_0
     124: invokespecial #17                 // Method generateHash:()V
     127: return
    Exception table:
       from    to  target type
          38   105   108   Class java/lang/Throwable

  public com.arjuna.ats.arjuna.common.Uid(java.lang.String);
    Code:
       0: aload_0
       1: aload_1
       2: iconst_1
       3: invokespecial #32                 // Method "<init>":(Ljava/lang/String;Z)V
       6: return

  public com.arjuna.ats.arjuna.common.Uid(java.lang.String, boolean);
    Code:
       0: aload_0
       1: invokespecial #1                  // Method java/lang/Object."<init>":()V
       4: aload_1
       5: ifnonnull     16
       8: new           #22                 // class java/lang/IllegalArgumentException
      11: dup
      12: invokespecial #23                 // Method java/lang/IllegalArgumentException."<init>":()V
      15: athrow
      16: aload_1
      17: invokestatic  #33                 // Method getBreakChar:(Ljava/lang/String;)C
      20: istore_3
      21: aload_0
      22: iconst_2
      23: newarray       long
      25: putfield      #2                  // Field hostAddr:[J
      28: aload_0
      29: iconst_0
      30: putfield      #3                  // Field process:I
      33: aload_0
      34: iconst_0
      35: putfield      #4                  // Field sec:I
      38: aload_0
      39: iconst_0
      40: putfield      #5                  // Field other:I
      43: aload_0
      44: iconst_m1
      45: putfield      #6                  // Field _hashValue:I
      48: aload_0
      49: iconst_0
      50: putfield      #7                  // Field _valid:Z
      53: aload_0
      54: aconst_null
      55: putfield      #8                  // Field _stringForm:Ljava/lang/String;
      58: aload_0
      59: aconst_null
      60: putfield      #9                  // Field _byteForm:[B
      63: aload_1
      64: invokevirtual #34                 // Method java/lang/String.length:()I
      67: ifle          359
      70: iconst_0
      71: istore        4
      73: iconst_0
      74: istore        5
      76: aconst_null
      77: astore        6
      79: aload_1
      80: iload         5
      82: invokevirtual #35                 // Method java/lang/String.charAt:(I)C
      85: iload_3
      86: if_icmpeq     95
      89: iinc          5, 1
      92: goto          79
      95: aload_1
      96: iload         4
      98: iload         5
     100: invokevirtual #36                 // Method java/lang/String.substring:(II)Ljava/lang/String;
     103: astore        6
     105: aload_0
     106: getfield      #2                  // Field hostAddr:[J
     109: iconst_0
     110: aload         6
     112: invokestatic  #37                 // Method com/arjuna/ats/arjuna/utils/Utility.hexStringToLong:(Ljava/lang/String;)J
     115: lastore
     116: iload         5
     118: iconst_1
     119: iadd
     120: istore        4
     122: iinc          5, 1
     125: aload_1
     126: iload         5
     128: invokevirtual #35                 // Method java/lang/String.charAt:(I)C
     131: iload_3
     132: if_icmpeq     141
     135: iinc          5, 1
     138: goto          125
     141: aload_1
     142: iload         4
     144: iload         5
     146: invokevirtual #36                 // Method java/lang/String.substring:(II)Ljava/lang/String;
     149: astore        6
     151: aload_0
     152: getfield      #2                  // Field hostAddr:[J
     155: iconst_1
     156: aload         6
     158: invokestatic  #37                 // Method com/arjuna/ats/arjuna/utils/Utility.hexStringToLong:(Ljava/lang/String;)J
     161: lastore
     162: iload         5
     164: iconst_1
     165: iadd
     166: istore        4
     168: iinc          5, 1
     171: aload_1
     172: iload         5
     174: invokevirtual #35                 // Method java/lang/String.charAt:(I)C
     177: iload_3
     178: if_icmpeq     187
     181: iinc          5, 1
     184: goto          171
     187: aload_1
     188: iload         4
     190: iload         5
     192: invokevirtual #36                 // Method java/lang/String.substring:(II)Ljava/lang/String;
     195: astore        6
     197: aload_0
     198: aload         6
     200: invokestatic  #37                 // Method com/arjuna/ats/arjuna/utils/Utility.hexStringToLong:(Ljava/lang/String;)J
     203: l2i
     204: putfield      #3                  // Field process:I
     207: iload         5
     209: iconst_1
     210: iadd
     211: istore        4
     213: iinc          5, 1
     216: aload_1
     217: iload         5
     219: invokevirtual #35                 // Method java/lang/String.charAt:(I)C
     222: iload_3
     223: if_icmpeq     232
     226: iinc          5, 1
     229: goto          216
     232: aload_1
     233: iload         4
     235: iload         5
     237: invokevirtual #36                 // Method java/lang/String.substring:(II)Ljava/lang/String;
     240: astore        6
     242: aload_0
     243: aload         6
     245: invokestatic  #37                 // Method com/arjuna/ats/arjuna/utils/Utility.hexStringToLong:(Ljava/lang/String;)J
     248: l2i
     249: putfield      #4                  // Field sec:I
     252: aload_1
     253: iload         5
     255: iconst_1
     256: iadd
     257: aload_1
     258: invokevirtual #34                 // Method java/lang/String.length:()I
     261: invokevirtual #36                 // Method java/lang/String.substring:(II)Ljava/lang/String;
     264: astore        6
     266: aload_0
     267: aload         6
     269: invokestatic  #37                 // Method com/arjuna/ats/arjuna/utils/Utility.hexStringToLong:(Ljava/lang/String;)J
     272: l2i
     273: putfield      #5                  // Field other:I
     276: aload_0
     277: iconst_1
     278: putfield      #7                  // Field _valid:Z
     281: aload_0
     282: invokespecial #17                 // Method generateHash:()V
     285: goto          356
     288: astore        7
     290: iload_2
     291: ifne          305
     294: getstatic     #19                 // Field com/arjuna/ats/arjuna/logging/tsLogger.i18NLogger:Lcom/arjuna/ats/arjuna/logging/arjunaI18NLogger;
     297: aload_1
     298: aload         7
     300: invokeinterface #39,  3           // InterfaceMethod com/arjuna/ats/arjuna/logging/arjunaI18NLogger.warn_common_Uid_3:(Ljava/lang/String;Ljava/lang/Throwable;)V
     305: aload_0
     306: iconst_0
     307: putfield      #7                  // Field _valid:Z
     310: goto          356
     313: astore        7
     315: iload_2
     316: ifne          330
     319: getstatic     #19                 // Field com/arjuna/ats/arjuna/logging/tsLogger.i18NLogger:Lcom/arjuna/ats/arjuna/logging/arjunaI18NLogger;
     322: aload_1
     323: aload         7
     325: invokeinterface #39,  3           // InterfaceMethod com/arjuna/ats/arjuna/logging/arjunaI18NLogger.warn_common_Uid_3:(Ljava/lang/String;Ljava/lang/Throwable;)V
     330: aload_0
     331: iconst_0
     332: putfield      #7                  // Field _valid:Z
     335: goto          356
     338: astore        7
     340: getstatic     #19                 // Field com/arjuna/ats/arjuna/logging/tsLogger.i18NLogger:Lcom/arjuna/ats/arjuna/logging/arjunaI18NLogger;
     343: aload_1
     344: aload         7
     346: invokeinterface #41,  3           // InterfaceMethod com/arjuna/ats/arjuna/logging/arjunaI18NLogger.warn_common_Uid_npe:(Ljava/lang/String;Ljava/lang/Throwable;)V
     351: aload_0
     352: iconst_0
     353: putfield      #7                  // Field _valid:Z
     356: goto          366
     359: aload_0
     360: invokestatic  #42                 // Method nullUid:()Lcom/arjuna/ats/arjuna/common/Uid;
     363: invokespecial #21                 // Method copy:(Lcom/arjuna/ats/arjuna/common/Uid;)V
     366: aload_0
     367: getfield      #7                  // Field _valid:Z
     370: ifne          438
     373: iload_2
     374: ifeq          421
     377: aload_0
     378: invokestatic  #42                 // Method nullUid:()Lcom/arjuna/ats/arjuna/common/Uid;
     381: invokespecial #21                 // Method copy:(Lcom/arjuna/ats/arjuna/common/Uid;)V
     384: aload_0
     385: iconst_0
     386: putfield      #7                  // Field _valid:Z
     389: goto          438
     392: astore        4
     394: getstatic     #19                 // Field com/arjuna/ats/arjuna/logging/tsLogger.i18NLogger:Lcom/arjuna/ats/arjuna/logging/arjunaI18NLogger;
     397: aload_1
     398: invokeinterface #44,  2           // InterfaceMethod com/arjuna/ats/arjuna/logging/arjunaI18NLogger.fatal_common_Uid_4:(Ljava/lang/String;)V
     403: new           #45                 // class com/arjuna/ats/arjuna/exceptions/FatalError
     406: dup
     407: getstatic     #19                 // Field com/arjuna/ats/arjuna/logging/tsLogger.i18NLogger:Lcom/arjuna/ats/arjuna/logging/arjunaI18NLogger;
     410: invokeinterface #46,  1           // InterfaceMethod com/arjuna/ats/arjuna/logging/arjunaI18NLogger.get_common_Uid_2:()Ljava/lang/String;
     415: aload         4
     417: invokespecial #47                 // Method com/arjuna/ats/arjuna/exceptions/FatalError."<init>":(Ljava/lang/String;Ljava/lang/Throwable;)V
     420: athrow
     421: new           #45                 // class com/arjuna/ats/arjuna/exceptions/FatalError
     424: dup
     425: getstatic     #19                 // Field com/arjuna/ats/arjuna/logging/tsLogger.i18NLogger:Lcom/arjuna/ats/arjuna/logging/arjunaI18NLogger;
     428: aload_1
     429: invokeinterface #48,  2           // InterfaceMethod com/arjuna/ats/arjuna/logging/arjunaI18NLogger.get_common_Uid_5:(Ljava/lang/String;)Ljava/lang/String;
     434: invokespecial #49                 // Method com/arjuna/ats/arjuna/exceptions/FatalError."<init>":(Ljava/lang/String;)V
     437: athrow
     438: return
    Exception table:
       from    to  target type
          79   285   288   Class java/lang/NumberFormatException
          79   285   313   Class java/lang/StringIndexOutOfBoundsException
          79   285   338   Class java/lang/Throwable
         377   389   392   Class java/lang/Exception

  public com.arjuna.ats.arjuna.common.Uid(long[], int, int, int);
    Code:
       0: aload_0
       1: invokespecial #1                  // Method java/lang/Object."<init>":()V
       4: aload_0
       5: iconst_2
       6: newarray       long
       8: putfield      #2                  // Field hostAddr:[J
      11: aload_0
      12: getfield      #2                  // Field hostAddr:[J
      15: iconst_0
      16: aload_1
      17: iconst_0
      18: laload
      19: lastore
      20: aload_0
      21: getfield      #2                  // Field hostAddr:[J
      24: iconst_1
      25: aload_1
      26: iconst_1
      27: laload
      28: lastore
      29: aload_0
      30: iload_2
      31: putfield      #3                  // Field process:I
      34: aload_0
      35: iload_3
      36: putfield      #4                  // Field sec:I
      39: aload_0
      40: iload         4
      42: putfield      #5                  // Field other:I
      45: aload_0
      46: iconst_1
      47: putfield      #7                  // Field _valid:Z
      50: aload_0
      51: invokespecial #17                 // Method generateHash:()V
      54: goto          98
      57: astore        5
      59: aload_0
      60: iconst_0
      61: putfield      #7                  // Field _valid:Z
      64: new           #45                 // class com/arjuna/ats/arjuna/exceptions/FatalError
      67: dup
      68: new           #50                 // class java/lang/StringBuilder
      71: dup
      72: invokespecial #51                 // Method java/lang/StringBuilder."<init>":()V
      75: getstatic     #19                 // Field com/arjuna/ats/arjuna/logging/tsLogger.i18NLogger:Lcom/arjuna/ats/arjuna/logging/arjunaI18NLogger;
      78: invokeinterface #52,  1           // InterfaceMethod com/arjuna/ats/arjuna/logging/arjunaI18NLogger.get_common_Uid_11:()Ljava/lang/String;
      83: invokevirtual #53                 // Method java/lang/StringBuilder.append:(Ljava/lang/String;)Ljava/lang/StringBuilder;
      86: aload         5
      88: invokevirtual #54                 // Method java/lang/StringBuilder.append:(Ljava/lang/Object;)Ljava/lang/StringBuilder;
      91: invokevirtual #55                 // Method java/lang/StringBuilder.toString:()Ljava/lang/String;
      94: invokespecial #49                 // Method com/arjuna/ats/arjuna/exceptions/FatalError."<init>":(Ljava/lang/String;)V
      97: athrow
      98: return
    Exception table:
       from    to  target type
           4    54    57   Class java/lang/Throwable

  public int hashCode();
    Code:
       0: aload_0
       1: getfield      #6                  // Field _hashValue:I
       4: ireturn

  public void print(java.io.PrintStream);
    Code:
       0: aload_1
       1: new           #50                 // class java/lang/StringBuilder
       4: dup
       5: invokespecial #51                 // Method java/lang/StringBuilder."<init>":()V
       8: ldc           #56                 // String <Uid:
      10: invokevirtual #53                 // Method java/lang/StringBuilder.append:(Ljava/lang/String;)Ljava/lang/StringBuilder;
      13: aload_0
      14: invokevirtual #57                 // Method toString:()Ljava/lang/String;
      17: invokevirtual #53                 // Method java/lang/StringBuilder.append:(Ljava/lang/String;)Ljava/lang/StringBuilder;
      20: ldc           #58                 // String >
      22: invokevirtual #53                 // Method java/lang/StringBuilder.append:(Ljava/lang/String;)Ljava/lang/StringBuilder;
      25: invokevirtual #55                 // Method java/lang/StringBuilder.toString:()Ljava/lang/String;
      28: invokevirtual #59                 // Method java/io/PrintStream.print:(Ljava/lang/String;)V
      31: return

  public java.lang.String stringForm();
    Code:
       0: aload_0
       1: getfield      #8                  // Field _stringForm:Ljava/lang/String;
       4: ifnonnull     95
       7: aload_0
       8: new           #50                 // class java/lang/StringBuilder
      11: dup
      12: invokespecial #51                 // Method java/lang/StringBuilder."<init>":()V
      15: aload_0
      16: getfield      #2                  // Field hostAddr:[J
      19: iconst_0
      20: laload
      21: invokestatic  #60                 // Method com/arjuna/ats/arjuna/utils/Utility.longToHexString:(J)Ljava/lang/String;
      24: invokevirtual #53                 // Method java/lang/StringBuilder.append:(Ljava/lang/String;)Ljava/lang/StringBuilder;
      27: bipush        58
      29: invokevirtual #62                 // Method java/lang/StringBuilder.append:(C)Ljava/lang/StringBuilder;
      32: aload_0
      33: getfield      #2                  // Field hostAddr:[J
      36: iconst_1
      37: laload
      38: invokestatic  #60                 // Method com/arjuna/ats/arjuna/utils/Utility.longToHexString:(J)Ljava/lang/String;
      41: invokevirtual #53                 // Method java/lang/StringBuilder.append:(Ljava/lang/String;)Ljava/lang/StringBuilder;
      44: bipush        58
      46: invokevirtual #62                 // Method java/lang/StringBuilder.append:(C)Ljava/lang/StringBuilder;
      49: aload_0
      50: getfield      #3                  // Field process:I
      53: invokestatic  #63                 // Method com/arjuna/ats/arjuna/utils/Utility.intToHexString:(I)Ljava/lang/String;
      56: invokevirtual #53                 // Method java/lang/StringBuilder.append:(Ljava/lang/String;)Ljava/lang/StringBuilder;
      59: bipush        58
      61: invokevirtual #62                 // Method java/lang/StringBuilder.append:(C)Ljava/lang/StringBuilder;
      64: aload_0
      65: getfield      #4                  // Field sec:I
      68: invokestatic  #63                 // Method com/arjuna/ats/arjuna/utils/Utility.intToHexString:(I)Ljava/lang/String;
      71: invokevirtual #53                 // Method java/lang/StringBuilder.append:(Ljava/lang/String;)Ljava/lang/StringBuilder;
      74: bipush        58
      76: invokevirtual #62                 // Method java/lang/StringBuilder.append:(C)Ljava/lang/StringBuilder;
      79: aload_0
      80: getfield      #5                  // Field other:I
      83: invokestatic  #63                 // Method com/arjuna/ats/arjuna/utils/Utility.intToHexString:(I)Ljava/lang/String;
      86: invokevirtual #53                 // Method java/lang/StringBuilder.append:(Ljava/lang/String;)Ljava/lang/StringBuilder;
      89: invokevirtual #55                 // Method java/lang/StringBuilder.toString:()Ljava/lang/String;
      92: putfield      #8                  // Field _stringForm:Ljava/lang/String;
      95: aload_0
      96: getfield      #8                  // Field _stringForm:Ljava/lang/String;
      99: areturn

  public java.lang.String fileStringForm();
    Code:
       0: new           #50                 // class java/lang/StringBuilder
       3: dup
       4: invokespecial #51                 // Method java/lang/StringBuilder."<init>":()V
       7: aload_0
       8: getfield      #2                  // Field hostAddr:[J
      11: iconst_0
      12: laload
      13: invokestatic  #60                 // Method com/arjuna/ats/arjuna/utils/Utility.longToHexString:(J)Ljava/lang/String;
      16: invokevirtual #53                 // Method java/lang/StringBuilder.append:(Ljava/lang/String;)Ljava/lang/StringBuilder;
      19: bipush        95
      21: invokevirtual #62                 // Method java/lang/StringBuilder.append:(C)Ljava/lang/StringBuilder;
      24: aload_0
      25: getfield      #2                  // Field hostAddr:[J
      28: iconst_1
      29: laload
      30: invokestatic  #60                 // Method com/arjuna/ats/arjuna/utils/Utility.longToHexString:(J)Ljava/lang/String;
      33: invokevirtual #53                 // Method java/lang/StringBuilder.append:(Ljava/lang/String;)Ljava/lang/StringBuilder;
      36: bipush        95
      38: invokevirtual #62                 // Method java/lang/StringBuilder.append:(C)Ljava/lang/StringBuilder;
      41: aload_0
      42: getfield      #3                  // Field process:I
      45: invokestatic  #63                 // Method com/arjuna/ats/arjuna/utils/Utility.intToHexString:(I)Ljava/lang/String;
      48: invokevirtual #53                 // Method java/lang/StringBuilder.append:(Ljava/lang/String;)Ljava/lang/StringBuilder;
      51: bipush        95
      53: invokevirtual #62                 // Method java/lang/StringBuilder.append:(C)Ljava/lang/StringBuilder;
      56: aload_0
      57: getfield      #4                  // Field sec:I
      60: invokestatic  #63                 // Method com/arjuna/ats/arjuna/utils/Utility.intToHexString:(I)Ljava/lang/String;
      63: invokevirtual #53                 // Method java/lang/StringBuilder.append:(Ljava/lang/String;)Ljava/lang/StringBuilder;
      66: bipush        95
      68: invokevirtual #62                 // Method java/lang/StringBuilder.append:(C)Ljava/lang/StringBuilder;
      71: aload_0
      72: getfield      #5                  // Field other:I
      75: invokestatic  #63                 // Method com/arjuna/ats/arjuna/utils/Utility.intToHexString:(I)Ljava/lang/String;
      78: invokevirtual #53                 // Method java/lang/StringBuilder.append:(Ljava/lang/String;)Ljava/lang/StringBuilder;
      81: invokevirtual #55                 // Method java/lang/StringBuilder.toString:()Ljava/lang/String;
      84: areturn

  public byte[] getBytes();
    Code:
       0: aload_0
       1: getfield      #9                  // Field _byteForm:[B
       4: ifnonnull     96
       7: new           #64                 // class java/io/ByteArrayOutputStream
      10: dup
      11: bipush        28
      13: invokespecial #65                 // Method java/io/ByteArrayOutputStream."<init>":(I)V
      16: astore_1
      17: new           #66                 // class java/io/DataOutputStream
      20: dup
      21: aload_1
      22: invokespecial #67                 // Method java/io/DataOutputStream."<init>":(Ljava/io/OutputStream;)V
      25: astore_2
      26: aload_2
      27: aload_0
      28: getfield      #2                  // Field hostAddr:[J
      31: iconst_0
      32: laload
      33: invokevirtual #68                 // Method java/io/DataOutputStream.writeLong:(J)V
      36: aload_2
      37: aload_0
      38: getfield      #2                  // Field hostAddr:[J
      41: iconst_1
      42: laload
      43: invokevirtual #68                 // Method java/io/DataOutputStream.writeLong:(J)V
      46: aload_2
      47: aload_0
      48: getfield      #3                  // Field process:I
      51: invokevirtual #69                 // Method java/io/DataOutputStream.writeInt:(I)V
      54: aload_2
      55: aload_0
      56: getfield      #4                  // Field sec:I
      59: invokevirtual #69                 // Method java/io/DataOutputStream.writeInt:(I)V
      62: aload_2
      63: aload_0
      64: getfield      #5                  // Field other:I
      67: invokevirtual #69                 // Method java/io/DataOutputStream.writeInt:(I)V
      70: aload_0
      71: aload_1
      72: invokevirtual #70                 // Method java/io/ByteArrayOutputStream.toByteArray:()[B
      75: putfield      #9                  // Field _byteForm:[B
      78: goto          96
      81: astore_3
      82: getstatic     #19                 // Field com/arjuna/ats/arjuna/logging/tsLogger.i18NLogger:Lcom/arjuna/ats/arjuna/logging/arjunaI18NLogger;
      85: aload_3
      86: invokeinterface #71,  2           // InterfaceMethod com/arjuna/ats/arjuna/logging/arjunaI18NLogger.warn_common_Uid_getbytes:(Ljava/lang/Throwable;)V
      91: aload_0
      92: aconst_null
      93: putfield      #9                  // Field _byteForm:[B
      96: aload_0
      97: getfield      #9                  // Field _byteForm:[B
     100: areturn
    Exception table:
       from    to  target type
          26    78    81   Class java/lang/Throwable

  public java.lang.String toString();
    Code:
       0: aload_0
       1: invokevirtual #72                 // Method stringForm:()Ljava/lang/String;
       4: areturn

  public java.lang.String getHexPid();
    Code:
       0: aload_0
       1: getfield      #3                  // Field process:I
       4: invokestatic  #63                 // Method com/arjuna/ats/arjuna/utils/Utility.intToHexString:(I)Ljava/lang/String;
       7: areturn

  public java.lang.Object clone() throws java.lang.CloneNotSupportedException;
    Code:
       0: new           #61                 // class com/arjuna/ats/arjuna/common/Uid
       3: dup
       4: aload_0
       5: invokespecial #73                 // Method "<init>":(Lcom/arjuna/ats/arjuna/common/Uid;)V
       8: areturn

  private void copy(com.arjuna.ats.arjuna.common.Uid);
    Code:
       0: aload_1
       1: aload_0
       2: if_acmpne     6
       5: return
       6: aload_0
       7: aload_1
       8: getfield      #2                  // Field hostAddr:[J
      11: putfield      #2                  // Field hostAddr:[J
      14: aload_0
      15: aload_1
      16: getfield      #3                  // Field process:I
      19: putfield      #3                  // Field process:I
      22: aload_0
      23: aload_1
      24: getfield      #4                  // Field sec:I
      27: putfield      #4                  // Field sec:I
      30: aload_0
      31: aload_1
      32: getfield      #5                  // Field other:I
      35: putfield      #5                  // Field other:I
      38: aload_0
      39: aload_1
      40: getfield      #6                  // Field _hashValue:I
      43: putfield      #6                  // Field _hashValue:I
      46: aload_0
      47: aload_1
      48: getfield      #7                  // Field _valid:Z
      51: putfield      #7                  // Field _valid:Z
      54: return

  public boolean equals(java.lang.Object);
    Code:
       0: aload_1
       1: instanceof    #61                 // class com/arjuna/ats/arjuna/common/Uid
       4: ifeq          16
       7: aload_0
       8: aload_1
       9: checkcast     #61                 // class com/arjuna/ats/arjuna/common/Uid
      12: invokevirtual #74                 // Method equals:(Lcom/arjuna/ats/arjuna/common/Uid;)Z
      15: ireturn
      16: iconst_0
      17: ireturn

  public boolean equals(com.arjuna.ats.arjuna.common.Uid);
    Code:
       0: aload_1
       1: ifnonnull     6
       4: iconst_0
       5: ireturn
       6: aload_1
       7: aload_0
       8: if_acmpne     13
      11: iconst_1
      12: ireturn
      13: aload_0
      14: getfield      #5                  // Field other:I
      17: aload_1
      18: getfield      #5                  // Field other:I
      21: if_icmpne     82
      24: aload_0
      25: getfield      #4                  // Field sec:I
      28: aload_1
      29: getfield      #4                  // Field sec:I
      32: if_icmpne     82
      35: aload_0
      36: getfield      #3                  // Field process:I
      39: aload_1
      40: getfield      #3                  // Field process:I
      43: if_icmpne     82
      46: aload_0
      47: getfield      #2                  // Field hostAddr:[J
      50: iconst_0
      51: laload
      52: aload_1
      53: getfield      #2                  // Field hostAddr:[J
      56: iconst_0
      57: laload
      58: lcmp
      59: ifne          82
      62: aload_0
      63: getfield      #2                  // Field hostAddr:[J
      66: iconst_1
      67: laload
      68: aload_1
      69: getfield      #2                  // Field hostAddr:[J
      72: iconst_1
      73: laload
      74: lcmp
      75: ifne          82
      78: iconst_1
      79: goto          83
      82: iconst_0
      83: ireturn

  public boolean notEquals(com.arjuna.ats.arjuna.common.Uid);
    Code:
       0: aload_1
       1: ifnonnull     6
       4: iconst_1
       5: ireturn
       6: aload_1
       7: aload_0
       8: if_acmpne     13
      11: iconst_0
      12: ireturn
      13: aload_0
      14: getfield      #5                  // Field other:I
      17: aload_1
      18: getfield      #5                  // Field other:I
      21: if_icmpne     78
      24: aload_0
      25: getfield      #4                  // Field sec:I
      28: aload_1
      29: getfield      #4                  // Field sec:I
      32: if_icmpne     78
      35: aload_0
      36: getfield      #3                  // Field process:I
      39: aload_1
      40: getfield      #3                  // Field process:I
      43: if_icmpne     78
      46: aload_0
      47: getfield      #2                  // Field hostAddr:[J
      50: iconst_0
      51: laload
      52: aload_1
      53: getfield      #2                  // Field hostAddr:[J
      56: iconst_0
      57: laload
      58: lcmp
      59: ifne          78
      62: aload_0
      63: getfield      #2                  // Field hostAddr:[J
      66: iconst_1
      67: laload
      68: aload_1
      69: getfield      #2                  // Field hostAddr:[J
      72: iconst_1
      73: laload
      74: lcmp
      75: ifeq          82
      78: iconst_1
      79: goto          83
      82: iconst_0
      83: ireturn

  public boolean lessThan(com.arjuna.ats.arjuna.common.Uid);
    Code:
       0: aload_1
       1: ifnonnull     6
       4: iconst_0
       5: ireturn
       6: aload_1
       7: aload_0
       8: if_acmpne     13
      11: iconst_0
      12: ireturn
      13: aload_0
      14: aload_1
      15: invokevirtual #74                 // Method equals:(Lcom/arjuna/ats/arjuna/common/Uid;)Z
      18: ifeq          23
      21: iconst_0
      22: ireturn
      23: getstatic     #75                 // Field LAST_RESOURCE_UID:Lcom/arjuna/ats/arjuna/common/Uid;
      26: aload_0
      27: invokevirtual #74                 // Method equals:(Lcom/arjuna/ats/arjuna/common/Uid;)Z
      30: ifeq          35
      33: iconst_0
      34: ireturn
      35: getstatic     #75                 // Field LAST_RESOURCE_UID:Lcom/arjuna/ats/arjuna/common/Uid;
      38: aload_1
      39: invokevirtual #74                 // Method equals:(Lcom/arjuna/ats/arjuna/common/Uid;)Z
      42: ifeq          47
      45: iconst_1
      46: ireturn
      47: aload_0
      48: getfield      #2                  // Field hostAddr:[J
      51: iconst_0
      52: laload
      53: aload_1
      54: getfield      #2                  // Field hostAddr:[J
      57: iconst_0
      58: laload
      59: lcmp
      60: ifge          81
      63: aload_0
      64: getfield      #2                  // Field hostAddr:[J
      67: iconst_1
      68: laload
      69: aload_1
      70: getfield      #2                  // Field hostAddr:[J
      73: iconst_1
      74: laload
      75: lcmp
      76: ifge          81
      79: iconst_1
      80: ireturn
      81: aload_0
      82: getfield      #2                  // Field hostAddr:[J
      85: iconst_0
      86: laload
      87: aload_1
      88: getfield      #2                  // Field hostAddr:[J
      91: iconst_0
      92: laload
      93: lcmp
      94: ifne          174
      97: aload_0
      98: getfield      #2                  // Field hostAddr:[J
     101: iconst_1
     102: laload
     103: aload_1
     104: getfield      #2                  // Field hostAddr:[J
     107: iconst_1
     108: laload
     109: lcmp
     110: ifne          174
     113: aload_0
     114: getfield      #3                  // Field process:I
     117: aload_1
     118: getfield      #3                  // Field process:I
     121: if_icmpge     126
     124: iconst_1
     125: ireturn
     126: aload_0
     127: getfield      #3                  // Field process:I
     130: aload_1
     131: getfield      #3                  // Field process:I
     134: if_icmpne     174
     137: aload_0
     138: getfield      #4                  // Field sec:I
     141: aload_1
     142: getfield      #4                  // Field sec:I
     145: if_icmpge     150
     148: iconst_1
     149: ireturn
     150: aload_0
     151: getfield      #4                  // Field sec:I
     154: aload_1
     155: getfield      #4                  // Field sec:I
     158: if_icmpne     174
     161: aload_0
     162: getfield      #5                  // Field other:I
     165: aload_1
     166: getfield      #5                  // Field other:I
     169: if_icmpge     174
     172: iconst_1
     173: ireturn
     174: iconst_0
     175: ireturn

  public boolean greaterThan(com.arjuna.ats.arjuna.common.Uid);
    Code:
       0: aload_1
       1: ifnonnull     6
       4: iconst_0
       5: ireturn
       6: aload_1
       7: aload_0
       8: if_acmpne     13
      11: iconst_0
      12: ireturn
      13: aload_0
      14: aload_1
      15: invokevirtual #74                 // Method equals:(Lcom/arjuna/ats/arjuna/common/Uid;)Z
      18: ifeq          23
      21: iconst_0
      22: ireturn
      23: getstatic     #75                 // Field LAST_RESOURCE_UID:Lcom/arjuna/ats/arjuna/common/Uid;
      26: aload_0
      27: invokevirtual #74                 // Method equals:(Lcom/arjuna/ats/arjuna/common/Uid;)Z
      30: ifeq          35
      33: iconst_1
      34: ireturn
      35: getstatic     #75                 // Field LAST_RESOURCE_UID:Lcom/arjuna/ats/arjuna/common/Uid;
      38: aload_1
      39: invokevirtual #74                 // Method equals:(Lcom/arjuna/ats/arjuna/common/Uid;)Z
      42: ifeq          47
      45: iconst_0
      46: ireturn
      47: aload_0
      48: getfield      #2                  // Field hostAddr:[J
      51: iconst_0
      52: laload
      53: aload_1
      54: getfield      #2                  // Field hostAddr:[J
      57: iconst_0
      58: laload
      59: lcmp
      60: ifle          81
      63: aload_0
      64: getfield      #2                  // Field hostAddr:[J
      67: iconst_1
      68: laload
      69: aload_1
      70: getfield      #2                  // Field hostAddr:[J
      73: iconst_1
      74: laload
      75: lcmp
      76: ifle          81
      79: iconst_1
      80: ireturn
      81: aload_0
      82: getfield      #2                  // Field hostAddr:[J
      85: iconst_0
      86: laload
      87: aload_1
      88: getfield      #2                  // Field hostAddr:[J
      91: iconst_0
      92: laload
      93: lcmp
      94: ifne          174
      97: aload_0
      98: getfield      #2                  // Field hostAddr:[J
     101: iconst_1
     102: laload
     103: aload_1
     104: getfield      #2                  // Field hostAddr:[J
     107: iconst_0
     108: laload
     109: lcmp
     110: ifne          174
     113: aload_0
     114: getfield      #3                  // Field process:I
     117: aload_1
     118: getfield      #3                  // Field process:I
     121: if_icmple     126
     124: iconst_1
     125: ireturn
     126: aload_0
     127: getfield      #3                  // Field process:I
     130: aload_1
     131: getfield      #3                  // Field process:I
     134: if_icmpne     174
     137: aload_0
     138: getfield      #4                  // Field sec:I
     141: aload_1
     142: getfield      #4                  // Field sec:I
     145: if_icmple     150
     148: iconst_1
     149: ireturn
     150: aload_0
     151: getfield      #4                  // Field sec:I
     154: aload_1
     155: getfield      #4                  // Field sec:I
     158: if_icmpne     174
     161: aload_0
     162: getfield      #5                  // Field other:I
     165: aload_1
     166: getfield      #5                  // Field other:I
     169: if_icmple     174
     172: iconst_1
     173: ireturn
     174: iconst_0
     175: ireturn

  public final boolean valid();
    Code:
       0: aload_0
       1: getfield      #7                  // Field _valid:Z
       4: ireturn

  public static final com.arjuna.ats.arjuna.common.Uid nullUid();
    Code:
       0: getstatic     #76                 // Field NIL_UID:Lcom/arjuna/ats/arjuna/common/Uid;
       3: areturn

  public static final com.arjuna.ats.arjuna.common.Uid lastResourceUid();
    Code:
       0: getstatic     #75                 // Field LAST_RESOURCE_UID:Lcom/arjuna/ats/arjuna/common/Uid;
       3: areturn

  public static final com.arjuna.ats.arjuna.common.Uid maxUid();
    Code:
       0: getstatic     #77                 // Field MAX_UID:Lcom/arjuna/ats/arjuna/common/Uid;
       3: areturn

  public static final com.arjuna.ats.arjuna.common.Uid minUid();
    Code:
       0: getstatic     #78                 // Field MIN_UID:Lcom/arjuna/ats/arjuna/common/Uid;
       3: areturn

  private void writeObject(java.io.ObjectOutputStream) throws java.io.IOException;
    Code:
       0: aload_0
       1: getfield      #7                  // Field _valid:Z
       4: ifeq          58
       7: aload_1
       8: invokevirtual #79                 // Method java/io/ObjectOutputStream.defaultWriteObject:()V
      11: aload_1
      12: aload_0
      13: getfield      #2                  // Field hostAddr:[J
      16: iconst_0
      17: laload
      18: invokevirtual #80                 // Method java/io/ObjectOutputStream.writeLong:(J)V
      21: aload_1
      22: aload_0
      23: getfield      #2                  // Field hostAddr:[J
      26: iconst_1
      27: laload
      28: invokevirtual #80                 // Method java/io/ObjectOutputStream.writeLong:(J)V
      31: aload_1
      32: aload_0
      33: getfield      #3                  // Field process:I
      36: invokevirtual #81                 // Method java/io/ObjectOutputStream.writeInt:(I)V
      39: aload_1
      40: aload_0
      41: getfield      #4                  // Field sec:I
      44: invokevirtual #81                 // Method java/io/ObjectOutputStream.writeInt:(I)V
      47: aload_1
      48: aload_0
      49: getfield      #5                  // Field other:I
      52: invokevirtual #81                 // Method java/io/ObjectOutputStream.writeInt:(I)V
      55: goto          68
      58: new           #82                 // class java/io/IOException
      61: dup
      62: ldc           #83                 // String Invalid Uid object.
      64: invokespecial #84                 // Method java/io/IOException."<init>":(Ljava/lang/String;)V
      67: athrow
      68: return

  private void readObject(java.io.ObjectInputStream) throws java.io.IOException, java.lang.ClassNotFoundException;
    Code:
       0: aload_1
       1: invokevirtual #85                 // Method java/io/ObjectInputStream.defaultReadObject:()V
       4: aload_0
       5: iconst_2
       6: newarray       long
       8: putfield      #2                  // Field hostAddr:[J
      11: aload_0
      12: getfield      #2                  // Field hostAddr:[J
      15: iconst_0
      16: aload_1
      17: invokevirtual #86                 // Method java/io/ObjectInputStream.readLong:()J
      20: lastore
      21: aload_0
      22: getfield      #2                  // Field hostAddr:[J
      25: iconst_1
      26: aload_1
      27: invokevirtual #86                 // Method java/io/ObjectInputStream.readLong:()J
      30: lastore
      31: aload_0
      32: aload_1
      33: invokevirtual #87                 // Method java/io/ObjectInputStream.readInt:()I
      36: putfield      #3                  // Field process:I
      39: aload_0
      40: aload_1
      41: invokevirtual #87                 // Method java/io/ObjectInputStream.readInt:()I
      44: putfield      #4                  // Field sec:I
      47: aload_0
      48: aload_1
      49: invokevirtual #87                 // Method java/io/ObjectInputStream.readInt:()I
      52: putfield      #5                  // Field other:I
      55: aload_0
      56: iconst_1
      57: putfield      #7                  // Field _valid:Z
      60: aload_0
      61: invokespecial #17                 // Method generateHash:()V
      64: goto          75
      67: astore_2
      68: aload_0
      69: iconst_0
      70: putfield      #7                  // Field _valid:Z
      73: aload_2
      74: athrow
      75: return
    Exception table:
       from    to  target type
           0    64    67   Class java/io/IOException

  private static int getValue();
    Code:
       0: iconst_0
       1: istore_0
       2: getstatic     #88                 // Field uidsCreated:Ljava/util/concurrent/atomic/AtomicInteger;
       5: invokevirtual #89                 // Method java/util/concurrent/atomic/AtomicInteger.getAndIncrement:()I
       8: istore_0
       9: iload_0
      10: ldc           #90                 // int 1073741824
      12: if_icmpne     33
      15: getstatic     #88                 // Field uidsCreated:Ljava/util/concurrent/atomic/AtomicInteger;
      18: iconst_0
      19: invokevirtual #91                 // Method java/util/concurrent/atomic/AtomicInteger.set:(I)V
      22: invokestatic  #13                 // Method java/lang/System.currentTimeMillis:()J
      25: ldc2_w        #14                 // long 1000l
      28: ldiv
      29: l2i
      30: putstatic     #12                 // Field initTime:I
      33: iload_0
      34: ldc           #90                 // int 1073741824
      36: if_icmpge     2
      39: iload_0
      40: ireturn

  private final void generateHash();
    Code:
       0: aload_0
       1: getfield      #7                  // Field _valid:Z
       4: ifeq          60
       7: aload_0
       8: aload_0
       9: getfield      #2                  // Field hostAddr:[J
      12: iconst_0
      13: laload
      14: l2i
      15: aload_0
      16: getfield      #2                  // Field hostAddr:[J
      19: iconst_1
      20: laload
      21: l2i
      22: ixor
      23: aload_0
      24: getfield      #3                  // Field process:I
      27: ixor
      28: aload_0
      29: getfield      #4                  // Field sec:I
      32: ixor
      33: aload_0
      34: getfield      #5                  // Field other:I
      37: ixor
      38: putfield      #6                  // Field _hashValue:I
      41: aload_0
      42: getfield      #6                  // Field _hashValue:I
      45: ifge          68
      48: aload_0
      49: aload_0
      50: getfield      #6                  // Field _hashValue:I
      53: ineg
      54: putfield      #6                  // Field _hashValue:I
      57: goto          68
      60: getstatic     #19                 // Field com/arjuna/ats/arjuna/logging/tsLogger.i18NLogger:Lcom/arjuna/ats/arjuna/logging/arjunaI18NLogger;
      63: invokeinterface #92,  1           // InterfaceMethod com/arjuna/ats/arjuna/logging/arjunaI18NLogger.warn_common_Uid_6:()V
      68: return

  private static final char getBreakChar(java.lang.String);
    Code:
       0: aload_0
       1: ifnonnull     7
       4: bipush        58
       6: ireturn
       7: aload_0
       8: bipush        95
      10: invokevirtual #93                 // Method java/lang/String.indexOf:(I)I
      13: iconst_m1
      14: if_icmpeq     20
      17: bipush        95
      19: ireturn
      20: bipush        58
      22: ireturn

  static {};
    Code:
       0: new           #94                 // class java/util/concurrent/atomic/AtomicInteger
       3: dup
       4: invokespecial #95                 // Method java/util/concurrent/atomic/AtomicInteger."<init>":()V
       7: putstatic     #88                 // Field uidsCreated:Ljava/util/concurrent/atomic/AtomicInteger;
      10: new           #61                 // class com/arjuna/ats/arjuna/common/Uid
      13: dup
      14: ldc           #96                 // String 0:0:0:0:0
      16: invokespecial #97                 // Method "<init>":(Ljava/lang/String;)V
      19: putstatic     #76                 // Field NIL_UID:Lcom/arjuna/ats/arjuna/common/Uid;
      22: new           #61                 // class com/arjuna/ats/arjuna/common/Uid
      25: dup
      26: ldc           #98                 // String 0:0:0:0:1
      28: invokespecial #97                 // Method "<init>":(Ljava/lang/String;)V
      31: putstatic     #75                 // Field LAST_RESOURCE_UID:Lcom/arjuna/ats/arjuna/common/Uid;
      34: new           #61                 // class com/arjuna/ats/arjuna/common/Uid
      37: dup
      38: ldc           #99                 // String 7fffffffffffffff:7fffffffffffffff:7fffffff:7fffffff:7fffffff
      40: invokespecial #97                 // Method "<init>":(Ljava/lang/String;)V
      43: putstatic     #77                 // Field MAX_UID:Lcom/arjuna/ats/arjuna/common/Uid;
      46: new           #61                 // class com/arjuna/ats/arjuna/common/Uid
      49: dup
      50: ldc           #100                // String -8000000000000000:-8000000000000000:-80000000:-80000000:-80000000
      52: invokespecial #97                 // Method "<init>":(Ljava/lang/String;)V
      55: putstatic     #78                 // Field MIN_UID:Lcom/arjuna/ats/arjuna/common/Uid;
      58: return
}
