Compiled from "PolicyFeatureBPDefinitionParser.java"
public class org.apache.cxf.ws.policy.blueprint.PolicyFeatureBPDefinitionParser extends org.apache.cxf.configuration.blueprint.AbstractBPBeanDefinitionParser {
  public org.apache.cxf.ws.policy.blueprint.PolicyFeatureBPDefinitionParser();
    Code:
       0: aload_0
       1: invokespecial #1                  // Method org/apache/cxf/configuration/blueprint/AbstractBPBeanDefinitionParser."<init>":()V
       4: return

  public org.osgi.service.blueprint.reflect.Metadata parse(org.w3c.dom.Element, org.apache.aries.blueprint.ParserContext);
    Code:
       0: aload_2
       1: ldc_w         #2                  // class org/apache/aries/blueprint/mutable/MutableCollectionMetadata
       4: invokeinterface #3,  2            // InterfaceMethod org/apache/aries/blueprint/ParserContext.createMetadata:(Ljava/lang/Class;)Lorg/osgi/service/blueprint/reflect/Metadata;
       9: checkcast     #2                  // class org/apache/aries/blueprint/mutable/MutableCollectionMetadata
      12: astore_3
      13: aload_3
      14: ldc_w         #4                  // class java/util/List
      17: invokeinterface #5,  2            // InterfaceMethod org/apache/aries/blueprint/mutable/MutableCollectionMetadata.setCollectionClass:(Ljava/lang/Class;)V
      22: aload_2
      23: ldc_w         #2                  // class org/apache/aries/blueprint/mutable/MutableCollectionMetadata
      26: invokeinterface #3,  2            // InterfaceMethod org/apache/aries/blueprint/ParserContext.createMetadata:(Ljava/lang/Class;)Lorg/osgi/service/blueprint/reflect/Metadata;
      31: checkcast     #2                  // class org/apache/aries/blueprint/mutable/MutableCollectionMetadata
      34: astore        4
      36: aload_3
      37: ldc_w         #4                  // class java/util/List
      40: invokeinterface #5,  2            // InterfaceMethod org/apache/aries/blueprint/mutable/MutableCollectionMetadata.setCollectionClass:(Ljava/lang/Class;)V
      45: aload_2
      46: ldc_w         #6                  // class org/apache/aries/blueprint/mutable/MutableBeanMetadata
      49: invokeinterface #3,  2            // InterfaceMethod org/apache/aries/blueprint/ParserContext.createMetadata:(Ljava/lang/Class;)Lorg/osgi/service/blueprint/reflect/Metadata;
      54: checkcast     #6                  // class org/apache/aries/blueprint/mutable/MutableBeanMetadata
      57: astore        5
      59: aload         5
      61: ldc_w         #7                  // class org/apache/cxf/ws/policy/WSPolicyFeature
      64: invokeinterface #8,  2            // InterfaceMethod org/apache/aries/blueprint/mutable/MutableBeanMetadata.setRuntimeClass:(Ljava/lang/Class;)V
      69: aload_1
      70: invokestatic  #9                  // Method org/apache/cxf/helpers/DOMUtils.getFirstElement:(Lorg/w3c/dom/Node;)Lorg/w3c/dom/Element;
      73: astore        6
      75: aload         6
      77: ifnull        148
      80: ldc           #10                 // String Policy
      82: aload         6
      84: invokeinterface #11,  1           // InterfaceMethod org/w3c/dom/Element.getLocalName:()Ljava/lang/String;
      89: invokevirtual #12                 // Method java/lang/String.equals:(Ljava/lang/Object;)Z
      92: ifeq          110
      95: aload_3
      96: aload_2
      97: aload         6
      99: invokestatic  #13                 // Method createElement:(Lorg/apache/aries/blueprint/ParserContext;Lorg/w3c/dom/Element;)Lorg/osgi/service/blueprint/reflect/Metadata;
     102: invokeinterface #14,  2           // InterfaceMethod org/apache/aries/blueprint/mutable/MutableCollectionMetadata.addValue:(Lorg/osgi/service/blueprint/reflect/Metadata;)V
     107: goto          138
     110: ldc           #15                 // String PolicyReference
     112: aload         6
     114: invokeinterface #11,  1           // InterfaceMethod org/w3c/dom/Element.getLocalName:()Ljava/lang/String;
     119: invokevirtual #12                 // Method java/lang/String.equals:(Ljava/lang/Object;)Z
     122: ifeq          138
     125: aload         4
     127: aload_2
     128: aload         6
     130: invokestatic  #13                 // Method createElement:(Lorg/apache/aries/blueprint/ParserContext;Lorg/w3c/dom/Element;)Lorg/osgi/service/blueprint/reflect/Metadata;
     133: invokeinterface #14,  2           // InterfaceMethod org/apache/aries/blueprint/mutable/MutableCollectionMetadata.addValue:(Lorg/osgi/service/blueprint/reflect/Metadata;)V
     138: aload         6
     140: invokestatic  #16                 // Method org/apache/cxf/helpers/DOMUtils.getNextElement:(Lorg/w3c/dom/Element;)Lorg/w3c/dom/Element;
     143: astore        6
     145: goto          75
     148: aload         5
     150: ldc           #17                 // String policyElements
     152: aload_3
     153: invokeinterface #18,  3           // InterfaceMethod org/apache/aries/blueprint/mutable/MutableBeanMetadata.addProperty:(Ljava/lang/String;Lorg/osgi/service/blueprint/reflect/Metadata;)Lorg/osgi/service/blueprint/reflect/BeanProperty;
     158: pop
     159: aload         5
     161: ldc           #19                 // String policyReferenceElements
     163: aload         4
     165: invokeinterface #18,  3           // InterfaceMethod org/apache/aries/blueprint/mutable/MutableBeanMetadata.addProperty:(Ljava/lang/String;Lorg/osgi/service/blueprint/reflect/Metadata;)Lorg/osgi/service/blueprint/reflect/BeanProperty;
     170: pop
     171: aload_0
     172: aload_1
     173: aload_2
     174: aload         5
     176: invokespecial #20                 // Method org/apache/cxf/configuration/blueprint/AbstractBPBeanDefinitionParser.parseChildElements:(Lorg/w3c/dom/Element;Lorg/apache/aries/blueprint/ParserContext;Lorg/apache/aries/blueprint/mutable/MutableBeanMetadata;)V
     179: aload         5
     181: areturn

  protected void mapElement(org.apache.aries.blueprint.ParserContext, org.apache.aries.blueprint.mutable.MutableBeanMetadata, org.w3c.dom.Element, java.lang.String);
    Code:
       0: ldc           #21                 // String alternativeSelector
       2: aload         4
       4: invokevirtual #12                 // Method java/lang/String.equals:(Ljava/lang/Object;)Z
       7: ifeq          19
      10: aload_0
      11: aload_3
      12: aload_1
      13: aload_2
      14: aload         4
      16: invokevirtual #22                 // Method setFirstChildAsProperty:(Lorg/w3c/dom/Element;Lorg/apache/aries/blueprint/ParserContext;Lorg/apache/aries/blueprint/mutable/MutableBeanMetadata;Ljava/lang/String;)V
      19: return

  public static org.osgi.service.blueprint.reflect.Metadata createElement(org.apache.aries.blueprint.ParserContext, org.w3c.dom.Element);
    Code:
       0: aload_0
       1: ldc_w         #23                 // class org/apache/aries/blueprint/mutable/MutablePassThroughMetadata
       4: invokeinterface #3,  2            // InterfaceMethod org/apache/aries/blueprint/ParserContext.createMetadata:(Ljava/lang/Class;)Lorg/osgi/service/blueprint/reflect/Metadata;
       9: checkcast     #23                 // class org/apache/aries/blueprint/mutable/MutablePassThroughMetadata
      12: astore_2
      13: aload_2
      14: aload_1
      15: invokeinterface #24,  2           // InterfaceMethod org/apache/aries/blueprint/mutable/MutablePassThroughMetadata.setObject:(Ljava/lang/Object;)V
      20: aload_2
      21: areturn
}
