Compiled from "HttpTraceAutoConfiguration.java"
class org.springframework.boot.actuate.autoconfigure.trace.http.HttpTraceAutoConfiguration$ReactiveTraceFilterConfiguration {
  org.springframework.boot.actuate.autoconfigure.trace.http.HttpTraceAutoConfiguration$ReactiveTraceFilterConfiguration();
    Code:
       0: aload_0
       1: invokespecial #1                  // Method java/lang/Object."<init>":()V
       4: return

  public org.springframework.boot.actuate.web.trace.reactive.HttpTraceWebFilter httpTraceWebFilter(org.springframework.boot.actuate.trace.http.HttpTraceRepository, org.springframework.boot.actuate.trace.http.HttpExchangeTracer, org.springframework.boot.actuate.autoconfigure.trace.http.HttpTraceProperties);
    Code:
       0: new           #2                  // class org/springframework/boot/actuate/web/trace/reactive/HttpTraceWebFilter
       3: dup
       4: aload_1
       5: aload_2
       6: aload_3
       7: invokevirtual #3                  // Method org/springframework/boot/actuate/autoconfigure/trace/http/HttpTraceProperties.getInclude:()Ljava/util/Set;
      10: invokespecial #4                  // Method org/springframework/boot/actuate/web/trace/reactive/HttpTraceWebFilter."<init>":(Lorg/springframework/boot/actuate/trace/http/HttpTraceRepository;Lorg/springframework/boot/actuate/trace/http/HttpExchangeTracer;Ljava/util/Set;)V
      13: areturn
}
