Compiled from "FileUtil.java"
final class org.aspectj.util.FileUtil$1 implements java.io.FileFilter {
  org.aspectj.util.FileUtil$1();
    Code:
       0: aload_0
       1: invokespecial #1                  // Method java/lang/Object."<init>":()V
       4: return

  public boolean accept(java.io.File);
    Code:
       0: aload_1
       1: invokestatic  #2                  // Method org/aspectj/util/FileUtil.isZipFile:(Ljava/io/File;)Z
       4: ireturn

  public java.lang.String toString();
    Code:
       0: ldc           #3                  // String ZIP_FILTER
       2: areturn
}
