Compiled from "CopyEntityAsMarkdownAction.java"
public class org.protege.editor.owl.model.entity.CopyEntityAsMarkdownAction extends org.protege.editor.owl.ui.action.SelectedOWLEntityAction {
  public org.protege.editor.owl.model.entity.CopyEntityAsMarkdownAction();
    Code:
       0: aload_0
       1: invokespecial #1                  // Method org/protege/editor/owl/ui/action/SelectedOWLEntityAction."<init>":()V
       4: return

  protected void actionPerformed(org.semanticweb.owlapi.model.OWLEntity);
    Code:
       0: invokestatic  #2                  // Method java/awt/Toolkit.getDefaultToolkit:()Ljava/awt/Toolkit;
       3: invokevirtual #3                  // Method java/awt/Toolkit.getSystemClipboard:()Ljava/awt/datatransfer/Clipboard;
       6: astore_2
       7: new           #4                  // class org/protege/editor/owl/model/entity/MarkdownRenderer
      10: dup
      11: aload_0
      12: invokevirtual #5                  // Method getOWLModelManager:()Lorg/protege/editor/owl/model/OWLModelManager;
      15: invokespecial #6                  // Method org/protege/editor/owl/model/entity/MarkdownRenderer."<init>":(Lorg/protege/editor/owl/model/OWLModelManager;)V
      18: astore_3
      19: aload_3
      20: aload_1
      21: invokevirtual #7                  // Method org/protege/editor/owl/model/entity/MarkdownRenderer.renderMarkdown:(Lorg/semanticweb/owlapi/model/OWLEntity;)Ljava/lang/String;
      24: astore        4
      26: aload_2
      27: new           #8                  // class java/awt/datatransfer/StringSelection
      30: dup
      31: aload         4
      33: invokespecial #9                  // Method java/awt/datatransfer/StringSelection."<init>":(Ljava/lang/String;)V
      36: aconst_null
      37: invokevirtual #10                 // Method java/awt/datatransfer/Clipboard.setContents:(Ljava/awt/datatransfer/Transferable;Ljava/awt/datatransfer/ClipboardOwner;)V
      40: return

  protected void disposeAction() throws java.lang.Exception;
    Code:
       0: return
}
