Compiled from "UniqueIdGenerator.java"
public class org.protege.editor.owl.model.entity.UniqueIdGenerator extends org.protege.editor.owl.model.entity.AbstractIDGenerator implements org.protege.editor.owl.model.entity.AutoIDGenerator,org.protege.editor.owl.model.entity.Revertable {
  private java.util.UUID nextId;

  public org.protege.editor.owl.model.entity.UniqueIdGenerator();
    Code:
       0: aload_0
       1: invokespecial #1                  // Method org/protege/editor/owl/model/entity/AbstractIDGenerator."<init>":()V
       4: aload_0
       5: invokestatic  #2                  // Method java/util/UUID.randomUUID:()Ljava/util/UUID;
       8: putfield      #3                  // Field nextId:Ljava/util/UUID;
      11: return

  public java.lang.String getNextID(java.lang.Class<? extends org.semanticweb.owlapi.model.OWLEntity>) throws org.protege.editor.owl.model.entity.AutoIDException;
    Code:
       0: aload_0
       1: getfield      #3                  // Field nextId:Ljava/util/UUID;
       4: astore_2
       5: aload_0
       6: invokestatic  #2                  // Method java/util/UUID.randomUUID:()Ljava/util/UUID;
       9: putfield      #3                  // Field nextId:Ljava/util/UUID;
      12: new           #4                  // class java/lang/StringBuilder
      15: dup
      16: invokespecial #5                  // Method java/lang/StringBuilder."<init>":()V
      19: aload_0
      20: aload_1
      21: invokevirtual #6                  // Method getPrefix:(Ljava/lang/Class;)Ljava/lang/String;
      24: invokevirtual #7                  // Method java/lang/StringBuilder.append:(Ljava/lang/String;)Ljava/lang/StringBuilder;
      27: aload_2
      28: invokevirtual #8                  // Method java/util/UUID.toString:()Ljava/lang/String;
      31: ldc           #9                  // String -
      33: ldc           #10                 // String _
      35: invokevirtual #11                 // Method java/lang/String.replace:(Ljava/lang/CharSequence;Ljava/lang/CharSequence;)Ljava/lang/String;
      38: invokevirtual #7                  // Method java/lang/StringBuilder.append:(Ljava/lang/String;)Ljava/lang/StringBuilder;
      41: aload_0
      42: aload_1
      43: invokevirtual #12                 // Method getSuffix:(Ljava/lang/Class;)Ljava/lang/String;
      46: invokevirtual #7                  // Method java/lang/StringBuilder.append:(Ljava/lang/String;)Ljava/lang/StringBuilder;
      49: invokevirtual #13                 // Method java/lang/StringBuilder.toString:()Ljava/lang/String;
      52: areturn

  protected long getRawID(java.lang.Class<? extends org.semanticweb.owlapi.model.OWLEntity>) throws org.protege.editor.owl.model.entity.AutoIDException;
    Code:
       0: new           #14                 // class java/lang/UnsupportedOperationException
       3: dup
       4: ldc           #15                 // String Shouldn\'t get here
       6: invokespecial #16                 // Method java/lang/UnsupportedOperationException."<init>":(Ljava/lang/String;)V
       9: athrow

  public void checkpoint();
    Code:
       0: return

  public void revert();
    Code:
       0: return
}
