Compiled from "UserPermissionMigrationState.java"
public abstract class org.graylog2.cluster.UserPermissionMigrationState {
  public org.graylog2.cluster.UserPermissionMigrationState();
    Code:
       0: aload_0
       1: invokespecial #1                  // Method java/lang/Object."<init>":()V
       4: return

  public abstract boolean migrationDone();

  public static org.graylog2.cluster.UserPermissionMigrationState create(boolean);
    Code:
       0: new           #2                  // class org/graylog2/cluster/AutoValue_UserPermissionMigrationState
       3: dup
       4: iload_0
       5: invokespecial #3                  // Method org/graylog2/cluster/AutoValue_UserPermissionMigrationState."<init>":(Z)V
       8: areturn
}
