Compiled from "CacheConfiguration.java"
class net.sf.ehcache.config.CacheConfiguration$1 extends net.sf.ehcache.config.AbstractCacheConfigurationListener {
  final net.sf.ehcache.CacheManager val$cacheManager;

  final net.sf.ehcache.config.CacheConfiguration this$0;

  net.sf.ehcache.config.CacheConfiguration$1(net.sf.ehcache.config.CacheConfiguration, net.sf.ehcache.CacheManager);
    Code:
       0: aload_0
       1: aload_1
       2: putfield      #1                  // Field this$0:Lnet/sf/ehcache/config/CacheConfiguration;
       5: aload_0
       6: aload_2
       7: putfield      #2                  // Field val$cacheManager:Lnet/sf/ehcache/CacheManager;
      10: aload_0
      11: invokespecial #3                  // Method net/sf/ehcache/config/AbstractCacheConfigurationListener."<init>":()V
      14: return

  public void maxBytesLocalHeapChanged(long, long);
    Code:
       0: aload_0
       1: getfield      #1                  // Field this$0:Lnet/sf/ehcache/config/CacheConfiguration;
       4: invokevirtual #4                  // Method net/sf/ehcache/config/CacheConfiguration.getMaxBytesLocalHeap:()J
       7: lconst_0
       8: lcmp
       9: ifle          87
      12: aload_0
      13: getfield      #2                  // Field val$cacheManager:Lnet/sf/ehcache/CacheManager;
      16: invokevirtual #5                  // Method net/sf/ehcache/CacheManager.getConfiguration:()Lnet/sf/ehcache/config/Configuration;
      19: invokevirtual #6                  // Method net/sf/ehcache/config/Configuration.getCacheConfigurations:()Ljava/util/Map;
      22: invokeinterface #7,  1            // InterfaceMethod java/util/Map.keySet:()Ljava/util/Set;
      27: aload_0
      28: getfield      #1                  // Field this$0:Lnet/sf/ehcache/config/CacheConfiguration;
      31: invokevirtual #8                  // Method net/sf/ehcache/config/CacheConfiguration.getName:()Ljava/lang/String;
      34: invokeinterface #9,  2            // InterfaceMethod java/util/Set.contains:(Ljava/lang/Object;)Z
      39: ifeq          87
      42: aload_0
      43: getfield      #2                  // Field val$cacheManager:Lnet/sf/ehcache/CacheManager;
      46: invokevirtual #5                  // Method net/sf/ehcache/CacheManager.getConfiguration:()Lnet/sf/ehcache/config/Configuration;
      49: invokevirtual #10                 // Method net/sf/ehcache/config/Configuration.isMaxBytesLocalHeapSet:()Z
      52: ifeq          87
      55: aload_0
      56: getfield      #2                  // Field val$cacheManager:Lnet/sf/ehcache/CacheManager;
      59: invokevirtual #11                 // Method net/sf/ehcache/CacheManager.getOnHeapPool:()Lnet/sf/ehcache/pool/Pool;
      62: invokeinterface #12,  1           // InterfaceMethod net/sf/ehcache/pool/Pool.getMaxSize:()J
      67: lstore        5
      69: aload_0
      70: getfield      #2                  // Field val$cacheManager:Lnet/sf/ehcache/CacheManager;
      73: invokevirtual #11                 // Method net/sf/ehcache/CacheManager.getOnHeapPool:()Lnet/sf/ehcache/pool/Pool;
      76: lload         5
      78: lload_1
      79: ladd
      80: lload_3
      81: lsub
      82: invokeinterface #13,  3           // InterfaceMethod net/sf/ehcache/pool/Pool.setMaxSize:(J)V
      87: return

  public void maxBytesLocalDiskChanged(long, long);
    Code:
       0: aload_0
       1: getfield      #1                  // Field this$0:Lnet/sf/ehcache/config/CacheConfiguration;
       4: invokevirtual #14                 // Method net/sf/ehcache/config/CacheConfiguration.getMaxBytesLocalDisk:()J
       7: lconst_0
       8: lcmp
       9: ifle          87
      12: aload_0
      13: getfield      #2                  // Field val$cacheManager:Lnet/sf/ehcache/CacheManager;
      16: invokevirtual #5                  // Method net/sf/ehcache/CacheManager.getConfiguration:()Lnet/sf/ehcache/config/Configuration;
      19: invokevirtual #6                  // Method net/sf/ehcache/config/Configuration.getCacheConfigurations:()Ljava/util/Map;
      22: invokeinterface #7,  1            // InterfaceMethod java/util/Map.keySet:()Ljava/util/Set;
      27: aload_0
      28: getfield      #1                  // Field this$0:Lnet/sf/ehcache/config/CacheConfiguration;
      31: invokevirtual #8                  // Method net/sf/ehcache/config/CacheConfiguration.getName:()Ljava/lang/String;
      34: invokeinterface #9,  2            // InterfaceMethod java/util/Set.contains:(Ljava/lang/Object;)Z
      39: ifeq          87
      42: aload_0
      43: getfield      #2                  // Field val$cacheManager:Lnet/sf/ehcache/CacheManager;
      46: invokevirtual #5                  // Method net/sf/ehcache/CacheManager.getConfiguration:()Lnet/sf/ehcache/config/Configuration;
      49: invokevirtual #15                 // Method net/sf/ehcache/config/Configuration.isMaxBytesLocalDiskSet:()Z
      52: ifeq          87
      55: aload_0
      56: getfield      #2                  // Field val$cacheManager:Lnet/sf/ehcache/CacheManager;
      59: invokevirtual #16                 // Method net/sf/ehcache/CacheManager.getOnDiskPool:()Lnet/sf/ehcache/pool/Pool;
      62: invokeinterface #12,  1           // InterfaceMethod net/sf/ehcache/pool/Pool.getMaxSize:()J
      67: lstore        5
      69: aload_0
      70: getfield      #2                  // Field val$cacheManager:Lnet/sf/ehcache/CacheManager;
      73: invokevirtual #16                 // Method net/sf/ehcache/CacheManager.getOnDiskPool:()Lnet/sf/ehcache/pool/Pool;
      76: lload         5
      78: lload_1
      79: ladd
      80: lload_3
      81: lsub
      82: invokeinterface #13,  3           // InterfaceMethod net/sf/ehcache/pool/Pool.setMaxSize:(J)V
      87: return
}
