Compiled from "TimeoutBehaviorConfiguration.java"
public class net.sf.ehcache.config.TimeoutBehaviorConfiguration implements java.lang.Cloneable {
  public static final java.lang.String EXCEPTION_TYPE_NAME;

  public static final java.lang.String LOCAL_READS_TYPE_NAME;

  public static final java.lang.String NOOP_TYPE_NAME;

  public static final java.lang.String CUSTOM_TYPE_NAME;

  public static final java.lang.String CUSTOM_TYPE_FACTORY_PROPERTY_NAME;

  public static final net.sf.ehcache.config.TimeoutBehaviorConfiguration$TimeoutBehaviorType DEFAULT_TIMEOUT_BEHAVIOR_TYPE;

  public static final java.lang.String DEFAULT_PROPERTIES;

  public static final java.lang.String DEFAULT_PROPERTY_SEPARATOR;

  public static final java.lang.String DEFAULT_VALUE;

  private volatile net.sf.ehcache.config.TimeoutBehaviorConfiguration$TimeoutBehaviorType type;

  private volatile java.lang.String properties;

  private volatile java.lang.String propertySeparator;

  public net.sf.ehcache.config.TimeoutBehaviorConfiguration();
    Code:
       0: aload_0
       1: invokespecial #1                  // Method java/lang/Object."<init>":()V
       4: aload_0
       5: getstatic     #2                  // Field DEFAULT_TIMEOUT_BEHAVIOR_TYPE:Lnet/sf/ehcache/config/TimeoutBehaviorConfiguration$TimeoutBehaviorType;
       8: putfield      #3                  // Field type:Lnet/sf/ehcache/config/TimeoutBehaviorConfiguration$TimeoutBehaviorType;
      11: aload_0
      12: ldc           #4                  // String
      14: putfield      #5                  // Field properties:Ljava/lang/String;
      17: aload_0
      18: ldc           #6                  // String ,
      20: putfield      #7                  // Field propertySeparator:Ljava/lang/String;
      23: return

  public java.lang.String getType();
    Code:
       0: aload_0
       1: getfield      #3                  // Field type:Lnet/sf/ehcache/config/TimeoutBehaviorConfiguration$TimeoutBehaviorType;
       4: invokevirtual #8                  // Method net/sf/ehcache/config/TimeoutBehaviorConfiguration$TimeoutBehaviorType.getTypeName:()Ljava/lang/String;
       7: areturn

  public net.sf.ehcache.config.TimeoutBehaviorConfiguration$TimeoutBehaviorType getTimeoutBehaviorType();
    Code:
       0: aload_0
       1: getfield      #3                  // Field type:Lnet/sf/ehcache/config/TimeoutBehaviorConfiguration$TimeoutBehaviorType;
       4: areturn

  public void setType(java.lang.String);
    Code:
       0: aload_1
       1: invokestatic  #9                  // Method net/sf/ehcache/config/TimeoutBehaviorConfiguration$TimeoutBehaviorType.isValidTimeoutBehaviorType:(Ljava/lang/String;)Z
       4: ifne          76
       7: new           #10                 // class net/sf/ehcache/CacheException
      10: dup
      11: new           #11                 // class java/lang/StringBuilder
      14: dup
      15: invokespecial #12                 // Method java/lang/StringBuilder."<init>":()V
      18: ldc           #13                 // String Invalid value for timeoutBehavior type - \'
      20: invokevirtual #14                 // Method java/lang/StringBuilder.append:(Ljava/lang/String;)Ljava/lang/StringBuilder;
      23: aload_1
      24: invokevirtual #14                 // Method java/lang/StringBuilder.append:(Ljava/lang/String;)Ljava/lang/StringBuilder;
      27: ldc           #15                 // String \'. Valid values are: \'
      29: invokevirtual #14                 // Method java/lang/StringBuilder.append:(Ljava/lang/String;)Ljava/lang/StringBuilder;
      32: getstatic     #16                 // Field net/sf/ehcache/config/TimeoutBehaviorConfiguration$TimeoutBehaviorType.EXCEPTION:Lnet/sf/ehcache/config/TimeoutBehaviorConfiguration$TimeoutBehaviorType;
      35: invokevirtual #8                  // Method net/sf/ehcache/config/TimeoutBehaviorConfiguration$TimeoutBehaviorType.getTypeName:()Ljava/lang/String;
      38: invokevirtual #14                 // Method java/lang/StringBuilder.append:(Ljava/lang/String;)Ljava/lang/StringBuilder;
      41: ldc           #17                 // String \',  \'
      43: invokevirtual #14                 // Method java/lang/StringBuilder.append:(Ljava/lang/String;)Ljava/lang/StringBuilder;
      46: getstatic     #18                 // Field net/sf/ehcache/config/TimeoutBehaviorConfiguration$TimeoutBehaviorType.NOOP:Lnet/sf/ehcache/config/TimeoutBehaviorConfiguration$TimeoutBehaviorType;
      49: invokevirtual #8                  // Method net/sf/ehcache/config/TimeoutBehaviorConfiguration$TimeoutBehaviorType.getTypeName:()Ljava/lang/String;
      52: invokevirtual #14                 // Method java/lang/StringBuilder.append:(Ljava/lang/String;)Ljava/lang/StringBuilder;
      55: ldc           #17                 // String \',  \'
      57: invokevirtual #14                 // Method java/lang/StringBuilder.append:(Ljava/lang/String;)Ljava/lang/StringBuilder;
      60: getstatic     #19                 // Field net/sf/ehcache/config/TimeoutBehaviorConfiguration$TimeoutBehaviorType.LOCAL_READS:Lnet/sf/ehcache/config/TimeoutBehaviorConfiguration$TimeoutBehaviorType;
      63: invokevirtual #8                  // Method net/sf/ehcache/config/TimeoutBehaviorConfiguration$TimeoutBehaviorType.getTypeName:()Ljava/lang/String;
      66: invokevirtual #14                 // Method java/lang/StringBuilder.append:(Ljava/lang/String;)Ljava/lang/StringBuilder;
      69: invokevirtual #20                 // Method java/lang/StringBuilder.toString:()Ljava/lang/String;
      72: invokespecial #21                 // Method net/sf/ehcache/CacheException."<init>":(Ljava/lang/String;)V
      75: athrow
      76: aload_0
      77: aload_1
      78: invokestatic  #22                 // Method net/sf/ehcache/config/TimeoutBehaviorConfiguration$TimeoutBehaviorType.getTimeoutBehaviorTypeFromName:(Ljava/lang/String;)Lnet/sf/ehcache/config/TimeoutBehaviorConfiguration$TimeoutBehaviorType;
      81: putfield      #3                  // Field type:Lnet/sf/ehcache/config/TimeoutBehaviorConfiguration$TimeoutBehaviorType;
      84: return

  public net.sf.ehcache.config.TimeoutBehaviorConfiguration type(java.lang.String);
    Code:
       0: aload_0
       1: aload_1
       2: invokevirtual #23                 // Method setType:(Ljava/lang/String;)V
       5: aload_0
       6: areturn

  public java.lang.String getProperties();
    Code:
       0: aload_0
       1: getfield      #5                  // Field properties:Ljava/lang/String;
       4: areturn

  public void setProperties(java.lang.String);
    Code:
       0: aload_1
       1: ifnonnull     14
       4: new           #24                 // class java/lang/IllegalArgumentException
       7: dup
       8: ldc           #25                 // String Properties cannot be null
      10: invokespecial #26                 // Method java/lang/IllegalArgumentException."<init>":(Ljava/lang/String;)V
      13: athrow
      14: aload_0
      15: aload_1
      16: putfield      #5                  // Field properties:Ljava/lang/String;
      19: return

  public net.sf.ehcache.config.TimeoutBehaviorConfiguration properties(java.lang.String);
    Code:
       0: aload_0
       1: aload_1
       2: invokevirtual #27                 // Method setProperties:(Ljava/lang/String;)V
       5: aload_0
       6: areturn

  public java.lang.String getPropertySeparator();
    Code:
       0: aload_0
       1: getfield      #7                  // Field propertySeparator:Ljava/lang/String;
       4: areturn

  public void setPropertySeparator(java.lang.String);
    Code:
       0: aload_1
       1: ifnonnull     14
       4: new           #24                 // class java/lang/IllegalArgumentException
       7: dup
       8: ldc           #28                 // String Property Separator cannot be null
      10: invokespecial #26                 // Method java/lang/IllegalArgumentException."<init>":(Ljava/lang/String;)V
      13: athrow
      14: aload_0
      15: aload_1
      16: putfield      #7                  // Field propertySeparator:Ljava/lang/String;
      19: return

  public net.sf.ehcache.config.TimeoutBehaviorConfiguration propertySeparator(java.lang.String);
    Code:
       0: aload_0
       1: aload_1
       2: invokevirtual #29                 // Method setPropertySeparator:(Ljava/lang/String;)V
       5: aload_0
       6: areturn

  public java.lang.Object clone() throws java.lang.CloneNotSupportedException;
    Code:
       0: aload_0
       1: invokespecial #30                 // Method java/lang/Object.clone:()Ljava/lang/Object;
       4: areturn

  public int hashCode();
    Code:
       0: bipush        31
       2: istore_1
       3: iconst_1
       4: istore_2
       5: bipush        31
       7: iload_2
       8: imul
       9: aload_0
      10: getfield      #5                  // Field properties:Ljava/lang/String;
      13: ifnonnull     20
      16: iconst_0
      17: goto          27
      20: aload_0
      21: getfield      #5                  // Field properties:Ljava/lang/String;
      24: invokevirtual #31                 // Method java/lang/String.hashCode:()I
      27: iadd
      28: istore_2
      29: bipush        31
      31: iload_2
      32: imul
      33: aload_0
      34: getfield      #7                  // Field propertySeparator:Ljava/lang/String;
      37: ifnonnull     44
      40: iconst_0
      41: goto          51
      44: aload_0
      45: getfield      #7                  // Field propertySeparator:Ljava/lang/String;
      48: invokevirtual #31                 // Method java/lang/String.hashCode:()I
      51: iadd
      52: istore_2
      53: bipush        31
      55: iload_2
      56: imul
      57: aload_0
      58: getfield      #3                  // Field type:Lnet/sf/ehcache/config/TimeoutBehaviorConfiguration$TimeoutBehaviorType;
      61: ifnonnull     68
      64: iconst_0
      65: goto          75
      68: aload_0
      69: getfield      #3                  // Field type:Lnet/sf/ehcache/config/TimeoutBehaviorConfiguration$TimeoutBehaviorType;
      72: invokevirtual #32                 // Method net/sf/ehcache/config/TimeoutBehaviorConfiguration$TimeoutBehaviorType.hashCode:()I
      75: iadd
      76: istore_2
      77: iload_2
      78: ireturn

  public boolean equals(java.lang.Object);
    Code:
       0: aload_0
       1: aload_1
       2: if_acmpne     7
       5: iconst_1
       6: ireturn
       7: aload_1
       8: ifnull        22
      11: aload_0
      12: invokevirtual #33                 // Method java/lang/Object.getClass:()Ljava/lang/Class;
      15: aload_1
      16: invokevirtual #33                 // Method java/lang/Object.getClass:()Ljava/lang/Class;
      19: if_acmpeq     24
      22: iconst_0
      23: ireturn
      24: aload_1
      25: checkcast     #34                 // class net/sf/ehcache/config/TimeoutBehaviorConfiguration
      28: astore_2
      29: aload_0
      30: getfield      #5                  // Field properties:Ljava/lang/String;
      33: ifnonnull     45
      36: aload_2
      37: getfield      #5                  // Field properties:Ljava/lang/String;
      40: ifnull        61
      43: iconst_0
      44: ireturn
      45: aload_0
      46: getfield      #5                  // Field properties:Ljava/lang/String;
      49: aload_2
      50: getfield      #5                  // Field properties:Ljava/lang/String;
      53: invokevirtual #35                 // Method java/lang/String.equals:(Ljava/lang/Object;)Z
      56: ifne          61
      59: iconst_0
      60: ireturn
      61: aload_0
      62: getfield      #7                  // Field propertySeparator:Ljava/lang/String;
      65: ifnonnull     77
      68: aload_2
      69: getfield      #7                  // Field propertySeparator:Ljava/lang/String;
      72: ifnull        93
      75: iconst_0
      76: ireturn
      77: aload_0
      78: getfield      #7                  // Field propertySeparator:Ljava/lang/String;
      81: aload_2
      82: getfield      #7                  // Field propertySeparator:Ljava/lang/String;
      85: invokevirtual #35                 // Method java/lang/String.equals:(Ljava/lang/Object;)Z
      88: ifne          93
      91: iconst_0
      92: ireturn
      93: aload_0
      94: getfield      #3                  // Field type:Lnet/sf/ehcache/config/TimeoutBehaviorConfiguration$TimeoutBehaviorType;
      97: aload_2
      98: getfield      #3                  // Field type:Lnet/sf/ehcache/config/TimeoutBehaviorConfiguration$TimeoutBehaviorType;
     101: if_acmpne     108
     104: iconst_1
     105: goto          109
     108: iconst_0
     109: ireturn

  public net.sf.ehcache.constructs.nonstop.NonstopTimeoutBehaviorFactory getNonstopTimeoutBehaviorFactory();
    Code:
       0: getstatic     #36                 // Field net/sf/ehcache/config/TimeoutBehaviorConfiguration$1.$SwitchMap$net$sf$ehcache$config$TimeoutBehaviorConfiguration$TimeoutBehaviorType:[I
       3: aload_0
       4: getfield      #3                  // Field type:Lnet/sf/ehcache/config/TimeoutBehaviorConfiguration$TimeoutBehaviorType;
       7: invokevirtual #37                 // Method net/sf/ehcache/config/TimeoutBehaviorConfiguration$TimeoutBehaviorType.ordinal:()I
      10: iaload
      11: tableswitch   { // 1 to 4
                     1: 40
                     2: 40
                     3: 40
                     4: 49
               default: 61
          }
      40: aload_0
      41: getfield      #3                  // Field type:Lnet/sf/ehcache/config/TimeoutBehaviorConfiguration$TimeoutBehaviorType;
      44: aconst_null
      45: invokevirtual #38                 // Method net/sf/ehcache/config/TimeoutBehaviorConfiguration$TimeoutBehaviorType.getTimeoutBehaviorFactory:(Ljava/util/Properties;)Lnet/sf/ehcache/constructs/nonstop/NonstopTimeoutBehaviorFactory;
      48: areturn
      49: aload_0
      50: getfield      #3                  // Field type:Lnet/sf/ehcache/config/TimeoutBehaviorConfiguration$TimeoutBehaviorType;
      53: aload_0
      54: invokespecial #39                 // Method extractProperties:()Ljava/util/Properties;
      57: invokevirtual #38                 // Method net/sf/ehcache/config/TimeoutBehaviorConfiguration$TimeoutBehaviorType.getTimeoutBehaviorFactory:(Ljava/util/Properties;)Lnet/sf/ehcache/constructs/nonstop/NonstopTimeoutBehaviorFactory;
      60: areturn
      61: new           #10                 // class net/sf/ehcache/CacheException
      64: dup
      65: new           #11                 // class java/lang/StringBuilder
      68: dup
      69: invokespecial #12                 // Method java/lang/StringBuilder."<init>":()V
      72: ldc           #40                 // String Unknown timeout behavior type -
      74: invokevirtual #14                 // Method java/lang/StringBuilder.append:(Ljava/lang/String;)Ljava/lang/StringBuilder;
      77: aload_0
      78: getfield      #3                  // Field type:Lnet/sf/ehcache/config/TimeoutBehaviorConfiguration$TimeoutBehaviorType;
      81: invokevirtual #41                 // Method java/lang/StringBuilder.append:(Ljava/lang/Object;)Ljava/lang/StringBuilder;
      84: invokevirtual #20                 // Method java/lang/StringBuilder.toString:()Ljava/lang/String;
      87: invokespecial #21                 // Method net/sf/ehcache/CacheException."<init>":(Ljava/lang/String;)V
      90: athrow

  private java.util.Properties extractProperties();
    Code:
       0: new           #42                 // class java/util/Properties
       3: dup
       4: invokespecial #43                 // Method java/util/Properties."<init>":()V
       7: astore_1
       8: aload_0
       9: getfield      #5                  // Field properties:Ljava/lang/String;
      12: astore_2
      13: aload_0
      14: getfield      #7                  // Field propertySeparator:Ljava/lang/String;
      17: astore_3
      18: aload_2
      19: aload_0
      20: getfield      #7                  // Field propertySeparator:Ljava/lang/String;
      23: invokevirtual #44                 // Method java/lang/String.split:(Ljava/lang/String;)[Ljava/lang/String;
      26: astore        4
      28: aload         4
      30: astore        5
      32: aload         5
      34: arraylength
      35: istore        6
      37: iconst_0
      38: istore        7
      40: iload         7
      42: iload         6
      44: if_icmpge     122
      47: aload         5
      49: iload         7
      51: aaload
      52: astore        8
      54: aload         8
      56: ldc           #45                 // String =
      58: invokevirtual #44                 // Method java/lang/String.split:(Ljava/lang/String;)[Ljava/lang/String;
      61: astore        9
      63: aload         9
      65: ifnull        75
      68: aload         9
      70: arraylength
      71: iconst_2
      72: if_icmpeq     103
      75: new           #46                 // class net/sf/ehcache/config/InvalidConfigurationException
      78: dup
      79: new           #11                 // class java/lang/StringBuilder
      82: dup
      83: invokespecial #12                 // Method java/lang/StringBuilder."<init>":()V
      86: ldc           #47                 // String Property not specified correctly. Failed to parse:
      88: invokevirtual #14                 // Method java/lang/StringBuilder.append:(Ljava/lang/String;)Ljava/lang/StringBuilder;
      91: aload         8
      93: invokevirtual #14                 // Method java/lang/StringBuilder.append:(Ljava/lang/String;)Ljava/lang/StringBuilder;
      96: invokevirtual #20                 // Method java/lang/StringBuilder.toString:()Ljava/lang/String;
      99: invokespecial #48                 // Method net/sf/ehcache/config/InvalidConfigurationException."<init>":(Ljava/lang/String;)V
     102: athrow
     103: aload_1
     104: aload         9
     106: iconst_0
     107: aaload
     108: aload         9
     110: iconst_1
     111: aaload
     112: invokevirtual #49                 // Method java/util/Properties.setProperty:(Ljava/lang/String;Ljava/lang/String;)Ljava/lang/Object;
     115: pop
     116: iinc          7, 1
     119: goto          40
     122: aload_1
     123: areturn

  static {};
    Code:
       0: getstatic     #16                 // Field net/sf/ehcache/config/TimeoutBehaviorConfiguration$TimeoutBehaviorType.EXCEPTION:Lnet/sf/ehcache/config/TimeoutBehaviorConfiguration$TimeoutBehaviorType;
       3: putstatic     #2                  // Field DEFAULT_TIMEOUT_BEHAVIOR_TYPE:Lnet/sf/ehcache/config/TimeoutBehaviorConfiguration$TimeoutBehaviorType;
       6: getstatic     #2                  // Field DEFAULT_TIMEOUT_BEHAVIOR_TYPE:Lnet/sf/ehcache/config/TimeoutBehaviorConfiguration$TimeoutBehaviorType;
       9: invokevirtual #8                  // Method net/sf/ehcache/config/TimeoutBehaviorConfiguration$TimeoutBehaviorType.getTypeName:()Ljava/lang/String;
      12: putstatic     #50                 // Field DEFAULT_VALUE:Ljava/lang/String;
      15: return
}
