Compiled from "PeekSource.kt"
public final class okio.PeekSource implements okio.Source {
  private final okio.Buffer buffer;

  private okio.Segment expectedSegment;

  private int expectedPos;

  private boolean closed;

  private long pos;

  private final okio.BufferedSource upstream;

  public long read(okio.Buffer, long);
    Code:
       0: aload_1
       1: ldc           #21                 // String sink
       3: invokestatic  #27                 // Method kotlin/jvm/internal/Intrinsics.checkNotNullParameter:(Ljava/lang/Object;Ljava/lang/String;)V
       6: lload_2
       7: lconst_0
       8: lcmp
       9: iflt          16
      12: iconst_1
      13: goto          17
      16: iconst_0
      17: istore        4
      19: iconst_0
      20: istore        5
      22: iconst_0
      23: istore        6
      25: iload         4
      27: ifne          70
      30: iconst_0
      31: istore        7
      33: new           #29                 // class java/lang/StringBuilder
      36: dup
      37: invokespecial #33                 // Method java/lang/StringBuilder."<init>":()V
      40: ldc           #35                 // String byteCount < 0:
      42: invokevirtual #39                 // Method java/lang/StringBuilder.append:(Ljava/lang/String;)Ljava/lang/StringBuilder;
      45: lload_2
      46: invokevirtual #42                 // Method java/lang/StringBuilder.append:(J)Ljava/lang/StringBuilder;
      49: invokevirtual #46                 // Method java/lang/StringBuilder.toString:()Ljava/lang/String;
      52: astore        6
      54: new           #48                 // class java/lang/IllegalArgumentException
      57: dup
      58: aload         6
      60: invokevirtual #49                 // Method java/lang/Object.toString:()Ljava/lang/String;
      63: invokespecial #52                 // Method java/lang/IllegalArgumentException."<init>":(Ljava/lang/String;)V
      66: checkcast     #54                 // class java/lang/Throwable
      69: athrow
      70: aload_0
      71: getfield      #56                 // Field closed:Z
      74: ifne          81
      77: iconst_1
      78: goto          82
      81: iconst_0
      82: istore        4
      84: iconst_0
      85: istore        5
      87: iconst_0
      88: istore        6
      90: iload         4
      92: ifne          118
      95: iconst_0
      96: istore        7
      98: ldc           #57                 // String closed
     100: astore        6
     102: new           #59                 // class java/lang/IllegalStateException
     105: dup
     106: aload         6
     108: invokevirtual #49                 // Method java/lang/Object.toString:()Ljava/lang/String;
     111: invokespecial #60                 // Method java/lang/IllegalStateException."<init>":(Ljava/lang/String;)V
     114: checkcast     #54                 // class java/lang/Throwable
     117: athrow
     118: aload_0
     119: getfield      #62                 // Field expectedSegment:Lokio/Segment;
     122: ifnull        160
     125: aload_0
     126: getfield      #62                 // Field expectedSegment:Lokio/Segment;
     129: aload_0
     130: getfield      #64                 // Field buffer:Lokio/Buffer;
     133: getfield      #69                 // Field okio/Buffer.head:Lokio/Segment;
     136: if_acmpne     164
     139: aload_0
     140: getfield      #71                 // Field expectedPos:I
     143: aload_0
     144: getfield      #64                 // Field buffer:Lokio/Buffer;
     147: getfield      #69                 // Field okio/Buffer.head:Lokio/Segment;
     150: dup
     151: invokestatic  #75                 // Method kotlin/jvm/internal/Intrinsics.checkNotNull:(Ljava/lang/Object;)V
     154: getfield      #79                 // Field okio/Segment.pos:I
     157: if_icmpne     164
     160: iconst_1
     161: goto          165
     164: iconst_0
     165: istore        4
     167: iconst_0
     168: istore        5
     170: iconst_0
     171: istore        6
     173: iload         4
     175: ifne          201
     178: iconst_0
     179: istore        7
     181: ldc           #81                 // String Peek source is invalid because upstream source was used
     183: astore        6
     185: new           #59                 // class java/lang/IllegalStateException
     188: dup
     189: aload         6
     191: invokevirtual #49                 // Method java/lang/Object.toString:()Ljava/lang/String;
     194: invokespecial #60                 // Method java/lang/IllegalStateException."<init>":(Ljava/lang/String;)V
     197: checkcast     #54                 // class java/lang/Throwable
     200: athrow
     201: lload_2
     202: lconst_0
     203: lcmp
     204: ifne          209
     207: lconst_0
     208: lreturn
     209: aload_0
     210: getfield      #85                 // Field upstream:Lokio/BufferedSource;
     213: aload_0
     214: getfield      #87                 // Field pos:J
     217: lconst_1
     218: ladd
     219: invokeinterface #93,  3           // InterfaceMethod okio/BufferedSource.request:(J)Z
     224: ifne          231
     227: ldc2_w        #94                 // long -1l
     230: lreturn
     231: aload_0
     232: getfield      #62                 // Field expectedSegment:Lokio/Segment;
     235: ifnonnull     277
     238: aload_0
     239: getfield      #64                 // Field buffer:Lokio/Buffer;
     242: getfield      #69                 // Field okio/Buffer.head:Lokio/Segment;
     245: ifnull        277
     248: aload_0
     249: aload_0
     250: getfield      #64                 // Field buffer:Lokio/Buffer;
     253: getfield      #69                 // Field okio/Buffer.head:Lokio/Segment;
     256: putfield      #62                 // Field expectedSegment:Lokio/Segment;
     259: aload_0
     260: aload_0
     261: getfield      #64                 // Field buffer:Lokio/Buffer;
     264: getfield      #69                 // Field okio/Buffer.head:Lokio/Segment;
     267: dup
     268: invokestatic  #75                 // Method kotlin/jvm/internal/Intrinsics.checkNotNull:(Ljava/lang/Object;)V
     271: getfield      #79                 // Field okio/Segment.pos:I
     274: putfield      #71                 // Field expectedPos:I
     277: aload_0
     278: getfield      #64                 // Field buffer:Lokio/Buffer;
     281: invokevirtual #99                 // Method okio/Buffer.size:()J
     284: aload_0
     285: getfield      #87                 // Field pos:J
     288: lsub
     289: lstore        6
     291: iconst_0
     292: istore        8
     294: lload_2
     295: lload         6
     297: invokestatic  #105                // Method java/lang/Math.min:(JJ)J
     300: lstore        4
     302: aload_0
     303: getfield      #64                 // Field buffer:Lokio/Buffer;
     306: aload_1
     307: aload_0
     308: getfield      #87                 // Field pos:J
     311: lload         4
     313: invokevirtual #109                // Method okio/Buffer.copyTo:(Lokio/Buffer;JJ)Lokio/Buffer;
     316: pop
     317: aload_0
     318: dup
     319: getfield      #87                 // Field pos:J
     322: lload         4
     324: ladd
     325: putfield      #87                 // Field pos:J
     328: lload         4
     330: lreturn

  public okio.Timeout timeout();
    Code:
       0: aload_0
       1: getfield      #85                 // Field upstream:Lokio/BufferedSource;
       4: invokeinterface #120,  1          // InterfaceMethod okio/BufferedSource.timeout:()Lokio/Timeout;
       9: areturn

  public void close();
    Code:
       0: aload_0
       1: iconst_1
       2: putfield      #56                 // Field closed:Z
       5: return

  public okio.PeekSource(okio.BufferedSource);
    Code:
       0: aload_1
       1: ldc           #123                // String upstream
       3: invokestatic  #27                 // Method kotlin/jvm/internal/Intrinsics.checkNotNullParameter:(Ljava/lang/Object;Ljava/lang/String;)V
       6: aload_0
       7: invokespecial #124                // Method java/lang/Object."<init>":()V
      10: aload_0
      11: aload_1
      12: putfield      #85                 // Field upstream:Lokio/BufferedSource;
      15: aload_0
      16: aload_0
      17: getfield      #85                 // Field upstream:Lokio/BufferedSource;
      20: invokeinterface #128,  1          // InterfaceMethod okio/BufferedSource.getBuffer:()Lokio/Buffer;
      25: putfield      #64                 // Field buffer:Lokio/Buffer;
      28: aload_0
      29: aload_0
      30: getfield      #64                 // Field buffer:Lokio/Buffer;
      33: getfield      #69                 // Field okio/Buffer.head:Lokio/Segment;
      36: putfield      #62                 // Field expectedSegment:Lokio/Segment;
      39: aload_0
      40: aload_0
      41: getfield      #64                 // Field buffer:Lokio/Buffer;
      44: getfield      #69                 // Field okio/Buffer.head:Lokio/Segment;
      47: dup
      48: ifnull        57
      51: getfield      #79                 // Field okio/Segment.pos:I
      54: goto          59
      57: pop
      58: iconst_m1
      59: putfield      #71                 // Field expectedPos:I
      62: return
}
