Compiled from "CachedClock.java"
public final class org.apache.logging.log4j.core.util.CachedClock implements org.apache.logging.log4j.core.util.Clock {
  private static final int UPDATE_THRESHOLD;

  private static volatile org.apache.logging.log4j.core.util.CachedClock instance;

  private static final java.lang.Object INSTANCE_LOCK;

  private volatile long millis;

  private short count;

  private org.apache.logging.log4j.core.util.CachedClock();
    Code:
       0: aload_0
       1: invokespecial #1                  // Method java/lang/Object."<init>":()V
       4: aload_0
       5: invokestatic  #2                  // Method java/lang/System.currentTimeMillis:()J
       8: putfield      #3                  // Field millis:J
      11: aload_0
      12: iconst_0
      13: putfield      #4                  // Field count:S
      16: new           #5                  // class org/apache/logging/log4j/core/util/Log4jThread
      19: dup
      20: aload_0
      21: invokedynamic #6,  0              // InvokeDynamic #0:run:(Lorg/apache/logging/log4j/core/util/CachedClock;)Ljava/lang/Runnable;
      26: ldc           #7                  // String CachedClock Updater Thread
      28: invokespecial #8                  // Method org/apache/logging/log4j/core/util/Log4jThread."<init>":(Ljava/lang/Runnable;Ljava/lang/String;)V
      31: astore_1
      32: aload_1
      33: iconst_1
      34: invokevirtual #9                  // Method java/lang/Thread.setDaemon:(Z)V
      37: aload_1
      38: invokevirtual #10                 // Method java/lang/Thread.start:()V
      41: return

  public static org.apache.logging.log4j.core.util.CachedClock instance();
    Code:
       0: getstatic     #11                 // Field instance:Lorg/apache/logging/log4j/core/util/CachedClock;
       3: astore_0
       4: aload_0
       5: ifnonnull     44
       8: getstatic     #12                 // Field INSTANCE_LOCK:Ljava/lang/Object;
      11: dup
      12: astore_1
      13: monitorenter
      14: getstatic     #11                 // Field instance:Lorg/apache/logging/log4j/core/util/CachedClock;
      17: astore_0
      18: aload_0
      19: ifnonnull     34
      22: new           #13                 // class org/apache/logging/log4j/core/util/CachedClock
      25: dup
      26: invokespecial #14                 // Method "<init>":()V
      29: dup
      30: astore_0
      31: putstatic     #11                 // Field instance:Lorg/apache/logging/log4j/core/util/CachedClock;
      34: aload_1
      35: monitorexit
      36: goto          44
      39: astore_2
      40: aload_1
      41: monitorexit
      42: aload_2
      43: athrow
      44: aload_0
      45: areturn
    Exception table:
       from    to  target type
          14    36    39   any
          39    42    39   any

  public long currentTimeMillis();
    Code:
       0: aload_0
       1: dup
       2: getfield      #4                  // Field count:S
       5: iconst_1
       6: iadd
       7: i2s
       8: dup_x1
       9: putfield      #4                  // Field count:S
      12: sipush        1000
      15: if_icmple     30
      18: aload_0
      19: invokestatic  #2                  // Method java/lang/System.currentTimeMillis:()J
      22: putfield      #3                  // Field millis:J
      25: aload_0
      26: iconst_0
      27: putfield      #4                  // Field count:S
      30: aload_0
      31: getfield      #3                  // Field millis:J
      34: lreturn

  private void lambda$new$0();
    Code:
       0: invokestatic  #2                  // Method java/lang/System.currentTimeMillis:()J
       3: lstore_1
       4: aload_0
       5: lload_1
       6: putfield      #3                  // Field millis:J
       9: ldc2_w        #15                 // long 1000000l
      12: invokestatic  #17                 // Method java/util/concurrent/locks/LockSupport.parkNanos:(J)V
      15: goto          0

  static {};
    Code:
       0: new           #18                 // class java/lang/Object
       3: dup
       4: invokespecial #1                  // Method java/lang/Object."<init>":()V
       7: putstatic     #12                 // Field INSTANCE_LOCK:Ljava/lang/Object;
      10: return
}
