Compiled from "JavaHttpClientChannel.scala"
public final class wvlet.airframe.http.client.JavaHttpClientChannel$$anon$1 implements java.util.function.Consumer<java.net.http.HttpResponse<java.io.InputStream>> {
  private final wvlet.airframe.http.client.JavaHttpClientChannel $outer;

  private final wvlet.airframe.rx.RxVar v$1;

  public java.util.function.Consumer<java.net.http.HttpResponse<java.io.InputStream>> andThen(java.util.function.Consumer<? super java.net.http.HttpResponse<java.io.InputStream>>);
    Code:
       0: aload_0
       1: aload_1
       2: invokespecial #28                 // InterfaceMethod java/util/function/Consumer.andThen:(Ljava/util/function/Consumer;)Ljava/util/function/Consumer;
       5: areturn

  public void accept(java.net.http.HttpResponse<java.io.InputStream>);
    Code:
       0: aload_0
       1: getfield      #37                 // Field $outer:Lwvlet/airframe/http/client/JavaHttpClientChannel;
       4: aload_1
       5: invokevirtual #41                 // Method wvlet/airframe/http/client/JavaHttpClientChannel.wvlet$airframe$http$client$JavaHttpClientChannel$$readResponse:(Ljava/net/http/HttpResponse;)Lwvlet/airframe/http/HttpMessage$Response;
       8: astore_2
       9: aload_0
      10: getfield      #43                 // Field v$1:Lwvlet/airframe/rx/RxVar;
      13: new           #45                 // class scala/Some
      16: dup
      17: aload_2
      18: invokespecial #49                 // Method scala/Some."<init>":(Ljava/lang/Object;)V
      21: invokevirtual #54                 // Method wvlet/airframe/rx/RxVar.set:(Ljava/lang/Object;)V
      24: aload_0
      25: getfield      #43                 // Field v$1:Lwvlet/airframe/rx/RxVar;
      28: invokevirtual #58                 // Method wvlet/airframe/rx/RxVar.stop:()V
      31: return

  public void accept(java.lang.Object);
    Code:
       0: aload_0
       1: aload_1
       2: checkcast     #63                 // class java/net/http/HttpResponse
       5: invokevirtual #65                 // Method accept:(Ljava/net/http/HttpResponse;)V
       8: return

  public wvlet.airframe.http.client.JavaHttpClientChannel$$anon$1(wvlet.airframe.http.client.JavaHttpClientChannel, wvlet.airframe.rx.RxVar);
    Code:
       0: aload_1
       1: ifnonnull     6
       4: aconst_null
       5: athrow
       6: aload_0
       7: aload_1
       8: putfield      #37                 // Field $outer:Lwvlet/airframe/http/client/JavaHttpClientChannel;
      11: aload_0
      12: aload_2
      13: putfield      #43                 // Field v$1:Lwvlet/airframe/rx/RxVar;
      16: aload_0
      17: invokespecial #69                 // Method java/lang/Object."<init>":()V
      20: return
}
