Compiled from "ExchangeFailedEvent.java"
public class org.apache.camel.management.event.ExchangeFailedEvent extends org.apache.camel.management.event.AbstractExchangeEvent {
  private static final long serialVersionUID;

  public org.apache.camel.management.event.ExchangeFailedEvent(org.apache.camel.Exchange);
    Code:
       0: aload_0
       1: aload_1
       2: invokespecial #13                 // Method org/apache/camel/management/event/AbstractExchangeEvent."<init>":(Lorg/apache/camel/Exchange;)V
       5: return

  public java.lang.String toString();
    Code:
       0: aload_0
       1: invokevirtual #23                 // Method getExchange:()Lorg/apache/camel/Exchange;
       4: invokeinterface #29,  1           // InterfaceMethod org/apache/camel/Exchange.getException:()Ljava/lang/Exception;
       9: astore_1
      10: aload_1
      11: ifnull        58
      14: new           #31                 // class java/lang/StringBuilder
      17: dup
      18: invokespecial #34                 // Method java/lang/StringBuilder."<init>":()V
      21: aload_0
      22: invokevirtual #23                 // Method getExchange:()Lorg/apache/camel/Exchange;
      25: invokeinterface #37,  1           // InterfaceMethod org/apache/camel/Exchange.getExchangeId:()Ljava/lang/String;
      30: invokevirtual #41                 // Method java/lang/StringBuilder.append:(Ljava/lang/String;)Ljava/lang/StringBuilder;
      33: ldc           #43                 // String  exchange failure:
      35: invokevirtual #41                 // Method java/lang/StringBuilder.append:(Ljava/lang/String;)Ljava/lang/StringBuilder;
      38: aload_0
      39: invokevirtual #23                 // Method getExchange:()Lorg/apache/camel/Exchange;
      42: invokevirtual #46                 // Method java/lang/StringBuilder.append:(Ljava/lang/Object;)Ljava/lang/StringBuilder;
      45: ldc           #48                 // String  cause
      47: invokevirtual #41                 // Method java/lang/StringBuilder.append:(Ljava/lang/String;)Ljava/lang/StringBuilder;
      50: aload_1
      51: invokevirtual #46                 // Method java/lang/StringBuilder.append:(Ljava/lang/Object;)Ljava/lang/StringBuilder;
      54: invokevirtual #50                 // Method java/lang/StringBuilder.toString:()Ljava/lang/String;
      57: areturn
      58: new           #31                 // class java/lang/StringBuilder
      61: dup
      62: invokespecial #34                 // Method java/lang/StringBuilder."<init>":()V
      65: aload_0
      66: invokevirtual #23                 // Method getExchange:()Lorg/apache/camel/Exchange;
      69: invokeinterface #37,  1           // InterfaceMethod org/apache/camel/Exchange.getExchangeId:()Ljava/lang/String;
      74: invokevirtual #41                 // Method java/lang/StringBuilder.append:(Ljava/lang/String;)Ljava/lang/StringBuilder;
      77: ldc           #43                 // String  exchange failure:
      79: invokevirtual #41                 // Method java/lang/StringBuilder.append:(Ljava/lang/String;)Ljava/lang/StringBuilder;
      82: aload_0
      83: invokevirtual #23                 // Method getExchange:()Lorg/apache/camel/Exchange;
      86: invokevirtual #46                 // Method java/lang/StringBuilder.append:(Ljava/lang/Object;)Ljava/lang/StringBuilder;
      89: invokevirtual #50                 // Method java/lang/StringBuilder.toString:()Ljava/lang/String;
      92: areturn
}
