Compiled from "CassandraProperties.java"
public class org.springframework.boot.autoconfigure.cassandra.CassandraProperties$Request {
  private java.time.Duration timeout;

  private com.datastax.oss.driver.api.core.DefaultConsistencyLevel consistency;

  private com.datastax.oss.driver.api.core.DefaultConsistencyLevel serialConsistency;

  private int pageSize;

  private final org.springframework.boot.autoconfigure.cassandra.CassandraProperties$Throttler throttler;

  public org.springframework.boot.autoconfigure.cassandra.CassandraProperties$Request();
    Code:
       0: aload_0
       1: invokespecial #1                  // Method java/lang/Object."<init>":()V
       4: aload_0
       5: ldc2_w        #2                  // long 2l
       8: invokestatic  #4                  // Method java/time/Duration.ofSeconds:(J)Ljava/time/Duration;
      11: putfield      #5                  // Field timeout:Ljava/time/Duration;
      14: aload_0
      15: sipush        5000
      18: putfield      #6                  // Field pageSize:I
      21: aload_0
      22: new           #7                  // class org/springframework/boot/autoconfigure/cassandra/CassandraProperties$Throttler
      25: dup
      26: invokespecial #8                  // Method org/springframework/boot/autoconfigure/cassandra/CassandraProperties$Throttler."<init>":()V
      29: putfield      #9                  // Field throttler:Lorg/springframework/boot/autoconfigure/cassandra/CassandraProperties$Throttler;
      32: return

  public java.time.Duration getTimeout();
    Code:
       0: aload_0
       1: getfield      #5                  // Field timeout:Ljava/time/Duration;
       4: areturn

  public void setTimeout(java.time.Duration);
    Code:
       0: aload_0
       1: aload_1
       2: putfield      #5                  // Field timeout:Ljava/time/Duration;
       5: return

  public com.datastax.oss.driver.api.core.DefaultConsistencyLevel getConsistency();
    Code:
       0: aload_0
       1: getfield      #10                 // Field consistency:Lcom/datastax/oss/driver/api/core/DefaultConsistencyLevel;
       4: areturn

  public void setConsistency(com.datastax.oss.driver.api.core.DefaultConsistencyLevel);
    Code:
       0: aload_0
       1: aload_1
       2: putfield      #10                 // Field consistency:Lcom/datastax/oss/driver/api/core/DefaultConsistencyLevel;
       5: return

  public com.datastax.oss.driver.api.core.DefaultConsistencyLevel getSerialConsistency();
    Code:
       0: aload_0
       1: getfield      #11                 // Field serialConsistency:Lcom/datastax/oss/driver/api/core/DefaultConsistencyLevel;
       4: areturn

  public void setSerialConsistency(com.datastax.oss.driver.api.core.DefaultConsistencyLevel);
    Code:
       0: aload_0
       1: aload_1
       2: putfield      #11                 // Field serialConsistency:Lcom/datastax/oss/driver/api/core/DefaultConsistencyLevel;
       5: return

  public int getPageSize();
    Code:
       0: aload_0
       1: getfield      #6                  // Field pageSize:I
       4: ireturn

  public void setPageSize(int);
    Code:
       0: aload_0
       1: iload_1
       2: putfield      #6                  // Field pageSize:I
       5: return

  public org.springframework.boot.autoconfigure.cassandra.CassandraProperties$Throttler getThrottler();
    Code:
       0: aload_0
       1: getfield      #9                  // Field throttler:Lorg/springframework/boot/autoconfigure/cassandra/CassandraProperties$Throttler;
       4: areturn
}
