Compiled from "AuthUserDetails.java"
public class io.mosip.kernel.core.authmanager.authadapter.model.AuthUserDetails implements org.springframework.security.core.userdetails.UserDetails {
  private static final long serialVersionUID;

  private java.lang.String userId;

  private java.lang.String token;

  private java.lang.String mail;

  private java.lang.String mobile;

  private java.lang.String rId;

  private java.util.Collection<? extends org.springframework.security.core.GrantedAuthority> authorities;

  public io.mosip.kernel.core.authmanager.authadapter.model.AuthUserDetails(io.mosip.kernel.core.authmanager.authadapter.model.MosipUserDto, java.lang.String);
    Code:
       0: aload_0
       1: invokespecial #1                  // Method java/lang/Object."<init>":()V
       4: aload_0
       5: aload_1
       6: invokevirtual #2                  // Method io/mosip/kernel/core/authmanager/authadapter/model/MosipUserDto.getUserId:()Ljava/lang/String;
       9: putfield      #3                  // Field userId:Ljava/lang/String;
      12: aload_0
      13: aload_2
      14: putfield      #4                  // Field token:Ljava/lang/String;
      17: aload_0
      18: aload_1
      19: invokevirtual #5                  // Method io/mosip/kernel/core/authmanager/authadapter/model/MosipUserDto.getMail:()Ljava/lang/String;
      22: putfield      #6                  // Field mail:Ljava/lang/String;
      25: aload_0
      26: aload_1
      27: invokevirtual #7                  // Method io/mosip/kernel/core/authmanager/authadapter/model/MosipUserDto.getMobile:()Ljava/lang/String;
      30: putfield      #8                  // Field mobile:Ljava/lang/String;
      33: aload_0
      34: aload_1
      35: invokevirtual #9                  // Method io/mosip/kernel/core/authmanager/authadapter/model/MosipUserDto.getRId:()Ljava/lang/String;
      38: putfield      #10                 // Field rId:Ljava/lang/String;
      41: return

  public java.util.Collection<? extends org.springframework.security.core.GrantedAuthority> getAuthorities();
    Code:
       0: aload_0
       1: getfield      #11                 // Field authorities:Ljava/util/Collection;
       4: invokeinterface #12,  1           // InterfaceMethod java/util/Collection.stream:()Ljava/util/stream/Stream;
       9: invokedynamic #13,  0             // InvokeDynamic #0:apply:()Ljava/util/function/Function;
      14: invokeinterface #14,  2           // InterfaceMethod java/util/stream/Stream.map:(Ljava/util/function/Function;)Ljava/util/stream/Stream;
      19: invokestatic  #15                 // Method java/util/stream/Collectors.toList:()Ljava/util/stream/Collector;
      22: invokeinterface #16,  2           // InterfaceMethod java/util/stream/Stream.collect:(Ljava/util/stream/Collector;)Ljava/lang/Object;
      27: checkcast     #17                 // class java/util/Collection
      30: areturn

  public void setAuthorities(java.util.Collection<? extends org.springframework.security.core.GrantedAuthority>);
    Code:
       0: aload_0
       1: aload_1
       2: putfield      #11                 // Field authorities:Ljava/util/Collection;
       5: return

  public java.lang.String getPassword();
    Code:
       0: aconst_null
       1: areturn

  public java.lang.String getUsername();
    Code:
       0: aload_0
       1: getfield      #3                  // Field userId:Ljava/lang/String;
       4: areturn

  public boolean isAccountNonExpired();
    Code:
       0: iconst_1
       1: ireturn

  public boolean isAccountNonLocked();
    Code:
       0: iconst_1
       1: ireturn

  public boolean isCredentialsNonExpired();
    Code:
       0: iconst_1
       1: ireturn

  public boolean isEnabled();
    Code:
       0: iconst_1
       1: ireturn

  public java.lang.String getUserId();
    Code:
       0: aload_0
       1: getfield      #3                  // Field userId:Ljava/lang/String;
       4: areturn

  public void setUserName(java.lang.String);
    Code:
       0: aload_0
       1: aload_1
       2: putfield      #3                  // Field userId:Ljava/lang/String;
       5: return

  public java.lang.String getToken();
    Code:
       0: aload_0
       1: getfield      #4                  // Field token:Ljava/lang/String;
       4: areturn

  public void setToken(java.lang.String);
    Code:
       0: aload_0
       1: aload_1
       2: putfield      #4                  // Field token:Ljava/lang/String;
       5: return

  public java.lang.String getMail();
    Code:
       0: aload_0
       1: getfield      #6                  // Field mail:Ljava/lang/String;
       4: areturn

  public void setMail(java.lang.String);
    Code:
       0: aload_0
       1: aload_1
       2: putfield      #6                  // Field mail:Ljava/lang/String;
       5: return

  public java.lang.String getMobile();
    Code:
       0: aload_0
       1: getfield      #8                  // Field mobile:Ljava/lang/String;
       4: areturn

  public void setMobile(java.lang.String);
    Code:
       0: aload_0
       1: aload_1
       2: putfield      #8                  // Field mobile:Ljava/lang/String;
       5: return

  public java.lang.String getrId();
    Code:
       0: aload_0
       1: getfield      #10                 // Field rId:Ljava/lang/String;
       4: areturn

  public void setrId(java.lang.String);
    Code:
       0: aload_0
       1: aload_1
       2: putfield      #10                 // Field rId:Ljava/lang/String;
       5: return

  private static org.springframework.security.core.authority.SimpleGrantedAuthority lambda$getAuthorities$0(org.springframework.security.core.GrantedAuthority);
    Code:
       0: new           #18                 // class org/springframework/security/core/authority/SimpleGrantedAuthority
       3: dup
       4: aload_0
       5: invokeinterface #19,  1           // InterfaceMethod org/springframework/security/core/GrantedAuthority.getAuthority:()Ljava/lang/String;
      10: invokedynamic #20,  0             // InvokeDynamic #1:makeConcatWithConstants:(Ljava/lang/String;)Ljava/lang/String;
      15: invokespecial #21                 // Method org/springframework/security/core/authority/SimpleGrantedAuthority."<init>":(Ljava/lang/String;)V
      18: areturn
}
