Compiled from "InterfaceMapper.java"
public final class org.apache.cxf.tools.wsdlto.frontend.jaxws.processor.internal.mapper.InterfaceMapper {
  private org.apache.cxf.tools.common.ToolContext context;

  public org.apache.cxf.tools.wsdlto.frontend.jaxws.processor.internal.mapper.InterfaceMapper(org.apache.cxf.tools.common.ToolContext);
    Code:
       0: aload_0
       1: invokespecial #1                  // Method java/lang/Object."<init>":()V
       4: aload_0
       5: aload_1
       6: putfield      #2                  // Field context:Lorg/apache/cxf/tools/common/ToolContext;
       9: return

  public org.apache.cxf.tools.common.model.JavaInterface map(org.apache.cxf.service.model.InterfaceInfo);
    Code:
       0: new           #3                  // class org/apache/cxf/tools/common/model/JavaInterface
       3: dup
       4: invokespecial #4                  // Method org/apache/cxf/tools/common/model/JavaInterface."<init>":()V
       7: astore_2
       8: aload_1
       9: invokevirtual #5                  // Method org/apache/cxf/service/model/InterfaceInfo.getName:()Ljavax/xml/namespace/QName;
      12: invokevirtual #6                  // Method javax/xml/namespace/QName.getNamespaceURI:()Ljava/lang/String;
      15: astore_3
      16: aload_3
      17: aload_0
      18: getfield      #2                  // Field context:Lorg/apache/cxf/tools/common/ToolContext;
      21: aload_3
      22: invokevirtual #7                  // Method org/apache/cxf/tools/common/ToolContext.mapPackageName:(Ljava/lang/String;)Ljava/lang/String;
      25: invokestatic  #8                  // Method org/apache/cxf/tools/wsdlto/frontend/jaxws/processor/internal/ProcessorUtil.parsePackageName:(Ljava/lang/String;Ljava/lang/String;)Ljava/lang/String;
      28: astore        4
      30: aload_0
      31: getfield      #2                  // Field context:Lorg/apache/cxf/tools/common/ToolContext;
      34: ldc           #9                  // String wsdlLocation
      36: invokevirtual #10                 // Method org/apache/cxf/tools/common/ToolContext.get:(Ljava/lang/String;)Ljava/lang/Object;
      39: checkcast     #11                 // class java/lang/String
      42: astore        5
      44: aload         5
      46: ifnonnull     63
      49: aload_0
      50: getfield      #2                  // Field context:Lorg/apache/cxf/tools/common/ToolContext;
      53: ldc           #12                 // String wsdlurl
      55: invokevirtual #10                 // Method org/apache/cxf/tools/common/ToolContext.get:(Ljava/lang/String;)Ljava/lang/Object;
      58: checkcast     #11                 // class java/lang/String
      61: astore        5
      63: aload_1
      64: invokevirtual #5                  // Method org/apache/cxf/service/model/InterfaceInfo.getName:()Ljavax/xml/namespace/QName;
      67: invokevirtual #13                 // Method javax/xml/namespace/QName.getLocalPart:()Ljava/lang/String;
      70: astore        6
      72: aload_2
      73: aload         6
      75: invokevirtual #14                 // Method org/apache/cxf/tools/common/model/JavaInterface.setWebServiceName:(Ljava/lang/String;)V
      78: aload_2
      79: aload         6
      81: invokestatic  #15                 // Method org/apache/cxf/tools/util/NameUtil.mangleNameToClassName:(Ljava/lang/String;)Ljava/lang/String;
      84: invokevirtual #16                 // Method org/apache/cxf/tools/common/model/JavaInterface.setName:(Ljava/lang/String;)V
      87: aload_2
      88: aload_3
      89: invokevirtual #17                 // Method org/apache/cxf/tools/common/model/JavaInterface.setNamespace:(Ljava/lang/String;)V
      92: aload_2
      93: aload         4
      95: invokevirtual #18                 // Method org/apache/cxf/tools/common/model/JavaInterface.setPackageName:(Ljava/lang/String;)V
      98: aload_2
      99: aload         5
     101: invokevirtual #19                 // Method org/apache/cxf/tools/common/model/JavaInterface.setLocation:(Ljava/lang/String;)V
     104: aload_2
     105: areturn
}
