Compiled from "TarEntry.java"
public class org.kamranzafar.jtar.TarEntry {
  protected java.io.File file;

  protected org.kamranzafar.jtar.TarHeader header;

  private org.kamranzafar.jtar.TarEntry();
    Code:
       0: aload_0
       1: invokespecial #1                  // Method java/lang/Object."<init>":()V
       4: aload_0
       5: aconst_null
       6: putfield      #2                  // Field file:Ljava/io/File;
       9: aload_0
      10: new           #3                  // class org/kamranzafar/jtar/TarHeader
      13: dup
      14: invokespecial #4                  // Method org/kamranzafar/jtar/TarHeader."<init>":()V
      17: putfield      #5                  // Field header:Lorg/kamranzafar/jtar/TarHeader;
      20: return

  public org.kamranzafar.jtar.TarEntry(java.io.File, java.lang.String);
    Code:
       0: aload_0
       1: invokespecial #6                  // Method "<init>":()V
       4: aload_0
       5: aload_1
       6: putfield      #2                  // Field file:Ljava/io/File;
       9: aload_0
      10: aload_2
      11: invokevirtual #7                  // Method extractTarHeader:(Ljava/lang/String;)V
      14: return

  public org.kamranzafar.jtar.TarEntry(byte[]);
    Code:
       0: aload_0
       1: invokespecial #6                  // Method "<init>":()V
       4: aload_0
       5: aload_1
       6: invokevirtual #8                  // Method parseTarHeader:([B)V
       9: return

  public org.kamranzafar.jtar.TarEntry(org.kamranzafar.jtar.TarHeader);
    Code:
       0: aload_0
       1: invokespecial #1                  // Method java/lang/Object."<init>":()V
       4: aload_0
       5: aconst_null
       6: putfield      #2                  // Field file:Ljava/io/File;
       9: aload_0
      10: aload_1
      11: putfield      #5                  // Field header:Lorg/kamranzafar/jtar/TarHeader;
      14: return

  public boolean equals(org.kamranzafar.jtar.TarEntry);
    Code:
       0: aload_0
       1: getfield      #5                  // Field header:Lorg/kamranzafar/jtar/TarHeader;
       4: getfield      #9                  // Field org/kamranzafar/jtar/TarHeader.name:Ljava/lang/StringBuffer;
       7: invokevirtual #10                 // Method java/lang/StringBuffer.toString:()Ljava/lang/String;
      10: aload_1
      11: getfield      #5                  // Field header:Lorg/kamranzafar/jtar/TarHeader;
      14: getfield      #9                  // Field org/kamranzafar/jtar/TarHeader.name:Ljava/lang/StringBuffer;
      17: invokevirtual #10                 // Method java/lang/StringBuffer.toString:()Ljava/lang/String;
      20: invokevirtual #11                 // Method java/lang/String.equals:(Ljava/lang/Object;)Z
      23: ireturn

  public boolean isDescendent(org.kamranzafar.jtar.TarEntry);
    Code:
       0: aload_1
       1: getfield      #5                  // Field header:Lorg/kamranzafar/jtar/TarHeader;
       4: getfield      #9                  // Field org/kamranzafar/jtar/TarHeader.name:Ljava/lang/StringBuffer;
       7: invokevirtual #10                 // Method java/lang/StringBuffer.toString:()Ljava/lang/String;
      10: aload_0
      11: getfield      #5                  // Field header:Lorg/kamranzafar/jtar/TarHeader;
      14: getfield      #9                  // Field org/kamranzafar/jtar/TarHeader.name:Ljava/lang/StringBuffer;
      17: invokevirtual #10                 // Method java/lang/StringBuffer.toString:()Ljava/lang/String;
      20: invokevirtual #12                 // Method java/lang/String.startsWith:(Ljava/lang/String;)Z
      23: ireturn

  public org.kamranzafar.jtar.TarHeader getHeader();
    Code:
       0: aload_0
       1: getfield      #5                  // Field header:Lorg/kamranzafar/jtar/TarHeader;
       4: areturn

  public java.lang.String getName();
    Code:
       0: aload_0
       1: getfield      #5                  // Field header:Lorg/kamranzafar/jtar/TarHeader;
       4: getfield      #9                  // Field org/kamranzafar/jtar/TarHeader.name:Ljava/lang/StringBuffer;
       7: invokevirtual #10                 // Method java/lang/StringBuffer.toString:()Ljava/lang/String;
      10: astore_1
      11: aload_0
      12: getfield      #5                  // Field header:Lorg/kamranzafar/jtar/TarHeader;
      15: getfield      #13                 // Field org/kamranzafar/jtar/TarHeader.namePrefix:Ljava/lang/StringBuffer;
      18: ifnull        72
      21: aload_0
      22: getfield      #5                  // Field header:Lorg/kamranzafar/jtar/TarHeader;
      25: getfield      #13                 // Field org/kamranzafar/jtar/TarHeader.namePrefix:Ljava/lang/StringBuffer;
      28: invokevirtual #10                 // Method java/lang/StringBuffer.toString:()Ljava/lang/String;
      31: ldc           #14                 // String
      33: invokevirtual #11                 // Method java/lang/String.equals:(Ljava/lang/Object;)Z
      36: ifne          72
      39: new           #15                 // class java/lang/StringBuilder
      42: dup
      43: invokespecial #16                 // Method java/lang/StringBuilder."<init>":()V
      46: aload_0
      47: getfield      #5                  // Field header:Lorg/kamranzafar/jtar/TarHeader;
      50: getfield      #13                 // Field org/kamranzafar/jtar/TarHeader.namePrefix:Ljava/lang/StringBuffer;
      53: invokevirtual #10                 // Method java/lang/StringBuffer.toString:()Ljava/lang/String;
      56: invokevirtual #17                 // Method java/lang/StringBuilder.append:(Ljava/lang/String;)Ljava/lang/StringBuilder;
      59: ldc           #18                 // String /
      61: invokevirtual #17                 // Method java/lang/StringBuilder.append:(Ljava/lang/String;)Ljava/lang/StringBuilder;
      64: aload_1
      65: invokevirtual #17                 // Method java/lang/StringBuilder.append:(Ljava/lang/String;)Ljava/lang/StringBuilder;
      68: invokevirtual #19                 // Method java/lang/StringBuilder.toString:()Ljava/lang/String;
      71: astore_1
      72: aload_1
      73: areturn

  public void setName(java.lang.String);
    Code:
       0: aload_0
       1: getfield      #5                  // Field header:Lorg/kamranzafar/jtar/TarHeader;
       4: new           #20                 // class java/lang/StringBuffer
       7: dup
       8: aload_1
       9: invokespecial #21                 // Method java/lang/StringBuffer."<init>":(Ljava/lang/String;)V
      12: putfield      #9                  // Field org/kamranzafar/jtar/TarHeader.name:Ljava/lang/StringBuffer;
      15: return

  public int getUserId();
    Code:
       0: aload_0
       1: getfield      #5                  // Field header:Lorg/kamranzafar/jtar/TarHeader;
       4: getfield      #22                 // Field org/kamranzafar/jtar/TarHeader.userId:I
       7: ireturn

  public void setUserId(int);
    Code:
       0: aload_0
       1: getfield      #5                  // Field header:Lorg/kamranzafar/jtar/TarHeader;
       4: iload_1
       5: putfield      #22                 // Field org/kamranzafar/jtar/TarHeader.userId:I
       8: return

  public int getGroupId();
    Code:
       0: aload_0
       1: getfield      #5                  // Field header:Lorg/kamranzafar/jtar/TarHeader;
       4: getfield      #23                 // Field org/kamranzafar/jtar/TarHeader.groupId:I
       7: ireturn

  public void setGroupId(int);
    Code:
       0: aload_0
       1: getfield      #5                  // Field header:Lorg/kamranzafar/jtar/TarHeader;
       4: iload_1
       5: putfield      #23                 // Field org/kamranzafar/jtar/TarHeader.groupId:I
       8: return

  public java.lang.String getUserName();
    Code:
       0: aload_0
       1: getfield      #5                  // Field header:Lorg/kamranzafar/jtar/TarHeader;
       4: getfield      #24                 // Field org/kamranzafar/jtar/TarHeader.userName:Ljava/lang/StringBuffer;
       7: invokevirtual #10                 // Method java/lang/StringBuffer.toString:()Ljava/lang/String;
      10: areturn

  public void setUserName(java.lang.String);
    Code:
       0: aload_0
       1: getfield      #5                  // Field header:Lorg/kamranzafar/jtar/TarHeader;
       4: new           #20                 // class java/lang/StringBuffer
       7: dup
       8: aload_1
       9: invokespecial #21                 // Method java/lang/StringBuffer."<init>":(Ljava/lang/String;)V
      12: putfield      #24                 // Field org/kamranzafar/jtar/TarHeader.userName:Ljava/lang/StringBuffer;
      15: return

  public java.lang.String getGroupName();
    Code:
       0: aload_0
       1: getfield      #5                  // Field header:Lorg/kamranzafar/jtar/TarHeader;
       4: getfield      #25                 // Field org/kamranzafar/jtar/TarHeader.groupName:Ljava/lang/StringBuffer;
       7: invokevirtual #10                 // Method java/lang/StringBuffer.toString:()Ljava/lang/String;
      10: areturn

  public void setGroupName(java.lang.String);
    Code:
       0: aload_0
       1: getfield      #5                  // Field header:Lorg/kamranzafar/jtar/TarHeader;
       4: new           #20                 // class java/lang/StringBuffer
       7: dup
       8: aload_1
       9: invokespecial #21                 // Method java/lang/StringBuffer."<init>":(Ljava/lang/String;)V
      12: putfield      #25                 // Field org/kamranzafar/jtar/TarHeader.groupName:Ljava/lang/StringBuffer;
      15: return

  public void setIds(int, int);
    Code:
       0: aload_0
       1: iload_1
       2: invokevirtual #26                 // Method setUserId:(I)V
       5: aload_0
       6: iload_2
       7: invokevirtual #27                 // Method setGroupId:(I)V
      10: return

  public void setModTime(long);
    Code:
       0: aload_0
       1: getfield      #5                  // Field header:Lorg/kamranzafar/jtar/TarHeader;
       4: lload_1
       5: ldc2_w        #28                 // long 1000l
       8: ldiv
       9: putfield      #30                 // Field org/kamranzafar/jtar/TarHeader.modTime:J
      12: return

  public void setModTime(java.util.Date);
    Code:
       0: aload_0
       1: getfield      #5                  // Field header:Lorg/kamranzafar/jtar/TarHeader;
       4: aload_1
       5: invokevirtual #31                 // Method java/util/Date.getTime:()J
       8: ldc2_w        #28                 // long 1000l
      11: ldiv
      12: putfield      #30                 // Field org/kamranzafar/jtar/TarHeader.modTime:J
      15: return

  public java.util.Date getModTime();
    Code:
       0: new           #32                 // class java/util/Date
       3: dup
       4: aload_0
       5: getfield      #5                  // Field header:Lorg/kamranzafar/jtar/TarHeader;
       8: getfield      #30                 // Field org/kamranzafar/jtar/TarHeader.modTime:J
      11: ldc2_w        #28                 // long 1000l
      14: lmul
      15: invokespecial #33                 // Method java/util/Date."<init>":(J)V
      18: areturn

  public java.io.File getFile();
    Code:
       0: aload_0
       1: getfield      #2                  // Field file:Ljava/io/File;
       4: areturn

  public long getSize();
    Code:
       0: aload_0
       1: getfield      #5                  // Field header:Lorg/kamranzafar/jtar/TarHeader;
       4: getfield      #34                 // Field org/kamranzafar/jtar/TarHeader.size:J
       7: lreturn

  public void setSize(long);
    Code:
       0: aload_0
       1: getfield      #5                  // Field header:Lorg/kamranzafar/jtar/TarHeader;
       4: lload_1
       5: putfield      #34                 // Field org/kamranzafar/jtar/TarHeader.size:J
       8: return

  public boolean isDirectory();
    Code:
       0: aload_0
       1: getfield      #2                  // Field file:Ljava/io/File;
       4: ifnull        15
       7: aload_0
       8: getfield      #2                  // Field file:Ljava/io/File;
      11: invokevirtual #35                 // Method java/io/File.isDirectory:()Z
      14: ireturn
      15: aload_0
      16: getfield      #5                  // Field header:Lorg/kamranzafar/jtar/TarHeader;
      19: ifnull        56
      22: aload_0
      23: getfield      #5                  // Field header:Lorg/kamranzafar/jtar/TarHeader;
      26: getfield      #36                 // Field org/kamranzafar/jtar/TarHeader.linkFlag:B
      29: bipush        53
      31: if_icmpne     36
      34: iconst_1
      35: ireturn
      36: aload_0
      37: getfield      #5                  // Field header:Lorg/kamranzafar/jtar/TarHeader;
      40: getfield      #9                  // Field org/kamranzafar/jtar/TarHeader.name:Ljava/lang/StringBuffer;
      43: invokevirtual #10                 // Method java/lang/StringBuffer.toString:()Ljava/lang/String;
      46: ldc           #18                 // String /
      48: invokevirtual #37                 // Method java/lang/String.endsWith:(Ljava/lang/String;)Z
      51: ifeq          56
      54: iconst_1
      55: ireturn
      56: iconst_0
      57: ireturn

  public void extractTarHeader(java.lang.String);
    Code:
       0: aload_0
       1: getfield      #2                  // Field file:Ljava/io/File;
       4: invokestatic  #38                 // Method org/kamranzafar/jtar/PermissionUtils.permissions:(Ljava/io/File;)I
       7: istore_2
       8: aload_0
       9: aload_1
      10: aload_0
      11: getfield      #2                  // Field file:Ljava/io/File;
      14: invokevirtual #39                 // Method java/io/File.length:()J
      17: aload_0
      18: getfield      #2                  // Field file:Ljava/io/File;
      21: invokevirtual #40                 // Method java/io/File.lastModified:()J
      24: ldc2_w        #28                 // long 1000l
      27: ldiv
      28: aload_0
      29: getfield      #2                  // Field file:Ljava/io/File;
      32: invokevirtual #35                 // Method java/io/File.isDirectory:()Z
      35: iload_2
      36: invokestatic  #41                 // Method org/kamranzafar/jtar/TarHeader.createHeader:(Ljava/lang/String;JJZI)Lorg/kamranzafar/jtar/TarHeader;
      39: putfield      #5                  // Field header:Lorg/kamranzafar/jtar/TarHeader;
      42: return

  public long computeCheckSum(byte[]);
    Code:
       0: lconst_0
       1: lstore_2
       2: iconst_0
       3: istore        4
       5: iload         4
       7: aload_1
       8: arraylength
       9: if_icmpge     30
      12: lload_2
      13: sipush        255
      16: aload_1
      17: iload         4
      19: baload
      20: iand
      21: i2l
      22: ladd
      23: lstore_2
      24: iinc          4, 1
      27: goto          5
      30: lload_2
      31: lreturn

  public void writeEntryHeader(byte[]);
    Code:
       0: iconst_0
       1: istore_2
       2: aload_0
       3: getfield      #5                  // Field header:Lorg/kamranzafar/jtar/TarHeader;
       6: getfield      #9                  // Field org/kamranzafar/jtar/TarHeader.name:Ljava/lang/StringBuffer;
       9: aload_1
      10: iload_2
      11: bipush        100
      13: invokestatic  #42                 // Method org/kamranzafar/jtar/TarHeader.getNameBytes:(Ljava/lang/StringBuffer;[BII)I
      16: istore_2
      17: aload_0
      18: getfield      #5                  // Field header:Lorg/kamranzafar/jtar/TarHeader;
      21: getfield      #43                 // Field org/kamranzafar/jtar/TarHeader.mode:I
      24: i2l
      25: aload_1
      26: iload_2
      27: bipush        8
      29: invokestatic  #44                 // Method org/kamranzafar/jtar/Octal.getOctalBytes:(J[BII)I
      32: istore_2
      33: aload_0
      34: getfield      #5                  // Field header:Lorg/kamranzafar/jtar/TarHeader;
      37: getfield      #22                 // Field org/kamranzafar/jtar/TarHeader.userId:I
      40: i2l
      41: aload_1
      42: iload_2
      43: bipush        8
      45: invokestatic  #44                 // Method org/kamranzafar/jtar/Octal.getOctalBytes:(J[BII)I
      48: istore_2
      49: aload_0
      50: getfield      #5                  // Field header:Lorg/kamranzafar/jtar/TarHeader;
      53: getfield      #23                 // Field org/kamranzafar/jtar/TarHeader.groupId:I
      56: i2l
      57: aload_1
      58: iload_2
      59: bipush        8
      61: invokestatic  #44                 // Method org/kamranzafar/jtar/Octal.getOctalBytes:(J[BII)I
      64: istore_2
      65: aload_0
      66: getfield      #5                  // Field header:Lorg/kamranzafar/jtar/TarHeader;
      69: getfield      #34                 // Field org/kamranzafar/jtar/TarHeader.size:J
      72: lstore_3
      73: lload_3
      74: aload_1
      75: iload_2
      76: bipush        12
      78: invokestatic  #45                 // Method org/kamranzafar/jtar/Octal.getLongOctalBytes:(J[BII)I
      81: istore_2
      82: aload_0
      83: getfield      #5                  // Field header:Lorg/kamranzafar/jtar/TarHeader;
      86: getfield      #30                 // Field org/kamranzafar/jtar/TarHeader.modTime:J
      89: aload_1
      90: iload_2
      91: bipush        12
      93: invokestatic  #45                 // Method org/kamranzafar/jtar/Octal.getLongOctalBytes:(J[BII)I
      96: istore_2
      97: iload_2
      98: istore        5
     100: iconst_0
     101: istore        6
     103: iload         6
     105: bipush        8
     107: if_icmpge     124
     110: aload_1
     111: iload_2
     112: iinc          2, 1
     115: bipush        32
     117: bastore
     118: iinc          6, 1
     121: goto          103
     124: aload_1
     125: iload_2
     126: iinc          2, 1
     129: aload_0
     130: getfield      #5                  // Field header:Lorg/kamranzafar/jtar/TarHeader;
     133: getfield      #36                 // Field org/kamranzafar/jtar/TarHeader.linkFlag:B
     136: bastore
     137: aload_0
     138: getfield      #5                  // Field header:Lorg/kamranzafar/jtar/TarHeader;
     141: getfield      #46                 // Field org/kamranzafar/jtar/TarHeader.linkName:Ljava/lang/StringBuffer;
     144: aload_1
     145: iload_2
     146: bipush        100
     148: invokestatic  #42                 // Method org/kamranzafar/jtar/TarHeader.getNameBytes:(Ljava/lang/StringBuffer;[BII)I
     151: istore_2
     152: aload_0
     153: getfield      #5                  // Field header:Lorg/kamranzafar/jtar/TarHeader;
     156: getfield      #47                 // Field org/kamranzafar/jtar/TarHeader.magic:Ljava/lang/StringBuffer;
     159: aload_1
     160: iload_2
     161: bipush        8
     163: invokestatic  #42                 // Method org/kamranzafar/jtar/TarHeader.getNameBytes:(Ljava/lang/StringBuffer;[BII)I
     166: istore_2
     167: aload_0
     168: getfield      #5                  // Field header:Lorg/kamranzafar/jtar/TarHeader;
     171: getfield      #24                 // Field org/kamranzafar/jtar/TarHeader.userName:Ljava/lang/StringBuffer;
     174: aload_1
     175: iload_2
     176: bipush        32
     178: invokestatic  #42                 // Method org/kamranzafar/jtar/TarHeader.getNameBytes:(Ljava/lang/StringBuffer;[BII)I
     181: istore_2
     182: aload_0
     183: getfield      #5                  // Field header:Lorg/kamranzafar/jtar/TarHeader;
     186: getfield      #25                 // Field org/kamranzafar/jtar/TarHeader.groupName:Ljava/lang/StringBuffer;
     189: aload_1
     190: iload_2
     191: bipush        32
     193: invokestatic  #42                 // Method org/kamranzafar/jtar/TarHeader.getNameBytes:(Ljava/lang/StringBuffer;[BII)I
     196: istore_2
     197: aload_0
     198: getfield      #5                  // Field header:Lorg/kamranzafar/jtar/TarHeader;
     201: getfield      #48                 // Field org/kamranzafar/jtar/TarHeader.devMajor:I
     204: i2l
     205: aload_1
     206: iload_2
     207: bipush        8
     209: invokestatic  #44                 // Method org/kamranzafar/jtar/Octal.getOctalBytes:(J[BII)I
     212: istore_2
     213: aload_0
     214: getfield      #5                  // Field header:Lorg/kamranzafar/jtar/TarHeader;
     217: getfield      #49                 // Field org/kamranzafar/jtar/TarHeader.devMinor:I
     220: i2l
     221: aload_1
     222: iload_2
     223: bipush        8
     225: invokestatic  #44                 // Method org/kamranzafar/jtar/Octal.getOctalBytes:(J[BII)I
     228: istore_2
     229: aload_0
     230: getfield      #5                  // Field header:Lorg/kamranzafar/jtar/TarHeader;
     233: getfield      #13                 // Field org/kamranzafar/jtar/TarHeader.namePrefix:Ljava/lang/StringBuffer;
     236: aload_1
     237: iload_2
     238: sipush        155
     241: invokestatic  #42                 // Method org/kamranzafar/jtar/TarHeader.getNameBytes:(Ljava/lang/StringBuffer;[BII)I
     244: istore_2
     245: iload_2
     246: aload_1
     247: arraylength
     248: if_icmpge     261
     251: aload_1
     252: iload_2
     253: iinc          2, 1
     256: iconst_0
     257: bastore
     258: goto          245
     261: aload_0
     262: aload_1
     263: invokevirtual #50                 // Method computeCheckSum:([B)J
     266: lstore        6
     268: lload         6
     270: aload_1
     271: iload         5
     273: bipush        8
     275: invokestatic  #51                 // Method org/kamranzafar/jtar/Octal.getCheckSumOctalBytes:(J[BII)I
     278: pop
     279: return

  public void parseTarHeader(byte[]);
    Code:
       0: iconst_0
       1: istore_2
       2: aload_0
       3: getfield      #5                  // Field header:Lorg/kamranzafar/jtar/TarHeader;
       6: aload_1
       7: iload_2
       8: bipush        100
      10: invokestatic  #52                 // Method org/kamranzafar/jtar/TarHeader.parseName:([BII)Ljava/lang/StringBuffer;
      13: putfield      #9                  // Field org/kamranzafar/jtar/TarHeader.name:Ljava/lang/StringBuffer;
      16: iinc          2, 100
      19: aload_0
      20: getfield      #5                  // Field header:Lorg/kamranzafar/jtar/TarHeader;
      23: aload_1
      24: iload_2
      25: bipush        8
      27: invokestatic  #53                 // Method org/kamranzafar/jtar/Octal.parseOctal:([BII)J
      30: l2i
      31: putfield      #43                 // Field org/kamranzafar/jtar/TarHeader.mode:I
      34: iinc          2, 8
      37: aload_0
      38: getfield      #5                  // Field header:Lorg/kamranzafar/jtar/TarHeader;
      41: aload_1
      42: iload_2
      43: bipush        8
      45: invokestatic  #53                 // Method org/kamranzafar/jtar/Octal.parseOctal:([BII)J
      48: l2i
      49: putfield      #22                 // Field org/kamranzafar/jtar/TarHeader.userId:I
      52: iinc          2, 8
      55: aload_0
      56: getfield      #5                  // Field header:Lorg/kamranzafar/jtar/TarHeader;
      59: aload_1
      60: iload_2
      61: bipush        8
      63: invokestatic  #53                 // Method org/kamranzafar/jtar/Octal.parseOctal:([BII)J
      66: l2i
      67: putfield      #23                 // Field org/kamranzafar/jtar/TarHeader.groupId:I
      70: iinc          2, 8
      73: aload_0
      74: getfield      #5                  // Field header:Lorg/kamranzafar/jtar/TarHeader;
      77: aload_1
      78: iload_2
      79: bipush        12
      81: invokestatic  #53                 // Method org/kamranzafar/jtar/Octal.parseOctal:([BII)J
      84: putfield      #34                 // Field org/kamranzafar/jtar/TarHeader.size:J
      87: iinc          2, 12
      90: aload_0
      91: getfield      #5                  // Field header:Lorg/kamranzafar/jtar/TarHeader;
      94: aload_1
      95: iload_2
      96: bipush        12
      98: invokestatic  #53                 // Method org/kamranzafar/jtar/Octal.parseOctal:([BII)J
     101: putfield      #30                 // Field org/kamranzafar/jtar/TarHeader.modTime:J
     104: iinc          2, 12
     107: aload_0
     108: getfield      #5                  // Field header:Lorg/kamranzafar/jtar/TarHeader;
     111: aload_1
     112: iload_2
     113: bipush        8
     115: invokestatic  #53                 // Method org/kamranzafar/jtar/Octal.parseOctal:([BII)J
     118: l2i
     119: putfield      #54                 // Field org/kamranzafar/jtar/TarHeader.checkSum:I
     122: iinc          2, 8
     125: aload_0
     126: getfield      #5                  // Field header:Lorg/kamranzafar/jtar/TarHeader;
     129: aload_1
     130: iload_2
     131: iinc          2, 1
     134: baload
     135: putfield      #36                 // Field org/kamranzafar/jtar/TarHeader.linkFlag:B
     138: aload_0
     139: getfield      #5                  // Field header:Lorg/kamranzafar/jtar/TarHeader;
     142: aload_1
     143: iload_2
     144: bipush        100
     146: invokestatic  #52                 // Method org/kamranzafar/jtar/TarHeader.parseName:([BII)Ljava/lang/StringBuffer;
     149: putfield      #46                 // Field org/kamranzafar/jtar/TarHeader.linkName:Ljava/lang/StringBuffer;
     152: iinc          2, 100
     155: aload_0
     156: getfield      #5                  // Field header:Lorg/kamranzafar/jtar/TarHeader;
     159: aload_1
     160: iload_2
     161: bipush        8
     163: invokestatic  #52                 // Method org/kamranzafar/jtar/TarHeader.parseName:([BII)Ljava/lang/StringBuffer;
     166: putfield      #47                 // Field org/kamranzafar/jtar/TarHeader.magic:Ljava/lang/StringBuffer;
     169: iinc          2, 8
     172: aload_0
     173: getfield      #5                  // Field header:Lorg/kamranzafar/jtar/TarHeader;
     176: aload_1
     177: iload_2
     178: bipush        32
     180: invokestatic  #52                 // Method org/kamranzafar/jtar/TarHeader.parseName:([BII)Ljava/lang/StringBuffer;
     183: putfield      #24                 // Field org/kamranzafar/jtar/TarHeader.userName:Ljava/lang/StringBuffer;
     186: iinc          2, 32
     189: aload_0
     190: getfield      #5                  // Field header:Lorg/kamranzafar/jtar/TarHeader;
     193: aload_1
     194: iload_2
     195: bipush        32
     197: invokestatic  #52                 // Method org/kamranzafar/jtar/TarHeader.parseName:([BII)Ljava/lang/StringBuffer;
     200: putfield      #25                 // Field org/kamranzafar/jtar/TarHeader.groupName:Ljava/lang/StringBuffer;
     203: iinc          2, 32
     206: aload_0
     207: getfield      #5                  // Field header:Lorg/kamranzafar/jtar/TarHeader;
     210: aload_1
     211: iload_2
     212: bipush        8
     214: invokestatic  #53                 // Method org/kamranzafar/jtar/Octal.parseOctal:([BII)J
     217: l2i
     218: putfield      #48                 // Field org/kamranzafar/jtar/TarHeader.devMajor:I
     221: iinc          2, 8
     224: aload_0
     225: getfield      #5                  // Field header:Lorg/kamranzafar/jtar/TarHeader;
     228: aload_1
     229: iload_2
     230: bipush        8
     232: invokestatic  #53                 // Method org/kamranzafar/jtar/Octal.parseOctal:([BII)J
     235: l2i
     236: putfield      #49                 // Field org/kamranzafar/jtar/TarHeader.devMinor:I
     239: iinc          2, 8
     242: aload_0
     243: getfield      #5                  // Field header:Lorg/kamranzafar/jtar/TarHeader;
     246: aload_1
     247: iload_2
     248: sipush        155
     251: invokestatic  #52                 // Method org/kamranzafar/jtar/TarHeader.parseName:([BII)Ljava/lang/StringBuffer;
     254: putfield      #13                 // Field org/kamranzafar/jtar/TarHeader.namePrefix:Ljava/lang/StringBuffer;
     257: return
}
