Compiled from "AsyncHttpRequestRetryExec.java"
class org.apache.hc.client5.http.impl.async.AsyncHttpRequestRetryExec$1 implements org.apache.hc.client5.http.async.AsyncExecCallback {
  final org.apache.hc.client5.http.async.AsyncExecChain$Scope val$scope;

  final org.apache.hc.core5.http.nio.AsyncEntityProducer val$entityProducer;

  final java.lang.String val$exchangeId;

  final org.apache.hc.client5.http.async.AsyncExecCallback val$asyncExecCallback;

  final org.apache.hc.client5.http.impl.async.AsyncHttpRequestRetryExec$State val$state;

  final org.apache.hc.core5.http.HttpRequest val$request;

  final org.apache.hc.client5.http.impl.async.AsyncHttpRequestRetryExec this$0;

  org.apache.hc.client5.http.impl.async.AsyncHttpRequestRetryExec$1(org.apache.hc.client5.http.impl.async.AsyncHttpRequestRetryExec, org.apache.hc.client5.http.async.AsyncExecChain$Scope, org.apache.hc.core5.http.nio.AsyncEntityProducer, java.lang.String, org.apache.hc.client5.http.async.AsyncExecCallback, org.apache.hc.client5.http.impl.async.AsyncHttpRequestRetryExec$State, org.apache.hc.core5.http.HttpRequest);
    Code:
       0: aload_0
       1: aload_1
       2: putfield      #1                  // Field this$0:Lorg/apache/hc/client5/http/impl/async/AsyncHttpRequestRetryExec;
       5: aload_0
       6: aload_2
       7: putfield      #2                  // Field val$scope:Lorg/apache/hc/client5/http/async/AsyncExecChain$Scope;
      10: aload_0
      11: aload_3
      12: putfield      #3                  // Field val$entityProducer:Lorg/apache/hc/core5/http/nio/AsyncEntityProducer;
      15: aload_0
      16: aload         4
      18: putfield      #4                  // Field val$exchangeId:Ljava/lang/String;
      21: aload_0
      22: aload         5
      24: putfield      #5                  // Field val$asyncExecCallback:Lorg/apache/hc/client5/http/async/AsyncExecCallback;
      27: aload_0
      28: aload         6
      30: putfield      #6                  // Field val$state:Lorg/apache/hc/client5/http/impl/async/AsyncHttpRequestRetryExec$State;
      33: aload_0
      34: aload         7
      36: putfield      #7                  // Field val$request:Lorg/apache/hc/core5/http/HttpRequest;
      39: aload_0
      40: invokespecial #8                  // Method java/lang/Object."<init>":()V
      43: return

  public org.apache.hc.core5.http.nio.AsyncDataConsumer handleResponse(org.apache.hc.core5.http.HttpResponse, org.apache.hc.core5.http.EntityDetails) throws org.apache.hc.core5.http.HttpException, java.io.IOException;
    Code:
       0: aload_0
       1: getfield      #2                  // Field val$scope:Lorg/apache/hc/client5/http/async/AsyncExecChain$Scope;
       4: getfield      #9                  // Field org/apache/hc/client5/http/async/AsyncExecChain$Scope.clientContext:Lorg/apache/hc/client5/http/protocol/HttpClientContext;
       7: astore_3
       8: aload_0
       9: getfield      #3                  // Field val$entityProducer:Lorg/apache/hc/core5/http/nio/AsyncEntityProducer;
      12: ifnull        64
      15: aload_0
      16: getfield      #3                  // Field val$entityProducer:Lorg/apache/hc/core5/http/nio/AsyncEntityProducer;
      19: invokeinterface #10,  1           // InterfaceMethod org/apache/hc/core5/http/nio/AsyncEntityProducer.isRepeatable:()Z
      24: ifne          64
      27: invokestatic  #11                 // Method org/apache/hc/client5/http/impl/async/AsyncHttpRequestRetryExec.access$000:()Lorg/slf4j/Logger;
      30: invokeinterface #12,  1           // InterfaceMethod org/slf4j/Logger.isDebugEnabled:()Z
      35: ifeq          52
      38: invokestatic  #11                 // Method org/apache/hc/client5/http/impl/async/AsyncHttpRequestRetryExec.access$000:()Lorg/slf4j/Logger;
      41: ldc           #13                 // String {} cannot retry non-repeatable request
      43: aload_0
      44: getfield      #4                  // Field val$exchangeId:Ljava/lang/String;
      47: invokeinterface #14,  3           // InterfaceMethod org/slf4j/Logger.debug:(Ljava/lang/String;Ljava/lang/Object;)V
      52: aload_0
      53: getfield      #5                  // Field val$asyncExecCallback:Lorg/apache/hc/client5/http/async/AsyncExecCallback;
      56: aload_1
      57: aload_2
      58: invokeinterface #15,  3           // InterfaceMethod org/apache/hc/client5/http/async/AsyncExecCallback.handleResponse:(Lorg/apache/hc/core5/http/HttpResponse;Lorg/apache/hc/core5/http/EntityDetails;)Lorg/apache/hc/core5/http/nio/AsyncDataConsumer;
      63: areturn
      64: aload_0
      65: getfield      #6                  // Field val$state:Lorg/apache/hc/client5/http/impl/async/AsyncHttpRequestRetryExec$State;
      68: aload_0
      69: getfield      #1                  // Field this$0:Lorg/apache/hc/client5/http/impl/async/AsyncHttpRequestRetryExec;
      72: invokestatic  #16                 // Method org/apache/hc/client5/http/impl/async/AsyncHttpRequestRetryExec.access$100:(Lorg/apache/hc/client5/http/impl/async/AsyncHttpRequestRetryExec;)Lorg/apache/hc/client5/http/HttpRequestRetryStrategy;
      75: aload_1
      76: aload_0
      77: getfield      #2                  // Field val$scope:Lorg/apache/hc/client5/http/async/AsyncExecChain$Scope;
      80: getfield      #17                 // Field org/apache/hc/client5/http/async/AsyncExecChain$Scope.execCount:Ljava/util/concurrent/atomic/AtomicInteger;
      83: invokevirtual #18                 // Method java/util/concurrent/atomic/AtomicInteger.get:()I
      86: aload_3
      87: invokeinterface #19,  4           // InterfaceMethod org/apache/hc/client5/http/HttpRequestRetryStrategy.retryRequest:(Lorg/apache/hc/core5/http/HttpResponse;ILorg/apache/hc/core5/http/protocol/HttpContext;)Z
      92: putfield      #20                 // Field org/apache/hc/client5/http/impl/async/AsyncHttpRequestRetryExec$State.retrying:Z
      95: aload_0
      96: getfield      #6                  // Field val$state:Lorg/apache/hc/client5/http/impl/async/AsyncHttpRequestRetryExec$State;
      99: getfield      #20                 // Field org/apache/hc/client5/http/impl/async/AsyncHttpRequestRetryExec$State.retrying:Z
     102: ifeq          176
     105: aload_0
     106: getfield      #6                  // Field val$state:Lorg/apache/hc/client5/http/impl/async/AsyncHttpRequestRetryExec$State;
     109: aload_0
     110: getfield      #1                  // Field this$0:Lorg/apache/hc/client5/http/impl/async/AsyncHttpRequestRetryExec;
     113: invokestatic  #16                 // Method org/apache/hc/client5/http/impl/async/AsyncHttpRequestRetryExec.access$100:(Lorg/apache/hc/client5/http/impl/async/AsyncHttpRequestRetryExec;)Lorg/apache/hc/client5/http/HttpRequestRetryStrategy;
     116: aload_1
     117: aload_0
     118: getfield      #2                  // Field val$scope:Lorg/apache/hc/client5/http/async/AsyncExecChain$Scope;
     121: getfield      #17                 // Field org/apache/hc/client5/http/async/AsyncExecChain$Scope.execCount:Ljava/util/concurrent/atomic/AtomicInteger;
     124: invokevirtual #18                 // Method java/util/concurrent/atomic/AtomicInteger.get:()I
     127: aload_3
     128: invokeinterface #21,  4           // InterfaceMethod org/apache/hc/client5/http/HttpRequestRetryStrategy.getRetryInterval:(Lorg/apache/hc/core5/http/HttpResponse;ILorg/apache/hc/core5/http/protocol/HttpContext;)Lorg/apache/hc/core5/util/TimeValue;
     133: putfield      #22                 // Field org/apache/hc/client5/http/impl/async/AsyncHttpRequestRetryExec$State.delay:Lorg/apache/hc/core5/util/TimeValue;
     136: invokestatic  #11                 // Method org/apache/hc/client5/http/impl/async/AsyncHttpRequestRetryExec.access$000:()Lorg/slf4j/Logger;
     139: invokeinterface #12,  1           // InterfaceMethod org/slf4j/Logger.isDebugEnabled:()Z
     144: ifeq          168
     147: invokestatic  #11                 // Method org/apache/hc/client5/http/impl/async/AsyncHttpRequestRetryExec.access$000:()Lorg/slf4j/Logger;
     150: ldc           #23                 // String {} retrying request in {}
     152: aload_0
     153: getfield      #4                  // Field val$exchangeId:Ljava/lang/String;
     156: aload_0
     157: getfield      #6                  // Field val$state:Lorg/apache/hc/client5/http/impl/async/AsyncHttpRequestRetryExec$State;
     160: getfield      #22                 // Field org/apache/hc/client5/http/impl/async/AsyncHttpRequestRetryExec$State.delay:Lorg/apache/hc/core5/util/TimeValue;
     163: invokeinterface #24,  4           // InterfaceMethod org/slf4j/Logger.debug:(Ljava/lang/String;Ljava/lang/Object;Ljava/lang/Object;)V
     168: new           #25                 // class org/apache/hc/core5/http/nio/entity/NoopEntityConsumer
     171: dup
     172: invokespecial #26                 // Method org/apache/hc/core5/http/nio/entity/NoopEntityConsumer."<init>":()V
     175: areturn
     176: aload_0
     177: getfield      #5                  // Field val$asyncExecCallback:Lorg/apache/hc/client5/http/async/AsyncExecCallback;
     180: aload_1
     181: aload_2
     182: invokeinterface #15,  3           // InterfaceMethod org/apache/hc/client5/http/async/AsyncExecCallback.handleResponse:(Lorg/apache/hc/core5/http/HttpResponse;Lorg/apache/hc/core5/http/EntityDetails;)Lorg/apache/hc/core5/http/nio/AsyncDataConsumer;
     187: areturn

  public void handleInformationResponse(org.apache.hc.core5.http.HttpResponse) throws org.apache.hc.core5.http.HttpException, java.io.IOException;
    Code:
       0: aload_0
       1: getfield      #5                  // Field val$asyncExecCallback:Lorg/apache/hc/client5/http/async/AsyncExecCallback;
       4: aload_1
       5: invokeinterface #27,  2           // InterfaceMethod org/apache/hc/client5/http/async/AsyncExecCallback.handleInformationResponse:(Lorg/apache/hc/core5/http/HttpResponse;)V
      10: return

  public void completed();
    Code:
       0: aload_0
       1: getfield      #6                  // Field val$state:Lorg/apache/hc/client5/http/impl/async/AsyncHttpRequestRetryExec$State;
       4: getfield      #20                 // Field org/apache/hc/client5/http/impl/async/AsyncHttpRequestRetryExec$State.retrying:Z
       7: ifeq          59
      10: aload_0
      11: getfield      #2                  // Field val$scope:Lorg/apache/hc/client5/http/async/AsyncExecChain$Scope;
      14: getfield      #17                 // Field org/apache/hc/client5/http/async/AsyncExecChain$Scope.execCount:Ljava/util/concurrent/atomic/AtomicInteger;
      17: invokevirtual #28                 // Method java/util/concurrent/atomic/AtomicInteger.incrementAndGet:()I
      20: pop
      21: aload_0
      22: getfield      #2                  // Field val$scope:Lorg/apache/hc/client5/http/async/AsyncExecChain$Scope;
      25: getfield      #29                 // Field org/apache/hc/client5/http/async/AsyncExecChain$Scope.scheduler:Lorg/apache/hc/client5/http/async/AsyncExecChain$Scheduler;
      28: aload_0
      29: getfield      #7                  // Field val$request:Lorg/apache/hc/core5/http/HttpRequest;
      32: aload_0
      33: getfield      #3                  // Field val$entityProducer:Lorg/apache/hc/core5/http/nio/AsyncEntityProducer;
      36: aload_0
      37: getfield      #2                  // Field val$scope:Lorg/apache/hc/client5/http/async/AsyncExecChain$Scope;
      40: aload_0
      41: getfield      #5                  // Field val$asyncExecCallback:Lorg/apache/hc/client5/http/async/AsyncExecCallback;
      44: aload_0
      45: getfield      #6                  // Field val$state:Lorg/apache/hc/client5/http/impl/async/AsyncHttpRequestRetryExec$State;
      48: getfield      #22                 // Field org/apache/hc/client5/http/impl/async/AsyncHttpRequestRetryExec$State.delay:Lorg/apache/hc/core5/util/TimeValue;
      51: invokeinterface #30,  6           // InterfaceMethod org/apache/hc/client5/http/async/AsyncExecChain$Scheduler.scheduleExecution:(Lorg/apache/hc/core5/http/HttpRequest;Lorg/apache/hc/core5/http/nio/AsyncEntityProducer;Lorg/apache/hc/client5/http/async/AsyncExecChain$Scope;Lorg/apache/hc/client5/http/async/AsyncExecCallback;Lorg/apache/hc/core5/util/TimeValue;)V
      56: goto          68
      59: aload_0
      60: getfield      #5                  // Field val$asyncExecCallback:Lorg/apache/hc/client5/http/async/AsyncExecCallback;
      63: invokeinterface #31,  1           // InterfaceMethod org/apache/hc/client5/http/async/AsyncExecCallback.completed:()V
      68: return

  public void failed(java.lang.Exception);
    Code:
       0: aload_1
       1: instanceof    #32                 // class java/io/IOException
       4: ifeq          259
       7: aload_0
       8: getfield      #2                  // Field val$scope:Lorg/apache/hc/client5/http/async/AsyncExecChain$Scope;
      11: getfield      #33                 // Field org/apache/hc/client5/http/async/AsyncExecChain$Scope.route:Lorg/apache/hc/client5/http/HttpRoute;
      14: astore_2
      15: aload_0
      16: getfield      #2                  // Field val$scope:Lorg/apache/hc/client5/http/async/AsyncExecChain$Scope;
      19: getfield      #9                  // Field org/apache/hc/client5/http/async/AsyncExecChain$Scope.clientContext:Lorg/apache/hc/client5/http/protocol/HttpClientContext;
      22: astore_3
      23: aload_0
      24: getfield      #3                  // Field val$entityProducer:Lorg/apache/hc/core5/http/nio/AsyncEntityProducer;
      27: ifnull        70
      30: aload_0
      31: getfield      #3                  // Field val$entityProducer:Lorg/apache/hc/core5/http/nio/AsyncEntityProducer;
      34: invokeinterface #10,  1           // InterfaceMethod org/apache/hc/core5/http/nio/AsyncEntityProducer.isRepeatable:()Z
      39: ifne          70
      42: invokestatic  #11                 // Method org/apache/hc/client5/http/impl/async/AsyncHttpRequestRetryExec.access$000:()Lorg/slf4j/Logger;
      45: invokeinterface #12,  1           // InterfaceMethod org/slf4j/Logger.isDebugEnabled:()Z
      50: ifeq          259
      53: invokestatic  #11                 // Method org/apache/hc/client5/http/impl/async/AsyncHttpRequestRetryExec.access$000:()Lorg/slf4j/Logger;
      56: ldc           #13                 // String {} cannot retry non-repeatable request
      58: aload_0
      59: getfield      #4                  // Field val$exchangeId:Ljava/lang/String;
      62: invokeinterface #14,  3           // InterfaceMethod org/slf4j/Logger.debug:(Ljava/lang/String;Ljava/lang/Object;)V
      67: goto          259
      70: aload_0
      71: getfield      #1                  // Field this$0:Lorg/apache/hc/client5/http/impl/async/AsyncHttpRequestRetryExec;
      74: invokestatic  #16                 // Method org/apache/hc/client5/http/impl/async/AsyncHttpRequestRetryExec.access$100:(Lorg/apache/hc/client5/http/impl/async/AsyncHttpRequestRetryExec;)Lorg/apache/hc/client5/http/HttpRequestRetryStrategy;
      77: aload_0
      78: getfield      #7                  // Field val$request:Lorg/apache/hc/core5/http/HttpRequest;
      81: aload_1
      82: checkcast     #32                 // class java/io/IOException
      85: aload_0
      86: getfield      #2                  // Field val$scope:Lorg/apache/hc/client5/http/async/AsyncExecChain$Scope;
      89: getfield      #17                 // Field org/apache/hc/client5/http/async/AsyncExecChain$Scope.execCount:Ljava/util/concurrent/atomic/AtomicInteger;
      92: invokevirtual #18                 // Method java/util/concurrent/atomic/AtomicInteger.get:()I
      95: aload_3
      96: invokeinterface #34,  5           // InterfaceMethod org/apache/hc/client5/http/HttpRequestRetryStrategy.retryRequest:(Lorg/apache/hc/core5/http/HttpRequest;Ljava/io/IOException;ILorg/apache/hc/core5/http/protocol/HttpContext;)Z
     101: ifeq          259
     104: invokestatic  #11                 // Method org/apache/hc/client5/http/impl/async/AsyncHttpRequestRetryExec.access$000:()Lorg/slf4j/Logger;
     107: invokeinterface #12,  1           // InterfaceMethod org/slf4j/Logger.isDebugEnabled:()Z
     112: ifeq          147
     115: invokestatic  #11                 // Method org/apache/hc/client5/http/impl/async/AsyncHttpRequestRetryExec.access$000:()Lorg/slf4j/Logger;
     118: ldc           #35                 // String {} {}
     120: iconst_3
     121: anewarray     #36                 // class java/lang/Object
     124: dup
     125: iconst_0
     126: aload_0
     127: getfield      #4                  // Field val$exchangeId:Ljava/lang/String;
     130: aastore
     131: dup
     132: iconst_1
     133: aload_1
     134: invokevirtual #37                 // Method java/lang/Exception.getMessage:()Ljava/lang/String;
     137: aastore
     138: dup
     139: iconst_2
     140: aload_1
     141: aastore
     142: invokeinterface #38,  3           // InterfaceMethod org/slf4j/Logger.debug:(Ljava/lang/String;[Ljava/lang/Object;)V
     147: invokestatic  #11                 // Method org/apache/hc/client5/http/impl/async/AsyncHttpRequestRetryExec.access$000:()Lorg/slf4j/Logger;
     150: invokeinterface #39,  1           // InterfaceMethod org/slf4j/Logger.isInfoEnabled:()Z
     155: ifeq          176
     158: invokestatic  #11                 // Method org/apache/hc/client5/http/impl/async/AsyncHttpRequestRetryExec.access$000:()Lorg/slf4j/Logger;
     161: ldc           #40                 // String Recoverable I/O exception ({}) caught when processing request to {}
     163: aload_1
     164: invokevirtual #41                 // Method java/lang/Object.getClass:()Ljava/lang/Class;
     167: invokevirtual #42                 // Method java/lang/Class.getName:()Ljava/lang/String;
     170: aload_2
     171: invokeinterface #43,  4           // InterfaceMethod org/slf4j/Logger.info:(Ljava/lang/String;Ljava/lang/Object;Ljava/lang/Object;)V
     176: aload_0
     177: getfield      #2                  // Field val$scope:Lorg/apache/hc/client5/http/async/AsyncExecChain$Scope;
     180: getfield      #44                 // Field org/apache/hc/client5/http/async/AsyncExecChain$Scope.execRuntime:Lorg/apache/hc/client5/http/async/AsyncExecRuntime;
     183: invokeinterface #45,  1           // InterfaceMethod org/apache/hc/client5/http/async/AsyncExecRuntime.discardEndpoint:()V
     188: aload_0
     189: getfield      #3                  // Field val$entityProducer:Lorg/apache/hc/core5/http/nio/AsyncEntityProducer;
     192: ifnull        204
     195: aload_0
     196: getfield      #3                  // Field val$entityProducer:Lorg/apache/hc/core5/http/nio/AsyncEntityProducer;
     199: invokeinterface #46,  1           // InterfaceMethod org/apache/hc/core5/http/nio/AsyncEntityProducer.releaseResources:()V
     204: aload_0
     205: getfield      #6                  // Field val$state:Lorg/apache/hc/client5/http/impl/async/AsyncHttpRequestRetryExec$State;
     208: iconst_1
     209: putfield      #20                 // Field org/apache/hc/client5/http/impl/async/AsyncHttpRequestRetryExec$State.retrying:Z
     212: aload_0
     213: getfield      #2                  // Field val$scope:Lorg/apache/hc/client5/http/async/AsyncExecChain$Scope;
     216: getfield      #17                 // Field org/apache/hc/client5/http/async/AsyncExecChain$Scope.execCount:Ljava/util/concurrent/atomic/AtomicInteger;
     219: invokevirtual #28                 // Method java/util/concurrent/atomic/AtomicInteger.incrementAndGet:()I
     222: pop
     223: aload_0
     224: getfield      #2                  // Field val$scope:Lorg/apache/hc/client5/http/async/AsyncExecChain$Scope;
     227: getfield      #29                 // Field org/apache/hc/client5/http/async/AsyncExecChain$Scope.scheduler:Lorg/apache/hc/client5/http/async/AsyncExecChain$Scheduler;
     230: aload_0
     231: getfield      #7                  // Field val$request:Lorg/apache/hc/core5/http/HttpRequest;
     234: aload_0
     235: getfield      #3                  // Field val$entityProducer:Lorg/apache/hc/core5/http/nio/AsyncEntityProducer;
     238: aload_0
     239: getfield      #2                  // Field val$scope:Lorg/apache/hc/client5/http/async/AsyncExecChain$Scope;
     242: aload_0
     243: getfield      #5                  // Field val$asyncExecCallback:Lorg/apache/hc/client5/http/async/AsyncExecCallback;
     246: aload_0
     247: getfield      #6                  // Field val$state:Lorg/apache/hc/client5/http/impl/async/AsyncHttpRequestRetryExec$State;
     250: getfield      #22                 // Field org/apache/hc/client5/http/impl/async/AsyncHttpRequestRetryExec$State.delay:Lorg/apache/hc/core5/util/TimeValue;
     253: invokeinterface #30,  6           // InterfaceMethod org/apache/hc/client5/http/async/AsyncExecChain$Scheduler.scheduleExecution:(Lorg/apache/hc/core5/http/HttpRequest;Lorg/apache/hc/core5/http/nio/AsyncEntityProducer;Lorg/apache/hc/client5/http/async/AsyncExecChain$Scope;Lorg/apache/hc/client5/http/async/AsyncExecCallback;Lorg/apache/hc/core5/util/TimeValue;)V
     258: return
     259: aload_0
     260: getfield      #5                  // Field val$asyncExecCallback:Lorg/apache/hc/client5/http/async/AsyncExecCallback;
     263: aload_1
     264: invokeinterface #47,  2           // InterfaceMethod org/apache/hc/client5/http/async/AsyncExecCallback.failed:(Ljava/lang/Exception;)V
     269: return
}
