Compiled from "AsyncConnectExec.java"
class org.apache.hc.client5.http.impl.async.AsyncConnectExec$3 implements org.apache.hc.core5.concurrent.FutureCallback<org.apache.hc.client5.http.async.AsyncExecRuntime> {
  final org.apache.hc.client5.http.HttpRoute val$route;

  final org.apache.hc.client5.http.RouteTracker val$tracker;

  final java.lang.String val$exchangeId;

  final org.apache.hc.client5.http.impl.async.AsyncConnectExec$State val$state;

  final org.apache.hc.core5.http.HttpRequest val$request;

  final org.apache.hc.core5.http.nio.AsyncEntityProducer val$entityProducer;

  final org.apache.hc.client5.http.async.AsyncExecChain$Scope val$scope;

  final org.apache.hc.client5.http.async.AsyncExecChain val$chain;

  final org.apache.hc.client5.http.async.AsyncExecCallback val$asyncExecCallback;

  final org.apache.hc.client5.http.impl.async.AsyncConnectExec this$0;

  org.apache.hc.client5.http.impl.async.AsyncConnectExec$3(org.apache.hc.client5.http.impl.async.AsyncConnectExec, org.apache.hc.client5.http.HttpRoute, org.apache.hc.client5.http.RouteTracker, java.lang.String, org.apache.hc.client5.http.impl.async.AsyncConnectExec$State, org.apache.hc.core5.http.HttpRequest, org.apache.hc.core5.http.nio.AsyncEntityProducer, org.apache.hc.client5.http.async.AsyncExecChain$Scope, org.apache.hc.client5.http.async.AsyncExecChain, org.apache.hc.client5.http.async.AsyncExecCallback);
    Code:
       0: aload_0
       1: aload_1
       2: putfield      #1                  // Field this$0:Lorg/apache/hc/client5/http/impl/async/AsyncConnectExec;
       5: aload_0
       6: aload_2
       7: putfield      #2                  // Field val$route:Lorg/apache/hc/client5/http/HttpRoute;
      10: aload_0
      11: aload_3
      12: putfield      #3                  // Field val$tracker:Lorg/apache/hc/client5/http/RouteTracker;
      15: aload_0
      16: aload         4
      18: putfield      #4                  // Field val$exchangeId:Ljava/lang/String;
      21: aload_0
      22: aload         5
      24: putfield      #5                  // Field val$state:Lorg/apache/hc/client5/http/impl/async/AsyncConnectExec$State;
      27: aload_0
      28: aload         6
      30: putfield      #6                  // Field val$request:Lorg/apache/hc/core5/http/HttpRequest;
      33: aload_0
      34: aload         7
      36: putfield      #7                  // Field val$entityProducer:Lorg/apache/hc/core5/http/nio/AsyncEntityProducer;
      39: aload_0
      40: aload         8
      42: putfield      #8                  // Field val$scope:Lorg/apache/hc/client5/http/async/AsyncExecChain$Scope;
      45: aload_0
      46: aload         9
      48: putfield      #9                  // Field val$chain:Lorg/apache/hc/client5/http/async/AsyncExecChain;
      51: aload_0
      52: aload         10
      54: putfield      #10                 // Field val$asyncExecCallback:Lorg/apache/hc/client5/http/async/AsyncExecCallback;
      57: aload_0
      58: invokespecial #11                 // Method java/lang/Object."<init>":()V
      61: return

  public void completed(org.apache.hc.client5.http.async.AsyncExecRuntime);
    Code:
       0: aload_0
       1: getfield      #2                  // Field val$route:Lorg/apache/hc/client5/http/HttpRoute;
       4: invokevirtual #12                 // Method org/apache/hc/client5/http/HttpRoute.getProxyHost:()Lorg/apache/hc/core5/http/HttpHost;
       7: astore_2
       8: aload_0
       9: getfield      #3                  // Field val$tracker:Lorg/apache/hc/client5/http/RouteTracker;
      12: aload_2
      13: aload_0
      14: getfield      #2                  // Field val$route:Lorg/apache/hc/client5/http/HttpRoute;
      17: invokevirtual #13                 // Method org/apache/hc/client5/http/HttpRoute.isSecure:()Z
      20: ifeq          37
      23: aload_0
      24: getfield      #2                  // Field val$route:Lorg/apache/hc/client5/http/HttpRoute;
      27: invokevirtual #14                 // Method org/apache/hc/client5/http/HttpRoute.isTunnelled:()Z
      30: ifne          37
      33: iconst_1
      34: goto          38
      37: iconst_0
      38: invokevirtual #15                 // Method org/apache/hc/client5/http/RouteTracker.connectProxy:(Lorg/apache/hc/core5/http/HttpHost;Z)V
      41: invokestatic  #16                 // Method org/apache/hc/client5/http/impl/async/AsyncConnectExec.access$100:()Lorg/slf4j/Logger;
      44: invokeinterface #17,  1           // InterfaceMethod org/slf4j/Logger.isDebugEnabled:()Z
      49: ifeq          66
      52: invokestatic  #16                 // Method org/apache/hc/client5/http/impl/async/AsyncConnectExec.access$100:()Lorg/slf4j/Logger;
      55: ldc           #18                 // String {} connected to proxy
      57: aload_0
      58: getfield      #4                  // Field val$exchangeId:Ljava/lang/String;
      61: invokeinterface #19,  3           // InterfaceMethod org/slf4j/Logger.debug:(Ljava/lang/String;Ljava/lang/Object;)V
      66: aload_0
      67: getfield      #1                  // Field this$0:Lorg/apache/hc/client5/http/impl/async/AsyncConnectExec;
      70: aload_0
      71: getfield      #5                  // Field val$state:Lorg/apache/hc/client5/http/impl/async/AsyncConnectExec$State;
      74: aload_0
      75: getfield      #6                  // Field val$request:Lorg/apache/hc/core5/http/HttpRequest;
      78: aload_0
      79: getfield      #7                  // Field val$entityProducer:Lorg/apache/hc/core5/http/nio/AsyncEntityProducer;
      82: aload_0
      83: getfield      #8                  // Field val$scope:Lorg/apache/hc/client5/http/async/AsyncExecChain$Scope;
      86: aload_0
      87: getfield      #9                  // Field val$chain:Lorg/apache/hc/client5/http/async/AsyncExecChain;
      90: aload_0
      91: getfield      #10                 // Field val$asyncExecCallback:Lorg/apache/hc/client5/http/async/AsyncExecCallback;
      94: invokestatic  #20                 // Method org/apache/hc/client5/http/impl/async/AsyncConnectExec.access$000:(Lorg/apache/hc/client5/http/impl/async/AsyncConnectExec;Lorg/apache/hc/client5/http/impl/async/AsyncConnectExec$State;Lorg/apache/hc/core5/http/HttpRequest;Lorg/apache/hc/core5/http/nio/AsyncEntityProducer;Lorg/apache/hc/client5/http/async/AsyncExecChain$Scope;Lorg/apache/hc/client5/http/async/AsyncExecChain;Lorg/apache/hc/client5/http/async/AsyncExecCallback;)V
      97: return

  public void failed(java.lang.Exception);
    Code:
       0: aload_0
       1: getfield      #10                 // Field val$asyncExecCallback:Lorg/apache/hc/client5/http/async/AsyncExecCallback;
       4: aload_1
       5: invokeinterface #21,  2           // InterfaceMethod org/apache/hc/client5/http/async/AsyncExecCallback.failed:(Ljava/lang/Exception;)V
      10: return

  public void cancelled();
    Code:
       0: aload_0
       1: getfield      #10                 // Field val$asyncExecCallback:Lorg/apache/hc/client5/http/async/AsyncExecCallback;
       4: new           #22                 // class java/io/InterruptedIOException
       7: dup
       8: invokespecial #23                 // Method java/io/InterruptedIOException."<init>":()V
      11: invokeinterface #21,  2           // InterfaceMethod org/apache/hc/client5/http/async/AsyncExecCallback.failed:(Ljava/lang/Exception;)V
      16: return

  public void completed(java.lang.Object);
    Code:
       0: aload_0
       1: aload_1
       2: checkcast     #24                 // class org/apache/hc/client5/http/async/AsyncExecRuntime
       5: invokevirtual #25                 // Method completed:(Lorg/apache/hc/client5/http/async/AsyncExecRuntime;)V
       8: return
}
