Compiled from "HttpAsyncClientBuilder.java"
class org.apache.hc.client5.http.impl.async.HttpAsyncClientBuilder$1 implements java.security.PrivilegedAction<java.net.ProxySelector> {
  final org.apache.hc.client5.http.impl.async.HttpAsyncClientBuilder this$0;

  org.apache.hc.client5.http.impl.async.HttpAsyncClientBuilder$1(org.apache.hc.client5.http.impl.async.HttpAsyncClientBuilder);
    Code:
       0: aload_0
       1: aload_1
       2: putfield      #1                  // Field this$0:Lorg/apache/hc/client5/http/impl/async/HttpAsyncClientBuilder;
       5: aload_0
       6: invokespecial #2                  // Method java/lang/Object."<init>":()V
       9: return

  public java.net.ProxySelector run();
    Code:
       0: invokestatic  #3                  // Method java/net/ProxySelector.getDefault:()Ljava/net/ProxySelector;
       3: areturn

  public java.lang.Object run();
    Code:
       0: aload_0
       1: invokevirtual #4                  // Method run:()Ljava/net/ProxySelector;
       4: areturn
}
