Compiled from "MinimalH2AsyncClient.java"
class org.apache.hc.client5.http.impl.async.MinimalH2AsyncClient$3$1 implements org.apache.hc.core5.concurrent.FutureCallback<org.apache.hc.core5.reactor.IOSession> {
  final org.apache.hc.core5.http.HttpRequest val$request;

  final org.apache.hc.core5.http.EntityDetails val$entityDetails;

  final org.apache.hc.client5.http.impl.async.MinimalH2AsyncClient$3 this$1;

  org.apache.hc.client5.http.impl.async.MinimalH2AsyncClient$3$1(org.apache.hc.client5.http.impl.async.MinimalH2AsyncClient$3, org.apache.hc.core5.http.HttpRequest, org.apache.hc.core5.http.EntityDetails);
    Code:
       0: aload_0
       1: aload_1
       2: putfield      #1                  // Field this$1:Lorg/apache/hc/client5/http/impl/async/MinimalH2AsyncClient$3;
       5: aload_0
       6: aload_2
       7: putfield      #2                  // Field val$request:Lorg/apache/hc/core5/http/HttpRequest;
      10: aload_0
      11: aload_3
      12: putfield      #3                  // Field val$entityDetails:Lorg/apache/hc/core5/http/EntityDetails;
      15: aload_0
      16: invokespecial #4                  // Method java/lang/Object."<init>":()V
      19: return

  public void completed(org.apache.hc.core5.reactor.IOSession);
    Code:
       0: new           #5                  // class org/apache/hc/client5/http/impl/async/MinimalH2AsyncClient$3$1$1
       3: dup
       4: aload_0
       5: invokespecial #6                  // Method org/apache/hc/client5/http/impl/async/MinimalH2AsyncClient$3$1$1."<init>":(Lorg/apache/hc/client5/http/impl/async/MinimalH2AsyncClient$3$1;)V
       8: astore_2
       9: invokestatic  #7                  // Method org/apache/hc/client5/http/impl/async/MinimalH2AsyncClient.access$000:()Lorg/slf4j/Logger;
      12: invokeinterface #8,  1            // InterfaceMethod org/slf4j/Logger.isDebugEnabled:()Z
      17: ifeq          113
      20: invokestatic  #9                  // Method org/apache/hc/client5/http/impl/ExecSupport.getNextExchangeId:()Ljava/lang/String;
      23: astore_3
      24: aload_0
      25: getfield      #1                  // Field this$1:Lorg/apache/hc/client5/http/impl/async/MinimalH2AsyncClient$3;
      28: getfield      #10                 // Field org/apache/hc/client5/http/impl/async/MinimalH2AsyncClient$3.val$clientContext:Lorg/apache/hc/client5/http/protocol/HttpClientContext;
      31: aload_3
      32: invokevirtual #11                 // Method org/apache/hc/client5/http/protocol/HttpClientContext.setExchangeId:(Ljava/lang/String;)V
      35: invokestatic  #7                  // Method org/apache/hc/client5/http/impl/async/MinimalH2AsyncClient.access$000:()Lorg/slf4j/Logger;
      38: invokeinterface #8,  1            // InterfaceMethod org/slf4j/Logger.isDebugEnabled:()Z
      43: ifeq          61
      46: invokestatic  #7                  // Method org/apache/hc/client5/http/impl/async/MinimalH2AsyncClient.access$000:()Lorg/slf4j/Logger;
      49: ldc           #12                 // String {} executing message exchange {}
      51: aload_3
      52: aload_1
      53: invokestatic  #13                 // Method org/apache/hc/client5/http/impl/ConnPoolSupport.getId:(Ljava/lang/Object;)Ljava/lang/String;
      56: invokeinterface #14,  4           // InterfaceMethod org/slf4j/Logger.debug:(Ljava/lang/String;Ljava/lang/Object;Ljava/lang/Object;)V
      61: aload_1
      62: new           #15                 // class org/apache/hc/core5/http/nio/command/RequestExecutionCommand
      65: dup
      66: new           #16                 // class org/apache/hc/client5/http/impl/async/LoggingAsyncClientExchangeHandler
      69: dup
      70: invokestatic  #7                  // Method org/apache/hc/client5/http/impl/async/MinimalH2AsyncClient.access$000:()Lorg/slf4j/Logger;
      73: aload_3
      74: aload_2
      75: invokespecial #17                 // Method org/apache/hc/client5/http/impl/async/LoggingAsyncClientExchangeHandler."<init>":(Lorg/slf4j/Logger;Ljava/lang/String;Lorg/apache/hc/core5/http/nio/AsyncClientExchangeHandler;)V
      78: aload_0
      79: getfield      #1                  // Field this$1:Lorg/apache/hc/client5/http/impl/async/MinimalH2AsyncClient$3;
      82: getfield      #18                 // Field org/apache/hc/client5/http/impl/async/MinimalH2AsyncClient$3.val$pushHandlerFactory:Lorg/apache/hc/core5/http/nio/HandlerFactory;
      85: aload_0
      86: getfield      #1                  // Field this$1:Lorg/apache/hc/client5/http/impl/async/MinimalH2AsyncClient$3;
      89: getfield      #19                 // Field org/apache/hc/client5/http/impl/async/MinimalH2AsyncClient$3.val$cancellable:Lorg/apache/hc/core5/concurrent/ComplexCancellable;
      92: aload_0
      93: getfield      #1                  // Field this$1:Lorg/apache/hc/client5/http/impl/async/MinimalH2AsyncClient$3;
      96: getfield      #10                 // Field org/apache/hc/client5/http/impl/async/MinimalH2AsyncClient$3.val$clientContext:Lorg/apache/hc/client5/http/protocol/HttpClientContext;
      99: invokespecial #20                 // Method org/apache/hc/core5/http/nio/command/RequestExecutionCommand."<init>":(Lorg/apache/hc/core5/http/nio/AsyncClientExchangeHandler;Lorg/apache/hc/core5/http/nio/HandlerFactory;Lorg/apache/hc/core5/concurrent/CancellableDependency;Lorg/apache/hc/core5/http/protocol/HttpContext;)V
     102: getstatic     #21                 // Field org/apache/hc/core5/reactor/Command$Priority.NORMAL:Lorg/apache/hc/core5/reactor/Command$Priority;
     105: invokeinterface #22,  3           // InterfaceMethod org/apache/hc/core5/reactor/IOSession.enqueue:(Lorg/apache/hc/core5/reactor/Command;Lorg/apache/hc/core5/reactor/Command$Priority;)V
     110: goto          151
     113: aload_1
     114: new           #15                 // class org/apache/hc/core5/http/nio/command/RequestExecutionCommand
     117: dup
     118: aload_2
     119: aload_0
     120: getfield      #1                  // Field this$1:Lorg/apache/hc/client5/http/impl/async/MinimalH2AsyncClient$3;
     123: getfield      #18                 // Field org/apache/hc/client5/http/impl/async/MinimalH2AsyncClient$3.val$pushHandlerFactory:Lorg/apache/hc/core5/http/nio/HandlerFactory;
     126: aload_0
     127: getfield      #1                  // Field this$1:Lorg/apache/hc/client5/http/impl/async/MinimalH2AsyncClient$3;
     130: getfield      #19                 // Field org/apache/hc/client5/http/impl/async/MinimalH2AsyncClient$3.val$cancellable:Lorg/apache/hc/core5/concurrent/ComplexCancellable;
     133: aload_0
     134: getfield      #1                  // Field this$1:Lorg/apache/hc/client5/http/impl/async/MinimalH2AsyncClient$3;
     137: getfield      #10                 // Field org/apache/hc/client5/http/impl/async/MinimalH2AsyncClient$3.val$clientContext:Lorg/apache/hc/client5/http/protocol/HttpClientContext;
     140: invokespecial #20                 // Method org/apache/hc/core5/http/nio/command/RequestExecutionCommand."<init>":(Lorg/apache/hc/core5/http/nio/AsyncClientExchangeHandler;Lorg/apache/hc/core5/http/nio/HandlerFactory;Lorg/apache/hc/core5/concurrent/CancellableDependency;Lorg/apache/hc/core5/http/protocol/HttpContext;)V
     143: getstatic     #21                 // Field org/apache/hc/core5/reactor/Command$Priority.NORMAL:Lorg/apache/hc/core5/reactor/Command$Priority;
     146: invokeinterface #22,  3           // InterfaceMethod org/apache/hc/core5/reactor/IOSession.enqueue:(Lorg/apache/hc/core5/reactor/Command;Lorg/apache/hc/core5/reactor/Command$Priority;)V
     151: return

  public void failed(java.lang.Exception);
    Code:
       0: aload_0
       1: getfield      #1                  // Field this$1:Lorg/apache/hc/client5/http/impl/async/MinimalH2AsyncClient$3;
       4: getfield      #23                 // Field org/apache/hc/client5/http/impl/async/MinimalH2AsyncClient$3.val$exchangeHandler:Lorg/apache/hc/core5/http/nio/AsyncClientExchangeHandler;
       7: aload_1
       8: invokeinterface #24,  2           // InterfaceMethod org/apache/hc/core5/http/nio/AsyncClientExchangeHandler.failed:(Ljava/lang/Exception;)V
      13: return

  public void cancelled();
    Code:
       0: aload_0
       1: getfield      #1                  // Field this$1:Lorg/apache/hc/client5/http/impl/async/MinimalH2AsyncClient$3;
       4: getfield      #23                 // Field org/apache/hc/client5/http/impl/async/MinimalH2AsyncClient$3.val$exchangeHandler:Lorg/apache/hc/core5/http/nio/AsyncClientExchangeHandler;
       7: invokeinterface #25,  1           // InterfaceMethod org/apache/hc/core5/http/nio/AsyncClientExchangeHandler.cancel:()V
      12: return

  public void completed(java.lang.Object);
    Code:
       0: aload_0
       1: aload_1
       2: checkcast     #26                 // class org/apache/hc/core5/reactor/IOSession
       5: invokevirtual #27                 // Method completed:(Lorg/apache/hc/core5/reactor/IOSession;)V
       8: return
}
