Compiled from "MinimalH2AsyncClient.java"
class org.apache.hc.client5.http.impl.async.MinimalH2AsyncClient$3 implements org.apache.hc.core5.http.nio.RequestChannel {
  final org.apache.hc.client5.http.protocol.HttpClientContext val$clientContext;

  final org.apache.hc.core5.http.nio.AsyncClientExchangeHandler val$exchangeHandler;

  final org.apache.hc.core5.http.nio.HandlerFactory val$pushHandlerFactory;

  final org.apache.hc.core5.concurrent.ComplexCancellable val$cancellable;

  final org.apache.hc.client5.http.impl.async.MinimalH2AsyncClient this$0;

  org.apache.hc.client5.http.impl.async.MinimalH2AsyncClient$3(org.apache.hc.client5.http.impl.async.MinimalH2AsyncClient, org.apache.hc.client5.http.protocol.HttpClientContext, org.apache.hc.core5.http.nio.AsyncClientExchangeHandler, org.apache.hc.core5.http.nio.HandlerFactory, org.apache.hc.core5.concurrent.ComplexCancellable);
    Code:
       0: aload_0
       1: aload_1
       2: putfield      #1                  // Field this$0:Lorg/apache/hc/client5/http/impl/async/MinimalH2AsyncClient;
       5: aload_0
       6: aload_2
       7: putfield      #2                  // Field val$clientContext:Lorg/apache/hc/client5/http/protocol/HttpClientContext;
      10: aload_0
      11: aload_3
      12: putfield      #3                  // Field val$exchangeHandler:Lorg/apache/hc/core5/http/nio/AsyncClientExchangeHandler;
      15: aload_0
      16: aload         4
      18: putfield      #4                  // Field val$pushHandlerFactory:Lorg/apache/hc/core5/http/nio/HandlerFactory;
      21: aload_0
      22: aload         5
      24: putfield      #5                  // Field val$cancellable:Lorg/apache/hc/core5/concurrent/ComplexCancellable;
      27: aload_0
      28: invokespecial #6                  // Method java/lang/Object."<init>":()V
      31: return

  public void sendRequest(org.apache.hc.core5.http.HttpRequest, org.apache.hc.core5.http.EntityDetails, org.apache.hc.core5.http.protocol.HttpContext) throws org.apache.hc.core5.http.HttpException, java.io.IOException;
    Code:
       0: aconst_null
       1: astore        4
       3: aload_1
       4: instanceof    #7                  // class org/apache/hc/client5/http/config/Configurable
       7: ifeq          21
      10: aload_1
      11: checkcast     #7                  // class org/apache/hc/client5/http/config/Configurable
      14: invokeinterface #8,  1            // InterfaceMethod org/apache/hc/client5/http/config/Configurable.getConfig:()Lorg/apache/hc/client5/http/config/RequestConfig;
      19: astore        4
      21: aload         4
      23: ifnull        38
      26: aload_0
      27: getfield      #2                  // Field val$clientContext:Lorg/apache/hc/client5/http/protocol/HttpClientContext;
      30: aload         4
      32: invokevirtual #9                  // Method org/apache/hc/client5/http/protocol/HttpClientContext.setRequestConfig:(Lorg/apache/hc/client5/http/config/RequestConfig;)V
      35: goto          47
      38: aload_0
      39: getfield      #2                  // Field val$clientContext:Lorg/apache/hc/client5/http/protocol/HttpClientContext;
      42: invokevirtual #10                 // Method org/apache/hc/client5/http/protocol/HttpClientContext.getRequestConfig:()Lorg/apache/hc/client5/http/config/RequestConfig;
      45: astore        4
      47: aload         4
      49: invokevirtual #11                 // Method org/apache/hc/client5/http/config/RequestConfig.getConnectTimeout:()Lorg/apache/hc/core5/util/Timeout;
      52: astore        5
      54: new           #12                 // class org/apache/hc/core5/http/HttpHost
      57: dup
      58: aload_1
      59: invokeinterface #13,  1           // InterfaceMethod org/apache/hc/core5/http/HttpRequest.getScheme:()Ljava/lang/String;
      64: aload_1
      65: invokeinterface #14,  1           // InterfaceMethod org/apache/hc/core5/http/HttpRequest.getAuthority:()Lorg/apache/hc/core5/net/URIAuthority;
      70: invokespecial #15                 // Method org/apache/hc/core5/http/HttpHost."<init>":(Ljava/lang/String;Lorg/apache/hc/core5/net/NamedEndpoint;)V
      73: astore        6
      75: aload_0
      76: getfield      #1                  // Field this$0:Lorg/apache/hc/client5/http/impl/async/MinimalH2AsyncClient;
      79: invokestatic  #16                 // Method org/apache/hc/client5/http/impl/async/MinimalH2AsyncClient.access$100:(Lorg/apache/hc/client5/http/impl/async/MinimalH2AsyncClient;)Lorg/apache/hc/core5/http2/nio/pool/H2ConnPool;
      82: aload         6
      84: aload         5
      86: new           #17                 // class org/apache/hc/client5/http/impl/async/MinimalH2AsyncClient$3$1
      89: dup
      90: aload_0
      91: aload_1
      92: aload_2
      93: invokespecial #18                 // Method org/apache/hc/client5/http/impl/async/MinimalH2AsyncClient$3$1."<init>":(Lorg/apache/hc/client5/http/impl/async/MinimalH2AsyncClient$3;Lorg/apache/hc/core5/http/HttpRequest;Lorg/apache/hc/core5/http/EntityDetails;)V
      96: invokevirtual #19                 // Method org/apache/hc/core5/http2/nio/pool/H2ConnPool.getSession:(Ljava/lang/Object;Lorg/apache/hc/core5/util/Timeout;Lorg/apache/hc/core5/concurrent/FutureCallback;)Ljava/util/concurrent/Future;
      99: astore        7
     101: aload_0
     102: getfield      #5                  // Field val$cancellable:Lorg/apache/hc/core5/concurrent/ComplexCancellable;
     105: new           #20                 // class org/apache/hc/client5/http/impl/async/MinimalH2AsyncClient$3$2
     108: dup
     109: aload_0
     110: aload         7
     112: invokespecial #21                 // Method org/apache/hc/client5/http/impl/async/MinimalH2AsyncClient$3$2."<init>":(Lorg/apache/hc/client5/http/impl/async/MinimalH2AsyncClient$3;Ljava/util/concurrent/Future;)V
     115: invokevirtual #22                 // Method org/apache/hc/core5/concurrent/ComplexCancellable.setDependency:(Lorg/apache/hc/core5/concurrent/Cancellable;)V
     118: return
}
