Compiled from "DiscoveredJmxOperation.java"
class org.springframework.boot.actuate.endpoint.jmx.annotation.DiscoveredJmxOperation$DiscoveredJmxOperationParameter implements org.springframework.boot.actuate.endpoint.jmx.JmxOperationParameter {
  private final java.lang.String name;

  private final java.lang.Class<?> type;

  private final java.lang.String description;

  org.springframework.boot.actuate.endpoint.jmx.annotation.DiscoveredJmxOperation$DiscoveredJmxOperationParameter(org.springframework.boot.actuate.endpoint.invoke.OperationParameter);
    Code:
       0: aload_0
       1: invokespecial #1                  // Method java/lang/Object."<init>":()V
       4: aload_0
       5: aload_1
       6: invokeinterface #2,  1            // InterfaceMethod org/springframework/boot/actuate/endpoint/invoke/OperationParameter.getName:()Ljava/lang/String;
      11: putfield      #3                  // Field name:Ljava/lang/String;
      14: aload_0
      15: aload_1
      16: invokeinterface #4,  1            // InterfaceMethod org/springframework/boot/actuate/endpoint/invoke/OperationParameter.getType:()Ljava/lang/Class;
      21: invokestatic  #5                  // Method org/springframework/boot/actuate/endpoint/jmx/annotation/DiscoveredJmxOperation$JmxType.get:(Ljava/lang/Class;)Ljava/lang/Class;
      24: putfield      #6                  // Field type:Ljava/lang/Class;
      27: aload_0
      28: aconst_null
      29: putfield      #7                  // Field description:Ljava/lang/String;
      32: return

  org.springframework.boot.actuate.endpoint.jmx.annotation.DiscoveredJmxOperation$DiscoveredJmxOperationParameter(org.springframework.jmx.export.metadata.ManagedOperationParameter, org.springframework.boot.actuate.endpoint.invoke.OperationParameter);
    Code:
       0: aload_0
       1: invokespecial #1                  // Method java/lang/Object."<init>":()V
       4: aload_0
       5: aload_1
       6: invokevirtual #8                  // Method org/springframework/jmx/export/metadata/ManagedOperationParameter.getName:()Ljava/lang/String;
       9: putfield      #3                  // Field name:Ljava/lang/String;
      12: aload_0
      13: aload_2
      14: invokeinterface #4,  1            // InterfaceMethod org/springframework/boot/actuate/endpoint/invoke/OperationParameter.getType:()Ljava/lang/Class;
      19: invokestatic  #5                  // Method org/springframework/boot/actuate/endpoint/jmx/annotation/DiscoveredJmxOperation$JmxType.get:(Ljava/lang/Class;)Ljava/lang/Class;
      22: putfield      #6                  // Field type:Ljava/lang/Class;
      25: aload_0
      26: aload_1
      27: invokevirtual #9                  // Method org/springframework/jmx/export/metadata/ManagedOperationParameter.getDescription:()Ljava/lang/String;
      30: putfield      #7                  // Field description:Ljava/lang/String;
      33: return

  public java.lang.String getName();
    Code:
       0: aload_0
       1: getfield      #3                  // Field name:Ljava/lang/String;
       4: areturn

  public java.lang.Class<?> getType();
    Code:
       0: aload_0
       1: getfield      #6                  // Field type:Ljava/lang/Class;
       4: areturn

  public java.lang.String getDescription();
    Code:
       0: aload_0
       1: getfield      #7                  // Field description:Ljava/lang/String;
       4: areturn

  public java.lang.String toString();
    Code:
       0: new           #10                 // class java/lang/StringBuilder
       3: dup
       4: aload_0
       5: getfield      #3                  // Field name:Ljava/lang/String;
       8: invokespecial #11                 // Method java/lang/StringBuilder."<init>":(Ljava/lang/String;)V
      11: astore_1
      12: aload_0
      13: getfield      #7                  // Field description:Ljava/lang/String;
      16: ifnull        51
      19: aload_1
      20: new           #10                 // class java/lang/StringBuilder
      23: dup
      24: invokespecial #12                 // Method java/lang/StringBuilder."<init>":()V
      27: ldc           #13                 // String  (
      29: invokevirtual #14                 // Method java/lang/StringBuilder.append:(Ljava/lang/String;)Ljava/lang/StringBuilder;
      32: aload_0
      33: getfield      #7                  // Field description:Ljava/lang/String;
      36: invokevirtual #14                 // Method java/lang/StringBuilder.append:(Ljava/lang/String;)Ljava/lang/StringBuilder;
      39: ldc           #15                 // String )
      41: invokevirtual #14                 // Method java/lang/StringBuilder.append:(Ljava/lang/String;)Ljava/lang/StringBuilder;
      44: invokevirtual #16                 // Method java/lang/StringBuilder.toString:()Ljava/lang/String;
      47: invokevirtual #14                 // Method java/lang/StringBuilder.append:(Ljava/lang/String;)Ljava/lang/StringBuilder;
      50: pop
      51: aload_1
      52: new           #10                 // class java/lang/StringBuilder
      55: dup
      56: invokespecial #12                 // Method java/lang/StringBuilder."<init>":()V
      59: ldc           #17                 // String :
      61: invokevirtual #14                 // Method java/lang/StringBuilder.append:(Ljava/lang/String;)Ljava/lang/StringBuilder;
      64: aload_0
      65: getfield      #6                  // Field type:Ljava/lang/Class;
      68: invokevirtual #18                 // Method java/lang/StringBuilder.append:(Ljava/lang/Object;)Ljava/lang/StringBuilder;
      71: invokevirtual #16                 // Method java/lang/StringBuilder.toString:()Ljava/lang/String;
      74: invokevirtual #14                 // Method java/lang/StringBuilder.append:(Ljava/lang/String;)Ljava/lang/StringBuilder;
      77: pop
      78: aload_1
      79: invokevirtual #16                 // Method java/lang/StringBuilder.toString:()Ljava/lang/String;
      82: areturn
}
