Compiled from "ExecuteProduceConsume.java"
public class org.eclipse.jetty.util.thread.strategy.ExecuteProduceConsume implements org.eclipse.jetty.util.thread.ExecutionStrategy,java.lang.Runnable {
  private static final org.eclipse.jetty.util.log.Logger LOG;

  private final org.eclipse.jetty.util.thread.Locker _locker;

  private final java.lang.Runnable _runProduce;

  private final org.eclipse.jetty.util.thread.ExecutionStrategy$Producer _producer;

  private final java.util.concurrent.Executor _executor;

  private boolean _idle;

  private boolean _execute;

  private boolean _producing;

  private boolean _pending;

  public org.eclipse.jetty.util.thread.strategy.ExecuteProduceConsume(org.eclipse.jetty.util.thread.ExecutionStrategy$Producer, java.util.concurrent.Executor);
    Code:
       0: aload_0
       1: invokespecial #1                  // Method java/lang/Object."<init>":()V
       4: aload_0
       5: new           #2                  // class org/eclipse/jetty/util/thread/Locker
       8: dup
       9: invokespecial #3                  // Method org/eclipse/jetty/util/thread/Locker."<init>":()V
      12: putfield      #4                  // Field _locker:Lorg/eclipse/jetty/util/thread/Locker;
      15: aload_0
      16: new           #5                  // class org/eclipse/jetty/util/thread/strategy/ExecuteProduceConsume$RunProduce
      19: dup
      20: aload_0
      21: aconst_null
      22: invokespecial #6                  // Method org/eclipse/jetty/util/thread/strategy/ExecuteProduceConsume$RunProduce."<init>":(Lorg/eclipse/jetty/util/thread/strategy/ExecuteProduceConsume;Lorg/eclipse/jetty/util/thread/strategy/ExecuteProduceConsume$1;)V
      25: putfield      #7                  // Field _runProduce:Ljava/lang/Runnable;
      28: aload_0
      29: iconst_1
      30: putfield      #8                  // Field _idle:Z
      33: aload_0
      34: aload_1
      35: putfield      #9                  // Field _producer:Lorg/eclipse/jetty/util/thread/ExecutionStrategy$Producer;
      38: aload_0
      39: aload_2
      40: putfield      #10                 // Field _executor:Ljava/util/concurrent/Executor;
      43: return

  public void produce();
    Code:
       0: getstatic     #11                 // Field LOG:Lorg/eclipse/jetty/util/log/Logger;
       3: invokeinterface #12,  1           // InterfaceMethod org/eclipse/jetty/util/log/Logger.isDebugEnabled:()Z
       8: ifeq          29
      11: getstatic     #11                 // Field LOG:Lorg/eclipse/jetty/util/log/Logger;
      14: ldc           #13                 // String {} execute
      16: iconst_1
      17: anewarray     #14                 // class java/lang/Object
      20: dup
      21: iconst_0
      22: aload_0
      23: aastore
      24: invokeinterface #15,  3           // InterfaceMethod org/eclipse/jetty/util/log/Logger.debug:(Ljava/lang/String;[Ljava/lang/Object;)V
      29: iconst_0
      30: istore_1
      31: aload_0
      32: getfield      #4                  // Field _locker:Lorg/eclipse/jetty/util/thread/Locker;
      35: invokevirtual #16                 // Method org/eclipse/jetty/util/thread/Locker.lock:()Lorg/eclipse/jetty/util/thread/Locker$Lock;
      38: astore_2
      39: aload_0
      40: getfield      #8                  // Field _idle:Z
      43: ifeq          76
      46: aload_0
      47: getfield      #17                 // Field _producing:Z
      50: ifeq          61
      53: new           #18                 // class java/lang/IllegalStateException
      56: dup
      57: invokespecial #19                 // Method java/lang/IllegalStateException."<init>":()V
      60: athrow
      61: aload_0
      62: iconst_1
      63: dup_x1
      64: putfield      #17                 // Field _producing:Z
      67: istore_1
      68: aload_0
      69: iconst_0
      70: putfield      #8                  // Field _idle:Z
      73: goto          81
      76: aload_0
      77: iconst_1
      78: putfield      #20                 // Field _execute:Z
      81: aload_2
      82: ifnull        114
      85: aload_2
      86: invokevirtual #21                 // Method org/eclipse/jetty/util/thread/Locker$Lock.close:()V
      89: goto          114
      92: astore_3
      93: aload_2
      94: ifnull        112
      97: aload_2
      98: invokevirtual #21                 // Method org/eclipse/jetty/util/thread/Locker$Lock.close:()V
     101: goto          112
     104: astore        4
     106: aload_3
     107: aload         4
     109: invokevirtual #23                 // Method java/lang/Throwable.addSuppressed:(Ljava/lang/Throwable;)V
     112: aload_3
     113: athrow
     114: iload_1
     115: ifeq          122
     118: aload_0
     119: invokespecial #24                 // Method produceConsume:()V
     122: return
    Exception table:
       from    to  target type
          39    81    92   Class java/lang/Throwable
          97   101   104   Class java/lang/Throwable

  public void dispatch();
    Code:
       0: getstatic     #11                 // Field LOG:Lorg/eclipse/jetty/util/log/Logger;
       3: invokeinterface #12,  1           // InterfaceMethod org/eclipse/jetty/util/log/Logger.isDebugEnabled:()Z
       8: ifeq          29
      11: getstatic     #11                 // Field LOG:Lorg/eclipse/jetty/util/log/Logger;
      14: ldc           #25                 // String {} spawning
      16: iconst_1
      17: anewarray     #14                 // class java/lang/Object
      20: dup
      21: iconst_0
      22: aload_0
      23: aastore
      24: invokeinterface #15,  3           // InterfaceMethod org/eclipse/jetty/util/log/Logger.debug:(Ljava/lang/String;[Ljava/lang/Object;)V
      29: iconst_0
      30: istore_1
      31: aload_0
      32: getfield      #4                  // Field _locker:Lorg/eclipse/jetty/util/thread/Locker;
      35: invokevirtual #16                 // Method org/eclipse/jetty/util/thread/Locker.lock:()Lorg/eclipse/jetty/util/thread/Locker$Lock;
      38: astore_2
      39: aload_0
      40: getfield      #8                  // Field _idle:Z
      43: ifeq          51
      46: iconst_1
      47: istore_1
      48: goto          56
      51: aload_0
      52: iconst_1
      53: putfield      #20                 // Field _execute:Z
      56: aload_2
      57: ifnull        89
      60: aload_2
      61: invokevirtual #21                 // Method org/eclipse/jetty/util/thread/Locker$Lock.close:()V
      64: goto          89
      67: astore_3
      68: aload_2
      69: ifnull        87
      72: aload_2
      73: invokevirtual #21                 // Method org/eclipse/jetty/util/thread/Locker$Lock.close:()V
      76: goto          87
      79: astore        4
      81: aload_3
      82: aload         4
      84: invokevirtual #23                 // Method java/lang/Throwable.addSuppressed:(Ljava/lang/Throwable;)V
      87: aload_3
      88: athrow
      89: iload_1
      90: ifeq          106
      93: aload_0
      94: getfield      #10                 // Field _executor:Ljava/util/concurrent/Executor;
      97: aload_0
      98: getfield      #7                  // Field _runProduce:Ljava/lang/Runnable;
     101: invokeinterface #26,  2           // InterfaceMethod java/util/concurrent/Executor.execute:(Ljava/lang/Runnable;)V
     106: return
    Exception table:
       from    to  target type
          39    56    67   Class java/lang/Throwable
          72    76    79   Class java/lang/Throwable

  public void run();
    Code:
       0: getstatic     #11                 // Field LOG:Lorg/eclipse/jetty/util/log/Logger;
       3: invokeinterface #12,  1           // InterfaceMethod org/eclipse/jetty/util/log/Logger.isDebugEnabled:()Z
       8: ifeq          29
      11: getstatic     #11                 // Field LOG:Lorg/eclipse/jetty/util/log/Logger;
      14: ldc           #27                 // String {} run
      16: iconst_1
      17: anewarray     #14                 // class java/lang/Object
      20: dup
      21: iconst_0
      22: aload_0
      23: aastore
      24: invokeinterface #15,  3           // InterfaceMethod org/eclipse/jetty/util/log/Logger.debug:(Ljava/lang/String;[Ljava/lang/Object;)V
      29: iconst_0
      30: istore_1
      31: aload_0
      32: getfield      #4                  // Field _locker:Lorg/eclipse/jetty/util/thread/Locker;
      35: invokevirtual #16                 // Method org/eclipse/jetty/util/thread/Locker.lock:()Lorg/eclipse/jetty/util/thread/Locker$Lock;
      38: astore_2
      39: aload_0
      40: iconst_0
      41: putfield      #28                 // Field _pending:Z
      44: aload_0
      45: getfield      #8                  // Field _idle:Z
      48: ifne          65
      51: aload_0
      52: getfield      #17                 // Field _producing:Z
      55: ifne          65
      58: aload_0
      59: iconst_1
      60: dup_x1
      61: putfield      #17                 // Field _producing:Z
      64: istore_1
      65: aload_2
      66: ifnull        98
      69: aload_2
      70: invokevirtual #21                 // Method org/eclipse/jetty/util/thread/Locker$Lock.close:()V
      73: goto          98
      76: astore_3
      77: aload_2
      78: ifnull        96
      81: aload_2
      82: invokevirtual #21                 // Method org/eclipse/jetty/util/thread/Locker$Lock.close:()V
      85: goto          96
      88: astore        4
      90: aload_3
      91: aload         4
      93: invokevirtual #23                 // Method java/lang/Throwable.addSuppressed:(Ljava/lang/Throwable;)V
      96: aload_3
      97: athrow
      98: iload_1
      99: ifeq          106
     102: aload_0
     103: invokespecial #24                 // Method produceConsume:()V
     106: return
    Exception table:
       from    to  target type
          39    65    76   Class java/lang/Throwable
          81    85    88   Class java/lang/Throwable

  private void produceConsume();
    Code:
       0: getstatic     #11                 // Field LOG:Lorg/eclipse/jetty/util/log/Logger;
       3: invokeinterface #12,  1           // InterfaceMethod org/eclipse/jetty/util/log/Logger.isDebugEnabled:()Z
       8: ifeq          29
      11: getstatic     #11                 // Field LOG:Lorg/eclipse/jetty/util/log/Logger;
      14: ldc           #29                 // String {} produce enter
      16: iconst_1
      17: anewarray     #14                 // class java/lang/Object
      20: dup
      21: iconst_0
      22: aload_0
      23: aastore
      24: invokeinterface #15,  3           // InterfaceMethod org/eclipse/jetty/util/log/Logger.debug:(Ljava/lang/String;[Ljava/lang/Object;)V
      29: getstatic     #11                 // Field LOG:Lorg/eclipse/jetty/util/log/Logger;
      32: invokeinterface #12,  1           // InterfaceMethod org/eclipse/jetty/util/log/Logger.isDebugEnabled:()Z
      37: ifeq          58
      40: getstatic     #11                 // Field LOG:Lorg/eclipse/jetty/util/log/Logger;
      43: ldc           #30                 // String {} producing
      45: iconst_1
      46: anewarray     #14                 // class java/lang/Object
      49: dup
      50: iconst_0
      51: aload_0
      52: aastore
      53: invokeinterface #15,  3           // InterfaceMethod org/eclipse/jetty/util/log/Logger.debug:(Ljava/lang/String;[Ljava/lang/Object;)V
      58: aload_0
      59: getfield      #9                  // Field _producer:Lorg/eclipse/jetty/util/thread/ExecutionStrategy$Producer;
      62: invokeinterface #31,  1           // InterfaceMethod org/eclipse/jetty/util/thread/ExecutionStrategy$Producer.produce:()Ljava/lang/Runnable;
      67: astore_1
      68: getstatic     #11                 // Field LOG:Lorg/eclipse/jetty/util/log/Logger;
      71: invokeinterface #12,  1           // InterfaceMethod org/eclipse/jetty/util/log/Logger.isDebugEnabled:()Z
      76: ifeq          101
      79: getstatic     #11                 // Field LOG:Lorg/eclipse/jetty/util/log/Logger;
      82: ldc           #32                 // String {} produced {}
      84: iconst_2
      85: anewarray     #14                 // class java/lang/Object
      88: dup
      89: iconst_0
      90: aload_0
      91: aastore
      92: dup
      93: iconst_1
      94: aload_1
      95: aastore
      96: invokeinterface #15,  3           // InterfaceMethod org/eclipse/jetty/util/log/Logger.debug:(Ljava/lang/String;[Ljava/lang/Object;)V
     101: iconst_0
     102: istore_2
     103: aload_0
     104: getfield      #4                  // Field _locker:Lorg/eclipse/jetty/util/thread/Locker;
     107: invokevirtual #16                 // Method org/eclipse/jetty/util/thread/Locker.lock:()Lorg/eclipse/jetty/util/thread/Locker$Lock;
     110: astore_3
     111: aload_0
     112: iconst_0
     113: putfield      #17                 // Field _producing:Z
     116: aload_1
     117: ifnonnull     169
     120: aload_0
     121: getfield      #20                 // Field _execute:Z
     124: ifeq          153
     127: aload_0
     128: iconst_0
     129: putfield      #8                  // Field _idle:Z
     132: aload_0
     133: iconst_1
     134: putfield      #17                 // Field _producing:Z
     137: aload_0
     138: iconst_0
     139: putfield      #20                 // Field _execute:Z
     142: aload_3
     143: ifnull        29
     146: aload_3
     147: invokevirtual #21                 // Method org/eclipse/jetty/util/thread/Locker$Lock.close:()V
     150: goto          29
     153: aload_0
     154: iconst_1
     155: putfield      #8                  // Field _idle:Z
     158: aload_3
     159: ifnull        434
     162: aload_3
     163: invokevirtual #21                 // Method org/eclipse/jetty/util/thread/Locker$Lock.close:()V
     166: goto          434
     169: aload_0
     170: getfield      #28                 // Field _pending:Z
     173: ifne          197
     176: aload_0
     177: aload_1
     178: invokestatic  #33                 // InterfaceMethod org/eclipse/jetty/util/thread/Invocable.getInvocationType:(Ljava/lang/Object;)Lorg/eclipse/jetty/util/thread/Invocable$InvocationType;
     181: getstatic     #34                 // Field org/eclipse/jetty/util/thread/Invocable$InvocationType.NON_BLOCKING:Lorg/eclipse/jetty/util/thread/Invocable$InvocationType;
     184: if_acmpeq     191
     187: iconst_1
     188: goto          192
     191: iconst_0
     192: dup_x1
     193: putfield      #28                 // Field _pending:Z
     196: istore_2
     197: aload_0
     198: iconst_0
     199: putfield      #20                 // Field _execute:Z
     202: aload_3
     203: ifnull        238
     206: aload_3
     207: invokevirtual #21                 // Method org/eclipse/jetty/util/thread/Locker$Lock.close:()V
     210: goto          238
     213: astore        4
     215: aload_3
     216: ifnull        235
     219: aload_3
     220: invokevirtual #21                 // Method org/eclipse/jetty/util/thread/Locker$Lock.close:()V
     223: goto          235
     226: astore        5
     228: aload         4
     230: aload         5
     232: invokevirtual #23                 // Method java/lang/Throwable.addSuppressed:(Ljava/lang/Throwable;)V
     235: aload         4
     237: athrow
     238: iload_2
     239: ifeq          281
     242: getstatic     #11                 // Field LOG:Lorg/eclipse/jetty/util/log/Logger;
     245: invokeinterface #12,  1           // InterfaceMethod org/eclipse/jetty/util/log/Logger.isDebugEnabled:()Z
     250: ifeq          271
     253: getstatic     #11                 // Field LOG:Lorg/eclipse/jetty/util/log/Logger;
     256: ldc           #35                 // String {} dispatch
     258: iconst_1
     259: anewarray     #14                 // class java/lang/Object
     262: dup
     263: iconst_0
     264: aload_0
     265: aastore
     266: invokeinterface #15,  3           // InterfaceMethod org/eclipse/jetty/util/log/Logger.debug:(Ljava/lang/String;[Ljava/lang/Object;)V
     271: aload_0
     272: getfield      #10                 // Field _executor:Ljava/util/concurrent/Executor;
     275: aload_0
     276: invokeinterface #26,  2           // InterfaceMethod java/util/concurrent/Executor.execute:(Ljava/lang/Runnable;)V
     281: getstatic     #11                 // Field LOG:Lorg/eclipse/jetty/util/log/Logger;
     284: invokeinterface #12,  1           // InterfaceMethod org/eclipse/jetty/util/log/Logger.isDebugEnabled:()Z
     289: ifeq          314
     292: getstatic     #11                 // Field LOG:Lorg/eclipse/jetty/util/log/Logger;
     295: ldc           #36                 // String {} run {}
     297: iconst_2
     298: anewarray     #14                 // class java/lang/Object
     301: dup
     302: iconst_0
     303: aload_0
     304: aastore
     305: dup
     306: iconst_1
     307: aload_1
     308: aastore
     309: invokeinterface #15,  3           // InterfaceMethod org/eclipse/jetty/util/log/Logger.debug:(Ljava/lang/String;[Ljava/lang/Object;)V
     314: aload_1
     315: ifnull        324
     318: aload_1
     319: invokeinterface #37,  1           // InterfaceMethod java/lang/Runnable.run:()V
     324: getstatic     #11                 // Field LOG:Lorg/eclipse/jetty/util/log/Logger;
     327: invokeinterface #12,  1           // InterfaceMethod org/eclipse/jetty/util/log/Logger.isDebugEnabled:()Z
     332: ifeq          357
     335: getstatic     #11                 // Field LOG:Lorg/eclipse/jetty/util/log/Logger;
     338: ldc           #38                 // String {} ran {}
     340: iconst_2
     341: anewarray     #14                 // class java/lang/Object
     344: dup
     345: iconst_0
     346: aload_0
     347: aastore
     348: dup
     349: iconst_1
     350: aload_1
     351: aastore
     352: invokeinterface #15,  3           // InterfaceMethod org/eclipse/jetty/util/log/Logger.debug:(Ljava/lang/String;[Ljava/lang/Object;)V
     357: aload_0
     358: getfield      #4                  // Field _locker:Lorg/eclipse/jetty/util/thread/Locker;
     361: invokevirtual #16                 // Method org/eclipse/jetty/util/thread/Locker.lock:()Lorg/eclipse/jetty/util/thread/Locker$Lock;
     364: astore_3
     365: aload_0
     366: getfield      #17                 // Field _producing:Z
     369: ifne          379
     372: aload_0
     373: getfield      #8                  // Field _idle:Z
     376: ifeq          390
     379: aload_3
     380: ifnull        434
     383: aload_3
     384: invokevirtual #21                 // Method org/eclipse/jetty/util/thread/Locker$Lock.close:()V
     387: goto          434
     390: aload_0
     391: iconst_1
     392: putfield      #17                 // Field _producing:Z
     395: aload_3
     396: ifnull        431
     399: aload_3
     400: invokevirtual #21                 // Method org/eclipse/jetty/util/thread/Locker$Lock.close:()V
     403: goto          431
     406: astore        4
     408: aload_3
     409: ifnull        428
     412: aload_3
     413: invokevirtual #21                 // Method org/eclipse/jetty/util/thread/Locker$Lock.close:()V
     416: goto          428
     419: astore        5
     421: aload         4
     423: aload         5
     425: invokevirtual #23                 // Method java/lang/Throwable.addSuppressed:(Ljava/lang/Throwable;)V
     428: aload         4
     430: athrow
     431: goto          29
     434: getstatic     #11                 // Field LOG:Lorg/eclipse/jetty/util/log/Logger;
     437: invokeinterface #12,  1           // InterfaceMethod org/eclipse/jetty/util/log/Logger.isDebugEnabled:()Z
     442: ifeq          463
     445: getstatic     #11                 // Field LOG:Lorg/eclipse/jetty/util/log/Logger;
     448: ldc           #39                 // String {} produce exit
     450: iconst_1
     451: anewarray     #14                 // class java/lang/Object
     454: dup
     455: iconst_0
     456: aload_0
     457: aastore
     458: invokeinterface #15,  3           // InterfaceMethod org/eclipse/jetty/util/log/Logger.debug:(Ljava/lang/String;[Ljava/lang/Object;)V
     463: return
    Exception table:
       from    to  target type
         111   142   213   Class java/lang/Throwable
         153   158   213   Class java/lang/Throwable
         169   202   213   Class java/lang/Throwable
         219   223   226   Class java/lang/Throwable
         365   379   406   Class java/lang/Throwable
         390   395   406   Class java/lang/Throwable
         412   416   419   Class java/lang/Throwable

  public java.lang.Boolean isIdle();
    Code:
       0: aload_0
       1: getfield      #4                  // Field _locker:Lorg/eclipse/jetty/util/thread/Locker;
       4: invokevirtual #16                 // Method org/eclipse/jetty/util/thread/Locker.lock:()Lorg/eclipse/jetty/util/thread/Locker$Lock;
       7: astore_1
       8: aload_0
       9: getfield      #8                  // Field _idle:Z
      12: invokestatic  #40                 // Method java/lang/Boolean.valueOf:(Z)Ljava/lang/Boolean;
      15: astore_2
      16: aload_1
      17: ifnull        24
      20: aload_1
      21: invokevirtual #21                 // Method org/eclipse/jetty/util/thread/Locker$Lock.close:()V
      24: aload_2
      25: areturn
      26: astore_2
      27: aload_1
      28: ifnull        44
      31: aload_1
      32: invokevirtual #21                 // Method org/eclipse/jetty/util/thread/Locker$Lock.close:()V
      35: goto          44
      38: astore_3
      39: aload_2
      40: aload_3
      41: invokevirtual #23                 // Method java/lang/Throwable.addSuppressed:(Ljava/lang/Throwable;)V
      44: aload_2
      45: athrow
    Exception table:
       from    to  target type
           8    16    26   Class java/lang/Throwable
          31    35    38   Class java/lang/Throwable

  public java.lang.String toString();
    Code:
       0: new           #41                 // class java/lang/StringBuilder
       3: dup
       4: invokespecial #42                 // Method java/lang/StringBuilder."<init>":()V
       7: astore_1
       8: aload_1
       9: ldc           #43                 // String EPC
      11: invokevirtual #44                 // Method java/lang/StringBuilder.append:(Ljava/lang/String;)Ljava/lang/StringBuilder;
      14: pop
      15: aload_0
      16: getfield      #4                  // Field _locker:Lorg/eclipse/jetty/util/thread/Locker;
      19: invokevirtual #16                 // Method org/eclipse/jetty/util/thread/Locker.lock:()Lorg/eclipse/jetty/util/thread/Locker$Lock;
      22: astore_2
      23: aload_1
      24: aload_0
      25: getfield      #8                  // Field _idle:Z
      28: ifeq          36
      31: ldc           #45                 // String Idle/
      33: goto          38
      36: ldc           #46                 // String
      38: invokevirtual #44                 // Method java/lang/StringBuilder.append:(Ljava/lang/String;)Ljava/lang/StringBuilder;
      41: pop
      42: aload_1
      43: aload_0
      44: getfield      #17                 // Field _producing:Z
      47: ifeq          55
      50: ldc           #47                 // String Prod/
      52: goto          57
      55: ldc           #46                 // String
      57: invokevirtual #44                 // Method java/lang/StringBuilder.append:(Ljava/lang/String;)Ljava/lang/StringBuilder;
      60: pop
      61: aload_1
      62: aload_0
      63: getfield      #28                 // Field _pending:Z
      66: ifeq          74
      69: ldc           #48                 // String Pend/
      71: goto          76
      74: ldc           #46                 // String
      76: invokevirtual #44                 // Method java/lang/StringBuilder.append:(Ljava/lang/String;)Ljava/lang/StringBuilder;
      79: pop
      80: aload_1
      81: aload_0
      82: getfield      #20                 // Field _execute:Z
      85: ifeq          93
      88: ldc           #49                 // String Exec/
      90: goto          95
      93: ldc           #46                 // String
      95: invokevirtual #44                 // Method java/lang/StringBuilder.append:(Ljava/lang/String;)Ljava/lang/StringBuilder;
      98: pop
      99: aload_2
     100: ifnull        132
     103: aload_2
     104: invokevirtual #21                 // Method org/eclipse/jetty/util/thread/Locker$Lock.close:()V
     107: goto          132
     110: astore_3
     111: aload_2
     112: ifnull        130
     115: aload_2
     116: invokevirtual #21                 // Method org/eclipse/jetty/util/thread/Locker$Lock.close:()V
     119: goto          130
     122: astore        4
     124: aload_3
     125: aload         4
     127: invokevirtual #23                 // Method java/lang/Throwable.addSuppressed:(Ljava/lang/Throwable;)V
     130: aload_3
     131: athrow
     132: aload_1
     133: aload_0
     134: getfield      #9                  // Field _producer:Lorg/eclipse/jetty/util/thread/ExecutionStrategy$Producer;
     137: invokevirtual #50                 // Method java/lang/StringBuilder.append:(Ljava/lang/Object;)Ljava/lang/StringBuilder;
     140: pop
     141: aload_1
     142: invokevirtual #51                 // Method java/lang/StringBuilder.toString:()Ljava/lang/String;
     145: areturn
    Exception table:
       from    to  target type
          23    99   110   Class java/lang/Throwable
         115   119   122   Class java/lang/Throwable

  static {};
    Code:
       0: ldc           #52                 // class org/eclipse/jetty/util/thread/strategy/ExecuteProduceConsume
       2: invokestatic  #53                 // Method org/eclipse/jetty/util/log/Log.getLogger:(Ljava/lang/Class;)Lorg/eclipse/jetty/util/log/Logger;
       5: putstatic     #11                 // Field LOG:Lorg/eclipse/jetty/util/log/Logger;
       8: return
}
