Compiled from "AddAzureDiskVolumeDecorator.java"
public class io.dekorate.kubernetes.decorator.AddAzureDiskVolumeDecorator extends io.dekorate.kubernetes.decorator.Decorator<io.dekorate.deps.kubernetes.api.model.PodSpecBuilder> {
  private final io.dekorate.kubernetes.config.AzureDiskVolume volume;

  public io.dekorate.kubernetes.decorator.AddAzureDiskVolumeDecorator(io.dekorate.kubernetes.config.AzureDiskVolume);
    Code:
       0: aload_0
       1: invokespecial #1                  // Method io/dekorate/kubernetes/decorator/Decorator."<init>":()V
       4: aload_0
       5: aload_1
       6: putfield      #2                  // Field volume:Lio/dekorate/kubernetes/config/AzureDiskVolume;
       9: return

  public void visit(io.dekorate.deps.kubernetes.api.model.PodSpecBuilder);
    Code:
       0: aload_1
       1: invokevirtual #3                  // Method io/dekorate/deps/kubernetes/api/model/PodSpecBuilder.addNewVolume:()Lio/dekorate/deps/kubernetes/api/model/PodSpecFluent$VolumesNested;
       4: aload_0
       5: getfield      #2                  // Field volume:Lio/dekorate/kubernetes/config/AzureDiskVolume;
       8: invokevirtual #4                  // Method io/dekorate/kubernetes/config/AzureDiskVolume.getVolumeName:()Ljava/lang/String;
      11: invokeinterface #5,  2            // InterfaceMethod io/dekorate/deps/kubernetes/api/model/PodSpecFluent$VolumesNested.withName:(Ljava/lang/String;)Lio/dekorate/deps/kubernetes/api/model/VolumeFluent;
      16: checkcast     #6                  // class io/dekorate/deps/kubernetes/api/model/PodSpecFluent$VolumesNested
      19: invokeinterface #7,  1            // InterfaceMethod io/dekorate/deps/kubernetes/api/model/PodSpecFluent$VolumesNested.withNewAzureDisk:()Lio/dekorate/deps/kubernetes/api/model/VolumeFluent$AzureDiskNested;
      24: aload_0
      25: getfield      #2                  // Field volume:Lio/dekorate/kubernetes/config/AzureDiskVolume;
      28: invokevirtual #8                  // Method io/dekorate/kubernetes/config/AzureDiskVolume.getKind:()Ljava/lang/String;
      31: invokeinterface #9,  2            // InterfaceMethod io/dekorate/deps/kubernetes/api/model/VolumeFluent$AzureDiskNested.withKind:(Ljava/lang/String;)Lio/dekorate/deps/kubernetes/api/model/AzureDiskVolumeSourceFluent;
      36: checkcast     #10                 // class io/dekorate/deps/kubernetes/api/model/VolumeFluent$AzureDiskNested
      39: aload_0
      40: getfield      #2                  // Field volume:Lio/dekorate/kubernetes/config/AzureDiskVolume;
      43: invokevirtual #11                 // Method io/dekorate/kubernetes/config/AzureDiskVolume.getDiskName:()Ljava/lang/String;
      46: invokeinterface #12,  2           // InterfaceMethod io/dekorate/deps/kubernetes/api/model/VolumeFluent$AzureDiskNested.withDiskName:(Ljava/lang/String;)Lio/dekorate/deps/kubernetes/api/model/AzureDiskVolumeSourceFluent;
      51: checkcast     #10                 // class io/dekorate/deps/kubernetes/api/model/VolumeFluent$AzureDiskNested
      54: aload_0
      55: getfield      #2                  // Field volume:Lio/dekorate/kubernetes/config/AzureDiskVolume;
      58: invokevirtual #13                 // Method io/dekorate/kubernetes/config/AzureDiskVolume.getDiskURI:()Ljava/lang/String;
      61: invokeinterface #14,  2           // InterfaceMethod io/dekorate/deps/kubernetes/api/model/VolumeFluent$AzureDiskNested.withDiskURI:(Ljava/lang/String;)Lio/dekorate/deps/kubernetes/api/model/AzureDiskVolumeSourceFluent;
      66: checkcast     #10                 // class io/dekorate/deps/kubernetes/api/model/VolumeFluent$AzureDiskNested
      69: aload_0
      70: getfield      #2                  // Field volume:Lio/dekorate/kubernetes/config/AzureDiskVolume;
      73: invokevirtual #15                 // Method io/dekorate/kubernetes/config/AzureDiskVolume.getFsType:()Ljava/lang/String;
      76: invokeinterface #16,  2           // InterfaceMethod io/dekorate/deps/kubernetes/api/model/VolumeFluent$AzureDiskNested.withFsType:(Ljava/lang/String;)Lio/dekorate/deps/kubernetes/api/model/AzureDiskVolumeSourceFluent;
      81: checkcast     #10                 // class io/dekorate/deps/kubernetes/api/model/VolumeFluent$AzureDiskNested
      84: aload_0
      85: getfield      #2                  // Field volume:Lio/dekorate/kubernetes/config/AzureDiskVolume;
      88: invokevirtual #17                 // Method io/dekorate/kubernetes/config/AzureDiskVolume.getCachingMode:()Ljava/lang/String;
      91: invokeinterface #18,  2           // InterfaceMethod io/dekorate/deps/kubernetes/api/model/VolumeFluent$AzureDiskNested.withCachingMode:(Ljava/lang/String;)Lio/dekorate/deps/kubernetes/api/model/AzureDiskVolumeSourceFluent;
      96: checkcast     #10                 // class io/dekorate/deps/kubernetes/api/model/VolumeFluent$AzureDiskNested
      99: aload_0
     100: getfield      #2                  // Field volume:Lio/dekorate/kubernetes/config/AzureDiskVolume;
     103: invokevirtual #19                 // Method io/dekorate/kubernetes/config/AzureDiskVolume.isReadOnly:()Z
     106: invokestatic  #20                 // Method java/lang/Boolean.valueOf:(Z)Ljava/lang/Boolean;
     109: invokeinterface #21,  2           // InterfaceMethod io/dekorate/deps/kubernetes/api/model/VolumeFluent$AzureDiskNested.withReadOnly:(Ljava/lang/Boolean;)Lio/dekorate/deps/kubernetes/api/model/AzureDiskVolumeSourceFluent;
     114: checkcast     #10                 // class io/dekorate/deps/kubernetes/api/model/VolumeFluent$AzureDiskNested
     117: invokeinterface #22,  1           // InterfaceMethod io/dekorate/deps/kubernetes/api/model/VolumeFluent$AzureDiskNested.endAzureDisk:()Ljava/lang/Object;
     122: checkcast     #6                  // class io/dekorate/deps/kubernetes/api/model/PodSpecFluent$VolumesNested
     125: invokeinterface #23,  1           // InterfaceMethod io/dekorate/deps/kubernetes/api/model/PodSpecFluent$VolumesNested.endVolume:()Ljava/lang/Object;
     130: pop
     131: return

  public void visit(java.lang.Object);
    Code:
       0: aload_0
       1: aload_1
       2: checkcast     #24                 // class io/dekorate/deps/kubernetes/api/model/PodSpecBuilder
       5: invokevirtual #25                 // Method visit:(Lio/dekorate/deps/kubernetes/api/model/PodSpecBuilder;)V
       8: return
}
