Compiled from "NamedResourceDecorator.java"
public abstract class io.dekorate.kubernetes.decorator.NamedResourceDecorator<T> extends io.dekorate.kubernetes.decorator.Decorator<io.dekorate.deps.kubernetes.api.builder.VisitableBuilder> {
  public static final java.lang.String ANY;

  protected final java.lang.String name;

  private final io.dekorate.kubernetes.decorator.NamedResourceDecorator<T>.ResourceVisitor visitor;

  public io.dekorate.kubernetes.decorator.NamedResourceDecorator();
    Code:
       0: aload_0
       1: getstatic     #1                  // Field ANY:Ljava/lang/String;
       4: invokespecial #2                  // Method "<init>":(Ljava/lang/String;)V
       7: return

  public io.dekorate.kubernetes.decorator.NamedResourceDecorator(java.lang.String);
    Code:
       0: aload_0
       1: invokespecial #3                  // Method io/dekorate/kubernetes/decorator/Decorator."<init>":()V
       4: aload_0
       5: new           #4                  // class io/dekorate/kubernetes/decorator/NamedResourceDecorator$ResourceVisitor
       8: dup
       9: aload_0
      10: aconst_null
      11: invokespecial #5                  // Method io/dekorate/kubernetes/decorator/NamedResourceDecorator$ResourceVisitor."<init>":(Lio/dekorate/kubernetes/decorator/NamedResourceDecorator;Lio/dekorate/deps/kubernetes/api/model/ObjectMeta;)V
      14: putfield      #6                  // Field visitor:Lio/dekorate/kubernetes/decorator/NamedResourceDecorator$ResourceVisitor;
      17: aload_0
      18: aload_1
      19: putfield      #7                  // Field name:Ljava/lang/String;
      22: return

  public void visit(io.dekorate.deps.kubernetes.api.builder.VisitableBuilder);
    Code:
       0: aload_1
       1: invokestatic  #8                  // Method io/dekorate/utils/Metadata.getMetadata:(Lio/dekorate/deps/kubernetes/api/builder/Builder;)Ljava/util/Optional;
       4: astore_2
       5: aload_2
       6: invokevirtual #9                  // Method java/util/Optional.isPresent:()Z
       9: ifne          13
      12: return
      13: aload_0
      14: getfield      #7                  // Field name:Ljava/lang/String;
      17: invokestatic  #10                 // Method io/dekorate/utils/Strings.isNullOrEmpty:(Ljava/lang/String;)Z
      20: ifeq          47
      23: aload_1
      24: aload_0
      25: getfield      #6                  // Field visitor:Lio/dekorate/kubernetes/decorator/NamedResourceDecorator$ResourceVisitor;
      28: aload_2
      29: invokevirtual #11                 // Method java/util/Optional.get:()Ljava/lang/Object;
      32: checkcast     #12                 // class io/dekorate/deps/kubernetes/api/model/ObjectMeta
      35: invokevirtual #13                 // Method io/dekorate/kubernetes/decorator/NamedResourceDecorator$ResourceVisitor.withMetadata:(Lio/dekorate/deps/kubernetes/api/model/ObjectMeta;)Lio/dekorate/kubernetes/decorator/NamedResourceDecorator$ResourceVisitor;
      38: invokeinterface #14,  2           // InterfaceMethod io/dekorate/deps/kubernetes/api/builder/VisitableBuilder.accept:(Lio/dekorate/deps/kubernetes/api/builder/Visitor;)Ljava/lang/Object;
      43: pop
      44: goto          92
      47: aload_2
      48: invokedynamic #15,  0             // InvokeDynamic #0:apply:()Ljava/util/function/Function;
      53: invokevirtual #16                 // Method java/util/Optional.map:(Ljava/util/function/Function;)Ljava/util/Optional;
      56: aload_0
      57: invokedynamic #17,  0             // InvokeDynamic #1:test:(Lio/dekorate/kubernetes/decorator/NamedResourceDecorator;)Ljava/util/function/Predicate;
      62: invokevirtual #18                 // Method java/util/Optional.filter:(Ljava/util/function/Predicate;)Ljava/util/Optional;
      65: invokevirtual #9                  // Method java/util/Optional.isPresent:()Z
      68: ifeq          92
      71: aload_1
      72: aload_0
      73: getfield      #6                  // Field visitor:Lio/dekorate/kubernetes/decorator/NamedResourceDecorator$ResourceVisitor;
      76: aload_2
      77: invokevirtual #11                 // Method java/util/Optional.get:()Ljava/lang/Object;
      80: checkcast     #12                 // class io/dekorate/deps/kubernetes/api/model/ObjectMeta
      83: invokevirtual #13                 // Method io/dekorate/kubernetes/decorator/NamedResourceDecorator$ResourceVisitor.withMetadata:(Lio/dekorate/deps/kubernetes/api/model/ObjectMeta;)Lio/dekorate/kubernetes/decorator/NamedResourceDecorator$ResourceVisitor;
      86: invokeinterface #14,  2           // InterfaceMethod io/dekorate/deps/kubernetes/api/builder/VisitableBuilder.accept:(Lio/dekorate/deps/kubernetes/api/builder/Visitor;)Ljava/lang/Object;
      91: pop
      92: return

  public abstract void andThenVisit(T, io.dekorate.deps.kubernetes.api.model.ObjectMeta);

  public void visit(java.lang.Object);
    Code:
       0: aload_0
       1: aload_1
       2: checkcast     #19                 // class io/dekorate/deps/kubernetes/api/builder/VisitableBuilder
       5: invokevirtual #20                 // Method visit:(Lio/dekorate/deps/kubernetes/api/builder/VisitableBuilder;)V
       8: return

  private boolean lambda$visit$1(java.lang.String);
    Code:
       0: aload_1
       1: aload_0
       2: getfield      #7                  // Field name:Ljava/lang/String;
       5: invokevirtual #21                 // Method java/lang/String.equals:(Ljava/lang/Object;)Z
       8: ireturn

  private static java.lang.String lambda$visit$0(io.dekorate.deps.kubernetes.api.model.ObjectMeta);
    Code:
       0: aload_0
       1: invokevirtual #22                 // Method io/dekorate/deps/kubernetes/api/model/ObjectMeta.getName:()Ljava/lang/String;
       4: areturn

  static {};
    Code:
       0: aconst_null
       1: putstatic     #1                  // Field ANY:Ljava/lang/String;
       4: return
}
