Compiled from "Saml2RelyingPartyProperties.java"
public class org.springframework.boot.autoconfigure.security.saml2.Saml2RelyingPartyProperties$Identityprovider$Singlesignon {
  private java.lang.String url;

  private org.springframework.security.saml2.provider.service.registration.Saml2MessageBinding binding;

  private boolean signRequest;

  public org.springframework.boot.autoconfigure.security.saml2.Saml2RelyingPartyProperties$Identityprovider$Singlesignon();
    Code:
       0: aload_0
       1: invokespecial #1                  // Method java/lang/Object."<init>":()V
       4: aload_0
       5: getstatic     #2                  // Field org/springframework/security/saml2/provider/service/registration/Saml2MessageBinding.REDIRECT:Lorg/springframework/security/saml2/provider/service/registration/Saml2MessageBinding;
       8: putfield      #3                  // Field binding:Lorg/springframework/security/saml2/provider/service/registration/Saml2MessageBinding;
      11: aload_0
      12: iconst_1
      13: putfield      #4                  // Field signRequest:Z
      16: return

  public java.lang.String getUrl();
    Code:
       0: aload_0
       1: getfield      #5                  // Field url:Ljava/lang/String;
       4: areturn

  public void setUrl(java.lang.String);
    Code:
       0: aload_0
       1: aload_1
       2: putfield      #5                  // Field url:Ljava/lang/String;
       5: return

  public org.springframework.security.saml2.provider.service.registration.Saml2MessageBinding getBinding();
    Code:
       0: aload_0
       1: getfield      #3                  // Field binding:Lorg/springframework/security/saml2/provider/service/registration/Saml2MessageBinding;
       4: areturn

  public void setBinding(org.springframework.security.saml2.provider.service.registration.Saml2MessageBinding);
    Code:
       0: aload_0
       1: aload_1
       2: putfield      #3                  // Field binding:Lorg/springframework/security/saml2/provider/service/registration/Saml2MessageBinding;
       5: return

  public boolean isSignRequest();
    Code:
       0: aload_0
       1: getfield      #4                  // Field signRequest:Z
       4: ireturn

  public void setSignRequest(boolean);
    Code:
       0: aload_0
       1: iload_1
       2: putfield      #4                  // Field signRequest:Z
       5: return
}
