Compiled from "WebEngineContext.java"
final class org.thymeleaf.context.WebEngineContext$RequestParametersMap extends org.thymeleaf.context.WebEngineContext$NoOpMapImpl {
  private final javax.servlet.http.HttpServletRequest request;

  org.thymeleaf.context.WebEngineContext$RequestParametersMap(javax.servlet.http.HttpServletRequest);
    Code:
       0: aload_0
       1: invokespecial #1                  // Method org/thymeleaf/context/WebEngineContext$NoOpMapImpl."<init>":()V
       4: aload_0
       5: aload_1
       6: putfield      #2                  // Field request:Ljavax/servlet/http/HttpServletRequest;
       9: return

  public int size();
    Code:
       0: aload_0
       1: getfield      #2                  // Field request:Ljavax/servlet/http/HttpServletRequest;
       4: invokeinterface #3,  1            // InterfaceMethod javax/servlet/http/HttpServletRequest.getParameterMap:()Ljava/util/Map;
       9: invokeinterface #4,  1            // InterfaceMethod java/util/Map.size:()I
      14: ireturn

  public boolean isEmpty();
    Code:
       0: aload_0
       1: getfield      #2                  // Field request:Ljavax/servlet/http/HttpServletRequest;
       4: invokeinterface #3,  1            // InterfaceMethod javax/servlet/http/HttpServletRequest.getParameterMap:()Ljava/util/Map;
       9: invokeinterface #5,  1            // InterfaceMethod java/util/Map.isEmpty:()Z
      14: ireturn

  public boolean containsKey(java.lang.Object);
    Code:
       0: iconst_1
       1: ireturn

  public boolean containsValue(java.lang.Object);
    Code:
       0: new           #6                  // class java/lang/UnsupportedOperationException
       3: dup
       4: ldc           #7                  // String Map does not support #containsValue()
       6: invokespecial #8                  // Method java/lang/UnsupportedOperationException."<init>":(Ljava/lang/String;)V
       9: athrow

  public java.lang.Object get(java.lang.Object);
    Code:
       0: aload_0
       1: getfield      #2                  // Field request:Ljavax/servlet/http/HttpServletRequest;
       4: aload_1
       5: ifnull        15
       8: aload_1
       9: invokevirtual #9                  // Method java/lang/Object.toString:()Ljava/lang/String;
      12: goto          16
      15: aconst_null
      16: invokeinterface #10,  2           // InterfaceMethod javax/servlet/http/HttpServletRequest.getParameterValues:(Ljava/lang/String;)[Ljava/lang/String;
      21: astore_2
      22: aload_2
      23: ifnonnull     28
      26: aconst_null
      27: areturn
      28: new           #11                 // class org/thymeleaf/context/WebEngineContext$RequestParameterValues
      31: dup
      32: aload_2
      33: invokespecial #12                 // Method org/thymeleaf/context/WebEngineContext$RequestParameterValues."<init>":([Ljava/lang/String;)V
      36: areturn

  public java.util.Set<java.lang.String> keySet();
    Code:
       0: aload_0
       1: getfield      #2                  // Field request:Ljavax/servlet/http/HttpServletRequest;
       4: invokeinterface #3,  1            // InterfaceMethod javax/servlet/http/HttpServletRequest.getParameterMap:()Ljava/util/Map;
       9: invokeinterface #13,  1           // InterfaceMethod java/util/Map.keySet:()Ljava/util/Set;
      14: areturn

  public java.util.Collection<java.lang.Object> values();
    Code:
       0: aload_0
       1: getfield      #2                  // Field request:Ljavax/servlet/http/HttpServletRequest;
       4: invokeinterface #3,  1            // InterfaceMethod javax/servlet/http/HttpServletRequest.getParameterMap:()Ljava/util/Map;
       9: invokeinterface #14,  1           // InterfaceMethod java/util/Map.values:()Ljava/util/Collection;
      14: areturn

  public java.util.Set<java.util.Map$Entry<java.lang.String, java.lang.Object>> entrySet();
    Code:
       0: aload_0
       1: getfield      #2                  // Field request:Ljavax/servlet/http/HttpServletRequest;
       4: invokeinterface #3,  1            // InterfaceMethod javax/servlet/http/HttpServletRequest.getParameterMap:()Ljava/util/Map;
       9: invokeinterface #15,  1           // InterfaceMethod java/util/Map.entrySet:()Ljava/util/Set;
      14: areturn
}
