Compiled from "JsonProperty.java"
public final class io.dekorate.deps.jackson.annotation.JsonProperty$Access extends java.lang.Enum<io.dekorate.deps.jackson.annotation.JsonProperty$Access> {
  public static final io.dekorate.deps.jackson.annotation.JsonProperty$Access AUTO;

  public static final io.dekorate.deps.jackson.annotation.JsonProperty$Access READ_ONLY;

  public static final io.dekorate.deps.jackson.annotation.JsonProperty$Access WRITE_ONLY;

  public static final io.dekorate.deps.jackson.annotation.JsonProperty$Access READ_WRITE;

  private static final io.dekorate.deps.jackson.annotation.JsonProperty$Access[] $VALUES;

  public static io.dekorate.deps.jackson.annotation.JsonProperty$Access[] values();
    Code:
       0: getstatic     #20                 // Field $VALUES:[Lio/dekorate/deps/jackson/annotation/JsonProperty$Access;
       3: invokevirtual #25                 // Method "[Lio/dekorate/deps/jackson/annotation/JsonProperty$Access;".clone:()Ljava/lang/Object;
       6: checkcast     #21                 // class "[Lio/dekorate/deps/jackson/annotation/JsonProperty$Access;"
       9: areturn

  public static io.dekorate.deps.jackson.annotation.JsonProperty$Access valueOf(java.lang.String);
    Code:
       0: ldc           #2                  // class io/dekorate/deps/jackson/annotation/JsonProperty$Access
       2: aload_0
       3: invokestatic  #30                 // Method java/lang/Enum.valueOf:(Ljava/lang/Class;Ljava/lang/String;)Ljava/lang/Enum;
       6: checkcast     #2                  // class io/dekorate/deps/jackson/annotation/JsonProperty$Access
       9: areturn

  private io.dekorate.deps.jackson.annotation.JsonProperty$Access();
    Code:
       0: aload_0
       1: aload_1
       2: iload_2
       3: invokespecial #37                 // Method java/lang/Enum."<init>":(Ljava/lang/String;I)V
       6: return

  static {};
    Code:
       0: new           #2                  // class io/dekorate/deps/jackson/annotation/JsonProperty$Access
       3: dup
       4: ldc           #40                 // String AUTO
       6: iconst_0
       7: invokespecial #41                 // Method "<init>":(Ljava/lang/String;I)V
      10: putstatic     #43                 // Field AUTO:Lio/dekorate/deps/jackson/annotation/JsonProperty$Access;
      13: new           #2                  // class io/dekorate/deps/jackson/annotation/JsonProperty$Access
      16: dup
      17: ldc           #44                 // String READ_ONLY
      19: iconst_1
      20: invokespecial #41                 // Method "<init>":(Ljava/lang/String;I)V
      23: putstatic     #46                 // Field READ_ONLY:Lio/dekorate/deps/jackson/annotation/JsonProperty$Access;
      26: new           #2                  // class io/dekorate/deps/jackson/annotation/JsonProperty$Access
      29: dup
      30: ldc           #47                 // String WRITE_ONLY
      32: iconst_2
      33: invokespecial #41                 // Method "<init>":(Ljava/lang/String;I)V
      36: putstatic     #49                 // Field WRITE_ONLY:Lio/dekorate/deps/jackson/annotation/JsonProperty$Access;
      39: new           #2                  // class io/dekorate/deps/jackson/annotation/JsonProperty$Access
      42: dup
      43: ldc           #50                 // String READ_WRITE
      45: iconst_3
      46: invokespecial #41                 // Method "<init>":(Ljava/lang/String;I)V
      49: putstatic     #52                 // Field READ_WRITE:Lio/dekorate/deps/jackson/annotation/JsonProperty$Access;
      52: iconst_4
      53: anewarray     #2                  // class io/dekorate/deps/jackson/annotation/JsonProperty$Access
      56: dup
      57: iconst_0
      58: getstatic     #43                 // Field AUTO:Lio/dekorate/deps/jackson/annotation/JsonProperty$Access;
      61: aastore
      62: dup
      63: iconst_1
      64: getstatic     #46                 // Field READ_ONLY:Lio/dekorate/deps/jackson/annotation/JsonProperty$Access;
      67: aastore
      68: dup
      69: iconst_2
      70: getstatic     #49                 // Field WRITE_ONLY:Lio/dekorate/deps/jackson/annotation/JsonProperty$Access;
      73: aastore
      74: dup
      75: iconst_3
      76: getstatic     #52                 // Field READ_WRITE:Lio/dekorate/deps/jackson/annotation/JsonProperty$Access;
      79: aastore
      80: putstatic     #20                 // Field $VALUES:[Lio/dekorate/deps/jackson/annotation/JsonProperty$Access;
      83: return
}
