Compiled from "TradeBankModel.java"
public class app.cybrid.cybrid_api_bank.client.model.TradeBankModel {
  public static final java.lang.String JSON_PROPERTY_GUID;

  private java.lang.String guid;

  public static final java.lang.String JSON_PROPERTY_CUSTOMER_GUID;

  private java.lang.String customerGuid;

  public static final java.lang.String JSON_PROPERTY_QUOTE_GUID;

  private java.lang.String quoteGuid;

  public static final java.lang.String JSON_PROPERTY_SYMBOL;

  private java.lang.String symbol;

  public static final java.lang.String JSON_PROPERTY_SIDE;

  private app.cybrid.cybrid_api_bank.client.model.TradeBankModel$SideEnum side;

  public static final java.lang.String JSON_PROPERTY_STATE;

  private app.cybrid.cybrid_api_bank.client.model.TradeBankModel$StateEnum state;

  public static final java.lang.String JSON_PROPERTY_FAILURE_CODE;

  private java.lang.String failureCode;

  public static final java.lang.String JSON_PROPERTY_RECEIVE_AMOUNT;

  private java.math.BigInteger receiveAmount;

  public static final java.lang.String JSON_PROPERTY_DELIVER_AMOUNT;

  private java.math.BigInteger deliverAmount;

  public static final java.lang.String JSON_PROPERTY_FEE;

  private java.math.BigInteger fee;

  public static final java.lang.String JSON_PROPERTY_CREATED_AT;

  private java.time.OffsetDateTime createdAt;

  public static final java.lang.String JSON_PROPERTY_UPDATED_AT;

  private java.time.OffsetDateTime updatedAt;

  public app.cybrid.cybrid_api_bank.client.model.TradeBankModel();
    Code:
       0: aload_0
       1: invokespecial #1                  // Method java/lang/Object."<init>":()V
       4: return

  public app.cybrid.cybrid_api_bank.client.model.TradeBankModel guid(java.lang.String);
    Code:
       0: aload_0
       1: aload_1
       2: putfield      #2                  // Field guid:Ljava/lang/String;
       5: aload_0
       6: areturn

  public java.lang.String getGuid();
    Code:
       0: aload_0
       1: getfield      #2                  // Field guid:Ljava/lang/String;
       4: areturn

  public void setGuid(java.lang.String);
    Code:
       0: aload_0
       1: aload_1
       2: putfield      #2                  // Field guid:Ljava/lang/String;
       5: return

  public app.cybrid.cybrid_api_bank.client.model.TradeBankModel customerGuid(java.lang.String);
    Code:
       0: aload_0
       1: aload_1
       2: putfield      #3                  // Field customerGuid:Ljava/lang/String;
       5: aload_0
       6: areturn

  public java.lang.String getCustomerGuid();
    Code:
       0: aload_0
       1: getfield      #3                  // Field customerGuid:Ljava/lang/String;
       4: areturn

  public void setCustomerGuid(java.lang.String);
    Code:
       0: aload_0
       1: aload_1
       2: putfield      #3                  // Field customerGuid:Ljava/lang/String;
       5: return

  public app.cybrid.cybrid_api_bank.client.model.TradeBankModel quoteGuid(java.lang.String);
    Code:
       0: aload_0
       1: aload_1
       2: putfield      #4                  // Field quoteGuid:Ljava/lang/String;
       5: aload_0
       6: areturn

  public java.lang.String getQuoteGuid();
    Code:
       0: aload_0
       1: getfield      #4                  // Field quoteGuid:Ljava/lang/String;
       4: areturn

  public void setQuoteGuid(java.lang.String);
    Code:
       0: aload_0
       1: aload_1
       2: putfield      #4                  // Field quoteGuid:Ljava/lang/String;
       5: return

  public app.cybrid.cybrid_api_bank.client.model.TradeBankModel symbol(java.lang.String);
    Code:
       0: aload_0
       1: aload_1
       2: putfield      #5                  // Field symbol:Ljava/lang/String;
       5: aload_0
       6: areturn

  public java.lang.String getSymbol();
    Code:
       0: aload_0
       1: getfield      #5                  // Field symbol:Ljava/lang/String;
       4: areturn

  public void setSymbol(java.lang.String);
    Code:
       0: aload_0
       1: aload_1
       2: putfield      #5                  // Field symbol:Ljava/lang/String;
       5: return

  public app.cybrid.cybrid_api_bank.client.model.TradeBankModel side(app.cybrid.cybrid_api_bank.client.model.TradeBankModel$SideEnum);
    Code:
       0: aload_0
       1: aload_1
       2: putfield      #6                  // Field side:Lapp/cybrid/cybrid_api_bank/client/model/TradeBankModel$SideEnum;
       5: aload_0
       6: areturn

  public app.cybrid.cybrid_api_bank.client.model.TradeBankModel$SideEnum getSide();
    Code:
       0: aload_0
       1: getfield      #6                  // Field side:Lapp/cybrid/cybrid_api_bank/client/model/TradeBankModel$SideEnum;
       4: areturn

  public void setSide(app.cybrid.cybrid_api_bank.client.model.TradeBankModel$SideEnum);
    Code:
       0: aload_0
       1: aload_1
       2: putfield      #6                  // Field side:Lapp/cybrid/cybrid_api_bank/client/model/TradeBankModel$SideEnum;
       5: return

  public app.cybrid.cybrid_api_bank.client.model.TradeBankModel state(app.cybrid.cybrid_api_bank.client.model.TradeBankModel$StateEnum);
    Code:
       0: aload_0
       1: aload_1
       2: putfield      #7                  // Field state:Lapp/cybrid/cybrid_api_bank/client/model/TradeBankModel$StateEnum;
       5: aload_0
       6: areturn

  public app.cybrid.cybrid_api_bank.client.model.TradeBankModel$StateEnum getState();
    Code:
       0: aload_0
       1: getfield      #7                  // Field state:Lapp/cybrid/cybrid_api_bank/client/model/TradeBankModel$StateEnum;
       4: areturn

  public void setState(app.cybrid.cybrid_api_bank.client.model.TradeBankModel$StateEnum);
    Code:
       0: aload_0
       1: aload_1
       2: putfield      #7                  // Field state:Lapp/cybrid/cybrid_api_bank/client/model/TradeBankModel$StateEnum;
       5: return

  public app.cybrid.cybrid_api_bank.client.model.TradeBankModel failureCode(java.lang.String);
    Code:
       0: aload_0
       1: aload_1
       2: putfield      #8                  // Field failureCode:Ljava/lang/String;
       5: aload_0
       6: areturn

  public java.lang.String getFailureCode();
    Code:
       0: aload_0
       1: getfield      #8                  // Field failureCode:Ljava/lang/String;
       4: areturn

  public void setFailureCode(java.lang.String);
    Code:
       0: aload_0
       1: aload_1
       2: putfield      #8                  // Field failureCode:Ljava/lang/String;
       5: return

  public app.cybrid.cybrid_api_bank.client.model.TradeBankModel receiveAmount(java.math.BigInteger);
    Code:
       0: aload_0
       1: aload_1
       2: putfield      #9                  // Field receiveAmount:Ljava/math/BigInteger;
       5: aload_0
       6: areturn

  public java.math.BigInteger getReceiveAmount();
    Code:
       0: aload_0
       1: getfield      #9                  // Field receiveAmount:Ljava/math/BigInteger;
       4: areturn

  public void setReceiveAmount(java.math.BigInteger);
    Code:
       0: aload_0
       1: aload_1
       2: putfield      #9                  // Field receiveAmount:Ljava/math/BigInteger;
       5: return

  public app.cybrid.cybrid_api_bank.client.model.TradeBankModel deliverAmount(java.math.BigInteger);
    Code:
       0: aload_0
       1: aload_1
       2: putfield      #10                 // Field deliverAmount:Ljava/math/BigInteger;
       5: aload_0
       6: areturn

  public java.math.BigInteger getDeliverAmount();
    Code:
       0: aload_0
       1: getfield      #10                 // Field deliverAmount:Ljava/math/BigInteger;
       4: areturn

  public void setDeliverAmount(java.math.BigInteger);
    Code:
       0: aload_0
       1: aload_1
       2: putfield      #10                 // Field deliverAmount:Ljava/math/BigInteger;
       5: return

  public app.cybrid.cybrid_api_bank.client.model.TradeBankModel fee(java.math.BigInteger);
    Code:
       0: aload_0
       1: aload_1
       2: putfield      #11                 // Field fee:Ljava/math/BigInteger;
       5: aload_0
       6: areturn

  public java.math.BigInteger getFee();
    Code:
       0: aload_0
       1: getfield      #11                 // Field fee:Ljava/math/BigInteger;
       4: areturn

  public void setFee(java.math.BigInteger);
    Code:
       0: aload_0
       1: aload_1
       2: putfield      #11                 // Field fee:Ljava/math/BigInteger;
       5: return

  public app.cybrid.cybrid_api_bank.client.model.TradeBankModel createdAt(java.time.OffsetDateTime);
    Code:
       0: aload_0
       1: aload_1
       2: putfield      #12                 // Field createdAt:Ljava/time/OffsetDateTime;
       5: aload_0
       6: areturn

  public java.time.OffsetDateTime getCreatedAt();
    Code:
       0: aload_0
       1: getfield      #12                 // Field createdAt:Ljava/time/OffsetDateTime;
       4: areturn

  public void setCreatedAt(java.time.OffsetDateTime);
    Code:
       0: aload_0
       1: aload_1
       2: putfield      #12                 // Field createdAt:Ljava/time/OffsetDateTime;
       5: return

  public app.cybrid.cybrid_api_bank.client.model.TradeBankModel updatedAt(java.time.OffsetDateTime);
    Code:
       0: aload_0
       1: aload_1
       2: putfield      #13                 // Field updatedAt:Ljava/time/OffsetDateTime;
       5: aload_0
       6: areturn

  public java.time.OffsetDateTime getUpdatedAt();
    Code:
       0: aload_0
       1: getfield      #13                 // Field updatedAt:Ljava/time/OffsetDateTime;
       4: areturn

  public void setUpdatedAt(java.time.OffsetDateTime);
    Code:
       0: aload_0
       1: aload_1
       2: putfield      #13                 // Field updatedAt:Ljava/time/OffsetDateTime;
       5: return

  public boolean equals(java.lang.Object);
    Code:
       0: aload_0
       1: aload_1
       2: if_acmpne     7
       5: iconst_1
       6: ireturn
       7: aload_1
       8: ifnull        22
      11: aload_0
      12: invokevirtual #14                 // Method java/lang/Object.getClass:()Ljava/lang/Class;
      15: aload_1
      16: invokevirtual #14                 // Method java/lang/Object.getClass:()Ljava/lang/Class;
      19: if_acmpeq     24
      22: iconst_0
      23: ireturn
      24: aload_1
      25: checkcast     #15                 // class app/cybrid/cybrid_api_bank/client/model/TradeBankModel
      28: astore_2
      29: aload_0
      30: getfield      #2                  // Field guid:Ljava/lang/String;
      33: aload_2
      34: getfield      #2                  // Field guid:Ljava/lang/String;
      37: invokestatic  #16                 // Method java/util/Objects.equals:(Ljava/lang/Object;Ljava/lang/Object;)Z
      40: ifeq          201
      43: aload_0
      44: getfield      #3                  // Field customerGuid:Ljava/lang/String;
      47: aload_2
      48: getfield      #3                  // Field customerGuid:Ljava/lang/String;
      51: invokestatic  #16                 // Method java/util/Objects.equals:(Ljava/lang/Object;Ljava/lang/Object;)Z
      54: ifeq          201
      57: aload_0
      58: getfield      #4                  // Field quoteGuid:Ljava/lang/String;
      61: aload_2
      62: getfield      #4                  // Field quoteGuid:Ljava/lang/String;
      65: invokestatic  #16                 // Method java/util/Objects.equals:(Ljava/lang/Object;Ljava/lang/Object;)Z
      68: ifeq          201
      71: aload_0
      72: getfield      #5                  // Field symbol:Ljava/lang/String;
      75: aload_2
      76: getfield      #5                  // Field symbol:Ljava/lang/String;
      79: invokestatic  #16                 // Method java/util/Objects.equals:(Ljava/lang/Object;Ljava/lang/Object;)Z
      82: ifeq          201
      85: aload_0
      86: getfield      #6                  // Field side:Lapp/cybrid/cybrid_api_bank/client/model/TradeBankModel$SideEnum;
      89: aload_2
      90: getfield      #6                  // Field side:Lapp/cybrid/cybrid_api_bank/client/model/TradeBankModel$SideEnum;
      93: invokestatic  #16                 // Method java/util/Objects.equals:(Ljava/lang/Object;Ljava/lang/Object;)Z
      96: ifeq          201
      99: aload_0
     100: getfield      #7                  // Field state:Lapp/cybrid/cybrid_api_bank/client/model/TradeBankModel$StateEnum;
     103: aload_2
     104: getfield      #7                  // Field state:Lapp/cybrid/cybrid_api_bank/client/model/TradeBankModel$StateEnum;
     107: invokestatic  #16                 // Method java/util/Objects.equals:(Ljava/lang/Object;Ljava/lang/Object;)Z
     110: ifeq          201
     113: aload_0
     114: getfield      #8                  // Field failureCode:Ljava/lang/String;
     117: aload_2
     118: getfield      #8                  // Field failureCode:Ljava/lang/String;
     121: invokestatic  #16                 // Method java/util/Objects.equals:(Ljava/lang/Object;Ljava/lang/Object;)Z
     124: ifeq          201
     127: aload_0
     128: getfield      #9                  // Field receiveAmount:Ljava/math/BigInteger;
     131: aload_2
     132: getfield      #9                  // Field receiveAmount:Ljava/math/BigInteger;
     135: invokestatic  #16                 // Method java/util/Objects.equals:(Ljava/lang/Object;Ljava/lang/Object;)Z
     138: ifeq          201
     141: aload_0
     142: getfield      #10                 // Field deliverAmount:Ljava/math/BigInteger;
     145: aload_2
     146: getfield      #10                 // Field deliverAmount:Ljava/math/BigInteger;
     149: invokestatic  #16                 // Method java/util/Objects.equals:(Ljava/lang/Object;Ljava/lang/Object;)Z
     152: ifeq          201
     155: aload_0
     156: getfield      #11                 // Field fee:Ljava/math/BigInteger;
     159: aload_2
     160: getfield      #11                 // Field fee:Ljava/math/BigInteger;
     163: invokestatic  #16                 // Method java/util/Objects.equals:(Ljava/lang/Object;Ljava/lang/Object;)Z
     166: ifeq          201
     169: aload_0
     170: getfield      #12                 // Field createdAt:Ljava/time/OffsetDateTime;
     173: aload_2
     174: getfield      #12                 // Field createdAt:Ljava/time/OffsetDateTime;
     177: invokestatic  #16                 // Method java/util/Objects.equals:(Ljava/lang/Object;Ljava/lang/Object;)Z
     180: ifeq          201
     183: aload_0
     184: getfield      #13                 // Field updatedAt:Ljava/time/OffsetDateTime;
     187: aload_2
     188: getfield      #13                 // Field updatedAt:Ljava/time/OffsetDateTime;
     191: invokestatic  #16                 // Method java/util/Objects.equals:(Ljava/lang/Object;Ljava/lang/Object;)Z
     194: ifeq          201
     197: iconst_1
     198: goto          202
     201: iconst_0
     202: ireturn

  public int hashCode();
    Code:
       0: bipush        12
       2: anewarray     #17                 // class java/lang/Object
       5: dup
       6: iconst_0
       7: aload_0
       8: getfield      #2                  // Field guid:Ljava/lang/String;
      11: aastore
      12: dup
      13: iconst_1
      14: aload_0
      15: getfield      #3                  // Field customerGuid:Ljava/lang/String;
      18: aastore
      19: dup
      20: iconst_2
      21: aload_0
      22: getfield      #4                  // Field quoteGuid:Ljava/lang/String;
      25: aastore
      26: dup
      27: iconst_3
      28: aload_0
      29: getfield      #5                  // Field symbol:Ljava/lang/String;
      32: aastore
      33: dup
      34: iconst_4
      35: aload_0
      36: getfield      #6                  // Field side:Lapp/cybrid/cybrid_api_bank/client/model/TradeBankModel$SideEnum;
      39: aastore
      40: dup
      41: iconst_5
      42: aload_0
      43: getfield      #7                  // Field state:Lapp/cybrid/cybrid_api_bank/client/model/TradeBankModel$StateEnum;
      46: aastore
      47: dup
      48: bipush        6
      50: aload_0
      51: getfield      #8                  // Field failureCode:Ljava/lang/String;
      54: aastore
      55: dup
      56: bipush        7
      58: aload_0
      59: getfield      #9                  // Field receiveAmount:Ljava/math/BigInteger;
      62: aastore
      63: dup
      64: bipush        8
      66: aload_0
      67: getfield      #10                 // Field deliverAmount:Ljava/math/BigInteger;
      70: aastore
      71: dup
      72: bipush        9
      74: aload_0
      75: getfield      #11                 // Field fee:Ljava/math/BigInteger;
      78: aastore
      79: dup
      80: bipush        10
      82: aload_0
      83: getfield      #12                 // Field createdAt:Ljava/time/OffsetDateTime;
      86: aastore
      87: dup
      88: bipush        11
      90: aload_0
      91: getfield      #13                 // Field updatedAt:Ljava/time/OffsetDateTime;
      94: aastore
      95: invokestatic  #18                 // Method java/util/Objects.hash:([Ljava/lang/Object;)I
      98: ireturn

  public java.lang.String toString();
    Code:
       0: new           #19                 // class java/lang/StringBuilder
       3: dup
       4: invokespecial #20                 // Method java/lang/StringBuilder."<init>":()V
       7: astore_1
       8: aload_1
       9: ldc           #21                 // String class TradeBankModel {\n
      11: invokevirtual #22                 // Method java/lang/StringBuilder.append:(Ljava/lang/String;)Ljava/lang/StringBuilder;
      14: pop
      15: aload_1
      16: ldc           #23                 // String     guid:
      18: invokevirtual #22                 // Method java/lang/StringBuilder.append:(Ljava/lang/String;)Ljava/lang/StringBuilder;
      21: aload_0
      22: aload_0
      23: getfield      #2                  // Field guid:Ljava/lang/String;
      26: invokespecial #24                 // Method toIndentedString:(Ljava/lang/Object;)Ljava/lang/String;
      29: invokevirtual #22                 // Method java/lang/StringBuilder.append:(Ljava/lang/String;)Ljava/lang/StringBuilder;
      32: ldc           #25                 // String \n
      34: invokevirtual #22                 // Method java/lang/StringBuilder.append:(Ljava/lang/String;)Ljava/lang/StringBuilder;
      37: pop
      38: aload_1
      39: ldc           #26                 // String     customerGuid:
      41: invokevirtual #22                 // Method java/lang/StringBuilder.append:(Ljava/lang/String;)Ljava/lang/StringBuilder;
      44: aload_0
      45: aload_0
      46: getfield      #3                  // Field customerGuid:Ljava/lang/String;
      49: invokespecial #24                 // Method toIndentedString:(Ljava/lang/Object;)Ljava/lang/String;
      52: invokevirtual #22                 // Method java/lang/StringBuilder.append:(Ljava/lang/String;)Ljava/lang/StringBuilder;
      55: ldc           #25                 // String \n
      57: invokevirtual #22                 // Method java/lang/StringBuilder.append:(Ljava/lang/String;)Ljava/lang/StringBuilder;
      60: pop
      61: aload_1
      62: ldc           #27                 // String     quoteGuid:
      64: invokevirtual #22                 // Method java/lang/StringBuilder.append:(Ljava/lang/String;)Ljava/lang/StringBuilder;
      67: aload_0
      68: aload_0
      69: getfield      #4                  // Field quoteGuid:Ljava/lang/String;
      72: invokespecial #24                 // Method toIndentedString:(Ljava/lang/Object;)Ljava/lang/String;
      75: invokevirtual #22                 // Method java/lang/StringBuilder.append:(Ljava/lang/String;)Ljava/lang/StringBuilder;
      78: ldc           #25                 // String \n
      80: invokevirtual #22                 // Method java/lang/StringBuilder.append:(Ljava/lang/String;)Ljava/lang/StringBuilder;
      83: pop
      84: aload_1
      85: ldc           #28                 // String     symbol:
      87: invokevirtual #22                 // Method java/lang/StringBuilder.append:(Ljava/lang/String;)Ljava/lang/StringBuilder;
      90: aload_0
      91: aload_0
      92: getfield      #5                  // Field symbol:Ljava/lang/String;
      95: invokespecial #24                 // Method toIndentedString:(Ljava/lang/Object;)Ljava/lang/String;
      98: invokevirtual #22                 // Method java/lang/StringBuilder.append:(Ljava/lang/String;)Ljava/lang/StringBuilder;
     101: ldc           #25                 // String \n
     103: invokevirtual #22                 // Method java/lang/StringBuilder.append:(Ljava/lang/String;)Ljava/lang/StringBuilder;
     106: pop
     107: aload_1
     108: ldc           #29                 // String     side:
     110: invokevirtual #22                 // Method java/lang/StringBuilder.append:(Ljava/lang/String;)Ljava/lang/StringBuilder;
     113: aload_0
     114: aload_0
     115: getfield      #6                  // Field side:Lapp/cybrid/cybrid_api_bank/client/model/TradeBankModel$SideEnum;
     118: invokespecial #24                 // Method toIndentedString:(Ljava/lang/Object;)Ljava/lang/String;
     121: invokevirtual #22                 // Method java/lang/StringBuilder.append:(Ljava/lang/String;)Ljava/lang/StringBuilder;
     124: ldc           #25                 // String \n
     126: invokevirtual #22                 // Method java/lang/StringBuilder.append:(Ljava/lang/String;)Ljava/lang/StringBuilder;
     129: pop
     130: aload_1
     131: ldc           #30                 // String     state:
     133: invokevirtual #22                 // Method java/lang/StringBuilder.append:(Ljava/lang/String;)Ljava/lang/StringBuilder;
     136: aload_0
     137: aload_0
     138: getfield      #7                  // Field state:Lapp/cybrid/cybrid_api_bank/client/model/TradeBankModel$StateEnum;
     141: invokespecial #24                 // Method toIndentedString:(Ljava/lang/Object;)Ljava/lang/String;
     144: invokevirtual #22                 // Method java/lang/StringBuilder.append:(Ljava/lang/String;)Ljava/lang/StringBuilder;
     147: ldc           #25                 // String \n
     149: invokevirtual #22                 // Method java/lang/StringBuilder.append:(Ljava/lang/String;)Ljava/lang/StringBuilder;
     152: pop
     153: aload_1
     154: ldc           #31                 // String     failureCode:
     156: invokevirtual #22                 // Method java/lang/StringBuilder.append:(Ljava/lang/String;)Ljava/lang/StringBuilder;
     159: aload_0
     160: aload_0
     161: getfield      #8                  // Field failureCode:Ljava/lang/String;
     164: invokespecial #24                 // Method toIndentedString:(Ljava/lang/Object;)Ljava/lang/String;
     167: invokevirtual #22                 // Method java/lang/StringBuilder.append:(Ljava/lang/String;)Ljava/lang/StringBuilder;
     170: ldc           #25                 // String \n
     172: invokevirtual #22                 // Method java/lang/StringBuilder.append:(Ljava/lang/String;)Ljava/lang/StringBuilder;
     175: pop
     176: aload_1
     177: ldc           #32                 // String     receiveAmount:
     179: invokevirtual #22                 // Method java/lang/StringBuilder.append:(Ljava/lang/String;)Ljava/lang/StringBuilder;
     182: aload_0
     183: aload_0
     184: getfield      #9                  // Field receiveAmount:Ljava/math/BigInteger;
     187: invokespecial #24                 // Method toIndentedString:(Ljava/lang/Object;)Ljava/lang/String;
     190: invokevirtual #22                 // Method java/lang/StringBuilder.append:(Ljava/lang/String;)Ljava/lang/StringBuilder;
     193: ldc           #25                 // String \n
     195: invokevirtual #22                 // Method java/lang/StringBuilder.append:(Ljava/lang/String;)Ljava/lang/StringBuilder;
     198: pop
     199: aload_1
     200: ldc           #33                 // String     deliverAmount:
     202: invokevirtual #22                 // Method java/lang/StringBuilder.append:(Ljava/lang/String;)Ljava/lang/StringBuilder;
     205: aload_0
     206: aload_0
     207: getfield      #10                 // Field deliverAmount:Ljava/math/BigInteger;
     210: invokespecial #24                 // Method toIndentedString:(Ljava/lang/Object;)Ljava/lang/String;
     213: invokevirtual #22                 // Method java/lang/StringBuilder.append:(Ljava/lang/String;)Ljava/lang/StringBuilder;
     216: ldc           #25                 // String \n
     218: invokevirtual #22                 // Method java/lang/StringBuilder.append:(Ljava/lang/String;)Ljava/lang/StringBuilder;
     221: pop
     222: aload_1
     223: ldc           #34                 // String     fee:
     225: invokevirtual #22                 // Method java/lang/StringBuilder.append:(Ljava/lang/String;)Ljava/lang/StringBuilder;
     228: aload_0
     229: aload_0
     230: getfield      #11                 // Field fee:Ljava/math/BigInteger;
     233: invokespecial #24                 // Method toIndentedString:(Ljava/lang/Object;)Ljava/lang/String;
     236: invokevirtual #22                 // Method java/lang/StringBuilder.append:(Ljava/lang/String;)Ljava/lang/StringBuilder;
     239: ldc           #25                 // String \n
     241: invokevirtual #22                 // Method java/lang/StringBuilder.append:(Ljava/lang/String;)Ljava/lang/StringBuilder;
     244: pop
     245: aload_1
     246: ldc           #35                 // String     createdAt:
     248: invokevirtual #22                 // Method java/lang/StringBuilder.append:(Ljava/lang/String;)Ljava/lang/StringBuilder;
     251: aload_0
     252: aload_0
     253: getfield      #12                 // Field createdAt:Ljava/time/OffsetDateTime;
     256: invokespecial #24                 // Method toIndentedString:(Ljava/lang/Object;)Ljava/lang/String;
     259: invokevirtual #22                 // Method java/lang/StringBuilder.append:(Ljava/lang/String;)Ljava/lang/StringBuilder;
     262: ldc           #25                 // String \n
     264: invokevirtual #22                 // Method java/lang/StringBuilder.append:(Ljava/lang/String;)Ljava/lang/StringBuilder;
     267: pop
     268: aload_1
     269: ldc           #36                 // String     updatedAt:
     271: invokevirtual #22                 // Method java/lang/StringBuilder.append:(Ljava/lang/String;)Ljava/lang/StringBuilder;
     274: aload_0
     275: aload_0
     276: getfield      #13                 // Field updatedAt:Ljava/time/OffsetDateTime;
     279: invokespecial #24                 // Method toIndentedString:(Ljava/lang/Object;)Ljava/lang/String;
     282: invokevirtual #22                 // Method java/lang/StringBuilder.append:(Ljava/lang/String;)Ljava/lang/StringBuilder;
     285: ldc           #25                 // String \n
     287: invokevirtual #22                 // Method java/lang/StringBuilder.append:(Ljava/lang/String;)Ljava/lang/StringBuilder;
     290: pop
     291: aload_1
     292: ldc           #37                 // String }
     294: invokevirtual #22                 // Method java/lang/StringBuilder.append:(Ljava/lang/String;)Ljava/lang/StringBuilder;
     297: pop
     298: aload_1
     299: invokevirtual #38                 // Method java/lang/StringBuilder.toString:()Ljava/lang/String;
     302: areturn

  private java.lang.String toIndentedString(java.lang.Object);
    Code:
       0: aload_1
       1: ifnonnull     7
       4: ldc           #39                 // String null
       6: areturn
       7: aload_1
       8: invokevirtual #40                 // Method java/lang/Object.toString:()Ljava/lang/String;
      11: ldc           #25                 // String \n
      13: ldc           #41                 // String \n
      15: invokevirtual #42                 // Method java/lang/String.replace:(Ljava/lang/CharSequence;Ljava/lang/CharSequence;)Ljava/lang/String;
      18: areturn
}
