Compiled from "HttpSessionEventPublisher.java"
public class org.springframework.security.web.session.HttpSessionEventPublisher implements javax.servlet.http.HttpSessionListener {
  private static final java.lang.String LOGGER_NAME;

  public org.springframework.security.web.session.HttpSessionEventPublisher();
    Code:
       0: aload_0
       1: invokespecial #1                  // Method java/lang/Object."<init>":()V
       4: return

  org.springframework.context.ApplicationContext getContext(javax.servlet.ServletContext);
    Code:
       0: aload_1
       1: invokestatic  #2                  // Method org/springframework/security/web/context/support/SecurityWebApplicationContextUtils.findRequiredWebApplicationContext:(Ljavax/servlet/ServletContext;)Lorg/springframework/web/context/WebApplicationContext;
       4: areturn

  public void sessionCreated(javax.servlet.http.HttpSessionEvent);
    Code:
       0: new           #3                  // class org/springframework/security/web/session/HttpSessionCreatedEvent
       3: dup
       4: aload_1
       5: invokevirtual #4                  // Method javax/servlet/http/HttpSessionEvent.getSession:()Ljavax/servlet/http/HttpSession;
       8: invokespecial #5                  // Method org/springframework/security/web/session/HttpSessionCreatedEvent."<init>":(Ljavax/servlet/http/HttpSession;)V
      11: astore_2
      12: getstatic     #6                  // Field LOGGER_NAME:Ljava/lang/String;
      15: invokestatic  #7                  // Method org/apache/commons/logging/LogFactory.getLog:(Ljava/lang/String;)Lorg/apache/commons/logging/Log;
      18: astore_3
      19: aload_3
      20: invokeinterface #8,  1            // InterfaceMethod org/apache/commons/logging/Log.isDebugEnabled:()Z
      25: ifeq          53
      28: aload_3
      29: new           #9                  // class java/lang/StringBuilder
      32: dup
      33: invokespecial #10                 // Method java/lang/StringBuilder."<init>":()V
      36: ldc           #11                 // String Publishing event:
      38: invokevirtual #12                 // Method java/lang/StringBuilder.append:(Ljava/lang/String;)Ljava/lang/StringBuilder;
      41: aload_2
      42: invokevirtual #13                 // Method java/lang/StringBuilder.append:(Ljava/lang/Object;)Ljava/lang/StringBuilder;
      45: invokevirtual #14                 // Method java/lang/StringBuilder.toString:()Ljava/lang/String;
      48: invokeinterface #15,  2           // InterfaceMethod org/apache/commons/logging/Log.debug:(Ljava/lang/Object;)V
      53: aload_0
      54: aload_1
      55: invokevirtual #4                  // Method javax/servlet/http/HttpSessionEvent.getSession:()Ljavax/servlet/http/HttpSession;
      58: invokeinterface #16,  1           // InterfaceMethod javax/servlet/http/HttpSession.getServletContext:()Ljavax/servlet/ServletContext;
      63: invokevirtual #17                 // Method getContext:(Ljavax/servlet/ServletContext;)Lorg/springframework/context/ApplicationContext;
      66: aload_2
      67: invokeinterface #18,  2           // InterfaceMethod org/springframework/context/ApplicationContext.publishEvent:(Lorg/springframework/context/ApplicationEvent;)V
      72: return

  public void sessionDestroyed(javax.servlet.http.HttpSessionEvent);
    Code:
       0: new           #19                 // class org/springframework/security/web/session/HttpSessionDestroyedEvent
       3: dup
       4: aload_1
       5: invokevirtual #4                  // Method javax/servlet/http/HttpSessionEvent.getSession:()Ljavax/servlet/http/HttpSession;
       8: invokespecial #20                 // Method org/springframework/security/web/session/HttpSessionDestroyedEvent."<init>":(Ljavax/servlet/http/HttpSession;)V
      11: astore_2
      12: getstatic     #6                  // Field LOGGER_NAME:Ljava/lang/String;
      15: invokestatic  #7                  // Method org/apache/commons/logging/LogFactory.getLog:(Ljava/lang/String;)Lorg/apache/commons/logging/Log;
      18: astore_3
      19: aload_3
      20: invokeinterface #8,  1            // InterfaceMethod org/apache/commons/logging/Log.isDebugEnabled:()Z
      25: ifeq          53
      28: aload_3
      29: new           #9                  // class java/lang/StringBuilder
      32: dup
      33: invokespecial #10                 // Method java/lang/StringBuilder."<init>":()V
      36: ldc           #11                 // String Publishing event:
      38: invokevirtual #12                 // Method java/lang/StringBuilder.append:(Ljava/lang/String;)Ljava/lang/StringBuilder;
      41: aload_2
      42: invokevirtual #13                 // Method java/lang/StringBuilder.append:(Ljava/lang/Object;)Ljava/lang/StringBuilder;
      45: invokevirtual #14                 // Method java/lang/StringBuilder.toString:()Ljava/lang/String;
      48: invokeinterface #15,  2           // InterfaceMethod org/apache/commons/logging/Log.debug:(Ljava/lang/Object;)V
      53: aload_0
      54: aload_1
      55: invokevirtual #4                  // Method javax/servlet/http/HttpSessionEvent.getSession:()Ljavax/servlet/http/HttpSession;
      58: invokeinterface #16,  1           // InterfaceMethod javax/servlet/http/HttpSession.getServletContext:()Ljavax/servlet/ServletContext;
      63: invokevirtual #17                 // Method getContext:(Ljavax/servlet/ServletContext;)Lorg/springframework/context/ApplicationContext;
      66: aload_2
      67: invokeinterface #18,  2           // InterfaceMethod org/springframework/context/ApplicationContext.publishEvent:(Lorg/springframework/context/ApplicationEvent;)V
      72: return

  static {};
    Code:
       0: ldc           #21                 // class org/springframework/security/web/session/HttpSessionEventPublisher
       2: invokevirtual #22                 // Method java/lang/Class.getName:()Ljava/lang/String;
       5: putstatic     #6                  // Field LOGGER_NAME:Ljava/lang/String;
       8: return
}
