Compiled from "SimpleBeanPropertyFilter.java"
public class io.dekorate.deps.jackson.databind.ser.impl.SimpleBeanPropertyFilter implements io.dekorate.deps.jackson.databind.ser.BeanPropertyFilter,io.dekorate.deps.jackson.databind.ser.PropertyFilter {
  protected io.dekorate.deps.jackson.databind.ser.impl.SimpleBeanPropertyFilter();
    Code:
       0: aload_0
       1: invokespecial #21                 // Method java/lang/Object."<init>":()V
       4: return

  public static io.dekorate.deps.jackson.databind.ser.impl.SimpleBeanPropertyFilter serializeAll();
    Code:
       0: getstatic     #29                 // Field io/dekorate/deps/jackson/databind/ser/impl/SimpleBeanPropertyFilter$SerializeExceptFilter.INCLUDE_ALL:Lio/dekorate/deps/jackson/databind/ser/impl/SimpleBeanPropertyFilter$SerializeExceptFilter;
       3: areturn

  public static io.dekorate.deps.jackson.databind.ser.impl.SimpleBeanPropertyFilter serializeAll(java.util.Set<java.lang.String>);
    Code:
       0: new           #14                 // class io/dekorate/deps/jackson/databind/ser/impl/SimpleBeanPropertyFilter$FilterExceptFilter
       3: dup
       4: aload_0
       5: invokespecial #35                 // Method io/dekorate/deps/jackson/databind/ser/impl/SimpleBeanPropertyFilter$FilterExceptFilter."<init>":(Ljava/util/Set;)V
       8: areturn

  public static io.dekorate.deps.jackson.databind.ser.impl.SimpleBeanPropertyFilter filterOutAllExcept(java.util.Set<java.lang.String>);
    Code:
       0: new           #14                 // class io/dekorate/deps/jackson/databind/ser/impl/SimpleBeanPropertyFilter$FilterExceptFilter
       3: dup
       4: aload_0
       5: invokespecial #35                 // Method io/dekorate/deps/jackson/databind/ser/impl/SimpleBeanPropertyFilter$FilterExceptFilter."<init>":(Ljava/util/Set;)V
       8: areturn

  public static io.dekorate.deps.jackson.databind.ser.impl.SimpleBeanPropertyFilter filterOutAllExcept(java.lang.String...);
    Code:
       0: new           #42                 // class java/util/HashSet
       3: dup
       4: aload_0
       5: arraylength
       6: invokespecial #45                 // Method java/util/HashSet."<init>":(I)V
       9: astore_1
      10: aload_1
      11: aload_0
      12: invokestatic  #51                 // Method java/util/Collections.addAll:(Ljava/util/Collection;[Ljava/lang/Object;)Z
      15: pop
      16: new           #14                 // class io/dekorate/deps/jackson/databind/ser/impl/SimpleBeanPropertyFilter$FilterExceptFilter
      19: dup
      20: aload_1
      21: invokespecial #35                 // Method io/dekorate/deps/jackson/databind/ser/impl/SimpleBeanPropertyFilter$FilterExceptFilter."<init>":(Ljava/util/Set;)V
      24: areturn

  public static io.dekorate.deps.jackson.databind.ser.impl.SimpleBeanPropertyFilter serializeAllExcept(java.util.Set<java.lang.String>);
    Code:
       0: new           #11                 // class io/dekorate/deps/jackson/databind/ser/impl/SimpleBeanPropertyFilter$SerializeExceptFilter
       3: dup
       4: aload_0
       5: invokespecial #57                 // Method io/dekorate/deps/jackson/databind/ser/impl/SimpleBeanPropertyFilter$SerializeExceptFilter."<init>":(Ljava/util/Set;)V
       8: areturn

  public static io.dekorate.deps.jackson.databind.ser.impl.SimpleBeanPropertyFilter serializeAllExcept(java.lang.String...);
    Code:
       0: new           #42                 // class java/util/HashSet
       3: dup
       4: aload_0
       5: arraylength
       6: invokespecial #45                 // Method java/util/HashSet."<init>":(I)V
       9: astore_1
      10: aload_1
      11: aload_0
      12: invokestatic  #51                 // Method java/util/Collections.addAll:(Ljava/util/Collection;[Ljava/lang/Object;)Z
      15: pop
      16: new           #11                 // class io/dekorate/deps/jackson/databind/ser/impl/SimpleBeanPropertyFilter$SerializeExceptFilter
      19: dup
      20: aload_1
      21: invokespecial #57                 // Method io/dekorate/deps/jackson/databind/ser/impl/SimpleBeanPropertyFilter$SerializeExceptFilter."<init>":(Ljava/util/Set;)V
      24: areturn

  public static io.dekorate.deps.jackson.databind.ser.PropertyFilter from(io.dekorate.deps.jackson.databind.ser.BeanPropertyFilter);
    Code:
       0: new           #17                 // class io/dekorate/deps/jackson/databind/ser/impl/SimpleBeanPropertyFilter$1
       3: dup
       4: aload_0
       5: invokespecial #62                 // Method io/dekorate/deps/jackson/databind/ser/impl/SimpleBeanPropertyFilter$1."<init>":(Lio/dekorate/deps/jackson/databind/ser/BeanPropertyFilter;)V
       8: areturn

  protected boolean include(io.dekorate.deps.jackson.databind.ser.BeanPropertyWriter);
    Code:
       0: iconst_1
       1: ireturn

  protected boolean include(io.dekorate.deps.jackson.databind.ser.PropertyWriter);
    Code:
       0: iconst_1
       1: ireturn

  protected boolean includeElement(java.lang.Object);
    Code:
       0: iconst_1
       1: ireturn

  public void serializeAsField(java.lang.Object, io.dekorate.deps.jackson.core.JsonGenerator, io.dekorate.deps.jackson.databind.SerializerProvider, io.dekorate.deps.jackson.databind.ser.BeanPropertyWriter) throws java.lang.Exception;
    Code:
       0: aload_0
       1: aload         4
       3: invokevirtual #80                 // Method include:(Lio/dekorate/deps/jackson/databind/ser/BeanPropertyWriter;)Z
       6: ifeq          20
       9: aload         4
      11: aload_1
      12: aload_2
      13: aload_3
      14: invokevirtual #85                 // Method io/dekorate/deps/jackson/databind/ser/BeanPropertyWriter.serializeAsField:(Ljava/lang/Object;Lio/dekorate/deps/jackson/core/JsonGenerator;Lio/dekorate/deps/jackson/databind/SerializerProvider;)V
      17: goto          35
      20: aload_2
      21: invokevirtual #91                 // Method io/dekorate/deps/jackson/core/JsonGenerator.canOmitFields:()Z
      24: ifne          35
      27: aload         4
      29: aload_1
      30: aload_2
      31: aload_3
      32: invokevirtual #94                 // Method io/dekorate/deps/jackson/databind/ser/BeanPropertyWriter.serializeAsOmittedField:(Ljava/lang/Object;Lio/dekorate/deps/jackson/core/JsonGenerator;Lio/dekorate/deps/jackson/databind/SerializerProvider;)V
      35: return

  public void depositSchemaProperty(io.dekorate.deps.jackson.databind.ser.BeanPropertyWriter, io.dekorate.deps.jackson.databind.node.ObjectNode, io.dekorate.deps.jackson.databind.SerializerProvider) throws io.dekorate.deps.jackson.databind.JsonMappingException;
    Code:
       0: aload_0
       1: aload_1
       2: invokevirtual #80                 // Method include:(Lio/dekorate/deps/jackson/databind/ser/BeanPropertyWriter;)Z
       5: ifeq          14
       8: aload_1
       9: aload_2
      10: aload_3
      11: invokevirtual #106                // Method io/dekorate/deps/jackson/databind/ser/BeanPropertyWriter.depositSchemaProperty:(Lio/dekorate/deps/jackson/databind/node/ObjectNode;Lio/dekorate/deps/jackson/databind/SerializerProvider;)V
      14: return

  public void depositSchemaProperty(io.dekorate.deps.jackson.databind.ser.BeanPropertyWriter, io.dekorate.deps.jackson.databind.jsonFormatVisitors.JsonObjectFormatVisitor, io.dekorate.deps.jackson.databind.SerializerProvider) throws io.dekorate.deps.jackson.databind.JsonMappingException;
    Code:
       0: aload_0
       1: aload_1
       2: invokevirtual #80                 // Method include:(Lio/dekorate/deps/jackson/databind/ser/BeanPropertyWriter;)Z
       5: ifeq          14
       8: aload_1
       9: aload_2
      10: aload_3
      11: invokevirtual #112                // Method io/dekorate/deps/jackson/databind/ser/BeanPropertyWriter.depositSchemaProperty:(Lio/dekorate/deps/jackson/databind/jsonFormatVisitors/JsonObjectFormatVisitor;Lio/dekorate/deps/jackson/databind/SerializerProvider;)V
      14: return

  public void serializeAsField(java.lang.Object, io.dekorate.deps.jackson.core.JsonGenerator, io.dekorate.deps.jackson.databind.SerializerProvider, io.dekorate.deps.jackson.databind.ser.PropertyWriter) throws java.lang.Exception;
    Code:
       0: aload_0
       1: aload         4
       3: invokevirtual #117                // Method include:(Lio/dekorate/deps/jackson/databind/ser/PropertyWriter;)Z
       6: ifeq          20
       9: aload         4
      11: aload_1
      12: aload_2
      13: aload_3
      14: invokevirtual #120                // Method io/dekorate/deps/jackson/databind/ser/PropertyWriter.serializeAsField:(Ljava/lang/Object;Lio/dekorate/deps/jackson/core/JsonGenerator;Lio/dekorate/deps/jackson/databind/SerializerProvider;)V
      17: goto          35
      20: aload_2
      21: invokevirtual #91                 // Method io/dekorate/deps/jackson/core/JsonGenerator.canOmitFields:()Z
      24: ifne          35
      27: aload         4
      29: aload_1
      30: aload_2
      31: aload_3
      32: invokevirtual #121                // Method io/dekorate/deps/jackson/databind/ser/PropertyWriter.serializeAsOmittedField:(Ljava/lang/Object;Lio/dekorate/deps/jackson/core/JsonGenerator;Lio/dekorate/deps/jackson/databind/SerializerProvider;)V
      35: return

  public void serializeAsElement(java.lang.Object, io.dekorate.deps.jackson.core.JsonGenerator, io.dekorate.deps.jackson.databind.SerializerProvider, io.dekorate.deps.jackson.databind.ser.PropertyWriter) throws java.lang.Exception;
    Code:
       0: aload_0
       1: aload_1
       2: invokevirtual #125                // Method includeElement:(Ljava/lang/Object;)Z
       5: ifeq          16
       8: aload         4
      10: aload_1
      11: aload_2
      12: aload_3
      13: invokevirtual #127                // Method io/dekorate/deps/jackson/databind/ser/PropertyWriter.serializeAsElement:(Ljava/lang/Object;Lio/dekorate/deps/jackson/core/JsonGenerator;Lio/dekorate/deps/jackson/databind/SerializerProvider;)V
      16: return

  public void depositSchemaProperty(io.dekorate.deps.jackson.databind.ser.PropertyWriter, io.dekorate.deps.jackson.databind.node.ObjectNode, io.dekorate.deps.jackson.databind.SerializerProvider) throws io.dekorate.deps.jackson.databind.JsonMappingException;
    Code:
       0: aload_0
       1: aload_1
       2: invokevirtual #117                // Method include:(Lio/dekorate/deps/jackson/databind/ser/PropertyWriter;)Z
       5: ifeq          14
       8: aload_1
       9: aload_2
      10: aload_3
      11: invokevirtual #129                // Method io/dekorate/deps/jackson/databind/ser/PropertyWriter.depositSchemaProperty:(Lio/dekorate/deps/jackson/databind/node/ObjectNode;Lio/dekorate/deps/jackson/databind/SerializerProvider;)V
      14: return

  public void depositSchemaProperty(io.dekorate.deps.jackson.databind.ser.PropertyWriter, io.dekorate.deps.jackson.databind.jsonFormatVisitors.JsonObjectFormatVisitor, io.dekorate.deps.jackson.databind.SerializerProvider) throws io.dekorate.deps.jackson.databind.JsonMappingException;
    Code:
       0: aload_0
       1: aload_1
       2: invokevirtual #117                // Method include:(Lio/dekorate/deps/jackson/databind/ser/PropertyWriter;)Z
       5: ifeq          14
       8: aload_1
       9: aload_2
      10: aload_3
      11: invokevirtual #131                // Method io/dekorate/deps/jackson/databind/ser/PropertyWriter.depositSchemaProperty:(Lio/dekorate/deps/jackson/databind/jsonFormatVisitors/JsonObjectFormatVisitor;Lio/dekorate/deps/jackson/databind/SerializerProvider;)V
      14: return
}
