Compiled from "FileSystemRuntimeConfigPersistor.scala"
public final class blended.updater.remote.FileSystemRuntimeConfigPersistor$$anonfun$initialize$1 extends scala.runtime.AbstractFunction1<scala.Tuple2<java.io.File, blended.updater.config.RuntimeConfig>, java.lang.Object> implements scala.Serializable {
  public static final long serialVersionUID;

  private final blended.updater.remote.FileSystemRuntimeConfigPersistor $outer;

  public final boolean apply(scala.Tuple2<java.io.File, blended.updater.config.RuntimeConfig>);
    Code:
       0: aload_1
       1: astore_2
       2: aload_2
       3: ifnull        69
       6: aload_2
       7: invokevirtual #27                 // Method scala/Tuple2._1:()Ljava/lang/Object;
      10: checkcast     #29                 // class java/io/File
      13: astore_3
      14: aload_2
      15: invokevirtual #32                 // Method scala/Tuple2._2:()Ljava/lang/Object;
      18: checkcast     #34                 // class blended/updater/config/RuntimeConfig
      21: astore        4
      23: aload_3
      24: invokevirtual #38                 // Method java/io/File.getName:()Ljava/lang/String;
      27: aload_0
      28: getfield      #40                 // Field $outer:Lblended/updater/remote/FileSystemRuntimeConfigPersistor;
      31: aload         4
      33: invokevirtual #44                 // Method blended/updater/remote/FileSystemRuntimeConfigPersistor.fileName:(Lblended/updater/config/RuntimeConfig;)Ljava/lang/String;
      36: astore        6
      38: dup
      39: ifnonnull     51
      42: pop
      43: aload         6
      45: ifnull        59
      48: goto          63
      51: aload         6
      53: invokevirtual #50                 // Method java/lang/Object.equals:(Ljava/lang/Object;)Z
      56: ifeq          63
      59: iconst_1
      60: goto          64
      63: iconst_0
      64: istore        5
      66: iload         5
      68: ireturn
      69: new           #52                 // class scala/MatchError
      72: dup
      73: aload_2
      74: invokespecial #56                 // Method scala/MatchError."<init>":(Ljava/lang/Object;)V
      77: athrow

  public final java.lang.Object apply(java.lang.Object);
    Code:
       0: aload_0
       1: aload_1
       2: checkcast     #23                 // class scala/Tuple2
       5: invokevirtual #69                 // Method apply:(Lscala/Tuple2;)Z
       8: invokestatic  #75                 // Method scala/runtime/BoxesRunTime.boxToBoolean:(Z)Ljava/lang/Boolean;
      11: areturn

  public blended.updater.remote.FileSystemRuntimeConfigPersistor$$anonfun$initialize$1(blended.updater.remote.FileSystemRuntimeConfigPersistor);
    Code:
       0: aload_1
       1: ifnonnull     6
       4: aconst_null
       5: athrow
       6: aload_0
       7: aload_1
       8: putfield      #40                 // Field $outer:Lblended/updater/remote/FileSystemRuntimeConfigPersistor;
      11: aload_0
      12: invokespecial #80                 // Method scala/runtime/AbstractFunction1."<init>":()V
      15: return
}
