Compiled from "HashBiMap.java"
final class com.google.common.collect.HashBiMap$InverseSerializedForm<K, V> implements java.io.Serializable {
  private final com.google.common.collect.HashBiMap<K, V> bimap;

  com.google.common.collect.HashBiMap$InverseSerializedForm(com.google.common.collect.HashBiMap<K, V>);
    Code:
       0: aload_0
       1: invokespecial #1                  // Method java/lang/Object."<init>":()V
       4: aload_0
       5: aload_1
       6: putfield      #2                  // Field bimap:Lcom/google/common/collect/HashBiMap;
       9: return

  java.lang.Object readResolve();
    Code:
       0: aload_0
       1: getfield      #2                  // Field bimap:Lcom/google/common/collect/HashBiMap;
       4: invokevirtual #3                  // Method com/google/common/collect/HashBiMap.inverse:()Lcom/google/common/collect/BiMap;
       7: areturn
}
