Compiled from "NetworkPublication.java"
class io.aeron.driver.NetworkPublicationReceiverFields extends io.aeron.driver.NetworkPublicationPadding2 {
  long timeOfLastSendOrHeartbeat;

  long senderPositionLimit;

  long timeOfLastSetup;

  boolean trackSenderLimits;

  boolean shouldSendSetupFrame;

  io.aeron.driver.NetworkPublicationReceiverFields();
    Code:
       0: aload_0
       1: invokespecial #1                  // Method io/aeron/driver/NetworkPublicationPadding2."<init>":()V
       4: aload_0
       5: lconst_0
       6: putfield      #2                  // Field senderPositionLimit:J
       9: aload_0
      10: iconst_1
      11: putfield      #3                  // Field trackSenderLimits:Z
      14: aload_0
      15: iconst_1
      16: putfield      #4                  // Field shouldSendSetupFrame:Z
      19: return
}
