Compiled from "JdkLoggerFactory.java"
public class org.jboss.netty.logging.JdkLoggerFactory extends org.jboss.netty.logging.InternalLoggerFactory {
  public org.jboss.netty.logging.JdkLoggerFactory();
    Code:
       0: aload_0
       1: invokespecial #1                  // Method org/jboss/netty/logging/InternalLoggerFactory."<init>":()V
       4: return

  public org.jboss.netty.logging.InternalLogger newInstance(java.lang.String);
    Code:
       0: aload_1
       1: invokestatic  #2                  // Method java/util/logging/Logger.getLogger:(Ljava/lang/String;)Ljava/util/logging/Logger;
       4: astore_2
       5: new           #3                  // class org/jboss/netty/logging/JdkLogger
       8: dup
       9: aload_2
      10: aload_1
      11: invokespecial #4                  // Method org/jboss/netty/logging/JdkLogger."<init>":(Ljava/util/logging/Logger;Ljava/lang/String;)V
      14: areturn
}
