Compiled from "GrokPatternRegistry.java"
public class org.graylog2.grok.GrokPatternRegistry {
  private static final org.slf4j.Logger log;

  private final org.graylog2.grok.GrokPatternService grokPatternService;

  private final java.util.concurrent.atomic.AtomicReference<java.util.Set<org.graylog2.grok.GrokPattern>> patterns;

  private final com.google.common.cache.LoadingCache<java.lang.String, io.krakens.grok.api.Grok> grokCache;

  private final com.google.common.cache.LoadingCache<java.lang.String, io.krakens.grok.api.Grok> grokCacheNamedOnly;

  public org.graylog2.grok.GrokPatternRegistry(com.google.common.eventbus.EventBus, org.graylog2.grok.GrokPatternService, java.util.concurrent.ScheduledExecutorService);
    Code:
       0: aload_0
       1: invokespecial #1                  // Method java/lang/Object."<init>":()V
       4: aload_0
       5: new           #2                  // class java/util/concurrent/atomic/AtomicReference
       8: dup
       9: invokestatic  #3                  // Method java/util/Collections.emptySet:()Ljava/util/Set;
      12: invokespecial #4                  // Method java/util/concurrent/atomic/AtomicReference."<init>":(Ljava/lang/Object;)V
      15: putfield      #5                  // Field patterns:Ljava/util/concurrent/atomic/AtomicReference;
      18: aload_0
      19: aload_2
      20: putfield      #6                  // Field grokPatternService:Lorg/graylog2/grok/GrokPatternService;
      23: aload_0
      24: invokestatic  #7                  // Method com/google/common/cache/CacheBuilder.newBuilder:()Lcom/google/common/cache/CacheBuilder;
      27: lconst_1
      28: getstatic     #8                  // Field java/util/concurrent/TimeUnit.MINUTES:Ljava/util/concurrent/TimeUnit;
      31: invokevirtual #9                  // Method com/google/common/cache/CacheBuilder.expireAfterAccess:(JLjava/util/concurrent/TimeUnit;)Lcom/google/common/cache/CacheBuilder;
      34: new           #10                 // class org/graylog2/grok/GrokPatternRegistry$GrokReloader
      37: dup
      38: aload_0
      39: iconst_0
      40: invokespecial #11                 // Method org/graylog2/grok/GrokPatternRegistry$GrokReloader."<init>":(Lorg/graylog2/grok/GrokPatternRegistry;Z)V
      43: aload_3
      44: invokestatic  #12                 // Method com/google/common/cache/CacheLoader.asyncReloading:(Lcom/google/common/cache/CacheLoader;Ljava/util/concurrent/Executor;)Lcom/google/common/cache/CacheLoader;
      47: invokevirtual #13                 // Method com/google/common/cache/CacheBuilder.build:(Lcom/google/common/cache/CacheLoader;)Lcom/google/common/cache/LoadingCache;
      50: putfield      #14                 // Field grokCache:Lcom/google/common/cache/LoadingCache;
      53: aload_0
      54: invokestatic  #7                  // Method com/google/common/cache/CacheBuilder.newBuilder:()Lcom/google/common/cache/CacheBuilder;
      57: lconst_1
      58: getstatic     #8                  // Field java/util/concurrent/TimeUnit.MINUTES:Ljava/util/concurrent/TimeUnit;
      61: invokevirtual #9                  // Method com/google/common/cache/CacheBuilder.expireAfterAccess:(JLjava/util/concurrent/TimeUnit;)Lcom/google/common/cache/CacheBuilder;
      64: new           #10                 // class org/graylog2/grok/GrokPatternRegistry$GrokReloader
      67: dup
      68: aload_0
      69: iconst_1
      70: invokespecial #11                 // Method org/graylog2/grok/GrokPatternRegistry$GrokReloader."<init>":(Lorg/graylog2/grok/GrokPatternRegistry;Z)V
      73: aload_3
      74: invokestatic  #12                 // Method com/google/common/cache/CacheLoader.asyncReloading:(Lcom/google/common/cache/CacheLoader;Ljava/util/concurrent/Executor;)Lcom/google/common/cache/CacheLoader;
      77: invokevirtual #13                 // Method com/google/common/cache/CacheBuilder.build:(Lcom/google/common/cache/CacheLoader;)Lcom/google/common/cache/LoadingCache;
      80: putfield      #15                 // Field grokCacheNamedOnly:Lcom/google/common/cache/LoadingCache;
      83: aload_0
      84: invokespecial #16                 // Method reload:()V
      87: aload_1
      88: aload_0
      89: invokevirtual #17                 // Method com/google/common/eventbus/EventBus.register:(Ljava/lang/Object;)V
      92: return

  public void grokPatternsUpdated(org.graylog2.grok.GrokPatternsUpdatedEvent);
    Code:
       0: aload_0
       1: invokespecial #16                 // Method reload:()V
       4: return

  public void grokPatternsDeleted(org.graylog2.grok.GrokPatternsDeletedEvent);
    Code:
       0: aload_0
       1: invokespecial #16                 // Method reload:()V
       4: return

  public io.krakens.grok.api.Grok cachedGrokForPattern(java.lang.String);
    Code:
       0: aload_0
       1: aload_1
       2: iconst_0
       3: invokevirtual #18                 // Method cachedGrokForPattern:(Ljava/lang/String;Z)Lio/krakens/grok/api/Grok;
       6: areturn

  public io.krakens.grok.api.Grok cachedGrokForPattern(java.lang.String, boolean);
    Code:
       0: iload_2
       1: ifeq          18
       4: aload_0
       5: getfield      #15                 // Field grokCacheNamedOnly:Lcom/google/common/cache/LoadingCache;
       8: aload_1
       9: invokeinterface #19,  2           // InterfaceMethod com/google/common/cache/LoadingCache.get:(Ljava/lang/Object;)Ljava/lang/Object;
      14: checkcast     #20                 // class io/krakens/grok/api/Grok
      17: areturn
      18: aload_0
      19: getfield      #14                 // Field grokCache:Lcom/google/common/cache/LoadingCache;
      22: aload_1
      23: invokeinterface #19,  2           // InterfaceMethod com/google/common/cache/LoadingCache.get:(Ljava/lang/Object;)Ljava/lang/Object;
      28: checkcast     #20                 // class io/krakens/grok/api/Grok
      31: areturn
      32: astore_3
      33: aload_3
      34: invokestatic  #23                 // Method com/google/common/base/Throwables.getRootCause:(Ljava/lang/Throwable;)Ljava/lang/Throwable;
      37: astore        4
      39: getstatic     #24                 // Field log:Lorg/slf4j/Logger;
      42: ldc           #25                 // String Unable to load grok pattern {} into cache
      44: aload_1
      45: aload         4
      47: invokeinterface #26,  4           // InterfaceMethod org/slf4j/Logger.error:(Ljava/lang/String;Ljava/lang/Object;Ljava/lang/Object;)V
      52: new           #27                 // class java/lang/RuntimeException
      55: dup
      56: aload         4
      58: invokespecial #28                 // Method java/lang/RuntimeException."<init>":(Ljava/lang/Throwable;)V
      61: athrow
    Exception table:
       from    to  target type
           0    17    32   Class com/google/common/util/concurrent/UncheckedExecutionException
           0    17    32   Class java/util/concurrent/ExecutionException
          18    31    32   Class com/google/common/util/concurrent/UncheckedExecutionException
          18    31    32   Class java/util/concurrent/ExecutionException

  private void reload();
    Code:
       0: aload_0
       1: getfield      #6                  // Field grokPatternService:Lorg/graylog2/grok/GrokPatternService;
       4: invokeinterface #29,  1           // InterfaceMethod org/graylog2/grok/GrokPatternService.loadAll:()Ljava/util/Set;
       9: astore_1
      10: aload_0
      11: getfield      #5                  // Field patterns:Ljava/util/concurrent/atomic/AtomicReference;
      14: aload_1
      15: invokevirtual #30                 // Method java/util/concurrent/atomic/AtomicReference.set:(Ljava/lang/Object;)V
      18: aload_0
      19: getfield      #14                 // Field grokCache:Lcom/google/common/cache/LoadingCache;
      22: invokeinterface #31,  1           // InterfaceMethod com/google/common/cache/LoadingCache.invalidateAll:()V
      27: aload_0
      28: getfield      #15                 // Field grokCacheNamedOnly:Lcom/google/common/cache/LoadingCache;
      31: invokeinterface #31,  1           // InterfaceMethod com/google/common/cache/LoadingCache.invalidateAll:()V
      36: return

  public java.util.Set<org.graylog2.grok.GrokPattern> patterns();
    Code:
       0: aload_0
       1: getfield      #5                  // Field patterns:Ljava/util/concurrent/atomic/AtomicReference;
       4: invokevirtual #32                 // Method java/util/concurrent/atomic/AtomicReference.get:()Ljava/lang/Object;
       7: checkcast     #33                 // class java/util/Set
      10: areturn

  static {};
    Code:
       0: ldc           #34                 // class org/graylog2/grok/GrokPatternRegistry
       2: invokestatic  #35                 // Method org/slf4j/LoggerFactory.getLogger:(Ljava/lang/Class;)Lorg/slf4j/Logger;
       5: putstatic     #24                 // Field log:Lorg/slf4j/Logger;
       8: return
}
