Compiled from "DuplicatesPredicate.java"
public class org.springframework.cglib.core.DuplicatesPredicate implements org.springframework.cglib.core.Predicate {
  private final java.util.Set unique;

  private final java.util.Set rejected;

  public org.springframework.cglib.core.DuplicatesPredicate();
    Code:
       0: aload_0
       1: invokespecial #17                 // Method java/lang/Object."<init>":()V
       4: aload_0
       5: new           #19                 // class java/util/HashSet
       8: dup
       9: invokespecial #20                 // Method java/util/HashSet."<init>":()V
      12: putfield      #22                 // Field unique:Ljava/util/Set;
      15: aload_0
      16: invokestatic  #28                 // Method java/util/Collections.emptySet:()Ljava/util/Set;
      19: putfield      #30                 // Field rejected:Ljava/util/Set;
      22: return

  public org.springframework.cglib.core.DuplicatesPredicate(java.util.List);
    Code:
       0: aload_0
       1: invokespecial #17                 // Method java/lang/Object."<init>":()V
       4: aload_0
       5: new           #19                 // class java/util/HashSet
       8: dup
       9: invokespecial #20                 // Method java/util/HashSet."<init>":()V
      12: putfield      #30                 // Field rejected:Ljava/util/Set;
      15: aload_0
      16: new           #19                 // class java/util/HashSet
      19: dup
      20: invokespecial #20                 // Method java/util/HashSet."<init>":()V
      23: putfield      #22                 // Field unique:Ljava/util/Set;
      26: new           #37                 // class java/util/HashMap
      29: dup
      30: invokespecial #38                 // Method java/util/HashMap."<init>":()V
      33: astore_2
      34: new           #37                 // class java/util/HashMap
      37: dup
      38: invokespecial #38                 // Method java/util/HashMap."<init>":()V
      41: astore_3
      42: aload_1
      43: invokeinterface #44,  1           // InterfaceMethod java/util/List.iterator:()Ljava/util/Iterator;
      48: astore        4
      50: aload         4
      52: invokeinterface #50,  1           // InterfaceMethod java/util/Iterator.hasNext:()Z
      57: ifeq          156
      60: aload         4
      62: invokeinterface #54,  1           // InterfaceMethod java/util/Iterator.next:()Ljava/lang/Object;
      67: astore        5
      69: aload         5
      71: checkcast     #56                 // class java/lang/reflect/Method
      74: astore        6
      76: aload         6
      78: invokestatic  #62                 // Method org/springframework/cglib/core/MethodWrapper.create:(Ljava/lang/reflect/Method;)Ljava/lang/Object;
      81: astore        7
      83: aload_2
      84: aload         7
      86: invokeinterface #68,  2           // InterfaceMethod java/util/Map.get:(Ljava/lang/Object;)Ljava/lang/Object;
      91: checkcast     #56                 // class java/lang/reflect/Method
      94: astore        8
      96: aload         8
      98: ifnonnull     115
     101: aload_2
     102: aload         7
     104: aload         6
     106: invokeinterface #72,  3           // InterfaceMethod java/util/Map.put:(Ljava/lang/Object;Ljava/lang/Object;)Ljava/lang/Object;
     111: pop
     112: goto          153
     115: aload_3
     116: aload         7
     118: invokeinterface #76,  2           // InterfaceMethod java/util/Map.containsKey:(Ljava/lang/Object;)Z
     123: ifne          153
     126: aload         8
     128: invokevirtual #79                 // Method java/lang/reflect/Method.isBridge:()Z
     131: ifeq          153
     134: aload         6
     136: invokevirtual #79                 // Method java/lang/reflect/Method.isBridge:()Z
     139: ifne          153
     142: aload_3
     143: aload         7
     145: aload         8
     147: invokeinterface #72,  3           // InterfaceMethod java/util/Map.put:(Ljava/lang/Object;Ljava/lang/Object;)Ljava/lang/Object;
     152: pop
     153: goto          50
     156: aload_3
     157: invokeinterface #82,  1           // InterfaceMethod java/util/Map.isEmpty:()Z
     162: ifne          386
     165: new           #19                 // class java/util/HashSet
     168: dup
     169: invokespecial #20                 // Method java/util/HashSet."<init>":()V
     172: astore        4
     174: new           #9                  // class org/springframework/cglib/core/DuplicatesPredicate$UnnecessaryBridgeFinder
     177: dup
     178: aload_0
     179: getfield      #30                 // Field rejected:Ljava/util/Set;
     182: invokespecial #85                 // Method org/springframework/cglib/core/DuplicatesPredicate$UnnecessaryBridgeFinder."<init>":(Ljava/util/Set;)V
     185: astore        5
     187: aload_3
     188: invokeinterface #89,  1           // InterfaceMethod java/util/Map.values:()Ljava/util/Collection;
     193: invokeinterface #92,  1           // InterfaceMethod java/util/Collection.iterator:()Ljava/util/Iterator;
     198: astore        6
     200: aload         6
     202: invokeinterface #50,  1           // InterfaceMethod java/util/Iterator.hasNext:()Z
     207: ifeq          249
     210: aload         6
     212: invokeinterface #54,  1           // InterfaceMethod java/util/Iterator.next:()Ljava/lang/Object;
     217: astore        7
     219: aload         7
     221: checkcast     #56                 // class java/lang/reflect/Method
     224: astore        8
     226: aload         4
     228: aload         8
     230: invokevirtual #96                 // Method java/lang/reflect/Method.getDeclaringClass:()Ljava/lang/Class;
     233: invokeinterface #101,  2          // InterfaceMethod java/util/Set.add:(Ljava/lang/Object;)Z
     238: pop
     239: aload         5
     241: aload         8
     243: invokevirtual #105                // Method org/springframework/cglib/core/DuplicatesPredicate$UnnecessaryBridgeFinder.addSuspectMethod:(Ljava/lang/reflect/Method;)V
     246: goto          200
     249: aload         4
     251: invokeinterface #106,  1          // InterfaceMethod java/util/Set.iterator:()Ljava/util/Iterator;
     256: astore        6
     258: aload         6
     260: invokeinterface #50,  1           // InterfaceMethod java/util/Iterator.hasNext:()Z
     265: ifeq          386
     268: aload         6
     270: invokeinterface #54,  1           // InterfaceMethod java/util/Iterator.next:()Ljava/lang/Object;
     275: astore        7
     277: aload         7
     279: checkcast     #108                // class java/lang/Class
     282: astore        8
     284: aload         8
     286: invokestatic  #112                // Method getClassLoader:(Ljava/lang/Class;)Ljava/lang/ClassLoader;
     289: astore        9
     291: aload         9
     293: ifnonnull     299
     296: goto          258
     299: aload         9
     301: new           #114                // class java/lang/StringBuilder
     304: dup
     305: invokespecial #115                // Method java/lang/StringBuilder."<init>":()V
     308: aload         8
     310: invokevirtual #119                // Method java/lang/Class.getName:()Ljava/lang/String;
     313: bipush        46
     315: bipush        47
     317: invokevirtual #125                // Method java/lang/String.replace:(CC)Ljava/lang/String;
     320: invokevirtual #129                // Method java/lang/StringBuilder.append:(Ljava/lang/String;)Ljava/lang/StringBuilder;
     323: ldc           #131                // String .class
     325: invokevirtual #129                // Method java/lang/StringBuilder.append:(Ljava/lang/String;)Ljava/lang/StringBuilder;
     328: invokevirtual #134                // Method java/lang/StringBuilder.toString:()Ljava/lang/String;
     331: invokevirtual #140                // Method java/lang/ClassLoader.getResourceAsStream:(Ljava/lang/String;)Ljava/io/InputStream;
     334: astore        10
     336: aload         10
     338: ifnonnull     344
     341: goto          258
     344: new           #142                // class org/springframework/asm/ClassReader
     347: dup
     348: aload         10
     350: invokespecial #145                // Method org/springframework/asm/ClassReader."<init>":(Ljava/io/InputStream;)V
     353: aload         5
     355: bipush        6
     357: invokevirtual #149                // Method org/springframework/asm/ClassReader.accept:(Lorg/springframework/asm/ClassVisitor;I)V
     360: aload         10
     362: invokevirtual #154                // Method java/io/InputStream.close:()V
     365: goto          378
     368: astore        11
     370: aload         10
     372: invokevirtual #154                // Method java/io/InputStream.close:()V
     375: aload         11
     377: athrow
     378: goto          383
     381: astore        9
     383: goto          258
     386: return
    Exception table:
       from    to  target type
         344   360   368   any
         368   370   368   any
         284   296   381   Class java/io/IOException
         299   341   381   Class java/io/IOException
         344   378   381   Class java/io/IOException

  public boolean evaluate(java.lang.Object);
    Code:
       0: aload_0
       1: getfield      #30                 // Field rejected:Ljava/util/Set;
       4: aload_1
       5: invokeinterface #179,  2          // InterfaceMethod java/util/Set.contains:(Ljava/lang/Object;)Z
      10: ifne          36
      13: aload_0
      14: getfield      #22                 // Field unique:Ljava/util/Set;
      17: aload_1
      18: checkcast     #56                 // class java/lang/reflect/Method
      21: invokestatic  #62                 // Method org/springframework/cglib/core/MethodWrapper.create:(Ljava/lang/reflect/Method;)Ljava/lang/Object;
      24: invokeinterface #101,  2          // InterfaceMethod java/util/Set.add:(Ljava/lang/Object;)Z
      29: ifeq          36
      32: iconst_1
      33: goto          37
      36: iconst_0
      37: ireturn

  private static java.lang.ClassLoader getClassLoader(java.lang.Class);
    Code:
       0: aload_0
       1: invokevirtual #183                // Method java/lang/Class.getClassLoader:()Ljava/lang/ClassLoader;
       4: astore_1
       5: aload_1
       6: ifnonnull     15
       9: ldc           #2                  // class org/springframework/cglib/core/DuplicatesPredicate
      11: invokevirtual #183                // Method java/lang/Class.getClassLoader:()Ljava/lang/ClassLoader;
      14: astore_1
      15: aload_1
      16: ifnonnull     26
      19: invokestatic  #189                // Method java/lang/Thread.currentThread:()Ljava/lang/Thread;
      22: invokevirtual #192                // Method java/lang/Thread.getContextClassLoader:()Ljava/lang/ClassLoader;
      25: astore_1
      26: aload_1
      27: areturn
}
