Compiled from "EmitUtils.java"
final class org.springframework.cglib.core.EmitUtils$9 implements org.springframework.cglib.core.ProcessArrayCallback {
  final org.springframework.cglib.core.CodeEmitter val$e;

  final org.springframework.cglib.core.EmitUtils$ArrayDelimiters val$d;

  final org.springframework.cglib.core.internal.CustomizerRegistry val$registry;

  org.springframework.cglib.core.EmitUtils$9(org.springframework.cglib.core.CodeEmitter, org.springframework.cglib.core.EmitUtils$ArrayDelimiters, org.springframework.cglib.core.internal.CustomizerRegistry);
    Code:
       0: aload_0
       1: aload_1
       2: putfield      #25                 // Field val$e:Lorg/springframework/cglib/core/CodeEmitter;
       5: aload_0
       6: aload_2
       7: putfield      #27                 // Field val$d:Lorg/springframework/cglib/core/EmitUtils$ArrayDelimiters;
      10: aload_0
      11: aload_3
      12: putfield      #29                 // Field val$registry:Lorg/springframework/cglib/core/internal/CustomizerRegistry;
      15: aload_0
      16: invokespecial #32                 // Method java/lang/Object."<init>":()V
      19: return

  public void processElement(org.springframework.asm.Type);
    Code:
       0: aload_0
       1: getfield      #25                 // Field val$e:Lorg/springframework/cglib/core/CodeEmitter;
       4: aload_1
       5: aload_0
       6: getfield      #27                 // Field val$d:Lorg/springframework/cglib/core/EmitUtils$ArrayDelimiters;
       9: aload_0
      10: getfield      #29                 // Field val$registry:Lorg/springframework/cglib/core/internal/CustomizerRegistry;
      13: aload_0
      14: invokestatic  #40                 // Method org/springframework/cglib/core/EmitUtils.access$300:(Lorg/springframework/cglib/core/CodeEmitter;Lorg/springframework/asm/Type;Lorg/springframework/cglib/core/EmitUtils$ArrayDelimiters;Lorg/springframework/cglib/core/internal/CustomizerRegistry;Lorg/springframework/cglib/core/ProcessArrayCallback;)V
      17: aload_0
      18: getfield      #25                 // Field val$e:Lorg/springframework/cglib/core/CodeEmitter;
      21: aload_0
      22: getfield      #27                 // Field val$d:Lorg/springframework/cglib/core/EmitUtils$ArrayDelimiters;
      25: invokestatic  #44                 // Method org/springframework/cglib/core/EmitUtils$ArrayDelimiters.access$400:(Lorg/springframework/cglib/core/EmitUtils$ArrayDelimiters;)Ljava/lang/String;
      28: invokevirtual #50                 // Method org/springframework/cglib/core/CodeEmitter.push:(Ljava/lang/String;)V
      31: aload_0
      32: getfield      #25                 // Field val$e:Lorg/springframework/cglib/core/CodeEmitter;
      35: getstatic     #56                 // Field org/springframework/cglib/core/Constants.TYPE_STRING_BUFFER:Lorg/springframework/asm/Type;
      38: invokestatic  #60                 // Method org/springframework/cglib/core/EmitUtils.access$500:()Lorg/springframework/cglib/core/Signature;
      41: invokevirtual #64                 // Method org/springframework/cglib/core/CodeEmitter.invoke_virtual:(Lorg/springframework/asm/Type;Lorg/springframework/cglib/core/Signature;)V
      44: return
}
