Compiled from "ReflectUtils.java"
final class org.springframework.cglib.core.ReflectUtils$4 implements java.security.PrivilegedExceptionAction {
  org.springframework.cglib.core.ReflectUtils$4();
    Code:
       0: aload_0
       1: invokespecial #1                  // Method java/lang/Object."<init>":()V
       4: return

  public java.lang.Object run() throws java.lang.Exception;
    Code:
       0: ldc           #2                  // class java/lang/Object
       2: invokevirtual #3                  // Method java/lang/Class.getDeclaredMethods:()[Ljava/lang/reflect/Method;
       5: astore_1
       6: aload_1
       7: astore_2
       8: aload_2
       9: arraylength
      10: istore_3
      11: iconst_0
      12: istore        4
      14: iload         4
      16: iload_3
      17: if_icmpge     70
      20: aload_2
      21: iload         4
      23: aaload
      24: astore        5
      26: ldc           #4                  // String finalize
      28: aload         5
      30: invokevirtual #5                  // Method java/lang/reflect/Method.getName:()Ljava/lang/String;
      33: invokevirtual #6                  // Method java/lang/String.equals:(Ljava/lang/Object;)Z
      36: ifne          64
      39: aload         5
      41: invokevirtual #7                  // Method java/lang/reflect/Method.getModifiers:()I
      44: bipush        24
      46: iand
      47: ifle          53
      50: goto          64
      53: invokestatic  #9                  // Method org/springframework/cglib/core/ReflectUtils.access$000:()Ljava/util/List;
      56: aload         5
      58: invokeinterface #10,  2           // InterfaceMethod java/util/List.add:(Ljava/lang/Object;)Z
      63: pop
      64: iinc          4, 1
      67: goto          14
      70: aconst_null
      71: areturn
}
