Compiled from "AbstractDistributionCommand.java"
public abstract class org.jboss.as.patching.cli.AbstractDistributionCommand implements org.aesh.command.Command<org.wildfly.core.cli.command.aesh.CLICommandInvocation> {
  private java.lang.String host;

  private java.io.File distribution;

  private java.util.List<java.io.File> modulePath;

  private java.util.List<java.io.File> bundlePath;

  private final java.lang.String action;

  static final java.lang.String lineSeparator;

  private static final java.lang.String HOME;

  private static final java.lang.String HOME_DIR;

  protected org.jboss.as.patching.cli.AbstractDistributionCommand(java.lang.String);
    Code:
       0: aload_0
       1: invokespecial #2                  // Method java/lang/Object."<init>":()V
       4: aload_0
       5: aload_1
       6: putfield      #3                  // Field action:Ljava/lang/String;
       9: return

  java.lang.String getHost();
    Code:
       0: aload_0
       1: getfield      #4                  // Field host:Ljava/lang/String;
       4: areturn

  java.lang.String getPatchStream();
    Code:
       0: aconst_null
       1: areturn

  public org.aesh.command.CommandResult execute(org.wildfly.core.cli.command.aesh.CLICommandInvocation) throws org.aesh.command.CommandException, java.lang.InterruptedException;
    Code:
       0: aload_0
       1: getfield      #4                  // Field host:Ljava/lang/String;
       4: ifnull        31
       7: aload_1
       8: invokeinterface #5,  1            // InterfaceMethod org/wildfly/core/cli/command/aesh/CLICommandInvocation.getCommandContext:()Lorg/jboss/as/cli/CommandContext;
      13: invokeinterface #6,  1            // InterfaceMethod org/jboss/as/cli/CommandContext.isDomainMode:()Z
      18: ifne          31
      21: new           #7                  // class org/aesh/command/CommandException
      24: dup
      25: ldc           #8                  // String The --host option is not available in the current context. Connection to the controller might be unavailable or not running in domain mode.
      27: invokespecial #9                  // Method org/aesh/command/CommandException."<init>":(Ljava/lang/String;)V
      30: athrow
      31: aload_0
      32: getfield      #4                  // Field host:Ljava/lang/String;
      35: ifnonnull     62
      38: aload_1
      39: invokeinterface #5,  1            // InterfaceMethod org/wildfly/core/cli/command/aesh/CLICommandInvocation.getCommandContext:()Lorg/jboss/as/cli/CommandContext;
      44: invokeinterface #6,  1            // InterfaceMethod org/jboss/as/cli/CommandContext.isDomainMode:()Z
      49: ifeq          62
      52: new           #7                  // class org/aesh/command/CommandException
      55: dup
      56: ldc           #10                 // String The --host option must be used in domain mode.
      58: invokespecial #9                  // Method org/aesh/command/CommandException."<init>":(Ljava/lang/String;)V
      61: athrow
      62: aload_0
      63: aload_1
      64: invokevirtual #11                 // Method verifyManagementVersion:(Lorg/wildfly/core/cli/command/aesh/CLICommandInvocation;)V
      67: goto          89
      70: astore_2
      71: new           #7                  // class org/aesh/command/CommandException
      74: dup
      75: aload_0
      76: getfield      #3                  // Field action:Ljava/lang/String;
      79: invokedynamic #13,  0             // InvokeDynamic #0:makeConcatWithConstants:(Ljava/lang/String;)Ljava/lang/String;
      84: aload_2
      85: invokespecial #14                 // Method org/aesh/command/CommandException."<init>":(Ljava/lang/String;Ljava/lang/Throwable;)V
      88: athrow
      89: aload_0
      90: aload_1
      91: invokeinterface #5,  1            // InterfaceMethod org/wildfly/core/cli/command/aesh/CLICommandInvocation.getCommandContext:()Lorg/jboss/as/cli/CommandContext;
      96: invokevirtual #15                 // Method createPatchOperationTarget:(Lorg/jboss/as/cli/CommandContext;)Lorg/jboss/as/patching/tool/PatchOperationTarget;
      99: astore_2
     100: aload_0
     101: aload_1
     102: invokeinterface #5,  1            // InterfaceMethod org/wildfly/core/cli/command/aesh/CLICommandInvocation.getCommandContext:()Lorg/jboss/as/cli/CommandContext;
     107: invokevirtual #16                 // Method createPatchOperationBuilder:(Lorg/jboss/as/cli/CommandContext;)Lorg/jboss/as/patching/tool/PatchOperationBuilder;
     110: astore_3
     111: aload_3
     112: aload_2
     113: invokeinterface #17,  2           // InterfaceMethod org/jboss/as/patching/tool/PatchOperationBuilder.execute:(Lorg/jboss/as/patching/tool/PatchOperationTarget;)Lorg/jboss/dmr/ModelNode;
     118: astore        4
     120: goto          144
     123: astore        5
     125: new           #7                  // class org/aesh/command/CommandException
     128: dup
     129: aload_0
     130: getfield      #3                  // Field action:Ljava/lang/String;
     133: invokedynamic #13,  0             // InvokeDynamic #0:makeConcatWithConstants:(Ljava/lang/String;)Ljava/lang/String;
     138: aload         5
     140: invokespecial #14                 // Method org/aesh/command/CommandException."<init>":(Ljava/lang/String;Ljava/lang/Throwable;)V
     143: athrow
     144: aload         4
     146: invokestatic  #19                 // Method org/jboss/as/cli/Util.isSuccess:(Lorg/jboss/dmr/ModelNode;)Z
     149: ifne          351
     152: aload         4
     154: ldc           #20                 // String failure-description
     156: invokevirtual #21                 // Method org/jboss/dmr/ModelNode.get:(Ljava/lang/String;)Lorg/jboss/dmr/ModelNode;
     159: astore        5
     161: aload         5
     163: invokevirtual #22                 // Method org/jboss/dmr/ModelNode.isDefined:()Z
     166: ifne          187
     169: new           #7                  // class org/aesh/command/CommandException
     172: dup
     173: aload         4
     175: invokevirtual #23                 // Method org/jboss/dmr/ModelNode.asString:()Ljava/lang/String;
     178: invokedynamic #24,  0             // InvokeDynamic #1:makeConcatWithConstants:(Ljava/lang/String;)Ljava/lang/String;
     183: invokespecial #9                  // Method org/aesh/command/CommandException."<init>":(Ljava/lang/String;)V
     186: athrow
     187: aload         5
     189: ldc           #26                 // String conflicts
     191: invokevirtual #27                 // Method org/jboss/dmr/ModelNode.has:(Ljava/lang/String;)Z
     194: ifeq          338
     197: new           #28                 // class java/lang/StringBuilder
     200: dup
     201: invokespecial #29                 // Method java/lang/StringBuilder."<init>":()V
     204: astore        6
     206: aload         6
     208: aload         5
     210: ldc           #30                 // String message
     212: invokevirtual #21                 // Method org/jboss/dmr/ModelNode.get:(Ljava/lang/String;)Lorg/jboss/dmr/ModelNode;
     215: invokevirtual #23                 // Method org/jboss/dmr/ModelNode.asString:()Ljava/lang/String;
     218: invokevirtual #31                 // Method java/lang/StringBuilder.append:(Ljava/lang/String;)Ljava/lang/StringBuilder;
     221: ldc           #32                 // String :
     223: invokevirtual #31                 // Method java/lang/StringBuilder.append:(Ljava/lang/String;)Ljava/lang/StringBuilder;
     226: pop
     227: aload         5
     229: ldc           #26                 // String conflicts
     231: invokevirtual #21                 // Method org/jboss/dmr/ModelNode.get:(Ljava/lang/String;)Lorg/jboss/dmr/ModelNode;
     234: astore        7
     236: ldc           #33                 // String
     238: astore        8
     240: aload         7
     242: ldc           #34                 // String bundles
     244: invokevirtual #27                 // Method org/jboss/dmr/ModelNode.has:(Ljava/lang/String;)Z
     247: ifeq          265
     250: aload         6
     252: aload         7
     254: ldc           #33                 // String
     256: ldc           #34                 // String bundles
     258: invokestatic  #35                 // Method formatConflictsList:(Ljava/lang/StringBuilder;Lorg/jboss/dmr/ModelNode;Ljava/lang/String;Ljava/lang/String;)V
     261: ldc           #36                 // String ,
     263: astore        8
     265: aload         7
     267: ldc           #37                 // String modules
     269: invokevirtual #27                 // Method org/jboss/dmr/ModelNode.has:(Ljava/lang/String;)Z
     272: ifeq          290
     275: aload         6
     277: aload         7
     279: aload         8
     281: ldc           #37                 // String modules
     283: invokestatic  #35                 // Method formatConflictsList:(Ljava/lang/StringBuilder;Lorg/jboss/dmr/ModelNode;Ljava/lang/String;Ljava/lang/String;)V
     286: ldc           #36                 // String ,
     288: astore        8
     290: aload         7
     292: ldc           #38                 // String misc
     294: invokevirtual #27                 // Method org/jboss/dmr/ModelNode.has:(Ljava/lang/String;)Z
     297: ifeq          311
     300: aload         6
     302: aload         7
     304: aload         8
     306: ldc           #38                 // String misc
     308: invokestatic  #35                 // Method formatConflictsList:(Ljava/lang/StringBuilder;Lorg/jboss/dmr/ModelNode;Ljava/lang/String;Ljava/lang/String;)V
     311: aload         6
     313: getstatic     #39                 // Field lineSeparator:Ljava/lang/String;
     316: invokevirtual #31                 // Method java/lang/StringBuilder.append:(Ljava/lang/String;)Ljava/lang/StringBuilder;
     319: ldc           #40                 // String Use the --override-all, --override=[] or --preserve=[] arguments in order to resolve the conflict.
     321: invokevirtual #31                 // Method java/lang/StringBuilder.append:(Ljava/lang/String;)Ljava/lang/StringBuilder;
     324: pop
     325: new           #7                  // class org/aesh/command/CommandException
     328: dup
     329: aload         6
     331: invokevirtual #41                 // Method java/lang/StringBuilder.toString:()Ljava/lang/String;
     334: invokespecial #9                  // Method org/aesh/command/CommandException."<init>":(Ljava/lang/String;)V
     337: athrow
     338: new           #7                  // class org/aesh/command/CommandException
     341: dup
     342: aload         4
     344: invokestatic  #42                 // Method org/jboss/as/cli/Util.getFailureDescription:(Lorg/jboss/dmr/ModelNode;)Ljava/lang/String;
     347: invokespecial #9                  // Method org/aesh/command/CommandException."<init>":(Ljava/lang/String;)V
     350: athrow
     351: aload_0
     352: aload_1
     353: invokeinterface #5,  1            // InterfaceMethod org/wildfly/core/cli/command/aesh/CLICommandInvocation.getCommandContext:()Lorg/jboss/as/cli/CommandContext;
     358: aload         4
     360: invokevirtual #43                 // Method handleResponse:(Lorg/jboss/as/cli/CommandContext;Lorg/jboss/dmr/ModelNode;)V
     363: getstatic     #44                 // Field org/aesh/command/CommandResult.SUCCESS:Lorg/aesh/command/CommandResult;
     366: areturn
    Exception table:
       from    to  target type
          62    67    70   Class java/io/IOException
         111   120   123   Class java/lang/Exception

  protected void handleResponse(org.jboss.as.cli.CommandContext, org.jboss.dmr.ModelNode) throws org.aesh.command.CommandException;
    Code:
       0: aload_1
       1: aload_2
       2: iconst_0
       3: invokevirtual #45                 // Method org/jboss/dmr/ModelNode.toJSONString:(Z)Ljava/lang/String;
       6: invokeinterface #46,  2           // InterfaceMethod org/jboss/as/cli/CommandContext.printLine:(Ljava/lang/String;)V
      11: return

  protected abstract org.jboss.as.patching.tool.PatchOperationBuilder createPatchOperationBuilder(org.jboss.as.cli.CommandContext) throws org.aesh.command.CommandException;

  org.jboss.as.patching.tool.PatchOperationTarget createPatchOperationTarget(org.jboss.as.cli.CommandContext) throws org.aesh.command.CommandException;
    Code:
       0: aload_1
       1: invokeinterface #47,  1           // InterfaceMethod org/jboss/as/cli/CommandContext.getParsedCommandLine:()Lorg/jboss/as/cli/operation/ParsedCommandLine;
       6: astore_3
       7: aload_1
       8: invokeinterface #48,  1           // InterfaceMethod org/jboss/as/cli/CommandContext.getModelControllerClient:()Lorg/jboss/as/controller/client/ModelControllerClient;
      13: ifnull        106
      16: aload_0
      17: getfield      #49                 // Field distribution:Ljava/io/File;
      20: ifnull        33
      23: new           #7                  // class org/aesh/command/CommandException
      26: dup
      27: ldc           #50                 // String --distribution is not allowed when connected to the controller.
      29: invokespecial #9                  // Method org/aesh/command/CommandException."<init>":(Ljava/lang/String;)V
      32: athrow
      33: aload_0
      34: getfield      #51                 // Field modulePath:Ljava/util/List;
      37: ifnull        50
      40: new           #7                  // class org/aesh/command/CommandException
      43: dup
      44: ldc           #52                 // String --module-path is not allowed when connected to the controller.
      46: invokespecial #9                  // Method org/aesh/command/CommandException."<init>":(Ljava/lang/String;)V
      49: athrow
      50: aload_0
      51: getfield      #53                 // Field bundlePath:Ljava/util/List;
      54: ifnull        67
      57: new           #7                  // class org/aesh/command/CommandException
      60: dup
      61: ldc           #54                 // String --bundle-path is not allowed when connected to the controller.
      63: invokespecial #9                  // Method org/aesh/command/CommandException."<init>":(Ljava/lang/String;)V
      66: athrow
      67: aload_1
      68: invokeinterface #6,  1            // InterfaceMethod org/jboss/as/cli/CommandContext.isDomainMode:()Z
      73: ifeq          93
      76: aload_0
      77: getfield      #4                  // Field host:Ljava/lang/String;
      80: aload_1
      81: invokeinterface #48,  1           // InterfaceMethod org/jboss/as/cli/CommandContext.getModelControllerClient:()Lorg/jboss/as/controller/client/ModelControllerClient;
      86: invokestatic  #55                 // Method org/jboss/as/patching/tool/PatchOperationTarget.createHost:(Ljava/lang/String;Lorg/jboss/as/controller/client/ModelControllerClient;)Lorg/jboss/as/patching/tool/PatchOperationTarget;
      89: astore_2
      90: goto          172
      93: aload_1
      94: invokeinterface #48,  1           // InterfaceMethod org/jboss/as/cli/CommandContext.getModelControllerClient:()Lorg/jboss/as/controller/client/ModelControllerClient;
      99: invokestatic  #56                 // Method org/jboss/as/patching/tool/PatchOperationTarget.createStandalone:(Lorg/jboss/as/controller/client/ModelControllerClient;)Lorg/jboss/as/patching/tool/PatchOperationTarget;
     102: astore_2
     103: goto          172
     106: aload_0
     107: invokevirtual #57                 // Method getJBossHome:()Ljava/io/File;
     110: astore        4
     112: aload_0
     113: getfield      #51                 // Field modulePath:Ljava/util/List;
     116: aload_3
     117: aload         4
     119: ldc           #37                 // String modules
     121: invokestatic  #58                 // Method getFSArgument:(Ljava/util/List;Lorg/jboss/as/cli/operation/ParsedCommandLine;Ljava/io/File;Ljava/lang/String;)Ljava/util/List;
     124: astore        5
     126: aload_0
     127: getfield      #53                 // Field bundlePath:Ljava/util/List;
     130: aload_3
     131: aload         4
     133: ldc           #34                 // String bundles
     135: invokestatic  #58                 // Method getFSArgument:(Ljava/util/List;Lorg/jboss/as/cli/operation/ParsedCommandLine;Ljava/io/File;Ljava/lang/String;)Ljava/util/List;
     138: astore        6
     140: aload         4
     142: aload         5
     144: aload         6
     146: invokestatic  #59                 // Method org/jboss/as/patching/tool/PatchOperationTarget.createLocal:(Ljava/io/File;Ljava/util/List;Ljava/util/List;)Lorg/jboss/as/patching/tool/PatchOperationTarget;
     149: astore_2
     150: goto          172
     153: astore        7
     155: new           #7                  // class org/aesh/command/CommandException
     158: dup
     159: aload         4
     161: invokedynamic #60,  0             // InvokeDynamic #2:makeConcatWithConstants:(Ljava/io/File;)Ljava/lang/String;
     166: aload         7
     168: invokespecial #14                 // Method org/aesh/command/CommandException."<init>":(Ljava/lang/String;Ljava/lang/Throwable;)V
     171: athrow
     172: aload_2
     173: areturn
    Exception table:
       from    to  target type
         140   150   153   Class java/lang/Exception

  private java.io.File getJBossHome();
    Code:
       0: aload_0
       1: getfield      #49                 // Field distribution:Ljava/io/File;
       4: ifnull        12
       7: aload_0
       8: getfield      #49                 // Field distribution:Ljava/io/File;
      11: areturn
      12: invokestatic  #61                 // Method java/lang/System.getSecurityManager:()Ljava/lang/SecurityManager;
      15: ifnonnull     26
      18: ldc           #63                 // String JBOSS_HOME
      20: invokestatic  #64                 // Method java/lang/System.getenv:(Ljava/lang/String;)Ljava/lang/String;
      23: goto          41
      26: new           #65                 // class org/wildfly/security/manager/action/ReadEnvironmentPropertyAction
      29: dup
      30: ldc           #63                 // String JBOSS_HOME
      32: invokespecial #66                 // Method org/wildfly/security/manager/action/ReadEnvironmentPropertyAction."<init>":(Ljava/lang/String;)V
      35: invokestatic  #67                 // Method java/security/AccessController.doPrivileged:(Ljava/security/PrivilegedAction;)Ljava/lang/Object;
      38: checkcast     #68                 // class java/lang/String
      41: astore_1
      42: aload_1
      43: ifnonnull     76
      46: invokestatic  #61                 // Method java/lang/System.getSecurityManager:()Ljava/lang/SecurityManager;
      49: ifnonnull     60
      52: ldc           #69                 // String jboss.home.dir
      54: invokestatic  #70                 // Method java/lang/System.getProperty:(Ljava/lang/String;)Ljava/lang/String;
      57: goto          75
      60: new           #71                 // class org/wildfly/security/manager/action/ReadPropertyAction
      63: dup
      64: ldc           #69                 // String jboss.home.dir
      66: invokespecial #72                 // Method org/wildfly/security/manager/action/ReadPropertyAction."<init>":(Ljava/lang/String;)V
      69: invokestatic  #67                 // Method java/security/AccessController.doPrivileged:(Ljava/security/PrivilegedAction;)Ljava/lang/Object;
      72: checkcast     #68                 // class java/lang/String
      75: astore_1
      76: aload_1
      77: ifnonnull     89
      80: getstatic     #73                 // Field org/jboss/as/patching/logging/PatchLogger.ROOT_LOGGER:Lorg/jboss/as/patching/logging/PatchLogger;
      83: invokeinterface #74,  1           // InterfaceMethod org/jboss/as/patching/logging/PatchLogger.cliFailedToResolveDistribution:()Ljava/lang/IllegalStateException;
      88: athrow
      89: new           #75                 // class java/io/File
      92: dup
      93: aload_1
      94: invokespecial #76                 // Method java/io/File."<init>":(Ljava/lang/String;)V
      97: areturn

  private static java.util.List<java.io.File> getFSArgument(java.util.List<java.io.File>, org.jboss.as.cli.operation.ParsedCommandLine, java.io.File, java.lang.String);
    Code:
       0: aload_0
       1: ifnull        6
       4: aload_0
       5: areturn
       6: new           #75                 // class java/io/File
       9: dup
      10: aload_2
      11: aload_3
      12: invokespecial #77                 // Method java/io/File."<init>":(Ljava/io/File;Ljava/lang/String;)V
      15: invokestatic  #78                 // Method java/util/Collections.singletonList:(Ljava/lang/Object;)Ljava/util/List;
      18: areturn

  private static void formatConflictsList(java.lang.StringBuilder, org.jboss.dmr.ModelNode, java.lang.String, java.lang.String);
    Code:
       0: aload_0
       1: aload_2
       2: invokevirtual #31                 // Method java/lang/StringBuilder.append:(Ljava/lang/String;)Ljava/lang/StringBuilder;
       5: pop
       6: aload_1
       7: aload_3
       8: invokevirtual #21                 // Method org/jboss/dmr/ModelNode.get:(Ljava/lang/String;)Lorg/jboss/dmr/ModelNode;
      11: invokevirtual #79                 // Method org/jboss/dmr/ModelNode.asList:()Ljava/util/List;
      14: astore        4
      16: iconst_0
      17: istore        5
      19: iload         5
      21: aload         4
      23: invokeinterface #80,  1           // InterfaceMethod java/util/List.size:()I
      28: if_icmpge     80
      31: aload         4
      33: iload         5
      35: iinc          5, 1
      38: invokeinterface #81,  2           // InterfaceMethod java/util/List.get:(I)Ljava/lang/Object;
      43: checkcast     #82                 // class org/jboss/dmr/ModelNode
      46: astore        6
      48: aload_0
      49: aload         6
      51: invokevirtual #23                 // Method org/jboss/dmr/ModelNode.asString:()Ljava/lang/String;
      54: invokevirtual #31                 // Method java/lang/StringBuilder.append:(Ljava/lang/String;)Ljava/lang/StringBuilder;
      57: pop
      58: iload         5
      60: aload         4
      62: invokeinterface #80,  1           // InterfaceMethod java/util/List.size:()I
      67: if_icmpge     77
      70: aload_0
      71: ldc           #36                 // String ,
      73: invokevirtual #31                 // Method java/lang/StringBuilder.append:(Ljava/lang/String;)Ljava/lang/StringBuilder;
      76: pop
      77: goto          19
      80: return

  private void verifyManagementVersion(org.wildfly.core.cli.command.aesh.CLICommandInvocation) throws java.io.IOException, org.aesh.command.CommandException;
    Code:
       0: aload_1
       1: invokeinterface #5,  1            // InterfaceMethod org/wildfly/core/cli/command/aesh/CLICommandInvocation.getCommandContext:()Lorg/jboss/as/cli/CommandContext;
       6: invokeinterface #6,  1            // InterfaceMethod org/jboss/as/cli/CommandContext.isDomainMode:()Z
      11: ifeq          183
      14: aload_1
      15: invokeinterface #5,  1            // InterfaceMethod org/wildfly/core/cli/command/aesh/CLICommandInvocation.getCommandContext:()Lorg/jboss/as/cli/CommandContext;
      20: invokeinterface #48,  1           // InterfaceMethod org/jboss/as/cli/CommandContext.getModelControllerClient:()Lorg/jboss/as/controller/client/ModelControllerClient;
      25: astore_2
      26: aload_1
      27: invokeinterface #5,  1            // InterfaceMethod org/wildfly/core/cli/command/aesh/CLICommandInvocation.getCommandContext:()Lorg/jboss/as/cli/CommandContext;
      32: invokeinterface #48,  1           // InterfaceMethod org/jboss/as/cli/CommandContext.getModelControllerClient:()Lorg/jboss/as/controller/client/ModelControllerClient;
      37: pop
      38: new           #82                 // class org/jboss/dmr/ModelNode
      41: dup
      42: invokespecial #83                 // Method org/jboss/dmr/ModelNode."<init>":()V
      45: astore_3
      46: iconst_1
      47: anewarray     #84                 // class org/jboss/as/controller/PathElement
      50: dup
      51: iconst_0
      52: ldc           #85                 // String host
      54: aload_0
      55: getfield      #4                  // Field host:Ljava/lang/String;
      58: invokestatic  #86                 // Method org/jboss/as/controller/PathElement.pathElement:(Ljava/lang/String;Ljava/lang/String;)Lorg/jboss/as/controller/PathElement;
      61: aastore
      62: invokestatic  #87                 // Method org/jboss/as/controller/PathAddress.pathAddress:([Lorg/jboss/as/controller/PathElement;)Lorg/jboss/as/controller/PathAddress;
      65: astore        4
      67: aload_3
      68: ldc           #89                 // String address
      70: invokevirtual #21                 // Method org/jboss/dmr/ModelNode.get:(Ljava/lang/String;)Lorg/jboss/dmr/ModelNode;
      73: aload         4
      75: invokevirtual #90                 // Method org/jboss/as/controller/PathAddress.toModelNode:()Lorg/jboss/dmr/ModelNode;
      78: invokevirtual #91                 // Method org/jboss/dmr/ModelNode.set:(Lorg/jboss/dmr/ModelNode;)Lorg/jboss/dmr/ModelNode;
      81: pop
      82: aload_3
      83: ldc           #92                 // String operation
      85: invokevirtual #21                 // Method org/jboss/dmr/ModelNode.get:(Ljava/lang/String;)Lorg/jboss/dmr/ModelNode;
      88: ldc           #93                 // String query
      90: invokevirtual #94                 // Method org/jboss/dmr/ModelNode.set:(Ljava/lang/String;)Lorg/jboss/dmr/ModelNode;
      93: pop
      94: new           #82                 // class org/jboss/dmr/ModelNode
      97: dup
      98: invokespecial #83                 // Method org/jboss/dmr/ModelNode."<init>":()V
     101: invokevirtual #95                 // Method org/jboss/dmr/ModelNode.addEmptyList:()Lorg/jboss/dmr/ModelNode;
     104: astore        5
     106: aload         5
     108: ldc           #96                 // String management-major-version
     110: invokevirtual #97                 // Method org/jboss/dmr/ModelNode.add:(Ljava/lang/String;)Lorg/jboss/dmr/ModelNode;
     113: pop
     114: aload_3
     115: ldc           #98                 // String select
     117: invokevirtual #21                 // Method org/jboss/dmr/ModelNode.get:(Ljava/lang/String;)Lorg/jboss/dmr/ModelNode;
     120: aload         5
     122: invokevirtual #91                 // Method org/jboss/dmr/ModelNode.set:(Lorg/jboss/dmr/ModelNode;)Lorg/jboss/dmr/ModelNode;
     125: pop
     126: aload_2
     127: aload_3
     128: invokeinterface #99,  2           // InterfaceMethod org/jboss/as/controller/client/ModelControllerClient.execute:(Lorg/jboss/dmr/ModelNode;)Lorg/jboss/dmr/ModelNode;
     133: astore        6
     135: aload         6
     137: iconst_2
     138: anewarray     #68                 // class java/lang/String
     141: dup
     142: iconst_0
     143: ldc           #100                // String result
     145: aastore
     146: dup
     147: iconst_1
     148: ldc           #96                 // String management-major-version
     150: aastore
     151: invokevirtual #101                // Method org/jboss/dmr/ModelNode.get:([Ljava/lang/String;)Lorg/jboss/dmr/ModelNode;
     154: invokevirtual #102                // Method org/jboss/dmr/ModelNode.asInt:()I
     157: istore        7
     159: iload         7
     161: bipush        20
     163: if_icmple     183
     166: new           #7                  // class org/aesh/command/CommandException
     169: dup
     170: aload_0
     171: getfield      #4                  // Field host:Ljava/lang/String;
     174: invokedynamic #103,  0            // InvokeDynamic #3:makeConcatWithConstants:(Ljava/lang/String;)Ljava/lang/String;
     179: invokespecial #9                  // Method org/aesh/command/CommandException."<init>":(Ljava/lang/String;)V
     182: athrow
     183: return

  public org.aesh.command.CommandResult execute(org.aesh.command.invocation.CommandInvocation) throws org.aesh.command.CommandException, java.lang.InterruptedException;
    Code:
       0: aload_0
       1: aload_1
       2: checkcast     #104                // class org/wildfly/core/cli/command/aesh/CLICommandInvocation
       5: invokevirtual #105                // Method execute:(Lorg/wildfly/core/cli/command/aesh/CLICommandInvocation;)Lorg/aesh/command/CommandResult;
       8: areturn

  static {};
    Code:
       0: invokestatic  #61                 // Method java/lang/System.getSecurityManager:()Ljava/lang/SecurityManager;
       3: ifnonnull     14
       6: ldc           #106                // String line.separator
       8: invokestatic  #70                 // Method java/lang/System.getProperty:(Ljava/lang/String;)Ljava/lang/String;
      11: goto          29
      14: new           #71                 // class org/wildfly/security/manager/action/ReadPropertyAction
      17: dup
      18: ldc           #106                // String line.separator
      20: invokespecial #72                 // Method org/wildfly/security/manager/action/ReadPropertyAction."<init>":(Ljava/lang/String;)V
      23: invokestatic  #67                 // Method java/security/AccessController.doPrivileged:(Ljava/security/PrivilegedAction;)Ljava/lang/Object;
      26: checkcast     #68                 // class java/lang/String
      29: putstatic     #39                 // Field lineSeparator:Ljava/lang/String;
      32: return
}
