Compiled from "WidgetSummary.java"
public abstract class org.graylog2.rest.models.dashboards.responses.WidgetSummary {
  public org.graylog2.rest.models.dashboards.responses.WidgetSummary();
    Code:
       0: aload_0
       1: invokespecial #1                  // Method java/lang/Object."<init>":()V
       4: return

  public abstract java.lang.String id();

  public abstract java.lang.String description();

  public abstract java.lang.String type();

  public abstract int cacheTime();

  public abstract java.lang.String creatorUserId();

  public abstract java.util.Map<java.lang.String, java.lang.Object> config();

  public static org.graylog2.rest.models.dashboards.responses.WidgetSummary create(java.lang.String, java.lang.String, java.lang.String, int, java.lang.String, java.util.Map<java.lang.String, java.lang.Object>);
    Code:
       0: new           #2                  // class org/graylog2/rest/models/dashboards/responses/AutoValue_WidgetSummary
       3: dup
       4: aload_0
       5: aload_1
       6: aload_2
       7: iload_3
       8: aload         4
      10: aload         5
      12: invokespecial #3                  // Method org/graylog2/rest/models/dashboards/responses/AutoValue_WidgetSummary."<init>":(Ljava/lang/String;Ljava/lang/String;Ljava/lang/String;ILjava/lang/String;Ljava/util/Map;)V
      15: areturn
}
