Compiled from "KerberosSchemeFactory.java"
public class org.apache.http.impl.auth.KerberosSchemeFactory implements org.apache.http.auth.AuthSchemeFactory,org.apache.http.auth.AuthSchemeProvider {
  private final boolean stripPort;

  private final boolean useCanonicalHostname;

  public org.apache.http.impl.auth.KerberosSchemeFactory(boolean, boolean);
    Code:
       0: aload_0
       1: invokespecial #1                  // Method java/lang/Object."<init>":()V
       4: aload_0
       5: iload_1
       6: putfield      #2                  // Field stripPort:Z
       9: aload_0
      10: iload_2
      11: putfield      #3                  // Field useCanonicalHostname:Z
      14: return

  public org.apache.http.impl.auth.KerberosSchemeFactory(boolean);
    Code:
       0: aload_0
       1: invokespecial #1                  // Method java/lang/Object."<init>":()V
       4: aload_0
       5: iload_1
       6: putfield      #2                  // Field stripPort:Z
       9: aload_0
      10: iconst_1
      11: putfield      #3                  // Field useCanonicalHostname:Z
      14: return

  public org.apache.http.impl.auth.KerberosSchemeFactory();
    Code:
       0: aload_0
       1: iconst_1
       2: iconst_1
       3: invokespecial #4                  // Method "<init>":(ZZ)V
       6: return

  public boolean isStripPort();
    Code:
       0: aload_0
       1: getfield      #2                  // Field stripPort:Z
       4: ireturn

  public boolean isUseCanonicalHostname();
    Code:
       0: aload_0
       1: getfield      #3                  // Field useCanonicalHostname:Z
       4: ireturn

  public org.apache.http.auth.AuthScheme newInstance(org.apache.http.params.HttpParams);
    Code:
       0: new           #5                  // class org/apache/http/impl/auth/KerberosScheme
       3: dup
       4: aload_0
       5: getfield      #2                  // Field stripPort:Z
       8: aload_0
       9: getfield      #3                  // Field useCanonicalHostname:Z
      12: invokespecial #6                  // Method org/apache/http/impl/auth/KerberosScheme."<init>":(ZZ)V
      15: areturn

  public org.apache.http.auth.AuthScheme create(org.apache.http.protocol.HttpContext);
    Code:
       0: new           #5                  // class org/apache/http/impl/auth/KerberosScheme
       3: dup
       4: aload_0
       5: getfield      #2                  // Field stripPort:Z
       8: aload_0
       9: getfield      #3                  // Field useCanonicalHostname:Z
      12: invokespecial #6                  // Method org/apache/http/impl/auth/KerberosScheme."<init>":(ZZ)V
      15: areturn
}
