Compiled from "Node.java"
class org.jsoup.nodes.Node$OuterHtmlVisitor implements org.jsoup.select.NodeVisitor {
  private java.lang.StringBuilder accum;

  private org.jsoup.nodes.Document$OutputSettings out;

  org.jsoup.nodes.Node$OuterHtmlVisitor(java.lang.StringBuilder, org.jsoup.nodes.Document$OutputSettings);
    Code:
       0: aload_0
       1: invokespecial #1                  // Method java/lang/Object."<init>":()V
       4: aload_0
       5: aload_1
       6: putfield      #2                  // Field accum:Ljava/lang/StringBuilder;
       9: aload_0
      10: aload_2
      11: putfield      #3                  // Field out:Lorg/jsoup/nodes/Document$OutputSettings;
      14: return

  public void head(org.jsoup.nodes.Node, int);
    Code:
       0: aload_1
       1: aload_0
       2: getfield      #2                  // Field accum:Ljava/lang/StringBuilder;
       5: iload_2
       6: aload_0
       7: getfield      #3                  // Field out:Lorg/jsoup/nodes/Document$OutputSettings;
      10: invokevirtual #4                  // Method org/jsoup/nodes/Node.outerHtmlHead:(Ljava/lang/StringBuilder;ILorg/jsoup/nodes/Document$OutputSettings;)V
      13: return

  public void tail(org.jsoup.nodes.Node, int);
    Code:
       0: aload_1
       1: invokevirtual #5                  // Method org/jsoup/nodes/Node.nodeName:()Ljava/lang/String;
       4: ldc           #6                  // String #text
       6: invokevirtual #7                  // Method java/lang/String.equals:(Ljava/lang/Object;)Z
       9: ifne          25
      12: aload_1
      13: aload_0
      14: getfield      #2                  // Field accum:Ljava/lang/StringBuilder;
      17: iload_2
      18: aload_0
      19: getfield      #3                  // Field out:Lorg/jsoup/nodes/Document$OutputSettings;
      22: invokevirtual #8                  // Method org/jsoup/nodes/Node.outerHtmlTail:(Ljava/lang/StringBuilder;ILorg/jsoup/nodes/Document$OutputSettings;)V
      25: return
}
