Compiled from "CollectionCredentialResolver.java"
public class org.opensaml.xml.security.credential.CollectionCredentialResolver extends org.opensaml.xml.security.credential.AbstractCriteriaFilteringCredentialResolver {
  private java.util.Collection<org.opensaml.xml.security.credential.Credential> collection;

  public org.opensaml.xml.security.credential.CollectionCredentialResolver();
    Code:
       0: aload_0
       1: invokespecial #1                  // Method org/opensaml/xml/security/credential/AbstractCriteriaFilteringCredentialResolver."<init>":()V
       4: aload_0
       5: new           #2                  // class java/util/ArrayList
       8: dup
       9: invokespecial #3                  // Method java/util/ArrayList."<init>":()V
      12: putfield      #4                  // Field collection:Ljava/util/Collection;
      15: return

  public org.opensaml.xml.security.credential.CollectionCredentialResolver(java.util.Collection<org.opensaml.xml.security.credential.Credential>);
    Code:
       0: aload_0
       1: invokespecial #1                  // Method org/opensaml/xml/security/credential/AbstractCriteriaFilteringCredentialResolver."<init>":()V
       4: aload_0
       5: aload_1
       6: putfield      #4                  // Field collection:Ljava/util/Collection;
       9: return

  public java.util.Collection<org.opensaml.xml.security.credential.Credential> getCollection();
    Code:
       0: aload_0
       1: getfield      #4                  // Field collection:Ljava/util/Collection;
       4: areturn

  protected java.lang.Iterable<org.opensaml.xml.security.credential.Credential> resolveFromSource(org.opensaml.xml.security.CriteriaSet) throws org.opensaml.xml.security.SecurityException;
    Code:
       0: aload_0
       1: getfield      #4                  // Field collection:Ljava/util/Collection;
       4: areturn
}
