Compiled from "SOAP11FaultImpl.java"
public class org.apache.axiom.soap.impl.llom.soap11.SOAP11FaultImpl extends org.apache.axiom.soap.impl.llom.SOAPFaultImpl implements org.apache.axiom.soap.impl.intf.AxiomSOAP11Fault {
  public org.apache.axiom.soap.impl.llom.soap11.SOAP11FaultImpl();
    Code:
       0: aload_0
       1: invokespecial #10                 // Method org/apache/axiom/soap/impl/llom/SOAPFaultImpl."<init>":()V
       4: return

  public void checkParent(org.apache.axiom.om.OMElement) throws org.apache.axiom.soap.SOAPProcessingException;
    Code:
       0: aload_1
       1: instanceof    #22                 // class org/apache/axiom/soap/impl/llom/soap11/SOAP11BodyImpl
       4: ifne          17
       7: new           #19                 // class org/apache/axiom/soap/SOAPProcessingException
      10: dup
      11: ldc           #24                 // String Expecting SOAP 1.1 implementation of SOAP Body as the parent. But received some other implementation
      13: invokespecial #26                 // Method org/apache/axiom/soap/SOAPProcessingException."<init>":(Ljava/lang/String;)V
      16: athrow
      17: return

  public final java.lang.Class<? extends org.apache.axiom.core.CoreNode> coreGetNodeClass();
    Code:
       0: aload_0
       1: invokestatic  #44                 // Method org/apache/axiom/soap/impl/common/AxiomSOAP11FaultSupport.ajc$interMethod$org_apache_axiom_soap_impl_common_AxiomSOAP11FaultSupport$org_apache_axiom_soap_impl_intf_AxiomSOAP11Fault$coreGetNodeClass:(Lorg/apache/axiom/soap/impl/intf/AxiomSOAP11Fault;)Ljava/lang/Class;
       4: areturn

  public final org.apache.axiom.soap.SOAPFaultCode getCode();
    Code:
       0: aload_0
       1: invokestatic  #70                 // Method org/apache/axiom/soap/impl/common/AxiomSOAP11FaultSupport.ajc$interMethod$org_apache_axiom_soap_impl_common_AxiomSOAP11FaultSupport$org_apache_axiom_soap_impl_intf_AxiomSOAP11Fault$getCode:(Lorg/apache/axiom/soap/impl/intf/AxiomSOAP11Fault;)Lorg/apache/axiom/soap/SOAPFaultCode;
       4: areturn

  public final org.apache.axiom.soap.SOAPFaultDetail getDetail();
    Code:
       0: aload_0
       1: invokestatic  #86                 // Method org/apache/axiom/soap/impl/common/AxiomSOAP11FaultSupport.ajc$interMethod$org_apache_axiom_soap_impl_common_AxiomSOAP11FaultSupport$org_apache_axiom_soap_impl_intf_AxiomSOAP11Fault$getDetail:(Lorg/apache/axiom/soap/impl/intf/AxiomSOAP11Fault;)Lorg/apache/axiom/soap/SOAPFaultDetail;
       4: areturn

  public final org.apache.axiom.soap.SOAPFaultNode getNode();
    Code:
       0: aload_0
       1: invokestatic  #78                 // Method org/apache/axiom/soap/impl/common/AxiomSOAP11FaultSupport.ajc$interMethod$org_apache_axiom_soap_impl_common_AxiomSOAP11FaultSupport$org_apache_axiom_soap_impl_intf_AxiomSOAP11Fault$getNode:(Lorg/apache/axiom/soap/impl/intf/AxiomSOAP11Fault;)Lorg/apache/axiom/soap/SOAPFaultNode;
       4: areturn

  public final org.apache.axiom.soap.SOAPFaultReason getReason();
    Code:
       0: aload_0
       1: invokestatic  #74                 // Method org/apache/axiom/soap/impl/common/AxiomSOAP11FaultSupport.ajc$interMethod$org_apache_axiom_soap_impl_common_AxiomSOAP11FaultSupport$org_apache_axiom_soap_impl_intf_AxiomSOAP11Fault$getReason:(Lorg/apache/axiom/soap/impl/intf/AxiomSOAP11Fault;)Lorg/apache/axiom/soap/SOAPFaultReason;
       4: areturn

  public final org.apache.axiom.soap.SOAPFaultRole getRole();
    Code:
       0: aload_0
       1: invokestatic  #82                 // Method org/apache/axiom/soap/impl/common/AxiomSOAP11FaultSupport.ajc$interMethod$org_apache_axiom_soap_impl_common_AxiomSOAP11FaultSupport$org_apache_axiom_soap_impl_intf_AxiomSOAP11Fault$getRole:(Lorg/apache/axiom/soap/impl/intf/AxiomSOAP11Fault;)Lorg/apache/axiom/soap/SOAPFaultRole;
       4: areturn

  public final org.apache.axiom.soap.impl.intf.SOAPHelper getSOAPHelper();
    Code:
       0: aload_0
       1: invokestatic  #38                 // Method org/apache/axiom/soap/impl/common/AxiomSOAP11ElementSupport.ajc$interMethod$org_apache_axiom_soap_impl_common_AxiomSOAP11ElementSupport$org_apache_axiom_soap_impl_intf_AxiomSOAP11Element$getSOAPHelper:(Lorg/apache/axiom/soap/impl/intf/AxiomSOAP11Element;)Lorg/apache/axiom/soap/impl/intf/SOAPHelper;
       4: areturn

  public final void setCode(org.apache.axiom.soap.SOAPFaultCode) throws org.apache.axiom.soap.SOAPProcessingException;
    Code:
       0: aload_0
       1: aload_1
       2: invokestatic  #50                 // Method org/apache/axiom/soap/impl/common/AxiomSOAP11FaultSupport.ajc$interMethod$org_apache_axiom_soap_impl_common_AxiomSOAP11FaultSupport$org_apache_axiom_soap_impl_intf_AxiomSOAP11Fault$setCode:(Lorg/apache/axiom/soap/impl/intf/AxiomSOAP11Fault;Lorg/apache/axiom/soap/SOAPFaultCode;)V
       5: return

  public final void setDetail(org.apache.axiom.soap.SOAPFaultDetail) throws org.apache.axiom.soap.SOAPProcessingException;
    Code:
       0: aload_0
       1: aload_1
       2: invokestatic  #66                 // Method org/apache/axiom/soap/impl/common/AxiomSOAP11FaultSupport.ajc$interMethod$org_apache_axiom_soap_impl_common_AxiomSOAP11FaultSupport$org_apache_axiom_soap_impl_intf_AxiomSOAP11Fault$setDetail:(Lorg/apache/axiom/soap/impl/intf/AxiomSOAP11Fault;Lorg/apache/axiom/soap/SOAPFaultDetail;)V
       5: return

  public final void setNode(org.apache.axiom.soap.SOAPFaultNode) throws org.apache.axiom.soap.SOAPProcessingException;
    Code:
       0: aload_0
       1: aload_1
       2: invokestatic  #58                 // Method org/apache/axiom/soap/impl/common/AxiomSOAP11FaultSupport.ajc$interMethod$org_apache_axiom_soap_impl_common_AxiomSOAP11FaultSupport$org_apache_axiom_soap_impl_intf_AxiomSOAP11Fault$setNode:(Lorg/apache/axiom/soap/impl/intf/AxiomSOAP11Fault;Lorg/apache/axiom/soap/SOAPFaultNode;)V
       5: return

  public final void setReason(org.apache.axiom.soap.SOAPFaultReason) throws org.apache.axiom.soap.SOAPProcessingException;
    Code:
       0: aload_0
       1: aload_1
       2: invokestatic  #54                 // Method org/apache/axiom/soap/impl/common/AxiomSOAP11FaultSupport.ajc$interMethod$org_apache_axiom_soap_impl_common_AxiomSOAP11FaultSupport$org_apache_axiom_soap_impl_intf_AxiomSOAP11Fault$setReason:(Lorg/apache/axiom/soap/impl/intf/AxiomSOAP11Fault;Lorg/apache/axiom/soap/SOAPFaultReason;)V
       5: return

  public final void setRole(org.apache.axiom.soap.SOAPFaultRole) throws org.apache.axiom.soap.SOAPProcessingException;
    Code:
       0: aload_0
       1: aload_1
       2: invokestatic  #62                 // Method org/apache/axiom/soap/impl/common/AxiomSOAP11FaultSupport.ajc$interMethod$org_apache_axiom_soap_impl_common_AxiomSOAP11FaultSupport$org_apache_axiom_soap_impl_intf_AxiomSOAP11Fault$setRole:(Lorg/apache/axiom/soap/impl/intf/AxiomSOAP11Fault;Lorg/apache/axiom/soap/SOAPFaultRole;)V
       5: return
}
