Compiled from "AbstractTriStatePredicate.java"
public abstract class net.shibboleth.utilities.java.support.logic.AbstractTriStatePredicate<T> implements com.google.common.base.Predicate<T> {
  private boolean nullInputSatisfies;

  private boolean unevaluableSatisfies;

  public net.shibboleth.utilities.java.support.logic.AbstractTriStatePredicate();
    Code:
       0: aload_0
       1: invokespecial #1                  // Method java/lang/Object."<init>":()V
       4: return

  public boolean isNullInputSatisfies();
    Code:
       0: aload_0
       1: getfield      #2                  // Field nullInputSatisfies:Z
       4: ireturn

  public void setNullInputSatisfies(boolean);
    Code:
       0: aload_0
       1: iload_1
       2: putfield      #2                  // Field nullInputSatisfies:Z
       5: return

  public boolean isUnevaluableSatisfies();
    Code:
       0: aload_0
       1: getfield      #3                  // Field unevaluableSatisfies:Z
       4: ireturn

  public void setUnevaluableSatisfies(boolean);
    Code:
       0: aload_0
       1: iload_1
       2: putfield      #3                  // Field unevaluableSatisfies:Z
       5: return
}
