Compiled from "AtomEventLoaderActor.java"
public class won.matcher.service.crawler.actor.AtomEventLoaderActor extends akka.actor.UntypedActor {
  private static int MAX_BULK_SIZE;

  private akka.event.LoggingAdapter log;

  private akka.actor.ActorRef pubSubMediator;

  private won.matcher.service.crawler.service.CrawlSparqlService sparqlService;

  public won.matcher.service.crawler.actor.AtomEventLoaderActor();
    Code:
       0: aload_0
       1: invokespecial #1                  // Method akka/actor/UntypedActor."<init>":()V
       4: aload_0
       5: aload_0
       6: invokevirtual #2                  // Method getContext:()Lakka/actor/UntypedActorContext;
       9: invokeinterface #3,  1            // InterfaceMethod akka/actor/UntypedActorContext.system:()Lakka/actor/ActorSystem;
      14: aload_0
      15: invokestatic  #4                  // Method akka/event/Logging.getLogger:(Lakka/actor/ActorSystem;Ljava/lang/Object;)Lakka/event/LoggingAdapter;
      18: putfield      #5                  // Field log:Lakka/event/LoggingAdapter;
      21: return

  public void preStart();
    Code:
       0: aload_0
       1: aload_0
       2: invokevirtual #2                  // Method getContext:()Lakka/actor/UntypedActorContext;
       5: invokeinterface #3,  1            // InterfaceMethod akka/actor/UntypedActorContext.system:()Lakka/actor/ActorSystem;
      10: invokestatic  #6                  // Method akka/cluster/pubsub/DistributedPubSub.get:(Lakka/actor/ActorSystem;)Lakka/cluster/pubsub/DistributedPubSub;
      13: invokevirtual #7                  // Method akka/cluster/pubsub/DistributedPubSub.mediator:()Lakka/actor/ActorRef;
      16: putfield      #8                  // Field pubSubMediator:Lakka/actor/ActorRef;
      19: aload_0
      20: getfield      #8                  // Field pubSubMediator:Lakka/actor/ActorRef;
      23: new           #9                  // class akka/cluster/pubsub/DistributedPubSubMediator$Subscribe
      26: dup
      27: ldc           #10                 // class won/matcher/service/common/event/LoadAtomEvent
      29: invokevirtual #11                 // Method java/lang/Class.getName:()Ljava/lang/String;
      32: aload_0
      33: invokevirtual #12                 // Method getSelf:()Lakka/actor/ActorRef;
      36: invokespecial #13                 // Method akka/cluster/pubsub/DistributedPubSubMediator$Subscribe."<init>":(Ljava/lang/String;Lakka/actor/ActorRef;)V
      39: aload_0
      40: invokevirtual #12                 // Method getSelf:()Lakka/actor/ActorRef;
      43: invokevirtual #14                 // Method akka/actor/ActorRef.tell:(Ljava/lang/Object;Lakka/actor/ActorRef;)V
      46: return

  public void onReceive(java.lang.Object) throws java.lang.Throwable;
    Code:
       0: aload_1
       1: instanceof    #10                 // class won/matcher/service/common/event/LoadAtomEvent
       4: ifeq          164
       7: aload_1
       8: checkcast     #10                 // class won/matcher/service/common/event/LoadAtomEvent
      11: astore_2
      12: aload_0
      13: getfield      #5                  // Field log:Lakka/event/LoggingAdapter;
      16: ldc           #15                 // String received request to load atoms events: {}
      18: aload_2
      19: invokeinterface #16,  3           // InterfaceMethod akka/event/LoggingAdapter.debug:(Ljava/lang/String;Ljava/lang/Object;)V
      24: iconst_0
      25: istore        4
      27: aload_2
      28: invokevirtual #17                 // Method won/matcher/service/common/event/LoadAtomEvent.getLastXAtomEvents:()I
      31: iconst_m1
      32: if_icmpne     60
      35: aload_0
      36: getfield      #18                 // Field sparqlService:Lwon/matcher/service/crawler/service/CrawlSparqlService;
      39: aload_2
      40: invokevirtual #19                 // Method won/matcher/service/common/event/LoadAtomEvent.getFromDate:()J
      43: aload_2
      44: invokevirtual #20                 // Method won/matcher/service/common/event/LoadAtomEvent.getToDate:()J
      47: iload         4
      49: getstatic     #21                 // Field MAX_BULK_SIZE:I
      52: iconst_1
      53: invokevirtual #22                 // Method won/matcher/service/crawler/service/CrawlSparqlService.retrieveActiveAtomEvents:(JJIIZ)Lwon/matcher/service/common/event/BulkAtomEvent;
      56: astore_3
      57: goto          88
      60: aload_0
      61: getfield      #18                 // Field sparqlService:Lwon/matcher/service/crawler/service/CrawlSparqlService;
      64: lconst_0
      65: ldc2_w        #24                 // long 9223372036854775807l
      68: iload         4
      70: getstatic     #21                 // Field MAX_BULK_SIZE:I
      73: aload_2
      74: invokevirtual #17                 // Method won/matcher/service/common/event/LoadAtomEvent.getLastXAtomEvents:()I
      77: iload         4
      79: isub
      80: invokestatic  #26                 // Method java/lang/Math.min:(II)I
      83: iconst_0
      84: invokevirtual #22                 // Method won/matcher/service/crawler/service/CrawlSparqlService.retrieveActiveAtomEvents:(JJIIZ)Lwon/matcher/service/common/event/BulkAtomEvent;
      87: astore_3
      88: aload_3
      89: invokevirtual #27                 // Method won/matcher/service/common/event/BulkAtomEvent.getAtomEvents:()Ljava/util/Collection;
      92: invokeinterface #28,  1           // InterfaceMethod java/util/Collection.size:()I
      97: ifle          149
     100: aload_0
     101: getfield      #5                  // Field log:Lakka/event/LoggingAdapter;
     104: ldc           #29                 // String send bulk event of size {} back to requesting actor
     106: aload_3
     107: invokevirtual #27                 // Method won/matcher/service/common/event/BulkAtomEvent.getAtomEvents:()Ljava/util/Collection;
     110: invokeinterface #28,  1           // InterfaceMethod java/util/Collection.size:()I
     115: invokestatic  #30                 // Method java/lang/Integer.valueOf:(I)Ljava/lang/Integer;
     118: invokeinterface #16,  3           // InterfaceMethod akka/event/LoggingAdapter.debug:(Ljava/lang/String;Ljava/lang/Object;)V
     123: aload_0
     124: invokevirtual #31                 // Method getSender:()Lakka/actor/ActorRef;
     127: aload_3
     128: aload_0
     129: invokevirtual #12                 // Method getSelf:()Lakka/actor/ActorRef;
     132: invokevirtual #14                 // Method akka/actor/ActorRef.tell:(Ljava/lang/Object;Lakka/actor/ActorRef;)V
     135: iload         4
     137: aload_3
     138: invokevirtual #27                 // Method won/matcher/service/common/event/BulkAtomEvent.getAtomEvents:()Ljava/util/Collection;
     141: invokeinterface #28,  1           // InterfaceMethod java/util/Collection.size:()I
     146: iadd
     147: istore        4
     149: aload_3
     150: invokevirtual #27                 // Method won/matcher/service/common/event/BulkAtomEvent.getAtomEvents:()Ljava/util/Collection;
     153: invokeinterface #28,  1           // InterfaceMethod java/util/Collection.size:()I
     158: getstatic     #21                 // Field MAX_BULK_SIZE:I
     161: if_icmpeq     27
     164: return

  static {};
    Code:
       0: bipush        10
       2: putstatic     #21                 // Field MAX_BULK_SIZE:I
       5: return
}
