Compiled from "HAProxyMessage.java"
public final class io.netty.handler.codec.haproxy.HAProxyMessage extends io.netty.util.AbstractReferenceCounted {
  private static final io.netty.util.ResourceLeakDetector<io.netty.handler.codec.haproxy.HAProxyMessage> leakDetector;

  private final io.netty.util.ResourceLeakTracker<io.netty.handler.codec.haproxy.HAProxyMessage> leak;

  private final io.netty.handler.codec.haproxy.HAProxyProtocolVersion protocolVersion;

  private final io.netty.handler.codec.haproxy.HAProxyCommand command;

  private final io.netty.handler.codec.haproxy.HAProxyProxiedProtocol proxiedProtocol;

  private final java.lang.String sourceAddress;

  private final java.lang.String destinationAddress;

  private final int sourcePort;

  private final int destinationPort;

  private final java.util.List<io.netty.handler.codec.haproxy.HAProxyTLV> tlvs;

  static final boolean $assertionsDisabled;

  private io.netty.handler.codec.haproxy.HAProxyMessage(io.netty.handler.codec.haproxy.HAProxyProtocolVersion, io.netty.handler.codec.haproxy.HAProxyCommand, io.netty.handler.codec.haproxy.HAProxyProxiedProtocol, java.lang.String, java.lang.String, java.lang.String, java.lang.String);
    Code:
       0: aload_0
       1: aload_1
       2: aload_2
       3: aload_3
       4: aload         4
       6: aload         5
       8: aload         6
      10: invokestatic  #1                  // Method portStringToInt:(Ljava/lang/String;)I
      13: aload         7
      15: invokestatic  #1                  // Method portStringToInt:(Ljava/lang/String;)I
      18: invokespecial #2                  // Method "<init>":(Lio/netty/handler/codec/haproxy/HAProxyProtocolVersion;Lio/netty/handler/codec/haproxy/HAProxyCommand;Lio/netty/handler/codec/haproxy/HAProxyProxiedProtocol;Ljava/lang/String;Ljava/lang/String;II)V
      21: return

  public io.netty.handler.codec.haproxy.HAProxyMessage(io.netty.handler.codec.haproxy.HAProxyProtocolVersion, io.netty.handler.codec.haproxy.HAProxyCommand, io.netty.handler.codec.haproxy.HAProxyProxiedProtocol, java.lang.String, java.lang.String, int, int);
    Code:
       0: aload_0
       1: aload_1
       2: aload_2
       3: aload_3
       4: aload         4
       6: aload         5
       8: iload         6
      10: iload         7
      12: invokestatic  #3                  // Method java/util/Collections.emptyList:()Ljava/util/List;
      15: invokespecial #4                  // Method "<init>":(Lio/netty/handler/codec/haproxy/HAProxyProtocolVersion;Lio/netty/handler/codec/haproxy/HAProxyCommand;Lio/netty/handler/codec/haproxy/HAProxyProxiedProtocol;Ljava/lang/String;Ljava/lang/String;IILjava/util/List;)V
      18: return

  public io.netty.handler.codec.haproxy.HAProxyMessage(io.netty.handler.codec.haproxy.HAProxyProtocolVersion, io.netty.handler.codec.haproxy.HAProxyCommand, io.netty.handler.codec.haproxy.HAProxyProxiedProtocol, java.lang.String, java.lang.String, int, int, java.util.List<? extends io.netty.handler.codec.haproxy.HAProxyTLV>);
    Code:
       0: aload_0
       1: invokespecial #5                  // Method io/netty/util/AbstractReferenceCounted."<init>":()V
       4: aload_1
       5: ldc           #6                  // String protocolVersion
       7: invokestatic  #7                  // Method io/netty/util/internal/ObjectUtil.checkNotNull:(Ljava/lang/Object;Ljava/lang/String;)Ljava/lang/Object;
      10: pop
      11: aload_3
      12: ldc           #8                  // String proxiedProtocol
      14: invokestatic  #7                  // Method io/netty/util/internal/ObjectUtil.checkNotNull:(Ljava/lang/Object;Ljava/lang/String;)Ljava/lang/Object;
      17: pop
      18: aload         8
      20: ldc           #9                  // String tlvs
      22: invokestatic  #7                  // Method io/netty/util/internal/ObjectUtil.checkNotNull:(Ljava/lang/Object;Ljava/lang/String;)Ljava/lang/Object;
      25: pop
      26: aload_3
      27: invokevirtual #10                 // Method io/netty/handler/codec/haproxy/HAProxyProxiedProtocol.addressFamily:()Lio/netty/handler/codec/haproxy/HAProxyProxiedProtocol$AddressFamily;
      30: astore        9
      32: aload         4
      34: aload         9
      36: invokestatic  #11                 // Method checkAddress:(Ljava/lang/String;Lio/netty/handler/codec/haproxy/HAProxyProxiedProtocol$AddressFamily;)V
      39: aload         5
      41: aload         9
      43: invokestatic  #11                 // Method checkAddress:(Ljava/lang/String;Lio/netty/handler/codec/haproxy/HAProxyProxiedProtocol$AddressFamily;)V
      46: iload         6
      48: aload         9
      50: invokestatic  #12                 // Method checkPort:(ILio/netty/handler/codec/haproxy/HAProxyProxiedProtocol$AddressFamily;)V
      53: iload         7
      55: aload         9
      57: invokestatic  #12                 // Method checkPort:(ILio/netty/handler/codec/haproxy/HAProxyProxiedProtocol$AddressFamily;)V
      60: aload_0
      61: aload_1
      62: putfield      #13                 // Field protocolVersion:Lio/netty/handler/codec/haproxy/HAProxyProtocolVersion;
      65: aload_0
      66: aload_2
      67: putfield      #14                 // Field command:Lio/netty/handler/codec/haproxy/HAProxyCommand;
      70: aload_0
      71: aload_3
      72: putfield      #15                 // Field proxiedProtocol:Lio/netty/handler/codec/haproxy/HAProxyProxiedProtocol;
      75: aload_0
      76: aload         4
      78: putfield      #16                 // Field sourceAddress:Ljava/lang/String;
      81: aload_0
      82: aload         5
      84: putfield      #17                 // Field destinationAddress:Ljava/lang/String;
      87: aload_0
      88: iload         6
      90: putfield      #18                 // Field sourcePort:I
      93: aload_0
      94: iload         7
      96: putfield      #19                 // Field destinationPort:I
      99: aload_0
     100: aload         8
     102: invokestatic  #20                 // Method java/util/Collections.unmodifiableList:(Ljava/util/List;)Ljava/util/List;
     105: putfield      #21                 // Field tlvs:Ljava/util/List;
     108: aload_0
     109: getstatic     #22                 // Field leakDetector:Lio/netty/util/ResourceLeakDetector;
     112: aload_0
     113: invokevirtual #23                 // Method io/netty/util/ResourceLeakDetector.track:(Ljava/lang/Object;)Lio/netty/util/ResourceLeakTracker;
     116: putfield      #24                 // Field leak:Lio/netty/util/ResourceLeakTracker;
     119: return

  static io.netty.handler.codec.haproxy.HAProxyMessage decodeHeader(io.netty.buffer.ByteBuf);
    Code:
       0: aload_0
       1: ldc           #25                 // String header
       3: invokestatic  #7                  // Method io/netty/util/internal/ObjectUtil.checkNotNull:(Ljava/lang/Object;Ljava/lang/String;)Ljava/lang/Object;
       6: pop
       7: aload_0
       8: invokevirtual #26                 // Method io/netty/buffer/ByteBuf.readableBytes:()I
      11: bipush        16
      13: if_icmpge     51
      16: new           #27                 // class io/netty/handler/codec/haproxy/HAProxyProtocolException
      19: dup
      20: new           #28                 // class java/lang/StringBuilder
      23: dup
      24: invokespecial #29                 // Method java/lang/StringBuilder."<init>":()V
      27: ldc           #30                 // String incomplete header:
      29: invokevirtual #31                 // Method java/lang/StringBuilder.append:(Ljava/lang/String;)Ljava/lang/StringBuilder;
      32: aload_0
      33: invokevirtual #26                 // Method io/netty/buffer/ByteBuf.readableBytes:()I
      36: invokevirtual #32                 // Method java/lang/StringBuilder.append:(I)Ljava/lang/StringBuilder;
      39: ldc           #33                 // String  bytes (expected: 16+ bytes)
      41: invokevirtual #31                 // Method java/lang/StringBuilder.append:(Ljava/lang/String;)Ljava/lang/StringBuilder;
      44: invokevirtual #34                 // Method java/lang/StringBuilder.toString:()Ljava/lang/String;
      47: invokespecial #35                 // Method io/netty/handler/codec/haproxy/HAProxyProtocolException."<init>":(Ljava/lang/String;)V
      50: athrow
      51: aload_0
      52: bipush        12
      54: invokevirtual #36                 // Method io/netty/buffer/ByteBuf.skipBytes:(I)Lio/netty/buffer/ByteBuf;
      57: pop
      58: aload_0
      59: invokevirtual #37                 // Method io/netty/buffer/ByteBuf.readByte:()B
      62: istore_1
      63: iload_1
      64: invokestatic  #38                 // Method io/netty/handler/codec/haproxy/HAProxyProtocolVersion.valueOf:(B)Lio/netty/handler/codec/haproxy/HAProxyProtocolVersion;
      67: astore_2
      68: goto          81
      71: astore_3
      72: new           #27                 // class io/netty/handler/codec/haproxy/HAProxyProtocolException
      75: dup
      76: aload_3
      77: invokespecial #40                 // Method io/netty/handler/codec/haproxy/HAProxyProtocolException."<init>":(Ljava/lang/Throwable;)V
      80: athrow
      81: aload_2
      82: getstatic     #41                 // Field io/netty/handler/codec/haproxy/HAProxyProtocolVersion.V2:Lio/netty/handler/codec/haproxy/HAProxyProtocolVersion;
      85: if_acmpeq     118
      88: new           #27                 // class io/netty/handler/codec/haproxy/HAProxyProtocolException
      91: dup
      92: new           #28                 // class java/lang/StringBuilder
      95: dup
      96: invokespecial #29                 // Method java/lang/StringBuilder."<init>":()V
      99: ldc           #42                 // String version 1 unsupported: 0x
     101: invokevirtual #31                 // Method java/lang/StringBuilder.append:(Ljava/lang/String;)Ljava/lang/StringBuilder;
     104: iload_1
     105: invokestatic  #43                 // Method java/lang/Integer.toHexString:(I)Ljava/lang/String;
     108: invokevirtual #31                 // Method java/lang/StringBuilder.append:(Ljava/lang/String;)Ljava/lang/StringBuilder;
     111: invokevirtual #34                 // Method java/lang/StringBuilder.toString:()Ljava/lang/String;
     114: invokespecial #35                 // Method io/netty/handler/codec/haproxy/HAProxyProtocolException."<init>":(Ljava/lang/String;)V
     117: athrow
     118: iload_1
     119: invokestatic  #44                 // Method io/netty/handler/codec/haproxy/HAProxyCommand.valueOf:(B)Lio/netty/handler/codec/haproxy/HAProxyCommand;
     122: astore_3
     123: goto          138
     126: astore        4
     128: new           #27                 // class io/netty/handler/codec/haproxy/HAProxyProtocolException
     131: dup
     132: aload         4
     134: invokespecial #40                 // Method io/netty/handler/codec/haproxy/HAProxyProtocolException."<init>":(Ljava/lang/Throwable;)V
     137: athrow
     138: aload_3
     139: getstatic     #45                 // Field io/netty/handler/codec/haproxy/HAProxyCommand.LOCAL:Lio/netty/handler/codec/haproxy/HAProxyCommand;
     142: if_acmpne     155
     145: getstatic     #41                 // Field io/netty/handler/codec/haproxy/HAProxyProtocolVersion.V2:Lio/netty/handler/codec/haproxy/HAProxyProtocolVersion;
     148: getstatic     #45                 // Field io/netty/handler/codec/haproxy/HAProxyCommand.LOCAL:Lio/netty/handler/codec/haproxy/HAProxyCommand;
     151: invokestatic  #46                 // Method unknownMsg:(Lio/netty/handler/codec/haproxy/HAProxyProtocolVersion;Lio/netty/handler/codec/haproxy/HAProxyCommand;)Lio/netty/handler/codec/haproxy/HAProxyMessage;
     154: areturn
     155: aload_0
     156: invokevirtual #37                 // Method io/netty/buffer/ByteBuf.readByte:()B
     159: invokestatic  #47                 // Method io/netty/handler/codec/haproxy/HAProxyProxiedProtocol.valueOf:(B)Lio/netty/handler/codec/haproxy/HAProxyProxiedProtocol;
     162: astore        4
     164: goto          179
     167: astore        5
     169: new           #27                 // class io/netty/handler/codec/haproxy/HAProxyProtocolException
     172: dup
     173: aload         5
     175: invokespecial #40                 // Method io/netty/handler/codec/haproxy/HAProxyProtocolException."<init>":(Ljava/lang/Throwable;)V
     178: athrow
     179: aload         4
     181: getstatic     #48                 // Field io/netty/handler/codec/haproxy/HAProxyProxiedProtocol.UNKNOWN:Lio/netty/handler/codec/haproxy/HAProxyProxiedProtocol;
     184: if_acmpne     197
     187: getstatic     #41                 // Field io/netty/handler/codec/haproxy/HAProxyProtocolVersion.V2:Lio/netty/handler/codec/haproxy/HAProxyProtocolVersion;
     190: getstatic     #49                 // Field io/netty/handler/codec/haproxy/HAProxyCommand.PROXY:Lio/netty/handler/codec/haproxy/HAProxyCommand;
     193: invokestatic  #46                 // Method unknownMsg:(Lio/netty/handler/codec/haproxy/HAProxyProtocolVersion;Lio/netty/handler/codec/haproxy/HAProxyCommand;)Lio/netty/handler/codec/haproxy/HAProxyMessage;
     196: areturn
     197: aload_0
     198: invokevirtual #50                 // Method io/netty/buffer/ByteBuf.readUnsignedShort:()I
     201: istore        5
     203: iconst_0
     204: istore        9
     206: iconst_0
     207: istore        10
     209: aload         4
     211: invokevirtual #10                 // Method io/netty/handler/codec/haproxy/HAProxyProxiedProtocol.addressFamily:()Lio/netty/handler/codec/haproxy/HAProxyProxiedProtocol$AddressFamily;
     214: astore        11
     216: aload         11
     218: getstatic     #51                 // Field io/netty/handler/codec/haproxy/HAProxyProxiedProtocol$AddressFamily.AF_UNIX:Lio/netty/handler/codec/haproxy/HAProxyProxiedProtocol$AddressFamily;
     221: if_acmpne     396
     224: iload         5
     226: sipush        216
     229: if_icmplt     242
     232: aload_0
     233: invokevirtual #26                 // Method io/netty/buffer/ByteBuf.readableBytes:()I
     236: sipush        216
     239: if_icmpge     282
     242: new           #27                 // class io/netty/handler/codec/haproxy/HAProxyProtocolException
     245: dup
     246: new           #28                 // class java/lang/StringBuilder
     249: dup
     250: invokespecial #29                 // Method java/lang/StringBuilder."<init>":()V
     253: ldc           #52                 // String incomplete UNIX socket address information:
     255: invokevirtual #31                 // Method java/lang/StringBuilder.append:(Ljava/lang/String;)Ljava/lang/StringBuilder;
     258: iload         5
     260: aload_0
     261: invokevirtual #26                 // Method io/netty/buffer/ByteBuf.readableBytes:()I
     264: invokestatic  #53                 // Method java/lang/Math.min:(II)I
     267: invokevirtual #32                 // Method java/lang/StringBuilder.append:(I)Ljava/lang/StringBuilder;
     270: ldc           #54                 // String  bytes (expected: 216+ bytes)
     272: invokevirtual #31                 // Method java/lang/StringBuilder.append:(Ljava/lang/String;)Ljava/lang/StringBuilder;
     275: invokevirtual #34                 // Method java/lang/StringBuilder.toString:()Ljava/lang/String;
     278: invokespecial #35                 // Method io/netty/handler/codec/haproxy/HAProxyProtocolException."<init>":(Ljava/lang/String;)V
     281: athrow
     282: aload_0
     283: invokevirtual #55                 // Method io/netty/buffer/ByteBuf.readerIndex:()I
     286: istore        12
     288: aload_0
     289: iload         12
     291: bipush        108
     293: getstatic     #56                 // Field io/netty/util/ByteProcessor.FIND_NUL:Lio/netty/util/ByteProcessor;
     296: invokevirtual #57                 // Method io/netty/buffer/ByteBuf.forEachByte:(IILio/netty/util/ByteProcessor;)I
     299: istore        13
     301: iload         13
     303: iconst_m1
     304: if_icmpne     314
     307: bipush        108
     309: istore        8
     311: goto          321
     314: iload         13
     316: iload         12
     318: isub
     319: istore        8
     321: aload_0
     322: iload         12
     324: iload         8
     326: getstatic     #58                 // Field io/netty/util/CharsetUtil.US_ASCII:Ljava/nio/charset/Charset;
     329: invokevirtual #59                 // Method io/netty/buffer/ByteBuf.toString:(IILjava/nio/charset/Charset;)Ljava/lang/String;
     332: astore        6
     334: iinc          12, 108
     337: aload_0
     338: iload         12
     340: bipush        108
     342: getstatic     #56                 // Field io/netty/util/ByteProcessor.FIND_NUL:Lio/netty/util/ByteProcessor;
     345: invokevirtual #57                 // Method io/netty/buffer/ByteBuf.forEachByte:(IILio/netty/util/ByteProcessor;)I
     348: istore        13
     350: iload         13
     352: iconst_m1
     353: if_icmpne     363
     356: bipush        108
     358: istore        8
     360: goto          370
     363: iload         13
     365: iload         12
     367: isub
     368: istore        8
     370: aload_0
     371: iload         12
     373: iload         8
     375: getstatic     #58                 // Field io/netty/util/CharsetUtil.US_ASCII:Ljava/nio/charset/Charset;
     378: invokevirtual #59                 // Method io/netty/buffer/ByteBuf.toString:(IILjava/nio/charset/Charset;)Ljava/lang/String;
     381: astore        7
     383: aload_0
     384: iload         12
     386: bipush        108
     388: iadd
     389: invokevirtual #60                 // Method io/netty/buffer/ByteBuf.readerIndex:(I)Lio/netty/buffer/ByteBuf;
     392: pop
     393: goto          598
     396: aload         11
     398: getstatic     #61                 // Field io/netty/handler/codec/haproxy/HAProxyProxiedProtocol$AddressFamily.AF_IPv4:Lio/netty/handler/codec/haproxy/HAProxyProxiedProtocol$AddressFamily;
     401: if_acmpne     466
     404: iload         5
     406: bipush        12
     408: if_icmplt     420
     411: aload_0
     412: invokevirtual #26                 // Method io/netty/buffer/ByteBuf.readableBytes:()I
     415: bipush        12
     417: if_icmpge     460
     420: new           #27                 // class io/netty/handler/codec/haproxy/HAProxyProtocolException
     423: dup
     424: new           #28                 // class java/lang/StringBuilder
     427: dup
     428: invokespecial #29                 // Method java/lang/StringBuilder."<init>":()V
     431: ldc           #62                 // String incomplete IPv4 address information:
     433: invokevirtual #31                 // Method java/lang/StringBuilder.append:(Ljava/lang/String;)Ljava/lang/StringBuilder;
     436: iload         5
     438: aload_0
     439: invokevirtual #26                 // Method io/netty/buffer/ByteBuf.readableBytes:()I
     442: invokestatic  #53                 // Method java/lang/Math.min:(II)I
     445: invokevirtual #32                 // Method java/lang/StringBuilder.append:(I)Ljava/lang/StringBuilder;
     448: ldc           #63                 // String  bytes (expected: 12+ bytes)
     450: invokevirtual #31                 // Method java/lang/StringBuilder.append:(Ljava/lang/String;)Ljava/lang/StringBuilder;
     453: invokevirtual #34                 // Method java/lang/StringBuilder.toString:()Ljava/lang/String;
     456: invokespecial #35                 // Method io/netty/handler/codec/haproxy/HAProxyProtocolException."<init>":(Ljava/lang/String;)V
     459: athrow
     460: iconst_4
     461: istore        8
     463: goto          570
     466: aload         11
     468: getstatic     #64                 // Field io/netty/handler/codec/haproxy/HAProxyProxiedProtocol$AddressFamily.AF_IPv6:Lio/netty/handler/codec/haproxy/HAProxyProxiedProtocol$AddressFamily;
     471: if_acmpne     537
     474: iload         5
     476: bipush        36
     478: if_icmplt     490
     481: aload_0
     482: invokevirtual #26                 // Method io/netty/buffer/ByteBuf.readableBytes:()I
     485: bipush        36
     487: if_icmpge     530
     490: new           #27                 // class io/netty/handler/codec/haproxy/HAProxyProtocolException
     493: dup
     494: new           #28                 // class java/lang/StringBuilder
     497: dup
     498: invokespecial #29                 // Method java/lang/StringBuilder."<init>":()V
     501: ldc           #65                 // String incomplete IPv6 address information:
     503: invokevirtual #31                 // Method java/lang/StringBuilder.append:(Ljava/lang/String;)Ljava/lang/StringBuilder;
     506: iload         5
     508: aload_0
     509: invokevirtual #26                 // Method io/netty/buffer/ByteBuf.readableBytes:()I
     512: invokestatic  #53                 // Method java/lang/Math.min:(II)I
     515: invokevirtual #32                 // Method java/lang/StringBuilder.append:(I)Ljava/lang/StringBuilder;
     518: ldc           #66                 // String  bytes (expected: 36+ bytes)
     520: invokevirtual #31                 // Method java/lang/StringBuilder.append:(Ljava/lang/String;)Ljava/lang/StringBuilder;
     523: invokevirtual #34                 // Method java/lang/StringBuilder.toString:()Ljava/lang/String;
     526: invokespecial #35                 // Method io/netty/handler/codec/haproxy/HAProxyProtocolException."<init>":(Ljava/lang/String;)V
     529: athrow
     530: bipush        16
     532: istore        8
     534: goto          570
     537: new           #27                 // class io/netty/handler/codec/haproxy/HAProxyProtocolException
     540: dup
     541: new           #28                 // class java/lang/StringBuilder
     544: dup
     545: invokespecial #29                 // Method java/lang/StringBuilder."<init>":()V
     548: ldc           #67                 // String unable to parse address information (unknown address family:
     550: invokevirtual #31                 // Method java/lang/StringBuilder.append:(Ljava/lang/String;)Ljava/lang/StringBuilder;
     553: aload         11
     555: invokevirtual #68                 // Method java/lang/StringBuilder.append:(Ljava/lang/Object;)Ljava/lang/StringBuilder;
     558: bipush        41
     560: invokevirtual #69                 // Method java/lang/StringBuilder.append:(C)Ljava/lang/StringBuilder;
     563: invokevirtual #34                 // Method java/lang/StringBuilder.toString:()Ljava/lang/String;
     566: invokespecial #35                 // Method io/netty/handler/codec/haproxy/HAProxyProtocolException."<init>":(Ljava/lang/String;)V
     569: athrow
     570: aload_0
     571: iload         8
     573: invokestatic  #70                 // Method ipBytesToString:(Lio/netty/buffer/ByteBuf;I)Ljava/lang/String;
     576: astore        6
     578: aload_0
     579: iload         8
     581: invokestatic  #70                 // Method ipBytesToString:(Lio/netty/buffer/ByteBuf;I)Ljava/lang/String;
     584: astore        7
     586: aload_0
     587: invokevirtual #50                 // Method io/netty/buffer/ByteBuf.readUnsignedShort:()I
     590: istore        9
     592: aload_0
     593: invokevirtual #50                 // Method io/netty/buffer/ByteBuf.readUnsignedShort:()I
     596: istore        10
     598: aload_0
     599: invokestatic  #71                 // Method readTlvs:(Lio/netty/buffer/ByteBuf;)Ljava/util/List;
     602: astore        12
     604: new           #72                 // class io/netty/handler/codec/haproxy/HAProxyMessage
     607: dup
     608: aload_2
     609: aload_3
     610: aload         4
     612: aload         6
     614: aload         7
     616: iload         9
     618: iload         10
     620: aload         12
     622: invokespecial #4                  // Method "<init>":(Lio/netty/handler/codec/haproxy/HAProxyProtocolVersion;Lio/netty/handler/codec/haproxy/HAProxyCommand;Lio/netty/handler/codec/haproxy/HAProxyProxiedProtocol;Ljava/lang/String;Ljava/lang/String;IILjava/util/List;)V
     625: areturn
    Exception table:
       from    to  target type
          63    68    71   Class java/lang/IllegalArgumentException
         118   123   126   Class java/lang/IllegalArgumentException
         155   164   167   Class java/lang/IllegalArgumentException

  private static java.util.List<io.netty.handler.codec.haproxy.HAProxyTLV> readTlvs(io.netty.buffer.ByteBuf);
    Code:
       0: aload_0
       1: invokestatic  #73                 // Method readNextTLV:(Lio/netty/buffer/ByteBuf;)Lio/netty/handler/codec/haproxy/HAProxyTLV;
       4: astore_1
       5: aload_1
       6: ifnonnull     13
       9: invokestatic  #3                  // Method java/util/Collections.emptyList:()Ljava/util/List;
      12: areturn
      13: new           #74                 // class java/util/ArrayList
      16: dup
      17: iconst_4
      18: invokespecial #75                 // Method java/util/ArrayList."<init>":(I)V
      21: astore_2
      22: aload_2
      23: aload_1
      24: invokeinterface #76,  2           // InterfaceMethod java/util/List.add:(Ljava/lang/Object;)Z
      29: pop
      30: aload_1
      31: instanceof    #77                 // class io/netty/handler/codec/haproxy/HAProxySSLTLV
      34: ifeq          51
      37: aload_2
      38: aload_1
      39: checkcast     #77                 // class io/netty/handler/codec/haproxy/HAProxySSLTLV
      42: invokevirtual #78                 // Method io/netty/handler/codec/haproxy/HAProxySSLTLV.encapsulatedTLVs:()Ljava/util/List;
      45: invokeinterface #79,  2           // InterfaceMethod java/util/List.addAll:(Ljava/util/Collection;)Z
      50: pop
      51: aload_0
      52: invokestatic  #73                 // Method readNextTLV:(Lio/netty/buffer/ByteBuf;)Lio/netty/handler/codec/haproxy/HAProxyTLV;
      55: dup
      56: astore_1
      57: ifnonnull     22
      60: aload_2
      61: areturn

  private static io.netty.handler.codec.haproxy.HAProxyTLV readNextTLV(io.netty.buffer.ByteBuf);
    Code:
       0: aload_0
       1: invokevirtual #26                 // Method io/netty/buffer/ByteBuf.readableBytes:()I
       4: iconst_4
       5: if_icmpge     10
       8: aconst_null
       9: areturn
      10: aload_0
      11: invokevirtual #37                 // Method io/netty/buffer/ByteBuf.readByte:()B
      14: istore_1
      15: iload_1
      16: invokestatic  #80                 // Method io/netty/handler/codec/haproxy/HAProxyTLV$Type.typeForByteValue:(B)Lio/netty/handler/codec/haproxy/HAProxyTLV$Type;
      19: astore_2
      20: aload_0
      21: invokevirtual #50                 // Method io/netty/buffer/ByteBuf.readUnsignedShort:()I
      24: istore_3
      25: getstatic     #81                 // Field io/netty/handler/codec/haproxy/HAProxyMessage$1.$SwitchMap$io$netty$handler$codec$haproxy$HAProxyTLV$Type:[I
      28: aload_2
      29: invokevirtual #82                 // Method io/netty/handler/codec/haproxy/HAProxyTLV$Type.ordinal:()I
      32: iaload
      33: tableswitch   { // 1 to 7
                     1: 76
                     2: 194
                     3: 194
                     4: 194
                     5: 194
                     6: 194
                     7: 194
               default: 209
          }
      76: aload_0
      77: aload_0
      78: invokevirtual #55                 // Method io/netty/buffer/ByteBuf.readerIndex:()I
      81: iload_3
      82: invokevirtual #83                 // Method io/netty/buffer/ByteBuf.retainedSlice:(II)Lio/netty/buffer/ByteBuf;
      85: astore        4
      87: aload_0
      88: iload_3
      89: invokevirtual #84                 // Method io/netty/buffer/ByteBuf.readSlice:(I)Lio/netty/buffer/ByteBuf;
      92: astore        5
      94: aload         5
      96: invokevirtual #37                 // Method io/netty/buffer/ByteBuf.readByte:()B
      99: istore        6
     101: aload         5
     103: invokevirtual #85                 // Method io/netty/buffer/ByteBuf.readInt:()I
     106: istore        7
     108: aload         5
     110: invokevirtual #26                 // Method io/netty/buffer/ByteBuf.readableBytes:()I
     113: iconst_4
     114: if_icmplt     177
     117: new           #74                 // class java/util/ArrayList
     120: dup
     121: iconst_4
     122: invokespecial #75                 // Method java/util/ArrayList."<init>":(I)V
     125: astore        8
     127: aload         5
     129: invokestatic  #73                 // Method readNextTLV:(Lio/netty/buffer/ByteBuf;)Lio/netty/handler/codec/haproxy/HAProxyTLV;
     132: astore        9
     134: aload         9
     136: ifnonnull     142
     139: goto          161
     142: aload         8
     144: aload         9
     146: invokeinterface #76,  2           // InterfaceMethod java/util/List.add:(Ljava/lang/Object;)Z
     151: pop
     152: aload         5
     154: invokevirtual #26                 // Method io/netty/buffer/ByteBuf.readableBytes:()I
     157: iconst_4
     158: if_icmpge     127
     161: new           #77                 // class io/netty/handler/codec/haproxy/HAProxySSLTLV
     164: dup
     165: iload         7
     167: iload         6
     169: aload         8
     171: aload         4
     173: invokespecial #86                 // Method io/netty/handler/codec/haproxy/HAProxySSLTLV."<init>":(IBLjava/util/List;Lio/netty/buffer/ByteBuf;)V
     176: areturn
     177: new           #77                 // class io/netty/handler/codec/haproxy/HAProxySSLTLV
     180: dup
     181: iload         7
     183: iload         6
     185: invokestatic  #3                  // Method java/util/Collections.emptyList:()Ljava/util/List;
     188: aload         4
     190: invokespecial #86                 // Method io/netty/handler/codec/haproxy/HAProxySSLTLV."<init>":(IBLjava/util/List;Lio/netty/buffer/ByteBuf;)V
     193: areturn
     194: new           #87                 // class io/netty/handler/codec/haproxy/HAProxyTLV
     197: dup
     198: aload_2
     199: iload_1
     200: aload_0
     201: iload_3
     202: invokevirtual #88                 // Method io/netty/buffer/ByteBuf.readRetainedSlice:(I)Lio/netty/buffer/ByteBuf;
     205: invokespecial #89                 // Method io/netty/handler/codec/haproxy/HAProxyTLV."<init>":(Lio/netty/handler/codec/haproxy/HAProxyTLV$Type;BLio/netty/buffer/ByteBuf;)V
     208: areturn
     209: aconst_null
     210: areturn

  static io.netty.handler.codec.haproxy.HAProxyMessage decodeHeader(java.lang.String);
    Code:
       0: aload_0
       1: ifnonnull     14
       4: new           #27                 // class io/netty/handler/codec/haproxy/HAProxyProtocolException
       7: dup
       8: ldc           #25                 // String header
      10: invokespecial #35                 // Method io/netty/handler/codec/haproxy/HAProxyProtocolException."<init>":(Ljava/lang/String;)V
      13: athrow
      14: aload_0
      15: ldc           #90                 // String
      17: invokevirtual #91                 // Method java/lang/String.split:(Ljava/lang/String;)[Ljava/lang/String;
      20: astore_1
      21: aload_1
      22: arraylength
      23: istore_2
      24: iload_2
      25: iconst_2
      26: if_icmpge     61
      29: new           #27                 // class io/netty/handler/codec/haproxy/HAProxyProtocolException
      32: dup
      33: new           #28                 // class java/lang/StringBuilder
      36: dup
      37: invokespecial #29                 // Method java/lang/StringBuilder."<init>":()V
      40: ldc           #92                 // String invalid header:
      42: invokevirtual #31                 // Method java/lang/StringBuilder.append:(Ljava/lang/String;)Ljava/lang/StringBuilder;
      45: aload_0
      46: invokevirtual #31                 // Method java/lang/StringBuilder.append:(Ljava/lang/String;)Ljava/lang/StringBuilder;
      49: ldc           #93                 // String  (expected: \'PROXY\' and proxied protocol values)
      51: invokevirtual #31                 // Method java/lang/StringBuilder.append:(Ljava/lang/String;)Ljava/lang/StringBuilder;
      54: invokevirtual #34                 // Method java/lang/StringBuilder.toString:()Ljava/lang/String;
      57: invokespecial #35                 // Method io/netty/handler/codec/haproxy/HAProxyProtocolException."<init>":(Ljava/lang/String;)V
      60: athrow
      61: ldc           #94                 // String PROXY
      63: aload_1
      64: iconst_0
      65: aaload
      66: invokevirtual #95                 // Method java/lang/String.equals:(Ljava/lang/Object;)Z
      69: ifne          101
      72: new           #27                 // class io/netty/handler/codec/haproxy/HAProxyProtocolException
      75: dup
      76: new           #28                 // class java/lang/StringBuilder
      79: dup
      80: invokespecial #29                 // Method java/lang/StringBuilder."<init>":()V
      83: ldc           #96                 // String unknown identifier:
      85: invokevirtual #31                 // Method java/lang/StringBuilder.append:(Ljava/lang/String;)Ljava/lang/StringBuilder;
      88: aload_1
      89: iconst_0
      90: aaload
      91: invokevirtual #31                 // Method java/lang/StringBuilder.append:(Ljava/lang/String;)Ljava/lang/StringBuilder;
      94: invokevirtual #34                 // Method java/lang/StringBuilder.toString:()Ljava/lang/String;
      97: invokespecial #35                 // Method io/netty/handler/codec/haproxy/HAProxyProtocolException."<init>":(Ljava/lang/String;)V
     100: athrow
     101: aload_1
     102: iconst_1
     103: aaload
     104: invokestatic  #97                 // Method io/netty/handler/codec/haproxy/HAProxyProxiedProtocol.valueOf:(Ljava/lang/String;)Lio/netty/handler/codec/haproxy/HAProxyProxiedProtocol;
     107: astore_3
     108: goto          123
     111: astore        4
     113: new           #27                 // class io/netty/handler/codec/haproxy/HAProxyProtocolException
     116: dup
     117: aload         4
     119: invokespecial #40                 // Method io/netty/handler/codec/haproxy/HAProxyProtocolException."<init>":(Ljava/lang/Throwable;)V
     122: athrow
     123: aload_3
     124: getstatic     #98                 // Field io/netty/handler/codec/haproxy/HAProxyProxiedProtocol.TCP4:Lio/netty/handler/codec/haproxy/HAProxyProxiedProtocol;
     127: if_acmpeq     173
     130: aload_3
     131: getstatic     #99                 // Field io/netty/handler/codec/haproxy/HAProxyProxiedProtocol.TCP6:Lio/netty/handler/codec/haproxy/HAProxyProxiedProtocol;
     134: if_acmpeq     173
     137: aload_3
     138: getstatic     #48                 // Field io/netty/handler/codec/haproxy/HAProxyProxiedProtocol.UNKNOWN:Lio/netty/handler/codec/haproxy/HAProxyProxiedProtocol;
     141: if_acmpeq     173
     144: new           #27                 // class io/netty/handler/codec/haproxy/HAProxyProtocolException
     147: dup
     148: new           #28                 // class java/lang/StringBuilder
     151: dup
     152: invokespecial #29                 // Method java/lang/StringBuilder."<init>":()V
     155: ldc           #100                // String unsupported v1 proxied protocol:
     157: invokevirtual #31                 // Method java/lang/StringBuilder.append:(Ljava/lang/String;)Ljava/lang/StringBuilder;
     160: aload_1
     161: iconst_1
     162: aaload
     163: invokevirtual #31                 // Method java/lang/StringBuilder.append:(Ljava/lang/String;)Ljava/lang/StringBuilder;
     166: invokevirtual #34                 // Method java/lang/StringBuilder.toString:()Ljava/lang/String;
     169: invokespecial #35                 // Method io/netty/handler/codec/haproxy/HAProxyProtocolException."<init>":(Ljava/lang/String;)V
     172: athrow
     173: aload_3
     174: getstatic     #48                 // Field io/netty/handler/codec/haproxy/HAProxyProxiedProtocol.UNKNOWN:Lio/netty/handler/codec/haproxy/HAProxyProxiedProtocol;
     177: if_acmpne     190
     180: getstatic     #101                // Field io/netty/handler/codec/haproxy/HAProxyProtocolVersion.V1:Lio/netty/handler/codec/haproxy/HAProxyProtocolVersion;
     183: getstatic     #49                 // Field io/netty/handler/codec/haproxy/HAProxyCommand.PROXY:Lio/netty/handler/codec/haproxy/HAProxyCommand;
     186: invokestatic  #46                 // Method unknownMsg:(Lio/netty/handler/codec/haproxy/HAProxyProtocolVersion;Lio/netty/handler/codec/haproxy/HAProxyCommand;)Lio/netty/handler/codec/haproxy/HAProxyMessage;
     189: areturn
     190: iload_2
     191: bipush        6
     193: if_icmpeq     228
     196: new           #27                 // class io/netty/handler/codec/haproxy/HAProxyProtocolException
     199: dup
     200: new           #28                 // class java/lang/StringBuilder
     203: dup
     204: invokespecial #29                 // Method java/lang/StringBuilder."<init>":()V
     207: ldc           #102                // String invalid TCP4/6 header:
     209: invokevirtual #31                 // Method java/lang/StringBuilder.append:(Ljava/lang/String;)Ljava/lang/StringBuilder;
     212: aload_0
     213: invokevirtual #31                 // Method java/lang/StringBuilder.append:(Ljava/lang/String;)Ljava/lang/StringBuilder;
     216: ldc           #103                // String  (expected: 6 parts)
     218: invokevirtual #31                 // Method java/lang/StringBuilder.append:(Ljava/lang/String;)Ljava/lang/StringBuilder;
     221: invokevirtual #34                 // Method java/lang/StringBuilder.toString:()Ljava/lang/String;
     224: invokespecial #35                 // Method io/netty/handler/codec/haproxy/HAProxyProtocolException."<init>":(Ljava/lang/String;)V
     227: athrow
     228: new           #72                 // class io/netty/handler/codec/haproxy/HAProxyMessage
     231: dup
     232: getstatic     #101                // Field io/netty/handler/codec/haproxy/HAProxyProtocolVersion.V1:Lio/netty/handler/codec/haproxy/HAProxyProtocolVersion;
     235: getstatic     #49                 // Field io/netty/handler/codec/haproxy/HAProxyCommand.PROXY:Lio/netty/handler/codec/haproxy/HAProxyCommand;
     238: aload_3
     239: aload_1
     240: iconst_2
     241: aaload
     242: aload_1
     243: iconst_3
     244: aaload
     245: aload_1
     246: iconst_4
     247: aaload
     248: aload_1
     249: iconst_5
     250: aaload
     251: invokespecial #104                // Method "<init>":(Lio/netty/handler/codec/haproxy/HAProxyProtocolVersion;Lio/netty/handler/codec/haproxy/HAProxyCommand;Lio/netty/handler/codec/haproxy/HAProxyProxiedProtocol;Ljava/lang/String;Ljava/lang/String;Ljava/lang/String;Ljava/lang/String;)V
     254: areturn
     255: astore        4
     257: new           #27                 // class io/netty/handler/codec/haproxy/HAProxyProtocolException
     260: dup
     261: ldc           #106                // String invalid HAProxy message
     263: aload         4
     265: invokespecial #107                // Method io/netty/handler/codec/haproxy/HAProxyProtocolException."<init>":(Ljava/lang/String;Ljava/lang/Throwable;)V
     268: athrow
    Exception table:
       from    to  target type
         101   108   111   Class java/lang/IllegalArgumentException
         228   254   255   Class java/lang/RuntimeException

  private static io.netty.handler.codec.haproxy.HAProxyMessage unknownMsg(io.netty.handler.codec.haproxy.HAProxyProtocolVersion, io.netty.handler.codec.haproxy.HAProxyCommand);
    Code:
       0: new           #72                 // class io/netty/handler/codec/haproxy/HAProxyMessage
       3: dup
       4: aload_0
       5: aload_1
       6: getstatic     #48                 // Field io/netty/handler/codec/haproxy/HAProxyProxiedProtocol.UNKNOWN:Lio/netty/handler/codec/haproxy/HAProxyProxiedProtocol;
       9: aconst_null
      10: aconst_null
      11: iconst_0
      12: iconst_0
      13: invokespecial #2                  // Method "<init>":(Lio/netty/handler/codec/haproxy/HAProxyProtocolVersion;Lio/netty/handler/codec/haproxy/HAProxyCommand;Lio/netty/handler/codec/haproxy/HAProxyProxiedProtocol;Ljava/lang/String;Ljava/lang/String;II)V
      16: areturn

  private static java.lang.String ipBytesToString(io.netty.buffer.ByteBuf, int);
    Code:
       0: new           #28                 // class java/lang/StringBuilder
       3: dup
       4: invokespecial #29                 // Method java/lang/StringBuilder."<init>":()V
       7: astore_2
       8: iconst_4
       9: istore_3
      10: bipush        8
      12: istore        4
      14: iload_1
      15: iconst_4
      16: if_icmpne     57
      19: iconst_0
      20: istore        5
      22: iload         5
      24: iconst_4
      25: if_icmpge     54
      28: aload_2
      29: aload_0
      30: invokevirtual #37                 // Method io/netty/buffer/ByteBuf.readByte:()B
      33: sipush        255
      36: iand
      37: invokevirtual #32                 // Method java/lang/StringBuilder.append:(I)Ljava/lang/StringBuilder;
      40: pop
      41: aload_2
      42: bipush        46
      44: invokevirtual #69                 // Method java/lang/StringBuilder.append:(C)Ljava/lang/StringBuilder;
      47: pop
      48: iinc          5, 1
      51: goto          22
      54: goto          92
      57: iconst_0
      58: istore        5
      60: iload         5
      62: bipush        8
      64: if_icmpge     92
      67: aload_2
      68: aload_0
      69: invokevirtual #50                 // Method io/netty/buffer/ByteBuf.readUnsignedShort:()I
      72: invokestatic  #43                 // Method java/lang/Integer.toHexString:(I)Ljava/lang/String;
      75: invokevirtual #31                 // Method java/lang/StringBuilder.append:(Ljava/lang/String;)Ljava/lang/StringBuilder;
      78: pop
      79: aload_2
      80: bipush        58
      82: invokevirtual #69                 // Method java/lang/StringBuilder.append:(C)Ljava/lang/StringBuilder;
      85: pop
      86: iinc          5, 1
      89: goto          60
      92: aload_2
      93: aload_2
      94: invokevirtual #108                // Method java/lang/StringBuilder.length:()I
      97: iconst_1
      98: isub
      99: invokevirtual #109                // Method java/lang/StringBuilder.setLength:(I)V
     102: aload_2
     103: invokevirtual #34                 // Method java/lang/StringBuilder.toString:()Ljava/lang/String;
     106: areturn

  private static int portStringToInt(java.lang.String);
    Code:
       0: aload_0
       1: invokestatic  #110                // Method java/lang/Integer.parseInt:(Ljava/lang/String;)I
       4: istore_1
       5: goto          37
       8: astore_2
       9: new           #39                 // class java/lang/IllegalArgumentException
      12: dup
      13: new           #28                 // class java/lang/StringBuilder
      16: dup
      17: invokespecial #29                 // Method java/lang/StringBuilder."<init>":()V
      20: ldc           #112                // String invalid port:
      22: invokevirtual #31                 // Method java/lang/StringBuilder.append:(Ljava/lang/String;)Ljava/lang/StringBuilder;
      25: aload_0
      26: invokevirtual #31                 // Method java/lang/StringBuilder.append:(Ljava/lang/String;)Ljava/lang/StringBuilder;
      29: invokevirtual #34                 // Method java/lang/StringBuilder.toString:()Ljava/lang/String;
      32: aload_2
      33: invokespecial #113                // Method java/lang/IllegalArgumentException."<init>":(Ljava/lang/String;Ljava/lang/Throwable;)V
      36: athrow
      37: iload_1
      38: ifle          47
      41: iload_1
      42: ldc           #114                // int 65535
      44: if_icmple     79
      47: new           #39                 // class java/lang/IllegalArgumentException
      50: dup
      51: new           #28                 // class java/lang/StringBuilder
      54: dup
      55: invokespecial #29                 // Method java/lang/StringBuilder."<init>":()V
      58: ldc           #112                // String invalid port:
      60: invokevirtual #31                 // Method java/lang/StringBuilder.append:(Ljava/lang/String;)Ljava/lang/StringBuilder;
      63: aload_0
      64: invokevirtual #31                 // Method java/lang/StringBuilder.append:(Ljava/lang/String;)Ljava/lang/StringBuilder;
      67: ldc           #115                // String  (expected: 1 ~ 65535)
      69: invokevirtual #31                 // Method java/lang/StringBuilder.append:(Ljava/lang/String;)Ljava/lang/StringBuilder;
      72: invokevirtual #34                 // Method java/lang/StringBuilder.toString:()Ljava/lang/String;
      75: invokespecial #116                // Method java/lang/IllegalArgumentException."<init>":(Ljava/lang/String;)V
      78: athrow
      79: iload_1
      80: ireturn
    Exception table:
       from    to  target type
           0     5     8   Class java/lang/NumberFormatException

  private static void checkAddress(java.lang.String, io.netty.handler.codec.haproxy.HAProxyProxiedProtocol$AddressFamily);
    Code:
       0: aload_1
       1: ldc           #117                // String addrFamily
       3: invokestatic  #7                  // Method io/netty/util/internal/ObjectUtil.checkNotNull:(Ljava/lang/Object;Ljava/lang/String;)Ljava/lang/Object;
       6: pop
       7: getstatic     #118                // Field io/netty/handler/codec/haproxy/HAProxyMessage$1.$SwitchMap$io$netty$handler$codec$haproxy$HAProxyProxiedProtocol$AddressFamily:[I
      10: aload_1
      11: invokevirtual #119                // Method io/netty/handler/codec/haproxy/HAProxyProxiedProtocol$AddressFamily.ordinal:()I
      14: iaload
      15: lookupswitch  { // 2
                     1: 40
                     2: 72
               default: 120
          }
      40: aload_0
      41: ifnull        71
      44: new           #39                 // class java/lang/IllegalArgumentException
      47: dup
      48: new           #28                 // class java/lang/StringBuilder
      51: dup
      52: invokespecial #29                 // Method java/lang/StringBuilder."<init>":()V
      55: ldc           #120                // String unable to validate an AF_UNSPEC address:
      57: invokevirtual #31                 // Method java/lang/StringBuilder.append:(Ljava/lang/String;)Ljava/lang/StringBuilder;
      60: aload_0
      61: invokevirtual #31                 // Method java/lang/StringBuilder.append:(Ljava/lang/String;)Ljava/lang/StringBuilder;
      64: invokevirtual #34                 // Method java/lang/StringBuilder.toString:()Ljava/lang/String;
      67: invokespecial #116                // Method java/lang/IllegalArgumentException."<init>":(Ljava/lang/String;)V
      70: athrow
      71: return
      72: aload_0
      73: ldc           #121                // String address
      75: invokestatic  #7                  // Method io/netty/util/internal/ObjectUtil.checkNotNull:(Ljava/lang/Object;Ljava/lang/String;)Ljava/lang/Object;
      78: pop
      79: aload_0
      80: getstatic     #58                 // Field io/netty/util/CharsetUtil.US_ASCII:Ljava/nio/charset/Charset;
      83: invokevirtual #122                // Method java/lang/String.getBytes:(Ljava/nio/charset/Charset;)[B
      86: arraylength
      87: bipush        108
      89: if_icmple     119
      92: new           #39                 // class java/lang/IllegalArgumentException
      95: dup
      96: new           #28                 // class java/lang/StringBuilder
      99: dup
     100: invokespecial #29                 // Method java/lang/StringBuilder."<init>":()V
     103: ldc           #123                // String invalid AF_UNIX address:
     105: invokevirtual #31                 // Method java/lang/StringBuilder.append:(Ljava/lang/String;)Ljava/lang/StringBuilder;
     108: aload_0
     109: invokevirtual #31                 // Method java/lang/StringBuilder.append:(Ljava/lang/String;)Ljava/lang/StringBuilder;
     112: invokevirtual #34                 // Method java/lang/StringBuilder.toString:()Ljava/lang/String;
     115: invokespecial #116                // Method java/lang/IllegalArgumentException."<init>":(Ljava/lang/String;)V
     118: athrow
     119: return
     120: aload_0
     121: ldc           #121                // String address
     123: invokestatic  #7                  // Method io/netty/util/internal/ObjectUtil.checkNotNull:(Ljava/lang/Object;Ljava/lang/String;)Ljava/lang/Object;
     126: pop
     127: getstatic     #118                // Field io/netty/handler/codec/haproxy/HAProxyMessage$1.$SwitchMap$io$netty$handler$codec$haproxy$HAProxyProxiedProtocol$AddressFamily:[I
     130: aload_1
     131: invokevirtual #119                // Method io/netty/handler/codec/haproxy/HAProxyProxiedProtocol$AddressFamily.ordinal:()I
     134: iaload
     135: lookupswitch  { // 2
                     3: 160
                     4: 194
               default: 228
          }
     160: aload_0
     161: invokestatic  #124                // Method io/netty/util/NetUtil.isValidIpV4Address:(Ljava/lang/String;)Z
     164: ifne          255
     167: new           #39                 // class java/lang/IllegalArgumentException
     170: dup
     171: new           #28                 // class java/lang/StringBuilder
     174: dup
     175: invokespecial #29                 // Method java/lang/StringBuilder."<init>":()V
     178: ldc           #125                // String invalid IPv4 address:
     180: invokevirtual #31                 // Method java/lang/StringBuilder.append:(Ljava/lang/String;)Ljava/lang/StringBuilder;
     183: aload_0
     184: invokevirtual #31                 // Method java/lang/StringBuilder.append:(Ljava/lang/String;)Ljava/lang/StringBuilder;
     187: invokevirtual #34                 // Method java/lang/StringBuilder.toString:()Ljava/lang/String;
     190: invokespecial #116                // Method java/lang/IllegalArgumentException."<init>":(Ljava/lang/String;)V
     193: athrow
     194: aload_0
     195: invokestatic  #126                // Method io/netty/util/NetUtil.isValidIpV6Address:(Ljava/lang/String;)Z
     198: ifne          255
     201: new           #39                 // class java/lang/IllegalArgumentException
     204: dup
     205: new           #28                 // class java/lang/StringBuilder
     208: dup
     209: invokespecial #29                 // Method java/lang/StringBuilder."<init>":()V
     212: ldc           #127                // String invalid IPv6 address:
     214: invokevirtual #31                 // Method java/lang/StringBuilder.append:(Ljava/lang/String;)Ljava/lang/StringBuilder;
     217: aload_0
     218: invokevirtual #31                 // Method java/lang/StringBuilder.append:(Ljava/lang/String;)Ljava/lang/StringBuilder;
     221: invokevirtual #34                 // Method java/lang/StringBuilder.toString:()Ljava/lang/String;
     224: invokespecial #116                // Method java/lang/IllegalArgumentException."<init>":(Ljava/lang/String;)V
     227: athrow
     228: new           #39                 // class java/lang/IllegalArgumentException
     231: dup
     232: new           #28                 // class java/lang/StringBuilder
     235: dup
     236: invokespecial #29                 // Method java/lang/StringBuilder."<init>":()V
     239: ldc           #128                // String unexpected addrFamily:
     241: invokevirtual #31                 // Method java/lang/StringBuilder.append:(Ljava/lang/String;)Ljava/lang/StringBuilder;
     244: aload_1
     245: invokevirtual #68                 // Method java/lang/StringBuilder.append:(Ljava/lang/Object;)Ljava/lang/StringBuilder;
     248: invokevirtual #34                 // Method java/lang/StringBuilder.toString:()Ljava/lang/String;
     251: invokespecial #116                // Method java/lang/IllegalArgumentException."<init>":(Ljava/lang/String;)V
     254: athrow
     255: return

  private static void checkPort(int, io.netty.handler.codec.haproxy.HAProxyProxiedProtocol$AddressFamily);
    Code:
       0: getstatic     #118                // Field io/netty/handler/codec/haproxy/HAProxyMessage$1.$SwitchMap$io$netty$handler$codec$haproxy$HAProxyProxiedProtocol$AddressFamily:[I
       3: aload_1
       4: invokevirtual #119                // Method io/netty/handler/codec/haproxy/HAProxyProxiedProtocol$AddressFamily.ordinal:()I
       7: iaload
       8: tableswitch   { // 1 to 4
                     1: 82
                     2: 82
                     3: 40
                     4: 40
               default: 113
          }
      40: iload_0
      41: iflt          50
      44: iload_0
      45: ldc           #114                // int 65535
      47: if_icmple     140
      50: new           #39                 // class java/lang/IllegalArgumentException
      53: dup
      54: new           #28                 // class java/lang/StringBuilder
      57: dup
      58: invokespecial #29                 // Method java/lang/StringBuilder."<init>":()V
      61: ldc           #112                // String invalid port:
      63: invokevirtual #31                 // Method java/lang/StringBuilder.append:(Ljava/lang/String;)Ljava/lang/StringBuilder;
      66: iload_0
      67: invokevirtual #32                 // Method java/lang/StringBuilder.append:(I)Ljava/lang/StringBuilder;
      70: ldc           #129                // String  (expected: 0 ~ 65535)
      72: invokevirtual #31                 // Method java/lang/StringBuilder.append:(Ljava/lang/String;)Ljava/lang/StringBuilder;
      75: invokevirtual #34                 // Method java/lang/StringBuilder.toString:()Ljava/lang/String;
      78: invokespecial #116                // Method java/lang/IllegalArgumentException."<init>":(Ljava/lang/String;)V
      81: athrow
      82: iload_0
      83: ifeq          140
      86: new           #39                 // class java/lang/IllegalArgumentException
      89: dup
      90: new           #28                 // class java/lang/StringBuilder
      93: dup
      94: invokespecial #29                 // Method java/lang/StringBuilder."<init>":()V
      97: ldc           #130                // String port cannot be specified with addrFamily:
      99: invokevirtual #31                 // Method java/lang/StringBuilder.append:(Ljava/lang/String;)Ljava/lang/StringBuilder;
     102: aload_1
     103: invokevirtual #68                 // Method java/lang/StringBuilder.append:(Ljava/lang/Object;)Ljava/lang/StringBuilder;
     106: invokevirtual #34                 // Method java/lang/StringBuilder.toString:()Ljava/lang/String;
     109: invokespecial #116                // Method java/lang/IllegalArgumentException."<init>":(Ljava/lang/String;)V
     112: athrow
     113: new           #39                 // class java/lang/IllegalArgumentException
     116: dup
     117: new           #28                 // class java/lang/StringBuilder
     120: dup
     121: invokespecial #29                 // Method java/lang/StringBuilder."<init>":()V
     124: ldc           #128                // String unexpected addrFamily:
     126: invokevirtual #31                 // Method java/lang/StringBuilder.append:(Ljava/lang/String;)Ljava/lang/StringBuilder;
     129: aload_1
     130: invokevirtual #68                 // Method java/lang/StringBuilder.append:(Ljava/lang/Object;)Ljava/lang/StringBuilder;
     133: invokevirtual #34                 // Method java/lang/StringBuilder.toString:()Ljava/lang/String;
     136: invokespecial #116                // Method java/lang/IllegalArgumentException."<init>":(Ljava/lang/String;)V
     139: athrow
     140: return

  public io.netty.handler.codec.haproxy.HAProxyProtocolVersion protocolVersion();
    Code:
       0: aload_0
       1: getfield      #13                 // Field protocolVersion:Lio/netty/handler/codec/haproxy/HAProxyProtocolVersion;
       4: areturn

  public io.netty.handler.codec.haproxy.HAProxyCommand command();
    Code:
       0: aload_0
       1: getfield      #14                 // Field command:Lio/netty/handler/codec/haproxy/HAProxyCommand;
       4: areturn

  public io.netty.handler.codec.haproxy.HAProxyProxiedProtocol proxiedProtocol();
    Code:
       0: aload_0
       1: getfield      #15                 // Field proxiedProtocol:Lio/netty/handler/codec/haproxy/HAProxyProxiedProtocol;
       4: areturn

  public java.lang.String sourceAddress();
    Code:
       0: aload_0
       1: getfield      #16                 // Field sourceAddress:Ljava/lang/String;
       4: areturn

  public java.lang.String destinationAddress();
    Code:
       0: aload_0
       1: getfield      #17                 // Field destinationAddress:Ljava/lang/String;
       4: areturn

  public int sourcePort();
    Code:
       0: aload_0
       1: getfield      #18                 // Field sourcePort:I
       4: ireturn

  public int destinationPort();
    Code:
       0: aload_0
       1: getfield      #19                 // Field destinationPort:I
       4: ireturn

  public java.util.List<io.netty.handler.codec.haproxy.HAProxyTLV> tlvs();
    Code:
       0: aload_0
       1: getfield      #21                 // Field tlvs:Ljava/util/List;
       4: areturn

  int tlvNumBytes();
    Code:
       0: iconst_0
       1: istore_1
       2: iconst_0
       3: istore_2
       4: iload_2
       5: aload_0
       6: getfield      #21                 // Field tlvs:Ljava/util/List;
       9: invokeinterface #131,  1          // InterfaceMethod java/util/List.size:()I
      14: if_icmpge     42
      17: iload_1
      18: aload_0
      19: getfield      #21                 // Field tlvs:Ljava/util/List;
      22: iload_2
      23: invokeinterface #132,  2          // InterfaceMethod java/util/List.get:(I)Ljava/lang/Object;
      28: checkcast     #87                 // class io/netty/handler/codec/haproxy/HAProxyTLV
      31: invokevirtual #133                // Method io/netty/handler/codec/haproxy/HAProxyTLV.totalNumBytes:()I
      34: iadd
      35: istore_1
      36: iinc          2, 1
      39: goto          4
      42: iload_1
      43: ireturn

  public io.netty.handler.codec.haproxy.HAProxyMessage touch();
    Code:
       0: aload_0
       1: invokespecial #134                // Method tryRecord:()V
       4: aload_0
       5: invokespecial #135                // Method io/netty/util/AbstractReferenceCounted.touch:()Lio/netty/util/ReferenceCounted;
       8: checkcast     #72                 // class io/netty/handler/codec/haproxy/HAProxyMessage
      11: areturn

  public io.netty.handler.codec.haproxy.HAProxyMessage touch(java.lang.Object);
    Code:
       0: aload_0
       1: getfield      #24                 // Field leak:Lio/netty/util/ResourceLeakTracker;
       4: ifnull        17
       7: aload_0
       8: getfield      #24                 // Field leak:Lio/netty/util/ResourceLeakTracker;
      11: aload_1
      12: invokeinterface #136,  2          // InterfaceMethod io/netty/util/ResourceLeakTracker.record:(Ljava/lang/Object;)V
      17: aload_0
      18: areturn

  public io.netty.handler.codec.haproxy.HAProxyMessage retain();
    Code:
       0: aload_0
       1: invokespecial #134                // Method tryRecord:()V
       4: aload_0
       5: invokespecial #137                // Method io/netty/util/AbstractReferenceCounted.retain:()Lio/netty/util/ReferenceCounted;
       8: checkcast     #72                 // class io/netty/handler/codec/haproxy/HAProxyMessage
      11: areturn

  public io.netty.handler.codec.haproxy.HAProxyMessage retain(int);
    Code:
       0: aload_0
       1: invokespecial #134                // Method tryRecord:()V
       4: aload_0
       5: iload_1
       6: invokespecial #138                // Method io/netty/util/AbstractReferenceCounted.retain:(I)Lio/netty/util/ReferenceCounted;
       9: checkcast     #72                 // class io/netty/handler/codec/haproxy/HAProxyMessage
      12: areturn

  public boolean release();
    Code:
       0: aload_0
       1: invokespecial #134                // Method tryRecord:()V
       4: aload_0
       5: invokespecial #139                // Method io/netty/util/AbstractReferenceCounted.release:()Z
       8: ireturn

  public boolean release(int);
    Code:
       0: aload_0
       1: invokespecial #134                // Method tryRecord:()V
       4: aload_0
       5: iload_1
       6: invokespecial #140                // Method io/netty/util/AbstractReferenceCounted.release:(I)Z
       9: ireturn

  private void tryRecord();
    Code:
       0: aload_0
       1: getfield      #24                 // Field leak:Lio/netty/util/ResourceLeakTracker;
       4: ifnull        16
       7: aload_0
       8: getfield      #24                 // Field leak:Lio/netty/util/ResourceLeakTracker;
      11: invokeinterface #141,  1          // InterfaceMethod io/netty/util/ResourceLeakTracker.record:()V
      16: return

  protected void deallocate();
    Code:
       0: aload_0
       1: getfield      #21                 // Field tlvs:Ljava/util/List;
       4: invokeinterface #142,  1          // InterfaceMethod java/util/List.iterator:()Ljava/util/Iterator;
       9: astore_1
      10: aload_1
      11: invokeinterface #143,  1          // InterfaceMethod java/util/Iterator.hasNext:()Z
      16: ifeq          37
      19: aload_1
      20: invokeinterface #144,  1          // InterfaceMethod java/util/Iterator.next:()Ljava/lang/Object;
      25: checkcast     #87                 // class io/netty/handler/codec/haproxy/HAProxyTLV
      28: astore_2
      29: aload_2
      30: invokevirtual #145                // Method io/netty/handler/codec/haproxy/HAProxyTLV.release:()Z
      33: pop
      34: goto          10
      37: aload_0
      38: getfield      #24                 // Field leak:Lio/netty/util/ResourceLeakTracker;
      41: astore_1
      42: aload_1
      43: ifnull        72
      46: aload_1
      47: aload_0
      48: invokeinterface #146,  2          // InterfaceMethod io/netty/util/ResourceLeakTracker.close:(Ljava/lang/Object;)Z
      53: istore_2
      54: getstatic     #147                // Field $assertionsDisabled:Z
      57: ifne          72
      60: iload_2
      61: ifne          72
      64: new           #148                // class java/lang/AssertionError
      67: dup
      68: invokespecial #149                // Method java/lang/AssertionError."<init>":()V
      71: athrow
      72: goto          118
      75: astore_3
      76: aload_0
      77: getfield      #24                 // Field leak:Lio/netty/util/ResourceLeakTracker;
      80: astore        4
      82: aload         4
      84: ifnull        116
      87: aload         4
      89: aload_0
      90: invokeinterface #146,  2          // InterfaceMethod io/netty/util/ResourceLeakTracker.close:(Ljava/lang/Object;)Z
      95: istore        5
      97: getstatic     #147                // Field $assertionsDisabled:Z
     100: ifne          116
     103: iload         5
     105: ifne          116
     108: new           #148                // class java/lang/AssertionError
     111: dup
     112: invokespecial #149                // Method java/lang/AssertionError."<init>":()V
     115: athrow
     116: aload_3
     117: athrow
     118: return
    Exception table:
       from    to  target type
           0    37    75   any

  public java.lang.String toString();
    Code:
       0: new           #28                 // class java/lang/StringBuilder
       3: dup
       4: sipush        256
       7: invokespecial #150                // Method java/lang/StringBuilder."<init>":(I)V
      10: aload_0
      11: invokestatic  #151                // Method io/netty/util/internal/StringUtil.simpleClassName:(Ljava/lang/Object;)Ljava/lang/String;
      14: invokevirtual #31                 // Method java/lang/StringBuilder.append:(Ljava/lang/String;)Ljava/lang/StringBuilder;
      17: ldc           #152                // String (protocolVersion:
      19: invokevirtual #31                 // Method java/lang/StringBuilder.append:(Ljava/lang/String;)Ljava/lang/StringBuilder;
      22: aload_0
      23: getfield      #13                 // Field protocolVersion:Lio/netty/handler/codec/haproxy/HAProxyProtocolVersion;
      26: invokevirtual #68                 // Method java/lang/StringBuilder.append:(Ljava/lang/Object;)Ljava/lang/StringBuilder;
      29: ldc           #153                // String , command:
      31: invokevirtual #31                 // Method java/lang/StringBuilder.append:(Ljava/lang/String;)Ljava/lang/StringBuilder;
      34: aload_0
      35: getfield      #14                 // Field command:Lio/netty/handler/codec/haproxy/HAProxyCommand;
      38: invokevirtual #68                 // Method java/lang/StringBuilder.append:(Ljava/lang/Object;)Ljava/lang/StringBuilder;
      41: ldc           #154                // String , proxiedProtocol:
      43: invokevirtual #31                 // Method java/lang/StringBuilder.append:(Ljava/lang/String;)Ljava/lang/StringBuilder;
      46: aload_0
      47: getfield      #15                 // Field proxiedProtocol:Lio/netty/handler/codec/haproxy/HAProxyProxiedProtocol;
      50: invokevirtual #68                 // Method java/lang/StringBuilder.append:(Ljava/lang/Object;)Ljava/lang/StringBuilder;
      53: ldc           #155                // String , sourceAddress:
      55: invokevirtual #31                 // Method java/lang/StringBuilder.append:(Ljava/lang/String;)Ljava/lang/StringBuilder;
      58: aload_0
      59: getfield      #16                 // Field sourceAddress:Ljava/lang/String;
      62: invokevirtual #31                 // Method java/lang/StringBuilder.append:(Ljava/lang/String;)Ljava/lang/StringBuilder;
      65: ldc           #156                // String , destinationAddress:
      67: invokevirtual #31                 // Method java/lang/StringBuilder.append:(Ljava/lang/String;)Ljava/lang/StringBuilder;
      70: aload_0
      71: getfield      #17                 // Field destinationAddress:Ljava/lang/String;
      74: invokevirtual #31                 // Method java/lang/StringBuilder.append:(Ljava/lang/String;)Ljava/lang/StringBuilder;
      77: ldc           #157                // String , sourcePort:
      79: invokevirtual #31                 // Method java/lang/StringBuilder.append:(Ljava/lang/String;)Ljava/lang/StringBuilder;
      82: aload_0
      83: getfield      #18                 // Field sourcePort:I
      86: invokevirtual #32                 // Method java/lang/StringBuilder.append:(I)Ljava/lang/StringBuilder;
      89: ldc           #158                // String , destinationPort:
      91: invokevirtual #31                 // Method java/lang/StringBuilder.append:(Ljava/lang/String;)Ljava/lang/StringBuilder;
      94: aload_0
      95: getfield      #19                 // Field destinationPort:I
      98: invokevirtual #32                 // Method java/lang/StringBuilder.append:(I)Ljava/lang/StringBuilder;
     101: ldc           #159                // String , tlvs: [
     103: invokevirtual #31                 // Method java/lang/StringBuilder.append:(Ljava/lang/String;)Ljava/lang/StringBuilder;
     106: astore_1
     107: aload_0
     108: getfield      #21                 // Field tlvs:Ljava/util/List;
     111: invokeinterface #160,  1          // InterfaceMethod java/util/List.isEmpty:()Z
     116: ifne          172
     119: aload_0
     120: getfield      #21                 // Field tlvs:Ljava/util/List;
     123: invokeinterface #142,  1          // InterfaceMethod java/util/List.iterator:()Ljava/util/Iterator;
     128: astore_2
     129: aload_2
     130: invokeinterface #143,  1          // InterfaceMethod java/util/Iterator.hasNext:()Z
     135: ifeq          162
     138: aload_2
     139: invokeinterface #144,  1          // InterfaceMethod java/util/Iterator.next:()Ljava/lang/Object;
     144: checkcast     #87                 // class io/netty/handler/codec/haproxy/HAProxyTLV
     147: astore_3
     148: aload_1
     149: aload_3
     150: invokevirtual #68                 // Method java/lang/StringBuilder.append:(Ljava/lang/Object;)Ljava/lang/StringBuilder;
     153: ldc           #161                // String ,
     155: invokevirtual #31                 // Method java/lang/StringBuilder.append:(Ljava/lang/String;)Ljava/lang/StringBuilder;
     158: pop
     159: goto          129
     162: aload_1
     163: aload_1
     164: invokevirtual #108                // Method java/lang/StringBuilder.length:()I
     167: iconst_2
     168: isub
     169: invokevirtual #109                // Method java/lang/StringBuilder.setLength:(I)V
     172: aload_1
     173: ldc           #162                // String ])
     175: invokevirtual #31                 // Method java/lang/StringBuilder.append:(Ljava/lang/String;)Ljava/lang/StringBuilder;
     178: pop
     179: aload_1
     180: invokevirtual #34                 // Method java/lang/StringBuilder.toString:()Ljava/lang/String;
     183: areturn

  public io.netty.util.ReferenceCounted touch();
    Code:
       0: aload_0
       1: invokevirtual #163                // Method touch:()Lio/netty/handler/codec/haproxy/HAProxyMessage;
       4: areturn

  public io.netty.util.ReferenceCounted retain(int);
    Code:
       0: aload_0
       1: iload_1
       2: invokevirtual #164                // Method retain:(I)Lio/netty/handler/codec/haproxy/HAProxyMessage;
       5: areturn

  public io.netty.util.ReferenceCounted retain();
    Code:
       0: aload_0
       1: invokevirtual #165                // Method retain:()Lio/netty/handler/codec/haproxy/HAProxyMessage;
       4: areturn

  public io.netty.util.ReferenceCounted touch(java.lang.Object);
    Code:
       0: aload_0
       1: aload_1
       2: invokevirtual #166                // Method touch:(Ljava/lang/Object;)Lio/netty/handler/codec/haproxy/HAProxyMessage;
       5: areturn

  static {};
    Code:
       0: ldc           #72                 // class io/netty/handler/codec/haproxy/HAProxyMessage
       2: invokevirtual #167                // Method java/lang/Class.desiredAssertionStatus:()Z
       5: ifne          12
       8: iconst_1
       9: goto          13
      12: iconst_0
      13: putstatic     #147                // Field $assertionsDisabled:Z
      16: invokestatic  #168                // Method io/netty/util/ResourceLeakDetectorFactory.instance:()Lio/netty/util/ResourceLeakDetectorFactory;
      19: ldc           #72                 // class io/netty/handler/codec/haproxy/HAProxyMessage
      21: invokevirtual #169                // Method io/netty/util/ResourceLeakDetectorFactory.newResourceLeakDetector:(Ljava/lang/Class;)Lio/netty/util/ResourceLeakDetector;
      24: putstatic     #22                 // Field leakDetector:Lio/netty/util/ResourceLeakDetector;
      27: return
}
