Compiled from "FinderUtil.java"
class org.apache.jena.reasoner.FinderUtil$Cascade implements org.apache.jena.reasoner.Finder {
  org.apache.jena.reasoner.Finder first;

  org.apache.jena.reasoner.Finder second;

  org.apache.jena.reasoner.FinderUtil$Cascade(org.apache.jena.reasoner.Finder, org.apache.jena.reasoner.Finder);
    Code:
       0: aload_0
       1: invokespecial #1                  // Method java/lang/Object."<init>":()V
       4: aload_0
       5: aload_1
       6: putfield      #2                  // Field first:Lorg/apache/jena/reasoner/Finder;
       9: aload_0
      10: aload_2
      11: putfield      #3                  // Field second:Lorg/apache/jena/reasoner/Finder;
      14: return

  public org.apache.jena.util.iterator.ExtendedIterator<org.apache.jena.graph.Triple> find(org.apache.jena.reasoner.TriplePattern);
    Code:
       0: aload_0
       1: getfield      #3                  // Field second:Lorg/apache/jena/reasoner/Finder;
       4: ifnonnull     18
       7: aload_0
       8: getfield      #2                  // Field first:Lorg/apache/jena/reasoner/Finder;
      11: aload_1
      12: invokeinterface #4,  2            // InterfaceMethod org/apache/jena/reasoner/Finder.find:(Lorg/apache/jena/reasoner/TriplePattern;)Lorg/apache/jena/util/iterator/ExtendedIterator;
      17: areturn
      18: aload_0
      19: getfield      #2                  // Field first:Lorg/apache/jena/reasoner/Finder;
      22: ifnonnull     36
      25: aload_0
      26: getfield      #3                  // Field second:Lorg/apache/jena/reasoner/Finder;
      29: aload_1
      30: invokeinterface #4,  2            // InterfaceMethod org/apache/jena/reasoner/Finder.find:(Lorg/apache/jena/reasoner/TriplePattern;)Lorg/apache/jena/util/iterator/ExtendedIterator;
      35: areturn
      36: aload_0
      37: getfield      #2                  // Field first:Lorg/apache/jena/reasoner/Finder;
      40: aload_1
      41: aload_0
      42: getfield      #3                  // Field second:Lorg/apache/jena/reasoner/Finder;
      45: invokeinterface #5,  3            // InterfaceMethod org/apache/jena/reasoner/Finder.findWithContinuation:(Lorg/apache/jena/reasoner/TriplePattern;Lorg/apache/jena/reasoner/Finder;)Lorg/apache/jena/util/iterator/ExtendedIterator;
      50: areturn

  public org.apache.jena.util.iterator.ExtendedIterator<org.apache.jena.graph.Triple> findWithContinuation(org.apache.jena.reasoner.TriplePattern, org.apache.jena.reasoner.Finder);
    Code:
       0: aload_0
       1: getfield      #2                  // Field first:Lorg/apache/jena/reasoner/Finder;
       4: aload_0
       5: getfield      #3                  // Field second:Lorg/apache/jena/reasoner/Finder;
       8: aload_2
       9: invokestatic  #6                  // Method org/apache/jena/reasoner/FinderUtil.cascade:(Lorg/apache/jena/reasoner/Finder;Lorg/apache/jena/reasoner/Finder;Lorg/apache/jena/reasoner/Finder;)Lorg/apache/jena/reasoner/Finder;
      12: aload_1
      13: invokeinterface #4,  2            // InterfaceMethod org/apache/jena/reasoner/Finder.find:(Lorg/apache/jena/reasoner/TriplePattern;)Lorg/apache/jena/util/iterator/ExtendedIterator;
      18: areturn

  public boolean contains(org.apache.jena.reasoner.TriplePattern);
    Code:
       0: aload_0
       1: aload_1
       2: invokevirtual #7                  // Method find:(Lorg/apache/jena/reasoner/TriplePattern;)Lorg/apache/jena/util/iterator/ExtendedIterator;
       5: astore_2
       6: aload_2
       7: invokeinterface #8,  1            // InterfaceMethod org/apache/jena/util/iterator/ClosableIterator.hasNext:()Z
      12: istore_3
      13: aload_2
      14: invokeinterface #9,  1            // InterfaceMethod org/apache/jena/util/iterator/ClosableIterator.close:()V
      19: iload_3
      20: ireturn
}
