Compiled from "CommandContextFactoryImpl.java"
public class org.jboss.as.cli.impl.CommandContextFactoryImpl extends org.jboss.as.cli.CommandContextFactory {
  public org.jboss.as.cli.impl.CommandContextFactoryImpl();
    Code:
       0: aload_0
       1: invokespecial #1                  // Method org/jboss/as/cli/CommandContextFactory."<init>":()V
       4: return

  public org.jboss.as.cli.CommandContext newCommandContext() throws org.jboss.as.cli.CliInitializationException;
    Code:
       0: new           #2                  // class org/jboss/as/cli/impl/CommandContextImpl
       3: dup
       4: invokespecial #3                  // Method org/jboss/as/cli/impl/CommandContextImpl."<init>":()V
       7: areturn

  public org.jboss.as.cli.CommandContext newCommandContext(java.lang.String, char[]) throws org.jboss.as.cli.CliInitializationException;
    Code:
       0: aload_0
       1: new           #4                  // class org/jboss/as/cli/impl/CommandContextConfiguration$Builder
       4: dup
       5: invokespecial #5                  // Method org/jboss/as/cli/impl/CommandContextConfiguration$Builder."<init>":()V
       8: aload_1
       9: invokevirtual #6                  // Method org/jboss/as/cli/impl/CommandContextConfiguration$Builder.setUsername:(Ljava/lang/String;)Lorg/jboss/as/cli/impl/CommandContextConfiguration$Builder;
      12: aload_2
      13: invokevirtual #7                  // Method org/jboss/as/cli/impl/CommandContextConfiguration$Builder.setPassword:([C)Lorg/jboss/as/cli/impl/CommandContextConfiguration$Builder;
      16: iconst_0
      17: invokevirtual #8                  // Method org/jboss/as/cli/impl/CommandContextConfiguration$Builder.setInitConsole:(Z)Lorg/jboss/as/cli/impl/CommandContextConfiguration$Builder;
      20: invokevirtual #9                  // Method org/jboss/as/cli/impl/CommandContextConfiguration$Builder.build:()Lorg/jboss/as/cli/impl/CommandContextConfiguration;
      23: invokevirtual #10                 // Method newCommandContext:(Lorg/jboss/as/cli/impl/CommandContextConfiguration;)Lorg/jboss/as/cli/CommandContext;
      26: areturn

  public org.jboss.as.cli.CommandContext newCommandContext(java.lang.String, java.lang.String, char[]) throws org.jboss.as.cli.CliInitializationException;
    Code:
       0: aload_0
       1: new           #4                  // class org/jboss/as/cli/impl/CommandContextConfiguration$Builder
       4: dup
       5: invokespecial #5                  // Method org/jboss/as/cli/impl/CommandContextConfiguration$Builder."<init>":()V
       8: aload_1
       9: invokevirtual #11                 // Method org/jboss/as/cli/impl/CommandContextConfiguration$Builder.setController:(Ljava/lang/String;)Lorg/jboss/as/cli/impl/CommandContextConfiguration$Builder;
      12: aload_2
      13: invokevirtual #6                  // Method org/jboss/as/cli/impl/CommandContextConfiguration$Builder.setUsername:(Ljava/lang/String;)Lorg/jboss/as/cli/impl/CommandContextConfiguration$Builder;
      16: aload_3
      17: invokevirtual #7                  // Method org/jboss/as/cli/impl/CommandContextConfiguration$Builder.setPassword:([C)Lorg/jboss/as/cli/impl/CommandContextConfiguration$Builder;
      20: iconst_0
      21: invokevirtual #8                  // Method org/jboss/as/cli/impl/CommandContextConfiguration$Builder.setInitConsole:(Z)Lorg/jboss/as/cli/impl/CommandContextConfiguration$Builder;
      24: invokevirtual #9                  // Method org/jboss/as/cli/impl/CommandContextConfiguration$Builder.build:()Lorg/jboss/as/cli/impl/CommandContextConfiguration;
      27: invokevirtual #10                 // Method newCommandContext:(Lorg/jboss/as/cli/impl/CommandContextConfiguration;)Lorg/jboss/as/cli/CommandContext;
      30: areturn

  public org.jboss.as.cli.CommandContext newCommandContext(java.lang.String, java.lang.String, char[], boolean, int) throws org.jboss.as.cli.CliInitializationException;
    Code:
       0: aload_0
       1: new           #4                  // class org/jboss/as/cli/impl/CommandContextConfiguration$Builder
       4: dup
       5: invokespecial #5                  // Method org/jboss/as/cli/impl/CommandContextConfiguration$Builder."<init>":()V
       8: aload_1
       9: invokevirtual #11                 // Method org/jboss/as/cli/impl/CommandContextConfiguration$Builder.setController:(Ljava/lang/String;)Lorg/jboss/as/cli/impl/CommandContextConfiguration$Builder;
      12: aload_2
      13: invokevirtual #6                  // Method org/jboss/as/cli/impl/CommandContextConfiguration$Builder.setUsername:(Ljava/lang/String;)Lorg/jboss/as/cli/impl/CommandContextConfiguration$Builder;
      16: aload_3
      17: invokevirtual #7                  // Method org/jboss/as/cli/impl/CommandContextConfiguration$Builder.setPassword:([C)Lorg/jboss/as/cli/impl/CommandContextConfiguration$Builder;
      20: iload         4
      22: invokevirtual #8                  // Method org/jboss/as/cli/impl/CommandContextConfiguration$Builder.setInitConsole:(Z)Lorg/jboss/as/cli/impl/CommandContextConfiguration$Builder;
      25: iload         5
      27: invokevirtual #12                 // Method org/jboss/as/cli/impl/CommandContextConfiguration$Builder.setConnectionTimeout:(I)Lorg/jboss/as/cli/impl/CommandContextConfiguration$Builder;
      30: invokevirtual #9                  // Method org/jboss/as/cli/impl/CommandContextConfiguration$Builder.build:()Lorg/jboss/as/cli/impl/CommandContextConfiguration;
      33: invokevirtual #10                 // Method newCommandContext:(Lorg/jboss/as/cli/impl/CommandContextConfiguration;)Lorg/jboss/as/cli/CommandContext;
      36: areturn

  public org.jboss.as.cli.CommandContext newCommandContext(java.lang.String, java.lang.String, char[], boolean, boolean, int) throws org.jboss.as.cli.CliInitializationException;
    Code:
       0: aload_0
       1: new           #4                  // class org/jboss/as/cli/impl/CommandContextConfiguration$Builder
       4: dup
       5: invokespecial #5                  // Method org/jboss/as/cli/impl/CommandContextConfiguration$Builder."<init>":()V
       8: aload_1
       9: invokevirtual #11                 // Method org/jboss/as/cli/impl/CommandContextConfiguration$Builder.setController:(Ljava/lang/String;)Lorg/jboss/as/cli/impl/CommandContextConfiguration$Builder;
      12: aload_2
      13: invokevirtual #6                  // Method org/jboss/as/cli/impl/CommandContextConfiguration$Builder.setUsername:(Ljava/lang/String;)Lorg/jboss/as/cli/impl/CommandContextConfiguration$Builder;
      16: aload_3
      17: invokevirtual #7                  // Method org/jboss/as/cli/impl/CommandContextConfiguration$Builder.setPassword:([C)Lorg/jboss/as/cli/impl/CommandContextConfiguration$Builder;
      20: iload         4
      22: invokevirtual #13                 // Method org/jboss/as/cli/impl/CommandContextConfiguration$Builder.setDisableLocalAuth:(Z)Lorg/jboss/as/cli/impl/CommandContextConfiguration$Builder;
      25: iload         5
      27: invokevirtual #8                  // Method org/jboss/as/cli/impl/CommandContextConfiguration$Builder.setInitConsole:(Z)Lorg/jboss/as/cli/impl/CommandContextConfiguration$Builder;
      30: iload         6
      32: invokevirtual #12                 // Method org/jboss/as/cli/impl/CommandContextConfiguration$Builder.setConnectionTimeout:(I)Lorg/jboss/as/cli/impl/CommandContextConfiguration$Builder;
      35: invokevirtual #9                  // Method org/jboss/as/cli/impl/CommandContextConfiguration$Builder.build:()Lorg/jboss/as/cli/impl/CommandContextConfiguration;
      38: invokevirtual #10                 // Method newCommandContext:(Lorg/jboss/as/cli/impl/CommandContextConfiguration;)Lorg/jboss/as/cli/CommandContext;
      41: areturn

  public org.jboss.as.cli.CommandContext newCommandContext(java.lang.String, java.lang.String, char[], java.io.InputStream, java.io.OutputStream) throws org.jboss.as.cli.CliInitializationException;
    Code:
       0: aload_0
       1: new           #4                  // class org/jboss/as/cli/impl/CommandContextConfiguration$Builder
       4: dup
       5: invokespecial #5                  // Method org/jboss/as/cli/impl/CommandContextConfiguration$Builder."<init>":()V
       8: aload_1
       9: invokevirtual #11                 // Method org/jboss/as/cli/impl/CommandContextConfiguration$Builder.setController:(Ljava/lang/String;)Lorg/jboss/as/cli/impl/CommandContextConfiguration$Builder;
      12: aload_2
      13: invokevirtual #6                  // Method org/jboss/as/cli/impl/CommandContextConfiguration$Builder.setUsername:(Ljava/lang/String;)Lorg/jboss/as/cli/impl/CommandContextConfiguration$Builder;
      16: aload_3
      17: invokevirtual #7                  // Method org/jboss/as/cli/impl/CommandContextConfiguration$Builder.setPassword:([C)Lorg/jboss/as/cli/impl/CommandContextConfiguration$Builder;
      20: aload         4
      22: invokevirtual #14                 // Method org/jboss/as/cli/impl/CommandContextConfiguration$Builder.setConsoleInput:(Ljava/io/InputStream;)Lorg/jboss/as/cli/impl/CommandContextConfiguration$Builder;
      25: aload         5
      27: invokevirtual #15                 // Method org/jboss/as/cli/impl/CommandContextConfiguration$Builder.setConsoleOutput:(Ljava/io/OutputStream;)Lorg/jboss/as/cli/impl/CommandContextConfiguration$Builder;
      30: iconst_0
      31: invokevirtual #13                 // Method org/jboss/as/cli/impl/CommandContextConfiguration$Builder.setDisableLocalAuth:(Z)Lorg/jboss/as/cli/impl/CommandContextConfiguration$Builder;
      34: iconst_0
      35: invokevirtual #8                  // Method org/jboss/as/cli/impl/CommandContextConfiguration$Builder.setInitConsole:(Z)Lorg/jboss/as/cli/impl/CommandContextConfiguration$Builder;
      38: invokevirtual #9                  // Method org/jboss/as/cli/impl/CommandContextConfiguration$Builder.build:()Lorg/jboss/as/cli/impl/CommandContextConfiguration;
      41: invokevirtual #10                 // Method newCommandContext:(Lorg/jboss/as/cli/impl/CommandContextConfiguration;)Lorg/jboss/as/cli/CommandContext;
      44: areturn

  public org.jboss.as.cli.CommandContext newCommandContext(java.lang.String, int, java.lang.String, char[]) throws org.jboss.as.cli.CliInitializationException;
    Code:
       0: aload_0
       1: new           #4                  // class org/jboss/as/cli/impl/CommandContextConfiguration$Builder
       4: dup
       5: invokespecial #5                  // Method org/jboss/as/cli/impl/CommandContextConfiguration$Builder."<init>":()V
       8: new           #16                 // class java/net/URI
      11: dup
      12: aconst_null
      13: aconst_null
      14: aload_1
      15: iload_2
      16: aconst_null
      17: aconst_null
      18: aconst_null
      19: invokespecial #17                 // Method java/net/URI."<init>":(Ljava/lang/String;Ljava/lang/String;Ljava/lang/String;ILjava/lang/String;Ljava/lang/String;Ljava/lang/String;)V
      22: invokevirtual #18                 // Method java/net/URI.toString:()Ljava/lang/String;
      25: iconst_2
      26: invokevirtual #19                 // Method java/lang/String.substring:(I)Ljava/lang/String;
      29: invokevirtual #11                 // Method org/jboss/as/cli/impl/CommandContextConfiguration$Builder.setController:(Ljava/lang/String;)Lorg/jboss/as/cli/impl/CommandContextConfiguration$Builder;
      32: aload_3
      33: invokevirtual #6                  // Method org/jboss/as/cli/impl/CommandContextConfiguration$Builder.setUsername:(Ljava/lang/String;)Lorg/jboss/as/cli/impl/CommandContextConfiguration$Builder;
      36: aload         4
      38: invokevirtual #7                  // Method org/jboss/as/cli/impl/CommandContextConfiguration$Builder.setPassword:([C)Lorg/jboss/as/cli/impl/CommandContextConfiguration$Builder;
      41: invokevirtual #9                  // Method org/jboss/as/cli/impl/CommandContextConfiguration$Builder.build:()Lorg/jboss/as/cli/impl/CommandContextConfiguration;
      44: invokevirtual #10                 // Method newCommandContext:(Lorg/jboss/as/cli/impl/CommandContextConfiguration;)Lorg/jboss/as/cli/CommandContext;
      47: areturn
      48: astore        5
      50: new           #21                 // class org/jboss/as/cli/CliInitializationException
      53: dup
      54: ldc           #22                 // String Unable to construct URI for connection.
      56: aload         5
      58: invokespecial #23                 // Method org/jboss/as/cli/CliInitializationException."<init>":(Ljava/lang/String;Ljava/lang/Throwable;)V
      61: athrow
    Exception table:
       from    to  target type
           0    47    48   Class java/net/URISyntaxException

  public org.jboss.as.cli.CommandContext newCommandContext(java.lang.String, int, java.lang.String, char[], boolean, int) throws org.jboss.as.cli.CliInitializationException;
    Code:
       0: aload_0
       1: new           #4                  // class org/jboss/as/cli/impl/CommandContextConfiguration$Builder
       4: dup
       5: invokespecial #5                  // Method org/jboss/as/cli/impl/CommandContextConfiguration$Builder."<init>":()V
       8: new           #16                 // class java/net/URI
      11: dup
      12: aconst_null
      13: aconst_null
      14: aload_1
      15: iload_2
      16: aconst_null
      17: aconst_null
      18: aconst_null
      19: invokespecial #17                 // Method java/net/URI."<init>":(Ljava/lang/String;Ljava/lang/String;Ljava/lang/String;ILjava/lang/String;Ljava/lang/String;Ljava/lang/String;)V
      22: invokevirtual #18                 // Method java/net/URI.toString:()Ljava/lang/String;
      25: iconst_2
      26: invokevirtual #19                 // Method java/lang/String.substring:(I)Ljava/lang/String;
      29: invokevirtual #11                 // Method org/jboss/as/cli/impl/CommandContextConfiguration$Builder.setController:(Ljava/lang/String;)Lorg/jboss/as/cli/impl/CommandContextConfiguration$Builder;
      32: aload_3
      33: invokevirtual #6                  // Method org/jboss/as/cli/impl/CommandContextConfiguration$Builder.setUsername:(Ljava/lang/String;)Lorg/jboss/as/cli/impl/CommandContextConfiguration$Builder;
      36: aload         4
      38: invokevirtual #7                  // Method org/jboss/as/cli/impl/CommandContextConfiguration$Builder.setPassword:([C)Lorg/jboss/as/cli/impl/CommandContextConfiguration$Builder;
      41: iload         5
      43: invokevirtual #8                  // Method org/jboss/as/cli/impl/CommandContextConfiguration$Builder.setInitConsole:(Z)Lorg/jboss/as/cli/impl/CommandContextConfiguration$Builder;
      46: iload         6
      48: invokevirtual #12                 // Method org/jboss/as/cli/impl/CommandContextConfiguration$Builder.setConnectionTimeout:(I)Lorg/jboss/as/cli/impl/CommandContextConfiguration$Builder;
      51: invokevirtual #9                  // Method org/jboss/as/cli/impl/CommandContextConfiguration$Builder.build:()Lorg/jboss/as/cli/impl/CommandContextConfiguration;
      54: invokevirtual #10                 // Method newCommandContext:(Lorg/jboss/as/cli/impl/CommandContextConfiguration;)Lorg/jboss/as/cli/CommandContext;
      57: areturn
      58: astore        7
      60: new           #21                 // class org/jboss/as/cli/CliInitializationException
      63: dup
      64: ldc           #22                 // String Unable to construct URI for connection.
      66: aload         7
      68: invokespecial #23                 // Method org/jboss/as/cli/CliInitializationException."<init>":(Ljava/lang/String;Ljava/lang/Throwable;)V
      71: athrow
    Exception table:
       from    to  target type
           0    57    58   Class java/net/URISyntaxException

  public org.jboss.as.cli.CommandContext newCommandContext(java.lang.String, int, java.lang.String, char[], java.io.InputStream, java.io.OutputStream) throws org.jboss.as.cli.CliInitializationException;
    Code:
       0: aload_0
       1: new           #4                  // class org/jboss/as/cli/impl/CommandContextConfiguration$Builder
       4: dup
       5: invokespecial #5                  // Method org/jboss/as/cli/impl/CommandContextConfiguration$Builder."<init>":()V
       8: new           #16                 // class java/net/URI
      11: dup
      12: aconst_null
      13: aconst_null
      14: aload_1
      15: iload_2
      16: aconst_null
      17: aconst_null
      18: aconst_null
      19: invokespecial #17                 // Method java/net/URI."<init>":(Ljava/lang/String;Ljava/lang/String;Ljava/lang/String;ILjava/lang/String;Ljava/lang/String;Ljava/lang/String;)V
      22: invokevirtual #18                 // Method java/net/URI.toString:()Ljava/lang/String;
      25: iconst_2
      26: invokevirtual #19                 // Method java/lang/String.substring:(I)Ljava/lang/String;
      29: invokevirtual #11                 // Method org/jboss/as/cli/impl/CommandContextConfiguration$Builder.setController:(Ljava/lang/String;)Lorg/jboss/as/cli/impl/CommandContextConfiguration$Builder;
      32: aload_3
      33: invokevirtual #6                  // Method org/jboss/as/cli/impl/CommandContextConfiguration$Builder.setUsername:(Ljava/lang/String;)Lorg/jboss/as/cli/impl/CommandContextConfiguration$Builder;
      36: aload         4
      38: invokevirtual #7                  // Method org/jboss/as/cli/impl/CommandContextConfiguration$Builder.setPassword:([C)Lorg/jboss/as/cli/impl/CommandContextConfiguration$Builder;
      41: aload         5
      43: invokevirtual #14                 // Method org/jboss/as/cli/impl/CommandContextConfiguration$Builder.setConsoleInput:(Ljava/io/InputStream;)Lorg/jboss/as/cli/impl/CommandContextConfiguration$Builder;
      46: aload         6
      48: invokevirtual #15                 // Method org/jboss/as/cli/impl/CommandContextConfiguration$Builder.setConsoleOutput:(Ljava/io/OutputStream;)Lorg/jboss/as/cli/impl/CommandContextConfiguration$Builder;
      51: iconst_0
      52: invokevirtual #8                  // Method org/jboss/as/cli/impl/CommandContextConfiguration$Builder.setInitConsole:(Z)Lorg/jboss/as/cli/impl/CommandContextConfiguration$Builder;
      55: iconst_0
      56: invokevirtual #13                 // Method org/jboss/as/cli/impl/CommandContextConfiguration$Builder.setDisableLocalAuth:(Z)Lorg/jboss/as/cli/impl/CommandContextConfiguration$Builder;
      59: invokevirtual #9                  // Method org/jboss/as/cli/impl/CommandContextConfiguration$Builder.build:()Lorg/jboss/as/cli/impl/CommandContextConfiguration;
      62: invokevirtual #10                 // Method newCommandContext:(Lorg/jboss/as/cli/impl/CommandContextConfiguration;)Lorg/jboss/as/cli/CommandContext;
      65: areturn
      66: astore        7
      68: new           #21                 // class org/jboss/as/cli/CliInitializationException
      71: dup
      72: ldc           #22                 // String Unable to construct URI for connection.
      74: aload         7
      76: invokespecial #23                 // Method org/jboss/as/cli/CliInitializationException."<init>":(Ljava/lang/String;Ljava/lang/Throwable;)V
      79: athrow
    Exception table:
       from    to  target type
           0    65    66   Class java/net/URISyntaxException

  public org.jboss.as.cli.CommandContext newCommandContext(org.jboss.as.cli.impl.CommandContextConfiguration) throws org.jboss.as.cli.CliInitializationException;
    Code:
       0: new           #2                  // class org/jboss/as/cli/impl/CommandContextImpl
       3: dup
       4: aload_1
       5: invokespecial #24                 // Method org/jboss/as/cli/impl/CommandContextImpl."<init>":(Lorg/jboss/as/cli/impl/CommandContextConfiguration;)V
       8: areturn
}
