Compiled from "CommandContextImpl.java"
class org.jboss.as.cli.impl.CommandContextImpl$JaasConfigurationWrapper extends javax.security.auth.login.Configuration {
  private final javax.security.auth.login.Configuration wrapped;

  final org.jboss.as.cli.impl.CommandContextImpl this$0;

  private org.jboss.as.cli.impl.CommandContextImpl$JaasConfigurationWrapper(org.jboss.as.cli.impl.CommandContextImpl, javax.security.auth.login.Configuration);
    Code:
       0: aload_0
       1: aload_1
       2: putfield      #2                  // Field this$0:Lorg/jboss/as/cli/impl/CommandContextImpl;
       5: aload_0
       6: invokespecial #3                  // Method javax/security/auth/login/Configuration."<init>":()V
       9: aload_0
      10: aload_2
      11: putfield      #4                  // Field wrapped:Ljavax/security/auth/login/Configuration;
      14: return

  public javax.security.auth.login.AppConfigurationEntry[] getAppConfigurationEntry(java.lang.String);
    Code:
       0: aload_0
       1: getfield      #4                  // Field wrapped:Ljavax/security/auth/login/Configuration;
       4: ifnull        18
       7: aload_0
       8: getfield      #4                  // Field wrapped:Ljavax/security/auth/login/Configuration;
      11: aload_1
      12: invokevirtual #5                  // Method javax/security/auth/login/Configuration.getAppConfigurationEntry:(Ljava/lang/String;)[Ljavax/security/auth/login/AppConfigurationEntry;
      15: goto          19
      18: aconst_null
      19: astore_2
      20: aload_2
      21: ifnonnull     81
      24: ldc           #6                  // String com.sun.security.jgss.initiate
      26: aload_1
      27: invokevirtual #7                  // Method java/lang/String.equals:(Ljava/lang/Object;)Z
      30: ifeq          81
      33: new           #8                  // class java/util/HashMap
      36: dup
      37: iconst_2
      38: invokespecial #9                  // Method java/util/HashMap."<init>":(I)V
      41: astore_3
      42: aload_3
      43: ldc           #10                 // String useTicketCache
      45: ldc           #11                 // String true
      47: invokevirtual #12                 // Method java/util/HashMap.put:(Ljava/lang/Object;Ljava/lang/Object;)Ljava/lang/Object;
      50: pop
      51: aload_3
      52: ldc           #13                 // String doNotPrompt
      54: ldc           #11                 // String true
      56: invokevirtual #12                 // Method java/util/HashMap.put:(Ljava/lang/Object;Ljava/lang/Object;)Ljava/lang/Object;
      59: pop
      60: iconst_1
      61: anewarray     #14                 // class javax/security/auth/login/AppConfigurationEntry
      64: dup
      65: iconst_0
      66: new           #14                 // class javax/security/auth/login/AppConfigurationEntry
      69: dup
      70: ldc           #15                 // String com.sun.security.auth.module.Krb5LoginModule
      72: getstatic     #16                 // Field javax/security/auth/login/AppConfigurationEntry$LoginModuleControlFlag.REQUIRED:Ljavax/security/auth/login/AppConfigurationEntry$LoginModuleControlFlag;
      75: aload_3
      76: invokespecial #17                 // Method javax/security/auth/login/AppConfigurationEntry."<init>":(Ljava/lang/String;Ljavax/security/auth/login/AppConfigurationEntry$LoginModuleControlFlag;Ljava/util/Map;)V
      79: aastore
      80: astore_2
      81: aload_2
      82: areturn

  org.jboss.as.cli.impl.CommandContextImpl$JaasConfigurationWrapper(org.jboss.as.cli.impl.CommandContextImpl, javax.security.auth.login.Configuration, org.jboss.as.cli.impl.CommandContextImpl$1);
    Code:
       0: aload_0
       1: aload_1
       2: aload_2
       3: invokespecial #1                  // Method "<init>":(Lorg/jboss/as/cli/impl/CommandContextImpl;Ljavax/security/auth/login/Configuration;)V
       6: return
}
