Compiled from "AppSequenceType.java"
public class org.apache.cxf.ws.discovery.wsdl.AppSequenceType {
  protected long instanceId;

  protected java.lang.String sequenceId;

  protected long messageNumber;

  private java.util.Map<javax.xml.namespace.QName, java.lang.String> otherAttributes;

  public org.apache.cxf.ws.discovery.wsdl.AppSequenceType();
    Code:
       0: aload_0
       1: invokespecial #1                  // Method java/lang/Object."<init>":()V
       4: aload_0
       5: new           #2                  // class java/util/HashMap
       8: dup
       9: invokespecial #3                  // Method java/util/HashMap."<init>":()V
      12: putfield      #4                  // Field otherAttributes:Ljava/util/Map;
      15: return

  public long getInstanceId();
    Code:
       0: aload_0
       1: getfield      #5                  // Field instanceId:J
       4: lreturn

  public void setInstanceId(long);
    Code:
       0: aload_0
       1: lload_1
       2: putfield      #5                  // Field instanceId:J
       5: return

  public java.lang.String getSequenceId();
    Code:
       0: aload_0
       1: getfield      #6                  // Field sequenceId:Ljava/lang/String;
       4: areturn

  public void setSequenceId(java.lang.String);
    Code:
       0: aload_0
       1: aload_1
       2: putfield      #6                  // Field sequenceId:Ljava/lang/String;
       5: return

  public long getMessageNumber();
    Code:
       0: aload_0
       1: getfield      #7                  // Field messageNumber:J
       4: lreturn

  public void setMessageNumber(long);
    Code:
       0: aload_0
       1: lload_1
       2: putfield      #7                  // Field messageNumber:J
       5: return

  public java.util.Map<javax.xml.namespace.QName, java.lang.String> getOtherAttributes();
    Code:
       0: aload_0
       1: getfield      #4                  // Field otherAttributes:Ljava/util/Map;
       4: areturn
}
