Compiled from "ModClusterNodeDefinition.java"
class org.wildfly.extension.undertow.filters.ModClusterNodeDefinition$19 extends org.wildfly.extension.undertow.filters.ModClusterNodeDefinition$AbstractNodeOperation {
  final org.wildfly.extension.undertow.filters.ModClusterNodeDefinition this$0;

  org.wildfly.extension.undertow.filters.ModClusterNodeDefinition$19(org.wildfly.extension.undertow.filters.ModClusterNodeDefinition);
    Code:
       0: aload_0
       1: aload_1
       2: putfield      #1                  // Field this$0:Lorg/wildfly/extension/undertow/filters/ModClusterNodeDefinition;
       5: aload_0
       6: aload_1
       7: aconst_null
       8: invokespecial #2                  // Method org/wildfly/extension/undertow/filters/ModClusterNodeDefinition$AbstractNodeOperation."<init>":(Lorg/wildfly/extension/undertow/filters/ModClusterNodeDefinition;Lorg/wildfly/extension/undertow/filters/ModClusterNodeDefinition$1;)V
      11: return

  protected void handleNode(org.jboss.as.controller.OperationContext, io.undertow.server.handlers.proxy.mod_cluster.ModClusterStatus$Node, org.jboss.dmr.ModelNode) throws org.jboss.as.controller.OperationFailedException;
    Code:
       0: new           #3                  // class org/jboss/dmr/ModelNode
       3: dup
       4: invokespecial #4                  // Method org/jboss/dmr/ModelNode."<init>":()V
       7: astore        4
       9: aload_2
      10: invokeinterface #5,  1            // InterfaceMethod io/undertow/server/handlers/proxy/mod_cluster/ModClusterStatus$Node.getAliases:()Ljava/util/List;
      15: invokeinterface #6,  1            // InterfaceMethod java/util/List.iterator:()Ljava/util/Iterator;
      20: astore        5
      22: aload         5
      24: invokeinterface #7,  1            // InterfaceMethod java/util/Iterator.hasNext:()Z
      29: ifeq          67
      32: aload         5
      34: invokeinterface #8,  1            // InterfaceMethod java/util/Iterator.next:()Ljava/lang/Object;
      39: checkcast     #9                  // class java/lang/String
      42: astore        6
      44: getstatic     #10                 // Field org/wildfly/extension/undertow/logging/UndertowLogger.ROOT_LOGGER:Lorg/wildfly/extension/undertow/logging/UndertowLogger;
      47: ldc           #11                 // String Adding alias %s
      49: aload         6
      51: invokeinterface #12,  3           // InterfaceMethod org/wildfly/extension/undertow/logging/UndertowLogger.tracef:(Ljava/lang/String;Ljava/lang/Object;)V
      56: aload         4
      58: aload         6
      60: invokevirtual #13                 // Method org/jboss/dmr/ModelNode.add:(Ljava/lang/String;)Lorg/jboss/dmr/ModelNode;
      63: pop
      64: goto          22
      67: aload_1
      68: invokeinterface #14,  1           // InterfaceMethod org/jboss/as/controller/OperationContext.getResult:()Lorg/jboss/dmr/ModelNode;
      73: aload         4
      75: invokevirtual #15                 // Method org/jboss/dmr/ModelNode.set:(Lorg/jboss/dmr/ModelNode;)Lorg/jboss/dmr/ModelNode;
      78: pop
      79: return
}
