Compiled from "Digester.java"
public class org.apache.tomcat.util.digester.Digester extends org.xml.sax.ext.DefaultHandler2 {
  protected static org.apache.tomcat.util.IntrospectionUtils$PropertySource[] propertySources;

  private static boolean propertySourcesSet;

  protected static final org.apache.tomcat.util.res.StringManager sm;

  private static final java.util.HashSet<java.lang.String> generatedClasses;

  private static org.apache.tomcat.util.digester.Digester$GeneratedCodeLoader generatedCodeLoader;

  protected org.apache.tomcat.util.IntrospectionUtils$PropertySource[] source;

  protected java.lang.StringBuilder bodyText;

  protected org.apache.tomcat.util.digester.ArrayStack<java.lang.StringBuilder> bodyTexts;

  protected org.apache.tomcat.util.digester.ArrayStack<java.util.List<org.apache.tomcat.util.digester.Rule>> matches;

  protected java.lang.ClassLoader classLoader;

  protected boolean configured;

  protected org.xml.sax.EntityResolver entityResolver;

  protected java.util.HashMap<java.lang.String, java.lang.String> entityValidator;

  protected org.xml.sax.ErrorHandler errorHandler;

  protected javax.xml.parsers.SAXParserFactory factory;

  protected org.xml.sax.Locator locator;

  protected java.lang.String match;

  protected boolean namespaceAware;

  protected java.util.HashMap<java.lang.String, org.apache.tomcat.util.digester.ArrayStack<java.lang.String>> namespaces;

  protected org.apache.tomcat.util.digester.ArrayStack<java.lang.Object> params;

  protected javax.xml.parsers.SAXParser parser;

  protected java.lang.String publicId;

  protected org.xml.sax.XMLReader reader;

  protected java.lang.Object root;

  protected org.apache.tomcat.util.digester.Rules rules;

  protected org.apache.tomcat.util.digester.ArrayStack<java.lang.Object> stack;

  protected boolean useContextClassLoader;

  protected boolean validating;

  protected boolean rulesValidation;

  protected java.util.Map<java.lang.Class<?>, java.util.List<java.lang.String>> fakeAttributes;

  protected org.apache.juli.logging.Log log;

  protected org.apache.juli.logging.Log saxLog;

  protected java.lang.StringBuilder code;

  protected java.util.ArrayList<java.lang.Object> known;

  public static void setPropertySource(org.apache.tomcat.util.IntrospectionUtils$PropertySource);
    Code:
       0: getstatic     #1                  // Field propertySourcesSet:Z
       3: ifne          23
       6: iconst_1
       7: anewarray     #2                  // class org/apache/tomcat/util/IntrospectionUtils$PropertySource
      10: putstatic     #3                  // Field propertySources:[Lorg/apache/tomcat/util/IntrospectionUtils$PropertySource;
      13: getstatic     #3                  // Field propertySources:[Lorg/apache/tomcat/util/IntrospectionUtils$PropertySource;
      16: iconst_0
      17: aload_0
      18: aastore
      19: iconst_1
      20: putstatic     #1                  // Field propertySourcesSet:Z
      23: return

  public static void setPropertySource(org.apache.tomcat.util.IntrospectionUtils$PropertySource[]);
    Code:
       0: getstatic     #1                  // Field propertySourcesSet:Z
       3: ifne          14
       6: aload_0
       7: putstatic     #3                  // Field propertySources:[Lorg/apache/tomcat/util/IntrospectionUtils$PropertySource;
      10: iconst_1
      11: putstatic     #1                  // Field propertySourcesSet:Z
      14: return

  public static void addGeneratedClass(java.lang.String);
    Code:
       0: getstatic     #4                  // Field generatedClasses:Ljava/util/HashSet;
       3: aload_0
       4: invokevirtual #5                  // Method java/util/HashSet.add:(Ljava/lang/Object;)Z
       7: pop
       8: return

  public static java.lang.String[] getGeneratedClasses();
    Code:
       0: getstatic     #4                  // Field generatedClasses:Ljava/util/HashSet;
       3: iconst_0
       4: anewarray     #6                  // class java/lang/String
       7: invokevirtual #7                  // Method java/util/HashSet.toArray:([Ljava/lang/Object;)[Ljava/lang/Object;
      10: checkcast     #8                  // class "[Ljava/lang/String;"
      13: areturn

  public static boolean isGeneratedCodeLoaderSet();
    Code:
       0: getstatic     #9                  // Field generatedCodeLoader:Lorg/apache/tomcat/util/digester/Digester$GeneratedCodeLoader;
       3: ifnull        10
       6: iconst_1
       7: goto          11
      10: iconst_0
      11: ireturn

  public static void setGeneratedCodeLoader(org.apache.tomcat.util.digester.Digester$GeneratedCodeLoader);
    Code:
       0: getstatic     #9                  // Field generatedCodeLoader:Lorg/apache/tomcat/util/digester/Digester$GeneratedCodeLoader;
       3: ifnonnull     10
       6: aload_0
       7: putstatic     #9                  // Field generatedCodeLoader:Lorg/apache/tomcat/util/digester/Digester$GeneratedCodeLoader;
      10: return

  public static java.lang.Object loadGeneratedClass(java.lang.String);
    Code:
       0: getstatic     #9                  // Field generatedCodeLoader:Lorg/apache/tomcat/util/digester/Digester$GeneratedCodeLoader;
       3: ifnull        16
       6: getstatic     #9                  // Field generatedCodeLoader:Lorg/apache/tomcat/util/digester/Digester$GeneratedCodeLoader;
       9: aload_0
      10: invokeinterface #10,  2           // InterfaceMethod org/apache/tomcat/util/digester/Digester$GeneratedCodeLoader.loadGeneratedCode:(Ljava/lang/String;)Ljava/lang/Object;
      15: areturn
      16: aconst_null
      17: areturn

  public org.apache.tomcat.util.digester.Digester();
    Code:
       0: aload_0
       1: invokespecial #11                 // Method org/xml/sax/ext/DefaultHandler2."<init>":()V
       4: aload_0
       5: iconst_1
       6: anewarray     #2                  // class org/apache/tomcat/util/IntrospectionUtils$PropertySource
       9: dup
      10: iconst_0
      11: new           #12                 // class org/apache/tomcat/util/digester/Digester$SystemPropertySource
      14: dup
      15: aconst_null
      16: invokespecial #13                 // Method org/apache/tomcat/util/digester/Digester$SystemPropertySource."<init>":(Lorg/apache/tomcat/util/digester/Digester$1;)V
      19: aastore
      20: putfield      #14                 // Field source:[Lorg/apache/tomcat/util/IntrospectionUtils$PropertySource;
      23: aload_0
      24: new           #15                 // class java/lang/StringBuilder
      27: dup
      28: invokespecial #16                 // Method java/lang/StringBuilder."<init>":()V
      31: putfield      #17                 // Field bodyText:Ljava/lang/StringBuilder;
      34: aload_0
      35: new           #18                 // class org/apache/tomcat/util/digester/ArrayStack
      38: dup
      39: invokespecial #19                 // Method org/apache/tomcat/util/digester/ArrayStack."<init>":()V
      42: putfield      #20                 // Field bodyTexts:Lorg/apache/tomcat/util/digester/ArrayStack;
      45: aload_0
      46: new           #18                 // class org/apache/tomcat/util/digester/ArrayStack
      49: dup
      50: bipush        10
      52: invokespecial #21                 // Method org/apache/tomcat/util/digester/ArrayStack."<init>":(I)V
      55: putfield      #22                 // Field matches:Lorg/apache/tomcat/util/digester/ArrayStack;
      58: aload_0
      59: aconst_null
      60: putfield      #23                 // Field classLoader:Ljava/lang/ClassLoader;
      63: aload_0
      64: iconst_0
      65: putfield      #24                 // Field configured:Z
      68: aload_0
      69: new           #25                 // class java/util/HashMap
      72: dup
      73: invokespecial #26                 // Method java/util/HashMap."<init>":()V
      76: putfield      #27                 // Field entityValidator:Ljava/util/HashMap;
      79: aload_0
      80: aconst_null
      81: putfield      #28                 // Field errorHandler:Lorg/xml/sax/ErrorHandler;
      84: aload_0
      85: aconst_null
      86: putfield      #29                 // Field factory:Ljavax/xml/parsers/SAXParserFactory;
      89: aload_0
      90: aconst_null
      91: putfield      #30                 // Field locator:Lorg/xml/sax/Locator;
      94: aload_0
      95: ldc           #31                 // String
      97: putfield      #32                 // Field match:Ljava/lang/String;
     100: aload_0
     101: iconst_0
     102: putfield      #33                 // Field namespaceAware:Z
     105: aload_0
     106: new           #25                 // class java/util/HashMap
     109: dup
     110: invokespecial #26                 // Method java/util/HashMap."<init>":()V
     113: putfield      #34                 // Field namespaces:Ljava/util/HashMap;
     116: aload_0
     117: new           #18                 // class org/apache/tomcat/util/digester/ArrayStack
     120: dup
     121: invokespecial #19                 // Method org/apache/tomcat/util/digester/ArrayStack."<init>":()V
     124: putfield      #35                 // Field params:Lorg/apache/tomcat/util/digester/ArrayStack;
     127: aload_0
     128: aconst_null
     129: putfield      #36                 // Field parser:Ljavax/xml/parsers/SAXParser;
     132: aload_0
     133: aconst_null
     134: putfield      #37                 // Field publicId:Ljava/lang/String;
     137: aload_0
     138: aconst_null
     139: putfield      #38                 // Field reader:Lorg/xml/sax/XMLReader;
     142: aload_0
     143: aconst_null
     144: putfield      #39                 // Field root:Ljava/lang/Object;
     147: aload_0
     148: aconst_null
     149: putfield      #40                 // Field rules:Lorg/apache/tomcat/util/digester/Rules;
     152: aload_0
     153: new           #18                 // class org/apache/tomcat/util/digester/ArrayStack
     156: dup
     157: invokespecial #19                 // Method org/apache/tomcat/util/digester/ArrayStack."<init>":()V
     160: putfield      #41                 // Field stack:Lorg/apache/tomcat/util/digester/ArrayStack;
     163: aload_0
     164: iconst_0
     165: putfield      #42                 // Field useContextClassLoader:Z
     168: aload_0
     169: iconst_0
     170: putfield      #43                 // Field validating:Z
     173: aload_0
     174: iconst_0
     175: putfield      #44                 // Field rulesValidation:Z
     178: aload_0
     179: aconst_null
     180: putfield      #45                 // Field fakeAttributes:Ljava/util/Map;
     183: aload_0
     184: ldc           #46                 // class org/apache/tomcat/util/digester/Digester
     186: invokestatic  #47                 // Method org/apache/juli/logging/LogFactory.getLog:(Ljava/lang/Class;)Lorg/apache/juli/logging/Log;
     189: putfield      #48                 // Field log:Lorg/apache/juli/logging/Log;
     192: aload_0
     193: ldc           #49                 // String org.apache.tomcat.util.digester.Digester.sax
     195: invokestatic  #50                 // Method org/apache/juli/logging/LogFactory.getLog:(Ljava/lang/String;)Lorg/apache/juli/logging/Log;
     198: putfield      #51                 // Field saxLog:Lorg/apache/juli/logging/Log;
     201: aload_0
     202: aconst_null
     203: putfield      #52                 // Field code:Ljava/lang/StringBuilder;
     206: aload_0
     207: new           #53                 // class java/util/ArrayList
     210: dup
     211: invokespecial #54                 // Method java/util/ArrayList."<init>":()V
     214: putfield      #55                 // Field known:Ljava/util/ArrayList;
     217: iconst_1
     218: putstatic     #1                  // Field propertySourcesSet:Z
     221: getstatic     #3                  // Field propertySources:[Lorg/apache/tomcat/util/IntrospectionUtils$PropertySource;
     224: ifnull        272
     227: new           #53                 // class java/util/ArrayList
     230: dup
     231: invokespecial #54                 // Method java/util/ArrayList."<init>":()V
     234: astore_1
     235: aload_1
     236: getstatic     #3                  // Field propertySources:[Lorg/apache/tomcat/util/IntrospectionUtils$PropertySource;
     239: invokestatic  #56                 // Method java/util/Arrays.asList:([Ljava/lang/Object;)Ljava/util/List;
     242: invokevirtual #57                 // Method java/util/ArrayList.addAll:(Ljava/util/Collection;)Z
     245: pop
     246: aload_1
     247: aload_0
     248: getfield      #14                 // Field source:[Lorg/apache/tomcat/util/IntrospectionUtils$PropertySource;
     251: iconst_0
     252: aaload
     253: invokevirtual #58                 // Method java/util/ArrayList.add:(Ljava/lang/Object;)Z
     256: pop
     257: aload_0
     258: aload_1
     259: iconst_0
     260: anewarray     #2                  // class org/apache/tomcat/util/IntrospectionUtils$PropertySource
     263: invokevirtual #59                 // Method java/util/ArrayList.toArray:([Ljava/lang/Object;)[Ljava/lang/Object;
     266: checkcast     #60                 // class "[Lorg/apache/tomcat/util/IntrospectionUtils$PropertySource;"
     269: putfield      #14                 // Field source:[Lorg/apache/tomcat/util/IntrospectionUtils$PropertySource;
     272: return

  public static void replaceSystemProperties();
    Code:
       0: ldc           #46                 // class org/apache/tomcat/util/digester/Digester
       2: invokestatic  #47                 // Method org/apache/juli/logging/LogFactory.getLog:(Ljava/lang/Class;)Lorg/apache/juli/logging/Log;
       5: astore_0
       6: getstatic     #3                  // Field propertySources:[Lorg/apache/tomcat/util/IntrospectionUtils$PropertySource;
       9: ifnull        128
      12: invokestatic  #61                 // Method java/lang/System.getProperties:()Ljava/util/Properties;
      15: astore_1
      16: aload_1
      17: invokevirtual #62                 // Method java/util/Properties.stringPropertyNames:()Ljava/util/Set;
      20: astore_2
      21: aload_2
      22: invokeinterface #63,  1           // InterfaceMethod java/util/Set.iterator:()Ljava/util/Iterator;
      27: astore_3
      28: aload_3
      29: invokeinterface #64,  1           // InterfaceMethod java/util/Iterator.hasNext:()Z
      34: ifeq          128
      37: aload_3
      38: invokeinterface #65,  1           // InterfaceMethod java/util/Iterator.next:()Ljava/lang/Object;
      43: checkcast     #6                  // class java/lang/String
      46: astore        4
      48: aload         4
      50: invokestatic  #66                 // Method java/lang/System.getProperty:(Ljava/lang/String;)Ljava/lang/String;
      53: astore        5
      55: aload         5
      57: ifnull        125
      60: aload         5
      62: aconst_null
      63: getstatic     #3                  // Field propertySources:[Lorg/apache/tomcat/util/IntrospectionUtils$PropertySource;
      66: aconst_null
      67: invokestatic  #67                 // Method org/apache/tomcat/util/IntrospectionUtils.replaceProperties:(Ljava/lang/String;Ljava/util/Hashtable;[Lorg/apache/tomcat/util/IntrospectionUtils$PropertySource;Ljava/lang/ClassLoader;)Ljava/lang/String;
      70: astore        6
      72: aload         5
      74: aload         6
      76: invokevirtual #68                 // Method java/lang/String.equals:(Ljava/lang/Object;)Z
      79: ifne          90
      82: aload         4
      84: aload         6
      86: invokestatic  #69                 // Method java/lang/System.setProperty:(Ljava/lang/String;Ljava/lang/String;)Ljava/lang/String;
      89: pop
      90: goto          125
      93: astore        6
      95: aload_0
      96: getstatic     #71                 // Field sm:Lorg/apache/tomcat/util/res/StringManager;
      99: ldc           #72                 // String digester.failedToUpdateSystemProperty
     101: iconst_2
     102: anewarray     #73                 // class java/lang/Object
     105: dup
     106: iconst_0
     107: aload         4
     109: aastore
     110: dup
     111: iconst_1
     112: aload         5
     114: aastore
     115: invokevirtual #74                 // Method org/apache/tomcat/util/res/StringManager.getString:(Ljava/lang/String;[Ljava/lang/Object;)Ljava/lang/String;
     118: aload         6
     120: invokeinterface #75,  3           // InterfaceMethod org/apache/juli/logging/Log.warn:(Ljava/lang/Object;Ljava/lang/Throwable;)V
     125: goto          28
     128: return
    Exception table:
       from    to  target type
          60    90    93   Class java/lang/Exception

  public void startGeneratingCode();
    Code:
       0: aload_0
       1: new           #15                 // class java/lang/StringBuilder
       4: dup
       5: invokespecial #16                 // Method java/lang/StringBuilder."<init>":()V
       8: putfield      #52                 // Field code:Ljava/lang/StringBuilder;
      11: return

  public void endGeneratingCode();
    Code:
       0: aload_0
       1: aconst_null
       2: putfield      #52                 // Field code:Ljava/lang/StringBuilder;
       5: aload_0
       6: getfield      #55                 // Field known:Ljava/util/ArrayList;
       9: invokevirtual #76                 // Method java/util/ArrayList.clear:()V
      12: return

  public java.lang.StringBuilder getGeneratedCode();
    Code:
       0: aload_0
       1: getfield      #52                 // Field code:Ljava/lang/StringBuilder;
       4: areturn

  public void setKnown(java.lang.Object);
    Code:
       0: aload_0
       1: getfield      #55                 // Field known:Ljava/util/ArrayList;
       4: aload_1
       5: invokevirtual #58                 // Method java/util/ArrayList.add:(Ljava/lang/Object;)Z
       8: pop
       9: return

  public java.lang.String toVariableName(java.lang.Object);
    Code:
       0: iconst_0
       1: istore_2
       2: iconst_0
       3: istore_3
       4: aload_0
       5: getfield      #55                 // Field known:Ljava/util/ArrayList;
       8: invokevirtual #77                 // Method java/util/ArrayList.size:()I
      11: ifle          57
      14: aload_0
      15: getfield      #55                 // Field known:Ljava/util/ArrayList;
      18: invokevirtual #77                 // Method java/util/ArrayList.size:()I
      21: iconst_1
      22: isub
      23: istore        4
      25: iload         4
      27: iflt          57
      30: aload_0
      31: getfield      #55                 // Field known:Ljava/util/ArrayList;
      34: iload         4
      36: invokevirtual #78                 // Method java/util/ArrayList.get:(I)Ljava/lang/Object;
      39: aload_1
      40: if_acmpne     51
      43: iload         4
      45: istore_3
      46: iconst_1
      47: istore_2
      48: goto          57
      51: iinc          4, -1
      54: goto          25
      57: iload_2
      58: ifne          78
      61: aload_0
      62: getfield      #55                 // Field known:Ljava/util/ArrayList;
      65: invokevirtual #77                 // Method java/util/ArrayList.size:()I
      68: istore_3
      69: aload_0
      70: getfield      #55                 // Field known:Ljava/util/ArrayList;
      73: aload_1
      74: invokevirtual #58                 // Method java/util/ArrayList.add:(Ljava/lang/Object;)Z
      77: pop
      78: new           #15                 // class java/lang/StringBuilder
      81: dup
      82: invokespecial #16                 // Method java/lang/StringBuilder."<init>":()V
      85: ldc           #79                 // String tc_
      87: invokevirtual #80                 // Method java/lang/StringBuilder.append:(Ljava/lang/String;)Ljava/lang/StringBuilder;
      90: aload_1
      91: invokevirtual #81                 // Method java/lang/Object.getClass:()Ljava/lang/Class;
      94: invokevirtual #82                 // Method java/lang/Class.getSimpleName:()Ljava/lang/String;
      97: invokevirtual #80                 // Method java/lang/StringBuilder.append:(Ljava/lang/String;)Ljava/lang/StringBuilder;
     100: ldc           #83                 // String _
     102: invokevirtual #80                 // Method java/lang/StringBuilder.append:(Ljava/lang/String;)Ljava/lang/StringBuilder;
     105: iload_3
     106: invokestatic  #84                 // Method java/lang/String.valueOf:(I)Ljava/lang/String;
     109: invokevirtual #80                 // Method java/lang/StringBuilder.append:(Ljava/lang/String;)Ljava/lang/StringBuilder;
     112: invokevirtual #85                 // Method java/lang/StringBuilder.toString:()Ljava/lang/String;
     115: areturn

  public java.lang.String findNamespaceURI(java.lang.String);
    Code:
       0: aload_0
       1: getfield      #34                 // Field namespaces:Ljava/util/HashMap;
       4: aload_1
       5: invokevirtual #86                 // Method java/util/HashMap.get:(Ljava/lang/Object;)Ljava/lang/Object;
       8: checkcast     #18                 // class org/apache/tomcat/util/digester/ArrayStack
      11: astore_2
      12: aload_2
      13: ifnonnull     18
      16: aconst_null
      17: areturn
      18: aload_2
      19: invokevirtual #87                 // Method org/apache/tomcat/util/digester/ArrayStack.peek:()Ljava/lang/Object;
      22: checkcast     #6                  // class java/lang/String
      25: areturn
      26: astore_3
      27: aconst_null
      28: areturn
    Exception table:
       from    to  target type
          18    25    26   Class java/util/EmptyStackException

  public java.lang.ClassLoader getClassLoader();
    Code:
       0: aload_0
       1: getfield      #23                 // Field classLoader:Ljava/lang/ClassLoader;
       4: ifnull        12
       7: aload_0
       8: getfield      #23                 // Field classLoader:Ljava/lang/ClassLoader;
      11: areturn
      12: aload_0
      13: getfield      #42                 // Field useContextClassLoader:Z
      16: ifeq          32
      19: invokestatic  #89                 // Method java/lang/Thread.currentThread:()Ljava/lang/Thread;
      22: invokevirtual #90                 // Method java/lang/Thread.getContextClassLoader:()Ljava/lang/ClassLoader;
      25: astore_1
      26: aload_1
      27: ifnull        32
      30: aload_1
      31: areturn
      32: aload_0
      33: invokevirtual #81                 // Method java/lang/Object.getClass:()Ljava/lang/Class;
      36: invokevirtual #91                 // Method java/lang/Class.getClassLoader:()Ljava/lang/ClassLoader;
      39: areturn

  public void setClassLoader(java.lang.ClassLoader);
    Code:
       0: aload_0
       1: aload_1
       2: putfield      #23                 // Field classLoader:Ljava/lang/ClassLoader;
       5: return

  public int getCount();
    Code:
       0: aload_0
       1: getfield      #41                 // Field stack:Lorg/apache/tomcat/util/digester/ArrayStack;
       4: invokevirtual #92                 // Method org/apache/tomcat/util/digester/ArrayStack.size:()I
       7: ireturn

  public java.lang.String getCurrentElementName();
    Code:
       0: aload_0
       1: getfield      #32                 // Field match:Ljava/lang/String;
       4: astore_1
       5: aload_1
       6: bipush        47
       8: invokevirtual #93                 // Method java/lang/String.lastIndexOf:(I)I
      11: istore_2
      12: iload_2
      13: iflt          24
      16: aload_1
      17: iload_2
      18: iconst_1
      19: iadd
      20: invokevirtual #94                 // Method java/lang/String.substring:(I)Ljava/lang/String;
      23: astore_1
      24: aload_1
      25: areturn

  public org.xml.sax.ErrorHandler getErrorHandler();
    Code:
       0: aload_0
       1: getfield      #28                 // Field errorHandler:Lorg/xml/sax/ErrorHandler;
       4: areturn

  public void setErrorHandler(org.xml.sax.ErrorHandler);
    Code:
       0: aload_0
       1: aload_1
       2: putfield      #28                 // Field errorHandler:Lorg/xml/sax/ErrorHandler;
       5: return

  public javax.xml.parsers.SAXParserFactory getFactory() throws org.xml.sax.SAXNotRecognizedException, org.xml.sax.SAXNotSupportedException, javax.xml.parsers.ParserConfigurationException;
    Code:
       0: aload_0
       1: getfield      #29                 // Field factory:Ljavax/xml/parsers/SAXParserFactory;
       4: ifnonnull     80
       7: aload_0
       8: invokestatic  #95                 // Method javax/xml/parsers/SAXParserFactory.newInstance:()Ljavax/xml/parsers/SAXParserFactory;
      11: putfield      #29                 // Field factory:Ljavax/xml/parsers/SAXParserFactory;
      14: aload_0
      15: getfield      #29                 // Field factory:Ljavax/xml/parsers/SAXParserFactory;
      18: aload_0
      19: getfield      #33                 // Field namespaceAware:Z
      22: invokevirtual #96                 // Method javax/xml/parsers/SAXParserFactory.setNamespaceAware:(Z)V
      25: aload_0
      26: getfield      #33                 // Field namespaceAware:Z
      29: ifeq          42
      32: aload_0
      33: getfield      #29                 // Field factory:Ljavax/xml/parsers/SAXParserFactory;
      36: ldc           #97                 // String http://xml.org/sax/features/namespace-prefixes
      38: iconst_1
      39: invokevirtual #98                 // Method javax/xml/parsers/SAXParserFactory.setFeature:(Ljava/lang/String;Z)V
      42: aload_0
      43: getfield      #29                 // Field factory:Ljavax/xml/parsers/SAXParserFactory;
      46: aload_0
      47: getfield      #43                 // Field validating:Z
      50: invokevirtual #99                 // Method javax/xml/parsers/SAXParserFactory.setValidating:(Z)V
      53: aload_0
      54: getfield      #43                 // Field validating:Z
      57: ifeq          80
      60: aload_0
      61: getfield      #29                 // Field factory:Ljavax/xml/parsers/SAXParserFactory;
      64: ldc           #100                // String http://xml.org/sax/features/validation
      66: iconst_1
      67: invokevirtual #98                 // Method javax/xml/parsers/SAXParserFactory.setFeature:(Ljava/lang/String;Z)V
      70: aload_0
      71: getfield      #29                 // Field factory:Ljavax/xml/parsers/SAXParserFactory;
      74: ldc           #101                // String http://apache.org/xml/features/validation/schema
      76: iconst_1
      77: invokevirtual #98                 // Method javax/xml/parsers/SAXParserFactory.setFeature:(Ljava/lang/String;Z)V
      80: aload_0
      81: getfield      #29                 // Field factory:Ljavax/xml/parsers/SAXParserFactory;
      84: areturn

  public void setFeature(java.lang.String, boolean) throws javax.xml.parsers.ParserConfigurationException, org.xml.sax.SAXNotRecognizedException, org.xml.sax.SAXNotSupportedException;
    Code:
       0: aload_0
       1: invokevirtual #102                // Method getFactory:()Ljavax/xml/parsers/SAXParserFactory;
       4: aload_1
       5: iload_2
       6: invokevirtual #98                 // Method javax/xml/parsers/SAXParserFactory.setFeature:(Ljava/lang/String;Z)V
       9: return

  public org.apache.juli.logging.Log getLogger();
    Code:
       0: aload_0
       1: getfield      #48                 // Field log:Lorg/apache/juli/logging/Log;
       4: areturn

  public void setLogger(org.apache.juli.logging.Log);
    Code:
       0: aload_0
       1: aload_1
       2: putfield      #48                 // Field log:Lorg/apache/juli/logging/Log;
       5: return

  public org.apache.juli.logging.Log getSAXLogger();
    Code:
       0: aload_0
       1: getfield      #51                 // Field saxLog:Lorg/apache/juli/logging/Log;
       4: areturn

  public void setSAXLogger(org.apache.juli.logging.Log);
    Code:
       0: aload_0
       1: aload_1
       2: putfield      #51                 // Field saxLog:Lorg/apache/juli/logging/Log;
       5: return

  public java.lang.String getMatch();
    Code:
       0: aload_0
       1: getfield      #32                 // Field match:Ljava/lang/String;
       4: areturn

  public boolean getNamespaceAware();
    Code:
       0: aload_0
       1: getfield      #33                 // Field namespaceAware:Z
       4: ireturn

  public void setNamespaceAware(boolean);
    Code:
       0: aload_0
       1: iload_1
       2: putfield      #33                 // Field namespaceAware:Z
       5: return

  public void setPublicId(java.lang.String);
    Code:
       0: aload_0
       1: aload_1
       2: putfield      #37                 // Field publicId:Ljava/lang/String;
       5: return

  public java.lang.String getPublicId();
    Code:
       0: aload_0
       1: getfield      #37                 // Field publicId:Ljava/lang/String;
       4: areturn

  public javax.xml.parsers.SAXParser getParser();
    Code:
       0: aload_0
       1: getfield      #36                 // Field parser:Ljavax/xml/parsers/SAXParser;
       4: ifnull        12
       7: aload_0
       8: getfield      #36                 // Field parser:Ljavax/xml/parsers/SAXParser;
      11: areturn
      12: aload_0
      13: aload_0
      14: invokevirtual #102                // Method getFactory:()Ljavax/xml/parsers/SAXParserFactory;
      17: invokevirtual #103                // Method javax/xml/parsers/SAXParserFactory.newSAXParser:()Ljavax/xml/parsers/SAXParser;
      20: putfield      #36                 // Field parser:Ljavax/xml/parsers/SAXParser;
      23: goto          47
      26: astore_1
      27: aload_0
      28: getfield      #48                 // Field log:Lorg/apache/juli/logging/Log;
      31: getstatic     #71                 // Field sm:Lorg/apache/tomcat/util/res/StringManager;
      34: ldc           #104                // String digester.createParserError
      36: invokevirtual #105                // Method org/apache/tomcat/util/res/StringManager.getString:(Ljava/lang/String;)Ljava/lang/String;
      39: aload_1
      40: invokeinterface #106,  3          // InterfaceMethod org/apache/juli/logging/Log.error:(Ljava/lang/Object;Ljava/lang/Throwable;)V
      45: aconst_null
      46: areturn
      47: aload_0
      48: getfield      #36                 // Field parser:Ljavax/xml/parsers/SAXParser;
      51: areturn
    Exception table:
       from    to  target type
          12    23    26   Class java/lang/Exception

  public java.lang.Object getProperty(java.lang.String) throws org.xml.sax.SAXNotRecognizedException, org.xml.sax.SAXNotSupportedException;
    Code:
       0: aload_0
       1: invokevirtual #107                // Method getParser:()Ljavax/xml/parsers/SAXParser;
       4: aload_1
       5: invokevirtual #108                // Method javax/xml/parsers/SAXParser.getProperty:(Ljava/lang/String;)Ljava/lang/Object;
       8: areturn

  public org.apache.tomcat.util.digester.Rules getRules();
    Code:
       0: aload_0
       1: getfield      #40                 // Field rules:Lorg/apache/tomcat/util/digester/Rules;
       4: ifnonnull     28
       7: aload_0
       8: new           #109                // class org/apache/tomcat/util/digester/RulesBase
      11: dup
      12: invokespecial #110                // Method org/apache/tomcat/util/digester/RulesBase."<init>":()V
      15: putfield      #40                 // Field rules:Lorg/apache/tomcat/util/digester/Rules;
      18: aload_0
      19: getfield      #40                 // Field rules:Lorg/apache/tomcat/util/digester/Rules;
      22: aload_0
      23: invokeinterface #111,  2          // InterfaceMethod org/apache/tomcat/util/digester/Rules.setDigester:(Lorg/apache/tomcat/util/digester/Digester;)V
      28: aload_0
      29: getfield      #40                 // Field rules:Lorg/apache/tomcat/util/digester/Rules;
      32: areturn

  public void setRules(org.apache.tomcat.util.digester.Rules);
    Code:
       0: aload_0
       1: aload_1
       2: putfield      #40                 // Field rules:Lorg/apache/tomcat/util/digester/Rules;
       5: aload_0
       6: getfield      #40                 // Field rules:Lorg/apache/tomcat/util/digester/Rules;
       9: aload_0
      10: invokeinterface #111,  2          // InterfaceMethod org/apache/tomcat/util/digester/Rules.setDigester:(Lorg/apache/tomcat/util/digester/Digester;)V
      15: return

  public boolean getUseContextClassLoader();
    Code:
       0: aload_0
       1: getfield      #42                 // Field useContextClassLoader:Z
       4: ireturn

  public void setUseContextClassLoader(boolean);
    Code:
       0: aload_0
       1: iload_1
       2: putfield      #42                 // Field useContextClassLoader:Z
       5: return

  public boolean getValidating();
    Code:
       0: aload_0
       1: getfield      #43                 // Field validating:Z
       4: ireturn

  public void setValidating(boolean);
    Code:
       0: aload_0
       1: iload_1
       2: putfield      #43                 // Field validating:Z
       5: return

  public boolean getRulesValidation();
    Code:
       0: aload_0
       1: getfield      #44                 // Field rulesValidation:Z
       4: ireturn

  public void setRulesValidation(boolean);
    Code:
       0: aload_0
       1: iload_1
       2: putfield      #44                 // Field rulesValidation:Z
       5: return

  public java.util.Map<java.lang.Class<?>, java.util.List<java.lang.String>> getFakeAttributes();
    Code:
       0: aload_0
       1: getfield      #45                 // Field fakeAttributes:Ljava/util/Map;
       4: areturn

  public boolean isFakeAttribute(java.lang.Object, java.lang.String);
    Code:
       0: aload_0
       1: getfield      #45                 // Field fakeAttributes:Ljava/util/Map;
       4: ifnonnull     9
       7: iconst_0
       8: ireturn
       9: aload_0
      10: getfield      #45                 // Field fakeAttributes:Ljava/util/Map;
      13: aload_1
      14: invokevirtual #81                 // Method java/lang/Object.getClass:()Ljava/lang/Class;
      17: invokeinterface #112,  2          // InterfaceMethod java/util/Map.get:(Ljava/lang/Object;)Ljava/lang/Object;
      22: checkcast     #113                // class java/util/List
      25: astore_3
      26: aload_3
      27: ifnonnull     45
      30: aload_0
      31: getfield      #45                 // Field fakeAttributes:Ljava/util/Map;
      34: ldc           #73                 // class java/lang/Object
      36: invokeinterface #112,  2          // InterfaceMethod java/util/Map.get:(Ljava/lang/Object;)Ljava/lang/Object;
      41: checkcast     #113                // class java/util/List
      44: astore_3
      45: aload_3
      46: ifnonnull     51
      49: iconst_0
      50: ireturn
      51: aload_3
      52: aload_2
      53: invokeinterface #114,  2          // InterfaceMethod java/util/List.contains:(Ljava/lang/Object;)Z
      58: ireturn

  public void setFakeAttributes(java.util.Map<java.lang.Class<?>, java.util.List<java.lang.String>>);
    Code:
       0: aload_0
       1: aload_1
       2: putfield      #45                 // Field fakeAttributes:Ljava/util/Map;
       5: return

  public org.xml.sax.XMLReader getXMLReader() throws org.xml.sax.SAXException;
    Code:
       0: aload_0
       1: getfield      #38                 // Field reader:Lorg/xml/sax/XMLReader;
       4: ifnonnull     18
       7: aload_0
       8: aload_0
       9: invokevirtual #107                // Method getParser:()Ljavax/xml/parsers/SAXParser;
      12: invokevirtual #115                // Method javax/xml/parsers/SAXParser.getXMLReader:()Lorg/xml/sax/XMLReader;
      15: putfield      #38                 // Field reader:Lorg/xml/sax/XMLReader;
      18: aload_0
      19: getfield      #38                 // Field reader:Lorg/xml/sax/XMLReader;
      22: aload_0
      23: invokeinterface #116,  2          // InterfaceMethod org/xml/sax/XMLReader.setDTDHandler:(Lorg/xml/sax/DTDHandler;)V
      28: aload_0
      29: getfield      #38                 // Field reader:Lorg/xml/sax/XMLReader;
      32: aload_0
      33: invokeinterface #117,  2          // InterfaceMethod org/xml/sax/XMLReader.setContentHandler:(Lorg/xml/sax/ContentHandler;)V
      38: aload_0
      39: invokevirtual #118                // Method getEntityResolver:()Lorg/xml/sax/EntityResolver;
      42: astore_1
      43: aload_1
      44: ifnonnull     49
      47: aload_0
      48: astore_1
      49: aload_1
      50: instanceof    #119                // class org/xml/sax/ext/EntityResolver2
      53: ifeq          79
      56: new           #120                // class org/apache/tomcat/util/digester/Digester$EntityResolver2Wrapper
      59: dup
      60: aload_1
      61: checkcast     #119                // class org/xml/sax/ext/EntityResolver2
      64: aload_0
      65: getfield      #14                 // Field source:[Lorg/apache/tomcat/util/IntrospectionUtils$PropertySource;
      68: aload_0
      69: getfield      #23                 // Field classLoader:Ljava/lang/ClassLoader;
      72: invokespecial #121                // Method org/apache/tomcat/util/digester/Digester$EntityResolver2Wrapper."<init>":(Lorg/xml/sax/ext/EntityResolver2;[Lorg/apache/tomcat/util/IntrospectionUtils$PropertySource;Ljava/lang/ClassLoader;)V
      75: astore_1
      76: goto          96
      79: new           #122                // class org/apache/tomcat/util/digester/Digester$EntityResolverWrapper
      82: dup
      83: aload_1
      84: aload_0
      85: getfield      #14                 // Field source:[Lorg/apache/tomcat/util/IntrospectionUtils$PropertySource;
      88: aload_0
      89: getfield      #23                 // Field classLoader:Ljava/lang/ClassLoader;
      92: invokespecial #123                // Method org/apache/tomcat/util/digester/Digester$EntityResolverWrapper."<init>":(Lorg/xml/sax/EntityResolver;[Lorg/apache/tomcat/util/IntrospectionUtils$PropertySource;Ljava/lang/ClassLoader;)V
      95: astore_1
      96: aload_0
      97: getfield      #38                 // Field reader:Lorg/xml/sax/XMLReader;
     100: aload_1
     101: invokeinterface #124,  2          // InterfaceMethod org/xml/sax/XMLReader.setEntityResolver:(Lorg/xml/sax/EntityResolver;)V
     106: aload_0
     107: getfield      #38                 // Field reader:Lorg/xml/sax/XMLReader;
     110: ldc           #125                // String http://xml.org/sax/properties/lexical-handler
     112: aload_0
     113: invokeinterface #126,  3          // InterfaceMethod org/xml/sax/XMLReader.setProperty:(Ljava/lang/String;Ljava/lang/Object;)V
     118: aload_0
     119: getfield      #38                 // Field reader:Lorg/xml/sax/XMLReader;
     122: aload_0
     123: invokeinterface #127,  2          // InterfaceMethod org/xml/sax/XMLReader.setErrorHandler:(Lorg/xml/sax/ErrorHandler;)V
     128: aload_0
     129: getfield      #38                 // Field reader:Lorg/xml/sax/XMLReader;
     132: areturn

  public void characters(char[], int, int) throws org.xml.sax.SAXException;
    Code:
       0: aload_0
       1: getfield      #51                 // Field saxLog:Lorg/apache/juli/logging/Log;
       4: invokeinterface #128,  1          // InterfaceMethod org/apache/juli/logging/Log.isDebugEnabled:()Z
       9: ifeq          54
      12: aload_0
      13: getfield      #51                 // Field saxLog:Lorg/apache/juli/logging/Log;
      16: new           #15                 // class java/lang/StringBuilder
      19: dup
      20: invokespecial #16                 // Method java/lang/StringBuilder."<init>":()V
      23: ldc           #129                // String characters(
      25: invokevirtual #80                 // Method java/lang/StringBuilder.append:(Ljava/lang/String;)Ljava/lang/StringBuilder;
      28: new           #6                  // class java/lang/String
      31: dup
      32: aload_1
      33: iload_2
      34: iload_3
      35: invokespecial #130                // Method java/lang/String."<init>":([CII)V
      38: invokevirtual #80                 // Method java/lang/StringBuilder.append:(Ljava/lang/String;)Ljava/lang/StringBuilder;
      41: ldc           #131                // String )
      43: invokevirtual #80                 // Method java/lang/StringBuilder.append:(Ljava/lang/String;)Ljava/lang/StringBuilder;
      46: invokevirtual #85                 // Method java/lang/StringBuilder.toString:()Ljava/lang/String;
      49: invokeinterface #132,  2          // InterfaceMethod org/apache/juli/logging/Log.debug:(Ljava/lang/Object;)V
      54: aload_0
      55: getfield      #17                 // Field bodyText:Ljava/lang/StringBuilder;
      58: aload_1
      59: iload_2
      60: iload_3
      61: invokevirtual #133                // Method java/lang/StringBuilder.append:([CII)Ljava/lang/StringBuilder;
      64: pop
      65: return

  public void endDocument() throws org.xml.sax.SAXException;
    Code:
       0: aload_0
       1: getfield      #51                 // Field saxLog:Lorg/apache/juli/logging/Log;
       4: invokeinterface #128,  1          // InterfaceMethod org/apache/juli/logging/Log.isDebugEnabled:()Z
       9: ifeq          70
      12: aload_0
      13: invokevirtual #134                // Method getCount:()I
      16: iconst_1
      17: if_icmple     59
      20: aload_0
      21: getfield      #51                 // Field saxLog:Lorg/apache/juli/logging/Log;
      24: new           #15                 // class java/lang/StringBuilder
      27: dup
      28: invokespecial #16                 // Method java/lang/StringBuilder."<init>":()V
      31: ldc           #135                // String endDocument():
      33: invokevirtual #80                 // Method java/lang/StringBuilder.append:(Ljava/lang/String;)Ljava/lang/StringBuilder;
      36: aload_0
      37: invokevirtual #134                // Method getCount:()I
      40: invokevirtual #136                // Method java/lang/StringBuilder.append:(I)Ljava/lang/StringBuilder;
      43: ldc           #137                // String  elements left
      45: invokevirtual #80                 // Method java/lang/StringBuilder.append:(Ljava/lang/String;)Ljava/lang/StringBuilder;
      48: invokevirtual #85                 // Method java/lang/StringBuilder.toString:()Ljava/lang/String;
      51: invokeinterface #132,  2          // InterfaceMethod org/apache/juli/logging/Log.debug:(Ljava/lang/Object;)V
      56: goto          70
      59: aload_0
      60: getfield      #51                 // Field saxLog:Lorg/apache/juli/logging/Log;
      63: ldc           #138                // String endDocument()
      65: invokeinterface #132,  2          // InterfaceMethod org/apache/juli/logging/Log.debug:(Ljava/lang/Object;)V
      70: aload_0
      71: invokevirtual #134                // Method getCount:()I
      74: iconst_1
      75: if_icmple     86
      78: aload_0
      79: invokevirtual #139                // Method pop:()Ljava/lang/Object;
      82: pop
      83: goto          70
      86: aload_0
      87: invokevirtual #140                // Method getRules:()Lorg/apache/tomcat/util/digester/Rules;
      90: invokeinterface #141,  1          // InterfaceMethod org/apache/tomcat/util/digester/Rules.rules:()Ljava/util/List;
      95: invokeinterface #142,  1          // InterfaceMethod java/util/List.iterator:()Ljava/util/Iterator;
     100: astore_1
     101: aload_1
     102: invokeinterface #64,  1           // InterfaceMethod java/util/Iterator.hasNext:()Z
     107: ifeq          176
     110: aload_1
     111: invokeinterface #65,  1           // InterfaceMethod java/util/Iterator.next:()Ljava/lang/Object;
     116: checkcast     #143                // class org/apache/tomcat/util/digester/Rule
     119: astore_2
     120: aload_2
     121: invokevirtual #144                // Method org/apache/tomcat/util/digester/Rule.finish:()V
     124: goto          173
     127: astore_3
     128: aload_0
     129: getfield      #48                 // Field log:Lorg/apache/juli/logging/Log;
     132: getstatic     #71                 // Field sm:Lorg/apache/tomcat/util/res/StringManager;
     135: ldc           #145                // String digester.error.finish
     137: invokevirtual #105                // Method org/apache/tomcat/util/res/StringManager.getString:(Ljava/lang/String;)Ljava/lang/String;
     140: aload_3
     141: invokeinterface #106,  3          // InterfaceMethod org/apache/juli/logging/Log.error:(Ljava/lang/Object;Ljava/lang/Throwable;)V
     146: aload_0
     147: aload_3
     148: invokevirtual #146                // Method createSAXException:(Ljava/lang/Exception;)Lorg/xml/sax/SAXException;
     151: athrow
     152: astore_3
     153: aload_0
     154: getfield      #48                 // Field log:Lorg/apache/juli/logging/Log;
     157: getstatic     #71                 // Field sm:Lorg/apache/tomcat/util/res/StringManager;
     160: ldc           #145                // String digester.error.finish
     162: invokevirtual #105                // Method org/apache/tomcat/util/res/StringManager.getString:(Ljava/lang/String;)Ljava/lang/String;
     165: aload_3
     166: invokeinterface #106,  3          // InterfaceMethod org/apache/juli/logging/Log.error:(Ljava/lang/Object;Ljava/lang/Throwable;)V
     171: aload_3
     172: athrow
     173: goto          101
     176: aload_0
     177: invokevirtual #148                // Method clear:()V
     180: return
    Exception table:
       from    to  target type
         120   124   127   Class java/lang/Exception
         120   124   152   Class java/lang/Error

  public void endElement(java.lang.String, java.lang.String, java.lang.String) throws org.xml.sax.SAXException;
    Code:
       0: aload_0
       1: getfield      #48                 // Field log:Lorg/apache/juli/logging/Log;
       4: invokeinterface #128,  1          // InterfaceMethod org/apache/juli/logging/Log.isDebugEnabled:()Z
       9: istore        4
      11: iload         4
      13: ifeq          151
      16: aload_0
      17: getfield      #51                 // Field saxLog:Lorg/apache/juli/logging/Log;
      20: invokeinterface #128,  1          // InterfaceMethod org/apache/juli/logging/Log.isDebugEnabled:()Z
      25: ifeq          79
      28: aload_0
      29: getfield      #51                 // Field saxLog:Lorg/apache/juli/logging/Log;
      32: new           #15                 // class java/lang/StringBuilder
      35: dup
      36: invokespecial #16                 // Method java/lang/StringBuilder."<init>":()V
      39: ldc           #149                // String endElement(
      41: invokevirtual #80                 // Method java/lang/StringBuilder.append:(Ljava/lang/String;)Ljava/lang/StringBuilder;
      44: aload_1
      45: invokevirtual #80                 // Method java/lang/StringBuilder.append:(Ljava/lang/String;)Ljava/lang/StringBuilder;
      48: ldc           #150                // String ,
      50: invokevirtual #80                 // Method java/lang/StringBuilder.append:(Ljava/lang/String;)Ljava/lang/StringBuilder;
      53: aload_2
      54: invokevirtual #80                 // Method java/lang/StringBuilder.append:(Ljava/lang/String;)Ljava/lang/StringBuilder;
      57: ldc           #150                // String ,
      59: invokevirtual #80                 // Method java/lang/StringBuilder.append:(Ljava/lang/String;)Ljava/lang/StringBuilder;
      62: aload_3
      63: invokevirtual #80                 // Method java/lang/StringBuilder.append:(Ljava/lang/String;)Ljava/lang/StringBuilder;
      66: ldc           #131                // String )
      68: invokevirtual #80                 // Method java/lang/StringBuilder.append:(Ljava/lang/String;)Ljava/lang/StringBuilder;
      71: invokevirtual #85                 // Method java/lang/StringBuilder.toString:()Ljava/lang/String;
      74: invokeinterface #132,  2          // InterfaceMethod org/apache/juli/logging/Log.debug:(Ljava/lang/Object;)V
      79: aload_0
      80: getfield      #48                 // Field log:Lorg/apache/juli/logging/Log;
      83: new           #15                 // class java/lang/StringBuilder
      86: dup
      87: invokespecial #16                 // Method java/lang/StringBuilder."<init>":()V
      90: ldc           #151                // String   match=\'
      92: invokevirtual #80                 // Method java/lang/StringBuilder.append:(Ljava/lang/String;)Ljava/lang/StringBuilder;
      95: aload_0
      96: getfield      #32                 // Field match:Ljava/lang/String;
      99: invokevirtual #80                 // Method java/lang/StringBuilder.append:(Ljava/lang/String;)Ljava/lang/StringBuilder;
     102: ldc           #152                // String \'
     104: invokevirtual #80                 // Method java/lang/StringBuilder.append:(Ljava/lang/String;)Ljava/lang/StringBuilder;
     107: invokevirtual #85                 // Method java/lang/StringBuilder.toString:()Ljava/lang/String;
     110: invokeinterface #132,  2          // InterfaceMethod org/apache/juli/logging/Log.debug:(Ljava/lang/Object;)V
     115: aload_0
     116: getfield      #48                 // Field log:Lorg/apache/juli/logging/Log;
     119: new           #15                 // class java/lang/StringBuilder
     122: dup
     123: invokespecial #16                 // Method java/lang/StringBuilder."<init>":()V
     126: ldc           #153                // String   bodyText=\'
     128: invokevirtual #80                 // Method java/lang/StringBuilder.append:(Ljava/lang/String;)Ljava/lang/StringBuilder;
     131: aload_0
     132: getfield      #17                 // Field bodyText:Ljava/lang/StringBuilder;
     135: invokevirtual #154                // Method java/lang/StringBuilder.append:(Ljava/lang/Object;)Ljava/lang/StringBuilder;
     138: ldc           #152                // String \'
     140: invokevirtual #80                 // Method java/lang/StringBuilder.append:(Ljava/lang/String;)Ljava/lang/StringBuilder;
     143: invokevirtual #85                 // Method java/lang/StringBuilder.toString:()Ljava/lang/String;
     146: invokeinterface #132,  2          // InterfaceMethod org/apache/juli/logging/Log.debug:(Ljava/lang/Object;)V
     151: aload_0
     152: aload_0
     153: aload_0
     154: getfield      #17                 // Field bodyText:Ljava/lang/StringBuilder;
     157: invokespecial #155                // Method updateBodyText:(Ljava/lang/StringBuilder;)Ljava/lang/StringBuilder;
     160: putfield      #17                 // Field bodyText:Ljava/lang/StringBuilder;
     163: aload_2
     164: astore        5
     166: aload         5
     168: ifnull        180
     171: aload         5
     173: invokevirtual #156                // Method java/lang/String.length:()I
     176: iconst_1
     177: if_icmpge     183
     180: aload_3
     181: astore        5
     183: aload_0
     184: getfield      #22                 // Field matches:Lorg/apache/tomcat/util/digester/ArrayStack;
     187: invokevirtual #157                // Method org/apache/tomcat/util/digester/ArrayStack.pop:()Ljava/lang/Object;
     190: checkcast     #113                // class java/util/List
     193: astore        6
     195: aload         6
     197: ifnull        362
     200: aload         6
     202: invokeinterface #158,  1          // InterfaceMethod java/util/List.size:()I
     207: ifle          362
     210: aload_0
     211: getfield      #17                 // Field bodyText:Ljava/lang/StringBuilder;
     214: invokevirtual #85                 // Method java/lang/StringBuilder.toString:()Ljava/lang/String;
     217: invokevirtual #159                // Method java/lang/String.intern:()Ljava/lang/String;
     220: astore        7
     222: aload         6
     224: invokeinterface #142,  1          // InterfaceMethod java/util/List.iterator:()Ljava/util/Iterator;
     229: astore        8
     231: aload         8
     233: invokeinterface #64,  1           // InterfaceMethod java/util/Iterator.hasNext:()Z
     238: ifeq          359
     241: aload         8
     243: invokeinterface #65,  1           // InterfaceMethod java/util/Iterator.next:()Ljava/lang/Object;
     248: checkcast     #143                // class org/apache/tomcat/util/digester/Rule
     251: astore        9
     253: aload         9
     255: astore        10
     257: iload         4
     259: ifeq          291
     262: aload_0
     263: getfield      #48                 // Field log:Lorg/apache/juli/logging/Log;
     266: new           #15                 // class java/lang/StringBuilder
     269: dup
     270: invokespecial #16                 // Method java/lang/StringBuilder."<init>":()V
     273: ldc           #160                // String   Fire body() for
     275: invokevirtual #80                 // Method java/lang/StringBuilder.append:(Ljava/lang/String;)Ljava/lang/StringBuilder;
     278: aload         10
     280: invokevirtual #154                // Method java/lang/StringBuilder.append:(Ljava/lang/Object;)Ljava/lang/StringBuilder;
     283: invokevirtual #85                 // Method java/lang/StringBuilder.toString:()Ljava/lang/String;
     286: invokeinterface #132,  2          // InterfaceMethod org/apache/juli/logging/Log.debug:(Ljava/lang/Object;)V
     291: aload         10
     293: aload_1
     294: aload         5
     296: aload         7
     298: invokevirtual #161                // Method org/apache/tomcat/util/digester/Rule.body:(Ljava/lang/String;Ljava/lang/String;Ljava/lang/String;)V
     301: goto          356
     304: astore        10
     306: aload_0
     307: getfield      #48                 // Field log:Lorg/apache/juli/logging/Log;
     310: getstatic     #71                 // Field sm:Lorg/apache/tomcat/util/res/StringManager;
     313: ldc           #162                // String digester.error.body
     315: invokevirtual #105                // Method org/apache/tomcat/util/res/StringManager.getString:(Ljava/lang/String;)Ljava/lang/String;
     318: aload         10
     320: invokeinterface #106,  3          // InterfaceMethod org/apache/juli/logging/Log.error:(Ljava/lang/Object;Ljava/lang/Throwable;)V
     325: aload_0
     326: aload         10
     328: invokevirtual #146                // Method createSAXException:(Ljava/lang/Exception;)Lorg/xml/sax/SAXException;
     331: athrow
     332: astore        10
     334: aload_0
     335: getfield      #48                 // Field log:Lorg/apache/juli/logging/Log;
     338: getstatic     #71                 // Field sm:Lorg/apache/tomcat/util/res/StringManager;
     341: ldc           #162                // String digester.error.body
     343: invokevirtual #105                // Method org/apache/tomcat/util/res/StringManager.getString:(Ljava/lang/String;)Ljava/lang/String;
     346: aload         10
     348: invokeinterface #106,  3          // InterfaceMethod org/apache/juli/logging/Log.error:(Ljava/lang/Object;Ljava/lang/Throwable;)V
     353: aload         10
     355: athrow
     356: goto          231
     359: goto          430
     362: iload         4
     364: ifeq          395
     367: aload_0
     368: getfield      #48                 // Field log:Lorg/apache/juli/logging/Log;
     371: getstatic     #71                 // Field sm:Lorg/apache/tomcat/util/res/StringManager;
     374: ldc           #163                // String digester.noRulesFound
     376: iconst_1
     377: anewarray     #73                 // class java/lang/Object
     380: dup
     381: iconst_0
     382: aload_0
     383: getfield      #32                 // Field match:Ljava/lang/String;
     386: aastore
     387: invokevirtual #74                 // Method org/apache/tomcat/util/res/StringManager.getString:(Ljava/lang/String;[Ljava/lang/Object;)Ljava/lang/String;
     390: invokeinterface #132,  2          // InterfaceMethod org/apache/juli/logging/Log.debug:(Ljava/lang/Object;)V
     395: aload_0
     396: getfield      #44                 // Field rulesValidation:Z
     399: ifeq          430
     402: aload_0
     403: getfield      #48                 // Field log:Lorg/apache/juli/logging/Log;
     406: getstatic     #71                 // Field sm:Lorg/apache/tomcat/util/res/StringManager;
     409: ldc           #163                // String digester.noRulesFound
     411: iconst_1
     412: anewarray     #73                 // class java/lang/Object
     415: dup
     416: iconst_0
     417: aload_0
     418: getfield      #32                 // Field match:Ljava/lang/String;
     421: aastore
     422: invokevirtual #74                 // Method org/apache/tomcat/util/res/StringManager.getString:(Ljava/lang/String;[Ljava/lang/Object;)Ljava/lang/String;
     425: invokeinterface #164,  2          // InterfaceMethod org/apache/juli/logging/Log.warn:(Ljava/lang/Object;)V
     430: aload_0
     431: aload_0
     432: getfield      #20                 // Field bodyTexts:Lorg/apache/tomcat/util/digester/ArrayStack;
     435: invokevirtual #157                // Method org/apache/tomcat/util/digester/ArrayStack.pop:()Ljava/lang/Object;
     438: checkcast     #15                 // class java/lang/StringBuilder
     441: putfield      #17                 // Field bodyText:Ljava/lang/StringBuilder;
     444: aload         6
     446: ifnull        595
     449: iconst_0
     450: istore        7
     452: iload         7
     454: aload         6
     456: invokeinterface #158,  1          // InterfaceMethod java/util/List.size:()I
     461: if_icmpge     595
     464: aload         6
     466: invokeinterface #158,  1          // InterfaceMethod java/util/List.size:()I
     471: iload         7
     473: isub
     474: iconst_1
     475: isub
     476: istore        8
     478: aload         6
     480: iload         8
     482: invokeinterface #165,  2          // InterfaceMethod java/util/List.get:(I)Ljava/lang/Object;
     487: checkcast     #143                // class org/apache/tomcat/util/digester/Rule
     490: astore        9
     492: iload         4
     494: ifeq          526
     497: aload_0
     498: getfield      #48                 // Field log:Lorg/apache/juli/logging/Log;
     501: new           #15                 // class java/lang/StringBuilder
     504: dup
     505: invokespecial #16                 // Method java/lang/StringBuilder."<init>":()V
     508: ldc           #166                // String   Fire end() for
     510: invokevirtual #80                 // Method java/lang/StringBuilder.append:(Ljava/lang/String;)Ljava/lang/StringBuilder;
     513: aload         9
     515: invokevirtual #154                // Method java/lang/StringBuilder.append:(Ljava/lang/Object;)Ljava/lang/StringBuilder;
     518: invokevirtual #85                 // Method java/lang/StringBuilder.toString:()Ljava/lang/String;
     521: invokeinterface #132,  2          // InterfaceMethod org/apache/juli/logging/Log.debug:(Ljava/lang/Object;)V
     526: aload         9
     528: aload_1
     529: aload         5
     531: invokevirtual #167                // Method org/apache/tomcat/util/digester/Rule.end:(Ljava/lang/String;Ljava/lang/String;)V
     534: goto          589
     537: astore        9
     539: aload_0
     540: getfield      #48                 // Field log:Lorg/apache/juli/logging/Log;
     543: getstatic     #71                 // Field sm:Lorg/apache/tomcat/util/res/StringManager;
     546: ldc           #168                // String digester.error.end
     548: invokevirtual #105                // Method org/apache/tomcat/util/res/StringManager.getString:(Ljava/lang/String;)Ljava/lang/String;
     551: aload         9
     553: invokeinterface #106,  3          // InterfaceMethod org/apache/juli/logging/Log.error:(Ljava/lang/Object;Ljava/lang/Throwable;)V
     558: aload_0
     559: aload         9
     561: invokevirtual #146                // Method createSAXException:(Ljava/lang/Exception;)Lorg/xml/sax/SAXException;
     564: athrow
     565: astore        9
     567: aload_0
     568: getfield      #48                 // Field log:Lorg/apache/juli/logging/Log;
     571: getstatic     #71                 // Field sm:Lorg/apache/tomcat/util/res/StringManager;
     574: ldc           #168                // String digester.error.end
     576: invokevirtual #105                // Method org/apache/tomcat/util/res/StringManager.getString:(Ljava/lang/String;)Ljava/lang/String;
     579: aload         9
     581: invokeinterface #106,  3          // InterfaceMethod org/apache/juli/logging/Log.error:(Ljava/lang/Object;Ljava/lang/Throwable;)V
     586: aload         9
     588: athrow
     589: iinc          7, 1
     592: goto          452
     595: aload_0
     596: getfield      #32                 // Field match:Ljava/lang/String;
     599: bipush        47
     601: invokevirtual #93                 // Method java/lang/String.lastIndexOf:(I)I
     604: istore        7
     606: iload         7
     608: iflt          628
     611: aload_0
     612: aload_0
     613: getfield      #32                 // Field match:Ljava/lang/String;
     616: iconst_0
     617: iload         7
     619: invokevirtual #169                // Method java/lang/String.substring:(II)Ljava/lang/String;
     622: putfield      #32                 // Field match:Ljava/lang/String;
     625: goto          634
     628: aload_0
     629: ldc           #31                 // String
     631: putfield      #32                 // Field match:Ljava/lang/String;
     634: return
    Exception table:
       from    to  target type
         253   301   304   Class java/lang/Exception
         253   301   332   Class java/lang/Error
         478   534   537   Class java/lang/Exception
         478   534   565   Class java/lang/Error

  public void endPrefixMapping(java.lang.String) throws org.xml.sax.SAXException;
    Code:
       0: aload_0
       1: getfield      #51                 // Field saxLog:Lorg/apache/juli/logging/Log;
       4: invokeinterface #128,  1          // InterfaceMethod org/apache/juli/logging/Log.isDebugEnabled:()Z
       9: ifeq          45
      12: aload_0
      13: getfield      #51                 // Field saxLog:Lorg/apache/juli/logging/Log;
      16: new           #15                 // class java/lang/StringBuilder
      19: dup
      20: invokespecial #16                 // Method java/lang/StringBuilder."<init>":()V
      23: ldc           #170                // String endPrefixMapping(
      25: invokevirtual #80                 // Method java/lang/StringBuilder.append:(Ljava/lang/String;)Ljava/lang/StringBuilder;
      28: aload_1
      29: invokevirtual #80                 // Method java/lang/StringBuilder.append:(Ljava/lang/String;)Ljava/lang/StringBuilder;
      32: ldc           #131                // String )
      34: invokevirtual #80                 // Method java/lang/StringBuilder.append:(Ljava/lang/String;)Ljava/lang/StringBuilder;
      37: invokevirtual #85                 // Method java/lang/StringBuilder.toString:()Ljava/lang/String;
      40: invokeinterface #132,  2          // InterfaceMethod org/apache/juli/logging/Log.debug:(Ljava/lang/Object;)V
      45: aload_0
      46: getfield      #34                 // Field namespaces:Ljava/util/HashMap;
      49: aload_1
      50: invokevirtual #86                 // Method java/util/HashMap.get:(Ljava/lang/Object;)Ljava/lang/Object;
      53: checkcast     #18                 // class org/apache/tomcat/util/digester/ArrayStack
      56: astore_2
      57: aload_2
      58: ifnonnull     62
      61: return
      62: aload_2
      63: invokevirtual #157                // Method org/apache/tomcat/util/digester/ArrayStack.pop:()Ljava/lang/Object;
      66: pop
      67: aload_2
      68: invokevirtual #171                // Method org/apache/tomcat/util/digester/ArrayStack.empty:()Z
      71: ifeq          83
      74: aload_0
      75: getfield      #34                 // Field namespaces:Ljava/util/HashMap;
      78: aload_1
      79: invokevirtual #172                // Method java/util/HashMap.remove:(Ljava/lang/Object;)Ljava/lang/Object;
      82: pop
      83: goto          100
      86: astore_3
      87: aload_0
      88: getstatic     #71                 // Field sm:Lorg/apache/tomcat/util/res/StringManager;
      91: ldc           #173                // String digester.emptyStackError
      93: invokevirtual #105                // Method org/apache/tomcat/util/res/StringManager.getString:(Ljava/lang/String;)Ljava/lang/String;
      96: invokevirtual #174                // Method createSAXException:(Ljava/lang/String;)Lorg/xml/sax/SAXException;
      99: athrow
     100: return
    Exception table:
       from    to  target type
          62    83    86   Class java/util/EmptyStackException

  public void ignorableWhitespace(char[], int, int) throws org.xml.sax.SAXException;
    Code:
       0: aload_0
       1: getfield      #51                 // Field saxLog:Lorg/apache/juli/logging/Log;
       4: invokeinterface #128,  1          // InterfaceMethod org/apache/juli/logging/Log.isDebugEnabled:()Z
       9: ifeq          54
      12: aload_0
      13: getfield      #51                 // Field saxLog:Lorg/apache/juli/logging/Log;
      16: new           #15                 // class java/lang/StringBuilder
      19: dup
      20: invokespecial #16                 // Method java/lang/StringBuilder."<init>":()V
      23: ldc           #175                // String ignorableWhitespace(
      25: invokevirtual #80                 // Method java/lang/StringBuilder.append:(Ljava/lang/String;)Ljava/lang/StringBuilder;
      28: new           #6                  // class java/lang/String
      31: dup
      32: aload_1
      33: iload_2
      34: iload_3
      35: invokespecial #130                // Method java/lang/String."<init>":([CII)V
      38: invokevirtual #80                 // Method java/lang/StringBuilder.append:(Ljava/lang/String;)Ljava/lang/StringBuilder;
      41: ldc           #131                // String )
      43: invokevirtual #80                 // Method java/lang/StringBuilder.append:(Ljava/lang/String;)Ljava/lang/StringBuilder;
      46: invokevirtual #85                 // Method java/lang/StringBuilder.toString:()Ljava/lang/String;
      49: invokeinterface #132,  2          // InterfaceMethod org/apache/juli/logging/Log.debug:(Ljava/lang/Object;)V
      54: return

  public void processingInstruction(java.lang.String, java.lang.String) throws org.xml.sax.SAXException;
    Code:
       0: aload_0
       1: getfield      #51                 // Field saxLog:Lorg/apache/juli/logging/Log;
       4: invokeinterface #128,  1          // InterfaceMethod org/apache/juli/logging/Log.isDebugEnabled:()Z
       9: ifeq          54
      12: aload_0
      13: getfield      #51                 // Field saxLog:Lorg/apache/juli/logging/Log;
      16: new           #15                 // class java/lang/StringBuilder
      19: dup
      20: invokespecial #16                 // Method java/lang/StringBuilder."<init>":()V
      23: ldc           #176                // String processingInstruction(\'
      25: invokevirtual #80                 // Method java/lang/StringBuilder.append:(Ljava/lang/String;)Ljava/lang/StringBuilder;
      28: aload_1
      29: invokevirtual #80                 // Method java/lang/StringBuilder.append:(Ljava/lang/String;)Ljava/lang/StringBuilder;
      32: ldc           #177                // String \',\'
      34: invokevirtual #80                 // Method java/lang/StringBuilder.append:(Ljava/lang/String;)Ljava/lang/StringBuilder;
      37: aload_2
      38: invokevirtual #80                 // Method java/lang/StringBuilder.append:(Ljava/lang/String;)Ljava/lang/StringBuilder;
      41: ldc           #178                // String \')
      43: invokevirtual #80                 // Method java/lang/StringBuilder.append:(Ljava/lang/String;)Ljava/lang/StringBuilder;
      46: invokevirtual #85                 // Method java/lang/StringBuilder.toString:()Ljava/lang/String;
      49: invokeinterface #132,  2          // InterfaceMethod org/apache/juli/logging/Log.debug:(Ljava/lang/Object;)V
      54: return

  public org.xml.sax.Locator getDocumentLocator();
    Code:
       0: aload_0
       1: getfield      #30                 // Field locator:Lorg/xml/sax/Locator;
       4: areturn

  public void setDocumentLocator(org.xml.sax.Locator);
    Code:
       0: aload_0
       1: getfield      #51                 // Field saxLog:Lorg/apache/juli/logging/Log;
       4: invokeinterface #128,  1          // InterfaceMethod org/apache/juli/logging/Log.isDebugEnabled:()Z
       9: ifeq          45
      12: aload_0
      13: getfield      #51                 // Field saxLog:Lorg/apache/juli/logging/Log;
      16: new           #15                 // class java/lang/StringBuilder
      19: dup
      20: invokespecial #16                 // Method java/lang/StringBuilder."<init>":()V
      23: ldc           #179                // String setDocumentLocator(
      25: invokevirtual #80                 // Method java/lang/StringBuilder.append:(Ljava/lang/String;)Ljava/lang/StringBuilder;
      28: aload_1
      29: invokevirtual #154                // Method java/lang/StringBuilder.append:(Ljava/lang/Object;)Ljava/lang/StringBuilder;
      32: ldc           #131                // String )
      34: invokevirtual #80                 // Method java/lang/StringBuilder.append:(Ljava/lang/String;)Ljava/lang/StringBuilder;
      37: invokevirtual #85                 // Method java/lang/StringBuilder.toString:()Ljava/lang/String;
      40: invokeinterface #132,  2          // InterfaceMethod org/apache/juli/logging/Log.debug:(Ljava/lang/Object;)V
      45: aload_0
      46: aload_1
      47: putfield      #30                 // Field locator:Lorg/xml/sax/Locator;
      50: return

  public void skippedEntity(java.lang.String) throws org.xml.sax.SAXException;
    Code:
       0: aload_0
       1: getfield      #51                 // Field saxLog:Lorg/apache/juli/logging/Log;
       4: invokeinterface #128,  1          // InterfaceMethod org/apache/juli/logging/Log.isDebugEnabled:()Z
       9: ifeq          45
      12: aload_0
      13: getfield      #51                 // Field saxLog:Lorg/apache/juli/logging/Log;
      16: new           #15                 // class java/lang/StringBuilder
      19: dup
      20: invokespecial #16                 // Method java/lang/StringBuilder."<init>":()V
      23: ldc           #180                // String skippedEntity(
      25: invokevirtual #80                 // Method java/lang/StringBuilder.append:(Ljava/lang/String;)Ljava/lang/StringBuilder;
      28: aload_1
      29: invokevirtual #80                 // Method java/lang/StringBuilder.append:(Ljava/lang/String;)Ljava/lang/StringBuilder;
      32: ldc           #131                // String )
      34: invokevirtual #80                 // Method java/lang/StringBuilder.append:(Ljava/lang/String;)Ljava/lang/StringBuilder;
      37: invokevirtual #85                 // Method java/lang/StringBuilder.toString:()Ljava/lang/String;
      40: invokeinterface #132,  2          // InterfaceMethod org/apache/juli/logging/Log.debug:(Ljava/lang/Object;)V
      45: return

  public void startDocument() throws org.xml.sax.SAXException;
    Code:
       0: aload_0
       1: getfield      #51                 // Field saxLog:Lorg/apache/juli/logging/Log;
       4: invokeinterface #128,  1          // InterfaceMethod org/apache/juli/logging/Log.isDebugEnabled:()Z
       9: ifeq          23
      12: aload_0
      13: getfield      #51                 // Field saxLog:Lorg/apache/juli/logging/Log;
      16: ldc           #181                // String startDocument()
      18: invokeinterface #132,  2          // InterfaceMethod org/apache/juli/logging/Log.debug:(Ljava/lang/Object;)V
      23: aload_0
      24: getfield      #30                 // Field locator:Lorg/xml/sax/Locator;
      27: instanceof    #182                // class org/xml/sax/ext/Locator2
      30: ifeq          106
      33: aload_0
      34: getfield      #39                 // Field root:Ljava/lang/Object;
      37: instanceof    #183                // class org/apache/tomcat/util/digester/DocumentProperties$Charset
      40: ifeq          106
      43: aload_0
      44: getfield      #30                 // Field locator:Lorg/xml/sax/Locator;
      47: checkcast     #182                // class org/xml/sax/ext/Locator2
      50: invokeinterface #184,  1          // InterfaceMethod org/xml/sax/ext/Locator2.getEncoding:()Ljava/lang/String;
      55: astore_1
      56: aload_1
      57: ifnull        106
      60: aload_0
      61: getfield      #39                 // Field root:Ljava/lang/Object;
      64: checkcast     #183                // class org/apache/tomcat/util/digester/DocumentProperties$Charset
      67: aload_1
      68: invokestatic  #185                // Method org/apache/tomcat/util/buf/B2CConverter.getCharset:(Ljava/lang/String;)Ljava/nio/charset/Charset;
      71: invokeinterface #186,  2          // InterfaceMethod org/apache/tomcat/util/digester/DocumentProperties$Charset.setCharset:(Ljava/nio/charset/Charset;)V
      76: goto          106
      79: astore_2
      80: aload_0
      81: getfield      #48                 // Field log:Lorg/apache/juli/logging/Log;
      84: getstatic     #71                 // Field sm:Lorg/apache/tomcat/util/res/StringManager;
      87: ldc           #188                // String digester.encodingInvalid
      89: iconst_1
      90: anewarray     #73                 // class java/lang/Object
      93: dup
      94: iconst_0
      95: aload_1
      96: aastore
      97: invokevirtual #74                 // Method org/apache/tomcat/util/res/StringManager.getString:(Ljava/lang/String;[Ljava/lang/Object;)Ljava/lang/String;
     100: aload_2
     101: invokeinterface #75,  3           // InterfaceMethod org/apache/juli/logging/Log.warn:(Ljava/lang/Object;Ljava/lang/Throwable;)V
     106: aload_0
     107: invokevirtual #189                // Method configure:()V
     110: return
    Exception table:
       from    to  target type
          60    76    79   Class java/io/UnsupportedEncodingException

  public void startElement(java.lang.String, java.lang.String, java.lang.String, org.xml.sax.Attributes) throws org.xml.sax.SAXException;
    Code:
       0: aload_0
       1: getfield      #48                 // Field log:Lorg/apache/juli/logging/Log;
       4: invokeinterface #128,  1          // InterfaceMethod org/apache/juli/logging/Log.isDebugEnabled:()Z
       9: istore        5
      11: aload_0
      12: getfield      #51                 // Field saxLog:Lorg/apache/juli/logging/Log;
      15: invokeinterface #128,  1          // InterfaceMethod org/apache/juli/logging/Log.isDebugEnabled:()Z
      20: ifeq          74
      23: aload_0
      24: getfield      #51                 // Field saxLog:Lorg/apache/juli/logging/Log;
      27: new           #15                 // class java/lang/StringBuilder
      30: dup
      31: invokespecial #16                 // Method java/lang/StringBuilder."<init>":()V
      34: ldc           #190                // String startElement(
      36: invokevirtual #80                 // Method java/lang/StringBuilder.append:(Ljava/lang/String;)Ljava/lang/StringBuilder;
      39: aload_1
      40: invokevirtual #80                 // Method java/lang/StringBuilder.append:(Ljava/lang/String;)Ljava/lang/StringBuilder;
      43: ldc           #150                // String ,
      45: invokevirtual #80                 // Method java/lang/StringBuilder.append:(Ljava/lang/String;)Ljava/lang/StringBuilder;
      48: aload_2
      49: invokevirtual #80                 // Method java/lang/StringBuilder.append:(Ljava/lang/String;)Ljava/lang/StringBuilder;
      52: ldc           #150                // String ,
      54: invokevirtual #80                 // Method java/lang/StringBuilder.append:(Ljava/lang/String;)Ljava/lang/StringBuilder;
      57: aload_3
      58: invokevirtual #80                 // Method java/lang/StringBuilder.append:(Ljava/lang/String;)Ljava/lang/StringBuilder;
      61: ldc           #131                // String )
      63: invokevirtual #80                 // Method java/lang/StringBuilder.append:(Ljava/lang/String;)Ljava/lang/StringBuilder;
      66: invokevirtual #85                 // Method java/lang/StringBuilder.toString:()Ljava/lang/String;
      69: invokeinterface #132,  2          // InterfaceMethod org/apache/juli/logging/Log.debug:(Ljava/lang/Object;)V
      74: aload_0
      75: aload         4
      77: invokespecial #191                // Method updateAttributes:(Lorg/xml/sax/Attributes;)Lorg/xml/sax/Attributes;
      80: astore        4
      82: aload_0
      83: getfield      #20                 // Field bodyTexts:Lorg/apache/tomcat/util/digester/ArrayStack;
      86: aload_0
      87: getfield      #17                 // Field bodyText:Ljava/lang/StringBuilder;
      90: invokevirtual #192                // Method org/apache/tomcat/util/digester/ArrayStack.push:(Ljava/lang/Object;)Ljava/lang/Object;
      93: pop
      94: aload_0
      95: new           #15                 // class java/lang/StringBuilder
      98: dup
      99: invokespecial #16                 // Method java/lang/StringBuilder."<init>":()V
     102: putfield      #17                 // Field bodyText:Ljava/lang/StringBuilder;
     105: aload_2
     106: astore        6
     108: aload         6
     110: ifnull        122
     113: aload         6
     115: invokevirtual #156                // Method java/lang/String.length:()I
     118: iconst_1
     119: if_icmpge     125
     122: aload_3
     123: astore        6
     125: new           #15                 // class java/lang/StringBuilder
     128: dup
     129: aload_0
     130: getfield      #32                 // Field match:Ljava/lang/String;
     133: invokespecial #193                // Method java/lang/StringBuilder."<init>":(Ljava/lang/String;)V
     136: astore        7
     138: aload_0
     139: getfield      #32                 // Field match:Ljava/lang/String;
     142: invokevirtual #156                // Method java/lang/String.length:()I
     145: ifle          156
     148: aload         7
     150: bipush        47
     152: invokevirtual #194                // Method java/lang/StringBuilder.append:(C)Ljava/lang/StringBuilder;
     155: pop
     156: aload         7
     158: aload         6
     160: invokevirtual #80                 // Method java/lang/StringBuilder.append:(Ljava/lang/String;)Ljava/lang/StringBuilder;
     163: pop
     164: aload_0
     165: aload         7
     167: invokevirtual #85                 // Method java/lang/StringBuilder.toString:()Ljava/lang/String;
     170: putfield      #32                 // Field match:Ljava/lang/String;
     173: iload         5
     175: ifeq          214
     178: aload_0
     179: getfield      #48                 // Field log:Lorg/apache/juli/logging/Log;
     182: new           #15                 // class java/lang/StringBuilder
     185: dup
     186: invokespecial #16                 // Method java/lang/StringBuilder."<init>":()V
     189: ldc           #195                // String   New match=\'
     191: invokevirtual #80                 // Method java/lang/StringBuilder.append:(Ljava/lang/String;)Ljava/lang/StringBuilder;
     194: aload_0
     195: getfield      #32                 // Field match:Ljava/lang/String;
     198: invokevirtual #80                 // Method java/lang/StringBuilder.append:(Ljava/lang/String;)Ljava/lang/StringBuilder;
     201: ldc           #152                // String \'
     203: invokevirtual #80                 // Method java/lang/StringBuilder.append:(Ljava/lang/String;)Ljava/lang/StringBuilder;
     206: invokevirtual #85                 // Method java/lang/StringBuilder.toString:()Ljava/lang/String;
     209: invokeinterface #132,  2          // InterfaceMethod org/apache/juli/logging/Log.debug:(Ljava/lang/Object;)V
     214: aload_0
     215: invokevirtual #140                // Method getRules:()Lorg/apache/tomcat/util/digester/Rules;
     218: aload_1
     219: aload_0
     220: getfield      #32                 // Field match:Ljava/lang/String;
     223: invokeinterface #196,  3          // InterfaceMethod org/apache/tomcat/util/digester/Rules.match:(Ljava/lang/String;Ljava/lang/String;)Ljava/util/List;
     228: astore        8
     230: aload_0
     231: getfield      #22                 // Field matches:Lorg/apache/tomcat/util/digester/ArrayStack;
     234: aload         8
     236: invokevirtual #192                // Method org/apache/tomcat/util/digester/ArrayStack.push:(Ljava/lang/Object;)Ljava/lang/Object;
     239: pop
     240: aload         8
     242: ifnull        395
     245: aload         8
     247: invokeinterface #158,  1          // InterfaceMethod java/util/List.size:()I
     252: ifle          395
     255: aload         8
     257: invokeinterface #142,  1          // InterfaceMethod java/util/List.iterator:()Ljava/util/Iterator;
     262: astore        9
     264: aload         9
     266: invokeinterface #64,  1           // InterfaceMethod java/util/Iterator.hasNext:()Z
     271: ifeq          392
     274: aload         9
     276: invokeinterface #65,  1           // InterfaceMethod java/util/Iterator.next:()Ljava/lang/Object;
     281: checkcast     #143                // class org/apache/tomcat/util/digester/Rule
     284: astore        10
     286: aload         10
     288: astore        11
     290: iload         5
     292: ifeq          324
     295: aload_0
     296: getfield      #48                 // Field log:Lorg/apache/juli/logging/Log;
     299: new           #15                 // class java/lang/StringBuilder
     302: dup
     303: invokespecial #16                 // Method java/lang/StringBuilder."<init>":()V
     306: ldc           #197                // String   Fire begin() for
     308: invokevirtual #80                 // Method java/lang/StringBuilder.append:(Ljava/lang/String;)Ljava/lang/StringBuilder;
     311: aload         11
     313: invokevirtual #154                // Method java/lang/StringBuilder.append:(Ljava/lang/Object;)Ljava/lang/StringBuilder;
     316: invokevirtual #85                 // Method java/lang/StringBuilder.toString:()Ljava/lang/String;
     319: invokeinterface #132,  2          // InterfaceMethod org/apache/juli/logging/Log.debug:(Ljava/lang/Object;)V
     324: aload         11
     326: aload_1
     327: aload         6
     329: aload         4
     331: invokevirtual #198                // Method org/apache/tomcat/util/digester/Rule.begin:(Ljava/lang/String;Ljava/lang/String;Lorg/xml/sax/Attributes;)V
     334: goto          389
     337: astore        11
     339: aload_0
     340: getfield      #48                 // Field log:Lorg/apache/juli/logging/Log;
     343: getstatic     #71                 // Field sm:Lorg/apache/tomcat/util/res/StringManager;
     346: ldc           #199                // String digester.error.begin
     348: invokevirtual #105                // Method org/apache/tomcat/util/res/StringManager.getString:(Ljava/lang/String;)Ljava/lang/String;
     351: aload         11
     353: invokeinterface #106,  3          // InterfaceMethod org/apache/juli/logging/Log.error:(Ljava/lang/Object;Ljava/lang/Throwable;)V
     358: aload_0
     359: aload         11
     361: invokevirtual #146                // Method createSAXException:(Ljava/lang/Exception;)Lorg/xml/sax/SAXException;
     364: athrow
     365: astore        11
     367: aload_0
     368: getfield      #48                 // Field log:Lorg/apache/juli/logging/Log;
     371: getstatic     #71                 // Field sm:Lorg/apache/tomcat/util/res/StringManager;
     374: ldc           #199                // String digester.error.begin
     376: invokevirtual #105                // Method org/apache/tomcat/util/res/StringManager.getString:(Ljava/lang/String;)Ljava/lang/String;
     379: aload         11
     381: invokeinterface #106,  3          // InterfaceMethod org/apache/juli/logging/Log.error:(Ljava/lang/Object;Ljava/lang/Throwable;)V
     386: aload         11
     388: athrow
     389: goto          264
     392: goto          428
     395: iload         5
     397: ifeq          428
     400: aload_0
     401: getfield      #48                 // Field log:Lorg/apache/juli/logging/Log;
     404: getstatic     #71                 // Field sm:Lorg/apache/tomcat/util/res/StringManager;
     407: ldc           #163                // String digester.noRulesFound
     409: iconst_1
     410: anewarray     #73                 // class java/lang/Object
     413: dup
     414: iconst_0
     415: aload_0
     416: getfield      #32                 // Field match:Ljava/lang/String;
     419: aastore
     420: invokevirtual #74                 // Method org/apache/tomcat/util/res/StringManager.getString:(Ljava/lang/String;[Ljava/lang/Object;)Ljava/lang/String;
     423: invokeinterface #132,  2          // InterfaceMethod org/apache/juli/logging/Log.debug:(Ljava/lang/Object;)V
     428: return
    Exception table:
       from    to  target type
         286   334   337   Class java/lang/Exception
         286   334   365   Class java/lang/Error

  public void startPrefixMapping(java.lang.String, java.lang.String) throws org.xml.sax.SAXException;
    Code:
       0: aload_0
       1: getfield      #51                 // Field saxLog:Lorg/apache/juli/logging/Log;
       4: invokeinterface #128,  1          // InterfaceMethod org/apache/juli/logging/Log.isDebugEnabled:()Z
       9: ifeq          54
      12: aload_0
      13: getfield      #51                 // Field saxLog:Lorg/apache/juli/logging/Log;
      16: new           #15                 // class java/lang/StringBuilder
      19: dup
      20: invokespecial #16                 // Method java/lang/StringBuilder."<init>":()V
      23: ldc           #200                // String startPrefixMapping(
      25: invokevirtual #80                 // Method java/lang/StringBuilder.append:(Ljava/lang/String;)Ljava/lang/StringBuilder;
      28: aload_1
      29: invokevirtual #80                 // Method java/lang/StringBuilder.append:(Ljava/lang/String;)Ljava/lang/StringBuilder;
      32: ldc           #150                // String ,
      34: invokevirtual #80                 // Method java/lang/StringBuilder.append:(Ljava/lang/String;)Ljava/lang/StringBuilder;
      37: aload_2
      38: invokevirtual #80                 // Method java/lang/StringBuilder.append:(Ljava/lang/String;)Ljava/lang/StringBuilder;
      41: ldc           #131                // String )
      43: invokevirtual #80                 // Method java/lang/StringBuilder.append:(Ljava/lang/String;)Ljava/lang/StringBuilder;
      46: invokevirtual #85                 // Method java/lang/StringBuilder.toString:()Ljava/lang/String;
      49: invokeinterface #132,  2          // InterfaceMethod org/apache/juli/logging/Log.debug:(Ljava/lang/Object;)V
      54: aload_0
      55: getfield      #34                 // Field namespaces:Ljava/util/HashMap;
      58: aload_1
      59: invokevirtual #86                 // Method java/util/HashMap.get:(Ljava/lang/Object;)Ljava/lang/Object;
      62: checkcast     #18                 // class org/apache/tomcat/util/digester/ArrayStack
      65: astore_3
      66: aload_3
      67: ifnonnull     88
      70: new           #18                 // class org/apache/tomcat/util/digester/ArrayStack
      73: dup
      74: invokespecial #19                 // Method org/apache/tomcat/util/digester/ArrayStack."<init>":()V
      77: astore_3
      78: aload_0
      79: getfield      #34                 // Field namespaces:Ljava/util/HashMap;
      82: aload_1
      83: aload_3
      84: invokevirtual #201                // Method java/util/HashMap.put:(Ljava/lang/Object;Ljava/lang/Object;)Ljava/lang/Object;
      87: pop
      88: aload_3
      89: aload_2
      90: invokevirtual #192                // Method org/apache/tomcat/util/digester/ArrayStack.push:(Ljava/lang/Object;)Ljava/lang/Object;
      93: pop
      94: return

  public void notationDecl(java.lang.String, java.lang.String, java.lang.String);
    Code:
       0: aload_0
       1: getfield      #51                 // Field saxLog:Lorg/apache/juli/logging/Log;
       4: invokeinterface #128,  1          // InterfaceMethod org/apache/juli/logging/Log.isDebugEnabled:()Z
       9: ifeq          63
      12: aload_0
      13: getfield      #51                 // Field saxLog:Lorg/apache/juli/logging/Log;
      16: new           #15                 // class java/lang/StringBuilder
      19: dup
      20: invokespecial #16                 // Method java/lang/StringBuilder."<init>":()V
      23: ldc           #202                // String notationDecl(
      25: invokevirtual #80                 // Method java/lang/StringBuilder.append:(Ljava/lang/String;)Ljava/lang/StringBuilder;
      28: aload_1
      29: invokevirtual #80                 // Method java/lang/StringBuilder.append:(Ljava/lang/String;)Ljava/lang/StringBuilder;
      32: ldc           #150                // String ,
      34: invokevirtual #80                 // Method java/lang/StringBuilder.append:(Ljava/lang/String;)Ljava/lang/StringBuilder;
      37: aload_2
      38: invokevirtual #80                 // Method java/lang/StringBuilder.append:(Ljava/lang/String;)Ljava/lang/StringBuilder;
      41: ldc           #150                // String ,
      43: invokevirtual #80                 // Method java/lang/StringBuilder.append:(Ljava/lang/String;)Ljava/lang/StringBuilder;
      46: aload_3
      47: invokevirtual #80                 // Method java/lang/StringBuilder.append:(Ljava/lang/String;)Ljava/lang/StringBuilder;
      50: ldc           #131                // String )
      52: invokevirtual #80                 // Method java/lang/StringBuilder.append:(Ljava/lang/String;)Ljava/lang/StringBuilder;
      55: invokevirtual #85                 // Method java/lang/StringBuilder.toString:()Ljava/lang/String;
      58: invokeinterface #132,  2          // InterfaceMethod org/apache/juli/logging/Log.debug:(Ljava/lang/Object;)V
      63: return

  public void unparsedEntityDecl(java.lang.String, java.lang.String, java.lang.String, java.lang.String);
    Code:
       0: aload_0
       1: getfield      #51                 // Field saxLog:Lorg/apache/juli/logging/Log;
       4: invokeinterface #128,  1          // InterfaceMethod org/apache/juli/logging/Log.isDebugEnabled:()Z
       9: ifeq          73
      12: aload_0
      13: getfield      #51                 // Field saxLog:Lorg/apache/juli/logging/Log;
      16: new           #15                 // class java/lang/StringBuilder
      19: dup
      20: invokespecial #16                 // Method java/lang/StringBuilder."<init>":()V
      23: ldc           #203                // String unparsedEntityDecl(
      25: invokevirtual #80                 // Method java/lang/StringBuilder.append:(Ljava/lang/String;)Ljava/lang/StringBuilder;
      28: aload_1
      29: invokevirtual #80                 // Method java/lang/StringBuilder.append:(Ljava/lang/String;)Ljava/lang/StringBuilder;
      32: ldc           #150                // String ,
      34: invokevirtual #80                 // Method java/lang/StringBuilder.append:(Ljava/lang/String;)Ljava/lang/StringBuilder;
      37: aload_2
      38: invokevirtual #80                 // Method java/lang/StringBuilder.append:(Ljava/lang/String;)Ljava/lang/StringBuilder;
      41: ldc           #150                // String ,
      43: invokevirtual #80                 // Method java/lang/StringBuilder.append:(Ljava/lang/String;)Ljava/lang/StringBuilder;
      46: aload_3
      47: invokevirtual #80                 // Method java/lang/StringBuilder.append:(Ljava/lang/String;)Ljava/lang/StringBuilder;
      50: ldc           #150                // String ,
      52: invokevirtual #80                 // Method java/lang/StringBuilder.append:(Ljava/lang/String;)Ljava/lang/StringBuilder;
      55: aload         4
      57: invokevirtual #80                 // Method java/lang/StringBuilder.append:(Ljava/lang/String;)Ljava/lang/StringBuilder;
      60: ldc           #131                // String )
      62: invokevirtual #80                 // Method java/lang/StringBuilder.append:(Ljava/lang/String;)Ljava/lang/StringBuilder;
      65: invokevirtual #85                 // Method java/lang/StringBuilder.toString:()Ljava/lang/String;
      68: invokeinterface #132,  2          // InterfaceMethod org/apache/juli/logging/Log.debug:(Ljava/lang/Object;)V
      73: return

  public void setEntityResolver(org.xml.sax.EntityResolver);
    Code:
       0: aload_0
       1: aload_1
       2: putfield      #204                // Field entityResolver:Lorg/xml/sax/EntityResolver;
       5: return

  public org.xml.sax.EntityResolver getEntityResolver();
    Code:
       0: aload_0
       1: getfield      #204                // Field entityResolver:Lorg/xml/sax/EntityResolver;
       4: areturn

  public org.xml.sax.InputSource resolveEntity(java.lang.String, java.lang.String, java.lang.String, java.lang.String) throws org.xml.sax.SAXException, java.io.IOException;
    Code:
       0: aload_0
       1: getfield      #51                 // Field saxLog:Lorg/apache/juli/logging/Log;
       4: invokeinterface #128,  1          // InterfaceMethod org/apache/juli/logging/Log.isDebugEnabled:()Z
       9: ifeq          64
      12: aload_0
      13: getfield      #51                 // Field saxLog:Lorg/apache/juli/logging/Log;
      16: new           #15                 // class java/lang/StringBuilder
      19: dup
      20: invokespecial #16                 // Method java/lang/StringBuilder."<init>":()V
      23: ldc           #205                // String resolveEntity(\'
      25: invokevirtual #80                 // Method java/lang/StringBuilder.append:(Ljava/lang/String;)Ljava/lang/StringBuilder;
      28: aload_2
      29: invokevirtual #80                 // Method java/lang/StringBuilder.append:(Ljava/lang/String;)Ljava/lang/StringBuilder;
      32: ldc           #206                // String \', \'
      34: invokevirtual #80                 // Method java/lang/StringBuilder.append:(Ljava/lang/String;)Ljava/lang/StringBuilder;
      37: aload         4
      39: invokevirtual #80                 // Method java/lang/StringBuilder.append:(Ljava/lang/String;)Ljava/lang/StringBuilder;
      42: ldc           #206                // String \', \'
      44: invokevirtual #80                 // Method java/lang/StringBuilder.append:(Ljava/lang/String;)Ljava/lang/StringBuilder;
      47: aload_3
      48: invokevirtual #80                 // Method java/lang/StringBuilder.append:(Ljava/lang/String;)Ljava/lang/StringBuilder;
      51: ldc           #178                // String \')
      53: invokevirtual #80                 // Method java/lang/StringBuilder.append:(Ljava/lang/String;)Ljava/lang/StringBuilder;
      56: invokevirtual #85                 // Method java/lang/StringBuilder.toString:()Ljava/lang/String;
      59: invokeinterface #132,  2          // InterfaceMethod org/apache/juli/logging/Log.debug:(Ljava/lang/Object;)V
      64: aconst_null
      65: astore        5
      67: aload_2
      68: ifnull        84
      71: aload_0
      72: getfield      #27                 // Field entityValidator:Ljava/util/HashMap;
      75: aload_2
      76: invokevirtual #86                 // Method java/util/HashMap.get:(Ljava/lang/Object;)Ljava/lang/Object;
      79: checkcast     #6                  // class java/lang/String
      82: astore        5
      84: aload         5
      86: ifnonnull     292
      89: aload         4
      91: ifnonnull     141
      94: aload_0
      95: getfield      #48                 // Field log:Lorg/apache/juli/logging/Log;
      98: invokeinterface #128,  1          // InterfaceMethod org/apache/juli/logging/Log.isDebugEnabled:()Z
     103: ifeq          139
     106: aload_0
     107: getfield      #48                 // Field log:Lorg/apache/juli/logging/Log;
     110: new           #15                 // class java/lang/StringBuilder
     113: dup
     114: invokespecial #16                 // Method java/lang/StringBuilder."<init>":()V
     117: ldc           #207                // String  Cannot resolve entity: \'
     119: invokevirtual #80                 // Method java/lang/StringBuilder.append:(Ljava/lang/String;)Ljava/lang/StringBuilder;
     122: aload_2
     123: invokevirtual #80                 // Method java/lang/StringBuilder.append:(Ljava/lang/String;)Ljava/lang/StringBuilder;
     126: ldc           #152                // String \'
     128: invokevirtual #80                 // Method java/lang/StringBuilder.append:(Ljava/lang/String;)Ljava/lang/StringBuilder;
     131: invokevirtual #85                 // Method java/lang/StringBuilder.toString:()Ljava/lang/String;
     134: invokeinterface #132,  2          // InterfaceMethod org/apache/juli/logging/Log.debug:(Ljava/lang/Object;)V
     139: aconst_null
     140: areturn
     141: aload_0
     142: getfield      #48                 // Field log:Lorg/apache/juli/logging/Log;
     145: invokeinterface #128,  1          // InterfaceMethod org/apache/juli/logging/Log.isDebugEnabled:()Z
     150: ifeq          187
     153: aload_0
     154: getfield      #48                 // Field log:Lorg/apache/juli/logging/Log;
     157: new           #15                 // class java/lang/StringBuilder
     160: dup
     161: invokespecial #16                 // Method java/lang/StringBuilder."<init>":()V
     164: ldc           #208                // String  Trying to resolve using system ID \'
     166: invokevirtual #80                 // Method java/lang/StringBuilder.append:(Ljava/lang/String;)Ljava/lang/StringBuilder;
     169: aload         4
     171: invokevirtual #80                 // Method java/lang/StringBuilder.append:(Ljava/lang/String;)Ljava/lang/StringBuilder;
     174: ldc           #152                // String \'
     176: invokevirtual #80                 // Method java/lang/StringBuilder.append:(Ljava/lang/String;)Ljava/lang/StringBuilder;
     179: invokevirtual #85                 // Method java/lang/StringBuilder.toString:()Ljava/lang/String;
     182: invokeinterface #132,  2          // InterfaceMethod org/apache/juli/logging/Log.debug:(Ljava/lang/Object;)V
     187: aload         4
     189: astore        5
     191: aload_3
     192: ifnull        292
     195: new           #209                // class java/net/URI
     198: dup
     199: aload         4
     201: invokespecial #210                // Method java/net/URI."<init>":(Ljava/lang/String;)V
     204: astore        6
     206: aload         6
     208: invokevirtual #211                // Method java/net/URI.isAbsolute:()Z
     211: ifne          232
     214: new           #209                // class java/net/URI
     217: dup
     218: aload_3
     219: invokespecial #210                // Method java/net/URI."<init>":(Ljava/lang/String;)V
     222: aload         6
     224: invokevirtual #212                // Method java/net/URI.resolve:(Ljava/net/URI;)Ljava/net/URI;
     227: invokevirtual #213                // Method java/net/URI.toString:()Ljava/lang/String;
     230: astore        5
     232: goto          292
     235: astore        6
     237: aload_0
     238: getfield      #48                 // Field log:Lorg/apache/juli/logging/Log;
     241: invokeinterface #128,  1          // InterfaceMethod org/apache/juli/logging/Log.isDebugEnabled:()Z
     246: ifeq          292
     249: aload_0
     250: getfield      #48                 // Field log:Lorg/apache/juli/logging/Log;
     253: new           #15                 // class java/lang/StringBuilder
     256: dup
     257: invokespecial #16                 // Method java/lang/StringBuilder."<init>":()V
     260: ldc           #215                // String Invalid URI \'
     262: invokevirtual #80                 // Method java/lang/StringBuilder.append:(Ljava/lang/String;)Ljava/lang/StringBuilder;
     265: aload_3
     266: invokevirtual #80                 // Method java/lang/StringBuilder.append:(Ljava/lang/String;)Ljava/lang/StringBuilder;
     269: ldc           #216                // String \' or \'
     271: invokevirtual #80                 // Method java/lang/StringBuilder.append:(Ljava/lang/String;)Ljava/lang/StringBuilder;
     274: aload         4
     276: invokevirtual #80                 // Method java/lang/StringBuilder.append:(Ljava/lang/String;)Ljava/lang/StringBuilder;
     279: ldc           #152                // String \'
     281: invokevirtual #80                 // Method java/lang/StringBuilder.append:(Ljava/lang/String;)Ljava/lang/StringBuilder;
     284: invokevirtual #85                 // Method java/lang/StringBuilder.toString:()Ljava/lang/String;
     287: invokeinterface #132,  2          // InterfaceMethod org/apache/juli/logging/Log.debug:(Ljava/lang/Object;)V
     292: aload_0
     293: getfield      #48                 // Field log:Lorg/apache/juli/logging/Log;
     296: invokeinterface #128,  1          // InterfaceMethod org/apache/juli/logging/Log.isDebugEnabled:()Z
     301: ifeq          338
     304: aload_0
     305: getfield      #48                 // Field log:Lorg/apache/juli/logging/Log;
     308: new           #15                 // class java/lang/StringBuilder
     311: dup
     312: invokespecial #16                 // Method java/lang/StringBuilder."<init>":()V
     315: ldc           #217                // String  Resolving to alternate DTD \'
     317: invokevirtual #80                 // Method java/lang/StringBuilder.append:(Ljava/lang/String;)Ljava/lang/StringBuilder;
     320: aload         5
     322: invokevirtual #80                 // Method java/lang/StringBuilder.append:(Ljava/lang/String;)Ljava/lang/StringBuilder;
     325: ldc           #152                // String \'
     327: invokevirtual #80                 // Method java/lang/StringBuilder.append:(Ljava/lang/String;)Ljava/lang/StringBuilder;
     330: invokevirtual #85                 // Method java/lang/StringBuilder.toString:()Ljava/lang/String;
     333: invokeinterface #132,  2          // InterfaceMethod org/apache/juli/logging/Log.debug:(Ljava/lang/Object;)V
     338: new           #218                // class org/xml/sax/InputSource
     341: dup
     342: aload         5
     344: invokespecial #219                // Method org/xml/sax/InputSource."<init>":(Ljava/lang/String;)V
     347: areturn
     348: astore        6
     350: aload_0
     351: aload         6
     353: invokevirtual #146                // Method createSAXException:(Ljava/lang/Exception;)Lorg/xml/sax/SAXException;
     356: athrow
    Exception table:
       from    to  target type
         195   232   235   Class java/net/URISyntaxException
         338   347   348   Class java/lang/Exception

  public void startDTD(java.lang.String, java.lang.String, java.lang.String) throws org.xml.sax.SAXException;
    Code:
       0: aload_0
       1: aload_2
       2: invokevirtual #220                // Method setPublicId:(Ljava/lang/String;)V
       5: return

  public void error(org.xml.sax.SAXParseException) throws org.xml.sax.SAXException;
    Code:
       0: aload_0
       1: getfield      #48                 // Field log:Lorg/apache/juli/logging/Log;
       4: getstatic     #71                 // Field sm:Lorg/apache/tomcat/util/res/StringManager;
       7: ldc           #221                // String digester.parseError
       9: iconst_2
      10: anewarray     #73                 // class java/lang/Object
      13: dup
      14: iconst_0
      15: aload_1
      16: invokevirtual #222                // Method org/xml/sax/SAXParseException.getLineNumber:()I
      19: invokestatic  #223                // Method java/lang/Integer.valueOf:(I)Ljava/lang/Integer;
      22: aastore
      23: dup
      24: iconst_1
      25: aload_1
      26: invokevirtual #224                // Method org/xml/sax/SAXParseException.getColumnNumber:()I
      29: invokestatic  #223                // Method java/lang/Integer.valueOf:(I)Ljava/lang/Integer;
      32: aastore
      33: invokevirtual #74                 // Method org/apache/tomcat/util/res/StringManager.getString:(Ljava/lang/String;[Ljava/lang/Object;)Ljava/lang/String;
      36: aload_1
      37: invokeinterface #106,  3          // InterfaceMethod org/apache/juli/logging/Log.error:(Ljava/lang/Object;Ljava/lang/Throwable;)V
      42: aload_0
      43: getfield      #28                 // Field errorHandler:Lorg/xml/sax/ErrorHandler;
      46: ifnull        59
      49: aload_0
      50: getfield      #28                 // Field errorHandler:Lorg/xml/sax/ErrorHandler;
      53: aload_1
      54: invokeinterface #225,  2          // InterfaceMethod org/xml/sax/ErrorHandler.error:(Lorg/xml/sax/SAXParseException;)V
      59: return

  public void fatalError(org.xml.sax.SAXParseException) throws org.xml.sax.SAXException;
    Code:
       0: aload_0
       1: getfield      #48                 // Field log:Lorg/apache/juli/logging/Log;
       4: getstatic     #71                 // Field sm:Lorg/apache/tomcat/util/res/StringManager;
       7: ldc           #226                // String digester.parseErrorFatal
       9: iconst_2
      10: anewarray     #73                 // class java/lang/Object
      13: dup
      14: iconst_0
      15: aload_1
      16: invokevirtual #222                // Method org/xml/sax/SAXParseException.getLineNumber:()I
      19: invokestatic  #223                // Method java/lang/Integer.valueOf:(I)Ljava/lang/Integer;
      22: aastore
      23: dup
      24: iconst_1
      25: aload_1
      26: invokevirtual #224                // Method org/xml/sax/SAXParseException.getColumnNumber:()I
      29: invokestatic  #223                // Method java/lang/Integer.valueOf:(I)Ljava/lang/Integer;
      32: aastore
      33: invokevirtual #74                 // Method org/apache/tomcat/util/res/StringManager.getString:(Ljava/lang/String;[Ljava/lang/Object;)Ljava/lang/String;
      36: aload_1
      37: invokeinterface #106,  3          // InterfaceMethod org/apache/juli/logging/Log.error:(Ljava/lang/Object;Ljava/lang/Throwable;)V
      42: aload_0
      43: getfield      #28                 // Field errorHandler:Lorg/xml/sax/ErrorHandler;
      46: ifnull        59
      49: aload_0
      50: getfield      #28                 // Field errorHandler:Lorg/xml/sax/ErrorHandler;
      53: aload_1
      54: invokeinterface #227,  2          // InterfaceMethod org/xml/sax/ErrorHandler.fatalError:(Lorg/xml/sax/SAXParseException;)V
      59: return

  public void warning(org.xml.sax.SAXParseException) throws org.xml.sax.SAXException;
    Code:
       0: aload_0
       1: getfield      #48                 // Field log:Lorg/apache/juli/logging/Log;
       4: getstatic     #71                 // Field sm:Lorg/apache/tomcat/util/res/StringManager;
       7: ldc           #228                // String digester.parseWarning
       9: iconst_3
      10: anewarray     #73                 // class java/lang/Object
      13: dup
      14: iconst_0
      15: aload_1
      16: invokevirtual #222                // Method org/xml/sax/SAXParseException.getLineNumber:()I
      19: invokestatic  #223                // Method java/lang/Integer.valueOf:(I)Ljava/lang/Integer;
      22: aastore
      23: dup
      24: iconst_1
      25: aload_1
      26: invokevirtual #224                // Method org/xml/sax/SAXParseException.getColumnNumber:()I
      29: invokestatic  #223                // Method java/lang/Integer.valueOf:(I)Ljava/lang/Integer;
      32: aastore
      33: dup
      34: iconst_2
      35: aload_1
      36: aastore
      37: invokevirtual #74                 // Method org/apache/tomcat/util/res/StringManager.getString:(Ljava/lang/String;[Ljava/lang/Object;)Ljava/lang/String;
      40: invokeinterface #229,  2          // InterfaceMethod org/apache/juli/logging/Log.error:(Ljava/lang/Object;)V
      45: aload_0
      46: getfield      #28                 // Field errorHandler:Lorg/xml/sax/ErrorHandler;
      49: ifnull        62
      52: aload_0
      53: getfield      #28                 // Field errorHandler:Lorg/xml/sax/ErrorHandler;
      56: aload_1
      57: invokeinterface #230,  2          // InterfaceMethod org/xml/sax/ErrorHandler.warning:(Lorg/xml/sax/SAXParseException;)V
      62: return

  public java.lang.Object parse(java.io.File) throws java.io.IOException, org.xml.sax.SAXException;
    Code:
       0: aload_0
       1: invokevirtual #189                // Method configure:()V
       4: new           #218                // class org/xml/sax/InputSource
       7: dup
       8: new           #231                // class java/io/FileInputStream
      11: dup
      12: aload_1
      13: invokespecial #232                // Method java/io/FileInputStream."<init>":(Ljava/io/File;)V
      16: invokespecial #233                // Method org/xml/sax/InputSource."<init>":(Ljava/io/InputStream;)V
      19: astore_2
      20: aload_2
      21: new           #15                 // class java/lang/StringBuilder
      24: dup
      25: invokespecial #16                 // Method java/lang/StringBuilder."<init>":()V
      28: ldc           #234                // String file://
      30: invokevirtual #80                 // Method java/lang/StringBuilder.append:(Ljava/lang/String;)Ljava/lang/StringBuilder;
      33: aload_1
      34: invokevirtual #235                // Method java/io/File.getAbsolutePath:()Ljava/lang/String;
      37: invokevirtual #80                 // Method java/lang/StringBuilder.append:(Ljava/lang/String;)Ljava/lang/StringBuilder;
      40: invokevirtual #85                 // Method java/lang/StringBuilder.toString:()Ljava/lang/String;
      43: invokevirtual #236                // Method org/xml/sax/InputSource.setSystemId:(Ljava/lang/String;)V
      46: aload_0
      47: invokevirtual #237                // Method getXMLReader:()Lorg/xml/sax/XMLReader;
      50: aload_2
      51: invokeinterface #238,  2          // InterfaceMethod org/xml/sax/XMLReader.parse:(Lorg/xml/sax/InputSource;)V
      56: aload_0
      57: getfield      #39                 // Field root:Ljava/lang/Object;
      60: areturn

  public java.lang.Object parse(org.xml.sax.InputSource) throws java.io.IOException, org.xml.sax.SAXException;
    Code:
       0: aload_0
       1: invokevirtual #189                // Method configure:()V
       4: aload_0
       5: invokevirtual #237                // Method getXMLReader:()Lorg/xml/sax/XMLReader;
       8: aload_1
       9: invokeinterface #238,  2          // InterfaceMethod org/xml/sax/XMLReader.parse:(Lorg/xml/sax/InputSource;)V
      14: aload_0
      15: getfield      #39                 // Field root:Ljava/lang/Object;
      18: areturn

  public java.lang.Object parse(java.io.InputStream) throws java.io.IOException, org.xml.sax.SAXException;
    Code:
       0: aload_0
       1: invokevirtual #189                // Method configure:()V
       4: new           #218                // class org/xml/sax/InputSource
       7: dup
       8: aload_1
       9: invokespecial #233                // Method org/xml/sax/InputSource."<init>":(Ljava/io/InputStream;)V
      12: astore_2
      13: aload_0
      14: invokevirtual #237                // Method getXMLReader:()Lorg/xml/sax/XMLReader;
      17: aload_2
      18: invokeinterface #238,  2          // InterfaceMethod org/xml/sax/XMLReader.parse:(Lorg/xml/sax/InputSource;)V
      23: aload_0
      24: getfield      #39                 // Field root:Ljava/lang/Object;
      27: areturn

  public void register(java.lang.String, java.lang.String);
    Code:
       0: aload_0
       1: getfield      #48                 // Field log:Lorg/apache/juli/logging/Log;
       4: invokeinterface #128,  1          // InterfaceMethod org/apache/juli/logging/Log.isDebugEnabled:()Z
       9: ifeq          54
      12: aload_0
      13: getfield      #48                 // Field log:Lorg/apache/juli/logging/Log;
      16: new           #15                 // class java/lang/StringBuilder
      19: dup
      20: invokespecial #16                 // Method java/lang/StringBuilder."<init>":()V
      23: ldc           #239                // String register(\'
      25: invokevirtual #80                 // Method java/lang/StringBuilder.append:(Ljava/lang/String;)Ljava/lang/StringBuilder;
      28: aload_1
      29: invokevirtual #80                 // Method java/lang/StringBuilder.append:(Ljava/lang/String;)Ljava/lang/StringBuilder;
      32: ldc           #206                // String \', \'
      34: invokevirtual #80                 // Method java/lang/StringBuilder.append:(Ljava/lang/String;)Ljava/lang/StringBuilder;
      37: aload_2
      38: invokevirtual #80                 // Method java/lang/StringBuilder.append:(Ljava/lang/String;)Ljava/lang/StringBuilder;
      41: ldc           #152                // String \'
      43: invokevirtual #80                 // Method java/lang/StringBuilder.append:(Ljava/lang/String;)Ljava/lang/StringBuilder;
      46: invokevirtual #85                 // Method java/lang/StringBuilder.toString:()Ljava/lang/String;
      49: invokeinterface #132,  2          // InterfaceMethod org/apache/juli/logging/Log.debug:(Ljava/lang/Object;)V
      54: aload_0
      55: getfield      #27                 // Field entityValidator:Ljava/util/HashMap;
      58: aload_1
      59: aload_2
      60: invokevirtual #201                // Method java/util/HashMap.put:(Ljava/lang/Object;Ljava/lang/Object;)Ljava/lang/Object;
      63: pop
      64: return

  public void addRule(java.lang.String, org.apache.tomcat.util.digester.Rule);
    Code:
       0: aload_2
       1: aload_0
       2: invokevirtual #240                // Method org/apache/tomcat/util/digester/Rule.setDigester:(Lorg/apache/tomcat/util/digester/Digester;)V
       5: aload_0
       6: invokevirtual #140                // Method getRules:()Lorg/apache/tomcat/util/digester/Rules;
       9: aload_1
      10: aload_2
      11: invokeinterface #241,  3          // InterfaceMethod org/apache/tomcat/util/digester/Rules.add:(Ljava/lang/String;Lorg/apache/tomcat/util/digester/Rule;)V
      16: return

  public void addRuleSet(org.apache.tomcat.util.digester.RuleSet);
    Code:
       0: aload_1
       1: aload_0
       2: invokeinterface #242,  2          // InterfaceMethod org/apache/tomcat/util/digester/RuleSet.addRuleInstances:(Lorg/apache/tomcat/util/digester/Digester;)V
       7: return

  public void addCallMethod(java.lang.String, java.lang.String);
    Code:
       0: aload_0
       1: aload_1
       2: new           #243                // class org/apache/tomcat/util/digester/CallMethodRule
       5: dup
       6: aload_2
       7: invokespecial #244                // Method org/apache/tomcat/util/digester/CallMethodRule."<init>":(Ljava/lang/String;)V
      10: invokevirtual #245                // Method addRule:(Ljava/lang/String;Lorg/apache/tomcat/util/digester/Rule;)V
      13: return

  public void addCallMethod(java.lang.String, java.lang.String, int);
    Code:
       0: aload_0
       1: aload_1
       2: new           #243                // class org/apache/tomcat/util/digester/CallMethodRule
       5: dup
       6: aload_2
       7: iload_3
       8: invokespecial #246                // Method org/apache/tomcat/util/digester/CallMethodRule."<init>":(Ljava/lang/String;I)V
      11: invokevirtual #245                // Method addRule:(Ljava/lang/String;Lorg/apache/tomcat/util/digester/Rule;)V
      14: return

  public void addCallParam(java.lang.String, int);
    Code:
       0: aload_0
       1: aload_1
       2: new           #247                // class org/apache/tomcat/util/digester/CallParamRule
       5: dup
       6: iload_2
       7: invokespecial #248                // Method org/apache/tomcat/util/digester/CallParamRule."<init>":(I)V
      10: invokevirtual #245                // Method addRule:(Ljava/lang/String;Lorg/apache/tomcat/util/digester/Rule;)V
      13: return

  public void addFactoryCreate(java.lang.String, org.apache.tomcat.util.digester.ObjectCreationFactory, boolean);
    Code:
       0: aload_2
       1: aload_0
       2: invokeinterface #249,  2          // InterfaceMethod org/apache/tomcat/util/digester/ObjectCreationFactory.setDigester:(Lorg/apache/tomcat/util/digester/Digester;)V
       7: aload_0
       8: aload_1
       9: new           #250                // class org/apache/tomcat/util/digester/FactoryCreateRule
      12: dup
      13: aload_2
      14: iload_3
      15: invokespecial #251                // Method org/apache/tomcat/util/digester/FactoryCreateRule."<init>":(Lorg/apache/tomcat/util/digester/ObjectCreationFactory;Z)V
      18: invokevirtual #245                // Method addRule:(Ljava/lang/String;Lorg/apache/tomcat/util/digester/Rule;)V
      21: return

  public void addObjectCreate(java.lang.String, java.lang.String);
    Code:
       0: aload_0
       1: aload_1
       2: new           #252                // class org/apache/tomcat/util/digester/ObjectCreateRule
       5: dup
       6: aload_2
       7: invokespecial #253                // Method org/apache/tomcat/util/digester/ObjectCreateRule."<init>":(Ljava/lang/String;)V
      10: invokevirtual #245                // Method addRule:(Ljava/lang/String;Lorg/apache/tomcat/util/digester/Rule;)V
      13: return

  public void addObjectCreate(java.lang.String, java.lang.String, java.lang.String);
    Code:
       0: aload_0
       1: aload_1
       2: new           #252                // class org/apache/tomcat/util/digester/ObjectCreateRule
       5: dup
       6: aload_2
       7: aload_3
       8: invokespecial #254                // Method org/apache/tomcat/util/digester/ObjectCreateRule."<init>":(Ljava/lang/String;Ljava/lang/String;)V
      11: invokevirtual #245                // Method addRule:(Ljava/lang/String;Lorg/apache/tomcat/util/digester/Rule;)V
      14: return

  public void addSetNext(java.lang.String, java.lang.String, java.lang.String);
    Code:
       0: aload_0
       1: aload_1
       2: new           #255                // class org/apache/tomcat/util/digester/SetNextRule
       5: dup
       6: aload_2
       7: aload_3
       8: invokespecial #256                // Method org/apache/tomcat/util/digester/SetNextRule."<init>":(Ljava/lang/String;Ljava/lang/String;)V
      11: invokevirtual #245                // Method addRule:(Ljava/lang/String;Lorg/apache/tomcat/util/digester/Rule;)V
      14: return

  public void addSetProperties(java.lang.String);
    Code:
       0: aload_0
       1: aload_1
       2: new           #257                // class org/apache/tomcat/util/digester/SetPropertiesRule
       5: dup
       6: invokespecial #258                // Method org/apache/tomcat/util/digester/SetPropertiesRule."<init>":()V
       9: invokevirtual #245                // Method addRule:(Ljava/lang/String;Lorg/apache/tomcat/util/digester/Rule;)V
      12: return

  public void addSetProperties(java.lang.String, java.lang.String[]);
    Code:
       0: aload_0
       1: aload_1
       2: new           #257                // class org/apache/tomcat/util/digester/SetPropertiesRule
       5: dup
       6: aload_2
       7: invokespecial #259                // Method org/apache/tomcat/util/digester/SetPropertiesRule."<init>":([Ljava/lang/String;)V
      10: invokevirtual #245                // Method addRule:(Ljava/lang/String;Lorg/apache/tomcat/util/digester/Rule;)V
      13: return

  public void clear();
    Code:
       0: aload_0
       1: ldc           #31                 // String
       3: putfield      #32                 // Field match:Ljava/lang/String;
       6: aload_0
       7: getfield      #20                 // Field bodyTexts:Lorg/apache/tomcat/util/digester/ArrayStack;
      10: invokevirtual #260                // Method org/apache/tomcat/util/digester/ArrayStack.clear:()V
      13: aload_0
      14: getfield      #35                 // Field params:Lorg/apache/tomcat/util/digester/ArrayStack;
      17: invokevirtual #260                // Method org/apache/tomcat/util/digester/ArrayStack.clear:()V
      20: aload_0
      21: aconst_null
      22: putfield      #37                 // Field publicId:Ljava/lang/String;
      25: aload_0
      26: getfield      #41                 // Field stack:Lorg/apache/tomcat/util/digester/ArrayStack;
      29: invokevirtual #260                // Method org/apache/tomcat/util/digester/ArrayStack.clear:()V
      32: aload_0
      33: aconst_null
      34: putfield      #48                 // Field log:Lorg/apache/juli/logging/Log;
      37: aload_0
      38: aconst_null
      39: putfield      #51                 // Field saxLog:Lorg/apache/juli/logging/Log;
      42: aload_0
      43: iconst_0
      44: putfield      #24                 // Field configured:Z
      47: return

  public void reset();
    Code:
       0: aload_0
       1: aconst_null
       2: putfield      #39                 // Field root:Ljava/lang/Object;
       5: aload_0
       6: aconst_null
       7: invokevirtual #261                // Method setErrorHandler:(Lorg/xml/sax/ErrorHandler;)V
      10: aload_0
      11: invokevirtual #148                // Method clear:()V
      14: return

  public java.lang.Object peek();
    Code:
       0: aload_0
       1: getfield      #41                 // Field stack:Lorg/apache/tomcat/util/digester/ArrayStack;
       4: invokevirtual #87                 // Method org/apache/tomcat/util/digester/ArrayStack.peek:()Ljava/lang/Object;
       7: areturn
       8: astore_1
       9: aload_0
      10: getfield      #48                 // Field log:Lorg/apache/juli/logging/Log;
      13: getstatic     #71                 // Field sm:Lorg/apache/tomcat/util/res/StringManager;
      16: ldc_w         #262                // String digester.emptyStack
      19: invokevirtual #105                // Method org/apache/tomcat/util/res/StringManager.getString:(Ljava/lang/String;)Ljava/lang/String;
      22: invokeinterface #164,  2          // InterfaceMethod org/apache/juli/logging/Log.warn:(Ljava/lang/Object;)V
      27: aconst_null
      28: areturn
    Exception table:
       from    to  target type
           0     7     8   Class java/util/EmptyStackException

  public java.lang.Object peek(int);
    Code:
       0: aload_0
       1: getfield      #41                 // Field stack:Lorg/apache/tomcat/util/digester/ArrayStack;
       4: iload_1
       5: invokevirtual #263                // Method org/apache/tomcat/util/digester/ArrayStack.peek:(I)Ljava/lang/Object;
       8: areturn
       9: astore_2
      10: aload_0
      11: getfield      #48                 // Field log:Lorg/apache/juli/logging/Log;
      14: getstatic     #71                 // Field sm:Lorg/apache/tomcat/util/res/StringManager;
      17: ldc_w         #262                // String digester.emptyStack
      20: invokevirtual #105                // Method org/apache/tomcat/util/res/StringManager.getString:(Ljava/lang/String;)Ljava/lang/String;
      23: invokeinterface #164,  2          // InterfaceMethod org/apache/juli/logging/Log.warn:(Ljava/lang/Object;)V
      28: aconst_null
      29: areturn
    Exception table:
       from    to  target type
           0     8     9   Class java/util/EmptyStackException

  public java.lang.Object pop();
    Code:
       0: aload_0
       1: getfield      #41                 // Field stack:Lorg/apache/tomcat/util/digester/ArrayStack;
       4: invokevirtual #157                // Method org/apache/tomcat/util/digester/ArrayStack.pop:()Ljava/lang/Object;
       7: areturn
       8: astore_1
       9: aload_0
      10: getfield      #48                 // Field log:Lorg/apache/juli/logging/Log;
      13: getstatic     #71                 // Field sm:Lorg/apache/tomcat/util/res/StringManager;
      16: ldc_w         #262                // String digester.emptyStack
      19: invokevirtual #105                // Method org/apache/tomcat/util/res/StringManager.getString:(Ljava/lang/String;)Ljava/lang/String;
      22: invokeinterface #164,  2          // InterfaceMethod org/apache/juli/logging/Log.warn:(Ljava/lang/Object;)V
      27: aconst_null
      28: areturn
    Exception table:
       from    to  target type
           0     7     8   Class java/util/EmptyStackException

  public void push(java.lang.Object);
    Code:
       0: aload_0
       1: getfield      #41                 // Field stack:Lorg/apache/tomcat/util/digester/ArrayStack;
       4: invokevirtual #92                 // Method org/apache/tomcat/util/digester/ArrayStack.size:()I
       7: ifne          15
      10: aload_0
      11: aload_1
      12: putfield      #39                 // Field root:Ljava/lang/Object;
      15: aload_0
      16: getfield      #41                 // Field stack:Lorg/apache/tomcat/util/digester/ArrayStack;
      19: aload_1
      20: invokevirtual #192                // Method org/apache/tomcat/util/digester/ArrayStack.push:(Ljava/lang/Object;)Ljava/lang/Object;
      23: pop
      24: return

  public java.lang.Object getRoot();
    Code:
       0: aload_0
       1: getfield      #39                 // Field root:Ljava/lang/Object;
       4: areturn

  protected void configure();
    Code:
       0: aload_0
       1: getfield      #24                 // Field configured:Z
       4: ifeq          8
       7: return
       8: aload_0
       9: ldc_w         #264                // String org.apache.tomcat.util.digester.Digester
      12: invokestatic  #50                 // Method org/apache/juli/logging/LogFactory.getLog:(Ljava/lang/String;)Lorg/apache/juli/logging/Log;
      15: putfield      #48                 // Field log:Lorg/apache/juli/logging/Log;
      18: aload_0
      19: ldc           #49                 // String org.apache.tomcat.util.digester.Digester.sax
      21: invokestatic  #50                 // Method org/apache/juli/logging/LogFactory.getLog:(Ljava/lang/String;)Lorg/apache/juli/logging/Log;
      24: putfield      #51                 // Field saxLog:Lorg/apache/juli/logging/Log;
      27: aload_0
      28: iconst_1
      29: putfield      #24                 // Field configured:Z
      32: return

  public java.lang.Object peekParams();
    Code:
       0: aload_0
       1: getfield      #35                 // Field params:Lorg/apache/tomcat/util/digester/ArrayStack;
       4: invokevirtual #87                 // Method org/apache/tomcat/util/digester/ArrayStack.peek:()Ljava/lang/Object;
       7: areturn
       8: astore_1
       9: aload_0
      10: getfield      #48                 // Field log:Lorg/apache/juli/logging/Log;
      13: getstatic     #71                 // Field sm:Lorg/apache/tomcat/util/res/StringManager;
      16: ldc_w         #262                // String digester.emptyStack
      19: invokevirtual #105                // Method org/apache/tomcat/util/res/StringManager.getString:(Ljava/lang/String;)Ljava/lang/String;
      22: invokeinterface #164,  2          // InterfaceMethod org/apache/juli/logging/Log.warn:(Ljava/lang/Object;)V
      27: aconst_null
      28: areturn
    Exception table:
       from    to  target type
           0     7     8   Class java/util/EmptyStackException

  public java.lang.Object popParams();
    Code:
       0: aload_0
       1: getfield      #48                 // Field log:Lorg/apache/juli/logging/Log;
       4: invokeinterface #265,  1          // InterfaceMethod org/apache/juli/logging/Log.isTraceEnabled:()Z
       9: ifeq          24
      12: aload_0
      13: getfield      #48                 // Field log:Lorg/apache/juli/logging/Log;
      16: ldc_w         #266                // String Popping params
      19: invokeinterface #267,  2          // InterfaceMethod org/apache/juli/logging/Log.trace:(Ljava/lang/Object;)V
      24: aload_0
      25: getfield      #35                 // Field params:Lorg/apache/tomcat/util/digester/ArrayStack;
      28: invokevirtual #157                // Method org/apache/tomcat/util/digester/ArrayStack.pop:()Ljava/lang/Object;
      31: areturn
      32: astore_1
      33: aload_0
      34: getfield      #48                 // Field log:Lorg/apache/juli/logging/Log;
      37: getstatic     #71                 // Field sm:Lorg/apache/tomcat/util/res/StringManager;
      40: ldc_w         #262                // String digester.emptyStack
      43: invokevirtual #105                // Method org/apache/tomcat/util/res/StringManager.getString:(Ljava/lang/String;)Ljava/lang/String;
      46: invokeinterface #164,  2          // InterfaceMethod org/apache/juli/logging/Log.warn:(Ljava/lang/Object;)V
      51: aconst_null
      52: areturn
    Exception table:
       from    to  target type
           0    31    32   Class java/util/EmptyStackException

  public void pushParams(java.lang.Object);
    Code:
       0: aload_0
       1: getfield      #48                 // Field log:Lorg/apache/juli/logging/Log;
       4: invokeinterface #265,  1          // InterfaceMethod org/apache/juli/logging/Log.isTraceEnabled:()Z
       9: ifeq          24
      12: aload_0
      13: getfield      #48                 // Field log:Lorg/apache/juli/logging/Log;
      16: ldc_w         #268                // String Pushing params
      19: invokeinterface #267,  2          // InterfaceMethod org/apache/juli/logging/Log.trace:(Ljava/lang/Object;)V
      24: aload_0
      25: getfield      #35                 // Field params:Lorg/apache/tomcat/util/digester/ArrayStack;
      28: aload_1
      29: invokevirtual #192                // Method org/apache/tomcat/util/digester/ArrayStack.push:(Ljava/lang/Object;)Ljava/lang/Object;
      32: pop
      33: return

  public org.xml.sax.SAXException createSAXException(java.lang.String, java.lang.Exception);
    Code:
       0: aload_2
       1: ifnull        52
       4: aload_2
       5: instanceof    #269                // class java/lang/reflect/InvocationTargetException
       8: ifeq          52
      11: aload_2
      12: invokevirtual #270                // Method java/lang/Exception.getCause:()Ljava/lang/Throwable;
      15: astore_3
      16: aload_3
      17: instanceof    #271                // class java/lang/ThreadDeath
      20: ifeq          28
      23: aload_3
      24: checkcast     #271                // class java/lang/ThreadDeath
      27: athrow
      28: aload_3
      29: instanceof    #272                // class java/lang/VirtualMachineError
      32: ifeq          40
      35: aload_3
      36: checkcast     #272                // class java/lang/VirtualMachineError
      39: athrow
      40: aload_3
      41: instanceof    #70                 // class java/lang/Exception
      44: ifeq          52
      47: aload_3
      48: checkcast     #70                 // class java/lang/Exception
      51: astore_2
      52: aload_0
      53: getfield      #30                 // Field locator:Lorg/xml/sax/Locator;
      56: ifnull        138
      59: getstatic     #71                 // Field sm:Lorg/apache/tomcat/util/res/StringManager;
      62: ldc_w         #273                // String digester.errorLocation
      65: iconst_3
      66: anewarray     #73                 // class java/lang/Object
      69: dup
      70: iconst_0
      71: aload_0
      72: getfield      #30                 // Field locator:Lorg/xml/sax/Locator;
      75: invokeinterface #274,  1          // InterfaceMethod org/xml/sax/Locator.getLineNumber:()I
      80: invokestatic  #223                // Method java/lang/Integer.valueOf:(I)Ljava/lang/Integer;
      83: aastore
      84: dup
      85: iconst_1
      86: aload_0
      87: getfield      #30                 // Field locator:Lorg/xml/sax/Locator;
      90: invokeinterface #275,  1          // InterfaceMethod org/xml/sax/Locator.getColumnNumber:()I
      95: invokestatic  #223                // Method java/lang/Integer.valueOf:(I)Ljava/lang/Integer;
      98: aastore
      99: dup
     100: iconst_2
     101: aload_1
     102: aastore
     103: invokevirtual #74                 // Method org/apache/tomcat/util/res/StringManager.getString:(Ljava/lang/String;[Ljava/lang/Object;)Ljava/lang/String;
     106: astore_3
     107: aload_2
     108: ifnull        125
     111: new           #276                // class org/xml/sax/SAXParseException
     114: dup
     115: aload_3
     116: aload_0
     117: getfield      #30                 // Field locator:Lorg/xml/sax/Locator;
     120: aload_2
     121: invokespecial #277                // Method org/xml/sax/SAXParseException."<init>":(Ljava/lang/String;Lorg/xml/sax/Locator;Ljava/lang/Exception;)V
     124: areturn
     125: new           #276                // class org/xml/sax/SAXParseException
     128: dup
     129: aload_3
     130: aload_0
     131: getfield      #30                 // Field locator:Lorg/xml/sax/Locator;
     134: invokespecial #278                // Method org/xml/sax/SAXParseException."<init>":(Ljava/lang/String;Lorg/xml/sax/Locator;)V
     137: areturn
     138: aload_0
     139: getfield      #48                 // Field log:Lorg/apache/juli/logging/Log;
     142: getstatic     #71                 // Field sm:Lorg/apache/tomcat/util/res/StringManager;
     145: ldc_w         #279                // String digester.noLocator
     148: invokevirtual #105                // Method org/apache/tomcat/util/res/StringManager.getString:(Ljava/lang/String;)Ljava/lang/String;
     151: invokeinterface #229,  2          // InterfaceMethod org/apache/juli/logging/Log.error:(Ljava/lang/Object;)V
     156: aload_2
     157: ifnull        170
     160: new           #280                // class org/xml/sax/SAXException
     163: dup
     164: aload_1
     165: aload_2
     166: invokespecial #281                // Method org/xml/sax/SAXException."<init>":(Ljava/lang/String;Ljava/lang/Exception;)V
     169: areturn
     170: new           #280                // class org/xml/sax/SAXException
     173: dup
     174: aload_1
     175: invokespecial #282                // Method org/xml/sax/SAXException."<init>":(Ljava/lang/String;)V
     178: areturn

  public org.xml.sax.SAXException createSAXException(java.lang.Exception);
    Code:
       0: aload_1
       1: instanceof    #269                // class java/lang/reflect/InvocationTargetException
       4: ifeq          48
       7: aload_1
       8: invokevirtual #270                // Method java/lang/Exception.getCause:()Ljava/lang/Throwable;
      11: astore_2
      12: aload_2
      13: instanceof    #271                // class java/lang/ThreadDeath
      16: ifeq          24
      19: aload_2
      20: checkcast     #271                // class java/lang/ThreadDeath
      23: athrow
      24: aload_2
      25: instanceof    #272                // class java/lang/VirtualMachineError
      28: ifeq          36
      31: aload_2
      32: checkcast     #272                // class java/lang/VirtualMachineError
      35: athrow
      36: aload_2
      37: instanceof    #70                 // class java/lang/Exception
      40: ifeq          48
      43: aload_2
      44: checkcast     #70                 // class java/lang/Exception
      47: astore_1
      48: aload_0
      49: aload_1
      50: invokevirtual #283                // Method java/lang/Exception.getMessage:()Ljava/lang/String;
      53: aload_1
      54: invokevirtual #284                // Method createSAXException:(Ljava/lang/String;Ljava/lang/Exception;)Lorg/xml/sax/SAXException;
      57: areturn

  public org.xml.sax.SAXException createSAXException(java.lang.String);
    Code:
       0: aload_0
       1: aload_1
       2: aconst_null
       3: invokevirtual #284                // Method createSAXException:(Ljava/lang/String;Ljava/lang/Exception;)Lorg/xml/sax/SAXException;
       6: areturn

  private org.xml.sax.Attributes updateAttributes(org.xml.sax.Attributes);
    Code:
       0: aload_1
       1: invokeinterface #285,  1          // InterfaceMethod org/xml/sax/Attributes.getLength:()I
       6: ifne          11
       9: aload_1
      10: areturn
      11: new           #286                // class org/xml/sax/helpers/AttributesImpl
      14: dup
      15: aload_1
      16: invokespecial #287                // Method org/xml/sax/helpers/AttributesImpl."<init>":(Lorg/xml/sax/Attributes;)V
      19: astore_2
      20: aload_2
      21: invokevirtual #288                // Method org/xml/sax/helpers/AttributesImpl.getLength:()I
      24: istore_3
      25: iconst_0
      26: istore        4
      28: iload         4
      30: iload_3
      31: if_icmpge     114
      34: aload_2
      35: iload         4
      37: invokevirtual #289                // Method org/xml/sax/helpers/AttributesImpl.getValue:(I)Ljava/lang/String;
      40: astore        5
      42: aload_2
      43: iload         4
      45: aload         5
      47: aconst_null
      48: aload_0
      49: getfield      #14                 // Field source:[Lorg/apache/tomcat/util/IntrospectionUtils$PropertySource;
      52: aload_0
      53: invokevirtual #290                // Method getClassLoader:()Ljava/lang/ClassLoader;
      56: invokestatic  #67                 // Method org/apache/tomcat/util/IntrospectionUtils.replaceProperties:(Ljava/lang/String;Ljava/util/Hashtable;[Lorg/apache/tomcat/util/IntrospectionUtils$PropertySource;Ljava/lang/ClassLoader;)Ljava/lang/String;
      59: invokevirtual #159                // Method java/lang/String.intern:()Ljava/lang/String;
      62: invokevirtual #291                // Method org/xml/sax/helpers/AttributesImpl.setValue:(ILjava/lang/String;)V
      65: goto          108
      68: astore        6
      70: aload_0
      71: getfield      #48                 // Field log:Lorg/apache/juli/logging/Log;
      74: getstatic     #71                 // Field sm:Lorg/apache/tomcat/util/res/StringManager;
      77: ldc_w         #292                // String digester.failedToUpdateAttributes
      80: iconst_2
      81: anewarray     #73                 // class java/lang/Object
      84: dup
      85: iconst_0
      86: aload_2
      87: iload         4
      89: invokevirtual #293                // Method org/xml/sax/helpers/AttributesImpl.getLocalName:(I)Ljava/lang/String;
      92: aastore
      93: dup
      94: iconst_1
      95: aload         5
      97: aastore
      98: invokevirtual #74                 // Method org/apache/tomcat/util/res/StringManager.getString:(Ljava/lang/String;[Ljava/lang/Object;)Ljava/lang/String;
     101: aload         6
     103: invokeinterface #75,  3           // InterfaceMethod org/apache/juli/logging/Log.warn:(Ljava/lang/Object;Ljava/lang/Throwable;)V
     108: iinc          4, 1
     111: goto          28
     114: aload_2
     115: areturn
    Exception table:
       from    to  target type
          42    65    68   Class java/lang/Exception

  private java.lang.StringBuilder updateBodyText(java.lang.StringBuilder);
    Code:
       0: aload_1
       1: invokevirtual #85                 // Method java/lang/StringBuilder.toString:()Ljava/lang/String;
       4: astore_2
       5: aload_2
       6: aconst_null
       7: aload_0
       8: getfield      #14                 // Field source:[Lorg/apache/tomcat/util/IntrospectionUtils$PropertySource;
      11: aload_0
      12: invokevirtual #290                // Method getClassLoader:()Ljava/lang/ClassLoader;
      15: invokestatic  #67                 // Method org/apache/tomcat/util/IntrospectionUtils.replaceProperties:(Ljava/lang/String;Ljava/util/Hashtable;[Lorg/apache/tomcat/util/IntrospectionUtils$PropertySource;Ljava/lang/ClassLoader;)Ljava/lang/String;
      18: astore_3
      19: goto          26
      22: astore        4
      24: aload_1
      25: areturn
      26: aload_3
      27: aload_2
      28: if_acmpne     33
      31: aload_1
      32: areturn
      33: new           #15                 // class java/lang/StringBuilder
      36: dup
      37: aload_3
      38: invokespecial #193                // Method java/lang/StringBuilder."<init>":(Ljava/lang/String;)V
      41: areturn
    Exception table:
       from    to  target type
           5    19    22   Class java/lang/Exception

  static {};
    Code:
       0: iconst_0
       1: putstatic     #1                  // Field propertySourcesSet:Z
       4: ldc           #46                 // class org/apache/tomcat/util/digester/Digester
       6: invokestatic  #294                // Method org/apache/tomcat/util/res/StringManager.getManager:(Ljava/lang/Class;)Lorg/apache/tomcat/util/res/StringManager;
       9: putstatic     #71                 // Field sm:Lorg/apache/tomcat/util/res/StringManager;
      12: ldc_w         #295                // String org.apache.tomcat.util.digester.PROPERTY_SOURCE
      15: invokestatic  #66                 // Method java/lang/System.getProperty:(Ljava/lang/String;)Ljava/lang/String;
      18: astore_0
      19: new           #53                 // class java/util/ArrayList
      22: dup
      23: invokespecial #54                 // Method java/util/ArrayList."<init>":()V
      26: astore_1
      27: aconst_null
      28: astore_2
      29: aload_0
      30: ifnull        204
      33: new           #296                // class java/util/StringTokenizer
      36: dup
      37: aload_0
      38: ldc           #150                // String ,
      40: invokespecial #297                // Method java/util/StringTokenizer."<init>":(Ljava/lang/String;Ljava/lang/String;)V
      43: astore_3
      44: aload_3
      45: invokevirtual #298                // Method java/util/StringTokenizer.hasMoreTokens:()Z
      48: ifeq          192
      51: aload_3
      52: invokevirtual #299                // Method java/util/StringTokenizer.nextToken:()Ljava/lang/String;
      55: invokevirtual #300                // Method java/lang/String.trim:()Ljava/lang/String;
      58: astore        4
      60: iconst_2
      61: anewarray     #301                // class java/lang/ClassLoader
      64: dup
      65: iconst_0
      66: ldc           #46                 // class org/apache/tomcat/util/digester/Digester
      68: invokevirtual #91                 // Method java/lang/Class.getClassLoader:()Ljava/lang/ClassLoader;
      71: aastore
      72: dup
      73: iconst_1
      74: invokestatic  #89                 // Method java/lang/Thread.currentThread:()Ljava/lang/Thread;
      77: invokevirtual #90                 // Method java/lang/Thread.getContextClassLoader:()Ljava/lang/ClassLoader;
      80: aastore
      81: astore        5
      83: aload         5
      85: astore        6
      87: aload         6
      89: arraylength
      90: istore        7
      92: iconst_0
      93: istore        8
      95: iload         8
      97: iload         7
      99: if_icmpge     189
     102: aload         6
     104: iload         8
     106: aaload
     107: astore        9
     109: aload         4
     111: iconst_1
     112: aload         9
     114: invokestatic  #302                // Method java/lang/Class.forName:(Ljava/lang/String;ZLjava/lang/ClassLoader;)Ljava/lang/Class;
     117: astore        10
     119: aload_1
     120: aload         10
     122: iconst_0
     123: anewarray     #303                // class java/lang/Class
     126: invokevirtual #304                // Method java/lang/Class.getConstructor:([Ljava/lang/Class;)Ljava/lang/reflect/Constructor;
     129: iconst_0
     130: anewarray     #73                 // class java/lang/Object
     133: invokevirtual #305                // Method java/lang/reflect/Constructor.newInstance:([Ljava/lang/Object;)Ljava/lang/Object;
     136: checkcast     #2                  // class org/apache/tomcat/util/IntrospectionUtils$PropertySource
     139: invokevirtual #58                 // Method java/util/ArrayList.add:(Ljava/lang/Object;)Z
     142: pop
     143: goto          189
     146: astore        10
     148: aload         10
     150: invokestatic  #307                // Method org/apache/tomcat/util/ExceptionUtils.handleThrowable:(Ljava/lang/Throwable;)V
     153: ldc           #46                 // class org/apache/tomcat/util/digester/Digester
     155: invokestatic  #47                 // Method org/apache/juli/logging/LogFactory.getLog:(Ljava/lang/Class;)Lorg/apache/juli/logging/Log;
     158: getstatic     #71                 // Field sm:Lorg/apache/tomcat/util/res/StringManager;
     161: ldc_w         #308                // String digester.propertySourceLoadError
     164: iconst_1
     165: anewarray     #73                 // class java/lang/Object
     168: dup
     169: iconst_0
     170: aload         4
     172: aastore
     173: invokevirtual #74                 // Method org/apache/tomcat/util/res/StringManager.getString:(Ljava/lang/String;[Ljava/lang/Object;)Ljava/lang/String;
     176: aload         10
     178: invokeinterface #106,  3          // InterfaceMethod org/apache/juli/logging/Log.error:(Ljava/lang/Object;Ljava/lang/Throwable;)V
     183: iinc          8, 1
     186: goto          95
     189: goto          44
     192: aload_1
     193: iconst_0
     194: anewarray     #2                  // class org/apache/tomcat/util/IntrospectionUtils$PropertySource
     197: invokevirtual #59                 // Method java/util/ArrayList.toArray:([Ljava/lang/Object;)[Ljava/lang/Object;
     200: checkcast     #60                 // class "[Lorg/apache/tomcat/util/IntrospectionUtils$PropertySource;"
     203: astore_2
     204: aload_2
     205: ifnull        216
     208: aload_2
     209: putstatic     #3                  // Field propertySources:[Lorg/apache/tomcat/util/IntrospectionUtils$PropertySource;
     212: iconst_1
     213: putstatic     #1                  // Field propertySourcesSet:Z
     216: ldc_w         #309                // String org.apache.tomcat.util.digester.REPLACE_SYSTEM_PROPERTIES
     219: invokestatic  #310                // Method java/lang/Boolean.getBoolean:(Ljava/lang/String;)Z
     222: ifeq          228
     225: invokestatic  #311                // Method replaceSystemProperties:()V
     228: new           #312                // class java/util/HashSet
     231: dup
     232: invokespecial #313                // Method java/util/HashSet."<init>":()V
     235: putstatic     #4                  // Field generatedClasses:Ljava/util/HashSet;
     238: return
    Exception table:
       from    to  target type
         109   143   146   Class java/lang/Throwable
}
