Compiled from "FunctionClassKind.kt"
public final class kotlin.reflect.jvm.internal.impl.builtins.functions.FunctionClassKind$Companion {
  private kotlin.reflect.jvm.internal.impl.builtins.functions.FunctionClassKind$Companion();
    Code:
       0: aload_0
       1: invokespecial #20                 // Method java/lang/Object."<init>":()V
       4: return

  public final kotlin.reflect.jvm.internal.impl.builtins.functions.FunctionClassKind getFunctionClassKind(kotlin.reflect.jvm.internal.impl.builtins.functions.FunctionTypeKind);
    Code:
       0: aload_1
       1: ldc           #1                  // String functionTypeKind
       3: invokestatic  #22                 // Method kotlin/jvm/internal/Intrinsics.checkNotNullParameter:(Ljava/lang/Object;Ljava/lang/String;)V
       6: aload_1
       7: astore_2
       8: aload_2
       9: getstatic     #16                 // Field kotlin/reflect/jvm/internal/impl/builtins/functions/FunctionTypeKind$Function.INSTANCE:Lkotlin/reflect/jvm/internal/impl/builtins/functions/FunctionTypeKind$Function;
      12: invokestatic  #21                 // Method kotlin/jvm/internal/Intrinsics.areEqual:(Ljava/lang/Object;Ljava/lang/Object;)Z
      15: ifeq          24
      18: getstatic     #11                 // Field kotlin/reflect/jvm/internal/impl/builtins/functions/FunctionClassKind.Function:Lkotlin/reflect/jvm/internal/impl/builtins/functions/FunctionClassKind;
      21: goto          75
      24: aload_2
      25: getstatic     #19                 // Field kotlin/reflect/jvm/internal/impl/builtins/functions/FunctionTypeKind$SuspendFunction.INSTANCE:Lkotlin/reflect/jvm/internal/impl/builtins/functions/FunctionTypeKind$SuspendFunction;
      28: invokestatic  #21                 // Method kotlin/jvm/internal/Intrinsics.areEqual:(Ljava/lang/Object;Ljava/lang/Object;)Z
      31: ifeq          40
      34: getstatic     #14                 // Field kotlin/reflect/jvm/internal/impl/builtins/functions/FunctionClassKind.SuspendFunction:Lkotlin/reflect/jvm/internal/impl/builtins/functions/FunctionClassKind;
      37: goto          75
      40: aload_2
      41: getstatic     #17                 // Field kotlin/reflect/jvm/internal/impl/builtins/functions/FunctionTypeKind$KFunction.INSTANCE:Lkotlin/reflect/jvm/internal/impl/builtins/functions/FunctionTypeKind$KFunction;
      44: invokestatic  #21                 // Method kotlin/jvm/internal/Intrinsics.areEqual:(Ljava/lang/Object;Ljava/lang/Object;)Z
      47: ifeq          56
      50: getstatic     #12                 // Field kotlin/reflect/jvm/internal/impl/builtins/functions/FunctionClassKind.KFunction:Lkotlin/reflect/jvm/internal/impl/builtins/functions/FunctionClassKind;
      53: goto          75
      56: aload_2
      57: getstatic     #18                 // Field kotlin/reflect/jvm/internal/impl/builtins/functions/FunctionTypeKind$KSuspendFunction.INSTANCE:Lkotlin/reflect/jvm/internal/impl/builtins/functions/FunctionTypeKind$KSuspendFunction;
      60: invokestatic  #21                 // Method kotlin/jvm/internal/Intrinsics.areEqual:(Ljava/lang/Object;Ljava/lang/Object;)Z
      63: ifeq          72
      66: getstatic     #13                 // Field kotlin/reflect/jvm/internal/impl/builtins/functions/FunctionClassKind.KSuspendFunction:Lkotlin/reflect/jvm/internal/impl/builtins/functions/FunctionClassKind;
      69: goto          75
      72: getstatic     #15                 // Field kotlin/reflect/jvm/internal/impl/builtins/functions/FunctionClassKind.UNKNOWN:Lkotlin/reflect/jvm/internal/impl/builtins/functions/FunctionClassKind;
      75: areturn

  public kotlin.reflect.jvm.internal.impl.builtins.functions.FunctionClassKind$Companion(kotlin.jvm.internal.DefaultConstructorMarker);
    Code:
       0: aload_0
       1: invokespecial #23                 // Method "<init>":()V
       4: return
}
