Compiled from "ScopedPreferenceStore.java"
public class org.eclipse.ui.preferences.ScopedPreferenceStore extends org.eclipse.core.commands.common.EventManager implements org.eclipse.jface.preference.IPreferenceStore,org.eclipse.jface.preference.IPersistentPreferenceStore {
  private org.eclipse.core.runtime.preferences.IScopeContext storeContext;

  private org.eclipse.core.runtime.preferences.IScopeContext[] searchContexts;

  protected boolean silentRunning;

  org.eclipse.core.runtime.preferences.IEclipsePreferences$IPreferenceChangeListener preferencesListener;

  private org.eclipse.core.runtime.preferences.IScopeContext defaultContext;

  java.lang.String nodeQualifier;

  java.lang.String defaultQualifier;

  private boolean dirty;

  public org.eclipse.ui.preferences.ScopedPreferenceStore(org.eclipse.core.runtime.preferences.IScopeContext, java.lang.String, java.lang.String);
    Code:
       0: aload_0
       1: aload_1
       2: aload_2
       3: invokespecial #412                // Method "<init>":(Lorg/eclipse/core/runtime/preferences/IScopeContext;Ljava/lang/String;)V
       6: aload_0
       7: aload_3
       8: putfield      #358                // Field defaultQualifier:Ljava/lang/String;
      11: return

  public org.eclipse.ui.preferences.ScopedPreferenceStore(org.eclipse.core.runtime.preferences.IScopeContext, java.lang.String);
    Code:
       0: aload_0
       1: invokespecial #379                // Method org/eclipse/core/commands/common/EventManager."<init>":()V
       4: aload_0
       5: iconst_0
       6: putfield      #357                // Field silentRunning:Z
       9: aload_0
      10: getstatic     #354                // Field org/eclipse/core/runtime/preferences/DefaultScope.INSTANCE:Lorg/eclipse/core/runtime/preferences/IScopeContext;
      13: putfield      #361                // Field defaultContext:Lorg/eclipse/core/runtime/preferences/IScopeContext;
      16: aload_0
      17: aload_1
      18: putfield      #362                // Field storeContext:Lorg/eclipse/core/runtime/preferences/IScopeContext;
      21: aload_0
      22: aload_2
      23: putfield      #359                // Field nodeQualifier:Ljava/lang/String;
      26: aload_0
      27: aload_2
      28: putfield      #358                // Field defaultQualifier:Ljava/lang/String;
      31: aload_0
      32: invokevirtual #405                // Method getStorePreferences:()Lorg/eclipse/core/runtime/preferences/IEclipsePreferences;
      35: invokeinterface #434,  1          // InterfaceMethod org/eclipse/core/runtime/preferences/IEclipsePreferences.parent:()Lorg/osgi/service/prefs/Preferences;
      40: checkcast     #182                // class org/eclipse/core/runtime/preferences/IEclipsePreferences
      43: aload_0
      44: invokevirtual #407                // Method getNodeChangeListener:()Lorg/eclipse/core/runtime/preferences/IEclipsePreferences$INodeChangeListener;
      47: invokeinterface #431,  2          // InterfaceMethod org/eclipse/core/runtime/preferences/IEclipsePreferences.addNodeChangeListener:(Lorg/eclipse/core/runtime/preferences/IEclipsePreferences$INodeChangeListener;)V
      52: return

  private org.eclipse.core.runtime.preferences.IEclipsePreferences$INodeChangeListener getNodeChangeListener();
    Code:
       0: new           #195                // class org/eclipse/ui/preferences/ScopedPreferenceStore$1
       3: dup
       4: aload_0
       5: invokespecial #415                // Method org/eclipse/ui/preferences/ScopedPreferenceStore$1."<init>":(Lorg/eclipse/ui/preferences/ScopedPreferenceStore;)V
       8: areturn

  private void initializePreferencesListener();
    Code:
       0: aload_0
       1: getfield      #360                // Field preferencesListener:Lorg/eclipse/core/runtime/preferences/IEclipsePreferences$IPreferenceChangeListener;
       4: ifnonnull     30
       7: aload_0
       8: aload_0
       9: invokedynamic #444,  0            // InvokeDynamic #0:preferenceChange:(Lorg/eclipse/ui/preferences/ScopedPreferenceStore;)Lorg/eclipse/core/runtime/preferences/IEclipsePreferences$IPreferenceChangeListener;
      14: putfield      #360                // Field preferencesListener:Lorg/eclipse/core/runtime/preferences/IEclipsePreferences$IPreferenceChangeListener;
      17: aload_0
      18: invokevirtual #405                // Method getStorePreferences:()Lorg/eclipse/core/runtime/preferences/IEclipsePreferences;
      21: aload_0
      22: getfield      #360                // Field preferencesListener:Lorg/eclipse/core/runtime/preferences/IEclipsePreferences$IPreferenceChangeListener;
      25: invokeinterface #432,  2          // InterfaceMethod org/eclipse/core/runtime/preferences/IEclipsePreferences.addPreferenceChangeListener:(Lorg/eclipse/core/runtime/preferences/IEclipsePreferences$IPreferenceChangeListener;)V
      30: return

  java.lang.Object getDefault(java.lang.String, java.lang.Object);
    Code:
       0: aload_0
       1: invokevirtual #404                // Method getDefaultPreferences:()Lorg/eclipse/core/runtime/preferences/IEclipsePreferences;
       4: astore_3
       5: aload_2
       6: instanceof    #172                // class java/lang/String
       9: ifeq          22
      12: aload_3
      13: aload_1
      14: ldc           #1                  // String
      16: invokeinterface #437,  3          // InterfaceMethod org/eclipse/core/runtime/preferences/IEclipsePreferences.get:(Ljava/lang/String;Ljava/lang/String;)Ljava/lang/String;
      21: areturn
      22: aload_2
      23: instanceof    #168                // class java/lang/Integer
      26: ifeq          41
      29: aload_3
      30: aload_1
      31: iconst_0
      32: invokeinterface #425,  3          // InterfaceMethod org/eclipse/core/runtime/preferences/IEclipsePreferences.getInt:(Ljava/lang/String;I)I
      37: invokestatic  #371                // Method java/lang/Integer.valueOf:(I)Ljava/lang/Integer;
      40: areturn
      41: aload_2
      42: instanceof    #166                // class java/lang/Double
      45: ifeq          60
      48: aload_3
      49: aload_1
      50: dconst_0
      51: invokeinterface #421,  4          // InterfaceMethod org/eclipse/core/runtime/preferences/IEclipsePreferences.getDouble:(Ljava/lang/String;D)D
      56: invokestatic  #367                // Method java/lang/Double.valueOf:(D)Ljava/lang/Double;
      59: areturn
      60: aload_2
      61: instanceof    #167                // class java/lang/Float
      64: ifeq          79
      67: aload_3
      68: aload_1
      69: fconst_0
      70: invokeinterface #423,  3          // InterfaceMethod org/eclipse/core/runtime/preferences/IEclipsePreferences.getFloat:(Ljava/lang/String;F)F
      75: invokestatic  #369                // Method java/lang/Float.valueOf:(F)Ljava/lang/Float;
      78: areturn
      79: aload_2
      80: instanceof    #169                // class java/lang/Long
      83: ifeq          98
      86: aload_3
      87: aload_1
      88: lconst_0
      89: invokeinterface #427,  4          // InterfaceMethod org/eclipse/core/runtime/preferences/IEclipsePreferences.getLong:(Ljava/lang/String;J)J
      94: invokestatic  #373                // Method java/lang/Long.valueOf:(J)Ljava/lang/Long;
      97: areturn
      98: aload_2
      99: instanceof    #165                // class java/lang/Boolean
     102: ifeq          126
     105: aload_3
     106: aload_1
     107: iconst_0
     108: invokeinterface #430,  3          // InterfaceMethod org/eclipse/core/runtime/preferences/IEclipsePreferences.getBoolean:(Ljava/lang/String;Z)Z
     113: ifeq          122
     116: getstatic     #353                // Field java/lang/Boolean.TRUE:Ljava/lang/Boolean;
     119: goto          125
     122: getstatic     #352                // Field java/lang/Boolean.FALSE:Ljava/lang/Boolean;
     125: areturn
     126: aconst_null
     127: areturn

  org.eclipse.core.runtime.preferences.IEclipsePreferences getStorePreferences();
    Code:
       0: aload_0
       1: getfield      #362                // Field storeContext:Lorg/eclipse/core/runtime/preferences/IScopeContext;
       4: aload_0
       5: getfield      #359                // Field nodeQualifier:Ljava/lang/String;
       8: invokeinterface #440,  2          // InterfaceMethod org/eclipse/core/runtime/preferences/IScopeContext.getNode:(Ljava/lang/String;)Lorg/eclipse/core/runtime/preferences/IEclipsePreferences;
      13: areturn

  private org.eclipse.core.runtime.preferences.IEclipsePreferences getDefaultPreferences();
    Code:
       0: aload_0
       1: getfield      #361                // Field defaultContext:Lorg/eclipse/core/runtime/preferences/IScopeContext;
       4: aload_0
       5: getfield      #358                // Field defaultQualifier:Ljava/lang/String;
       8: invokeinterface #440,  2          // InterfaceMethod org/eclipse/core/runtime/preferences/IScopeContext.getNode:(Ljava/lang/String;)Lorg/eclipse/core/runtime/preferences/IEclipsePreferences;
      13: areturn

  public void addPropertyChangeListener(org.eclipse.jface.util.IPropertyChangeListener);
    Code:
       0: aload_0
       1: invokevirtual #389                // Method initializePreferencesListener:()V
       4: aload_0
       5: aload_1
       6: invokevirtual #392                // Method addListenerObject:(Ljava/lang/Object;)V
       9: return

  public org.eclipse.core.runtime.preferences.IEclipsePreferences[] getPreferenceNodes(boolean);
    Code:
       0: aload_0
       1: getfield      #363                // Field searchContexts:[Lorg/eclipse/core/runtime/preferences/IScopeContext;
       4: ifnonnull     42
       7: iload_1
       8: ifeq          30
      11: iconst_2
      12: anewarray     #182                // class org/eclipse/core/runtime/preferences/IEclipsePreferences
      15: dup
      16: iconst_0
      17: aload_0
      18: invokevirtual #405                // Method getStorePreferences:()Lorg/eclipse/core/runtime/preferences/IEclipsePreferences;
      21: aastore
      22: dup
      23: iconst_1
      24: aload_0
      25: invokevirtual #404                // Method getDefaultPreferences:()Lorg/eclipse/core/runtime/preferences/IEclipsePreferences;
      28: aastore
      29: areturn
      30: iconst_1
      31: anewarray     #182                // class org/eclipse/core/runtime/preferences/IEclipsePreferences
      34: dup
      35: iconst_0
      36: aload_0
      37: invokevirtual #405                // Method getStorePreferences:()Lorg/eclipse/core/runtime/preferences/IEclipsePreferences;
      40: aastore
      41: areturn
      42: aload_0
      43: getfield      #363                // Field searchContexts:[Lorg/eclipse/core/runtime/preferences/IScopeContext;
      46: arraylength
      47: istore_2
      48: iload_1
      49: ifeq          55
      52: iinc          2, 1
      55: iload_2
      56: anewarray     #182                // class org/eclipse/core/runtime/preferences/IEclipsePreferences
      59: astore_3
      60: iconst_0
      61: istore        4
      63: goto          89
      66: aload_3
      67: iload         4
      69: aload_0
      70: getfield      #363                // Field searchContexts:[Lorg/eclipse/core/runtime/preferences/IScopeContext;
      73: iload         4
      75: aaload
      76: aload_0
      77: getfield      #359                // Field nodeQualifier:Ljava/lang/String;
      80: invokeinterface #440,  2          // InterfaceMethod org/eclipse/core/runtime/preferences/IScopeContext.getNode:(Ljava/lang/String;)Lorg/eclipse/core/runtime/preferences/IEclipsePreferences;
      85: aastore
      86: iinc          4, 1
      89: iload         4
      91: aload_0
      92: getfield      #363                // Field searchContexts:[Lorg/eclipse/core/runtime/preferences/IScopeContext;
      95: arraylength
      96: if_icmplt     66
      99: iload_1
     100: ifeq          112
     103: aload_3
     104: iload_2
     105: iconst_1
     106: isub
     107: aload_0
     108: invokevirtual #404                // Method getDefaultPreferences:()Lorg/eclipse/core/runtime/preferences/IEclipsePreferences;
     111: aastore
     112: aload_3
     113: areturn

  public void setSearchContexts(org.eclipse.core.runtime.preferences.IScopeContext[]);
    Code:
       0: aload_0
       1: aload_1
       2: putfield      #363                // Field searchContexts:[Lorg/eclipse/core/runtime/preferences/IScopeContext;
       5: aload_1
       6: ifnonnull     10
       9: return
      10: aload_1
      11: dup
      12: astore        5
      14: arraylength
      15: istore        4
      17: iconst_0
      18: istore_3
      19: goto          49
      22: aload         5
      24: iload_3
      25: aaload
      26: astore_2
      27: aload_2
      28: aload_0
      29: getfield      #361                // Field defaultContext:Lorg/eclipse/core/runtime/preferences/IScopeContext;
      32: invokevirtual #375                // Method java/lang/Object.equals:(Ljava/lang/Object;)Z
      35: ifeq          46
      38: iconst_0
      39: getstatic     #355                // Field org/eclipse/ui/internal/WorkbenchMessages.ScopedPreferenceStore_DefaultAddedError:Ljava/lang/String;
      42: invokestatic  #380                // Method org/eclipse/core/runtime/Assert.isTrue:(ZLjava/lang/String;)Z
      45: pop
      46: iinc          3, 1
      49: iload_3
      50: iload         4
      52: if_icmplt     22
      55: return

  public boolean contains(java.lang.String);
    Code:
       0: aload_1
       1: ifnonnull     6
       4: iconst_0
       5: ireturn
       6: invokestatic  #381                // Method org/eclipse/core/runtime/Platform.getPreferencesService:()Lorg/eclipse/core/runtime/preferences/IPreferencesService;
       9: aload_1
      10: aconst_null
      11: aload_0
      12: iconst_1
      13: invokevirtual #406                // Method getPreferenceNodes:(Z)[Lorg/eclipse/core/runtime/preferences/IEclipsePreferences;
      16: invokeinterface #439,  4          // InterfaceMethod org/eclipse/core/runtime/preferences/IPreferencesService.get:(Ljava/lang/String;Ljava/lang/String;[Lorg/osgi/service/prefs/Preferences;)Ljava/lang/String;
      21: ifnull        26
      24: iconst_1
      25: ireturn
      26: iconst_0
      27: ireturn

  public void firePropertyChangeEvent(java.lang.String, java.lang.Object, java.lang.Object);
    Code:
       0: aload_0
       1: invokevirtual #391                // Method getListeners:()[Ljava/lang/Object;
       4: astore        4
       6: aload         4
       8: arraylength
       9: ifne          13
      12: return
      13: new           #192                // class org/eclipse/jface/util/PropertyChangeEvent
      16: dup
      17: aload_0
      18: aload_1
      19: aload_2
      20: aload_3
      21: invokespecial #387                // Method org/eclipse/jface/util/PropertyChangeEvent."<init>":(Ljava/lang/Object;Ljava/lang/String;Ljava/lang/Object;Ljava/lang/Object;)V
      24: astore        5
      26: aload         4
      28: dup
      29: astore        9
      31: arraylength
      32: istore        8
      34: iconst_0
      35: istore        7
      37: goto          77
      40: aload         9
      42: iload         7
      44: aaload
      45: astore        6
      47: aload         6
      49: checkcast     #191                // class org/eclipse/jface/util/IPropertyChangeListener
      52: astore        10
      54: new           #196                // class org/eclipse/ui/preferences/ScopedPreferenceStore$2
      57: dup
      58: aload_0
      59: ldc           #2                  // String PreferenceStore.changeError
      61: invokestatic  #386                // Method org/eclipse/jface/resource/JFaceResources.getString:(Ljava/lang/String;)Ljava/lang/String;
      64: aload         10
      66: aload         5
      68: invokespecial #416                // Method org/eclipse/ui/preferences/ScopedPreferenceStore$2."<init>":(Lorg/eclipse/ui/preferences/ScopedPreferenceStore;Ljava/lang/String;Lorg/eclipse/jface/util/IPropertyChangeListener;Lorg/eclipse/jface/util/PropertyChangeEvent;)V
      71: invokestatic  #382                // Method org/eclipse/core/runtime/SafeRunner.run:(Lorg/eclipse/core/runtime/ISafeRunnable;)V
      74: iinc          7, 1
      77: iload         7
      79: iload         8
      81: if_icmplt     40
      84: return

  public boolean getBoolean(java.lang.String);
    Code:
       0: aload_0
       1: aload_1
       2: invokevirtual #411                // Method internalGet:(Ljava/lang/String;)Ljava/lang/String;
       5: astore_2
       6: aload_2
       7: ifnonnull     14
      10: iconst_0
      11: goto          21
      14: aload_2
      15: invokestatic  #366                // Method java/lang/Boolean.valueOf:(Ljava/lang/String;)Ljava/lang/Boolean;
      18: invokevirtual #365                // Method java/lang/Boolean.booleanValue:()Z
      21: ireturn

  public boolean getDefaultBoolean(java.lang.String);
    Code:
       0: aload_0
       1: invokevirtual #404                // Method getDefaultPreferences:()Lorg/eclipse/core/runtime/preferences/IEclipsePreferences;
       4: aload_1
       5: iconst_0
       6: invokeinterface #430,  3          // InterfaceMethod org/eclipse/core/runtime/preferences/IEclipsePreferences.getBoolean:(Ljava/lang/String;Z)Z
      11: ireturn

  public double getDefaultDouble(java.lang.String);
    Code:
       0: aload_0
       1: invokevirtual #404                // Method getDefaultPreferences:()Lorg/eclipse/core/runtime/preferences/IEclipsePreferences;
       4: aload_1
       5: dconst_0
       6: invokeinterface #421,  4          // InterfaceMethod org/eclipse/core/runtime/preferences/IEclipsePreferences.getDouble:(Ljava/lang/String;D)D
      11: dreturn

  public float getDefaultFloat(java.lang.String);
    Code:
       0: aload_0
       1: invokevirtual #404                // Method getDefaultPreferences:()Lorg/eclipse/core/runtime/preferences/IEclipsePreferences;
       4: aload_1
       5: fconst_0
       6: invokeinterface #423,  3          // InterfaceMethod org/eclipse/core/runtime/preferences/IEclipsePreferences.getFloat:(Ljava/lang/String;F)F
      11: freturn

  public int getDefaultInt(java.lang.String);
    Code:
       0: aload_0
       1: invokevirtual #404                // Method getDefaultPreferences:()Lorg/eclipse/core/runtime/preferences/IEclipsePreferences;
       4: aload_1
       5: iconst_0
       6: invokeinterface #425,  3          // InterfaceMethod org/eclipse/core/runtime/preferences/IEclipsePreferences.getInt:(Ljava/lang/String;I)I
      11: ireturn

  public long getDefaultLong(java.lang.String);
    Code:
       0: aload_0
       1: invokevirtual #404                // Method getDefaultPreferences:()Lorg/eclipse/core/runtime/preferences/IEclipsePreferences;
       4: aload_1
       5: lconst_0
       6: invokeinterface #427,  4          // InterfaceMethod org/eclipse/core/runtime/preferences/IEclipsePreferences.getLong:(Ljava/lang/String;J)J
      11: lreturn

  public java.lang.String getDefaultString(java.lang.String);
    Code:
       0: aload_0
       1: invokevirtual #404                // Method getDefaultPreferences:()Lorg/eclipse/core/runtime/preferences/IEclipsePreferences;
       4: aload_1
       5: ldc           #1                  // String
       7: invokeinterface #437,  3          // InterfaceMethod org/eclipse/core/runtime/preferences/IEclipsePreferences.get:(Ljava/lang/String;Ljava/lang/String;)Ljava/lang/String;
      12: areturn

  public double getDouble(java.lang.String);
    Code:
       0: aload_0
       1: aload_1
       2: invokevirtual #411                // Method internalGet:(Ljava/lang/String;)Ljava/lang/String;
       5: astore_2
       6: aload_2
       7: ifnonnull     12
      10: dconst_0
      11: dreturn
      12: aload_2
      13: invokestatic  #368                // Method java/lang/Double.parseDouble:(Ljava/lang/String;)D
      16: dreturn
      17: pop
      18: dconst_0
      19: dreturn
    Exception table:
       from    to  target type
          12    16    17   Class java/lang/NumberFormatException

  private java.lang.String internalGet(java.lang.String);
    Code:
       0: invokestatic  #381                // Method org/eclipse/core/runtime/Platform.getPreferencesService:()Lorg/eclipse/core/runtime/preferences/IPreferencesService;
       3: aload_1
       4: aconst_null
       5: aload_0
       6: iconst_1
       7: invokevirtual #406                // Method getPreferenceNodes:(Z)[Lorg/eclipse/core/runtime/preferences/IEclipsePreferences;
      10: invokeinterface #439,  4          // InterfaceMethod org/eclipse/core/runtime/preferences/IPreferencesService.get:(Ljava/lang/String;Ljava/lang/String;[Lorg/osgi/service/prefs/Preferences;)Ljava/lang/String;
      15: areturn

  public float getFloat(java.lang.String);
    Code:
       0: aload_0
       1: aload_1
       2: invokevirtual #411                // Method internalGet:(Ljava/lang/String;)Ljava/lang/String;
       5: astore_2
       6: aload_2
       7: ifnonnull     12
      10: fconst_0
      11: freturn
      12: aload_2
      13: invokestatic  #370                // Method java/lang/Float.parseFloat:(Ljava/lang/String;)F
      16: freturn
      17: pop
      18: fconst_0
      19: freturn
    Exception table:
       from    to  target type
          12    16    17   Class java/lang/NumberFormatException

  public int getInt(java.lang.String);
    Code:
       0: aload_0
       1: aload_1
       2: invokevirtual #411                // Method internalGet:(Ljava/lang/String;)Ljava/lang/String;
       5: astore_2
       6: aload_2
       7: ifnonnull     12
      10: iconst_0
      11: ireturn
      12: aload_2
      13: invokestatic  #372                // Method java/lang/Integer.parseInt:(Ljava/lang/String;)I
      16: ireturn
      17: pop
      18: iconst_0
      19: ireturn
    Exception table:
       from    to  target type
          12    16    17   Class java/lang/NumberFormatException

  public long getLong(java.lang.String);
    Code:
       0: aload_0
       1: aload_1
       2: invokevirtual #411                // Method internalGet:(Ljava/lang/String;)Ljava/lang/String;
       5: astore_2
       6: aload_2
       7: ifnonnull     12
      10: lconst_0
      11: lreturn
      12: aload_2
      13: invokestatic  #374                // Method java/lang/Long.parseLong:(Ljava/lang/String;)J
      16: lreturn
      17: pop
      18: lconst_0
      19: lreturn
    Exception table:
       from    to  target type
          12    16    17   Class java/lang/NumberFormatException

  public java.lang.String getString(java.lang.String);
    Code:
       0: aload_0
       1: aload_1
       2: invokevirtual #411                // Method internalGet:(Ljava/lang/String;)Ljava/lang/String;
       5: astore_2
       6: aload_2
       7: ifnonnull     15
      10: ldc           #1                  // String
      12: goto          16
      15: aload_2
      16: areturn

  public boolean isDefault(java.lang.String);
    Code:
       0: aload_1
       1: ifnonnull     6
       4: iconst_0
       5: ireturn
       6: invokestatic  #381                // Method org/eclipse/core/runtime/Platform.getPreferencesService:()Lorg/eclipse/core/runtime/preferences/IPreferencesService;
       9: aload_1
      10: aconst_null
      11: aload_0
      12: iconst_0
      13: invokevirtual #406                // Method getPreferenceNodes:(Z)[Lorg/eclipse/core/runtime/preferences/IEclipsePreferences;
      16: invokeinterface #439,  4          // InterfaceMethod org/eclipse/core/runtime/preferences/IPreferencesService.get:(Ljava/lang/String;Ljava/lang/String;[Lorg/osgi/service/prefs/Preferences;)Ljava/lang/String;
      21: ifnonnull     26
      24: iconst_1
      25: ireturn
      26: iconst_0
      27: ireturn

  public boolean needsSaving();
    Code:
       0: aload_0
       1: getfield      #356                // Field dirty:Z
       4: ireturn

  public void putValue(java.lang.String, java.lang.String);
    Code:
       0: aload_0
       1: iconst_1
       2: putfield      #357                // Field silentRunning:Z
       5: aload_0
       6: invokevirtual #405                // Method getStorePreferences:()Lorg/eclipse/core/runtime/preferences/IEclipsePreferences;
       9: aload_1
      10: aload_2
      11: invokeinterface #435,  3          // InterfaceMethod org/eclipse/core/runtime/preferences/IEclipsePreferences.put:(Ljava/lang/String;Ljava/lang/String;)V
      16: goto          32
      19: astore_3
      20: aload_0
      21: iconst_0
      22: putfield      #357                // Field silentRunning:Z
      25: aload_0
      26: iconst_1
      27: putfield      #356                // Field dirty:Z
      30: aload_3
      31: athrow
      32: aload_0
      33: iconst_0
      34: putfield      #357                // Field silentRunning:Z
      37: aload_0
      38: iconst_1
      39: putfield      #356                // Field dirty:Z
      42: return
    Exception table:
       from    to  target type
           0    19    19   any

  public void removePropertyChangeListener(org.eclipse.jface.util.IPropertyChangeListener);
    Code:
       0: aload_0
       1: aload_1
       2: invokevirtual #393                // Method removeListenerObject:(Ljava/lang/Object;)V
       5: aload_0
       6: invokevirtual #390                // Method isListenerAttached:()Z
       9: ifne          16
      12: aload_0
      13: invokevirtual #388                // Method disposePreferenceStoreListener:()V
      16: return

  public void setDefault(java.lang.String, double);
    Code:
       0: aload_0
       1: invokevirtual #404                // Method getDefaultPreferences:()Lorg/eclipse/core/runtime/preferences/IEclipsePreferences;
       4: aload_1
       5: dload_2
       6: invokeinterface #422,  4          // InterfaceMethod org/eclipse/core/runtime/preferences/IEclipsePreferences.putDouble:(Ljava/lang/String;D)V
      11: return

  public void setDefault(java.lang.String, float);
    Code:
       0: aload_0
       1: invokevirtual #404                // Method getDefaultPreferences:()Lorg/eclipse/core/runtime/preferences/IEclipsePreferences;
       4: aload_1
       5: fload_2
       6: invokeinterface #424,  3          // InterfaceMethod org/eclipse/core/runtime/preferences/IEclipsePreferences.putFloat:(Ljava/lang/String;F)V
      11: return

  public void setDefault(java.lang.String, int);
    Code:
       0: aload_0
       1: invokevirtual #404                // Method getDefaultPreferences:()Lorg/eclipse/core/runtime/preferences/IEclipsePreferences;
       4: aload_1
       5: iload_2
       6: invokeinterface #426,  3          // InterfaceMethod org/eclipse/core/runtime/preferences/IEclipsePreferences.putInt:(Ljava/lang/String;I)V
      11: return

  public void setDefault(java.lang.String, long);
    Code:
       0: aload_0
       1: invokevirtual #404                // Method getDefaultPreferences:()Lorg/eclipse/core/runtime/preferences/IEclipsePreferences;
       4: aload_1
       5: lload_2
       6: invokeinterface #428,  4          // InterfaceMethod org/eclipse/core/runtime/preferences/IEclipsePreferences.putLong:(Ljava/lang/String;J)V
      11: return

  public void setDefault(java.lang.String, java.lang.String);
    Code:
       0: aload_0
       1: invokevirtual #404                // Method getDefaultPreferences:()Lorg/eclipse/core/runtime/preferences/IEclipsePreferences;
       4: aload_1
       5: aload_2
       6: invokeinterface #435,  3          // InterfaceMethod org/eclipse/core/runtime/preferences/IEclipsePreferences.put:(Ljava/lang/String;Ljava/lang/String;)V
      11: return

  public void setDefault(java.lang.String, boolean);
    Code:
       0: aload_0
       1: invokevirtual #404                // Method getDefaultPreferences:()Lorg/eclipse/core/runtime/preferences/IEclipsePreferences;
       4: aload_1
       5: iload_2
       6: invokeinterface #429,  3          // InterfaceMethod org/eclipse/core/runtime/preferences/IEclipsePreferences.putBoolean:(Ljava/lang/String;Z)V
      11: return

  public void setToDefault(java.lang.String);
    Code:
       0: aload_0
       1: aload_1
       2: invokevirtual #410                // Method getString:(Ljava/lang/String;)Ljava/lang/String;
       5: astore_2
       6: aload_0
       7: aload_1
       8: invokevirtual #409                // Method getDefaultString:(Ljava/lang/String;)Ljava/lang/String;
      11: astore_3
      12: aload_0
      13: iconst_1
      14: putfield      #357                // Field silentRunning:Z
      17: aload_0
      18: invokevirtual #405                // Method getStorePreferences:()Lorg/eclipse/core/runtime/preferences/IEclipsePreferences;
      21: aload_1
      22: invokeinterface #419,  2          // InterfaceMethod org/eclipse/core/runtime/preferences/IEclipsePreferences.remove:(Ljava/lang/String;)V
      27: aload_2
      28: aload_3
      29: invokestatic  #378                // Method java/util/Objects.equals:(Ljava/lang/Object;Ljava/lang/Object;)Z
      32: ifne          60
      35: aload_0
      36: iconst_1
      37: putfield      #356                // Field dirty:Z
      40: aload_0
      41: aload_1
      42: aload_2
      43: aload_3
      44: invokevirtual #414                // Method firePropertyChangeEvent:(Ljava/lang/String;Ljava/lang/Object;Ljava/lang/Object;)V
      47: goto          60
      50: astore        4
      52: aload_0
      53: iconst_0
      54: putfield      #357                // Field silentRunning:Z
      57: aload         4
      59: athrow
      60: aload_0
      61: iconst_0
      62: putfield      #357                // Field silentRunning:Z
      65: return
    Exception table:
       from    to  target type
          12    50    50   any

  public void setValue(java.lang.String, double);
    Code:
       0: aload_0
       1: aload_1
       2: invokevirtual #395                // Method getDouble:(Ljava/lang/String;)D
       5: dstore        4
       7: dload         4
       9: dload_2
      10: dcmpl
      11: ifne          15
      14: return
      15: aload_0
      16: iconst_1
      17: putfield      #357                // Field silentRunning:Z
      20: aload_0
      21: aload_1
      22: invokevirtual #394                // Method getDefaultDouble:(Ljava/lang/String;)D
      25: dload_2
      26: dcmpl
      27: ifne          43
      30: aload_0
      31: invokevirtual #405                // Method getStorePreferences:()Lorg/eclipse/core/runtime/preferences/IEclipsePreferences;
      34: aload_1
      35: invokeinterface #419,  2          // InterfaceMethod org/eclipse/core/runtime/preferences/IEclipsePreferences.remove:(Ljava/lang/String;)V
      40: goto          54
      43: aload_0
      44: invokevirtual #405                // Method getStorePreferences:()Lorg/eclipse/core/runtime/preferences/IEclipsePreferences;
      47: aload_1
      48: dload_2
      49: invokeinterface #422,  4          // InterfaceMethod org/eclipse/core/runtime/preferences/IEclipsePreferences.putDouble:(Ljava/lang/String;D)V
      54: aload_0
      55: iconst_1
      56: putfield      #356                // Field dirty:Z
      59: aload_0
      60: aload_1
      61: dload         4
      63: invokestatic  #367                // Method java/lang/Double.valueOf:(D)Ljava/lang/Double;
      66: dload_2
      67: invokestatic  #367                // Method java/lang/Double.valueOf:(D)Ljava/lang/Double;
      70: invokevirtual #414                // Method firePropertyChangeEvent:(Ljava/lang/String;Ljava/lang/Object;Ljava/lang/Object;)V
      73: goto          86
      76: astore        6
      78: aload_0
      79: iconst_0
      80: putfield      #357                // Field silentRunning:Z
      83: aload         6
      85: athrow
      86: aload_0
      87: iconst_0
      88: putfield      #357                // Field silentRunning:Z
      91: return
    Exception table:
       from    to  target type
          15    76    76   any

  public void setValue(java.lang.String, float);
    Code:
       0: aload_0
       1: aload_1
       2: invokevirtual #397                // Method getFloat:(Ljava/lang/String;)F
       5: fstore_3
       6: fload_3
       7: fload_2
       8: fcmpl
       9: ifne          13
      12: return
      13: aload_0
      14: iconst_1
      15: putfield      #357                // Field silentRunning:Z
      18: aload_0
      19: aload_1
      20: invokevirtual #396                // Method getDefaultFloat:(Ljava/lang/String;)F
      23: fload_2
      24: fcmpl
      25: ifne          41
      28: aload_0
      29: invokevirtual #405                // Method getStorePreferences:()Lorg/eclipse/core/runtime/preferences/IEclipsePreferences;
      32: aload_1
      33: invokeinterface #419,  2          // InterfaceMethod org/eclipse/core/runtime/preferences/IEclipsePreferences.remove:(Ljava/lang/String;)V
      38: goto          52
      41: aload_0
      42: invokevirtual #405                // Method getStorePreferences:()Lorg/eclipse/core/runtime/preferences/IEclipsePreferences;
      45: aload_1
      46: fload_2
      47: invokeinterface #424,  3          // InterfaceMethod org/eclipse/core/runtime/preferences/IEclipsePreferences.putFloat:(Ljava/lang/String;F)V
      52: aload_0
      53: iconst_1
      54: putfield      #356                // Field dirty:Z
      57: aload_0
      58: aload_1
      59: fload_3
      60: invokestatic  #369                // Method java/lang/Float.valueOf:(F)Ljava/lang/Float;
      63: fload_2
      64: invokestatic  #369                // Method java/lang/Float.valueOf:(F)Ljava/lang/Float;
      67: invokevirtual #414                // Method firePropertyChangeEvent:(Ljava/lang/String;Ljava/lang/Object;Ljava/lang/Object;)V
      70: goto          83
      73: astore        4
      75: aload_0
      76: iconst_0
      77: putfield      #357                // Field silentRunning:Z
      80: aload         4
      82: athrow
      83: aload_0
      84: iconst_0
      85: putfield      #357                // Field silentRunning:Z
      88: return
    Exception table:
       from    to  target type
          13    73    73   any

  public void setValue(java.lang.String, int);
    Code:
       0: aload_0
       1: aload_1
       2: invokevirtual #399                // Method getInt:(Ljava/lang/String;)I
       5: istore_3
       6: iload_3
       7: iload_2
       8: if_icmpne     12
      11: return
      12: aload_0
      13: iconst_1
      14: putfield      #357                // Field silentRunning:Z
      17: aload_0
      18: aload_1
      19: invokevirtual #398                // Method getDefaultInt:(Ljava/lang/String;)I
      22: iload_2
      23: if_icmpne     39
      26: aload_0
      27: invokevirtual #405                // Method getStorePreferences:()Lorg/eclipse/core/runtime/preferences/IEclipsePreferences;
      30: aload_1
      31: invokeinterface #419,  2          // InterfaceMethod org/eclipse/core/runtime/preferences/IEclipsePreferences.remove:(Ljava/lang/String;)V
      36: goto          50
      39: aload_0
      40: invokevirtual #405                // Method getStorePreferences:()Lorg/eclipse/core/runtime/preferences/IEclipsePreferences;
      43: aload_1
      44: iload_2
      45: invokeinterface #426,  3          // InterfaceMethod org/eclipse/core/runtime/preferences/IEclipsePreferences.putInt:(Ljava/lang/String;I)V
      50: aload_0
      51: iconst_1
      52: putfield      #356                // Field dirty:Z
      55: aload_0
      56: aload_1
      57: iload_3
      58: invokestatic  #371                // Method java/lang/Integer.valueOf:(I)Ljava/lang/Integer;
      61: iload_2
      62: invokestatic  #371                // Method java/lang/Integer.valueOf:(I)Ljava/lang/Integer;
      65: invokevirtual #414                // Method firePropertyChangeEvent:(Ljava/lang/String;Ljava/lang/Object;Ljava/lang/Object;)V
      68: goto          81
      71: astore        4
      73: aload_0
      74: iconst_0
      75: putfield      #357                // Field silentRunning:Z
      78: aload         4
      80: athrow
      81: aload_0
      82: iconst_0
      83: putfield      #357                // Field silentRunning:Z
      86: return
    Exception table:
       from    to  target type
          12    71    71   any

  public void setValue(java.lang.String, long);
    Code:
       0: aload_0
       1: aload_1
       2: invokevirtual #401                // Method getLong:(Ljava/lang/String;)J
       5: lstore        4
       7: lload         4
       9: lload_2
      10: lcmp
      11: ifne          15
      14: return
      15: aload_0
      16: iconst_1
      17: putfield      #357                // Field silentRunning:Z
      20: aload_0
      21: aload_1
      22: invokevirtual #400                // Method getDefaultLong:(Ljava/lang/String;)J
      25: lload_2
      26: lcmp
      27: ifne          43
      30: aload_0
      31: invokevirtual #405                // Method getStorePreferences:()Lorg/eclipse/core/runtime/preferences/IEclipsePreferences;
      34: aload_1
      35: invokeinterface #419,  2          // InterfaceMethod org/eclipse/core/runtime/preferences/IEclipsePreferences.remove:(Ljava/lang/String;)V
      40: goto          54
      43: aload_0
      44: invokevirtual #405                // Method getStorePreferences:()Lorg/eclipse/core/runtime/preferences/IEclipsePreferences;
      47: aload_1
      48: lload_2
      49: invokeinterface #428,  4          // InterfaceMethod org/eclipse/core/runtime/preferences/IEclipsePreferences.putLong:(Ljava/lang/String;J)V
      54: aload_0
      55: iconst_1
      56: putfield      #356                // Field dirty:Z
      59: aload_0
      60: aload_1
      61: lload         4
      63: invokestatic  #373                // Method java/lang/Long.valueOf:(J)Ljava/lang/Long;
      66: lload_2
      67: invokestatic  #373                // Method java/lang/Long.valueOf:(J)Ljava/lang/Long;
      70: invokevirtual #414                // Method firePropertyChangeEvent:(Ljava/lang/String;Ljava/lang/Object;Ljava/lang/Object;)V
      73: goto          86
      76: astore        6
      78: aload_0
      79: iconst_0
      80: putfield      #357                // Field silentRunning:Z
      83: aload         6
      85: athrow
      86: aload_0
      87: iconst_0
      88: putfield      #357                // Field silentRunning:Z
      91: return
    Exception table:
       from    to  target type
          15    76    76   any

  public void setValue(java.lang.String, java.lang.String);
    Code:
       0: aload_0
       1: aload_1
       2: invokevirtual #409                // Method getDefaultString:(Ljava/lang/String;)Ljava/lang/String;
       5: aload_2
       6: invokevirtual #376                // Method java/lang/String.equals:(Ljava/lang/Object;)Z
       9: ifeq          25
      12: aload_0
      13: invokevirtual #405                // Method getStorePreferences:()Lorg/eclipse/core/runtime/preferences/IEclipsePreferences;
      16: aload_1
      17: invokeinterface #419,  2          // InterfaceMethod org/eclipse/core/runtime/preferences/IEclipsePreferences.remove:(Ljava/lang/String;)V
      22: goto          36
      25: aload_0
      26: invokevirtual #405                // Method getStorePreferences:()Lorg/eclipse/core/runtime/preferences/IEclipsePreferences;
      29: aload_1
      30: aload_2
      31: invokeinterface #435,  3          // InterfaceMethod org/eclipse/core/runtime/preferences/IEclipsePreferences.put:(Ljava/lang/String;Ljava/lang/String;)V
      36: aload_0
      37: iconst_1
      38: putfield      #356                // Field dirty:Z
      41: return

  public void setValue(java.lang.String, boolean);
    Code:
       0: aload_0
       1: aload_1
       2: invokevirtual #402                // Method getBoolean:(Ljava/lang/String;)Z
       5: istore_3
       6: iload_3
       7: iload_2
       8: if_icmpne     12
      11: return
      12: aload_0
      13: iconst_1
      14: putfield      #357                // Field silentRunning:Z
      17: aload_0
      18: aload_1
      19: invokevirtual #403                // Method getDefaultBoolean:(Ljava/lang/String;)Z
      22: iload_2
      23: if_icmpne     39
      26: aload_0
      27: invokevirtual #405                // Method getStorePreferences:()Lorg/eclipse/core/runtime/preferences/IEclipsePreferences;
      30: aload_1
      31: invokeinterface #419,  2          // InterfaceMethod org/eclipse/core/runtime/preferences/IEclipsePreferences.remove:(Ljava/lang/String;)V
      36: goto          50
      39: aload_0
      40: invokevirtual #405                // Method getStorePreferences:()Lorg/eclipse/core/runtime/preferences/IEclipsePreferences;
      43: aload_1
      44: iload_2
      45: invokeinterface #429,  3          // InterfaceMethod org/eclipse/core/runtime/preferences/IEclipsePreferences.putBoolean:(Ljava/lang/String;Z)V
      50: aload_0
      51: iconst_1
      52: putfield      #356                // Field dirty:Z
      55: aload_0
      56: aload_1
      57: iload_3
      58: ifeq          67
      61: getstatic     #353                // Field java/lang/Boolean.TRUE:Ljava/lang/Boolean;
      64: goto          70
      67: getstatic     #352                // Field java/lang/Boolean.FALSE:Ljava/lang/Boolean;
      70: iload_2
      71: ifeq          80
      74: getstatic     #353                // Field java/lang/Boolean.TRUE:Ljava/lang/Boolean;
      77: goto          83
      80: getstatic     #352                // Field java/lang/Boolean.FALSE:Ljava/lang/Boolean;
      83: invokevirtual #414                // Method firePropertyChangeEvent:(Ljava/lang/String;Ljava/lang/Object;Ljava/lang/Object;)V
      86: goto          99
      89: astore        4
      91: aload_0
      92: iconst_0
      93: putfield      #357                // Field silentRunning:Z
      96: aload         4
      98: athrow
      99: aload_0
     100: iconst_0
     101: putfield      #357                // Field silentRunning:Z
     104: return
    Exception table:
       from    to  target type
          12    89    89   any

  public void save() throws java.io.IOException;
    Code:
       0: aload_0
       1: invokevirtual #405                // Method getStorePreferences:()Lorg/eclipse/core/runtime/preferences/IEclipsePreferences;
       4: invokeinterface #418,  1          // InterfaceMethod org/eclipse/core/runtime/preferences/IEclipsePreferences.flush:()V
       9: aload_0
      10: iconst_0
      11: putfield      #356                // Field dirty:Z
      14: goto          30
      17: astore_1
      18: new           #164                // class java/io/IOException
      21: dup
      22: aload_1
      23: invokevirtual #417                // Method org/osgi/service/prefs/BackingStoreException.getMessage:()Ljava/lang/String;
      26: invokespecial #364                // Method java/io/IOException."<init>":(Ljava/lang/String;)V
      29: athrow
      30: return
    Exception table:
       from    to  target type
           0    14    17   Class org/osgi/service/prefs/BackingStoreException

  private void disposePreferenceStoreListener();
    Code:
       0: invokestatic  #381                // Method org/eclipse/core/runtime/Platform.getPreferencesService:()Lorg/eclipse/core/runtime/preferences/IPreferencesService;
       3: invokeinterface #438,  1          // InterfaceMethod org/eclipse/core/runtime/preferences/IPreferencesService.getRootNode:()Lorg/eclipse/core/runtime/preferences/IEclipsePreferences;
       8: ldc_w         #160                // String instance
      11: invokeinterface #436,  2          // InterfaceMethod org/eclipse/core/runtime/preferences/IEclipsePreferences.node:(Ljava/lang/String;)Lorg/osgi/service/prefs/Preferences;
      16: checkcast     #182                // class org/eclipse/core/runtime/preferences/IEclipsePreferences
      19: astore_1
      20: aload_1
      21: aload_0
      22: getfield      #359                // Field nodeQualifier:Ljava/lang/String;
      25: invokeinterface #420,  2          // InterfaceMethod org/eclipse/core/runtime/preferences/IEclipsePreferences.nodeExists:(Ljava/lang/String;)Z
      30: ifne          36
      33: return
      34: pop
      35: return
      36: aload_0
      37: invokevirtual #405                // Method getStorePreferences:()Lorg/eclipse/core/runtime/preferences/IEclipsePreferences;
      40: astore_2
      41: aload_2
      42: ifnonnull     46
      45: return
      46: aload_0
      47: getfield      #360                // Field preferencesListener:Lorg/eclipse/core/runtime/preferences/IEclipsePreferences$IPreferenceChangeListener;
      50: ifnull        68
      53: aload_2
      54: aload_0
      55: getfield      #360                // Field preferencesListener:Lorg/eclipse/core/runtime/preferences/IEclipsePreferences$IPreferenceChangeListener;
      58: invokeinterface #433,  2          // InterfaceMethod org/eclipse/core/runtime/preferences/IEclipsePreferences.removePreferenceChangeListener:(Lorg/eclipse/core/runtime/preferences/IEclipsePreferences$IPreferenceChangeListener;)V
      63: aload_0
      64: aconst_null
      65: putfield      #360                // Field preferencesListener:Lorg/eclipse/core/runtime/preferences/IEclipsePreferences$IPreferenceChangeListener;
      68: return
    Exception table:
       from    to  target type
          20    33    34   Class org/osgi/service/prefs/BackingStoreException

  static boolean access$0(org.eclipse.ui.preferences.ScopedPreferenceStore);
    Code:
       0: aload_0
       1: invokevirtual #390                // Method isListenerAttached:()Z
       4: ireturn

  private void lambda$0(org.eclipse.core.runtime.preferences.IEclipsePreferences$PreferenceChangeEvent);
    Code:
       0: aload_0
       1: getfield      #357                // Field silentRunning:Z
       4: ifeq          8
       7: return
       8: aload_1
       9: invokevirtual #384                // Method org/eclipse/core/runtime/preferences/IEclipsePreferences$PreferenceChangeEvent.getOldValue:()Ljava/lang/Object;
      12: astore_2
      13: aload_1
      14: invokevirtual #383                // Method org/eclipse/core/runtime/preferences/IEclipsePreferences$PreferenceChangeEvent.getNewValue:()Ljava/lang/Object;
      17: astore_3
      18: aload_1
      19: invokevirtual #385                // Method org/eclipse/core/runtime/preferences/IEclipsePreferences$PreferenceChangeEvent.getKey:()Ljava/lang/String;
      22: astore        4
      24: aload_3
      25: ifnonnull     39
      28: aload_0
      29: aload         4
      31: aload_2
      32: invokevirtual #413                // Method getDefault:(Ljava/lang/String;Ljava/lang/Object;)Ljava/lang/Object;
      35: astore_3
      36: goto          51
      39: aload_2
      40: ifnonnull     51
      43: aload_0
      44: aload         4
      46: aload_3
      47: invokevirtual #413                // Method getDefault:(Ljava/lang/String;Ljava/lang/Object;)Ljava/lang/Object;
      50: astore_2
      51: aload_0
      52: aload_1
      53: invokevirtual #385                // Method org/eclipse/core/runtime/preferences/IEclipsePreferences$PreferenceChangeEvent.getKey:()Ljava/lang/String;
      56: aload_2
      57: aload_3
      58: invokevirtual #414                // Method firePropertyChangeEvent:(Ljava/lang/String;Ljava/lang/Object;Ljava/lang/Object;)V
      61: return
}
