Compiled from "WorkingCopyManager.java"
public class org.eclipse.ui.preferences.WorkingCopyManager implements org.eclipse.ui.preferences.IWorkingCopyManager {
  private static final java.lang.String EMPTY_STRING;

  private java.util.Map<java.lang.String, org.eclipse.core.runtime.preferences.IEclipsePreferences> workingCopies;

  public org.eclipse.ui.preferences.WorkingCopyManager();
    Code:
       0: aload_0
       1: invokespecial #80                 // Method java/lang/Object."<init>":()V
       4: aload_0
       5: new           #42                 // class java/util/HashMap
       8: dup
       9: invokespecial #81                 // Method java/util/HashMap."<init>":()V
      12: putfield      #78                 // Field workingCopies:Ljava/util/Map;
      15: return

  public org.eclipse.core.runtime.preferences.IEclipsePreferences getWorkingCopy(org.eclipse.core.runtime.preferences.IEclipsePreferences);
    Code:
       0: aload_1
       1: instanceof    #45                 // class org/eclipse/ui/internal/preferences/WorkingCopyPreferences
       4: ifeq          17
       7: new           #38                 // class java/lang/IllegalArgumentException
      10: dup
      11: ldc           #2                  // String Trying to get a working copy of a working copy
      13: invokespecial #79                 // Method java/lang/IllegalArgumentException."<init>":(Ljava/lang/String;)V
      16: athrow
      17: aload_1
      18: invokeinterface #90,  1           // InterfaceMethod org/eclipse/core/runtime/preferences/IEclipsePreferences.absolutePath:()Ljava/lang/String;
      23: astore_2
      24: aload_0
      25: getfield      #78                 // Field workingCopies:Ljava/util/Map;
      28: aload_2
      29: invokeinterface #88,  2           // InterfaceMethod java/util/Map.get:(Ljava/lang/Object;)Ljava/lang/Object;
      34: checkcast     #44                 // class org/eclipse/core/runtime/preferences/IEclipsePreferences
      37: astore_3
      38: aload_3
      39: ifnonnull     64
      42: new           #45                 // class org/eclipse/ui/internal/preferences/WorkingCopyPreferences
      45: dup
      46: aload_1
      47: aload_0
      48: invokespecial #84                 // Method org/eclipse/ui/internal/preferences/WorkingCopyPreferences."<init>":(Lorg/eclipse/core/runtime/preferences/IEclipsePreferences;Lorg/eclipse/ui/preferences/WorkingCopyManager;)V
      51: astore_3
      52: aload_0
      53: getfield      #78                 // Field workingCopies:Ljava/util/Map;
      56: aload_2
      57: aload_3
      58: invokeinterface #89,  3           // InterfaceMethod java/util/Map.put:(Ljava/lang/Object;Ljava/lang/Object;)Ljava/lang/Object;
      63: pop
      64: aload_3
      65: areturn

  public void applyChanges() throws org.osgi.service.prefs.BackingStoreException;
    Code:
       0: aload_0
       1: getfield      #78                 // Field workingCopies:Ljava/util/Map;
       4: invokeinterface #87,  1           // InterfaceMethod java/util/Map.values:()Ljava/util/Collection;
       9: astore_1
      10: aload_1
      11: aload_1
      12: invokeinterface #85,  1           // InterfaceMethod java/util/Collection.size:()I
      17: anewarray     #45                 // class org/eclipse/ui/internal/preferences/WorkingCopyPreferences
      20: invokeinterface #86,  2           // InterfaceMethod java/util/Collection.toArray:([Ljava/lang/Object;)[Ljava/lang/Object;
      25: checkcast     #37                 // class "[Lorg/eclipse/ui/internal/preferences/WorkingCopyPreferences;"
      28: astore_2
      29: aload_2
      30: dup
      31: astore        6
      33: arraylength
      34: istore        5
      36: iconst_0
      37: istore        4
      39: goto          64
      42: aload         6
      44: iload         4
      46: aaload
      47: astore_3
      48: aload_3
      49: ldc           #1                  // String
      51: invokevirtual #83                 // Method org/eclipse/ui/internal/preferences/WorkingCopyPreferences.nodeExists:(Ljava/lang/String;)Z
      54: ifeq          61
      57: aload_3
      58: invokevirtual #82                 // Method org/eclipse/ui/internal/preferences/WorkingCopyPreferences.flush:()V
      61: iinc          4, 1
      64: iload         4
      66: iload         5
      68: if_icmplt     42
      71: return
}
