Compiled from "MetaProperty.java"
public abstract class groovy.lang.MetaProperty {
  protected final java.lang.String name;

  protected java.lang.Class type;

  public static final java.lang.String PROPERTY_SET_PREFIX;

  public groovy.lang.MetaProperty(java.lang.String, java.lang.Class);
    Code:
       0: aload_0
       1: invokespecial #17                 // Method java/lang/Object."<init>":()V
       4: aload_0
       5: aload_1
       6: putfield      #19                 // Field name:Ljava/lang/String;
       9: aload_0
      10: aload_2
      11: putfield      #21                 // Field type:Ljava/lang/Class;
      14: return

  public abstract java.lang.Object getProperty(java.lang.Object);

  public abstract void setProperty(java.lang.Object, java.lang.Object);

  public java.lang.String getName();
    Code:
       0: aload_0
       1: getfield      #19                 // Field name:Ljava/lang/String;
       4: areturn

  public java.lang.Class getType();
    Code:
       0: aload_0
       1: getfield      #21                 // Field type:Ljava/lang/Class;
       4: areturn

  public int getModifiers();
    Code:
       0: iconst_1
       1: ireturn

  public static java.lang.String getGetterName(java.lang.String, java.lang.Class);
    Code:
       0: aload_1
       1: getstatic     #40                 // Field java/lang/Boolean.TYPE:Ljava/lang/Class;
       4: if_acmpeq     13
       7: aload_1
       8: ldc           #37                 // class java/lang/Boolean
      10: if_acmpne     18
      13: ldc           #42                 // String is
      15: goto          20
      18: ldc           #44                 // String get
      20: astore_2
      21: new           #48                 // class java/lang/StringBuilder
      24: dup
      25: invokespecial #49                 // Method java/lang/StringBuilder."<init>":()V
      28: aload_2
      29: invokevirtual #53                 // Method java/lang/StringBuilder.append:(Ljava/lang/String;)Ljava/lang/StringBuilder;
      32: aload_0
      33: invokestatic  #59                 // Method org/codehaus/groovy/runtime/MetaClassHelper.capitalize:(Ljava/lang/String;)Ljava/lang/String;
      36: invokevirtual #53                 // Method java/lang/StringBuilder.append:(Ljava/lang/String;)Ljava/lang/StringBuilder;
      39: invokevirtual #62                 // Method java/lang/StringBuilder.toString:()Ljava/lang/String;
      42: areturn

  public static java.lang.String getSetterName(java.lang.String);
    Code:
       0: new           #48                 // class java/lang/StringBuilder
       3: dup
       4: invokespecial #49                 // Method java/lang/StringBuilder."<init>":()V
       7: ldc           #12                 // String set
       9: invokevirtual #53                 // Method java/lang/StringBuilder.append:(Ljava/lang/String;)Ljava/lang/StringBuilder;
      12: aload_0
      13: invokestatic  #59                 // Method org/codehaus/groovy/runtime/MetaClassHelper.capitalize:(Ljava/lang/String;)Ljava/lang/String;
      16: invokevirtual #53                 // Method java/lang/StringBuilder.append:(Ljava/lang/String;)Ljava/lang/StringBuilder;
      19: invokevirtual #62                 // Method java/lang/StringBuilder.toString:()Ljava/lang/String;
      22: areturn
}
