Compiled from "RouteSelector.kt"
final class okhttp3.internal.connection.RouteSelector$resetNextProxy$1 extends kotlin.jvm.internal.Lambda implements kotlin.jvm.functions.Function0<java.util.List<? extends java.net.Proxy>> {
  final okhttp3.internal.connection.RouteSelector this$0;

  final java.net.Proxy $proxy;

  final okhttp3.HttpUrl $url;

  public java.lang.Object invoke();
    Code:
       0: aload_0
       1: invokevirtual #12                 // Method invoke:()Ljava/util/List;
       4: areturn

  public final java.util.List<java.net.Proxy> invoke();
    Code:
       0: aload_0
       1: getfield      #18                 // Field $proxy:Ljava/net/Proxy;
       4: ifnull        15
       7: aload_0
       8: getfield      #18                 // Field $proxy:Ljava/net/Proxy;
      11: invokestatic  #24                 // Method kotlin/collections/CollectionsKt.listOf:(Ljava/lang/Object;)Ljava/util/List;
      14: areturn
      15: aload_0
      16: getfield      #28                 // Field $url:Lokhttp3/HttpUrl;
      19: invokevirtual #34                 // Method okhttp3/HttpUrl.uri:()Ljava/net/URI;
      22: astore_1
      23: aload_1
      24: invokevirtual #40                 // Method java/net/URI.getHost:()Ljava/lang/String;
      27: ifnonnull     44
      30: iconst_1
      31: anewarray     #42                 // class java/net/Proxy
      34: dup
      35: iconst_0
      36: getstatic     #45                 // Field java/net/Proxy.NO_PROXY:Ljava/net/Proxy;
      39: aastore
      40: invokestatic  #51                 // Method okhttp3/internal/Util.immutableListOf:([Ljava/lang/Object;)Ljava/util/List;
      43: areturn
      44: aload_0
      45: getfield      #55                 // Field this$0:Lokhttp3/internal/connection/RouteSelector;
      48: invokestatic  #61                 // Method okhttp3/internal/connection/RouteSelector.access$getAddress$p:(Lokhttp3/internal/connection/RouteSelector;)Lokhttp3/Address;
      51: invokevirtual #67                 // Method okhttp3/Address.proxySelector:()Ljava/net/ProxySelector;
      54: aload_1
      55: invokevirtual #73                 // Method java/net/ProxySelector.select:(Ljava/net/URI;)Ljava/util/List;
      58: astore_2
      59: aload_2
      60: checkcast     #75                 // class java/util/Collection
      63: astore_3
      64: iconst_0
      65: istore        4
      67: iconst_0
      68: istore        5
      70: aload_3
      71: ifnull        83
      74: aload_3
      75: invokeinterface #79,  1           // InterfaceMethod java/util/Collection.isEmpty:()Z
      80: ifeq          87
      83: iconst_1
      84: goto          88
      87: iconst_0
      88: ifeq          105
      91: iconst_1
      92: anewarray     #42                 // class java/net/Proxy
      95: dup
      96: iconst_0
      97: getstatic     #45                 // Field java/net/Proxy.NO_PROXY:Ljava/net/Proxy;
     100: aastore
     101: invokestatic  #51                 // Method okhttp3/internal/Util.immutableListOf:([Ljava/lang/Object;)Ljava/util/List;
     104: areturn
     105: aload_2
     106: invokestatic  #83                 // Method okhttp3/internal/Util.toImmutableList:(Ljava/util/List;)Ljava/util/List;
     109: areturn

  okhttp3.internal.connection.RouteSelector$resetNextProxy$1(okhttp3.internal.connection.RouteSelector, java.net.Proxy, okhttp3.HttpUrl);
    Code:
       0: aload_0
       1: aload_1
       2: putfield      #55                 // Field this$0:Lokhttp3/internal/connection/RouteSelector;
       5: aload_0
       6: aload_2
       7: putfield      #18                 // Field $proxy:Ljava/net/Proxy;
      10: aload_0
      11: aload_3
      12: putfield      #28                 // Field $url:Lokhttp3/HttpUrl;
      15: aload_0
      16: iconst_0
      17: invokespecial #95                 // Method kotlin/jvm/internal/Lambda."<init>":(I)V
      20: return
}
