Compiled from "AbstractDataPipeline.java"
public class com.amazonaws.services.datapipeline.AbstractDataPipeline implements com.amazonaws.services.datapipeline.DataPipeline {
  protected com.amazonaws.services.datapipeline.AbstractDataPipeline();
    Code:
       0: aload_0
       1: invokespecial #1                  // Method java/lang/Object."<init>":()V
       4: return

  public void setEndpoint(java.lang.String);
    Code:
       0: new           #2                  // class java/lang/UnsupportedOperationException
       3: dup
       4: invokespecial #3                  // Method java/lang/UnsupportedOperationException."<init>":()V
       7: athrow

  public void setRegion(com.amazonaws.regions.Region);
    Code:
       0: new           #2                  // class java/lang/UnsupportedOperationException
       3: dup
       4: invokespecial #3                  // Method java/lang/UnsupportedOperationException."<init>":()V
       7: athrow

  public com.amazonaws.services.datapipeline.model.ActivatePipelineResult activatePipeline(com.amazonaws.services.datapipeline.model.ActivatePipelineRequest);
    Code:
       0: new           #2                  // class java/lang/UnsupportedOperationException
       3: dup
       4: invokespecial #3                  // Method java/lang/UnsupportedOperationException."<init>":()V
       7: athrow

  public com.amazonaws.services.datapipeline.model.AddTagsResult addTags(com.amazonaws.services.datapipeline.model.AddTagsRequest);
    Code:
       0: new           #2                  // class java/lang/UnsupportedOperationException
       3: dup
       4: invokespecial #3                  // Method java/lang/UnsupportedOperationException."<init>":()V
       7: athrow

  public com.amazonaws.services.datapipeline.model.CreatePipelineResult createPipeline(com.amazonaws.services.datapipeline.model.CreatePipelineRequest);
    Code:
       0: new           #2                  // class java/lang/UnsupportedOperationException
       3: dup
       4: invokespecial #3                  // Method java/lang/UnsupportedOperationException."<init>":()V
       7: athrow

  public com.amazonaws.services.datapipeline.model.DeactivatePipelineResult deactivatePipeline(com.amazonaws.services.datapipeline.model.DeactivatePipelineRequest);
    Code:
       0: new           #2                  // class java/lang/UnsupportedOperationException
       3: dup
       4: invokespecial #3                  // Method java/lang/UnsupportedOperationException."<init>":()V
       7: athrow

  public com.amazonaws.services.datapipeline.model.DeletePipelineResult deletePipeline(com.amazonaws.services.datapipeline.model.DeletePipelineRequest);
    Code:
       0: new           #2                  // class java/lang/UnsupportedOperationException
       3: dup
       4: invokespecial #3                  // Method java/lang/UnsupportedOperationException."<init>":()V
       7: athrow

  public com.amazonaws.services.datapipeline.model.DescribeObjectsResult describeObjects(com.amazonaws.services.datapipeline.model.DescribeObjectsRequest);
    Code:
       0: new           #2                  // class java/lang/UnsupportedOperationException
       3: dup
       4: invokespecial #3                  // Method java/lang/UnsupportedOperationException."<init>":()V
       7: athrow

  public com.amazonaws.services.datapipeline.model.DescribePipelinesResult describePipelines(com.amazonaws.services.datapipeline.model.DescribePipelinesRequest);
    Code:
       0: new           #2                  // class java/lang/UnsupportedOperationException
       3: dup
       4: invokespecial #3                  // Method java/lang/UnsupportedOperationException."<init>":()V
       7: athrow

  public com.amazonaws.services.datapipeline.model.EvaluateExpressionResult evaluateExpression(com.amazonaws.services.datapipeline.model.EvaluateExpressionRequest);
    Code:
       0: new           #2                  // class java/lang/UnsupportedOperationException
       3: dup
       4: invokespecial #3                  // Method java/lang/UnsupportedOperationException."<init>":()V
       7: athrow

  public com.amazonaws.services.datapipeline.model.GetPipelineDefinitionResult getPipelineDefinition(com.amazonaws.services.datapipeline.model.GetPipelineDefinitionRequest);
    Code:
       0: new           #2                  // class java/lang/UnsupportedOperationException
       3: dup
       4: invokespecial #3                  // Method java/lang/UnsupportedOperationException."<init>":()V
       7: athrow

  public com.amazonaws.services.datapipeline.model.ListPipelinesResult listPipelines(com.amazonaws.services.datapipeline.model.ListPipelinesRequest);
    Code:
       0: new           #2                  // class java/lang/UnsupportedOperationException
       3: dup
       4: invokespecial #3                  // Method java/lang/UnsupportedOperationException."<init>":()V
       7: athrow

  public com.amazonaws.services.datapipeline.model.ListPipelinesResult listPipelines();
    Code:
       0: aload_0
       1: new           #4                  // class com/amazonaws/services/datapipeline/model/ListPipelinesRequest
       4: dup
       5: invokespecial #5                  // Method com/amazonaws/services/datapipeline/model/ListPipelinesRequest."<init>":()V
       8: invokevirtual #6                  // Method listPipelines:(Lcom/amazonaws/services/datapipeline/model/ListPipelinesRequest;)Lcom/amazonaws/services/datapipeline/model/ListPipelinesResult;
      11: areturn

  public com.amazonaws.services.datapipeline.model.PollForTaskResult pollForTask(com.amazonaws.services.datapipeline.model.PollForTaskRequest);
    Code:
       0: new           #2                  // class java/lang/UnsupportedOperationException
       3: dup
       4: invokespecial #3                  // Method java/lang/UnsupportedOperationException."<init>":()V
       7: athrow

  public com.amazonaws.services.datapipeline.model.PutPipelineDefinitionResult putPipelineDefinition(com.amazonaws.services.datapipeline.model.PutPipelineDefinitionRequest);
    Code:
       0: new           #2                  // class java/lang/UnsupportedOperationException
       3: dup
       4: invokespecial #3                  // Method java/lang/UnsupportedOperationException."<init>":()V
       7: athrow

  public com.amazonaws.services.datapipeline.model.QueryObjectsResult queryObjects(com.amazonaws.services.datapipeline.model.QueryObjectsRequest);
    Code:
       0: new           #2                  // class java/lang/UnsupportedOperationException
       3: dup
       4: invokespecial #3                  // Method java/lang/UnsupportedOperationException."<init>":()V
       7: athrow

  public com.amazonaws.services.datapipeline.model.RemoveTagsResult removeTags(com.amazonaws.services.datapipeline.model.RemoveTagsRequest);
    Code:
       0: new           #2                  // class java/lang/UnsupportedOperationException
       3: dup
       4: invokespecial #3                  // Method java/lang/UnsupportedOperationException."<init>":()V
       7: athrow

  public com.amazonaws.services.datapipeline.model.ReportTaskProgressResult reportTaskProgress(com.amazonaws.services.datapipeline.model.ReportTaskProgressRequest);
    Code:
       0: new           #2                  // class java/lang/UnsupportedOperationException
       3: dup
       4: invokespecial #3                  // Method java/lang/UnsupportedOperationException."<init>":()V
       7: athrow

  public com.amazonaws.services.datapipeline.model.ReportTaskRunnerHeartbeatResult reportTaskRunnerHeartbeat(com.amazonaws.services.datapipeline.model.ReportTaskRunnerHeartbeatRequest);
    Code:
       0: new           #2                  // class java/lang/UnsupportedOperationException
       3: dup
       4: invokespecial #3                  // Method java/lang/UnsupportedOperationException."<init>":()V
       7: athrow

  public com.amazonaws.services.datapipeline.model.SetStatusResult setStatus(com.amazonaws.services.datapipeline.model.SetStatusRequest);
    Code:
       0: new           #2                  // class java/lang/UnsupportedOperationException
       3: dup
       4: invokespecial #3                  // Method java/lang/UnsupportedOperationException."<init>":()V
       7: athrow

  public com.amazonaws.services.datapipeline.model.SetTaskStatusResult setTaskStatus(com.amazonaws.services.datapipeline.model.SetTaskStatusRequest);
    Code:
       0: new           #2                  // class java/lang/UnsupportedOperationException
       3: dup
       4: invokespecial #3                  // Method java/lang/UnsupportedOperationException."<init>":()V
       7: athrow

  public com.amazonaws.services.datapipeline.model.ValidatePipelineDefinitionResult validatePipelineDefinition(com.amazonaws.services.datapipeline.model.ValidatePipelineDefinitionRequest);
    Code:
       0: new           #2                  // class java/lang/UnsupportedOperationException
       3: dup
       4: invokespecial #3                  // Method java/lang/UnsupportedOperationException."<init>":()V
       7: athrow

  public void shutdown();
    Code:
       0: new           #2                  // class java/lang/UnsupportedOperationException
       3: dup
       4: invokespecial #3                  // Method java/lang/UnsupportedOperationException."<init>":()V
       7: athrow

  public com.amazonaws.ResponseMetadata getCachedResponseMetadata(com.amazonaws.AmazonWebServiceRequest);
    Code:
       0: new           #2                  // class java/lang/UnsupportedOperationException
       3: dup
       4: invokespecial #3                  // Method java/lang/UnsupportedOperationException."<init>":()V
       7: athrow
}
