Compiled from "RequestingNodeType.java"
public final class org.mobicents.protocols.ss7.map.api.service.mobility.authentication.RequestingNodeType extends java.lang.Enum<org.mobicents.protocols.ss7.map.api.service.mobility.authentication.RequestingNodeType> {
  public static final org.mobicents.protocols.ss7.map.api.service.mobility.authentication.RequestingNodeType vlr;

  public static final org.mobicents.protocols.ss7.map.api.service.mobility.authentication.RequestingNodeType sgsn;

  public static final org.mobicents.protocols.ss7.map.api.service.mobility.authentication.RequestingNodeType sCscf;

  public static final org.mobicents.protocols.ss7.map.api.service.mobility.authentication.RequestingNodeType bsf;

  public static final org.mobicents.protocols.ss7.map.api.service.mobility.authentication.RequestingNodeType ganAaaServer;

  public static final org.mobicents.protocols.ss7.map.api.service.mobility.authentication.RequestingNodeType wlanAaaaServer;

  public static final org.mobicents.protocols.ss7.map.api.service.mobility.authentication.RequestingNodeType mme;

  public static final org.mobicents.protocols.ss7.map.api.service.mobility.authentication.RequestingNodeType mmeSgsn;

  private int code;

  private static final org.mobicents.protocols.ss7.map.api.service.mobility.authentication.RequestingNodeType[] $VALUES;

  public static org.mobicents.protocols.ss7.map.api.service.mobility.authentication.RequestingNodeType[] values();
    Code:
       0: getstatic     #1                  // Field $VALUES:[Lorg/mobicents/protocols/ss7/map/api/service/mobility/authentication/RequestingNodeType;
       3: invokevirtual #2                  // Method "[Lorg/mobicents/protocols/ss7/map/api/service/mobility/authentication/RequestingNodeType;".clone:()Ljava/lang/Object;
       6: checkcast     #3                  // class "[Lorg/mobicents/protocols/ss7/map/api/service/mobility/authentication/RequestingNodeType;"
       9: areturn

  public static org.mobicents.protocols.ss7.map.api.service.mobility.authentication.RequestingNodeType valueOf(java.lang.String);
    Code:
       0: ldc_w         #4                  // class org/mobicents/protocols/ss7/map/api/service/mobility/authentication/RequestingNodeType
       3: aload_0
       4: invokestatic  #5                  // Method java/lang/Enum.valueOf:(Ljava/lang/Class;Ljava/lang/String;)Ljava/lang/Enum;
       7: checkcast     #4                  // class org/mobicents/protocols/ss7/map/api/service/mobility/authentication/RequestingNodeType
      10: areturn

  private org.mobicents.protocols.ss7.map.api.service.mobility.authentication.RequestingNodeType(int);
    Code:
       0: aload_0
       1: aload_1
       2: iload_2
       3: invokespecial #6                  // Method java/lang/Enum."<init>":(Ljava/lang/String;I)V
       6: aload_0
       7: iload_3
       8: putfield      #7                  // Field code:I
      11: return

  public static org.mobicents.protocols.ss7.map.api.service.mobility.authentication.RequestingNodeType getInstance(int);
    Code:
       0: iload_0
       1: tableswitch   { // 0 to 17
                     0: 88
                     1: 92
                     2: 96
                     3: 100
                     4: 104
                     5: 108
                     6: 120
                     7: 120
                     8: 120
                     9: 120
                    10: 120
                    11: 120
                    12: 120
                    13: 120
                    14: 120
                    15: 120
                    16: 112
                    17: 116
               default: 120
          }
      88: getstatic     #8                  // Field vlr:Lorg/mobicents/protocols/ss7/map/api/service/mobility/authentication/RequestingNodeType;
      91: areturn
      92: getstatic     #9                  // Field sgsn:Lorg/mobicents/protocols/ss7/map/api/service/mobility/authentication/RequestingNodeType;
      95: areturn
      96: getstatic     #10                 // Field sCscf:Lorg/mobicents/protocols/ss7/map/api/service/mobility/authentication/RequestingNodeType;
      99: areturn
     100: getstatic     #11                 // Field bsf:Lorg/mobicents/protocols/ss7/map/api/service/mobility/authentication/RequestingNodeType;
     103: areturn
     104: getstatic     #12                 // Field ganAaaServer:Lorg/mobicents/protocols/ss7/map/api/service/mobility/authentication/RequestingNodeType;
     107: areturn
     108: getstatic     #13                 // Field wlanAaaaServer:Lorg/mobicents/protocols/ss7/map/api/service/mobility/authentication/RequestingNodeType;
     111: areturn
     112: getstatic     #14                 // Field mme:Lorg/mobicents/protocols/ss7/map/api/service/mobility/authentication/RequestingNodeType;
     115: areturn
     116: getstatic     #15                 // Field mmeSgsn:Lorg/mobicents/protocols/ss7/map/api/service/mobility/authentication/RequestingNodeType;
     119: areturn
     120: aconst_null
     121: areturn

  public int getCode();
    Code:
       0: aload_0
       1: getfield      #7                  // Field code:I
       4: ireturn

  static {};
    Code:
       0: new           #4                  // class org/mobicents/protocols/ss7/map/api/service/mobility/authentication/RequestingNodeType
       3: dup
       4: ldc           #16                 // String vlr
       6: iconst_0
       7: iconst_0
       8: invokespecial #17                 // Method "<init>":(Ljava/lang/String;II)V
      11: putstatic     #8                  // Field vlr:Lorg/mobicents/protocols/ss7/map/api/service/mobility/authentication/RequestingNodeType;
      14: new           #4                  // class org/mobicents/protocols/ss7/map/api/service/mobility/authentication/RequestingNodeType
      17: dup
      18: ldc           #18                 // String sgsn
      20: iconst_1
      21: iconst_1
      22: invokespecial #17                 // Method "<init>":(Ljava/lang/String;II)V
      25: putstatic     #9                  // Field sgsn:Lorg/mobicents/protocols/ss7/map/api/service/mobility/authentication/RequestingNodeType;
      28: new           #4                  // class org/mobicents/protocols/ss7/map/api/service/mobility/authentication/RequestingNodeType
      31: dup
      32: ldc           #19                 // String sCscf
      34: iconst_2
      35: iconst_2
      36: invokespecial #17                 // Method "<init>":(Ljava/lang/String;II)V
      39: putstatic     #10                 // Field sCscf:Lorg/mobicents/protocols/ss7/map/api/service/mobility/authentication/RequestingNodeType;
      42: new           #4                  // class org/mobicents/protocols/ss7/map/api/service/mobility/authentication/RequestingNodeType
      45: dup
      46: ldc           #20                 // String bsf
      48: iconst_3
      49: iconst_3
      50: invokespecial #17                 // Method "<init>":(Ljava/lang/String;II)V
      53: putstatic     #11                 // Field bsf:Lorg/mobicents/protocols/ss7/map/api/service/mobility/authentication/RequestingNodeType;
      56: new           #4                  // class org/mobicents/protocols/ss7/map/api/service/mobility/authentication/RequestingNodeType
      59: dup
      60: ldc           #21                 // String ganAaaServer
      62: iconst_4
      63: iconst_4
      64: invokespecial #17                 // Method "<init>":(Ljava/lang/String;II)V
      67: putstatic     #12                 // Field ganAaaServer:Lorg/mobicents/protocols/ss7/map/api/service/mobility/authentication/RequestingNodeType;
      70: new           #4                  // class org/mobicents/protocols/ss7/map/api/service/mobility/authentication/RequestingNodeType
      73: dup
      74: ldc           #22                 // String wlanAaaaServer
      76: iconst_5
      77: iconst_5
      78: invokespecial #17                 // Method "<init>":(Ljava/lang/String;II)V
      81: putstatic     #13                 // Field wlanAaaaServer:Lorg/mobicents/protocols/ss7/map/api/service/mobility/authentication/RequestingNodeType;
      84: new           #4                  // class org/mobicents/protocols/ss7/map/api/service/mobility/authentication/RequestingNodeType
      87: dup
      88: ldc           #23                 // String mme
      90: bipush        6
      92: bipush        16
      94: invokespecial #17                 // Method "<init>":(Ljava/lang/String;II)V
      97: putstatic     #14                 // Field mme:Lorg/mobicents/protocols/ss7/map/api/service/mobility/authentication/RequestingNodeType;
     100: new           #4                  // class org/mobicents/protocols/ss7/map/api/service/mobility/authentication/RequestingNodeType
     103: dup
     104: ldc           #24                 // String mmeSgsn
     106: bipush        7
     108: bipush        17
     110: invokespecial #17                 // Method "<init>":(Ljava/lang/String;II)V
     113: putstatic     #15                 // Field mmeSgsn:Lorg/mobicents/protocols/ss7/map/api/service/mobility/authentication/RequestingNodeType;
     116: bipush        8
     118: anewarray     #4                  // class org/mobicents/protocols/ss7/map/api/service/mobility/authentication/RequestingNodeType
     121: dup
     122: iconst_0
     123: getstatic     #8                  // Field vlr:Lorg/mobicents/protocols/ss7/map/api/service/mobility/authentication/RequestingNodeType;
     126: aastore
     127: dup
     128: iconst_1
     129: getstatic     #9                  // Field sgsn:Lorg/mobicents/protocols/ss7/map/api/service/mobility/authentication/RequestingNodeType;
     132: aastore
     133: dup
     134: iconst_2
     135: getstatic     #10                 // Field sCscf:Lorg/mobicents/protocols/ss7/map/api/service/mobility/authentication/RequestingNodeType;
     138: aastore
     139: dup
     140: iconst_3
     141: getstatic     #11                 // Field bsf:Lorg/mobicents/protocols/ss7/map/api/service/mobility/authentication/RequestingNodeType;
     144: aastore
     145: dup
     146: iconst_4
     147: getstatic     #12                 // Field ganAaaServer:Lorg/mobicents/protocols/ss7/map/api/service/mobility/authentication/RequestingNodeType;
     150: aastore
     151: dup
     152: iconst_5
     153: getstatic     #13                 // Field wlanAaaaServer:Lorg/mobicents/protocols/ss7/map/api/service/mobility/authentication/RequestingNodeType;
     156: aastore
     157: dup
     158: bipush        6
     160: getstatic     #14                 // Field mme:Lorg/mobicents/protocols/ss7/map/api/service/mobility/authentication/RequestingNodeType;
     163: aastore
     164: dup
     165: bipush        7
     167: getstatic     #15                 // Field mmeSgsn:Lorg/mobicents/protocols/ss7/map/api/service/mobility/authentication/RequestingNodeType;
     170: aastore
     171: putstatic     #1                  // Field $VALUES:[Lorg/mobicents/protocols/ss7/map/api/service/mobility/authentication/RequestingNodeType;
     174: return
}
