Compiled from "LocalChannel.java"
class io.netty.channel.local.LocalChannel$LocalUnsafe extends io.netty.channel.AbstractChannel$AbstractUnsafe {
  final io.netty.channel.local.LocalChannel this$0;

  private io.netty.channel.local.LocalChannel$LocalUnsafe(io.netty.channel.local.LocalChannel);
    Code:
       0: aload_0
       1: aload_1
       2: putfield      #2                  // Field this$0:Lio/netty/channel/local/LocalChannel;
       5: aload_0
       6: aload_1
       7: invokespecial #3                  // Method io/netty/channel/AbstractChannel$AbstractUnsafe."<init>":(Lio/netty/channel/AbstractChannel;)V
      10: return

  public void connect(java.net.SocketAddress, java.net.SocketAddress, io.netty.channel.ChannelPromise);
    Code:
       0: aload_3
       1: invokeinterface #4,  1            // InterfaceMethod io/netty/channel/ChannelPromise.setUncancellable:()Z
       6: ifeq          17
       9: aload_0
      10: aload_3
      11: invokevirtual #5                  // Method ensureOpen:(Lio/netty/channel/ChannelPromise;)Z
      14: ifne          18
      17: return
      18: aload_0
      19: getfield      #2                  // Field this$0:Lio/netty/channel/local/LocalChannel;
      22: invokestatic  #6                  // Method io/netty/channel/local/LocalChannel.access$500:(Lio/netty/channel/local/LocalChannel;)Lio/netty/channel/local/LocalChannel$State;
      25: getstatic     #7                  // Field io/netty/channel/local/LocalChannel$State.CONNECTED:Lio/netty/channel/local/LocalChannel$State;
      28: if_acmpne     63
      31: new           #8                  // class java/nio/channels/AlreadyConnectedException
      34: dup
      35: invokespecial #9                  // Method java/nio/channels/AlreadyConnectedException."<init>":()V
      38: astore        4
      40: aload_0
      41: aload_3
      42: aload         4
      44: invokevirtual #10                 // Method safeSetFailure:(Lio/netty/channel/ChannelPromise;Ljava/lang/Throwable;)V
      47: aload_0
      48: getfield      #2                  // Field this$0:Lio/netty/channel/local/LocalChannel;
      51: invokevirtual #11                 // Method io/netty/channel/local/LocalChannel.pipeline:()Lio/netty/channel/ChannelPipeline;
      54: aload         4
      56: invokeinterface #12,  2           // InterfaceMethod io/netty/channel/ChannelPipeline.fireExceptionCaught:(Ljava/lang/Throwable;)Lio/netty/channel/ChannelPipeline;
      61: pop
      62: return
      63: aload_0
      64: getfield      #2                  // Field this$0:Lio/netty/channel/local/LocalChannel;
      67: invokestatic  #13                 // Method io/netty/channel/local/LocalChannel.access$200:(Lio/netty/channel/local/LocalChannel;)Lio/netty/channel/ChannelPromise;
      70: ifnull        81
      73: new           #14                 // class java/nio/channels/ConnectionPendingException
      76: dup
      77: invokespecial #15                 // Method java/nio/channels/ConnectionPendingException."<init>":()V
      80: athrow
      81: aload_0
      82: getfield      #2                  // Field this$0:Lio/netty/channel/local/LocalChannel;
      85: aload_3
      86: invokestatic  #16                 // Method io/netty/channel/local/LocalChannel.access$202:(Lio/netty/channel/local/LocalChannel;Lio/netty/channel/ChannelPromise;)Lio/netty/channel/ChannelPromise;
      89: pop
      90: aload_0
      91: getfield      #2                  // Field this$0:Lio/netty/channel/local/LocalChannel;
      94: invokestatic  #6                  // Method io/netty/channel/local/LocalChannel.access$500:(Lio/netty/channel/local/LocalChannel;)Lio/netty/channel/local/LocalChannel$State;
      97: getstatic     #17                 // Field io/netty/channel/local/LocalChannel$State.BOUND:Lio/netty/channel/local/LocalChannel$State;
     100: if_acmpeq     119
     103: aload_2
     104: ifnonnull     119
     107: new           #18                 // class io/netty/channel/local/LocalAddress
     110: dup
     111: aload_0
     112: getfield      #2                  // Field this$0:Lio/netty/channel/local/LocalChannel;
     115: invokespecial #19                 // Method io/netty/channel/local/LocalAddress."<init>":(Lio/netty/channel/Channel;)V
     118: astore_2
     119: aload_2
     120: ifnull        152
     123: aload_0
     124: getfield      #2                  // Field this$0:Lio/netty/channel/local/LocalChannel;
     127: aload_2
     128: invokevirtual #20                 // Method io/netty/channel/local/LocalChannel.doBind:(Ljava/net/SocketAddress;)V
     131: goto          152
     134: astore        4
     136: aload_0
     137: aload_3
     138: aload         4
     140: invokevirtual #10                 // Method safeSetFailure:(Lio/netty/channel/ChannelPromise;Ljava/lang/Throwable;)V
     143: aload_0
     144: aload_0
     145: invokevirtual #22                 // Method voidPromise:()Lio/netty/channel/ChannelPromise;
     148: invokevirtual #23                 // Method close:(Lio/netty/channel/ChannelPromise;)V
     151: return
     152: aload_1
     153: invokestatic  #24                 // Method io/netty/channel/local/LocalChannelRegistry.get:(Ljava/net/SocketAddress;)Lio/netty/channel/Channel;
     156: astore        4
     158: aload         4
     160: instanceof    #25                 // class io/netty/channel/local/LocalServerChannel
     163: ifne          210
     166: new           #26                 // class java/net/ConnectException
     169: dup
     170: new           #27                 // class java/lang/StringBuilder
     173: dup
     174: invokespecial #28                 // Method java/lang/StringBuilder."<init>":()V
     177: ldc           #29                 // String connection refused:
     179: invokevirtual #30                 // Method java/lang/StringBuilder.append:(Ljava/lang/String;)Ljava/lang/StringBuilder;
     182: aload_1
     183: invokevirtual #31                 // Method java/lang/StringBuilder.append:(Ljava/lang/Object;)Ljava/lang/StringBuilder;
     186: invokevirtual #32                 // Method java/lang/StringBuilder.toString:()Ljava/lang/String;
     189: invokespecial #33                 // Method java/net/ConnectException."<init>":(Ljava/lang/String;)V
     192: astore        5
     194: aload_0
     195: aload_3
     196: aload         5
     198: invokevirtual #10                 // Method safeSetFailure:(Lio/netty/channel/ChannelPromise;Ljava/lang/Throwable;)V
     201: aload_0
     202: aload_0
     203: invokevirtual #22                 // Method voidPromise:()Lio/netty/channel/ChannelPromise;
     206: invokevirtual #23                 // Method close:(Lio/netty/channel/ChannelPromise;)V
     209: return
     210: aload         4
     212: checkcast     #25                 // class io/netty/channel/local/LocalServerChannel
     215: astore        5
     217: aload_0
     218: getfield      #2                  // Field this$0:Lio/netty/channel/local/LocalChannel;
     221: aload         5
     223: aload_0
     224: getfield      #2                  // Field this$0:Lio/netty/channel/local/LocalChannel;
     227: invokevirtual #34                 // Method io/netty/channel/local/LocalServerChannel.serve:(Lio/netty/channel/local/LocalChannel;)Lio/netty/channel/local/LocalChannel;
     230: invokestatic  #35                 // Method io/netty/channel/local/LocalChannel.access$602:(Lio/netty/channel/local/LocalChannel;Lio/netty/channel/local/LocalChannel;)Lio/netty/channel/local/LocalChannel;
     233: pop
     234: return
    Exception table:
       from    to  target type
         123   131   134   Class java/lang/Throwable

  io.netty.channel.local.LocalChannel$LocalUnsafe(io.netty.channel.local.LocalChannel, io.netty.channel.local.LocalChannel$1);
    Code:
       0: aload_0
       1: aload_1
       2: invokespecial #1                  // Method "<init>":(Lio/netty/channel/local/LocalChannel;)V
       5: return
}
