Compiled from "LocalChannel.java"
class io.netty.channel.local.LocalChannel$2 implements java.lang.Runnable {
  final io.netty.channel.local.LocalChannel this$0;

  io.netty.channel.local.LocalChannel$2(io.netty.channel.local.LocalChannel);
    Code:
       0: aload_0
       1: aload_1
       2: putfield      #1                  // Field this$0:Lio/netty/channel/local/LocalChannel;
       5: aload_0
       6: invokespecial #2                  // Method java/lang/Object."<init>":()V
       9: return

  public void run();
    Code:
       0: aload_0
       1: getfield      #1                  // Field this$0:Lio/netty/channel/local/LocalChannel;
       4: invokevirtual #3                  // Method io/netty/channel/local/LocalChannel.unsafe:()Lio/netty/channel/Channel$Unsafe;
       7: aload_0
       8: getfield      #1                  // Field this$0:Lio/netty/channel/local/LocalChannel;
      11: invokevirtual #3                  // Method io/netty/channel/local/LocalChannel.unsafe:()Lio/netty/channel/Channel$Unsafe;
      14: invokeinterface #4,  1            // InterfaceMethod io/netty/channel/Channel$Unsafe.voidPromise:()Lio/netty/channel/ChannelPromise;
      19: invokeinterface #5,  2            // InterfaceMethod io/netty/channel/Channel$Unsafe.close:(Lio/netty/channel/ChannelPromise;)V
      24: return
}
