Compiled from "ValidationConfigStaxBuilder.java"
class org.hibernate.validator.internal.xml.config.ValidationConfigStaxBuilder$PropertyStaxBuilder extends org.hibernate.validator.internal.xml.AbstractStaxBuilder {
  private static final java.lang.String PROPERTY_QNAME_LOCAL_PART;

  private static final javax.xml.namespace.QName NAME_QNAME;

  private final java.util.Map<java.lang.String, java.lang.String> properties;

  private org.hibernate.validator.internal.xml.config.ValidationConfigStaxBuilder$PropertyStaxBuilder();
    Code:
       0: aload_0
       1: invokespecial #2                  // Method org/hibernate/validator/internal/xml/AbstractStaxBuilder."<init>":()V
       4: aload_0
       5: new           #3                  // class java/util/HashMap
       8: dup
       9: invokespecial #4                  // Method java/util/HashMap."<init>":()V
      12: putfield      #5                  // Field properties:Ljava/util/Map;
      15: return

  protected java.lang.String getAcceptableQName();
    Code:
       0: ldc           #7                  // String property
       2: areturn

  protected void add(javax.xml.stream.XMLEventReader, javax.xml.stream.events.XMLEvent) throws javax.xml.stream.XMLStreamException;
    Code:
       0: aload_2
       1: invokeinterface #8,  1            // InterfaceMethod javax/xml/stream/events/XMLEvent.asStartElement:()Ljavax/xml/stream/events/StartElement;
       6: astore_3
       7: aload_0
       8: aload_3
       9: getstatic     #9                  // Field NAME_QNAME:Ljavax/xml/namespace/QName;
      12: invokevirtual #10                 // Method readAttribute:(Ljavax/xml/stream/events/StartElement;Ljavax/xml/namespace/QName;)Ljava/util/Optional;
      15: invokevirtual #11                 // Method java/util/Optional.get:()Ljava/lang/Object;
      18: checkcast     #12                 // class java/lang/String
      21: astore        4
      23: aload_0
      24: aload_1
      25: invokevirtual #13                 // Method readSingleElement:(Ljavax/xml/stream/XMLEventReader;)Ljava/lang/String;
      28: astore        5
      30: invokestatic  #14                 // Method org/hibernate/validator/internal/xml/config/ValidationConfigStaxBuilder.access$500:()Lorg/hibernate/validator/internal/util/logging/Log;
      33: invokeinterface #15,  1           // InterfaceMethod org/hibernate/validator/internal/util/logging/Log.isDebugEnabled:()Z
      38: ifeq          55
      41: invokestatic  #14                 // Method org/hibernate/validator/internal/xml/config/ValidationConfigStaxBuilder.access$500:()Lorg/hibernate/validator/internal/util/logging/Log;
      44: ldc           #16                 // String Found property \'%s\' with value \'%s\' in validation.xml.
      46: aload         4
      48: aload         5
      50: invokeinterface #17,  4           // InterfaceMethod org/hibernate/validator/internal/util/logging/Log.debugf:(Ljava/lang/String;Ljava/lang/Object;Ljava/lang/Object;)V
      55: aload_0
      56: getfield      #5                  // Field properties:Ljava/util/Map;
      59: aload         4
      61: aload         5
      63: invokeinterface #18,  3           // InterfaceMethod java/util/Map.put:(Ljava/lang/Object;Ljava/lang/Object;)Ljava/lang/Object;
      68: pop
      69: return

  public java.util.Map<java.lang.String, java.lang.String> build();
    Code:
       0: aload_0
       1: getfield      #5                  // Field properties:Ljava/util/Map;
       4: areturn

  org.hibernate.validator.internal.xml.config.ValidationConfigStaxBuilder$PropertyStaxBuilder(org.hibernate.validator.internal.xml.config.ValidationConfigStaxBuilder$1);
    Code:
       0: aload_0
       1: invokespecial #1                  // Method "<init>":()V
       4: return

  static {};
    Code:
       0: new           #19                 // class javax/xml/namespace/QName
       3: dup
       4: ldc           #20                 // String name
       6: invokespecial #21                 // Method javax/xml/namespace/QName."<init>":(Ljava/lang/String;)V
       9: putstatic     #9                  // Field NAME_QNAME:Ljavax/xml/namespace/QName;
      12: return
}
