Compiled from "EventToViewTestCase.java"
public class juzu.impl.bridge.portlet.EventToViewTestCase extends juzu.test.AbstractWebTestCase {
  java.net.URL deploymentURL;

  org.openqa.selenium.WebDriver driver;

  public juzu.impl.bridge.portlet.EventToViewTestCase();
    Code:
       0: aload_0
       1: invokespecial #1                  // Method juzu/test/AbstractWebTestCase."<init>":()V
       4: return

  public static org.jboss.shrinkwrap.api.spec.WebArchive createDeployment();
    Code:
       0: invokestatic  #2                  // Method java/lang/Thread.currentThread:()Ljava/lang/Thread;
       3: invokevirtual #3                  // Method java/lang/Thread.getContextClassLoader:()Ljava/lang/ClassLoader;
       6: ldc           #4                  // String bridge/portlet/event/view/portlet.xml
       8: invokevirtual #5                  // Method java/lang/ClassLoader.getResource:(Ljava/lang/String;)Ljava/net/URL;
      11: astore_0
      12: ldc           #6                  // String bridge.portlet.event.view
      14: aload_0
      15: invokestatic  #7                  // Method createPortletDeployment:(Ljava/lang/String;Ljava/net/URL;)Lorg/jboss/shrinkwrap/api/spec/WebArchive;
      18: areturn

  public void testFoo() throws java.lang.Exception;
    Code:
       0: aload_0
       1: getfield      #8                  // Field driver:Lorg/openqa/selenium/WebDriver;
       4: aload_0
       5: invokevirtual #9                  // Method getPortletURL:()Ljava/net/URL;
       8: invokevirtual #10                 // Method java/net/URL.toString:()Ljava/lang/String;
      11: invokeinterface #11,  2           // InterfaceMethod org/openqa/selenium/WebDriver.get:(Ljava/lang/String;)V
      16: aload_0
      17: getfield      #8                  // Field driver:Lorg/openqa/selenium/WebDriver;
      20: ldc           #12                 // String trigger
      22: invokestatic  #13                 // Method org/openqa/selenium/By.id:(Ljava/lang/String;)Lorg/openqa/selenium/By;
      25: invokeinterface #14,  2           // InterfaceMethod org/openqa/selenium/WebDriver.findElement:(Lorg/openqa/selenium/By;)Lorg/openqa/selenium/WebElement;
      30: astore_1
      31: aload_1
      32: invokeinterface #15,  1           // InterfaceMethod org/openqa/selenium/WebElement.click:()V
      37: aload_0
      38: getfield      #8                  // Field driver:Lorg/openqa/selenium/WebDriver;
      41: invokeinterface #16,  1           // InterfaceMethod org/openqa/selenium/WebDriver.getPageSource:()Ljava/lang/String;
      46: astore_2
      47: new           #17                 // class java/lang/StringBuilder
      50: dup
      51: invokespecial #18                 // Method java/lang/StringBuilder."<init>":()V
      54: ldc           #19                 // String Was expecting
      56: invokevirtual #20                 // Method java/lang/StringBuilder.append:(Ljava/lang/String;)Ljava/lang/StringBuilder;
      59: aload_2
      60: invokevirtual #20                 // Method java/lang/StringBuilder.append:(Ljava/lang/String;)Ljava/lang/StringBuilder;
      63: ldc           #21                 // String  to contain \'done:foo\'
      65: invokevirtual #20                 // Method java/lang/StringBuilder.append:(Ljava/lang/String;)Ljava/lang/StringBuilder;
      68: invokevirtual #22                 // Method java/lang/StringBuilder.toString:()Ljava/lang/String;
      71: aload_2
      72: ldc           #23                 // String done: foo
      74: invokevirtual #24                 // Method java/lang/String.contains:(Ljava/lang/CharSequence;)Z
      77: invokestatic  #25                 // Method assertTrue:(Ljava/lang/String;Z)V
      80: return
}
