Compiled from "OperationFormatException.java"
public class org.jboss.as.cli.operation.OperationFormatException extends org.jboss.as.cli.CommandFormatException {
  private static final long serialVersionUID;

  public org.jboss.as.cli.operation.OperationFormatException(java.lang.String, java.lang.Throwable);
    Code:
       0: aload_0
       1: aload_1
       2: aload_2
       3: invokespecial #1                  // Method org/jboss/as/cli/CommandFormatException."<init>":(Ljava/lang/String;Ljava/lang/Throwable;)V
       6: return

  public org.jboss.as.cli.operation.OperationFormatException(java.lang.String);
    Code:
       0: aload_0
       1: aload_1
       2: invokespecial #2                  // Method org/jboss/as/cli/CommandFormatException."<init>":(Ljava/lang/String;)V
       5: return

  public org.jboss.as.cli.operation.OperationFormatException(java.lang.Throwable);
    Code:
       0: aload_0
       1: aload_1
       2: invokespecial #3                  // Method org/jboss/as/cli/CommandFormatException."<init>":(Ljava/lang/Throwable;)V
       5: return
}
