Compiled from "GroovyPageResourceScriptSource.java"
public class org.grails.gsp.io.GroovyPageResourceScriptSource extends org.springframework.scripting.support.ResourceScriptSource implements org.grails.gsp.io.GroovyPageScriptSource {
  private java.lang.String uri;

  private boolean isPublic;

  public org.grails.gsp.io.GroovyPageResourceScriptSource(java.lang.String, org.springframework.core.io.Resource);
    Code:
       0: aload_0
       1: aload_2
       2: invokespecial #1                  // Method org/springframework/scripting/support/ResourceScriptSource."<init>":(Lorg/springframework/core/io/Resource;)V
       5: aload_0
       6: aload_1
       7: putfield      #2                  // Field uri:Ljava/lang/String;
      10: aload_0
      11: invokevirtual #3                  // Method getResource:()Lorg/springframework/core/io/Resource;
      14: invokeinterface #4,  1            // InterfaceMethod org/springframework/core/io/Resource.getURL:()Ljava/net/URL;
      19: astore_3
      20: aload_3
      21: ifnonnull     35
      24: aload_0
      25: aload_1
      26: invokestatic  #5                  // Method isPublicPath:(Ljava/lang/String;)Z
      29: putfield      #6                  // Field isPublic:Z
      32: goto          46
      35: aload_0
      36: aload_3
      37: invokevirtual #7                  // Method java/net/URL.getPath:()Ljava/lang/String;
      40: invokestatic  #5                  // Method isPublicPath:(Ljava/lang/String;)Z
      43: putfield      #6                  // Field isPublic:Z
      46: goto          58
      49: astore_3
      50: aload_0
      51: aload_1
      52: invokestatic  #5                  // Method isPublicPath:(Ljava/lang/String;)Z
      55: putfield      #6                  // Field isPublic:Z
      58: return
    Exception table:
       from    to  target type
          10    46    49   Class java/io/IOException

  public static boolean isPublicPath(java.lang.String);
    Code:
       0: aload_0
       1: ldc           #9                  // String /WEB-INF
       3: invokevirtual #10                 // Method java/lang/String.contains:(Ljava/lang/CharSequence;)Z
       6: ifne          22
       9: aload_0
      10: ldc           #11                 // String grails-app/views/
      12: invokevirtual #10                 // Method java/lang/String.contains:(Ljava/lang/CharSequence;)Z
      15: ifne          22
      18: iconst_1
      19: goto          23
      22: iconst_0
      23: ireturn

  public java.lang.String getURI();
    Code:
       0: aload_0
       1: getfield      #2                  // Field uri:Ljava/lang/String;
       4: areturn

  public boolean isPublic();
    Code:
       0: aload_0
       1: getfield      #6                  // Field isPublic:Z
       4: ireturn
}
