Compiled from "PdfBoxGraphics2DFontTextDrawerDefaultFonts.java"
public class de.rototor.pdfbox.graphics2d.PdfBoxGraphics2DFontTextDrawerDefaultFonts extends de.rototor.pdfbox.graphics2d.PdfBoxGraphics2DFontTextDrawer {
  public de.rototor.pdfbox.graphics2d.PdfBoxGraphics2DFontTextDrawerDefaultFonts();
    Code:
       0: aload_0
       1: invokespecial #1                  // Method de/rototor/pdfbox/graphics2d/PdfBoxGraphics2DFontTextDrawer."<init>":()V
       4: return

  protected org.apache.pdfbox.pdmodel.font.PDFont mapFont(java.awt.Font, de.rototor.pdfbox.graphics2d.IPdfBoxGraphics2DFontTextDrawer$IFontTextDrawerEnv) throws java.io.IOException, java.awt.FontFormatException;
    Code:
       0: aload_1
       1: invokestatic  #2                  // Method mapDefaultFonts:(Ljava/awt/Font;)Lorg/apache/pdfbox/pdmodel/font/PDFont;
       4: astore_3
       5: aload_3
       6: ifnull        11
       9: aload_3
      10: areturn
      11: aload_0
      12: aload_1
      13: aload_2
      14: invokespecial #3                  // Method de/rototor/pdfbox/graphics2d/PdfBoxGraphics2DFontTextDrawer.mapFont:(Ljava/awt/Font;Lde/rototor/pdfbox/graphics2d/IPdfBoxGraphics2DFontTextDrawer$IFontTextDrawerEnv;)Lorg/apache/pdfbox/pdmodel/font/PDFont;
      17: astore_3
      18: aload_3
      19: ifnull        24
      22: aload_3
      23: areturn
      24: aload_1
      25: invokestatic  #4                  // Method chooseMatchingHelvetica:(Ljava/awt/Font;)Lorg/apache/pdfbox/pdmodel/font/PDFont;
      28: areturn

  public static org.apache.pdfbox.pdmodel.font.PDFont mapDefaultFonts(java.awt.Font);
    Code:
       0: aload_0
       1: iconst_5
       2: anewarray     #5                  // class java/lang/String
       5: dup
       6: iconst_0
       7: ldc           #7                  // String SansSerif
       9: aastore
      10: dup
      11: iconst_1
      12: ldc           #8                  // String Dialog
      14: aastore
      15: dup
      16: iconst_2
      17: ldc           #9                  // String DialogInput
      19: aastore
      20: dup
      21: iconst_3
      22: ldc           #10                 // String Arial
      24: aastore
      25: dup
      26: iconst_4
      27: ldc           #11                 // String Helvetica
      29: aastore
      30: invokestatic  #12                 // Method fontNameEqualsAnyOf:(Ljava/awt/Font;[Ljava/lang/String;)Z
      33: ifeq          41
      36: aload_0
      37: invokestatic  #4                  // Method chooseMatchingHelvetica:(Ljava/awt/Font;)Lorg/apache/pdfbox/pdmodel/font/PDFont;
      40: areturn
      41: aload_0
      42: iconst_3
      43: anewarray     #5                  // class java/lang/String
      46: dup
      47: iconst_0
      48: ldc           #13                 // String Monospaced
      50: aastore
      51: dup
      52: iconst_1
      53: ldc           #14                 // String courier
      55: aastore
      56: dup
      57: iconst_2
      58: ldc           #15                 // String courier new
      60: aastore
      61: invokestatic  #12                 // Method fontNameEqualsAnyOf:(Ljava/awt/Font;[Ljava/lang/String;)Z
      64: ifeq          72
      67: aload_0
      68: invokestatic  #16                 // Method chooseMatchingCourier:(Ljava/awt/Font;)Lorg/apache/pdfbox/pdmodel/font/PDFont;
      71: areturn
      72: aload_0
      73: iconst_4
      74: anewarray     #5                  // class java/lang/String
      77: dup
      78: iconst_0
      79: ldc           #17                 // String Serif
      81: aastore
      82: dup
      83: iconst_1
      84: ldc           #18                 // String Times
      86: aastore
      87: dup
      88: iconst_2
      89: ldc           #19                 // String Times New Roman
      91: aastore
      92: dup
      93: iconst_3
      94: ldc           #20                 // String Times Roman
      96: aastore
      97: invokestatic  #12                 // Method fontNameEqualsAnyOf:(Ljava/awt/Font;[Ljava/lang/String;)Z
     100: ifeq          108
     103: aload_0
     104: invokestatic  #21                 // Method chooseMatchingTimes:(Ljava/awt/Font;)Lorg/apache/pdfbox/pdmodel/font/PDFont;
     107: areturn
     108: aload_0
     109: iconst_1
     110: anewarray     #5                  // class java/lang/String
     113: dup
     114: iconst_0
     115: ldc           #22                 // String Symbol
     117: aastore
     118: invokestatic  #12                 // Method fontNameEqualsAnyOf:(Ljava/awt/Font;[Ljava/lang/String;)Z
     121: ifeq          128
     124: getstatic     #23                 // Field org/apache/pdfbox/pdmodel/font/PDType1Font.SYMBOL:Lorg/apache/pdfbox/pdmodel/font/PDType1Font;
     127: areturn
     128: aload_0
     129: iconst_2
     130: anewarray     #5                  // class java/lang/String
     133: dup
     134: iconst_0
     135: ldc           #24                 // String ZapfDingbats
     137: aastore
     138: dup
     139: iconst_1
     140: ldc           #25                 // String Dingbats
     142: aastore
     143: invokestatic  #12                 // Method fontNameEqualsAnyOf:(Ljava/awt/Font;[Ljava/lang/String;)Z
     146: ifeq          153
     149: getstatic     #26                 // Field org/apache/pdfbox/pdmodel/font/PDType1Font.ZAPF_DINGBATS:Lorg/apache/pdfbox/pdmodel/font/PDType1Font;
     152: areturn
     153: aconst_null
     154: areturn

  private static boolean fontNameEqualsAnyOf(java.awt.Font, java.lang.String...);
    Code:
       0: aload_0
       1: invokevirtual #27                 // Method java/awt/Font.getName:()Ljava/lang/String;
       4: astore_2
       5: aload_1
       6: astore_3
       7: aload_3
       8: arraylength
       9: istore        4
      11: iconst_0
      12: istore        5
      14: iload         5
      16: iload         4
      18: if_icmpge     44
      21: aload_3
      22: iload         5
      24: aaload
      25: astore        6
      27: aload         6
      29: aload_2
      30: invokevirtual #28                 // Method java/lang/String.equalsIgnoreCase:(Ljava/lang/String;)Z
      33: ifeq          38
      36: iconst_1
      37: ireturn
      38: iinc          5, 1
      41: goto          14
      44: iconst_0
      45: ireturn

  public static org.apache.pdfbox.pdmodel.font.PDFont chooseMatchingTimes(java.awt.Font);
    Code:
       0: aload_0
       1: invokevirtual #29                 // Method java/awt/Font.getStyle:()I
       4: iconst_3
       5: iand
       6: iconst_3
       7: if_icmpne     14
      10: getstatic     #30                 // Field org/apache/pdfbox/pdmodel/font/PDType1Font.TIMES_BOLD_ITALIC:Lorg/apache/pdfbox/pdmodel/font/PDType1Font;
      13: areturn
      14: aload_0
      15: invokevirtual #29                 // Method java/awt/Font.getStyle:()I
      18: iconst_2
      19: iand
      20: iconst_2
      21: if_icmpne     28
      24: getstatic     #31                 // Field org/apache/pdfbox/pdmodel/font/PDType1Font.TIMES_ITALIC:Lorg/apache/pdfbox/pdmodel/font/PDType1Font;
      27: areturn
      28: aload_0
      29: invokevirtual #29                 // Method java/awt/Font.getStyle:()I
      32: iconst_1
      33: iand
      34: iconst_1
      35: if_icmpne     42
      38: getstatic     #32                 // Field org/apache/pdfbox/pdmodel/font/PDType1Font.TIMES_BOLD:Lorg/apache/pdfbox/pdmodel/font/PDType1Font;
      41: areturn
      42: getstatic     #33                 // Field org/apache/pdfbox/pdmodel/font/PDType1Font.TIMES_ROMAN:Lorg/apache/pdfbox/pdmodel/font/PDType1Font;
      45: areturn

  public static org.apache.pdfbox.pdmodel.font.PDFont chooseMatchingCourier(java.awt.Font);
    Code:
       0: aload_0
       1: invokevirtual #29                 // Method java/awt/Font.getStyle:()I
       4: iconst_3
       5: iand
       6: iconst_3
       7: if_icmpne     14
      10: getstatic     #34                 // Field org/apache/pdfbox/pdmodel/font/PDType1Font.COURIER_BOLD_OBLIQUE:Lorg/apache/pdfbox/pdmodel/font/PDType1Font;
      13: areturn
      14: aload_0
      15: invokevirtual #29                 // Method java/awt/Font.getStyle:()I
      18: iconst_2
      19: iand
      20: iconst_2
      21: if_icmpne     28
      24: getstatic     #35                 // Field org/apache/pdfbox/pdmodel/font/PDType1Font.COURIER_OBLIQUE:Lorg/apache/pdfbox/pdmodel/font/PDType1Font;
      27: areturn
      28: aload_0
      29: invokevirtual #29                 // Method java/awt/Font.getStyle:()I
      32: iconst_1
      33: iand
      34: iconst_1
      35: if_icmpne     42
      38: getstatic     #36                 // Field org/apache/pdfbox/pdmodel/font/PDType1Font.COURIER_BOLD:Lorg/apache/pdfbox/pdmodel/font/PDType1Font;
      41: areturn
      42: getstatic     #37                 // Field org/apache/pdfbox/pdmodel/font/PDType1Font.COURIER:Lorg/apache/pdfbox/pdmodel/font/PDType1Font;
      45: areturn

  public static org.apache.pdfbox.pdmodel.font.PDFont chooseMatchingHelvetica(java.awt.Font);
    Code:
       0: aload_0
       1: invokevirtual #29                 // Method java/awt/Font.getStyle:()I
       4: iconst_3
       5: iand
       6: iconst_3
       7: if_icmpne     14
      10: getstatic     #38                 // Field org/apache/pdfbox/pdmodel/font/PDType1Font.HELVETICA_BOLD_OBLIQUE:Lorg/apache/pdfbox/pdmodel/font/PDType1Font;
      13: areturn
      14: aload_0
      15: invokevirtual #29                 // Method java/awt/Font.getStyle:()I
      18: iconst_2
      19: iand
      20: iconst_2
      21: if_icmpne     28
      24: getstatic     #39                 // Field org/apache/pdfbox/pdmodel/font/PDType1Font.HELVETICA_OBLIQUE:Lorg/apache/pdfbox/pdmodel/font/PDType1Font;
      27: areturn
      28: aload_0
      29: invokevirtual #29                 // Method java/awt/Font.getStyle:()I
      32: iconst_1
      33: iand
      34: iconst_1
      35: if_icmpne     42
      38: getstatic     #40                 // Field org/apache/pdfbox/pdmodel/font/PDType1Font.HELVETICA_BOLD:Lorg/apache/pdfbox/pdmodel/font/PDType1Font;
      41: areturn
      42: getstatic     #41                 // Field org/apache/pdfbox/pdmodel/font/PDType1Font.HELVETICA:Lorg/apache/pdfbox/pdmodel/font/PDType1Font;
      45: areturn
}
