Compiled from "DetachableStreamSourceChannel.java"
class io.undertow.channels.DetachableStreamSourceChannel$SetterDelegatingListener implements org.xnio.ChannelListener<org.xnio.channels.StreamSourceChannel> {
  private final org.xnio.ChannelListener$SimpleSetter<org.xnio.channels.StreamSourceChannel> setter;

  private final org.xnio.channels.StreamSourceChannel channel;

  io.undertow.channels.DetachableStreamSourceChannel$SetterDelegatingListener(org.xnio.ChannelListener$SimpleSetter<org.xnio.channels.StreamSourceChannel>, org.xnio.channels.StreamSourceChannel);
    Code:
       0: aload_0
       1: invokespecial #1                  // Method java/lang/Object."<init>":()V
       4: aload_0
       5: aload_1
       6: putfield      #2                  // Field setter:Lorg/xnio/ChannelListener$SimpleSetter;
       9: aload_0
      10: aload_2
      11: putfield      #3                  // Field channel:Lorg/xnio/channels/StreamSourceChannel;
      14: return

  public void handleEvent(org.xnio.channels.StreamSourceChannel);
    Code:
       0: aload_0
       1: getfield      #2                  // Field setter:Lorg/xnio/ChannelListener$SimpleSetter;
       4: invokevirtual #4                  // Method org/xnio/ChannelListener$SimpleSetter.get:()Lorg/xnio/ChannelListener;
       7: astore_2
       8: aload_2
       9: ifnull        24
      12: aload_0
      13: getfield      #3                  // Field channel:Lorg/xnio/channels/StreamSourceChannel;
      16: aload_2
      17: invokestatic  #5                  // Method org/xnio/ChannelListeners.invokeChannelListener:(Ljava/nio/channels/Channel;Lorg/xnio/ChannelListener;)Z
      20: pop
      21: goto          41
      24: getstatic     #6                  // Field io/undertow/UndertowLogger.REQUEST_LOGGER:Lio/undertow/UndertowLogger;
      27: ldc           #7                  // String suspending reads on %s to prevent listener runaway
      29: aload_1
      30: invokeinterface #8,  3            // InterfaceMethod io/undertow/UndertowLogger.debugf:(Ljava/lang/String;Ljava/lang/Object;)V
      35: aload_1
      36: invokeinterface #9,  1            // InterfaceMethod org/xnio/channels/StreamSourceChannel.suspendReads:()V
      41: return

  public java.lang.String toString();
    Code:
       0: new           #10                 // class java/lang/StringBuilder
       3: dup
       4: invokespecial #11                 // Method java/lang/StringBuilder."<init>":()V
       7: ldc           #12                 // String Setter delegating channel listener ->
       9: invokevirtual #13                 // Method java/lang/StringBuilder.append:(Ljava/lang/String;)Ljava/lang/StringBuilder;
      12: aload_0
      13: getfield      #2                  // Field setter:Lorg/xnio/ChannelListener$SimpleSetter;
      16: invokevirtual #14                 // Method java/lang/StringBuilder.append:(Ljava/lang/Object;)Ljava/lang/StringBuilder;
      19: invokevirtual #15                 // Method java/lang/StringBuilder.toString:()Ljava/lang/String;
      22: areturn

  public void handleEvent(java.nio.channels.Channel);
    Code:
       0: aload_0
       1: aload_1
       2: checkcast     #16                 // class org/xnio/channels/StreamSourceChannel
       5: invokevirtual #17                 // Method handleEvent:(Lorg/xnio/channels/StreamSourceChannel;)V
       8: return
}
