public class org.bouncycastle.asn1.dvcs.DVCSCertInfoBuilder {
  private int version;

  private org.bouncycastle.asn1.dvcs.DVCSRequestInformation dvReqInfo;

  private org.bouncycastle.asn1.x509.DigestInfo messageImprint;

  private org.bouncycastle.asn1.ASN1Integer serialNumber;

  private org.bouncycastle.asn1.dvcs.DVCSTime responseTime;

  private org.bouncycastle.asn1.cmp.PKIStatusInfo dvStatus;

  private org.bouncycastle.asn1.x509.PolicyInformation policy;

  private org.bouncycastle.asn1.ASN1Set reqSignature;

  private org.bouncycastle.asn1.ASN1Sequence certs;

  private org.bouncycastle.asn1.x509.Extensions extensions;

  private static final int DEFAULT_VERSION;

  private static final int TAG_DV_STATUS;

  private static final int TAG_POLICY;

  private static final int TAG_REQ_SIGNATURE;

  private static final int TAG_CERTS;

  public org.bouncycastle.asn1.dvcs.DVCSCertInfoBuilder(org.bouncycastle.asn1.dvcs.DVCSRequestInformation, org.bouncycastle.asn1.x509.DigestInfo, org.bouncycastle.asn1.ASN1Integer, org.bouncycastle.asn1.dvcs.DVCSTime);
    Code:
       0: aload_0
       1: invokespecial #105                // Method java/lang/Object."<init>":()V
       4: aload_0
       5: iconst_1
       6: putfield      #95                 // Field version:I
       9: aload_0
      10: aload_1
      11: putfield      #100                // Field dvReqInfo:Lorg/bouncycastle/asn1/dvcs/DVCSRequestInformation;
      14: aload_0
      15: aload_2
      16: putfield      #102                // Field messageImprint:Lorg/bouncycastle/asn1/x509/DigestInfo;
      19: aload_0
      20: aload_3
      21: putfield      #96                 // Field serialNumber:Lorg/bouncycastle/asn1/ASN1Integer;
      24: aload_0
      25: aload         4
      27: putfield      #101                // Field responseTime:Lorg/bouncycastle/asn1/dvcs/DVCSTime;
      30: return

  public org.bouncycastle.asn1.dvcs.DVCSCertInfo build();
    Code:
       0: new           #46                 // class org/bouncycastle/asn1/ASN1EncodableVector
       3: dup
       4: bipush        10
       6: invokespecial #106                // Method org/bouncycastle/asn1/ASN1EncodableVector."<init>":(I)V
       9: astore_1
      10: aload_0
      11: getfield      #95                 // Field version:I
      14: iconst_1
      15: if_icmpeq     34
      18: aload_1
      19: new           #47                 // class org/bouncycastle/asn1/ASN1Integer
      22: dup
      23: aload_0
      24: getfield      #95                 // Field version:I
      27: i2l
      28: invokespecial #108                // Method org/bouncycastle/asn1/ASN1Integer."<init>":(J)V
      31: invokevirtual #107                // Method org/bouncycastle/asn1/ASN1EncodableVector.add:(Lorg/bouncycastle/asn1/ASN1Encodable;)V
      34: aload_1
      35: aload_0
      36: getfield      #100                // Field dvReqInfo:Lorg/bouncycastle/asn1/dvcs/DVCSRequestInformation;
      39: invokevirtual #107                // Method org/bouncycastle/asn1/ASN1EncodableVector.add:(Lorg/bouncycastle/asn1/ASN1Encodable;)V
      42: aload_1
      43: aload_0
      44: getfield      #102                // Field messageImprint:Lorg/bouncycastle/asn1/x509/DigestInfo;
      47: invokevirtual #107                // Method org/bouncycastle/asn1/ASN1EncodableVector.add:(Lorg/bouncycastle/asn1/ASN1Encodable;)V
      50: aload_1
      51: aload_0
      52: getfield      #96                 // Field serialNumber:Lorg/bouncycastle/asn1/ASN1Integer;
      55: invokevirtual #107                // Method org/bouncycastle/asn1/ASN1EncodableVector.add:(Lorg/bouncycastle/asn1/ASN1Encodable;)V
      58: aload_1
      59: aload_0
      60: getfield      #101                // Field responseTime:Lorg/bouncycastle/asn1/dvcs/DVCSTime;
      63: invokevirtual #107                // Method org/bouncycastle/asn1/ASN1EncodableVector.add:(Lorg/bouncycastle/asn1/ASN1Encodable;)V
      66: aload_0
      67: getfield      #99                 // Field dvStatus:Lorg/bouncycastle/asn1/cmp/PKIStatusInfo;
      70: ifnull        90
      73: aload_1
      74: new           #49                 // class org/bouncycastle/asn1/DERTaggedObject
      77: dup
      78: iconst_0
      79: iconst_0
      80: aload_0
      81: getfield      #99                 // Field dvStatus:Lorg/bouncycastle/asn1/cmp/PKIStatusInfo;
      84: invokespecial #111                // Method org/bouncycastle/asn1/DERTaggedObject."<init>":(ZILorg/bouncycastle/asn1/ASN1Encodable;)V
      87: invokevirtual #107                // Method org/bouncycastle/asn1/ASN1EncodableVector.add:(Lorg/bouncycastle/asn1/ASN1Encodable;)V
      90: aload_0
      91: getfield      #104                // Field policy:Lorg/bouncycastle/asn1/x509/PolicyInformation;
      94: ifnull        114
      97: aload_1
      98: new           #49                 // class org/bouncycastle/asn1/DERTaggedObject
     101: dup
     102: iconst_0
     103: iconst_1
     104: aload_0
     105: getfield      #104                // Field policy:Lorg/bouncycastle/asn1/x509/PolicyInformation;
     108: invokespecial #111                // Method org/bouncycastle/asn1/DERTaggedObject."<init>":(ZILorg/bouncycastle/asn1/ASN1Encodable;)V
     111: invokevirtual #107                // Method org/bouncycastle/asn1/ASN1EncodableVector.add:(Lorg/bouncycastle/asn1/ASN1Encodable;)V
     114: aload_0
     115: getfield      #98                 // Field reqSignature:Lorg/bouncycastle/asn1/ASN1Set;
     118: ifnull        138
     121: aload_1
     122: new           #49                 // class org/bouncycastle/asn1/DERTaggedObject
     125: dup
     126: iconst_0
     127: iconst_2
     128: aload_0
     129: getfield      #98                 // Field reqSignature:Lorg/bouncycastle/asn1/ASN1Set;
     132: invokespecial #111                // Method org/bouncycastle/asn1/DERTaggedObject."<init>":(ZILorg/bouncycastle/asn1/ASN1Encodable;)V
     135: invokevirtual #107                // Method org/bouncycastle/asn1/ASN1EncodableVector.add:(Lorg/bouncycastle/asn1/ASN1Encodable;)V
     138: aload_0
     139: getfield      #97                 // Field certs:Lorg/bouncycastle/asn1/ASN1Sequence;
     142: ifnull        162
     145: aload_1
     146: new           #49                 // class org/bouncycastle/asn1/DERTaggedObject
     149: dup
     150: iconst_0
     151: iconst_3
     152: aload_0
     153: getfield      #97                 // Field certs:Lorg/bouncycastle/asn1/ASN1Sequence;
     156: invokespecial #111                // Method org/bouncycastle/asn1/DERTaggedObject."<init>":(ZILorg/bouncycastle/asn1/ASN1Encodable;)V
     159: invokevirtual #107                // Method org/bouncycastle/asn1/ASN1EncodableVector.add:(Lorg/bouncycastle/asn1/ASN1Encodable;)V
     162: aload_0
     163: getfield      #103                // Field extensions:Lorg/bouncycastle/asn1/x509/Extensions;
     166: ifnull        177
     169: aload_1
     170: aload_0
     171: getfield      #103                // Field extensions:Lorg/bouncycastle/asn1/x509/Extensions;
     174: invokevirtual #107                // Method org/bouncycastle/asn1/ASN1EncodableVector.add:(Lorg/bouncycastle/asn1/ASN1Encodable;)V
     177: new           #48                 // class org/bouncycastle/asn1/DERSequence
     180: dup
     181: aload_1
     182: invokespecial #110                // Method org/bouncycastle/asn1/DERSequence."<init>":(Lorg/bouncycastle/asn1/ASN1EncodableVector;)V
     185: invokestatic  #112                // Method org/bouncycastle/asn1/dvcs/DVCSCertInfo.getInstance:(Ljava/lang/Object;)Lorg/bouncycastle/asn1/dvcs/DVCSCertInfo;
     188: areturn

  public void setVersion(int);
    Code:
       0: aload_0
       1: iload_1
       2: putfield      #95                 // Field version:I
       5: return

  public void setDvReqInfo(org.bouncycastle.asn1.dvcs.DVCSRequestInformation);
    Code:
       0: aload_0
       1: aload_1
       2: putfield      #100                // Field dvReqInfo:Lorg/bouncycastle/asn1/dvcs/DVCSRequestInformation;
       5: return

  public void setMessageImprint(org.bouncycastle.asn1.x509.DigestInfo);
    Code:
       0: aload_0
       1: aload_1
       2: putfield      #102                // Field messageImprint:Lorg/bouncycastle/asn1/x509/DigestInfo;
       5: return

  public void setSerialNumber(org.bouncycastle.asn1.ASN1Integer);
    Code:
       0: aload_0
       1: aload_1
       2: putfield      #96                 // Field serialNumber:Lorg/bouncycastle/asn1/ASN1Integer;
       5: return

  public void setResponseTime(org.bouncycastle.asn1.dvcs.DVCSTime);
    Code:
       0: aload_0
       1: aload_1
       2: putfield      #101                // Field responseTime:Lorg/bouncycastle/asn1/dvcs/DVCSTime;
       5: return

  public void setDvStatus(org.bouncycastle.asn1.cmp.PKIStatusInfo);
    Code:
       0: aload_0
       1: aload_1
       2: putfield      #99                 // Field dvStatus:Lorg/bouncycastle/asn1/cmp/PKIStatusInfo;
       5: return

  public void setPolicy(org.bouncycastle.asn1.x509.PolicyInformation);
    Code:
       0: aload_0
       1: aload_1
       2: putfield      #104                // Field policy:Lorg/bouncycastle/asn1/x509/PolicyInformation;
       5: return

  public void setReqSignature(org.bouncycastle.asn1.ASN1Set);
    Code:
       0: aload_0
       1: aload_1
       2: putfield      #98                 // Field reqSignature:Lorg/bouncycastle/asn1/ASN1Set;
       5: return

  public void setCerts(org.bouncycastle.asn1.dvcs.TargetEtcChain[]);
    Code:
       0: aload_0
       1: new           #48                 // class org/bouncycastle/asn1/DERSequence
       4: dup
       5: aload_1
       6: invokespecial #109                // Method org/bouncycastle/asn1/DERSequence."<init>":([Lorg/bouncycastle/asn1/ASN1Encodable;)V
       9: putfield      #97                 // Field certs:Lorg/bouncycastle/asn1/ASN1Sequence;
      12: return

  public void setExtensions(org.bouncycastle.asn1.x509.Extensions);
    Code:
       0: aload_0
       1: aload_1
       2: putfield      #103                // Field extensions:Lorg/bouncycastle/asn1/x509/Extensions;
       5: return
}
