Compiled from "SpecificErrorBuilderBase.java"
public abstract class org.apache.avro.specific.SpecificErrorBuilderBase<T extends org.apache.avro.specific.SpecificExceptionBase> extends org.apache.avro.data.RecordBuilderBase<T> implements org.apache.avro.data.ErrorBuilder<T> {
  private java.lang.reflect.Constructor<T> errorConstructor;

  private java.lang.Object value;

  private boolean hasValue;

  private java.lang.Throwable cause;

  private boolean hasCause;

  protected org.apache.avro.specific.SpecificErrorBuilderBase(org.apache.avro.Schema);
    Code:
       0: aload_0
       1: aload_1
       2: invokestatic  #1                  // Method org/apache/avro/specific/SpecificData.get:()Lorg/apache/avro/specific/SpecificData;
       5: invokespecial #2                  // Method org/apache/avro/data/RecordBuilderBase."<init>":(Lorg/apache/avro/Schema;Lorg/apache/avro/generic/GenericData;)V
       8: return

  protected org.apache.avro.specific.SpecificErrorBuilderBase(org.apache.avro.specific.SpecificErrorBuilderBase<T>);
    Code:
       0: aload_0
       1: aload_1
       2: invokestatic  #1                  // Method org/apache/avro/specific/SpecificData.get:()Lorg/apache/avro/specific/SpecificData;
       5: invokespecial #3                  // Method org/apache/avro/data/RecordBuilderBase."<init>":(Lorg/apache/avro/data/RecordBuilderBase;Lorg/apache/avro/generic/GenericData;)V
       8: aload_0
       9: aload_1
      10: getfield      #4                  // Field errorConstructor:Ljava/lang/reflect/Constructor;
      13: putfield      #4                  // Field errorConstructor:Ljava/lang/reflect/Constructor;
      16: aload_0
      17: aload_1
      18: getfield      #5                  // Field value:Ljava/lang/Object;
      21: putfield      #5                  // Field value:Ljava/lang/Object;
      24: aload_0
      25: aload_1
      26: getfield      #6                  // Field hasValue:Z
      29: putfield      #6                  // Field hasValue:Z
      32: aload_0
      33: aload_1
      34: getfield      #7                  // Field cause:Ljava/lang/Throwable;
      37: putfield      #7                  // Field cause:Ljava/lang/Throwable;
      40: aload_0
      41: aload_1
      42: getfield      #8                  // Field hasCause:Z
      45: putfield      #8                  // Field hasCause:Z
      48: return

  protected org.apache.avro.specific.SpecificErrorBuilderBase(T);
    Code:
       0: aload_0
       1: aload_1
       2: invokevirtual #9                  // Method org/apache/avro/specific/SpecificExceptionBase.getSchema:()Lorg/apache/avro/Schema;
       5: invokestatic  #1                  // Method org/apache/avro/specific/SpecificData.get:()Lorg/apache/avro/specific/SpecificData;
       8: invokespecial #2                  // Method org/apache/avro/data/RecordBuilderBase."<init>":(Lorg/apache/avro/Schema;Lorg/apache/avro/generic/GenericData;)V
      11: aload_1
      12: invokevirtual #10                 // Method org/apache/avro/specific/SpecificExceptionBase.getValue:()Ljava/lang/Object;
      15: astore_2
      16: aload_2
      17: ifnull        26
      20: aload_0
      21: aload_2
      22: invokevirtual #11                 // Method setValue:(Ljava/lang/Object;)Lorg/apache/avro/specific/SpecificErrorBuilderBase;
      25: pop
      26: aload_1
      27: invokevirtual #12                 // Method org/apache/avro/specific/SpecificExceptionBase.getCause:()Ljava/lang/Throwable;
      30: astore_3
      31: aload_3
      32: ifnull        41
      35: aload_0
      36: aload_3
      37: invokevirtual #13                 // Method setCause:(Ljava/lang/Throwable;)Lorg/apache/avro/specific/SpecificErrorBuilderBase;
      40: pop
      41: return

  public java.lang.Object getValue();
    Code:
       0: aload_0
       1: getfield      #5                  // Field value:Ljava/lang/Object;
       4: areturn

  public org.apache.avro.specific.SpecificErrorBuilderBase<T> setValue(java.lang.Object);
    Code:
       0: aload_0
       1: aload_1
       2: putfield      #5                  // Field value:Ljava/lang/Object;
       5: aload_0
       6: iconst_1
       7: putfield      #6                  // Field hasValue:Z
      10: aload_0
      11: areturn

  public boolean hasValue();
    Code:
       0: aload_0
       1: getfield      #6                  // Field hasValue:Z
       4: ireturn

  public org.apache.avro.specific.SpecificErrorBuilderBase<T> clearValue();
    Code:
       0: aload_0
       1: aconst_null
       2: putfield      #5                  // Field value:Ljava/lang/Object;
       5: aload_0
       6: iconst_0
       7: putfield      #6                  // Field hasValue:Z
      10: aload_0
      11: areturn

  public java.lang.Throwable getCause();
    Code:
       0: aload_0
       1: getfield      #7                  // Field cause:Ljava/lang/Throwable;
       4: areturn

  public org.apache.avro.specific.SpecificErrorBuilderBase<T> setCause(java.lang.Throwable);
    Code:
       0: aload_0
       1: aload_1
       2: putfield      #7                  // Field cause:Ljava/lang/Throwable;
       5: aload_0
       6: iconst_1
       7: putfield      #8                  // Field hasCause:Z
      10: aload_0
      11: areturn

  public boolean hasCause();
    Code:
       0: aload_0
       1: getfield      #8                  // Field hasCause:Z
       4: ireturn

  public org.apache.avro.specific.SpecificErrorBuilderBase<T> clearCause();
    Code:
       0: aload_0
       1: aconst_null
       2: putfield      #7                  // Field cause:Ljava/lang/Throwable;
       5: aload_0
       6: iconst_0
       7: putfield      #8                  // Field hasCause:Z
      10: aload_0
      11: areturn

  public org.apache.avro.data.ErrorBuilder clearCause();
    Code:
       0: aload_0
       1: invokevirtual #14                 // Method clearCause:()Lorg/apache/avro/specific/SpecificErrorBuilderBase;
       4: areturn

  public org.apache.avro.data.ErrorBuilder setCause(java.lang.Throwable);
    Code:
       0: aload_0
       1: aload_1
       2: invokevirtual #13                 // Method setCause:(Ljava/lang/Throwable;)Lorg/apache/avro/specific/SpecificErrorBuilderBase;
       5: areturn

  public org.apache.avro.data.ErrorBuilder clearValue();
    Code:
       0: aload_0
       1: invokevirtual #15                 // Method clearValue:()Lorg/apache/avro/specific/SpecificErrorBuilderBase;
       4: areturn

  public org.apache.avro.data.ErrorBuilder setValue(java.lang.Object);
    Code:
       0: aload_0
       1: aload_1
       2: invokevirtual #11                 // Method setValue:(Ljava/lang/Object;)Lorg/apache/avro/specific/SpecificErrorBuilderBase;
       5: areturn
}
