Compiled from "AwsAutoScalingUtil.java"
public class nl.jpoint.maven.vertx.utils.AwsAutoScalingUtil {
  private static final java.lang.String AWS_AUTOSCALING_SERVICE;

  private final java.lang.String targetHost;

  private final nl.jpoint.maven.vertx.utils.AwsUtil awsUtil;

  protected final java.text.SimpleDateFormat compressedIso8601DateFormat;

  public nl.jpoint.maven.vertx.utils.AwsAutoScalingUtil(java.lang.String, java.lang.String);
    Code:
       0: aload_0
       1: invokespecial #1                  // Method java/lang/Object."<init>":()V
       4: aload_0
       5: ldc           #3                  // String autoscaling.eu-west-1.amazonaws.com
       7: putfield      #4                  // Field targetHost:Ljava/lang/String;
      10: aload_0
      11: new           #5                  // class java/text/SimpleDateFormat
      14: dup
      15: ldc           #6                  // String yyyyMMdd\'T\'HHmmss\'Z\'
      17: invokespecial #7                  // Method java/text/SimpleDateFormat."<init>":(Ljava/lang/String;)V
      20: putfield      #8                  // Field compressedIso8601DateFormat:Ljava/text/SimpleDateFormat;
      23: aload_0
      24: new           #9                  // class nl/jpoint/maven/vertx/utils/AwsUtil
      27: dup
      28: aload_1
      29: aload_2
      30: invokespecial #10                 // Method nl/jpoint/maven/vertx/utils/AwsUtil."<init>":(Ljava/lang/String;Ljava/lang/String;)V
      33: putfield      #11                 // Field awsUtil:Lnl/jpoint/maven/vertx/utils/AwsUtil;
      36: aload_0
      37: getfield      #8                  // Field compressedIso8601DateFormat:Ljava/text/SimpleDateFormat;
      40: ldc           #12                 // String GMT
      42: invokestatic  #13                 // Method java/util/TimeZone.getTimeZone:(Ljava/lang/String;)Ljava/util/TimeZone;
      45: invokevirtual #14                 // Method java/text/SimpleDateFormat.setTimeZone:(Ljava/util/TimeZone;)V
      48: return

  public nl.jpoint.maven.vertx.utils.AutoScalingGroup describeAutoScalingGroup(java.lang.String, boolean, org.apache.maven.plugin.logging.Log) throws nl.jpoint.maven.vertx.utils.AwsException;
    Code:
       0: aload_0
       1: getfield      #8                  // Field compressedIso8601DateFormat:Ljava/text/SimpleDateFormat;
       4: new           #15                 // class java/util/Date
       7: dup
       8: invokespecial #16                 // Method java/util/Date."<init>":()V
      11: invokevirtual #17                 // Method java/text/SimpleDateFormat.format:(Ljava/util/Date;)Ljava/lang/String;
      14: astore        4
      16: aload_0
      17: aload         4
      19: ldc           #3                  // String autoscaling.eu-west-1.amazonaws.com
      21: invokespecial #18                 // Method createDefaultSignedHeaders:(Ljava/lang/String;Ljava/lang/String;)Ljava/util/Map;
      24: astore        5
      26: new           #19                 // class java/util/HashMap
      29: dup
      30: invokespecial #20                 // Method java/util/HashMap."<init>":()V
      33: astore        6
      35: aload         6
      37: ldc           #21                 // String AutoScalingGroupNames.member.1
      39: aload_1
      40: invokeinterface #22,  3           // InterfaceMethod java/util/Map.put:(Ljava/lang/Object;Ljava/lang/Object;)Ljava/lang/Object;
      45: pop
      46: aload         6
      48: ldc           #23                 // String MaxRecords
      50: ldc           #24                 // String 20
      52: invokeinterface #22,  3           // InterfaceMethod java/util/Map.put:(Ljava/lang/Object;Ljava/lang/Object;)Ljava/lang/Object;
      57: pop
      58: aload         6
      60: ldc           #25                 // String Version
      62: ldc           #26                 // String 2011-01-01
      64: invokeinterface #22,  3           // InterfaceMethod java/util/Map.put:(Ljava/lang/Object;Ljava/lang/Object;)Ljava/lang/Object;
      69: pop
      70: aload         6
      72: ldc           #27                 // String Action
      74: ldc           #28                 // String DescribeAutoScalingGroups
      76: invokeinterface #22,  3           // InterfaceMethod java/util/Map.put:(Ljava/lang/Object;Ljava/lang/Object;)Ljava/lang/Object;
      81: pop
      82: aload_0
      83: getfield      #11                 // Field awsUtil:Lnl/jpoint/maven/vertx/utils/AwsUtil;
      86: ldc           #3                  // String autoscaling.eu-west-1.amazonaws.com
      88: aload         6
      90: aload         5
      92: aload         4
      94: ldc           #29                 // String autoscaling
      96: ldc           #30                 // String eu-west-1
      98: ldc           #28                 // String DescribeAutoScalingGroups
     100: invokevirtual #31                 // Method nl/jpoint/maven/vertx/utils/AwsUtil.createSignedGet:(Ljava/lang/String;Ljava/util/Map;Ljava/util/Map;Ljava/lang/String;Ljava/lang/String;Ljava/lang/String;Ljava/lang/String;)Lorg/apache/http/client/methods/HttpGet;
     103: astore        7
     105: aload_0
     106: aload         7
     108: invokespecial #32                 // Method executeRequest:(Lorg/apache/http/client/methods/HttpGet;)[B
     111: astore        8
     113: new           #33                 // class nl/jpoint/maven/vertx/utils/AutoScalingGroup$Builder
     116: dup
     117: invokespecial #34                 // Method nl/jpoint/maven/vertx/utils/AutoScalingGroup$Builder."<init>":()V
     120: aload         8
     122: iload_2
     123: invokestatic  #35                 // Method nl/jpoint/maven/vertx/utils/AwsXpathUtil.listInstancesInAutoscalingGroupResponse:([BZ)Ljava/util/List;
     126: invokevirtual #36                 // Method nl/jpoint/maven/vertx/utils/AutoScalingGroup$Builder.withInstances:(Ljava/util/List;)Lnl/jpoint/maven/vertx/utils/AutoScalingGroup$Builder;
     129: aload         8
     131: invokestatic  #37                 // Method nl/jpoint/maven/vertx/utils/AwsXpathUtil.listELBsInAutoscalingGroupResponse:([B)Ljava/util/List;
     134: invokevirtual #38                 // Method nl/jpoint/maven/vertx/utils/AutoScalingGroup$Builder.withElbs:(Ljava/util/List;)Lnl/jpoint/maven/vertx/utils/AutoScalingGroup$Builder;
     137: aload         8
     139: invokestatic  #39                 // Method nl/jpoint/maven/vertx/utils/AwsXpathUtil.listMaximumInstancesInAutoscalingGroupResponse:([B)I
     142: invokevirtual #40                 // Method nl/jpoint/maven/vertx/utils/AutoScalingGroup$Builder.withMaxInstances:(I)Lnl/jpoint/maven/vertx/utils/AutoScalingGroup$Builder;
     145: aload         8
     147: invokestatic  #41                 // Method nl/jpoint/maven/vertx/utils/AwsXpathUtil.listMinimalInstancesInAutoscalingGroupResponse:([B)I
     150: invokevirtual #42                 // Method nl/jpoint/maven/vertx/utils/AutoScalingGroup$Builder.withMinInstances:(I)Lnl/jpoint/maven/vertx/utils/AutoScalingGroup$Builder;
     153: aload         8
     155: invokestatic  #43                 // Method nl/jpoint/maven/vertx/utils/AwsXpathUtil.listDesiredCapacityInAutoscalingGroupResponse:([B)I
     158: invokevirtual #44                 // Method nl/jpoint/maven/vertx/utils/AutoScalingGroup$Builder.withDesiredCapacity:(I)Lnl/jpoint/maven/vertx/utils/AutoScalingGroup$Builder;
     161: invokevirtual #45                 // Method nl/jpoint/maven/vertx/utils/AutoScalingGroup$Builder.build:()Lnl/jpoint/maven/vertx/utils/AutoScalingGroup;
     164: areturn

  private byte[] executeRequest(org.apache.http.client.methods.HttpGet) throws nl.jpoint.maven.vertx.utils.AwsException;
    Code:
       0: invokestatic  #46                 // Method org/apache/http/impl/client/HttpClients.createDefault:()Lorg/apache/http/impl/client/CloseableHttpClient;
       3: astore_2
       4: aconst_null
       5: astore_3
       6: aload_2
       7: aload_1
       8: invokevirtual #47                 // Method org/apache/http/impl/client/CloseableHttpClient.execute:(Lorg/apache/http/client/methods/HttpUriRequest;)Lorg/apache/http/client/methods/CloseableHttpResponse;
      11: astore        4
      13: aconst_null
      14: astore        5
      16: aload         4
      18: invokeinterface #48,  1           // InterfaceMethod org/apache/http/client/methods/CloseableHttpResponse.getEntity:()Lorg/apache/http/HttpEntity;
      23: invokestatic  #49                 // Method org/apache/http/util/EntityUtils.toByteArray:(Lorg/apache/http/HttpEntity;)[B
      26: astore        6
      28: aload         4
      30: ifnull        67
      33: aload         5
      35: ifnull        60
      38: aload         4
      40: invokeinterface #50,  1           // InterfaceMethod org/apache/http/client/methods/CloseableHttpResponse.close:()V
      45: goto          67
      48: astore        7
      50: aload         5
      52: aload         7
      54: invokevirtual #52                 // Method java/lang/Throwable.addSuppressed:(Ljava/lang/Throwable;)V
      57: goto          67
      60: aload         4
      62: invokeinterface #50,  1           // InterfaceMethod org/apache/http/client/methods/CloseableHttpResponse.close:()V
      67: aload_2
      68: ifnull        97
      71: aload_3
      72: ifnull        93
      75: aload_2
      76: invokevirtual #53                 // Method org/apache/http/impl/client/CloseableHttpClient.close:()V
      79: goto          97
      82: astore        7
      84: aload_3
      85: aload         7
      87: invokevirtual #52                 // Method java/lang/Throwable.addSuppressed:(Ljava/lang/Throwable;)V
      90: goto          97
      93: aload_2
      94: invokevirtual #53                 // Method org/apache/http/impl/client/CloseableHttpClient.close:()V
      97: aload         6
      99: areturn
     100: astore        6
     102: aload         6
     104: astore        5
     106: aload         6
     108: athrow
     109: astore        8
     111: aload         4
     113: ifnull        150
     116: aload         5
     118: ifnull        143
     121: aload         4
     123: invokeinterface #50,  1           // InterfaceMethod org/apache/http/client/methods/CloseableHttpResponse.close:()V
     128: goto          150
     131: astore        9
     133: aload         5
     135: aload         9
     137: invokevirtual #52                 // Method java/lang/Throwable.addSuppressed:(Ljava/lang/Throwable;)V
     140: goto          150
     143: aload         4
     145: invokeinterface #50,  1           // InterfaceMethod org/apache/http/client/methods/CloseableHttpResponse.close:()V
     150: aload         8
     152: athrow
     153: astore        4
     155: aload         4
     157: astore_3
     158: aload         4
     160: athrow
     161: astore        10
     163: aload_2
     164: ifnull        193
     167: aload_3
     168: ifnull        189
     171: aload_2
     172: invokevirtual #53                 // Method org/apache/http/impl/client/CloseableHttpClient.close:()V
     175: goto          193
     178: astore        11
     180: aload_3
     181: aload         11
     183: invokevirtual #52                 // Method java/lang/Throwable.addSuppressed:(Ljava/lang/Throwable;)V
     186: goto          193
     189: aload_2
     190: invokevirtual #53                 // Method org/apache/http/impl/client/CloseableHttpClient.close:()V
     193: aload         10
     195: athrow
     196: astore_2
     197: new           #55                 // class nl/jpoint/maven/vertx/utils/AwsException
     200: dup
     201: aload_2
     202: invokespecial #56                 // Method nl/jpoint/maven/vertx/utils/AwsException."<init>":(Ljava/lang/Throwable;)V
     205: athrow
    Exception table:
       from    to  target type
          38    45    48   Class java/lang/Throwable
          75    79    82   Class java/lang/Throwable
          16    28   100   Class java/lang/Throwable
          16    28   109   any
         121   128   131   Class java/lang/Throwable
         100   111   109   any
           6    67   153   Class java/lang/Throwable
         100   153   153   Class java/lang/Throwable
           6    67   161   any
         171   175   178   Class java/lang/Throwable
         100   163   161   any
           0    97   196   Class java/io/IOException
         100   196   196   Class java/io/IOException

  private java.util.Map<java.lang.String, java.lang.String> createDefaultSignedHeaders(java.lang.String, java.lang.String);
    Code:
       0: new           #19                 // class java/util/HashMap
       3: dup
       4: invokespecial #20                 // Method java/util/HashMap."<init>":()V
       7: astore_3
       8: aload_3
       9: ldc           #57                 // String X-Amz-Date
      11: aload_1
      12: invokeinterface #22,  3           // InterfaceMethod java/util/Map.put:(Ljava/lang/Object;Ljava/lang/Object;)Ljava/lang/Object;
      17: pop
      18: aload_3
      19: ldc           #58                 // String Host
      21: aload_2
      22: invokeinterface #22,  3           // InterfaceMethod java/util/Map.put:(Ljava/lang/Object;Ljava/lang/Object;)Ljava/lang/Object;
      27: pop
      28: aload_3
      29: areturn
}
