Compiled from "JsonDecoder.java"
class org.apache.avro.io.JsonDecoder$ReorderBuffer {
  public java.util.Map<java.lang.String, java.util.List<org.apache.avro.io.JsonDecoder$JsonElement>> savedFields;

  public org.codehaus.jackson.JsonParser origParser;

  private org.apache.avro.io.JsonDecoder$ReorderBuffer();
    Code:
       0: aload_0
       1: invokespecial #2                  // Method java/lang/Object."<init>":()V
       4: aload_0
       5: new           #3                  // class java/util/HashMap
       8: dup
       9: invokespecial #4                  // Method java/util/HashMap."<init>":()V
      12: putfield      #5                  // Field savedFields:Ljava/util/Map;
      15: aload_0
      16: aconst_null
      17: putfield      #6                  // Field origParser:Lorg/codehaus/jackson/JsonParser;
      20: return

  org.apache.avro.io.JsonDecoder$ReorderBuffer(org.apache.avro.io.JsonDecoder$1);
    Code:
       0: aload_0
       1: invokespecial #1                  // Method "<init>":()V
       4: return
}
