Compiled from "ValidatingDecoder.java"
public class org.apache.avro.io.ValidatingDecoder extends org.apache.avro.io.ParsingDecoder implements org.apache.avro.io.parsing.Parser$ActionHandler {
  protected org.apache.avro.io.Decoder in;

  org.apache.avro.io.ValidatingDecoder(org.apache.avro.io.parsing.Symbol, org.apache.avro.io.Decoder) throws java.io.IOException;
    Code:
       0: aload_0
       1: aload_1
       2: invokespecial #1                  // Method org/apache/avro/io/ParsingDecoder."<init>":(Lorg/apache/avro/io/parsing/Symbol;)V
       5: aload_0
       6: aload_2
       7: invokevirtual #2                  // Method configure:(Lorg/apache/avro/io/Decoder;)Lorg/apache/avro/io/ValidatingDecoder;
      10: pop
      11: return

  org.apache.avro.io.ValidatingDecoder(org.apache.avro.Schema, org.apache.avro.io.Decoder) throws java.io.IOException;
    Code:
       0: aload_0
       1: aload_1
       2: invokestatic  #3                  // Method getSymbol:(Lorg/apache/avro/Schema;)Lorg/apache/avro/io/parsing/Symbol;
       5: aload_2
       6: invokespecial #4                  // Method "<init>":(Lorg/apache/avro/io/parsing/Symbol;Lorg/apache/avro/io/Decoder;)V
       9: return

  private static org.apache.avro.io.parsing.Symbol getSymbol(org.apache.avro.Schema);
    Code:
       0: aconst_null
       1: aload_0
       2: if_acmpne     15
       5: new           #5                  // class java/lang/NullPointerException
       8: dup
       9: ldc           #6                  // String Schema cannot be null
      11: invokespecial #7                  // Method java/lang/NullPointerException."<init>":(Ljava/lang/String;)V
      14: athrow
      15: new           #8                  // class org/apache/avro/io/parsing/ValidatingGrammarGenerator
      18: dup
      19: invokespecial #9                  // Method org/apache/avro/io/parsing/ValidatingGrammarGenerator."<init>":()V
      22: aload_0
      23: invokevirtual #10                 // Method org/apache/avro/io/parsing/ValidatingGrammarGenerator.generate:(Lorg/apache/avro/Schema;)Lorg/apache/avro/io/parsing/Symbol;
      26: areturn

  public org.apache.avro.io.ValidatingDecoder configure(org.apache.avro.io.Decoder) throws java.io.IOException;
    Code:
       0: aload_0
       1: getfield      #11                 // Field parser:Lorg/apache/avro/io/parsing/SkipParser;
       4: invokevirtual #12                 // Method org/apache/avro/io/parsing/SkipParser.reset:()V
       7: aload_0
       8: aload_1
       9: putfield      #13                 // Field in:Lorg/apache/avro/io/Decoder;
      12: aload_0
      13: areturn

  public void readNull() throws java.io.IOException;
    Code:
       0: aload_0
       1: getfield      #11                 // Field parser:Lorg/apache/avro/io/parsing/SkipParser;
       4: getstatic     #14                 // Field org/apache/avro/io/parsing/Symbol.NULL:Lorg/apache/avro/io/parsing/Symbol;
       7: invokevirtual #15                 // Method org/apache/avro/io/parsing/SkipParser.advance:(Lorg/apache/avro/io/parsing/Symbol;)Lorg/apache/avro/io/parsing/Symbol;
      10: pop
      11: aload_0
      12: getfield      #13                 // Field in:Lorg/apache/avro/io/Decoder;
      15: invokevirtual #16                 // Method org/apache/avro/io/Decoder.readNull:()V
      18: return

  public boolean readBoolean() throws java.io.IOException;
    Code:
       0: aload_0
       1: getfield      #11                 // Field parser:Lorg/apache/avro/io/parsing/SkipParser;
       4: getstatic     #17                 // Field org/apache/avro/io/parsing/Symbol.BOOLEAN:Lorg/apache/avro/io/parsing/Symbol;
       7: invokevirtual #15                 // Method org/apache/avro/io/parsing/SkipParser.advance:(Lorg/apache/avro/io/parsing/Symbol;)Lorg/apache/avro/io/parsing/Symbol;
      10: pop
      11: aload_0
      12: getfield      #13                 // Field in:Lorg/apache/avro/io/Decoder;
      15: invokevirtual #18                 // Method org/apache/avro/io/Decoder.readBoolean:()Z
      18: ireturn

  public int readInt() throws java.io.IOException;
    Code:
       0: aload_0
       1: getfield      #11                 // Field parser:Lorg/apache/avro/io/parsing/SkipParser;
       4: getstatic     #19                 // Field org/apache/avro/io/parsing/Symbol.INT:Lorg/apache/avro/io/parsing/Symbol;
       7: invokevirtual #15                 // Method org/apache/avro/io/parsing/SkipParser.advance:(Lorg/apache/avro/io/parsing/Symbol;)Lorg/apache/avro/io/parsing/Symbol;
      10: pop
      11: aload_0
      12: getfield      #13                 // Field in:Lorg/apache/avro/io/Decoder;
      15: invokevirtual #20                 // Method org/apache/avro/io/Decoder.readInt:()I
      18: ireturn

  public long readLong() throws java.io.IOException;
    Code:
       0: aload_0
       1: getfield      #11                 // Field parser:Lorg/apache/avro/io/parsing/SkipParser;
       4: getstatic     #21                 // Field org/apache/avro/io/parsing/Symbol.LONG:Lorg/apache/avro/io/parsing/Symbol;
       7: invokevirtual #15                 // Method org/apache/avro/io/parsing/SkipParser.advance:(Lorg/apache/avro/io/parsing/Symbol;)Lorg/apache/avro/io/parsing/Symbol;
      10: pop
      11: aload_0
      12: getfield      #13                 // Field in:Lorg/apache/avro/io/Decoder;
      15: invokevirtual #22                 // Method org/apache/avro/io/Decoder.readLong:()J
      18: lreturn

  public float readFloat() throws java.io.IOException;
    Code:
       0: aload_0
       1: getfield      #11                 // Field parser:Lorg/apache/avro/io/parsing/SkipParser;
       4: getstatic     #23                 // Field org/apache/avro/io/parsing/Symbol.FLOAT:Lorg/apache/avro/io/parsing/Symbol;
       7: invokevirtual #15                 // Method org/apache/avro/io/parsing/SkipParser.advance:(Lorg/apache/avro/io/parsing/Symbol;)Lorg/apache/avro/io/parsing/Symbol;
      10: pop
      11: aload_0
      12: getfield      #13                 // Field in:Lorg/apache/avro/io/Decoder;
      15: invokevirtual #24                 // Method org/apache/avro/io/Decoder.readFloat:()F
      18: freturn

  public double readDouble() throws java.io.IOException;
    Code:
       0: aload_0
       1: getfield      #11                 // Field parser:Lorg/apache/avro/io/parsing/SkipParser;
       4: getstatic     #25                 // Field org/apache/avro/io/parsing/Symbol.DOUBLE:Lorg/apache/avro/io/parsing/Symbol;
       7: invokevirtual #15                 // Method org/apache/avro/io/parsing/SkipParser.advance:(Lorg/apache/avro/io/parsing/Symbol;)Lorg/apache/avro/io/parsing/Symbol;
      10: pop
      11: aload_0
      12: getfield      #13                 // Field in:Lorg/apache/avro/io/Decoder;
      15: invokevirtual #26                 // Method org/apache/avro/io/Decoder.readDouble:()D
      18: dreturn

  public org.apache.avro.util.Utf8 readString(org.apache.avro.util.Utf8) throws java.io.IOException;
    Code:
       0: aload_0
       1: getfield      #11                 // Field parser:Lorg/apache/avro/io/parsing/SkipParser;
       4: getstatic     #27                 // Field org/apache/avro/io/parsing/Symbol.STRING:Lorg/apache/avro/io/parsing/Symbol;
       7: invokevirtual #15                 // Method org/apache/avro/io/parsing/SkipParser.advance:(Lorg/apache/avro/io/parsing/Symbol;)Lorg/apache/avro/io/parsing/Symbol;
      10: pop
      11: aload_0
      12: getfield      #13                 // Field in:Lorg/apache/avro/io/Decoder;
      15: aload_1
      16: invokevirtual #28                 // Method org/apache/avro/io/Decoder.readString:(Lorg/apache/avro/util/Utf8;)Lorg/apache/avro/util/Utf8;
      19: areturn

  public java.lang.String readString() throws java.io.IOException;
    Code:
       0: aload_0
       1: getfield      #11                 // Field parser:Lorg/apache/avro/io/parsing/SkipParser;
       4: getstatic     #27                 // Field org/apache/avro/io/parsing/Symbol.STRING:Lorg/apache/avro/io/parsing/Symbol;
       7: invokevirtual #15                 // Method org/apache/avro/io/parsing/SkipParser.advance:(Lorg/apache/avro/io/parsing/Symbol;)Lorg/apache/avro/io/parsing/Symbol;
      10: pop
      11: aload_0
      12: getfield      #13                 // Field in:Lorg/apache/avro/io/Decoder;
      15: invokevirtual #29                 // Method org/apache/avro/io/Decoder.readString:()Ljava/lang/String;
      18: areturn

  public void skipString() throws java.io.IOException;
    Code:
       0: aload_0
       1: getfield      #11                 // Field parser:Lorg/apache/avro/io/parsing/SkipParser;
       4: getstatic     #27                 // Field org/apache/avro/io/parsing/Symbol.STRING:Lorg/apache/avro/io/parsing/Symbol;
       7: invokevirtual #15                 // Method org/apache/avro/io/parsing/SkipParser.advance:(Lorg/apache/avro/io/parsing/Symbol;)Lorg/apache/avro/io/parsing/Symbol;
      10: pop
      11: aload_0
      12: getfield      #13                 // Field in:Lorg/apache/avro/io/Decoder;
      15: invokevirtual #30                 // Method org/apache/avro/io/Decoder.skipString:()V
      18: return

  public java.nio.ByteBuffer readBytes(java.nio.ByteBuffer) throws java.io.IOException;
    Code:
       0: aload_0
       1: getfield      #11                 // Field parser:Lorg/apache/avro/io/parsing/SkipParser;
       4: getstatic     #31                 // Field org/apache/avro/io/parsing/Symbol.BYTES:Lorg/apache/avro/io/parsing/Symbol;
       7: invokevirtual #15                 // Method org/apache/avro/io/parsing/SkipParser.advance:(Lorg/apache/avro/io/parsing/Symbol;)Lorg/apache/avro/io/parsing/Symbol;
      10: pop
      11: aload_0
      12: getfield      #13                 // Field in:Lorg/apache/avro/io/Decoder;
      15: aload_1
      16: invokevirtual #32                 // Method org/apache/avro/io/Decoder.readBytes:(Ljava/nio/ByteBuffer;)Ljava/nio/ByteBuffer;
      19: areturn

  public void skipBytes() throws java.io.IOException;
    Code:
       0: aload_0
       1: getfield      #11                 // Field parser:Lorg/apache/avro/io/parsing/SkipParser;
       4: getstatic     #31                 // Field org/apache/avro/io/parsing/Symbol.BYTES:Lorg/apache/avro/io/parsing/Symbol;
       7: invokevirtual #15                 // Method org/apache/avro/io/parsing/SkipParser.advance:(Lorg/apache/avro/io/parsing/Symbol;)Lorg/apache/avro/io/parsing/Symbol;
      10: pop
      11: aload_0
      12: getfield      #13                 // Field in:Lorg/apache/avro/io/Decoder;
      15: invokevirtual #33                 // Method org/apache/avro/io/Decoder.skipBytes:()V
      18: return

  private void checkFixed(int) throws java.io.IOException;
    Code:
       0: aload_0
       1: getfield      #11                 // Field parser:Lorg/apache/avro/io/parsing/SkipParser;
       4: getstatic     #34                 // Field org/apache/avro/io/parsing/Symbol.FIXED:Lorg/apache/avro/io/parsing/Symbol;
       7: invokevirtual #15                 // Method org/apache/avro/io/parsing/SkipParser.advance:(Lorg/apache/avro/io/parsing/Symbol;)Lorg/apache/avro/io/parsing/Symbol;
      10: pop
      11: aload_0
      12: getfield      #11                 // Field parser:Lorg/apache/avro/io/parsing/SkipParser;
      15: invokevirtual #35                 // Method org/apache/avro/io/parsing/SkipParser.popSymbol:()Lorg/apache/avro/io/parsing/Symbol;
      18: checkcast     #36                 // class org/apache/avro/io/parsing/Symbol$IntCheckAction
      21: astore_2
      22: iload_1
      23: aload_2
      24: getfield      #37                 // Field org/apache/avro/io/parsing/Symbol$IntCheckAction.size:I
      27: if_icmpeq     74
      30: new           #38                 // class org/apache/avro/AvroTypeException
      33: dup
      34: new           #39                 // class java/lang/StringBuilder
      37: dup
      38: invokespecial #40                 // Method java/lang/StringBuilder."<init>":()V
      41: ldc           #41                 // String Incorrect length for fixed binary: expected
      43: invokevirtual #42                 // Method java/lang/StringBuilder.append:(Ljava/lang/String;)Ljava/lang/StringBuilder;
      46: aload_2
      47: getfield      #37                 // Field org/apache/avro/io/parsing/Symbol$IntCheckAction.size:I
      50: invokevirtual #43                 // Method java/lang/StringBuilder.append:(I)Ljava/lang/StringBuilder;
      53: ldc           #44                 // String  but received
      55: invokevirtual #42                 // Method java/lang/StringBuilder.append:(Ljava/lang/String;)Ljava/lang/StringBuilder;
      58: iload_1
      59: invokevirtual #43                 // Method java/lang/StringBuilder.append:(I)Ljava/lang/StringBuilder;
      62: ldc           #45                 // String  bytes.
      64: invokevirtual #42                 // Method java/lang/StringBuilder.append:(Ljava/lang/String;)Ljava/lang/StringBuilder;
      67: invokevirtual #46                 // Method java/lang/StringBuilder.toString:()Ljava/lang/String;
      70: invokespecial #47                 // Method org/apache/avro/AvroTypeException."<init>":(Ljava/lang/String;)V
      73: athrow
      74: return

  public void readFixed(byte[], int, int) throws java.io.IOException;
    Code:
       0: aload_0
       1: iload_3
       2: invokespecial #48                 // Method checkFixed:(I)V
       5: aload_0
       6: getfield      #13                 // Field in:Lorg/apache/avro/io/Decoder;
       9: aload_1
      10: iload_2
      11: iload_3
      12: invokevirtual #49                 // Method org/apache/avro/io/Decoder.readFixed:([BII)V
      15: return

  public void skipFixed(int) throws java.io.IOException;
    Code:
       0: aload_0
       1: iload_1
       2: invokespecial #48                 // Method checkFixed:(I)V
       5: aload_0
       6: getfield      #13                 // Field in:Lorg/apache/avro/io/Decoder;
       9: iload_1
      10: invokevirtual #50                 // Method org/apache/avro/io/Decoder.skipFixed:(I)V
      13: return

  protected void skipFixed() throws java.io.IOException;
    Code:
       0: aload_0
       1: getfield      #11                 // Field parser:Lorg/apache/avro/io/parsing/SkipParser;
       4: getstatic     #34                 // Field org/apache/avro/io/parsing/Symbol.FIXED:Lorg/apache/avro/io/parsing/Symbol;
       7: invokevirtual #15                 // Method org/apache/avro/io/parsing/SkipParser.advance:(Lorg/apache/avro/io/parsing/Symbol;)Lorg/apache/avro/io/parsing/Symbol;
      10: pop
      11: aload_0
      12: getfield      #11                 // Field parser:Lorg/apache/avro/io/parsing/SkipParser;
      15: invokevirtual #35                 // Method org/apache/avro/io/parsing/SkipParser.popSymbol:()Lorg/apache/avro/io/parsing/Symbol;
      18: checkcast     #36                 // class org/apache/avro/io/parsing/Symbol$IntCheckAction
      21: astore_1
      22: aload_0
      23: getfield      #13                 // Field in:Lorg/apache/avro/io/Decoder;
      26: aload_1
      27: getfield      #37                 // Field org/apache/avro/io/parsing/Symbol$IntCheckAction.size:I
      30: invokevirtual #50                 // Method org/apache/avro/io/Decoder.skipFixed:(I)V
      33: return

  public int readEnum() throws java.io.IOException;
    Code:
       0: aload_0
       1: getfield      #11                 // Field parser:Lorg/apache/avro/io/parsing/SkipParser;
       4: getstatic     #51                 // Field org/apache/avro/io/parsing/Symbol.ENUM:Lorg/apache/avro/io/parsing/Symbol;
       7: invokevirtual #15                 // Method org/apache/avro/io/parsing/SkipParser.advance:(Lorg/apache/avro/io/parsing/Symbol;)Lorg/apache/avro/io/parsing/Symbol;
      10: pop
      11: aload_0
      12: getfield      #11                 // Field parser:Lorg/apache/avro/io/parsing/SkipParser;
      15: invokevirtual #35                 // Method org/apache/avro/io/parsing/SkipParser.popSymbol:()Lorg/apache/avro/io/parsing/Symbol;
      18: checkcast     #36                 // class org/apache/avro/io/parsing/Symbol$IntCheckAction
      21: astore_1
      22: aload_0
      23: getfield      #13                 // Field in:Lorg/apache/avro/io/Decoder;
      26: invokevirtual #52                 // Method org/apache/avro/io/Decoder.readEnum:()I
      29: istore_2
      30: iload_2
      31: iflt          42
      34: iload_2
      35: aload_1
      36: getfield      #37                 // Field org/apache/avro/io/parsing/Symbol$IntCheckAction.size:I
      39: if_icmplt     81
      42: new           #38                 // class org/apache/avro/AvroTypeException
      45: dup
      46: new           #39                 // class java/lang/StringBuilder
      49: dup
      50: invokespecial #40                 // Method java/lang/StringBuilder."<init>":()V
      53: ldc           #53                 // String Enumeration out of range: max is
      55: invokevirtual #42                 // Method java/lang/StringBuilder.append:(Ljava/lang/String;)Ljava/lang/StringBuilder;
      58: aload_1
      59: getfield      #37                 // Field org/apache/avro/io/parsing/Symbol$IntCheckAction.size:I
      62: invokevirtual #43                 // Method java/lang/StringBuilder.append:(I)Ljava/lang/StringBuilder;
      65: ldc           #44                 // String  but received
      67: invokevirtual #42                 // Method java/lang/StringBuilder.append:(Ljava/lang/String;)Ljava/lang/StringBuilder;
      70: iload_2
      71: invokevirtual #43                 // Method java/lang/StringBuilder.append:(I)Ljava/lang/StringBuilder;
      74: invokevirtual #46                 // Method java/lang/StringBuilder.toString:()Ljava/lang/String;
      77: invokespecial #47                 // Method org/apache/avro/AvroTypeException."<init>":(Ljava/lang/String;)V
      80: athrow
      81: iload_2
      82: ireturn

  public long readArrayStart() throws java.io.IOException;
    Code:
       0: aload_0
       1: getfield      #11                 // Field parser:Lorg/apache/avro/io/parsing/SkipParser;
       4: getstatic     #54                 // Field org/apache/avro/io/parsing/Symbol.ARRAY_START:Lorg/apache/avro/io/parsing/Symbol;
       7: invokevirtual #15                 // Method org/apache/avro/io/parsing/SkipParser.advance:(Lorg/apache/avro/io/parsing/Symbol;)Lorg/apache/avro/io/parsing/Symbol;
      10: pop
      11: aload_0
      12: getfield      #13                 // Field in:Lorg/apache/avro/io/Decoder;
      15: invokevirtual #55                 // Method org/apache/avro/io/Decoder.readArrayStart:()J
      18: lstore_1
      19: lload_1
      20: lconst_0
      21: lcmp
      22: ifne          36
      25: aload_0
      26: getfield      #11                 // Field parser:Lorg/apache/avro/io/parsing/SkipParser;
      29: getstatic     #56                 // Field org/apache/avro/io/parsing/Symbol.ARRAY_END:Lorg/apache/avro/io/parsing/Symbol;
      32: invokevirtual #15                 // Method org/apache/avro/io/parsing/SkipParser.advance:(Lorg/apache/avro/io/parsing/Symbol;)Lorg/apache/avro/io/parsing/Symbol;
      35: pop
      36: lload_1
      37: lreturn

  public long arrayNext() throws java.io.IOException;
    Code:
       0: aload_0
       1: getfield      #11                 // Field parser:Lorg/apache/avro/io/parsing/SkipParser;
       4: invokevirtual #57                 // Method org/apache/avro/io/parsing/SkipParser.processTrailingImplicitActions:()V
       7: aload_0
       8: getfield      #13                 // Field in:Lorg/apache/avro/io/Decoder;
      11: invokevirtual #58                 // Method org/apache/avro/io/Decoder.arrayNext:()J
      14: lstore_1
      15: lload_1
      16: lconst_0
      17: lcmp
      18: ifne          32
      21: aload_0
      22: getfield      #11                 // Field parser:Lorg/apache/avro/io/parsing/SkipParser;
      25: getstatic     #56                 // Field org/apache/avro/io/parsing/Symbol.ARRAY_END:Lorg/apache/avro/io/parsing/Symbol;
      28: invokevirtual #15                 // Method org/apache/avro/io/parsing/SkipParser.advance:(Lorg/apache/avro/io/parsing/Symbol;)Lorg/apache/avro/io/parsing/Symbol;
      31: pop
      32: lload_1
      33: lreturn

  public long skipArray() throws java.io.IOException;
    Code:
       0: aload_0
       1: getfield      #11                 // Field parser:Lorg/apache/avro/io/parsing/SkipParser;
       4: getstatic     #54                 // Field org/apache/avro/io/parsing/Symbol.ARRAY_START:Lorg/apache/avro/io/parsing/Symbol;
       7: invokevirtual #15                 // Method org/apache/avro/io/parsing/SkipParser.advance:(Lorg/apache/avro/io/parsing/Symbol;)Lorg/apache/avro/io/parsing/Symbol;
      10: pop
      11: aload_0
      12: getfield      #13                 // Field in:Lorg/apache/avro/io/Decoder;
      15: invokevirtual #59                 // Method org/apache/avro/io/Decoder.skipArray:()J
      18: lstore_1
      19: lload_1
      20: lconst_0
      21: lcmp
      22: ifeq          56
      25: lload_1
      26: dup2
      27: lconst_1
      28: lsub
      29: lstore_1
      30: lconst_0
      31: lcmp
      32: ifle          45
      35: aload_0
      36: getfield      #11                 // Field parser:Lorg/apache/avro/io/parsing/SkipParser;
      39: invokevirtual #60                 // Method org/apache/avro/io/parsing/SkipParser.skipRepeater:()V
      42: goto          25
      45: aload_0
      46: getfield      #13                 // Field in:Lorg/apache/avro/io/Decoder;
      49: invokevirtual #59                 // Method org/apache/avro/io/Decoder.skipArray:()J
      52: lstore_1
      53: goto          19
      56: aload_0
      57: getfield      #11                 // Field parser:Lorg/apache/avro/io/parsing/SkipParser;
      60: getstatic     #56                 // Field org/apache/avro/io/parsing/Symbol.ARRAY_END:Lorg/apache/avro/io/parsing/Symbol;
      63: invokevirtual #15                 // Method org/apache/avro/io/parsing/SkipParser.advance:(Lorg/apache/avro/io/parsing/Symbol;)Lorg/apache/avro/io/parsing/Symbol;
      66: pop
      67: lconst_0
      68: lreturn

  public long readMapStart() throws java.io.IOException;
    Code:
       0: aload_0
       1: getfield      #11                 // Field parser:Lorg/apache/avro/io/parsing/SkipParser;
       4: getstatic     #61                 // Field org/apache/avro/io/parsing/Symbol.MAP_START:Lorg/apache/avro/io/parsing/Symbol;
       7: invokevirtual #15                 // Method org/apache/avro/io/parsing/SkipParser.advance:(Lorg/apache/avro/io/parsing/Symbol;)Lorg/apache/avro/io/parsing/Symbol;
      10: pop
      11: aload_0
      12: getfield      #13                 // Field in:Lorg/apache/avro/io/Decoder;
      15: invokevirtual #62                 // Method org/apache/avro/io/Decoder.readMapStart:()J
      18: lstore_1
      19: lload_1
      20: lconst_0
      21: lcmp
      22: ifne          36
      25: aload_0
      26: getfield      #11                 // Field parser:Lorg/apache/avro/io/parsing/SkipParser;
      29: getstatic     #63                 // Field org/apache/avro/io/parsing/Symbol.MAP_END:Lorg/apache/avro/io/parsing/Symbol;
      32: invokevirtual #15                 // Method org/apache/avro/io/parsing/SkipParser.advance:(Lorg/apache/avro/io/parsing/Symbol;)Lorg/apache/avro/io/parsing/Symbol;
      35: pop
      36: lload_1
      37: lreturn

  public long mapNext() throws java.io.IOException;
    Code:
       0: aload_0
       1: getfield      #11                 // Field parser:Lorg/apache/avro/io/parsing/SkipParser;
       4: invokevirtual #57                 // Method org/apache/avro/io/parsing/SkipParser.processTrailingImplicitActions:()V
       7: aload_0
       8: getfield      #13                 // Field in:Lorg/apache/avro/io/Decoder;
      11: invokevirtual #64                 // Method org/apache/avro/io/Decoder.mapNext:()J
      14: lstore_1
      15: lload_1
      16: lconst_0
      17: lcmp
      18: ifne          32
      21: aload_0
      22: getfield      #11                 // Field parser:Lorg/apache/avro/io/parsing/SkipParser;
      25: getstatic     #63                 // Field org/apache/avro/io/parsing/Symbol.MAP_END:Lorg/apache/avro/io/parsing/Symbol;
      28: invokevirtual #15                 // Method org/apache/avro/io/parsing/SkipParser.advance:(Lorg/apache/avro/io/parsing/Symbol;)Lorg/apache/avro/io/parsing/Symbol;
      31: pop
      32: lload_1
      33: lreturn

  public long skipMap() throws java.io.IOException;
    Code:
       0: aload_0
       1: getfield      #11                 // Field parser:Lorg/apache/avro/io/parsing/SkipParser;
       4: getstatic     #61                 // Field org/apache/avro/io/parsing/Symbol.MAP_START:Lorg/apache/avro/io/parsing/Symbol;
       7: invokevirtual #15                 // Method org/apache/avro/io/parsing/SkipParser.advance:(Lorg/apache/avro/io/parsing/Symbol;)Lorg/apache/avro/io/parsing/Symbol;
      10: pop
      11: aload_0
      12: getfield      #13                 // Field in:Lorg/apache/avro/io/Decoder;
      15: invokevirtual #65                 // Method org/apache/avro/io/Decoder.skipMap:()J
      18: lstore_1
      19: lload_1
      20: lconst_0
      21: lcmp
      22: ifeq          56
      25: lload_1
      26: dup2
      27: lconst_1
      28: lsub
      29: lstore_1
      30: lconst_0
      31: lcmp
      32: ifle          45
      35: aload_0
      36: getfield      #11                 // Field parser:Lorg/apache/avro/io/parsing/SkipParser;
      39: invokevirtual #60                 // Method org/apache/avro/io/parsing/SkipParser.skipRepeater:()V
      42: goto          25
      45: aload_0
      46: getfield      #13                 // Field in:Lorg/apache/avro/io/Decoder;
      49: invokevirtual #65                 // Method org/apache/avro/io/Decoder.skipMap:()J
      52: lstore_1
      53: goto          19
      56: aload_0
      57: getfield      #11                 // Field parser:Lorg/apache/avro/io/parsing/SkipParser;
      60: getstatic     #63                 // Field org/apache/avro/io/parsing/Symbol.MAP_END:Lorg/apache/avro/io/parsing/Symbol;
      63: invokevirtual #15                 // Method org/apache/avro/io/parsing/SkipParser.advance:(Lorg/apache/avro/io/parsing/Symbol;)Lorg/apache/avro/io/parsing/Symbol;
      66: pop
      67: lconst_0
      68: lreturn

  public int readIndex() throws java.io.IOException;
    Code:
       0: aload_0
       1: getfield      #11                 // Field parser:Lorg/apache/avro/io/parsing/SkipParser;
       4: getstatic     #66                 // Field org/apache/avro/io/parsing/Symbol.UNION:Lorg/apache/avro/io/parsing/Symbol;
       7: invokevirtual #15                 // Method org/apache/avro/io/parsing/SkipParser.advance:(Lorg/apache/avro/io/parsing/Symbol;)Lorg/apache/avro/io/parsing/Symbol;
      10: pop
      11: aload_0
      12: getfield      #11                 // Field parser:Lorg/apache/avro/io/parsing/SkipParser;
      15: invokevirtual #35                 // Method org/apache/avro/io/parsing/SkipParser.popSymbol:()Lorg/apache/avro/io/parsing/Symbol;
      18: checkcast     #67                 // class org/apache/avro/io/parsing/Symbol$Alternative
      21: astore_1
      22: aload_0
      23: getfield      #13                 // Field in:Lorg/apache/avro/io/Decoder;
      26: invokevirtual #68                 // Method org/apache/avro/io/Decoder.readIndex:()I
      29: istore_2
      30: aload_0
      31: getfield      #11                 // Field parser:Lorg/apache/avro/io/parsing/SkipParser;
      34: aload_1
      35: iload_2
      36: invokevirtual #69                 // Method org/apache/avro/io/parsing/Symbol$Alternative.getSymbol:(I)Lorg/apache/avro/io/parsing/Symbol;
      39: invokevirtual #70                 // Method org/apache/avro/io/parsing/SkipParser.pushSymbol:(Lorg/apache/avro/io/parsing/Symbol;)V
      42: iload_2
      43: ireturn

  public org.apache.avro.io.parsing.Symbol doAction(org.apache.avro.io.parsing.Symbol, org.apache.avro.io.parsing.Symbol) throws java.io.IOException;
    Code:
       0: aconst_null
       1: areturn
}
