Compiled from "MockEvent.java"
public class org.springframework.mock.web.portlet.MockEvent implements javax.portlet.Event {
  private final javax.xml.namespace.QName name;

  private final java.io.Serializable value;

  public org.springframework.mock.web.portlet.MockEvent(javax.xml.namespace.QName);
    Code:
       0: aload_0
       1: invokespecial #1                  // Method java/lang/Object."<init>":()V
       4: aload_0
       5: aload_1
       6: putfield      #2                  // Field name:Ljavax/xml/namespace/QName;
       9: aload_0
      10: aconst_null
      11: putfield      #3                  // Field value:Ljava/io/Serializable;
      14: return

  public org.springframework.mock.web.portlet.MockEvent(javax.xml.namespace.QName, java.io.Serializable);
    Code:
       0: aload_0
       1: invokespecial #1                  // Method java/lang/Object."<init>":()V
       4: aload_0
       5: aload_1
       6: putfield      #2                  // Field name:Ljavax/xml/namespace/QName;
       9: aload_0
      10: aload_2
      11: putfield      #3                  // Field value:Ljava/io/Serializable;
      14: return

  public org.springframework.mock.web.portlet.MockEvent(java.lang.String);
    Code:
       0: aload_0
       1: invokespecial #1                  // Method java/lang/Object."<init>":()V
       4: aload_0
       5: new           #4                  // class javax/xml/namespace/QName
       8: dup
       9: aload_1
      10: invokespecial #5                  // Method javax/xml/namespace/QName."<init>":(Ljava/lang/String;)V
      13: putfield      #2                  // Field name:Ljavax/xml/namespace/QName;
      16: aload_0
      17: aconst_null
      18: putfield      #3                  // Field value:Ljava/io/Serializable;
      21: return

  public org.springframework.mock.web.portlet.MockEvent(java.lang.String, java.io.Serializable);
    Code:
       0: aload_0
       1: invokespecial #1                  // Method java/lang/Object."<init>":()V
       4: aload_0
       5: new           #4                  // class javax/xml/namespace/QName
       8: dup
       9: aload_1
      10: invokespecial #5                  // Method javax/xml/namespace/QName."<init>":(Ljava/lang/String;)V
      13: putfield      #2                  // Field name:Ljavax/xml/namespace/QName;
      16: aload_0
      17: aload_2
      18: putfield      #3                  // Field value:Ljava/io/Serializable;
      21: return

  public javax.xml.namespace.QName getQName();
    Code:
       0: aload_0
       1: getfield      #2                  // Field name:Ljavax/xml/namespace/QName;
       4: areturn

  public java.lang.String getName();
    Code:
       0: aload_0
       1: getfield      #2                  // Field name:Ljavax/xml/namespace/QName;
       4: invokevirtual #6                  // Method javax/xml/namespace/QName.getLocalPart:()Ljava/lang/String;
       7: areturn

  public java.io.Serializable getValue();
    Code:
       0: aload_0
       1: getfield      #3                  // Field value:Ljava/io/Serializable;
       4: areturn
}
