Compiled from "UnpooledHeapByteBuf.java"
public class io.netty.buffer.UnpooledHeapByteBuf extends io.netty.buffer.AbstractReferenceCountedByteBuf {
  private final io.netty.buffer.ByteBufAllocator alloc;

  byte[] array;

  private java.nio.ByteBuffer tmpNioBuf;

  protected io.netty.buffer.UnpooledHeapByteBuf(io.netty.buffer.ByteBufAllocator, int, int);
    Code:
       0: aload_0
       1: iload_3
       2: invokespecial #1                  // Method io/netty/buffer/AbstractReferenceCountedByteBuf."<init>":(I)V
       5: aload_1
       6: ldc           #2                  // String alloc
       8: invokestatic  #3                  // Method io/netty/util/internal/ObjectUtil.checkNotNull:(Ljava/lang/Object;Ljava/lang/String;)Ljava/lang/Object;
      11: pop
      12: iload_2
      13: iload_3
      14: if_icmple     48
      17: new           #4                  // class java/lang/IllegalArgumentException
      20: dup
      21: ldc           #5                  // String initialCapacity(%d) > maxCapacity(%d)
      23: iconst_2
      24: anewarray     #6                  // class java/lang/Object
      27: dup
      28: iconst_0
      29: iload_2
      30: invokestatic  #7                  // Method java/lang/Integer.valueOf:(I)Ljava/lang/Integer;
      33: aastore
      34: dup
      35: iconst_1
      36: iload_3
      37: invokestatic  #7                  // Method java/lang/Integer.valueOf:(I)Ljava/lang/Integer;
      40: aastore
      41: invokestatic  #8                  // Method java/lang/String.format:(Ljava/lang/String;[Ljava/lang/Object;)Ljava/lang/String;
      44: invokespecial #9                  // Method java/lang/IllegalArgumentException."<init>":(Ljava/lang/String;)V
      47: athrow
      48: aload_0
      49: aload_1
      50: putfield      #10                 // Field alloc:Lio/netty/buffer/ByteBufAllocator;
      53: aload_0
      54: aload_0
      55: iload_2
      56: invokevirtual #11                 // Method allocateArray:(I)[B
      59: invokespecial #12                 // Method setArray:([B)V
      62: aload_0
      63: iconst_0
      64: iconst_0
      65: invokevirtual #13                 // Method setIndex:(II)Lio/netty/buffer/ByteBuf;
      68: pop
      69: return

  protected io.netty.buffer.UnpooledHeapByteBuf(io.netty.buffer.ByteBufAllocator, byte[], int);
    Code:
       0: aload_0
       1: iload_3
       2: invokespecial #1                  // Method io/netty/buffer/AbstractReferenceCountedByteBuf."<init>":(I)V
       5: aload_1
       6: ldc           #2                  // String alloc
       8: invokestatic  #3                  // Method io/netty/util/internal/ObjectUtil.checkNotNull:(Ljava/lang/Object;Ljava/lang/String;)Ljava/lang/Object;
      11: pop
      12: aload_2
      13: ldc           #14                 // String initialArray
      15: invokestatic  #3                  // Method io/netty/util/internal/ObjectUtil.checkNotNull:(Ljava/lang/Object;Ljava/lang/String;)Ljava/lang/Object;
      18: pop
      19: aload_2
      20: arraylength
      21: iload_3
      22: if_icmple     57
      25: new           #4                  // class java/lang/IllegalArgumentException
      28: dup
      29: ldc           #5                  // String initialCapacity(%d) > maxCapacity(%d)
      31: iconst_2
      32: anewarray     #6                  // class java/lang/Object
      35: dup
      36: iconst_0
      37: aload_2
      38: arraylength
      39: invokestatic  #7                  // Method java/lang/Integer.valueOf:(I)Ljava/lang/Integer;
      42: aastore
      43: dup
      44: iconst_1
      45: iload_3
      46: invokestatic  #7                  // Method java/lang/Integer.valueOf:(I)Ljava/lang/Integer;
      49: aastore
      50: invokestatic  #8                  // Method java/lang/String.format:(Ljava/lang/String;[Ljava/lang/Object;)Ljava/lang/String;
      53: invokespecial #9                  // Method java/lang/IllegalArgumentException."<init>":(Ljava/lang/String;)V
      56: athrow
      57: aload_0
      58: aload_1
      59: putfield      #10                 // Field alloc:Lio/netty/buffer/ByteBufAllocator;
      62: aload_0
      63: aload_2
      64: invokespecial #12                 // Method setArray:([B)V
      67: aload_0
      68: iconst_0
      69: aload_2
      70: arraylength
      71: invokevirtual #13                 // Method setIndex:(II)Lio/netty/buffer/ByteBuf;
      74: pop
      75: return

  byte[] allocateArray(int);
    Code:
       0: iload_1
       1: newarray       byte
       3: areturn

  void freeArray(byte[]);
    Code:
       0: return

  private void setArray(byte[]);
    Code:
       0: aload_0
       1: aload_1
       2: putfield      #15                 // Field array:[B
       5: aload_0
       6: aconst_null
       7: putfield      #16                 // Field tmpNioBuf:Ljava/nio/ByteBuffer;
      10: return

  public io.netty.buffer.ByteBufAllocator alloc();
    Code:
       0: aload_0
       1: getfield      #10                 // Field alloc:Lio/netty/buffer/ByteBufAllocator;
       4: areturn

  public java.nio.ByteOrder order();
    Code:
       0: getstatic     #17                 // Field java/nio/ByteOrder.BIG_ENDIAN:Ljava/nio/ByteOrder;
       3: areturn

  public boolean isDirect();
    Code:
       0: iconst_0
       1: ireturn

  public int capacity();
    Code:
       0: aload_0
       1: invokevirtual #18                 // Method ensureAccessible:()V
       4: aload_0
       5: getfield      #15                 // Field array:[B
       8: arraylength
       9: ireturn

  public io.netty.buffer.ByteBuf capacity(int);
    Code:
       0: aload_0
       1: iload_1
       2: invokevirtual #19                 // Method checkNewCapacity:(I)V
       5: aload_0
       6: getfield      #15                 // Field array:[B
       9: arraylength
      10: istore_2
      11: aload_0
      12: getfield      #15                 // Field array:[B
      15: astore_3
      16: iload_1
      17: iload_2
      18: if_icmple     52
      21: aload_0
      22: iload_1
      23: invokevirtual #11                 // Method allocateArray:(I)[B
      26: astore        4
      28: aload_3
      29: iconst_0
      30: aload         4
      32: iconst_0
      33: aload_3
      34: arraylength
      35: invokestatic  #20                 // Method java/lang/System.arraycopy:(Ljava/lang/Object;ILjava/lang/Object;II)V
      38: aload_0
      39: aload         4
      41: invokespecial #12                 // Method setArray:([B)V
      44: aload_0
      45: aload_3
      46: invokevirtual #21                 // Method freeArray:([B)V
      49: goto          133
      52: iload_1
      53: iload_2
      54: if_icmpge     133
      57: aload_0
      58: iload_1
      59: invokevirtual #11                 // Method allocateArray:(I)[B
      62: astore        4
      64: aload_0
      65: invokevirtual #22                 // Method readerIndex:()I
      68: istore        5
      70: iload         5
      72: iload_1
      73: if_icmpge     115
      76: aload_0
      77: invokevirtual #23                 // Method writerIndex:()I
      80: istore        6
      82: iload         6
      84: iload_1
      85: if_icmple     97
      88: aload_0
      89: iload_1
      90: dup
      91: istore        6
      93: invokevirtual #24                 // Method writerIndex:(I)Lio/netty/buffer/ByteBuf;
      96: pop
      97: aload_3
      98: iload         5
     100: aload         4
     102: iload         5
     104: iload         6
     106: iload         5
     108: isub
     109: invokestatic  #20                 // Method java/lang/System.arraycopy:(Ljava/lang/Object;ILjava/lang/Object;II)V
     112: goto          122
     115: aload_0
     116: iload_1
     117: iload_1
     118: invokevirtual #13                 // Method setIndex:(II)Lio/netty/buffer/ByteBuf;
     121: pop
     122: aload_0
     123: aload         4
     125: invokespecial #12                 // Method setArray:([B)V
     128: aload_0
     129: aload_3
     130: invokevirtual #21                 // Method freeArray:([B)V
     133: aload_0
     134: areturn

  public boolean hasArray();
    Code:
       0: iconst_1
       1: ireturn

  public byte[] array();
    Code:
       0: aload_0
       1: invokevirtual #18                 // Method ensureAccessible:()V
       4: aload_0
       5: getfield      #15                 // Field array:[B
       8: areturn

  public int arrayOffset();
    Code:
       0: iconst_0
       1: ireturn

  public boolean hasMemoryAddress();
    Code:
       0: iconst_0
       1: ireturn

  public long memoryAddress();
    Code:
       0: new           #25                 // class java/lang/UnsupportedOperationException
       3: dup
       4: invokespecial #26                 // Method java/lang/UnsupportedOperationException."<init>":()V
       7: athrow

  public io.netty.buffer.ByteBuf getBytes(int, io.netty.buffer.ByteBuf, int, int);
    Code:
       0: aload_0
       1: iload_1
       2: iload         4
       4: iload_3
       5: aload_2
       6: invokevirtual #27                 // Method io/netty/buffer/ByteBuf.capacity:()I
       9: invokevirtual #28                 // Method checkDstIndex:(IIII)V
      12: aload_2
      13: invokevirtual #29                 // Method io/netty/buffer/ByteBuf.hasMemoryAddress:()Z
      16: ifeq          40
      19: aload_0
      20: getfield      #15                 // Field array:[B
      23: iload_1
      24: aload_2
      25: invokevirtual #30                 // Method io/netty/buffer/ByteBuf.memoryAddress:()J
      28: iload_3
      29: i2l
      30: ladd
      31: iload         4
      33: i2l
      34: invokestatic  #31                 // Method io/netty/util/internal/PlatformDependent.copyMemory:([BIJJ)V
      37: goto          81
      40: aload_2
      41: invokevirtual #32                 // Method io/netty/buffer/ByteBuf.hasArray:()Z
      44: ifeq          68
      47: aload_0
      48: iload_1
      49: aload_2
      50: invokevirtual #33                 // Method io/netty/buffer/ByteBuf.array:()[B
      53: aload_2
      54: invokevirtual #34                 // Method io/netty/buffer/ByteBuf.arrayOffset:()I
      57: iload_3
      58: iadd
      59: iload         4
      61: invokevirtual #35                 // Method getBytes:(I[BII)Lio/netty/buffer/ByteBuf;
      64: pop
      65: goto          81
      68: aload_2
      69: iload_3
      70: aload_0
      71: getfield      #15                 // Field array:[B
      74: iload_1
      75: iload         4
      77: invokevirtual #36                 // Method io/netty/buffer/ByteBuf.setBytes:(I[BII)Lio/netty/buffer/ByteBuf;
      80: pop
      81: aload_0
      82: areturn

  public io.netty.buffer.ByteBuf getBytes(int, byte[], int, int);
    Code:
       0: aload_0
       1: iload_1
       2: iload         4
       4: iload_3
       5: aload_2
       6: arraylength
       7: invokevirtual #28                 // Method checkDstIndex:(IIII)V
      10: aload_0
      11: getfield      #15                 // Field array:[B
      14: iload_1
      15: aload_2
      16: iload_3
      17: iload         4
      19: invokestatic  #20                 // Method java/lang/System.arraycopy:(Ljava/lang/Object;ILjava/lang/Object;II)V
      22: aload_0
      23: areturn

  public io.netty.buffer.ByteBuf getBytes(int, java.nio.ByteBuffer);
    Code:
       0: aload_0
       1: iload_1
       2: aload_2
       3: invokevirtual #37                 // Method java/nio/ByteBuffer.remaining:()I
       6: invokevirtual #38                 // Method checkIndex:(II)V
       9: aload_2
      10: aload_0
      11: getfield      #15                 // Field array:[B
      14: iload_1
      15: aload_2
      16: invokevirtual #37                 // Method java/nio/ByteBuffer.remaining:()I
      19: invokevirtual #39                 // Method java/nio/ByteBuffer.put:([BII)Ljava/nio/ByteBuffer;
      22: pop
      23: aload_0
      24: areturn

  public io.netty.buffer.ByteBuf getBytes(int, java.io.OutputStream, int) throws java.io.IOException;
    Code:
       0: aload_0
       1: invokevirtual #18                 // Method ensureAccessible:()V
       4: aload_2
       5: aload_0
       6: getfield      #15                 // Field array:[B
       9: iload_1
      10: iload_3
      11: invokevirtual #40                 // Method java/io/OutputStream.write:([BII)V
      14: aload_0
      15: areturn

  public int getBytes(int, java.nio.channels.GatheringByteChannel, int) throws java.io.IOException;
    Code:
       0: aload_0
       1: invokevirtual #18                 // Method ensureAccessible:()V
       4: aload_0
       5: iload_1
       6: aload_2
       7: iload_3
       8: iconst_0
       9: invokespecial #41                 // Method getBytes:(ILjava/nio/channels/GatheringByteChannel;IZ)I
      12: ireturn

  public int getBytes(int, java.nio.channels.FileChannel, long, int) throws java.io.IOException;
    Code:
       0: aload_0
       1: invokevirtual #18                 // Method ensureAccessible:()V
       4: aload_0
       5: iload_1
       6: aload_2
       7: lload_3
       8: iload         5
      10: iconst_0
      11: invokespecial #42                 // Method getBytes:(ILjava/nio/channels/FileChannel;JIZ)I
      14: ireturn

  private int getBytes(int, java.nio.channels.GatheringByteChannel, int, boolean) throws java.io.IOException;
    Code:
       0: aload_0
       1: invokevirtual #18                 // Method ensureAccessible:()V
       4: iload         4
       6: ifeq          18
       9: aload_0
      10: invokespecial #43                 // Method internalNioBuffer:()Ljava/nio/ByteBuffer;
      13: astore        5
      15: goto          27
      18: aload_0
      19: getfield      #15                 // Field array:[B
      22: invokestatic  #44                 // Method java/nio/ByteBuffer.wrap:([B)Ljava/nio/ByteBuffer;
      25: astore        5
      27: aload_2
      28: aload         5
      30: invokevirtual #45                 // Method java/nio/ByteBuffer.clear:()Ljava/nio/Buffer;
      33: iload_1
      34: invokevirtual #46                 // Method java/nio/Buffer.position:(I)Ljava/nio/Buffer;
      37: iload_1
      38: iload_3
      39: iadd
      40: invokevirtual #47                 // Method java/nio/Buffer.limit:(I)Ljava/nio/Buffer;
      43: checkcast     #48                 // class java/nio/ByteBuffer
      46: invokeinterface #49,  2           // InterfaceMethod java/nio/channels/GatheringByteChannel.write:(Ljava/nio/ByteBuffer;)I
      51: ireturn

  private int getBytes(int, java.nio.channels.FileChannel, long, int, boolean) throws java.io.IOException;
    Code:
       0: aload_0
       1: invokevirtual #18                 // Method ensureAccessible:()V
       4: iload         6
       6: ifeq          16
       9: aload_0
      10: invokespecial #43                 // Method internalNioBuffer:()Ljava/nio/ByteBuffer;
      13: goto          23
      16: aload_0
      17: getfield      #15                 // Field array:[B
      20: invokestatic  #44                 // Method java/nio/ByteBuffer.wrap:([B)Ljava/nio/ByteBuffer;
      23: astore        7
      25: aload_2
      26: aload         7
      28: invokevirtual #45                 // Method java/nio/ByteBuffer.clear:()Ljava/nio/Buffer;
      31: iload_1
      32: invokevirtual #46                 // Method java/nio/Buffer.position:(I)Ljava/nio/Buffer;
      35: iload_1
      36: iload         5
      38: iadd
      39: invokevirtual #47                 // Method java/nio/Buffer.limit:(I)Ljava/nio/Buffer;
      42: checkcast     #48                 // class java/nio/ByteBuffer
      45: lload_3
      46: invokevirtual #50                 // Method java/nio/channels/FileChannel.write:(Ljava/nio/ByteBuffer;J)I
      49: ireturn

  public int readBytes(java.nio.channels.GatheringByteChannel, int) throws java.io.IOException;
    Code:
       0: aload_0
       1: iload_2
       2: invokevirtual #51                 // Method checkReadableBytes:(I)V
       5: aload_0
       6: aload_0
       7: getfield      #52                 // Field readerIndex:I
      10: aload_1
      11: iload_2
      12: iconst_1
      13: invokespecial #41                 // Method getBytes:(ILjava/nio/channels/GatheringByteChannel;IZ)I
      16: istore_3
      17: aload_0
      18: dup
      19: getfield      #52                 // Field readerIndex:I
      22: iload_3
      23: iadd
      24: putfield      #52                 // Field readerIndex:I
      27: iload_3
      28: ireturn

  public int readBytes(java.nio.channels.FileChannel, long, int) throws java.io.IOException;
    Code:
       0: aload_0
       1: iload         4
       3: invokevirtual #51                 // Method checkReadableBytes:(I)V
       6: aload_0
       7: aload_0
       8: getfield      #52                 // Field readerIndex:I
      11: aload_1
      12: lload_2
      13: iload         4
      15: iconst_1
      16: invokespecial #42                 // Method getBytes:(ILjava/nio/channels/FileChannel;JIZ)I
      19: istore        5
      21: aload_0
      22: dup
      23: getfield      #52                 // Field readerIndex:I
      26: iload         5
      28: iadd
      29: putfield      #52                 // Field readerIndex:I
      32: iload         5
      34: ireturn

  public io.netty.buffer.ByteBuf setBytes(int, io.netty.buffer.ByteBuf, int, int);
    Code:
       0: aload_0
       1: iload_1
       2: iload         4
       4: iload_3
       5: aload_2
       6: invokevirtual #27                 // Method io/netty/buffer/ByteBuf.capacity:()I
       9: invokevirtual #53                 // Method checkSrcIndex:(IIII)V
      12: aload_2
      13: invokevirtual #29                 // Method io/netty/buffer/ByteBuf.hasMemoryAddress:()Z
      16: ifeq          40
      19: aload_2
      20: invokevirtual #30                 // Method io/netty/buffer/ByteBuf.memoryAddress:()J
      23: iload_3
      24: i2l
      25: ladd
      26: aload_0
      27: getfield      #15                 // Field array:[B
      30: iload_1
      31: iload         4
      33: i2l
      34: invokestatic  #54                 // Method io/netty/util/internal/PlatformDependent.copyMemory:(J[BIJ)V
      37: goto          81
      40: aload_2
      41: invokevirtual #32                 // Method io/netty/buffer/ByteBuf.hasArray:()Z
      44: ifeq          68
      47: aload_0
      48: iload_1
      49: aload_2
      50: invokevirtual #33                 // Method io/netty/buffer/ByteBuf.array:()[B
      53: aload_2
      54: invokevirtual #34                 // Method io/netty/buffer/ByteBuf.arrayOffset:()I
      57: iload_3
      58: iadd
      59: iload         4
      61: invokevirtual #55                 // Method setBytes:(I[BII)Lio/netty/buffer/ByteBuf;
      64: pop
      65: goto          81
      68: aload_2
      69: iload_3
      70: aload_0
      71: getfield      #15                 // Field array:[B
      74: iload_1
      75: iload         4
      77: invokevirtual #56                 // Method io/netty/buffer/ByteBuf.getBytes:(I[BII)Lio/netty/buffer/ByteBuf;
      80: pop
      81: aload_0
      82: areturn

  public io.netty.buffer.ByteBuf setBytes(int, byte[], int, int);
    Code:
       0: aload_0
       1: iload_1
       2: iload         4
       4: iload_3
       5: aload_2
       6: arraylength
       7: invokevirtual #53                 // Method checkSrcIndex:(IIII)V
      10: aload_2
      11: iload_3
      12: aload_0
      13: getfield      #15                 // Field array:[B
      16: iload_1
      17: iload         4
      19: invokestatic  #20                 // Method java/lang/System.arraycopy:(Ljava/lang/Object;ILjava/lang/Object;II)V
      22: aload_0
      23: areturn

  public io.netty.buffer.ByteBuf setBytes(int, java.nio.ByteBuffer);
    Code:
       0: aload_0
       1: invokevirtual #18                 // Method ensureAccessible:()V
       4: aload_2
       5: aload_0
       6: getfield      #15                 // Field array:[B
       9: iload_1
      10: aload_2
      11: invokevirtual #37                 // Method java/nio/ByteBuffer.remaining:()I
      14: invokevirtual #57                 // Method java/nio/ByteBuffer.get:([BII)Ljava/nio/ByteBuffer;
      17: pop
      18: aload_0
      19: areturn

  public int setBytes(int, java.io.InputStream, int) throws java.io.IOException;
    Code:
       0: aload_0
       1: invokevirtual #18                 // Method ensureAccessible:()V
       4: aload_2
       5: aload_0
       6: getfield      #15                 // Field array:[B
       9: iload_1
      10: iload_3
      11: invokevirtual #58                 // Method java/io/InputStream.read:([BII)I
      14: ireturn

  public int setBytes(int, java.nio.channels.ScatteringByteChannel, int) throws java.io.IOException;
    Code:
       0: aload_0
       1: invokevirtual #18                 // Method ensureAccessible:()V
       4: aload_2
       5: aload_0
       6: invokespecial #43                 // Method internalNioBuffer:()Ljava/nio/ByteBuffer;
       9: invokevirtual #45                 // Method java/nio/ByteBuffer.clear:()Ljava/nio/Buffer;
      12: iload_1
      13: invokevirtual #46                 // Method java/nio/Buffer.position:(I)Ljava/nio/Buffer;
      16: iload_1
      17: iload_3
      18: iadd
      19: invokevirtual #47                 // Method java/nio/Buffer.limit:(I)Ljava/nio/Buffer;
      22: checkcast     #48                 // class java/nio/ByteBuffer
      25: invokeinterface #59,  2           // InterfaceMethod java/nio/channels/ScatteringByteChannel.read:(Ljava/nio/ByteBuffer;)I
      30: ireturn
      31: astore        4
      33: iconst_m1
      34: ireturn
    Exception table:
       from    to  target type
           4    30    31   Class java/nio/channels/ClosedChannelException

  public int setBytes(int, java.nio.channels.FileChannel, long, int) throws java.io.IOException;
    Code:
       0: aload_0
       1: invokevirtual #18                 // Method ensureAccessible:()V
       4: aload_2
       5: aload_0
       6: invokespecial #43                 // Method internalNioBuffer:()Ljava/nio/ByteBuffer;
       9: invokevirtual #45                 // Method java/nio/ByteBuffer.clear:()Ljava/nio/Buffer;
      12: iload_1
      13: invokevirtual #46                 // Method java/nio/Buffer.position:(I)Ljava/nio/Buffer;
      16: iload_1
      17: iload         5
      19: iadd
      20: invokevirtual #47                 // Method java/nio/Buffer.limit:(I)Ljava/nio/Buffer;
      23: checkcast     #48                 // class java/nio/ByteBuffer
      26: lload_3
      27: invokevirtual #61                 // Method java/nio/channels/FileChannel.read:(Ljava/nio/ByteBuffer;J)I
      30: ireturn
      31: astore        6
      33: iconst_m1
      34: ireturn
    Exception table:
       from    to  target type
           4    30    31   Class java/nio/channels/ClosedChannelException

  public int nioBufferCount();
    Code:
       0: iconst_1
       1: ireturn

  public java.nio.ByteBuffer nioBuffer(int, int);
    Code:
       0: aload_0
       1: invokevirtual #18                 // Method ensureAccessible:()V
       4: aload_0
       5: getfield      #15                 // Field array:[B
       8: iload_1
       9: iload_2
      10: invokestatic  #62                 // Method java/nio/ByteBuffer.wrap:([BII)Ljava/nio/ByteBuffer;
      13: invokevirtual #63                 // Method java/nio/ByteBuffer.slice:()Ljava/nio/ByteBuffer;
      16: areturn

  public java.nio.ByteBuffer[] nioBuffers(int, int);
    Code:
       0: iconst_1
       1: anewarray     #48                 // class java/nio/ByteBuffer
       4: dup
       5: iconst_0
       6: aload_0
       7: iload_1
       8: iload_2
       9: invokevirtual #64                 // Method nioBuffer:(II)Ljava/nio/ByteBuffer;
      12: aastore
      13: areturn

  public java.nio.ByteBuffer internalNioBuffer(int, int);
    Code:
       0: aload_0
       1: iload_1
       2: iload_2
       3: invokevirtual #38                 // Method checkIndex:(II)V
       6: aload_0
       7: invokespecial #43                 // Method internalNioBuffer:()Ljava/nio/ByteBuffer;
      10: invokevirtual #45                 // Method java/nio/ByteBuffer.clear:()Ljava/nio/Buffer;
      13: iload_1
      14: invokevirtual #46                 // Method java/nio/Buffer.position:(I)Ljava/nio/Buffer;
      17: iload_1
      18: iload_2
      19: iadd
      20: invokevirtual #47                 // Method java/nio/Buffer.limit:(I)Ljava/nio/Buffer;
      23: checkcast     #48                 // class java/nio/ByteBuffer
      26: areturn

  public byte getByte(int);
    Code:
       0: aload_0
       1: invokevirtual #18                 // Method ensureAccessible:()V
       4: aload_0
       5: iload_1
       6: invokevirtual #65                 // Method _getByte:(I)B
       9: ireturn

  protected byte _getByte(int);
    Code:
       0: aload_0
       1: getfield      #15                 // Field array:[B
       4: iload_1
       5: invokestatic  #66                 // Method io/netty/buffer/HeapByteBufUtil.getByte:([BI)B
       8: ireturn

  public short getShort(int);
    Code:
       0: aload_0
       1: invokevirtual #18                 // Method ensureAccessible:()V
       4: aload_0
       5: iload_1
       6: invokevirtual #67                 // Method _getShort:(I)S
       9: ireturn

  protected short _getShort(int);
    Code:
       0: aload_0
       1: getfield      #15                 // Field array:[B
       4: iload_1
       5: invokestatic  #68                 // Method io/netty/buffer/HeapByteBufUtil.getShort:([BI)S
       8: ireturn

  public short getShortLE(int);
    Code:
       0: aload_0
       1: invokevirtual #18                 // Method ensureAccessible:()V
       4: aload_0
       5: iload_1
       6: invokevirtual #69                 // Method _getShortLE:(I)S
       9: ireturn

  protected short _getShortLE(int);
    Code:
       0: aload_0
       1: getfield      #15                 // Field array:[B
       4: iload_1
       5: invokestatic  #70                 // Method io/netty/buffer/HeapByteBufUtil.getShortLE:([BI)S
       8: ireturn

  public int getUnsignedMedium(int);
    Code:
       0: aload_0
       1: invokevirtual #18                 // Method ensureAccessible:()V
       4: aload_0
       5: iload_1
       6: invokevirtual #71                 // Method _getUnsignedMedium:(I)I
       9: ireturn

  protected int _getUnsignedMedium(int);
    Code:
       0: aload_0
       1: getfield      #15                 // Field array:[B
       4: iload_1
       5: invokestatic  #72                 // Method io/netty/buffer/HeapByteBufUtil.getUnsignedMedium:([BI)I
       8: ireturn

  public int getUnsignedMediumLE(int);
    Code:
       0: aload_0
       1: invokevirtual #18                 // Method ensureAccessible:()V
       4: aload_0
       5: iload_1
       6: invokevirtual #73                 // Method _getUnsignedMediumLE:(I)I
       9: ireturn

  protected int _getUnsignedMediumLE(int);
    Code:
       0: aload_0
       1: getfield      #15                 // Field array:[B
       4: iload_1
       5: invokestatic  #74                 // Method io/netty/buffer/HeapByteBufUtil.getUnsignedMediumLE:([BI)I
       8: ireturn

  public int getInt(int);
    Code:
       0: aload_0
       1: invokevirtual #18                 // Method ensureAccessible:()V
       4: aload_0
       5: iload_1
       6: invokevirtual #75                 // Method _getInt:(I)I
       9: ireturn

  protected int _getInt(int);
    Code:
       0: aload_0
       1: getfield      #15                 // Field array:[B
       4: iload_1
       5: invokestatic  #76                 // Method io/netty/buffer/HeapByteBufUtil.getInt:([BI)I
       8: ireturn

  public int getIntLE(int);
    Code:
       0: aload_0
       1: invokevirtual #18                 // Method ensureAccessible:()V
       4: aload_0
       5: iload_1
       6: invokevirtual #77                 // Method _getIntLE:(I)I
       9: ireturn

  protected int _getIntLE(int);
    Code:
       0: aload_0
       1: getfield      #15                 // Field array:[B
       4: iload_1
       5: invokestatic  #78                 // Method io/netty/buffer/HeapByteBufUtil.getIntLE:([BI)I
       8: ireturn

  public long getLong(int);
    Code:
       0: aload_0
       1: invokevirtual #18                 // Method ensureAccessible:()V
       4: aload_0
       5: iload_1
       6: invokevirtual #79                 // Method _getLong:(I)J
       9: lreturn

  protected long _getLong(int);
    Code:
       0: aload_0
       1: getfield      #15                 // Field array:[B
       4: iload_1
       5: invokestatic  #80                 // Method io/netty/buffer/HeapByteBufUtil.getLong:([BI)J
       8: lreturn

  public long getLongLE(int);
    Code:
       0: aload_0
       1: invokevirtual #18                 // Method ensureAccessible:()V
       4: aload_0
       5: iload_1
       6: invokevirtual #81                 // Method _getLongLE:(I)J
       9: lreturn

  protected long _getLongLE(int);
    Code:
       0: aload_0
       1: getfield      #15                 // Field array:[B
       4: iload_1
       5: invokestatic  #82                 // Method io/netty/buffer/HeapByteBufUtil.getLongLE:([BI)J
       8: lreturn

  public io.netty.buffer.ByteBuf setByte(int, int);
    Code:
       0: aload_0
       1: invokevirtual #18                 // Method ensureAccessible:()V
       4: aload_0
       5: iload_1
       6: iload_2
       7: invokevirtual #83                 // Method _setByte:(II)V
      10: aload_0
      11: areturn

  protected void _setByte(int, int);
    Code:
       0: aload_0
       1: getfield      #15                 // Field array:[B
       4: iload_1
       5: iload_2
       6: invokestatic  #84                 // Method io/netty/buffer/HeapByteBufUtil.setByte:([BII)V
       9: return

  public io.netty.buffer.ByteBuf setShort(int, int);
    Code:
       0: aload_0
       1: invokevirtual #18                 // Method ensureAccessible:()V
       4: aload_0
       5: iload_1
       6: iload_2
       7: invokevirtual #85                 // Method _setShort:(II)V
      10: aload_0
      11: areturn

  protected void _setShort(int, int);
    Code:
       0: aload_0
       1: getfield      #15                 // Field array:[B
       4: iload_1
       5: iload_2
       6: invokestatic  #86                 // Method io/netty/buffer/HeapByteBufUtil.setShort:([BII)V
       9: return

  public io.netty.buffer.ByteBuf setShortLE(int, int);
    Code:
       0: aload_0
       1: invokevirtual #18                 // Method ensureAccessible:()V
       4: aload_0
       5: iload_1
       6: iload_2
       7: invokevirtual #87                 // Method _setShortLE:(II)V
      10: aload_0
      11: areturn

  protected void _setShortLE(int, int);
    Code:
       0: aload_0
       1: getfield      #15                 // Field array:[B
       4: iload_1
       5: iload_2
       6: invokestatic  #88                 // Method io/netty/buffer/HeapByteBufUtil.setShortLE:([BII)V
       9: return

  public io.netty.buffer.ByteBuf setMedium(int, int);
    Code:
       0: aload_0
       1: invokevirtual #18                 // Method ensureAccessible:()V
       4: aload_0
       5: iload_1
       6: iload_2
       7: invokevirtual #89                 // Method _setMedium:(II)V
      10: aload_0
      11: areturn

  protected void _setMedium(int, int);
    Code:
       0: aload_0
       1: getfield      #15                 // Field array:[B
       4: iload_1
       5: iload_2
       6: invokestatic  #90                 // Method io/netty/buffer/HeapByteBufUtil.setMedium:([BII)V
       9: return

  public io.netty.buffer.ByteBuf setMediumLE(int, int);
    Code:
       0: aload_0
       1: invokevirtual #18                 // Method ensureAccessible:()V
       4: aload_0
       5: iload_1
       6: iload_2
       7: invokevirtual #91                 // Method _setMediumLE:(II)V
      10: aload_0
      11: areturn

  protected void _setMediumLE(int, int);
    Code:
       0: aload_0
       1: getfield      #15                 // Field array:[B
       4: iload_1
       5: iload_2
       6: invokestatic  #92                 // Method io/netty/buffer/HeapByteBufUtil.setMediumLE:([BII)V
       9: return

  public io.netty.buffer.ByteBuf setInt(int, int);
    Code:
       0: aload_0
       1: invokevirtual #18                 // Method ensureAccessible:()V
       4: aload_0
       5: iload_1
       6: iload_2
       7: invokevirtual #93                 // Method _setInt:(II)V
      10: aload_0
      11: areturn

  protected void _setInt(int, int);
    Code:
       0: aload_0
       1: getfield      #15                 // Field array:[B
       4: iload_1
       5: iload_2
       6: invokestatic  #94                 // Method io/netty/buffer/HeapByteBufUtil.setInt:([BII)V
       9: return

  public io.netty.buffer.ByteBuf setIntLE(int, int);
    Code:
       0: aload_0
       1: invokevirtual #18                 // Method ensureAccessible:()V
       4: aload_0
       5: iload_1
       6: iload_2
       7: invokevirtual #95                 // Method _setIntLE:(II)V
      10: aload_0
      11: areturn

  protected void _setIntLE(int, int);
    Code:
       0: aload_0
       1: getfield      #15                 // Field array:[B
       4: iload_1
       5: iload_2
       6: invokestatic  #96                 // Method io/netty/buffer/HeapByteBufUtil.setIntLE:([BII)V
       9: return

  public io.netty.buffer.ByteBuf setLong(int, long);
    Code:
       0: aload_0
       1: invokevirtual #18                 // Method ensureAccessible:()V
       4: aload_0
       5: iload_1
       6: lload_2
       7: invokevirtual #97                 // Method _setLong:(IJ)V
      10: aload_0
      11: areturn

  protected void _setLong(int, long);
    Code:
       0: aload_0
       1: getfield      #15                 // Field array:[B
       4: iload_1
       5: lload_2
       6: invokestatic  #98                 // Method io/netty/buffer/HeapByteBufUtil.setLong:([BIJ)V
       9: return

  public io.netty.buffer.ByteBuf setLongLE(int, long);
    Code:
       0: aload_0
       1: invokevirtual #18                 // Method ensureAccessible:()V
       4: aload_0
       5: iload_1
       6: lload_2
       7: invokevirtual #99                 // Method _setLongLE:(IJ)V
      10: aload_0
      11: areturn

  protected void _setLongLE(int, long);
    Code:
       0: aload_0
       1: getfield      #15                 // Field array:[B
       4: iload_1
       5: lload_2
       6: invokestatic  #100                // Method io/netty/buffer/HeapByteBufUtil.setLongLE:([BIJ)V
       9: return

  public io.netty.buffer.ByteBuf copy(int, int);
    Code:
       0: aload_0
       1: iload_1
       2: iload_2
       3: invokevirtual #38                 // Method checkIndex:(II)V
       6: iload_2
       7: newarray       byte
       9: astore_3
      10: aload_0
      11: getfield      #15                 // Field array:[B
      14: iload_1
      15: aload_3
      16: iconst_0
      17: iload_2
      18: invokestatic  #20                 // Method java/lang/System.arraycopy:(Ljava/lang/Object;ILjava/lang/Object;II)V
      21: new           #101                // class io/netty/buffer/UnpooledHeapByteBuf
      24: dup
      25: aload_0
      26: invokevirtual #102                // Method alloc:()Lio/netty/buffer/ByteBufAllocator;
      29: aload_3
      30: aload_0
      31: invokevirtual #103                // Method maxCapacity:()I
      34: invokespecial #104                // Method "<init>":(Lio/netty/buffer/ByteBufAllocator;[BI)V
      37: areturn

  private java.nio.ByteBuffer internalNioBuffer();
    Code:
       0: aload_0
       1: getfield      #16                 // Field tmpNioBuf:Ljava/nio/ByteBuffer;
       4: astore_1
       5: aload_1
       6: ifnonnull     22
       9: aload_0
      10: aload_0
      11: getfield      #15                 // Field array:[B
      14: invokestatic  #44                 // Method java/nio/ByteBuffer.wrap:([B)Ljava/nio/ByteBuffer;
      17: dup
      18: astore_1
      19: putfield      #16                 // Field tmpNioBuf:Ljava/nio/ByteBuffer;
      22: aload_1
      23: areturn

  protected void deallocate();
    Code:
       0: aload_0
       1: aload_0
       2: getfield      #15                 // Field array:[B
       5: invokevirtual #21                 // Method freeArray:([B)V
       8: aload_0
       9: aconst_null
      10: putfield      #15                 // Field array:[B
      13: return

  public io.netty.buffer.ByteBuf unwrap();
    Code:
       0: aconst_null
       1: areturn
}
