Compiled from "Iterators.java"
public class org.aspectj.weaver.Iterators$ResolvedTypeArrayIterator implements java.util.Iterator<org.aspectj.weaver.ResolvedType> {
  private org.aspectj.weaver.ResolvedType[] array;

  private int index;

  private int len;

  private boolean wantGenerics;

  private java.util.List<java.lang.String> alreadySeen;

  static final boolean $assertionsDisabled;

  public org.aspectj.weaver.Iterators$ResolvedTypeArrayIterator(org.aspectj.weaver.ResolvedType[], java.util.List<java.lang.String>, boolean);
    Code:
       0: aload_0
       1: invokespecial #1                  // Method java/lang/Object."<init>":()V
       4: getstatic     #2                  // Field $assertionsDisabled:Z
       7: ifne          22
      10: aload_1
      11: ifnonnull     22
      14: new           #3                  // class java/lang/AssertionError
      17: dup
      18: invokespecial #4                  // Method java/lang/AssertionError."<init>":()V
      21: athrow
      22: aload_0
      23: aload_1
      24: putfield      #5                  // Field array:[Lorg/aspectj/weaver/ResolvedType;
      27: aload_0
      28: iload_3
      29: putfield      #6                  // Field wantGenerics:Z
      32: aload_0
      33: aload_1
      34: arraylength
      35: putfield      #7                  // Field len:I
      38: aload_0
      39: iconst_0
      40: putfield      #8                  // Field index:I
      43: aload_0
      44: aload_2
      45: putfield      #9                  // Field alreadySeen:Ljava/util/List;
      48: aload_0
      49: invokespecial #10                 // Method moveToNextNewOne:()V
      52: return

  private void moveToNextNewOne();
    Code:
       0: aload_0
       1: getfield      #8                  // Field index:I
       4: aload_0
       5: getfield      #7                  // Field len:I
       8: if_icmpge     74
      11: aload_0
      12: getfield      #5                  // Field array:[Lorg/aspectj/weaver/ResolvedType;
      15: aload_0
      16: getfield      #8                  // Field index:I
      19: aaload
      20: astore_1
      21: aload_0
      22: getfield      #6                  // Field wantGenerics:Z
      25: ifne          40
      28: aload_1
      29: invokevirtual #11                 // Method org/aspectj/weaver/ResolvedType.isParameterizedOrGenericType:()Z
      32: ifeq          40
      35: aload_1
      36: invokevirtual #12                 // Method org/aspectj/weaver/ResolvedType.getRawType:()Lorg/aspectj/weaver/ResolvedType;
      39: astore_1
      40: aload_1
      41: invokevirtual #13                 // Method org/aspectj/weaver/ResolvedType.getSignature:()Ljava/lang/String;
      44: astore_2
      45: aload_0
      46: getfield      #9                  // Field alreadySeen:Ljava/util/List;
      49: aload_2
      50: invokeinterface #14,  2           // InterfaceMethod java/util/List.contains:(Ljava/lang/Object;)Z
      55: ifne          61
      58: goto          74
      61: aload_0
      62: dup
      63: getfield      #8                  // Field index:I
      66: iconst_1
      67: iadd
      68: putfield      #8                  // Field index:I
      71: goto          0
      74: return

  public boolean hasNext();
    Code:
       0: aload_0
       1: getfield      #8                  // Field index:I
       4: aload_0
       5: getfield      #7                  // Field len:I
       8: if_icmpge     15
      11: iconst_1
      12: goto          16
      15: iconst_0
      16: ireturn

  public org.aspectj.weaver.ResolvedType next();
    Code:
       0: aload_0
       1: getfield      #8                  // Field index:I
       4: aload_0
       5: getfield      #7                  // Field len:I
       8: if_icmpge     74
      11: aload_0
      12: getfield      #5                  // Field array:[Lorg/aspectj/weaver/ResolvedType;
      15: aload_0
      16: dup
      17: getfield      #8                  // Field index:I
      20: dup_x1
      21: iconst_1
      22: iadd
      23: putfield      #8                  // Field index:I
      26: aaload
      27: astore_1
      28: aload_0
      29: getfield      #6                  // Field wantGenerics:Z
      32: ifne          54
      35: aload_1
      36: invokevirtual #15                 // Method org/aspectj/weaver/ResolvedType.isParameterizedType:()Z
      39: ifne          49
      42: aload_1
      43: invokevirtual #16                 // Method org/aspectj/weaver/ResolvedType.isGenericType:()Z
      46: ifeq          54
      49: aload_1
      50: invokevirtual #12                 // Method org/aspectj/weaver/ResolvedType.getRawType:()Lorg/aspectj/weaver/ResolvedType;
      53: astore_1
      54: aload_0
      55: getfield      #9                  // Field alreadySeen:Ljava/util/List;
      58: aload_1
      59: invokevirtual #13                 // Method org/aspectj/weaver/ResolvedType.getSignature:()Ljava/lang/String;
      62: invokeinterface #17,  2           // InterfaceMethod java/util/List.add:(Ljava/lang/Object;)Z
      67: pop
      68: aload_0
      69: invokespecial #10                 // Method moveToNextNewOne:()V
      72: aload_1
      73: areturn
      74: new           #18                 // class java/util/NoSuchElementException
      77: dup
      78: invokespecial #19                 // Method java/util/NoSuchElementException."<init>":()V
      81: athrow

  public void remove();
    Code:
       0: new           #20                 // class java/lang/UnsupportedOperationException
       3: dup
       4: invokespecial #21                 // Method java/lang/UnsupportedOperationException."<init>":()V
       7: athrow

  public java.lang.Object next();
    Code:
       0: aload_0
       1: invokevirtual #22                 // Method next:()Lorg/aspectj/weaver/ResolvedType;
       4: areturn

  static {};
    Code:
       0: ldc           #23                 // class org/aspectj/weaver/Iterators
       2: invokevirtual #24                 // Method java/lang/Class.desiredAssertionStatus:()Z
       5: ifne          12
       8: iconst_1
       9: goto          13
      12: iconst_0
      13: putstatic     #2                  // Field $assertionsDisabled:Z
      16: return
}
