Compiled from "Iterators.java"
final class org.aspectj.weaver.Iterators$2 implements java.util.Iterator<T> {
  int i;

  int len;

  final java.lang.Object[] val$o;

  org.aspectj.weaver.Iterators$2(java.lang.Object[]);
    Code:
       0: aload_0
       1: aload_1
       2: putfield      #1                  // Field val$o:[Ljava/lang/Object;
       5: aload_0
       6: invokespecial #2                  // Method java/lang/Object."<init>":()V
       9: aload_0
      10: iconst_0
      11: putfield      #3                  // Field i:I
      14: aload_0
      15: aload_0
      16: getfield      #1                  // Field val$o:[Ljava/lang/Object;
      19: ifnonnull     26
      22: iconst_0
      23: goto          31
      26: aload_0
      27: getfield      #1                  // Field val$o:[Ljava/lang/Object;
      30: arraylength
      31: putfield      #4                  // Field len:I
      34: return

  public boolean hasNext();
    Code:
       0: aload_0
       1: getfield      #3                  // Field i:I
       4: aload_0
       5: getfield      #4                  // Field len:I
       8: if_icmpge     15
      11: iconst_1
      12: goto          16
      15: iconst_0
      16: ireturn

  public T next();
    Code:
       0: aload_0
       1: getfield      #3                  // Field i:I
       4: aload_0
       5: getfield      #4                  // Field len:I
       8: if_icmpge     28
      11: aload_0
      12: getfield      #1                  // Field val$o:[Ljava/lang/Object;
      15: aload_0
      16: dup
      17: getfield      #3                  // Field i:I
      20: dup_x1
      21: iconst_1
      22: iadd
      23: putfield      #3                  // Field i:I
      26: aaload
      27: areturn
      28: new           #5                  // class java/util/NoSuchElementException
      31: dup
      32: invokespecial #6                  // Method java/util/NoSuchElementException."<init>":()V
      35: athrow

  public void remove();
    Code:
       0: new           #7                  // class java/lang/UnsupportedOperationException
       3: dup
       4: invokespecial #8                  // Method java/lang/UnsupportedOperationException."<init>":()V
       7: athrow
}
