Compiled from "MissingResolvedTypeWithKnownSignature.java"
public class org.aspectj.weaver.MissingResolvedTypeWithKnownSignature extends org.aspectj.weaver.ResolvedType {
  private static org.aspectj.weaver.ResolvedMember[] NO_MEMBERS;

  private static org.aspectj.weaver.ResolvedType[] NO_TYPES;

  private boolean issuedCantFindTypeError;

  private boolean issuedJoinPointWarning;

  private boolean issuedMissingInterfaceWarning;

  public org.aspectj.weaver.MissingResolvedTypeWithKnownSignature(java.lang.String, org.aspectj.weaver.World);
    Code:
       0: aload_0
       1: aload_1
       2: aload_2
       3: invokespecial #1                  // Method org/aspectj/weaver/ResolvedType."<init>":(Ljava/lang/String;Lorg/aspectj/weaver/World;)V
       6: aload_0
       7: iconst_0
       8: putfield      #2                  // Field issuedCantFindTypeError:Z
      11: aload_0
      12: iconst_0
      13: putfield      #3                  // Field issuedJoinPointWarning:Z
      16: aload_0
      17: iconst_0
      18: putfield      #4                  // Field issuedMissingInterfaceWarning:Z
      21: return

  public boolean isMissing();
    Code:
       0: iconst_1
       1: ireturn

  public org.aspectj.weaver.MissingResolvedTypeWithKnownSignature(java.lang.String, java.lang.String, org.aspectj.weaver.World);
    Code:
       0: aload_0
       1: aload_1
       2: aload_2
       3: aload_3
       4: invokespecial #5                  // Method org/aspectj/weaver/ResolvedType."<init>":(Ljava/lang/String;Ljava/lang/String;Lorg/aspectj/weaver/World;)V
       7: aload_0
       8: iconst_0
       9: putfield      #2                  // Field issuedCantFindTypeError:Z
      12: aload_0
      13: iconst_0
      14: putfield      #3                  // Field issuedJoinPointWarning:Z
      17: aload_0
      18: iconst_0
      19: putfield      #4                  // Field issuedMissingInterfaceWarning:Z
      22: return

  public org.aspectj.weaver.ResolvedMember[] getDeclaredFields();
    Code:
       0: aload_0
       1: ldc           #7                  // String cantFindTypeFields
       3: invokespecial #8                  // Method raiseCantFindType:(Ljava/lang/String;)V
       6: getstatic     #9                  // Field NO_MEMBERS:[Lorg/aspectj/weaver/ResolvedMember;
       9: areturn

  public org.aspectj.weaver.ResolvedMember[] getDeclaredMethods();
    Code:
       0: aload_0
       1: ldc           #10                 // String cantFindTypeMethods
       3: invokespecial #8                  // Method raiseCantFindType:(Ljava/lang/String;)V
       6: getstatic     #9                  // Field NO_MEMBERS:[Lorg/aspectj/weaver/ResolvedMember;
       9: areturn

  public org.aspectj.weaver.AnnotationAJ[] getAnnotations();
    Code:
       0: aload_0
       1: ldc           #11                 // String cantFindTypeAnnotation
       3: invokespecial #8                  // Method raiseCantFindType:(Ljava/lang/String;)V
       6: getstatic     #12                 // Field org/aspectj/weaver/AnnotationAJ.EMPTY_ARRAY:[Lorg/aspectj/weaver/AnnotationAJ;
       9: areturn

  public org.aspectj.weaver.ResolvedType[] getDeclaredInterfaces();
    Code:
       0: aload_0
       1: ldc           #13                 // String cantFindTypeInterfaces
       3: invokespecial #8                  // Method raiseCantFindType:(Ljava/lang/String;)V
       6: getstatic     #14                 // Field NO_TYPES:[Lorg/aspectj/weaver/ResolvedType;
       9: areturn

  public org.aspectj.weaver.ResolvedMember[] getDeclaredPointcuts();
    Code:
       0: aload_0
       1: ldc           #15                 // String cantFindTypePointcuts
       3: invokespecial #8                  // Method raiseCantFindType:(Ljava/lang/String;)V
       6: getstatic     #9                  // Field NO_MEMBERS:[Lorg/aspectj/weaver/ResolvedMember;
       9: areturn

  public org.aspectj.weaver.ResolvedType getSuperclass();
    Code:
       0: aload_0
       1: ldc           #16                 // String cantFindTypeSuperclass
       3: invokespecial #8                  // Method raiseCantFindType:(Ljava/lang/String;)V
       6: getstatic     #17                 // Field org/aspectj/weaver/ResolvedType.MISSING:Lorg/aspectj/weaver/ResolvedType$Missing;
       9: areturn

  public int getModifiers();
    Code:
       0: aload_0
       1: ldc           #18                 // String cantFindTypeModifiers
       3: invokespecial #8                  // Method raiseCantFindType:(Ljava/lang/String;)V
       6: iconst_0
       7: ireturn

  public org.aspectj.weaver.ISourceContext getSourceContext();
    Code:
       0: new           #19                 // class org/aspectj/weaver/MissingResolvedTypeWithKnownSignature$1
       3: dup
       4: aload_0
       5: invokespecial #20                 // Method org/aspectj/weaver/MissingResolvedTypeWithKnownSignature$1."<init>":(Lorg/aspectj/weaver/MissingResolvedTypeWithKnownSignature;)V
       8: areturn

  public boolean isAssignableFrom(org.aspectj.weaver.ResolvedType);
    Code:
       0: aload_0
       1: ldc           #21                 // String cantFindTypeAssignable
       3: aload_1
       4: invokevirtual #22                 // Method org/aspectj/weaver/ResolvedType.getName:()Ljava/lang/String;
       7: invokespecial #23                 // Method raiseCantFindType:(Ljava/lang/String;Ljava/lang/String;)V
      10: iconst_0
      11: ireturn

  public boolean isAssignableFrom(org.aspectj.weaver.ResolvedType, boolean);
    Code:
       0: iload_2
       1: ifeq          6
       4: iconst_0
       5: ireturn
       6: aload_0
       7: aload_1
       8: invokevirtual #24                 // Method isAssignableFrom:(Lorg/aspectj/weaver/ResolvedType;)Z
      11: ireturn

  public boolean isCoerceableFrom(org.aspectj.weaver.ResolvedType);
    Code:
       0: aload_0
       1: ldc           #25                 // String cantFindTypeCoerceable
       3: aload_1
       4: invokevirtual #22                 // Method org/aspectj/weaver/ResolvedType.getName:()Ljava/lang/String;
       7: invokespecial #23                 // Method raiseCantFindType:(Ljava/lang/String;Ljava/lang/String;)V
      10: iconst_0
      11: ireturn

  public boolean hasAnnotation(org.aspectj.weaver.UnresolvedType);
    Code:
       0: aload_0
       1: ldc           #11                 // String cantFindTypeAnnotation
       3: invokespecial #8                  // Method raiseCantFindType:(Ljava/lang/String;)V
       6: iconst_0
       7: ireturn

  public java.util.List getInterTypeMungers();
    Code:
       0: getstatic     #26                 // Field java/util/Collections.EMPTY_LIST:Ljava/util/List;
       3: areturn

  public java.util.List getInterTypeMungersIncludingSupers();
    Code:
       0: getstatic     #26                 // Field java/util/Collections.EMPTY_LIST:Ljava/util/List;
       3: areturn

  public java.util.List getInterTypeParentMungers();
    Code:
       0: getstatic     #26                 // Field java/util/Collections.EMPTY_LIST:Ljava/util/List;
       3: areturn

  public java.util.List getInterTypeParentMungersIncludingSupers();
    Code:
       0: getstatic     #26                 // Field java/util/Collections.EMPTY_LIST:Ljava/util/List;
       3: areturn

  protected void collectInterTypeMungers(java.util.List);
    Code:
       0: return

  public void raiseWarningOnJoinPointSignature(java.lang.String);
    Code:
       0: aload_0
       1: getfield      #3                  // Field issuedJoinPointWarning:Z
       4: ifeq          8
       7: return
       8: ldc           #27                 // String cantFindTypeJoinPoint
      10: aload_0
      11: invokevirtual #28                 // Method getName:()Ljava/lang/String;
      14: aload_1
      15: invokestatic  #29                 // Method org/aspectj/weaver/WeaverMessages.format:(Ljava/lang/String;Ljava/lang/Object;Ljava/lang/Object;)Ljava/lang/String;
      18: astore_2
      19: new           #30                 // class java/lang/StringBuilder
      22: dup
      23: invokespecial #31                 // Method java/lang/StringBuilder."<init>":()V
      26: aload_2
      27: invokevirtual #32                 // Method java/lang/StringBuilder.append:(Ljava/lang/String;)Ljava/lang/StringBuilder;
      30: ldc           #33                 // String \n
      32: invokevirtual #32                 // Method java/lang/StringBuilder.append:(Ljava/lang/String;)Ljava/lang/StringBuilder;
      35: invokestatic  #34                 // Method org/aspectj/bridge/context/CompilationAndWeavingContext.getCurrentContext:()Ljava/lang/String;
      38: invokevirtual #32                 // Method java/lang/StringBuilder.append:(Ljava/lang/String;)Ljava/lang/StringBuilder;
      41: invokevirtual #35                 // Method java/lang/StringBuilder.toString:()Ljava/lang/String;
      44: astore_2
      45: aload_0
      46: getfield      #36                 // Field world:Lorg/aspectj/weaver/World;
      49: invokevirtual #37                 // Method org/aspectj/weaver/World.getLint:()Lorg/aspectj/weaver/Lint;
      52: getfield      #38                 // Field org/aspectj/weaver/Lint.cantFindTypeAffectingJoinPointMatch:Lorg/aspectj/weaver/Lint$Kind;
      55: aload_2
      56: aconst_null
      57: invokevirtual #39                 // Method org/aspectj/weaver/Lint$Kind.signal:(Ljava/lang/String;Lorg/aspectj/bridge/ISourceLocation;)V
      60: aload_0
      61: iconst_1
      62: putfield      #3                  // Field issuedJoinPointWarning:Z
      65: return

  public void raiseWarningOnMissingInterfaceWhilstFindingMethods();
    Code:
       0: aload_0
       1: getfield      #4                  // Field issuedMissingInterfaceWarning:Z
       4: ifeq          8
       7: return
       8: ldc           #40                 // String cantFindTypeInterfaceMethods
      10: aload_0
      11: invokevirtual #28                 // Method getName:()Ljava/lang/String;
      14: aload_0
      15: getfield      #41                 // Field signature:Ljava/lang/String;
      18: invokestatic  #29                 // Method org/aspectj/weaver/WeaverMessages.format:(Ljava/lang/String;Ljava/lang/Object;Ljava/lang/Object;)Ljava/lang/String;
      21: astore_1
      22: new           #30                 // class java/lang/StringBuilder
      25: dup
      26: invokespecial #31                 // Method java/lang/StringBuilder."<init>":()V
      29: aload_1
      30: invokevirtual #32                 // Method java/lang/StringBuilder.append:(Ljava/lang/String;)Ljava/lang/StringBuilder;
      33: ldc           #33                 // String \n
      35: invokevirtual #32                 // Method java/lang/StringBuilder.append:(Ljava/lang/String;)Ljava/lang/StringBuilder;
      38: invokestatic  #34                 // Method org/aspectj/bridge/context/CompilationAndWeavingContext.getCurrentContext:()Ljava/lang/String;
      41: invokevirtual #32                 // Method java/lang/StringBuilder.append:(Ljava/lang/String;)Ljava/lang/StringBuilder;
      44: invokevirtual #35                 // Method java/lang/StringBuilder.toString:()Ljava/lang/String;
      47: astore_1
      48: aload_0
      49: getfield      #36                 // Field world:Lorg/aspectj/weaver/World;
      52: invokevirtual #37                 // Method org/aspectj/weaver/World.getLint:()Lorg/aspectj/weaver/Lint;
      55: getfield      #38                 // Field org/aspectj/weaver/Lint.cantFindTypeAffectingJoinPointMatch:Lorg/aspectj/weaver/Lint$Kind;
      58: aload_1
      59: aconst_null
      60: invokevirtual #39                 // Method org/aspectj/weaver/Lint$Kind.signal:(Ljava/lang/String;Lorg/aspectj/bridge/ISourceLocation;)V
      63: aload_0
      64: iconst_1
      65: putfield      #4                  // Field issuedMissingInterfaceWarning:Z
      68: return

  private void raiseCantFindType(java.lang.String);
    Code:
       0: aload_0
       1: getfield      #36                 // Field world:Lorg/aspectj/weaver/World;
       4: invokevirtual #37                 // Method org/aspectj/weaver/World.getLint:()Lorg/aspectj/weaver/Lint;
       7: getfield      #42                 // Field org/aspectj/weaver/Lint.cantFindType:Lorg/aspectj/weaver/Lint$Kind;
      10: invokevirtual #43                 // Method org/aspectj/weaver/Lint$Kind.isEnabled:()Z
      13: ifne          17
      16: return
      17: aload_0
      18: getfield      #2                  // Field issuedCantFindTypeError:Z
      21: ifeq          25
      24: return
      25: aload_1
      26: aload_0
      27: invokevirtual #28                 // Method getName:()Ljava/lang/String;
      30: invokestatic  #44                 // Method org/aspectj/weaver/WeaverMessages.format:(Ljava/lang/String;Ljava/lang/Object;)Ljava/lang/String;
      33: astore_2
      34: new           #30                 // class java/lang/StringBuilder
      37: dup
      38: invokespecial #31                 // Method java/lang/StringBuilder."<init>":()V
      41: aload_2
      42: invokevirtual #32                 // Method java/lang/StringBuilder.append:(Ljava/lang/String;)Ljava/lang/StringBuilder;
      45: ldc           #33                 // String \n
      47: invokevirtual #32                 // Method java/lang/StringBuilder.append:(Ljava/lang/String;)Ljava/lang/StringBuilder;
      50: invokestatic  #34                 // Method org/aspectj/bridge/context/CompilationAndWeavingContext.getCurrentContext:()Ljava/lang/String;
      53: invokevirtual #32                 // Method java/lang/StringBuilder.append:(Ljava/lang/String;)Ljava/lang/StringBuilder;
      56: invokevirtual #35                 // Method java/lang/StringBuilder.toString:()Ljava/lang/String;
      59: astore_2
      60: aload_0
      61: getfield      #36                 // Field world:Lorg/aspectj/weaver/World;
      64: invokevirtual #37                 // Method org/aspectj/weaver/World.getLint:()Lorg/aspectj/weaver/Lint;
      67: getfield      #42                 // Field org/aspectj/weaver/Lint.cantFindType:Lorg/aspectj/weaver/Lint$Kind;
      70: aload_2
      71: aconst_null
      72: invokevirtual #39                 // Method org/aspectj/weaver/Lint$Kind.signal:(Ljava/lang/String;Lorg/aspectj/bridge/ISourceLocation;)V
      75: aload_0
      76: iconst_1
      77: putfield      #2                  // Field issuedCantFindTypeError:Z
      80: return

  private void raiseCantFindType(java.lang.String, java.lang.String);
    Code:
       0: aload_0
       1: getfield      #2                  // Field issuedCantFindTypeError:Z
       4: ifeq          8
       7: return
       8: aload_1
       9: aload_0
      10: invokevirtual #28                 // Method getName:()Ljava/lang/String;
      13: aload_2
      14: invokestatic  #29                 // Method org/aspectj/weaver/WeaverMessages.format:(Ljava/lang/String;Ljava/lang/Object;Ljava/lang/Object;)Ljava/lang/String;
      17: astore_3
      18: new           #30                 // class java/lang/StringBuilder
      21: dup
      22: invokespecial #31                 // Method java/lang/StringBuilder."<init>":()V
      25: aload_3
      26: invokevirtual #32                 // Method java/lang/StringBuilder.append:(Ljava/lang/String;)Ljava/lang/StringBuilder;
      29: ldc           #33                 // String \n
      31: invokevirtual #32                 // Method java/lang/StringBuilder.append:(Ljava/lang/String;)Ljava/lang/StringBuilder;
      34: invokestatic  #34                 // Method org/aspectj/bridge/context/CompilationAndWeavingContext.getCurrentContext:()Ljava/lang/String;
      37: invokevirtual #32                 // Method java/lang/StringBuilder.append:(Ljava/lang/String;)Ljava/lang/StringBuilder;
      40: invokevirtual #35                 // Method java/lang/StringBuilder.toString:()Ljava/lang/String;
      43: astore_3
      44: aload_0
      45: getfield      #36                 // Field world:Lorg/aspectj/weaver/World;
      48: invokevirtual #37                 // Method org/aspectj/weaver/World.getLint:()Lorg/aspectj/weaver/Lint;
      51: getfield      #42                 // Field org/aspectj/weaver/Lint.cantFindType:Lorg/aspectj/weaver/Lint$Kind;
      54: aload_3
      55: aconst_null
      56: invokevirtual #39                 // Method org/aspectj/weaver/Lint$Kind.signal:(Ljava/lang/String;Lorg/aspectj/bridge/ISourceLocation;)V
      59: aload_0
      60: iconst_1
      61: putfield      #2                  // Field issuedCantFindTypeError:Z
      64: return

  static {};
    Code:
       0: iconst_0
       1: anewarray     #45                 // class org/aspectj/weaver/ResolvedMember
       4: putstatic     #9                  // Field NO_MEMBERS:[Lorg/aspectj/weaver/ResolvedMember;
       7: iconst_0
       8: anewarray     #46                 // class org/aspectj/weaver/ResolvedType
      11: putstatic     #14                 // Field NO_TYPES:[Lorg/aspectj/weaver/ResolvedType;
      14: return
}
