Compiled from "PersistenceSupport.java"
public class org.aspectj.weaver.PersistenceSupport {
  public org.aspectj.weaver.PersistenceSupport();
    Code:
       0: aload_0
       1: invokespecial #1                  // Method java/lang/Object."<init>":()V
       4: return

  public static void write(org.aspectj.weaver.CompressingDataOutputStream, org.aspectj.weaver.ISourceContext) throws java.io.IOException;
    Code:
       0: new           #2                  // class java/lang/IllegalStateException
       3: dup
       4: invokespecial #3                  // Method java/lang/IllegalStateException."<init>":()V
       7: athrow

  public static void write(org.aspectj.weaver.CompressingDataOutputStream, java.io.Serializable) throws java.io.IOException;
    Code:
       0: new           #4                  // class java/io/ObjectOutputStream
       3: dup
       4: aload_0
       5: invokespecial #5                  // Method java/io/ObjectOutputStream."<init>":(Ljava/io/OutputStream;)V
       8: astore_2
       9: aload_2
      10: aload_1
      11: invokevirtual #6                  // Method java/io/ObjectOutputStream.writeObject:(Ljava/lang/Object;)V
      14: aload_2
      15: invokevirtual #7                  // Method java/io/ObjectOutputStream.flush:()V
      18: return
}
