Compiled from "WeaverMessages.java"
public class org.aspectj.weaver.WeaverMessages {
  private static java.util.ResourceBundle bundle;

  public static final java.lang.String ARGS_IN_DECLARE;

  public static final java.lang.String CFLOW_IN_DECLARE;

  public static final java.lang.String IF_IN_DECLARE;

  public static final java.lang.String THIS_OR_TARGET_IN_DECLARE;

  public static final java.lang.String ABSTRACT_POINTCUT;

  public static final java.lang.String POINCUT_NOT_CONCRETE;

  public static final java.lang.String POINTCUT_NOT_VISIBLE;

  public static final java.lang.String CONFLICTING_INHERITED_POINTCUTS;

  public static final java.lang.String CIRCULAR_POINTCUT;

  public static final java.lang.String CANT_FIND_POINTCUT;

  public static final java.lang.String EXACT_TYPE_PATTERN_REQD;

  public static final java.lang.String CANT_BIND_TYPE;

  public static final java.lang.String WILDCARD_NOT_ALLOWED;

  public static final java.lang.String FIELDS_CANT_HAVE_VOID_TYPE;

  public static final java.lang.String NO_NEWARRAY_JOINPOINTS_BY_DEFAULT;

  public static final java.lang.String UNSUPPORTED_POINTCUT_PRIMITIVE;

  public static final java.lang.String MISSING_TYPE_PREVENTS_MATCH;

  public static final java.lang.String DECP_OBJECT;

  public static final java.lang.String CANT_EXTEND_SELF;

  public static final java.lang.String INTERFACE_CANT_EXTEND_CLASS;

  public static final java.lang.String DECP_HIERARCHY_ERROR;

  public static final java.lang.String MULTIPLE_MATCHES_IN_PRECEDENCE;

  public static final java.lang.String TWO_STARS_IN_PRECEDENCE;

  public static final java.lang.String CLASSES_IN_PRECEDENCE;

  public static final java.lang.String TWO_PATTERN_MATCHES_IN_PRECEDENCE;

  public static final java.lang.String NOT_THROWABLE;

  public static final java.lang.String ITD_CONS_ON_ASPECT;

  public static final java.lang.String ITD_RETURN_TYPE_MISMATCH;

  public static final java.lang.String ITD_PARAM_TYPE_MISMATCH;

  public static final java.lang.String ITD_VISIBILITY_REDUCTION;

  public static final java.lang.String ITD_DOESNT_THROW;

  public static final java.lang.String ITD_OVERRIDDEN_STATIC;

  public static final java.lang.String ITD_OVERIDDING_STATIC;

  public static final java.lang.String ITD_CONFLICT;

  public static final java.lang.String ITD_MEMBER_CONFLICT;

  public static final java.lang.String ITD_NON_EXPOSED_IMPLEMENTOR;

  public static final java.lang.String ITD_ABSTRACT_MUST_BE_PUBLIC_ON_INTERFACE;

  public static final java.lang.String CANT_OVERRIDE_FINAL_MEMBER;

  public static final java.lang.String NON_VOID_RETURN;

  public static final java.lang.String INCOMPATIBLE_RETURN_TYPE;

  public static final java.lang.String CANT_THROW_CHECKED;

  public static final java.lang.String CIRCULAR_DEPENDENCY;

  public static final java.lang.String MISSING_PER_CLAUSE;

  public static final java.lang.String WRONG_PER_CLAUSE;

  public static final java.lang.String ALREADY_WOVEN;

  public static final java.lang.String REWEAVABLE_MODE;

  public static final java.lang.String PROCESSING_REWEAVABLE;

  public static final java.lang.String MISSING_REWEAVABLE_TYPE;

  public static final java.lang.String VERIFIED_REWEAVABLE_TYPE;

  public static final java.lang.String ASPECT_NEEDED;

  public static final java.lang.String REWEAVABLE_ASPECT_NOT_REGISTERED;

  public static final java.lang.String CANT_FIND_TYPE;

  public static final java.lang.String CANT_FIND_CORE_TYPE;

  public static final java.lang.String CANT_FIND_TYPE_WITHINPCD;

  public static final java.lang.String CANT_FIND_TYPE_DURING_AROUND_WEAVE;

  public static final java.lang.String CANT_FIND_TYPE_DURING_AROUND_WEAVE_PREINIT;

  public static final java.lang.String CANT_FIND_TYPE_EXCEPTION_TYPE;

  public static final java.lang.String CANT_FIND_TYPE_ARG_TYPE;

  public static final java.lang.String CANT_FIND_PARENT_TYPE;

  public static final java.lang.String CANT_FIND_PARENT_TYPE_NO_SUB;

  public static final java.lang.String CANT_FIND_TYPE_FIELDS;

  public static final java.lang.String CANT_FIND_TYPE_SUPERCLASS;

  public static final java.lang.String CANT_FIND_TYPE_INTERFACES;

  public static final java.lang.String CANT_FIND_TYPE_METHODS;

  public static final java.lang.String CANT_FIND_TYPE_POINTCUTS;

  public static final java.lang.String CANT_FIND_TYPE_MODIFIERS;

  public static final java.lang.String CANT_FIND_TYPE_ANNOTATION;

  public static final java.lang.String CANT_FIND_TYPE_ASSIGNABLE;

  public static final java.lang.String CANT_FIND_TYPE_COERCEABLE;

  public static final java.lang.String CANT_FIND_TYPE_JOINPOINT;

  public static final java.lang.String CANT_FIND_TYPE_INTERFACE_METHODS;

  public static final java.lang.String DECP_BINARY_LIMITATION;

  public static final java.lang.String OVERWRITE_JSR45;

  public static final java.lang.String IF_IN_PERCLAUSE;

  public static final java.lang.String IF_LEXICALLY_IN_CFLOW;

  public static final java.lang.String ONLY_BEFORE_ON_HANDLER;

  public static final java.lang.String NO_AROUND_ON_SYNCHRONIZATION;

  public static final java.lang.String AROUND_ON_PREINIT;

  public static final java.lang.String AROUND_ON_INIT;

  public static final java.lang.String AROUND_ON_INTERFACE_STATICINIT;

  public static final java.lang.String PROBLEM_GENERATING_METHOD;

  public static final java.lang.String CLASS_TOO_BIG;

  public static final java.lang.String ZIPFILE_ENTRY_MISSING;

  public static final java.lang.String ZIPFILE_ENTRY_INVALID;

  public static final java.lang.String DIRECTORY_ENTRY_MISSING;

  public static final java.lang.String OUTJAR_IN_INPUT_PATH;

  public static final java.lang.String XLINT_LOAD_ERROR;

  public static final java.lang.String XLINTDEFAULT_LOAD_ERROR;

  public static final java.lang.String XLINTDEFAULT_LOAD_PROBLEM;

  public static final java.lang.String XLINT_KEY_ERROR;

  public static final java.lang.String XLINT_VALUE_ERROR;

  public static final java.lang.String UNBOUND_FORMAL;

  public static final java.lang.String AMBIGUOUS_BINDING;

  public static final java.lang.String AMBIGUOUS_BINDING_IN_OR;

  public static final java.lang.String NEGATION_DOESNT_ALLOW_BINDING;

  public static final java.lang.String ITDC_ON_ENUM_NOT_ALLOWED;

  public static final java.lang.String ITDM_ON_ENUM_NOT_ALLOWED;

  public static final java.lang.String ITDF_ON_ENUM_NOT_ALLOWED;

  public static final java.lang.String CANT_DECP_ON_ENUM_TO_IMPL_INTERFACE;

  public static final java.lang.String CANT_DECP_ON_ENUM_TO_EXTEND_CLASS;

  public static final java.lang.String CANT_DECP_TO_MAKE_ENUM_SUPERTYPE;

  public static final java.lang.String ITDC_ON_ANNOTATION_NOT_ALLOWED;

  public static final java.lang.String ITDM_ON_ANNOTATION_NOT_ALLOWED;

  public static final java.lang.String ITDF_ON_ANNOTATION_NOT_ALLOWED;

  public static final java.lang.String CANT_DECP_ON_ANNOTATION_TO_IMPL_INTERFACE;

  public static final java.lang.String CANT_DECP_ON_ANNOTATION_TO_EXTEND_CLASS;

  public static final java.lang.String CANT_DECP_TO_MAKE_ANNOTATION_SUPERTYPE;

  public static final java.lang.String REFERENCE_TO_NON_ANNOTATION_TYPE;

  public static final java.lang.String BINDING_NON_RUNTIME_RETENTION_ANNOTATION;

  public static final java.lang.String UNSUPPORTED_ANNOTATION_VALUE_TYPE;

  public static final java.lang.String INCORRECT_TARGET_FOR_DECLARE_ANNOTATION;

  public static final java.lang.String NO_MATCH_BECAUSE_SOURCE_RETENTION;

  public static final java.lang.String INVALID_ANNOTATION_VALUE;

  public static final java.lang.String UNKNOWN_ANNOTATION_VALUE;

  public static final java.lang.String ATANNOTATION_ONLY_SUPPORTED_AT_JAVA5_LEVEL;

  public static final java.lang.String ATWITHIN_ONLY_SUPPORTED_AT_JAVA5_LEVEL;

  public static final java.lang.String ATWITHINCODE_ONLY_SUPPORTED_AT_JAVA5_LEVEL;

  public static final java.lang.String ATTHIS_ONLY_SUPPORTED_AT_JAVA5_LEVEL;

  public static final java.lang.String ATTARGET_ONLY_SUPPORTED_AT_JAVA5_LEVEL;

  public static final java.lang.String ATARGS_ONLY_SUPPORTED_AT_JAVA5_LEVEL;

  public static final java.lang.String DECLARE_ATTYPE_ONLY_SUPPORTED_AT_JAVA5_LEVEL;

  public static final java.lang.String DECLARE_ATMETHOD_ONLY_SUPPORTED_AT_JAVA5_LEVEL;

  public static final java.lang.String DECLARE_ATFIELD_ONLY_SUPPORTED_AT_JAVA5_LEVEL;

  public static final java.lang.String DECLARE_ATCONS_ONLY_SUPPORTED_AT_JAVA5_LEVEL;

  public static final java.lang.String ANNOTATIONS_NEED_JAVA5;

  public static final java.lang.String CANT_DECP_MULTIPLE_PARAMETERIZATIONS;

  public static final java.lang.String HANDLER_PCD_DOESNT_SUPPORT_PARAMETERS;

  public static final java.lang.String INCORRECT_NUMBER_OF_TYPE_ARGUMENTS;

  public static final java.lang.String VIOLATES_TYPE_VARIABLE_BOUNDS;

  public static final java.lang.String NO_STATIC_INIT_JPS_FOR_PARAMETERIZED_TYPES;

  public static final java.lang.String NOT_A_GENERIC_TYPE;

  public static final java.lang.String WITHIN_PCD_DOESNT_SUPPORT_PARAMETERS;

  public static final java.lang.String THIS_AND_TARGET_DONT_SUPPORT_PARAMETERS;

  public static final java.lang.String GET_AND_SET_DONT_SUPPORT_DEC_TYPE_PARAMETERS;

  public static final java.lang.String NO_INIT_JPS_FOR_PARAMETERIZED_TYPES;

  public static final java.lang.String NO_GENERIC_THROWABLES;

  public static final java.lang.String WITHINCODE_DOESNT_SUPPORT_PARAMETERIZED_DECLARING_TYPES;

  public static final java.lang.String EXECUTION_DOESNT_SUPPORT_PARAMETERIZED_DECLARING_TYPES;

  public static final java.lang.String CALL_DOESNT_SUPPORT_PARAMETERIZED_DECLARING_TYPES;

  public static final java.lang.String CANT_REFERENCE_POINTCUT_IN_RAW_TYPE;

  public static final java.lang.String HAS_MEMBER_NOT_ENABLED;

  public static final java.lang.String MUST_KEEP_OVERWEAVING_ONCE_START;

  public static final java.lang.String RETURNING_FORMAL_NOT_DECLARED_IN_ADVICE;

  public static final java.lang.String THROWN_FORMAL_NOT_DECLARED_IN_ADVICE;

  public org.aspectj.weaver.WeaverMessages();
    Code:
       0: aload_0
       1: invokespecial #1                  // Method java/lang/Object."<init>":()V
       4: return

  public static java.lang.String format(java.lang.String);
    Code:
       0: getstatic     #2                  // Field bundle:Ljava/util/ResourceBundle;
       3: aload_0
       4: invokevirtual #3                  // Method java/util/ResourceBundle.getString:(Ljava/lang/String;)Ljava/lang/String;
       7: areturn

  public static java.lang.String format(java.lang.String, java.lang.Object);
    Code:
       0: getstatic     #2                  // Field bundle:Ljava/util/ResourceBundle;
       3: aload_0
       4: invokevirtual #3                  // Method java/util/ResourceBundle.getString:(Ljava/lang/String;)Ljava/lang/String;
       7: iconst_1
       8: anewarray     #4                  // class java/lang/Object
      11: dup
      12: iconst_0
      13: aload_1
      14: aastore
      15: invokestatic  #5                  // Method java/text/MessageFormat.format:(Ljava/lang/String;[Ljava/lang/Object;)Ljava/lang/String;
      18: areturn

  public static java.lang.String format(java.lang.String, java.lang.Object, java.lang.Object);
    Code:
       0: getstatic     #2                  // Field bundle:Ljava/util/ResourceBundle;
       3: aload_0
       4: invokevirtual #3                  // Method java/util/ResourceBundle.getString:(Ljava/lang/String;)Ljava/lang/String;
       7: iconst_2
       8: anewarray     #4                  // class java/lang/Object
      11: dup
      12: iconst_0
      13: aload_1
      14: aastore
      15: dup
      16: iconst_1
      17: aload_2
      18: aastore
      19: invokestatic  #5                  // Method java/text/MessageFormat.format:(Ljava/lang/String;[Ljava/lang/Object;)Ljava/lang/String;
      22: areturn

  public static java.lang.String format(java.lang.String, java.lang.Object, java.lang.Object, java.lang.Object);
    Code:
       0: getstatic     #2                  // Field bundle:Ljava/util/ResourceBundle;
       3: aload_0
       4: invokevirtual #3                  // Method java/util/ResourceBundle.getString:(Ljava/lang/String;)Ljava/lang/String;
       7: iconst_3
       8: anewarray     #4                  // class java/lang/Object
      11: dup
      12: iconst_0
      13: aload_1
      14: aastore
      15: dup
      16: iconst_1
      17: aload_2
      18: aastore
      19: dup
      20: iconst_2
      21: aload_3
      22: aastore
      23: invokestatic  #5                  // Method java/text/MessageFormat.format:(Ljava/lang/String;[Ljava/lang/Object;)Ljava/lang/String;
      26: areturn

  public static java.lang.String format(java.lang.String, java.lang.Object, java.lang.Object, java.lang.Object, java.lang.Object);
    Code:
       0: getstatic     #2                  // Field bundle:Ljava/util/ResourceBundle;
       3: aload_0
       4: invokevirtual #3                  // Method java/util/ResourceBundle.getString:(Ljava/lang/String;)Ljava/lang/String;
       7: iconst_4
       8: anewarray     #4                  // class java/lang/Object
      11: dup
      12: iconst_0
      13: aload_1
      14: aastore
      15: dup
      16: iconst_1
      17: aload_2
      18: aastore
      19: dup
      20: iconst_2
      21: aload_3
      22: aastore
      23: dup
      24: iconst_3
      25: aload         4
      27: aastore
      28: invokestatic  #5                  // Method java/text/MessageFormat.format:(Ljava/lang/String;[Ljava/lang/Object;)Ljava/lang/String;
      31: areturn

  static {};
    Code:
       0: ldc           #6                  // String org.aspectj.weaver.weaver-messages
       2: invokestatic  #7                  // Method java/util/ResourceBundle.getBundle:(Ljava/lang/String;)Ljava/util/ResourceBundle;
       5: putstatic     #2                  // Field bundle:Ljava/util/ResourceBundle;
       8: return
}
