Compiled from "AbstractMapBasedMultimap.java"
class org.apache.curator.shaded.com.google.common.collect.AbstractMapBasedMultimap$2 extends org.apache.curator.shaded.com.google.common.collect.AbstractMapBasedMultimap<K, V>.Itr<java.util.Map$Entry<K, V>> {
  final org.apache.curator.shaded.com.google.common.collect.AbstractMapBasedMultimap this$0;

  org.apache.curator.shaded.com.google.common.collect.AbstractMapBasedMultimap$2(org.apache.curator.shaded.com.google.common.collect.AbstractMapBasedMultimap);
    Code:
       0: aload_0
       1: aload_1
       2: putfield      #23                 // Field this$0:Lorg/apache/curator/shaded/com/google/common/collect/AbstractMapBasedMultimap;
       5: aload_0
       6: aload_1
       7: invokespecial #25                 // Method org/apache/curator/shaded/com/google/common/collect/AbstractMapBasedMultimap$Itr."<init>":(Lorg/apache/curator/shaded/com/google/common/collect/AbstractMapBasedMultimap;)V
      10: return

  java.util.Map$Entry<K, V> output(K, V);
    Code:
       0: aload_1
       1: aload_2
       2: invokestatic  #35                 // Method org/apache/curator/shaded/com/google/common/collect/Maps.immutableEntry:(Ljava/lang/Object;Ljava/lang/Object;)Ljava/util/Map$Entry;
       5: areturn

  java.lang.Object output(java.lang.Object, java.lang.Object);
    Code:
       0: aload_0
       1: aload_1
       2: aload_2
       3: invokevirtual #43                 // Method output:(Ljava/lang/Object;Ljava/lang/Object;)Ljava/util/Map$Entry;
       6: areturn
}
