Compiled from "Interners.java"
public final class org.apache.curator.shaded.com.google.common.collect.Interners {
  private org.apache.curator.shaded.com.google.common.collect.Interners();
    Code:
       0: aload_0
       1: invokespecial #18                 // Method java/lang/Object."<init>":()V
       4: return

  public static <E> org.apache.curator.shaded.com.google.common.collect.Interner<E> newStrongInterner();
    Code:
       0: new           #24                 // class org/apache/curator/shaded/com/google/common/collect/MapMaker
       3: dup
       4: invokespecial #25                 // Method org/apache/curator/shaded/com/google/common/collect/MapMaker."<init>":()V
       7: invokevirtual #29                 // Method org/apache/curator/shaded/com/google/common/collect/MapMaker.makeMap:()Ljava/util/concurrent/ConcurrentMap;
      10: astore_0
      11: new           #14                 // class org/apache/curator/shaded/com/google/common/collect/Interners$1
      14: dup
      15: aload_0
      16: invokespecial #32                 // Method org/apache/curator/shaded/com/google/common/collect/Interners$1."<init>":(Ljava/util/concurrent/ConcurrentMap;)V
      19: areturn

  public static <E> org.apache.curator.shaded.com.google.common.collect.Interner<E> newWeakInterner();
    Code:
       0: new           #11                 // class org/apache/curator/shaded/com/google/common/collect/Interners$WeakInterner
       3: dup
       4: aconst_null
       5: invokespecial #42                 // Method org/apache/curator/shaded/com/google/common/collect/Interners$WeakInterner."<init>":(Lorg/apache/curator/shaded/com/google/common/collect/Interners$1;)V
       8: areturn

  public static <E> com.google.common.base.Function<E, E> asFunction(org.apache.curator.shaded.com.google.common.collect.Interner<E>);
    Code:
       0: new           #8                  // class org/apache/curator/shaded/com/google/common/collect/Interners$InternerFunction
       3: dup
       4: aload_0
       5: invokestatic  #50                 // Method org/apache/curator/shaded/com/google/common/base/Preconditions.checkNotNull:(Ljava/lang/Object;)Ljava/lang/Object;
       8: checkcast     #52                 // class org/apache/curator/shaded/com/google/common/collect/Interner
      11: invokespecial #55                 // Method org/apache/curator/shaded/com/google/common/collect/Interners$InternerFunction."<init>":(Lorg/apache/curator/shaded/com/google/common/collect/Interner;)V
      14: areturn
}
