Compiled from "Iterators.java"
final class org.apache.curator.shaded.com.google.common.collect.Iterators$2 implements java.util.Iterator<java.lang.Object> {
  org.apache.curator.shaded.com.google.common.collect.Iterators$2();
    Code:
       0: aload_0
       1: invokespecial #14                 // Method java/lang/Object."<init>":()V
       4: return

  public boolean hasNext();
    Code:
       0: iconst_0
       1: ireturn

  public java.lang.Object next();
    Code:
       0: new           #22                 // class java/util/NoSuchElementException
       3: dup
       4: invokespecial #23                 // Method java/util/NoSuchElementException."<init>":()V
       7: athrow

  public void remove();
    Code:
       0: iconst_0
       1: invokestatic  #30                 // Method org/apache/curator/shaded/com/google/common/collect/CollectPreconditions.checkRemove:(Z)V
       4: return
}
