Compiled from "MultimapBuilder.java"
class org.apache.curator.shaded.com.google.common.collect.MultimapBuilder$MultimapBuilderWithKeys$1 extends org.apache.curator.shaded.com.google.common.collect.MultimapBuilder$ListMultimapBuilder<K0, java.lang.Object> {
  final int val$expectedValuesPerKey;

  final org.apache.curator.shaded.com.google.common.collect.MultimapBuilder$MultimapBuilderWithKeys this$0;

  org.apache.curator.shaded.com.google.common.collect.MultimapBuilder$MultimapBuilderWithKeys$1(org.apache.curator.shaded.com.google.common.collect.MultimapBuilder$MultimapBuilderWithKeys, int);
    Code:
       0: aload_0
       1: aload_1
       2: putfield      #26                 // Field this$0:Lorg/apache/curator/shaded/com/google/common/collect/MultimapBuilder$MultimapBuilderWithKeys;
       5: aload_0
       6: iload_2
       7: putfield      #28                 // Field val$expectedValuesPerKey:I
      10: aload_0
      11: invokespecial #31                 // Method org/apache/curator/shaded/com/google/common/collect/MultimapBuilder$ListMultimapBuilder."<init>":()V
      14: return

  public <K extends K0, V> org.apache.curator.shaded.com.google.common.collect.ListMultimap<K, V> build();
    Code:
       0: aload_0
       1: getfield      #26                 // Field this$0:Lorg/apache/curator/shaded/com/google/common/collect/MultimapBuilder$MultimapBuilderWithKeys;
       4: invokevirtual #40                 // Method org/apache/curator/shaded/com/google/common/collect/MultimapBuilder$MultimapBuilderWithKeys.createMap:()Ljava/util/Map;
       7: new           #17                 // class org/apache/curator/shaded/com/google/common/collect/MultimapBuilder$ArrayListSupplier
      10: dup
      11: aload_0
      12: getfield      #28                 // Field val$expectedValuesPerKey:I
      15: invokespecial #43                 // Method org/apache/curator/shaded/com/google/common/collect/MultimapBuilder$ArrayListSupplier."<init>":(I)V
      18: invokestatic  #49                 // Method org/apache/curator/shaded/com/google/common/collect/Multimaps.newListMultimap:(Ljava/util/Map;Lorg/apache/curator/shaded/com/google/common/base/Supplier;)Lorg/apache/curator/shaded/com/google/common/collect/ListMultimap;
      21: areturn

  public org.apache.curator.shaded.com.google.common.collect.Multimap build();
    Code:
       0: aload_0
       1: invokevirtual #52                 // Method build:()Lorg/apache/curator/shaded/com/google/common/collect/ListMultimap;
       4: areturn
}
