Compiled from "Multimaps.java"
class org.apache.curator.shaded.com.google.common.collect.Multimaps$Keys$KeysEntrySet extends org.apache.curator.shaded.com.google.common.collect.Multisets$EntrySet<K> {
  final org.apache.curator.shaded.com.google.common.collect.Multimaps$Keys this$0;

  org.apache.curator.shaded.com.google.common.collect.Multimaps$Keys$KeysEntrySet(org.apache.curator.shaded.com.google.common.collect.Multimaps$Keys);
    Code:
       0: aload_0
       1: aload_1
       2: putfield      #26                 // Field this$0:Lorg/apache/curator/shaded/com/google/common/collect/Multimaps$Keys;
       5: aload_0
       6: invokespecial #29                 // Method org/apache/curator/shaded/com/google/common/collect/Multisets$EntrySet."<init>":()V
       9: return

  org.apache.curator.shaded.com.google.common.collect.Multiset<K> multiset();
    Code:
       0: aload_0
       1: getfield      #26                 // Field this$0:Lorg/apache/curator/shaded/com/google/common/collect/Multimaps$Keys;
       4: areturn

  public java.util.Iterator<org.apache.curator.shaded.com.google.common.collect.Multiset$Entry<K>> iterator();
    Code:
       0: aload_0
       1: getfield      #26                 // Field this$0:Lorg/apache/curator/shaded/com/google/common/collect/Multimaps$Keys;
       4: invokevirtual #39                 // Method org/apache/curator/shaded/com/google/common/collect/Multimaps$Keys.entryIterator:()Ljava/util/Iterator;
       7: areturn

  public int size();
    Code:
       0: aload_0
       1: getfield      #26                 // Field this$0:Lorg/apache/curator/shaded/com/google/common/collect/Multimaps$Keys;
       4: invokevirtual #44                 // Method org/apache/curator/shaded/com/google/common/collect/Multimaps$Keys.distinctElements:()I
       7: ireturn

  public boolean isEmpty();
    Code:
       0: aload_0
       1: getfield      #26                 // Field this$0:Lorg/apache/curator/shaded/com/google/common/collect/Multimaps$Keys;
       4: getfield      #50                 // Field org/apache/curator/shaded/com/google/common/collect/Multimaps$Keys.multimap:Lorg/apache/curator/shaded/com/google/common/collect/Multimap;
       7: invokeinterface #54,  1           // InterfaceMethod org/apache/curator/shaded/com/google/common/collect/Multimap.isEmpty:()Z
      12: ireturn

  public boolean contains(java.lang.Object);
    Code:
       0: aload_1
       1: instanceof    #14                 // class org/apache/curator/shaded/com/google/common/collect/Multiset$Entry
       4: ifeq          64
       7: aload_1
       8: checkcast     #14                 // class org/apache/curator/shaded/com/google/common/collect/Multiset$Entry
      11: astore_2
      12: aload_0
      13: getfield      #26                 // Field this$0:Lorg/apache/curator/shaded/com/google/common/collect/Multimaps$Keys;
      16: getfield      #50                 // Field org/apache/curator/shaded/com/google/common/collect/Multimaps$Keys.multimap:Lorg/apache/curator/shaded/com/google/common/collect/Multimap;
      19: invokeinterface #61,  1           // InterfaceMethod org/apache/curator/shaded/com/google/common/collect/Multimap.asMap:()Ljava/util/Map;
      24: aload_2
      25: invokeinterface #65,  1           // InterfaceMethod org/apache/curator/shaded/com/google/common/collect/Multiset$Entry.getElement:()Ljava/lang/Object;
      30: invokeinterface #71,  2           // InterfaceMethod java/util/Map.get:(Ljava/lang/Object;)Ljava/lang/Object;
      35: checkcast     #73                 // class java/util/Collection
      38: astore_3
      39: aload_3
      40: ifnull        62
      43: aload_3
      44: invokeinterface #75,  1           // InterfaceMethod java/util/Collection.size:()I
      49: aload_2
      50: invokeinterface #78,  1           // InterfaceMethod org/apache/curator/shaded/com/google/common/collect/Multiset$Entry.getCount:()I
      55: if_icmpne     62
      58: iconst_1
      59: goto          63
      62: iconst_0
      63: ireturn
      64: iconst_0
      65: ireturn

  public boolean remove(java.lang.Object);
    Code:
       0: aload_1
       1: instanceof    #14                 // class org/apache/curator/shaded/com/google/common/collect/Multiset$Entry
       4: ifeq          66
       7: aload_1
       8: checkcast     #14                 // class org/apache/curator/shaded/com/google/common/collect/Multiset$Entry
      11: astore_2
      12: aload_0
      13: getfield      #26                 // Field this$0:Lorg/apache/curator/shaded/com/google/common/collect/Multimaps$Keys;
      16: getfield      #50                 // Field org/apache/curator/shaded/com/google/common/collect/Multimaps$Keys.multimap:Lorg/apache/curator/shaded/com/google/common/collect/Multimap;
      19: invokeinterface #61,  1           // InterfaceMethod org/apache/curator/shaded/com/google/common/collect/Multimap.asMap:()Ljava/util/Map;
      24: aload_2
      25: invokeinterface #65,  1           // InterfaceMethod org/apache/curator/shaded/com/google/common/collect/Multiset$Entry.getElement:()Ljava/lang/Object;
      30: invokeinterface #71,  2           // InterfaceMethod java/util/Map.get:(Ljava/lang/Object;)Ljava/lang/Object;
      35: checkcast     #73                 // class java/util/Collection
      38: astore_3
      39: aload_3
      40: ifnull        66
      43: aload_3
      44: invokeinterface #75,  1           // InterfaceMethod java/util/Collection.size:()I
      49: aload_2
      50: invokeinterface #78,  1           // InterfaceMethod org/apache/curator/shaded/com/google/common/collect/Multiset$Entry.getCount:()I
      55: if_icmpne     66
      58: aload_3
      59: invokeinterface #90,  1           // InterfaceMethod java/util/Collection.clear:()V
      64: iconst_1
      65: ireturn
      66: iconst_0
      67: ireturn
}
