Compiled from "Ordering.java"
class org.apache.curator.shaded.com.google.common.collect.Ordering$ArbitraryOrderingHolder {
  static final org.apache.curator.shaded.com.google.common.collect.Ordering<java.lang.Object> ARBITRARY_ORDERING;

  private org.apache.curator.shaded.com.google.common.collect.Ordering$ArbitraryOrderingHolder();
    Code:
       0: aload_0
       1: invokespecial #18                 // Method java/lang/Object."<init>":()V
       4: return

  static {};
    Code:
       0: new           #10                 // class org/apache/curator/shaded/com/google/common/collect/Ordering$ArbitraryOrdering
       3: dup
       4: invokespecial #22                 // Method org/apache/curator/shaded/com/google/common/collect/Ordering$ArbitraryOrdering."<init>":()V
       7: putstatic     #24                 // Field ARBITRARY_ORDERING:Lorg/apache/curator/shaded/com/google/common/collect/Ordering;
      10: return
}
