Compiled from "RegularImmutableSortedSet.java"
final class org.apache.curator.shaded.com.google.common.collect.RegularImmutableSortedSet<E> extends org.apache.curator.shaded.com.google.common.collect.ImmutableSortedSet<E> {
  private final transient org.apache.curator.shaded.com.google.common.collect.ImmutableList<E> elements;

  org.apache.curator.shaded.com.google.common.collect.RegularImmutableSortedSet(org.apache.curator.shaded.com.google.common.collect.ImmutableList<E>, java.util.Comparator<? super E>);
    Code:
       0: aload_0
       1: aload_2
       2: invokespecial #26                 // Method org/apache/curator/shaded/com/google/common/collect/ImmutableSortedSet."<init>":(Ljava/util/Comparator;)V
       5: aload_0
       6: aload_1
       7: putfield      #28                 // Field elements:Lorg/apache/curator/shaded/com/google/common/collect/ImmutableList;
      10: aload_1
      11: invokevirtual #34                 // Method org/apache/curator/shaded/com/google/common/collect/ImmutableList.isEmpty:()Z
      14: ifne          21
      17: iconst_1
      18: goto          22
      21: iconst_0
      22: invokestatic  #42                 // Method org/apache/curator/shaded/com/google/common/base/Preconditions.checkArgument:(Z)V
      25: return

  public org.apache.curator.shaded.com.google.common.collect.UnmodifiableIterator<E> iterator();
    Code:
       0: aload_0
       1: getfield      #28                 // Field elements:Lorg/apache/curator/shaded/com/google/common/collect/ImmutableList;
       4: invokevirtual #52                 // Method org/apache/curator/shaded/com/google/common/collect/ImmutableList.iterator:()Lorg/apache/curator/shaded/com/google/common/collect/UnmodifiableIterator;
       7: areturn

  public org.apache.curator.shaded.com.google.common.collect.UnmodifiableIterator<E> descendingIterator();
    Code:
       0: aload_0
       1: getfield      #28                 // Field elements:Lorg/apache/curator/shaded/com/google/common/collect/ImmutableList;
       4: invokevirtual #60                 // Method org/apache/curator/shaded/com/google/common/collect/ImmutableList.reverse:()Lorg/apache/curator/shaded/com/google/common/collect/ImmutableList;
       7: invokevirtual #52                 // Method org/apache/curator/shaded/com/google/common/collect/ImmutableList.iterator:()Lorg/apache/curator/shaded/com/google/common/collect/UnmodifiableIterator;
      10: areturn

  public boolean isEmpty();
    Code:
       0: iconst_0
       1: ireturn

  public int size();
    Code:
       0: aload_0
       1: getfield      #28                 // Field elements:Lorg/apache/curator/shaded/com/google/common/collect/ImmutableList;
       4: invokevirtual #64                 // Method org/apache/curator/shaded/com/google/common/collect/ImmutableList.size:()I
       7: ireturn

  public boolean contains(java.lang.Object);
    Code:
       0: aload_1
       1: ifnull        16
       4: aload_0
       5: aload_1
       6: invokespecial #72                 // Method unsafeBinarySearch:(Ljava/lang/Object;)I
       9: iflt          16
      12: iconst_1
      13: goto          17
      16: iconst_0
      17: ireturn
      18: astore_2
      19: iconst_0
      20: ireturn
    Exception table:
       from    to  target type
           0    17    18   Class java/lang/ClassCastException

  public boolean containsAll(java.util.Collection<?>);
    Code:
       0: aload_1
       1: instanceof    #82                 // class org/apache/curator/shaded/com/google/common/collect/Multiset
       4: ifeq          17
       7: aload_1
       8: checkcast     #82                 // class org/apache/curator/shaded/com/google/common/collect/Multiset
      11: invokeinterface #86,  1           // InterfaceMethod org/apache/curator/shaded/com/google/common/collect/Multiset.elementSet:()Ljava/util/Set;
      16: astore_1
      17: aload_0
      18: invokevirtual #89                 // Method comparator:()Ljava/util/Comparator;
      21: aload_1
      22: invokestatic  #95                 // Method org/apache/curator/shaded/com/google/common/collect/SortedIterables.hasSameComparator:(Ljava/util/Comparator;Ljava/lang/Iterable;)Z
      25: ifeq          38
      28: aload_1
      29: invokeinterface #98,  1           // InterfaceMethod java/util/Collection.size:()I
      34: iconst_1
      35: if_icmpgt     44
      38: aload_0
      39: aload_1
      40: invokespecial #100                // Method org/apache/curator/shaded/com/google/common/collect/ImmutableSortedSet.containsAll:(Ljava/util/Collection;)Z
      43: ireturn
      44: aload_0
      45: invokevirtual #101                // Method iterator:()Lorg/apache/curator/shaded/com/google/common/collect/UnmodifiableIterator;
      48: invokestatic  #107                // Method org/apache/curator/shaded/com/google/common/collect/Iterators.peekingIterator:(Ljava/util/Iterator;)Lorg/apache/curator/shaded/com/google/common/collect/PeekingIterator;
      51: astore_2
      52: aload_1
      53: invokeinterface #110,  1          // InterfaceMethod java/util/Collection.iterator:()Ljava/util/Iterator;
      58: astore_3
      59: aload_3
      60: invokeinterface #116,  1          // InterfaceMethod java/util/Iterator.next:()Ljava/lang/Object;
      65: astore        4
      67: aload_2
      68: invokeinterface #123,  1          // InterfaceMethod org/apache/curator/shaded/com/google/common/collect/PeekingIterator.hasNext:()Z
      73: ifeq          142
      76: aload_0
      77: aload_2
      78: invokeinterface #126,  1          // InterfaceMethod org/apache/curator/shaded/com/google/common/collect/PeekingIterator.peek:()Ljava/lang/Object;
      83: aload         4
      85: invokevirtual #130                // Method unsafeCompare:(Ljava/lang/Object;Ljava/lang/Object;)I
      88: istore        5
      90: iload         5
      92: ifge          105
      95: aload_2
      96: invokeinterface #131,  1          // InterfaceMethod org/apache/curator/shaded/com/google/common/collect/PeekingIterator.next:()Ljava/lang/Object;
     101: pop
     102: goto          139
     105: iload         5
     107: ifne          132
     110: aload_3
     111: invokeinterface #132,  1          // InterfaceMethod java/util/Iterator.hasNext:()Z
     116: ifne          121
     119: iconst_1
     120: ireturn
     121: aload_3
     122: invokeinterface #116,  1          // InterfaceMethod java/util/Iterator.next:()Ljava/lang/Object;
     127: astore        4
     129: goto          139
     132: iload         5
     134: ifle          139
     137: iconst_0
     138: ireturn
     139: goto          67
     142: goto          153
     145: astore        5
     147: iconst_0
     148: ireturn
     149: astore        5
     151: iconst_0
     152: ireturn
     153: iconst_0
     154: ireturn
    Exception table:
       from    to  target type
          67   120   145   Class java/lang/NullPointerException
         121   138   145   Class java/lang/NullPointerException
         139   142   145   Class java/lang/NullPointerException
          67   120   149   Class java/lang/ClassCastException
         121   138   149   Class java/lang/ClassCastException
         139   142   149   Class java/lang/ClassCastException

  private int unsafeBinarySearch(java.lang.Object) throws java.lang.ClassCastException;
    Code:
       0: aload_0
       1: getfield      #28                 // Field elements:Lorg/apache/curator/shaded/com/google/common/collect/ImmutableList;
       4: aload_1
       5: aload_0
       6: invokevirtual #148                // Method unsafeComparator:()Ljava/util/Comparator;
       9: invokestatic  #154                // Method java/util/Collections.binarySearch:(Ljava/util/List;Ljava/lang/Object;Ljava/util/Comparator;)I
      12: ireturn

  boolean isPartialView();
    Code:
       0: aload_0
       1: getfield      #28                 // Field elements:Lorg/apache/curator/shaded/com/google/common/collect/ImmutableList;
       4: invokevirtual #158                // Method org/apache/curator/shaded/com/google/common/collect/ImmutableList.isPartialView:()Z
       7: ireturn

  int copyIntoArray(java.lang.Object[], int);
    Code:
       0: aload_0
       1: getfield      #28                 // Field elements:Lorg/apache/curator/shaded/com/google/common/collect/ImmutableList;
       4: aload_1
       5: iload_2
       6: invokevirtual #162                // Method org/apache/curator/shaded/com/google/common/collect/ImmutableList.copyIntoArray:([Ljava/lang/Object;I)I
       9: ireturn

  public boolean equals(java.lang.Object);
    Code:
       0: aload_1
       1: aload_0
       2: if_acmpne     7
       5: iconst_1
       6: ireturn
       7: aload_1
       8: instanceof    #171                // class java/util/Set
      11: ifne          16
      14: iconst_0
      15: ireturn
      16: aload_1
      17: checkcast     #171                // class java/util/Set
      20: astore_2
      21: aload_0
      22: invokevirtual #172                // Method size:()I
      25: aload_2
      26: invokeinterface #173,  1          // InterfaceMethod java/util/Set.size:()I
      31: if_icmpeq     36
      34: iconst_0
      35: ireturn
      36: aload_0
      37: getfield      #175                // Field comparator:Ljava/util/Comparator;
      40: aload_2
      41: invokestatic  #95                 // Method org/apache/curator/shaded/com/google/common/collect/SortedIterables.hasSameComparator:(Ljava/util/Comparator;Ljava/lang/Iterable;)Z
      44: ifeq          118
      47: aload_2
      48: invokeinterface #176,  1          // InterfaceMethod java/util/Set.iterator:()Ljava/util/Iterator;
      53: astore_3
      54: aload_0
      55: invokevirtual #101                // Method iterator:()Lorg/apache/curator/shaded/com/google/common/collect/UnmodifiableIterator;
      58: astore        4
      60: aload         4
      62: invokeinterface #132,  1          // InterfaceMethod java/util/Iterator.hasNext:()Z
      67: ifeq          108
      70: aload         4
      72: invokeinterface #116,  1          // InterfaceMethod java/util/Iterator.next:()Ljava/lang/Object;
      77: astore        5
      79: aload_3
      80: invokeinterface #116,  1          // InterfaceMethod java/util/Iterator.next:()Ljava/lang/Object;
      85: astore        6
      87: aload         6
      89: ifnull        103
      92: aload_0
      93: aload         5
      95: aload         6
      97: invokevirtual #130                // Method unsafeCompare:(Ljava/lang/Object;Ljava/lang/Object;)I
     100: ifeq          105
     103: iconst_0
     104: ireturn
     105: goto          60
     108: iconst_1
     109: ireturn
     110: astore        4
     112: iconst_0
     113: ireturn
     114: astore        4
     116: iconst_0
     117: ireturn
     118: aload_0
     119: aload_2
     120: invokevirtual #177                // Method containsAll:(Ljava/util/Collection;)Z
     123: ireturn
    Exception table:
       from    to  target type
          54   104   110   Class java/lang/ClassCastException
         105   109   110   Class java/lang/ClassCastException
          54   104   114   Class java/util/NoSuchElementException
         105   109   114   Class java/util/NoSuchElementException

  public E first();
    Code:
       0: aload_0
       1: getfield      #28                 // Field elements:Lorg/apache/curator/shaded/com/google/common/collect/ImmutableList;
       4: iconst_0
       5: invokevirtual #191                // Method org/apache/curator/shaded/com/google/common/collect/ImmutableList.get:(I)Ljava/lang/Object;
       8: areturn

  public E last();
    Code:
       0: aload_0
       1: getfield      #28                 // Field elements:Lorg/apache/curator/shaded/com/google/common/collect/ImmutableList;
       4: aload_0
       5: invokevirtual #172                // Method size:()I
       8: iconst_1
       9: isub
      10: invokevirtual #191                // Method org/apache/curator/shaded/com/google/common/collect/ImmutableList.get:(I)Ljava/lang/Object;
      13: areturn

  public E lower(E);
    Code:
       0: aload_0
       1: aload_1
       2: iconst_0
       3: invokevirtual #198                // Method headIndex:(Ljava/lang/Object;Z)I
       6: iconst_1
       7: isub
       8: istore_2
       9: iload_2
      10: iconst_m1
      11: if_icmpne     18
      14: aconst_null
      15: goto          26
      18: aload_0
      19: getfield      #28                 // Field elements:Lorg/apache/curator/shaded/com/google/common/collect/ImmutableList;
      22: iload_2
      23: invokevirtual #191                // Method org/apache/curator/shaded/com/google/common/collect/ImmutableList.get:(I)Ljava/lang/Object;
      26: areturn

  public E floor(E);
    Code:
       0: aload_0
       1: aload_1
       2: iconst_1
       3: invokevirtual #198                // Method headIndex:(Ljava/lang/Object;Z)I
       6: iconst_1
       7: isub
       8: istore_2
       9: iload_2
      10: iconst_m1
      11: if_icmpne     18
      14: aconst_null
      15: goto          26
      18: aload_0
      19: getfield      #28                 // Field elements:Lorg/apache/curator/shaded/com/google/common/collect/ImmutableList;
      22: iload_2
      23: invokevirtual #191                // Method org/apache/curator/shaded/com/google/common/collect/ImmutableList.get:(I)Ljava/lang/Object;
      26: areturn

  public E ceiling(E);
    Code:
       0: aload_0
       1: aload_1
       2: iconst_1
       3: invokevirtual #205                // Method tailIndex:(Ljava/lang/Object;Z)I
       6: istore_2
       7: iload_2
       8: aload_0
       9: invokevirtual #172                // Method size:()I
      12: if_icmpne     19
      15: aconst_null
      16: goto          27
      19: aload_0
      20: getfield      #28                 // Field elements:Lorg/apache/curator/shaded/com/google/common/collect/ImmutableList;
      23: iload_2
      24: invokevirtual #191                // Method org/apache/curator/shaded/com/google/common/collect/ImmutableList.get:(I)Ljava/lang/Object;
      27: areturn

  public E higher(E);
    Code:
       0: aload_0
       1: aload_1
       2: iconst_0
       3: invokevirtual #205                // Method tailIndex:(Ljava/lang/Object;Z)I
       6: istore_2
       7: iload_2
       8: aload_0
       9: invokevirtual #172                // Method size:()I
      12: if_icmpne     19
      15: aconst_null
      16: goto          27
      19: aload_0
      20: getfield      #28                 // Field elements:Lorg/apache/curator/shaded/com/google/common/collect/ImmutableList;
      23: iload_2
      24: invokevirtual #191                // Method org/apache/curator/shaded/com/google/common/collect/ImmutableList.get:(I)Ljava/lang/Object;
      27: areturn

  org.apache.curator.shaded.com.google.common.collect.ImmutableSortedSet<E> headSetImpl(E, boolean);
    Code:
       0: aload_0
       1: iconst_0
       2: aload_0
       3: aload_1
       4: iload_2
       5: invokevirtual #198                // Method headIndex:(Ljava/lang/Object;Z)I
       8: invokevirtual #212                // Method getSubSet:(II)Lorg/apache/curator/shaded/com/google/common/collect/ImmutableSortedSet;
      11: areturn

  int headIndex(E, boolean);
    Code:
       0: aload_0
       1: getfield      #28                 // Field elements:Lorg/apache/curator/shaded/com/google/common/collect/ImmutableList;
       4: aload_1
       5: invokestatic  #218                // Method org/apache/curator/shaded/com/google/common/base/Preconditions.checkNotNull:(Ljava/lang/Object;)Ljava/lang/Object;
       8: aload_0
       9: invokevirtual #89                 // Method comparator:()Ljava/util/Comparator;
      12: iload_2
      13: ifeq          22
      16: getstatic     #222                // Field org/apache/curator/shaded/com/google/common/collect/SortedLists$KeyPresentBehavior.FIRST_AFTER:Lorg/apache/curator/shaded/com/google/common/collect/SortedLists$KeyPresentBehavior;
      19: goto          25
      22: getstatic     #225                // Field org/apache/curator/shaded/com/google/common/collect/SortedLists$KeyPresentBehavior.FIRST_PRESENT:Lorg/apache/curator/shaded/com/google/common/collect/SortedLists$KeyPresentBehavior;
      25: getstatic     #229                // Field org/apache/curator/shaded/com/google/common/collect/SortedLists$KeyAbsentBehavior.NEXT_HIGHER:Lorg/apache/curator/shaded/com/google/common/collect/SortedLists$KeyAbsentBehavior;
      28: invokestatic  #232                // Method org/apache/curator/shaded/com/google/common/collect/SortedLists.binarySearch:(Ljava/util/List;Ljava/lang/Object;Ljava/util/Comparator;Lorg/apache/curator/shaded/com/google/common/collect/SortedLists$KeyPresentBehavior;Lorg/apache/curator/shaded/com/google/common/collect/SortedLists$KeyAbsentBehavior;)I
      31: ireturn

  org.apache.curator.shaded.com.google.common.collect.ImmutableSortedSet<E> subSetImpl(E, boolean, E, boolean);
    Code:
       0: aload_0
       1: aload_1
       2: iload_2
       3: invokevirtual #237                // Method tailSetImpl:(Ljava/lang/Object;Z)Lorg/apache/curator/shaded/com/google/common/collect/ImmutableSortedSet;
       6: aload_3
       7: iload         4
       9: invokevirtual #239                // Method org/apache/curator/shaded/com/google/common/collect/ImmutableSortedSet.headSetImpl:(Ljava/lang/Object;Z)Lorg/apache/curator/shaded/com/google/common/collect/ImmutableSortedSet;
      12: areturn

  org.apache.curator.shaded.com.google.common.collect.ImmutableSortedSet<E> tailSetImpl(E, boolean);
    Code:
       0: aload_0
       1: aload_0
       2: aload_1
       3: iload_2
       4: invokevirtual #205                // Method tailIndex:(Ljava/lang/Object;Z)I
       7: aload_0
       8: invokevirtual #172                // Method size:()I
      11: invokevirtual #212                // Method getSubSet:(II)Lorg/apache/curator/shaded/com/google/common/collect/ImmutableSortedSet;
      14: areturn

  int tailIndex(E, boolean);
    Code:
       0: aload_0
       1: getfield      #28                 // Field elements:Lorg/apache/curator/shaded/com/google/common/collect/ImmutableList;
       4: aload_1
       5: invokestatic  #218                // Method org/apache/curator/shaded/com/google/common/base/Preconditions.checkNotNull:(Ljava/lang/Object;)Ljava/lang/Object;
       8: aload_0
       9: invokevirtual #89                 // Method comparator:()Ljava/util/Comparator;
      12: iload_2
      13: ifeq          22
      16: getstatic     #225                // Field org/apache/curator/shaded/com/google/common/collect/SortedLists$KeyPresentBehavior.FIRST_PRESENT:Lorg/apache/curator/shaded/com/google/common/collect/SortedLists$KeyPresentBehavior;
      19: goto          25
      22: getstatic     #222                // Field org/apache/curator/shaded/com/google/common/collect/SortedLists$KeyPresentBehavior.FIRST_AFTER:Lorg/apache/curator/shaded/com/google/common/collect/SortedLists$KeyPresentBehavior;
      25: getstatic     #229                // Field org/apache/curator/shaded/com/google/common/collect/SortedLists$KeyAbsentBehavior.NEXT_HIGHER:Lorg/apache/curator/shaded/com/google/common/collect/SortedLists$KeyAbsentBehavior;
      28: invokestatic  #232                // Method org/apache/curator/shaded/com/google/common/collect/SortedLists.binarySearch:(Ljava/util/List;Ljava/lang/Object;Ljava/util/Comparator;Lorg/apache/curator/shaded/com/google/common/collect/SortedLists$KeyPresentBehavior;Lorg/apache/curator/shaded/com/google/common/collect/SortedLists$KeyAbsentBehavior;)I
      31: ireturn

  java.util.Comparator<java.lang.Object> unsafeComparator();
    Code:
       0: aload_0
       1: getfield      #175                // Field comparator:Ljava/util/Comparator;
       4: areturn

  org.apache.curator.shaded.com.google.common.collect.ImmutableSortedSet<E> getSubSet(int, int);
    Code:
       0: iload_1
       1: ifne          14
       4: iload_2
       5: aload_0
       6: invokevirtual #172                // Method size:()I
       9: if_icmpne     14
      12: aload_0
      13: areturn
      14: iload_1
      15: iload_2
      16: if_icmpge     40
      19: new           #2                  // class org/apache/curator/shaded/com/google/common/collect/RegularImmutableSortedSet
      22: dup
      23: aload_0
      24: getfield      #28                 // Field elements:Lorg/apache/curator/shaded/com/google/common/collect/ImmutableList;
      27: iload_1
      28: iload_2
      29: invokevirtual #246                // Method org/apache/curator/shaded/com/google/common/collect/ImmutableList.subList:(II)Lorg/apache/curator/shaded/com/google/common/collect/ImmutableList;
      32: aload_0
      33: getfield      #175                // Field comparator:Ljava/util/Comparator;
      36: invokespecial #248                // Method "<init>":(Lorg/apache/curator/shaded/com/google/common/collect/ImmutableList;Ljava/util/Comparator;)V
      39: areturn
      40: aload_0
      41: getfield      #175                // Field comparator:Ljava/util/Comparator;
      44: invokestatic  #252                // Method emptySet:(Ljava/util/Comparator;)Lorg/apache/curator/shaded/com/google/common/collect/ImmutableSortedSet;
      47: areturn

  int indexOf(java.lang.Object);
    Code:
       0: aload_1
       1: ifnonnull     6
       4: iconst_m1
       5: ireturn
       6: aload_0
       7: getfield      #28                 // Field elements:Lorg/apache/curator/shaded/com/google/common/collect/ImmutableList;
      10: aload_1
      11: aload_0
      12: invokevirtual #148                // Method unsafeComparator:()Ljava/util/Comparator;
      15: getstatic     #258                // Field org/apache/curator/shaded/com/google/common/collect/SortedLists$KeyPresentBehavior.ANY_PRESENT:Lorg/apache/curator/shaded/com/google/common/collect/SortedLists$KeyPresentBehavior;
      18: getstatic     #261                // Field org/apache/curator/shaded/com/google/common/collect/SortedLists$KeyAbsentBehavior.INVERTED_INSERTION_INDEX:Lorg/apache/curator/shaded/com/google/common/collect/SortedLists$KeyAbsentBehavior;
      21: invokestatic  #232                // Method org/apache/curator/shaded/com/google/common/collect/SortedLists.binarySearch:(Ljava/util/List;Ljava/lang/Object;Ljava/util/Comparator;Lorg/apache/curator/shaded/com/google/common/collect/SortedLists$KeyPresentBehavior;Lorg/apache/curator/shaded/com/google/common/collect/SortedLists$KeyAbsentBehavior;)I
      24: istore_2
      25: goto          31
      28: astore_3
      29: iconst_m1
      30: ireturn
      31: iload_2
      32: iflt          39
      35: iload_2
      36: goto          40
      39: iconst_m1
      40: ireturn
    Exception table:
       from    to  target type
           6    25    28   Class java/lang/ClassCastException

  org.apache.curator.shaded.com.google.common.collect.ImmutableList<E> createAsList();
    Code:
       0: new           #265                // class org/apache/curator/shaded/com/google/common/collect/ImmutableSortedAsList
       3: dup
       4: aload_0
       5: aload_0
       6: getfield      #28                 // Field elements:Lorg/apache/curator/shaded/com/google/common/collect/ImmutableList;
       9: invokespecial #268                // Method org/apache/curator/shaded/com/google/common/collect/ImmutableSortedAsList."<init>":(Lorg/apache/curator/shaded/com/google/common/collect/ImmutableSortedSet;Lorg/apache/curator/shaded/com/google/common/collect/ImmutableList;)V
      12: areturn

  org.apache.curator.shaded.com.google.common.collect.ImmutableSortedSet<E> createDescendingSet();
    Code:
       0: new           #2                  // class org/apache/curator/shaded/com/google/common/collect/RegularImmutableSortedSet
       3: dup
       4: aload_0
       5: getfield      #28                 // Field elements:Lorg/apache/curator/shaded/com/google/common/collect/ImmutableList;
       8: invokevirtual #60                 // Method org/apache/curator/shaded/com/google/common/collect/ImmutableList.reverse:()Lorg/apache/curator/shaded/com/google/common/collect/ImmutableList;
      11: aload_0
      12: getfield      #175                // Field comparator:Ljava/util/Comparator;
      15: invokestatic  #276                // Method org/apache/curator/shaded/com/google/common/collect/Ordering.from:(Ljava/util/Comparator;)Lorg/apache/curator/shaded/com/google/common/collect/Ordering;
      18: invokevirtual #279                // Method org/apache/curator/shaded/com/google/common/collect/Ordering.reverse:()Lorg/apache/curator/shaded/com/google/common/collect/Ordering;
      21: invokespecial #248                // Method "<init>":(Lorg/apache/curator/shaded/com/google/common/collect/ImmutableList;Ljava/util/Comparator;)V
      24: areturn

  public java.util.Iterator descendingIterator();
    Code:
       0: aload_0
       1: invokevirtual #281                // Method descendingIterator:()Lorg/apache/curator/shaded/com/google/common/collect/UnmodifiableIterator;
       4: areturn

  public java.util.Iterator iterator();
    Code:
       0: aload_0
       1: invokevirtual #101                // Method iterator:()Lorg/apache/curator/shaded/com/google/common/collect/UnmodifiableIterator;
       4: areturn
}
