Compiled from "Synchronized.java"
class org.apache.curator.shaded.com.google.common.collect.Synchronized$SynchronizedEntry<K, V> extends org.apache.curator.shaded.com.google.common.collect.Synchronized$SynchronizedObject implements java.util.Map$Entry<K, V> {
  private static final long serialVersionUID;

  org.apache.curator.shaded.com.google.common.collect.Synchronized$SynchronizedEntry(java.util.Map$Entry<K, V>, java.lang.Object);
    Code:
       0: aload_0
       1: aload_1
       2: aload_2
       3: invokespecial #28                 // Method org/apache/curator/shaded/com/google/common/collect/Synchronized$SynchronizedObject."<init>":(Ljava/lang/Object;Ljava/lang/Object;)V
       6: return

  java.util.Map$Entry<K, V> delegate();
    Code:
       0: aload_0
       1: invokespecial #40                 // Method org/apache/curator/shaded/com/google/common/collect/Synchronized$SynchronizedObject.delegate:()Ljava/lang/Object;
       4: checkcast     #7                  // class java/util/Map$Entry
       7: areturn

  public boolean equals(java.lang.Object);
    Code:
       0: aload_0
       1: getfield      #44                 // Field mutex:Ljava/lang/Object;
       4: dup
       5: astore_2
       6: monitorenter
       7: aload_0
       8: invokevirtual #46                 // Method delegate:()Ljava/util/Map$Entry;
      11: aload_1
      12: invokeinterface #48,  2           // InterfaceMethod java/util/Map$Entry.equals:(Ljava/lang/Object;)Z
      17: aload_2
      18: monitorexit
      19: ireturn
      20: astore_3
      21: aload_2
      22: monitorexit
      23: aload_3
      24: athrow
    Exception table:
       from    to  target type
           7    19    20   any
          20    23    20   any

  public int hashCode();
    Code:
       0: aload_0
       1: getfield      #44                 // Field mutex:Ljava/lang/Object;
       4: dup
       5: astore_1
       6: monitorenter
       7: aload_0
       8: invokevirtual #46                 // Method delegate:()Ljava/util/Map$Entry;
      11: invokeinterface #57,  1           // InterfaceMethod java/util/Map$Entry.hashCode:()I
      16: aload_1
      17: monitorexit
      18: ireturn
      19: astore_2
      20: aload_1
      21: monitorexit
      22: aload_2
      23: athrow
    Exception table:
       from    to  target type
           7    18    19   any
          19    22    19   any

  public K getKey();
    Code:
       0: aload_0
       1: getfield      #44                 // Field mutex:Ljava/lang/Object;
       4: dup
       5: astore_1
       6: monitorenter
       7: aload_0
       8: invokevirtual #46                 // Method delegate:()Ljava/util/Map$Entry;
      11: invokeinterface #60,  1           // InterfaceMethod java/util/Map$Entry.getKey:()Ljava/lang/Object;
      16: aload_1
      17: monitorexit
      18: areturn
      19: astore_2
      20: aload_1
      21: monitorexit
      22: aload_2
      23: athrow
    Exception table:
       from    to  target type
           7    18    19   any
          19    22    19   any

  public V getValue();
    Code:
       0: aload_0
       1: getfield      #44                 // Field mutex:Ljava/lang/Object;
       4: dup
       5: astore_1
       6: monitorenter
       7: aload_0
       8: invokevirtual #46                 // Method delegate:()Ljava/util/Map$Entry;
      11: invokeinterface #63,  1           // InterfaceMethod java/util/Map$Entry.getValue:()Ljava/lang/Object;
      16: aload_1
      17: monitorexit
      18: areturn
      19: astore_2
      20: aload_1
      21: monitorexit
      22: aload_2
      23: athrow
    Exception table:
       from    to  target type
           7    18    19   any
          19    22    19   any

  public V setValue(V);
    Code:
       0: aload_0
       1: getfield      #44                 // Field mutex:Ljava/lang/Object;
       4: dup
       5: astore_2
       6: monitorenter
       7: aload_0
       8: invokevirtual #46                 // Method delegate:()Ljava/util/Map$Entry;
      11: aload_1
      12: invokeinterface #67,  2           // InterfaceMethod java/util/Map$Entry.setValue:(Ljava/lang/Object;)Ljava/lang/Object;
      17: aload_2
      18: monitorexit
      19: areturn
      20: astore_3
      21: aload_2
      22: monitorexit
      23: aload_3
      24: athrow
    Exception table:
       from    to  target type
           7    19    20   any
          20    23    20   any

  java.lang.Object delegate();
    Code:
       0: aload_0
       1: invokevirtual #46                 // Method delegate:()Ljava/util/Map$Entry;
       4: areturn
}
