Compiled from "AbstractAnnotationHandlerBeanPostProcessor.java"
final class org.axonframework.spring.config.AbstractAnnotationHandlerBeanPostProcessor$ProxyOrImplementationInvocationInterceptor implements org.springframework.aop.IntroductionInfo,org.springframework.aop.IntroductionInterceptor {
  private final java.lang.Object proxy;

  private final java.lang.reflect.Method[] proxyMethods;

  private final java.lang.Class<?>[] interfaces;

  private org.axonframework.spring.config.AbstractAnnotationHandlerBeanPostProcessor$ProxyOrImplementationInvocationInterceptor(java.lang.Object, java.lang.Object);
    Code:
       0: aload_0
       1: invokespecial #2                  // Method java/lang/Object."<init>":()V
       4: aload_0
       5: aload_1
       6: putfield      #3                  // Field proxy:Ljava/lang/Object;
       9: aload_0
      10: aload_1
      11: invokevirtual #4                  // Method java/lang/Object.getClass:()Ljava/lang/Class;
      14: invokevirtual #5                  // Method java/lang/Class.getDeclaredMethods:()[Ljava/lang/reflect/Method;
      17: putfield      #6                  // Field proxyMethods:[Ljava/lang/reflect/Method;
      20: aload_0
      21: aload_2
      22: invokestatic  #7                  // Method org/springframework/util/ClassUtils.getAllInterfaces:(Ljava/lang/Object;)[Ljava/lang/Class;
      25: putfield      #8                  // Field interfaces:[Ljava/lang/Class;
      28: return

  public boolean implementsInterface(java.lang.Class<?>);
    Code:
       0: aload_0
       1: getfield      #8                  // Field interfaces:[Ljava/lang/Class;
       4: astore_2
       5: aload_2
       6: arraylength
       7: istore_3
       8: iconst_0
       9: istore        4
      11: iload         4
      13: iload_3
      14: if_icmpge     40
      17: aload_2
      18: iload         4
      20: aaload
      21: astore        5
      23: aload_1
      24: aload         5
      26: invokevirtual #9                  // Method java/lang/Object.equals:(Ljava/lang/Object;)Z
      29: ifeq          34
      32: iconst_1
      33: ireturn
      34: iinc          4, 1
      37: goto          11
      40: iconst_0
      41: ireturn

  public java.lang.Class<?>[] getInterfaces();
    Code:
       0: aload_0
       1: getfield      #8                  // Field interfaces:[Ljava/lang/Class;
       4: areturn

  public java.lang.Object invoke(org.aopalliance.intercept.MethodInvocation) throws java.lang.Exception;
    Code:
       0: aload_0
       1: getfield      #6                  // Field proxyMethods:[Ljava/lang/reflect/Method;
       4: astore_2
       5: aload_2
       6: arraylength
       7: istore_3
       8: iconst_0
       9: istore        4
      11: iload         4
      13: iload_3
      14: if_icmpge     85
      17: aload_2
      18: iload         4
      20: aaload
      21: astore        5
      23: aload         5
      25: invokevirtual #10                 // Method java/lang/reflect/Method.getName:()Ljava/lang/String;
      28: aload_1
      29: invokeinterface #11,  1           // InterfaceMethod org/aopalliance/intercept/MethodInvocation.getMethod:()Ljava/lang/reflect/Method;
      34: invokevirtual #10                 // Method java/lang/reflect/Method.getName:()Ljava/lang/String;
      37: invokevirtual #12                 // Method java/lang/String.equals:(Ljava/lang/Object;)Z
      40: ifeq          79
      43: aload         5
      45: invokevirtual #13                 // Method java/lang/reflect/Method.getParameterTypes:()[Ljava/lang/Class;
      48: aload_1
      49: invokeinterface #11,  1           // InterfaceMethod org/aopalliance/intercept/MethodInvocation.getMethod:()Ljava/lang/reflect/Method;
      54: invokevirtual #13                 // Method java/lang/reflect/Method.getParameterTypes:()[Ljava/lang/Class;
      57: invokestatic  #14                 // Method java/util/Arrays.equals:([Ljava/lang/Object;[Ljava/lang/Object;)Z
      60: ifeq          79
      63: aload         5
      65: aload_0
      66: getfield      #3                  // Field proxy:Ljava/lang/Object;
      69: aload_1
      70: invokeinterface #15,  1           // InterfaceMethod org/aopalliance/intercept/MethodInvocation.getArguments:()[Ljava/lang/Object;
      75: invokevirtual #16                 // Method java/lang/reflect/Method.invoke:(Ljava/lang/Object;[Ljava/lang/Object;)Ljava/lang/Object;
      78: areturn
      79: iinc          4, 1
      82: goto          11
      85: aload_1
      86: invokeinterface #17,  1           // InterfaceMethod org/aopalliance/intercept/MethodInvocation.proceed:()Ljava/lang/Object;
      91: areturn
      92: astore_2
      93: aload_2
      94: invokevirtual #19                 // Method java/lang/reflect/InvocationTargetException.getCause:()Ljava/lang/Throwable;
      97: instanceof    #20                 // class java/lang/Exception
     100: ifeq          113
     103: aload_2
     104: invokevirtual #19                 // Method java/lang/reflect/InvocationTargetException.getCause:()Ljava/lang/Throwable;
     107: checkcast     #20                 // class java/lang/Exception
     110: goto          114
     113: aload_2
     114: athrow
     115: astore_2
     116: aload_2
     117: instanceof    #22                 // class java/lang/Error
     120: ifeq          128
     123: aload_2
     124: checkcast     #22                 // class java/lang/Error
     127: athrow
     128: new           #18                 // class java/lang/reflect/InvocationTargetException
     131: dup
     132: aload_2
     133: invokespecial #23                 // Method java/lang/reflect/InvocationTargetException."<init>":(Ljava/lang/Throwable;)V
     136: athrow
    Exception table:
       from    to  target type
           0    78    92   Class java/lang/reflect/InvocationTargetException
          79    91    92   Class java/lang/reflect/InvocationTargetException
           0    78   115   Class java/lang/Throwable
          79    91   115   Class java/lang/Throwable

  org.axonframework.spring.config.AbstractAnnotationHandlerBeanPostProcessor$ProxyOrImplementationInvocationInterceptor(java.lang.Object, java.lang.Object, org.axonframework.spring.config.AbstractAnnotationHandlerBeanPostProcessor$1);
    Code:
       0: aload_0
       1: aload_1
       2: aload_2
       3: invokespecial #1                  // Method "<init>":(Ljava/lang/Object;Ljava/lang/Object;)V
       6: return
}
