Compiled from "GraphStage.scala"
public abstract class akka.stream.stage.AbstractInHandler implements akka.stream.stage.InHandler {
  public void onUpstreamFinish() throws java.lang.Exception;
    Code:
       0: aload_0
       1: invokestatic  #19                 // Method akka/stream/stage/InHandler$class.onUpstreamFinish:(Lakka/stream/stage/InHandler;)V
       4: return

  public void onUpstreamFailure(java.lang.Throwable) throws java.lang.Exception;
    Code:
       0: aload_0
       1: aload_1
       2: invokestatic  #26                 // Method akka/stream/stage/InHandler$class.onUpstreamFailure:(Lakka/stream/stage/InHandler;Ljava/lang/Throwable;)V
       5: return

  public akka.stream.stage.AbstractInHandler();
    Code:
       0: aload_0
       1: invokespecial #31                 // Method java/lang/Object."<init>":()V
       4: aload_0
       5: invokestatic  #34                 // Method akka/stream/stage/InHandler$class.$init$:(Lakka/stream/stage/InHandler;)V
       8: return
}
