Compiled from "GraphStage.scala"
public final class akka.stream.stage.CallbackWrapper$$anonfun$invoke$1 extends scala.runtime.AbstractFunction0$mcV$sp implements scala.Serializable {
  public static final long serialVersionUID;

  private final akka.stream.stage.CallbackWrapper $outer;

  private final java.lang.Object arg$1;

  public final void apply();
    Code:
       0: aload_0
       1: invokevirtual #25                 // Method apply$mcV$sp:()V
       4: return

  public void apply$mcV$sp();
    Code:
       0: aload_0
       1: getfield      #29                 // Field $outer:Lakka/stream/stage/CallbackWrapper;
       4: invokeinterface #33,  1           // InterfaceMethod akka/stream/stage/CallbackWrapper.akka$stream$stage$CallbackWrapper$$callbackState:()Ljava/util/concurrent/atomic/AtomicReference;
       9: invokevirtual #39                 // Method java/util/concurrent/atomic/AtomicReference.get:()Ljava/lang/Object;
      12: checkcast     #41                 // class akka/stream/stage/CallbackWrapper$CallbackState
      15: astore_1
      16: aload_1
      17: instanceof    #43                 // class akka/stream/stage/CallbackWrapper$Initialized
      20: ifeq          51
      23: aload_1
      24: checkcast     #43                 // class akka/stream/stage/CallbackWrapper$Initialized
      27: astore_2
      28: aload_2
      29: invokevirtual #47                 // Method akka/stream/stage/CallbackWrapper$Initialized.f:()Lscala/Function1;
      32: astore_3
      33: aload_3
      34: aload_0
      35: getfield      #49                 // Field arg$1:Ljava/lang/Object;
      38: invokeinterface #54,  2           // InterfaceMethod scala/Function1.apply:(Ljava/lang/Object;)Ljava/lang/Object;
      43: checkcast     #56                 // class scala/runtime/BoxedUnit
      46: astore        4
      48: goto          155
      51: aload_1
      52: instanceof    #58                 // class akka/stream/stage/CallbackWrapper$NotInitialized
      55: ifeq          119
      58: aload_1
      59: checkcast     #58                 // class akka/stream/stage/CallbackWrapper$NotInitialized
      62: astore        5
      64: aload         5
      66: invokevirtual #62                 // Method akka/stream/stage/CallbackWrapper$NotInitialized.list:()Lscala/collection/immutable/List;
      69: astore        6
      71: aload_0
      72: getfield      #29                 // Field $outer:Lakka/stream/stage/CallbackWrapper;
      75: invokeinterface #33,  1           // InterfaceMethod akka/stream/stage/CallbackWrapper.akka$stream$stage$CallbackWrapper$$callbackState:()Ljava/util/concurrent/atomic/AtomicReference;
      80: aload         5
      82: aload_0
      83: getfield      #29                 // Field $outer:Lakka/stream/stage/CallbackWrapper;
      86: invokeinterface #66,  1           // InterfaceMethod akka/stream/stage/CallbackWrapper.akka$stream$stage$CallbackWrapper$$NotInitialized:()Lakka/stream/stage/CallbackWrapper$NotInitialized$;
      91: aload_0
      92: getfield      #49                 // Field arg$1:Ljava/lang/Object;
      95: astore        7
      97: aload         6
      99: aload         7
     101: invokevirtual #72                 // Method scala/collection/immutable/List.$colon$colon:(Ljava/lang/Object;)Lscala/collection/immutable/List;
     104: invokevirtual #77                 // Method akka/stream/stage/CallbackWrapper$NotInitialized$.apply:(Lscala/collection/immutable/List;)Lakka/stream/stage/CallbackWrapper$NotInitialized;
     107: invokevirtual #81                 // Method java/util/concurrent/atomic/AtomicReference.compareAndSet:(Ljava/lang/Object;Ljava/lang/Object;)Z
     110: pop
     111: getstatic     #85                 // Field scala/runtime/BoxedUnit.UNIT:Lscala/runtime/BoxedUnit;
     114: astore        4
     116: goto          155
     119: aload_1
     120: instanceof    #87                 // class akka/stream/stage/CallbackWrapper$Stopped
     123: ifeq          156
     126: aload_1
     127: checkcast     #87                 // class akka/stream/stage/CallbackWrapper$Stopped
     130: astore        8
     132: aload         8
     134: invokevirtual #88                 // Method akka/stream/stage/CallbackWrapper$Stopped.f:()Lscala/Function1;
     137: astore        9
     139: aload         9
     141: aload_0
     142: getfield      #49                 // Field arg$1:Ljava/lang/Object;
     145: invokeinterface #54,  2           // InterfaceMethod scala/Function1.apply:(Ljava/lang/Object;)Ljava/lang/Object;
     150: checkcast     #56                 // class scala/runtime/BoxedUnit
     153: astore        4
     155: return
     156: new           #90                 // class scala/MatchError
     159: dup
     160: aload_1
     161: invokespecial #93                 // Method scala/MatchError."<init>":(Ljava/lang/Object;)V
     164: athrow

  public final java.lang.Object apply();
    Code:
       0: aload_0
       1: invokevirtual #99                 // Method apply:()V
       4: getstatic     #85                 // Field scala/runtime/BoxedUnit.UNIT:Lscala/runtime/BoxedUnit;
       7: areturn

  public akka.stream.stage.CallbackWrapper$$anonfun$invoke$1(akka.stream.stage.CallbackWrapper<T>);
    Code:
       0: aload_1
       1: ifnonnull     6
       4: aconst_null
       5: athrow
       6: aload_0
       7: aload_1
       8: putfield      #29                 // Field $outer:Lakka/stream/stage/CallbackWrapper;
      11: aload_0
      12: aload_2
      13: putfield      #49                 // Field arg$1:Ljava/lang/Object;
      16: aload_0
      17: invokespecial #102                // Method scala/runtime/AbstractFunction0$mcV$sp."<init>":()V
      20: return
}
