Compiled from "Op.java"
public final class io.etcd.jetcd.op.Op$Type extends java.lang.Enum<io.etcd.jetcd.op.Op$Type> {
  public static final io.etcd.jetcd.op.Op$Type PUT;

  public static final io.etcd.jetcd.op.Op$Type RANGE;

  public static final io.etcd.jetcd.op.Op$Type DELETE_RANGE;

  public static final io.etcd.jetcd.op.Op$Type TXN;

  private static final io.etcd.jetcd.op.Op$Type[] $VALUES;

  public static io.etcd.jetcd.op.Op$Type[] values();
    Code:
       0: getstatic     #1                  // Field $VALUES:[Lio/etcd/jetcd/op/Op$Type;
       3: invokevirtual #2                  // Method "[Lio/etcd/jetcd/op/Op$Type;".clone:()Ljava/lang/Object;
       6: checkcast     #3                  // class "[Lio/etcd/jetcd/op/Op$Type;"
       9: areturn

  public static io.etcd.jetcd.op.Op$Type valueOf(java.lang.String);
    Code:
       0: ldc           #4                  // class io/etcd/jetcd/op/Op$Type
       2: aload_0
       3: invokestatic  #5                  // Method java/lang/Enum.valueOf:(Ljava/lang/Class;Ljava/lang/String;)Ljava/lang/Enum;
       6: checkcast     #4                  // class io/etcd/jetcd/op/Op$Type
       9: areturn

  private io.etcd.jetcd.op.Op$Type();
    Code:
       0: aload_0
       1: aload_1
       2: iload_2
       3: invokespecial #6                  // Method java/lang/Enum."<init>":(Ljava/lang/String;I)V
       6: return

  static {};
    Code:
       0: new           #4                  // class io/etcd/jetcd/op/Op$Type
       3: dup
       4: ldc           #7                  // String PUT
       6: iconst_0
       7: invokespecial #8                  // Method "<init>":(Ljava/lang/String;I)V
      10: putstatic     #9                  // Field PUT:Lio/etcd/jetcd/op/Op$Type;
      13: new           #4                  // class io/etcd/jetcd/op/Op$Type
      16: dup
      17: ldc           #10                 // String RANGE
      19: iconst_1
      20: invokespecial #8                  // Method "<init>":(Ljava/lang/String;I)V
      23: putstatic     #11                 // Field RANGE:Lio/etcd/jetcd/op/Op$Type;
      26: new           #4                  // class io/etcd/jetcd/op/Op$Type
      29: dup
      30: ldc           #12                 // String DELETE_RANGE
      32: iconst_2
      33: invokespecial #8                  // Method "<init>":(Ljava/lang/String;I)V
      36: putstatic     #13                 // Field DELETE_RANGE:Lio/etcd/jetcd/op/Op$Type;
      39: new           #4                  // class io/etcd/jetcd/op/Op$Type
      42: dup
      43: ldc           #14                 // String TXN
      45: iconst_3
      46: invokespecial #8                  // Method "<init>":(Ljava/lang/String;I)V
      49: putstatic     #15                 // Field TXN:Lio/etcd/jetcd/op/Op$Type;
      52: iconst_4
      53: anewarray     #4                  // class io/etcd/jetcd/op/Op$Type
      56: dup
      57: iconst_0
      58: getstatic     #9                  // Field PUT:Lio/etcd/jetcd/op/Op$Type;
      61: aastore
      62: dup
      63: iconst_1
      64: getstatic     #11                 // Field RANGE:Lio/etcd/jetcd/op/Op$Type;
      67: aastore
      68: dup
      69: iconst_2
      70: getstatic     #13                 // Field DELETE_RANGE:Lio/etcd/jetcd/op/Op$Type;
      73: aastore
      74: dup
      75: iconst_3
      76: getstatic     #15                 // Field TXN:Lio/etcd/jetcd/op/Op$Type;
      79: aastore
      80: putstatic     #1                  // Field $VALUES:[Lio/etcd/jetcd/op/Op$Type;
      83: return
}
