Compiled from "LiquibaseEndpointAutoConfiguration.java"
final class org.springframework.boot.actuate.autoconfigure.liquibase.LiquibaseEndpointAutoConfiguration$1 implements org.springframework.beans.factory.config.BeanPostProcessor {
  org.springframework.boot.actuate.autoconfigure.liquibase.LiquibaseEndpointAutoConfiguration$1();
    Code:
       0: aload_0
       1: invokespecial #1                  // Method java/lang/Object."<init>":()V
       4: return

  public java.lang.Object postProcessBeforeInitialization(java.lang.Object, java.lang.String) throws org.springframework.beans.BeansException;
    Code:
       0: aload_1
       1: instanceof    #2                  // class org/springframework/boot/autoconfigure/liquibase/DataSourceClosingSpringLiquibase
       4: ifeq          15
       7: aload_1
       8: checkcast     #2                  // class org/springframework/boot/autoconfigure/liquibase/DataSourceClosingSpringLiquibase
      11: iconst_0
      12: invokevirtual #3                  // Method org/springframework/boot/autoconfigure/liquibase/DataSourceClosingSpringLiquibase.setCloseDataSourceOnceMigrated:(Z)V
      15: aload_1
      16: areturn

  public java.lang.Object postProcessAfterInitialization(java.lang.Object, java.lang.String) throws org.springframework.beans.BeansException;
    Code:
       0: aload_1
       1: areturn
}
