Compiled from "ConcatSourcesParam.java"
public class org.apache.hadoop.hdfs.web.resources.ConcatSourcesParam extends org.apache.hadoop.hdfs.web.resources.StringParam {
  public static final java.lang.String NAME;

  public static final java.lang.String DEFAULT;

  private static final org.apache.hadoop.hdfs.web.resources.StringParam$Domain DOMAIN;

  private static java.lang.String paths2String(org.apache.hadoop.fs.Path[]);
    Code:
       0: aload_0
       1: ifnull        9
       4: aload_0
       5: arraylength
       6: ifne          12
       9: ldc           #1                  // String
      11: areturn
      12: new           #2                  // class java/lang/StringBuilder
      15: dup
      16: aload_0
      17: iconst_0
      18: aaload
      19: invokevirtual #3                  // Method org/apache/hadoop/fs/Path.toUri:()Ljava/net/URI;
      22: invokevirtual #4                  // Method java/net/URI.getPath:()Ljava/lang/String;
      25: invokespecial #5                  // Method java/lang/StringBuilder."<init>":(Ljava/lang/String;)V
      28: astore_1
      29: iconst_1
      30: istore_2
      31: iload_2
      32: aload_0
      33: arraylength
      34: if_icmpge     62
      37: aload_1
      38: bipush        44
      40: invokevirtual #6                  // Method java/lang/StringBuilder.append:(C)Ljava/lang/StringBuilder;
      43: aload_0
      44: iload_2
      45: aaload
      46: invokevirtual #3                  // Method org/apache/hadoop/fs/Path.toUri:()Ljava/net/URI;
      49: invokevirtual #4                  // Method java/net/URI.getPath:()Ljava/lang/String;
      52: invokevirtual #7                  // Method java/lang/StringBuilder.append:(Ljava/lang/String;)Ljava/lang/StringBuilder;
      55: pop
      56: iinc          2, 1
      59: goto          31
      62: aload_1
      63: invokevirtual #8                  // Method java/lang/StringBuilder.toString:()Ljava/lang/String;
      66: areturn

  public org.apache.hadoop.hdfs.web.resources.ConcatSourcesParam(java.lang.String);
    Code:
       0: aload_0
       1: getstatic     #9                  // Field DOMAIN:Lorg/apache/hadoop/hdfs/web/resources/StringParam$Domain;
       4: aload_1
       5: invokespecial #10                 // Method org/apache/hadoop/hdfs/web/resources/StringParam."<init>":(Lorg/apache/hadoop/hdfs/web/resources/StringParam$Domain;Ljava/lang/String;)V
       8: return

  public org.apache.hadoop.hdfs.web.resources.ConcatSourcesParam(org.apache.hadoop.fs.Path[]);
    Code:
       0: aload_0
       1: aload_1
       2: invokestatic  #11                 // Method paths2String:([Lorg/apache/hadoop/fs/Path;)Ljava/lang/String;
       5: invokespecial #12                 // Method "<init>":(Ljava/lang/String;)V
       8: return

  public java.lang.String getName();
    Code:
       0: ldc           #14                 // String sources
       2: areturn

  public final java.lang.String[] getAbsolutePaths();
    Code:
       0: aload_0
       1: invokevirtual #15                 // Method getValue:()Ljava/lang/Object;
       4: checkcast     #16                 // class java/lang/String
       7: ldc           #17                 // String ,
       9: invokevirtual #18                 // Method java/lang/String.split:(Ljava/lang/String;)[Ljava/lang/String;
      12: areturn

  public java.lang.String getValueString();
    Code:
       0: aload_0
       1: invokespecial #19                 // Method org/apache/hadoop/hdfs/web/resources/StringParam.getValueString:()Ljava/lang/String;
       4: areturn

  static {};
    Code:
       0: new           #20                 // class org/apache/hadoop/hdfs/web/resources/StringParam$Domain
       3: dup
       4: ldc           #14                 // String sources
       6: aconst_null
       7: invokespecial #21                 // Method org/apache/hadoop/hdfs/web/resources/StringParam$Domain."<init>":(Ljava/lang/String;Ljava/util/regex/Pattern;)V
      10: putstatic     #9                  // Field DOMAIN:Lorg/apache/hadoop/hdfs/web/resources/StringParam$Domain;
      13: return
}
