Compiled from "StringParam.java"
abstract class org.apache.hadoop.hdfs.web.resources.StringParam extends org.apache.hadoop.hdfs.web.resources.Param<java.lang.String, org.apache.hadoop.hdfs.web.resources.StringParam$Domain> {
  org.apache.hadoop.hdfs.web.resources.StringParam(org.apache.hadoop.hdfs.web.resources.StringParam$Domain, java.lang.String);
    Code:
       0: aload_0
       1: aload_1
       2: aload_1
       3: aload_2
       4: invokevirtual #1                  // Method org/apache/hadoop/hdfs/web/resources/StringParam$Domain.parse:(Ljava/lang/String;)Ljava/lang/String;
       7: invokespecial #2                  // Method org/apache/hadoop/hdfs/web/resources/Param."<init>":(Lorg/apache/hadoop/hdfs/web/resources/Param$Domain;Ljava/lang/Object;)V
      10: return

  public java.lang.String getValueString();
    Code:
       0: aload_0
       1: getfield      #3                  // Field value:Ljava/lang/Object;
       4: checkcast     #4                  // class java/lang/String
       7: areturn
}
