Compiled from "XAttrSetFlagParam.java"
public class org.apache.hadoop.hdfs.web.resources.XAttrSetFlagParam extends org.apache.hadoop.hdfs.web.resources.EnumSetParam<org.apache.hadoop.fs.XAttrSetFlag> {
  public static final java.lang.String NAME;

  public static final java.lang.String DEFAULT;

  private static final org.apache.hadoop.hdfs.web.resources.EnumSetParam$Domain<org.apache.hadoop.fs.XAttrSetFlag> DOMAIN;

  public org.apache.hadoop.hdfs.web.resources.XAttrSetFlagParam(java.util.EnumSet<org.apache.hadoop.fs.XAttrSetFlag>);
    Code:
       0: aload_0
       1: getstatic     #1                  // Field DOMAIN:Lorg/apache/hadoop/hdfs/web/resources/EnumSetParam$Domain;
       4: aload_1
       5: invokespecial #2                  // Method org/apache/hadoop/hdfs/web/resources/EnumSetParam."<init>":(Lorg/apache/hadoop/hdfs/web/resources/EnumSetParam$Domain;Ljava/util/EnumSet;)V
       8: return

  public org.apache.hadoop.hdfs.web.resources.XAttrSetFlagParam(java.lang.String);
    Code:
       0: aload_0
       1: getstatic     #1                  // Field DOMAIN:Lorg/apache/hadoop/hdfs/web/resources/EnumSetParam$Domain;
       4: getstatic     #1                  // Field DOMAIN:Lorg/apache/hadoop/hdfs/web/resources/EnumSetParam$Domain;
       7: aload_1
       8: invokevirtual #3                  // Method org/apache/hadoop/hdfs/web/resources/EnumSetParam$Domain.parse:(Ljava/lang/String;)Ljava/util/EnumSet;
      11: invokespecial #2                  // Method org/apache/hadoop/hdfs/web/resources/EnumSetParam."<init>":(Lorg/apache/hadoop/hdfs/web/resources/EnumSetParam$Domain;Ljava/util/EnumSet;)V
      14: return

  public java.lang.String getName();
    Code:
       0: ldc           #5                  // String flag
       2: areturn

  public java.util.EnumSet<org.apache.hadoop.fs.XAttrSetFlag> getFlag();
    Code:
       0: aload_0
       1: invokevirtual #6                  // Method getValue:()Ljava/lang/Object;
       4: checkcast     #7                  // class java/util/EnumSet
       7: areturn

  public java.lang.String getValueString();
    Code:
       0: aload_0
       1: invokespecial #8                  // Method org/apache/hadoop/hdfs/web/resources/EnumSetParam.getValueString:()Ljava/lang/String;
       4: areturn

  public java.lang.String toString();
    Code:
       0: aload_0
       1: invokespecial #9                  // Method org/apache/hadoop/hdfs/web/resources/EnumSetParam.toString:()Ljava/lang/String;
       4: areturn

  static {};
    Code:
       0: new           #10                 // class org/apache/hadoop/hdfs/web/resources/EnumSetParam$Domain
       3: dup
       4: ldc           #5                  // String flag
       6: ldc           #11                 // class org/apache/hadoop/fs/XAttrSetFlag
       8: invokespecial #12                 // Method org/apache/hadoop/hdfs/web/resources/EnumSetParam$Domain."<init>":(Ljava/lang/String;Ljava/lang/Class;)V
      11: putstatic     #1                  // Field DOMAIN:Lorg/apache/hadoop/hdfs/web/resources/EnumSetParam$Domain;
      14: return
}
