Compiled from "JAXBDSContext.java"
final class org.apache.axis2.datasource.jaxb.JAXBDSContext$2 implements java.security.PrivilegedAction<java.lang.Object> {
  final boolean val$isList;

  final java.lang.Class val$type;

  final org.apache.axis2.jaxws.message.databinding.JAXBUtils$CONSTRUCTION_TYPE val$ctype;

  final javax.xml.bind.Unmarshaller val$u;

  final javax.xml.stream.XMLStreamReader val$reader;

  org.apache.axis2.datasource.jaxb.JAXBDSContext$2(boolean, java.lang.Class, org.apache.axis2.jaxws.message.databinding.JAXBUtils$CONSTRUCTION_TYPE, javax.xml.bind.Unmarshaller, javax.xml.stream.XMLStreamReader);
    Code:
       0: aload_0
       1: iload_1
       2: putfield      #1                  // Field val$isList:Z
       5: aload_0
       6: aload_2
       7: putfield      #2                  // Field val$type:Ljava/lang/Class;
      10: aload_0
      11: aload_3
      12: putfield      #3                  // Field val$ctype:Lorg/apache/axis2/jaxws/message/databinding/JAXBUtils$CONSTRUCTION_TYPE;
      15: aload_0
      16: aload         4
      18: putfield      #4                  // Field val$u:Ljavax/xml/bind/Unmarshaller;
      21: aload_0
      22: aload         5
      24: putfield      #5                  // Field val$reader:Ljavax/xml/stream/XMLStreamReader;
      27: aload_0
      28: invokespecial #6                  // Method java/lang/Object."<init>":()V
      31: return

  public java.lang.Object run();
    Code:
       0: aload_0
       1: getfield      #1                  // Field val$isList:Z
       4: ifne          349
       7: aload_0
       8: getfield      #2                  // Field val$type:Ljava/lang/Class;
      11: invokevirtual #7                  // Method java/lang/Class.isArray:()Z
      14: ifeq          213
      17: aload_0
      18: getfield      #3                  // Field val$ctype:Lorg/apache/axis2/jaxws/message/databinding/JAXBUtils$CONSTRUCTION_TYPE;
      21: getstatic     #8                  // Field org/apache/axis2/jaxws/message/databinding/JAXBUtils$CONSTRUCTION_TYPE.BY_CONTEXT_PATH:Lorg/apache/axis2/jaxws/message/databinding/JAXBUtils$CONSTRUCTION_TYPE;
      24: if_acmpne     64
      27: getstatic     #9                  // Field org/apache/axis2/datasource/jaxb/JAXBDSContext.DEBUG_ENABLED:Z
      30: ifeq          43
      33: invokestatic  #10                 // Method org/apache/axis2/datasource/jaxb/JAXBDSContext.access$200:()Lorg/apache/commons/logging/Log;
      36: ldc           #11                 // String Unmarshal Array via BY_CONTEXT_PATH approach
      38: invokeinterface #12,  2           // InterfaceMethod org/apache/commons/logging/Log.debug:(Ljava/lang/Object;)V
      43: aload_0
      44: getfield      #4                  // Field val$u:Ljavax/xml/bind/Unmarshaller;
      47: aload_0
      48: getfield      #5                  // Field val$reader:Ljavax/xml/stream/XMLStreamReader;
      51: aload_0
      52: getfield      #2                  // Field val$type:Ljava/lang/Class;
      55: invokeinterface #13,  3           // InterfaceMethod javax/xml/bind/Unmarshaller.unmarshal:(Ljavax/xml/stream/XMLStreamReader;Ljava/lang/Class;)Ljavax/xml/bind/JAXBElement;
      60: astore_1
      61: goto          381
      64: aload_0
      65: getfield      #3                  // Field val$ctype:Lorg/apache/axis2/jaxws/message/databinding/JAXBUtils$CONSTRUCTION_TYPE;
      68: getstatic     #14                 // Field org/apache/axis2/jaxws/message/databinding/JAXBUtils$CONSTRUCTION_TYPE.BY_CLASS_ARRAY:Lorg/apache/axis2/jaxws/message/databinding/JAXBUtils$CONSTRUCTION_TYPE;
      71: if_acmpne     176
      74: aload_0
      75: getfield      #2                  // Field val$type:Ljava/lang/Class;
      78: invokevirtual #15                 // Method java/lang/Class.getComponentType:()Ljava/lang/Class;
      81: astore_2
      82: aload_2
      83: invokevirtual #7                  // Method java/lang/Class.isArray:()Z
      86: ifeq          97
      89: aload_2
      90: invokevirtual #15                 // Method java/lang/Class.getComponentType:()Ljava/lang/Class;
      93: astore_2
      94: goto          82
      97: aload_2
      98: invokevirtual #16                 // Method java/lang/Class.isPrimitive:()Z
     101: ifeq          141
     104: getstatic     #9                  // Field org/apache/axis2/datasource/jaxb/JAXBDSContext.DEBUG_ENABLED:Z
     107: ifeq          120
     110: invokestatic  #10                 // Method org/apache/axis2/datasource/jaxb/JAXBDSContext.access$200:()Lorg/apache/commons/logging/Log;
     113: ldc           #17                 // String Unmarshal Array of primitive via BY_CLASS_ARRAY approach
     115: invokeinterface #12,  2           // InterfaceMethod org/apache/commons/logging/Log.debug:(Ljava/lang/Object;)V
     120: aload_0
     121: getfield      #4                  // Field val$u:Ljavax/xml/bind/Unmarshaller;
     124: aload_0
     125: getfield      #5                  // Field val$reader:Ljavax/xml/stream/XMLStreamReader;
     128: aload_0
     129: getfield      #2                  // Field val$type:Ljava/lang/Class;
     132: invokeinterface #13,  3           // InterfaceMethod javax/xml/bind/Unmarshaller.unmarshal:(Ljavax/xml/stream/XMLStreamReader;Ljava/lang/Class;)Ljavax/xml/bind/JAXBElement;
     137: astore_1
     138: goto          173
     141: getstatic     #9                  // Field org/apache/axis2/datasource/jaxb/JAXBDSContext.DEBUG_ENABLED:Z
     144: ifeq          157
     147: invokestatic  #10                 // Method org/apache/axis2/datasource/jaxb/JAXBDSContext.access$200:()Lorg/apache/commons/logging/Log;
     150: ldc           #18                 // String Unmarshal Array of non-primitive via BY_CLASS_ARRAY approach
     152: invokeinterface #12,  2           // InterfaceMethod org/apache/commons/logging/Log.debug:(Ljava/lang/Object;)V
     157: aload_0
     158: getfield      #5                  // Field val$reader:Ljavax/xml/stream/XMLStreamReader;
     161: aload_0
     162: getfield      #4                  // Field val$u:Ljavax/xml/bind/Unmarshaller;
     165: aload_0
     166: getfield      #2                  // Field val$type:Ljava/lang/Class;
     169: invokestatic  #19                 // Method org/apache/axis2/datasource/jaxb/JAXBDSContext.access$300:(Ljavax/xml/stream/XMLStreamReader;Ljavax/xml/bind/Unmarshaller;Ljava/lang/Class;)Ljava/lang/Object;
     172: astore_1
     173: goto          381
     176: getstatic     #9                  // Field org/apache/axis2/datasource/jaxb/JAXBDSContext.DEBUG_ENABLED:Z
     179: ifeq          192
     182: invokestatic  #10                 // Method org/apache/axis2/datasource/jaxb/JAXBDSContext.access$200:()Lorg/apache/commons/logging/Log;
     185: ldc           #20                 // String Unmarshal Array
     187: invokeinterface #12,  2           // InterfaceMethod org/apache/commons/logging/Log.debug:(Ljava/lang/Object;)V
     192: aload_0
     193: getfield      #4                  // Field val$u:Ljavax/xml/bind/Unmarshaller;
     196: aload_0
     197: getfield      #5                  // Field val$reader:Ljavax/xml/stream/XMLStreamReader;
     200: aload_0
     201: getfield      #2                  // Field val$type:Ljava/lang/Class;
     204: invokeinterface #13,  3           // InterfaceMethod javax/xml/bind/Unmarshaller.unmarshal:(Ljavax/xml/stream/XMLStreamReader;Ljava/lang/Class;)Ljavax/xml/bind/JAXBElement;
     209: astore_1
     210: goto          381
     213: aload_0
     214: getfield      #2                  // Field val$type:Ljava/lang/Class;
     217: invokevirtual #21                 // Method java/lang/Class.isEnum:()Z
     220: ifeq          312
     223: getstatic     #9                  // Field org/apache/axis2/datasource/jaxb/JAXBDSContext.DEBUG_ENABLED:Z
     226: ifeq          267
     229: invokestatic  #10                 // Method org/apache/axis2/datasource/jaxb/JAXBDSContext.access$200:()Lorg/apache/commons/logging/Log;
     232: new           #22                 // class java/lang/StringBuilder
     235: dup
     236: invokespecial #23                 // Method java/lang/StringBuilder."<init>":()V
     239: ldc           #24                 // String Unmarshalling
     241: invokevirtual #25                 // Method java/lang/StringBuilder.append:(Ljava/lang/String;)Ljava/lang/StringBuilder;
     244: aload_0
     245: getfield      #2                  // Field val$type:Ljava/lang/Class;
     248: invokevirtual #26                 // Method java/lang/Class.getName:()Ljava/lang/String;
     251: invokevirtual #25                 // Method java/lang/StringBuilder.append:(Ljava/lang/String;)Ljava/lang/StringBuilder;
     254: ldc           #27                 // String  as Enum
     256: invokevirtual #25                 // Method java/lang/StringBuilder.append:(Ljava/lang/String;)Ljava/lang/StringBuilder;
     259: invokevirtual #28                 // Method java/lang/StringBuilder.toString:()Ljava/lang/String;
     262: invokeinterface #12,  2           // InterfaceMethod org/apache/commons/logging/Log.debug:(Ljava/lang/Object;)V
     267: aload_0
     268: getfield      #4                  // Field val$u:Ljavax/xml/bind/Unmarshaller;
     271: aload_0
     272: getfield      #5                  // Field val$reader:Ljavax/xml/stream/XMLStreamReader;
     275: aload_0
     276: getfield      #2                  // Field val$type:Ljava/lang/Class;
     279: invokestatic  #29                 // Method org/apache/axis2/jaxws/utility/XmlEnumUtils.getConversionType:(Ljava/lang/Class;)Ljava/lang/Class;
     282: invokeinterface #13,  3           // InterfaceMethod javax/xml/bind/Unmarshaller.unmarshal:(Ljavax/xml/stream/XMLStreamReader;Ljava/lang/Class;)Ljavax/xml/bind/JAXBElement;
     287: astore_2
     288: aload_2
     289: ifnull        307
     292: aload_0
     293: getfield      #2                  // Field val$type:Ljava/lang/Class;
     296: aload_2
     297: invokevirtual #30                 // Method javax/xml/bind/JAXBElement.getValue:()Ljava/lang/Object;
     300: invokestatic  #31                 // Method org/apache/axis2/jaxws/utility/XmlEnumUtils.fromValue:(Ljava/lang/Class;Ljava/lang/Object;)Ljava/lang/Object;
     303: astore_1
     304: goto          309
     307: aconst_null
     308: astore_1
     309: goto          381
     312: getstatic     #9                  // Field org/apache/axis2/datasource/jaxb/JAXBDSContext.DEBUG_ENABLED:Z
     315: ifeq          328
     318: invokestatic  #10                 // Method org/apache/axis2/datasource/jaxb/JAXBDSContext.access$200:()Lorg/apache/commons/logging/Log;
     321: ldc           #32                 // String Unmarshalling normal case (not array, not xsd:list, not enum)
     323: invokeinterface #12,  2           // InterfaceMethod org/apache/commons/logging/Log.debug:(Ljava/lang/Object;)V
     328: aload_0
     329: getfield      #4                  // Field val$u:Ljavax/xml/bind/Unmarshaller;
     332: aload_0
     333: getfield      #5                  // Field val$reader:Ljavax/xml/stream/XMLStreamReader;
     336: aload_0
     337: getfield      #2                  // Field val$type:Ljava/lang/Class;
     340: invokeinterface #13,  3           // InterfaceMethod javax/xml/bind/Unmarshaller.unmarshal:(Ljavax/xml/stream/XMLStreamReader;Ljava/lang/Class;)Ljavax/xml/bind/JAXBElement;
     345: astore_1
     346: goto          381
     349: getstatic     #9                  // Field org/apache/axis2/datasource/jaxb/JAXBDSContext.DEBUG_ENABLED:Z
     352: ifeq          365
     355: invokestatic  #10                 // Method org/apache/axis2/datasource/jaxb/JAXBDSContext.access$200:()Lorg/apache/commons/logging/Log;
     358: ldc           #33                 // String Unmarshalling xsd:list
     360: invokeinterface #12,  2           // InterfaceMethod org/apache/commons/logging/Log.debug:(Ljava/lang/Object;)V
     365: aload_0
     366: getfield      #5                  // Field val$reader:Ljavax/xml/stream/XMLStreamReader;
     369: aload_0
     370: getfield      #4                  // Field val$u:Ljavax/xml/bind/Unmarshaller;
     373: aload_0
     374: getfield      #2                  // Field val$type:Ljava/lang/Class;
     377: invokestatic  #34                 // Method org/apache/axis2/datasource/jaxb/JAXBDSContext.unmarshalAsListOrArray:(Ljavax/xml/stream/XMLStreamReader;Ljavax/xml/bind/Unmarshaller;Ljava/lang/Class;)Ljava/lang/Object;
     380: astore_1
     381: invokestatic  #10                 // Method org/apache/axis2/datasource/jaxb/JAXBDSContext.access$200:()Lorg/apache/commons/logging/Log;
     384: invokeinterface #35,  1           // InterfaceMethod org/apache/commons/logging/Log.isDebugEnabled:()Z
     389: ifeq          542
     392: aload_1
     393: ifnonnull     415
     396: getstatic     #9                  // Field org/apache/axis2/datasource/jaxb/JAXBDSContext.DEBUG_ENABLED:Z
     399: ifeq          542
     402: invokestatic  #10                 // Method org/apache/axis2/datasource/jaxb/JAXBDSContext.access$200:()Lorg/apache/commons/logging/Log;
     405: ldc           #36                 // String End unmarshalByType returning null object
     407: invokeinterface #12,  2           // InterfaceMethod org/apache/commons/logging/Log.debug:(Ljava/lang/Object;)V
     412: goto          542
     415: aload_1
     416: instanceof    #37                 // class javax/xml/bind/JAXBElement
     419: ifeq          506
     422: aload_1
     423: checkcast     #37                 // class javax/xml/bind/JAXBElement
     426: astore_2
     427: getstatic     #9                  // Field org/apache/axis2/datasource/jaxb/JAXBDSContext.DEBUG_ENABLED:Z
     430: ifeq          503
     433: invokestatic  #10                 // Method org/apache/axis2/datasource/jaxb/JAXBDSContext.access$200:()Lorg/apache/commons/logging/Log;
     436: ldc           #38                 // String End unmarshalByType returning JAXBElement
     438: invokeinterface #12,  2           // InterfaceMethod org/apache/commons/logging/Log.debug:(Ljava/lang/Object;)V
     443: invokestatic  #10                 // Method org/apache/axis2/datasource/jaxb/JAXBDSContext.access$200:()Lorg/apache/commons/logging/Log;
     446: new           #22                 // class java/lang/StringBuilder
     449: dup
     450: invokespecial #23                 // Method java/lang/StringBuilder."<init>":()V
     453: ldc           #39                 // String   Class =
     455: invokevirtual #25                 // Method java/lang/StringBuilder.append:(Ljava/lang/String;)Ljava/lang/StringBuilder;
     458: aload_2
     459: invokevirtual #40                 // Method javax/xml/bind/JAXBElement.getDeclaredType:()Ljava/lang/Class;
     462: invokevirtual #41                 // Method java/lang/StringBuilder.append:(Ljava/lang/Object;)Ljava/lang/StringBuilder;
     465: invokevirtual #28                 // Method java/lang/StringBuilder.toString:()Ljava/lang/String;
     468: invokeinterface #12,  2           // InterfaceMethod org/apache/commons/logging/Log.debug:(Ljava/lang/Object;)V
     473: invokestatic  #10                 // Method org/apache/axis2/datasource/jaxb/JAXBDSContext.access$200:()Lorg/apache/commons/logging/Log;
     476: new           #22                 // class java/lang/StringBuilder
     479: dup
     480: invokespecial #23                 // Method java/lang/StringBuilder."<init>":()V
     483: ldc           #42                 // String   QName =
     485: invokevirtual #25                 // Method java/lang/StringBuilder.append:(Ljava/lang/String;)Ljava/lang/StringBuilder;
     488: aload_2
     489: invokevirtual #43                 // Method javax/xml/bind/JAXBElement.getName:()Ljavax/xml/namespace/QName;
     492: invokevirtual #41                 // Method java/lang/StringBuilder.append:(Ljava/lang/Object;)Ljava/lang/StringBuilder;
     495: invokevirtual #28                 // Method java/lang/StringBuilder.toString:()Ljava/lang/String;
     498: invokeinterface #12,  2           // InterfaceMethod org/apache/commons/logging/Log.debug:(Ljava/lang/Object;)V
     503: goto          542
     506: getstatic     #9                  // Field org/apache/axis2/datasource/jaxb/JAXBDSContext.DEBUG_ENABLED:Z
     509: ifeq          542
     512: invokestatic  #10                 // Method org/apache/axis2/datasource/jaxb/JAXBDSContext.access$200:()Lorg/apache/commons/logging/Log;
     515: new           #22                 // class java/lang/StringBuilder
     518: dup
     519: invokespecial #23                 // Method java/lang/StringBuilder."<init>":()V
     522: ldc           #44                 // String End unmarshalByType returning
     524: invokevirtual #25                 // Method java/lang/StringBuilder.append:(Ljava/lang/String;)Ljava/lang/StringBuilder;
     527: aload_1
     528: invokevirtual #45                 // Method java/lang/Object.getClass:()Ljava/lang/Class;
     531: invokevirtual #41                 // Method java/lang/StringBuilder.append:(Ljava/lang/Object;)Ljava/lang/StringBuilder;
     534: invokevirtual #28                 // Method java/lang/StringBuilder.toString:()Ljava/lang/String;
     537: invokeinterface #12,  2           // InterfaceMethod org/apache/commons/logging/Log.debug:(Ljava/lang/Object;)V
     542: aload_1
     543: areturn
     544: astore_1
     545: aload_1
     546: athrow
     547: astore_1
     548: new           #46                 // class org/apache/axiom/om/OMException
     551: dup
     552: aload_1
     553: invokespecial #48                 // Method org/apache/axiom/om/OMException."<init>":(Ljava/lang/Throwable;)V
     556: athrow
    Exception table:
       from    to  target type
           0   543   544   Class org/apache/axiom/om/OMException
           0   543   547   Class java/lang/Throwable
}
