Compiled from "ModifyClusterRequestMarshaller.java"
public class com.amazonaws.services.redshift.model.transform.ModifyClusterRequestMarshaller implements com.amazonaws.transform.Marshaller<com.amazonaws.Request<com.amazonaws.services.redshift.model.ModifyClusterRequest>, com.amazonaws.services.redshift.model.ModifyClusterRequest> {
  public com.amazonaws.services.redshift.model.transform.ModifyClusterRequestMarshaller();
    Code:
       0: aload_0
       1: invokespecial #1                  // Method java/lang/Object."<init>":()V
       4: return

  public com.amazonaws.Request<com.amazonaws.services.redshift.model.ModifyClusterRequest> marshall(com.amazonaws.services.redshift.model.ModifyClusterRequest);
    Code:
       0: aload_1
       1: ifnonnull     14
       4: new           #2                  // class com/amazonaws/AmazonClientException
       7: dup
       8: ldc           #3                  // String Invalid argument passed to marshall(...)
      10: invokespecial #4                  // Method com/amazonaws/AmazonClientException."<init>":(Ljava/lang/String;)V
      13: athrow
      14: new           #5                  // class com/amazonaws/DefaultRequest
      17: dup
      18: aload_1
      19: ldc           #6                  // String AmazonRedshift
      21: invokespecial #7                  // Method com/amazonaws/DefaultRequest."<init>":(Lcom/amazonaws/AmazonWebServiceRequest;Ljava/lang/String;)V
      24: astore_2
      25: aload_2
      26: ldc           #8                  // String Action
      28: ldc           #9                  // String ModifyCluster
      30: invokeinterface #10,  3           // InterfaceMethod com/amazonaws/Request.addParameter:(Ljava/lang/String;Ljava/lang/String;)V
      35: aload_2
      36: ldc           #11                 // String Version
      38: ldc           #12                 // String 2012-12-01
      40: invokeinterface #10,  3           // InterfaceMethod com/amazonaws/Request.addParameter:(Ljava/lang/String;Ljava/lang/String;)V
      45: aload_2
      46: getstatic     #13                 // Field com/amazonaws/http/HttpMethodName.POST:Lcom/amazonaws/http/HttpMethodName;
      49: invokeinterface #14,  2           // InterfaceMethod com/amazonaws/Request.setHttpMethod:(Lcom/amazonaws/http/HttpMethodName;)V
      54: aload_1
      55: invokevirtual #15                 // Method com/amazonaws/services/redshift/model/ModifyClusterRequest.getClusterIdentifier:()Ljava/lang/String;
      58: ifnull        76
      61: aload_2
      62: ldc           #16                 // String ClusterIdentifier
      64: aload_1
      65: invokevirtual #15                 // Method com/amazonaws/services/redshift/model/ModifyClusterRequest.getClusterIdentifier:()Ljava/lang/String;
      68: invokestatic  #17                 // Method com/amazonaws/util/StringUtils.fromString:(Ljava/lang/String;)Ljava/lang/String;
      71: invokeinterface #10,  3           // InterfaceMethod com/amazonaws/Request.addParameter:(Ljava/lang/String;Ljava/lang/String;)V
      76: aload_1
      77: invokevirtual #18                 // Method com/amazonaws/services/redshift/model/ModifyClusterRequest.getClusterType:()Ljava/lang/String;
      80: ifnull        98
      83: aload_2
      84: ldc           #19                 // String ClusterType
      86: aload_1
      87: invokevirtual #18                 // Method com/amazonaws/services/redshift/model/ModifyClusterRequest.getClusterType:()Ljava/lang/String;
      90: invokestatic  #17                 // Method com/amazonaws/util/StringUtils.fromString:(Ljava/lang/String;)Ljava/lang/String;
      93: invokeinterface #10,  3           // InterfaceMethod com/amazonaws/Request.addParameter:(Ljava/lang/String;Ljava/lang/String;)V
      98: aload_1
      99: invokevirtual #20                 // Method com/amazonaws/services/redshift/model/ModifyClusterRequest.getNodeType:()Ljava/lang/String;
     102: ifnull        120
     105: aload_2
     106: ldc           #21                 // String NodeType
     108: aload_1
     109: invokevirtual #20                 // Method com/amazonaws/services/redshift/model/ModifyClusterRequest.getNodeType:()Ljava/lang/String;
     112: invokestatic  #17                 // Method com/amazonaws/util/StringUtils.fromString:(Ljava/lang/String;)Ljava/lang/String;
     115: invokeinterface #10,  3           // InterfaceMethod com/amazonaws/Request.addParameter:(Ljava/lang/String;Ljava/lang/String;)V
     120: aload_1
     121: invokevirtual #22                 // Method com/amazonaws/services/redshift/model/ModifyClusterRequest.getNumberOfNodes:()Ljava/lang/Integer;
     124: ifnull        142
     127: aload_2
     128: ldc           #23                 // String NumberOfNodes
     130: aload_1
     131: invokevirtual #22                 // Method com/amazonaws/services/redshift/model/ModifyClusterRequest.getNumberOfNodes:()Ljava/lang/Integer;
     134: invokestatic  #24                 // Method com/amazonaws/util/StringUtils.fromInteger:(Ljava/lang/Integer;)Ljava/lang/String;
     137: invokeinterface #10,  3           // InterfaceMethod com/amazonaws/Request.addParameter:(Ljava/lang/String;Ljava/lang/String;)V
     142: aload_1
     143: invokevirtual #25                 // Method com/amazonaws/services/redshift/model/ModifyClusterRequest.getClusterSecurityGroups:()Ljava/util/List;
     146: checkcast     #26                 // class com/amazonaws/internal/SdkInternalList
     149: astore_3
     150: aload_3
     151: invokevirtual #27                 // Method com/amazonaws/internal/SdkInternalList.isEmpty:()Z
     154: ifeq          164
     157: aload_3
     158: invokevirtual #28                 // Method com/amazonaws/internal/SdkInternalList.isAutoConstruct:()Z
     161: ifne          237
     164: iconst_1
     165: istore        4
     167: aload_3
     168: invokevirtual #29                 // Method com/amazonaws/internal/SdkInternalList.iterator:()Ljava/util/Iterator;
     171: astore        5
     173: aload         5
     175: invokeinterface #30,  1           // InterfaceMethod java/util/Iterator.hasNext:()Z
     180: ifeq          237
     183: aload         5
     185: invokeinterface #31,  1           // InterfaceMethod java/util/Iterator.next:()Ljava/lang/Object;
     190: checkcast     #32                 // class java/lang/String
     193: astore        6
     195: aload         6
     197: ifnull        231
     200: aload_2
     201: new           #33                 // class java/lang/StringBuilder
     204: dup
     205: invokespecial #34                 // Method java/lang/StringBuilder."<init>":()V
     208: ldc           #35                 // String ClusterSecurityGroups.ClusterSecurityGroupName.
     210: invokevirtual #36                 // Method java/lang/StringBuilder.append:(Ljava/lang/String;)Ljava/lang/StringBuilder;
     213: iload         4
     215: invokevirtual #37                 // Method java/lang/StringBuilder.append:(I)Ljava/lang/StringBuilder;
     218: invokevirtual #38                 // Method java/lang/StringBuilder.toString:()Ljava/lang/String;
     221: aload         6
     223: invokestatic  #17                 // Method com/amazonaws/util/StringUtils.fromString:(Ljava/lang/String;)Ljava/lang/String;
     226: invokeinterface #10,  3           // InterfaceMethod com/amazonaws/Request.addParameter:(Ljava/lang/String;Ljava/lang/String;)V
     231: iinc          4, 1
     234: goto          173
     237: aload_1
     238: invokevirtual #39                 // Method com/amazonaws/services/redshift/model/ModifyClusterRequest.getVpcSecurityGroupIds:()Ljava/util/List;
     241: checkcast     #26                 // class com/amazonaws/internal/SdkInternalList
     244: astore        4
     246: aload         4
     248: invokevirtual #27                 // Method com/amazonaws/internal/SdkInternalList.isEmpty:()Z
     251: ifeq          262
     254: aload         4
     256: invokevirtual #28                 // Method com/amazonaws/internal/SdkInternalList.isAutoConstruct:()Z
     259: ifne          336
     262: iconst_1
     263: istore        5
     265: aload         4
     267: invokevirtual #29                 // Method com/amazonaws/internal/SdkInternalList.iterator:()Ljava/util/Iterator;
     270: astore        6
     272: aload         6
     274: invokeinterface #30,  1           // InterfaceMethod java/util/Iterator.hasNext:()Z
     279: ifeq          336
     282: aload         6
     284: invokeinterface #31,  1           // InterfaceMethod java/util/Iterator.next:()Ljava/lang/Object;
     289: checkcast     #32                 // class java/lang/String
     292: astore        7
     294: aload         7
     296: ifnull        330
     299: aload_2
     300: new           #33                 // class java/lang/StringBuilder
     303: dup
     304: invokespecial #34                 // Method java/lang/StringBuilder."<init>":()V
     307: ldc           #40                 // String VpcSecurityGroupIds.VpcSecurityGroupId.
     309: invokevirtual #36                 // Method java/lang/StringBuilder.append:(Ljava/lang/String;)Ljava/lang/StringBuilder;
     312: iload         5
     314: invokevirtual #37                 // Method java/lang/StringBuilder.append:(I)Ljava/lang/StringBuilder;
     317: invokevirtual #38                 // Method java/lang/StringBuilder.toString:()Ljava/lang/String;
     320: aload         7
     322: invokestatic  #17                 // Method com/amazonaws/util/StringUtils.fromString:(Ljava/lang/String;)Ljava/lang/String;
     325: invokeinterface #10,  3           // InterfaceMethod com/amazonaws/Request.addParameter:(Ljava/lang/String;Ljava/lang/String;)V
     330: iinc          5, 1
     333: goto          272
     336: aload_1
     337: invokevirtual #41                 // Method com/amazonaws/services/redshift/model/ModifyClusterRequest.getMasterUserPassword:()Ljava/lang/String;
     340: ifnull        358
     343: aload_2
     344: ldc           #42                 // String MasterUserPassword
     346: aload_1
     347: invokevirtual #41                 // Method com/amazonaws/services/redshift/model/ModifyClusterRequest.getMasterUserPassword:()Ljava/lang/String;
     350: invokestatic  #17                 // Method com/amazonaws/util/StringUtils.fromString:(Ljava/lang/String;)Ljava/lang/String;
     353: invokeinterface #10,  3           // InterfaceMethod com/amazonaws/Request.addParameter:(Ljava/lang/String;Ljava/lang/String;)V
     358: aload_1
     359: invokevirtual #43                 // Method com/amazonaws/services/redshift/model/ModifyClusterRequest.getClusterParameterGroupName:()Ljava/lang/String;
     362: ifnull        380
     365: aload_2
     366: ldc           #44                 // String ClusterParameterGroupName
     368: aload_1
     369: invokevirtual #43                 // Method com/amazonaws/services/redshift/model/ModifyClusterRequest.getClusterParameterGroupName:()Ljava/lang/String;
     372: invokestatic  #17                 // Method com/amazonaws/util/StringUtils.fromString:(Ljava/lang/String;)Ljava/lang/String;
     375: invokeinterface #10,  3           // InterfaceMethod com/amazonaws/Request.addParameter:(Ljava/lang/String;Ljava/lang/String;)V
     380: aload_1
     381: invokevirtual #45                 // Method com/amazonaws/services/redshift/model/ModifyClusterRequest.getAutomatedSnapshotRetentionPeriod:()Ljava/lang/Integer;
     384: ifnull        402
     387: aload_2
     388: ldc           #46                 // String AutomatedSnapshotRetentionPeriod
     390: aload_1
     391: invokevirtual #45                 // Method com/amazonaws/services/redshift/model/ModifyClusterRequest.getAutomatedSnapshotRetentionPeriod:()Ljava/lang/Integer;
     394: invokestatic  #24                 // Method com/amazonaws/util/StringUtils.fromInteger:(Ljava/lang/Integer;)Ljava/lang/String;
     397: invokeinterface #10,  3           // InterfaceMethod com/amazonaws/Request.addParameter:(Ljava/lang/String;Ljava/lang/String;)V
     402: aload_1
     403: invokevirtual #47                 // Method com/amazonaws/services/redshift/model/ModifyClusterRequest.getPreferredMaintenanceWindow:()Ljava/lang/String;
     406: ifnull        424
     409: aload_2
     410: ldc           #48                 // String PreferredMaintenanceWindow
     412: aload_1
     413: invokevirtual #47                 // Method com/amazonaws/services/redshift/model/ModifyClusterRequest.getPreferredMaintenanceWindow:()Ljava/lang/String;
     416: invokestatic  #17                 // Method com/amazonaws/util/StringUtils.fromString:(Ljava/lang/String;)Ljava/lang/String;
     419: invokeinterface #10,  3           // InterfaceMethod com/amazonaws/Request.addParameter:(Ljava/lang/String;Ljava/lang/String;)V
     424: aload_1
     425: invokevirtual #49                 // Method com/amazonaws/services/redshift/model/ModifyClusterRequest.getClusterVersion:()Ljava/lang/String;
     428: ifnull        446
     431: aload_2
     432: ldc           #50                 // String ClusterVersion
     434: aload_1
     435: invokevirtual #49                 // Method com/amazonaws/services/redshift/model/ModifyClusterRequest.getClusterVersion:()Ljava/lang/String;
     438: invokestatic  #17                 // Method com/amazonaws/util/StringUtils.fromString:(Ljava/lang/String;)Ljava/lang/String;
     441: invokeinterface #10,  3           // InterfaceMethod com/amazonaws/Request.addParameter:(Ljava/lang/String;Ljava/lang/String;)V
     446: aload_1
     447: invokevirtual #51                 // Method com/amazonaws/services/redshift/model/ModifyClusterRequest.getAllowVersionUpgrade:()Ljava/lang/Boolean;
     450: ifnull        468
     453: aload_2
     454: ldc           #52                 // String AllowVersionUpgrade
     456: aload_1
     457: invokevirtual #51                 // Method com/amazonaws/services/redshift/model/ModifyClusterRequest.getAllowVersionUpgrade:()Ljava/lang/Boolean;
     460: invokestatic  #53                 // Method com/amazonaws/util/StringUtils.fromBoolean:(Ljava/lang/Boolean;)Ljava/lang/String;
     463: invokeinterface #10,  3           // InterfaceMethod com/amazonaws/Request.addParameter:(Ljava/lang/String;Ljava/lang/String;)V
     468: aload_1
     469: invokevirtual #54                 // Method com/amazonaws/services/redshift/model/ModifyClusterRequest.getHsmClientCertificateIdentifier:()Ljava/lang/String;
     472: ifnull        490
     475: aload_2
     476: ldc           #55                 // String HsmClientCertificateIdentifier
     478: aload_1
     479: invokevirtual #54                 // Method com/amazonaws/services/redshift/model/ModifyClusterRequest.getHsmClientCertificateIdentifier:()Ljava/lang/String;
     482: invokestatic  #17                 // Method com/amazonaws/util/StringUtils.fromString:(Ljava/lang/String;)Ljava/lang/String;
     485: invokeinterface #10,  3           // InterfaceMethod com/amazonaws/Request.addParameter:(Ljava/lang/String;Ljava/lang/String;)V
     490: aload_1
     491: invokevirtual #56                 // Method com/amazonaws/services/redshift/model/ModifyClusterRequest.getHsmConfigurationIdentifier:()Ljava/lang/String;
     494: ifnull        512
     497: aload_2
     498: ldc           #57                 // String HsmConfigurationIdentifier
     500: aload_1
     501: invokevirtual #56                 // Method com/amazonaws/services/redshift/model/ModifyClusterRequest.getHsmConfigurationIdentifier:()Ljava/lang/String;
     504: invokestatic  #17                 // Method com/amazonaws/util/StringUtils.fromString:(Ljava/lang/String;)Ljava/lang/String;
     507: invokeinterface #10,  3           // InterfaceMethod com/amazonaws/Request.addParameter:(Ljava/lang/String;Ljava/lang/String;)V
     512: aload_1
     513: invokevirtual #58                 // Method com/amazonaws/services/redshift/model/ModifyClusterRequest.getNewClusterIdentifier:()Ljava/lang/String;
     516: ifnull        534
     519: aload_2
     520: ldc           #59                 // String NewClusterIdentifier
     522: aload_1
     523: invokevirtual #58                 // Method com/amazonaws/services/redshift/model/ModifyClusterRequest.getNewClusterIdentifier:()Ljava/lang/String;
     526: invokestatic  #17                 // Method com/amazonaws/util/StringUtils.fromString:(Ljava/lang/String;)Ljava/lang/String;
     529: invokeinterface #10,  3           // InterfaceMethod com/amazonaws/Request.addParameter:(Ljava/lang/String;Ljava/lang/String;)V
     534: aload_1
     535: invokevirtual #60                 // Method com/amazonaws/services/redshift/model/ModifyClusterRequest.getPubliclyAccessible:()Ljava/lang/Boolean;
     538: ifnull        556
     541: aload_2
     542: ldc           #61                 // String PubliclyAccessible
     544: aload_1
     545: invokevirtual #60                 // Method com/amazonaws/services/redshift/model/ModifyClusterRequest.getPubliclyAccessible:()Ljava/lang/Boolean;
     548: invokestatic  #53                 // Method com/amazonaws/util/StringUtils.fromBoolean:(Ljava/lang/Boolean;)Ljava/lang/String;
     551: invokeinterface #10,  3           // InterfaceMethod com/amazonaws/Request.addParameter:(Ljava/lang/String;Ljava/lang/String;)V
     556: aload_1
     557: invokevirtual #62                 // Method com/amazonaws/services/redshift/model/ModifyClusterRequest.getElasticIp:()Ljava/lang/String;
     560: ifnull        578
     563: aload_2
     564: ldc           #63                 // String ElasticIp
     566: aload_1
     567: invokevirtual #62                 // Method com/amazonaws/services/redshift/model/ModifyClusterRequest.getElasticIp:()Ljava/lang/String;
     570: invokestatic  #17                 // Method com/amazonaws/util/StringUtils.fromString:(Ljava/lang/String;)Ljava/lang/String;
     573: invokeinterface #10,  3           // InterfaceMethod com/amazonaws/Request.addParameter:(Ljava/lang/String;Ljava/lang/String;)V
     578: aload_2
     579: areturn

  public java.lang.Object marshall(java.lang.Object) throws java.lang.Exception;
    Code:
       0: aload_0
       1: aload_1
       2: checkcast     #64                 // class com/amazonaws/services/redshift/model/ModifyClusterRequest
       5: invokevirtual #65                 // Method marshall:(Lcom/amazonaws/services/redshift/model/ModifyClusterRequest;)Lcom/amazonaws/Request;
       8: areturn
}
