Compiled from "ConfigurationMap.java"
final class org.apache.commons.configuration.ConfigurationMap$ConfigurationSet$Entry implements java.util.Map$Entry<java.lang.Object, java.lang.Object> {
  private java.lang.Object key;

  final org.apache.commons.configuration.ConfigurationMap$ConfigurationSet this$0;

  private org.apache.commons.configuration.ConfigurationMap$ConfigurationSet$Entry(org.apache.commons.configuration.ConfigurationMap$ConfigurationSet, java.lang.Object);
    Code:
       0: aload_0
       1: aload_1
       2: putfield      #2                  // Field this$0:Lorg/apache/commons/configuration/ConfigurationMap$ConfigurationSet;
       5: aload_0
       6: invokespecial #3                  // Method java/lang/Object."<init>":()V
       9: aload_0
      10: aload_2
      11: putfield      #4                  // Field key:Ljava/lang/Object;
      14: return

  public java.lang.Object getKey();
    Code:
       0: aload_0
       1: getfield      #4                  // Field key:Ljava/lang/Object;
       4: areturn

  public java.lang.Object getValue();
    Code:
       0: aload_0
       1: getfield      #2                  // Field this$0:Lorg/apache/commons/configuration/ConfigurationMap$ConfigurationSet;
       4: invokestatic  #5                  // Method org/apache/commons/configuration/ConfigurationMap$ConfigurationSet.access$000:(Lorg/apache/commons/configuration/ConfigurationMap$ConfigurationSet;)Lorg/apache/commons/configuration/Configuration;
       7: aload_0
       8: getfield      #4                  // Field key:Ljava/lang/Object;
      11: checkcast     #6                  // class java/lang/String
      14: invokeinterface #7,  2            // InterfaceMethod org/apache/commons/configuration/Configuration.getProperty:(Ljava/lang/String;)Ljava/lang/Object;
      19: areturn

  public java.lang.Object setValue(java.lang.Object);
    Code:
       0: aload_0
       1: invokevirtual #8                  // Method getValue:()Ljava/lang/Object;
       4: astore_2
       5: aload_0
       6: getfield      #2                  // Field this$0:Lorg/apache/commons/configuration/ConfigurationMap$ConfigurationSet;
       9: invokestatic  #5                  // Method org/apache/commons/configuration/ConfigurationMap$ConfigurationSet.access$000:(Lorg/apache/commons/configuration/ConfigurationMap$ConfigurationSet;)Lorg/apache/commons/configuration/Configuration;
      12: aload_0
      13: getfield      #4                  // Field key:Ljava/lang/Object;
      16: checkcast     #6                  // class java/lang/String
      19: aload_1
      20: invokeinterface #9,  3            // InterfaceMethod org/apache/commons/configuration/Configuration.setProperty:(Ljava/lang/String;Ljava/lang/Object;)V
      25: aload_2
      26: areturn

  org.apache.commons.configuration.ConfigurationMap$ConfigurationSet$Entry(org.apache.commons.configuration.ConfigurationMap$ConfigurationSet, java.lang.Object, org.apache.commons.configuration.ConfigurationMap$1);
    Code:
       0: aload_0
       1: aload_1
       2: aload_2
       3: invokespecial #1                  // Method "<init>":(Lorg/apache/commons/configuration/ConfigurationMap$ConfigurationSet;Ljava/lang/Object;)V
       6: return
}
