Compiled from "DefaultConfigurationBuilder.java"
class org.apache.commons.configuration.DefaultConfigurationBuilder$ConfigurationBuilderProvider extends org.apache.commons.configuration.DefaultConfigurationBuilder$ConfigurationProvider {
  public org.apache.commons.configuration.DefaultConfigurationBuilder$ConfigurationBuilderProvider();
    Code:
       0: aload_0
       1: ldc_w         #1                  // class org/apache/commons/configuration/DefaultConfigurationBuilder
       4: invokespecial #2                  // Method org/apache/commons/configuration/DefaultConfigurationBuilder$ConfigurationProvider."<init>":(Ljava/lang/Class;)V
       7: return

  public org.apache.commons.configuration.AbstractConfiguration getConfiguration(org.apache.commons.configuration.DefaultConfigurationBuilder$ConfigurationDeclaration) throws java.lang.Exception;
    Code:
       0: aload_0
       1: aload_1
       2: invokespecial #3                  // Method org/apache/commons/configuration/DefaultConfigurationBuilder$ConfigurationProvider.getConfiguration:(Lorg/apache/commons/configuration/DefaultConfigurationBuilder$ConfigurationDeclaration;)Lorg/apache/commons/configuration/AbstractConfiguration;
       5: checkcast     #1                  // class org/apache/commons/configuration/DefaultConfigurationBuilder
       8: astore_2
       9: aload_2
      10: iconst_1
      11: invokevirtual #4                  // Method org/apache/commons/configuration/DefaultConfigurationBuilder.getConfiguration:(Z)Lorg/apache/commons/configuration/CombinedConfiguration;
      14: areturn

  public org.apache.commons.configuration.AbstractConfiguration getEmptyConfiguration(org.apache.commons.configuration.DefaultConfigurationBuilder$ConfigurationDeclaration) throws java.lang.Exception;
    Code:
       0: new           #5                  // class org/apache/commons/configuration/CombinedConfiguration
       3: dup
       4: invokespecial #6                  // Method org/apache/commons/configuration/CombinedConfiguration."<init>":()V
       7: areturn

  protected void initBeanInstance(java.lang.Object, org.apache.commons.configuration.beanutils.BeanDeclaration) throws java.lang.Exception;
    Code:
       0: aload_2
       1: checkcast     #7                  // class org/apache/commons/configuration/DefaultConfigurationBuilder$ConfigurationDeclaration
       4: astore_3
       5: aload_3
       6: invokevirtual #8                  // Method org/apache/commons/configuration/DefaultConfigurationBuilder$ConfigurationDeclaration.getConfigurationBuilder:()Lorg/apache/commons/configuration/DefaultConfigurationBuilder;
       9: aload_1
      10: checkcast     #1                  // class org/apache/commons/configuration/DefaultConfigurationBuilder
      13: invokestatic  #9                  // Method initChildBuilder:(Lorg/apache/commons/configuration/DefaultConfigurationBuilder;Lorg/apache/commons/configuration/DefaultConfigurationBuilder;)V
      16: aload_0
      17: aload_1
      18: aload_2
      19: invokespecial #10                 // Method org/apache/commons/configuration/DefaultConfigurationBuilder$ConfigurationProvider.initBeanInstance:(Ljava/lang/Object;Lorg/apache/commons/configuration/beanutils/BeanDeclaration;)V
      22: return

  private static void initChildBuilder(org.apache.commons.configuration.DefaultConfigurationBuilder, org.apache.commons.configuration.DefaultConfigurationBuilder);
    Code:
       0: aload_1
       1: aload_0
       2: invokevirtual #11                 // Method org/apache/commons/configuration/DefaultConfigurationBuilder.isAttributeSplittingDisabled:()Z
       5: invokevirtual #12                 // Method org/apache/commons/configuration/DefaultConfigurationBuilder.setAttributeSplittingDisabled:(Z)V
       8: aload_1
       9: aload_0
      10: invokevirtual #13                 // Method org/apache/commons/configuration/DefaultConfigurationBuilder.getBasePath:()Ljava/lang/String;
      13: invokevirtual #14                 // Method org/apache/commons/configuration/DefaultConfigurationBuilder.setBasePath:(Ljava/lang/String;)V
      16: aload_1
      17: aload_0
      18: invokevirtual #15                 // Method org/apache/commons/configuration/DefaultConfigurationBuilder.isDelimiterParsingDisabled:()Z
      21: invokevirtual #16                 // Method org/apache/commons/configuration/DefaultConfigurationBuilder.setDelimiterParsingDisabled:(Z)V
      24: aload_1
      25: aload_0
      26: invokevirtual #17                 // Method org/apache/commons/configuration/DefaultConfigurationBuilder.getListDelimiter:()C
      29: invokevirtual #18                 // Method org/apache/commons/configuration/DefaultConfigurationBuilder.setListDelimiter:(C)V
      32: aload_1
      33: aload_0
      34: invokevirtual #19                 // Method org/apache/commons/configuration/DefaultConfigurationBuilder.isThrowExceptionOnMissing:()Z
      37: invokevirtual #20                 // Method org/apache/commons/configuration/DefaultConfigurationBuilder.setThrowExceptionOnMissing:(Z)V
      40: aload_1
      41: aload_0
      42: invokevirtual #21                 // Method org/apache/commons/configuration/DefaultConfigurationBuilder.getLogger:()Lorg/apache/commons/logging/Log;
      45: invokevirtual #22                 // Method org/apache/commons/configuration/DefaultConfigurationBuilder.setLogger:(Lorg/apache/commons/logging/Log;)V
      48: aload_1
      49: invokevirtual #23                 // Method org/apache/commons/configuration/DefaultConfigurationBuilder.clearConfigurationListeners:()V
      52: aload_0
      53: invokevirtual #24                 // Method org/apache/commons/configuration/DefaultConfigurationBuilder.getConfigurationListeners:()Ljava/util/Collection;
      56: invokeinterface #25,  1           // InterfaceMethod java/util/Collection.iterator:()Ljava/util/Iterator;
      61: astore_2
      62: aload_2
      63: invokeinterface #26,  1           // InterfaceMethod java/util/Iterator.hasNext:()Z
      68: ifeq          89
      71: aload_2
      72: invokeinterface #27,  1           // InterfaceMethod java/util/Iterator.next:()Ljava/lang/Object;
      77: checkcast     #28                 // class org/apache/commons/configuration/event/ConfigurationListener
      80: astore_3
      81: aload_1
      82: aload_3
      83: invokevirtual #29                 // Method org/apache/commons/configuration/DefaultConfigurationBuilder.addConfigurationListener:(Lorg/apache/commons/configuration/event/ConfigurationListener;)V
      86: goto          62
      89: aload_1
      90: invokevirtual #30                 // Method org/apache/commons/configuration/DefaultConfigurationBuilder.clearErrorListeners:()V
      93: aload_0
      94: invokevirtual #31                 // Method org/apache/commons/configuration/DefaultConfigurationBuilder.getErrorListeners:()Ljava/util/Collection;
      97: invokeinterface #25,  1           // InterfaceMethod java/util/Collection.iterator:()Ljava/util/Iterator;
     102: astore_2
     103: aload_2
     104: invokeinterface #26,  1           // InterfaceMethod java/util/Iterator.hasNext:()Z
     109: ifeq          130
     112: aload_2
     113: invokeinterface #27,  1           // InterfaceMethod java/util/Iterator.next:()Ljava/lang/Object;
     118: checkcast     #32                 // class org/apache/commons/configuration/event/ConfigurationErrorListener
     121: astore_3
     122: aload_1
     123: aload_3
     124: invokevirtual #33                 // Method org/apache/commons/configuration/DefaultConfigurationBuilder.addErrorListener:(Lorg/apache/commons/configuration/event/ConfigurationErrorListener;)V
     127: goto          103
     130: return
}
