Compiled from "TreeConstructor.java"
class org.biojava.nbio.phylo.TreeConstructor$1 {
  static final int[] $SwitchMap$org$biojava$nbio$phylo$TreeConstructorType;

  static {};
    Code:
       0: invokestatic  #1                  // Method org/biojava/nbio/phylo/TreeConstructorType.values:()[Lorg/biojava/nbio/phylo/TreeConstructorType;
       3: arraylength
       4: newarray       int
       6: putstatic     #2                  // Field $SwitchMap$org$biojava$nbio$phylo$TreeConstructorType:[I
       9: getstatic     #2                  // Field $SwitchMap$org$biojava$nbio$phylo$TreeConstructorType:[I
      12: getstatic     #3                  // Field org/biojava/nbio/phylo/TreeConstructorType.NJ:Lorg/biojava/nbio/phylo/TreeConstructorType;
      15: invokevirtual #4                  // Method org/biojava/nbio/phylo/TreeConstructorType.ordinal:()I
      18: iconst_1
      19: iastore
      20: goto          24
      23: astore_0
      24: return
    Exception table:
       from    to  target type
           9    20    23   Class java/lang/NoSuchFieldError
}
