Compiled from "MappingStartEvent.java"
public final class nl.basjes.shaded.org.yaml.snakeyaml.events.MappingStartEvent extends nl.basjes.shaded.org.yaml.snakeyaml.events.CollectionStartEvent {
  public nl.basjes.shaded.org.yaml.snakeyaml.events.MappingStartEvent(java.lang.String, java.lang.String, boolean, nl.basjes.shaded.org.yaml.snakeyaml.error.Mark, nl.basjes.shaded.org.yaml.snakeyaml.error.Mark, nl.basjes.shaded.org.yaml.snakeyaml.DumperOptions$FlowStyle);
    Code:
       0: aload_0
       1: aload_1
       2: aload_2
       3: iload_3
       4: aload         4
       6: aload         5
       8: aload         6
      10: invokespecial #19                 // Method nl/basjes/shaded/org/yaml/snakeyaml/events/CollectionStartEvent."<init>":(Ljava/lang/String;Ljava/lang/String;ZLnl/basjes/shaded/org/yaml/snakeyaml/error/Mark;Lnl/basjes/shaded/org/yaml/snakeyaml/error/Mark;Lnl/basjes/shaded/org/yaml/snakeyaml/DumperOptions$FlowStyle;)V
      13: return

  public nl.basjes.shaded.org.yaml.snakeyaml.events.MappingStartEvent(java.lang.String, java.lang.String, boolean, nl.basjes.shaded.org.yaml.snakeyaml.error.Mark, nl.basjes.shaded.org.yaml.snakeyaml.error.Mark, java.lang.Boolean);
    Code:
       0: aload_0
       1: aload_1
       2: aload_2
       3: iload_3
       4: aload         4
       6: aload         5
       8: aload         6
      10: invokestatic  #37                 // Method nl/basjes/shaded/org/yaml/snakeyaml/DumperOptions$FlowStyle.fromBoolean:(Ljava/lang/Boolean;)Lnl/basjes/shaded/org/yaml/snakeyaml/DumperOptions$FlowStyle;
      13: invokespecial #38                 // Method "<init>":(Ljava/lang/String;Ljava/lang/String;ZLnl/basjes/shaded/org/yaml/snakeyaml/error/Mark;Lnl/basjes/shaded/org/yaml/snakeyaml/error/Mark;Lnl/basjes/shaded/org/yaml/snakeyaml/DumperOptions$FlowStyle;)V
      16: return

  public nl.basjes.shaded.org.yaml.snakeyaml.events.Event$ID getEventId();
    Code:
       0: getstatic     #45                 // Field nl/basjes/shaded/org/yaml/snakeyaml/events/Event$ID.MappingStart:Lnl/basjes/shaded/org/yaml/snakeyaml/events/Event$ID;
       3: areturn
}
