Compiled from "AuditNotificationReceiver.java"
public class org.wildfly.extension.undertow.security.AuditNotificationReceiver implements io.undertow.security.api.NotificationReceiver {
  private final org.jboss.security.audit.AuditManager auditManager;

  public org.wildfly.extension.undertow.security.AuditNotificationReceiver(org.jboss.security.audit.AuditManager);
    Code:
       0: aload_0
       1: invokespecial #1                  // Method java/lang/Object."<init>":()V
       4: aload_0
       5: aload_1
       6: putfield      #2                  // Field auditManager:Lorg/jboss/security/audit/AuditManager;
       9: return

  public void handleNotification(io.undertow.security.api.SecurityNotification);
    Code:
       0: aload_1
       1: invokevirtual #3                  // Method io/undertow/security/api/SecurityNotification.getEventType:()Lio/undertow/security/api/SecurityNotification$EventType;
       4: astore_2
       5: aload_2
       6: getstatic     #4                  // Field io/undertow/security/api/SecurityNotification$EventType.AUTHENTICATED:Lio/undertow/security/api/SecurityNotification$EventType;
       9: if_acmpeq     19
      12: aload_2
      13: getstatic     #5                  // Field io/undertow/security/api/SecurityNotification$EventType.FAILED_AUTHENTICATION:Lio/undertow/security/api/SecurityNotification$EventType;
      16: if_acmpne     183
      19: new           #6                  // class org/jboss/security/audit/AuditEvent
      22: dup
      23: aload_2
      24: getstatic     #4                  // Field io/undertow/security/api/SecurityNotification$EventType.AUTHENTICATED:Lio/undertow/security/api/SecurityNotification$EventType;
      27: if_acmpne     35
      30: ldc           #7                  // String Success
      32: goto          37
      35: ldc           #8                  // String Failure
      37: invokespecial #9                  // Method org/jboss/security/audit/AuditEvent."<init>":(Ljava/lang/String;)V
      40: astore_3
      41: new           #10                 // class java/util/HashMap
      44: dup
      45: invokespecial #11                 // Method java/util/HashMap."<init>":()V
      48: astore        4
      50: aload_1
      51: invokevirtual #12                 // Method io/undertow/security/api/SecurityNotification.getAccount:()Lio/undertow/security/idm/Account;
      54: astore        5
      56: aload         5
      58: ifnull        83
      61: aload         4
      63: ldc           #13                 // String principal
      65: aload         5
      67: invokeinterface #14,  1           // InterfaceMethod io/undertow/security/idm/Account.getPrincipal:()Ljava/security/Principal;
      72: invokeinterface #15,  1           // InterfaceMethod java/security/Principal.getName:()Ljava/lang/String;
      77: invokeinterface #16,  3           // InterfaceMethod java/util/Map.put:(Ljava/lang/Object;Ljava/lang/Object;)Ljava/lang/Object;
      82: pop
      83: aload         4
      85: ldc           #17                 // String message
      87: aload_1
      88: invokevirtual #18                 // Method io/undertow/security/api/SecurityNotification.getMessage:()Ljava/lang/String;
      91: invokeinterface #16,  3           // InterfaceMethod java/util/Map.put:(Ljava/lang/Object;Ljava/lang/Object;)Ljava/lang/Object;
      96: pop
      97: aload_1
      98: invokevirtual #19                 // Method io/undertow/security/api/SecurityNotification.getExchange:()Lio/undertow/server/HttpServerExchange;
     101: getstatic     #20                 // Field io/undertow/servlet/handlers/ServletRequestContext.ATTACHMENT_KEY:Lio/undertow/util/AttachmentKey;
     104: invokevirtual #21                 // Method io/undertow/server/HttpServerExchange.getAttachment:(Lio/undertow/util/AttachmentKey;)Ljava/lang/Object;
     107: checkcast     #22                 // class io/undertow/servlet/handlers/ServletRequestContext
     110: astore        6
     112: aload         6
     114: ifnull        150
     117: aload         6
     119: invokevirtual #23                 // Method io/undertow/servlet/handlers/ServletRequestContext.getServletRequest:()Ljavax/servlet/ServletRequest;
     122: astore        7
     124: aload         7
     126: instanceof    #24                 // class javax/servlet/http/HttpServletRequest
     129: ifeq          150
     132: aload         4
     134: ldc           #25                 // String request
     136: aload         7
     138: checkcast     #24                 // class javax/servlet/http/HttpServletRequest
     141: invokestatic  #26                 // Method org/wildfly/extension/undertow/security/WebUtil.deriveUsefulInfo:(Ljavax/servlet/http/HttpServletRequest;)Ljava/lang/String;
     144: invokeinterface #16,  3           // InterfaceMethod java/util/Map.put:(Ljava/lang/Object;Ljava/lang/Object;)Ljava/lang/Object;
     149: pop
     150: aload         4
     152: ldc           #27                 // String Source
     154: aload_0
     155: invokevirtual #28                 // Method java/lang/Object.getClass:()Ljava/lang/Class;
     158: invokevirtual #29                 // Method java/lang/Class.getCanonicalName:()Ljava/lang/String;
     161: invokeinterface #16,  3           // InterfaceMethod java/util/Map.put:(Ljava/lang/Object;Ljava/lang/Object;)Ljava/lang/Object;
     166: pop
     167: aload_3
     168: aload         4
     170: invokevirtual #30                 // Method org/jboss/security/audit/AuditEvent.setContextMap:(Ljava/util/Map;)V
     173: aload_0
     174: getfield      #2                  // Field auditManager:Lorg/jboss/security/audit/AuditManager;
     177: aload_3
     178: invokeinterface #31,  2           // InterfaceMethod org/jboss/security/audit/AuditManager.audit:(Lorg/jboss/security/audit/AuditEvent;)V
     183: return
}
