Compiled from "Configuration.java"
public class org.eclipse.jetty.webapp.Configuration$Wrapper implements org.eclipse.jetty.webapp.Configuration {
  private org.eclipse.jetty.webapp.Configuration delegate;

  public org.eclipse.jetty.webapp.Configuration$Wrapper(org.eclipse.jetty.webapp.Configuration);
    Code:
       0: aload_0
       1: invokespecial #1                  // Method java/lang/Object."<init>":()V
       4: aload_0
       5: aload_1
       6: putfield      #2                  // Field delegate:Lorg/eclipse/jetty/webapp/Configuration;
       9: return

  public org.eclipse.jetty.webapp.Configuration getWrapped();
    Code:
       0: aload_0
       1: getfield      #2                  // Field delegate:Lorg/eclipse/jetty/webapp/Configuration;
       4: areturn

  public void preConfigure(org.eclipse.jetty.webapp.WebAppContext) throws java.lang.Exception;
    Code:
       0: aload_0
       1: getfield      #2                  // Field delegate:Lorg/eclipse/jetty/webapp/Configuration;
       4: aload_1
       5: invokeinterface #3,  2            // InterfaceMethod org/eclipse/jetty/webapp/Configuration.preConfigure:(Lorg/eclipse/jetty/webapp/WebAppContext;)V
      10: return

  public void configure(org.eclipse.jetty.webapp.WebAppContext) throws java.lang.Exception;
    Code:
       0: aload_0
       1: getfield      #2                  // Field delegate:Lorg/eclipse/jetty/webapp/Configuration;
       4: aload_1
       5: invokeinterface #4,  2            // InterfaceMethod org/eclipse/jetty/webapp/Configuration.configure:(Lorg/eclipse/jetty/webapp/WebAppContext;)V
      10: return

  public void postConfigure(org.eclipse.jetty.webapp.WebAppContext) throws java.lang.Exception;
    Code:
       0: aload_0
       1: getfield      #2                  // Field delegate:Lorg/eclipse/jetty/webapp/Configuration;
       4: aload_1
       5: invokeinterface #5,  2            // InterfaceMethod org/eclipse/jetty/webapp/Configuration.postConfigure:(Lorg/eclipse/jetty/webapp/WebAppContext;)V
      10: return

  public void deconfigure(org.eclipse.jetty.webapp.WebAppContext) throws java.lang.Exception;
    Code:
       0: aload_0
       1: getfield      #2                  // Field delegate:Lorg/eclipse/jetty/webapp/Configuration;
       4: aload_1
       5: invokeinterface #6,  2            // InterfaceMethod org/eclipse/jetty/webapp/Configuration.deconfigure:(Lorg/eclipse/jetty/webapp/WebAppContext;)V
      10: return

  public void destroy(org.eclipse.jetty.webapp.WebAppContext) throws java.lang.Exception;
    Code:
       0: aload_0
       1: getfield      #2                  // Field delegate:Lorg/eclipse/jetty/webapp/Configuration;
       4: aload_1
       5: invokeinterface #7,  2            // InterfaceMethod org/eclipse/jetty/webapp/Configuration.destroy:(Lorg/eclipse/jetty/webapp/WebAppContext;)V
      10: return

  public void cloneConfigure(org.eclipse.jetty.webapp.WebAppContext, org.eclipse.jetty.webapp.WebAppContext) throws java.lang.Exception;
    Code:
       0: aload_0
       1: getfield      #2                  // Field delegate:Lorg/eclipse/jetty/webapp/Configuration;
       4: aload_1
       5: aload_2
       6: invokeinterface #8,  3            // InterfaceMethod org/eclipse/jetty/webapp/Configuration.cloneConfigure:(Lorg/eclipse/jetty/webapp/WebAppContext;Lorg/eclipse/jetty/webapp/WebAppContext;)V
      11: return
}
