Compiled from "UserDataElement.java"
public class org.dom4j.util.UserDataElement extends org.dom4j.tree.DefaultElement {
  private java.lang.Object data;

  public org.dom4j.util.UserDataElement(java.lang.String);
    Code:
       0: aload_0
       1: aload_1
       2: invokespecial #1                  // Method org/dom4j/tree/DefaultElement."<init>":(Ljava/lang/String;)V
       5: return

  public org.dom4j.util.UserDataElement(org.dom4j.QName);
    Code:
       0: aload_0
       1: aload_1
       2: invokespecial #2                  // Method org/dom4j/tree/DefaultElement."<init>":(Lorg/dom4j/QName;)V
       5: return

  public java.lang.Object getData();
    Code:
       0: aload_0
       1: getfield      #3                  // Field data:Ljava/lang/Object;
       4: areturn

  public void setData(java.lang.Object);
    Code:
       0: aload_0
       1: aload_1
       2: putfield      #3                  // Field data:Ljava/lang/Object;
       5: return

  public java.lang.String toString();
    Code:
       0: new           #4                  // class java/lang/StringBuilder
       3: dup
       4: invokespecial #5                  // Method java/lang/StringBuilder."<init>":()V
       7: aload_0
       8: invokespecial #6                  // Method org/dom4j/tree/DefaultElement.toString:()Ljava/lang/String;
      11: invokevirtual #7                  // Method java/lang/StringBuilder.append:(Ljava/lang/String;)Ljava/lang/StringBuilder;
      14: ldc           #8                  // String  userData:
      16: invokevirtual #7                  // Method java/lang/StringBuilder.append:(Ljava/lang/String;)Ljava/lang/StringBuilder;
      19: aload_0
      20: getfield      #3                  // Field data:Ljava/lang/Object;
      23: invokevirtual #9                  // Method java/lang/StringBuilder.append:(Ljava/lang/Object;)Ljava/lang/StringBuilder;
      26: invokevirtual #10                 // Method java/lang/StringBuilder.toString:()Ljava/lang/String;
      29: areturn

  public java.lang.Object clone();
    Code:
       0: aload_0
       1: invokespecial #11                 // Method org/dom4j/tree/DefaultElement.clone:()Ljava/lang/Object;
       4: checkcast     #12                 // class org/dom4j/util/UserDataElement
       7: astore_1
       8: aload_1
       9: aload_0
      10: if_acmpeq     21
      13: aload_1
      14: aload_0
      15: invokevirtual #13                 // Method getCopyOfUserData:()Ljava/lang/Object;
      18: putfield      #3                  // Field data:Ljava/lang/Object;
      21: aload_1
      22: areturn

  protected java.lang.Object getCopyOfUserData();
    Code:
       0: aload_0
       1: getfield      #3                  // Field data:Ljava/lang/Object;
       4: areturn

  protected org.dom4j.Element createElement(java.lang.String);
    Code:
       0: aload_0
       1: invokevirtual #14                 // Method getDocumentFactory:()Lorg/dom4j/DocumentFactory;
       4: aload_1
       5: invokevirtual #15                 // Method org/dom4j/DocumentFactory.createElement:(Ljava/lang/String;)Lorg/dom4j/Element;
       8: astore_2
       9: aload_2
      10: aload_0
      11: invokevirtual #13                 // Method getCopyOfUserData:()Ljava/lang/Object;
      14: invokeinterface #16,  2           // InterfaceMethod org/dom4j/Element.setData:(Ljava/lang/Object;)V
      19: aload_2
      20: areturn

  protected org.dom4j.Element createElement(org.dom4j.QName);
    Code:
       0: aload_0
       1: invokevirtual #14                 // Method getDocumentFactory:()Lorg/dom4j/DocumentFactory;
       4: aload_1
       5: invokevirtual #17                 // Method org/dom4j/DocumentFactory.createElement:(Lorg/dom4j/QName;)Lorg/dom4j/Element;
       8: astore_2
       9: aload_2
      10: aload_0
      11: invokevirtual #13                 // Method getCopyOfUserData:()Ljava/lang/Object;
      14: invokeinterface #16,  2           // InterfaceMethod org/dom4j/Element.setData:(Ljava/lang/Object;)V
      19: aload_2
      20: areturn
}
