Compiled from "RumMock.scala"
public final class zio.aws.rum.RumMock$ extends zio.test.mock.Mock<zio.aws.rum.Rum> {
  public static final zio.aws.rum.RumMock$DeleteAppMonitor$ DeleteAppMonitor;

  public static final zio.aws.rum.RumMock$PutRumEvents$ PutRumEvents;

  public static final zio.aws.rum.RumMock$ListAppMonitors$ ListAppMonitors;

  public static final zio.aws.rum.RumMock$ListAppMonitorsPaginated$ ListAppMonitorsPaginated;

  public static final zio.aws.rum.RumMock$UntagResource$ UntagResource;

  public static final zio.aws.rum.RumMock$ListTagsForResource$ ListTagsForResource;

  public static final zio.aws.rum.RumMock$GetAppMonitorData$ GetAppMonitorData;

  public static final zio.aws.rum.RumMock$GetAppMonitorDataPaginated$ GetAppMonitorDataPaginated;

  public static final zio.aws.rum.RumMock$TagResource$ TagResource;

  public static final zio.aws.rum.RumMock$UpdateAppMonitor$ UpdateAppMonitor;

  public static final zio.aws.rum.RumMock$GetAppMonitor$ GetAppMonitor;

  public static final zio.aws.rum.RumMock$CreateAppMonitor$ CreateAppMonitor;

  private static final zio.ZLayer compose;

  public static final zio.aws.rum.RumMock$ MODULE$;

  private zio.aws.rum.RumMock$();
    Code:
       0: aload_0
       1: getstatic     #92                 // Field izumi/reflect/Tag$.MODULE$:Lizumi/reflect/Tag$;
       4: ldc           #94                 // class java/lang/Object
       6: getstatic     #99                 // Field izumi/reflect/macrortti/LightTypeTag$.MODULE$:Lizumi/reflect/macrortti/LightTypeTag$;
       9: ldc           #100                // int -1623495259
      11: ldc           #102                // String \u0004\u0000\u0001\u000fzio.aws.rum.Rum\u0001\u0001
      13: ldc           #104                // String \u0000\u0004\u0004\u0000\u0001\u000fscala.Matchable\u0001\u0001\u0001\u0004\u0000\u0001\tscala.Any\u0001\u0001\u0004\u0000\u0001\u0010java.lang.Object\u0001\u0001\u0002\u0004\u0000\u0001\u0090\u0002\u0001\u0001\u0004\u0000\u0001\u0090\u0003\u0001\u0001\u0004\u0000\u0001\u000fzio.aws.rum.Rum\u0001\u0001\u0002\u0004\u0000\u0001\u0090\u0004\u0001\u0001\u0001\u0000+zio.aws.core.aspects.package$.AspectSupport\u0001\u0000\u0004\u0000\u0001\u0090\u0005\u0001\u0001\u0000\u0002\u0003\u0000\u0001\u001dzio.aws.core.aspects.package$\u0001\u0001\u0001\u0000\u0090\u0006\u0001\u0000\u0004\u0000\u0001\u0090\u0005\u0001\u0001\u0000\u0002\u0003\u0000\u0001\u0090\u0007\u0001\u0001\u0003\u0004\u0000\u0001\u0090\u0002\u0001\u0001\u0004\u0000\u0001\u0090\u0003\u0001\u0001\u0004\u0000\u0001\u0090\u0004\u0001\u0001\u0001\u0000\u0001\u0090\u0005\u0001\u0001\u0004\u0000\u0001\u0090\u0002\u0001\u0001\u0000\u0001\u0090\u0003\u0001\u0001\u0000\u0001\u0090\u0006\u0001\u0002\u0003\u0000\u0001\u0090\u0007\u0001\u0001\u0000\u0001\u0090\u0004\u0001\u0001
      15: bipush        11
      17: invokevirtual #108                // Method izumi/reflect/macrortti/LightTypeTag$.parse:(ILjava/lang/String;Ljava/lang/String;I)Lizumi/reflect/macrortti/LightTypeTag;
      20: invokevirtual #112                // Method izumi/reflect/Tag$.apply:(Ljava/lang/Class;Lizumi/reflect/macrortti/LightTypeTag;)Lizumi/reflect/Tag;
      23: invokespecial #115                // Method zio/test/mock/Mock."<init>":(Lizumi/reflect/Tag;)V
      26: return

  public static {};
    Code:
       0: new           #2                  // class zio/aws/rum/RumMock$
       3: dup
       4: invokespecial #119                // Method "<init>":()V
       7: putstatic     #121                // Field MODULE$:Lzio/aws/rum/RumMock$;
      10: getstatic     #126                // Field zio/ZIO$.MODULE$:Lzio/ZIO$;
      13: getstatic     #92                 // Field izumi/reflect/Tag$.MODULE$:Lizumi/reflect/Tag$;
      16: ldc           #94                 // class java/lang/Object
      18: getstatic     #99                 // Field izumi/reflect/macrortti/LightTypeTag$.MODULE$:Lizumi/reflect/macrortti/LightTypeTag$;
      21: ldc           #127                // int -1374222839
      23: ldc           #129                // String \u0004\u0000\u0001\u0013zio.test.mock.Proxy\u0001\u0001
      25: ldc           #131                // String \u0000\u0003\u0004\u0000\u0001\u000fscala.Matchable\u0001\u0001\u0001\u0004\u0000\u0001\tscala.Any\u0001\u0001\u0004\u0000\u0001\u0010java.lang.Object\u0001\u0001\u0002\u0004\u0000\u0001\u0090\u0002\u0001\u0001\u0004\u0000\u0001\u0090\u0003\u0001\u0001\u0004\u0000\u0001\u0013zio.test.mock.Proxy\u0001\u0001\u0001\u0004\u0000\u0001\u0090\u0004\u0001\u0001\u0001\u0000\u0001\u0090\u0005\u0001\u0001\u0003\u0000\u0001\u0090\u0002\u0001\u0001\u0000\u0001\u0090\u0003\u0001\u0001\u0000\u0001\u0090\u0004\u0001\u0001
      27: bipush        11
      29: invokevirtual #108                // Method izumi/reflect/macrortti/LightTypeTag$.parse:(ILjava/lang/String;Ljava/lang/String;I)Lizumi/reflect/macrortti/LightTypeTag;
      32: invokevirtual #112                // Method izumi/reflect/Tag$.apply:(Ljava/lang/Class;Lizumi/reflect/macrortti/LightTypeTag;)Lizumi/reflect/Tag;
      35: new           #10                 // class zio/aws/rum/RumMock$$anon$1
      38: dup
      39: invokespecial #132                // Method zio/aws/rum/RumMock$$anon$1."<init>":()V
      42: ldc           #134                // String zio.aws.rum.RumMock$.compose.macro(RumMock.scala:88)
      44: invokevirtual #138                // Method zio/ZIO$.service:(Lizumi/reflect/Tag;Lzio/package$IsNotIntersection;Ljava/lang/Object;)Lzio/ZIO;
      47: getstatic     #121                // Field MODULE$:Lzio/aws/rum/RumMock$;
      50: invokedynamic #158,  0            // InvokeDynamic #0:apply:(Lzio/aws/rum/RumMock$;)Lscala/Function1;
      55: ldc           #160                // String zio.aws.rum.RumMock$.compose.macro(RumMock.scala:145)
      57: invokeinterface #166,  3          // InterfaceMethod zio/ZIO.flatMap:(Lscala/Function1;Ljava/lang/Object;)Lzio/ZIO;
      62: getstatic     #92                 // Field izumi/reflect/Tag$.MODULE$:Lizumi/reflect/Tag$;
      65: ldc           #94                 // class java/lang/Object
      67: getstatic     #99                 // Field izumi/reflect/macrortti/LightTypeTag$.MODULE$:Lizumi/reflect/macrortti/LightTypeTag$;
      70: ldc           #100                // int -1623495259
      72: ldc           #102                // String \u0004\u0000\u0001\u000fzio.aws.rum.Rum\u0001\u0001
      74: ldc           #104                // String \u0000\u0004\u0004\u0000\u0001\u000fscala.Matchable\u0001\u0001\u0001\u0004\u0000\u0001\tscala.Any\u0001\u0001\u0004\u0000\u0001\u0010java.lang.Object\u0001\u0001\u0002\u0004\u0000\u0001\u0090\u0002\u0001\u0001\u0004\u0000\u0001\u0090\u0003\u0001\u0001\u0004\u0000\u0001\u000fzio.aws.rum.Rum\u0001\u0001\u0002\u0004\u0000\u0001\u0090\u0004\u0001\u0001\u0001\u0000+zio.aws.core.aspects.package$.AspectSupport\u0001\u0000\u0004\u0000\u0001\u0090\u0005\u0001\u0001\u0000\u0002\u0003\u0000\u0001\u001dzio.aws.core.aspects.package$\u0001\u0001\u0001\u0000\u0090\u0006\u0001\u0000\u0004\u0000\u0001\u0090\u0005\u0001\u0001\u0000\u0002\u0003\u0000\u0001\u0090\u0007\u0001\u0001\u0003\u0004\u0000\u0001\u0090\u0002\u0001\u0001\u0004\u0000\u0001\u0090\u0003\u0001\u0001\u0004\u0000\u0001\u0090\u0004\u0001\u0001\u0001\u0000\u0001\u0090\u0005\u0001\u0001\u0004\u0000\u0001\u0090\u0002\u0001\u0001\u0000\u0001\u0090\u0003\u0001\u0001\u0000\u0001\u0090\u0006\u0001\u0002\u0003\u0000\u0001\u0090\u0007\u0001\u0001\u0000\u0001\u0090\u0004\u0001\u0001
      76: bipush        11
      78: invokevirtual #108                // Method izumi/reflect/macrortti/LightTypeTag$.parse:(ILjava/lang/String;Ljava/lang/String;I)Lizumi/reflect/macrortti/LightTypeTag;
      81: invokevirtual #112                // Method izumi/reflect/Tag$.apply:(Ljava/lang/Class;Lizumi/reflect/macrortti/LightTypeTag;)Lizumi/reflect/Tag;
      84: new           #12                 // class zio/aws/rum/RumMock$$anon$2
      87: dup
      88: invokespecial #167                // Method zio/aws/rum/RumMock$$anon$2."<init>":()V
      91: ldc           #169                // String zio.aws.rum.RumMock$.compose.macro(RumMock.scala:146)
      93: invokeinterface #173,  4          // InterfaceMethod zio/ZIO.toLayer:(Lizumi/reflect/Tag;Lzio/package$IsNotIntersection;Ljava/lang/Object;)Lzio/ZLayer;
      98: putstatic     #175                // Field compose:Lzio/ZLayer;
     101: return

  private java.lang.Object writeReplace();
    Code:
       0: new           #179                // class scala/runtime/ModuleSerializationProxy
       3: dup
       4: ldc           #2                  // class zio/aws/rum/RumMock$
       6: invokespecial #182                // Method scala/runtime/ModuleSerializationProxy."<init>":(Ljava/lang/Class;)V
       9: areturn

  public zio.ZLayer compose();
    Code:
       0: getstatic     #175                // Field compose:Lzio/ZLayer;
       3: areturn

  private final zio.aws.rum.Rum $init$$$anonfun$2$$anonfun$1(zio.test.mock.Proxy, zio.Runtime);
    Code:
       0: new           #14                 // class zio/aws/rum/RumMock$$anon$3
       3: dup
       4: aload_1
       5: aload_2
       6: invokespecial #190                // Method zio/aws/rum/RumMock$$anon$3."<init>":(Lzio/test/mock/Proxy;Lzio/Runtime;)V
       9: areturn

  private final zio.ZIO $init$$$anonfun$1(zio.test.mock.Proxy);
    Code:
       0: aload_0
       1: ldc           #195                // String zio.aws.rum.RumMock$.compose.macro(RumMock.scala:90)
       3: invokevirtual #199                // Method withRuntime:(Ljava/lang/Object;)Lzio/ZIO;
       6: aload_0
       7: aload_1
       8: invokedynamic #207,  0            // InvokeDynamic #1:apply:(Lzio/aws/rum/RumMock$;Lzio/test/mock/Proxy;)Lscala/Function1;
      13: ldc           #209                // String zio.aws.rum.RumMock$.compose.macro(RumMock.scala:144)
      15: invokeinterface #212,  3          // InterfaceMethod zio/ZIO.map:(Lscala/Function1;Ljava/lang/Object;)Lzio/ZIO;
      20: areturn

  private static java.lang.Object $deserializeLambda$(java.lang.invoke.SerializedLambda);
    Code:
       0: aload_0
       1: invokedynamic #224,  0            // InvokeDynamic #2:lambdaDeserialize:(Ljava/lang/invoke/SerializedLambda;)Ljava/lang/Object;
       6: areturn
}
