Compiled from "AsWrapperTypeDeserializer.java"
public class org.codehaus.jackson.map.jsontype.impl.AsWrapperTypeDeserializer extends org.codehaus.jackson.map.jsontype.impl.TypeDeserializerBase {
  public org.codehaus.jackson.map.jsontype.impl.AsWrapperTypeDeserializer(org.codehaus.jackson.type.JavaType, org.codehaus.jackson.map.jsontype.TypeIdResolver, org.codehaus.jackson.map.BeanProperty);
    Code:
       0: aload_0
       1: aload_1
       2: aload_2
       3: aload_3
       4: aconst_null
       5: invokespecial #1                  // Method "<init>":(Lorg/codehaus/jackson/type/JavaType;Lorg/codehaus/jackson/map/jsontype/TypeIdResolver;Lorg/codehaus/jackson/map/BeanProperty;Ljava/lang/Class;)V
       8: return

  public org.codehaus.jackson.map.jsontype.impl.AsWrapperTypeDeserializer(org.codehaus.jackson.type.JavaType, org.codehaus.jackson.map.jsontype.TypeIdResolver, org.codehaus.jackson.map.BeanProperty, java.lang.Class<?>);
    Code:
       0: aload_0
       1: aload_1
       2: aload_2
       3: aload_3
       4: aconst_null
       5: invokespecial #2                  // Method org/codehaus/jackson/map/jsontype/impl/TypeDeserializerBase."<init>":(Lorg/codehaus/jackson/type/JavaType;Lorg/codehaus/jackson/map/jsontype/TypeIdResolver;Lorg/codehaus/jackson/map/BeanProperty;Ljava/lang/Class;)V
       8: return

  public org.codehaus.jackson.annotate.JsonTypeInfo$As getTypeInclusion();
    Code:
       0: getstatic     #3                  // Field org/codehaus/jackson/annotate/JsonTypeInfo$As.WRAPPER_OBJECT:Lorg/codehaus/jackson/annotate/JsonTypeInfo$As;
       3: areturn

  public java.lang.Object deserializeTypedFromObject(org.codehaus.jackson.JsonParser, org.codehaus.jackson.map.DeserializationContext) throws java.io.IOException, org.codehaus.jackson.JsonProcessingException;
    Code:
       0: aload_0
       1: aload_1
       2: aload_2
       3: invokespecial #4                  // Method _deserialize:(Lorg/codehaus/jackson/JsonParser;Lorg/codehaus/jackson/map/DeserializationContext;)Ljava/lang/Object;
       6: areturn

  public java.lang.Object deserializeTypedFromArray(org.codehaus.jackson.JsonParser, org.codehaus.jackson.map.DeserializationContext) throws java.io.IOException, org.codehaus.jackson.JsonProcessingException;
    Code:
       0: aload_0
       1: aload_1
       2: aload_2
       3: invokespecial #4                  // Method _deserialize:(Lorg/codehaus/jackson/JsonParser;Lorg/codehaus/jackson/map/DeserializationContext;)Ljava/lang/Object;
       6: areturn

  public java.lang.Object deserializeTypedFromScalar(org.codehaus.jackson.JsonParser, org.codehaus.jackson.map.DeserializationContext) throws java.io.IOException, org.codehaus.jackson.JsonProcessingException;
    Code:
       0: aload_0
       1: aload_1
       2: aload_2
       3: invokespecial #4                  // Method _deserialize:(Lorg/codehaus/jackson/JsonParser;Lorg/codehaus/jackson/map/DeserializationContext;)Ljava/lang/Object;
       6: areturn

  public java.lang.Object deserializeTypedFromAny(org.codehaus.jackson.JsonParser, org.codehaus.jackson.map.DeserializationContext) throws java.io.IOException, org.codehaus.jackson.JsonProcessingException;
    Code:
       0: aload_0
       1: aload_1
       2: aload_2
       3: invokespecial #4                  // Method _deserialize:(Lorg/codehaus/jackson/JsonParser;Lorg/codehaus/jackson/map/DeserializationContext;)Ljava/lang/Object;
       6: areturn

  private final java.lang.Object _deserialize(org.codehaus.jackson.JsonParser, org.codehaus.jackson.map.DeserializationContext) throws java.io.IOException, org.codehaus.jackson.JsonProcessingException;
    Code:
       0: aload_1
       1: invokevirtual #5                  // Method org/codehaus/jackson/JsonParser.getCurrentToken:()Lorg/codehaus/jackson/JsonToken;
       4: getstatic     #6                  // Field org/codehaus/jackson/JsonToken.START_OBJECT:Lorg/codehaus/jackson/JsonToken;
       7: if_acmpeq     41
      10: aload_2
      11: aload_1
      12: getstatic     #6                  // Field org/codehaus/jackson/JsonToken.START_OBJECT:Lorg/codehaus/jackson/JsonToken;
      15: new           #7                  // class java/lang/StringBuilder
      18: dup
      19: invokespecial #8                  // Method java/lang/StringBuilder."<init>":()V
      22: ldc           #9                  // String need JSON Object to contain As.WRAPPER_OBJECT type information for class
      24: invokevirtual #10                 // Method java/lang/StringBuilder.append:(Ljava/lang/String;)Ljava/lang/StringBuilder;
      27: aload_0
      28: invokevirtual #11                 // Method baseTypeName:()Ljava/lang/String;
      31: invokevirtual #10                 // Method java/lang/StringBuilder.append:(Ljava/lang/String;)Ljava/lang/StringBuilder;
      34: invokevirtual #12                 // Method java/lang/StringBuilder.toString:()Ljava/lang/String;
      37: invokevirtual #13                 // Method org/codehaus/jackson/map/DeserializationContext.wrongTokenException:(Lorg/codehaus/jackson/JsonParser;Lorg/codehaus/jackson/JsonToken;Ljava/lang/String;)Lorg/codehaus/jackson/map/JsonMappingException;
      40: athrow
      41: aload_1
      42: invokevirtual #14                 // Method org/codehaus/jackson/JsonParser.nextToken:()Lorg/codehaus/jackson/JsonToken;
      45: getstatic     #15                 // Field org/codehaus/jackson/JsonToken.FIELD_NAME:Lorg/codehaus/jackson/JsonToken;
      48: if_acmpeq     87
      51: aload_2
      52: aload_1
      53: getstatic     #15                 // Field org/codehaus/jackson/JsonToken.FIELD_NAME:Lorg/codehaus/jackson/JsonToken;
      56: new           #7                  // class java/lang/StringBuilder
      59: dup
      60: invokespecial #8                  // Method java/lang/StringBuilder."<init>":()V
      63: ldc           #16                 // String need JSON String that contains type id (for subtype of
      65: invokevirtual #10                 // Method java/lang/StringBuilder.append:(Ljava/lang/String;)Ljava/lang/StringBuilder;
      68: aload_0
      69: invokevirtual #11                 // Method baseTypeName:()Ljava/lang/String;
      72: invokevirtual #10                 // Method java/lang/StringBuilder.append:(Ljava/lang/String;)Ljava/lang/StringBuilder;
      75: ldc           #17                 // String )
      77: invokevirtual #10                 // Method java/lang/StringBuilder.append:(Ljava/lang/String;)Ljava/lang/StringBuilder;
      80: invokevirtual #12                 // Method java/lang/StringBuilder.toString:()Ljava/lang/String;
      83: invokevirtual #13                 // Method org/codehaus/jackson/map/DeserializationContext.wrongTokenException:(Lorg/codehaus/jackson/JsonParser;Lorg/codehaus/jackson/JsonToken;Ljava/lang/String;)Lorg/codehaus/jackson/map/JsonMappingException;
      86: athrow
      87: aload_0
      88: aload_2
      89: aload_1
      90: invokevirtual #18                 // Method org/codehaus/jackson/JsonParser.getText:()Ljava/lang/String;
      93: invokevirtual #19                 // Method _findDeserializer:(Lorg/codehaus/jackson/map/DeserializationContext;Ljava/lang/String;)Lorg/codehaus/jackson/map/JsonDeserializer;
      96: astore_3
      97: aload_1
      98: invokevirtual #14                 // Method org/codehaus/jackson/JsonParser.nextToken:()Lorg/codehaus/jackson/JsonToken;
     101: pop
     102: aload_3
     103: aload_1
     104: aload_2
     105: invokevirtual #20                 // Method org/codehaus/jackson/map/JsonDeserializer.deserialize:(Lorg/codehaus/jackson/JsonParser;Lorg/codehaus/jackson/map/DeserializationContext;)Ljava/lang/Object;
     108: astore        4
     110: aload_1
     111: invokevirtual #14                 // Method org/codehaus/jackson/JsonParser.nextToken:()Lorg/codehaus/jackson/JsonToken;
     114: getstatic     #21                 // Field org/codehaus/jackson/JsonToken.END_OBJECT:Lorg/codehaus/jackson/JsonToken;
     117: if_acmpeq     131
     120: aload_2
     121: aload_1
     122: getstatic     #21                 // Field org/codehaus/jackson/JsonToken.END_OBJECT:Lorg/codehaus/jackson/JsonToken;
     125: ldc           #22                 // String expected closing END_OBJECT after type information and deserialized value
     127: invokevirtual #13                 // Method org/codehaus/jackson/map/DeserializationContext.wrongTokenException:(Lorg/codehaus/jackson/JsonParser;Lorg/codehaus/jackson/JsonToken;Ljava/lang/String;)Lorg/codehaus/jackson/map/JsonMappingException;
     130: athrow
     131: aload         4
     133: areturn
}
