Compiled from "OptionalProxyProtocolDecoder.java"
public class org.apache.pulsar.common.protocol.OptionalProxyProtocolDecoder extends io.netty.channel.ChannelInboundHandlerAdapter {
  public static final java.lang.String NAME;

  public org.apache.pulsar.common.protocol.OptionalProxyProtocolDecoder();
    Code:
       0: aload_0
       1: invokespecial #1                  // Method io/netty/channel/ChannelInboundHandlerAdapter."<init>":()V
       4: return

  public void channelRead(io.netty.channel.ChannelHandlerContext, java.lang.Object) throws java.lang.Exception;
    Code:
       0: aload_2
       1: instanceof    #2                  // class io/netty/buffer/ByteBuf
       4: ifeq          60
       7: aload_2
       8: checkcast     #2                  // class io/netty/buffer/ByteBuf
      11: invokestatic  #3                  // Method io/netty/handler/codec/haproxy/HAProxyMessageDecoder.detectProtocol:(Lio/netty/buffer/ByteBuf;)Lio/netty/handler/codec/ProtocolDetectionResult;
      14: astore_3
      15: aload_3
      16: invokevirtual #4                  // Method io/netty/handler/codec/ProtocolDetectionResult.state:()Lio/netty/handler/codec/ProtocolDetectionState;
      19: getstatic     #5                  // Field io/netty/handler/codec/ProtocolDetectionState.DETECTED:Lio/netty/handler/codec/ProtocolDetectionState;
      22: if_acmpne     60
      25: aload_1
      26: invokeinterface #6,  1            // InterfaceMethod io/netty/channel/ChannelHandlerContext.pipeline:()Lio/netty/channel/ChannelPipeline;
      31: ldc           #8                  // String optional-proxy-protocol-decoder
      33: aconst_null
      34: new           #9                  // class io/netty/handler/codec/haproxy/HAProxyMessageDecoder
      37: dup
      38: invokespecial #10                 // Method io/netty/handler/codec/haproxy/HAProxyMessageDecoder."<init>":()V
      41: invokeinterface #11,  4           // InterfaceMethod io/netty/channel/ChannelPipeline.addAfter:(Ljava/lang/String;Ljava/lang/String;Lio/netty/channel/ChannelHandler;)Lio/netty/channel/ChannelPipeline;
      46: pop
      47: aload_1
      48: invokeinterface #6,  1            // InterfaceMethod io/netty/channel/ChannelHandlerContext.pipeline:()Lio/netty/channel/ChannelPipeline;
      53: aload_0
      54: invokeinterface #12,  2           // InterfaceMethod io/netty/channel/ChannelPipeline.remove:(Lio/netty/channel/ChannelHandler;)Lio/netty/channel/ChannelPipeline;
      59: pop
      60: aload_0
      61: aload_1
      62: aload_2
      63: invokespecial #13                 // Method io/netty/channel/ChannelInboundHandlerAdapter.channelRead:(Lio/netty/channel/ChannelHandlerContext;Ljava/lang/Object;)V
      66: return
}
