Compiled from "JsonPatch.java"
class io.dekorate.deps.zjsonpatch.JsonPatch$1 {
  static final int[] $SwitchMap$io$fabric8$zjsonpatch$Operation;

  static {};
    Code:
       0: invokestatic  #19                 // Method io/dekorate/deps/zjsonpatch/Operation.values:()[Lio/dekorate/deps/zjsonpatch/Operation;
       3: arraylength
       4: newarray       int
       6: putstatic     #21                 // Field $SwitchMap$io$fabric8$zjsonpatch$Operation:[I
       9: getstatic     #21                 // Field $SwitchMap$io$fabric8$zjsonpatch$Operation:[I
      12: getstatic     #25                 // Field io/dekorate/deps/zjsonpatch/Operation.REMOVE:Lio/dekorate/deps/zjsonpatch/Operation;
      15: invokevirtual #29                 // Method io/dekorate/deps/zjsonpatch/Operation.ordinal:()I
      18: iconst_1
      19: iastore
      20: goto          24
      23: astore_0
      24: getstatic     #21                 // Field $SwitchMap$io$fabric8$zjsonpatch$Operation:[I
      27: getstatic     #32                 // Field io/dekorate/deps/zjsonpatch/Operation.REPLACE:Lio/dekorate/deps/zjsonpatch/Operation;
      30: invokevirtual #29                 // Method io/dekorate/deps/zjsonpatch/Operation.ordinal:()I
      33: iconst_2
      34: iastore
      35: goto          39
      38: astore_0
      39: getstatic     #21                 // Field $SwitchMap$io$fabric8$zjsonpatch$Operation:[I
      42: getstatic     #35                 // Field io/dekorate/deps/zjsonpatch/Operation.ADD:Lio/dekorate/deps/zjsonpatch/Operation;
      45: invokevirtual #29                 // Method io/dekorate/deps/zjsonpatch/Operation.ordinal:()I
      48: iconst_3
      49: iastore
      50: goto          54
      53: astore_0
      54: getstatic     #21                 // Field $SwitchMap$io$fabric8$zjsonpatch$Operation:[I
      57: getstatic     #38                 // Field io/dekorate/deps/zjsonpatch/Operation.MOVE:Lio/dekorate/deps/zjsonpatch/Operation;
      60: invokevirtual #29                 // Method io/dekorate/deps/zjsonpatch/Operation.ordinal:()I
      63: iconst_4
      64: iastore
      65: goto          69
      68: astore_0
      69: return
    Exception table:
       from    to  target type
           9    20    23   Class java/lang/NoSuchFieldError
          24    35    38   Class java/lang/NoSuchFieldError
          39    50    53   Class java/lang/NoSuchFieldError
          54    65    68   Class java/lang/NoSuchFieldError
}
