Compiled from "IntroductoryPanel.java"
public class org.protege.editor.owl.ui.explanation.io.IntroductoryPanel extends javax.swing.JPanel {
  private static final long serialVersionUID;

  private org.protege.editor.owl.ui.explanation.io.InconsistentOntologyPlugin selectedPlugin;

  public org.protege.editor.owl.ui.explanation.io.IntroductoryPanel(org.protege.editor.owl.OWLEditorKit, org.protege.editor.owl.ui.explanation.io.InconsistentOntologyPlugin) throws java.io.IOException;
    Code:
       0: aload_0
       1: invokespecial #1                  // Method javax/swing/JPanel."<init>":()V
       4: aload_0
       5: new           #2                  // class java/awt/BorderLayout
       8: dup
       9: invokespecial #3                  // Method java/awt/BorderLayout."<init>":()V
      12: invokevirtual #4                  // Method setLayout:(Ljava/awt/LayoutManager;)V
      15: aload_0
      16: aload_0
      17: aload_1
      18: aload_2
      19: invokespecial #5                  // Method createCenterPanel:(Lorg/protege/editor/owl/OWLEditorKit;Lorg/protege/editor/owl/ui/explanation/io/InconsistentOntologyPlugin;)Ljavax/swing/JPanel;
      22: invokevirtual #6                  // Method add:(Ljava/awt/Component;)Ljava/awt/Component;
      25: pop
      26: return

  private javax.swing.JPanel createCenterPanel(org.protege.editor.owl.OWLEditorKit, org.protege.editor.owl.ui.explanation.io.InconsistentOntologyPlugin) throws java.io.IOException;
    Code:
       0: new           #7                  // class javax/swing/JPanel
       3: dup
       4: invokespecial #1                  // Method javax/swing/JPanel."<init>":()V
       7: astore_3
       8: aload_3
       9: new           #8                  // class javax/swing/BoxLayout
      12: dup
      13: aload_3
      14: iconst_3
      15: invokespecial #9                  // Method javax/swing/BoxLayout."<init>":(Ljava/awt/Container;I)V
      18: invokevirtual #10                 // Method javax/swing/JPanel.setLayout:(Ljava/awt/LayoutManager;)V
      21: new           #11                 // class javax/swing/JTextPane
      24: dup
      25: invokespecial #12                 // Method javax/swing/JTextPane."<init>":()V
      28: astore        4
      30: aload         4
      32: iconst_0
      33: invokevirtual #13                 // Method javax/swing/JTextPane.setEditable:(Z)V
      36: aload_0
      37: invokevirtual #14                 // Method java/lang/Object.getClass:()Ljava/lang/Class;
      40: ldc           #15                 // String /InconsistentOntologyHelp.html
      42: invokevirtual #16                 // Method java/lang/Class.getResource:(Ljava/lang/String;)Ljava/net/URL;
      45: astore        5
      47: aload         4
      49: aload         5
      51: invokevirtual #17                 // Method javax/swing/JTextPane.setPage:(Ljava/net/URL;)V
      54: ldc           #18                 // String TextArea.font
      56: invokestatic  #19                 // Method javax/swing/UIManager.getFont:(Ljava/lang/Object;)Ljava/awt/Font;
      59: astore        6
      61: aload         6
      63: ifnull        125
      66: new           #20                 // class java/lang/StringBuilder
      69: dup
      70: invokespecial #21                 // Method java/lang/StringBuilder."<init>":()V
      73: ldc           #22                 // String body { font-family:
      75: invokevirtual #23                 // Method java/lang/StringBuilder.append:(Ljava/lang/String;)Ljava/lang/StringBuilder;
      78: aload         6
      80: invokevirtual #24                 // Method java/awt/Font.getFamily:()Ljava/lang/String;
      83: invokevirtual #23                 // Method java/lang/StringBuilder.append:(Ljava/lang/String;)Ljava/lang/StringBuilder;
      86: ldc           #25                 // String ; font-size:
      88: invokevirtual #23                 // Method java/lang/StringBuilder.append:(Ljava/lang/String;)Ljava/lang/StringBuilder;
      91: aload         6
      93: invokevirtual #26                 // Method java/awt/Font.getSize:()I
      96: invokevirtual #27                 // Method java/lang/StringBuilder.append:(I)Ljava/lang/StringBuilder;
      99: ldc           #28                 // String pt; }
     101: invokevirtual #23                 // Method java/lang/StringBuilder.append:(Ljava/lang/String;)Ljava/lang/StringBuilder;
     104: invokevirtual #29                 // Method java/lang/StringBuilder.toString:()Ljava/lang/String;
     107: astore        7
     109: aload         4
     111: invokevirtual #30                 // Method javax/swing/JTextPane.getDocument:()Ljavax/swing/text/Document;
     114: checkcast     #31                 // class javax/swing/text/html/HTMLDocument
     117: invokevirtual #32                 // Method javax/swing/text/html/HTMLDocument.getStyleSheet:()Ljavax/swing/text/html/StyleSheet;
     120: aload         7
     122: invokevirtual #33                 // Method javax/swing/text/html/StyleSheet.addRule:(Ljava/lang/String;)V
     125: new           #34                 // class javax/swing/JScrollPane
     128: dup
     129: invokespecial #35                 // Method javax/swing/JScrollPane."<init>":()V
     132: astore        7
     134: aload         7
     136: invokevirtual #36                 // Method javax/swing/JScrollPane.getViewport:()Ljavax/swing/JViewport;
     139: aload         4
     141: invokevirtual #37                 // Method javax/swing/JViewport.add:(Ljava/awt/Component;)Ljava/awt/Component;
     144: pop
     145: aload         7
     147: new           #38                 // class java/awt/Dimension
     150: dup
     151: sipush        480
     154: sipush        300
     157: invokespecial #39                 // Method java/awt/Dimension."<init>":(II)V
     160: invokevirtual #40                 // Method javax/swing/JScrollPane.setPreferredSize:(Ljava/awt/Dimension;)V
     163: aload_3
     164: aload         7
     166: invokevirtual #41                 // Method javax/swing/JPanel.add:(Ljava/awt/Component;)Ljava/awt/Component;
     169: pop
     170: new           #42                 // class org/protege/editor/owl/ui/explanation/io/InconsistentOntologyPluginLoader
     173: dup
     174: aload_1
     175: invokespecial #43                 // Method org/protege/editor/owl/ui/explanation/io/InconsistentOntologyPluginLoader."<init>":(Lorg/protege/editor/owl/OWLEditorKit;)V
     178: astore        8
     180: aload         8
     182: invokevirtual #44                 // Method org/protege/editor/owl/ui/explanation/io/InconsistentOntologyPluginLoader.getPlugins:()Ljava/util/Set;
     185: astore        9
     187: aload         9
     189: invokeinterface #45,  1           // InterfaceMethod java/util/Set.size:()I
     194: iconst_1
     195: if_icmple     373
     198: new           #46                 // class javax/swing/Box
     201: dup
     202: iconst_1
     203: invokespecial #47                 // Method javax/swing/Box."<init>":(I)V
     206: astore        10
     208: aload         10
     210: fconst_0
     211: invokevirtual #48                 // Method javax/swing/Box.setAlignmentX:(F)V
     214: aload         10
     216: ldc           #49                 // String Explanation Plugins
     218: invokestatic  #50                 // Method org/protege/editor/core/ui/util/ComponentFactory.createTitledBorder:(Ljava/lang/String;)Ljavax/swing/border/Border;
     221: invokevirtual #51                 // Method javax/swing/Box.setBorder:(Ljavax/swing/border/Border;)V
     224: new           #52                 // class javax/swing/ButtonGroup
     227: dup
     228: invokespecial #53                 // Method javax/swing/ButtonGroup."<init>":()V
     231: astore        11
     233: iconst_0
     234: istore        12
     236: aload         9
     238: invokeinterface #54,  1           // InterfaceMethod java/util/Set.iterator:()Ljava/util/Iterator;
     243: astore        13
     245: aload         13
     247: invokeinterface #55,  1           // InterfaceMethod java/util/Iterator.hasNext:()Z
     252: ifeq          363
     255: aload         13
     257: invokeinterface #56,  1           // InterfaceMethod java/util/Iterator.next:()Ljava/lang/Object;
     262: checkcast     #57                 // class org/protege/editor/owl/ui/explanation/io/InconsistentOntologyPlugin
     265: astore        14
     267: new           #58                 // class javax/swing/JRadioButton
     270: dup
     271: aload         14
     273: invokevirtual #59                 // Method org/protege/editor/owl/ui/explanation/io/InconsistentOntologyPlugin.getName:()Ljava/lang/String;
     276: invokespecial #60                 // Method javax/swing/JRadioButton."<init>":(Ljava/lang/String;)V
     279: astore        15
     281: iload         12
     283: ifne          301
     286: aload         15
     288: iconst_1
     289: invokevirtual #61                 // Method javax/swing/JRadioButton.setSelected:(Z)V
     292: iconst_1
     293: istore        12
     295: aload_0
     296: aload         14
     298: putfield      #62                 // Field selectedPlugin:Lorg/protege/editor/owl/ui/explanation/io/InconsistentOntologyPlugin;
     301: aload_2
     302: ifnull        332
     305: aload         14
     307: invokevirtual #59                 // Method org/protege/editor/owl/ui/explanation/io/InconsistentOntologyPlugin.getName:()Ljava/lang/String;
     310: aload_2
     311: invokevirtual #59                 // Method org/protege/editor/owl/ui/explanation/io/InconsistentOntologyPlugin.getName:()Ljava/lang/String;
     314: invokevirtual #63                 // Method java/lang/String.equals:(Ljava/lang/Object;)Z
     317: ifeq          332
     320: aload         15
     322: iconst_1
     323: invokevirtual #61                 // Method javax/swing/JRadioButton.setSelected:(Z)V
     326: aload_0
     327: aload         14
     329: putfield      #62                 // Field selectedPlugin:Lorg/protege/editor/owl/ui/explanation/io/InconsistentOntologyPlugin;
     332: aload         11
     334: aload         15
     336: invokevirtual #64                 // Method javax/swing/ButtonGroup.add:(Ljavax/swing/AbstractButton;)V
     339: aload         15
     341: aload_0
     342: aload         14
     344: invokedynamic #65,  0             // InvokeDynamic #0:actionPerformed:(Lorg/protege/editor/owl/ui/explanation/io/IntroductoryPanel;Lorg/protege/editor/owl/ui/explanation/io/InconsistentOntologyPlugin;)Ljava/awt/event/ActionListener;
     349: invokevirtual #66                 // Method javax/swing/JRadioButton.addActionListener:(Ljava/awt/event/ActionListener;)V
     352: aload         10
     354: aload         15
     356: invokevirtual #67                 // Method javax/swing/Box.add:(Ljava/awt/Component;)Ljava/awt/Component;
     359: pop
     360: goto          245
     363: aload_3
     364: aload         10
     366: invokevirtual #41                 // Method javax/swing/JPanel.add:(Ljava/awt/Component;)Ljava/awt/Component;
     369: pop
     370: goto          392
     373: aload_0
     374: aload         9
     376: invokeinterface #54,  1           // InterfaceMethod java/util/Set.iterator:()Ljava/util/Iterator;
     381: invokeinterface #56,  1           // InterfaceMethod java/util/Iterator.next:()Ljava/lang/Object;
     386: checkcast     #57                 // class org/protege/editor/owl/ui/explanation/io/InconsistentOntologyPlugin
     389: putfield      #62                 // Field selectedPlugin:Lorg/protege/editor/owl/ui/explanation/io/InconsistentOntologyPlugin;
     392: aload_3
     393: areturn

  public org.protege.editor.owl.ui.explanation.io.InconsistentOntologyPlugin getSelectedPlugin();
    Code:
       0: aload_0
       1: getfield      #62                 // Field selectedPlugin:Lorg/protege/editor/owl/ui/explanation/io/InconsistentOntologyPlugin;
       4: areturn

  private void lambda$createCenterPanel$0(org.protege.editor.owl.ui.explanation.io.InconsistentOntologyPlugin, java.awt.event.ActionEvent);
    Code:
       0: aload_0
       1: aload_1
       2: putfield      #62                 // Field selectedPlugin:Lorg/protege/editor/owl/ui/explanation/io/InconsistentOntologyPlugin;
       5: return
}
