Compiled from "JerseyPublisher.java"
public final class org.glassfish.jersey.internal.util.JerseyPublisher$PublisherStrategy extends java.lang.Enum<org.glassfish.jersey.internal.util.JerseyPublisher$PublisherStrategy> {
  public static final org.glassfish.jersey.internal.util.JerseyPublisher$PublisherStrategy BLOCKING;

  public static final org.glassfish.jersey.internal.util.JerseyPublisher$PublisherStrategy BEST_EFFORT;

  private static final org.glassfish.jersey.internal.util.JerseyPublisher$PublisherStrategy[] $VALUES;

  public static org.glassfish.jersey.internal.util.JerseyPublisher$PublisherStrategy[] values();
    Code:
       0: getstatic     #1                  // Field $VALUES:[Lorg/glassfish/jersey/internal/util/JerseyPublisher$PublisherStrategy;
       3: invokevirtual #2                  // Method "[Lorg/glassfish/jersey/internal/util/JerseyPublisher$PublisherStrategy;".clone:()Ljava/lang/Object;
       6: checkcast     #3                  // class "[Lorg/glassfish/jersey/internal/util/JerseyPublisher$PublisherStrategy;"
       9: areturn

  public static org.glassfish.jersey.internal.util.JerseyPublisher$PublisherStrategy valueOf(java.lang.String);
    Code:
       0: ldc           #4                  // class org/glassfish/jersey/internal/util/JerseyPublisher$PublisherStrategy
       2: aload_0
       3: invokestatic  #5                  // Method java/lang/Enum.valueOf:(Ljava/lang/Class;Ljava/lang/String;)Ljava/lang/Enum;
       6: checkcast     #4                  // class org/glassfish/jersey/internal/util/JerseyPublisher$PublisherStrategy
       9: areturn

  private org.glassfish.jersey.internal.util.JerseyPublisher$PublisherStrategy();
    Code:
       0: aload_0
       1: aload_1
       2: iload_2
       3: invokespecial #6                  // Method java/lang/Enum."<init>":(Ljava/lang/String;I)V
       6: return

  static {};
    Code:
       0: new           #4                  // class org/glassfish/jersey/internal/util/JerseyPublisher$PublisherStrategy
       3: dup
       4: ldc           #7                  // String BLOCKING
       6: iconst_0
       7: invokespecial #8                  // Method "<init>":(Ljava/lang/String;I)V
      10: putstatic     #9                  // Field BLOCKING:Lorg/glassfish/jersey/internal/util/JerseyPublisher$PublisherStrategy;
      13: new           #4                  // class org/glassfish/jersey/internal/util/JerseyPublisher$PublisherStrategy
      16: dup
      17: ldc           #10                 // String BEST_EFFORT
      19: iconst_1
      20: invokespecial #8                  // Method "<init>":(Ljava/lang/String;I)V
      23: putstatic     #11                 // Field BEST_EFFORT:Lorg/glassfish/jersey/internal/util/JerseyPublisher$PublisherStrategy;
      26: iconst_2
      27: anewarray     #4                  // class org/glassfish/jersey/internal/util/JerseyPublisher$PublisherStrategy
      30: dup
      31: iconst_0
      32: getstatic     #9                  // Field BLOCKING:Lorg/glassfish/jersey/internal/util/JerseyPublisher$PublisherStrategy;
      35: aastore
      36: dup
      37: iconst_1
      38: getstatic     #11                 // Field BEST_EFFORT:Lorg/glassfish/jersey/internal/util/JerseyPublisher$PublisherStrategy;
      41: aastore
      42: putstatic     #1                  // Field $VALUES:[Lorg/glassfish/jersey/internal/util/JerseyPublisher$PublisherStrategy;
      45: return
}
