Compiled from "Base64Url.java"
public class org.jose4j.base64url.Base64Url {
  private org.jose4j.base64url.internal.apache.commons.codec.binary.Base64 base64urlCodec;

  public org.jose4j.base64url.Base64Url();
    Code:
       0: aload_0
       1: invokespecial #1                  // Method java/lang/Object."<init>":()V
       4: aload_0
       5: new           #2                  // class org/jose4j/base64url/internal/apache/commons/codec/binary/Base64
       8: dup
       9: iconst_m1
      10: aconst_null
      11: iconst_1
      12: invokespecial #3                  // Method org/jose4j/base64url/internal/apache/commons/codec/binary/Base64."<init>":(I[BZ)V
      15: putfield      #4                  // Field base64urlCodec:Lorg/jose4j/base64url/internal/apache/commons/codec/binary/Base64;
      18: return

  public java.lang.String base64UrlDecodeToUtf8String(java.lang.String);
    Code:
       0: aload_0
       1: aload_1
       2: ldc           #5                  // String UTF-8
       4: invokevirtual #6                  // Method base64UrlDecodeToString:(Ljava/lang/String;Ljava/lang/String;)Ljava/lang/String;
       7: areturn

  public java.lang.String base64UrlDecodeToString(java.lang.String, java.lang.String);
    Code:
       0: aload_0
       1: aload_1
       2: invokevirtual #7                  // Method base64UrlDecode:(Ljava/lang/String;)[B
       5: astore_3
       6: aload_3
       7: aload_2
       8: invokestatic  #8                  // Method org/jose4j/lang/StringUtil.newString:([BLjava/lang/String;)Ljava/lang/String;
      11: areturn

  public byte[] base64UrlDecode(java.lang.String);
    Code:
       0: aload_0
       1: getfield      #4                  // Field base64urlCodec:Lorg/jose4j/base64url/internal/apache/commons/codec/binary/Base64;
       4: aload_1
       5: invokevirtual #9                  // Method org/jose4j/base64url/internal/apache/commons/codec/binary/Base64.decode:(Ljava/lang/String;)[B
       8: areturn

  public java.lang.String base64UrlEncodeUtf8ByteRepresentation(java.lang.String);
    Code:
       0: aload_0
       1: aload_1
       2: ldc           #5                  // String UTF-8
       4: invokevirtual #10                 // Method base64UrlEncode:(Ljava/lang/String;Ljava/lang/String;)Ljava/lang/String;
       7: areturn

  public java.lang.String base64UrlEncode(java.lang.String, java.lang.String);
    Code:
       0: aload_1
       1: aload_2
       2: invokestatic  #11                 // Method org/jose4j/lang/StringUtil.getBytesUnchecked:(Ljava/lang/String;Ljava/lang/String;)[B
       5: astore_3
       6: aload_0
       7: aload_3
       8: invokevirtual #12                 // Method base64UrlEncode:([B)Ljava/lang/String;
      11: areturn

  public java.lang.String base64UrlEncode(byte[]);
    Code:
       0: aload_0
       1: getfield      #4                  // Field base64urlCodec:Lorg/jose4j/base64url/internal/apache/commons/codec/binary/Base64;
       4: aload_1
       5: invokevirtual #13                 // Method org/jose4j/base64url/internal/apache/commons/codec/binary/Base64.encodeToString:([B)Ljava/lang/String;
       8: areturn

  private static org.jose4j.base64url.Base64Url getOne();
    Code:
       0: new           #14                 // class org/jose4j/base64url/Base64Url
       3: dup
       4: invokespecial #15                 // Method "<init>":()V
       7: areturn

  public static java.lang.String decodeToUtf8String(java.lang.String);
    Code:
       0: invokestatic  #16                 // Method getOne:()Lorg/jose4j/base64url/Base64Url;
       3: aload_0
       4: ldc           #5                  // String UTF-8
       6: invokevirtual #6                  // Method base64UrlDecodeToString:(Ljava/lang/String;Ljava/lang/String;)Ljava/lang/String;
       9: areturn

  public static java.lang.String decodeToString(java.lang.String, java.lang.String);
    Code:
       0: invokestatic  #16                 // Method getOne:()Lorg/jose4j/base64url/Base64Url;
       3: aload_0
       4: aload_1
       5: invokevirtual #6                  // Method base64UrlDecodeToString:(Ljava/lang/String;Ljava/lang/String;)Ljava/lang/String;
       8: areturn

  public static byte[] decode(java.lang.String);
    Code:
       0: invokestatic  #16                 // Method getOne:()Lorg/jose4j/base64url/Base64Url;
       3: aload_0
       4: invokevirtual #7                  // Method base64UrlDecode:(Ljava/lang/String;)[B
       7: areturn

  public static java.lang.String encodeUtf8ByteRepresentation(java.lang.String);
    Code:
       0: invokestatic  #16                 // Method getOne:()Lorg/jose4j/base64url/Base64Url;
       3: aload_0
       4: invokevirtual #17                 // Method base64UrlEncodeUtf8ByteRepresentation:(Ljava/lang/String;)Ljava/lang/String;
       7: areturn

  public static java.lang.String encode(java.lang.String, java.lang.String);
    Code:
       0: invokestatic  #16                 // Method getOne:()Lorg/jose4j/base64url/Base64Url;
       3: aload_0
       4: aload_1
       5: invokevirtual #10                 // Method base64UrlEncode:(Ljava/lang/String;Ljava/lang/String;)Ljava/lang/String;
       8: areturn

  public static java.lang.String encode(byte[]);
    Code:
       0: invokestatic  #16                 // Method getOne:()Lorg/jose4j/base64url/Base64Url;
       3: aload_0
       4: invokevirtual #12                 // Method base64UrlEncode:([B)Ljava/lang/String;
       7: areturn
}
