Compiled from "TableBinder.java"
class org.hibernate.cfg.annotations.TableBinder$3$1 implements org.hibernate.boot.model.naming.EntityNaming {
  final org.hibernate.cfg.annotations.TableBinder$3 this$1;

  org.hibernate.cfg.annotations.TableBinder$3$1(org.hibernate.cfg.annotations.TableBinder$3);
    Code:
       0: aload_0
       1: aload_1
       2: putfield      #1                  // Field this$1:Lorg/hibernate/cfg/annotations/TableBinder$3;
       5: aload_0
       6: invokespecial #2                  // Method java/lang/Object."<init>":()V
       9: return

  public java.lang.String getClassName();
    Code:
       0: aload_0
       1: getfield      #1                  // Field this$1:Lorg/hibernate/cfg/annotations/TableBinder$3;
       4: getfield      #3                  // Field org/hibernate/cfg/annotations/TableBinder$3.this$0:Lorg/hibernate/cfg/annotations/TableBinder;
       7: invokestatic  #4                  // Method org/hibernate/cfg/annotations/TableBinder.access$100:(Lorg/hibernate/cfg/annotations/TableBinder;)Ljava/lang/String;
      10: areturn

  public java.lang.String getEntityName();
    Code:
       0: aload_0
       1: getfield      #1                  // Field this$1:Lorg/hibernate/cfg/annotations/TableBinder$3;
       4: getfield      #3                  // Field org/hibernate/cfg/annotations/TableBinder$3.this$0:Lorg/hibernate/cfg/annotations/TableBinder;
       7: invokestatic  #5                  // Method org/hibernate/cfg/annotations/TableBinder.access$200:(Lorg/hibernate/cfg/annotations/TableBinder;)Ljava/lang/String;
      10: areturn

  public java.lang.String getJpaEntityName();
    Code:
       0: aload_0
       1: getfield      #1                  // Field this$1:Lorg/hibernate/cfg/annotations/TableBinder$3;
       4: getfield      #3                  // Field org/hibernate/cfg/annotations/TableBinder$3.this$0:Lorg/hibernate/cfg/annotations/TableBinder;
       7: invokestatic  #6                  // Method org/hibernate/cfg/annotations/TableBinder.access$300:(Lorg/hibernate/cfg/annotations/TableBinder;)Ljava/lang/String;
      10: areturn
}
