Compiled from "CreateKeySecondPass.java"
public class org.hibernate.cfg.CreateKeySecondPass implements org.hibernate.cfg.SecondPass {
  private org.hibernate.mapping.RootClass rootClass;

  private org.hibernate.mapping.JoinedSubclass joinedSubClass;

  public org.hibernate.cfg.CreateKeySecondPass(org.hibernate.mapping.RootClass);
    Code:
       0: aload_0
       1: invokespecial #1                  // Method java/lang/Object."<init>":()V
       4: aload_0
       5: aload_1
       6: putfield      #2                  // Field rootClass:Lorg/hibernate/mapping/RootClass;
       9: return

  public org.hibernate.cfg.CreateKeySecondPass(org.hibernate.mapping.JoinedSubclass);
    Code:
       0: aload_0
       1: invokespecial #1                  // Method java/lang/Object."<init>":()V
       4: aload_0
       5: aload_1
       6: putfield      #3                  // Field joinedSubClass:Lorg/hibernate/mapping/JoinedSubclass;
       9: return

  public void doSecondPass(java.util.Map) throws org.hibernate.MappingException;
    Code:
       0: aload_0
       1: getfield      #2                  // Field rootClass:Lorg/hibernate/mapping/RootClass;
       4: ifnull        17
       7: aload_0
       8: getfield      #2                  // Field rootClass:Lorg/hibernate/mapping/RootClass;
      11: invokevirtual #4                  // Method org/hibernate/mapping/RootClass.createPrimaryKey:()V
      14: goto          51
      17: aload_0
      18: getfield      #3                  // Field joinedSubClass:Lorg/hibernate/mapping/JoinedSubclass;
      21: ifnull        41
      24: aload_0
      25: getfield      #3                  // Field joinedSubClass:Lorg/hibernate/mapping/JoinedSubclass;
      28: invokevirtual #5                  // Method org/hibernate/mapping/JoinedSubclass.createPrimaryKey:()V
      31: aload_0
      32: getfield      #3                  // Field joinedSubClass:Lorg/hibernate/mapping/JoinedSubclass;
      35: invokevirtual #6                  // Method org/hibernate/mapping/JoinedSubclass.createForeignKey:()V
      38: goto          51
      41: new           #7                  // class java/lang/AssertionError
      44: dup
      45: ldc           #8                  // String rootClass and joinedSubClass are null
      47: invokespecial #9                  // Method java/lang/AssertionError."<init>":(Ljava/lang/Object;)V
      50: athrow
      51: return
}
