Compiled from "UniqueConstraintHolder.java"
public class org.hibernate.cfg.UniqueConstraintHolder {
  private java.lang.String name;

  private java.lang.String[] columns;

  public org.hibernate.cfg.UniqueConstraintHolder();
    Code:
       0: aload_0
       1: invokespecial #1                  // Method java/lang/Object."<init>":()V
       4: return

  public java.lang.String getName();
    Code:
       0: aload_0
       1: getfield      #2                  // Field name:Ljava/lang/String;
       4: areturn

  public org.hibernate.cfg.UniqueConstraintHolder setName(java.lang.String);
    Code:
       0: aload_0
       1: aload_1
       2: putfield      #2                  // Field name:Ljava/lang/String;
       5: aload_0
       6: areturn

  public java.lang.String[] getColumns();
    Code:
       0: aload_0
       1: getfield      #3                  // Field columns:[Ljava/lang/String;
       4: areturn

  public org.hibernate.cfg.UniqueConstraintHolder setColumns(java.lang.String[]);
    Code:
       0: aload_0
       1: aload_1
       2: putfield      #3                  // Field columns:[Ljava/lang/String;
       5: aload_0
       6: areturn
}
