Compiled from "TestQueryTest.java"
public class uk.gov.gchq.gaffer.performancetesting.ingest.TestQueryTest {
  public org.junit.rules.TemporaryFolder folder;

  public uk.gov.gchq.gaffer.performancetesting.ingest.TestQueryTest();
    Code:
       0: aload_0
       1: invokespecial #1                  // Method java/lang/Object."<init>":()V
       4: aload_0
       5: new           #2                  // class org/junit/rules/TemporaryFolder
       8: dup
       9: getstatic     #3                  // Field uk/gov/gchq/gaffer/commonutil/CommonTestConstants.TMP_DIRECTORY:Ljava/io/File;
      12: invokespecial #4                  // Method org/junit/rules/TemporaryFolder."<init>":(Ljava/io/File;)V
      15: putfield      #5                  // Field folder:Lorg/junit/rules/TemporaryFolder;
      18: return

  public void testQueryTestRuns() throws uk.gov.gchq.gaffer.operation.OperationException;
    Code:
       0: new           #6                  // class uk/gov/gchq/gaffer/performancetesting/query/QueryTestProperties
       3: dup
       4: invokespecial #7                  // Method uk/gov/gchq/gaffer/performancetesting/query/QueryTestProperties."<init>":()V
       7: astore_1
       8: aload_1
       9: ldc2_w        #8                  // long 100l
      12: invokevirtual #10                 // Method uk/gov/gchq/gaffer/performancetesting/query/QueryTestProperties.setNumSeeds:(J)V
      15: aload_1
      16: ldc2_w        #11                 // long 10l
      19: invokevirtual #13                 // Method uk/gov/gchq/gaffer/performancetesting/query/QueryTestProperties.setBatchSize:(J)V
      22: aload_1
      23: ldc           #14                 // class uk/gov/gchq/gaffer/randomelementgeneration/supplier/EntitySeedSupplier
      25: invokevirtual #15                 // Method java/lang/Class.getName:()Ljava/lang/String;
      28: invokevirtual #16                 // Method uk/gov/gchq/gaffer/performancetesting/query/QueryTestProperties.setElementIdSupplierClass:(Ljava/lang/String;)V
      31: aload_1
      32: getstatic     #17                 // Field uk/gov/gchq/gaffer/randomelementgeneration/Constants.RMAT_PROBABILITIES:[D
      35: invokevirtual #18                 // Method uk/gov/gchq/gaffer/performancetesting/query/QueryTestProperties.setRmatProbabilities:([D)V
      38: aload_1
      39: ldc2_w        #8                  // long 100l
      42: invokevirtual #19                 // Method uk/gov/gchq/gaffer/performancetesting/query/QueryTestProperties.setRmatMaxNodeId:(J)V
      45: new           #20                 // class uk/gov/gchq/gaffer/accumulostore/AccumuloProperties
      48: dup
      49: invokespecial #21                 // Method uk/gov/gchq/gaffer/accumulostore/AccumuloProperties."<init>":()V
      52: astore_2
      53: aload_2
      54: ldc           #22                 // class uk/gov/gchq/gaffer/accumulostore/MockAccumuloStore
      56: invokevirtual #15                 // Method java/lang/Class.getName:()Ljava/lang/String;
      59: invokevirtual #23                 // Method uk/gov/gchq/gaffer/accumulostore/AccumuloProperties.setStoreClass:(Ljava/lang/String;)V
      62: new           #24                 // class uk/gov/gchq/gaffer/graph/Graph$Builder
      65: dup
      66: invokespecial #25                 // Method uk/gov/gchq/gaffer/graph/Graph$Builder."<init>":()V
      69: ldc           #26                 // String id
      71: invokevirtual #27                 // Method uk/gov/gchq/gaffer/graph/Graph$Builder.graphId:(Ljava/lang/String;)Luk/gov/gchq/gaffer/graph/Graph$Builder;
      74: aload_2
      75: invokevirtual #28                 // Method uk/gov/gchq/gaffer/graph/Graph$Builder.storeProperties:(Luk/gov/gchq/gaffer/store/StoreProperties;)Luk/gov/gchq/gaffer/graph/Graph$Builder;
      78: ldc           #29                 // class uk/gov/gchq/gaffer/randomelementgeneration/Constants
      80: invokestatic  #30                 // Method uk/gov/gchq/gaffer/commonutil/StreamUtil.schemas:(Ljava/lang/Class;)[Ljava/io/InputStream;
      83: invokevirtual #31                 // Method uk/gov/gchq/gaffer/graph/Graph$Builder.addSchemas:([Ljava/io/InputStream;)Luk/gov/gchq/gaffer/graph/Graph$Builder;
      86: invokevirtual #32                 // Method uk/gov/gchq/gaffer/graph/Graph$Builder.build:()Luk/gov/gchq/gaffer/graph/Graph;
      89: astore_3
      90: aload_3
      91: new           #33                 // class uk/gov/gchq/gaffer/operation/impl/add/AddElements$Builder
      94: dup
      95: invokespecial #34                 // Method uk/gov/gchq/gaffer/operation/impl/add/AddElements$Builder."<init>":()V
      98: new           #35                 // class uk/gov/gchq/gaffer/randomelementgeneration/supplier/ElementsSupplier
     101: dup
     102: new           #36                 // class uk/gov/gchq/gaffer/randomelementgeneration/supplier/RmatElementSupplier
     105: dup
     106: getstatic     #17                 // Field uk/gov/gchq/gaffer/randomelementgeneration/Constants.RMAT_PROBABILITIES:[D
     109: ldc2_w        #8                  // long 100l
     112: iconst_1
     113: invokespecial #37                 // Method uk/gov/gchq/gaffer/randomelementgeneration/supplier/RmatElementSupplier."<init>":([DJZ)V
     116: invokespecial #38                 // Method uk/gov/gchq/gaffer/randomelementgeneration/supplier/ElementsSupplier."<init>":(Ljava/util/function/Supplier;)V
     119: invokestatic  #39                 // InterfaceMethod java/util/stream/Stream.generate:(Ljava/util/function/Supplier;)Ljava/util/stream/Stream;
     122: ldc2_w        #40                 // long 1000l
     125: invokeinterface #42,  3           // InterfaceMethod java/util/stream/Stream.limit:(J)Ljava/util/stream/Stream;
     130: dup
     131: invokevirtual #43                 // Method java/lang/Object.getClass:()Ljava/lang/Class;
     134: pop
     135: invokedynamic #44,  0             // InvokeDynamic #0:iterator:(Ljava/util/stream/Stream;)Ljava/lang/Iterable;
     140: invokevirtual #45                 // Method uk/gov/gchq/gaffer/operation/impl/add/AddElements$Builder.input:(Ljava/lang/Iterable;)Luk/gov/gchq/gaffer/operation/io/MultiInput$Builder;
     143: checkcast     #33                 // class uk/gov/gchq/gaffer/operation/impl/add/AddElements$Builder
     146: invokevirtual #46                 // Method uk/gov/gchq/gaffer/operation/impl/add/AddElements$Builder.build:()Luk/gov/gchq/gaffer/operation/Operation;
     149: new           #47                 // class uk/gov/gchq/gaffer/user/User
     152: dup
     153: invokespecial #48                 // Method uk/gov/gchq/gaffer/user/User."<init>":()V
     156: invokevirtual #49                 // Method uk/gov/gchq/gaffer/graph/Graph.execute:(Luk/gov/gchq/gaffer/operation/Operation;Luk/gov/gchq/gaffer/user/User;)V
     159: new           #50                 // class uk/gov/gchq/gaffer/performancetesting/query/QueryTest
     162: dup
     163: aload_3
     164: aload_1
     165: invokespecial #51                 // Method uk/gov/gchq/gaffer/performancetesting/query/QueryTest."<init>":(Luk/gov/gchq/gaffer/graph/Graph;Luk/gov/gchq/gaffer/performancetesting/query/QueryTestProperties;)V
     168: astore        4
     170: aload         4
     172: invokevirtual #52                 // Method uk/gov/gchq/gaffer/performancetesting/query/QueryTest.run:()D
     175: dstore        5
     177: dload         5
     179: dconst_0
     180: dcmpl
     181: ifle          188
     184: iconst_1
     185: goto          189
     188: iconst_0
     189: invokestatic  #53                 // Method org/junit/Assert.assertTrue:(Z)V
     192: return

  public void testQueryTestOutputsToListener() throws java.io.IOException, uk.gov.gchq.gaffer.operation.OperationException;
    Code:
       0: new           #6                  // class uk/gov/gchq/gaffer/performancetesting/query/QueryTestProperties
       3: dup
       4: invokespecial #7                  // Method uk/gov/gchq/gaffer/performancetesting/query/QueryTestProperties."<init>":()V
       7: astore_1
       8: aload_1
       9: ldc2_w        #8                  // long 100l
      12: invokevirtual #10                 // Method uk/gov/gchq/gaffer/performancetesting/query/QueryTestProperties.setNumSeeds:(J)V
      15: aload_1
      16: ldc2_w        #11                 // long 10l
      19: invokevirtual #13                 // Method uk/gov/gchq/gaffer/performancetesting/query/QueryTestProperties.setBatchSize:(J)V
      22: aload_1
      23: ldc           #14                 // class uk/gov/gchq/gaffer/randomelementgeneration/supplier/EntitySeedSupplier
      25: invokevirtual #15                 // Method java/lang/Class.getName:()Ljava/lang/String;
      28: invokevirtual #16                 // Method uk/gov/gchq/gaffer/performancetesting/query/QueryTestProperties.setElementIdSupplierClass:(Ljava/lang/String;)V
      31: aload_1
      32: getstatic     #17                 // Field uk/gov/gchq/gaffer/randomelementgeneration/Constants.RMAT_PROBABILITIES:[D
      35: invokevirtual #18                 // Method uk/gov/gchq/gaffer/performancetesting/query/QueryTestProperties.setRmatProbabilities:([D)V
      38: aload_1
      39: ldc2_w        #8                  // long 100l
      42: invokevirtual #19                 // Method uk/gov/gchq/gaffer/performancetesting/query/QueryTestProperties.setRmatMaxNodeId:(J)V
      45: aload_1
      46: ldc           #54                 // class uk/gov/gchq/gaffer/performancetesting/FileWriterMetricsListener
      48: invokevirtual #15                 // Method java/lang/Class.getName:()Ljava/lang/String;
      51: invokevirtual #55                 // Method uk/gov/gchq/gaffer/performancetesting/query/QueryTestProperties.setMetricsListenerClass:(Ljava/lang/String;)V
      54: aload_0
      55: getfield      #5                  // Field folder:Lorg/junit/rules/TemporaryFolder;
      58: invokevirtual #56                 // Method org/junit/rules/TemporaryFolder.newFile:()Ljava/io/File;
      61: astore_2
      62: aload_2
      63: invokevirtual #57                 // Method java/io/File.getPath:()Ljava/lang/String;
      66: astore_3
      67: aload_1
      68: ldc           #58                 // String gaffer.performancetesting.filewritermetricslistener.filename
      70: aload_3
      71: invokevirtual #59                 // Method uk/gov/gchq/gaffer/performancetesting/query/QueryTestProperties.setProperty:(Ljava/lang/String;Ljava/lang/String;)Ljava/lang/Object;
      74: pop
      75: new           #20                 // class uk/gov/gchq/gaffer/accumulostore/AccumuloProperties
      78: dup
      79: invokespecial #21                 // Method uk/gov/gchq/gaffer/accumulostore/AccumuloProperties."<init>":()V
      82: astore        4
      84: aload         4
      86: ldc           #22                 // class uk/gov/gchq/gaffer/accumulostore/MockAccumuloStore
      88: invokevirtual #15                 // Method java/lang/Class.getName:()Ljava/lang/String;
      91: invokevirtual #23                 // Method uk/gov/gchq/gaffer/accumulostore/AccumuloProperties.setStoreClass:(Ljava/lang/String;)V
      94: new           #24                 // class uk/gov/gchq/gaffer/graph/Graph$Builder
      97: dup
      98: invokespecial #25                 // Method uk/gov/gchq/gaffer/graph/Graph$Builder."<init>":()V
     101: ldc           #26                 // String id
     103: invokevirtual #27                 // Method uk/gov/gchq/gaffer/graph/Graph$Builder.graphId:(Ljava/lang/String;)Luk/gov/gchq/gaffer/graph/Graph$Builder;
     106: aload         4
     108: invokevirtual #28                 // Method uk/gov/gchq/gaffer/graph/Graph$Builder.storeProperties:(Luk/gov/gchq/gaffer/store/StoreProperties;)Luk/gov/gchq/gaffer/graph/Graph$Builder;
     111: ldc           #29                 // class uk/gov/gchq/gaffer/randomelementgeneration/Constants
     113: invokestatic  #30                 // Method uk/gov/gchq/gaffer/commonutil/StreamUtil.schemas:(Ljava/lang/Class;)[Ljava/io/InputStream;
     116: invokevirtual #31                 // Method uk/gov/gchq/gaffer/graph/Graph$Builder.addSchemas:([Ljava/io/InputStream;)Luk/gov/gchq/gaffer/graph/Graph$Builder;
     119: invokevirtual #32                 // Method uk/gov/gchq/gaffer/graph/Graph$Builder.build:()Luk/gov/gchq/gaffer/graph/Graph;
     122: astore        5
     124: aload         5
     126: new           #33                 // class uk/gov/gchq/gaffer/operation/impl/add/AddElements$Builder
     129: dup
     130: invokespecial #34                 // Method uk/gov/gchq/gaffer/operation/impl/add/AddElements$Builder."<init>":()V
     133: new           #35                 // class uk/gov/gchq/gaffer/randomelementgeneration/supplier/ElementsSupplier
     136: dup
     137: new           #36                 // class uk/gov/gchq/gaffer/randomelementgeneration/supplier/RmatElementSupplier
     140: dup
     141: getstatic     #17                 // Field uk/gov/gchq/gaffer/randomelementgeneration/Constants.RMAT_PROBABILITIES:[D
     144: ldc2_w        #8                  // long 100l
     147: iconst_1
     148: invokespecial #37                 // Method uk/gov/gchq/gaffer/randomelementgeneration/supplier/RmatElementSupplier."<init>":([DJZ)V
     151: invokespecial #38                 // Method uk/gov/gchq/gaffer/randomelementgeneration/supplier/ElementsSupplier."<init>":(Ljava/util/function/Supplier;)V
     154: invokestatic  #39                 // InterfaceMethod java/util/stream/Stream.generate:(Ljava/util/function/Supplier;)Ljava/util/stream/Stream;
     157: ldc2_w        #40                 // long 1000l
     160: invokeinterface #42,  3           // InterfaceMethod java/util/stream/Stream.limit:(J)Ljava/util/stream/Stream;
     165: dup
     166: invokevirtual #43                 // Method java/lang/Object.getClass:()Ljava/lang/Class;
     169: pop
     170: invokedynamic #44,  0             // InvokeDynamic #0:iterator:(Ljava/util/stream/Stream;)Ljava/lang/Iterable;
     175: invokevirtual #45                 // Method uk/gov/gchq/gaffer/operation/impl/add/AddElements$Builder.input:(Ljava/lang/Iterable;)Luk/gov/gchq/gaffer/operation/io/MultiInput$Builder;
     178: checkcast     #33                 // class uk/gov/gchq/gaffer/operation/impl/add/AddElements$Builder
     181: invokevirtual #46                 // Method uk/gov/gchq/gaffer/operation/impl/add/AddElements$Builder.build:()Luk/gov/gchq/gaffer/operation/Operation;
     184: new           #47                 // class uk/gov/gchq/gaffer/user/User
     187: dup
     188: invokespecial #48                 // Method uk/gov/gchq/gaffer/user/User."<init>":()V
     191: invokevirtual #49                 // Method uk/gov/gchq/gaffer/graph/Graph.execute:(Luk/gov/gchq/gaffer/operation/Operation;Luk/gov/gchq/gaffer/user/User;)V
     194: new           #50                 // class uk/gov/gchq/gaffer/performancetesting/query/QueryTest
     197: dup
     198: aload         5
     200: aload_1
     201: invokespecial #51                 // Method uk/gov/gchq/gaffer/performancetesting/query/QueryTest."<init>":(Luk/gov/gchq/gaffer/graph/Graph;Luk/gov/gchq/gaffer/performancetesting/query/QueryTestProperties;)V
     204: astore        6
     206: aload         6
     208: invokevirtual #52                 // Method uk/gov/gchq/gaffer/performancetesting/query/QueryTest.run:()D
     211: pop2
     212: new           #60                 // class java/io/File
     215: dup
     216: aload_3
     217: invokespecial #61                 // Method java/io/File."<init>":(Ljava/lang/String;)V
     220: invokestatic  #62                 // Method org/apache/commons/io/FileUtils.readLines:(Ljava/io/File;)Ljava/util/List;
     223: astore        7
     225: aload         7
     227: invokeinterface #63,  1           // InterfaceMethod java/util/List.size:()I
     232: ifle          239
     235: iconst_1
     236: goto          240
     239: iconst_0
     240: invokestatic  #53                 // Method org/junit/Assert.assertTrue:(Z)V
     243: aload         7
     245: invokedynamic #64,  0             // InvokeDynamic #1:accept:()Ljava/util/function/Consumer;
     250: invokeinterface #65,  2           // InterfaceMethod java/util/List.forEach:(Ljava/util/function/Consumer;)V
     255: return

  private static void lambda$testQueryTestOutputsToListener$0(java.lang.String);
    Code:
       0: aload_0
       1: ldc           #66                 // String ,
       3: invokevirtual #67                 // Method java/lang/String.split:(Ljava/lang/String;)[Ljava/lang/String;
       6: astore_1
       7: aload_1
       8: iconst_0
       9: aaload
      10: ldc           #69                 // String results_per_second
      12: invokevirtual #70                 // Method java/lang/String.startsWith:(Ljava/lang/String;)Z
      15: invokestatic  #53                 // Method org/junit/Assert.assertTrue:(Z)V
      18: aload_1
      19: iconst_0
      20: aaload
      21: ldc           #71                 // String :
      23: invokevirtual #67                 // Method java/lang/String.split:(Ljava/lang/String;)[Ljava/lang/String;
      26: iconst_1
      27: aaload
      28: invokestatic  #72                 // Method java/lang/Double.parseDouble:(Ljava/lang/String;)D
      31: dconst_0
      32: dcmpl
      33: ifle          40
      36: iconst_1
      37: goto          41
      40: iconst_0
      41: invokestatic  #53                 // Method org/junit/Assert.assertTrue:(Z)V
      44: aload_1
      45: iconst_1
      46: aaload
      47: ldc           #73                 // String seeds_per_second
      49: invokevirtual #70                 // Method java/lang/String.startsWith:(Ljava/lang/String;)Z
      52: invokestatic  #53                 // Method org/junit/Assert.assertTrue:(Z)V
      55: aload_1
      56: iconst_1
      57: aaload
      58: ldc           #71                 // String :
      60: invokevirtual #67                 // Method java/lang/String.split:(Ljava/lang/String;)[Ljava/lang/String;
      63: iconst_1
      64: aaload
      65: invokestatic  #72                 // Method java/lang/Double.parseDouble:(Ljava/lang/String;)D
      68: dconst_0
      69: dcmpl
      70: ifle          77
      73: iconst_1
      74: goto          78
      77: iconst_0
      78: invokestatic  #53                 // Method org/junit/Assert.assertTrue:(Z)V
      81: return
}
