Compiled from "RequiredSearch.java"
public final class io.micrometer.core.instrument.search.RequiredSearch {
  final io.micrometer.core.instrument.MeterRegistry registry;

  final java.util.List<io.micrometer.core.instrument.Tag> requiredTags;

  final java.util.Set<java.lang.String> requiredTagKeys;

  java.lang.String exactNameMatch;

  java.util.function.Predicate<java.lang.String> nameMatches;

  private io.micrometer.core.instrument.search.RequiredSearch(io.micrometer.core.instrument.MeterRegistry);
    Code:
       0: aload_0
       1: invokespecial #1                  // Method java/lang/Object."<init>":()V
       4: aload_0
       5: new           #7                  // class java/util/ArrayList
       8: dup
       9: invokespecial #9                  // Method java/util/ArrayList."<init>":()V
      12: putfield      #10                 // Field requiredTags:Ljava/util/List;
      15: aload_0
      16: new           #16                 // class java/util/HashSet
      19: dup
      20: invokespecial #18                 // Method java/util/HashSet."<init>":()V
      23: putfield      #19                 // Field requiredTagKeys:Ljava/util/Set;
      26: aload_0
      27: aload_1
      28: putfield      #23                 // Field registry:Lio/micrometer/core/instrument/MeterRegistry;
      31: return

  public io.micrometer.core.instrument.search.RequiredSearch name(java.lang.String);
    Code:
       0: aload_0
       1: aload_1
       2: invokedynamic #27,  0             // InvokeDynamic #0:test:(Ljava/lang/String;)Ljava/util/function/Predicate;
       7: putfield      #31                 // Field nameMatches:Ljava/util/function/Predicate;
      10: aload_0
      11: aload_1
      12: putfield      #35                 // Field exactNameMatch:Ljava/lang/String;
      15: aload_0
      16: areturn

  public io.micrometer.core.instrument.search.RequiredSearch name(java.util.function.Predicate<java.lang.String>);
    Code:
       0: aload_0
       1: aload_1
       2: putfield      #31                 // Field nameMatches:Ljava/util/function/Predicate;
       5: aload_0
       6: areturn

  public io.micrometer.core.instrument.search.RequiredSearch tags(java.lang.Iterable<io.micrometer.core.instrument.Tag>);
    Code:
       0: aload_1
       1: aload_0
       2: getfield      #10                 // Field requiredTags:Ljava/util/List;
       5: dup
       6: invokestatic  #39                 // Method java/util/Objects.requireNonNull:(Ljava/lang/Object;)Ljava/lang/Object;
       9: pop
      10: invokedynamic #45,  0             // InvokeDynamic #1:accept:(Ljava/util/List;)Ljava/util/function/Consumer;
      15: invokeinterface #49,  2           // InterfaceMethod java/lang/Iterable.forEach:(Ljava/util/function/Consumer;)V
      20: aload_0
      21: areturn

  public io.micrometer.core.instrument.search.RequiredSearch tags(java.lang.String...);
    Code:
       0: aload_0
       1: aload_1
       2: invokestatic  #55                 // Method io/micrometer/core/instrument/Tags.of:([Ljava/lang/String;)Lio/micrometer/core/instrument/Tags;
       5: invokevirtual #61                 // Method tags:(Ljava/lang/Iterable;)Lio/micrometer/core/instrument/search/RequiredSearch;
       8: areturn

  public io.micrometer.core.instrument.search.RequiredSearch tag(java.lang.String, java.lang.String);
    Code:
       0: aload_0
       1: aload_1
       2: aload_2
       3: invokestatic  #65                 // Method io/micrometer/core/instrument/Tags.of:(Ljava/lang/String;Ljava/lang/String;)Lio/micrometer/core/instrument/Tags;
       6: invokevirtual #61                 // Method tags:(Ljava/lang/Iterable;)Lio/micrometer/core/instrument/search/RequiredSearch;
       9: areturn

  public io.micrometer.core.instrument.search.RequiredSearch tagKeys(java.lang.String...);
    Code:
       0: aload_0
       1: getfield      #19                 // Field requiredTagKeys:Ljava/util/Set;
       4: aload_1
       5: invokestatic  #68                 // Method java/util/Arrays.asList:([Ljava/lang/Object;)Ljava/util/List;
       8: invokeinterface #74,  2           // InterfaceMethod java/util/Set.addAll:(Ljava/util/Collection;)Z
      13: pop
      14: aload_0
      15: areturn

  public io.micrometer.core.instrument.Timer timer();
    Code:
       0: aload_0
       1: ldc           #80                 // class io/micrometer/core/instrument/Timer
       3: invokespecial #82                 // Method findOne:(Ljava/lang/Class;)Lio/micrometer/core/instrument/Meter;
       6: checkcast     #80                 // class io/micrometer/core/instrument/Timer
       9: areturn

  public io.micrometer.core.instrument.Counter counter();
    Code:
       0: aload_0
       1: ldc           #86                 // class io/micrometer/core/instrument/Counter
       3: invokespecial #82                 // Method findOne:(Ljava/lang/Class;)Lio/micrometer/core/instrument/Meter;
       6: checkcast     #86                 // class io/micrometer/core/instrument/Counter
       9: areturn

  public io.micrometer.core.instrument.Gauge gauge();
    Code:
       0: aload_0
       1: ldc           #88                 // class io/micrometer/core/instrument/Gauge
       3: invokespecial #82                 // Method findOne:(Ljava/lang/Class;)Lio/micrometer/core/instrument/Meter;
       6: checkcast     #88                 // class io/micrometer/core/instrument/Gauge
       9: areturn

  public io.micrometer.core.instrument.FunctionCounter functionCounter();
    Code:
       0: aload_0
       1: ldc           #90                 // class io/micrometer/core/instrument/FunctionCounter
       3: invokespecial #82                 // Method findOne:(Ljava/lang/Class;)Lio/micrometer/core/instrument/Meter;
       6: checkcast     #90                 // class io/micrometer/core/instrument/FunctionCounter
       9: areturn

  public io.micrometer.core.instrument.TimeGauge timeGauge();
    Code:
       0: aload_0
       1: ldc           #92                 // class io/micrometer/core/instrument/TimeGauge
       3: invokespecial #82                 // Method findOne:(Ljava/lang/Class;)Lio/micrometer/core/instrument/Meter;
       6: checkcast     #92                 // class io/micrometer/core/instrument/TimeGauge
       9: areturn

  public io.micrometer.core.instrument.FunctionTimer functionTimer();
    Code:
       0: aload_0
       1: ldc           #94                 // class io/micrometer/core/instrument/FunctionTimer
       3: invokespecial #82                 // Method findOne:(Ljava/lang/Class;)Lio/micrometer/core/instrument/Meter;
       6: checkcast     #94                 // class io/micrometer/core/instrument/FunctionTimer
       9: areturn

  public io.micrometer.core.instrument.DistributionSummary summary();
    Code:
       0: aload_0
       1: ldc           #96                 // class io/micrometer/core/instrument/DistributionSummary
       3: invokespecial #82                 // Method findOne:(Ljava/lang/Class;)Lio/micrometer/core/instrument/Meter;
       6: checkcast     #96                 // class io/micrometer/core/instrument/DistributionSummary
       9: areturn

  public io.micrometer.core.instrument.LongTaskTimer longTaskTimer();
    Code:
       0: aload_0
       1: ldc           #98                 // class io/micrometer/core/instrument/LongTaskTimer
       3: invokespecial #82                 // Method findOne:(Ljava/lang/Class;)Lio/micrometer/core/instrument/Meter;
       6: checkcast     #98                 // class io/micrometer/core/instrument/LongTaskTimer
       9: areturn

  public io.micrometer.core.instrument.Meter meter();
    Code:
       0: aload_0
       1: ldc           #100                // class io/micrometer/core/instrument/Meter
       3: invokespecial #82                 // Method findOne:(Ljava/lang/Class;)Lio/micrometer/core/instrument/Meter;
       6: areturn

  private <M extends io.micrometer.core.instrument.Meter> M findOne(java.lang.Class<M>);
    Code:
       0: aload_0
       1: invokespecial #102                // Method meterStream:()Ljava/util/stream/Stream;
       4: aload_1
       5: dup
       6: invokestatic  #39                 // Method java/util/Objects.requireNonNull:(Ljava/lang/Object;)Ljava/lang/Object;
       9: pop
      10: invokedynamic #106,  0            // InvokeDynamic #2:test:(Ljava/lang/Class;)Ljava/util/function/Predicate;
      15: invokeinterface #109,  2          // InterfaceMethod java/util/stream/Stream.filter:(Ljava/util/function/Predicate;)Ljava/util/stream/Stream;
      20: invokeinterface #115,  1          // InterfaceMethod java/util/stream/Stream.findAny:()Ljava/util/Optional;
      25: aload_1
      26: dup
      27: invokestatic  #39                 // Method java/util/Objects.requireNonNull:(Ljava/lang/Object;)Ljava/lang/Object;
      30: pop
      31: invokedynamic #119,  0            // InvokeDynamic #3:apply:(Ljava/lang/Class;)Ljava/util/function/Function;
      36: invokevirtual #123                // Method java/util/Optional.map:(Ljava/util/function/Function;)Ljava/util/Optional;
      39: astore_2
      40: aload_2
      41: invokevirtual #129                // Method java/util/Optional.isPresent:()Z
      44: ifeq          55
      47: aload_2
      48: invokevirtual #133                // Method java/util/Optional.get:()Ljava/lang/Object;
      51: checkcast     #100                // class io/micrometer/core/instrument/Meter
      54: areturn
      55: aload_0
      56: aload_1
      57: invokestatic  #137                // Method io/micrometer/core/instrument/search/MeterNotFoundException.forSearch:(Lio/micrometer/core/instrument/search/RequiredSearch;Ljava/lang/Class;)Lio/micrometer/core/instrument/search/MeterNotFoundException;
      60: athrow

  private <M extends io.micrometer.core.instrument.Meter> java.util.Collection<M> findAll(java.lang.Class<M>);
    Code:
       0: aload_0
       1: invokespecial #102                // Method meterStream:()Ljava/util/stream/Stream;
       4: aload_1
       5: dup
       6: invokestatic  #39                 // Method java/util/Objects.requireNonNull:(Ljava/lang/Object;)Ljava/lang/Object;
       9: pop
      10: invokedynamic #106,  0            // InvokeDynamic #2:test:(Ljava/lang/Class;)Ljava/util/function/Predicate;
      15: invokeinterface #109,  2          // InterfaceMethod java/util/stream/Stream.filter:(Ljava/util/function/Predicate;)Ljava/util/stream/Stream;
      20: aload_1
      21: dup
      22: invokestatic  #39                 // Method java/util/Objects.requireNonNull:(Ljava/lang/Object;)Ljava/lang/Object;
      25: pop
      26: invokedynamic #119,  0            // InvokeDynamic #3:apply:(Ljava/lang/Class;)Ljava/util/function/Function;
      31: invokeinterface #143,  2          // InterfaceMethod java/util/stream/Stream.map:(Ljava/util/function/Function;)Ljava/util/stream/Stream;
      36: invokestatic  #146                // Method java/util/stream/Collectors.toList:()Ljava/util/stream/Collector;
      39: invokeinterface #152,  2          // InterfaceMethod java/util/stream/Stream.collect:(Ljava/util/stream/Collector;)Ljava/lang/Object;
      44: checkcast     #156                // class java/util/List
      47: astore_2
      48: aload_2
      49: invokeinterface #158,  1          // InterfaceMethod java/util/List.isEmpty:()Z
      54: ifeq          63
      57: aload_0
      58: aload_1
      59: invokestatic  #137                // Method io/micrometer/core/instrument/search/MeterNotFoundException.forSearch:(Lio/micrometer/core/instrument/search/RequiredSearch;Ljava/lang/Class;)Lio/micrometer/core/instrument/search/MeterNotFoundException;
      62: athrow
      63: aload_2
      64: areturn

  public java.util.Collection<io.micrometer.core.instrument.Meter> meters();
    Code:
       0: aload_0
       1: invokespecial #102                // Method meterStream:()Ljava/util/stream/Stream;
       4: invokestatic  #146                // Method java/util/stream/Collectors.toList:()Ljava/util/stream/Collector;
       7: invokeinterface #152,  2          // InterfaceMethod java/util/stream/Stream.collect:(Ljava/util/stream/Collector;)Ljava/lang/Object;
      12: checkcast     #156                // class java/util/List
      15: astore_1
      16: aload_1
      17: invokeinterface #158,  1          // InterfaceMethod java/util/List.isEmpty:()Z
      22: ifeq          32
      25: aload_0
      26: ldc           #100                // class io/micrometer/core/instrument/Meter
      28: invokestatic  #137                // Method io/micrometer/core/instrument/search/MeterNotFoundException.forSearch:(Lio/micrometer/core/instrument/search/RequiredSearch;Ljava/lang/Class;)Lio/micrometer/core/instrument/search/MeterNotFoundException;
      31: athrow
      32: aload_1
      33: areturn

  private java.util.stream.Stream<io.micrometer.core.instrument.Meter> meterStream();
    Code:
       0: aload_0
       1: getfield      #23                 // Field registry:Lio/micrometer/core/instrument/MeterRegistry;
       4: invokevirtual #161                // Method io/micrometer/core/instrument/MeterRegistry.getMeters:()Ljava/util/List;
       7: invokeinterface #167,  1          // InterfaceMethod java/util/List.stream:()Ljava/util/stream/Stream;
      12: aload_0
      13: invokedynamic #170,  0            // InvokeDynamic #4:test:(Lio/micrometer/core/instrument/search/RequiredSearch;)Ljava/util/function/Predicate;
      18: invokeinterface #109,  2          // InterfaceMethod java/util/stream/Stream.filter:(Ljava/util/function/Predicate;)Ljava/util/stream/Stream;
      23: astore_1
      24: aload_0
      25: getfield      #10                 // Field requiredTags:Ljava/util/List;
      28: invokeinterface #158,  1          // InterfaceMethod java/util/List.isEmpty:()Z
      33: ifeq          48
      36: aload_0
      37: getfield      #19                 // Field requiredTagKeys:Ljava/util/Set;
      40: invokeinterface #173,  1          // InterfaceMethod java/util/Set.isEmpty:()Z
      45: ifne          61
      48: aload_1
      49: aload_0
      50: invokedynamic #174,  0            // InvokeDynamic #5:test:(Lio/micrometer/core/instrument/search/RequiredSearch;)Ljava/util/function/Predicate;
      55: invokeinterface #109,  2          // InterfaceMethod java/util/stream/Stream.filter:(Ljava/util/function/Predicate;)Ljava/util/stream/Stream;
      60: astore_1
      61: aload_1
      62: areturn

  public java.util.Collection<io.micrometer.core.instrument.Counter> counters();
    Code:
       0: aload_0
       1: ldc           #86                 // class io/micrometer/core/instrument/Counter
       3: invokespecial #175                // Method findAll:(Ljava/lang/Class;)Ljava/util/Collection;
       6: areturn

  public java.util.Collection<io.micrometer.core.instrument.Gauge> gauges();
    Code:
       0: aload_0
       1: ldc           #88                 // class io/micrometer/core/instrument/Gauge
       3: invokespecial #175                // Method findAll:(Ljava/lang/Class;)Ljava/util/Collection;
       6: areturn

  public java.util.Collection<io.micrometer.core.instrument.Timer> timers();
    Code:
       0: aload_0
       1: ldc           #80                 // class io/micrometer/core/instrument/Timer
       3: invokespecial #175                // Method findAll:(Ljava/lang/Class;)Ljava/util/Collection;
       6: areturn

  public java.util.Collection<io.micrometer.core.instrument.DistributionSummary> summaries();
    Code:
       0: aload_0
       1: ldc           #96                 // class io/micrometer/core/instrument/DistributionSummary
       3: invokespecial #175                // Method findAll:(Ljava/lang/Class;)Ljava/util/Collection;
       6: areturn

  public java.util.Collection<io.micrometer.core.instrument.LongTaskTimer> longTaskTimers();
    Code:
       0: aload_0
       1: ldc           #98                 // class io/micrometer/core/instrument/LongTaskTimer
       3: invokespecial #175                // Method findAll:(Ljava/lang/Class;)Ljava/util/Collection;
       6: areturn

  public java.util.Collection<io.micrometer.core.instrument.FunctionCounter> functionCounters();
    Code:
       0: aload_0
       1: ldc           #90                 // class io/micrometer/core/instrument/FunctionCounter
       3: invokespecial #175                // Method findAll:(Ljava/lang/Class;)Ljava/util/Collection;
       6: areturn

  public java.util.Collection<io.micrometer.core.instrument.FunctionTimer> functionTimers();
    Code:
       0: aload_0
       1: ldc           #94                 // class io/micrometer/core/instrument/FunctionTimer
       3: invokespecial #175                // Method findAll:(Ljava/lang/Class;)Ljava/util/Collection;
       6: areturn

  public java.util.Collection<io.micrometer.core.instrument.TimeGauge> timeGauges();
    Code:
       0: aload_0
       1: ldc           #92                 // class io/micrometer/core/instrument/TimeGauge
       3: invokespecial #175                // Method findAll:(Ljava/lang/Class;)Ljava/util/Collection;
       6: areturn

  public static io.micrometer.core.instrument.search.RequiredSearch in(io.micrometer.core.instrument.MeterRegistry);
    Code:
       0: new           #11                 // class io/micrometer/core/instrument/search/RequiredSearch
       3: dup
       4: aload_0
       5: invokespecial #179                // Method "<init>":(Lio/micrometer/core/instrument/MeterRegistry;)V
       8: areturn

  private boolean lambda$meterStream$3(io.micrometer.core.instrument.Meter);
    Code:
       0: iconst_1
       1: istore_2
       2: aload_0
       3: getfield      #19                 // Field requiredTagKeys:Ljava/util/Set;
       6: invokeinterface #173,  1          // InterfaceMethod java/util/Set.isEmpty:()Z
      11: ifne          53
      14: new           #7                  // class java/util/ArrayList
      17: dup
      18: invokespecial #9                  // Method java/util/ArrayList."<init>":()V
      21: astore_3
      22: aload_1
      23: invokeinterface #182,  1          // InterfaceMethod io/micrometer/core/instrument/Meter.getId:()Lio/micrometer/core/instrument/Meter$Id;
      28: invokevirtual #186                // Method io/micrometer/core/instrument/Meter$Id.getTagsAsIterable:()Ljava/lang/Iterable;
      31: aload_3
      32: invokedynamic #192,  0            // InvokeDynamic #6:accept:(Ljava/util/List;)Ljava/util/function/Consumer;
      37: invokeinterface #49,  2           // InterfaceMethod java/lang/Iterable.forEach:(Ljava/util/function/Consumer;)V
      42: aload_3
      43: aload_0
      44: getfield      #19                 // Field requiredTagKeys:Ljava/util/Set;
      47: invokeinterface #193,  2          // InterfaceMethod java/util/List.containsAll:(Ljava/util/Collection;)Z
      52: istore_2
      53: iload_2
      54: ifeq          82
      57: aload_1
      58: invokeinterface #182,  1          // InterfaceMethod io/micrometer/core/instrument/Meter.getId:()Lio/micrometer/core/instrument/Meter$Id;
      63: invokevirtual #196                // Method io/micrometer/core/instrument/Meter$Id.getTags:()Ljava/util/List;
      66: aload_0
      67: getfield      #10                 // Field requiredTags:Ljava/util/List;
      70: invokeinterface #193,  2          // InterfaceMethod java/util/List.containsAll:(Ljava/util/Collection;)Z
      75: ifeq          82
      78: iconst_1
      79: goto          83
      82: iconst_0
      83: ireturn

  private static void lambda$meterStream$2(java.util.List, io.micrometer.core.instrument.Tag);
    Code:
       0: aload_0
       1: aload_1
       2: invokeinterface #199,  1          // InterfaceMethod io/micrometer/core/instrument/Tag.getKey:()Ljava/lang/String;
       7: invokeinterface #205,  2          // InterfaceMethod java/util/List.add:(Ljava/lang/Object;)Z
      12: pop
      13: return

  private boolean lambda$meterStream$1(io.micrometer.core.instrument.Meter);
    Code:
       0: aload_0
       1: getfield      #31                 // Field nameMatches:Ljava/util/function/Predicate;
       4: ifnull        28
       7: aload_0
       8: getfield      #31                 // Field nameMatches:Ljava/util/function/Predicate;
      11: aload_1
      12: invokeinterface #182,  1          // InterfaceMethod io/micrometer/core/instrument/Meter.getId:()Lio/micrometer/core/instrument/Meter$Id;
      17: invokevirtual #209                // Method io/micrometer/core/instrument/Meter$Id.getName:()Ljava/lang/String;
      20: invokeinterface #212,  2          // InterfaceMethod java/util/function/Predicate.test:(Ljava/lang/Object;)Z
      25: ifeq          32
      28: iconst_1
      29: goto          33
      32: iconst_0
      33: ireturn

  private static boolean lambda$name$0(java.lang.String, java.lang.String);
    Code:
       0: aload_1
       1: aload_0
       2: invokevirtual #216                // Method java/lang/String.equals:(Ljava/lang/Object;)Z
       5: ireturn
}
