Compiled from "Tool.java"
public class org.antlr.v4.Tool$Option {
  java.lang.String fieldName;

  java.lang.String name;

  org.antlr.v4.Tool$OptionArgType argType;

  java.lang.String description;

  public org.antlr.v4.Tool$Option(java.lang.String, java.lang.String, java.lang.String);
    Code:
       0: aload_0
       1: aload_1
       2: aload_2
       3: getstatic     #1                  // Field org/antlr/v4/Tool$OptionArgType.NONE:Lorg/antlr/v4/Tool$OptionArgType;
       6: aload_3
       7: invokespecial #2                  // Method "<init>":(Ljava/lang/String;Ljava/lang/String;Lorg/antlr/v4/Tool$OptionArgType;Ljava/lang/String;)V
      10: return

  public org.antlr.v4.Tool$Option(java.lang.String, java.lang.String, org.antlr.v4.Tool$OptionArgType, java.lang.String);
    Code:
       0: aload_0
       1: invokespecial #3                  // Method java/lang/Object."<init>":()V
       4: aload_0
       5: aload_1
       6: putfield      #4                  // Field fieldName:Ljava/lang/String;
       9: aload_0
      10: aload_2
      11: putfield      #5                  // Field name:Ljava/lang/String;
      14: aload_0
      15: aload_3
      16: putfield      #6                  // Field argType:Lorg/antlr/v4/Tool$OptionArgType;
      19: aload_0
      20: aload         4
      22: putfield      #7                  // Field description:Ljava/lang/String;
      25: return
}
