Compiled from "CredentialScope.java"
public class com.amazonaws.partitions.model.CredentialScope {
  private java.lang.String region;

  private java.lang.String service;

  public com.amazonaws.partitions.model.CredentialScope();
    Code:
       0: aload_0
       1: invokespecial #1                  // Method java/lang/Object."<init>":()V
       4: return

  public java.lang.String getRegion();
    Code:
       0: aload_0
       1: getfield      #2                  // Field region:Ljava/lang/String;
       4: areturn

  public void setRegion(java.lang.String);
    Code:
       0: aload_0
       1: aload_1
       2: putfield      #2                  // Field region:Ljava/lang/String;
       5: return

  public java.lang.String getService();
    Code:
       0: aload_0
       1: getfield      #3                  // Field service:Ljava/lang/String;
       4: areturn

  public void setService(java.lang.String);
    Code:
       0: aload_0
       1: aload_1
       2: putfield      #3                  // Field service:Ljava/lang/String;
       5: return
}
