Compiled from "DoneableBrokerSpec.java"
public class io.dekorate.deps.knative.eventing.v1alpha1.DoneableBrokerSpec extends io.dekorate.deps.knative.eventing.v1alpha1.BrokerSpecFluentImpl<io.dekorate.deps.knative.eventing.v1alpha1.DoneableBrokerSpec> implements io.dekorate.deps.kubernetes.api.model.Doneable<io.dekorate.deps.knative.eventing.v1alpha1.BrokerSpec> {
  private final io.dekorate.deps.knative.eventing.v1alpha1.BrokerSpecBuilder builder;

  private final io.dekorate.deps.kubernetes.api.builder.Function<io.dekorate.deps.knative.eventing.v1alpha1.BrokerSpec, io.dekorate.deps.knative.eventing.v1alpha1.BrokerSpec> function;

  public io.dekorate.deps.knative.eventing.v1alpha1.DoneableBrokerSpec(io.dekorate.deps.kubernetes.api.builder.Function<io.dekorate.deps.knative.eventing.v1alpha1.BrokerSpec, io.dekorate.deps.knative.eventing.v1alpha1.BrokerSpec>);
    Code:
       0: aload_0
       1: invokespecial #21                 // Method io/dekorate/deps/knative/eventing/v1alpha1/BrokerSpecFluentImpl."<init>":()V
       4: aload_0
       5: new           #23                 // class io/dekorate/deps/knative/eventing/v1alpha1/BrokerSpecBuilder
       8: dup
       9: aload_0
      10: invokespecial #26                 // Method io/dekorate/deps/knative/eventing/v1alpha1/BrokerSpecBuilder."<init>":(Lio/dekorate/deps/knative/eventing/v1alpha1/BrokerSpecFluent;)V
      13: putfield      #28                 // Field builder:Lio/dekorate/deps/knative/eventing/v1alpha1/BrokerSpecBuilder;
      16: aload_0
      17: aload_1
      18: putfield      #30                 // Field function:Lio/dekorate/deps/kubernetes/api/builder/Function;
      21: return

  public io.dekorate.deps.knative.eventing.v1alpha1.DoneableBrokerSpec(io.dekorate.deps.knative.eventing.v1alpha1.BrokerSpec, io.dekorate.deps.kubernetes.api.builder.Function<io.dekorate.deps.knative.eventing.v1alpha1.BrokerSpec, io.dekorate.deps.knative.eventing.v1alpha1.BrokerSpec>);
    Code:
       0: aload_0
       1: aload_1
       2: invokespecial #37                 // Method io/dekorate/deps/knative/eventing/v1alpha1/BrokerSpecFluentImpl."<init>":(Lio/dekorate/deps/knative/eventing/v1alpha1/BrokerSpec;)V
       5: aload_0
       6: new           #23                 // class io/dekorate/deps/knative/eventing/v1alpha1/BrokerSpecBuilder
       9: dup
      10: aload_0
      11: aload_1
      12: invokespecial #40                 // Method io/dekorate/deps/knative/eventing/v1alpha1/BrokerSpecBuilder."<init>":(Lio/dekorate/deps/knative/eventing/v1alpha1/BrokerSpecFluent;Lio/dekorate/deps/knative/eventing/v1alpha1/BrokerSpec;)V
      15: putfield      #28                 // Field builder:Lio/dekorate/deps/knative/eventing/v1alpha1/BrokerSpecBuilder;
      18: aload_0
      19: aload_2
      20: putfield      #30                 // Field function:Lio/dekorate/deps/kubernetes/api/builder/Function;
      23: return

  public io.dekorate.deps.knative.eventing.v1alpha1.DoneableBrokerSpec(io.dekorate.deps.knative.eventing.v1alpha1.BrokerSpec);
    Code:
       0: aload_0
       1: aload_1
       2: invokespecial #37                 // Method io/dekorate/deps/knative/eventing/v1alpha1/BrokerSpecFluentImpl."<init>":(Lio/dekorate/deps/knative/eventing/v1alpha1/BrokerSpec;)V
       5: aload_0
       6: new           #23                 // class io/dekorate/deps/knative/eventing/v1alpha1/BrokerSpecBuilder
       9: dup
      10: aload_0
      11: aload_1
      12: invokespecial #40                 // Method io/dekorate/deps/knative/eventing/v1alpha1/BrokerSpecBuilder."<init>":(Lio/dekorate/deps/knative/eventing/v1alpha1/BrokerSpecFluent;Lio/dekorate/deps/knative/eventing/v1alpha1/BrokerSpec;)V
      15: putfield      #28                 // Field builder:Lio/dekorate/deps/knative/eventing/v1alpha1/BrokerSpecBuilder;
      18: aload_0
      19: new           #10                 // class io/dekorate/deps/knative/eventing/v1alpha1/DoneableBrokerSpec$1
      22: dup
      23: aload_0
      24: invokespecial #45                 // Method io/dekorate/deps/knative/eventing/v1alpha1/DoneableBrokerSpec$1."<init>":(Lio/dekorate/deps/knative/eventing/v1alpha1/DoneableBrokerSpec;)V
      27: putfield      #30                 // Field function:Lio/dekorate/deps/kubernetes/api/builder/Function;
      30: return

  public io.dekorate.deps.knative.eventing.v1alpha1.BrokerSpec done();
    Code:
       0: aload_0
       1: getfield      #30                 // Field function:Lio/dekorate/deps/kubernetes/api/builder/Function;
       4: aload_0
       5: getfield      #28                 // Field builder:Lio/dekorate/deps/knative/eventing/v1alpha1/BrokerSpecBuilder;
       8: invokevirtual #50                 // Method io/dekorate/deps/knative/eventing/v1alpha1/BrokerSpecBuilder.build:()Lio/dekorate/deps/knative/eventing/v1alpha1/BrokerSpec;
      11: invokeinterface #56,  2           // InterfaceMethod io/dekorate/deps/kubernetes/api/builder/Function.apply:(Ljava/lang/Object;)Ljava/lang/Object;
      16: checkcast     #58                 // class io/dekorate/deps/knative/eventing/v1alpha1/BrokerSpec
      19: areturn

  public java.lang.Object done();
    Code:
       0: aload_0
       1: invokevirtual #61                 // Method done:()Lio/dekorate/deps/knative/eventing/v1alpha1/BrokerSpec;
       4: areturn
}
