Compiled from "TriggerSpecBuilder.java"
public class io.dekorate.deps.knative.eventing.v1alpha1.TriggerSpecBuilder extends io.dekorate.deps.knative.eventing.v1alpha1.TriggerSpecFluentImpl<io.dekorate.deps.knative.eventing.v1alpha1.TriggerSpecBuilder> implements io.dekorate.deps.kubernetes.api.builder.VisitableBuilder<io.dekorate.deps.knative.eventing.v1alpha1.TriggerSpec, io.dekorate.deps.knative.eventing.v1alpha1.TriggerSpecBuilder> {
  io.dekorate.deps.knative.eventing.v1alpha1.TriggerSpecFluent<?> fluent;

  java.lang.Boolean validationEnabled;

  public io.dekorate.deps.knative.eventing.v1alpha1.TriggerSpecBuilder();
    Code:
       0: aload_0
       1: iconst_1
       2: invokestatic  #21                 // Method java/lang/Boolean.valueOf:(Z)Ljava/lang/Boolean;
       5: invokespecial #24                 // Method "<init>":(Ljava/lang/Boolean;)V
       8: return

  public io.dekorate.deps.knative.eventing.v1alpha1.TriggerSpecBuilder(java.lang.Boolean);
    Code:
       0: aload_0
       1: new           #28                 // class io/dekorate/deps/knative/eventing/v1alpha1/TriggerSpec
       4: dup
       5: invokespecial #30                 // Method io/dekorate/deps/knative/eventing/v1alpha1/TriggerSpec."<init>":()V
       8: aload_1
       9: invokespecial #33                 // Method "<init>":(Lio/dekorate/deps/knative/eventing/v1alpha1/TriggerSpec;Ljava/lang/Boolean;)V
      12: return

  public io.dekorate.deps.knative.eventing.v1alpha1.TriggerSpecBuilder(io.dekorate.deps.knative.eventing.v1alpha1.TriggerSpecFluent<?>);
    Code:
       0: aload_0
       1: aload_1
       2: iconst_1
       3: invokestatic  #21                 // Method java/lang/Boolean.valueOf:(Z)Ljava/lang/Boolean;
       6: invokespecial #38                 // Method "<init>":(Lio/dekorate/deps/knative/eventing/v1alpha1/TriggerSpecFluent;Ljava/lang/Boolean;)V
       9: return

  public io.dekorate.deps.knative.eventing.v1alpha1.TriggerSpecBuilder(io.dekorate.deps.knative.eventing.v1alpha1.TriggerSpecFluent<?>, java.lang.Boolean);
    Code:
       0: aload_0
       1: aload_1
       2: new           #28                 // class io/dekorate/deps/knative/eventing/v1alpha1/TriggerSpec
       5: dup
       6: invokespecial #30                 // Method io/dekorate/deps/knative/eventing/v1alpha1/TriggerSpec."<init>":()V
       9: aload_2
      10: invokespecial #42                 // Method "<init>":(Lio/dekorate/deps/knative/eventing/v1alpha1/TriggerSpecFluent;Lio/dekorate/deps/knative/eventing/v1alpha1/TriggerSpec;Ljava/lang/Boolean;)V
      13: return

  public io.dekorate.deps.knative.eventing.v1alpha1.TriggerSpecBuilder(io.dekorate.deps.knative.eventing.v1alpha1.TriggerSpecFluent<?>, io.dekorate.deps.knative.eventing.v1alpha1.TriggerSpec);
    Code:
       0: aload_0
       1: aload_1
       2: aload_2
       3: iconst_1
       4: invokestatic  #21                 // Method java/lang/Boolean.valueOf:(Z)Ljava/lang/Boolean;
       7: invokespecial #42                 // Method "<init>":(Lio/dekorate/deps/knative/eventing/v1alpha1/TriggerSpecFluent;Lio/dekorate/deps/knative/eventing/v1alpha1/TriggerSpec;Ljava/lang/Boolean;)V
      10: return

  public io.dekorate.deps.knative.eventing.v1alpha1.TriggerSpecBuilder(io.dekorate.deps.knative.eventing.v1alpha1.TriggerSpecFluent<?>, io.dekorate.deps.knative.eventing.v1alpha1.TriggerSpec, java.lang.Boolean);
    Code:
       0: aload_0
       1: invokespecial #48                 // Method io/dekorate/deps/knative/eventing/v1alpha1/TriggerSpecFluentImpl."<init>":()V
       4: aload_0
       5: aload_1
       6: putfield      #50                 // Field fluent:Lio/dekorate/deps/knative/eventing/v1alpha1/TriggerSpecFluent;
       9: aload_1
      10: aload_2
      11: invokevirtual #54                 // Method io/dekorate/deps/knative/eventing/v1alpha1/TriggerSpec.getBroker:()Ljava/lang/String;
      14: invokeinterface #60,  2           // InterfaceMethod io/dekorate/deps/knative/eventing/v1alpha1/TriggerSpecFluent.withBroker:(Ljava/lang/String;)Lio/dekorate/deps/knative/eventing/v1alpha1/TriggerSpecFluent;
      19: pop
      20: aload_1
      21: aload_2
      22: invokevirtual #64                 // Method io/dekorate/deps/knative/eventing/v1alpha1/TriggerSpec.getFilter:()Lio/dekorate/deps/knative/eventing/v1alpha1/TriggerFilter;
      25: invokeinterface #68,  2           // InterfaceMethod io/dekorate/deps/knative/eventing/v1alpha1/TriggerSpecFluent.withFilter:(Lio/dekorate/deps/knative/eventing/v1alpha1/TriggerFilter;)Lio/dekorate/deps/knative/eventing/v1alpha1/TriggerSpecFluent;
      30: pop
      31: aload_1
      32: aload_2
      33: invokevirtual #72                 // Method io/dekorate/deps/knative/eventing/v1alpha1/TriggerSpec.getSubscriber:()Lio/dekorate/deps/knative/duck/v1/Destination;
      36: invokeinterface #76,  2           // InterfaceMethod io/dekorate/deps/knative/eventing/v1alpha1/TriggerSpecFluent.withSubscriber:(Lio/dekorate/deps/knative/duck/v1/Destination;)Lio/dekorate/deps/knative/eventing/v1alpha1/TriggerSpecFluent;
      41: pop
      42: aload_0
      43: aload_3
      44: putfield      #78                 // Field validationEnabled:Ljava/lang/Boolean;
      47: return

  public io.dekorate.deps.knative.eventing.v1alpha1.TriggerSpecBuilder(io.dekorate.deps.knative.eventing.v1alpha1.TriggerSpec);
    Code:
       0: aload_0
       1: aload_1
       2: iconst_1
       3: invokestatic  #21                 // Method java/lang/Boolean.valueOf:(Z)Ljava/lang/Boolean;
       6: invokespecial #33                 // Method "<init>":(Lio/dekorate/deps/knative/eventing/v1alpha1/TriggerSpec;Ljava/lang/Boolean;)V
       9: return

  public io.dekorate.deps.knative.eventing.v1alpha1.TriggerSpecBuilder(io.dekorate.deps.knative.eventing.v1alpha1.TriggerSpec, java.lang.Boolean);
    Code:
       0: aload_0
       1: invokespecial #48                 // Method io/dekorate/deps/knative/eventing/v1alpha1/TriggerSpecFluentImpl."<init>":()V
       4: aload_0
       5: aload_0
       6: putfield      #50                 // Field fluent:Lio/dekorate/deps/knative/eventing/v1alpha1/TriggerSpecFluent;
       9: aload_0
      10: aload_1
      11: invokevirtual #54                 // Method io/dekorate/deps/knative/eventing/v1alpha1/TriggerSpec.getBroker:()Ljava/lang/String;
      14: invokevirtual #80                 // Method withBroker:(Ljava/lang/String;)Lio/dekorate/deps/knative/eventing/v1alpha1/TriggerSpecFluent;
      17: pop
      18: aload_0
      19: aload_1
      20: invokevirtual #64                 // Method io/dekorate/deps/knative/eventing/v1alpha1/TriggerSpec.getFilter:()Lio/dekorate/deps/knative/eventing/v1alpha1/TriggerFilter;
      23: invokevirtual #81                 // Method withFilter:(Lio/dekorate/deps/knative/eventing/v1alpha1/TriggerFilter;)Lio/dekorate/deps/knative/eventing/v1alpha1/TriggerSpecFluent;
      26: pop
      27: aload_0
      28: aload_1
      29: invokevirtual #72                 // Method io/dekorate/deps/knative/eventing/v1alpha1/TriggerSpec.getSubscriber:()Lio/dekorate/deps/knative/duck/v1/Destination;
      32: invokevirtual #82                 // Method withSubscriber:(Lio/dekorate/deps/knative/duck/v1/Destination;)Lio/dekorate/deps/knative/eventing/v1alpha1/TriggerSpecFluent;
      35: pop
      36: aload_0
      37: aload_2
      38: putfield      #78                 // Field validationEnabled:Ljava/lang/Boolean;
      41: return

  public io.dekorate.deps.knative.eventing.v1alpha1.TriggerSpec build();
    Code:
       0: new           #28                 // class io/dekorate/deps/knative/eventing/v1alpha1/TriggerSpec
       3: dup
       4: aload_0
       5: getfield      #50                 // Field fluent:Lio/dekorate/deps/knative/eventing/v1alpha1/TriggerSpecFluent;
       8: invokeinterface #85,  1           // InterfaceMethod io/dekorate/deps/knative/eventing/v1alpha1/TriggerSpecFluent.getBroker:()Ljava/lang/String;
      13: aload_0
      14: getfield      #50                 // Field fluent:Lio/dekorate/deps/knative/eventing/v1alpha1/TriggerSpecFluent;
      17: invokeinterface #86,  1           // InterfaceMethod io/dekorate/deps/knative/eventing/v1alpha1/TriggerSpecFluent.getFilter:()Lio/dekorate/deps/knative/eventing/v1alpha1/TriggerFilter;
      22: aload_0
      23: getfield      #50                 // Field fluent:Lio/dekorate/deps/knative/eventing/v1alpha1/TriggerSpecFluent;
      26: invokeinterface #87,  1           // InterfaceMethod io/dekorate/deps/knative/eventing/v1alpha1/TriggerSpecFluent.getSubscriber:()Lio/dekorate/deps/knative/duck/v1/Destination;
      31: invokespecial #90                 // Method io/dekorate/deps/knative/eventing/v1alpha1/TriggerSpec."<init>":(Ljava/lang/String;Lio/dekorate/deps/knative/eventing/v1alpha1/TriggerFilter;Lio/dekorate/deps/knative/duck/v1/Destination;)V
      34: astore_1
      35: aload_1
      36: areturn

  public boolean equals(java.lang.Object);
    Code:
       0: aload_0
       1: aload_1
       2: if_acmpne     7
       5: iconst_1
       6: ireturn
       7: aload_1
       8: ifnull        22
      11: aload_0
      12: invokevirtual #99                 // Method java/lang/Object.getClass:()Ljava/lang/Class;
      15: aload_1
      16: invokevirtual #99                 // Method java/lang/Object.getClass:()Ljava/lang/Class;
      19: if_acmpeq     24
      22: iconst_0
      23: ireturn
      24: aload_0
      25: aload_1
      26: invokespecial #101                // Method io/dekorate/deps/knative/eventing/v1alpha1/TriggerSpecFluentImpl.equals:(Ljava/lang/Object;)Z
      29: ifne          34
      32: iconst_0
      33: ireturn
      34: aload_1
      35: checkcast     #2                  // class io/dekorate/deps/knative/eventing/v1alpha1/TriggerSpecBuilder
      38: astore_2
      39: aload_0
      40: getfield      #50                 // Field fluent:Lio/dekorate/deps/knative/eventing/v1alpha1/TriggerSpecFluent;
      43: ifnull        71
      46: aload_0
      47: getfield      #50                 // Field fluent:Lio/dekorate/deps/knative/eventing/v1alpha1/TriggerSpecFluent;
      50: aload_0
      51: if_acmpeq     71
      54: aload_0
      55: getfield      #50                 // Field fluent:Lio/dekorate/deps/knative/eventing/v1alpha1/TriggerSpecFluent;
      58: aload_2
      59: getfield      #50                 // Field fluent:Lio/dekorate/deps/knative/eventing/v1alpha1/TriggerSpecFluent;
      62: invokevirtual #102                // Method java/lang/Object.equals:(Ljava/lang/Object;)Z
      65: ifne          88
      68: goto          86
      71: aload_2
      72: getfield      #50                 // Field fluent:Lio/dekorate/deps/knative/eventing/v1alpha1/TriggerSpecFluent;
      75: ifnull        88
      78: aload_0
      79: getfield      #50                 // Field fluent:Lio/dekorate/deps/knative/eventing/v1alpha1/TriggerSpecFluent;
      82: aload_0
      83: if_acmpeq     88
      86: iconst_0
      87: ireturn
      88: aload_0
      89: getfield      #78                 // Field validationEnabled:Ljava/lang/Boolean;
      92: ifnull        112
      95: aload_0
      96: getfield      #78                 // Field validationEnabled:Ljava/lang/Boolean;
      99: aload_2
     100: getfield      #78                 // Field validationEnabled:Ljava/lang/Boolean;
     103: invokevirtual #103                // Method java/lang/Boolean.equals:(Ljava/lang/Object;)Z
     106: ifne          121
     109: goto          119
     112: aload_2
     113: getfield      #78                 // Field validationEnabled:Ljava/lang/Boolean;
     116: ifnull        121
     119: iconst_0
     120: ireturn
     121: iconst_1
     122: ireturn

  public java.lang.Object build();
    Code:
       0: aload_0
       1: invokevirtual #109                // Method build:()Lio/dekorate/deps/knative/eventing/v1alpha1/TriggerSpec;
       4: areturn
}
