Compiled from "SproutWebAppInitializer.java"
public class net.savantly.sprout.starter.SproutWebAppInitializer extends org.springframework.web.servlet.support.AbstractAnnotationConfigDispatcherServletInitializer {
  public net.savantly.sprout.starter.SproutWebAppInitializer();
    Code:
       0: aload_0
       1: invokespecial #1                  // Method org/springframework/web/servlet/support/AbstractAnnotationConfigDispatcherServletInitializer."<init>":()V
       4: return

  protected java.lang.Class<?>[] getRootConfigClasses();
    Code:
       0: aconst_null
       1: areturn

  protected java.lang.Class<?>[] getServletConfigClasses();
    Code:
       0: iconst_1
       1: anewarray     #2                  // class java/lang/Class
       4: dup
       5: iconst_0
       6: ldc           #3                  // class net/savantly/sprout/starter/mvc/SproutWebMvcConfigurer
       8: aastore
       9: areturn

  protected java.lang.String[] getServletMappings();
    Code:
       0: iconst_1
       1: anewarray     #4                  // class java/lang/String
       4: dup
       5: iconst_0
       6: ldc           #5                  // String /
       8: aastore
       9: areturn
}
