Compiled from "HttpRequestMapper.scala"
public final class wvlet.airframe.http.router.HttpRequestMapper {
  public static <Req, Resp, F> scala.collection.immutable.Seq<java.lang.Object> buildControllerMethodArgs(java.lang.Object, wvlet.airframe.surface.MethodSurface, Req, wvlet.airframe.http.HttpContext<Req, Resp, F>, scala.collection.immutable.Map<java.lang.String, java.lang.String>, wvlet.airframe.codec.MessageCodecFactory, boolean, wvlet.airframe.http.HttpRequestAdapter<Req>);
    Code:
       0: getstatic     #25                 // Field wvlet/airframe/http/router/HttpRequestMapper$.MODULE$:Lwvlet/airframe/http/router/HttpRequestMapper$;
       3: aload_0
       4: aload_1
       5: aload_2
       6: aload_3
       7: aload         4
       9: aload         5
      11: iload         6
      13: aload         7
      15: invokevirtual #27                 // Method wvlet/airframe/http/router/HttpRequestMapper$.buildControllerMethodArgs:(Ljava/lang/Object;Lwvlet/airframe/surface/MethodSurface;Ljava/lang/Object;Lwvlet/airframe/http/HttpContext;Lscala/collection/immutable/Map;Lwvlet/airframe/codec/MessageCodecFactory;ZLwvlet/airframe/http/HttpRequestAdapter;)Lscala/collection/immutable/Seq;
      18: areturn
}
