Compiled from "RedirectToRxEndpoint.scala"
public class wvlet.airframe.http.router.RedirectToRxEndpoint implements wvlet.log.LogSupport {
  private final wvlet.airframe.http.RxHttpEndpoint endpoint;

  private wvlet.log.Logger logger;

  private volatile boolean bitmap$0;

  private wvlet.log.Logger logger$lzycompute();
    Code:
       0: aload_0
       1: dup
       2: astore_1
       3: monitorenter
       4: aload_0
       5: getfield      #28                 // Field bitmap$0:Z
       8: ifne          24
      11: aload_0
      12: aload_0
      13: invokestatic  #34                 // InterfaceMethod wvlet/log/LazyLogger.logger$:(Lwvlet/log/LazyLogger;)Lwvlet/log/Logger;
      16: putfield      #36                 // Field logger:Lwvlet/log/Logger;
      19: aload_0
      20: iconst_1
      21: putfield      #28                 // Field bitmap$0:Z
      24: aload_1
      25: monitorexit
      26: goto          32
      29: aload_1
      30: monitorexit
      31: athrow
      32: aload_0
      33: getfield      #36                 // Field logger:Lwvlet/log/Logger;
      36: areturn
    Exception table:
       from    to  target type
           4    24    29   any

  public wvlet.log.Logger logger();
    Code:
       0: aload_0
       1: getfield      #28                 // Field bitmap$0:Z
       4: ifne          12
       7: aload_0
       8: invokespecial #42                 // Method logger$lzycompute:()Lwvlet/log/Logger;
      11: areturn
      12: aload_0
      13: getfield      #36                 // Field logger:Lwvlet/log/Logger;
      16: areturn

  public wvlet.airframe.rx.Rx<wvlet.airframe.http.HttpMessage$Response> get();
    Code:
       0: aload_0
       1: invokespecial #53                 // Method process:()Lwvlet/airframe/rx/Rx;
       4: areturn

  public wvlet.airframe.rx.Rx<wvlet.airframe.http.HttpMessage$Response> post();
    Code:
       0: aload_0
       1: invokespecial #53                 // Method process:()Lwvlet/airframe/rx/Rx;
       4: areturn

  public wvlet.airframe.rx.Rx<wvlet.airframe.http.HttpMessage$Response> put();
    Code:
       0: aload_0
       1: invokespecial #53                 // Method process:()Lwvlet/airframe/rx/Rx;
       4: areturn

  public wvlet.airframe.rx.Rx<wvlet.airframe.http.HttpMessage$Response> head();
    Code:
       0: aload_0
       1: invokespecial #53                 // Method process:()Lwvlet/airframe/rx/Rx;
       4: areturn

  public wvlet.airframe.rx.Rx<wvlet.airframe.http.HttpMessage$Response> patch();
    Code:
       0: aload_0
       1: invokespecial #53                 // Method process:()Lwvlet/airframe/rx/Rx;
       4: areturn

  public wvlet.airframe.rx.Rx<wvlet.airframe.http.HttpMessage$Response> delete();
    Code:
       0: aload_0
       1: invokespecial #53                 // Method process:()Lwvlet/airframe/rx/Rx;
       4: areturn

  public wvlet.airframe.rx.Rx<wvlet.airframe.http.HttpMessage$Response> options();
    Code:
       0: aload_0
       1: invokespecial #53                 // Method process:()Lwvlet/airframe/rx/Rx;
       4: areturn

  public wvlet.airframe.rx.Rx<wvlet.airframe.http.HttpMessage$Response> trace();
    Code:
       0: aload_0
       1: invokespecial #53                 // Method process:()Lwvlet/airframe/rx/Rx;
       4: areturn

  private wvlet.airframe.rx.Rx<wvlet.airframe.http.HttpMessage$Response> process();
    Code:
       0: getstatic     #73                 // Field wvlet/airframe/http/RPCContext$.MODULE$:Lwvlet/airframe/http/RPCContext$;
       3: invokevirtual #77                 // Method wvlet/airframe/http/RPCContext$.current:()Lwvlet/airframe/http/RPCContext;
       6: invokeinterface #83,  1           // InterfaceMethod wvlet/airframe/http/RPCContext.httpRequest:()Lwvlet/airframe/http/HttpMessage$Request;
      11: astore_1
      12: aload_0
      13: getfield      #85                 // Field endpoint:Lwvlet/airframe/http/RxHttpEndpoint;
      16: aload_1
      17: invokeinterface #91,  2           // InterfaceMethod wvlet/airframe/http/RxHttpEndpoint.apply:(Lwvlet/airframe/http/HttpMessage$Request;)Lwvlet/airframe/rx/Rx;
      22: areturn

  public wvlet.airframe.http.router.RedirectToRxEndpoint(wvlet.airframe.http.RxHttpEndpoint);
    Code:
       0: aload_0
       1: aload_1
       2: putfield      #85                 // Field endpoint:Lwvlet/airframe/http/RxHttpEndpoint;
       5: aload_0
       6: invokespecial #98                 // Method java/lang/Object."<init>":()V
       9: aload_0
      10: invokestatic  #104                // InterfaceMethod wvlet/log/LoggingMethods.$init$:(Lwvlet/log/LoggingMethods;)V
      13: aload_0
      14: invokestatic  #107                // InterfaceMethod wvlet/log/LazyLogger.$init$:(Lwvlet/log/LazyLogger;)V
      17: return
}
