Compiled from "RouteMatcher.scala"
public class wvlet.airframe.http.router.RouteMatcher$ConstantPathMapping$ extends scala.runtime.AbstractFunction4<java.lang.String, java.lang.Object, java.lang.String, scala.Option<wvlet.airframe.http.router.Route>, wvlet.airframe.http.router.RouteMatcher$ConstantPathMapping> implements java.io.Serializable {
  public static final wvlet.airframe.http.router.RouteMatcher$ConstantPathMapping$ MODULE$;

  public static {};
    Code:
       0: new           #2                  // class wvlet/airframe/http/router/RouteMatcher$ConstantPathMapping$
       3: dup
       4: invokespecial #21                 // Method "<init>":()V
       7: putstatic     #23                 // Field MODULE$:Lwvlet/airframe/http/router/RouteMatcher$ConstantPathMapping$;
      10: return

  public final java.lang.String toString();
    Code:
       0: ldc           #26                 // String ConstantPathMapping
       2: areturn

  public wvlet.airframe.http.router.RouteMatcher$ConstantPathMapping apply(java.lang.String, int, java.lang.String, scala.Option<wvlet.airframe.http.router.Route>);
    Code:
       0: new           #10                 // class wvlet/airframe/http/router/RouteMatcher$ConstantPathMapping
       3: dup
       4: aload_1
       5: iload_2
       6: aload_3
       7: aload         4
       9: invokespecial #37                 // Method wvlet/airframe/http/router/RouteMatcher$ConstantPathMapping."<init>":(Ljava/lang/String;ILjava/lang/String;Lscala/Option;)V
      12: areturn

  public scala.Option<scala.Tuple4<java.lang.String, java.lang.Object, java.lang.String, scala.Option<wvlet.airframe.http.router.Route>>> unapply(wvlet.airframe.http.router.RouteMatcher$ConstantPathMapping);
    Code:
       0: aload_1
       1: ifnonnull     8
       4: getstatic     #49                 // Field scala/None$.MODULE$:Lscala/None$;
       7: areturn
       8: new           #51                 // class scala/Some
      11: dup
      12: new           #53                 // class scala/Tuple4
      15: dup
      16: aload_1
      17: invokevirtual #55                 // Method wvlet/airframe/http/router/RouteMatcher$ConstantPathMapping.pathPrefix:()Ljava/lang/String;
      20: aload_1
      21: invokevirtual #58                 // Method wvlet/airframe/http/router/RouteMatcher$ConstantPathMapping.index:()I
      24: invokestatic  #64                 // Method scala/runtime/BoxesRunTime.boxToInteger:(I)Ljava/lang/Integer;
      27: aload_1
      28: invokevirtual #66                 // Method wvlet/airframe/http/router/RouteMatcher$ConstantPathMapping.name:()Ljava/lang/String;
      31: aload_1
      32: invokevirtual #69                 // Method wvlet/airframe/http/router/RouteMatcher$ConstantPathMapping.matchedRoute:()Lscala/Option;
      35: invokespecial #72                 // Method scala/Tuple4."<init>":(Ljava/lang/Object;Ljava/lang/Object;Ljava/lang/Object;Ljava/lang/Object;)V
      38: invokespecial #75                 // Method scala/Some."<init>":(Ljava/lang/Object;)V
      41: areturn

  private java.lang.Object writeReplace();
    Code:
       0: new           #80                 // class scala/runtime/ModuleSerializationProxy
       3: dup
       4: ldc           #2                  // class wvlet/airframe/http/router/RouteMatcher$ConstantPathMapping$
       6: invokespecial #83                 // Method scala/runtime/ModuleSerializationProxy."<init>":(Ljava/lang/Class;)V
       9: areturn

  public java.lang.Object apply(java.lang.Object, java.lang.Object, java.lang.Object, java.lang.Object);
    Code:
       0: aload_0
       1: aload_1
       2: checkcast     #90                 // class java/lang/String
       5: aload_2
       6: invokestatic  #94                 // Method scala/runtime/BoxesRunTime.unboxToInt:(Ljava/lang/Object;)I
       9: aload_3
      10: checkcast     #90                 // class java/lang/String
      13: aload         4
      15: checkcast     #96                 // class scala/Option
      18: invokevirtual #98                 // Method apply:(Ljava/lang/String;ILjava/lang/String;Lscala/Option;)Lwvlet/airframe/http/router/RouteMatcher$ConstantPathMapping;
      21: areturn

  public wvlet.airframe.http.router.RouteMatcher$ConstantPathMapping$();
    Code:
       0: aload_0
       1: invokespecial #100                // Method scala/runtime/AbstractFunction4."<init>":()V
       4: return
}
