Compiled from "PositiveOrZeroValidatorForLong.java"
public class org.hibernate.validator.internal.constraintvalidators.bv.number.sign.PositiveOrZeroValidatorForLong implements javax.validation.ConstraintValidator<javax.validation.constraints.PositiveOrZero, java.lang.Long> {
  public org.hibernate.validator.internal.constraintvalidators.bv.number.sign.PositiveOrZeroValidatorForLong();
    Code:
       0: aload_0
       1: invokespecial #1                  // Method java/lang/Object."<init>":()V
       4: return

  public boolean isValid(java.lang.Long, javax.validation.ConstraintValidatorContext);
    Code:
       0: aload_1
       1: ifnonnull     6
       4: iconst_1
       5: ireturn
       6: aload_1
       7: invokestatic  #2                  // Method org/hibernate/validator/internal/constraintvalidators/bv/number/sign/NumberSignHelper.signum:(Ljava/lang/Long;)I
      10: iflt          17
      13: iconst_1
      14: goto          18
      17: iconst_0
      18: ireturn

  public boolean isValid(java.lang.Object, javax.validation.ConstraintValidatorContext);
    Code:
       0: aload_0
       1: aload_1
       2: checkcast     #3                  // class java/lang/Long
       5: aload_2
       6: invokevirtual #4                  // Method isValid:(Ljava/lang/Long;Ljavax/validation/ConstraintValidatorContext;)Z
       9: ireturn
}
