Compiled from "LogbackLogger.java"
class org.sonar.api.utils.log.LogbackLogger$1 {
  static final int[] $SwitchMap$org$sonar$api$utils$log$LoggerLevel;

  static {};
    Code:
       0: invokestatic  #19                 // Method org/sonar/api/utils/log/LoggerLevel.values:()[Lorg/sonar/api/utils/log/LoggerLevel;
       3: arraylength
       4: newarray       int
       6: putstatic     #21                 // Field $SwitchMap$org$sonar$api$utils$log$LoggerLevel:[I
       9: getstatic     #21                 // Field $SwitchMap$org$sonar$api$utils$log$LoggerLevel:[I
      12: getstatic     #25                 // Field org/sonar/api/utils/log/LoggerLevel.TRACE:Lorg/sonar/api/utils/log/LoggerLevel;
      15: invokevirtual #29                 // Method org/sonar/api/utils/log/LoggerLevel.ordinal:()I
      18: iconst_1
      19: iastore
      20: goto          24
      23: astore_0
      24: getstatic     #21                 // Field $SwitchMap$org$sonar$api$utils$log$LoggerLevel:[I
      27: getstatic     #32                 // Field org/sonar/api/utils/log/LoggerLevel.DEBUG:Lorg/sonar/api/utils/log/LoggerLevel;
      30: invokevirtual #29                 // Method org/sonar/api/utils/log/LoggerLevel.ordinal:()I
      33: iconst_2
      34: iastore
      35: goto          39
      38: astore_0
      39: getstatic     #21                 // Field $SwitchMap$org$sonar$api$utils$log$LoggerLevel:[I
      42: getstatic     #35                 // Field org/sonar/api/utils/log/LoggerLevel.INFO:Lorg/sonar/api/utils/log/LoggerLevel;
      45: invokevirtual #29                 // Method org/sonar/api/utils/log/LoggerLevel.ordinal:()I
      48: iconst_3
      49: iastore
      50: goto          54
      53: astore_0
      54: return
    Exception table:
       from    to  target type
           9    20    23   Class java/lang/NoSuchFieldError
          24    35    38   Class java/lang/NoSuchFieldError
          39    50    53   Class java/lang/NoSuchFieldError
}
