Compiled from "BigInt.scala"
public final class scalaz.std.math.bigInt$ implements scalaz.std.math.BigInts {
  public static final scalaz.std.math.bigInt$ MODULE$;

  private static scalaz.Monoid<scala.math.BigInt> bigIntInstance;

  private static scalaz.Monoid<java.lang.Object> bigIntMultiplication;

  public static {};
    Code:
       0: new           #2                  // class scalaz/std/math/bigInt$
       3: dup
       4: invokespecial #19                 // Method "<init>":()V
       7: putstatic     #21                 // Field MODULE$:Lscalaz/std/math/bigInt$;
      10: getstatic     #21                 // Field MODULE$:Lscalaz/std/math/bigInt$;
      13: invokestatic  #25                 // InterfaceMethod scalaz/std/math/BigInts.$init$:(Lscalaz/std/math/BigInts;)V
      16: return

  public scalaz.Monoid<scala.math.BigInt> bigIntInstance();
    Code:
       0: getstatic     #29                 // Field bigIntInstance:Lscalaz/Monoid;
       3: areturn

  public scalaz.Monoid<java.lang.Object> bigIntMultiplication();
    Code:
       0: getstatic     #33                 // Field bigIntMultiplication:Lscalaz/Monoid;
       3: areturn

  public void scalaz$std$math$BigInts$_setter_$bigIntInstance_$eq(scalaz.Monoid<scala.math.BigInt>);
    Code:
       0: aload_1
       1: putstatic     #29                 // Field bigIntInstance:Lscalaz/Monoid;
       4: return

  public void scalaz$std$math$BigInts$_setter_$bigIntMultiplication_$eq(scalaz.Monoid<java.lang.Object>);
    Code:
       0: aload_1
       1: putstatic     #33                 // Field bigIntMultiplication:Lscalaz/Monoid;
       4: return

  private scalaz.std.math.bigInt$();
    Code:
       0: aload_0
       1: invokespecial #40                 // Method java/lang/Object."<init>":()V
       4: return
}
