Compiled from "ScaleXPointMap.java"
public class org.bouncycastle.math.ec.ScaleXPointMap implements org.bouncycastle.math.ec.ECPointMap {
  protected final org.bouncycastle.math.ec.ECFieldElement scale;

  public org.bouncycastle.math.ec.ScaleXPointMap(org.bouncycastle.math.ec.ECFieldElement);
    Code:
       0: aload_0
       1: invokespecial #1                  // Method java/lang/Object."<init>":()V
       4: aload_0
       5: aload_1
       6: putfield      #2                  // Field scale:Lorg/bouncycastle/math/ec/ECFieldElement;
       9: return

  public org.bouncycastle.math.ec.ECPoint map(org.bouncycastle.math.ec.ECPoint);
    Code:
       0: aload_1
       1: aload_0
       2: getfield      #2                  // Field scale:Lorg/bouncycastle/math/ec/ECFieldElement;
       5: invokevirtual #3                  // Method org/bouncycastle/math/ec/ECPoint.scaleX:(Lorg/bouncycastle/math/ec/ECFieldElement;)Lorg/bouncycastle/math/ec/ECPoint;
       8: areturn
}
