Compiled from "KrbRuntime.java"
public class org.apache.kerby.kerberos.kerb.KrbRuntime {
  private static org.apache.kerby.kerberos.kerb.provider.TokenProvider tokenProvider;

  public org.apache.kerby.kerberos.kerb.KrbRuntime();
    Code:
       0: aload_0
       1: invokespecial #1                  // Method java/lang/Object."<init>":()V
       4: return

  public static synchronized org.apache.kerby.kerberos.kerb.provider.TokenProvider getTokenProvider();
    Code:
       0: getstatic     #2                  // Field tokenProvider:Lorg/apache/kerby/kerberos/kerb/provider/TokenProvider;
       3: ifnonnull     16
       6: new           #3                  // class java/lang/RuntimeException
       9: dup
      10: ldc           #4                  // String No token provider is available
      12: invokespecial #5                  // Method java/lang/RuntimeException."<init>":(Ljava/lang/String;)V
      15: athrow
      16: getstatic     #2                  // Field tokenProvider:Lorg/apache/kerby/kerberos/kerb/provider/TokenProvider;
      19: areturn

  public static synchronized void setTokenProvider(org.apache.kerby.kerberos.kerb.provider.TokenProvider);
    Code:
       0: aload_0
       1: putstatic     #2                  // Field tokenProvider:Lorg/apache/kerby/kerberos/kerb/provider/TokenProvider;
       4: return
}
