Compiled from "WorkerInfo.java"
public class org.apache.pulsar.common.functions.WorkerInfo {
  private static final org.slf4j.Logger log;

  private java.lang.String workerId;

  private java.lang.String workerHostname;

  private int port;

  public static org.apache.pulsar.common.functions.WorkerInfo of(java.lang.String, java.lang.String, int);
    Code:
       0: new           #1                  // class org/apache/pulsar/common/functions/WorkerInfo
       3: dup
       4: aload_0
       5: aload_1
       6: iload_2
       7: invokespecial #2                  // Method "<init>":(Ljava/lang/String;Ljava/lang/String;I)V
      10: areturn

  public static org.apache.pulsar.common.functions.WorkerInfo parseFrom(java.lang.String);
    Code:
       0: aload_0
       1: ldc           #3                  // String :
       3: invokevirtual #4                  // Method java/lang/String.split:(Ljava/lang/String;)[Ljava/lang/String;
       6: astore_1
       7: aload_1
       8: arraylength
       9: iconst_3
      10: if_icmpeq     40
      13: new           #5                  // class java/lang/IllegalArgumentException
      16: dup
      17: new           #6                  // class java/lang/StringBuilder
      20: dup
      21: invokespecial #7                  // Method java/lang/StringBuilder."<init>":()V
      24: ldc           #8                  // String Invalid string to parse WorkerInfo :
      26: invokevirtual #9                  // Method java/lang/StringBuilder.append:(Ljava/lang/String;)Ljava/lang/StringBuilder;
      29: aload_0
      30: invokevirtual #9                  // Method java/lang/StringBuilder.append:(Ljava/lang/String;)Ljava/lang/StringBuilder;
      33: invokevirtual #10                 // Method java/lang/StringBuilder.toString:()Ljava/lang/String;
      36: invokespecial #11                 // Method java/lang/IllegalArgumentException."<init>":(Ljava/lang/String;)V
      39: athrow
      40: aload_1
      41: iconst_0
      42: aaload
      43: astore_2
      44: aload_1
      45: iconst_1
      46: aaload
      47: astore_3
      48: aload_1
      49: iconst_2
      50: aaload
      51: invokestatic  #12                 // Method java/lang/Integer.parseInt:(Ljava/lang/String;)I
      54: istore        4
      56: new           #1                  // class org/apache/pulsar/common/functions/WorkerInfo
      59: dup
      60: aload_2
      61: aload_3
      62: iload         4
      64: invokespecial #2                  // Method "<init>":(Ljava/lang/String;Ljava/lang/String;I)V
      67: areturn
      68: astore        4
      70: getstatic     #14                 // Field log:Lorg/slf4j/Logger;
      73: ldc           #15                 // String Invalid worker info : {}
      75: aload_0
      76: invokeinterface #16,  3           // InterfaceMethod org/slf4j/Logger.warn:(Ljava/lang/String;Ljava/lang/Object;)V
      81: aload         4
      83: athrow
    Exception table:
       from    to  target type
          48    67    68   Class java/lang/NumberFormatException

  public java.lang.String getWorkerId();
    Code:
       0: aload_0
       1: getfield      #17                 // Field workerId:Ljava/lang/String;
       4: areturn

  public java.lang.String getWorkerHostname();
    Code:
       0: aload_0
       1: getfield      #18                 // Field workerHostname:Ljava/lang/String;
       4: areturn

  public int getPort();
    Code:
       0: aload_0
       1: getfield      #19                 // Field port:I
       4: ireturn

  private org.apache.pulsar.common.functions.WorkerInfo(java.lang.String, java.lang.String, int);
    Code:
       0: aload_0
       1: invokespecial #20                 // Method java/lang/Object."<init>":()V
       4: aload_0
       5: aload_1
       6: putfield      #17                 // Field workerId:Ljava/lang/String;
       9: aload_0
      10: aload_2
      11: putfield      #18                 // Field workerHostname:Ljava/lang/String;
      14: aload_0
      15: iload_3
      16: putfield      #19                 // Field port:I
      19: return

  public org.apache.pulsar.common.functions.WorkerInfo();
    Code:
       0: aload_0
       1: invokespecial #20                 // Method java/lang/Object."<init>":()V
       4: return

  public java.lang.String toString();
    Code:
       0: new           #6                  // class java/lang/StringBuilder
       3: dup
       4: invokespecial #7                  // Method java/lang/StringBuilder."<init>":()V
       7: ldc           #21                 // String WorkerInfo(workerId=
       9: invokevirtual #9                  // Method java/lang/StringBuilder.append:(Ljava/lang/String;)Ljava/lang/StringBuilder;
      12: aload_0
      13: invokevirtual #22                 // Method getWorkerId:()Ljava/lang/String;
      16: invokevirtual #9                  // Method java/lang/StringBuilder.append:(Ljava/lang/String;)Ljava/lang/StringBuilder;
      19: ldc           #23                 // String , workerHostname=
      21: invokevirtual #9                  // Method java/lang/StringBuilder.append:(Ljava/lang/String;)Ljava/lang/StringBuilder;
      24: aload_0
      25: invokevirtual #24                 // Method getWorkerHostname:()Ljava/lang/String;
      28: invokevirtual #9                  // Method java/lang/StringBuilder.append:(Ljava/lang/String;)Ljava/lang/StringBuilder;
      31: ldc           #25                 // String , port=
      33: invokevirtual #9                  // Method java/lang/StringBuilder.append:(Ljava/lang/String;)Ljava/lang/StringBuilder;
      36: aload_0
      37: invokevirtual #26                 // Method getPort:()I
      40: invokevirtual #27                 // Method java/lang/StringBuilder.append:(I)Ljava/lang/StringBuilder;
      43: ldc           #28                 // String )
      45: invokevirtual #9                  // Method java/lang/StringBuilder.append:(Ljava/lang/String;)Ljava/lang/StringBuilder;
      48: invokevirtual #10                 // Method java/lang/StringBuilder.toString:()Ljava/lang/String;
      51: areturn

  static {};
    Code:
       0: ldc           #1                  // class org/apache/pulsar/common/functions/WorkerInfo
       2: invokestatic  #29                 // Method org/slf4j/LoggerFactory.getLogger:(Ljava/lang/Class;)Lorg/slf4j/Logger;
       5: putstatic     #14                 // Field log:Lorg/slf4j/Logger;
       8: return
}
