Compiled from "CurrencyTypeDescriptor.java"
public class org.hibernate.type.descriptor.java.CurrencyTypeDescriptor extends org.hibernate.type.descriptor.java.AbstractTypeDescriptor<java.util.Currency> {
  public static final org.hibernate.type.descriptor.java.CurrencyTypeDescriptor INSTANCE;

  public org.hibernate.type.descriptor.java.CurrencyTypeDescriptor();
    Code:
       0: aload_0
       1: ldc           #1                  // class java/util/Currency
       3: invokespecial #2                  // Method org/hibernate/type/descriptor/java/AbstractTypeDescriptor."<init>":(Ljava/lang/Class;)V
       6: return

  public java.lang.String toString(java.util.Currency);
    Code:
       0: aload_1
       1: invokevirtual #3                  // Method java/util/Currency.getCurrencyCode:()Ljava/lang/String;
       4: areturn

  public java.util.Currency fromString(java.lang.String);
    Code:
       0: aload_1
       1: invokestatic  #4                  // Method java/util/Currency.getInstance:(Ljava/lang/String;)Ljava/util/Currency;
       4: areturn

  public <X> X unwrap(java.util.Currency, java.lang.Class<X>, org.hibernate.type.descriptor.WrapperOptions);
    Code:
       0: aload_1
       1: ifnonnull     6
       4: aconst_null
       5: areturn
       6: ldc           #5                  // class java/lang/String
       8: aload_2
       9: invokevirtual #6                  // Method java/lang/Class.isAssignableFrom:(Ljava/lang/Class;)Z
      12: ifeq          20
      15: aload_1
      16: invokevirtual #3                  // Method java/util/Currency.getCurrencyCode:()Ljava/lang/String;
      19: areturn
      20: aload_0
      21: aload_2
      22: invokevirtual #7                  // Method unknownUnwrap:(Ljava/lang/Class;)Lorg/hibernate/HibernateException;
      25: athrow

  public <X> java.util.Currency wrap(X, org.hibernate.type.descriptor.WrapperOptions);
    Code:
       0: aload_1
       1: ifnonnull     6
       4: aconst_null
       5: areturn
       6: ldc           #5                  // class java/lang/String
       8: aload_1
       9: invokevirtual #8                  // Method java/lang/Class.isInstance:(Ljava/lang/Object;)Z
      12: ifeq          23
      15: aload_1
      16: checkcast     #5                  // class java/lang/String
      19: invokestatic  #4                  // Method java/util/Currency.getInstance:(Ljava/lang/String;)Ljava/util/Currency;
      22: areturn
      23: aload_0
      24: aload_1
      25: invokevirtual #9                  // Method java/lang/Object.getClass:()Ljava/lang/Class;
      28: invokevirtual #10                 // Method unknownWrap:(Ljava/lang/Class;)Lorg/hibernate/HibernateException;
      31: athrow

  public java.lang.Object wrap(java.lang.Object, org.hibernate.type.descriptor.WrapperOptions);
    Code:
       0: aload_0
       1: aload_1
       2: aload_2
       3: invokevirtual #11                 // Method wrap:(Ljava/lang/Object;Lorg/hibernate/type/descriptor/WrapperOptions;)Ljava/util/Currency;
       6: areturn

  public java.lang.Object unwrap(java.lang.Object, java.lang.Class, org.hibernate.type.descriptor.WrapperOptions);
    Code:
       0: aload_0
       1: aload_1
       2: checkcast     #1                  // class java/util/Currency
       5: aload_2
       6: aload_3
       7: invokevirtual #12                 // Method unwrap:(Ljava/util/Currency;Ljava/lang/Class;Lorg/hibernate/type/descriptor/WrapperOptions;)Ljava/lang/Object;
      10: areturn

  public java.lang.Object fromString(java.lang.String);
    Code:
       0: aload_0
       1: aload_1
       2: invokevirtual #13                 // Method fromString:(Ljava/lang/String;)Ljava/util/Currency;
       5: areturn

  public java.lang.String toString(java.lang.Object);
    Code:
       0: aload_0
       1: aload_1
       2: checkcast     #1                  // class java/util/Currency
       5: invokevirtual #14                 // Method toString:(Ljava/util/Currency;)Ljava/lang/String;
       8: areturn

  static {};
    Code:
       0: new           #15                 // class org/hibernate/type/descriptor/java/CurrencyTypeDescriptor
       3: dup
       4: invokespecial #16                 // Method "<init>":()V
       7: putstatic     #17                 // Field INSTANCE:Lorg/hibernate/type/descriptor/java/CurrencyTypeDescriptor;
      10: return
}
