Compiled from "URIDomainExpressionBuilder.java"
public class org.apache.cxf.ws.policy.attachment.external.URIDomainExpressionBuilder implements org.apache.cxf.ws.policy.attachment.external.DomainExpressionBuilder {
  private static final java.util.Collection<javax.xml.namespace.QName> SUPPORTED_TYPES;

  public org.apache.cxf.ws.policy.attachment.external.URIDomainExpressionBuilder();
    Code:
       0: aload_0
       1: invokespecial #1                  // Method java/lang/Object."<init>":()V
       4: return

  public org.apache.cxf.ws.policy.attachment.external.DomainExpression build(org.w3c.dom.Element);
    Code:
       0: new           #2                  // class org/apache/cxf/ws/policy/attachment/external/URIDomainExpression
       3: dup
       4: aload_1
       5: invokeinterface #3,  1            // InterfaceMethod org/w3c/dom/Element.getTextContent:()Ljava/lang/String;
      10: invokespecial #4                  // Method org/apache/cxf/ws/policy/attachment/external/URIDomainExpression."<init>":(Ljava/lang/String;)V
      13: areturn

  public java.util.Collection<javax.xml.namespace.QName> getDomainExpressionTypes();
    Code:
       0: getstatic     #5                  // Field SUPPORTED_TYPES:Ljava/util/Collection;
       3: areturn

  static {};
    Code:
       0: iconst_2
       1: anewarray     #6                  // class javax/xml/namespace/QName
       4: dup
       5: iconst_0
       6: new           #6                  // class javax/xml/namespace/QName
       9: dup
      10: ldc           #7                  // String http://www.w3.org/ns/ws-policy
      12: ldc           #8                  // String URI
      14: invokespecial #9                  // Method javax/xml/namespace/QName."<init>":(Ljava/lang/String;Ljava/lang/String;)V
      17: aastore
      18: dup
      19: iconst_1
      20: new           #6                  // class javax/xml/namespace/QName
      23: dup
      24: ldc           #10                 // String http://schemas.xmlsoap.org/ws/2004/09/policy
      26: ldc           #8                  // String URI
      28: invokespecial #9                  // Method javax/xml/namespace/QName."<init>":(Ljava/lang/String;Ljava/lang/String;)V
      31: aastore
      32: invokestatic  #11                 // Method java/util/Arrays.asList:([Ljava/lang/Object;)Ljava/util/List;
      35: invokestatic  #12                 // Method java/util/Collections.unmodifiableList:(Ljava/util/List;)Ljava/util/List;
      38: putstatic     #5                  // Field SUPPORTED_TYPES:Ljava/util/Collection;
      41: return
}
