Compiled from "ListImportsIterable.java"
class software.amazon.awssdk.services.dynamodb.paginators.ListImportsIterable$ListImportsResponseFetcher implements software.amazon.awssdk.core.pagination.sync.SyncPageFetcher<software.amazon.awssdk.services.dynamodb.model.ListImportsResponse> {
  final software.amazon.awssdk.services.dynamodb.paginators.ListImportsIterable this$0;

  private software.amazon.awssdk.services.dynamodb.paginators.ListImportsIterable$ListImportsResponseFetcher(software.amazon.awssdk.services.dynamodb.paginators.ListImportsIterable);
    Code:
       0: aload_0
       1: aload_1
       2: putfield      #2                  // Field this$0:Lsoftware/amazon/awssdk/services/dynamodb/paginators/ListImportsIterable;
       5: aload_0
       6: invokespecial #3                  // Method java/lang/Object."<init>":()V
       9: return

  public boolean hasNextPage(software.amazon.awssdk.services.dynamodb.model.ListImportsResponse);
    Code:
       0: aload_1
       1: invokevirtual #4                  // Method software/amazon/awssdk/services/dynamodb/model/ListImportsResponse.nextToken:()Ljava/lang/String;
       4: invokestatic  #5                  // Method software/amazon/awssdk/core/util/PaginatorUtils.isOutputTokenAvailable:(Ljava/lang/Object;)Z
       7: ireturn

  public software.amazon.awssdk.services.dynamodb.model.ListImportsResponse nextPage(software.amazon.awssdk.services.dynamodb.model.ListImportsResponse);
    Code:
       0: aload_1
       1: ifnonnull     24
       4: aload_0
       5: getfield      #2                  // Field this$0:Lsoftware/amazon/awssdk/services/dynamodb/paginators/ListImportsIterable;
       8: invokestatic  #6                  // Method software/amazon/awssdk/services/dynamodb/paginators/ListImportsIterable.access$200:(Lsoftware/amazon/awssdk/services/dynamodb/paginators/ListImportsIterable;)Lsoftware/amazon/awssdk/services/dynamodb/DynamoDbClient;
      11: aload_0
      12: getfield      #2                  // Field this$0:Lsoftware/amazon/awssdk/services/dynamodb/paginators/ListImportsIterable;
      15: invokestatic  #7                  // Method software/amazon/awssdk/services/dynamodb/paginators/ListImportsIterable.access$100:(Lsoftware/amazon/awssdk/services/dynamodb/paginators/ListImportsIterable;)Lsoftware/amazon/awssdk/services/dynamodb/model/ListImportsRequest;
      18: invokeinterface #8,  2            // InterfaceMethod software/amazon/awssdk/services/dynamodb/DynamoDbClient.listImports:(Lsoftware/amazon/awssdk/services/dynamodb/model/ListImportsRequest;)Lsoftware/amazon/awssdk/services/dynamodb/model/ListImportsResponse;
      23: areturn
      24: aload_0
      25: getfield      #2                  // Field this$0:Lsoftware/amazon/awssdk/services/dynamodb/paginators/ListImportsIterable;
      28: invokestatic  #6                  // Method software/amazon/awssdk/services/dynamodb/paginators/ListImportsIterable.access$200:(Lsoftware/amazon/awssdk/services/dynamodb/paginators/ListImportsIterable;)Lsoftware/amazon/awssdk/services/dynamodb/DynamoDbClient;
      31: aload_0
      32: getfield      #2                  // Field this$0:Lsoftware/amazon/awssdk/services/dynamodb/paginators/ListImportsIterable;
      35: invokestatic  #7                  // Method software/amazon/awssdk/services/dynamodb/paginators/ListImportsIterable.access$100:(Lsoftware/amazon/awssdk/services/dynamodb/paginators/ListImportsIterable;)Lsoftware/amazon/awssdk/services/dynamodb/model/ListImportsRequest;
      38: invokevirtual #9                  // Method software/amazon/awssdk/services/dynamodb/model/ListImportsRequest.toBuilder:()Lsoftware/amazon/awssdk/services/dynamodb/model/ListImportsRequest$Builder;
      41: aload_1
      42: invokevirtual #4                  // Method software/amazon/awssdk/services/dynamodb/model/ListImportsResponse.nextToken:()Ljava/lang/String;
      45: invokeinterface #10,  2           // InterfaceMethod software/amazon/awssdk/services/dynamodb/model/ListImportsRequest$Builder.nextToken:(Ljava/lang/String;)Lsoftware/amazon/awssdk/services/dynamodb/model/ListImportsRequest$Builder;
      50: invokeinterface #11,  1           // InterfaceMethod software/amazon/awssdk/services/dynamodb/model/ListImportsRequest$Builder.build:()Ljava/lang/Object;
      55: checkcast     #12                 // class software/amazon/awssdk/services/dynamodb/model/ListImportsRequest
      58: invokeinterface #8,  2            // InterfaceMethod software/amazon/awssdk/services/dynamodb/DynamoDbClient.listImports:(Lsoftware/amazon/awssdk/services/dynamodb/model/ListImportsRequest;)Lsoftware/amazon/awssdk/services/dynamodb/model/ListImportsResponse;
      63: areturn

  public java.lang.Object nextPage(java.lang.Object);
    Code:
       0: aload_0
       1: aload_1
       2: checkcast     #13                 // class software/amazon/awssdk/services/dynamodb/model/ListImportsResponse
       5: invokevirtual #14                 // Method nextPage:(Lsoftware/amazon/awssdk/services/dynamodb/model/ListImportsResponse;)Lsoftware/amazon/awssdk/services/dynamodb/model/ListImportsResponse;
       8: areturn

  public boolean hasNextPage(java.lang.Object);
    Code:
       0: aload_0
       1: aload_1
       2: checkcast     #13                 // class software/amazon/awssdk/services/dynamodb/model/ListImportsResponse
       5: invokevirtual #15                 // Method hasNextPage:(Lsoftware/amazon/awssdk/services/dynamodb/model/ListImportsResponse;)Z
       8: ireturn

  software.amazon.awssdk.services.dynamodb.paginators.ListImportsIterable$ListImportsResponseFetcher(software.amazon.awssdk.services.dynamodb.paginators.ListImportsIterable, software.amazon.awssdk.services.dynamodb.paginators.ListImportsIterable$1);
    Code:
       0: aload_0
       1: aload_1
       2: invokespecial #1                  // Method "<init>":(Lsoftware/amazon/awssdk/services/dynamodb/paginators/ListImportsIterable;)V
       5: return
}
