Compiled from "SpringTransactionSynchronizationManager.java"
final class org.springframework.data.transaction.SpringTransactionSynchronizationManager extends java.lang.Enum<org.springframework.data.transaction.SpringTransactionSynchronizationManager> implements org.springframework.data.transaction.SynchronizationManager {
  public static final org.springframework.data.transaction.SpringTransactionSynchronizationManager INSTANCE;

  private static final org.springframework.data.transaction.SpringTransactionSynchronizationManager[] $VALUES;

  public static org.springframework.data.transaction.SpringTransactionSynchronizationManager[] values();
    Code:
       0: getstatic     #1                  // Field $VALUES:[Lorg/springframework/data/transaction/SpringTransactionSynchronizationManager;
       3: invokevirtual #2                  // Method "[Lorg/springframework/data/transaction/SpringTransactionSynchronizationManager;".clone:()Ljava/lang/Object;
       6: checkcast     #3                  // class "[Lorg/springframework/data/transaction/SpringTransactionSynchronizationManager;"
       9: areturn

  public static org.springframework.data.transaction.SpringTransactionSynchronizationManager valueOf(java.lang.String);
    Code:
       0: ldc           #4                  // class org/springframework/data/transaction/SpringTransactionSynchronizationManager
       2: aload_0
       3: invokestatic  #5                  // Method java/lang/Enum.valueOf:(Ljava/lang/Class;Ljava/lang/String;)Ljava/lang/Enum;
       6: checkcast     #4                  // class org/springframework/data/transaction/SpringTransactionSynchronizationManager
       9: areturn

  private org.springframework.data.transaction.SpringTransactionSynchronizationManager();
    Code:
       0: aload_0
       1: aload_1
       2: iload_2
       3: invokespecial #6                  // Method java/lang/Enum."<init>":(Ljava/lang/String;I)V
       6: return

  public void initSynchronization();
    Code:
       0: invokestatic  #7                  // Method org/springframework/transaction/support/TransactionSynchronizationManager.initSynchronization:()V
       3: return

  public boolean isSynchronizationActive();
    Code:
       0: invokestatic  #8                  // Method org/springframework/transaction/support/TransactionSynchronizationManager.isSynchronizationActive:()Z
       3: ireturn

  public void clearSynchronization();
    Code:
       0: invokestatic  #9                  // Method org/springframework/transaction/support/TransactionSynchronizationManager.clear:()V
       3: return

  static {};
    Code:
       0: new           #4                  // class org/springframework/data/transaction/SpringTransactionSynchronizationManager
       3: dup
       4: ldc           #10                 // String INSTANCE
       6: iconst_0
       7: invokespecial #11                 // Method "<init>":(Ljava/lang/String;I)V
      10: putstatic     #12                 // Field INSTANCE:Lorg/springframework/data/transaction/SpringTransactionSynchronizationManager;
      13: iconst_1
      14: anewarray     #4                  // class org/springframework/data/transaction/SpringTransactionSynchronizationManager
      17: dup
      18: iconst_0
      19: getstatic     #12                 // Field INSTANCE:Lorg/springframework/data/transaction/SpringTransactionSynchronizationManager;
      22: aastore
      23: putstatic     #1                  // Field $VALUES:[Lorg/springframework/data/transaction/SpringTransactionSynchronizationManager;
      26: return
}
