Compiled from "RedisProperties.java"
public class org.springframework.boot.autoconfigure.data.redis.RedisProperties$Lettuce {
  private java.time.Duration shutdownTimeout;

  private org.springframework.boot.autoconfigure.data.redis.RedisProperties$Pool pool;

  private final org.springframework.boot.autoconfigure.data.redis.RedisProperties$Lettuce$Cluster cluster;

  public org.springframework.boot.autoconfigure.data.redis.RedisProperties$Lettuce();
    Code:
       0: aload_0
       1: invokespecial #1                  // Method java/lang/Object."<init>":()V
       4: aload_0
       5: ldc2_w        #2                  // long 100l
       8: invokestatic  #4                  // Method java/time/Duration.ofMillis:(J)Ljava/time/Duration;
      11: putfield      #5                  // Field shutdownTimeout:Ljava/time/Duration;
      14: aload_0
      15: new           #6                  // class org/springframework/boot/autoconfigure/data/redis/RedisProperties$Lettuce$Cluster
      18: dup
      19: invokespecial #7                  // Method org/springframework/boot/autoconfigure/data/redis/RedisProperties$Lettuce$Cluster."<init>":()V
      22: putfield      #8                  // Field cluster:Lorg/springframework/boot/autoconfigure/data/redis/RedisProperties$Lettuce$Cluster;
      25: return

  public java.time.Duration getShutdownTimeout();
    Code:
       0: aload_0
       1: getfield      #5                  // Field shutdownTimeout:Ljava/time/Duration;
       4: areturn

  public void setShutdownTimeout(java.time.Duration);
    Code:
       0: aload_0
       1: aload_1
       2: putfield      #5                  // Field shutdownTimeout:Ljava/time/Duration;
       5: return

  public org.springframework.boot.autoconfigure.data.redis.RedisProperties$Pool getPool();
    Code:
       0: aload_0
       1: getfield      #9                  // Field pool:Lorg/springframework/boot/autoconfigure/data/redis/RedisProperties$Pool;
       4: areturn

  public void setPool(org.springframework.boot.autoconfigure.data.redis.RedisProperties$Pool);
    Code:
       0: aload_0
       1: aload_1
       2: putfield      #9                  // Field pool:Lorg/springframework/boot/autoconfigure/data/redis/RedisProperties$Pool;
       5: return

  public org.springframework.boot.autoconfigure.data.redis.RedisProperties$Lettuce$Cluster getCluster();
    Code:
       0: aload_0
       1: getfield      #8                  // Field cluster:Lorg/springframework/boot/autoconfigure/data/redis/RedisProperties$Lettuce$Cluster;
       4: areturn
}
