Compiled from "ServiceAuthorizationManager.java"
public class org.apache.hadoop.security.authorize.ServiceAuthorizationManager {
  static final java.lang.String BLOCKED;

  static final java.lang.String HOSTS;

  private static final java.lang.String HADOOP_POLICY_FILE;

  private volatile java.util.Map<java.lang.Class<?>, org.apache.hadoop.security.authorize.AccessControlList[]> protocolToAcls;

  private volatile java.util.Map<java.lang.Class<?>, org.apache.hadoop.util.MachineList[]> protocolToMachineLists;

  public static final java.lang.String SERVICE_AUTHORIZATION_CONFIG;

  public static final org.slf4j.Logger AUDITLOG;

  private static final java.lang.String AUTHZ_SUCCESSFUL_FOR;

  private static final java.lang.String AUTHZ_FAILED_FOR;

  public org.apache.hadoop.security.authorize.ServiceAuthorizationManager();
    Code:
       0: aload_0
       1: invokespecial #1                  // Method java/lang/Object."<init>":()V
       4: aload_0
       5: new           #2                  // class java/util/IdentityHashMap
       8: dup
       9: invokespecial #3                  // Method java/util/IdentityHashMap."<init>":()V
      12: putfield      #4                  // Field protocolToAcls:Ljava/util/Map;
      15: aload_0
      16: new           #2                  // class java/util/IdentityHashMap
      19: dup
      20: invokespecial #3                  // Method java/util/IdentityHashMap."<init>":()V
      23: putfield      #5                  // Field protocolToMachineLists:Ljava/util/Map;
      26: return

  public void authorize(org.apache.hadoop.security.UserGroupInformation, java.lang.Class<?>, org.apache.hadoop.conf.Configuration, java.net.InetAddress) throws org.apache.hadoop.security.authorize.AuthorizationException;
    Code:
       0: aload_0
       1: getfield      #4                  // Field protocolToAcls:Ljava/util/Map;
       4: aload_2
       5: invokeinterface #6,  2            // InterfaceMethod java/util/Map.get:(Ljava/lang/Object;)Ljava/lang/Object;
      10: checkcast     #7                  // class "[Lorg/apache/hadoop/security/authorize/AccessControlList;"
      13: astore        5
      15: aload_0
      16: getfield      #5                  // Field protocolToMachineLists:Ljava/util/Map;
      19: aload_2
      20: invokeinterface #6,  2            // InterfaceMethod java/util/Map.get:(Ljava/lang/Object;)Ljava/lang/Object;
      25: checkcast     #8                  // class "[Lorg/apache/hadoop/util/MachineList;"
      28: astore        6
      30: aload         5
      32: ifnull        40
      35: aload         6
      37: ifnonnull     72
      40: new           #9                  // class org/apache/hadoop/security/authorize/AuthorizationException
      43: dup
      44: new           #10                 // class java/lang/StringBuilder
      47: dup
      48: invokespecial #11                 // Method java/lang/StringBuilder."<init>":()V
      51: ldc           #12                 // String Protocol
      53: invokevirtual #13                 // Method java/lang/StringBuilder.append:(Ljava/lang/String;)Ljava/lang/StringBuilder;
      56: aload_2
      57: invokevirtual #14                 // Method java/lang/StringBuilder.append:(Ljava/lang/Object;)Ljava/lang/StringBuilder;
      60: ldc           #15                 // String  is not known.
      62: invokevirtual #13                 // Method java/lang/StringBuilder.append:(Ljava/lang/String;)Ljava/lang/StringBuilder;
      65: invokevirtual #16                 // Method java/lang/StringBuilder.toString:()Ljava/lang/String;
      68: invokespecial #17                 // Method org/apache/hadoop/security/authorize/AuthorizationException."<init>":(Ljava/lang/String;)V
      71: athrow
      72: aconst_null
      73: astore        7
      75: aload_2
      76: aload_3
      77: invokestatic  #18                 // Method org/apache/hadoop/security/SecurityUtil.getClientPrincipal:(Ljava/lang/Class;Lorg/apache/hadoop/conf/Configuration;)Ljava/lang/String;
      80: astore        7
      82: aload         7
      84: ifnull        96
      87: aload         7
      89: aload         4
      91: invokestatic  #19                 // Method org/apache/hadoop/security/SecurityUtil.getServerPrincipal:(Ljava/lang/String;Ljava/net/InetAddress;)Ljava/lang/String;
      94: astore        7
      96: goto          155
      99: astore        8
     101: new           #9                  // class org/apache/hadoop/security/authorize/AuthorizationException
     104: dup
     105: new           #10                 // class java/lang/StringBuilder
     108: dup
     109: invokespecial #11                 // Method java/lang/StringBuilder."<init>":()V
     112: ldc           #21                 // String Can\'t figure out Kerberos principal name for connection from
     114: invokevirtual #13                 // Method java/lang/StringBuilder.append:(Ljava/lang/String;)Ljava/lang/StringBuilder;
     117: aload         4
     119: invokevirtual #14                 // Method java/lang/StringBuilder.append:(Ljava/lang/Object;)Ljava/lang/StringBuilder;
     122: ldc           #22                 // String  for user=
     124: invokevirtual #13                 // Method java/lang/StringBuilder.append:(Ljava/lang/String;)Ljava/lang/StringBuilder;
     127: aload_1
     128: invokevirtual #14                 // Method java/lang/StringBuilder.append:(Ljava/lang/Object;)Ljava/lang/StringBuilder;
     131: ldc           #23                 // String  protocol=
     133: invokevirtual #13                 // Method java/lang/StringBuilder.append:(Ljava/lang/String;)Ljava/lang/StringBuilder;
     136: aload_2
     137: invokevirtual #14                 // Method java/lang/StringBuilder.append:(Ljava/lang/Object;)Ljava/lang/StringBuilder;
     140: invokevirtual #16                 // Method java/lang/StringBuilder.toString:()Ljava/lang/String;
     143: invokespecial #17                 // Method org/apache/hadoop/security/authorize/AuthorizationException."<init>":(Ljava/lang/String;)V
     146: aload         8
     148: invokevirtual #24                 // Method org/apache/hadoop/security/authorize/AuthorizationException.initCause:(Ljava/lang/Throwable;)Ljava/lang/Throwable;
     151: checkcast     #9                  // class org/apache/hadoop/security/authorize/AuthorizationException
     154: athrow
     155: aload         7
     157: ifnull        172
     160: aload         7
     162: aload_1
     163: invokevirtual #25                 // Method org/apache/hadoop/security/UserGroupInformation.getUserName:()Ljava/lang/String;
     166: invokevirtual #26                 // Method java/lang/String.equals:(Ljava/lang/Object;)Z
     169: ifeq          201
     172: aload         5
     174: arraylength
     175: iconst_2
     176: if_icmpne     201
     179: aload         5
     181: iconst_0
     182: aaload
     183: aload_1
     184: invokevirtual #27                 // Method org/apache/hadoop/security/authorize/AccessControlList.isUserAllowed:(Lorg/apache/hadoop/security/UserGroupInformation;)Z
     187: ifeq          201
     190: aload         5
     192: iconst_1
     193: aaload
     194: aload_1
     195: invokevirtual #27                 // Method org/apache/hadoop/security/authorize/AccessControlList.isUserAllowed:(Lorg/apache/hadoop/security/UserGroupInformation;)Z
     198: ifeq          315
     201: aload         7
     203: ifnull        229
     206: new           #10                 // class java/lang/StringBuilder
     209: dup
     210: invokespecial #11                 // Method java/lang/StringBuilder."<init>":()V
     213: ldc           #28                 // String : this service is only accessible by
     215: invokevirtual #13                 // Method java/lang/StringBuilder.append:(Ljava/lang/String;)Ljava/lang/StringBuilder;
     218: aload         7
     220: invokevirtual #13                 // Method java/lang/StringBuilder.append:(Ljava/lang/String;)Ljava/lang/StringBuilder;
     223: invokevirtual #16                 // Method java/lang/StringBuilder.toString:()Ljava/lang/String;
     226: goto          231
     229: ldc           #29                 // String : denied by configured ACL
     231: astore        8
     233: getstatic     #30                 // Field AUDITLOG:Lorg/slf4j/Logger;
     236: new           #10                 // class java/lang/StringBuilder
     239: dup
     240: invokespecial #11                 // Method java/lang/StringBuilder."<init>":()V
     243: ldc           #32                 // String Authorization failed for
     245: invokevirtual #13                 // Method java/lang/StringBuilder.append:(Ljava/lang/String;)Ljava/lang/StringBuilder;
     248: aload_1
     249: invokevirtual #14                 // Method java/lang/StringBuilder.append:(Ljava/lang/Object;)Ljava/lang/StringBuilder;
     252: ldc           #33                 // String  for protocol=
     254: invokevirtual #13                 // Method java/lang/StringBuilder.append:(Ljava/lang/String;)Ljava/lang/StringBuilder;
     257: aload_2
     258: invokevirtual #14                 // Method java/lang/StringBuilder.append:(Ljava/lang/Object;)Ljava/lang/StringBuilder;
     261: aload         8
     263: invokevirtual #13                 // Method java/lang/StringBuilder.append:(Ljava/lang/String;)Ljava/lang/StringBuilder;
     266: invokevirtual #16                 // Method java/lang/StringBuilder.toString:()Ljava/lang/String;
     269: invokeinterface #34,  2           // InterfaceMethod org/slf4j/Logger.warn:(Ljava/lang/String;)V
     274: new           #9                  // class org/apache/hadoop/security/authorize/AuthorizationException
     277: dup
     278: new           #10                 // class java/lang/StringBuilder
     281: dup
     282: invokespecial #11                 // Method java/lang/StringBuilder."<init>":()V
     285: ldc           #35                 // String User
     287: invokevirtual #13                 // Method java/lang/StringBuilder.append:(Ljava/lang/String;)Ljava/lang/StringBuilder;
     290: aload_1
     291: invokevirtual #14                 // Method java/lang/StringBuilder.append:(Ljava/lang/Object;)Ljava/lang/StringBuilder;
     294: ldc           #36                 // String  is not authorized for protocol
     296: invokevirtual #13                 // Method java/lang/StringBuilder.append:(Ljava/lang/String;)Ljava/lang/StringBuilder;
     299: aload_2
     300: invokevirtual #14                 // Method java/lang/StringBuilder.append:(Ljava/lang/Object;)Ljava/lang/StringBuilder;
     303: aload         8
     305: invokevirtual #13                 // Method java/lang/StringBuilder.append:(Ljava/lang/String;)Ljava/lang/StringBuilder;
     308: invokevirtual #16                 // Method java/lang/StringBuilder.toString:()Ljava/lang/String;
     311: invokespecial #17                 // Method org/apache/hadoop/security/authorize/AuthorizationException."<init>":(Ljava/lang/String;)V
     314: athrow
     315: aload         4
     317: ifnull        432
     320: aload         4
     322: invokevirtual #37                 // Method java/net/InetAddress.getHostAddress:()Ljava/lang/String;
     325: astore        8
     327: aload         6
     329: arraylength
     330: iconst_2
     331: if_icmpne     358
     334: aload         6
     336: iconst_0
     337: aaload
     338: aload         8
     340: invokevirtual #38                 // Method org/apache/hadoop/util/MachineList.includes:(Ljava/lang/String;)Z
     343: ifeq          358
     346: aload         6
     348: iconst_1
     349: aaload
     350: aload         8
     352: invokevirtual #38                 // Method org/apache/hadoop/util/MachineList.includes:(Ljava/lang/String;)Z
     355: ifeq          432
     358: getstatic     #30                 // Field AUDITLOG:Lorg/slf4j/Logger;
     361: new           #10                 // class java/lang/StringBuilder
     364: dup
     365: invokespecial #11                 // Method java/lang/StringBuilder."<init>":()V
     368: ldc           #39                 // String Authorization failed for  for protocol=
     370: invokevirtual #13                 // Method java/lang/StringBuilder.append:(Ljava/lang/String;)Ljava/lang/StringBuilder;
     373: aload_2
     374: invokevirtual #14                 // Method java/lang/StringBuilder.append:(Ljava/lang/Object;)Ljava/lang/StringBuilder;
     377: ldc           #40                 // String  from host =
     379: invokevirtual #13                 // Method java/lang/StringBuilder.append:(Ljava/lang/String;)Ljava/lang/StringBuilder;
     382: aload         8
     384: invokevirtual #13                 // Method java/lang/StringBuilder.append:(Ljava/lang/String;)Ljava/lang/StringBuilder;
     387: invokevirtual #16                 // Method java/lang/StringBuilder.toString:()Ljava/lang/String;
     390: invokeinterface #34,  2           // InterfaceMethod org/slf4j/Logger.warn:(Ljava/lang/String;)V
     395: new           #9                  // class org/apache/hadoop/security/authorize/AuthorizationException
     398: dup
     399: new           #10                 // class java/lang/StringBuilder
     402: dup
     403: invokespecial #11                 // Method java/lang/StringBuilder."<init>":()V
     406: ldc           #41                 // String Host
     408: invokevirtual #13                 // Method java/lang/StringBuilder.append:(Ljava/lang/String;)Ljava/lang/StringBuilder;
     411: aload         8
     413: invokevirtual #13                 // Method java/lang/StringBuilder.append:(Ljava/lang/String;)Ljava/lang/StringBuilder;
     416: ldc           #36                 // String  is not authorized for protocol
     418: invokevirtual #13                 // Method java/lang/StringBuilder.append:(Ljava/lang/String;)Ljava/lang/StringBuilder;
     421: aload_2
     422: invokevirtual #14                 // Method java/lang/StringBuilder.append:(Ljava/lang/Object;)Ljava/lang/StringBuilder;
     425: invokevirtual #16                 // Method java/lang/StringBuilder.toString:()Ljava/lang/String;
     428: invokespecial #17                 // Method org/apache/hadoop/security/authorize/AuthorizationException."<init>":(Ljava/lang/String;)V
     431: athrow
     432: getstatic     #30                 // Field AUDITLOG:Lorg/slf4j/Logger;
     435: new           #10                 // class java/lang/StringBuilder
     438: dup
     439: invokespecial #11                 // Method java/lang/StringBuilder."<init>":()V
     442: ldc           #42                 // String Authorization successful for
     444: invokevirtual #13                 // Method java/lang/StringBuilder.append:(Ljava/lang/String;)Ljava/lang/StringBuilder;
     447: aload_1
     448: invokevirtual #14                 // Method java/lang/StringBuilder.append:(Ljava/lang/Object;)Ljava/lang/StringBuilder;
     451: ldc           #33                 // String  for protocol=
     453: invokevirtual #13                 // Method java/lang/StringBuilder.append:(Ljava/lang/String;)Ljava/lang/StringBuilder;
     456: aload_2
     457: invokevirtual #14                 // Method java/lang/StringBuilder.append:(Ljava/lang/Object;)Ljava/lang/StringBuilder;
     460: invokevirtual #16                 // Method java/lang/StringBuilder.toString:()Ljava/lang/String;
     463: invokeinterface #43,  2           // InterfaceMethod org/slf4j/Logger.info:(Ljava/lang/String;)V
     468: return
    Exception table:
       from    to  target type
          75    96    99   Class java/io/IOException

  public void refresh(org.apache.hadoop.conf.Configuration, org.apache.hadoop.security.authorize.PolicyProvider);
    Code:
       0: ldc           #44                 // String hadoop.policy.file
       2: ldc           #45                 // String hadoop-policy.xml
       4: invokestatic  #46                 // Method java/lang/System.getProperty:(Ljava/lang/String;Ljava/lang/String;)Ljava/lang/String;
       7: astore_3
       8: new           #47                 // class org/apache/hadoop/conf/Configuration
      11: dup
      12: aload_1
      13: invokespecial #48                 // Method org/apache/hadoop/conf/Configuration."<init>":(Lorg/apache/hadoop/conf/Configuration;)V
      16: astore        4
      18: aload         4
      20: aload_3
      21: invokevirtual #49                 // Method org/apache/hadoop/conf/Configuration.addResource:(Ljava/lang/String;)V
      24: aload_0
      25: aload         4
      27: aload_2
      28: invokevirtual #50                 // Method refreshWithLoadedConfiguration:(Lorg/apache/hadoop/conf/Configuration;Lorg/apache/hadoop/security/authorize/PolicyProvider;)V
      31: return

  public void refreshWithLoadedConfiguration(org.apache.hadoop.conf.Configuration, org.apache.hadoop.security.authorize.PolicyProvider);
    Code:
       0: new           #2                  // class java/util/IdentityHashMap
       3: dup
       4: invokespecial #3                  // Method java/util/IdentityHashMap."<init>":()V
       7: astore_3
       8: new           #2                  // class java/util/IdentityHashMap
      11: dup
      12: invokespecial #3                  // Method java/util/IdentityHashMap."<init>":()V
      15: astore        4
      17: aload_1
      18: ldc           #52                 // String security.service.authorization.default.acl
      20: ldc           #54                 // String *
      22: invokevirtual #55                 // Method org/apache/hadoop/conf/Configuration.get:(Ljava/lang/String;Ljava/lang/String;)Ljava/lang/String;
      25: astore        5
      27: aload_1
      28: ldc           #56                 // String security.service.authorization.default.acl.blocked
      30: ldc           #57                 // String
      32: invokevirtual #55                 // Method org/apache/hadoop/conf/Configuration.get:(Ljava/lang/String;Ljava/lang/String;)Ljava/lang/String;
      35: astore        6
      37: aload_0
      38: ldc           #52                 // String security.service.authorization.default.acl
      40: invokespecial #58                 // Method getHostKey:(Ljava/lang/String;)Ljava/lang/String;
      43: astore        7
      45: aload_1
      46: aload         7
      48: ldc           #54                 // String *
      50: invokevirtual #55                 // Method org/apache/hadoop/conf/Configuration.get:(Ljava/lang/String;Ljava/lang/String;)Ljava/lang/String;
      53: astore        8
      55: aload_1
      56: new           #10                 // class java/lang/StringBuilder
      59: dup
      60: invokespecial #11                 // Method java/lang/StringBuilder."<init>":()V
      63: aload         7
      65: invokevirtual #13                 // Method java/lang/StringBuilder.append:(Ljava/lang/String;)Ljava/lang/StringBuilder;
      68: ldc           #60                 // String .blocked
      70: invokevirtual #13                 // Method java/lang/StringBuilder.append:(Ljava/lang/String;)Ljava/lang/StringBuilder;
      73: invokevirtual #16                 // Method java/lang/StringBuilder.toString:()Ljava/lang/String;
      76: ldc           #57                 // String
      78: invokevirtual #55                 // Method org/apache/hadoop/conf/Configuration.get:(Ljava/lang/String;Ljava/lang/String;)Ljava/lang/String;
      81: astore        9
      83: aload_2
      84: invokevirtual #61                 // Method org/apache/hadoop/security/authorize/PolicyProvider.getServices:()[Lorg/apache/hadoop/security/authorize/Service;
      87: astore        10
      89: aload         10
      91: ifnull        300
      94: aload         10
      96: astore        11
      98: aload         11
     100: arraylength
     101: istore        12
     103: iconst_0
     104: istore        13
     106: iload         13
     108: iload         12
     110: if_icmpge     300
     113: aload         11
     115: iload         13
     117: aaload
     118: astore        14
     120: new           #53                 // class org/apache/hadoop/security/authorize/AccessControlList
     123: dup
     124: aload_1
     125: aload         14
     127: invokevirtual #62                 // Method org/apache/hadoop/security/authorize/Service.getServiceKey:()Ljava/lang/String;
     130: aload         5
     132: invokevirtual #55                 // Method org/apache/hadoop/conf/Configuration.get:(Ljava/lang/String;Ljava/lang/String;)Ljava/lang/String;
     135: invokespecial #63                 // Method org/apache/hadoop/security/authorize/AccessControlList."<init>":(Ljava/lang/String;)V
     138: astore        15
     140: new           #53                 // class org/apache/hadoop/security/authorize/AccessControlList
     143: dup
     144: aload_1
     145: new           #10                 // class java/lang/StringBuilder
     148: dup
     149: invokespecial #11                 // Method java/lang/StringBuilder."<init>":()V
     152: aload         14
     154: invokevirtual #62                 // Method org/apache/hadoop/security/authorize/Service.getServiceKey:()Ljava/lang/String;
     157: invokevirtual #13                 // Method java/lang/StringBuilder.append:(Ljava/lang/String;)Ljava/lang/StringBuilder;
     160: ldc           #60                 // String .blocked
     162: invokevirtual #13                 // Method java/lang/StringBuilder.append:(Ljava/lang/String;)Ljava/lang/StringBuilder;
     165: invokevirtual #16                 // Method java/lang/StringBuilder.toString:()Ljava/lang/String;
     168: aload         6
     170: invokevirtual #55                 // Method org/apache/hadoop/conf/Configuration.get:(Ljava/lang/String;Ljava/lang/String;)Ljava/lang/String;
     173: invokespecial #63                 // Method org/apache/hadoop/security/authorize/AccessControlList."<init>":(Ljava/lang/String;)V
     176: astore        16
     178: aload_3
     179: aload         14
     181: invokevirtual #64                 // Method org/apache/hadoop/security/authorize/Service.getProtocol:()Ljava/lang/Class;
     184: iconst_2
     185: anewarray     #53                 // class org/apache/hadoop/security/authorize/AccessControlList
     188: dup
     189: iconst_0
     190: aload         15
     192: aastore
     193: dup
     194: iconst_1
     195: aload         16
     197: aastore
     198: invokeinterface #65,  3           // InterfaceMethod java/util/Map.put:(Ljava/lang/Object;Ljava/lang/Object;)Ljava/lang/Object;
     203: pop
     204: aload_0
     205: aload         14
     207: invokevirtual #62                 // Method org/apache/hadoop/security/authorize/Service.getServiceKey:()Ljava/lang/String;
     210: invokespecial #58                 // Method getHostKey:(Ljava/lang/String;)Ljava/lang/String;
     213: astore        17
     215: new           #59                 // class org/apache/hadoop/util/MachineList
     218: dup
     219: aload_1
     220: aload         17
     222: aload         8
     224: invokevirtual #55                 // Method org/apache/hadoop/conf/Configuration.get:(Ljava/lang/String;Ljava/lang/String;)Ljava/lang/String;
     227: invokespecial #66                 // Method org/apache/hadoop/util/MachineList."<init>":(Ljava/lang/String;)V
     230: astore        18
     232: new           #59                 // class org/apache/hadoop/util/MachineList
     235: dup
     236: aload_1
     237: new           #10                 // class java/lang/StringBuilder
     240: dup
     241: invokespecial #11                 // Method java/lang/StringBuilder."<init>":()V
     244: aload         17
     246: invokevirtual #13                 // Method java/lang/StringBuilder.append:(Ljava/lang/String;)Ljava/lang/StringBuilder;
     249: ldc           #60                 // String .blocked
     251: invokevirtual #13                 // Method java/lang/StringBuilder.append:(Ljava/lang/String;)Ljava/lang/StringBuilder;
     254: invokevirtual #16                 // Method java/lang/StringBuilder.toString:()Ljava/lang/String;
     257: aload         9
     259: invokevirtual #55                 // Method org/apache/hadoop/conf/Configuration.get:(Ljava/lang/String;Ljava/lang/String;)Ljava/lang/String;
     262: invokespecial #66                 // Method org/apache/hadoop/util/MachineList."<init>":(Ljava/lang/String;)V
     265: astore        19
     267: aload         4
     269: aload         14
     271: invokevirtual #64                 // Method org/apache/hadoop/security/authorize/Service.getProtocol:()Ljava/lang/Class;
     274: iconst_2
     275: anewarray     #59                 // class org/apache/hadoop/util/MachineList
     278: dup
     279: iconst_0
     280: aload         18
     282: aastore
     283: dup
     284: iconst_1
     285: aload         19
     287: aastore
     288: invokeinterface #65,  3           // InterfaceMethod java/util/Map.put:(Ljava/lang/Object;Ljava/lang/Object;)Ljava/lang/Object;
     293: pop
     294: iinc          13, 1
     297: goto          106
     300: aload_0
     301: aload_3
     302: putfield      #4                  // Field protocolToAcls:Ljava/util/Map;
     305: aload_0
     306: aload         4
     308: putfield      #5                  // Field protocolToMachineLists:Ljava/util/Map;
     311: return

  private java.lang.String getHostKey(java.lang.String);
    Code:
       0: aload_1
       1: ldc           #67                 // String .
       3: invokevirtual #68                 // Method java/lang/String.lastIndexOf:(Ljava/lang/String;)I
       6: istore_2
       7: iload_2
       8: iconst_m1
       9: if_icmpeq     37
      12: new           #10                 // class java/lang/StringBuilder
      15: dup
      16: invokespecial #11                 // Method java/lang/StringBuilder."<init>":()V
      19: aload_1
      20: iconst_0
      21: iload_2
      22: invokevirtual #69                 // Method java/lang/String.substring:(II)Ljava/lang/String;
      25: invokevirtual #13                 // Method java/lang/StringBuilder.append:(Ljava/lang/String;)Ljava/lang/StringBuilder;
      28: ldc           #70                 // String .hosts
      30: invokevirtual #13                 // Method java/lang/StringBuilder.append:(Ljava/lang/String;)Ljava/lang/StringBuilder;
      33: invokevirtual #16                 // Method java/lang/StringBuilder.toString:()Ljava/lang/String;
      36: areturn
      37: aload_1
      38: areturn

  public java.util.Set<java.lang.Class<?>> getProtocolsWithAcls();
    Code:
       0: aload_0
       1: getfield      #4                  // Field protocolToAcls:Ljava/util/Map;
       4: invokeinterface #71,  1           // InterfaceMethod java/util/Map.keySet:()Ljava/util/Set;
       9: areturn

  public org.apache.hadoop.security.authorize.AccessControlList getProtocolsAcls(java.lang.Class<?>);
    Code:
       0: aload_0
       1: getfield      #4                  // Field protocolToAcls:Ljava/util/Map;
       4: aload_1
       5: invokeinterface #6,  2            // InterfaceMethod java/util/Map.get:(Ljava/lang/Object;)Ljava/lang/Object;
      10: checkcast     #7                  // class "[Lorg/apache/hadoop/security/authorize/AccessControlList;"
      13: iconst_0
      14: aaload
      15: areturn

  public org.apache.hadoop.security.authorize.AccessControlList getProtocolsBlockedAcls(java.lang.Class<?>);
    Code:
       0: aload_0
       1: getfield      #4                  // Field protocolToAcls:Ljava/util/Map;
       4: aload_1
       5: invokeinterface #6,  2            // InterfaceMethod java/util/Map.get:(Ljava/lang/Object;)Ljava/lang/Object;
      10: checkcast     #7                  // class "[Lorg/apache/hadoop/security/authorize/AccessControlList;"
      13: iconst_1
      14: aaload
      15: areturn

  public java.util.Set<java.lang.Class<?>> getProtocolsWithMachineLists();
    Code:
       0: aload_0
       1: getfield      #5                  // Field protocolToMachineLists:Ljava/util/Map;
       4: invokeinterface #71,  1           // InterfaceMethod java/util/Map.keySet:()Ljava/util/Set;
       9: areturn

  public org.apache.hadoop.util.MachineList getProtocolsMachineList(java.lang.Class<?>);
    Code:
       0: aload_0
       1: getfield      #5                  // Field protocolToMachineLists:Ljava/util/Map;
       4: aload_1
       5: invokeinterface #6,  2            // InterfaceMethod java/util/Map.get:(Ljava/lang/Object;)Ljava/lang/Object;
      10: checkcast     #8                  // class "[Lorg/apache/hadoop/util/MachineList;"
      13: iconst_0
      14: aaload
      15: areturn

  public org.apache.hadoop.util.MachineList getProtocolsBlockedMachineList(java.lang.Class<?>);
    Code:
       0: aload_0
       1: getfield      #5                  // Field protocolToMachineLists:Ljava/util/Map;
       4: aload_1
       5: invokeinterface #6,  2            // InterfaceMethod java/util/Map.get:(Ljava/lang/Object;)Ljava/lang/Object;
      10: checkcast     #8                  // class "[Lorg/apache/hadoop/util/MachineList;"
      13: iconst_1
      14: aaload
      15: areturn

  static {};
    Code:
       0: new           #10                 // class java/lang/StringBuilder
       3: dup
       4: invokespecial #11                 // Method java/lang/StringBuilder."<init>":()V
       7: ldc           #72                 // String SecurityLogger.
       9: invokevirtual #13                 // Method java/lang/StringBuilder.append:(Ljava/lang/String;)Ljava/lang/StringBuilder;
      12: ldc           #31                 // class org/apache/hadoop/security/authorize/ServiceAuthorizationManager
      14: invokevirtual #73                 // Method java/lang/Class.getName:()Ljava/lang/String;
      17: invokevirtual #13                 // Method java/lang/StringBuilder.append:(Ljava/lang/String;)Ljava/lang/StringBuilder;
      20: invokevirtual #16                 // Method java/lang/StringBuilder.toString:()Ljava/lang/String;
      23: invokestatic  #74                 // Method org/slf4j/LoggerFactory.getLogger:(Ljava/lang/String;)Lorg/slf4j/Logger;
      26: putstatic     #30                 // Field AUDITLOG:Lorg/slf4j/Logger;
      29: return
}
