Compiled from "ExtendedThreadInfoFactory.java"
public class org.apache.logging.log4j.core.message.ExtendedThreadInfoFactory implements org.apache.logging.log4j.message.ThreadDumpMessage$ThreadInfoFactory {
  public org.apache.logging.log4j.core.message.ExtendedThreadInfoFactory();
    Code:
       0: aload_0
       1: invokespecial #1                  // Method java/lang/Object."<init>":()V
       4: ldc           #2                  // class java/lang/management/ThreadInfo
       6: invokevirtual #3                  // Method java/lang/Class.getMethods:()[Ljava/lang/reflect/Method;
       9: astore_1
      10: iconst_1
      11: istore_2
      12: aload_1
      13: astore_3
      14: aload_3
      15: arraylength
      16: istore        4
      18: iconst_0
      19: istore        5
      21: iload         5
      23: iload         4
      25: if_icmpge     58
      28: aload_3
      29: iload         5
      31: aaload
      32: astore        6
      34: aload         6
      36: invokevirtual #4                  // Method java/lang/reflect/Method.getName:()Ljava/lang/String;
      39: ldc           #5                  // String getLockInfo
      41: invokevirtual #6                  // Method java/lang/String.equals:(Ljava/lang/Object;)Z
      44: ifeq          52
      47: iconst_0
      48: istore_2
      49: goto          58
      52: iinc          5, 1
      55: goto          21
      58: iload_2
      59: ifeq          70
      62: new           #7                  // class java/lang/IllegalStateException
      65: dup
      66: invokespecial #8                  // Method java/lang/IllegalStateException."<init>":()V
      69: athrow
      70: return

  public java.util.Map<org.apache.logging.log4j.message.ThreadInformation, java.lang.StackTraceElement[]> createThreadInfo();
    Code:
       0: invokestatic  #9                  // Method java/lang/management/ManagementFactory.getThreadMXBean:()Ljava/lang/management/ThreadMXBean;
       3: astore_1
       4: aload_1
       5: iconst_1
       6: iconst_1
       7: invokeinterface #10,  3           // InterfaceMethod java/lang/management/ThreadMXBean.dumpAllThreads:(ZZ)[Ljava/lang/management/ThreadInfo;
      12: astore_2
      13: new           #11                 // class java/util/HashMap
      16: dup
      17: aload_2
      18: arraylength
      19: invokespecial #12                 // Method java/util/HashMap."<init>":(I)V
      22: astore_3
      23: aload_2
      24: astore        4
      26: aload         4
      28: arraylength
      29: istore        5
      31: iconst_0
      32: istore        6
      34: iload         6
      36: iload         5
      38: if_icmpge     75
      41: aload         4
      43: iload         6
      45: aaload
      46: astore        7
      48: aload_3
      49: new           #13                 // class org/apache/logging/log4j/core/message/ExtendedThreadInformation
      52: dup
      53: aload         7
      55: invokespecial #14                 // Method org/apache/logging/log4j/core/message/ExtendedThreadInformation."<init>":(Ljava/lang/management/ThreadInfo;)V
      58: aload         7
      60: invokevirtual #15                 // Method java/lang/management/ThreadInfo.getStackTrace:()[Ljava/lang/StackTraceElement;
      63: invokeinterface #16,  3           // InterfaceMethod java/util/Map.put:(Ljava/lang/Object;Ljava/lang/Object;)Ljava/lang/Object;
      68: pop
      69: iinc          6, 1
      72: goto          34
      75: aload_3
      76: areturn
}
