Compiled from "XPathUtils.java"
public class com.ibm.wsdl.util.xml.XPathUtils {
  public com.ibm.wsdl.util.xml.XPathUtils();
    Code:
       0: aload_0
       1: invokespecial #1                  // Method java/lang/Object."<init>":()V
       4: return

  private static org.w3c.dom.Node getPreviousTypedNode(org.w3c.dom.Node, short);
    Code:
       0: aload_0
       1: invokeinterface #2,  1            // InterfaceMethod org/w3c/dom/Node.getPreviousSibling:()Lorg/w3c/dom/Node;
       6: astore_0
       7: aload_0
       8: ifnull        31
      11: aload_0
      12: invokeinterface #3,  1            // InterfaceMethod org/w3c/dom/Node.getNodeType:()S
      17: iload_1
      18: if_icmpeq     31
      21: aload_0
      22: invokeinterface #2,  1            // InterfaceMethod org/w3c/dom/Node.getPreviousSibling:()Lorg/w3c/dom/Node;
      27: astore_0
      28: goto          7
      31: aload_0
      32: areturn

  private static org.w3c.dom.Node getNextTypedNode(org.w3c.dom.Node, short);
    Code:
       0: aload_0
       1: invokeinterface #4,  1            // InterfaceMethod org/w3c/dom/Node.getNextSibling:()Lorg/w3c/dom/Node;
       6: astore_0
       7: aload_0
       8: ifnull        31
      11: aload_0
      12: invokeinterface #3,  1            // InterfaceMethod org/w3c/dom/Node.getNodeType:()S
      17: iload_1
      18: if_icmpeq     31
      21: aload_0
      22: invokeinterface #4,  1            // InterfaceMethod org/w3c/dom/Node.getNextSibling:()Lorg/w3c/dom/Node;
      27: astore_0
      28: goto          7
      31: aload_0
      32: areturn

  private static java.lang.String getValue(org.w3c.dom.Node, short);
    Code:
       0: iload_1
       1: lookupswitch  { // 3
                     1: 36
                     3: 46
                     7: 56
               default: 66
          }
      36: aload_0
      37: checkcast     #5                  // class org/w3c/dom/Element
      40: invokeinterface #6,  1            // InterfaceMethod org/w3c/dom/Element.getTagName:()Ljava/lang/String;
      45: areturn
      46: aload_0
      47: checkcast     #7                  // class org/w3c/dom/Text
      50: invokeinterface #8,  1            // InterfaceMethod org/w3c/dom/Text.getData:()Ljava/lang/String;
      55: areturn
      56: aload_0
      57: checkcast     #9                  // class org/w3c/dom/ProcessingInstruction
      60: invokeinterface #10,  1           // InterfaceMethod org/w3c/dom/ProcessingInstruction.getData:()Ljava/lang/String;
      65: areturn
      66: ldc           #11                 // String
      68: areturn

  private static short getNodeType(org.w3c.dom.Node);
    Code:
       0: aload_0
       1: ifnull        13
       4: aload_0
       5: invokeinterface #3,  1            // InterfaceMethod org/w3c/dom/Node.getNodeType:()S
      10: goto          14
      13: iconst_m1
      14: ireturn

  private static java.lang.String getXPathFromVector(java.util.Vector);
    Code:
       0: new           #12                 // class java/lang/StringBuffer
       3: dup
       4: invokespecial #13                 // Method java/lang/StringBuffer."<init>":()V
       7: astore_1
       8: aload_0
       9: invokevirtual #14                 // Method java/util/Vector.size:()I
      12: istore_2
      13: iconst_0
      14: istore_3
      15: iload_3
      16: iload_2
      17: if_icmpge     321
      20: aload_0
      21: iload_3
      22: invokevirtual #15                 // Method java/util/Vector.elementAt:(I)Ljava/lang/Object;
      25: checkcast     #16                 // class org/w3c/dom/Node
      28: astore        4
      30: aload         4
      32: invokestatic  #17                 // Method getNodeType:(Lorg/w3c/dom/Node;)S
      35: istore        5
      37: aload         4
      39: iload         5
      41: invokestatic  #18                 // Method getValue:(Lorg/w3c/dom/Node;S)Ljava/lang/String;
      44: astore        6
      46: iconst_1
      47: istore        7
      49: aload         4
      51: iload         5
      53: invokestatic  #19                 // Method getPreviousTypedNode:(Lorg/w3c/dom/Node;S)Lorg/w3c/dom/Node;
      56: astore        4
      58: aload         4
      60: ifnull        105
      63: iload         5
      65: iconst_1
      66: if_icmpne     90
      69: aload         4
      71: iload         5
      73: invokestatic  #18                 // Method getValue:(Lorg/w3c/dom/Node;S)Ljava/lang/String;
      76: aload         6
      78: invokevirtual #20                 // Method java/lang/String.equals:(Ljava/lang/Object;)Z
      81: ifeq          93
      84: iinc          7, 1
      87: goto          93
      90: iinc          7, 1
      93: aload         4
      95: iload         5
      97: invokestatic  #19                 // Method getPreviousTypedNode:(Lorg/w3c/dom/Node;S)Lorg/w3c/dom/Node;
     100: astore        4
     102: goto          58
     105: iload         7
     107: iconst_1
     108: if_icmple     115
     111: iconst_1
     112: goto          116
     115: iconst_0
     116: istore        8
     118: iload         8
     120: ifne          197
     123: aload_0
     124: iload_3
     125: invokevirtual #15                 // Method java/util/Vector.elementAt:(I)Ljava/lang/Object;
     128: checkcast     #16                 // class org/w3c/dom/Node
     131: astore        4
     133: aload         4
     135: iload         5
     137: invokestatic  #21                 // Method getNextTypedNode:(Lorg/w3c/dom/Node;S)Lorg/w3c/dom/Node;
     140: astore        4
     142: iload         8
     144: ifne          197
     147: aload         4
     149: ifnull        197
     152: iload         5
     154: iconst_1
     155: if_icmpne     191
     158: aload         4
     160: iload         5
     162: invokestatic  #18                 // Method getValue:(Lorg/w3c/dom/Node;S)Ljava/lang/String;
     165: aload         6
     167: invokevirtual #20                 // Method java/lang/String.equals:(Ljava/lang/Object;)Z
     170: ifeq          179
     173: iconst_1
     174: istore        8
     176: goto          142
     179: aload         4
     181: iload         5
     183: invokestatic  #21                 // Method getNextTypedNode:(Lorg/w3c/dom/Node;S)Lorg/w3c/dom/Node;
     186: astore        4
     188: goto          142
     191: iconst_1
     192: istore        8
     194: goto          142
     197: iload         5
     199: lookupswitch  { // 2
                     3: 224
                     7: 231
               default: 238
          }
     224: ldc           #22                 // String text()
     226: astore        9
     228: goto          242
     231: ldc           #23                 // String processing-instruction()
     233: astore        9
     235: goto          242
     238: aload         6
     240: astore        9
     242: aload         9
     244: ifnull        280
     247: aload         9
     249: invokevirtual #24                 // Method java/lang/String.length:()I
     252: ifle          280
     255: aload_1
     256: new           #25                 // class java/lang/StringBuilder
     259: dup
     260: invokespecial #26                 // Method java/lang/StringBuilder."<init>":()V
     263: bipush        47
     265: invokevirtual #27                 // Method java/lang/StringBuilder.append:(C)Ljava/lang/StringBuilder;
     268: aload         9
     270: invokevirtual #28                 // Method java/lang/StringBuilder.append:(Ljava/lang/String;)Ljava/lang/StringBuilder;
     273: invokevirtual #29                 // Method java/lang/StringBuilder.toString:()Ljava/lang/String;
     276: invokevirtual #30                 // Method java/lang/StringBuffer.append:(Ljava/lang/String;)Ljava/lang/StringBuffer;
     279: pop
     280: iload         8
     282: ifeq          315
     285: aload_1
     286: new           #25                 // class java/lang/StringBuilder
     289: dup
     290: invokespecial #26                 // Method java/lang/StringBuilder."<init>":()V
     293: ldc           #31                 // String [
     295: invokevirtual #28                 // Method java/lang/StringBuilder.append:(Ljava/lang/String;)Ljava/lang/StringBuilder;
     298: iload         7
     300: invokevirtual #32                 // Method java/lang/StringBuilder.append:(I)Ljava/lang/StringBuilder;
     303: ldc           #33                 // String ]
     305: invokevirtual #28                 // Method java/lang/StringBuilder.append:(Ljava/lang/String;)Ljava/lang/StringBuilder;
     308: invokevirtual #29                 // Method java/lang/StringBuilder.toString:()Ljava/lang/String;
     311: invokevirtual #30                 // Method java/lang/StringBuffer.append:(Ljava/lang/String;)Ljava/lang/StringBuffer;
     314: pop
     315: iinc          3, 1
     318: goto          15
     321: aload_1
     322: invokevirtual #34                 // Method java/lang/StringBuffer.toString:()Ljava/lang/String;
     325: areturn

  private static java.util.Vector getVectorPathFromNode(org.w3c.dom.Node);
    Code:
       0: new           #35                 // class java/util/Vector
       3: dup
       4: invokespecial #36                 // Method java/util/Vector."<init>":()V
       7: astore_1
       8: aload_0
       9: ifnull        28
      12: aload_1
      13: aload_0
      14: iconst_0
      15: invokevirtual #37                 // Method java/util/Vector.insertElementAt:(Ljava/lang/Object;I)V
      18: aload_0
      19: invokeinterface #38,  1           // InterfaceMethod org/w3c/dom/Node.getParentNode:()Lorg/w3c/dom/Node;
      24: astore_0
      25: goto          8
      28: aload_1
      29: areturn

  public static java.lang.String getXPathExprFromNode(org.w3c.dom.Node) throws java.lang.IllegalArgumentException;
    Code:
       0: aload_0
       1: invokestatic  #17                 // Method getNodeType:(Lorg/w3c/dom/Node;)S
       4: istore_1
       5: iload_1
       6: tableswitch   { // 1 to 9
                     1: 56
                     2: 67
                     3: 56
                     4: 67
                     5: 67
                     6: 67
                     7: 56
                     8: 67
                     9: 64
               default: 67
          }
      56: aload_0
      57: invokestatic  #39                 // Method getVectorPathFromNode:(Lorg/w3c/dom/Node;)Ljava/util/Vector;
      60: invokestatic  #40                 // Method getXPathFromVector:(Ljava/util/Vector;)Ljava/lang/String;
      63: areturn
      64: ldc           #41                 // String /
      66: areturn
      67: new           #42                 // class java/lang/IllegalArgumentException
      70: dup
      71: ldc           #43                 // String Only works for element, text, document, and PI nodes.
      73: invokespecial #44                 // Method java/lang/IllegalArgumentException."<init>":(Ljava/lang/String;)V
      76: athrow
}
