Compiled from "ConcreteNotificationHandlerRegistration.java"
class org.jboss.as.controller.registry.ConcreteNotificationHandlerRegistration implements org.jboss.as.controller.registry.NotificationHandlerRegistration {
  org.jboss.as.controller.registry.NotificationHandlerNodeRegistry rootRegistry;

  java.util.Set<org.jboss.as.controller.registry.ConcreteNotificationHandlerRegistration$NotificationHandlerEntry> anyAddressEntries;

  org.jboss.as.controller.registry.ConcreteNotificationHandlerRegistration();
    Code:
       0: aload_0
       1: invokespecial #1                  // Method java/lang/Object."<init>":()V
       4: aload_0
       5: new           #2                  // class org/jboss/as/controller/registry/NotificationHandlerNodeRegistry
       8: dup
       9: aconst_null
      10: aconst_null
      11: invokespecial #3                  // Method org/jboss/as/controller/registry/NotificationHandlerNodeRegistry."<init>":(Ljava/lang/String;Lorg/jboss/as/controller/registry/NotificationHandlerNodeSubregistry;)V
      14: putfield      #4                  // Field rootRegistry:Lorg/jboss/as/controller/registry/NotificationHandlerNodeRegistry;
      17: aload_0
      18: new           #5                  // class java/util/concurrent/CopyOnWriteArraySet
      21: dup
      22: invokespecial #6                  // Method java/util/concurrent/CopyOnWriteArraySet."<init>":()V
      25: putfield      #7                  // Field anyAddressEntries:Ljava/util/Set;
      28: return

  public void registerNotificationHandler(org.jboss.as.controller.PathAddress, org.jboss.as.controller.notification.NotificationHandler, org.jboss.as.controller.notification.NotificationFilter);
    Code:
       0: new           #8                  // class org/jboss/as/controller/registry/ConcreteNotificationHandlerRegistration$NotificationHandlerEntry
       3: dup
       4: aload_2
       5: aload_3
       6: invokespecial #9                  // Method org/jboss/as/controller/registry/ConcreteNotificationHandlerRegistration$NotificationHandlerEntry."<init>":(Lorg/jboss/as/controller/notification/NotificationHandler;Lorg/jboss/as/controller/notification/NotificationFilter;)V
       9: astore        4
      11: aload_1
      12: getstatic     #10                 // Field ANY_ADDRESS:Lorg/jboss/as/controller/PathAddress;
      15: if_acmpne     31
      18: aload_0
      19: getfield      #7                  // Field anyAddressEntries:Ljava/util/Set;
      22: aload         4
      24: invokeinterface #11,  2           // InterfaceMethod java/util/Set.add:(Ljava/lang/Object;)Z
      29: pop
      30: return
      31: aload_1
      32: invokevirtual #12                 // Method org/jboss/as/controller/PathAddress.iterator:()Ljava/util/ListIterator;
      35: astore        5
      37: aload_0
      38: getfield      #4                  // Field rootRegistry:Lorg/jboss/as/controller/registry/NotificationHandlerNodeRegistry;
      41: aload         5
      43: aload         4
      45: invokevirtual #13                 // Method org/jboss/as/controller/registry/NotificationHandlerNodeRegistry.registerEntry:(Ljava/util/ListIterator;Lorg/jboss/as/controller/registry/ConcreteNotificationHandlerRegistration$NotificationHandlerEntry;)V
      48: return

  public void unregisterNotificationHandler(org.jboss.as.controller.PathAddress, org.jboss.as.controller.notification.NotificationHandler, org.jboss.as.controller.notification.NotificationFilter);
    Code:
       0: new           #8                  // class org/jboss/as/controller/registry/ConcreteNotificationHandlerRegistration$NotificationHandlerEntry
       3: dup
       4: aload_2
       5: aload_3
       6: invokespecial #9                  // Method org/jboss/as/controller/registry/ConcreteNotificationHandlerRegistration$NotificationHandlerEntry."<init>":(Lorg/jboss/as/controller/notification/NotificationHandler;Lorg/jboss/as/controller/notification/NotificationFilter;)V
       9: astore        4
      11: aload_1
      12: getstatic     #10                 // Field ANY_ADDRESS:Lorg/jboss/as/controller/PathAddress;
      15: if_acmpne     31
      18: aload_0
      19: getfield      #7                  // Field anyAddressEntries:Ljava/util/Set;
      22: aload         4
      24: invokeinterface #14,  2           // InterfaceMethod java/util/Set.remove:(Ljava/lang/Object;)Z
      29: pop
      30: return
      31: aload_1
      32: invokevirtual #12                 // Method org/jboss/as/controller/PathAddress.iterator:()Ljava/util/ListIterator;
      35: astore        5
      37: aload_0
      38: getfield      #4                  // Field rootRegistry:Lorg/jboss/as/controller/registry/NotificationHandlerNodeRegistry;
      41: aload         5
      43: aload         4
      45: invokevirtual #15                 // Method org/jboss/as/controller/registry/NotificationHandlerNodeRegistry.unregisterEntry:(Ljava/util/ListIterator;Lorg/jboss/as/controller/registry/ConcreteNotificationHandlerRegistration$NotificationHandlerEntry;)V
      48: return

  public java.util.Collection<org.jboss.as.controller.notification.NotificationHandler> findMatchingNotificationHandlers(org.jboss.as.controller.notification.Notification);
    Code:
       0: new           #16                 // class java/util/HashSet
       3: dup
       4: invokespecial #17                 // Method java/util/HashSet."<init>":()V
       7: astore_2
       8: aload_1
       9: invokevirtual #18                 // Method org/jboss/as/controller/notification/Notification.getSource:()Lorg/jboss/as/controller/PathAddress;
      12: invokevirtual #12                 // Method org/jboss/as/controller/PathAddress.iterator:()Ljava/util/ListIterator;
      15: astore_3
      16: aload_0
      17: getfield      #4                  // Field rootRegistry:Lorg/jboss/as/controller/registry/NotificationHandlerNodeRegistry;
      20: aload_3
      21: aload_2
      22: aload_1
      23: invokevirtual #19                 // Method org/jboss/as/controller/registry/NotificationHandlerNodeRegistry.findEntries:(Ljava/util/ListIterator;Ljava/util/Collection;Lorg/jboss/as/controller/notification/Notification;)V
      26: aload_0
      27: getfield      #7                  // Field anyAddressEntries:Ljava/util/Set;
      30: invokeinterface #20,  1           // InterfaceMethod java/util/Set.iterator:()Ljava/util/Iterator;
      35: astore        4
      37: aload         4
      39: invokeinterface #21,  1           // InterfaceMethod java/util/Iterator.hasNext:()Z
      44: ifeq          88
      47: aload         4
      49: invokeinterface #22,  1           // InterfaceMethod java/util/Iterator.next:()Ljava/lang/Object;
      54: checkcast     #8                  // class org/jboss/as/controller/registry/ConcreteNotificationHandlerRegistration$NotificationHandlerEntry
      57: astore        5
      59: aload         5
      61: invokevirtual #23                 // Method org/jboss/as/controller/registry/ConcreteNotificationHandlerRegistration$NotificationHandlerEntry.getFilter:()Lorg/jboss/as/controller/notification/NotificationFilter;
      64: aload_1
      65: invokeinterface #24,  2           // InterfaceMethod org/jboss/as/controller/notification/NotificationFilter.isNotificationEnabled:(Lorg/jboss/as/controller/notification/Notification;)Z
      70: ifeq          85
      73: aload_2
      74: aload         5
      76: invokevirtual #25                 // Method org/jboss/as/controller/registry/ConcreteNotificationHandlerRegistration$NotificationHandlerEntry.getHandler:()Lorg/jboss/as/controller/notification/NotificationHandler;
      79: invokeinterface #26,  2           // InterfaceMethod java/util/Collection.add:(Ljava/lang/Object;)Z
      84: pop
      85: goto          37
      88: aload_2
      89: areturn
}
