Compiled from "GlobalTransformerRegistry.java"
public class org.jboss.as.controller.registry.GlobalTransformerRegistry {
  private volatile java.util.Map<java.lang.String, org.jboss.as.controller.registry.GlobalTransformerRegistry$SubRegistry> subRegistries;

  private volatile java.util.Map<org.jboss.as.controller.ModelVersion, org.jboss.as.controller.registry.OperationTransformerRegistry> versionedRegistries;

  private static final org.jboss.as.controller.registry.AtomicMapFieldUpdater<org.jboss.as.controller.registry.GlobalTransformerRegistry, java.lang.String, org.jboss.as.controller.registry.GlobalTransformerRegistry$SubRegistry> subRegistriesUpdater;

  private static final org.jboss.as.controller.registry.AtomicMapFieldUpdater<org.jboss.as.controller.registry.GlobalTransformerRegistry, org.jboss.as.controller.ModelVersion, org.jboss.as.controller.registry.OperationTransformerRegistry> registryUpdater;

  static org.jboss.as.controller.registry.OperationTransformerRegistry$ResourceTransformerEntry RESOURCE_TRANSFORMER;

  static org.jboss.as.controller.registry.OperationTransformerRegistry$ResourceTransformerEntry DISCARD;

  public org.jboss.as.controller.registry.GlobalTransformerRegistry();
    Code:
       0: aload_0
       1: invokespecial #1                  // Method java/lang/Object."<init>":()V
       4: getstatic     #2                  // Field registryUpdater:Lorg/jboss/as/controller/registry/AtomicMapFieldUpdater;
       7: aload_0
       8: invokevirtual #3                  // Method org/jboss/as/controller/registry/AtomicMapFieldUpdater.clear:(Ljava/lang/Object;)V
      11: getstatic     #4                  // Field subRegistriesUpdater:Lorg/jboss/as/controller/registry/AtomicMapFieldUpdater;
      14: aload_0
      15: invokevirtual #3                  // Method org/jboss/as/controller/registry/AtomicMapFieldUpdater.clear:(Ljava/lang/Object;)V
      18: return

  public void discardOperation(org.jboss.as.controller.PathAddress, int, int, java.lang.String);
    Code:
       0: aload_0
       1: aload_1
       2: invokevirtual #5                  // Method org/jboss/as/controller/PathAddress.iterator:()Ljava/util/ListIterator;
       5: iload_2
       6: iload_3
       7: invokestatic  #6                  // Method org/jboss/as/controller/ModelVersion.create:(II)Lorg/jboss/as/controller/ModelVersion;
      10: aload         4
      12: getstatic     #7                  // Field org/jboss/as/controller/registry/OperationTransformerRegistry.DISCARD:Lorg/jboss/as/controller/registry/OperationTransformerRegistry$OperationTransformerEntry;
      15: invokevirtual #8                  // Method registerTransformer:(Ljava/util/Iterator;Lorg/jboss/as/controller/ModelVersion;Ljava/lang/String;Lorg/jboss/as/controller/registry/OperationTransformerRegistry$OperationTransformerEntry;)V
      18: return

  public void discardOperation(org.jboss.as.controller.PathAddress, org.jboss.as.controller.ModelVersion, java.lang.String);
    Code:
       0: aload_0
       1: aload_1
       2: invokevirtual #5                  // Method org/jboss/as/controller/PathAddress.iterator:()Ljava/util/ListIterator;
       5: aload_2
       6: aload_3
       7: getstatic     #7                  // Field org/jboss/as/controller/registry/OperationTransformerRegistry.DISCARD:Lorg/jboss/as/controller/registry/OperationTransformerRegistry$OperationTransformerEntry;
      10: invokevirtual #8                  // Method registerTransformer:(Ljava/util/Iterator;Lorg/jboss/as/controller/ModelVersion;Ljava/lang/String;Lorg/jboss/as/controller/registry/OperationTransformerRegistry$OperationTransformerEntry;)V
      13: return

  public void registerTransformer(org.jboss.as.controller.PathAddress, int, int, java.lang.String, org.jboss.as.controller.transform.OperationTransformer);
    Code:
       0: aload_0
       1: aload_1
       2: invokevirtual #5                  // Method org/jboss/as/controller/PathAddress.iterator:()Ljava/util/ListIterator;
       5: iload_2
       6: iload_3
       7: invokestatic  #6                  // Method org/jboss/as/controller/ModelVersion.create:(II)Lorg/jboss/as/controller/ModelVersion;
      10: aload         4
      12: new           #9                  // class org/jboss/as/controller/registry/OperationTransformerRegistry$OperationTransformerEntry
      15: dup
      16: aload         5
      18: iconst_0
      19: invokespecial #10                 // Method org/jboss/as/controller/registry/OperationTransformerRegistry$OperationTransformerEntry."<init>":(Lorg/jboss/as/controller/transform/OperationTransformer;Z)V
      22: invokevirtual #8                  // Method registerTransformer:(Ljava/util/Iterator;Lorg/jboss/as/controller/ModelVersion;Ljava/lang/String;Lorg/jboss/as/controller/registry/OperationTransformerRegistry$OperationTransformerEntry;)V
      25: return

  public void createDiscardingChildRegistry(org.jboss.as.controller.PathAddress, org.jboss.as.controller.ModelVersion);
    Code:
       0: aload_0
       1: aload_1
       2: invokevirtual #5                  // Method org/jboss/as/controller/PathAddress.iterator:()Ljava/util/ListIterator;
       5: aload_2
       6: getstatic     #11                 // Field org/jboss/as/controller/transform/PathAddressTransformer.DEFAULT:Lorg/jboss/as/controller/transform/PathAddressTransformer;
       9: getstatic     #12                 // Field DISCARD:Lorg/jboss/as/controller/registry/OperationTransformerRegistry$ResourceTransformerEntry;
      12: getstatic     #7                  // Field org/jboss/as/controller/registry/OperationTransformerRegistry.DISCARD:Lorg/jboss/as/controller/registry/OperationTransformerRegistry$OperationTransformerEntry;
      15: iconst_0
      16: invokevirtual #13                 // Method createChildRegistry:(Ljava/util/Iterator;Lorg/jboss/as/controller/ModelVersion;Lorg/jboss/as/controller/transform/PathAddressTransformer;Lorg/jboss/as/controller/registry/OperationTransformerRegistry$ResourceTransformerEntry;Lorg/jboss/as/controller/registry/OperationTransformerRegistry$OperationTransformerEntry;Z)V
      19: return

  public void createChildRegistry(org.jboss.as.controller.PathAddress, org.jboss.as.controller.ModelVersion, org.jboss.as.controller.transform.OperationTransformer);
    Code:
       0: aload_0
       1: aload_1
       2: invokevirtual #5                  // Method org/jboss/as/controller/PathAddress.iterator:()Ljava/util/ListIterator;
       5: aload_2
       6: getstatic     #11                 // Field org/jboss/as/controller/transform/PathAddressTransformer.DEFAULT:Lorg/jboss/as/controller/transform/PathAddressTransformer;
       9: getstatic     #14                 // Field RESOURCE_TRANSFORMER:Lorg/jboss/as/controller/registry/OperationTransformerRegistry$ResourceTransformerEntry;
      12: new           #9                  // class org/jboss/as/controller/registry/OperationTransformerRegistry$OperationTransformerEntry
      15: dup
      16: aload_3
      17: iconst_0
      18: invokespecial #10                 // Method org/jboss/as/controller/registry/OperationTransformerRegistry$OperationTransformerEntry."<init>":(Lorg/jboss/as/controller/transform/OperationTransformer;Z)V
      21: iconst_0
      22: invokevirtual #13                 // Method createChildRegistry:(Ljava/util/Iterator;Lorg/jboss/as/controller/ModelVersion;Lorg/jboss/as/controller/transform/PathAddressTransformer;Lorg/jboss/as/controller/registry/OperationTransformerRegistry$ResourceTransformerEntry;Lorg/jboss/as/controller/registry/OperationTransformerRegistry$OperationTransformerEntry;Z)V
      25: return

  public void createChildRegistry(org.jboss.as.controller.PathAddress, org.jboss.as.controller.ModelVersion, org.jboss.as.controller.transform.ResourceTransformer, boolean);
    Code:
       0: aload_0
       1: aload_1
       2: invokevirtual #5                  // Method org/jboss/as/controller/PathAddress.iterator:()Ljava/util/ListIterator;
       5: aload_2
       6: getstatic     #11                 // Field org/jboss/as/controller/transform/PathAddressTransformer.DEFAULT:Lorg/jboss/as/controller/transform/PathAddressTransformer;
       9: new           #15                 // class org/jboss/as/controller/registry/OperationTransformerRegistry$ResourceTransformerEntry
      12: dup
      13: aload_3
      14: iload         4
      16: invokespecial #16                 // Method org/jboss/as/controller/registry/OperationTransformerRegistry$ResourceTransformerEntry."<init>":(Lorg/jboss/as/controller/transform/ResourceTransformer;Z)V
      19: getstatic     #17                 // Field org/jboss/as/controller/registry/OperationTransformerRegistry.FORWARD:Lorg/jboss/as/controller/registry/OperationTransformerRegistry$OperationTransformerEntry;
      22: iconst_0
      23: invokevirtual #13                 // Method createChildRegistry:(Ljava/util/Iterator;Lorg/jboss/as/controller/ModelVersion;Lorg/jboss/as/controller/transform/PathAddressTransformer;Lorg/jboss/as/controller/registry/OperationTransformerRegistry$ResourceTransformerEntry;Lorg/jboss/as/controller/registry/OperationTransformerRegistry$OperationTransformerEntry;Z)V
      26: return

  public void createChildRegistry(org.jboss.as.controller.PathAddress, org.jboss.as.controller.ModelVersion, org.jboss.as.controller.transform.ResourceTransformer, org.jboss.as.controller.transform.OperationTransformer, boolean);
    Code:
       0: aload_0
       1: aload_1
       2: aload_2
       3: getstatic     #11                 // Field org/jboss/as/controller/transform/PathAddressTransformer.DEFAULT:Lorg/jboss/as/controller/transform/PathAddressTransformer;
       6: aload_3
       7: aload         4
       9: iload         5
      11: invokevirtual #18                 // Method createChildRegistry:(Lorg/jboss/as/controller/PathAddress;Lorg/jboss/as/controller/ModelVersion;Lorg/jboss/as/controller/transform/PathAddressTransformer;Lorg/jboss/as/controller/transform/ResourceTransformer;Lorg/jboss/as/controller/transform/OperationTransformer;Z)V
      14: return

  public void createChildRegistry(org.jboss.as.controller.PathAddress, org.jboss.as.controller.ModelVersion, org.jboss.as.controller.transform.PathAddressTransformer, org.jboss.as.controller.transform.ResourceTransformer, org.jboss.as.controller.transform.OperationTransformer, boolean);
    Code:
       0: aload_0
       1: aload_1
       2: invokevirtual #5                  // Method org/jboss/as/controller/PathAddress.iterator:()Ljava/util/ListIterator;
       5: aload_2
       6: aload_3
       7: new           #15                 // class org/jboss/as/controller/registry/OperationTransformerRegistry$ResourceTransformerEntry
      10: dup
      11: aload         4
      13: iconst_0
      14: invokespecial #16                 // Method org/jboss/as/controller/registry/OperationTransformerRegistry$ResourceTransformerEntry."<init>":(Lorg/jboss/as/controller/transform/ResourceTransformer;Z)V
      17: new           #9                  // class org/jboss/as/controller/registry/OperationTransformerRegistry$OperationTransformerEntry
      20: dup
      21: aload         5
      23: iconst_0
      24: invokespecial #10                 // Method org/jboss/as/controller/registry/OperationTransformerRegistry$OperationTransformerEntry."<init>":(Lorg/jboss/as/controller/transform/OperationTransformer;Z)V
      27: iload         6
      29: invokevirtual #13                 // Method createChildRegistry:(Ljava/util/Iterator;Lorg/jboss/as/controller/ModelVersion;Lorg/jboss/as/controller/transform/PathAddressTransformer;Lorg/jboss/as/controller/registry/OperationTransformerRegistry$ResourceTransformerEntry;Lorg/jboss/as/controller/registry/OperationTransformerRegistry$OperationTransformerEntry;Z)V
      32: return

  public void createChildRegistry(org.jboss.as.controller.PathAddress, org.jboss.as.controller.ModelVersion, org.jboss.as.controller.transform.PathAddressTransformer, org.jboss.as.controller.transform.ResourceTransformer, org.jboss.as.controller.transform.OperationTransformer, boolean, boolean);
    Code:
       0: aload_0
       1: aload_1
       2: invokevirtual #5                  // Method org/jboss/as/controller/PathAddress.iterator:()Ljava/util/ListIterator;
       5: aload_2
       6: aload_3
       7: new           #15                 // class org/jboss/as/controller/registry/OperationTransformerRegistry$ResourceTransformerEntry
      10: dup
      11: aload         4
      13: iconst_0
      14: invokespecial #16                 // Method org/jboss/as/controller/registry/OperationTransformerRegistry$ResourceTransformerEntry."<init>":(Lorg/jboss/as/controller/transform/ResourceTransformer;Z)V
      17: new           #9                  // class org/jboss/as/controller/registry/OperationTransformerRegistry$OperationTransformerEntry
      20: dup
      21: aload         5
      23: iload         6
      25: invokespecial #10                 // Method org/jboss/as/controller/registry/OperationTransformerRegistry$OperationTransformerEntry."<init>":(Lorg/jboss/as/controller/transform/OperationTransformer;Z)V
      28: iload         7
      30: invokevirtual #13                 // Method createChildRegistry:(Ljava/util/Iterator;Lorg/jboss/as/controller/ModelVersion;Lorg/jboss/as/controller/transform/PathAddressTransformer;Lorg/jboss/as/controller/registry/OperationTransformerRegistry$ResourceTransformerEntry;Lorg/jboss/as/controller/registry/OperationTransformerRegistry$OperationTransformerEntry;Z)V
      33: return

  public void registerTransformer(org.jboss.as.controller.PathAddress, org.jboss.as.controller.ModelVersion, java.lang.String, org.jboss.as.controller.transform.OperationTransformer);
    Code:
       0: aload_0
       1: aload_1
       2: invokevirtual #5                  // Method org/jboss/as/controller/PathAddress.iterator:()Ljava/util/ListIterator;
       5: aload_2
       6: aload_3
       7: new           #9                  // class org/jboss/as/controller/registry/OperationTransformerRegistry$OperationTransformerEntry
      10: dup
      11: aload         4
      13: iconst_0
      14: invokespecial #10                 // Method org/jboss/as/controller/registry/OperationTransformerRegistry$OperationTransformerEntry."<init>":(Lorg/jboss/as/controller/transform/OperationTransformer;Z)V
      17: invokevirtual #8                  // Method registerTransformer:(Ljava/util/Iterator;Lorg/jboss/as/controller/ModelVersion;Ljava/lang/String;Lorg/jboss/as/controller/registry/OperationTransformerRegistry$OperationTransformerEntry;)V
      20: return

  public org.jboss.as.controller.registry.OperationTransformerRegistry mergeSubtree(org.jboss.as.controller.registry.OperationTransformerRegistry, org.jboss.as.controller.PathAddress, java.util.Map<org.jboss.as.controller.PathAddress, org.jboss.as.controller.ModelVersion>);
    Code:
       0: aload_1
       1: aload_2
       2: invokevirtual #5                  // Method org/jboss/as/controller/PathAddress.iterator:()Ljava/util/ListIterator;
       5: getstatic     #11                 // Field org/jboss/as/controller/transform/PathAddressTransformer.DEFAULT:Lorg/jboss/as/controller/transform/PathAddressTransformer;
       8: getstatic     #14                 // Field RESOURCE_TRANSFORMER:Lorg/jboss/as/controller/registry/OperationTransformerRegistry$ResourceTransformerEntry;
      11: getstatic     #17                 // Field org/jboss/as/controller/registry/OperationTransformerRegistry.FORWARD:Lorg/jboss/as/controller/registry/OperationTransformerRegistry$OperationTransformerEntry;
      14: iconst_0
      15: invokevirtual #19                 // Method org/jboss/as/controller/registry/OperationTransformerRegistry.createChildRegistry:(Ljava/util/Iterator;Lorg/jboss/as/controller/transform/PathAddressTransformer;Lorg/jboss/as/controller/registry/OperationTransformerRegistry$ResourceTransformerEntry;Lorg/jboss/as/controller/registry/OperationTransformerRegistry$OperationTransformerEntry;Z)Lorg/jboss/as/controller/registry/OperationTransformerRegistry;
      18: astore        4
      20: aload_0
      21: aload         4
      23: aload_3
      24: invokevirtual #20                 // Method mergeSubtree:(Lorg/jboss/as/controller/registry/OperationTransformerRegistry;Ljava/util/Map;)V
      27: aload         4
      29: areturn

  public void mergeSubtree(org.jboss.as.controller.registry.OperationTransformerRegistry, java.util.Map<org.jboss.as.controller.PathAddress, org.jboss.as.controller.ModelVersion>);
    Code:
       0: aload_2
       1: invokeinterface #21,  1           // InterfaceMethod java/util/Map.entrySet:()Ljava/util/Set;
       6: invokeinterface #22,  1           // InterfaceMethod java/util/Set.iterator:()Ljava/util/Iterator;
      11: astore_3
      12: aload_3
      13: invokeinterface #23,  1           // InterfaceMethod java/util/Iterator.hasNext:()Z
      18: ifeq          60
      21: aload_3
      22: invokeinterface #24,  1           // InterfaceMethod java/util/Iterator.next:()Ljava/lang/Object;
      27: checkcast     #25                 // class java/util/Map$Entry
      30: astore        4
      32: aload_0
      33: aload_1
      34: aload         4
      36: invokeinterface #26,  1           // InterfaceMethod java/util/Map$Entry.getKey:()Ljava/lang/Object;
      41: checkcast     #27                 // class org/jboss/as/controller/PathAddress
      44: aload         4
      46: invokeinterface #28,  1           // InterfaceMethod java/util/Map$Entry.getValue:()Ljava/lang/Object;
      51: checkcast     #29                 // class org/jboss/as/controller/ModelVersion
      54: invokevirtual #30                 // Method mergeSubtree:(Lorg/jboss/as/controller/registry/OperationTransformerRegistry;Lorg/jboss/as/controller/PathAddress;Lorg/jboss/as/controller/ModelVersion;)V
      57: goto          12
      60: return

  protected void mergeSubtree(org.jboss.as.controller.registry.OperationTransformerRegistry, org.jboss.as.controller.PathAddress, org.jboss.as.controller.ModelVersion);
    Code:
       0: aload_0
       1: aload_2
       2: invokevirtual #5                  // Method org/jboss/as/controller/PathAddress.iterator:()Ljava/util/ListIterator;
       5: invokevirtual #31                 // Method navigate:(Ljava/util/Iterator;)Lorg/jboss/as/controller/registry/GlobalTransformerRegistry;
       8: astore        4
      10: aload         4
      12: ifnull        26
      15: aload         4
      17: aload_1
      18: aload_2
      19: aload_3
      20: invokestatic  #32                 // Method java/util/Collections.emptyMap:()Ljava/util/Map;
      23: invokevirtual #33                 // Method process:(Lorg/jboss/as/controller/registry/OperationTransformerRegistry;Lorg/jboss/as/controller/PathAddress;Lorg/jboss/as/controller/ModelVersion;Ljava/util/Map;)V
      26: return

  public org.jboss.as.controller.registry.OperationTransformerRegistry create(org.jboss.as.controller.ModelVersion, java.util.Map<org.jboss.as.controller.PathAddress, org.jboss.as.controller.ModelVersion>);
    Code:
       0: new           #34                 // class org/jboss/as/controller/registry/OperationTransformerRegistry
       3: dup
       4: getstatic     #11                 // Field org/jboss/as/controller/transform/PathAddressTransformer.DEFAULT:Lorg/jboss/as/controller/transform/PathAddressTransformer;
       7: getstatic     #14                 // Field RESOURCE_TRANSFORMER:Lorg/jboss/as/controller/registry/OperationTransformerRegistry$ResourceTransformerEntry;
      10: aconst_null
      11: iconst_0
      12: invokespecial #35                 // Method org/jboss/as/controller/registry/OperationTransformerRegistry."<init>":(Lorg/jboss/as/controller/transform/PathAddressTransformer;Lorg/jboss/as/controller/registry/OperationTransformerRegistry$ResourceTransformerEntry;Lorg/jboss/as/controller/registry/OperationTransformerRegistry$OperationTransformerEntry;Z)V
      15: astore_3
      16: aload_0
      17: aload_3
      18: getstatic     #36                 // Field org/jboss/as/controller/PathAddress.EMPTY_ADDRESS:Lorg/jboss/as/controller/PathAddress;
      21: aload_1
      22: aload_2
      23: invokevirtual #33                 // Method process:(Lorg/jboss/as/controller/registry/OperationTransformerRegistry;Lorg/jboss/as/controller/PathAddress;Lorg/jboss/as/controller/ModelVersion;Ljava/util/Map;)V
      26: aload_3
      27: areturn

  protected void process(org.jboss.as.controller.registry.OperationTransformerRegistry, org.jboss.as.controller.PathAddress, org.jboss.as.controller.ModelVersion, java.util.Map<org.jboss.as.controller.PathAddress, org.jboss.as.controller.ModelVersion>);
    Code:
       0: aload_0
       1: aload_3
       2: invokespecial #37                 // Method getRegistryUpdater:(Lorg/jboss/as/controller/ModelVersion;)Lorg/jboss/as/controller/registry/OperationTransformerRegistry;
       5: astore        5
       7: aload         5
       9: ifnull        123
      12: aload         5
      14: invokevirtual #38                 // Method org/jboss/as/controller/registry/OperationTransformerRegistry.getResourceTransformer:()Lorg/jboss/as/controller/registry/OperationTransformerRegistry$ResourceTransformerEntry;
      17: astore        6
      19: aload         5
      21: invokevirtual #39                 // Method org/jboss/as/controller/registry/OperationTransformerRegistry.getDefaultTransformer:()Lorg/jboss/as/controller/registry/OperationTransformerRegistry$OperationTransformerEntry;
      24: astore        7
      26: aload_1
      27: aload_2
      28: invokevirtual #5                  // Method org/jboss/as/controller/PathAddress.iterator:()Ljava/util/ListIterator;
      31: aload         5
      33: invokevirtual #40                 // Method org/jboss/as/controller/registry/OperationTransformerRegistry.getPathAddressTransformer:()Lorg/jboss/as/controller/transform/PathAddressTransformer;
      36: aload         6
      38: aload         7
      40: aload         5
      42: invokevirtual #41                 // Method org/jboss/as/controller/registry/OperationTransformerRegistry.isPlaceholder:()Z
      45: invokevirtual #19                 // Method org/jboss/as/controller/registry/OperationTransformerRegistry.createChildRegistry:(Ljava/util/Iterator;Lorg/jboss/as/controller/transform/PathAddressTransformer;Lorg/jboss/as/controller/registry/OperationTransformerRegistry$ResourceTransformerEntry;Lorg/jboss/as/controller/registry/OperationTransformerRegistry$OperationTransformerEntry;Z)Lorg/jboss/as/controller/registry/OperationTransformerRegistry;
      48: pop
      49: aload         5
      51: invokevirtual #42                 // Method org/jboss/as/controller/registry/OperationTransformerRegistry.getTransformers:()Ljava/util/Map;
      54: astore        8
      56: aload         8
      58: invokeinterface #21,  1           // InterfaceMethod java/util/Map.entrySet:()Ljava/util/Set;
      63: invokeinterface #22,  1           // InterfaceMethod java/util/Set.iterator:()Ljava/util/Iterator;
      68: astore        9
      70: aload         9
      72: invokeinterface #23,  1           // InterfaceMethod java/util/Iterator.hasNext:()Z
      77: ifeq          123
      80: aload         9
      82: invokeinterface #24,  1           // InterfaceMethod java/util/Iterator.next:()Ljava/lang/Object;
      87: checkcast     #25                 // class java/util/Map$Entry
      90: astore        10
      92: aload_1
      93: aload_2
      94: aload         10
      96: invokeinterface #26,  1           // InterfaceMethod java/util/Map$Entry.getKey:()Ljava/lang/Object;
     101: checkcast     #43                 // class java/lang/String
     104: aload         10
     106: invokeinterface #28,  1           // InterfaceMethod java/util/Map$Entry.getValue:()Ljava/lang/Object;
     111: checkcast     #9                  // class org/jboss/as/controller/registry/OperationTransformerRegistry$OperationTransformerEntry
     114: invokevirtual #44                 // Method org/jboss/as/controller/registry/OperationTransformerRegistry$OperationTransformerEntry.getTransformer:()Lorg/jboss/as/controller/transform/OperationTransformer;
     117: invokevirtual #45                 // Method org/jboss/as/controller/registry/OperationTransformerRegistry.registerTransformer:(Lorg/jboss/as/controller/PathAddress;Ljava/lang/String;Lorg/jboss/as/controller/transform/OperationTransformer;)V
     120: goto          70
     123: getstatic     #4                  // Field subRegistriesUpdater:Lorg/jboss/as/controller/registry/AtomicMapFieldUpdater;
     126: aload_0
     127: invokevirtual #46                 // Method org/jboss/as/controller/registry/AtomicMapFieldUpdater.get:(Ljava/lang/Object;)Ljava/util/Map;
     130: astore        6
     132: aload         6
     134: ifnull        335
     137: aload         6
     139: invokeinterface #21,  1           // InterfaceMethod java/util/Map.entrySet:()Ljava/util/Set;
     144: invokeinterface #22,  1           // InterfaceMethod java/util/Set.iterator:()Ljava/util/Iterator;
     149: astore        7
     151: aload         7
     153: invokeinterface #23,  1           // InterfaceMethod java/util/Iterator.hasNext:()Z
     158: ifeq          335
     161: aload         7
     163: invokeinterface #24,  1           // InterfaceMethod java/util/Iterator.next:()Ljava/lang/Object;
     168: checkcast     #25                 // class java/util/Map$Entry
     171: astore        8
     173: aload         8
     175: invokeinterface #26,  1           // InterfaceMethod java/util/Map$Entry.getKey:()Ljava/lang/Object;
     180: checkcast     #43                 // class java/lang/String
     183: astore        9
     185: aload         8
     187: invokeinterface #28,  1           // InterfaceMethod java/util/Map$Entry.getValue:()Ljava/lang/Object;
     192: checkcast     #47                 // class org/jboss/as/controller/registry/GlobalTransformerRegistry$SubRegistry
     195: astore        10
     197: invokestatic  #48                 // Method org/jboss/as/controller/registry/GlobalTransformerRegistry$SubRegistry.access$000:()Lorg/jboss/as/controller/registry/AtomicMapFieldUpdater;
     200: aload         10
     202: invokevirtual #46                 // Method org/jboss/as/controller/registry/AtomicMapFieldUpdater.get:(Ljava/lang/Object;)Ljava/util/Map;
     205: astore        11
     207: aload         11
     209: invokeinterface #21,  1           // InterfaceMethod java/util/Map.entrySet:()Ljava/util/Set;
     214: invokeinterface #22,  1           // InterfaceMethod java/util/Set.iterator:()Ljava/util/Iterator;
     219: astore        12
     221: aload         12
     223: invokeinterface #23,  1           // InterfaceMethod java/util/Iterator.hasNext:()Z
     228: ifeq          332
     231: aload         12
     233: invokeinterface #24,  1           // InterfaceMethod java/util/Iterator.next:()Ljava/lang/Object;
     238: checkcast     #25                 // class java/util/Map$Entry
     241: astore        13
     243: aload         13
     245: invokeinterface #26,  1           // InterfaceMethod java/util/Map$Entry.getKey:()Ljava/lang/Object;
     250: checkcast     #43                 // class java/lang/String
     253: astore        14
     255: aload         13
     257: invokeinterface #28,  1           // InterfaceMethod java/util/Map$Entry.getValue:()Ljava/lang/Object;
     262: checkcast     #49                 // class org/jboss/as/controller/registry/GlobalTransformerRegistry
     265: astore        15
     267: aload_2
     268: iconst_1
     269: anewarray     #50                 // class org/jboss/as/controller/PathElement
     272: dup
     273: iconst_0
     274: aload         9
     276: aload         14
     278: invokestatic  #51                 // Method org/jboss/as/controller/PathElement.pathElement:(Ljava/lang/String;Ljava/lang/String;)Lorg/jboss/as/controller/PathElement;
     281: aastore
     282: invokevirtual #52                 // Method org/jboss/as/controller/PathAddress.append:([Lorg/jboss/as/controller/PathElement;)Lorg/jboss/as/controller/PathAddress;
     285: astore        16
     287: aload         4
     289: aload         16
     291: invokeinterface #53,  2           // InterfaceMethod java/util/Map.containsKey:(Ljava/lang/Object;)Z
     296: ifeq          314
     299: aload         4
     301: aload         16
     303: invokeinterface #54,  2           // InterfaceMethod java/util/Map.get:(Ljava/lang/Object;)Ljava/lang/Object;
     308: checkcast     #29                 // class org/jboss/as/controller/ModelVersion
     311: goto          315
     314: aload_3
     315: astore        17
     317: aload         15
     319: aload_1
     320: aload         16
     322: aload         17
     324: aload         4
     326: invokevirtual #33                 // Method process:(Lorg/jboss/as/controller/registry/OperationTransformerRegistry;Lorg/jboss/as/controller/PathAddress;Lorg/jboss/as/controller/ModelVersion;Ljava/util/Map;)V
     329: goto          221
     332: goto          151
     335: return

  private org.jboss.as.controller.registry.OperationTransformerRegistry getRegistryUpdater(org.jboss.as.controller.ModelVersion);
    Code:
       0: aload_1
       1: invokevirtual #55                 // Method org/jboss/as/controller/ModelVersion.getMicro:()I
       4: istore_2
       5: iload_2
       6: istore_3
       7: iload_3
       8: iflt          79
      11: aload_1
      12: invokevirtual #56                 // Method org/jboss/as/controller/ModelVersion.getMajor:()I
      15: aload_1
      16: invokevirtual #57                 // Method org/jboss/as/controller/ModelVersion.getMinor:()I
      19: iload_3
      20: invokestatic  #58                 // Method org/jboss/as/controller/ModelVersion.create:(III)Lorg/jboss/as/controller/ModelVersion;
      23: astore        4
      25: getstatic     #2                  // Field registryUpdater:Lorg/jboss/as/controller/registry/AtomicMapFieldUpdater;
      28: aload_0
      29: aload         4
      31: invokevirtual #59                 // Method org/jboss/as/controller/registry/AtomicMapFieldUpdater.get:(Ljava/lang/Object;Ljava/lang/Object;)Ljava/lang/Object;
      34: checkcast     #34                 // class org/jboss/as/controller/registry/OperationTransformerRegistry
      37: astore        5
      39: aload         5
      41: ifnull        73
      44: iload_2
      45: iload_3
      46: if_icmpeq     70
      49: aload_0
      50: invokevirtual #60                 // Method java/lang/Object.getClass:()Ljava/lang/Class;
      53: invokevirtual #61                 // Method java/lang/Class.desiredAssertionStatus:()Z
      56: ifeq          70
      59: getstatic     #62                 // Field org/jboss/as/controller/logging/ControllerLogger.MGMT_OP_LOGGER:Lorg/jboss/as/controller/logging/ControllerLogger;
      62: aload_1
      63: aload         4
      65: invokeinterface #63,  3           // InterfaceMethod org/jboss/as/controller/logging/ControllerLogger.couldNotFindTransformerRegistryFallingBack:(Lorg/jboss/as/controller/ModelVersion;Lorg/jboss/as/controller/ModelVersion;)V
      70: aload         5
      72: areturn
      73: iinc          3, -1
      76: goto          7
      79: aconst_null
      80: areturn

  protected void createChildRegistry(java.util.Iterator<org.jboss.as.controller.PathElement>, org.jboss.as.controller.ModelVersion, org.jboss.as.controller.transform.PathAddressTransformer, org.jboss.as.controller.registry.OperationTransformerRegistry$ResourceTransformerEntry, org.jboss.as.controller.registry.OperationTransformerRegistry$OperationTransformerEntry, boolean);
    Code:
       0: aload_1
       1: invokeinterface #23,  1           // InterfaceMethod java/util/Iterator.hasNext:()Z
       6: ifne          25
       9: aload_0
      10: aload_2
      11: aload_3
      12: aload         4
      14: aload         5
      16: iload         6
      18: invokevirtual #64                 // Method getOrCreate:(Lorg/jboss/as/controller/ModelVersion;Lorg/jboss/as/controller/transform/PathAddressTransformer;Lorg/jboss/as/controller/registry/OperationTransformerRegistry$ResourceTransformerEntry;Lorg/jboss/as/controller/registry/OperationTransformerRegistry$OperationTransformerEntry;Z)Lorg/jboss/as/controller/registry/OperationTransformerRegistry;
      21: pop
      22: goto          65
      25: aload_1
      26: invokeinterface #24,  1           // InterfaceMethod java/util/Iterator.next:()Ljava/lang/Object;
      31: checkcast     #50                 // class org/jboss/as/controller/PathElement
      34: astore        7
      36: aload_0
      37: aload         7
      39: invokevirtual #65                 // Method org/jboss/as/controller/PathElement.getKey:()Ljava/lang/String;
      42: invokevirtual #66                 // Method getOrCreate:(Ljava/lang/String;)Lorg/jboss/as/controller/registry/GlobalTransformerRegistry$SubRegistry;
      45: aload         7
      47: invokevirtual #67                 // Method org/jboss/as/controller/PathElement.getValue:()Ljava/lang/String;
      50: invokevirtual #68                 // Method org/jboss/as/controller/registry/GlobalTransformerRegistry$SubRegistry.getOrCreate:(Ljava/lang/String;)Lorg/jboss/as/controller/registry/GlobalTransformerRegistry;
      53: aload_1
      54: aload_2
      55: aload_3
      56: aload         4
      58: aload         5
      60: iload         6
      62: invokevirtual #13                 // Method createChildRegistry:(Ljava/util/Iterator;Lorg/jboss/as/controller/ModelVersion;Lorg/jboss/as/controller/transform/PathAddressTransformer;Lorg/jboss/as/controller/registry/OperationTransformerRegistry$ResourceTransformerEntry;Lorg/jboss/as/controller/registry/OperationTransformerRegistry$OperationTransformerEntry;Z)V
      65: return

  protected void registerTransformer(java.util.Iterator<org.jboss.as.controller.PathElement>, org.jboss.as.controller.ModelVersion, java.lang.String, org.jboss.as.controller.registry.OperationTransformerRegistry$OperationTransformerEntry);
    Code:
       0: aload_1
       1: invokeinterface #23,  1           // InterfaceMethod java/util/Iterator.hasNext:()Z
       6: ifne          35
       9: aload_0
      10: aload_2
      11: getstatic     #11                 // Field org/jboss/as/controller/transform/PathAddressTransformer.DEFAULT:Lorg/jboss/as/controller/transform/PathAddressTransformer;
      14: aconst_null
      15: aconst_null
      16: iconst_0
      17: invokevirtual #64                 // Method getOrCreate:(Lorg/jboss/as/controller/ModelVersion;Lorg/jboss/as/controller/transform/PathAddressTransformer;Lorg/jboss/as/controller/registry/OperationTransformerRegistry$ResourceTransformerEntry;Lorg/jboss/as/controller/registry/OperationTransformerRegistry$OperationTransformerEntry;Z)Lorg/jboss/as/controller/registry/OperationTransformerRegistry;
      20: getstatic     #36                 // Field org/jboss/as/controller/PathAddress.EMPTY_ADDRESS:Lorg/jboss/as/controller/PathAddress;
      23: invokevirtual #5                  // Method org/jboss/as/controller/PathAddress.iterator:()Ljava/util/ListIterator;
      26: aload_3
      27: aload         4
      29: invokevirtual #69                 // Method org/jboss/as/controller/registry/OperationTransformerRegistry.registerTransformer:(Ljava/util/Iterator;Ljava/lang/String;Lorg/jboss/as/controller/registry/OperationTransformerRegistry$OperationTransformerEntry;)V
      32: goto          72
      35: aload_1
      36: invokeinterface #24,  1           // InterfaceMethod java/util/Iterator.next:()Ljava/lang/Object;
      41: checkcast     #50                 // class org/jboss/as/controller/PathElement
      44: astore        5
      46: aload_0
      47: aload         5
      49: invokevirtual #65                 // Method org/jboss/as/controller/PathElement.getKey:()Ljava/lang/String;
      52: invokevirtual #66                 // Method getOrCreate:(Ljava/lang/String;)Lorg/jboss/as/controller/registry/GlobalTransformerRegistry$SubRegistry;
      55: astore        6
      57: aload         6
      59: aload_1
      60: aload         5
      62: invokevirtual #67                 // Method org/jboss/as/controller/PathElement.getValue:()Ljava/lang/String;
      65: aload_2
      66: aload_3
      67: aload         4
      69: invokevirtual #70                 // Method org/jboss/as/controller/registry/GlobalTransformerRegistry$SubRegistry.registerTransformer:(Ljava/util/Iterator;Ljava/lang/String;Lorg/jboss/as/controller/ModelVersion;Ljava/lang/String;Lorg/jboss/as/controller/registry/OperationTransformerRegistry$OperationTransformerEntry;)V
      72: return

  protected org.jboss.as.controller.registry.OperationTransformerRegistry$OperationTransformerEntry resolveTransformer(java.util.Iterator<org.jboss.as.controller.PathElement>, org.jboss.as.controller.ModelVersion, java.lang.String);
    Code:
       0: aload_1
       1: invokeinterface #23,  1           // InterfaceMethod java/util/Iterator.hasNext:()Z
       6: ifne          40
       9: getstatic     #2                  // Field registryUpdater:Lorg/jboss/as/controller/registry/AtomicMapFieldUpdater;
      12: aload_0
      13: aload_2
      14: invokevirtual #59                 // Method org/jboss/as/controller/registry/AtomicMapFieldUpdater.get:(Ljava/lang/Object;Ljava/lang/Object;)Ljava/lang/Object;
      17: checkcast     #34                 // class org/jboss/as/controller/registry/OperationTransformerRegistry
      20: astore        4
      22: aload         4
      24: ifnonnull     29
      27: aconst_null
      28: areturn
      29: aload         4
      31: getstatic     #36                 // Field org/jboss/as/controller/PathAddress.EMPTY_ADDRESS:Lorg/jboss/as/controller/PathAddress;
      34: aload_3
      35: aconst_null
      36: invokevirtual #71                 // Method org/jboss/as/controller/registry/OperationTransformerRegistry.resolveOperationTransformer:(Lorg/jboss/as/controller/PathAddress;Ljava/lang/String;Lorg/jboss/as/controller/registry/OperationTransformerRegistry$PlaceholderResolver;)Lorg/jboss/as/controller/registry/OperationTransformerRegistry$OperationTransformerEntry;
      39: areturn
      40: aload_1
      41: invokeinterface #24,  1           // InterfaceMethod java/util/Iterator.next:()Ljava/lang/Object;
      46: checkcast     #50                 // class org/jboss/as/controller/PathElement
      49: astore        4
      51: getstatic     #4                  // Field subRegistriesUpdater:Lorg/jboss/as/controller/registry/AtomicMapFieldUpdater;
      54: aload_0
      55: aload         4
      57: invokevirtual #65                 // Method org/jboss/as/controller/PathElement.getKey:()Ljava/lang/String;
      60: invokevirtual #59                 // Method org/jboss/as/controller/registry/AtomicMapFieldUpdater.get:(Ljava/lang/Object;Ljava/lang/Object;)Ljava/lang/Object;
      63: checkcast     #47                 // class org/jboss/as/controller/registry/GlobalTransformerRegistry$SubRegistry
      66: astore        5
      68: aload         5
      70: ifnonnull     75
      73: aconst_null
      74: areturn
      75: aload         5
      77: aload_1
      78: aload         4
      80: invokevirtual #67                 // Method org/jboss/as/controller/PathElement.getValue:()Ljava/lang/String;
      83: aload_2
      84: aload_3
      85: invokevirtual #72                 // Method org/jboss/as/controller/registry/GlobalTransformerRegistry$SubRegistry.resolveTransformer:(Ljava/util/Iterator;Ljava/lang/String;Lorg/jboss/as/controller/ModelVersion;Ljava/lang/String;)Lorg/jboss/as/controller/registry/OperationTransformerRegistry$OperationTransformerEntry;
      88: areturn

  org.jboss.as.controller.registry.GlobalTransformerRegistry navigate(java.util.Iterator<org.jboss.as.controller.PathElement>);
    Code:
       0: aload_1
       1: invokeinterface #23,  1           // InterfaceMethod java/util/Iterator.hasNext:()Z
       6: ifne          11
       9: aload_0
      10: areturn
      11: aload_1
      12: invokeinterface #24,  1           // InterfaceMethod java/util/Iterator.next:()Ljava/lang/Object;
      17: checkcast     #50                 // class org/jboss/as/controller/PathElement
      20: astore_2
      21: getstatic     #4                  // Field subRegistriesUpdater:Lorg/jboss/as/controller/registry/AtomicMapFieldUpdater;
      24: aload_0
      25: aload_2
      26: invokevirtual #65                 // Method org/jboss/as/controller/PathElement.getKey:()Ljava/lang/String;
      29: invokevirtual #59                 // Method org/jboss/as/controller/registry/AtomicMapFieldUpdater.get:(Ljava/lang/Object;Ljava/lang/Object;)Ljava/lang/Object;
      32: checkcast     #47                 // class org/jboss/as/controller/registry/GlobalTransformerRegistry$SubRegistry
      35: astore_3
      36: aload_3
      37: ifnonnull     42
      40: aconst_null
      41: areturn
      42: invokestatic  #48                 // Method org/jboss/as/controller/registry/GlobalTransformerRegistry$SubRegistry.access$000:()Lorg/jboss/as/controller/registry/AtomicMapFieldUpdater;
      45: aload_3
      46: aload_2
      47: invokevirtual #67                 // Method org/jboss/as/controller/PathElement.getValue:()Ljava/lang/String;
      50: invokevirtual #59                 // Method org/jboss/as/controller/registry/AtomicMapFieldUpdater.get:(Ljava/lang/Object;Ljava/lang/Object;)Ljava/lang/Object;
      53: checkcast     #49                 // class org/jboss/as/controller/registry/GlobalTransformerRegistry
      56: astore        4
      58: aload         4
      60: ifnull        70
      63: aload         4
      65: aload_1
      66: invokevirtual #31                 // Method navigate:(Ljava/util/Iterator;)Lorg/jboss/as/controller/registry/GlobalTransformerRegistry;
      69: areturn
      70: aconst_null
      71: areturn

  org.jboss.as.controller.registry.GlobalTransformerRegistry$SubRegistry getOrCreate(java.lang.String);
    Code:
       0: getstatic     #4                  // Field subRegistriesUpdater:Lorg/jboss/as/controller/registry/AtomicMapFieldUpdater;
       3: aload_0
       4: invokevirtual #46                 // Method org/jboss/as/controller/registry/AtomicMapFieldUpdater.get:(Ljava/lang/Object;)Ljava/util/Map;
       7: astore_2
       8: aload_2
       9: aload_1
      10: invokeinterface #54,  2           // InterfaceMethod java/util/Map.get:(Ljava/lang/Object;)Ljava/lang/Object;
      15: checkcast     #47                 // class org/jboss/as/controller/registry/GlobalTransformerRegistry$SubRegistry
      18: astore_3
      19: aload_3
      20: ifnonnull     62
      23: new           #47                 // class org/jboss/as/controller/registry/GlobalTransformerRegistry$SubRegistry
      26: dup
      27: invokespecial #73                 // Method org/jboss/as/controller/registry/GlobalTransformerRegistry$SubRegistry."<init>":()V
      30: astore_3
      31: getstatic     #4                  // Field subRegistriesUpdater:Lorg/jboss/as/controller/registry/AtomicMapFieldUpdater;
      34: aload_0
      35: aload_1
      36: aload_3
      37: aload_2
      38: invokevirtual #74                 // Method org/jboss/as/controller/registry/AtomicMapFieldUpdater.putAtomic:(Ljava/lang/Object;Ljava/lang/Object;Ljava/lang/Object;Ljava/util/Map;)Ljava/lang/Object;
      41: checkcast     #47                 // class org/jboss/as/controller/registry/GlobalTransformerRegistry$SubRegistry
      44: astore        4
      46: aload         4
      48: ifnonnull     53
      51: aload_3
      52: areturn
      53: aload         4
      55: aload_3
      56: if_acmpeq     62
      59: aload         4
      61: areturn
      62: aload_3
      63: areturn

  org.jboss.as.controller.registry.OperationTransformerRegistry getOrCreate(org.jboss.as.controller.ModelVersion, org.jboss.as.controller.transform.PathAddressTransformer, org.jboss.as.controller.registry.OperationTransformerRegistry$ResourceTransformerEntry, org.jboss.as.controller.registry.OperationTransformerRegistry$OperationTransformerEntry, boolean);
    Code:
       0: getstatic     #2                  // Field registryUpdater:Lorg/jboss/as/controller/registry/AtomicMapFieldUpdater;
       3: aload_0
       4: invokevirtual #46                 // Method org/jboss/as/controller/registry/AtomicMapFieldUpdater.get:(Ljava/lang/Object;)Ljava/util/Map;
       7: astore        6
       9: aload         6
      11: aload_1
      12: invokeinterface #54,  2           // InterfaceMethod java/util/Map.get:(Ljava/lang/Object;)Ljava/lang/Object;
      17: checkcast     #34                 // class org/jboss/as/controller/registry/OperationTransformerRegistry
      20: astore        7
      22: aload         7
      24: ifnonnull     77
      27: new           #34                 // class org/jboss/as/controller/registry/OperationTransformerRegistry
      30: dup
      31: aload_2
      32: aload_3
      33: aload         4
      35: iload         5
      37: invokespecial #35                 // Method org/jboss/as/controller/registry/OperationTransformerRegistry."<init>":(Lorg/jboss/as/controller/transform/PathAddressTransformer;Lorg/jboss/as/controller/registry/OperationTransformerRegistry$ResourceTransformerEntry;Lorg/jboss/as/controller/registry/OperationTransformerRegistry$OperationTransformerEntry;Z)V
      40: astore        7
      42: getstatic     #2                  // Field registryUpdater:Lorg/jboss/as/controller/registry/AtomicMapFieldUpdater;
      45: aload_0
      46: aload_1
      47: aload         7
      49: aload         6
      51: invokevirtual #74                 // Method org/jboss/as/controller/registry/AtomicMapFieldUpdater.putAtomic:(Ljava/lang/Object;Ljava/lang/Object;Ljava/lang/Object;Ljava/util/Map;)Ljava/lang/Object;
      54: checkcast     #34                 // class org/jboss/as/controller/registry/OperationTransformerRegistry
      57: astore        8
      59: aload         8
      61: ifnonnull     67
      64: aload         7
      66: areturn
      67: aload         8
      69: aload         7
      71: if_acmpeq     77
      74: aload         8
      76: areturn
      77: aload         7
      79: areturn

  static {};
    Code:
       0: ldc           #49                 // class org/jboss/as/controller/registry/GlobalTransformerRegistry
       2: ldc           #75                 // class java/util/Map
       4: ldc           #76                 // String subRegistries
       6: invokestatic  #77                 // Method java/util/concurrent/atomic/AtomicReferenceFieldUpdater.newUpdater:(Ljava/lang/Class;Ljava/lang/Class;Ljava/lang/String;)Ljava/util/concurrent/atomic/AtomicReferenceFieldUpdater;
       9: invokestatic  #78                 // Method org/jboss/as/controller/registry/AtomicMapFieldUpdater.newMapUpdater:(Ljava/util/concurrent/atomic/AtomicReferenceFieldUpdater;)Lorg/jboss/as/controller/registry/AtomicMapFieldUpdater;
      12: putstatic     #4                  // Field subRegistriesUpdater:Lorg/jboss/as/controller/registry/AtomicMapFieldUpdater;
      15: ldc           #49                 // class org/jboss/as/controller/registry/GlobalTransformerRegistry
      17: ldc           #75                 // class java/util/Map
      19: ldc           #79                 // String versionedRegistries
      21: invokestatic  #77                 // Method java/util/concurrent/atomic/AtomicReferenceFieldUpdater.newUpdater:(Ljava/lang/Class;Ljava/lang/Class;Ljava/lang/String;)Ljava/util/concurrent/atomic/AtomicReferenceFieldUpdater;
      24: invokestatic  #78                 // Method org/jboss/as/controller/registry/AtomicMapFieldUpdater.newMapUpdater:(Ljava/util/concurrent/atomic/AtomicReferenceFieldUpdater;)Lorg/jboss/as/controller/registry/AtomicMapFieldUpdater;
      27: putstatic     #2                  // Field registryUpdater:Lorg/jboss/as/controller/registry/AtomicMapFieldUpdater;
      30: new           #15                 // class org/jboss/as/controller/registry/OperationTransformerRegistry$ResourceTransformerEntry
      33: dup
      34: getstatic     #80                 // Field org/jboss/as/controller/transform/ResourceTransformer.DEFAULT:Lorg/jboss/as/controller/transform/ResourceTransformer;
      37: iconst_0
      38: invokespecial #16                 // Method org/jboss/as/controller/registry/OperationTransformerRegistry$ResourceTransformerEntry."<init>":(Lorg/jboss/as/controller/transform/ResourceTransformer;Z)V
      41: putstatic     #14                 // Field RESOURCE_TRANSFORMER:Lorg/jboss/as/controller/registry/OperationTransformerRegistry$ResourceTransformerEntry;
      44: new           #15                 // class org/jboss/as/controller/registry/OperationTransformerRegistry$ResourceTransformerEntry
      47: dup
      48: getstatic     #81                 // Field org/jboss/as/controller/transform/ResourceTransformer.DISCARD:Lorg/jboss/as/controller/transform/ResourceTransformer;
      51: iconst_1
      52: invokespecial #16                 // Method org/jboss/as/controller/registry/OperationTransformerRegistry$ResourceTransformerEntry."<init>":(Lorg/jboss/as/controller/transform/ResourceTransformer;Z)V
      55: putstatic     #12                 // Field DISCARD:Lorg/jboss/as/controller/registry/OperationTransformerRegistry$ResourceTransformerEntry;
      58: return
}
