public class org.bouncycastle.asn1.ocsp.ResponderID extends org.bouncycastle.asn1.ASN1Object implements org.bouncycastle.asn1.ASN1Choice {
  private org.bouncycastle.asn1.ASN1Encodable value;

  public org.bouncycastle.asn1.ocsp.ResponderID(org.bouncycastle.asn1.ASN1OctetString);
    Code:
       0: aload_0
       1: invokespecial #53                 // Method org/bouncycastle/asn1/ASN1Object."<init>":()V
       4: aload_0
       5: aload_1
       6: putfield      #52                 // Field value:Lorg/bouncycastle/asn1/ASN1Encodable;
       9: return

  public org.bouncycastle.asn1.ocsp.ResponderID(org.bouncycastle.asn1.x500.X500Name);
    Code:
       0: aload_0
       1: invokespecial #53                 // Method org/bouncycastle/asn1/ASN1Object."<init>":()V
       4: aload_0
       5: aload_1
       6: putfield      #52                 // Field value:Lorg/bouncycastle/asn1/ASN1Encodable;
       9: return

  public static org.bouncycastle.asn1.ocsp.ResponderID getInstance(java.lang.Object);
    Code:
       0: aload_0
       1: instanceof    #27                 // class org/bouncycastle/asn1/ocsp/ResponderID
       4: ifeq          12
       7: aload_0
       8: checkcast     #27                 // class org/bouncycastle/asn1/ocsp/ResponderID
      11: areturn
      12: aload_0
      13: instanceof    #25                 // class org/bouncycastle/asn1/DEROctetString
      16: ifeq          31
      19: new           #27                 // class org/bouncycastle/asn1/ocsp/ResponderID
      22: dup
      23: aload_0
      24: checkcast     #25                 // class org/bouncycastle/asn1/DEROctetString
      27: invokespecial #59                 // Method "<init>":(Lorg/bouncycastle/asn1/ASN1OctetString;)V
      30: areturn
      31: aload_0
      32: instanceof    #24                 // class org/bouncycastle/asn1/ASN1TaggedObject
      35: ifeq          77
      38: aload_0
      39: checkcast     #24                 // class org/bouncycastle/asn1/ASN1TaggedObject
      42: astore_1
      43: aload_1
      44: invokevirtual #56                 // Method org/bouncycastle/asn1/ASN1TaggedObject.getTagNo:()I
      47: iconst_1
      48: if_icmpne     64
      51: new           #27                 // class org/bouncycastle/asn1/ocsp/ResponderID
      54: dup
      55: aload_1
      56: iconst_1
      57: invokestatic  #63                 // Method org/bouncycastle/asn1/x500/X500Name.getInstance:(Lorg/bouncycastle/asn1/ASN1TaggedObject;Z)Lorg/bouncycastle/asn1/x500/X500Name;
      60: invokespecial #60                 // Method "<init>":(Lorg/bouncycastle/asn1/x500/X500Name;)V
      63: areturn
      64: new           #27                 // class org/bouncycastle/asn1/ocsp/ResponderID
      67: dup
      68: aload_1
      69: iconst_1
      70: invokestatic  #55                 // Method org/bouncycastle/asn1/ASN1OctetString.getInstance:(Lorg/bouncycastle/asn1/ASN1TaggedObject;Z)Lorg/bouncycastle/asn1/ASN1OctetString;
      73: invokespecial #59                 // Method "<init>":(Lorg/bouncycastle/asn1/ASN1OctetString;)V
      76: areturn
      77: new           #27                 // class org/bouncycastle/asn1/ocsp/ResponderID
      80: dup
      81: aload_0
      82: invokestatic  #62                 // Method org/bouncycastle/asn1/x500/X500Name.getInstance:(Ljava/lang/Object;)Lorg/bouncycastle/asn1/x500/X500Name;
      85: invokespecial #60                 // Method "<init>":(Lorg/bouncycastle/asn1/x500/X500Name;)V
      88: areturn

  public static org.bouncycastle.asn1.ocsp.ResponderID getInstance(org.bouncycastle.asn1.ASN1TaggedObject, boolean);
    Code:
       0: aload_0
       1: invokevirtual #57                 // Method org/bouncycastle/asn1/ASN1TaggedObject.getObject:()Lorg/bouncycastle/asn1/ASN1Primitive;
       4: invokestatic  #61                 // Method getInstance:(Ljava/lang/Object;)Lorg/bouncycastle/asn1/ocsp/ResponderID;
       7: areturn

  public byte[] getKeyHash();
    Code:
       0: aload_0
       1: getfield      #52                 // Field value:Lorg/bouncycastle/asn1/ASN1Encodable;
       4: instanceof    #23                 // class org/bouncycastle/asn1/ASN1OctetString
       7: ifeq          23
      10: aload_0
      11: getfield      #52                 // Field value:Lorg/bouncycastle/asn1/ASN1Encodable;
      14: checkcast     #23                 // class org/bouncycastle/asn1/ASN1OctetString
      17: astore_1
      18: aload_1
      19: invokevirtual #54                 // Method org/bouncycastle/asn1/ASN1OctetString.getOctets:()[B
      22: areturn
      23: aconst_null
      24: areturn

  public org.bouncycastle.asn1.x500.X500Name getName();
    Code:
       0: aload_0
       1: getfield      #52                 // Field value:Lorg/bouncycastle/asn1/ASN1Encodable;
       4: instanceof    #23                 // class org/bouncycastle/asn1/ASN1OctetString
       7: ifeq          12
      10: aconst_null
      11: areturn
      12: aload_0
      13: getfield      #52                 // Field value:Lorg/bouncycastle/asn1/ASN1Encodable;
      16: invokestatic  #62                 // Method org/bouncycastle/asn1/x500/X500Name.getInstance:(Ljava/lang/Object;)Lorg/bouncycastle/asn1/x500/X500Name;
      19: areturn

  public org.bouncycastle.asn1.ASN1Primitive toASN1Primitive();
    Code:
       0: aload_0
       1: getfield      #52                 // Field value:Lorg/bouncycastle/asn1/ASN1Encodable;
       4: instanceof    #23                 // class org/bouncycastle/asn1/ASN1OctetString
       7: ifeq          24
      10: new           #26                 // class org/bouncycastle/asn1/DERTaggedObject
      13: dup
      14: iconst_1
      15: iconst_2
      16: aload_0
      17: getfield      #52                 // Field value:Lorg/bouncycastle/asn1/ASN1Encodable;
      20: invokespecial #58                 // Method org/bouncycastle/asn1/DERTaggedObject."<init>":(ZILorg/bouncycastle/asn1/ASN1Encodable;)V
      23: areturn
      24: new           #26                 // class org/bouncycastle/asn1/DERTaggedObject
      27: dup
      28: iconst_1
      29: iconst_1
      30: aload_0
      31: getfield      #52                 // Field value:Lorg/bouncycastle/asn1/ASN1Encodable;
      34: invokespecial #58                 // Method org/bouncycastle/asn1/DERTaggedObject."<init>":(ZILorg/bouncycastle/asn1/ASN1Encodable;)V
      37: areturn
}
