Compiled from "IndexHtmlGenerator.java"
public class org.graylog2.web.IndexHtmlGenerator {
  private final java.lang.String template;

  private final java.util.List<java.lang.String> cssFiles;

  private final java.util.List<java.lang.String> sortedJsFiles;

  private final com.floreysoft.jmte.Engine templateEngine;

  private final org.graylog2.configuration.HttpConfiguration httpConfiguration;

  public org.graylog2.web.IndexHtmlGenerator(org.graylog2.web.PluginAssets, com.floreysoft.jmte.Engine, org.graylog2.configuration.HttpConfiguration) throws java.io.IOException;
    Code:
       0: aload_0
       1: ldc           #1                  // String web-interface/index.html.template
       3: invokestatic  #2                  // Method com/google/common/io/Resources.getResource:(Ljava/lang/String;)Ljava/net/URL;
       6: getstatic     #3                  // Field java/nio/charset/StandardCharsets.UTF_8:Ljava/nio/charset/Charset;
       9: invokestatic  #4                  // Method com/google/common/io/Resources.toString:(Ljava/net/URL;Ljava/nio/charset/Charset;)Ljava/lang/String;
      12: aload_1
      13: invokevirtual #5                  // Method org/graylog2/web/PluginAssets.cssFiles:()Ljava/util/List;
      16: aload_1
      17: invokevirtual #6                  // Method org/graylog2/web/PluginAssets.sortedJsFiles:()Ljava/util/List;
      20: aload_2
      21: aload_3
      22: invokespecial #7                  // Method "<init>":(Ljava/lang/String;Ljava/util/List;Ljava/util/List;Lcom/floreysoft/jmte/Engine;Lorg/graylog2/configuration/HttpConfiguration;)V
      25: return

  private org.graylog2.web.IndexHtmlGenerator(java.lang.String, java.util.List<java.lang.String>, java.util.List<java.lang.String>, com.floreysoft.jmte.Engine, org.graylog2.configuration.HttpConfiguration) throws java.io.IOException;
    Code:
       0: aload_0
       1: invokespecial #8                  // Method java/lang/Object."<init>":()V
       4: aload_0
       5: aload_1
       6: ldc           #9                  // String template
       8: invokestatic  #10                 // Method java/util/Objects.requireNonNull:(Ljava/lang/Object;Ljava/lang/String;)Ljava/lang/Object;
      11: checkcast     #11                 // class java/lang/String
      14: putfield      #12                 // Field template:Ljava/lang/String;
      17: aload_0
      18: aload_2
      19: ldc           #13                 // String cssFiles
      21: invokestatic  #10                 // Method java/util/Objects.requireNonNull:(Ljava/lang/Object;Ljava/lang/String;)Ljava/lang/Object;
      24: checkcast     #14                 // class java/util/List
      27: putfield      #15                 // Field cssFiles:Ljava/util/List;
      30: aload_0
      31: aload_3
      32: ldc           #16                 // String sortedJsFiles
      34: invokestatic  #10                 // Method java/util/Objects.requireNonNull:(Ljava/lang/Object;Ljava/lang/String;)Ljava/lang/Object;
      37: checkcast     #14                 // class java/util/List
      40: putfield      #17                 // Field sortedJsFiles:Ljava/util/List;
      43: aload_0
      44: aload         4
      46: ldc           #18                 // String templateEngine
      48: invokestatic  #10                 // Method java/util/Objects.requireNonNull:(Ljava/lang/Object;Ljava/lang/String;)Ljava/lang/Object;
      51: checkcast     #19                 // class com/floreysoft/jmte/Engine
      54: putfield      #20                 // Field templateEngine:Lcom/floreysoft/jmte/Engine;
      57: aload_0
      58: aload         5
      60: ldc           #21                 // String httpConfiguration
      62: invokestatic  #10                 // Method java/util/Objects.requireNonNull:(Ljava/lang/Object;Ljava/lang/String;)Ljava/lang/Object;
      65: checkcast     #22                 // class org/graylog2/configuration/HttpConfiguration
      68: putfield      #23                 // Field httpConfiguration:Lorg/graylog2/configuration/HttpConfiguration;
      71: return

  public java.lang.String get(javax.ws.rs.core.MultivaluedMap<java.lang.String, java.lang.String>);
    Code:
       0: invokestatic  #24                 // Method com/google/common/collect/ImmutableMap.builder:()Lcom/google/common/collect/ImmutableMap$Builder;
       3: ldc           #25                 // String title
       5: ldc           #26                 // String Graylog Web Interface
       7: invokevirtual #27                 // Method com/google/common/collect/ImmutableMap$Builder.put:(Ljava/lang/Object;Ljava/lang/Object;)Lcom/google/common/collect/ImmutableMap$Builder;
      10: ldc           #13                 // String cssFiles
      12: aload_0
      13: getfield      #15                 // Field cssFiles:Ljava/util/List;
      16: invokevirtual #27                 // Method com/google/common/collect/ImmutableMap$Builder.put:(Ljava/lang/Object;Ljava/lang/Object;)Lcom/google/common/collect/ImmutableMap$Builder;
      19: ldc           #28                 // String jsFiles
      21: aload_0
      22: getfield      #17                 // Field sortedJsFiles:Ljava/util/List;
      25: invokevirtual #27                 // Method com/google/common/collect/ImmutableMap$Builder.put:(Ljava/lang/Object;Ljava/lang/Object;)Lcom/google/common/collect/ImmutableMap$Builder;
      28: ldc           #29                 // String appPrefix
      30: aload_1
      31: aload_0
      32: getfield      #23                 // Field httpConfiguration:Lorg/graylog2/configuration/HttpConfiguration;
      35: invokevirtual #30                 // Method org/graylog2/configuration/HttpConfiguration.getHttpExternalUri:()Ljava/net/URI;
      38: invokestatic  #31                 // Method org/graylog2/rest/RestTools.buildExternalUri:(Ljavax/ws/rs/core/MultivaluedMap;Ljava/net/URI;)Ljava/net/URI;
      41: invokevirtual #27                 // Method com/google/common/collect/ImmutableMap$Builder.put:(Ljava/lang/Object;Ljava/lang/Object;)Lcom/google/common/collect/ImmutableMap$Builder;
      44: invokevirtual #32                 // Method com/google/common/collect/ImmutableMap$Builder.build:()Lcom/google/common/collect/ImmutableMap;
      47: astore_2
      48: aload_0
      49: getfield      #20                 // Field templateEngine:Lcom/floreysoft/jmte/Engine;
      52: aload_0
      53: getfield      #12                 // Field template:Ljava/lang/String;
      56: aload_2
      57: invokevirtual #33                 // Method com/floreysoft/jmte/Engine.transform:(Ljava/lang/String;Ljava/util/Map;)Ljava/lang/String;
      60: areturn
}
