Compiled from "MapSerializer.java"
public class com.fasterxml.jackson.databind.ser.std.MapSerializer extends com.fasterxml.jackson.databind.ser.ContainerSerializer<java.util.Map<?, ?>> implements com.fasterxml.jackson.databind.ser.ContextualSerializer {
  private static final long serialVersionUID;

  protected static final com.fasterxml.jackson.databind.JavaType UNSPECIFIED_TYPE;

  public static final java.lang.Object MARKER_FOR_EMPTY;

  protected final com.fasterxml.jackson.databind.BeanProperty _property;

  protected final boolean _valueTypeIsStatic;

  protected final com.fasterxml.jackson.databind.JavaType _keyType;

  protected final com.fasterxml.jackson.databind.JavaType _valueType;

  protected com.fasterxml.jackson.databind.JsonSerializer<java.lang.Object> _keySerializer;

  protected com.fasterxml.jackson.databind.JsonSerializer<java.lang.Object> _valueSerializer;

  protected final com.fasterxml.jackson.databind.jsontype.TypeSerializer _valueTypeSerializer;

  protected com.fasterxml.jackson.databind.ser.impl.PropertySerializerMap _dynamicValueSerializers;

  protected final java.util.Set<java.lang.String> _ignoredEntries;

  protected final java.util.Set<java.lang.String> _includedEntries;

  protected final java.lang.Object _filterId;

  protected final java.lang.Object _suppressableValue;

  protected final boolean _suppressNulls;

  protected final com.fasterxml.jackson.databind.util.IgnorePropertiesUtil$Checker _inclusionChecker;

  protected final boolean _sortKeys;

  protected com.fasterxml.jackson.databind.ser.std.MapSerializer(java.util.Set<java.lang.String>, java.util.Set<java.lang.String>, com.fasterxml.jackson.databind.JavaType, com.fasterxml.jackson.databind.JavaType, boolean, com.fasterxml.jackson.databind.jsontype.TypeSerializer, com.fasterxml.jackson.databind.JsonSerializer<?>, com.fasterxml.jackson.databind.JsonSerializer<?>);
    Code:
       0: aload_0
       1: ldc           #1                  // class java/util/Map
       3: iconst_0
       4: invokespecial #2                  // Method com/fasterxml/jackson/databind/ser/ContainerSerializer."<init>":(Ljava/lang/Class;Z)V
       7: aload_0
       8: aload_1
       9: ifnull        21
      12: aload_1
      13: invokeinterface #3,  1            // InterfaceMethod java/util/Set.isEmpty:()Z
      18: ifeq          25
      21: aconst_null
      22: goto          26
      25: aload_1
      26: putfield      #4                  // Field _ignoredEntries:Ljava/util/Set;
      29: aload_0
      30: aload_2
      31: putfield      #5                  // Field _includedEntries:Ljava/util/Set;
      34: aload_0
      35: aload_3
      36: putfield      #6                  // Field _keyType:Lcom/fasterxml/jackson/databind/JavaType;
      39: aload_0
      40: aload         4
      42: putfield      #7                  // Field _valueType:Lcom/fasterxml/jackson/databind/JavaType;
      45: aload_0
      46: iload         5
      48: putfield      #8                  // Field _valueTypeIsStatic:Z
      51: aload_0
      52: aload         6
      54: putfield      #9                  // Field _valueTypeSerializer:Lcom/fasterxml/jackson/databind/jsontype/TypeSerializer;
      57: aload_0
      58: aload         7
      60: putfield      #10                 // Field _keySerializer:Lcom/fasterxml/jackson/databind/JsonSerializer;
      63: aload_0
      64: aload         8
      66: putfield      #11                 // Field _valueSerializer:Lcom/fasterxml/jackson/databind/JsonSerializer;
      69: aload_0
      70: invokestatic  #12                 // Method com/fasterxml/jackson/databind/ser/impl/PropertySerializerMap.emptyForProperties:()Lcom/fasterxml/jackson/databind/ser/impl/PropertySerializerMap;
      73: putfield      #13                 // Field _dynamicValueSerializers:Lcom/fasterxml/jackson/databind/ser/impl/PropertySerializerMap;
      76: aload_0
      77: aconst_null
      78: putfield      #14                 // Field _property:Lcom/fasterxml/jackson/databind/BeanProperty;
      81: aload_0
      82: aconst_null
      83: putfield      #15                 // Field _filterId:Ljava/lang/Object;
      86: aload_0
      87: iconst_0
      88: putfield      #16                 // Field _sortKeys:Z
      91: aload_0
      92: aconst_null
      93: putfield      #17                 // Field _suppressableValue:Ljava/lang/Object;
      96: aload_0
      97: iconst_0
      98: putfield      #18                 // Field _suppressNulls:Z
     101: aload_0
     102: aload_0
     103: getfield      #4                  // Field _ignoredEntries:Ljava/util/Set;
     106: aload_0
     107: getfield      #5                  // Field _includedEntries:Ljava/util/Set;
     110: invokestatic  #19                 // Method com/fasterxml/jackson/databind/util/IgnorePropertiesUtil.buildCheckerIfNeeded:(Ljava/util/Set;Ljava/util/Set;)Lcom/fasterxml/jackson/databind/util/IgnorePropertiesUtil$Checker;
     113: putfield      #20                 // Field _inclusionChecker:Lcom/fasterxml/jackson/databind/util/IgnorePropertiesUtil$Checker;
     116: return

  protected com.fasterxml.jackson.databind.ser.std.MapSerializer(java.util.Set<java.lang.String>, com.fasterxml.jackson.databind.JavaType, com.fasterxml.jackson.databind.JavaType, boolean, com.fasterxml.jackson.databind.jsontype.TypeSerializer, com.fasterxml.jackson.databind.JsonSerializer<?>, com.fasterxml.jackson.databind.JsonSerializer<?>);
    Code:
       0: aload_0
       1: aload_1
       2: aconst_null
       3: aload_2
       4: aload_3
       5: iload         4
       7: aload         5
       9: aload         6
      11: aload         7
      13: invokespecial #21                 // Method "<init>":(Ljava/util/Set;Ljava/util/Set;Lcom/fasterxml/jackson/databind/JavaType;Lcom/fasterxml/jackson/databind/JavaType;ZLcom/fasterxml/jackson/databind/jsontype/TypeSerializer;Lcom/fasterxml/jackson/databind/JsonSerializer;Lcom/fasterxml/jackson/databind/JsonSerializer;)V
      16: return

  protected com.fasterxml.jackson.databind.ser.std.MapSerializer(com.fasterxml.jackson.databind.ser.std.MapSerializer, com.fasterxml.jackson.databind.BeanProperty, com.fasterxml.jackson.databind.JsonSerializer<?>, com.fasterxml.jackson.databind.JsonSerializer<?>, java.util.Set<java.lang.String>, java.util.Set<java.lang.String>);
    Code:
       0: aload_0
       1: ldc           #1                  // class java/util/Map
       3: iconst_0
       4: invokespecial #2                  // Method com/fasterxml/jackson/databind/ser/ContainerSerializer."<init>":(Ljava/lang/Class;Z)V
       7: aload_0
       8: aload         5
      10: ifnull        23
      13: aload         5
      15: invokeinterface #3,  1            // InterfaceMethod java/util/Set.isEmpty:()Z
      20: ifeq          27
      23: aconst_null
      24: goto          29
      27: aload         5
      29: putfield      #4                  // Field _ignoredEntries:Ljava/util/Set;
      32: aload_0
      33: aload         6
      35: putfield      #5                  // Field _includedEntries:Ljava/util/Set;
      38: aload_0
      39: aload_1
      40: getfield      #6                  // Field _keyType:Lcom/fasterxml/jackson/databind/JavaType;
      43: putfield      #6                  // Field _keyType:Lcom/fasterxml/jackson/databind/JavaType;
      46: aload_0
      47: aload_1
      48: getfield      #7                  // Field _valueType:Lcom/fasterxml/jackson/databind/JavaType;
      51: putfield      #7                  // Field _valueType:Lcom/fasterxml/jackson/databind/JavaType;
      54: aload_0
      55: aload_1
      56: getfield      #8                  // Field _valueTypeIsStatic:Z
      59: putfield      #8                  // Field _valueTypeIsStatic:Z
      62: aload_0
      63: aload_1
      64: getfield      #9                  // Field _valueTypeSerializer:Lcom/fasterxml/jackson/databind/jsontype/TypeSerializer;
      67: putfield      #9                  // Field _valueTypeSerializer:Lcom/fasterxml/jackson/databind/jsontype/TypeSerializer;
      70: aload_0
      71: aload_3
      72: putfield      #10                 // Field _keySerializer:Lcom/fasterxml/jackson/databind/JsonSerializer;
      75: aload_0
      76: aload         4
      78: putfield      #11                 // Field _valueSerializer:Lcom/fasterxml/jackson/databind/JsonSerializer;
      81: aload_0
      82: invokestatic  #12                 // Method com/fasterxml/jackson/databind/ser/impl/PropertySerializerMap.emptyForProperties:()Lcom/fasterxml/jackson/databind/ser/impl/PropertySerializerMap;
      85: putfield      #13                 // Field _dynamicValueSerializers:Lcom/fasterxml/jackson/databind/ser/impl/PropertySerializerMap;
      88: aload_0
      89: aload_2
      90: putfield      #14                 // Field _property:Lcom/fasterxml/jackson/databind/BeanProperty;
      93: aload_0
      94: aload_1
      95: getfield      #15                 // Field _filterId:Ljava/lang/Object;
      98: putfield      #15                 // Field _filterId:Ljava/lang/Object;
     101: aload_0
     102: aload_1
     103: getfield      #16                 // Field _sortKeys:Z
     106: putfield      #16                 // Field _sortKeys:Z
     109: aload_0
     110: aload_1
     111: getfield      #17                 // Field _suppressableValue:Ljava/lang/Object;
     114: putfield      #17                 // Field _suppressableValue:Ljava/lang/Object;
     117: aload_0
     118: aload_1
     119: getfield      #18                 // Field _suppressNulls:Z
     122: putfield      #18                 // Field _suppressNulls:Z
     125: aload_0
     126: aload_0
     127: getfield      #4                  // Field _ignoredEntries:Ljava/util/Set;
     130: aload_0
     131: getfield      #5                  // Field _includedEntries:Ljava/util/Set;
     134: invokestatic  #19                 // Method com/fasterxml/jackson/databind/util/IgnorePropertiesUtil.buildCheckerIfNeeded:(Ljava/util/Set;Ljava/util/Set;)Lcom/fasterxml/jackson/databind/util/IgnorePropertiesUtil$Checker;
     137: putfield      #20                 // Field _inclusionChecker:Lcom/fasterxml/jackson/databind/util/IgnorePropertiesUtil$Checker;
     140: return

  protected com.fasterxml.jackson.databind.ser.std.MapSerializer(com.fasterxml.jackson.databind.ser.std.MapSerializer, com.fasterxml.jackson.databind.BeanProperty, com.fasterxml.jackson.databind.JsonSerializer<?>, com.fasterxml.jackson.databind.JsonSerializer<?>, java.util.Set<java.lang.String>);
    Code:
       0: aload_0
       1: aload_1
       2: aload_2
       3: aload_3
       4: aload         4
       6: aload         5
       8: aconst_null
       9: invokespecial #22                 // Method "<init>":(Lcom/fasterxml/jackson/databind/ser/std/MapSerializer;Lcom/fasterxml/jackson/databind/BeanProperty;Lcom/fasterxml/jackson/databind/JsonSerializer;Lcom/fasterxml/jackson/databind/JsonSerializer;Ljava/util/Set;Ljava/util/Set;)V
      12: return

  protected com.fasterxml.jackson.databind.ser.std.MapSerializer(com.fasterxml.jackson.databind.ser.std.MapSerializer, com.fasterxml.jackson.databind.jsontype.TypeSerializer, java.lang.Object, boolean);
    Code:
       0: aload_0
       1: ldc           #1                  // class java/util/Map
       3: iconst_0
       4: invokespecial #2                  // Method com/fasterxml/jackson/databind/ser/ContainerSerializer."<init>":(Ljava/lang/Class;Z)V
       7: aload_0
       8: aload_1
       9: getfield      #4                  // Field _ignoredEntries:Ljava/util/Set;
      12: putfield      #4                  // Field _ignoredEntries:Ljava/util/Set;
      15: aload_0
      16: aload_1
      17: getfield      #5                  // Field _includedEntries:Ljava/util/Set;
      20: putfield      #5                  // Field _includedEntries:Ljava/util/Set;
      23: aload_0
      24: aload_1
      25: getfield      #6                  // Field _keyType:Lcom/fasterxml/jackson/databind/JavaType;
      28: putfield      #6                  // Field _keyType:Lcom/fasterxml/jackson/databind/JavaType;
      31: aload_0
      32: aload_1
      33: getfield      #7                  // Field _valueType:Lcom/fasterxml/jackson/databind/JavaType;
      36: putfield      #7                  // Field _valueType:Lcom/fasterxml/jackson/databind/JavaType;
      39: aload_0
      40: aload_1
      41: getfield      #8                  // Field _valueTypeIsStatic:Z
      44: putfield      #8                  // Field _valueTypeIsStatic:Z
      47: aload_0
      48: aload_2
      49: putfield      #9                  // Field _valueTypeSerializer:Lcom/fasterxml/jackson/databind/jsontype/TypeSerializer;
      52: aload_0
      53: aload_1
      54: getfield      #10                 // Field _keySerializer:Lcom/fasterxml/jackson/databind/JsonSerializer;
      57: putfield      #10                 // Field _keySerializer:Lcom/fasterxml/jackson/databind/JsonSerializer;
      60: aload_0
      61: aload_1
      62: getfield      #11                 // Field _valueSerializer:Lcom/fasterxml/jackson/databind/JsonSerializer;
      65: putfield      #11                 // Field _valueSerializer:Lcom/fasterxml/jackson/databind/JsonSerializer;
      68: aload_0
      69: aload_1
      70: getfield      #13                 // Field _dynamicValueSerializers:Lcom/fasterxml/jackson/databind/ser/impl/PropertySerializerMap;
      73: putfield      #13                 // Field _dynamicValueSerializers:Lcom/fasterxml/jackson/databind/ser/impl/PropertySerializerMap;
      76: aload_0
      77: aload_1
      78: getfield      #14                 // Field _property:Lcom/fasterxml/jackson/databind/BeanProperty;
      81: putfield      #14                 // Field _property:Lcom/fasterxml/jackson/databind/BeanProperty;
      84: aload_0
      85: aload_1
      86: getfield      #15                 // Field _filterId:Ljava/lang/Object;
      89: putfield      #15                 // Field _filterId:Ljava/lang/Object;
      92: aload_0
      93: aload_1
      94: getfield      #16                 // Field _sortKeys:Z
      97: putfield      #16                 // Field _sortKeys:Z
     100: aload_0
     101: aload_3
     102: putfield      #17                 // Field _suppressableValue:Ljava/lang/Object;
     105: aload_0
     106: iload         4
     108: putfield      #18                 // Field _suppressNulls:Z
     111: aload_0
     112: aload_1
     113: getfield      #20                 // Field _inclusionChecker:Lcom/fasterxml/jackson/databind/util/IgnorePropertiesUtil$Checker;
     116: putfield      #20                 // Field _inclusionChecker:Lcom/fasterxml/jackson/databind/util/IgnorePropertiesUtil$Checker;
     119: return

  protected com.fasterxml.jackson.databind.ser.std.MapSerializer(com.fasterxml.jackson.databind.ser.std.MapSerializer, java.lang.Object, boolean);
    Code:
       0: aload_0
       1: ldc           #1                  // class java/util/Map
       3: iconst_0
       4: invokespecial #2                  // Method com/fasterxml/jackson/databind/ser/ContainerSerializer."<init>":(Ljava/lang/Class;Z)V
       7: aload_0
       8: aload_1
       9: getfield      #4                  // Field _ignoredEntries:Ljava/util/Set;
      12: putfield      #4                  // Field _ignoredEntries:Ljava/util/Set;
      15: aload_0
      16: aload_1
      17: getfield      #5                  // Field _includedEntries:Ljava/util/Set;
      20: putfield      #5                  // Field _includedEntries:Ljava/util/Set;
      23: aload_0
      24: aload_1
      25: getfield      #6                  // Field _keyType:Lcom/fasterxml/jackson/databind/JavaType;
      28: putfield      #6                  // Field _keyType:Lcom/fasterxml/jackson/databind/JavaType;
      31: aload_0
      32: aload_1
      33: getfield      #7                  // Field _valueType:Lcom/fasterxml/jackson/databind/JavaType;
      36: putfield      #7                  // Field _valueType:Lcom/fasterxml/jackson/databind/JavaType;
      39: aload_0
      40: aload_1
      41: getfield      #8                  // Field _valueTypeIsStatic:Z
      44: putfield      #8                  // Field _valueTypeIsStatic:Z
      47: aload_0
      48: aload_1
      49: getfield      #9                  // Field _valueTypeSerializer:Lcom/fasterxml/jackson/databind/jsontype/TypeSerializer;
      52: putfield      #9                  // Field _valueTypeSerializer:Lcom/fasterxml/jackson/databind/jsontype/TypeSerializer;
      55: aload_0
      56: aload_1
      57: getfield      #10                 // Field _keySerializer:Lcom/fasterxml/jackson/databind/JsonSerializer;
      60: putfield      #10                 // Field _keySerializer:Lcom/fasterxml/jackson/databind/JsonSerializer;
      63: aload_0
      64: aload_1
      65: getfield      #11                 // Field _valueSerializer:Lcom/fasterxml/jackson/databind/JsonSerializer;
      68: putfield      #11                 // Field _valueSerializer:Lcom/fasterxml/jackson/databind/JsonSerializer;
      71: aload_0
      72: invokestatic  #12                 // Method com/fasterxml/jackson/databind/ser/impl/PropertySerializerMap.emptyForProperties:()Lcom/fasterxml/jackson/databind/ser/impl/PropertySerializerMap;
      75: putfield      #13                 // Field _dynamicValueSerializers:Lcom/fasterxml/jackson/databind/ser/impl/PropertySerializerMap;
      78: aload_0
      79: aload_1
      80: getfield      #14                 // Field _property:Lcom/fasterxml/jackson/databind/BeanProperty;
      83: putfield      #14                 // Field _property:Lcom/fasterxml/jackson/databind/BeanProperty;
      86: aload_0
      87: aload_2
      88: putfield      #15                 // Field _filterId:Ljava/lang/Object;
      91: aload_0
      92: iload_3
      93: putfield      #16                 // Field _sortKeys:Z
      96: aload_0
      97: aload_1
      98: getfield      #17                 // Field _suppressableValue:Ljava/lang/Object;
     101: putfield      #17                 // Field _suppressableValue:Ljava/lang/Object;
     104: aload_0
     105: aload_1
     106: getfield      #18                 // Field _suppressNulls:Z
     109: putfield      #18                 // Field _suppressNulls:Z
     112: aload_0
     113: aload_1
     114: getfield      #20                 // Field _inclusionChecker:Lcom/fasterxml/jackson/databind/util/IgnorePropertiesUtil$Checker;
     117: putfield      #20                 // Field _inclusionChecker:Lcom/fasterxml/jackson/databind/util/IgnorePropertiesUtil$Checker;
     120: return

  public com.fasterxml.jackson.databind.ser.std.MapSerializer _withValueTypeSerializer(com.fasterxml.jackson.databind.jsontype.TypeSerializer);
    Code:
       0: aload_0
       1: getfield      #9                  // Field _valueTypeSerializer:Lcom/fasterxml/jackson/databind/jsontype/TypeSerializer;
       4: aload_1
       5: if_acmpne     10
       8: aload_0
       9: areturn
      10: aload_0
      11: ldc           #23                 // String _withValueTypeSerializer
      13: invokevirtual #24                 // Method _ensureOverride:(Ljava/lang/String;)V
      16: new           #25                 // class com/fasterxml/jackson/databind/ser/std/MapSerializer
      19: dup
      20: aload_0
      21: aload_1
      22: aload_0
      23: getfield      #17                 // Field _suppressableValue:Ljava/lang/Object;
      26: aload_0
      27: getfield      #18                 // Field _suppressNulls:Z
      30: invokespecial #26                 // Method "<init>":(Lcom/fasterxml/jackson/databind/ser/std/MapSerializer;Lcom/fasterxml/jackson/databind/jsontype/TypeSerializer;Ljava/lang/Object;Z)V
      33: areturn

  public com.fasterxml.jackson.databind.ser.std.MapSerializer withResolved(com.fasterxml.jackson.databind.BeanProperty, com.fasterxml.jackson.databind.JsonSerializer<?>, com.fasterxml.jackson.databind.JsonSerializer<?>, java.util.Set<java.lang.String>, java.util.Set<java.lang.String>, boolean);
    Code:
       0: aload_0
       1: ldc           #27                 // String withResolved
       3: invokevirtual #24                 // Method _ensureOverride:(Ljava/lang/String;)V
       6: new           #25                 // class com/fasterxml/jackson/databind/ser/std/MapSerializer
       9: dup
      10: aload_0
      11: aload_1
      12: aload_2
      13: aload_3
      14: aload         4
      16: aload         5
      18: invokespecial #22                 // Method "<init>":(Lcom/fasterxml/jackson/databind/ser/std/MapSerializer;Lcom/fasterxml/jackson/databind/BeanProperty;Lcom/fasterxml/jackson/databind/JsonSerializer;Lcom/fasterxml/jackson/databind/JsonSerializer;Ljava/util/Set;Ljava/util/Set;)V
      21: astore        7
      23: iload         6
      25: aload         7
      27: getfield      #16                 // Field _sortKeys:Z
      30: if_icmpeq     50
      33: new           #25                 // class com/fasterxml/jackson/databind/ser/std/MapSerializer
      36: dup
      37: aload         7
      39: aload_0
      40: getfield      #15                 // Field _filterId:Ljava/lang/Object;
      43: iload         6
      45: invokespecial #28                 // Method "<init>":(Lcom/fasterxml/jackson/databind/ser/std/MapSerializer;Ljava/lang/Object;Z)V
      48: astore        7
      50: aload         7
      52: areturn

  public com.fasterxml.jackson.databind.ser.std.MapSerializer withResolved(com.fasterxml.jackson.databind.BeanProperty, com.fasterxml.jackson.databind.JsonSerializer<?>, com.fasterxml.jackson.databind.JsonSerializer<?>, java.util.Set<java.lang.String>, boolean);
    Code:
       0: aload_0
       1: aload_1
       2: aload_2
       3: aload_3
       4: aload         4
       6: aconst_null
       7: iload         5
       9: invokevirtual #29                 // Method withResolved:(Lcom/fasterxml/jackson/databind/BeanProperty;Lcom/fasterxml/jackson/databind/JsonSerializer;Lcom/fasterxml/jackson/databind/JsonSerializer;Ljava/util/Set;Ljava/util/Set;Z)Lcom/fasterxml/jackson/databind/ser/std/MapSerializer;
      12: areturn

  public com.fasterxml.jackson.databind.ser.std.MapSerializer withFilterId(java.lang.Object);
    Code:
       0: aload_0
       1: getfield      #15                 // Field _filterId:Ljava/lang/Object;
       4: aload_1
       5: if_acmpne     10
       8: aload_0
       9: areturn
      10: aload_0
      11: ldc           #30                 // String withFilterId
      13: invokevirtual #24                 // Method _ensureOverride:(Ljava/lang/String;)V
      16: new           #25                 // class com/fasterxml/jackson/databind/ser/std/MapSerializer
      19: dup
      20: aload_0
      21: aload_1
      22: aload_0
      23: getfield      #16                 // Field _sortKeys:Z
      26: invokespecial #28                 // Method "<init>":(Lcom/fasterxml/jackson/databind/ser/std/MapSerializer;Ljava/lang/Object;Z)V
      29: areturn

  public com.fasterxml.jackson.databind.ser.std.MapSerializer withContentInclusion(java.lang.Object, boolean);
    Code:
       0: aload_1
       1: aload_0
       2: getfield      #17                 // Field _suppressableValue:Ljava/lang/Object;
       5: if_acmpne     18
       8: iload_2
       9: aload_0
      10: getfield      #18                 // Field _suppressNulls:Z
      13: if_icmpne     18
      16: aload_0
      17: areturn
      18: aload_0
      19: ldc           #31                 // String withContentInclusion
      21: invokevirtual #24                 // Method _ensureOverride:(Ljava/lang/String;)V
      24: new           #25                 // class com/fasterxml/jackson/databind/ser/std/MapSerializer
      27: dup
      28: aload_0
      29: aload_0
      30: getfield      #9                  // Field _valueTypeSerializer:Lcom/fasterxml/jackson/databind/jsontype/TypeSerializer;
      33: aload_1
      34: iload_2
      35: invokespecial #26                 // Method "<init>":(Lcom/fasterxml/jackson/databind/ser/std/MapSerializer;Lcom/fasterxml/jackson/databind/jsontype/TypeSerializer;Ljava/lang/Object;Z)V
      38: areturn

  public static com.fasterxml.jackson.databind.ser.std.MapSerializer construct(java.util.Set<java.lang.String>, java.util.Set<java.lang.String>, com.fasterxml.jackson.databind.JavaType, boolean, com.fasterxml.jackson.databind.jsontype.TypeSerializer, com.fasterxml.jackson.databind.JsonSerializer<java.lang.Object>, com.fasterxml.jackson.databind.JsonSerializer<java.lang.Object>, java.lang.Object);
    Code:
       0: aload_2
       1: ifnonnull     15
       4: getstatic     #32                 // Field UNSPECIFIED_TYPE:Lcom/fasterxml/jackson/databind/JavaType;
       7: dup
       8: astore        9
      10: astore        8
      12: goto          44
      15: aload_2
      16: invokevirtual #33                 // Method com/fasterxml/jackson/databind/JavaType.getKeyType:()Lcom/fasterxml/jackson/databind/JavaType;
      19: astore        8
      21: aload_2
      22: ldc           #34                 // class java/util/Properties
      24: invokevirtual #35                 // Method com/fasterxml/jackson/databind/JavaType.hasRawClass:(Ljava/lang/Class;)Z
      27: ifeq          38
      30: invokestatic  #36                 // Method com/fasterxml/jackson/databind/type/TypeFactory.unknownType:()Lcom/fasterxml/jackson/databind/JavaType;
      33: astore        9
      35: goto          44
      38: aload_2
      39: invokevirtual #37                 // Method com/fasterxml/jackson/databind/JavaType.getContentType:()Lcom/fasterxml/jackson/databind/JavaType;
      42: astore        9
      44: iload_3
      45: ifne          70
      48: aload         9
      50: ifnull        65
      53: aload         9
      55: invokevirtual #38                 // Method com/fasterxml/jackson/databind/JavaType.isFinal:()Z
      58: ifeq          65
      61: iconst_1
      62: goto          66
      65: iconst_0
      66: istore_3
      67: goto          82
      70: aload         9
      72: invokevirtual #39                 // Method com/fasterxml/jackson/databind/JavaType.getRawClass:()Ljava/lang/Class;
      75: ldc           #40                 // class java/lang/Object
      77: if_acmpne     82
      80: iconst_0
      81: istore_3
      82: new           #25                 // class com/fasterxml/jackson/databind/ser/std/MapSerializer
      85: dup
      86: aload_0
      87: aload_1
      88: aload         8
      90: aload         9
      92: iload_3
      93: aload         4
      95: aload         5
      97: aload         6
      99: invokespecial #21                 // Method "<init>":(Ljava/util/Set;Ljava/util/Set;Lcom/fasterxml/jackson/databind/JavaType;Lcom/fasterxml/jackson/databind/JavaType;ZLcom/fasterxml/jackson/databind/jsontype/TypeSerializer;Lcom/fasterxml/jackson/databind/JsonSerializer;Lcom/fasterxml/jackson/databind/JsonSerializer;)V
     102: astore        10
     104: aload         7
     106: ifnull        118
     109: aload         10
     111: aload         7
     113: invokevirtual #41                 // Method withFilterId:(Ljava/lang/Object;)Lcom/fasterxml/jackson/databind/ser/std/MapSerializer;
     116: astore        10
     118: aload         10
     120: areturn

  public static com.fasterxml.jackson.databind.ser.std.MapSerializer construct(java.util.Set<java.lang.String>, com.fasterxml.jackson.databind.JavaType, boolean, com.fasterxml.jackson.databind.jsontype.TypeSerializer, com.fasterxml.jackson.databind.JsonSerializer<java.lang.Object>, com.fasterxml.jackson.databind.JsonSerializer<java.lang.Object>, java.lang.Object);
    Code:
       0: aload_0
       1: aconst_null
       2: aload_1
       3: iload_2
       4: aload_3
       5: aload         4
       7: aload         5
       9: aload         6
      11: invokestatic  #42                 // Method construct:(Ljava/util/Set;Ljava/util/Set;Lcom/fasterxml/jackson/databind/JavaType;ZLcom/fasterxml/jackson/databind/jsontype/TypeSerializer;Lcom/fasterxml/jackson/databind/JsonSerializer;Lcom/fasterxml/jackson/databind/JsonSerializer;Ljava/lang/Object;)Lcom/fasterxml/jackson/databind/ser/std/MapSerializer;
      14: areturn

  protected void _ensureOverride(java.lang.String);
    Code:
       0: ldc           #25                 // class com/fasterxml/jackson/databind/ser/std/MapSerializer
       2: aload_0
       3: aload_1
       4: invokestatic  #43                 // Method com/fasterxml/jackson/databind/util/ClassUtil.verifyMustOverride:(Ljava/lang/Class;Ljava/lang/Object;Ljava/lang/String;)V
       7: return

  protected void _ensureOverride();
    Code:
       0: aload_0
       1: ldc           #44                 // String N/A
       3: invokevirtual #24                 // Method _ensureOverride:(Ljava/lang/String;)V
       6: return

  protected com.fasterxml.jackson.databind.ser.std.MapSerializer(com.fasterxml.jackson.databind.ser.std.MapSerializer, com.fasterxml.jackson.databind.jsontype.TypeSerializer, java.lang.Object);
    Code:
       0: aload_0
       1: aload_1
       2: aload_2
       3: aload_3
       4: iconst_0
       5: invokespecial #26                 // Method "<init>":(Lcom/fasterxml/jackson/databind/ser/std/MapSerializer;Lcom/fasterxml/jackson/databind/jsontype/TypeSerializer;Ljava/lang/Object;Z)V
       8: return

  public com.fasterxml.jackson.databind.ser.std.MapSerializer withContentInclusion(java.lang.Object);
    Code:
       0: new           #25                 // class com/fasterxml/jackson/databind/ser/std/MapSerializer
       3: dup
       4: aload_0
       5: aload_0
       6: getfield      #9                  // Field _valueTypeSerializer:Lcom/fasterxml/jackson/databind/jsontype/TypeSerializer;
       9: aload_1
      10: aload_0
      11: getfield      #18                 // Field _suppressNulls:Z
      14: invokespecial #26                 // Method "<init>":(Lcom/fasterxml/jackson/databind/ser/std/MapSerializer;Lcom/fasterxml/jackson/databind/jsontype/TypeSerializer;Ljava/lang/Object;Z)V
      17: areturn

  public static com.fasterxml.jackson.databind.ser.std.MapSerializer construct(java.lang.String[], com.fasterxml.jackson.databind.JavaType, boolean, com.fasterxml.jackson.databind.jsontype.TypeSerializer, com.fasterxml.jackson.databind.JsonSerializer<java.lang.Object>, com.fasterxml.jackson.databind.JsonSerializer<java.lang.Object>, java.lang.Object);
    Code:
       0: aload_0
       1: invokestatic  #45                 // Method com/fasterxml/jackson/databind/util/ArrayBuilders.arrayToSet:([Ljava/lang/Object;)Ljava/util/HashSet;
       4: astore        7
       6: aload         7
       8: aload_1
       9: iload_2
      10: aload_3
      11: aload         4
      13: aload         5
      15: aload         6
      17: invokestatic  #46                 // Method construct:(Ljava/util/Set;Lcom/fasterxml/jackson/databind/JavaType;ZLcom/fasterxml/jackson/databind/jsontype/TypeSerializer;Lcom/fasterxml/jackson/databind/JsonSerializer;Lcom/fasterxml/jackson/databind/JsonSerializer;Ljava/lang/Object;)Lcom/fasterxml/jackson/databind/ser/std/MapSerializer;
      20: areturn

  public com.fasterxml.jackson.databind.JsonSerializer<?> createContextual(com.fasterxml.jackson.databind.SerializerProvider, com.fasterxml.jackson.databind.BeanProperty) throws com.fasterxml.jackson.databind.JsonMappingException;
    Code:
       0: aconst_null
       1: astore_3
       2: aconst_null
       3: astore        4
       5: aload_1
       6: invokevirtual #47                 // Method com/fasterxml/jackson/databind/SerializerProvider.getAnnotationIntrospector:()Lcom/fasterxml/jackson/databind/AnnotationIntrospector;
       9: astore        5
      11: aload_2
      12: ifnonnull     19
      15: aconst_null
      16: goto          25
      19: aload_2
      20: invokeinterface #48,  1           // InterfaceMethod com/fasterxml/jackson/databind/BeanProperty.getMember:()Lcom/fasterxml/jackson/databind/introspect/AnnotatedMember;
      25: astore        6
      27: aload         6
      29: aload         5
      31: invokestatic  #49                 // Method _neitherNull:(Ljava/lang/Object;Ljava/lang/Object;)Z
      34: ifeq          84
      37: aload         5
      39: aload         6
      41: invokevirtual #50                 // Method com/fasterxml/jackson/databind/AnnotationIntrospector.findKeySerializer:(Lcom/fasterxml/jackson/databind/introspect/Annotated;)Ljava/lang/Object;
      44: astore        7
      46: aload         7
      48: ifnull        61
      51: aload_1
      52: aload         6
      54: aload         7
      56: invokevirtual #51                 // Method com/fasterxml/jackson/databind/SerializerProvider.serializerInstance:(Lcom/fasterxml/jackson/databind/introspect/Annotated;Ljava/lang/Object;)Lcom/fasterxml/jackson/databind/JsonSerializer;
      59: astore        4
      61: aload         5
      63: aload         6
      65: invokevirtual #52                 // Method com/fasterxml/jackson/databind/AnnotationIntrospector.findContentSerializer:(Lcom/fasterxml/jackson/databind/introspect/Annotated;)Ljava/lang/Object;
      68: astore        7
      70: aload         7
      72: ifnull        84
      75: aload_1
      76: aload         6
      78: aload         7
      80: invokevirtual #51                 // Method com/fasterxml/jackson/databind/SerializerProvider.serializerInstance:(Lcom/fasterxml/jackson/databind/introspect/Annotated;Ljava/lang/Object;)Lcom/fasterxml/jackson/databind/JsonSerializer;
      83: astore_3
      84: aload_3
      85: ifnonnull     93
      88: aload_0
      89: getfield      #11                 // Field _valueSerializer:Lcom/fasterxml/jackson/databind/JsonSerializer;
      92: astore_3
      93: aload_0
      94: aload_1
      95: aload_2
      96: aload_3
      97: invokevirtual #53                 // Method findContextualConvertingSerializer:(Lcom/fasterxml/jackson/databind/SerializerProvider;Lcom/fasterxml/jackson/databind/BeanProperty;Lcom/fasterxml/jackson/databind/JsonSerializer;)Lcom/fasterxml/jackson/databind/JsonSerializer;
     100: astore_3
     101: aload_3
     102: ifnonnull     132
     105: aload_0
     106: getfield      #8                  // Field _valueTypeIsStatic:Z
     109: ifeq          132
     112: aload_0
     113: getfield      #7                  // Field _valueType:Lcom/fasterxml/jackson/databind/JavaType;
     116: invokevirtual #54                 // Method com/fasterxml/jackson/databind/JavaType.isJavaLangObject:()Z
     119: ifne          132
     122: aload_1
     123: aload_0
     124: getfield      #7                  // Field _valueType:Lcom/fasterxml/jackson/databind/JavaType;
     127: aload_2
     128: invokevirtual #55                 // Method com/fasterxml/jackson/databind/SerializerProvider.findContentValueSerializer:(Lcom/fasterxml/jackson/databind/JavaType;Lcom/fasterxml/jackson/databind/BeanProperty;)Lcom/fasterxml/jackson/databind/JsonSerializer;
     131: astore_3
     132: aload         4
     134: ifnonnull     143
     137: aload_0
     138: getfield      #10                 // Field _keySerializer:Lcom/fasterxml/jackson/databind/JsonSerializer;
     141: astore        4
     143: aload         4
     145: ifnonnull     162
     148: aload_1
     149: aload_0
     150: getfield      #6                  // Field _keyType:Lcom/fasterxml/jackson/databind/JavaType;
     153: aload_2
     154: invokevirtual #56                 // Method com/fasterxml/jackson/databind/SerializerProvider.findKeySerializer:(Lcom/fasterxml/jackson/databind/JavaType;Lcom/fasterxml/jackson/databind/BeanProperty;)Lcom/fasterxml/jackson/databind/JsonSerializer;
     157: astore        4
     159: goto          171
     162: aload_1
     163: aload         4
     165: aload_2
     166: invokevirtual #57                 // Method com/fasterxml/jackson/databind/SerializerProvider.handleSecondaryContextualization:(Lcom/fasterxml/jackson/databind/JsonSerializer;Lcom/fasterxml/jackson/databind/BeanProperty;)Lcom/fasterxml/jackson/databind/JsonSerializer;
     169: astore        4
     171: aload_0
     172: getfield      #4                  // Field _ignoredEntries:Ljava/util/Set;
     175: astore        7
     177: aload_0
     178: getfield      #5                  // Field _includedEntries:Ljava/util/Set;
     181: astore        8
     183: iconst_0
     184: istore        9
     186: aload         6
     188: aload         5
     190: invokestatic  #49                 // Method _neitherNull:(Ljava/lang/Object;Ljava/lang/Object;)Z
     193: ifeq          402
     196: aload_1
     197: invokevirtual #58                 // Method com/fasterxml/jackson/databind/SerializerProvider.getConfig:()Lcom/fasterxml/jackson/databind/SerializationConfig;
     200: astore        10
     202: aload         5
     204: aload         10
     206: aload         6
     208: invokevirtual #59                 // Method com/fasterxml/jackson/databind/AnnotationIntrospector.findPropertyIgnoralByName:(Lcom/fasterxml/jackson/databind/cfg/MapperConfig;Lcom/fasterxml/jackson/databind/introspect/Annotated;)Lcom/fasterxml/jackson/annotation/JsonIgnoreProperties$Value;
     211: invokevirtual #60                 // Method com/fasterxml/jackson/annotation/JsonIgnoreProperties$Value.findIgnoredForSerialization:()Ljava/util/Set;
     214: astore        11
     216: aload         11
     218: invokestatic  #61                 // Method _nonEmpty:(Ljava/util/Collection;)Z
     221: ifeq          294
     224: aload         7
     226: ifnonnull     239
     229: new           #62                 // class java/util/HashSet
     232: dup
     233: invokespecial #63                 // Method java/util/HashSet."<init>":()V
     236: goto          248
     239: new           #62                 // class java/util/HashSet
     242: dup
     243: aload         7
     245: invokespecial #64                 // Method java/util/HashSet."<init>":(Ljava/util/Collection;)V
     248: astore        7
     250: aload         11
     252: invokeinterface #65,  1           // InterfaceMethod java/util/Set.iterator:()Ljava/util/Iterator;
     257: astore        12
     259: aload         12
     261: invokeinterface #66,  1           // InterfaceMethod java/util/Iterator.hasNext:()Z
     266: ifeq          294
     269: aload         12
     271: invokeinterface #67,  1           // InterfaceMethod java/util/Iterator.next:()Ljava/lang/Object;
     276: checkcast     #68                 // class java/lang/String
     279: astore        13
     281: aload         7
     283: aload         13
     285: invokeinterface #69,  2           // InterfaceMethod java/util/Set.add:(Ljava/lang/Object;)Z
     290: pop
     291: goto          259
     294: aload         5
     296: aload         10
     298: aload         6
     300: invokevirtual #70                 // Method com/fasterxml/jackson/databind/AnnotationIntrospector.findPropertyInclusionByName:(Lcom/fasterxml/jackson/databind/cfg/MapperConfig;Lcom/fasterxml/jackson/databind/introspect/Annotated;)Lcom/fasterxml/jackson/annotation/JsonIncludeProperties$Value;
     303: invokevirtual #71                 // Method com/fasterxml/jackson/annotation/JsonIncludeProperties$Value.getIncluded:()Ljava/util/Set;
     306: astore        12
     308: aload         12
     310: ifnull        383
     313: aload         8
     315: ifnonnull     328
     318: new           #62                 // class java/util/HashSet
     321: dup
     322: invokespecial #63                 // Method java/util/HashSet."<init>":()V
     325: goto          337
     328: new           #62                 // class java/util/HashSet
     331: dup
     332: aload         8
     334: invokespecial #64                 // Method java/util/HashSet."<init>":(Ljava/util/Collection;)V
     337: astore        8
     339: aload         12
     341: invokeinterface #65,  1           // InterfaceMethod java/util/Set.iterator:()Ljava/util/Iterator;
     346: astore        13
     348: aload         13
     350: invokeinterface #66,  1           // InterfaceMethod java/util/Iterator.hasNext:()Z
     355: ifeq          383
     358: aload         13
     360: invokeinterface #67,  1           // InterfaceMethod java/util/Iterator.next:()Ljava/lang/Object;
     365: checkcast     #68                 // class java/lang/String
     368: astore        14
     370: aload         8
     372: aload         14
     374: invokeinterface #69,  2           // InterfaceMethod java/util/Set.add:(Ljava/lang/Object;)Z
     379: pop
     380: goto          348
     383: aload         5
     385: aload         6
     387: invokevirtual #72                 // Method com/fasterxml/jackson/databind/AnnotationIntrospector.findSerializationSortAlphabetically:(Lcom/fasterxml/jackson/databind/introspect/Annotated;)Ljava/lang/Boolean;
     390: astore        13
     392: getstatic     #73                 // Field java/lang/Boolean.TRUE:Ljava/lang/Boolean;
     395: aload         13
     397: invokevirtual #74                 // Method java/lang/Boolean.equals:(Ljava/lang/Object;)Z
     400: istore        9
     402: aload_0
     403: aload_1
     404: aload_2
     405: ldc           #1                  // class java/util/Map
     407: invokevirtual #75                 // Method findFormatOverrides:(Lcom/fasterxml/jackson/databind/SerializerProvider;Lcom/fasterxml/jackson/databind/BeanProperty;Ljava/lang/Class;)Lcom/fasterxml/jackson/annotation/JsonFormat$Value;
     410: astore        10
     412: aload         10
     414: ifnull        439
     417: aload         10
     419: getstatic     #76                 // Field com/fasterxml/jackson/annotation/JsonFormat$Feature.WRITE_SORTED_MAP_ENTRIES:Lcom/fasterxml/jackson/annotation/JsonFormat$Feature;
     422: invokevirtual #77                 // Method com/fasterxml/jackson/annotation/JsonFormat$Value.getFeature:(Lcom/fasterxml/jackson/annotation/JsonFormat$Feature;)Ljava/lang/Boolean;
     425: astore        11
     427: aload         11
     429: ifnull        439
     432: aload         11
     434: invokevirtual #78                 // Method java/lang/Boolean.booleanValue:()Z
     437: istore        9
     439: aload_0
     440: aload_2
     441: aload         4
     443: aload_3
     444: aload         7
     446: aload         8
     448: iload         9
     450: invokevirtual #29                 // Method withResolved:(Lcom/fasterxml/jackson/databind/BeanProperty;Lcom/fasterxml/jackson/databind/JsonSerializer;Lcom/fasterxml/jackson/databind/JsonSerializer;Ljava/util/Set;Ljava/util/Set;Z)Lcom/fasterxml/jackson/databind/ser/std/MapSerializer;
     453: astore        11
     455: aload         6
     457: ifnull        483
     460: aload         5
     462: aload         6
     464: invokevirtual #79                 // Method com/fasterxml/jackson/databind/AnnotationIntrospector.findFilterId:(Lcom/fasterxml/jackson/databind/introspect/Annotated;)Ljava/lang/Object;
     467: astore        12
     469: aload         12
     471: ifnull        483
     474: aload         11
     476: aload         12
     478: invokevirtual #41                 // Method withFilterId:(Ljava/lang/Object;)Lcom/fasterxml/jackson/databind/ser/std/MapSerializer;
     481: astore        11
     483: aload_0
     484: aload_1
     485: aload_2
     486: ldc           #1                  // class java/util/Map
     488: invokevirtual #80                 // Method findIncludeOverrides:(Lcom/fasterxml/jackson/databind/SerializerProvider;Lcom/fasterxml/jackson/databind/BeanProperty;Ljava/lang/Class;)Lcom/fasterxml/jackson/annotation/JsonInclude$Value;
     491: astore        12
     493: aload         12
     495: ifnull        694
     498: aload         12
     500: invokevirtual #81                 // Method com/fasterxml/jackson/annotation/JsonInclude$Value.getContentInclusion:()Lcom/fasterxml/jackson/annotation/JsonInclude$Include;
     503: astore        13
     505: aload         13
     507: getstatic     #82                 // Field com/fasterxml/jackson/annotation/JsonInclude$Include.USE_DEFAULTS:Lcom/fasterxml/jackson/annotation/JsonInclude$Include;
     510: if_acmpeq     694
     513: getstatic     #83                 // Field com/fasterxml/jackson/databind/ser/std/MapSerializer$1.$SwitchMap$com$fasterxml$jackson$annotation$JsonInclude$Include:[I
     516: aload         13
     518: invokevirtual #84                 // Method com/fasterxml/jackson/annotation/JsonInclude$Include.ordinal:()I
     521: iaload
     522: tableswitch   { // 1 to 6
                     1: 560
                     2: 598
                     3: 623
                     4: 634
                     5: 668
                     6: 677
               default: 677
          }
     560: aload_0
     561: getfield      #7                  // Field _valueType:Lcom/fasterxml/jackson/databind/JavaType;
     564: invokestatic  #85                 // Method com/fasterxml/jackson/databind/util/BeanUtil.getDefaultValue:(Lcom/fasterxml/jackson/databind/JavaType;)Ljava/lang/Object;
     567: astore        14
     569: iconst_1
     570: istore        15
     572: aload         14
     574: ifnull        683
     577: aload         14
     579: invokevirtual #86                 // Method java/lang/Object.getClass:()Ljava/lang/Class;
     582: invokevirtual #87                 // Method java/lang/Class.isArray:()Z
     585: ifeq          683
     588: aload         14
     590: invokestatic  #88                 // Method com/fasterxml/jackson/databind/util/ArrayBuilders.getArrayComparator:(Ljava/lang/Object;)Ljava/lang/Object;
     593: astore        14
     595: goto          683
     598: iconst_1
     599: istore        15
     601: aload_0
     602: getfield      #7                  // Field _valueType:Lcom/fasterxml/jackson/databind/JavaType;
     605: invokevirtual #89                 // Method com/fasterxml/jackson/databind/JavaType.isReferenceType:()Z
     608: ifeq          617
     611: getstatic     #90                 // Field MARKER_FOR_EMPTY:Ljava/lang/Object;
     614: goto          618
     617: aconst_null
     618: astore        14
     620: goto          683
     623: iconst_1
     624: istore        15
     626: getstatic     #90                 // Field MARKER_FOR_EMPTY:Ljava/lang/Object;
     629: astore        14
     631: goto          683
     634: aload_1
     635: aconst_null
     636: aload         12
     638: invokevirtual #91                 // Method com/fasterxml/jackson/annotation/JsonInclude$Value.getContentFilter:()Ljava/lang/Class;
     641: invokevirtual #92                 // Method com/fasterxml/jackson/databind/SerializerProvider.includeFilterInstance:(Lcom/fasterxml/jackson/databind/introspect/BeanPropertyDefinition;Ljava/lang/Class;)Ljava/lang/Object;
     644: astore        14
     646: aload         14
     648: ifnonnull     657
     651: iconst_1
     652: istore        15
     654: goto          683
     657: aload_1
     658: aload         14
     660: invokevirtual #93                 // Method com/fasterxml/jackson/databind/SerializerProvider.includeFilterSuppressNulls:(Ljava/lang/Object;)Z
     663: istore        15
     665: goto          683
     668: aconst_null
     669: astore        14
     671: iconst_1
     672: istore        15
     674: goto          683
     677: aconst_null
     678: astore        14
     680: iconst_0
     681: istore        15
     683: aload         11
     685: aload         14
     687: iload         15
     689: invokevirtual #94                 // Method withContentInclusion:(Ljava/lang/Object;Z)Lcom/fasterxml/jackson/databind/ser/std/MapSerializer;
     692: astore        11
     694: aload         11
     696: areturn

  public com.fasterxml.jackson.databind.JavaType getContentType();
    Code:
       0: aload_0
       1: getfield      #7                  // Field _valueType:Lcom/fasterxml/jackson/databind/JavaType;
       4: areturn

  public com.fasterxml.jackson.databind.JsonSerializer<?> getContentSerializer();
    Code:
       0: aload_0
       1: getfield      #11                 // Field _valueSerializer:Lcom/fasterxml/jackson/databind/JsonSerializer;
       4: areturn

  public boolean isEmpty(com.fasterxml.jackson.databind.SerializerProvider, java.util.Map<?, ?>);
    Code:
       0: aload_2
       1: invokeinterface #95,  1           // InterfaceMethod java/util/Map.isEmpty:()Z
       6: ifeq          11
       9: iconst_1
      10: ireturn
      11: aload_0
      12: getfield      #17                 // Field _suppressableValue:Ljava/lang/Object;
      15: astore_3
      16: aload_3
      17: ifnonnull     29
      20: aload_0
      21: getfield      #18                 // Field _suppressNulls:Z
      24: ifne          29
      27: iconst_0
      28: ireturn
      29: aload_0
      30: getfield      #11                 // Field _valueSerializer:Lcom/fasterxml/jackson/databind/JsonSerializer;
      33: astore        4
      35: getstatic     #90                 // Field MARKER_FOR_EMPTY:Ljava/lang/Object;
      38: aload_3
      39: if_acmpne     46
      42: iconst_1
      43: goto          47
      46: iconst_0
      47: istore        5
      49: aload         4
      51: ifnull        140
      54: aload_2
      55: invokeinterface #96,  1           // InterfaceMethod java/util/Map.values:()Ljava/util/Collection;
      60: invokeinterface #97,  1           // InterfaceMethod java/util/Collection.iterator:()Ljava/util/Iterator;
      65: astore        6
      67: aload         6
      69: invokeinterface #66,  1           // InterfaceMethod java/util/Iterator.hasNext:()Z
      74: ifeq          138
      77: aload         6
      79: invokeinterface #67,  1           // InterfaceMethod java/util/Iterator.next:()Ljava/lang/Object;
      84: astore        7
      86: aload         7
      88: ifnonnull     103
      91: aload_0
      92: getfield      #18                 // Field _suppressNulls:Z
      95: ifeq          101
      98: goto          67
     101: iconst_0
     102: ireturn
     103: iload         5
     105: ifeq          121
     108: aload         4
     110: aload_1
     111: aload         7
     113: invokevirtual #98                 // Method com/fasterxml/jackson/databind/JsonSerializer.isEmpty:(Lcom/fasterxml/jackson/databind/SerializerProvider;Ljava/lang/Object;)Z
     116: ifne          135
     119: iconst_0
     120: ireturn
     121: aload_3
     122: ifnull        133
     125: aload_3
     126: aload_2
     127: invokevirtual #99                 // Method java/lang/Object.equals:(Ljava/lang/Object;)Z
     130: ifne          135
     133: iconst_0
     134: ireturn
     135: goto          67
     138: iconst_1
     139: ireturn
     140: aload_2
     141: invokeinterface #96,  1           // InterfaceMethod java/util/Map.values:()Ljava/util/Collection;
     146: invokeinterface #97,  1           // InterfaceMethod java/util/Collection.iterator:()Ljava/util/Iterator;
     151: astore        6
     153: aload         6
     155: invokeinterface #66,  1           // InterfaceMethod java/util/Iterator.hasNext:()Z
     160: ifeq          240
     163: aload         6
     165: invokeinterface #67,  1           // InterfaceMethod java/util/Iterator.next:()Ljava/lang/Object;
     170: astore        7
     172: aload         7
     174: ifnonnull     189
     177: aload_0
     178: getfield      #18                 // Field _suppressNulls:Z
     181: ifeq          187
     184: goto          153
     187: iconst_0
     188: ireturn
     189: aload_0
     190: aload_1
     191: aload         7
     193: invokespecial #100                // Method _findSerializer:(Lcom/fasterxml/jackson/databind/SerializerProvider;Ljava/lang/Object;)Lcom/fasterxml/jackson/databind/JsonSerializer;
     196: astore        4
     198: goto          205
     201: astore        8
     203: iconst_0
     204: ireturn
     205: iload         5
     207: ifeq          223
     210: aload         4
     212: aload_1
     213: aload         7
     215: invokevirtual #98                 // Method com/fasterxml/jackson/databind/JsonSerializer.isEmpty:(Lcom/fasterxml/jackson/databind/SerializerProvider;Ljava/lang/Object;)Z
     218: ifne          237
     221: iconst_0
     222: ireturn
     223: aload_3
     224: ifnull        235
     227: aload_3
     228: aload_2
     229: invokevirtual #99                 // Method java/lang/Object.equals:(Ljava/lang/Object;)Z
     232: ifne          237
     235: iconst_0
     236: ireturn
     237: goto          153
     240: iconst_1
     241: ireturn
    Exception table:
       from    to  target type
         189   198   201   Class com/fasterxml/jackson/databind/JsonMappingException

  public boolean hasSingleElement(java.util.Map<?, ?>);
    Code:
       0: aload_1
       1: invokeinterface #102,  1          // InterfaceMethod java/util/Map.size:()I
       6: iconst_1
       7: if_icmpne     14
      10: iconst_1
      11: goto          15
      14: iconst_0
      15: ireturn

  public com.fasterxml.jackson.databind.JsonSerializer<?> getKeySerializer();
    Code:
       0: aload_0
       1: getfield      #10                 // Field _keySerializer:Lcom/fasterxml/jackson/databind/JsonSerializer;
       4: areturn

  public void serialize(java.util.Map<?, ?>, com.fasterxml.jackson.core.JsonGenerator, com.fasterxml.jackson.databind.SerializerProvider) throws java.io.IOException;
    Code:
       0: aload_2
       1: aload_1
       2: invokevirtual #103                // Method com/fasterxml/jackson/core/JsonGenerator.writeStartObject:(Ljava/lang/Object;)V
       5: aload_0
       6: aload_1
       7: aload_2
       8: aload_3
       9: invokevirtual #104                // Method serializeWithoutTypeInfo:(Ljava/util/Map;Lcom/fasterxml/jackson/core/JsonGenerator;Lcom/fasterxml/jackson/databind/SerializerProvider;)V
      12: aload_2
      13: invokevirtual #105                // Method com/fasterxml/jackson/core/JsonGenerator.writeEndObject:()V
      16: return

  public void serializeWithType(java.util.Map<?, ?>, com.fasterxml.jackson.core.JsonGenerator, com.fasterxml.jackson.databind.SerializerProvider, com.fasterxml.jackson.databind.jsontype.TypeSerializer) throws java.io.IOException;
    Code:
       0: aload_2
       1: aload_1
       2: invokevirtual #106                // Method com/fasterxml/jackson/core/JsonGenerator.setCurrentValue:(Ljava/lang/Object;)V
       5: aload         4
       7: aload_2
       8: aload         4
      10: aload_1
      11: getstatic     #107                // Field com/fasterxml/jackson/core/JsonToken.START_OBJECT:Lcom/fasterxml/jackson/core/JsonToken;
      14: invokevirtual #108                // Method com/fasterxml/jackson/databind/jsontype/TypeSerializer.typeId:(Ljava/lang/Object;Lcom/fasterxml/jackson/core/JsonToken;)Lcom/fasterxml/jackson/core/type/WritableTypeId;
      17: invokevirtual #109                // Method com/fasterxml/jackson/databind/jsontype/TypeSerializer.writeTypePrefix:(Lcom/fasterxml/jackson/core/JsonGenerator;Lcom/fasterxml/jackson/core/type/WritableTypeId;)Lcom/fasterxml/jackson/core/type/WritableTypeId;
      20: astore        5
      22: aload_0
      23: aload_1
      24: aload_2
      25: aload_3
      26: invokevirtual #104                // Method serializeWithoutTypeInfo:(Ljava/util/Map;Lcom/fasterxml/jackson/core/JsonGenerator;Lcom/fasterxml/jackson/databind/SerializerProvider;)V
      29: aload         4
      31: aload_2
      32: aload         5
      34: invokevirtual #110                // Method com/fasterxml/jackson/databind/jsontype/TypeSerializer.writeTypeSuffix:(Lcom/fasterxml/jackson/core/JsonGenerator;Lcom/fasterxml/jackson/core/type/WritableTypeId;)Lcom/fasterxml/jackson/core/type/WritableTypeId;
      37: pop
      38: return

  public void serializeWithoutTypeInfo(java.util.Map<?, ?>, com.fasterxml.jackson.core.JsonGenerator, com.fasterxml.jackson.databind.SerializerProvider) throws java.io.IOException;
    Code:
       0: aload_1
       1: invokeinterface #95,  1           // InterfaceMethod java/util/Map.isEmpty:()Z
       6: ifne          129
       9: aload_0
      10: getfield      #16                 // Field _sortKeys:Z
      13: ifne          26
      16: aload_3
      17: getstatic     #111                // Field com/fasterxml/jackson/databind/SerializationFeature.ORDER_MAP_ENTRIES_BY_KEYS:Lcom/fasterxml/jackson/databind/SerializationFeature;
      20: invokevirtual #112                // Method com/fasterxml/jackson/databind/SerializerProvider.isEnabled:(Lcom/fasterxml/jackson/databind/SerializationFeature;)Z
      23: ifeq          34
      26: aload_0
      27: aload_1
      28: aload_2
      29: aload_3
      30: invokevirtual #113                // Method _orderEntries:(Ljava/util/Map;Lcom/fasterxml/jackson/core/JsonGenerator;Lcom/fasterxml/jackson/databind/SerializerProvider;)Ljava/util/Map;
      33: astore_1
      34: aload_0
      35: getfield      #15                 // Field _filterId:Ljava/lang/Object;
      38: ifnull        73
      41: aload_0
      42: aload_3
      43: aload_0
      44: getfield      #15                 // Field _filterId:Ljava/lang/Object;
      47: aload_1
      48: invokevirtual #114                // Method findPropertyFilter:(Lcom/fasterxml/jackson/databind/SerializerProvider;Ljava/lang/Object;Ljava/lang/Object;)Lcom/fasterxml/jackson/databind/ser/PropertyFilter;
      51: dup
      52: astore        4
      54: ifnull        73
      57: aload_0
      58: aload_1
      59: aload_2
      60: aload_3
      61: aload         4
      63: aload_0
      64: getfield      #17                 // Field _suppressableValue:Ljava/lang/Object;
      67: invokevirtual #115                // Method serializeFilteredFields:(Ljava/util/Map;Lcom/fasterxml/jackson/core/JsonGenerator;Lcom/fasterxml/jackson/databind/SerializerProvider;Lcom/fasterxml/jackson/databind/ser/PropertyFilter;Ljava/lang/Object;)V
      70: goto          129
      73: aload_0
      74: getfield      #17                 // Field _suppressableValue:Ljava/lang/Object;
      77: ifnonnull     87
      80: aload_0
      81: getfield      #18                 // Field _suppressNulls:Z
      84: ifeq          101
      87: aload_0
      88: aload_1
      89: aload_2
      90: aload_3
      91: aload_0
      92: getfield      #17                 // Field _suppressableValue:Ljava/lang/Object;
      95: invokevirtual #116                // Method serializeOptionalFields:(Ljava/util/Map;Lcom/fasterxml/jackson/core/JsonGenerator;Lcom/fasterxml/jackson/databind/SerializerProvider;Ljava/lang/Object;)V
      98: goto          129
     101: aload_0
     102: getfield      #11                 // Field _valueSerializer:Lcom/fasterxml/jackson/databind/JsonSerializer;
     105: ifnull        122
     108: aload_0
     109: aload_1
     110: aload_2
     111: aload_3
     112: aload_0
     113: getfield      #11                 // Field _valueSerializer:Lcom/fasterxml/jackson/databind/JsonSerializer;
     116: invokevirtual #117                // Method serializeFieldsUsing:(Ljava/util/Map;Lcom/fasterxml/jackson/core/JsonGenerator;Lcom/fasterxml/jackson/databind/SerializerProvider;Lcom/fasterxml/jackson/databind/JsonSerializer;)V
     119: goto          129
     122: aload_0
     123: aload_1
     124: aload_2
     125: aload_3
     126: invokevirtual #118                // Method serializeFields:(Ljava/util/Map;Lcom/fasterxml/jackson/core/JsonGenerator;Lcom/fasterxml/jackson/databind/SerializerProvider;)V
     129: return

  public void serializeFields(java.util.Map<?, ?>, com.fasterxml.jackson.core.JsonGenerator, com.fasterxml.jackson.databind.SerializerProvider) throws java.io.IOException;
    Code:
       0: aload_0
       1: getfield      #9                  // Field _valueTypeSerializer:Lcom/fasterxml/jackson/databind/jsontype/TypeSerializer;
       4: ifnull        16
       7: aload_0
       8: aload_1
       9: aload_2
      10: aload_3
      11: aconst_null
      12: invokevirtual #119                // Method serializeTypedFields:(Ljava/util/Map;Lcom/fasterxml/jackson/core/JsonGenerator;Lcom/fasterxml/jackson/databind/SerializerProvider;Ljava/lang/Object;)V
      15: return
      16: aload_0
      17: getfield      #10                 // Field _keySerializer:Lcom/fasterxml/jackson/databind/JsonSerializer;
      20: astore        4
      22: aconst_null
      23: astore        5
      25: aload_1
      26: invokeinterface #120,  1          // InterfaceMethod java/util/Map.entrySet:()Ljava/util/Set;
      31: invokeinterface #65,  1           // InterfaceMethod java/util/Set.iterator:()Ljava/util/Iterator;
      36: astore        6
      38: aload         6
      40: invokeinterface #66,  1           // InterfaceMethod java/util/Iterator.hasNext:()Z
      45: ifeq          180
      48: aload         6
      50: invokeinterface #67,  1           // InterfaceMethod java/util/Iterator.next:()Ljava/lang/Object;
      55: checkcast     #121                // class java/util/Map$Entry
      58: astore        7
      60: aload         7
      62: invokeinterface #122,  1          // InterfaceMethod java/util/Map$Entry.getValue:()Ljava/lang/Object;
      67: astore        8
      69: aload         7
      71: invokeinterface #123,  1          // InterfaceMethod java/util/Map$Entry.getKey:()Ljava/lang/Object;
      76: astore        5
      78: aload         5
      80: ifnonnull     104
      83: aload_3
      84: aload_0
      85: getfield      #6                  // Field _keyType:Lcom/fasterxml/jackson/databind/JavaType;
      88: aload_0
      89: getfield      #14                 // Field _property:Lcom/fasterxml/jackson/databind/BeanProperty;
      92: invokevirtual #124                // Method com/fasterxml/jackson/databind/SerializerProvider.findNullKeySerializer:(Lcom/fasterxml/jackson/databind/JavaType;Lcom/fasterxml/jackson/databind/BeanProperty;)Lcom/fasterxml/jackson/databind/JsonSerializer;
      95: aconst_null
      96: aload_2
      97: aload_3
      98: invokevirtual #125                // Method com/fasterxml/jackson/databind/JsonSerializer.serialize:(Ljava/lang/Object;Lcom/fasterxml/jackson/core/JsonGenerator;Lcom/fasterxml/jackson/databind/SerializerProvider;)V
     101: goto          135
     104: aload_0
     105: getfield      #20                 // Field _inclusionChecker:Lcom/fasterxml/jackson/databind/util/IgnorePropertiesUtil$Checker;
     108: ifnull        126
     111: aload_0
     112: getfield      #20                 // Field _inclusionChecker:Lcom/fasterxml/jackson/databind/util/IgnorePropertiesUtil$Checker;
     115: aload         5
     117: invokevirtual #126                // Method com/fasterxml/jackson/databind/util/IgnorePropertiesUtil$Checker.shouldIgnore:(Ljava/lang/Object;)Z
     120: ifeq          126
     123: goto          38
     126: aload         4
     128: aload         5
     130: aload_2
     131: aload_3
     132: invokevirtual #125                // Method com/fasterxml/jackson/databind/JsonSerializer.serialize:(Ljava/lang/Object;Lcom/fasterxml/jackson/core/JsonGenerator;Lcom/fasterxml/jackson/databind/SerializerProvider;)V
     135: aload         8
     137: ifnonnull     148
     140: aload_3
     141: aload_2
     142: invokevirtual #127                // Method com/fasterxml/jackson/databind/SerializerProvider.defaultSerializeNull:(Lcom/fasterxml/jackson/core/JsonGenerator;)V
     145: goto          38
     148: aload_0
     149: getfield      #11                 // Field _valueSerializer:Lcom/fasterxml/jackson/databind/JsonSerializer;
     152: astore        9
     154: aload         9
     156: ifnonnull     168
     159: aload_0
     160: aload_3
     161: aload         8
     163: invokespecial #100                // Method _findSerializer:(Lcom/fasterxml/jackson/databind/SerializerProvider;Ljava/lang/Object;)Lcom/fasterxml/jackson/databind/JsonSerializer;
     166: astore        9
     168: aload         9
     170: aload         8
     172: aload_2
     173: aload_3
     174: invokevirtual #125                // Method com/fasterxml/jackson/databind/JsonSerializer.serialize:(Ljava/lang/Object;Lcom/fasterxml/jackson/core/JsonGenerator;Lcom/fasterxml/jackson/databind/SerializerProvider;)V
     177: goto          38
     180: goto          198
     183: astore        6
     185: aload_0
     186: aload_3
     187: aload         6
     189: aload_1
     190: aload         5
     192: invokestatic  #129                // Method java/lang/String.valueOf:(Ljava/lang/Object;)Ljava/lang/String;
     195: invokevirtual #130                // Method wrapAndThrow:(Lcom/fasterxml/jackson/databind/SerializerProvider;Ljava/lang/Throwable;Ljava/lang/Object;Ljava/lang/String;)V
     198: return
    Exception table:
       from    to  target type
          25   180   183   Class java/lang/Exception

  public void serializeOptionalFields(java.util.Map<?, ?>, com.fasterxml.jackson.core.JsonGenerator, com.fasterxml.jackson.databind.SerializerProvider, java.lang.Object) throws java.io.IOException;
    Code:
       0: aload_0
       1: getfield      #9                  // Field _valueTypeSerializer:Lcom/fasterxml/jackson/databind/jsontype/TypeSerializer;
       4: ifnull        17
       7: aload_0
       8: aload_1
       9: aload_2
      10: aload_3
      11: aload         4
      13: invokevirtual #119                // Method serializeTypedFields:(Ljava/util/Map;Lcom/fasterxml/jackson/core/JsonGenerator;Lcom/fasterxml/jackson/databind/SerializerProvider;Ljava/lang/Object;)V
      16: return
      17: getstatic     #90                 // Field MARKER_FOR_EMPTY:Ljava/lang/Object;
      20: aload         4
      22: if_acmpne     29
      25: iconst_1
      26: goto          30
      29: iconst_0
      30: istore        5
      32: aload_1
      33: invokeinterface #120,  1          // InterfaceMethod java/util/Map.entrySet:()Ljava/util/Set;
      38: invokeinterface #65,  1           // InterfaceMethod java/util/Set.iterator:()Ljava/util/Iterator;
      43: astore        6
      45: aload         6
      47: invokeinterface #66,  1           // InterfaceMethod java/util/Iterator.hasNext:()Z
      52: ifeq          255
      55: aload         6
      57: invokeinterface #67,  1           // InterfaceMethod java/util/Iterator.next:()Ljava/lang/Object;
      62: checkcast     #121                // class java/util/Map$Entry
      65: astore        7
      67: aload         7
      69: invokeinterface #123,  1          // InterfaceMethod java/util/Map$Entry.getKey:()Ljava/lang/Object;
      74: astore        8
      76: aload         8
      78: ifnonnull     98
      81: aload_3
      82: aload_0
      83: getfield      #6                  // Field _keyType:Lcom/fasterxml/jackson/databind/JavaType;
      86: aload_0
      87: getfield      #14                 // Field _property:Lcom/fasterxml/jackson/databind/BeanProperty;
      90: invokevirtual #124                // Method com/fasterxml/jackson/databind/SerializerProvider.findNullKeySerializer:(Lcom/fasterxml/jackson/databind/JavaType;Lcom/fasterxml/jackson/databind/BeanProperty;)Lcom/fasterxml/jackson/databind/JsonSerializer;
      93: astore        9
      95: goto          126
      98: aload_0
      99: getfield      #20                 // Field _inclusionChecker:Lcom/fasterxml/jackson/databind/util/IgnorePropertiesUtil$Checker;
     102: ifnull        120
     105: aload_0
     106: getfield      #20                 // Field _inclusionChecker:Lcom/fasterxml/jackson/databind/util/IgnorePropertiesUtil$Checker;
     109: aload         8
     111: invokevirtual #126                // Method com/fasterxml/jackson/databind/util/IgnorePropertiesUtil$Checker.shouldIgnore:(Ljava/lang/Object;)Z
     114: ifeq          120
     117: goto          45
     120: aload_0
     121: getfield      #10                 // Field _keySerializer:Lcom/fasterxml/jackson/databind/JsonSerializer;
     124: astore        9
     126: aload         7
     128: invokeinterface #122,  1          // InterfaceMethod java/util/Map$Entry.getValue:()Ljava/lang/Object;
     133: astore        10
     135: aload         10
     137: ifnonnull     159
     140: aload_0
     141: getfield      #18                 // Field _suppressNulls:Z
     144: ifeq          150
     147: goto          45
     150: aload_3
     151: invokevirtual #131                // Method com/fasterxml/jackson/databind/SerializerProvider.getDefaultNullValueSerializer:()Lcom/fasterxml/jackson/databind/JsonSerializer;
     154: astore        11
     156: goto          216
     159: aload_0
     160: getfield      #11                 // Field _valueSerializer:Lcom/fasterxml/jackson/databind/JsonSerializer;
     163: astore        11
     165: aload         11
     167: ifnonnull     179
     170: aload_0
     171: aload_3
     172: aload         10
     174: invokespecial #100                // Method _findSerializer:(Lcom/fasterxml/jackson/databind/SerializerProvider;Ljava/lang/Object;)Lcom/fasterxml/jackson/databind/JsonSerializer;
     177: astore        11
     179: iload         5
     181: ifeq          198
     184: aload         11
     186: aload_3
     187: aload         10
     189: invokevirtual #98                 // Method com/fasterxml/jackson/databind/JsonSerializer.isEmpty:(Lcom/fasterxml/jackson/databind/SerializerProvider;Ljava/lang/Object;)Z
     192: ifeq          216
     195: goto          45
     198: aload         4
     200: ifnull        216
     203: aload         4
     205: aload         10
     207: invokevirtual #99                 // Method java/lang/Object.equals:(Ljava/lang/Object;)Z
     210: ifeq          216
     213: goto          45
     216: aload         9
     218: aload         8
     220: aload_2
     221: aload_3
     222: invokevirtual #125                // Method com/fasterxml/jackson/databind/JsonSerializer.serialize:(Ljava/lang/Object;Lcom/fasterxml/jackson/core/JsonGenerator;Lcom/fasterxml/jackson/databind/SerializerProvider;)V
     225: aload         11
     227: aload         10
     229: aload_2
     230: aload_3
     231: invokevirtual #125                // Method com/fasterxml/jackson/databind/JsonSerializer.serialize:(Ljava/lang/Object;Lcom/fasterxml/jackson/core/JsonGenerator;Lcom/fasterxml/jackson/databind/SerializerProvider;)V
     234: goto          252
     237: astore        12
     239: aload_0
     240: aload_3
     241: aload         12
     243: aload_1
     244: aload         8
     246: invokestatic  #129                // Method java/lang/String.valueOf:(Ljava/lang/Object;)Ljava/lang/String;
     249: invokevirtual #130                // Method wrapAndThrow:(Lcom/fasterxml/jackson/databind/SerializerProvider;Ljava/lang/Throwable;Ljava/lang/Object;Ljava/lang/String;)V
     252: goto          45
     255: return
    Exception table:
       from    to  target type
         216   234   237   Class java/lang/Exception

  public void serializeFieldsUsing(java.util.Map<?, ?>, com.fasterxml.jackson.core.JsonGenerator, com.fasterxml.jackson.databind.SerializerProvider, com.fasterxml.jackson.databind.JsonSerializer<java.lang.Object>) throws java.io.IOException;
    Code:
       0: aload_0
       1: getfield      #10                 // Field _keySerializer:Lcom/fasterxml/jackson/databind/JsonSerializer;
       4: astore        5
       6: aload_0
       7: getfield      #9                  // Field _valueTypeSerializer:Lcom/fasterxml/jackson/databind/jsontype/TypeSerializer;
      10: astore        6
      12: aload_1
      13: invokeinterface #120,  1          // InterfaceMethod java/util/Map.entrySet:()Ljava/util/Set;
      18: invokeinterface #65,  1           // InterfaceMethod java/util/Set.iterator:()Ljava/util/Iterator;
      23: astore        7
      25: aload         7
      27: invokeinterface #66,  1           // InterfaceMethod java/util/Iterator.hasNext:()Z
      32: ifeq          184
      35: aload         7
      37: invokeinterface #67,  1           // InterfaceMethod java/util/Iterator.next:()Ljava/lang/Object;
      42: checkcast     #121                // class java/util/Map$Entry
      45: astore        8
      47: aload         8
      49: invokeinterface #123,  1          // InterfaceMethod java/util/Map$Entry.getKey:()Ljava/lang/Object;
      54: astore        9
      56: aload_0
      57: getfield      #20                 // Field _inclusionChecker:Lcom/fasterxml/jackson/databind/util/IgnorePropertiesUtil$Checker;
      60: ifnull        78
      63: aload_0
      64: getfield      #20                 // Field _inclusionChecker:Lcom/fasterxml/jackson/databind/util/IgnorePropertiesUtil$Checker;
      67: aload         9
      69: invokevirtual #126                // Method com/fasterxml/jackson/databind/util/IgnorePropertiesUtil$Checker.shouldIgnore:(Ljava/lang/Object;)Z
      72: ifeq          78
      75: goto          25
      78: aload         9
      80: ifnonnull     104
      83: aload_3
      84: aload_0
      85: getfield      #6                  // Field _keyType:Lcom/fasterxml/jackson/databind/JavaType;
      88: aload_0
      89: getfield      #14                 // Field _property:Lcom/fasterxml/jackson/databind/BeanProperty;
      92: invokevirtual #124                // Method com/fasterxml/jackson/databind/SerializerProvider.findNullKeySerializer:(Lcom/fasterxml/jackson/databind/JavaType;Lcom/fasterxml/jackson/databind/BeanProperty;)Lcom/fasterxml/jackson/databind/JsonSerializer;
      95: aconst_null
      96: aload_2
      97: aload_3
      98: invokevirtual #125                // Method com/fasterxml/jackson/databind/JsonSerializer.serialize:(Ljava/lang/Object;Lcom/fasterxml/jackson/core/JsonGenerator;Lcom/fasterxml/jackson/databind/SerializerProvider;)V
     101: goto          113
     104: aload         5
     106: aload         9
     108: aload_2
     109: aload_3
     110: invokevirtual #125                // Method com/fasterxml/jackson/databind/JsonSerializer.serialize:(Ljava/lang/Object;Lcom/fasterxml/jackson/core/JsonGenerator;Lcom/fasterxml/jackson/databind/SerializerProvider;)V
     113: aload         8
     115: invokeinterface #122,  1          // InterfaceMethod java/util/Map$Entry.getValue:()Ljava/lang/Object;
     120: astore        10
     122: aload         10
     124: ifnonnull     135
     127: aload_3
     128: aload_2
     129: invokevirtual #127                // Method com/fasterxml/jackson/databind/SerializerProvider.defaultSerializeNull:(Lcom/fasterxml/jackson/core/JsonGenerator;)V
     132: goto          181
     135: aload         6
     137: ifnonnull     152
     140: aload         4
     142: aload         10
     144: aload_2
     145: aload_3
     146: invokevirtual #125                // Method com/fasterxml/jackson/databind/JsonSerializer.serialize:(Ljava/lang/Object;Lcom/fasterxml/jackson/core/JsonGenerator;Lcom/fasterxml/jackson/databind/SerializerProvider;)V
     149: goto          163
     152: aload         4
     154: aload         10
     156: aload_2
     157: aload_3
     158: aload         6
     160: invokevirtual #132                // Method com/fasterxml/jackson/databind/JsonSerializer.serializeWithType:(Ljava/lang/Object;Lcom/fasterxml/jackson/core/JsonGenerator;Lcom/fasterxml/jackson/databind/SerializerProvider;Lcom/fasterxml/jackson/databind/jsontype/TypeSerializer;)V
     163: goto          181
     166: astore        11
     168: aload_0
     169: aload_3
     170: aload         11
     172: aload_1
     173: aload         9
     175: invokestatic  #129                // Method java/lang/String.valueOf:(Ljava/lang/Object;)Ljava/lang/String;
     178: invokevirtual #130                // Method wrapAndThrow:(Lcom/fasterxml/jackson/databind/SerializerProvider;Ljava/lang/Throwable;Ljava/lang/Object;Ljava/lang/String;)V
     181: goto          25
     184: return
    Exception table:
       from    to  target type
         135   163   166   Class java/lang/Exception

  public void serializeFilteredFields(java.util.Map<?, ?>, com.fasterxml.jackson.core.JsonGenerator, com.fasterxml.jackson.databind.SerializerProvider, com.fasterxml.jackson.databind.ser.PropertyFilter, java.lang.Object) throws java.io.IOException;
    Code:
       0: new           #133                // class com/fasterxml/jackson/databind/ser/std/MapProperty
       3: dup
       4: aload_0
       5: getfield      #9                  // Field _valueTypeSerializer:Lcom/fasterxml/jackson/databind/jsontype/TypeSerializer;
       8: aload_0
       9: getfield      #14                 // Field _property:Lcom/fasterxml/jackson/databind/BeanProperty;
      12: invokespecial #134                // Method com/fasterxml/jackson/databind/ser/std/MapProperty."<init>":(Lcom/fasterxml/jackson/databind/jsontype/TypeSerializer;Lcom/fasterxml/jackson/databind/BeanProperty;)V
      15: astore        6
      17: getstatic     #90                 // Field MARKER_FOR_EMPTY:Ljava/lang/Object;
      20: aload         5
      22: if_acmpne     29
      25: iconst_1
      26: goto          30
      29: iconst_0
      30: istore        7
      32: aload_1
      33: invokeinterface #120,  1          // InterfaceMethod java/util/Map.entrySet:()Ljava/util/Set;
      38: invokeinterface #65,  1           // InterfaceMethod java/util/Set.iterator:()Ljava/util/Iterator;
      43: astore        8
      45: aload         8
      47: invokeinterface #66,  1           // InterfaceMethod java/util/Iterator.hasNext:()Z
      52: ifeq          262
      55: aload         8
      57: invokeinterface #67,  1           // InterfaceMethod java/util/Iterator.next:()Ljava/lang/Object;
      62: checkcast     #121                // class java/util/Map$Entry
      65: astore        9
      67: aload         9
      69: invokeinterface #123,  1          // InterfaceMethod java/util/Map$Entry.getKey:()Ljava/lang/Object;
      74: astore        10
      76: aload_0
      77: getfield      #20                 // Field _inclusionChecker:Lcom/fasterxml/jackson/databind/util/IgnorePropertiesUtil$Checker;
      80: ifnull        98
      83: aload_0
      84: getfield      #20                 // Field _inclusionChecker:Lcom/fasterxml/jackson/databind/util/IgnorePropertiesUtil$Checker;
      87: aload         10
      89: invokevirtual #126                // Method com/fasterxml/jackson/databind/util/IgnorePropertiesUtil$Checker.shouldIgnore:(Ljava/lang/Object;)Z
      92: ifeq          98
      95: goto          45
      98: aload         10
     100: ifnonnull     120
     103: aload_3
     104: aload_0
     105: getfield      #6                  // Field _keyType:Lcom/fasterxml/jackson/databind/JavaType;
     108: aload_0
     109: getfield      #14                 // Field _property:Lcom/fasterxml/jackson/databind/BeanProperty;
     112: invokevirtual #124                // Method com/fasterxml/jackson/databind/SerializerProvider.findNullKeySerializer:(Lcom/fasterxml/jackson/databind/JavaType;Lcom/fasterxml/jackson/databind/BeanProperty;)Lcom/fasterxml/jackson/databind/JsonSerializer;
     115: astore        11
     117: goto          126
     120: aload_0
     121: getfield      #10                 // Field _keySerializer:Lcom/fasterxml/jackson/databind/JsonSerializer;
     124: astore        11
     126: aload         9
     128: invokeinterface #122,  1          // InterfaceMethod java/util/Map$Entry.getValue:()Ljava/lang/Object;
     133: astore        12
     135: aload         12
     137: ifnonnull     159
     140: aload_0
     141: getfield      #18                 // Field _suppressNulls:Z
     144: ifeq          150
     147: goto          45
     150: aload_3
     151: invokevirtual #131                // Method com/fasterxml/jackson/databind/SerializerProvider.getDefaultNullValueSerializer:()Lcom/fasterxml/jackson/databind/JsonSerializer;
     154: astore        13
     156: goto          216
     159: aload_0
     160: getfield      #11                 // Field _valueSerializer:Lcom/fasterxml/jackson/databind/JsonSerializer;
     163: astore        13
     165: aload         13
     167: ifnonnull     179
     170: aload_0
     171: aload_3
     172: aload         12
     174: invokespecial #100                // Method _findSerializer:(Lcom/fasterxml/jackson/databind/SerializerProvider;Ljava/lang/Object;)Lcom/fasterxml/jackson/databind/JsonSerializer;
     177: astore        13
     179: iload         7
     181: ifeq          198
     184: aload         13
     186: aload_3
     187: aload         12
     189: invokevirtual #98                 // Method com/fasterxml/jackson/databind/JsonSerializer.isEmpty:(Lcom/fasterxml/jackson/databind/SerializerProvider;Ljava/lang/Object;)Z
     192: ifeq          216
     195: goto          45
     198: aload         5
     200: ifnull        216
     203: aload         5
     205: aload         12
     207: invokevirtual #99                 // Method java/lang/Object.equals:(Ljava/lang/Object;)Z
     210: ifeq          216
     213: goto          45
     216: aload         6
     218: aload         10
     220: aload         12
     222: aload         11
     224: aload         13
     226: invokevirtual #135                // Method com/fasterxml/jackson/databind/ser/std/MapProperty.reset:(Ljava/lang/Object;Ljava/lang/Object;Lcom/fasterxml/jackson/databind/JsonSerializer;Lcom/fasterxml/jackson/databind/JsonSerializer;)V
     229: aload         4
     231: aload_1
     232: aload_2
     233: aload_3
     234: aload         6
     236: invokeinterface #136,  5          // InterfaceMethod com/fasterxml/jackson/databind/ser/PropertyFilter.serializeAsField:(Ljava/lang/Object;Lcom/fasterxml/jackson/core/JsonGenerator;Lcom/fasterxml/jackson/databind/SerializerProvider;Lcom/fasterxml/jackson/databind/ser/PropertyWriter;)V
     241: goto          259
     244: astore        14
     246: aload_0
     247: aload_3
     248: aload         14
     250: aload_1
     251: aload         10
     253: invokestatic  #129                // Method java/lang/String.valueOf:(Ljava/lang/Object;)Ljava/lang/String;
     256: invokevirtual #130                // Method wrapAndThrow:(Lcom/fasterxml/jackson/databind/SerializerProvider;Ljava/lang/Throwable;Ljava/lang/Object;Ljava/lang/String;)V
     259: goto          45
     262: return
    Exception table:
       from    to  target type
         229   241   244   Class java/lang/Exception

  public void serializeTypedFields(java.util.Map<?, ?>, com.fasterxml.jackson.core.JsonGenerator, com.fasterxml.jackson.databind.SerializerProvider, java.lang.Object) throws java.io.IOException;
    Code:
       0: getstatic     #90                 // Field MARKER_FOR_EMPTY:Ljava/lang/Object;
       3: aload         4
       5: if_acmpne     12
       8: iconst_1
       9: goto          13
      12: iconst_0
      13: istore        5
      15: aload_1
      16: invokeinterface #120,  1          // InterfaceMethod java/util/Map.entrySet:()Ljava/util/Set;
      21: invokeinterface #65,  1           // InterfaceMethod java/util/Set.iterator:()Ljava/util/Iterator;
      26: astore        6
      28: aload         6
      30: invokeinterface #66,  1           // InterfaceMethod java/util/Iterator.hasNext:()Z
      35: ifeq          242
      38: aload         6
      40: invokeinterface #67,  1           // InterfaceMethod java/util/Iterator.next:()Ljava/lang/Object;
      45: checkcast     #121                // class java/util/Map$Entry
      48: astore        7
      50: aload         7
      52: invokeinterface #123,  1          // InterfaceMethod java/util/Map$Entry.getKey:()Ljava/lang/Object;
      57: astore        8
      59: aload         8
      61: ifnonnull     81
      64: aload_3
      65: aload_0
      66: getfield      #6                  // Field _keyType:Lcom/fasterxml/jackson/databind/JavaType;
      69: aload_0
      70: getfield      #14                 // Field _property:Lcom/fasterxml/jackson/databind/BeanProperty;
      73: invokevirtual #124                // Method com/fasterxml/jackson/databind/SerializerProvider.findNullKeySerializer:(Lcom/fasterxml/jackson/databind/JavaType;Lcom/fasterxml/jackson/databind/BeanProperty;)Lcom/fasterxml/jackson/databind/JsonSerializer;
      76: astore        9
      78: goto          109
      81: aload_0
      82: getfield      #20                 // Field _inclusionChecker:Lcom/fasterxml/jackson/databind/util/IgnorePropertiesUtil$Checker;
      85: ifnull        103
      88: aload_0
      89: getfield      #20                 // Field _inclusionChecker:Lcom/fasterxml/jackson/databind/util/IgnorePropertiesUtil$Checker;
      92: aload         8
      94: invokevirtual #126                // Method com/fasterxml/jackson/databind/util/IgnorePropertiesUtil$Checker.shouldIgnore:(Ljava/lang/Object;)Z
      97: ifeq          103
     100: goto          28
     103: aload_0
     104: getfield      #10                 // Field _keySerializer:Lcom/fasterxml/jackson/databind/JsonSerializer;
     107: astore        9
     109: aload         7
     111: invokeinterface #122,  1          // InterfaceMethod java/util/Map$Entry.getValue:()Ljava/lang/Object;
     116: astore        10
     118: aload         10
     120: ifnonnull     142
     123: aload_0
     124: getfield      #18                 // Field _suppressNulls:Z
     127: ifeq          133
     130: goto          28
     133: aload_3
     134: invokevirtual #131                // Method com/fasterxml/jackson/databind/SerializerProvider.getDefaultNullValueSerializer:()Lcom/fasterxml/jackson/databind/JsonSerializer;
     137: astore        11
     139: goto          199
     142: aload_0
     143: getfield      #11                 // Field _valueSerializer:Lcom/fasterxml/jackson/databind/JsonSerializer;
     146: astore        11
     148: aload         11
     150: ifnonnull     162
     153: aload_0
     154: aload_3
     155: aload         10
     157: invokespecial #100                // Method _findSerializer:(Lcom/fasterxml/jackson/databind/SerializerProvider;Ljava/lang/Object;)Lcom/fasterxml/jackson/databind/JsonSerializer;
     160: astore        11
     162: iload         5
     164: ifeq          181
     167: aload         11
     169: aload_3
     170: aload         10
     172: invokevirtual #98                 // Method com/fasterxml/jackson/databind/JsonSerializer.isEmpty:(Lcom/fasterxml/jackson/databind/SerializerProvider;Ljava/lang/Object;)Z
     175: ifeq          199
     178: goto          28
     181: aload         4
     183: ifnull        199
     186: aload         4
     188: aload         10
     190: invokevirtual #99                 // Method java/lang/Object.equals:(Ljava/lang/Object;)Z
     193: ifeq          199
     196: goto          28
     199: aload         9
     201: aload         8
     203: aload_2
     204: aload_3
     205: invokevirtual #125                // Method com/fasterxml/jackson/databind/JsonSerializer.serialize:(Ljava/lang/Object;Lcom/fasterxml/jackson/core/JsonGenerator;Lcom/fasterxml/jackson/databind/SerializerProvider;)V
     208: aload         11
     210: aload         10
     212: aload_2
     213: aload_3
     214: aload_0
     215: getfield      #9                  // Field _valueTypeSerializer:Lcom/fasterxml/jackson/databind/jsontype/TypeSerializer;
     218: invokevirtual #132                // Method com/fasterxml/jackson/databind/JsonSerializer.serializeWithType:(Ljava/lang/Object;Lcom/fasterxml/jackson/core/JsonGenerator;Lcom/fasterxml/jackson/databind/SerializerProvider;Lcom/fasterxml/jackson/databind/jsontype/TypeSerializer;)V
     221: goto          239
     224: astore        12
     226: aload_0
     227: aload_3
     228: aload         12
     230: aload_1
     231: aload         8
     233: invokestatic  #129                // Method java/lang/String.valueOf:(Ljava/lang/Object;)Ljava/lang/String;
     236: invokevirtual #130                // Method wrapAndThrow:(Lcom/fasterxml/jackson/databind/SerializerProvider;Ljava/lang/Throwable;Ljava/lang/Object;Ljava/lang/String;)V
     239: goto          28
     242: return
    Exception table:
       from    to  target type
         208   221   224   Class java/lang/Exception

  public void serializeFilteredAnyProperties(com.fasterxml.jackson.databind.SerializerProvider, com.fasterxml.jackson.core.JsonGenerator, java.lang.Object, java.util.Map<?, ?>, com.fasterxml.jackson.databind.ser.PropertyFilter, java.lang.Object) throws java.io.IOException;
    Code:
       0: new           #133                // class com/fasterxml/jackson/databind/ser/std/MapProperty
       3: dup
       4: aload_0
       5: getfield      #9                  // Field _valueTypeSerializer:Lcom/fasterxml/jackson/databind/jsontype/TypeSerializer;
       8: aload_0
       9: getfield      #14                 // Field _property:Lcom/fasterxml/jackson/databind/BeanProperty;
      12: invokespecial #134                // Method com/fasterxml/jackson/databind/ser/std/MapProperty."<init>":(Lcom/fasterxml/jackson/databind/jsontype/TypeSerializer;Lcom/fasterxml/jackson/databind/BeanProperty;)V
      15: astore        7
      17: getstatic     #90                 // Field MARKER_FOR_EMPTY:Ljava/lang/Object;
      20: aload         6
      22: if_acmpne     29
      25: iconst_1
      26: goto          30
      29: iconst_0
      30: istore        8
      32: aload         4
      34: invokeinterface #120,  1          // InterfaceMethod java/util/Map.entrySet:()Ljava/util/Set;
      39: invokeinterface #65,  1           // InterfaceMethod java/util/Set.iterator:()Ljava/util/Iterator;
      44: astore        9
      46: aload         9
      48: invokeinterface #66,  1           // InterfaceMethod java/util/Iterator.hasNext:()Z
      53: ifeq          264
      56: aload         9
      58: invokeinterface #67,  1           // InterfaceMethod java/util/Iterator.next:()Ljava/lang/Object;
      63: checkcast     #121                // class java/util/Map$Entry
      66: astore        10
      68: aload         10
      70: invokeinterface #123,  1          // InterfaceMethod java/util/Map$Entry.getKey:()Ljava/lang/Object;
      75: astore        11
      77: aload_0
      78: getfield      #20                 // Field _inclusionChecker:Lcom/fasterxml/jackson/databind/util/IgnorePropertiesUtil$Checker;
      81: ifnull        99
      84: aload_0
      85: getfield      #20                 // Field _inclusionChecker:Lcom/fasterxml/jackson/databind/util/IgnorePropertiesUtil$Checker;
      88: aload         11
      90: invokevirtual #126                // Method com/fasterxml/jackson/databind/util/IgnorePropertiesUtil$Checker.shouldIgnore:(Ljava/lang/Object;)Z
      93: ifeq          99
      96: goto          46
      99: aload         11
     101: ifnonnull     121
     104: aload_1
     105: aload_0
     106: getfield      #6                  // Field _keyType:Lcom/fasterxml/jackson/databind/JavaType;
     109: aload_0
     110: getfield      #14                 // Field _property:Lcom/fasterxml/jackson/databind/BeanProperty;
     113: invokevirtual #124                // Method com/fasterxml/jackson/databind/SerializerProvider.findNullKeySerializer:(Lcom/fasterxml/jackson/databind/JavaType;Lcom/fasterxml/jackson/databind/BeanProperty;)Lcom/fasterxml/jackson/databind/JsonSerializer;
     116: astore        12
     118: goto          127
     121: aload_0
     122: getfield      #10                 // Field _keySerializer:Lcom/fasterxml/jackson/databind/JsonSerializer;
     125: astore        12
     127: aload         10
     129: invokeinterface #122,  1          // InterfaceMethod java/util/Map$Entry.getValue:()Ljava/lang/Object;
     134: astore        13
     136: aload         13
     138: ifnonnull     160
     141: aload_0
     142: getfield      #18                 // Field _suppressNulls:Z
     145: ifeq          151
     148: goto          46
     151: aload_1
     152: invokevirtual #131                // Method com/fasterxml/jackson/databind/SerializerProvider.getDefaultNullValueSerializer:()Lcom/fasterxml/jackson/databind/JsonSerializer;
     155: astore        14
     157: goto          217
     160: aload_0
     161: getfield      #11                 // Field _valueSerializer:Lcom/fasterxml/jackson/databind/JsonSerializer;
     164: astore        14
     166: aload         14
     168: ifnonnull     180
     171: aload_0
     172: aload_1
     173: aload         13
     175: invokespecial #100                // Method _findSerializer:(Lcom/fasterxml/jackson/databind/SerializerProvider;Ljava/lang/Object;)Lcom/fasterxml/jackson/databind/JsonSerializer;
     178: astore        14
     180: iload         8
     182: ifeq          199
     185: aload         14
     187: aload_1
     188: aload         13
     190: invokevirtual #98                 // Method com/fasterxml/jackson/databind/JsonSerializer.isEmpty:(Lcom/fasterxml/jackson/databind/SerializerProvider;Ljava/lang/Object;)Z
     193: ifeq          217
     196: goto          46
     199: aload         6
     201: ifnull        217
     204: aload         6
     206: aload         13
     208: invokevirtual #99                 // Method java/lang/Object.equals:(Ljava/lang/Object;)Z
     211: ifeq          217
     214: goto          46
     217: aload         7
     219: aload         11
     221: aload         13
     223: aload         12
     225: aload         14
     227: invokevirtual #135                // Method com/fasterxml/jackson/databind/ser/std/MapProperty.reset:(Ljava/lang/Object;Ljava/lang/Object;Lcom/fasterxml/jackson/databind/JsonSerializer;Lcom/fasterxml/jackson/databind/JsonSerializer;)V
     230: aload         5
     232: aload_3
     233: aload_2
     234: aload_1
     235: aload         7
     237: invokeinterface #136,  5          // InterfaceMethod com/fasterxml/jackson/databind/ser/PropertyFilter.serializeAsField:(Ljava/lang/Object;Lcom/fasterxml/jackson/core/JsonGenerator;Lcom/fasterxml/jackson/databind/SerializerProvider;Lcom/fasterxml/jackson/databind/ser/PropertyWriter;)V
     242: goto          261
     245: astore        15
     247: aload_0
     248: aload_1
     249: aload         15
     251: aload         4
     253: aload         11
     255: invokestatic  #129                // Method java/lang/String.valueOf:(Ljava/lang/Object;)Ljava/lang/String;
     258: invokevirtual #130                // Method wrapAndThrow:(Lcom/fasterxml/jackson/databind/SerializerProvider;Ljava/lang/Throwable;Ljava/lang/Object;Ljava/lang/String;)V
     261: goto          46
     264: return
    Exception table:
       from    to  target type
         230   242   245   Class java/lang/Exception

  public com.fasterxml.jackson.databind.JsonNode getSchema(com.fasterxml.jackson.databind.SerializerProvider, java.lang.reflect.Type);
    Code:
       0: aload_0
       1: ldc           #137                // String object
       3: iconst_1
       4: invokevirtual #138                // Method createSchemaNode:(Ljava/lang/String;Z)Lcom/fasterxml/jackson/databind/node/ObjectNode;
       7: areturn

  public void acceptJsonFormatVisitor(com.fasterxml.jackson.databind.jsonFormatVisitors.JsonFormatVisitorWrapper, com.fasterxml.jackson.databind.JavaType) throws com.fasterxml.jackson.databind.JsonMappingException;
    Code:
       0: aload_1
       1: aload_2
       2: invokeinterface #139,  2          // InterfaceMethod com/fasterxml/jackson/databind/jsonFormatVisitors/JsonFormatVisitorWrapper.expectMapFormat:(Lcom/fasterxml/jackson/databind/JavaType;)Lcom/fasterxml/jackson/databind/jsonFormatVisitors/JsonMapFormatVisitor;
       7: astore_3
       8: aload_3
       9: ifnull        69
      12: aload_3
      13: aload_0
      14: getfield      #10                 // Field _keySerializer:Lcom/fasterxml/jackson/databind/JsonSerializer;
      17: aload_0
      18: getfield      #6                  // Field _keyType:Lcom/fasterxml/jackson/databind/JavaType;
      21: invokeinterface #140,  3          // InterfaceMethod com/fasterxml/jackson/databind/jsonFormatVisitors/JsonMapFormatVisitor.keyFormat:(Lcom/fasterxml/jackson/databind/jsonFormatVisitors/JsonFormatVisitable;Lcom/fasterxml/jackson/databind/JavaType;)V
      26: aload_0
      27: getfield      #11                 // Field _valueSerializer:Lcom/fasterxml/jackson/databind/JsonSerializer;
      30: astore        4
      32: aload         4
      34: ifnonnull     57
      37: aload_0
      38: aload_0
      39: getfield      #13                 // Field _dynamicValueSerializers:Lcom/fasterxml/jackson/databind/ser/impl/PropertySerializerMap;
      42: aload_0
      43: getfield      #7                  // Field _valueType:Lcom/fasterxml/jackson/databind/JavaType;
      46: aload_1
      47: invokeinterface #141,  1          // InterfaceMethod com/fasterxml/jackson/databind/jsonFormatVisitors/JsonFormatVisitorWrapper.getProvider:()Lcom/fasterxml/jackson/databind/SerializerProvider;
      52: invokevirtual #142                // Method _findAndAddDynamic:(Lcom/fasterxml/jackson/databind/ser/impl/PropertySerializerMap;Lcom/fasterxml/jackson/databind/JavaType;Lcom/fasterxml/jackson/databind/SerializerProvider;)Lcom/fasterxml/jackson/databind/JsonSerializer;
      55: astore        4
      57: aload_3
      58: aload         4
      60: aload_0
      61: getfield      #7                  // Field _valueType:Lcom/fasterxml/jackson/databind/JavaType;
      64: invokeinterface #143,  3          // InterfaceMethod com/fasterxml/jackson/databind/jsonFormatVisitors/JsonMapFormatVisitor.valueFormat:(Lcom/fasterxml/jackson/databind/jsonFormatVisitors/JsonFormatVisitable;Lcom/fasterxml/jackson/databind/JavaType;)V
      69: return

  protected final com.fasterxml.jackson.databind.JsonSerializer<java.lang.Object> _findAndAddDynamic(com.fasterxml.jackson.databind.ser.impl.PropertySerializerMap, java.lang.Class<?>, com.fasterxml.jackson.databind.SerializerProvider) throws com.fasterxml.jackson.databind.JsonMappingException;
    Code:
       0: aload_1
       1: aload_2
       2: aload_3
       3: aload_0
       4: getfield      #14                 // Field _property:Lcom/fasterxml/jackson/databind/BeanProperty;
       7: invokevirtual #144                // Method com/fasterxml/jackson/databind/ser/impl/PropertySerializerMap.findAndAddSecondarySerializer:(Ljava/lang/Class;Lcom/fasterxml/jackson/databind/SerializerProvider;Lcom/fasterxml/jackson/databind/BeanProperty;)Lcom/fasterxml/jackson/databind/ser/impl/PropertySerializerMap$SerializerAndMapResult;
      10: astore        4
      12: aload_1
      13: aload         4
      15: getfield      #145                // Field com/fasterxml/jackson/databind/ser/impl/PropertySerializerMap$SerializerAndMapResult.map:Lcom/fasterxml/jackson/databind/ser/impl/PropertySerializerMap;
      18: if_acmpeq     30
      21: aload_0
      22: aload         4
      24: getfield      #145                // Field com/fasterxml/jackson/databind/ser/impl/PropertySerializerMap$SerializerAndMapResult.map:Lcom/fasterxml/jackson/databind/ser/impl/PropertySerializerMap;
      27: putfield      #13                 // Field _dynamicValueSerializers:Lcom/fasterxml/jackson/databind/ser/impl/PropertySerializerMap;
      30: aload         4
      32: getfield      #146                // Field com/fasterxml/jackson/databind/ser/impl/PropertySerializerMap$SerializerAndMapResult.serializer:Lcom/fasterxml/jackson/databind/JsonSerializer;
      35: areturn

  protected final com.fasterxml.jackson.databind.JsonSerializer<java.lang.Object> _findAndAddDynamic(com.fasterxml.jackson.databind.ser.impl.PropertySerializerMap, com.fasterxml.jackson.databind.JavaType, com.fasterxml.jackson.databind.SerializerProvider) throws com.fasterxml.jackson.databind.JsonMappingException;
    Code:
       0: aload_1
       1: aload_2
       2: aload_3
       3: aload_0
       4: getfield      #14                 // Field _property:Lcom/fasterxml/jackson/databind/BeanProperty;
       7: invokevirtual #147                // Method com/fasterxml/jackson/databind/ser/impl/PropertySerializerMap.findAndAddSecondarySerializer:(Lcom/fasterxml/jackson/databind/JavaType;Lcom/fasterxml/jackson/databind/SerializerProvider;Lcom/fasterxml/jackson/databind/BeanProperty;)Lcom/fasterxml/jackson/databind/ser/impl/PropertySerializerMap$SerializerAndMapResult;
      10: astore        4
      12: aload_1
      13: aload         4
      15: getfield      #145                // Field com/fasterxml/jackson/databind/ser/impl/PropertySerializerMap$SerializerAndMapResult.map:Lcom/fasterxml/jackson/databind/ser/impl/PropertySerializerMap;
      18: if_acmpeq     30
      21: aload_0
      22: aload         4
      24: getfield      #145                // Field com/fasterxml/jackson/databind/ser/impl/PropertySerializerMap$SerializerAndMapResult.map:Lcom/fasterxml/jackson/databind/ser/impl/PropertySerializerMap;
      27: putfield      #13                 // Field _dynamicValueSerializers:Lcom/fasterxml/jackson/databind/ser/impl/PropertySerializerMap;
      30: aload         4
      32: getfield      #146                // Field com/fasterxml/jackson/databind/ser/impl/PropertySerializerMap$SerializerAndMapResult.serializer:Lcom/fasterxml/jackson/databind/JsonSerializer;
      35: areturn

  protected java.util.Map<?, ?> _orderEntries(java.util.Map<?, ?>, com.fasterxml.jackson.core.JsonGenerator, com.fasterxml.jackson.databind.SerializerProvider) throws java.io.IOException;
    Code:
       0: aload_1
       1: instanceof    #148                // class java/util/SortedMap
       4: ifeq          9
       7: aload_1
       8: areturn
       9: aload_0
      10: aload_1
      11: invokevirtual #149                // Method _hasNullKey:(Ljava/util/Map;)Z
      14: ifeq          112
      17: new           #150                // class java/util/TreeMap
      20: dup
      21: invokespecial #151                // Method java/util/TreeMap."<init>":()V
      24: astore        4
      26: aload_1
      27: invokeinterface #120,  1          // InterfaceMethod java/util/Map.entrySet:()Ljava/util/Set;
      32: invokeinterface #65,  1           // InterfaceMethod java/util/Set.iterator:()Ljava/util/Iterator;
      37: astore        5
      39: aload         5
      41: invokeinterface #66,  1           // InterfaceMethod java/util/Iterator.hasNext:()Z
      46: ifeq          109
      49: aload         5
      51: invokeinterface #67,  1           // InterfaceMethod java/util/Iterator.next:()Ljava/lang/Object;
      56: checkcast     #121                // class java/util/Map$Entry
      59: astore        6
      61: aload         6
      63: invokeinterface #123,  1          // InterfaceMethod java/util/Map$Entry.getKey:()Ljava/lang/Object;
      68: astore        7
      70: aload         7
      72: ifnonnull     91
      75: aload_0
      76: aload_2
      77: aload_3
      78: aload         6
      80: invokeinterface #122,  1          // InterfaceMethod java/util/Map$Entry.getValue:()Ljava/lang/Object;
      85: invokevirtual #152                // Method _writeNullKeyedEntry:(Lcom/fasterxml/jackson/core/JsonGenerator;Lcom/fasterxml/jackson/databind/SerializerProvider;Ljava/lang/Object;)V
      88: goto          39
      91: aload         4
      93: aload         7
      95: aload         6
      97: invokeinterface #122,  1          // InterfaceMethod java/util/Map$Entry.getValue:()Ljava/lang/Object;
     102: invokevirtual #153                // Method java/util/TreeMap.put:(Ljava/lang/Object;Ljava/lang/Object;)Ljava/lang/Object;
     105: pop
     106: goto          39
     109: aload         4
     111: areturn
     112: new           #150                // class java/util/TreeMap
     115: dup
     116: aload_1
     117: invokespecial #154                // Method java/util/TreeMap."<init>":(Ljava/util/Map;)V
     120: areturn

  protected boolean _hasNullKey(java.util.Map<?, ?>);
    Code:
       0: aload_1
       1: instanceof    #155                // class java/util/HashMap
       4: ifeq          21
       7: aload_1
       8: aconst_null
       9: invokeinterface #156,  2          // InterfaceMethod java/util/Map.containsKey:(Ljava/lang/Object;)Z
      14: ifeq          21
      17: iconst_1
      18: goto          22
      21: iconst_0
      22: ireturn

  protected void _writeNullKeyedEntry(com.fasterxml.jackson.core.JsonGenerator, com.fasterxml.jackson.databind.SerializerProvider, java.lang.Object) throws java.io.IOException;
    Code:
       0: aload_2
       1: aload_0
       2: getfield      #6                  // Field _keyType:Lcom/fasterxml/jackson/databind/JavaType;
       5: aload_0
       6: getfield      #14                 // Field _property:Lcom/fasterxml/jackson/databind/BeanProperty;
       9: invokevirtual #124                // Method com/fasterxml/jackson/databind/SerializerProvider.findNullKeySerializer:(Lcom/fasterxml/jackson/databind/JavaType;Lcom/fasterxml/jackson/databind/BeanProperty;)Lcom/fasterxml/jackson/databind/JsonSerializer;
      12: astore        4
      14: aload_3
      15: ifnonnull     35
      18: aload_0
      19: getfield      #18                 // Field _suppressNulls:Z
      22: ifeq          26
      25: return
      26: aload_2
      27: invokevirtual #131                // Method com/fasterxml/jackson/databind/SerializerProvider.getDefaultNullValueSerializer:()Lcom/fasterxml/jackson/databind/JsonSerializer;
      30: astore        5
      32: goto          94
      35: aload_0
      36: getfield      #11                 // Field _valueSerializer:Lcom/fasterxml/jackson/databind/JsonSerializer;
      39: astore        5
      41: aload         5
      43: ifnonnull     54
      46: aload_0
      47: aload_2
      48: aload_3
      49: invokespecial #100                // Method _findSerializer:(Lcom/fasterxml/jackson/databind/SerializerProvider;Ljava/lang/Object;)Lcom/fasterxml/jackson/databind/JsonSerializer;
      52: astore        5
      54: aload_0
      55: getfield      #17                 // Field _suppressableValue:Ljava/lang/Object;
      58: getstatic     #90                 // Field MARKER_FOR_EMPTY:Ljava/lang/Object;
      61: if_acmpne     75
      64: aload         5
      66: aload_2
      67: aload_3
      68: invokevirtual #98                 // Method com/fasterxml/jackson/databind/JsonSerializer.isEmpty:(Lcom/fasterxml/jackson/databind/SerializerProvider;Ljava/lang/Object;)Z
      71: ifeq          94
      74: return
      75: aload_0
      76: getfield      #17                 // Field _suppressableValue:Ljava/lang/Object;
      79: ifnull        94
      82: aload_0
      83: getfield      #17                 // Field _suppressableValue:Ljava/lang/Object;
      86: aload_3
      87: invokevirtual #99                 // Method java/lang/Object.equals:(Ljava/lang/Object;)Z
      90: ifeq          94
      93: return
      94: aload         4
      96: aconst_null
      97: aload_1
      98: aload_2
      99: invokevirtual #125                // Method com/fasterxml/jackson/databind/JsonSerializer.serialize:(Ljava/lang/Object;Lcom/fasterxml/jackson/core/JsonGenerator;Lcom/fasterxml/jackson/databind/SerializerProvider;)V
     102: aload         5
     104: aload_3
     105: aload_1
     106: aload_2
     107: invokevirtual #125                // Method com/fasterxml/jackson/databind/JsonSerializer.serialize:(Ljava/lang/Object;Lcom/fasterxml/jackson/core/JsonGenerator;Lcom/fasterxml/jackson/databind/SerializerProvider;)V
     110: goto          125
     113: astore        6
     115: aload_0
     116: aload_2
     117: aload         6
     119: aload_3
     120: ldc           #157                // String
     122: invokevirtual #130                // Method wrapAndThrow:(Lcom/fasterxml/jackson/databind/SerializerProvider;Ljava/lang/Throwable;Ljava/lang/Object;Ljava/lang/String;)V
     125: return
    Exception table:
       from    to  target type
          94   110   113   Class java/lang/Exception

  private final com.fasterxml.jackson.databind.JsonSerializer<java.lang.Object> _findSerializer(com.fasterxml.jackson.databind.SerializerProvider, java.lang.Object) throws com.fasterxml.jackson.databind.JsonMappingException;
    Code:
       0: aload_2
       1: invokevirtual #86                 // Method java/lang/Object.getClass:()Ljava/lang/Class;
       4: astore_3
       5: aload_0
       6: getfield      #13                 // Field _dynamicValueSerializers:Lcom/fasterxml/jackson/databind/ser/impl/PropertySerializerMap;
       9: aload_3
      10: invokevirtual #158                // Method com/fasterxml/jackson/databind/ser/impl/PropertySerializerMap.serializerFor:(Ljava/lang/Class;)Lcom/fasterxml/jackson/databind/JsonSerializer;
      13: astore        4
      15: aload         4
      17: ifnull        23
      20: aload         4
      22: areturn
      23: aload_0
      24: getfield      #7                  // Field _valueType:Lcom/fasterxml/jackson/databind/JavaType;
      27: invokevirtual #159                // Method com/fasterxml/jackson/databind/JavaType.hasGenericTypes:()Z
      30: ifeq          52
      33: aload_0
      34: aload_0
      35: getfield      #13                 // Field _dynamicValueSerializers:Lcom/fasterxml/jackson/databind/ser/impl/PropertySerializerMap;
      38: aload_1
      39: aload_0
      40: getfield      #7                  // Field _valueType:Lcom/fasterxml/jackson/databind/JavaType;
      43: aload_3
      44: invokevirtual #160                // Method com/fasterxml/jackson/databind/SerializerProvider.constructSpecializedType:(Lcom/fasterxml/jackson/databind/JavaType;Ljava/lang/Class;)Lcom/fasterxml/jackson/databind/JavaType;
      47: aload_1
      48: invokevirtual #142                // Method _findAndAddDynamic:(Lcom/fasterxml/jackson/databind/ser/impl/PropertySerializerMap;Lcom/fasterxml/jackson/databind/JavaType;Lcom/fasterxml/jackson/databind/SerializerProvider;)Lcom/fasterxml/jackson/databind/JsonSerializer;
      51: areturn
      52: aload_0
      53: aload_0
      54: getfield      #13                 // Field _dynamicValueSerializers:Lcom/fasterxml/jackson/databind/ser/impl/PropertySerializerMap;
      57: aload_3
      58: aload_1
      59: invokevirtual #161                // Method _findAndAddDynamic:(Lcom/fasterxml/jackson/databind/ser/impl/PropertySerializerMap;Ljava/lang/Class;Lcom/fasterxml/jackson/databind/SerializerProvider;)Lcom/fasterxml/jackson/databind/JsonSerializer;
      62: areturn

  public com.fasterxml.jackson.databind.ser.ContainerSerializer _withValueTypeSerializer(com.fasterxml.jackson.databind.jsontype.TypeSerializer);
    Code:
       0: aload_0
       1: aload_1
       2: invokevirtual #162                // Method _withValueTypeSerializer:(Lcom/fasterxml/jackson/databind/jsontype/TypeSerializer;)Lcom/fasterxml/jackson/databind/ser/std/MapSerializer;
       5: areturn

  public boolean hasSingleElement(java.lang.Object);
    Code:
       0: aload_0
       1: aload_1
       2: checkcast     #1                  // class java/util/Map
       5: invokevirtual #163                // Method hasSingleElement:(Ljava/util/Map;)Z
       8: ireturn

  public void serialize(java.lang.Object, com.fasterxml.jackson.core.JsonGenerator, com.fasterxml.jackson.databind.SerializerProvider) throws java.io.IOException;
    Code:
       0: aload_0
       1: aload_1
       2: checkcast     #1                  // class java/util/Map
       5: aload_2
       6: aload_3
       7: invokevirtual #164                // Method serialize:(Ljava/util/Map;Lcom/fasterxml/jackson/core/JsonGenerator;Lcom/fasterxml/jackson/databind/SerializerProvider;)V
      10: return

  public boolean isEmpty(com.fasterxml.jackson.databind.SerializerProvider, java.lang.Object);
    Code:
       0: aload_0
       1: aload_1
       2: aload_2
       3: checkcast     #1                  // class java/util/Map
       6: invokevirtual #165                // Method isEmpty:(Lcom/fasterxml/jackson/databind/SerializerProvider;Ljava/util/Map;)Z
       9: ireturn

  public void serializeWithType(java.lang.Object, com.fasterxml.jackson.core.JsonGenerator, com.fasterxml.jackson.databind.SerializerProvider, com.fasterxml.jackson.databind.jsontype.TypeSerializer) throws java.io.IOException;
    Code:
       0: aload_0
       1: aload_1
       2: checkcast     #1                  // class java/util/Map
       5: aload_2
       6: aload_3
       7: aload         4
       9: invokevirtual #166                // Method serializeWithType:(Ljava/util/Map;Lcom/fasterxml/jackson/core/JsonGenerator;Lcom/fasterxml/jackson/databind/SerializerProvider;Lcom/fasterxml/jackson/databind/jsontype/TypeSerializer;)V
      12: return

  public com.fasterxml.jackson.databind.JsonSerializer withFilterId(java.lang.Object);
    Code:
       0: aload_0
       1: aload_1
       2: invokevirtual #41                 // Method withFilterId:(Ljava/lang/Object;)Lcom/fasterxml/jackson/databind/ser/std/MapSerializer;
       5: areturn

  static {};
    Code:
       0: invokestatic  #36                 // Method com/fasterxml/jackson/databind/type/TypeFactory.unknownType:()Lcom/fasterxml/jackson/databind/JavaType;
       3: putstatic     #32                 // Field UNSPECIFIED_TYPE:Lcom/fasterxml/jackson/databind/JavaType;
       6: getstatic     #167                // Field com/fasterxml/jackson/annotation/JsonInclude$Include.NON_EMPTY:Lcom/fasterxml/jackson/annotation/JsonInclude$Include;
       9: putstatic     #90                 // Field MARKER_FOR_EMPTY:Ljava/lang/Object;
      12: return
}
