Compiled from "WithLayoutListAppender.java"
public class ch.qos.logback.classic.helpers.WithLayoutListAppender extends ch.qos.logback.core.AppenderBase<ch.qos.logback.classic.spi.ILoggingEvent> {
  public java.util.List<java.lang.String> list;

  java.lang.String pattern;

  ch.qos.logback.classic.PatternLayout patternLayout;

  public ch.qos.logback.classic.helpers.WithLayoutListAppender();
    Code:
       0: aload_0
       1: invokespecial #1                  // Method ch/qos/logback/core/AppenderBase."<init>":()V
       4: aload_0
       5: new           #7                  // class java/util/ArrayList
       8: dup
       9: invokespecial #9                  // Method java/util/ArrayList."<init>":()V
      12: putfield      #10                 // Field list:Ljava/util/List;
      15: return

  public void start();
    Code:
       0: aload_0
       1: getfield      #16                 // Field pattern:Ljava/lang/String;
       4: ifnonnull     14
       7: aload_0
       8: ldc           #20                 // String null pattern disallowed
      10: invokevirtual #22                 // Method addError:(Ljava/lang/String;)V
      13: return
      14: aload_0
      15: new           #26                 // class ch/qos/logback/classic/PatternLayout
      18: dup
      19: invokespecial #28                 // Method ch/qos/logback/classic/PatternLayout."<init>":()V
      22: putfield      #29                 // Field patternLayout:Lch/qos/logback/classic/PatternLayout;
      25: aload_0
      26: getfield      #29                 // Field patternLayout:Lch/qos/logback/classic/PatternLayout;
      29: aload_0
      30: getfield      #33                 // Field context:Lch/qos/logback/core/Context;
      33: invokevirtual #37                 // Method ch/qos/logback/classic/PatternLayout.setContext:(Lch/qos/logback/core/Context;)V
      36: aload_0
      37: getfield      #29                 // Field patternLayout:Lch/qos/logback/classic/PatternLayout;
      40: aload_0
      41: getfield      #16                 // Field pattern:Ljava/lang/String;
      44: invokevirtual #41                 // Method ch/qos/logback/classic/PatternLayout.setPattern:(Ljava/lang/String;)V
      47: aload_0
      48: getfield      #29                 // Field patternLayout:Lch/qos/logback/classic/PatternLayout;
      51: invokevirtual #44                 // Method ch/qos/logback/classic/PatternLayout.start:()V
      54: aload_0
      55: getfield      #29                 // Field patternLayout:Lch/qos/logback/classic/PatternLayout;
      58: invokevirtual #47                 // Method ch/qos/logback/classic/PatternLayout.isStarted:()Z
      61: ifeq          68
      64: aload_0
      65: invokespecial #51                 // Method ch/qos/logback/core/AppenderBase.start:()V
      68: return

  protected void append(ch.qos.logback.classic.spi.ILoggingEvent);
    Code:
       0: aload_0
       1: getfield      #29                 // Field patternLayout:Lch/qos/logback/classic/PatternLayout;
       4: aload_1
       5: invokevirtual #52                 // Method ch/qos/logback/classic/PatternLayout.doLayout:(Lch/qos/logback/classic/spi/ILoggingEvent;)Ljava/lang/String;
       8: astore_2
       9: aload_0
      10: getfield      #10                 // Field list:Ljava/util/List;
      13: aload_2
      14: invokeinterface #56,  2           // InterfaceMethod java/util/List.add:(Ljava/lang/Object;)Z
      19: pop
      20: return

  public java.lang.String getPattern();
    Code:
       0: aload_0
       1: getfield      #16                 // Field pattern:Ljava/lang/String;
       4: areturn

  public void setPattern(java.lang.String);
    Code:
       0: aload_0
       1: aload_1
       2: putfield      #16                 // Field pattern:Ljava/lang/String;
       5: return

  protected void append(java.lang.Object);
    Code:
       0: aload_0
       1: aload_1
       2: checkcast     #62                 // class ch/qos/logback/classic/spi/ILoggingEvent
       5: invokevirtual #64                 // Method append:(Lch/qos/logback/classic/spi/ILoggingEvent;)V
       8: return
}
