Compiled from "WorkflowExecutionStartedEventAttributes.java"
public class com.amazonaws.services.simpleworkflow.model.WorkflowExecutionStartedEventAttributes implements java.io.Serializable,java.lang.Cloneable {
  private java.lang.String input;

  private java.lang.String executionStartToCloseTimeout;

  private java.lang.String taskStartToCloseTimeout;

  private java.lang.String childPolicy;

  private com.amazonaws.services.simpleworkflow.model.TaskList taskList;

  private com.amazonaws.services.simpleworkflow.model.WorkflowType workflowType;

  private java.util.List<java.lang.String> tagList;

  private java.lang.String taskPriority;

  private java.lang.String continuedExecutionRunId;

  private com.amazonaws.services.simpleworkflow.model.WorkflowExecution parentWorkflowExecution;

  private java.lang.Long parentInitiatedEventId;

  private java.lang.String lambdaRole;

  public com.amazonaws.services.simpleworkflow.model.WorkflowExecutionStartedEventAttributes();
    Code:
       0: aload_0
       1: invokespecial #1                  // Method java/lang/Object."<init>":()V
       4: return

  public void setInput(java.lang.String);
    Code:
       0: aload_0
       1: aload_1
       2: putfield      #2                  // Field input:Ljava/lang/String;
       5: return

  public java.lang.String getInput();
    Code:
       0: aload_0
       1: getfield      #2                  // Field input:Ljava/lang/String;
       4: areturn

  public com.amazonaws.services.simpleworkflow.model.WorkflowExecutionStartedEventAttributes withInput(java.lang.String);
    Code:
       0: aload_0
       1: aload_1
       2: invokevirtual #3                  // Method setInput:(Ljava/lang/String;)V
       5: aload_0
       6: areturn

  public void setExecutionStartToCloseTimeout(java.lang.String);
    Code:
       0: aload_0
       1: aload_1
       2: putfield      #4                  // Field executionStartToCloseTimeout:Ljava/lang/String;
       5: return

  public java.lang.String getExecutionStartToCloseTimeout();
    Code:
       0: aload_0
       1: getfield      #4                  // Field executionStartToCloseTimeout:Ljava/lang/String;
       4: areturn

  public com.amazonaws.services.simpleworkflow.model.WorkflowExecutionStartedEventAttributes withExecutionStartToCloseTimeout(java.lang.String);
    Code:
       0: aload_0
       1: aload_1
       2: invokevirtual #5                  // Method setExecutionStartToCloseTimeout:(Ljava/lang/String;)V
       5: aload_0
       6: areturn

  public void setTaskStartToCloseTimeout(java.lang.String);
    Code:
       0: aload_0
       1: aload_1
       2: putfield      #6                  // Field taskStartToCloseTimeout:Ljava/lang/String;
       5: return

  public java.lang.String getTaskStartToCloseTimeout();
    Code:
       0: aload_0
       1: getfield      #6                  // Field taskStartToCloseTimeout:Ljava/lang/String;
       4: areturn

  public com.amazonaws.services.simpleworkflow.model.WorkflowExecutionStartedEventAttributes withTaskStartToCloseTimeout(java.lang.String);
    Code:
       0: aload_0
       1: aload_1
       2: invokevirtual #7                  // Method setTaskStartToCloseTimeout:(Ljava/lang/String;)V
       5: aload_0
       6: areturn

  public void setChildPolicy(java.lang.String);
    Code:
       0: aload_0
       1: aload_1
       2: putfield      #8                  // Field childPolicy:Ljava/lang/String;
       5: return

  public java.lang.String getChildPolicy();
    Code:
       0: aload_0
       1: getfield      #8                  // Field childPolicy:Ljava/lang/String;
       4: areturn

  public com.amazonaws.services.simpleworkflow.model.WorkflowExecutionStartedEventAttributes withChildPolicy(java.lang.String);
    Code:
       0: aload_0
       1: aload_1
       2: invokevirtual #9                  // Method setChildPolicy:(Ljava/lang/String;)V
       5: aload_0
       6: areturn

  public void setChildPolicy(com.amazonaws.services.simpleworkflow.model.ChildPolicy);
    Code:
       0: aload_0
       1: aload_1
       2: invokevirtual #10                 // Method com/amazonaws/services/simpleworkflow/model/ChildPolicy.toString:()Ljava/lang/String;
       5: putfield      #8                  // Field childPolicy:Ljava/lang/String;
       8: return

  public com.amazonaws.services.simpleworkflow.model.WorkflowExecutionStartedEventAttributes withChildPolicy(com.amazonaws.services.simpleworkflow.model.ChildPolicy);
    Code:
       0: aload_0
       1: aload_1
       2: invokevirtual #11                 // Method setChildPolicy:(Lcom/amazonaws/services/simpleworkflow/model/ChildPolicy;)V
       5: aload_0
       6: areturn

  public void setTaskList(com.amazonaws.services.simpleworkflow.model.TaskList);
    Code:
       0: aload_0
       1: aload_1
       2: putfield      #12                 // Field taskList:Lcom/amazonaws/services/simpleworkflow/model/TaskList;
       5: return

  public com.amazonaws.services.simpleworkflow.model.TaskList getTaskList();
    Code:
       0: aload_0
       1: getfield      #12                 // Field taskList:Lcom/amazonaws/services/simpleworkflow/model/TaskList;
       4: areturn

  public com.amazonaws.services.simpleworkflow.model.WorkflowExecutionStartedEventAttributes withTaskList(com.amazonaws.services.simpleworkflow.model.TaskList);
    Code:
       0: aload_0
       1: aload_1
       2: invokevirtual #13                 // Method setTaskList:(Lcom/amazonaws/services/simpleworkflow/model/TaskList;)V
       5: aload_0
       6: areturn

  public void setWorkflowType(com.amazonaws.services.simpleworkflow.model.WorkflowType);
    Code:
       0: aload_0
       1: aload_1
       2: putfield      #14                 // Field workflowType:Lcom/amazonaws/services/simpleworkflow/model/WorkflowType;
       5: return

  public com.amazonaws.services.simpleworkflow.model.WorkflowType getWorkflowType();
    Code:
       0: aload_0
       1: getfield      #14                 // Field workflowType:Lcom/amazonaws/services/simpleworkflow/model/WorkflowType;
       4: areturn

  public com.amazonaws.services.simpleworkflow.model.WorkflowExecutionStartedEventAttributes withWorkflowType(com.amazonaws.services.simpleworkflow.model.WorkflowType);
    Code:
       0: aload_0
       1: aload_1
       2: invokevirtual #15                 // Method setWorkflowType:(Lcom/amazonaws/services/simpleworkflow/model/WorkflowType;)V
       5: aload_0
       6: areturn

  public java.util.List<java.lang.String> getTagList();
    Code:
       0: aload_0
       1: getfield      #16                 // Field tagList:Ljava/util/List;
       4: areturn

  public void setTagList(java.util.Collection<java.lang.String>);
    Code:
       0: aload_1
       1: ifnonnull     10
       4: aload_0
       5: aconst_null
       6: putfield      #16                 // Field tagList:Ljava/util/List;
       9: return
      10: aload_0
      11: new           #17                 // class java/util/ArrayList
      14: dup
      15: aload_1
      16: invokespecial #18                 // Method java/util/ArrayList."<init>":(Ljava/util/Collection;)V
      19: putfield      #16                 // Field tagList:Ljava/util/List;
      22: return

  public com.amazonaws.services.simpleworkflow.model.WorkflowExecutionStartedEventAttributes withTagList(java.lang.String...);
    Code:
       0: aload_0
       1: getfield      #16                 // Field tagList:Ljava/util/List;
       4: ifnonnull     20
       7: aload_0
       8: new           #17                 // class java/util/ArrayList
      11: dup
      12: aload_1
      13: arraylength
      14: invokespecial #19                 // Method java/util/ArrayList."<init>":(I)V
      17: invokevirtual #20                 // Method setTagList:(Ljava/util/Collection;)V
      20: aload_1
      21: astore_2
      22: aload_2
      23: arraylength
      24: istore_3
      25: iconst_0
      26: istore        4
      28: iload         4
      30: iload_3
      31: if_icmpge     58
      34: aload_2
      35: iload         4
      37: aaload
      38: astore        5
      40: aload_0
      41: getfield      #16                 // Field tagList:Ljava/util/List;
      44: aload         5
      46: invokeinterface #21,  2           // InterfaceMethod java/util/List.add:(Ljava/lang/Object;)Z
      51: pop
      52: iinc          4, 1
      55: goto          28
      58: aload_0
      59: areturn

  public com.amazonaws.services.simpleworkflow.model.WorkflowExecutionStartedEventAttributes withTagList(java.util.Collection<java.lang.String>);
    Code:
       0: aload_0
       1: aload_1
       2: invokevirtual #20                 // Method setTagList:(Ljava/util/Collection;)V
       5: aload_0
       6: areturn

  public void setTaskPriority(java.lang.String);
    Code:
       0: aload_0
       1: aload_1
       2: putfield      #22                 // Field taskPriority:Ljava/lang/String;
       5: return

  public java.lang.String getTaskPriority();
    Code:
       0: aload_0
       1: getfield      #22                 // Field taskPriority:Ljava/lang/String;
       4: areturn

  public com.amazonaws.services.simpleworkflow.model.WorkflowExecutionStartedEventAttributes withTaskPriority(java.lang.String);
    Code:
       0: aload_0
       1: aload_1
       2: invokevirtual #23                 // Method setTaskPriority:(Ljava/lang/String;)V
       5: aload_0
       6: areturn

  public void setContinuedExecutionRunId(java.lang.String);
    Code:
       0: aload_0
       1: aload_1
       2: putfield      #24                 // Field continuedExecutionRunId:Ljava/lang/String;
       5: return

  public java.lang.String getContinuedExecutionRunId();
    Code:
       0: aload_0
       1: getfield      #24                 // Field continuedExecutionRunId:Ljava/lang/String;
       4: areturn

  public com.amazonaws.services.simpleworkflow.model.WorkflowExecutionStartedEventAttributes withContinuedExecutionRunId(java.lang.String);
    Code:
       0: aload_0
       1: aload_1
       2: invokevirtual #25                 // Method setContinuedExecutionRunId:(Ljava/lang/String;)V
       5: aload_0
       6: areturn

  public void setParentWorkflowExecution(com.amazonaws.services.simpleworkflow.model.WorkflowExecution);
    Code:
       0: aload_0
       1: aload_1
       2: putfield      #26                 // Field parentWorkflowExecution:Lcom/amazonaws/services/simpleworkflow/model/WorkflowExecution;
       5: return

  public com.amazonaws.services.simpleworkflow.model.WorkflowExecution getParentWorkflowExecution();
    Code:
       0: aload_0
       1: getfield      #26                 // Field parentWorkflowExecution:Lcom/amazonaws/services/simpleworkflow/model/WorkflowExecution;
       4: areturn

  public com.amazonaws.services.simpleworkflow.model.WorkflowExecutionStartedEventAttributes withParentWorkflowExecution(com.amazonaws.services.simpleworkflow.model.WorkflowExecution);
    Code:
       0: aload_0
       1: aload_1
       2: invokevirtual #27                 // Method setParentWorkflowExecution:(Lcom/amazonaws/services/simpleworkflow/model/WorkflowExecution;)V
       5: aload_0
       6: areturn

  public void setParentInitiatedEventId(java.lang.Long);
    Code:
       0: aload_0
       1: aload_1
       2: putfield      #28                 // Field parentInitiatedEventId:Ljava/lang/Long;
       5: return

  public java.lang.Long getParentInitiatedEventId();
    Code:
       0: aload_0
       1: getfield      #28                 // Field parentInitiatedEventId:Ljava/lang/Long;
       4: areturn

  public com.amazonaws.services.simpleworkflow.model.WorkflowExecutionStartedEventAttributes withParentInitiatedEventId(java.lang.Long);
    Code:
       0: aload_0
       1: aload_1
       2: invokevirtual #29                 // Method setParentInitiatedEventId:(Ljava/lang/Long;)V
       5: aload_0
       6: areturn

  public void setLambdaRole(java.lang.String);
    Code:
       0: aload_0
       1: aload_1
       2: putfield      #30                 // Field lambdaRole:Ljava/lang/String;
       5: return

  public java.lang.String getLambdaRole();
    Code:
       0: aload_0
       1: getfield      #30                 // Field lambdaRole:Ljava/lang/String;
       4: areturn

  public com.amazonaws.services.simpleworkflow.model.WorkflowExecutionStartedEventAttributes withLambdaRole(java.lang.String);
    Code:
       0: aload_0
       1: aload_1
       2: invokevirtual #31                 // Method setLambdaRole:(Ljava/lang/String;)V
       5: aload_0
       6: areturn

  public java.lang.String toString();
    Code:
       0: new           #32                 // class java/lang/StringBuilder
       3: dup
       4: invokespecial #33                 // Method java/lang/StringBuilder."<init>":()V
       7: astore_1
       8: aload_1
       9: ldc           #34                 // String {
      11: invokevirtual #35                 // Method java/lang/StringBuilder.append:(Ljava/lang/String;)Ljava/lang/StringBuilder;
      14: pop
      15: aload_0
      16: invokevirtual #36                 // Method getInput:()Ljava/lang/String;
      19: ifnull        54
      22: aload_1
      23: new           #32                 // class java/lang/StringBuilder
      26: dup
      27: invokespecial #33                 // Method java/lang/StringBuilder."<init>":()V
      30: ldc           #37                 // String Input:
      32: invokevirtual #35                 // Method java/lang/StringBuilder.append:(Ljava/lang/String;)Ljava/lang/StringBuilder;
      35: aload_0
      36: invokevirtual #36                 // Method getInput:()Ljava/lang/String;
      39: invokevirtual #35                 // Method java/lang/StringBuilder.append:(Ljava/lang/String;)Ljava/lang/StringBuilder;
      42: ldc           #38                 // String ,
      44: invokevirtual #35                 // Method java/lang/StringBuilder.append:(Ljava/lang/String;)Ljava/lang/StringBuilder;
      47: invokevirtual #39                 // Method java/lang/StringBuilder.toString:()Ljava/lang/String;
      50: invokevirtual #35                 // Method java/lang/StringBuilder.append:(Ljava/lang/String;)Ljava/lang/StringBuilder;
      53: pop
      54: aload_0
      55: invokevirtual #40                 // Method getExecutionStartToCloseTimeout:()Ljava/lang/String;
      58: ifnull        93
      61: aload_1
      62: new           #32                 // class java/lang/StringBuilder
      65: dup
      66: invokespecial #33                 // Method java/lang/StringBuilder."<init>":()V
      69: ldc           #41                 // String ExecutionStartToCloseTimeout:
      71: invokevirtual #35                 // Method java/lang/StringBuilder.append:(Ljava/lang/String;)Ljava/lang/StringBuilder;
      74: aload_0
      75: invokevirtual #40                 // Method getExecutionStartToCloseTimeout:()Ljava/lang/String;
      78: invokevirtual #35                 // Method java/lang/StringBuilder.append:(Ljava/lang/String;)Ljava/lang/StringBuilder;
      81: ldc           #38                 // String ,
      83: invokevirtual #35                 // Method java/lang/StringBuilder.append:(Ljava/lang/String;)Ljava/lang/StringBuilder;
      86: invokevirtual #39                 // Method java/lang/StringBuilder.toString:()Ljava/lang/String;
      89: invokevirtual #35                 // Method java/lang/StringBuilder.append:(Ljava/lang/String;)Ljava/lang/StringBuilder;
      92: pop
      93: aload_0
      94: invokevirtual #42                 // Method getTaskStartToCloseTimeout:()Ljava/lang/String;
      97: ifnull        132
     100: aload_1
     101: new           #32                 // class java/lang/StringBuilder
     104: dup
     105: invokespecial #33                 // Method java/lang/StringBuilder."<init>":()V
     108: ldc           #43                 // String TaskStartToCloseTimeout:
     110: invokevirtual #35                 // Method java/lang/StringBuilder.append:(Ljava/lang/String;)Ljava/lang/StringBuilder;
     113: aload_0
     114: invokevirtual #42                 // Method getTaskStartToCloseTimeout:()Ljava/lang/String;
     117: invokevirtual #35                 // Method java/lang/StringBuilder.append:(Ljava/lang/String;)Ljava/lang/StringBuilder;
     120: ldc           #38                 // String ,
     122: invokevirtual #35                 // Method java/lang/StringBuilder.append:(Ljava/lang/String;)Ljava/lang/StringBuilder;
     125: invokevirtual #39                 // Method java/lang/StringBuilder.toString:()Ljava/lang/String;
     128: invokevirtual #35                 // Method java/lang/StringBuilder.append:(Ljava/lang/String;)Ljava/lang/StringBuilder;
     131: pop
     132: aload_0
     133: invokevirtual #44                 // Method getChildPolicy:()Ljava/lang/String;
     136: ifnull        171
     139: aload_1
     140: new           #32                 // class java/lang/StringBuilder
     143: dup
     144: invokespecial #33                 // Method java/lang/StringBuilder."<init>":()V
     147: ldc           #45                 // String ChildPolicy:
     149: invokevirtual #35                 // Method java/lang/StringBuilder.append:(Ljava/lang/String;)Ljava/lang/StringBuilder;
     152: aload_0
     153: invokevirtual #44                 // Method getChildPolicy:()Ljava/lang/String;
     156: invokevirtual #35                 // Method java/lang/StringBuilder.append:(Ljava/lang/String;)Ljava/lang/StringBuilder;
     159: ldc           #38                 // String ,
     161: invokevirtual #35                 // Method java/lang/StringBuilder.append:(Ljava/lang/String;)Ljava/lang/StringBuilder;
     164: invokevirtual #39                 // Method java/lang/StringBuilder.toString:()Ljava/lang/String;
     167: invokevirtual #35                 // Method java/lang/StringBuilder.append:(Ljava/lang/String;)Ljava/lang/StringBuilder;
     170: pop
     171: aload_0
     172: invokevirtual #46                 // Method getTaskList:()Lcom/amazonaws/services/simpleworkflow/model/TaskList;
     175: ifnull        210
     178: aload_1
     179: new           #32                 // class java/lang/StringBuilder
     182: dup
     183: invokespecial #33                 // Method java/lang/StringBuilder."<init>":()V
     186: ldc           #47                 // String TaskList:
     188: invokevirtual #35                 // Method java/lang/StringBuilder.append:(Ljava/lang/String;)Ljava/lang/StringBuilder;
     191: aload_0
     192: invokevirtual #46                 // Method getTaskList:()Lcom/amazonaws/services/simpleworkflow/model/TaskList;
     195: invokevirtual #48                 // Method java/lang/StringBuilder.append:(Ljava/lang/Object;)Ljava/lang/StringBuilder;
     198: ldc           #38                 // String ,
     200: invokevirtual #35                 // Method java/lang/StringBuilder.append:(Ljava/lang/String;)Ljava/lang/StringBuilder;
     203: invokevirtual #39                 // Method java/lang/StringBuilder.toString:()Ljava/lang/String;
     206: invokevirtual #35                 // Method java/lang/StringBuilder.append:(Ljava/lang/String;)Ljava/lang/StringBuilder;
     209: pop
     210: aload_0
     211: invokevirtual #49                 // Method getWorkflowType:()Lcom/amazonaws/services/simpleworkflow/model/WorkflowType;
     214: ifnull        249
     217: aload_1
     218: new           #32                 // class java/lang/StringBuilder
     221: dup
     222: invokespecial #33                 // Method java/lang/StringBuilder."<init>":()V
     225: ldc           #50                 // String WorkflowType:
     227: invokevirtual #35                 // Method java/lang/StringBuilder.append:(Ljava/lang/String;)Ljava/lang/StringBuilder;
     230: aload_0
     231: invokevirtual #49                 // Method getWorkflowType:()Lcom/amazonaws/services/simpleworkflow/model/WorkflowType;
     234: invokevirtual #48                 // Method java/lang/StringBuilder.append:(Ljava/lang/Object;)Ljava/lang/StringBuilder;
     237: ldc           #38                 // String ,
     239: invokevirtual #35                 // Method java/lang/StringBuilder.append:(Ljava/lang/String;)Ljava/lang/StringBuilder;
     242: invokevirtual #39                 // Method java/lang/StringBuilder.toString:()Ljava/lang/String;
     245: invokevirtual #35                 // Method java/lang/StringBuilder.append:(Ljava/lang/String;)Ljava/lang/StringBuilder;
     248: pop
     249: aload_0
     250: invokevirtual #51                 // Method getTagList:()Ljava/util/List;
     253: ifnull        288
     256: aload_1
     257: new           #32                 // class java/lang/StringBuilder
     260: dup
     261: invokespecial #33                 // Method java/lang/StringBuilder."<init>":()V
     264: ldc           #52                 // String TagList:
     266: invokevirtual #35                 // Method java/lang/StringBuilder.append:(Ljava/lang/String;)Ljava/lang/StringBuilder;
     269: aload_0
     270: invokevirtual #51                 // Method getTagList:()Ljava/util/List;
     273: invokevirtual #48                 // Method java/lang/StringBuilder.append:(Ljava/lang/Object;)Ljava/lang/StringBuilder;
     276: ldc           #38                 // String ,
     278: invokevirtual #35                 // Method java/lang/StringBuilder.append:(Ljava/lang/String;)Ljava/lang/StringBuilder;
     281: invokevirtual #39                 // Method java/lang/StringBuilder.toString:()Ljava/lang/String;
     284: invokevirtual #35                 // Method java/lang/StringBuilder.append:(Ljava/lang/String;)Ljava/lang/StringBuilder;
     287: pop
     288: aload_0
     289: invokevirtual #53                 // Method getTaskPriority:()Ljava/lang/String;
     292: ifnull        327
     295: aload_1
     296: new           #32                 // class java/lang/StringBuilder
     299: dup
     300: invokespecial #33                 // Method java/lang/StringBuilder."<init>":()V
     303: ldc           #54                 // String TaskPriority:
     305: invokevirtual #35                 // Method java/lang/StringBuilder.append:(Ljava/lang/String;)Ljava/lang/StringBuilder;
     308: aload_0
     309: invokevirtual #53                 // Method getTaskPriority:()Ljava/lang/String;
     312: invokevirtual #35                 // Method java/lang/StringBuilder.append:(Ljava/lang/String;)Ljava/lang/StringBuilder;
     315: ldc           #38                 // String ,
     317: invokevirtual #35                 // Method java/lang/StringBuilder.append:(Ljava/lang/String;)Ljava/lang/StringBuilder;
     320: invokevirtual #39                 // Method java/lang/StringBuilder.toString:()Ljava/lang/String;
     323: invokevirtual #35                 // Method java/lang/StringBuilder.append:(Ljava/lang/String;)Ljava/lang/StringBuilder;
     326: pop
     327: aload_0
     328: invokevirtual #55                 // Method getContinuedExecutionRunId:()Ljava/lang/String;
     331: ifnull        366
     334: aload_1
     335: new           #32                 // class java/lang/StringBuilder
     338: dup
     339: invokespecial #33                 // Method java/lang/StringBuilder."<init>":()V
     342: ldc           #56                 // String ContinuedExecutionRunId:
     344: invokevirtual #35                 // Method java/lang/StringBuilder.append:(Ljava/lang/String;)Ljava/lang/StringBuilder;
     347: aload_0
     348: invokevirtual #55                 // Method getContinuedExecutionRunId:()Ljava/lang/String;
     351: invokevirtual #35                 // Method java/lang/StringBuilder.append:(Ljava/lang/String;)Ljava/lang/StringBuilder;
     354: ldc           #38                 // String ,
     356: invokevirtual #35                 // Method java/lang/StringBuilder.append:(Ljava/lang/String;)Ljava/lang/StringBuilder;
     359: invokevirtual #39                 // Method java/lang/StringBuilder.toString:()Ljava/lang/String;
     362: invokevirtual #35                 // Method java/lang/StringBuilder.append:(Ljava/lang/String;)Ljava/lang/StringBuilder;
     365: pop
     366: aload_0
     367: invokevirtual #57                 // Method getParentWorkflowExecution:()Lcom/amazonaws/services/simpleworkflow/model/WorkflowExecution;
     370: ifnull        405
     373: aload_1
     374: new           #32                 // class java/lang/StringBuilder
     377: dup
     378: invokespecial #33                 // Method java/lang/StringBuilder."<init>":()V
     381: ldc           #58                 // String ParentWorkflowExecution:
     383: invokevirtual #35                 // Method java/lang/StringBuilder.append:(Ljava/lang/String;)Ljava/lang/StringBuilder;
     386: aload_0
     387: invokevirtual #57                 // Method getParentWorkflowExecution:()Lcom/amazonaws/services/simpleworkflow/model/WorkflowExecution;
     390: invokevirtual #48                 // Method java/lang/StringBuilder.append:(Ljava/lang/Object;)Ljava/lang/StringBuilder;
     393: ldc           #38                 // String ,
     395: invokevirtual #35                 // Method java/lang/StringBuilder.append:(Ljava/lang/String;)Ljava/lang/StringBuilder;
     398: invokevirtual #39                 // Method java/lang/StringBuilder.toString:()Ljava/lang/String;
     401: invokevirtual #35                 // Method java/lang/StringBuilder.append:(Ljava/lang/String;)Ljava/lang/StringBuilder;
     404: pop
     405: aload_0
     406: invokevirtual #59                 // Method getParentInitiatedEventId:()Ljava/lang/Long;
     409: ifnull        444
     412: aload_1
     413: new           #32                 // class java/lang/StringBuilder
     416: dup
     417: invokespecial #33                 // Method java/lang/StringBuilder."<init>":()V
     420: ldc           #60                 // String ParentInitiatedEventId:
     422: invokevirtual #35                 // Method java/lang/StringBuilder.append:(Ljava/lang/String;)Ljava/lang/StringBuilder;
     425: aload_0
     426: invokevirtual #59                 // Method getParentInitiatedEventId:()Ljava/lang/Long;
     429: invokevirtual #48                 // Method java/lang/StringBuilder.append:(Ljava/lang/Object;)Ljava/lang/StringBuilder;
     432: ldc           #38                 // String ,
     434: invokevirtual #35                 // Method java/lang/StringBuilder.append:(Ljava/lang/String;)Ljava/lang/StringBuilder;
     437: invokevirtual #39                 // Method java/lang/StringBuilder.toString:()Ljava/lang/String;
     440: invokevirtual #35                 // Method java/lang/StringBuilder.append:(Ljava/lang/String;)Ljava/lang/StringBuilder;
     443: pop
     444: aload_0
     445: invokevirtual #61                 // Method getLambdaRole:()Ljava/lang/String;
     448: ifnull        478
     451: aload_1
     452: new           #32                 // class java/lang/StringBuilder
     455: dup
     456: invokespecial #33                 // Method java/lang/StringBuilder."<init>":()V
     459: ldc           #62                 // String LambdaRole:
     461: invokevirtual #35                 // Method java/lang/StringBuilder.append:(Ljava/lang/String;)Ljava/lang/StringBuilder;
     464: aload_0
     465: invokevirtual #61                 // Method getLambdaRole:()Ljava/lang/String;
     468: invokevirtual #35                 // Method java/lang/StringBuilder.append:(Ljava/lang/String;)Ljava/lang/StringBuilder;
     471: invokevirtual #39                 // Method java/lang/StringBuilder.toString:()Ljava/lang/String;
     474: invokevirtual #35                 // Method java/lang/StringBuilder.append:(Ljava/lang/String;)Ljava/lang/StringBuilder;
     477: pop
     478: aload_1
     479: ldc           #63                 // String }
     481: invokevirtual #35                 // Method java/lang/StringBuilder.append:(Ljava/lang/String;)Ljava/lang/StringBuilder;
     484: pop
     485: aload_1
     486: invokevirtual #39                 // Method java/lang/StringBuilder.toString:()Ljava/lang/String;
     489: areturn

  public boolean equals(java.lang.Object);
    Code:
       0: aload_0
       1: aload_1
       2: if_acmpne     7
       5: iconst_1
       6: ireturn
       7: aload_1
       8: ifnonnull     13
      11: iconst_0
      12: ireturn
      13: aload_1
      14: instanceof    #64                 // class com/amazonaws/services/simpleworkflow/model/WorkflowExecutionStartedEventAttributes
      17: ifne          22
      20: iconst_0
      21: ireturn
      22: aload_1
      23: checkcast     #64                 // class com/amazonaws/services/simpleworkflow/model/WorkflowExecutionStartedEventAttributes
      26: astore_2
      27: aload_2
      28: invokevirtual #36                 // Method getInput:()Ljava/lang/String;
      31: ifnonnull     38
      34: iconst_1
      35: goto          39
      38: iconst_0
      39: aload_0
      40: invokevirtual #36                 // Method getInput:()Ljava/lang/String;
      43: ifnonnull     50
      46: iconst_1
      47: goto          51
      50: iconst_0
      51: ixor
      52: ifeq          57
      55: iconst_0
      56: ireturn
      57: aload_2
      58: invokevirtual #36                 // Method getInput:()Ljava/lang/String;
      61: ifnull        80
      64: aload_2
      65: invokevirtual #36                 // Method getInput:()Ljava/lang/String;
      68: aload_0
      69: invokevirtual #36                 // Method getInput:()Ljava/lang/String;
      72: invokevirtual #65                 // Method java/lang/String.equals:(Ljava/lang/Object;)Z
      75: ifne          80
      78: iconst_0
      79: ireturn
      80: aload_2
      81: invokevirtual #40                 // Method getExecutionStartToCloseTimeout:()Ljava/lang/String;
      84: ifnonnull     91
      87: iconst_1
      88: goto          92
      91: iconst_0
      92: aload_0
      93: invokevirtual #40                 // Method getExecutionStartToCloseTimeout:()Ljava/lang/String;
      96: ifnonnull     103
      99: iconst_1
     100: goto          104
     103: iconst_0
     104: ixor
     105: ifeq          110
     108: iconst_0
     109: ireturn
     110: aload_2
     111: invokevirtual #40                 // Method getExecutionStartToCloseTimeout:()Ljava/lang/String;
     114: ifnull        133
     117: aload_2
     118: invokevirtual #40                 // Method getExecutionStartToCloseTimeout:()Ljava/lang/String;
     121: aload_0
     122: invokevirtual #40                 // Method getExecutionStartToCloseTimeout:()Ljava/lang/String;
     125: invokevirtual #65                 // Method java/lang/String.equals:(Ljava/lang/Object;)Z
     128: ifne          133
     131: iconst_0
     132: ireturn
     133: aload_2
     134: invokevirtual #42                 // Method getTaskStartToCloseTimeout:()Ljava/lang/String;
     137: ifnonnull     144
     140: iconst_1
     141: goto          145
     144: iconst_0
     145: aload_0
     146: invokevirtual #42                 // Method getTaskStartToCloseTimeout:()Ljava/lang/String;
     149: ifnonnull     156
     152: iconst_1
     153: goto          157
     156: iconst_0
     157: ixor
     158: ifeq          163
     161: iconst_0
     162: ireturn
     163: aload_2
     164: invokevirtual #42                 // Method getTaskStartToCloseTimeout:()Ljava/lang/String;
     167: ifnull        186
     170: aload_2
     171: invokevirtual #42                 // Method getTaskStartToCloseTimeout:()Ljava/lang/String;
     174: aload_0
     175: invokevirtual #42                 // Method getTaskStartToCloseTimeout:()Ljava/lang/String;
     178: invokevirtual #65                 // Method java/lang/String.equals:(Ljava/lang/Object;)Z
     181: ifne          186
     184: iconst_0
     185: ireturn
     186: aload_2
     187: invokevirtual #44                 // Method getChildPolicy:()Ljava/lang/String;
     190: ifnonnull     197
     193: iconst_1
     194: goto          198
     197: iconst_0
     198: aload_0
     199: invokevirtual #44                 // Method getChildPolicy:()Ljava/lang/String;
     202: ifnonnull     209
     205: iconst_1
     206: goto          210
     209: iconst_0
     210: ixor
     211: ifeq          216
     214: iconst_0
     215: ireturn
     216: aload_2
     217: invokevirtual #44                 // Method getChildPolicy:()Ljava/lang/String;
     220: ifnull        239
     223: aload_2
     224: invokevirtual #44                 // Method getChildPolicy:()Ljava/lang/String;
     227: aload_0
     228: invokevirtual #44                 // Method getChildPolicy:()Ljava/lang/String;
     231: invokevirtual #65                 // Method java/lang/String.equals:(Ljava/lang/Object;)Z
     234: ifne          239
     237: iconst_0
     238: ireturn
     239: aload_2
     240: invokevirtual #46                 // Method getTaskList:()Lcom/amazonaws/services/simpleworkflow/model/TaskList;
     243: ifnonnull     250
     246: iconst_1
     247: goto          251
     250: iconst_0
     251: aload_0
     252: invokevirtual #46                 // Method getTaskList:()Lcom/amazonaws/services/simpleworkflow/model/TaskList;
     255: ifnonnull     262
     258: iconst_1
     259: goto          263
     262: iconst_0
     263: ixor
     264: ifeq          269
     267: iconst_0
     268: ireturn
     269: aload_2
     270: invokevirtual #46                 // Method getTaskList:()Lcom/amazonaws/services/simpleworkflow/model/TaskList;
     273: ifnull        292
     276: aload_2
     277: invokevirtual #46                 // Method getTaskList:()Lcom/amazonaws/services/simpleworkflow/model/TaskList;
     280: aload_0
     281: invokevirtual #46                 // Method getTaskList:()Lcom/amazonaws/services/simpleworkflow/model/TaskList;
     284: invokevirtual #66                 // Method com/amazonaws/services/simpleworkflow/model/TaskList.equals:(Ljava/lang/Object;)Z
     287: ifne          292
     290: iconst_0
     291: ireturn
     292: aload_2
     293: invokevirtual #49                 // Method getWorkflowType:()Lcom/amazonaws/services/simpleworkflow/model/WorkflowType;
     296: ifnonnull     303
     299: iconst_1
     300: goto          304
     303: iconst_0
     304: aload_0
     305: invokevirtual #49                 // Method getWorkflowType:()Lcom/amazonaws/services/simpleworkflow/model/WorkflowType;
     308: ifnonnull     315
     311: iconst_1
     312: goto          316
     315: iconst_0
     316: ixor
     317: ifeq          322
     320: iconst_0
     321: ireturn
     322: aload_2
     323: invokevirtual #49                 // Method getWorkflowType:()Lcom/amazonaws/services/simpleworkflow/model/WorkflowType;
     326: ifnull        345
     329: aload_2
     330: invokevirtual #49                 // Method getWorkflowType:()Lcom/amazonaws/services/simpleworkflow/model/WorkflowType;
     333: aload_0
     334: invokevirtual #49                 // Method getWorkflowType:()Lcom/amazonaws/services/simpleworkflow/model/WorkflowType;
     337: invokevirtual #67                 // Method com/amazonaws/services/simpleworkflow/model/WorkflowType.equals:(Ljava/lang/Object;)Z
     340: ifne          345
     343: iconst_0
     344: ireturn
     345: aload_2
     346: invokevirtual #51                 // Method getTagList:()Ljava/util/List;
     349: ifnonnull     356
     352: iconst_1
     353: goto          357
     356: iconst_0
     357: aload_0
     358: invokevirtual #51                 // Method getTagList:()Ljava/util/List;
     361: ifnonnull     368
     364: iconst_1
     365: goto          369
     368: iconst_0
     369: ixor
     370: ifeq          375
     373: iconst_0
     374: ireturn
     375: aload_2
     376: invokevirtual #51                 // Method getTagList:()Ljava/util/List;
     379: ifnull        400
     382: aload_2
     383: invokevirtual #51                 // Method getTagList:()Ljava/util/List;
     386: aload_0
     387: invokevirtual #51                 // Method getTagList:()Ljava/util/List;
     390: invokeinterface #68,  2           // InterfaceMethod java/util/List.equals:(Ljava/lang/Object;)Z
     395: ifne          400
     398: iconst_0
     399: ireturn
     400: aload_2
     401: invokevirtual #53                 // Method getTaskPriority:()Ljava/lang/String;
     404: ifnonnull     411
     407: iconst_1
     408: goto          412
     411: iconst_0
     412: aload_0
     413: invokevirtual #53                 // Method getTaskPriority:()Ljava/lang/String;
     416: ifnonnull     423
     419: iconst_1
     420: goto          424
     423: iconst_0
     424: ixor
     425: ifeq          430
     428: iconst_0
     429: ireturn
     430: aload_2
     431: invokevirtual #53                 // Method getTaskPriority:()Ljava/lang/String;
     434: ifnull        453
     437: aload_2
     438: invokevirtual #53                 // Method getTaskPriority:()Ljava/lang/String;
     441: aload_0
     442: invokevirtual #53                 // Method getTaskPriority:()Ljava/lang/String;
     445: invokevirtual #65                 // Method java/lang/String.equals:(Ljava/lang/Object;)Z
     448: ifne          453
     451: iconst_0
     452: ireturn
     453: aload_2
     454: invokevirtual #55                 // Method getContinuedExecutionRunId:()Ljava/lang/String;
     457: ifnonnull     464
     460: iconst_1
     461: goto          465
     464: iconst_0
     465: aload_0
     466: invokevirtual #55                 // Method getContinuedExecutionRunId:()Ljava/lang/String;
     469: ifnonnull     476
     472: iconst_1
     473: goto          477
     476: iconst_0
     477: ixor
     478: ifeq          483
     481: iconst_0
     482: ireturn
     483: aload_2
     484: invokevirtual #55                 // Method getContinuedExecutionRunId:()Ljava/lang/String;
     487: ifnull        506
     490: aload_2
     491: invokevirtual #55                 // Method getContinuedExecutionRunId:()Ljava/lang/String;
     494: aload_0
     495: invokevirtual #55                 // Method getContinuedExecutionRunId:()Ljava/lang/String;
     498: invokevirtual #65                 // Method java/lang/String.equals:(Ljava/lang/Object;)Z
     501: ifne          506
     504: iconst_0
     505: ireturn
     506: aload_2
     507: invokevirtual #57                 // Method getParentWorkflowExecution:()Lcom/amazonaws/services/simpleworkflow/model/WorkflowExecution;
     510: ifnonnull     517
     513: iconst_1
     514: goto          518
     517: iconst_0
     518: aload_0
     519: invokevirtual #57                 // Method getParentWorkflowExecution:()Lcom/amazonaws/services/simpleworkflow/model/WorkflowExecution;
     522: ifnonnull     529
     525: iconst_1
     526: goto          530
     529: iconst_0
     530: ixor
     531: ifeq          536
     534: iconst_0
     535: ireturn
     536: aload_2
     537: invokevirtual #57                 // Method getParentWorkflowExecution:()Lcom/amazonaws/services/simpleworkflow/model/WorkflowExecution;
     540: ifnull        559
     543: aload_2
     544: invokevirtual #57                 // Method getParentWorkflowExecution:()Lcom/amazonaws/services/simpleworkflow/model/WorkflowExecution;
     547: aload_0
     548: invokevirtual #57                 // Method getParentWorkflowExecution:()Lcom/amazonaws/services/simpleworkflow/model/WorkflowExecution;
     551: invokevirtual #69                 // Method com/amazonaws/services/simpleworkflow/model/WorkflowExecution.equals:(Ljava/lang/Object;)Z
     554: ifne          559
     557: iconst_0
     558: ireturn
     559: aload_2
     560: invokevirtual #59                 // Method getParentInitiatedEventId:()Ljava/lang/Long;
     563: ifnonnull     570
     566: iconst_1
     567: goto          571
     570: iconst_0
     571: aload_0
     572: invokevirtual #59                 // Method getParentInitiatedEventId:()Ljava/lang/Long;
     575: ifnonnull     582
     578: iconst_1
     579: goto          583
     582: iconst_0
     583: ixor
     584: ifeq          589
     587: iconst_0
     588: ireturn
     589: aload_2
     590: invokevirtual #59                 // Method getParentInitiatedEventId:()Ljava/lang/Long;
     593: ifnull        612
     596: aload_2
     597: invokevirtual #59                 // Method getParentInitiatedEventId:()Ljava/lang/Long;
     600: aload_0
     601: invokevirtual #59                 // Method getParentInitiatedEventId:()Ljava/lang/Long;
     604: invokevirtual #70                 // Method java/lang/Long.equals:(Ljava/lang/Object;)Z
     607: ifne          612
     610: iconst_0
     611: ireturn
     612: aload_2
     613: invokevirtual #61                 // Method getLambdaRole:()Ljava/lang/String;
     616: ifnonnull     623
     619: iconst_1
     620: goto          624
     623: iconst_0
     624: aload_0
     625: invokevirtual #61                 // Method getLambdaRole:()Ljava/lang/String;
     628: ifnonnull     635
     631: iconst_1
     632: goto          636
     635: iconst_0
     636: ixor
     637: ifeq          642
     640: iconst_0
     641: ireturn
     642: aload_2
     643: invokevirtual #61                 // Method getLambdaRole:()Ljava/lang/String;
     646: ifnull        665
     649: aload_2
     650: invokevirtual #61                 // Method getLambdaRole:()Ljava/lang/String;
     653: aload_0
     654: invokevirtual #61                 // Method getLambdaRole:()Ljava/lang/String;
     657: invokevirtual #65                 // Method java/lang/String.equals:(Ljava/lang/Object;)Z
     660: ifne          665
     663: iconst_0
     664: ireturn
     665: iconst_1
     666: ireturn

  public int hashCode();
    Code:
       0: bipush        31
       2: istore_1
       3: iconst_1
       4: istore_2
       5: bipush        31
       7: iload_2
       8: imul
       9: aload_0
      10: invokevirtual #36                 // Method getInput:()Ljava/lang/String;
      13: ifnonnull     20
      16: iconst_0
      17: goto          27
      20: aload_0
      21: invokevirtual #36                 // Method getInput:()Ljava/lang/String;
      24: invokevirtual #71                 // Method java/lang/String.hashCode:()I
      27: iadd
      28: istore_2
      29: bipush        31
      31: iload_2
      32: imul
      33: aload_0
      34: invokevirtual #40                 // Method getExecutionStartToCloseTimeout:()Ljava/lang/String;
      37: ifnonnull     44
      40: iconst_0
      41: goto          51
      44: aload_0
      45: invokevirtual #40                 // Method getExecutionStartToCloseTimeout:()Ljava/lang/String;
      48: invokevirtual #71                 // Method java/lang/String.hashCode:()I
      51: iadd
      52: istore_2
      53: bipush        31
      55: iload_2
      56: imul
      57: aload_0
      58: invokevirtual #42                 // Method getTaskStartToCloseTimeout:()Ljava/lang/String;
      61: ifnonnull     68
      64: iconst_0
      65: goto          75
      68: aload_0
      69: invokevirtual #42                 // Method getTaskStartToCloseTimeout:()Ljava/lang/String;
      72: invokevirtual #71                 // Method java/lang/String.hashCode:()I
      75: iadd
      76: istore_2
      77: bipush        31
      79: iload_2
      80: imul
      81: aload_0
      82: invokevirtual #44                 // Method getChildPolicy:()Ljava/lang/String;
      85: ifnonnull     92
      88: iconst_0
      89: goto          99
      92: aload_0
      93: invokevirtual #44                 // Method getChildPolicy:()Ljava/lang/String;
      96: invokevirtual #71                 // Method java/lang/String.hashCode:()I
      99: iadd
     100: istore_2
     101: bipush        31
     103: iload_2
     104: imul
     105: aload_0
     106: invokevirtual #46                 // Method getTaskList:()Lcom/amazonaws/services/simpleworkflow/model/TaskList;
     109: ifnonnull     116
     112: iconst_0
     113: goto          123
     116: aload_0
     117: invokevirtual #46                 // Method getTaskList:()Lcom/amazonaws/services/simpleworkflow/model/TaskList;
     120: invokevirtual #72                 // Method com/amazonaws/services/simpleworkflow/model/TaskList.hashCode:()I
     123: iadd
     124: istore_2
     125: bipush        31
     127: iload_2
     128: imul
     129: aload_0
     130: invokevirtual #49                 // Method getWorkflowType:()Lcom/amazonaws/services/simpleworkflow/model/WorkflowType;
     133: ifnonnull     140
     136: iconst_0
     137: goto          147
     140: aload_0
     141: invokevirtual #49                 // Method getWorkflowType:()Lcom/amazonaws/services/simpleworkflow/model/WorkflowType;
     144: invokevirtual #73                 // Method com/amazonaws/services/simpleworkflow/model/WorkflowType.hashCode:()I
     147: iadd
     148: istore_2
     149: bipush        31
     151: iload_2
     152: imul
     153: aload_0
     154: invokevirtual #51                 // Method getTagList:()Ljava/util/List;
     157: ifnonnull     164
     160: iconst_0
     161: goto          173
     164: aload_0
     165: invokevirtual #51                 // Method getTagList:()Ljava/util/List;
     168: invokeinterface #74,  1           // InterfaceMethod java/util/List.hashCode:()I
     173: iadd
     174: istore_2
     175: bipush        31
     177: iload_2
     178: imul
     179: aload_0
     180: invokevirtual #53                 // Method getTaskPriority:()Ljava/lang/String;
     183: ifnonnull     190
     186: iconst_0
     187: goto          197
     190: aload_0
     191: invokevirtual #53                 // Method getTaskPriority:()Ljava/lang/String;
     194: invokevirtual #71                 // Method java/lang/String.hashCode:()I
     197: iadd
     198: istore_2
     199: bipush        31
     201: iload_2
     202: imul
     203: aload_0
     204: invokevirtual #55                 // Method getContinuedExecutionRunId:()Ljava/lang/String;
     207: ifnonnull     214
     210: iconst_0
     211: goto          221
     214: aload_0
     215: invokevirtual #55                 // Method getContinuedExecutionRunId:()Ljava/lang/String;
     218: invokevirtual #71                 // Method java/lang/String.hashCode:()I
     221: iadd
     222: istore_2
     223: bipush        31
     225: iload_2
     226: imul
     227: aload_0
     228: invokevirtual #57                 // Method getParentWorkflowExecution:()Lcom/amazonaws/services/simpleworkflow/model/WorkflowExecution;
     231: ifnonnull     238
     234: iconst_0
     235: goto          245
     238: aload_0
     239: invokevirtual #57                 // Method getParentWorkflowExecution:()Lcom/amazonaws/services/simpleworkflow/model/WorkflowExecution;
     242: invokevirtual #75                 // Method com/amazonaws/services/simpleworkflow/model/WorkflowExecution.hashCode:()I
     245: iadd
     246: istore_2
     247: bipush        31
     249: iload_2
     250: imul
     251: aload_0
     252: invokevirtual #59                 // Method getParentInitiatedEventId:()Ljava/lang/Long;
     255: ifnonnull     262
     258: iconst_0
     259: goto          269
     262: aload_0
     263: invokevirtual #59                 // Method getParentInitiatedEventId:()Ljava/lang/Long;
     266: invokevirtual #76                 // Method java/lang/Long.hashCode:()I
     269: iadd
     270: istore_2
     271: bipush        31
     273: iload_2
     274: imul
     275: aload_0
     276: invokevirtual #61                 // Method getLambdaRole:()Ljava/lang/String;
     279: ifnonnull     286
     282: iconst_0
     283: goto          293
     286: aload_0
     287: invokevirtual #61                 // Method getLambdaRole:()Ljava/lang/String;
     290: invokevirtual #71                 // Method java/lang/String.hashCode:()I
     293: iadd
     294: istore_2
     295: iload_2
     296: ireturn

  public com.amazonaws.services.simpleworkflow.model.WorkflowExecutionStartedEventAttributes clone();
    Code:
       0: aload_0
       1: invokespecial #77                 // Method java/lang/Object.clone:()Ljava/lang/Object;
       4: checkcast     #64                 // class com/amazonaws/services/simpleworkflow/model/WorkflowExecutionStartedEventAttributes
       7: areturn
       8: astore_1
       9: new           #79                 // class java/lang/IllegalStateException
      12: dup
      13: ldc           #80                 // String Got a CloneNotSupportedException from Object.clone() even though we\'re Cloneable!
      15: aload_1
      16: invokespecial #81                 // Method java/lang/IllegalStateException."<init>":(Ljava/lang/String;Ljava/lang/Throwable;)V
      19: athrow
    Exception table:
       from    to  target type
           0     7     8   Class java/lang/CloneNotSupportedException

  public java.lang.Object clone() throws java.lang.CloneNotSupportedException;
    Code:
       0: aload_0
       1: invokevirtual #82                 // Method clone:()Lcom/amazonaws/services/simpleworkflow/model/WorkflowExecutionStartedEventAttributes;
       4: areturn
}
