Compiled from "APIKeyHandlerImpl.java"
public class io.vertx.ext.web.handler.impl.APIKeyHandlerImpl extends io.vertx.ext.web.handler.impl.AuthenticationHandlerImpl<io.vertx.ext.auth.authentication.AuthenticationProvider> implements io.vertx.ext.web.handler.APIKeyHandler {
  private io.vertx.ext.web.handler.impl.APIKeyHandlerImpl$Type source;

  private java.lang.String value;

  public io.vertx.ext.web.handler.impl.APIKeyHandlerImpl(io.vertx.ext.auth.authentication.AuthenticationProvider);
    Code:
       0: aload_0
       1: aload_1
       2: invokespecial #1                  // Method io/vertx/ext/web/handler/impl/AuthenticationHandlerImpl."<init>":(Lio/vertx/ext/auth/authentication/AuthenticationProvider;)V
       5: aload_0
       6: getstatic     #2                  // Field io/vertx/ext/web/handler/impl/APIKeyHandlerImpl$Type.HEADER:Lio/vertx/ext/web/handler/impl/APIKeyHandlerImpl$Type;
       9: putfield      #3                  // Field source:Lio/vertx/ext/web/handler/impl/APIKeyHandlerImpl$Type;
      12: aload_0
      13: ldc           #4                  // String X-API-KEY
      15: putfield      #5                  // Field value:Ljava/lang/String;
      18: return

  public io.vertx.ext.web.handler.APIKeyHandler header(java.lang.String);
    Code:
       0: aload_1
       1: ifnonnull     14
       4: new           #6                  // class java/lang/IllegalArgumentException
       7: dup
       8: ldc           #7                  // String \'headerName\' cannot be null
      10: invokespecial #8                  // Method java/lang/IllegalArgumentException."<init>":(Ljava/lang/String;)V
      13: athrow
      14: aload_0
      15: getstatic     #2                  // Field io/vertx/ext/web/handler/impl/APIKeyHandlerImpl$Type.HEADER:Lio/vertx/ext/web/handler/impl/APIKeyHandlerImpl$Type;
      18: putfield      #3                  // Field source:Lio/vertx/ext/web/handler/impl/APIKeyHandlerImpl$Type;
      21: aload_0
      22: aload_1
      23: putfield      #5                  // Field value:Ljava/lang/String;
      26: aload_0
      27: areturn

  public io.vertx.ext.web.handler.APIKeyHandler parameter(java.lang.String);
    Code:
       0: aload_1
       1: ifnonnull     14
       4: new           #6                  // class java/lang/IllegalArgumentException
       7: dup
       8: ldc           #9                  // String \'paramName\' cannot be null
      10: invokespecial #8                  // Method java/lang/IllegalArgumentException."<init>":(Ljava/lang/String;)V
      13: athrow
      14: aload_0
      15: getstatic     #10                 // Field io/vertx/ext/web/handler/impl/APIKeyHandlerImpl$Type.PARAMETER:Lio/vertx/ext/web/handler/impl/APIKeyHandlerImpl$Type;
      18: putfield      #3                  // Field source:Lio/vertx/ext/web/handler/impl/APIKeyHandlerImpl$Type;
      21: aload_0
      22: aload_1
      23: putfield      #5                  // Field value:Ljava/lang/String;
      26: aload_0
      27: areturn

  public io.vertx.ext.web.handler.APIKeyHandler cookie(java.lang.String);
    Code:
       0: aload_1
       1: ifnonnull     14
       4: new           #6                  // class java/lang/IllegalArgumentException
       7: dup
       8: ldc           #11                 // String \'cookieName\' cannot be null
      10: invokespecial #8                  // Method java/lang/IllegalArgumentException."<init>":(Ljava/lang/String;)V
      13: athrow
      14: aload_0
      15: getstatic     #12                 // Field io/vertx/ext/web/handler/impl/APIKeyHandlerImpl$Type.COOKIE:Lio/vertx/ext/web/handler/impl/APIKeyHandlerImpl$Type;
      18: putfield      #3                  // Field source:Lio/vertx/ext/web/handler/impl/APIKeyHandlerImpl$Type;
      21: aload_0
      22: aload_1
      23: putfield      #5                  // Field value:Ljava/lang/String;
      26: aload_0
      27: areturn

  public void authenticate(io.vertx.ext.web.RoutingContext, io.vertx.core.Handler<io.vertx.core.AsyncResult<io.vertx.ext.auth.User>>);
    Code:
       0: getstatic     #13                 // Field io/vertx/ext/web/handler/impl/APIKeyHandlerImpl$1.$SwitchMap$io$vertx$ext$web$handler$impl$APIKeyHandlerImpl$Type:[I
       3: aload_0
       4: getfield      #3                  // Field source:Lio/vertx/ext/web/handler/impl/APIKeyHandlerImpl$Type;
       7: invokevirtual #14                 // Method io/vertx/ext/web/handler/impl/APIKeyHandlerImpl$Type.ordinal:()I
      10: iaload
      11: tableswitch   { // 1 to 3
                     1: 36
                     2: 98
                     3: 164
               default: 216
          }
      36: aload_1
      37: invokeinterface #15,  1           // InterfaceMethod io/vertx/ext/web/RoutingContext.request:()Lio/vertx/core/http/HttpServerRequest;
      42: invokeinterface #16,  1           // InterfaceMethod io/vertx/core/http/HttpServerRequest.headers:()Lio/vertx/core/MultiMap;
      47: astore_3
      48: aload_3
      49: ifnull        216
      52: aload_3
      53: aload_0
      54: getfield      #5                  // Field value:Ljava/lang/String;
      57: invokeinterface #17,  2           // InterfaceMethod io/vertx/core/MultiMap.contains:(Ljava/lang/String;)Z
      62: ifeq          216
      65: aload_0
      66: getfield      #18                 // Field authProvider:Lio/vertx/ext/auth/authentication/AuthenticationProvider;
      69: new           #19                 // class io/vertx/ext/auth/authentication/TokenCredentials
      72: dup
      73: aload_3
      74: aload_0
      75: getfield      #5                  // Field value:Ljava/lang/String;
      78: invokeinterface #20,  2           // InterfaceMethod io/vertx/core/MultiMap.get:(Ljava/lang/String;)Ljava/lang/String;
      83: invokespecial #21                 // Method io/vertx/ext/auth/authentication/TokenCredentials."<init>":(Ljava/lang/String;)V
      86: aload_2
      87: invokedynamic #22,  0             // InvokeDynamic #0:handle:(Lio/vertx/core/Handler;)Lio/vertx/core/Handler;
      92: invokeinterface #23,  3           // InterfaceMethod io/vertx/ext/auth/authentication/AuthenticationProvider.authenticate:(Lio/vertx/ext/auth/authentication/Credentials;Lio/vertx/core/Handler;)V
      97: return
      98: aload_1
      99: invokeinterface #15,  1           // InterfaceMethod io/vertx/ext/web/RoutingContext.request:()Lio/vertx/core/http/HttpServerRequest;
     104: invokeinterface #24,  1           // InterfaceMethod io/vertx/core/http/HttpServerRequest.params:()Lio/vertx/core/MultiMap;
     109: astore        4
     111: aload         4
     113: ifnull        216
     116: aload         4
     118: aload_0
     119: getfield      #5                  // Field value:Ljava/lang/String;
     122: invokeinterface #17,  2           // InterfaceMethod io/vertx/core/MultiMap.contains:(Ljava/lang/String;)Z
     127: ifeq          216
     130: aload_0
     131: getfield      #18                 // Field authProvider:Lio/vertx/ext/auth/authentication/AuthenticationProvider;
     134: new           #19                 // class io/vertx/ext/auth/authentication/TokenCredentials
     137: dup
     138: aload         4
     140: aload_0
     141: getfield      #5                  // Field value:Ljava/lang/String;
     144: invokeinterface #20,  2           // InterfaceMethod io/vertx/core/MultiMap.get:(Ljava/lang/String;)Ljava/lang/String;
     149: invokespecial #21                 // Method io/vertx/ext/auth/authentication/TokenCredentials."<init>":(Ljava/lang/String;)V
     152: aload_2
     153: invokedynamic #25,  0             // InvokeDynamic #1:handle:(Lio/vertx/core/Handler;)Lio/vertx/core/Handler;
     158: invokeinterface #23,  3           // InterfaceMethod io/vertx/ext/auth/authentication/AuthenticationProvider.authenticate:(Lio/vertx/ext/auth/authentication/Credentials;Lio/vertx/core/Handler;)V
     163: return
     164: aload_1
     165: invokeinterface #15,  1           // InterfaceMethod io/vertx/ext/web/RoutingContext.request:()Lio/vertx/core/http/HttpServerRequest;
     170: aload_0
     171: getfield      #5                  // Field value:Ljava/lang/String;
     174: invokeinterface #26,  2           // InterfaceMethod io/vertx/core/http/HttpServerRequest.getCookie:(Ljava/lang/String;)Lio/vertx/core/http/Cookie;
     179: astore        5
     181: aload         5
     183: ifnull        216
     186: aload_0
     187: getfield      #18                 // Field authProvider:Lio/vertx/ext/auth/authentication/AuthenticationProvider;
     190: new           #19                 // class io/vertx/ext/auth/authentication/TokenCredentials
     193: dup
     194: aload         5
     196: invokeinterface #27,  1           // InterfaceMethod io/vertx/core/http/Cookie.getValue:()Ljava/lang/String;
     201: invokespecial #21                 // Method io/vertx/ext/auth/authentication/TokenCredentials."<init>":(Ljava/lang/String;)V
     204: aload_2
     205: invokedynamic #28,  0             // InvokeDynamic #2:handle:(Lio/vertx/core/Handler;)Lio/vertx/core/Handler;
     210: invokeinterface #23,  3           // InterfaceMethod io/vertx/ext/auth/authentication/AuthenticationProvider.authenticate:(Lio/vertx/ext/auth/authentication/Credentials;Lio/vertx/core/Handler;)V
     215: return
     216: aload_2
     217: getstatic     #29                 // Field UNAUTHORIZED:Lio/vertx/ext/web/handler/HttpException;
     220: invokestatic  #30                 // InterfaceMethod io/vertx/core/Future.failedFuture:(Ljava/lang/Throwable;)Lio/vertx/core/Future;
     223: invokeinterface #31,  2           // InterfaceMethod io/vertx/core/Handler.handle:(Ljava/lang/Object;)V
     228: return

  private static void lambda$authenticate$2(io.vertx.core.Handler, io.vertx.core.AsyncResult);
    Code:
       0: aload_1
       1: invokeinterface #32,  1           // InterfaceMethod io/vertx/core/AsyncResult.failed:()Z
       6: ifeq          37
       9: aload_0
      10: new           #33                 // class io/vertx/ext/web/handler/HttpException
      13: dup
      14: sipush        401
      17: aload_1
      18: invokeinterface #34,  1           // InterfaceMethod io/vertx/core/AsyncResult.cause:()Ljava/lang/Throwable;
      23: invokespecial #35                 // Method io/vertx/ext/web/handler/HttpException."<init>":(ILjava/lang/Throwable;)V
      26: invokestatic  #30                 // InterfaceMethod io/vertx/core/Future.failedFuture:(Ljava/lang/Throwable;)Lio/vertx/core/Future;
      29: invokeinterface #31,  2           // InterfaceMethod io/vertx/core/Handler.handle:(Ljava/lang/Object;)V
      34: goto          44
      37: aload_0
      38: aload_1
      39: invokeinterface #31,  2           // InterfaceMethod io/vertx/core/Handler.handle:(Ljava/lang/Object;)V
      44: return

  private static void lambda$authenticate$1(io.vertx.core.Handler, io.vertx.core.AsyncResult);
    Code:
       0: aload_1
       1: invokeinterface #32,  1           // InterfaceMethod io/vertx/core/AsyncResult.failed:()Z
       6: ifeq          37
       9: aload_0
      10: new           #33                 // class io/vertx/ext/web/handler/HttpException
      13: dup
      14: sipush        401
      17: aload_1
      18: invokeinterface #34,  1           // InterfaceMethod io/vertx/core/AsyncResult.cause:()Ljava/lang/Throwable;
      23: invokespecial #35                 // Method io/vertx/ext/web/handler/HttpException."<init>":(ILjava/lang/Throwable;)V
      26: invokestatic  #30                 // InterfaceMethod io/vertx/core/Future.failedFuture:(Ljava/lang/Throwable;)Lio/vertx/core/Future;
      29: invokeinterface #31,  2           // InterfaceMethod io/vertx/core/Handler.handle:(Ljava/lang/Object;)V
      34: goto          44
      37: aload_0
      38: aload_1
      39: invokeinterface #31,  2           // InterfaceMethod io/vertx/core/Handler.handle:(Ljava/lang/Object;)V
      44: return

  private static void lambda$authenticate$0(io.vertx.core.Handler, io.vertx.core.AsyncResult);
    Code:
       0: aload_1
       1: invokeinterface #32,  1           // InterfaceMethod io/vertx/core/AsyncResult.failed:()Z
       6: ifeq          37
       9: aload_0
      10: new           #33                 // class io/vertx/ext/web/handler/HttpException
      13: dup
      14: sipush        401
      17: aload_1
      18: invokeinterface #34,  1           // InterfaceMethod io/vertx/core/AsyncResult.cause:()Ljava/lang/Throwable;
      23: invokespecial #35                 // Method io/vertx/ext/web/handler/HttpException."<init>":(ILjava/lang/Throwable;)V
      26: invokestatic  #30                 // InterfaceMethod io/vertx/core/Future.failedFuture:(Ljava/lang/Throwable;)Lio/vertx/core/Future;
      29: invokeinterface #31,  2           // InterfaceMethod io/vertx/core/Handler.handle:(Ljava/lang/Object;)V
      34: goto          44
      37: aload_0
      38: aload_1
      39: invokeinterface #31,  2           // InterfaceMethod io/vertx/core/Handler.handle:(Ljava/lang/Object;)V
      44: return
}
