Compiled from "FormattingTuple.java"
class org.sonarsource.sonarlint.core.commons.log.FormattingTuple {
  private final java.lang.String message;

  private final java.lang.Throwable throwable;

  public org.sonarsource.sonarlint.core.commons.log.FormattingTuple(java.lang.String);
    Code:
       0: aload_0
       1: aload_1
       2: aconst_null
       3: invokespecial #15                 // Method "<init>":(Ljava/lang/String;Ljava/lang/Throwable;)V
       6: return

  public org.sonarsource.sonarlint.core.commons.log.FormattingTuple(java.lang.String, java.lang.Throwable);
    Code:
       0: aload_0
       1: invokespecial #20                 // Method java/lang/Object."<init>":()V
       4: aload_0
       5: aload_1
       6: putfield      #22                 // Field message:Ljava/lang/String;
       9: aload_0
      10: aload_2
      11: putfield      #24                 // Field throwable:Ljava/lang/Throwable;
      14: return

  public java.lang.String getMessage();
    Code:
       0: aload_0
       1: getfield      #22                 // Field message:Ljava/lang/String;
       4: areturn

  public java.lang.Throwable getThrowable();
    Code:
       0: aload_0
       1: getfield      #24                 // Field throwable:Ljava/lang/Throwable;
       4: areturn
}
