Compiled from "JRubyScriptUtils.java"
public abstract class org.springframework.scripting.jruby.JRubyScriptUtils {
  public org.springframework.scripting.jruby.JRubyScriptUtils();
    Code:
       0: aload_0
       1: invokespecial #1                  // Method java/lang/Object."<init>":()V
       4: return

  public static java.lang.Object createJRubyObject(java.lang.String, java.lang.Class<?>...) throws org.jruby.exceptions.JumpException;
    Code:
       0: aload_0
       1: aload_1
       2: invokestatic  #2                  // Method org/springframework/util/ClassUtils.getDefaultClassLoader:()Ljava/lang/ClassLoader;
       5: invokestatic  #3                  // Method createJRubyObject:(Ljava/lang/String;[Ljava/lang/Class;Ljava/lang/ClassLoader;)Ljava/lang/Object;
       8: areturn

  public static java.lang.Object createJRubyObject(java.lang.String, java.lang.Class<?>[], java.lang.ClassLoader);
    Code:
       0: invokestatic  #4                  // Method initializeRuntime:()Lorg/jruby/Ruby;
       3: astore_3
       4: aload_3
       5: aload_0
       6: ldc           #5                  // String
       8: aconst_null
       9: iconst_0
      10: invokevirtual #6                  // Method org/jruby/Ruby.parseEval:(Ljava/lang/String;Ljava/lang/String;Lorg/jruby/runtime/DynamicScope;I)Lorg/jruby/ast/Node;
      13: astore        4
      15: aload_3
      16: aload         4
      18: invokevirtual #7                  // Method org/jruby/Ruby.runNormally:(Lorg/jruby/ast/Node;)Lorg/jruby/runtime/builtin/IRubyObject;
      21: astore        5
      23: aload         5
      25: instanceof    #8                  // class org/jruby/RubyNil
      28: ifeq          69
      31: aload         4
      33: invokestatic  #9                  // Method findClassName:(Lorg/jruby/ast/Node;)Ljava/lang/String;
      36: astore        6
      38: aload_3
      39: new           #10                 // class java/lang/StringBuilder
      42: dup
      43: invokespecial #11                 // Method java/lang/StringBuilder."<init>":()V
      46: ldc           #12                 // String \n
      48: invokevirtual #13                 // Method java/lang/StringBuilder.append:(Ljava/lang/String;)Ljava/lang/StringBuilder;
      51: aload         6
      53: invokevirtual #13                 // Method java/lang/StringBuilder.append:(Ljava/lang/String;)Ljava/lang/StringBuilder;
      56: ldc           #14                 // String .new
      58: invokevirtual #13                 // Method java/lang/StringBuilder.append:(Ljava/lang/String;)Ljava/lang/StringBuilder;
      61: invokevirtual #15                 // Method java/lang/StringBuilder.toString:()Ljava/lang/String;
      64: invokevirtual #16                 // Method org/jruby/Ruby.evalScriptlet:(Ljava/lang/String;)Lorg/jruby/runtime/builtin/IRubyObject;
      67: astore        5
      69: aload         5
      71: instanceof    #8                  // class org/jruby/RubyNil
      74: ifeq          105
      77: new           #17                 // class java/lang/IllegalStateException
      80: dup
      81: new           #10                 // class java/lang/StringBuilder
      84: dup
      85: invokespecial #11                 // Method java/lang/StringBuilder."<init>":()V
      88: ldc           #18                 // String Compilation of JRuby script returned RubyNil:
      90: invokevirtual #13                 // Method java/lang/StringBuilder.append:(Ljava/lang/String;)Ljava/lang/StringBuilder;
      93: aload         5
      95: invokevirtual #19                 // Method java/lang/StringBuilder.append:(Ljava/lang/Object;)Ljava/lang/StringBuilder;
      98: invokevirtual #15                 // Method java/lang/StringBuilder.toString:()Ljava/lang/String;
     101: invokespecial #20                 // Method java/lang/IllegalStateException."<init>":(Ljava/lang/String;)V
     104: athrow
     105: aload_2
     106: aload_1
     107: new           #21                 // class org/springframework/scripting/jruby/JRubyScriptUtils$RubyObjectInvocationHandler
     110: dup
     111: aload         5
     113: aload_3
     114: invokespecial #22                 // Method org/springframework/scripting/jruby/JRubyScriptUtils$RubyObjectInvocationHandler."<init>":(Lorg/jruby/runtime/builtin/IRubyObject;Lorg/jruby/Ruby;)V
     117: invokestatic  #23                 // Method java/lang/reflect/Proxy.newProxyInstance:(Ljava/lang/ClassLoader;[Ljava/lang/Class;Ljava/lang/reflect/InvocationHandler;)Ljava/lang/Object;
     120: areturn

  private static org.jruby.Ruby initializeRuntime();
    Code:
       0: getstatic     #24                 // Field java/util/Collections.EMPTY_LIST:Ljava/util/List;
       3: invokestatic  #25                 // Method org/jruby/javasupport/JavaEmbedUtils.initialize:(Ljava/util/List;)Lorg/jruby/Ruby;
       6: areturn

  private static java.lang.String findClassName(org.jruby.ast.Node);
    Code:
       0: aload_0
       1: invokestatic  #26                 // Method findClassNode:(Lorg/jruby/ast/Node;)Lorg/jruby/ast/ClassNode;
       4: astore_1
       5: aload_1
       6: ifnonnull     41
       9: new           #27                 // class java/lang/IllegalArgumentException
      12: dup
      13: new           #10                 // class java/lang/StringBuilder
      16: dup
      17: invokespecial #11                 // Method java/lang/StringBuilder."<init>":()V
      20: ldc           #28                 // String Unable to determine class name for root node \'
      22: invokevirtual #13                 // Method java/lang/StringBuilder.append:(Ljava/lang/String;)Ljava/lang/StringBuilder;
      25: aload_0
      26: invokevirtual #19                 // Method java/lang/StringBuilder.append:(Ljava/lang/Object;)Ljava/lang/StringBuilder;
      29: ldc           #29                 // String \'
      31: invokevirtual #13                 // Method java/lang/StringBuilder.append:(Ljava/lang/String;)Ljava/lang/StringBuilder;
      34: invokevirtual #15                 // Method java/lang/StringBuilder.toString:()Ljava/lang/String;
      37: invokespecial #30                 // Method java/lang/IllegalArgumentException."<init>":(Ljava/lang/String;)V
      40: athrow
      41: aload_1
      42: invokevirtual #31                 // Method org/jruby/ast/ClassNode.getCPath:()Lorg/jruby/ast/Colon3Node;
      45: checkcast     #32                 // class org/jruby/ast/Colon2Node
      48: astore_2
      49: aload_2
      50: invokevirtual #33                 // Method org/jruby/ast/Colon2Node.getName:()Ljava/lang/String;
      53: areturn

  private static org.jruby.ast.ClassNode findClassNode(org.jruby.ast.Node);
    Code:
       0: aload_0
       1: ifnonnull     6
       4: aconst_null
       5: areturn
       6: aload_0
       7: instanceof    #34                 // class org/jruby/ast/ClassNode
      10: ifeq          18
      13: aload_0
      14: checkcast     #34                 // class org/jruby/ast/ClassNode
      17: areturn
      18: aload_0
      19: invokevirtual #35                 // Method org/jruby/ast/Node.childNodes:()Ljava/util/List;
      22: astore_1
      23: aload_1
      24: invokeinterface #36,  1           // InterfaceMethod java/util/List.iterator:()Ljava/util/Iterator;
      29: astore_2
      30: aload_2
      31: invokeinterface #37,  1           // InterfaceMethod java/util/Iterator.hasNext:()Z
      36: ifeq          95
      39: aload_2
      40: invokeinterface #38,  1           // InterfaceMethod java/util/Iterator.next:()Ljava/lang/Object;
      45: checkcast     #39                 // class org/jruby/ast/Node
      48: astore_3
      49: aload_3
      50: instanceof    #34                 // class org/jruby/ast/ClassNode
      53: ifeq          61
      56: aload_3
      57: checkcast     #34                 // class org/jruby/ast/ClassNode
      60: areturn
      61: aload_3
      62: instanceof    #40                 // class org/jruby/ast/NewlineNode
      65: ifeq          92
      68: aload_3
      69: checkcast     #40                 // class org/jruby/ast/NewlineNode
      72: astore        4
      74: aload         4
      76: invokevirtual #41                 // Method org/jruby/ast/NewlineNode.getNextNode:()Lorg/jruby/ast/Node;
      79: invokestatic  #26                 // Method findClassNode:(Lorg/jruby/ast/Node;)Lorg/jruby/ast/ClassNode;
      82: astore        5
      84: aload         5
      86: ifnull        92
      89: aload         5
      91: areturn
      92: goto          30
      95: aload_1
      96: invokeinterface #36,  1           // InterfaceMethod java/util/List.iterator:()Ljava/util/Iterator;
     101: astore_2
     102: aload_2
     103: invokeinterface #37,  1           // InterfaceMethod java/util/Iterator.hasNext:()Z
     108: ifeq          138
     111: aload_2
     112: invokeinterface #38,  1           // InterfaceMethod java/util/Iterator.next:()Ljava/lang/Object;
     117: checkcast     #39                 // class org/jruby/ast/Node
     120: astore_3
     121: aload_3
     122: invokestatic  #26                 // Method findClassNode:(Lorg/jruby/ast/Node;)Lorg/jruby/ast/ClassNode;
     125: astore        4
     127: aload         4
     129: ifnull        135
     132: aload         4
     134: areturn
     135: goto          102
     138: aconst_null
     139: areturn
}
