Compiled from "WSDLWrapperReloadImpl.java"
public class org.apache.axis2.wsdl.util.WSDLWrapperReloadImpl implements org.apache.axis2.wsdl.util.WSDLWrapperImpl {
  private static final org.apache.commons.logging.Log log;

  private static final boolean isDebugEnabled;

  private static final java.lang.String myClassName;

  static final long serialVersionUID;

  private javax.wsdl.Definition wsdlDefinition;

  private java.net.URL wsdlURL;

  private java.lang.String wsdlExplicitURI;

  private java.lang.String wsdlDocumentBaseURI;

  private static boolean USE_SOFT_REFERENCES;

  private transient java.lang.ref.SoftReference softTypes;

  private transient java.lang.ref.SoftReference softDocElement;

  public org.apache.axis2.wsdl.util.WSDLWrapperReloadImpl(javax.wsdl.Definition);
    Code:
       0: aload_0
       1: invokespecial #3                  // Method java/lang/Object."<init>":()V
       4: aload_0
       5: aconst_null
       6: putfield      #4                  // Field wsdlDefinition:Ljavax/wsdl/Definition;
       9: aload_0
      10: aconst_null
      11: putfield      #5                  // Field wsdlURL:Ljava/net/URL;
      14: aload_0
      15: aconst_null
      16: putfield      #1                  // Field wsdlExplicitURI:Ljava/lang/String;
      19: aload_0
      20: aconst_null
      21: putfield      #6                  // Field wsdlDocumentBaseURI:Ljava/lang/String;
      24: aload_0
      25: aconst_null
      26: putfield      #7                  // Field softTypes:Ljava/lang/ref/SoftReference;
      29: aload_0
      30: aconst_null
      31: putfield      #8                  // Field softDocElement:Ljava/lang/ref/SoftReference;
      34: getstatic     #9                  // Field log:Lorg/apache/commons/logging/Log;
      37: invokeinterface #10,  1           // InterfaceMethod org/apache/commons/logging/Log.isDebugEnabled:()Z
      42: ifeq          66
      45: getstatic     #9                  // Field log:Lorg/apache/commons/logging/Log;
      48: ldc           #11                 // String WSDLWrapperReloadImpl(Definition def) called
      50: invokeinterface #12,  2           // InterfaceMethod org/apache/commons/logging/Log.debug:(Ljava/lang/Object;)V
      55: getstatic     #9                  // Field log:Lorg/apache/commons/logging/Log;
      58: invokestatic  #13                 // Method org/apache/axis2/util/JavaUtils.callStackToString:()Ljava/lang/String;
      61: invokeinterface #14,  2           // InterfaceMethod org/apache/commons/logging/Log.trace:(Ljava/lang/Object;)V
      66: aload_0
      67: aload_1
      68: aconst_null
      69: invokespecial #15                 // Method prepare:(Ljavax/wsdl/Definition;Ljava/net/URL;)V
      72: return

  public org.apache.axis2.wsdl.util.WSDLWrapperReloadImpl(javax.wsdl.Definition, java.net.URL);
    Code:
       0: aload_0
       1: invokespecial #3                  // Method java/lang/Object."<init>":()V
       4: aload_0
       5: aconst_null
       6: putfield      #4                  // Field wsdlDefinition:Ljavax/wsdl/Definition;
       9: aload_0
      10: aconst_null
      11: putfield      #5                  // Field wsdlURL:Ljava/net/URL;
      14: aload_0
      15: aconst_null
      16: putfield      #1                  // Field wsdlExplicitURI:Ljava/lang/String;
      19: aload_0
      20: aconst_null
      21: putfield      #6                  // Field wsdlDocumentBaseURI:Ljava/lang/String;
      24: aload_0
      25: aconst_null
      26: putfield      #7                  // Field softTypes:Ljava/lang/ref/SoftReference;
      29: aload_0
      30: aconst_null
      31: putfield      #8                  // Field softDocElement:Ljava/lang/ref/SoftReference;
      34: getstatic     #9                  // Field log:Lorg/apache/commons/logging/Log;
      37: invokeinterface #10,  1           // InterfaceMethod org/apache/commons/logging/Log.isDebugEnabled:()Z
      42: ifeq          66
      45: getstatic     #9                  // Field log:Lorg/apache/commons/logging/Log;
      48: ldc           #16                 // String WSDLWrapperReloadImpl(Definition def, URL wURL) called
      50: invokeinterface #12,  2           // InterfaceMethod org/apache/commons/logging/Log.debug:(Ljava/lang/Object;)V
      55: getstatic     #9                  // Field log:Lorg/apache/commons/logging/Log;
      58: invokestatic  #13                 // Method org/apache/axis2/util/JavaUtils.callStackToString:()Ljava/lang/String;
      61: invokeinterface #14,  2           // InterfaceMethod org/apache/commons/logging/Log.trace:(Ljava/lang/Object;)V
      66: aload_0
      67: aload_1
      68: aload_2
      69: invokespecial #15                 // Method prepare:(Ljavax/wsdl/Definition;Ljava/net/URL;)V
      72: return

  public static boolean isReloadable(javax.wsdl.Definition, java.net.URL);
    Code:
       0: getstatic     #17                 // Field isDebugEnabled:Z
       3: ifeq          33
       6: getstatic     #9                  // Field log:Lorg/apache/commons/logging/Log;
       9: new           #18                 // class java/lang/StringBuilder
      12: dup
      13: invokespecial #19                 // Method java/lang/StringBuilder."<init>":()V
      16: ldc           #21                 // String Enter WSDLWrapperReloadImpl.isReloadable():
      18: invokevirtual #22                 // Method java/lang/StringBuilder.append:(Ljava/lang/String;)Ljava/lang/StringBuilder;
      21: aload_1
      22: invokevirtual #23                 // Method java/lang/StringBuilder.append:(Ljava/lang/Object;)Ljava/lang/StringBuilder;
      25: invokevirtual #24                 // Method java/lang/StringBuilder.toString:()Ljava/lang/String;
      28: invokeinterface #12,  2           // InterfaceMethod org/apache/commons/logging/Log.debug:(Ljava/lang/Object;)V
      33: aconst_null
      34: astore_2
      35: aload_0
      36: ifnull        143
      39: aload_0
      40: invokeinterface #25,  1           // InterfaceMethod javax/wsdl/Definition.getDocumentBaseURI:()Ljava/lang/String;
      45: astore_3
      46: aload_1
      47: ifnonnull     63
      50: aload_3
      51: ifnull        63
      54: new           #26                 // class java/net/URL
      57: dup
      58: aload_3
      59: invokespecial #27                 // Method java/net/URL."<init>":(Ljava/lang/String;)V
      62: astore_1
      63: aload_1
      64: ifnull        72
      67: aload_1
      68: invokestatic  #28                 // Method getExplicitURI:(Ljava/net/URL;)Ljava/lang/String;
      71: astore_2
      72: goto          143
      75: astore_3
      76: getstatic     #17                 // Field isDebugEnabled:Z
      79: ifeq          143
      82: getstatic     #9                  // Field log:Lorg/apache/commons/logging/Log;
      85: new           #18                 // class java/lang/StringBuilder
      88: dup
      89: invokespecial #19                 // Method java/lang/StringBuilder."<init>":()V
      92: ldc           #30                 // String WSDLWrapperReloadImpl.isReloaded(): [
      94: invokevirtual #22                 // Method java/lang/StringBuilder.append:(Ljava/lang/String;)Ljava/lang/StringBuilder;
      97: aload_3
      98: invokevirtual #31                 // Method java/lang/Object.getClass:()Ljava/lang/Class;
     101: invokevirtual #32                 // Method java/lang/Class.getName:()Ljava/lang/String;
     104: invokevirtual #22                 // Method java/lang/StringBuilder.append:(Ljava/lang/String;)Ljava/lang/StringBuilder;
     107: ldc           #33                 // String ]  error [
     109: invokevirtual #22                 // Method java/lang/StringBuilder.append:(Ljava/lang/String;)Ljava/lang/StringBuilder;
     112: aload_3
     113: invokevirtual #34                 // Method java/lang/Exception.getMessage:()Ljava/lang/String;
     116: invokevirtual #22                 // Method java/lang/StringBuilder.append:(Ljava/lang/String;)Ljava/lang/StringBuilder;
     119: ldc           #35                 // String ]
     121: invokevirtual #22                 // Method java/lang/StringBuilder.append:(Ljava/lang/String;)Ljava/lang/StringBuilder;
     124: invokevirtual #24                 // Method java/lang/StringBuilder.toString:()Ljava/lang/String;
     127: aload_3
     128: invokeinterface #36,  3           // InterfaceMethod org/apache/commons/logging/Log.debug:(Ljava/lang/Object;Ljava/lang/Throwable;)V
     133: getstatic     #9                  // Field log:Lorg/apache/commons/logging/Log;
     136: ldc           #37                 // String Processing continues.
     138: invokeinterface #12,  2           // InterfaceMethod org/apache/commons/logging/Log.debug:(Ljava/lang/Object;)V
     143: getstatic     #17                 // Field isDebugEnabled:Z
     146: ifeq          176
     149: getstatic     #9                  // Field log:Lorg/apache/commons/logging/Log;
     152: new           #18                 // class java/lang/StringBuilder
     155: dup
     156: invokespecial #19                 // Method java/lang/StringBuilder."<init>":()V
     159: ldc           #38                 // String  explicitURI=
     161: invokevirtual #22                 // Method java/lang/StringBuilder.append:(Ljava/lang/String;)Ljava/lang/StringBuilder;
     164: aload_2
     165: invokevirtual #22                 // Method java/lang/StringBuilder.append:(Ljava/lang/String;)Ljava/lang/StringBuilder;
     168: invokevirtual #24                 // Method java/lang/StringBuilder.toString:()Ljava/lang/String;
     171: invokeinterface #12,  2           // InterfaceMethod org/apache/commons/logging/Log.debug:(Ljava/lang/Object;)V
     176: aload_2
     177: ifnull        191
     180: aload_2
     181: invokevirtual #39                 // Method java/lang/String.length:()I
     184: ifle          191
     187: iconst_1
     188: goto          192
     191: iconst_0
     192: istore_3
     193: getstatic     #17                 // Field isDebugEnabled:Z
     196: ifeq          226
     199: getstatic     #9                  // Field log:Lorg/apache/commons/logging/Log;
     202: new           #18                 // class java/lang/StringBuilder
     205: dup
     206: invokespecial #19                 // Method java/lang/StringBuilder."<init>":()V
     209: ldc           #40                 // String Exit WSDLWrapperReloadImpl.isReloadable():
     211: invokevirtual #22                 // Method java/lang/StringBuilder.append:(Ljava/lang/String;)Ljava/lang/StringBuilder;
     214: iload_3
     215: invokevirtual #41                 // Method java/lang/StringBuilder.append:(Z)Ljava/lang/StringBuilder;
     218: invokevirtual #24                 // Method java/lang/StringBuilder.toString:()Ljava/lang/String;
     221: invokeinterface #12,  2           // InterfaceMethod org/apache/commons/logging/Log.debug:(Ljava/lang/Object;)V
     226: iload_3
     227: ireturn
    Exception table:
       from    to  target type
          39    72    75   Class java/lang/Exception

  private void prepare(javax.wsdl.Definition, java.net.URL);
    Code:
       0: getstatic     #17                 // Field isDebugEnabled:Z
       3: ifeq          16
       6: getstatic     #9                  // Field log:Lorg/apache/commons/logging/Log;
       9: ldc           #42                 // String WSDLWrapperReloadImpl.prepare()
      11: invokeinterface #12,  2           // InterfaceMethod org/apache/commons/logging/Log.debug:(Ljava/lang/Object;)V
      16: aload_0
      17: aload_1
      18: putfield      #4                  // Field wsdlDefinition:Ljavax/wsdl/Definition;
      21: aload_0
      22: aload_2
      23: putfield      #5                  // Field wsdlURL:Ljava/net/URL;
      26: aload_1
      27: ifnull        158
      30: aload_0
      31: aload_1
      32: invokeinterface #25,  1           // InterfaceMethod javax/wsdl/Definition.getDocumentBaseURI:()Ljava/lang/String;
      37: putfield      #6                  // Field wsdlDocumentBaseURI:Ljava/lang/String;
      40: aload_0
      41: getfield      #5                  // Field wsdlURL:Ljava/net/URL;
      44: ifnonnull     75
      47: aload_0
      48: getfield      #6                  // Field wsdlDocumentBaseURI:Ljava/lang/String;
      51: ifnull        75
      54: new           #26                 // class java/net/URL
      57: dup
      58: aload_0
      59: getfield      #6                  // Field wsdlDocumentBaseURI:Ljava/lang/String;
      62: invokespecial #27                 // Method java/net/URL."<init>":(Ljava/lang/String;)V
      65: astore_3
      66: aload_0
      67: aload_3
      68: putfield      #5                  // Field wsdlURL:Ljava/net/URL;
      71: goto          75
      74: astore_3
      75: aload_0
      76: getfield      #5                  // Field wsdlURL:Ljava/net/URL;
      79: ifnull        93
      82: aload_0
      83: aload_0
      84: getfield      #5                  // Field wsdlURL:Ljava/net/URL;
      87: invokestatic  #28                 // Method getExplicitURI:(Ljava/net/URL;)Ljava/lang/String;
      90: putfield      #1                  // Field wsdlExplicitURI:Ljava/lang/String;
      93: aload_0
      94: invokevirtual #43                 // Method releaseResources:()V
      97: goto          158
     100: astore_3
     101: getstatic     #17                 // Field isDebugEnabled:Z
     104: ifeq          158
     107: getstatic     #9                  // Field log:Lorg/apache/commons/logging/Log;
     110: new           #18                 // class java/lang/StringBuilder
     113: dup
     114: invokespecial #19                 // Method java/lang/StringBuilder."<init>":()V
     117: ldc           #44                 // String WSDLWrapperReloadImpl.prepare():  Caught exception [
     119: invokevirtual #22                 // Method java/lang/StringBuilder.append:(Ljava/lang/String;)Ljava/lang/StringBuilder;
     122: aload_3
     123: invokevirtual #31                 // Method java/lang/Object.getClass:()Ljava/lang/Class;
     126: invokevirtual #32                 // Method java/lang/Class.getName:()Ljava/lang/String;
     129: invokevirtual #22                 // Method java/lang/StringBuilder.append:(Ljava/lang/String;)Ljava/lang/StringBuilder;
     132: ldc           #33                 // String ]  error [
     134: invokevirtual #22                 // Method java/lang/StringBuilder.append:(Ljava/lang/String;)Ljava/lang/StringBuilder;
     137: aload_3
     138: invokevirtual #34                 // Method java/lang/Exception.getMessage:()Ljava/lang/String;
     141: invokevirtual #22                 // Method java/lang/StringBuilder.append:(Ljava/lang/String;)Ljava/lang/StringBuilder;
     144: ldc           #35                 // String ]
     146: invokevirtual #22                 // Method java/lang/StringBuilder.append:(Ljava/lang/String;)Ljava/lang/StringBuilder;
     149: invokevirtual #24                 // Method java/lang/StringBuilder.toString:()Ljava/lang/String;
     152: aload_3
     153: invokeinterface #36,  3           // InterfaceMethod org/apache/commons/logging/Log.debug:(Ljava/lang/Object;Ljava/lang/Throwable;)V
     158: getstatic     #17                 // Field isDebugEnabled:Z
     161: ifeq          223
     164: getstatic     #9                  // Field log:Lorg/apache/commons/logging/Log;
     167: new           #18                 // class java/lang/StringBuilder
     170: dup
     171: invokespecial #19                 // Method java/lang/StringBuilder."<init>":()V
     174: ldc           #45                 // String WSDLWrapperReloadImpl.prepare():   wsdlDocumentBaseURI [
     176: invokevirtual #22                 // Method java/lang/StringBuilder.append:(Ljava/lang/String;)Ljava/lang/StringBuilder;
     179: aload_0
     180: getfield      #6                  // Field wsdlDocumentBaseURI:Ljava/lang/String;
     183: invokevirtual #22                 // Method java/lang/StringBuilder.append:(Ljava/lang/String;)Ljava/lang/StringBuilder;
     186: ldc           #46                 // String ]     wsdlExplicitURI [
     188: invokevirtual #22                 // Method java/lang/StringBuilder.append:(Ljava/lang/String;)Ljava/lang/StringBuilder;
     191: aload_0
     192: getfield      #1                  // Field wsdlExplicitURI:Ljava/lang/String;
     195: invokevirtual #22                 // Method java/lang/StringBuilder.append:(Ljava/lang/String;)Ljava/lang/StringBuilder;
     198: ldc           #47                 // String ]   wsdlURL [
     200: invokevirtual #22                 // Method java/lang/StringBuilder.append:(Ljava/lang/String;)Ljava/lang/StringBuilder;
     203: aload_0
     204: getfield      #5                  // Field wsdlURL:Ljava/net/URL;
     207: invokevirtual #23                 // Method java/lang/StringBuilder.append:(Ljava/lang/Object;)Ljava/lang/StringBuilder;
     210: ldc           #35                 // String ]
     212: invokevirtual #22                 // Method java/lang/StringBuilder.append:(Ljava/lang/String;)Ljava/lang/StringBuilder;
     215: invokevirtual #24                 // Method java/lang/StringBuilder.toString:()Ljava/lang/String;
     218: invokeinterface #12,  2           // InterfaceMethod org/apache/commons/logging/Log.debug:(Ljava/lang/Object;)V
     223: return
    Exception table:
       from    to  target type
          54    71    74   Class java/lang/Exception
          30    97   100   Class java/lang/Exception

  public void releaseResources();
    Code:
       0: aload_0
       1: getfield      #4                  // Field wsdlDefinition:Ljavax/wsdl/Definition;
       4: ifnull        65
       7: aload_0
       8: getfield      #4                  // Field wsdlDefinition:Ljavax/wsdl/Definition;
      11: invokeinterface #48,  1           // InterfaceMethod javax/wsdl/Definition.getTypes:()Ljavax/wsdl/Types;
      16: astore_1
      17: aload_1
      18: ifnull        31
      21: aload_0
      22: getfield      #4                  // Field wsdlDefinition:Ljavax/wsdl/Definition;
      25: aconst_null
      26: invokeinterface #49,  2           // InterfaceMethod javax/wsdl/Definition.setTypes:(Ljavax/wsdl/Types;)V
      31: aload_0
      32: aload_1
      33: invokespecial #50                 // Method setCachedTypes:(Ljavax/wsdl/Types;)V
      36: aload_0
      37: getfield      #4                  // Field wsdlDefinition:Ljavax/wsdl/Definition;
      40: invokeinterface #51,  1           // InterfaceMethod javax/wsdl/Definition.getDocumentationElement:()Lorg/w3c/dom/Element;
      45: astore_2
      46: aload_2
      47: ifnull        60
      50: aload_0
      51: getfield      #4                  // Field wsdlDefinition:Ljavax/wsdl/Definition;
      54: aconst_null
      55: invokeinterface #52,  2           // InterfaceMethod javax/wsdl/Definition.setDocumentationElement:(Lorg/w3c/dom/Element;)V
      60: aload_0
      61: aload_2
      62: invokespecial #53                 // Method setCachedDocElement:(Lorg/w3c/dom/Element;)V
      65: return

  private void setCachedTypes(javax.wsdl.Types);
    Code:
       0: getstatic     #54                 // Field USE_SOFT_REFERENCES:Z
       3: ifeq          56
       6: aload_0
       7: getfield      #7                  // Field softTypes:Ljava/lang/ref/SoftReference;
      10: ifnull        23
      13: aload_0
      14: getfield      #7                  // Field softTypes:Ljava/lang/ref/SoftReference;
      17: invokevirtual #55                 // Method java/lang/ref/SoftReference.get:()Ljava/lang/Object;
      20: ifnonnull     56
      23: aload_1
      24: ifnull        42
      27: aload_0
      28: new           #56                 // class java/lang/ref/SoftReference
      31: dup
      32: aload_1
      33: invokespecial #57                 // Method java/lang/ref/SoftReference."<init>":(Ljava/lang/Object;)V
      36: putfield      #7                  // Field softTypes:Ljava/lang/ref/SoftReference;
      39: goto          56
      42: aload_0
      43: new           #56                 // class java/lang/ref/SoftReference
      46: dup
      47: getstatic     #58                 // Field java/lang/Boolean.FALSE:Ljava/lang/Boolean;
      50: invokespecial #57                 // Method java/lang/ref/SoftReference."<init>":(Ljava/lang/Object;)V
      53: putfield      #7                  // Field softTypes:Ljava/lang/ref/SoftReference;
      56: return

  private javax.wsdl.Types getCachedTypes();
    Code:
       0: getstatic     #54                 // Field USE_SOFT_REFERENCES:Z
       3: ifeq          54
       6: aload_0
       7: getfield      #7                  // Field softTypes:Ljava/lang/ref/SoftReference;
      10: ifnull        23
      13: aload_0
      14: getfield      #7                  // Field softTypes:Ljava/lang/ref/SoftReference;
      17: invokevirtual #55                 // Method java/lang/ref/SoftReference.get:()Ljava/lang/Object;
      20: ifnonnull     25
      23: aconst_null
      24: areturn
      25: aload_0
      26: getfield      #7                  // Field softTypes:Ljava/lang/ref/SoftReference;
      29: invokevirtual #55                 // Method java/lang/ref/SoftReference.get:()Ljava/lang/Object;
      32: getstatic     #58                 // Field java/lang/Boolean.FALSE:Ljava/lang/Boolean;
      35: invokevirtual #59                 // Method java/lang/Object.equals:(Ljava/lang/Object;)Z
      38: ifeq          43
      41: aconst_null
      42: areturn
      43: aload_0
      44: getfield      #7                  // Field softTypes:Ljava/lang/ref/SoftReference;
      47: invokevirtual #55                 // Method java/lang/ref/SoftReference.get:()Ljava/lang/Object;
      50: checkcast     #60                 // class javax/wsdl/Types
      53: areturn
      54: aconst_null
      55: areturn

  private boolean hasCachedTypes();
    Code:
       0: getstatic     #54                 // Field USE_SOFT_REFERENCES:Z
       3: ifeq          29
       6: aload_0
       7: getfield      #7                  // Field softTypes:Ljava/lang/ref/SoftReference;
      10: ifnull        27
      13: aload_0
      14: getfield      #7                  // Field softTypes:Ljava/lang/ref/SoftReference;
      17: invokevirtual #55                 // Method java/lang/ref/SoftReference.get:()Ljava/lang/Object;
      20: ifnull        27
      23: iconst_1
      24: goto          28
      27: iconst_0
      28: ireturn
      29: iconst_0
      30: ireturn

  private void setCachedDocElement(org.w3c.dom.Element);
    Code:
       0: getstatic     #54                 // Field USE_SOFT_REFERENCES:Z
       3: ifeq          56
       6: aload_0
       7: getfield      #8                  // Field softDocElement:Ljava/lang/ref/SoftReference;
      10: ifnull        23
      13: aload_0
      14: getfield      #8                  // Field softDocElement:Ljava/lang/ref/SoftReference;
      17: invokevirtual #55                 // Method java/lang/ref/SoftReference.get:()Ljava/lang/Object;
      20: ifnonnull     56
      23: aload_1
      24: ifnull        42
      27: aload_0
      28: new           #56                 // class java/lang/ref/SoftReference
      31: dup
      32: aload_1
      33: invokespecial #57                 // Method java/lang/ref/SoftReference."<init>":(Ljava/lang/Object;)V
      36: putfield      #8                  // Field softDocElement:Ljava/lang/ref/SoftReference;
      39: goto          56
      42: aload_0
      43: new           #56                 // class java/lang/ref/SoftReference
      46: dup
      47: getstatic     #58                 // Field java/lang/Boolean.FALSE:Ljava/lang/Boolean;
      50: invokespecial #57                 // Method java/lang/ref/SoftReference."<init>":(Ljava/lang/Object;)V
      53: putfield      #8                  // Field softDocElement:Ljava/lang/ref/SoftReference;
      56: return

  private org.w3c.dom.Element getCachedDocElement();
    Code:
       0: getstatic     #54                 // Field USE_SOFT_REFERENCES:Z
       3: ifeq          54
       6: aload_0
       7: getfield      #8                  // Field softDocElement:Ljava/lang/ref/SoftReference;
      10: ifnull        23
      13: aload_0
      14: getfield      #8                  // Field softDocElement:Ljava/lang/ref/SoftReference;
      17: invokevirtual #55                 // Method java/lang/ref/SoftReference.get:()Ljava/lang/Object;
      20: ifnonnull     25
      23: aconst_null
      24: areturn
      25: aload_0
      26: getfield      #8                  // Field softDocElement:Ljava/lang/ref/SoftReference;
      29: invokevirtual #55                 // Method java/lang/ref/SoftReference.get:()Ljava/lang/Object;
      32: getstatic     #58                 // Field java/lang/Boolean.FALSE:Ljava/lang/Boolean;
      35: invokevirtual #59                 // Method java/lang/Object.equals:(Ljava/lang/Object;)Z
      38: ifeq          43
      41: aconst_null
      42: areturn
      43: aload_0
      44: getfield      #8                  // Field softDocElement:Ljava/lang/ref/SoftReference;
      47: invokevirtual #55                 // Method java/lang/ref/SoftReference.get:()Ljava/lang/Object;
      50: checkcast     #61                 // class org/w3c/dom/Element
      53: areturn
      54: aconst_null
      55: areturn

  private boolean hasCachedDocElement();
    Code:
       0: getstatic     #54                 // Field USE_SOFT_REFERENCES:Z
       3: ifeq          29
       6: aload_0
       7: getfield      #8                  // Field softDocElement:Ljava/lang/ref/SoftReference;
      10: ifnull        27
      13: aload_0
      14: getfield      #8                  // Field softDocElement:Ljava/lang/ref/SoftReference;
      17: invokevirtual #55                 // Method java/lang/ref/SoftReference.get:()Ljava/lang/Object;
      20: ifnull        27
      23: iconst_1
      24: goto          28
      27: iconst_0
      28: ireturn
      29: iconst_0
      30: ireturn

  public javax.wsdl.Definition getUnwrappedDefinition();
    Code:
       0: aload_0
       1: getfield      #4                  // Field wsdlDefinition:Ljavax/wsdl/Definition;
       4: ifnonnull     78
       7: aload_0
       8: invokespecial #62                 // Method loadDefinition:()Ljavax/wsdl/Definition;
      11: astore_1
      12: goto          182
      15: astore_2
      16: getstatic     #17                 // Field isDebugEnabled:Z
      19: ifeq          73
      22: getstatic     #9                  // Field log:Lorg/apache/commons/logging/Log;
      25: new           #18                 // class java/lang/StringBuilder
      28: dup
      29: invokespecial #19                 // Method java/lang/StringBuilder."<init>":()V
      32: ldc           #63                 // String WSDLWrapperReloadImpl.getUnwrappedDefinition(): error trying to load Definition    [
      34: invokevirtual #22                 // Method java/lang/StringBuilder.append:(Ljava/lang/String;)Ljava/lang/StringBuilder;
      37: aload_2
      38: invokevirtual #31                 // Method java/lang/Object.getClass:()Ljava/lang/Class;
      41: invokevirtual #32                 // Method java/lang/Class.getName:()Ljava/lang/String;
      44: invokevirtual #22                 // Method java/lang/StringBuilder.append:(Ljava/lang/String;)Ljava/lang/StringBuilder;
      47: ldc           #33                 // String ]  error [
      49: invokevirtual #22                 // Method java/lang/StringBuilder.append:(Ljava/lang/String;)Ljava/lang/StringBuilder;
      52: aload_2
      53: invokevirtual #34                 // Method java/lang/Exception.getMessage:()Ljava/lang/String;
      56: invokevirtual #22                 // Method java/lang/StringBuilder.append:(Ljava/lang/String;)Ljava/lang/StringBuilder;
      59: ldc           #64                 // String ]
      61: invokevirtual #22                 // Method java/lang/StringBuilder.append:(Ljava/lang/String;)Ljava/lang/StringBuilder;
      64: invokevirtual #24                 // Method java/lang/StringBuilder.toString:()Ljava/lang/String;
      67: aload_2
      68: invokeinterface #36,  3           // InterfaceMethod org/apache/commons/logging/Log.debug:(Ljava/lang/Object;Ljava/lang/Throwable;)V
      73: aconst_null
      74: astore_1
      75: goto          182
      78: aload_0
      79: getfield      #4                  // Field wsdlDefinition:Ljavax/wsdl/Definition;
      82: instanceof    #65                 // class org/apache/axis2/wsdl/util/WSDLWrapperBasicImpl
      85: ifeq          102
      88: aload_0
      89: getfield      #4                  // Field wsdlDefinition:Ljavax/wsdl/Definition;
      92: checkcast     #65                 // class org/apache/axis2/wsdl/util/WSDLWrapperBasicImpl
      95: invokevirtual #66                 // Method org/apache/axis2/wsdl/util/WSDLWrapperBasicImpl.getUnwrappedDefinition:()Ljavax/wsdl/Definition;
      98: astore_1
      99: goto          182
     102: aload_0
     103: invokespecial #62                 // Method loadDefinition:()Ljavax/wsdl/Definition;
     106: astore_1
     107: aload_1
     108: ifnonnull     116
     111: aload_0
     112: getfield      #4                  // Field wsdlDefinition:Ljavax/wsdl/Definition;
     115: astore_1
     116: goto          182
     119: astore_2
     120: getstatic     #17                 // Field isDebugEnabled:Z
     123: ifeq          177
     126: getstatic     #9                  // Field log:Lorg/apache/commons/logging/Log;
     129: new           #18                 // class java/lang/StringBuilder
     132: dup
     133: invokespecial #19                 // Method java/lang/StringBuilder."<init>":()V
     136: ldc           #63                 // String WSDLWrapperReloadImpl.getUnwrappedDefinition(): error trying to load Definition    [
     138: invokevirtual #22                 // Method java/lang/StringBuilder.append:(Ljava/lang/String;)Ljava/lang/StringBuilder;
     141: aload_2
     142: invokevirtual #31                 // Method java/lang/Object.getClass:()Ljava/lang/Class;
     145: invokevirtual #32                 // Method java/lang/Class.getName:()Ljava/lang/String;
     148: invokevirtual #22                 // Method java/lang/StringBuilder.append:(Ljava/lang/String;)Ljava/lang/StringBuilder;
     151: ldc           #33                 // String ]  error [
     153: invokevirtual #22                 // Method java/lang/StringBuilder.append:(Ljava/lang/String;)Ljava/lang/StringBuilder;
     156: aload_2
     157: invokevirtual #34                 // Method java/lang/Exception.getMessage:()Ljava/lang/String;
     160: invokevirtual #22                 // Method java/lang/StringBuilder.append:(Ljava/lang/String;)Ljava/lang/StringBuilder;
     163: ldc           #64                 // String ]
     165: invokevirtual #22                 // Method java/lang/StringBuilder.append:(Ljava/lang/String;)Ljava/lang/StringBuilder;
     168: invokevirtual #24                 // Method java/lang/StringBuilder.toString:()Ljava/lang/String;
     171: aload_2
     172: invokeinterface #36,  3           // InterfaceMethod org/apache/commons/logging/Log.debug:(Ljava/lang/Object;Ljava/lang/Throwable;)V
     177: aload_0
     178: getfield      #4                  // Field wsdlDefinition:Ljavax/wsdl/Definition;
     181: astore_1
     182: aload_1
     183: areturn
    Exception table:
       from    to  target type
           7    12    15   Class java/lang/Exception
         102   116   119   Class java/lang/Exception

  public void setDefinitionToWrap(javax.wsdl.Definition);
    Code:
       0: aload_0
       1: aload_1
       2: putfield      #4                  // Field wsdlDefinition:Ljavax/wsdl/Definition;
       5: return

  public void setWSDLLocation(java.lang.String);
    Code:
       0: aload_1
       1: ifnull        20
       4: aload_0
       5: new           #26                 // class java/net/URL
       8: dup
       9: aload_1
      10: invokespecial #27                 // Method java/net/URL."<init>":(Ljava/lang/String;)V
      13: putfield      #5                  // Field wsdlURL:Ljava/net/URL;
      16: goto          20
      19: astore_2
      20: return
    Exception table:
       from    to  target type
           4    16    19   Class java/lang/Exception

  public java.lang.String getWSDLLocation();
    Code:
       0: aload_0
       1: getfield      #5                  // Field wsdlURL:Ljava/net/URL;
       4: ifnull        15
       7: aload_0
       8: getfield      #5                  // Field wsdlURL:Ljava/net/URL;
      11: invokevirtual #67                 // Method java/net/URL.toString:()Ljava/lang/String;
      14: areturn
      15: aconst_null
      16: areturn

  public void close();
    Code:
       0: return

  public void setDocumentBaseURI(java.lang.String);
    Code:
       0: getstatic     #17                 // Field isDebugEnabled:Z
       3: ifeq          38
       6: getstatic     #9                  // Field log:Lorg/apache/commons/logging/Log;
       9: new           #18                 // class java/lang/StringBuilder
      12: dup
      13: invokespecial #19                 // Method java/lang/StringBuilder."<init>":()V
      16: ldc           #68                 // String WSDLWrapperReloadImpl.setDocumentBaseURI(
      18: invokevirtual #22                 // Method java/lang/StringBuilder.append:(Ljava/lang/String;)Ljava/lang/StringBuilder;
      21: aload_1
      22: invokevirtual #22                 // Method java/lang/StringBuilder.append:(Ljava/lang/String;)Ljava/lang/StringBuilder;
      25: ldc           #69                 // String )
      27: invokevirtual #22                 // Method java/lang/StringBuilder.append:(Ljava/lang/String;)Ljava/lang/StringBuilder;
      30: invokevirtual #24                 // Method java/lang/StringBuilder.toString:()Ljava/lang/String;
      33: invokeinterface #12,  2           // InterfaceMethod org/apache/commons/logging/Log.debug:(Ljava/lang/Object;)V
      38: aload_0
      39: getfield      #4                  // Field wsdlDefinition:Ljavax/wsdl/Definition;
      42: ifnull        55
      45: aload_0
      46: getfield      #4                  // Field wsdlDefinition:Ljavax/wsdl/Definition;
      49: aload_1
      50: invokeinterface #70,  2           // InterfaceMethod javax/wsdl/Definition.setDocumentBaseURI:(Ljava/lang/String;)V
      55: return

  public java.lang.String getDocumentBaseURI();
    Code:
       0: getstatic     #17                 // Field isDebugEnabled:Z
       3: ifeq          16
       6: getstatic     #9                  // Field log:Lorg/apache/commons/logging/Log;
       9: ldc           #71                 // String WSDLWrapperReloadImpl.getDocumentBaseURI()
      11: invokeinterface #12,  2           // InterfaceMethod org/apache/commons/logging/Log.debug:(Ljava/lang/Object;)V
      16: aload_0
      17: getfield      #4                  // Field wsdlDefinition:Ljavax/wsdl/Definition;
      20: ifnull        33
      23: aload_0
      24: getfield      #4                  // Field wsdlDefinition:Ljavax/wsdl/Definition;
      27: invokeinterface #25,  1           // InterfaceMethod javax/wsdl/Definition.getDocumentBaseURI:()Ljava/lang/String;
      32: areturn
      33: aconst_null
      34: areturn

  public void setQName(javax.xml.namespace.QName);
    Code:
       0: getstatic     #17                 // Field isDebugEnabled:Z
       3: ifeq          38
       6: getstatic     #9                  // Field log:Lorg/apache/commons/logging/Log;
       9: new           #18                 // class java/lang/StringBuilder
      12: dup
      13: invokespecial #19                 // Method java/lang/StringBuilder."<init>":()V
      16: ldc           #72                 // String WSDLWrapperReloadImpl.setQName(
      18: invokevirtual #22                 // Method java/lang/StringBuilder.append:(Ljava/lang/String;)Ljava/lang/StringBuilder;
      21: aload_1
      22: invokevirtual #23                 // Method java/lang/StringBuilder.append:(Ljava/lang/Object;)Ljava/lang/StringBuilder;
      25: ldc           #69                 // String )
      27: invokevirtual #22                 // Method java/lang/StringBuilder.append:(Ljava/lang/String;)Ljava/lang/StringBuilder;
      30: invokevirtual #24                 // Method java/lang/StringBuilder.toString:()Ljava/lang/String;
      33: invokeinterface #12,  2           // InterfaceMethod org/apache/commons/logging/Log.debug:(Ljava/lang/Object;)V
      38: aload_0
      39: getfield      #4                  // Field wsdlDefinition:Ljavax/wsdl/Definition;
      42: ifnull        55
      45: aload_0
      46: getfield      #4                  // Field wsdlDefinition:Ljavax/wsdl/Definition;
      49: aload_1
      50: invokeinterface #73,  2           // InterfaceMethod javax/wsdl/Definition.setQName:(Ljavax/xml/namespace/QName;)V
      55: return

  public javax.xml.namespace.QName getQName();
    Code:
       0: getstatic     #17                 // Field isDebugEnabled:Z
       3: ifeq          16
       6: getstatic     #9                  // Field log:Lorg/apache/commons/logging/Log;
       9: ldc           #74                 // String WSDLWrapperReloadImpl.getQName()
      11: invokeinterface #12,  2           // InterfaceMethod org/apache/commons/logging/Log.debug:(Ljava/lang/Object;)V
      16: aload_0
      17: getfield      #4                  // Field wsdlDefinition:Ljavax/wsdl/Definition;
      20: ifnull        33
      23: aload_0
      24: getfield      #4                  // Field wsdlDefinition:Ljavax/wsdl/Definition;
      27: invokeinterface #75,  1           // InterfaceMethod javax/wsdl/Definition.getQName:()Ljavax/xml/namespace/QName;
      32: areturn
      33: aconst_null
      34: areturn

  public void setTargetNamespace(java.lang.String);
    Code:
       0: getstatic     #17                 // Field isDebugEnabled:Z
       3: ifeq          38
       6: getstatic     #9                  // Field log:Lorg/apache/commons/logging/Log;
       9: new           #18                 // class java/lang/StringBuilder
      12: dup
      13: invokespecial #19                 // Method java/lang/StringBuilder."<init>":()V
      16: ldc           #76                 // String WSDLWrapperReloadImpl.setTargetNamespace(
      18: invokevirtual #22                 // Method java/lang/StringBuilder.append:(Ljava/lang/String;)Ljava/lang/StringBuilder;
      21: aload_1
      22: invokevirtual #22                 // Method java/lang/StringBuilder.append:(Ljava/lang/String;)Ljava/lang/StringBuilder;
      25: ldc           #69                 // String )
      27: invokevirtual #22                 // Method java/lang/StringBuilder.append:(Ljava/lang/String;)Ljava/lang/StringBuilder;
      30: invokevirtual #24                 // Method java/lang/StringBuilder.toString:()Ljava/lang/String;
      33: invokeinterface #12,  2           // InterfaceMethod org/apache/commons/logging/Log.debug:(Ljava/lang/Object;)V
      38: aload_0
      39: getfield      #4                  // Field wsdlDefinition:Ljavax/wsdl/Definition;
      42: ifnull        55
      45: aload_0
      46: getfield      #4                  // Field wsdlDefinition:Ljavax/wsdl/Definition;
      49: aload_1
      50: invokeinterface #77,  2           // InterfaceMethod javax/wsdl/Definition.setTargetNamespace:(Ljava/lang/String;)V
      55: return

  public java.lang.String getTargetNamespace();
    Code:
       0: getstatic     #17                 // Field isDebugEnabled:Z
       3: ifeq          16
       6: getstatic     #9                  // Field log:Lorg/apache/commons/logging/Log;
       9: ldc           #78                 // String WSDLWrapperReloadImpl.getTargetNamespace()
      11: invokeinterface #12,  2           // InterfaceMethod org/apache/commons/logging/Log.debug:(Ljava/lang/Object;)V
      16: aload_0
      17: getfield      #4                  // Field wsdlDefinition:Ljavax/wsdl/Definition;
      20: ifnull        33
      23: aload_0
      24: getfield      #4                  // Field wsdlDefinition:Ljavax/wsdl/Definition;
      27: invokeinterface #79,  1           // InterfaceMethod javax/wsdl/Definition.getTargetNamespace:()Ljava/lang/String;
      32: areturn
      33: aconst_null
      34: areturn

  public void addNamespace(java.lang.String, java.lang.String);
    Code:
       0: getstatic     #17                 // Field isDebugEnabled:Z
       3: ifeq          47
       6: getstatic     #9                  // Field log:Lorg/apache/commons/logging/Log;
       9: new           #18                 // class java/lang/StringBuilder
      12: dup
      13: invokespecial #19                 // Method java/lang/StringBuilder."<init>":()V
      16: ldc           #80                 // String WSDLWrapperReloadImpl.addNamespace(
      18: invokevirtual #22                 // Method java/lang/StringBuilder.append:(Ljava/lang/String;)Ljava/lang/StringBuilder;
      21: aload_1
      22: invokevirtual #22                 // Method java/lang/StringBuilder.append:(Ljava/lang/String;)Ljava/lang/StringBuilder;
      25: ldc           #81                 // String ,
      27: invokevirtual #22                 // Method java/lang/StringBuilder.append:(Ljava/lang/String;)Ljava/lang/StringBuilder;
      30: aload_2
      31: invokevirtual #22                 // Method java/lang/StringBuilder.append:(Ljava/lang/String;)Ljava/lang/StringBuilder;
      34: ldc           #69                 // String )
      36: invokevirtual #22                 // Method java/lang/StringBuilder.append:(Ljava/lang/String;)Ljava/lang/StringBuilder;
      39: invokevirtual #24                 // Method java/lang/StringBuilder.toString:()Ljava/lang/String;
      42: invokeinterface #12,  2           // InterfaceMethod org/apache/commons/logging/Log.debug:(Ljava/lang/Object;)V
      47: aload_0
      48: getfield      #4                  // Field wsdlDefinition:Ljavax/wsdl/Definition;
      51: ifnull        65
      54: aload_0
      55: getfield      #4                  // Field wsdlDefinition:Ljavax/wsdl/Definition;
      58: aload_1
      59: aload_2
      60: invokeinterface #82,  3           // InterfaceMethod javax/wsdl/Definition.addNamespace:(Ljava/lang/String;Ljava/lang/String;)V
      65: return

  public java.lang.String removeNamespace(java.lang.String);
    Code:
       0: getstatic     #17                 // Field isDebugEnabled:Z
       3: ifeq          38
       6: getstatic     #9                  // Field log:Lorg/apache/commons/logging/Log;
       9: new           #18                 // class java/lang/StringBuilder
      12: dup
      13: invokespecial #19                 // Method java/lang/StringBuilder."<init>":()V
      16: ldc           #83                 // String WSDLWrapperReloadImpl.removeNamespace(
      18: invokevirtual #22                 // Method java/lang/StringBuilder.append:(Ljava/lang/String;)Ljava/lang/StringBuilder;
      21: aload_1
      22: invokevirtual #22                 // Method java/lang/StringBuilder.append:(Ljava/lang/String;)Ljava/lang/StringBuilder;
      25: ldc           #69                 // String )
      27: invokevirtual #22                 // Method java/lang/StringBuilder.append:(Ljava/lang/String;)Ljava/lang/StringBuilder;
      30: invokevirtual #24                 // Method java/lang/StringBuilder.toString:()Ljava/lang/String;
      33: invokeinterface #12,  2           // InterfaceMethod org/apache/commons/logging/Log.debug:(Ljava/lang/Object;)V
      38: aload_0
      39: getfield      #4                  // Field wsdlDefinition:Ljavax/wsdl/Definition;
      42: ifnull        56
      45: aload_0
      46: getfield      #4                  // Field wsdlDefinition:Ljavax/wsdl/Definition;
      49: aload_1
      50: invokeinterface #84,  2           // InterfaceMethod javax/wsdl/Definition.removeNamespace:(Ljava/lang/String;)Ljava/lang/String;
      55: areturn
      56: aconst_null
      57: areturn

  public java.lang.String getNamespace(java.lang.String);
    Code:
       0: getstatic     #17                 // Field isDebugEnabled:Z
       3: ifeq          38
       6: getstatic     #9                  // Field log:Lorg/apache/commons/logging/Log;
       9: new           #18                 // class java/lang/StringBuilder
      12: dup
      13: invokespecial #19                 // Method java/lang/StringBuilder."<init>":()V
      16: ldc           #85                 // String WSDLWrapperReloadImpl.getNamespace(
      18: invokevirtual #22                 // Method java/lang/StringBuilder.append:(Ljava/lang/String;)Ljava/lang/StringBuilder;
      21: aload_1
      22: invokevirtual #22                 // Method java/lang/StringBuilder.append:(Ljava/lang/String;)Ljava/lang/StringBuilder;
      25: ldc           #69                 // String )
      27: invokevirtual #22                 // Method java/lang/StringBuilder.append:(Ljava/lang/String;)Ljava/lang/StringBuilder;
      30: invokevirtual #24                 // Method java/lang/StringBuilder.toString:()Ljava/lang/String;
      33: invokeinterface #12,  2           // InterfaceMethod org/apache/commons/logging/Log.debug:(Ljava/lang/Object;)V
      38: aload_0
      39: getfield      #4                  // Field wsdlDefinition:Ljavax/wsdl/Definition;
      42: ifnull        56
      45: aload_0
      46: getfield      #4                  // Field wsdlDefinition:Ljavax/wsdl/Definition;
      49: aload_1
      50: invokeinterface #86,  2           // InterfaceMethod javax/wsdl/Definition.getNamespace:(Ljava/lang/String;)Ljava/lang/String;
      55: areturn
      56: aconst_null
      57: areturn

  public java.lang.String getPrefix(java.lang.String);
    Code:
       0: getstatic     #17                 // Field isDebugEnabled:Z
       3: ifeq          38
       6: getstatic     #9                  // Field log:Lorg/apache/commons/logging/Log;
       9: new           #18                 // class java/lang/StringBuilder
      12: dup
      13: invokespecial #19                 // Method java/lang/StringBuilder."<init>":()V
      16: ldc           #87                 // String WSDLWrapperReloadImpl.getPrefix(
      18: invokevirtual #22                 // Method java/lang/StringBuilder.append:(Ljava/lang/String;)Ljava/lang/StringBuilder;
      21: aload_1
      22: invokevirtual #22                 // Method java/lang/StringBuilder.append:(Ljava/lang/String;)Ljava/lang/StringBuilder;
      25: ldc           #69                 // String )
      27: invokevirtual #22                 // Method java/lang/StringBuilder.append:(Ljava/lang/String;)Ljava/lang/StringBuilder;
      30: invokevirtual #24                 // Method java/lang/StringBuilder.toString:()Ljava/lang/String;
      33: invokeinterface #12,  2           // InterfaceMethod org/apache/commons/logging/Log.debug:(Ljava/lang/Object;)V
      38: aload_0
      39: getfield      #4                  // Field wsdlDefinition:Ljavax/wsdl/Definition;
      42: ifnull        56
      45: aload_0
      46: getfield      #4                  // Field wsdlDefinition:Ljavax/wsdl/Definition;
      49: aload_1
      50: invokeinterface #88,  2           // InterfaceMethod javax/wsdl/Definition.getPrefix:(Ljava/lang/String;)Ljava/lang/String;
      55: areturn
      56: aconst_null
      57: areturn

  public java.util.Map getNamespaces();
    Code:
       0: getstatic     #17                 // Field isDebugEnabled:Z
       3: ifeq          16
       6: getstatic     #9                  // Field log:Lorg/apache/commons/logging/Log;
       9: ldc           #89                 // String WSDLWrapperReloadImpl.getNamespaces()
      11: invokeinterface #12,  2           // InterfaceMethod org/apache/commons/logging/Log.debug:(Ljava/lang/Object;)V
      16: aload_0
      17: getfield      #4                  // Field wsdlDefinition:Ljavax/wsdl/Definition;
      20: ifnull        33
      23: aload_0
      24: getfield      #4                  // Field wsdlDefinition:Ljavax/wsdl/Definition;
      27: invokeinterface #90,  1           // InterfaceMethod javax/wsdl/Definition.getNamespaces:()Ljava/util/Map;
      32: areturn
      33: aconst_null
      34: areturn

  public java.util.List getNativeAttributeNames();
    Code:
       0: getstatic     #17                 // Field isDebugEnabled:Z
       3: ifeq          16
       6: getstatic     #9                  // Field log:Lorg/apache/commons/logging/Log;
       9: ldc           #91                 // String WSDLWrapperReloadImpl.getNativeAttributeNames()
      11: invokeinterface #12,  2           // InterfaceMethod org/apache/commons/logging/Log.debug:(Ljava/lang/Object;)V
      16: aload_0
      17: getfield      #4                  // Field wsdlDefinition:Ljavax/wsdl/Definition;
      20: ifnull        33
      23: aload_0
      24: getfield      #4                  // Field wsdlDefinition:Ljavax/wsdl/Definition;
      27: invokeinterface #92,  1           // InterfaceMethod javax/wsdl/Definition.getNativeAttributeNames:()Ljava/util/List;
      32: areturn
      33: aconst_null
      34: areturn

  public void setTypes(javax.wsdl.Types);
    Code:
       0: aload_0
       1: getfield      #4                  // Field wsdlDefinition:Ljavax/wsdl/Definition;
       4: ifnull        46
       7: getstatic     #17                 // Field isDebugEnabled:Z
      10: ifeq          23
      13: getstatic     #9                  // Field log:Lorg/apache/commons/logging/Log;
      16: ldc           #93                 // String WSDLWrapperReloadImpl.setTypes() from wsdl Definition
      18: invokeinterface #12,  2           // InterfaceMethod org/apache/commons/logging/Log.debug:(Ljava/lang/Object;)V
      23: aload_0
      24: getfield      #4                  // Field wsdlDefinition:Ljavax/wsdl/Definition;
      27: aload_1
      28: invokeinterface #49,  2           // InterfaceMethod javax/wsdl/Definition.setTypes:(Ljavax/wsdl/Types;)V
      33: aload_0
      34: getfield      #4                  // Field wsdlDefinition:Ljavax/wsdl/Definition;
      37: aconst_null
      38: invokeinterface #49,  2           // InterfaceMethod javax/wsdl/Definition.setTypes:(Ljavax/wsdl/Types;)V
      43: goto          62
      46: getstatic     #17                 // Field isDebugEnabled:Z
      49: ifeq          62
      52: getstatic     #9                  // Field log:Lorg/apache/commons/logging/Log;
      55: ldc           #94                 // String WSDLWrapperReloadImpl.setTypes(): nothing to set
      57: invokeinterface #12,  2           // InterfaceMethod org/apache/commons/logging/Log.debug:(Ljava/lang/Object;)V
      62: return

  public javax.wsdl.Types getTypes();
    Code:
       0: getstatic     #17                 // Field isDebugEnabled:Z
       3: ifeq          35
       6: getstatic     #9                  // Field log:Lorg/apache/commons/logging/Log;
       9: new           #18                 // class java/lang/StringBuilder
      12: dup
      13: invokespecial #19                 // Method java/lang/StringBuilder."<init>":()V
      16: ldc           #95                 // String WSDLWrapperReloadImpl.getTypes() call stack =
      18: invokevirtual #22                 // Method java/lang/StringBuilder.append:(Ljava/lang/String;)Ljava/lang/StringBuilder;
      21: invokestatic  #13                 // Method org/apache/axis2/util/JavaUtils.callStackToString:()Ljava/lang/String;
      24: invokevirtual #22                 // Method java/lang/StringBuilder.append:(Ljava/lang/String;)Ljava/lang/StringBuilder;
      27: invokevirtual #24                 // Method java/lang/StringBuilder.toString:()Ljava/lang/String;
      30: invokeinterface #14,  2           // InterfaceMethod org/apache/commons/logging/Log.trace:(Ljava/lang/Object;)V
      35: aload_0
      36: invokespecial #96                 // Method hasCachedTypes:()Z
      39: ifeq          87
      42: aload_0
      43: invokespecial #97                 // Method getCachedTypes:()Ljavax/wsdl/Types;
      46: astore_1
      47: getstatic     #17                 // Field isDebugEnabled:Z
      50: ifeq          85
      53: getstatic     #9                  // Field log:Lorg/apache/commons/logging/Log;
      56: new           #18                 // class java/lang/StringBuilder
      59: dup
      60: invokespecial #19                 // Method java/lang/StringBuilder."<init>":()V
      63: ldc           #98                 // String WSDLWrapperReloadImpl.getTypes() from soft reference [
      65: invokevirtual #22                 // Method java/lang/StringBuilder.append:(Ljava/lang/String;)Ljava/lang/StringBuilder;
      68: aload_1
      69: invokevirtual #23                 // Method java/lang/StringBuilder.append:(Ljava/lang/Object;)Ljava/lang/StringBuilder;
      72: ldc           #35                 // String ]
      74: invokevirtual #22                 // Method java/lang/StringBuilder.append:(Ljava/lang/String;)Ljava/lang/StringBuilder;
      77: invokevirtual #24                 // Method java/lang/StringBuilder.toString:()Ljava/lang/String;
      80: invokeinterface #12,  2           // InterfaceMethod org/apache/commons/logging/Log.debug:(Ljava/lang/Object;)V
      85: aload_1
      86: areturn
      87: aconst_null
      88: astore_1
      89: aload_0
      90: invokespecial #62                 // Method loadDefinition:()Ljavax/wsdl/Definition;
      93: astore_1
      94: goto          155
      97: astore_2
      98: getstatic     #17                 // Field isDebugEnabled:Z
     101: ifeq          155
     104: getstatic     #9                  // Field log:Lorg/apache/commons/logging/Log;
     107: new           #18                 // class java/lang/StringBuilder
     110: dup
     111: invokespecial #19                 // Method java/lang/StringBuilder."<init>":()V
     114: ldc           #99                 // String WSDLWrapperReloadImpl.getTypes(): error trying to load Definition    [
     116: invokevirtual #22                 // Method java/lang/StringBuilder.append:(Ljava/lang/String;)Ljava/lang/StringBuilder;
     119: aload_2
     120: invokevirtual #31                 // Method java/lang/Object.getClass:()Ljava/lang/Class;
     123: invokevirtual #32                 // Method java/lang/Class.getName:()Ljava/lang/String;
     126: invokevirtual #22                 // Method java/lang/StringBuilder.append:(Ljava/lang/String;)Ljava/lang/StringBuilder;
     129: ldc           #33                 // String ]  error [
     131: invokevirtual #22                 // Method java/lang/StringBuilder.append:(Ljava/lang/String;)Ljava/lang/StringBuilder;
     134: aload_2
     135: invokevirtual #34                 // Method java/lang/Exception.getMessage:()Ljava/lang/String;
     138: invokevirtual #22                 // Method java/lang/StringBuilder.append:(Ljava/lang/String;)Ljava/lang/StringBuilder;
     141: ldc           #64                 // String ]
     143: invokevirtual #22                 // Method java/lang/StringBuilder.append:(Ljava/lang/String;)Ljava/lang/StringBuilder;
     146: invokevirtual #24                 // Method java/lang/StringBuilder.toString:()Ljava/lang/String;
     149: aload_2
     150: invokeinterface #36,  3           // InterfaceMethod org/apache/commons/logging/Log.debug:(Ljava/lang/Object;Ljava/lang/Throwable;)V
     155: aload_1
     156: ifnull        221
     159: aload_1
     160: invokeinterface #48,  1           // InterfaceMethod javax/wsdl/Definition.getTypes:()Ljavax/wsdl/Types;
     165: astore_2
     166: aload_0
     167: aload_2
     168: invokespecial #50                 // Method setCachedTypes:(Ljavax/wsdl/Types;)V
     171: aload_0
     172: aload_1
     173: invokeinterface #51,  1           // InterfaceMethod javax/wsdl/Definition.getDocumentationElement:()Lorg/w3c/dom/Element;
     178: invokespecial #53                 // Method setCachedDocElement:(Lorg/w3c/dom/Element;)V
     181: getstatic     #17                 // Field isDebugEnabled:Z
     184: ifeq          219
     187: getstatic     #9                  // Field log:Lorg/apache/commons/logging/Log;
     190: new           #18                 // class java/lang/StringBuilder
     193: dup
     194: invokespecial #19                 // Method java/lang/StringBuilder."<init>":()V
     197: ldc           #100                // String WSDLWrapperReloadImpl.getTypes() from reloaded wsdl Definition returning [
     199: invokevirtual #22                 // Method java/lang/StringBuilder.append:(Ljava/lang/String;)Ljava/lang/StringBuilder;
     202: aload_2
     203: invokevirtual #23                 // Method java/lang/StringBuilder.append:(Ljava/lang/Object;)Ljava/lang/StringBuilder;
     206: ldc           #35                 // String ]
     208: invokevirtual #22                 // Method java/lang/StringBuilder.append:(Ljava/lang/String;)Ljava/lang/StringBuilder;
     211: invokevirtual #24                 // Method java/lang/StringBuilder.toString:()Ljava/lang/String;
     214: invokeinterface #12,  2           // InterfaceMethod org/apache/commons/logging/Log.debug:(Ljava/lang/Object;)V
     219: aload_2
     220: areturn
     221: getstatic     #17                 // Field isDebugEnabled:Z
     224: ifeq          237
     227: getstatic     #9                  // Field log:Lorg/apache/commons/logging/Log;
     230: ldc           #101                // String WSDLWrapperReloadImpl.getTypes() returning NULL
     232: invokeinterface #12,  2           // InterfaceMethod org/apache/commons/logging/Log.debug:(Ljava/lang/Object;)V
     237: aconst_null
     238: areturn
    Exception table:
       from    to  target type
          89    94    97   Class java/lang/Exception

  public void addImport(javax.wsdl.Import);
    Code:
       0: getstatic     #17                 // Field isDebugEnabled:Z
       3: ifeq          38
       6: getstatic     #9                  // Field log:Lorg/apache/commons/logging/Log;
       9: new           #18                 // class java/lang/StringBuilder
      12: dup
      13: invokespecial #19                 // Method java/lang/StringBuilder."<init>":()V
      16: ldc           #102                // String WSDLWrapperReloadImpl.addImport(
      18: invokevirtual #22                 // Method java/lang/StringBuilder.append:(Ljava/lang/String;)Ljava/lang/StringBuilder;
      21: aload_1
      22: invokevirtual #23                 // Method java/lang/StringBuilder.append:(Ljava/lang/Object;)Ljava/lang/StringBuilder;
      25: ldc           #69                 // String )
      27: invokevirtual #22                 // Method java/lang/StringBuilder.append:(Ljava/lang/String;)Ljava/lang/StringBuilder;
      30: invokevirtual #24                 // Method java/lang/StringBuilder.toString:()Ljava/lang/String;
      33: invokeinterface #12,  2           // InterfaceMethod org/apache/commons/logging/Log.debug:(Ljava/lang/Object;)V
      38: aload_0
      39: getfield      #4                  // Field wsdlDefinition:Ljavax/wsdl/Definition;
      42: ifnull        55
      45: aload_0
      46: getfield      #4                  // Field wsdlDefinition:Ljavax/wsdl/Definition;
      49: aload_1
      50: invokeinterface #103,  2          // InterfaceMethod javax/wsdl/Definition.addImport:(Ljavax/wsdl/Import;)V
      55: return

  public javax.wsdl.Import removeImport(javax.wsdl.Import);
    Code:
       0: getstatic     #17                 // Field isDebugEnabled:Z
       3: ifeq          38
       6: getstatic     #9                  // Field log:Lorg/apache/commons/logging/Log;
       9: new           #18                 // class java/lang/StringBuilder
      12: dup
      13: invokespecial #19                 // Method java/lang/StringBuilder."<init>":()V
      16: ldc           #104                // String WSDLWrapperReloadImpl.removeImport(
      18: invokevirtual #22                 // Method java/lang/StringBuilder.append:(Ljava/lang/String;)Ljava/lang/StringBuilder;
      21: aload_1
      22: invokevirtual #23                 // Method java/lang/StringBuilder.append:(Ljava/lang/Object;)Ljava/lang/StringBuilder;
      25: ldc           #69                 // String )
      27: invokevirtual #22                 // Method java/lang/StringBuilder.append:(Ljava/lang/String;)Ljava/lang/StringBuilder;
      30: invokevirtual #24                 // Method java/lang/StringBuilder.toString:()Ljava/lang/String;
      33: invokeinterface #12,  2           // InterfaceMethod org/apache/commons/logging/Log.debug:(Ljava/lang/Object;)V
      38: aload_0
      39: getfield      #4                  // Field wsdlDefinition:Ljavax/wsdl/Definition;
      42: ifnull        56
      45: aload_0
      46: getfield      #4                  // Field wsdlDefinition:Ljavax/wsdl/Definition;
      49: aload_1
      50: invokeinterface #105,  2          // InterfaceMethod javax/wsdl/Definition.removeImport:(Ljavax/wsdl/Import;)Ljavax/wsdl/Import;
      55: areturn
      56: aconst_null
      57: areturn

  public java.util.List getImports(java.lang.String);
    Code:
       0: getstatic     #17                 // Field isDebugEnabled:Z
       3: ifeq          38
       6: getstatic     #9                  // Field log:Lorg/apache/commons/logging/Log;
       9: new           #18                 // class java/lang/StringBuilder
      12: dup
      13: invokespecial #19                 // Method java/lang/StringBuilder."<init>":()V
      16: ldc           #106                // String WSDLWrapperReloadImpl.getImports(
      18: invokevirtual #22                 // Method java/lang/StringBuilder.append:(Ljava/lang/String;)Ljava/lang/StringBuilder;
      21: aload_1
      22: invokevirtual #22                 // Method java/lang/StringBuilder.append:(Ljava/lang/String;)Ljava/lang/StringBuilder;
      25: ldc           #69                 // String )
      27: invokevirtual #22                 // Method java/lang/StringBuilder.append:(Ljava/lang/String;)Ljava/lang/StringBuilder;
      30: invokevirtual #24                 // Method java/lang/StringBuilder.toString:()Ljava/lang/String;
      33: invokeinterface #12,  2           // InterfaceMethod org/apache/commons/logging/Log.debug:(Ljava/lang/Object;)V
      38: aload_0
      39: getfield      #4                  // Field wsdlDefinition:Ljavax/wsdl/Definition;
      42: ifnull        56
      45: aload_0
      46: getfield      #4                  // Field wsdlDefinition:Ljavax/wsdl/Definition;
      49: aload_1
      50: invokeinterface #107,  2          // InterfaceMethod javax/wsdl/Definition.getImports:(Ljava/lang/String;)Ljava/util/List;
      55: areturn
      56: aconst_null
      57: areturn

  public java.util.Map getImports();
    Code:
       0: getstatic     #17                 // Field isDebugEnabled:Z
       3: ifeq          16
       6: getstatic     #9                  // Field log:Lorg/apache/commons/logging/Log;
       9: ldc           #108                // String WSDLWrapperReloadImpl.getImports()
      11: invokeinterface #12,  2           // InterfaceMethod org/apache/commons/logging/Log.debug:(Ljava/lang/Object;)V
      16: aload_0
      17: getfield      #4                  // Field wsdlDefinition:Ljavax/wsdl/Definition;
      20: ifnull        33
      23: aload_0
      24: getfield      #4                  // Field wsdlDefinition:Ljavax/wsdl/Definition;
      27: invokeinterface #109,  1          // InterfaceMethod javax/wsdl/Definition.getImports:()Ljava/util/Map;
      32: areturn
      33: aconst_null
      34: areturn

  public void addMessage(javax.wsdl.Message);
    Code:
       0: getstatic     #17                 // Field isDebugEnabled:Z
       3: ifeq          38
       6: getstatic     #9                  // Field log:Lorg/apache/commons/logging/Log;
       9: new           #18                 // class java/lang/StringBuilder
      12: dup
      13: invokespecial #19                 // Method java/lang/StringBuilder."<init>":()V
      16: ldc           #110                // String WSDLWrapperReloadImpl.addMessage(
      18: invokevirtual #22                 // Method java/lang/StringBuilder.append:(Ljava/lang/String;)Ljava/lang/StringBuilder;
      21: aload_1
      22: invokevirtual #23                 // Method java/lang/StringBuilder.append:(Ljava/lang/Object;)Ljava/lang/StringBuilder;
      25: ldc           #69                 // String )
      27: invokevirtual #22                 // Method java/lang/StringBuilder.append:(Ljava/lang/String;)Ljava/lang/StringBuilder;
      30: invokevirtual #24                 // Method java/lang/StringBuilder.toString:()Ljava/lang/String;
      33: invokeinterface #12,  2           // InterfaceMethod org/apache/commons/logging/Log.debug:(Ljava/lang/Object;)V
      38: aload_0
      39: getfield      #4                  // Field wsdlDefinition:Ljavax/wsdl/Definition;
      42: ifnull        55
      45: aload_0
      46: getfield      #4                  // Field wsdlDefinition:Ljavax/wsdl/Definition;
      49: aload_1
      50: invokeinterface #111,  2          // InterfaceMethod javax/wsdl/Definition.addMessage:(Ljavax/wsdl/Message;)V
      55: return

  public javax.wsdl.Message getMessage(javax.xml.namespace.QName);
    Code:
       0: getstatic     #17                 // Field isDebugEnabled:Z
       3: ifeq          38
       6: getstatic     #9                  // Field log:Lorg/apache/commons/logging/Log;
       9: new           #18                 // class java/lang/StringBuilder
      12: dup
      13: invokespecial #19                 // Method java/lang/StringBuilder."<init>":()V
      16: ldc           #112                // String WSDLWrapperReloadImpl.getMessage(
      18: invokevirtual #22                 // Method java/lang/StringBuilder.append:(Ljava/lang/String;)Ljava/lang/StringBuilder;
      21: aload_1
      22: invokevirtual #23                 // Method java/lang/StringBuilder.append:(Ljava/lang/Object;)Ljava/lang/StringBuilder;
      25: ldc           #69                 // String )
      27: invokevirtual #22                 // Method java/lang/StringBuilder.append:(Ljava/lang/String;)Ljava/lang/StringBuilder;
      30: invokevirtual #24                 // Method java/lang/StringBuilder.toString:()Ljava/lang/String;
      33: invokeinterface #12,  2           // InterfaceMethod org/apache/commons/logging/Log.debug:(Ljava/lang/Object;)V
      38: aload_0
      39: getfield      #4                  // Field wsdlDefinition:Ljavax/wsdl/Definition;
      42: ifnull        56
      45: aload_0
      46: getfield      #4                  // Field wsdlDefinition:Ljavax/wsdl/Definition;
      49: aload_1
      50: invokeinterface #113,  2          // InterfaceMethod javax/wsdl/Definition.getMessage:(Ljavax/xml/namespace/QName;)Ljavax/wsdl/Message;
      55: areturn
      56: aconst_null
      57: areturn

  public javax.wsdl.Message removeMessage(javax.xml.namespace.QName);
    Code:
       0: getstatic     #17                 // Field isDebugEnabled:Z
       3: ifeq          38
       6: getstatic     #9                  // Field log:Lorg/apache/commons/logging/Log;
       9: new           #18                 // class java/lang/StringBuilder
      12: dup
      13: invokespecial #19                 // Method java/lang/StringBuilder."<init>":()V
      16: ldc           #114                // String WSDLWrapperReloadImpl.removeMessage(
      18: invokevirtual #22                 // Method java/lang/StringBuilder.append:(Ljava/lang/String;)Ljava/lang/StringBuilder;
      21: aload_1
      22: invokevirtual #23                 // Method java/lang/StringBuilder.append:(Ljava/lang/Object;)Ljava/lang/StringBuilder;
      25: ldc           #69                 // String )
      27: invokevirtual #22                 // Method java/lang/StringBuilder.append:(Ljava/lang/String;)Ljava/lang/StringBuilder;
      30: invokevirtual #24                 // Method java/lang/StringBuilder.toString:()Ljava/lang/String;
      33: invokeinterface #12,  2           // InterfaceMethod org/apache/commons/logging/Log.debug:(Ljava/lang/Object;)V
      38: aload_0
      39: getfield      #4                  // Field wsdlDefinition:Ljavax/wsdl/Definition;
      42: ifnull        56
      45: aload_0
      46: getfield      #4                  // Field wsdlDefinition:Ljavax/wsdl/Definition;
      49: aload_1
      50: invokeinterface #115,  2          // InterfaceMethod javax/wsdl/Definition.removeMessage:(Ljavax/xml/namespace/QName;)Ljavax/wsdl/Message;
      55: areturn
      56: aconst_null
      57: areturn

  public java.util.Map getMessages();
    Code:
       0: getstatic     #17                 // Field isDebugEnabled:Z
       3: ifeq          16
       6: getstatic     #9                  // Field log:Lorg/apache/commons/logging/Log;
       9: ldc           #116                // String WSDLWrapperReloadImpl.getMessages()
      11: invokeinterface #12,  2           // InterfaceMethod org/apache/commons/logging/Log.debug:(Ljava/lang/Object;)V
      16: aload_0
      17: getfield      #4                  // Field wsdlDefinition:Ljavax/wsdl/Definition;
      20: ifnull        33
      23: aload_0
      24: getfield      #4                  // Field wsdlDefinition:Ljavax/wsdl/Definition;
      27: invokeinterface #117,  1          // InterfaceMethod javax/wsdl/Definition.getMessages:()Ljava/util/Map;
      32: areturn
      33: aconst_null
      34: areturn

  public void addBinding(javax.wsdl.Binding);
    Code:
       0: getstatic     #17                 // Field isDebugEnabled:Z
       3: ifeq          38
       6: getstatic     #9                  // Field log:Lorg/apache/commons/logging/Log;
       9: new           #18                 // class java/lang/StringBuilder
      12: dup
      13: invokespecial #19                 // Method java/lang/StringBuilder."<init>":()V
      16: ldc           #118                // String WSDLWrapperReloadImpl.addBinding(
      18: invokevirtual #22                 // Method java/lang/StringBuilder.append:(Ljava/lang/String;)Ljava/lang/StringBuilder;
      21: aload_1
      22: invokevirtual #23                 // Method java/lang/StringBuilder.append:(Ljava/lang/Object;)Ljava/lang/StringBuilder;
      25: ldc           #69                 // String )
      27: invokevirtual #22                 // Method java/lang/StringBuilder.append:(Ljava/lang/String;)Ljava/lang/StringBuilder;
      30: invokevirtual #24                 // Method java/lang/StringBuilder.toString:()Ljava/lang/String;
      33: invokeinterface #12,  2           // InterfaceMethod org/apache/commons/logging/Log.debug:(Ljava/lang/Object;)V
      38: aload_0
      39: getfield      #4                  // Field wsdlDefinition:Ljavax/wsdl/Definition;
      42: ifnull        55
      45: aload_0
      46: getfield      #4                  // Field wsdlDefinition:Ljavax/wsdl/Definition;
      49: aload_1
      50: invokeinterface #119,  2          // InterfaceMethod javax/wsdl/Definition.addBinding:(Ljavax/wsdl/Binding;)V
      55: return

  public javax.wsdl.Binding getBinding(javax.xml.namespace.QName);
    Code:
       0: getstatic     #17                 // Field isDebugEnabled:Z
       3: ifeq          38
       6: getstatic     #9                  // Field log:Lorg/apache/commons/logging/Log;
       9: new           #18                 // class java/lang/StringBuilder
      12: dup
      13: invokespecial #19                 // Method java/lang/StringBuilder."<init>":()V
      16: ldc           #120                // String WSDLWrapperReloadImpl.getBinding(
      18: invokevirtual #22                 // Method java/lang/StringBuilder.append:(Ljava/lang/String;)Ljava/lang/StringBuilder;
      21: aload_1
      22: invokevirtual #23                 // Method java/lang/StringBuilder.append:(Ljava/lang/Object;)Ljava/lang/StringBuilder;
      25: ldc           #69                 // String )
      27: invokevirtual #22                 // Method java/lang/StringBuilder.append:(Ljava/lang/String;)Ljava/lang/StringBuilder;
      30: invokevirtual #24                 // Method java/lang/StringBuilder.toString:()Ljava/lang/String;
      33: invokeinterface #12,  2           // InterfaceMethod org/apache/commons/logging/Log.debug:(Ljava/lang/Object;)V
      38: aload_0
      39: getfield      #4                  // Field wsdlDefinition:Ljavax/wsdl/Definition;
      42: ifnull        56
      45: aload_0
      46: getfield      #4                  // Field wsdlDefinition:Ljavax/wsdl/Definition;
      49: aload_1
      50: invokeinterface #121,  2          // InterfaceMethod javax/wsdl/Definition.getBinding:(Ljavax/xml/namespace/QName;)Ljavax/wsdl/Binding;
      55: areturn
      56: aconst_null
      57: areturn

  public javax.wsdl.Binding removeBinding(javax.xml.namespace.QName);
    Code:
       0: getstatic     #17                 // Field isDebugEnabled:Z
       3: ifeq          38
       6: getstatic     #9                  // Field log:Lorg/apache/commons/logging/Log;
       9: new           #18                 // class java/lang/StringBuilder
      12: dup
      13: invokespecial #19                 // Method java/lang/StringBuilder."<init>":()V
      16: ldc           #122                // String WSDLWrapperReloadImpl.removeBinding(
      18: invokevirtual #22                 // Method java/lang/StringBuilder.append:(Ljava/lang/String;)Ljava/lang/StringBuilder;
      21: aload_1
      22: invokevirtual #23                 // Method java/lang/StringBuilder.append:(Ljava/lang/Object;)Ljava/lang/StringBuilder;
      25: ldc           #69                 // String )
      27: invokevirtual #22                 // Method java/lang/StringBuilder.append:(Ljava/lang/String;)Ljava/lang/StringBuilder;
      30: invokevirtual #24                 // Method java/lang/StringBuilder.toString:()Ljava/lang/String;
      33: invokeinterface #12,  2           // InterfaceMethod org/apache/commons/logging/Log.debug:(Ljava/lang/Object;)V
      38: aload_0
      39: getfield      #4                  // Field wsdlDefinition:Ljavax/wsdl/Definition;
      42: ifnull        56
      45: aload_0
      46: getfield      #4                  // Field wsdlDefinition:Ljavax/wsdl/Definition;
      49: aload_1
      50: invokeinterface #123,  2          // InterfaceMethod javax/wsdl/Definition.removeBinding:(Ljavax/xml/namespace/QName;)Ljavax/wsdl/Binding;
      55: areturn
      56: aconst_null
      57: areturn

  public java.util.Map getBindings();
    Code:
       0: getstatic     #17                 // Field isDebugEnabled:Z
       3: ifeq          16
       6: getstatic     #9                  // Field log:Lorg/apache/commons/logging/Log;
       9: ldc           #124                // String WSDLWrapperReloadImpl.getBindings()
      11: invokeinterface #12,  2           // InterfaceMethod org/apache/commons/logging/Log.debug:(Ljava/lang/Object;)V
      16: aload_0
      17: getfield      #4                  // Field wsdlDefinition:Ljavax/wsdl/Definition;
      20: ifnull        33
      23: aload_0
      24: getfield      #4                  // Field wsdlDefinition:Ljavax/wsdl/Definition;
      27: invokeinterface #125,  1          // InterfaceMethod javax/wsdl/Definition.getBindings:()Ljava/util/Map;
      32: areturn
      33: aconst_null
      34: areturn

  public java.util.Map getAllBindings();
    Code:
       0: getstatic     #17                 // Field isDebugEnabled:Z
       3: ifeq          16
       6: getstatic     #9                  // Field log:Lorg/apache/commons/logging/Log;
       9: ldc           #126                // String WSDLWrapperReloadImpl.getAllBindings()
      11: invokeinterface #12,  2           // InterfaceMethod org/apache/commons/logging/Log.debug:(Ljava/lang/Object;)V
      16: aload_0
      17: getfield      #4                  // Field wsdlDefinition:Ljavax/wsdl/Definition;
      20: ifnull        33
      23: aload_0
      24: getfield      #4                  // Field wsdlDefinition:Ljavax/wsdl/Definition;
      27: invokeinterface #127,  1          // InterfaceMethod javax/wsdl/Definition.getAllBindings:()Ljava/util/Map;
      32: areturn
      33: aconst_null
      34: areturn

  public void addPortType(javax.wsdl.PortType);
    Code:
       0: getstatic     #17                 // Field isDebugEnabled:Z
       3: ifeq          38
       6: getstatic     #9                  // Field log:Lorg/apache/commons/logging/Log;
       9: new           #18                 // class java/lang/StringBuilder
      12: dup
      13: invokespecial #19                 // Method java/lang/StringBuilder."<init>":()V
      16: ldc           #128                // String WSDLWrapperReloadImpl.addPortType(
      18: invokevirtual #22                 // Method java/lang/StringBuilder.append:(Ljava/lang/String;)Ljava/lang/StringBuilder;
      21: aload_1
      22: invokevirtual #23                 // Method java/lang/StringBuilder.append:(Ljava/lang/Object;)Ljava/lang/StringBuilder;
      25: ldc           #69                 // String )
      27: invokevirtual #22                 // Method java/lang/StringBuilder.append:(Ljava/lang/String;)Ljava/lang/StringBuilder;
      30: invokevirtual #24                 // Method java/lang/StringBuilder.toString:()Ljava/lang/String;
      33: invokeinterface #12,  2           // InterfaceMethod org/apache/commons/logging/Log.debug:(Ljava/lang/Object;)V
      38: aload_0
      39: getfield      #4                  // Field wsdlDefinition:Ljavax/wsdl/Definition;
      42: ifnull        55
      45: aload_0
      46: getfield      #4                  // Field wsdlDefinition:Ljavax/wsdl/Definition;
      49: aload_1
      50: invokeinterface #129,  2          // InterfaceMethod javax/wsdl/Definition.addPortType:(Ljavax/wsdl/PortType;)V
      55: return

  public javax.wsdl.PortType getPortType(javax.xml.namespace.QName);
    Code:
       0: getstatic     #17                 // Field isDebugEnabled:Z
       3: ifeq          38
       6: getstatic     #9                  // Field log:Lorg/apache/commons/logging/Log;
       9: new           #18                 // class java/lang/StringBuilder
      12: dup
      13: invokespecial #19                 // Method java/lang/StringBuilder."<init>":()V
      16: ldc           #130                // String WSDLWrapperReloadImpl.getPortType(
      18: invokevirtual #22                 // Method java/lang/StringBuilder.append:(Ljava/lang/String;)Ljava/lang/StringBuilder;
      21: aload_1
      22: invokevirtual #23                 // Method java/lang/StringBuilder.append:(Ljava/lang/Object;)Ljava/lang/StringBuilder;
      25: ldc           #69                 // String )
      27: invokevirtual #22                 // Method java/lang/StringBuilder.append:(Ljava/lang/String;)Ljava/lang/StringBuilder;
      30: invokevirtual #24                 // Method java/lang/StringBuilder.toString:()Ljava/lang/String;
      33: invokeinterface #12,  2           // InterfaceMethod org/apache/commons/logging/Log.debug:(Ljava/lang/Object;)V
      38: aload_0
      39: getfield      #4                  // Field wsdlDefinition:Ljavax/wsdl/Definition;
      42: ifnull        56
      45: aload_0
      46: getfield      #4                  // Field wsdlDefinition:Ljavax/wsdl/Definition;
      49: aload_1
      50: invokeinterface #131,  2          // InterfaceMethod javax/wsdl/Definition.getPortType:(Ljavax/xml/namespace/QName;)Ljavax/wsdl/PortType;
      55: areturn
      56: aconst_null
      57: areturn

  public javax.wsdl.PortType removePortType(javax.xml.namespace.QName);
    Code:
       0: getstatic     #17                 // Field isDebugEnabled:Z
       3: ifeq          38
       6: getstatic     #9                  // Field log:Lorg/apache/commons/logging/Log;
       9: new           #18                 // class java/lang/StringBuilder
      12: dup
      13: invokespecial #19                 // Method java/lang/StringBuilder."<init>":()V
      16: ldc           #132                // String WSDLWrapperReloadImpl.removePortType(
      18: invokevirtual #22                 // Method java/lang/StringBuilder.append:(Ljava/lang/String;)Ljava/lang/StringBuilder;
      21: aload_1
      22: invokevirtual #23                 // Method java/lang/StringBuilder.append:(Ljava/lang/Object;)Ljava/lang/StringBuilder;
      25: ldc           #69                 // String )
      27: invokevirtual #22                 // Method java/lang/StringBuilder.append:(Ljava/lang/String;)Ljava/lang/StringBuilder;
      30: invokevirtual #24                 // Method java/lang/StringBuilder.toString:()Ljava/lang/String;
      33: invokeinterface #12,  2           // InterfaceMethod org/apache/commons/logging/Log.debug:(Ljava/lang/Object;)V
      38: aload_0
      39: getfield      #4                  // Field wsdlDefinition:Ljavax/wsdl/Definition;
      42: ifnull        56
      45: aload_0
      46: getfield      #4                  // Field wsdlDefinition:Ljavax/wsdl/Definition;
      49: aload_1
      50: invokeinterface #133,  2          // InterfaceMethod javax/wsdl/Definition.removePortType:(Ljavax/xml/namespace/QName;)Ljavax/wsdl/PortType;
      55: areturn
      56: aconst_null
      57: areturn

  public java.util.Map getPortTypes();
    Code:
       0: getstatic     #17                 // Field isDebugEnabled:Z
       3: ifeq          16
       6: getstatic     #9                  // Field log:Lorg/apache/commons/logging/Log;
       9: ldc           #134                // String WSDLWrapperReloadImpl.getPortTypes()
      11: invokeinterface #12,  2           // InterfaceMethod org/apache/commons/logging/Log.debug:(Ljava/lang/Object;)V
      16: aload_0
      17: getfield      #4                  // Field wsdlDefinition:Ljavax/wsdl/Definition;
      20: ifnull        33
      23: aload_0
      24: getfield      #4                  // Field wsdlDefinition:Ljavax/wsdl/Definition;
      27: invokeinterface #135,  1          // InterfaceMethod javax/wsdl/Definition.getPortTypes:()Ljava/util/Map;
      32: areturn
      33: aconst_null
      34: areturn

  public java.util.Map getAllPortTypes();
    Code:
       0: getstatic     #17                 // Field isDebugEnabled:Z
       3: ifeq          16
       6: getstatic     #9                  // Field log:Lorg/apache/commons/logging/Log;
       9: ldc           #136                // String WSDLWrapperReloadImpl.getAllPortTypes()
      11: invokeinterface #12,  2           // InterfaceMethod org/apache/commons/logging/Log.debug:(Ljava/lang/Object;)V
      16: aload_0
      17: getfield      #4                  // Field wsdlDefinition:Ljavax/wsdl/Definition;
      20: ifnull        33
      23: aload_0
      24: getfield      #4                  // Field wsdlDefinition:Ljavax/wsdl/Definition;
      27: invokeinterface #137,  1          // InterfaceMethod javax/wsdl/Definition.getAllPortTypes:()Ljava/util/Map;
      32: areturn
      33: aconst_null
      34: areturn

  public void addService(javax.wsdl.Service);
    Code:
       0: getstatic     #17                 // Field isDebugEnabled:Z
       3: ifeq          38
       6: getstatic     #9                  // Field log:Lorg/apache/commons/logging/Log;
       9: new           #18                 // class java/lang/StringBuilder
      12: dup
      13: invokespecial #19                 // Method java/lang/StringBuilder."<init>":()V
      16: ldc           #138                // String WSDLWrapperReloadImpl.addService(
      18: invokevirtual #22                 // Method java/lang/StringBuilder.append:(Ljava/lang/String;)Ljava/lang/StringBuilder;
      21: aload_1
      22: invokevirtual #23                 // Method java/lang/StringBuilder.append:(Ljava/lang/Object;)Ljava/lang/StringBuilder;
      25: ldc           #69                 // String )
      27: invokevirtual #22                 // Method java/lang/StringBuilder.append:(Ljava/lang/String;)Ljava/lang/StringBuilder;
      30: invokevirtual #24                 // Method java/lang/StringBuilder.toString:()Ljava/lang/String;
      33: invokeinterface #12,  2           // InterfaceMethod org/apache/commons/logging/Log.debug:(Ljava/lang/Object;)V
      38: aload_0
      39: getfield      #4                  // Field wsdlDefinition:Ljavax/wsdl/Definition;
      42: ifnull        55
      45: aload_0
      46: getfield      #4                  // Field wsdlDefinition:Ljavax/wsdl/Definition;
      49: aload_1
      50: invokeinterface #139,  2          // InterfaceMethod javax/wsdl/Definition.addService:(Ljavax/wsdl/Service;)V
      55: return

  public javax.wsdl.Service getService(javax.xml.namespace.QName);
    Code:
       0: getstatic     #17                 // Field isDebugEnabled:Z
       3: ifeq          38
       6: getstatic     #9                  // Field log:Lorg/apache/commons/logging/Log;
       9: new           #18                 // class java/lang/StringBuilder
      12: dup
      13: invokespecial #19                 // Method java/lang/StringBuilder."<init>":()V
      16: ldc           #140                // String WSDLWrapperReloadImpl.getService(
      18: invokevirtual #22                 // Method java/lang/StringBuilder.append:(Ljava/lang/String;)Ljava/lang/StringBuilder;
      21: aload_1
      22: invokevirtual #23                 // Method java/lang/StringBuilder.append:(Ljava/lang/Object;)Ljava/lang/StringBuilder;
      25: ldc           #69                 // String )
      27: invokevirtual #22                 // Method java/lang/StringBuilder.append:(Ljava/lang/String;)Ljava/lang/StringBuilder;
      30: invokevirtual #24                 // Method java/lang/StringBuilder.toString:()Ljava/lang/String;
      33: invokeinterface #12,  2           // InterfaceMethod org/apache/commons/logging/Log.debug:(Ljava/lang/Object;)V
      38: aload_0
      39: getfield      #4                  // Field wsdlDefinition:Ljavax/wsdl/Definition;
      42: ifnull        56
      45: aload_0
      46: getfield      #4                  // Field wsdlDefinition:Ljavax/wsdl/Definition;
      49: aload_1
      50: invokeinterface #141,  2          // InterfaceMethod javax/wsdl/Definition.getService:(Ljavax/xml/namespace/QName;)Ljavax/wsdl/Service;
      55: areturn
      56: aconst_null
      57: areturn

  public javax.wsdl.Service removeService(javax.xml.namespace.QName);
    Code:
       0: getstatic     #17                 // Field isDebugEnabled:Z
       3: ifeq          38
       6: getstatic     #9                  // Field log:Lorg/apache/commons/logging/Log;
       9: new           #18                 // class java/lang/StringBuilder
      12: dup
      13: invokespecial #19                 // Method java/lang/StringBuilder."<init>":()V
      16: ldc           #142                // String WSDLWrapperReloadImpl.removeService(
      18: invokevirtual #22                 // Method java/lang/StringBuilder.append:(Ljava/lang/String;)Ljava/lang/StringBuilder;
      21: aload_1
      22: invokevirtual #23                 // Method java/lang/StringBuilder.append:(Ljava/lang/Object;)Ljava/lang/StringBuilder;
      25: ldc           #69                 // String )
      27: invokevirtual #22                 // Method java/lang/StringBuilder.append:(Ljava/lang/String;)Ljava/lang/StringBuilder;
      30: invokevirtual #24                 // Method java/lang/StringBuilder.toString:()Ljava/lang/String;
      33: invokeinterface #12,  2           // InterfaceMethod org/apache/commons/logging/Log.debug:(Ljava/lang/Object;)V
      38: aload_0
      39: getfield      #4                  // Field wsdlDefinition:Ljavax/wsdl/Definition;
      42: ifnull        56
      45: aload_0
      46: getfield      #4                  // Field wsdlDefinition:Ljavax/wsdl/Definition;
      49: aload_1
      50: invokeinterface #143,  2          // InterfaceMethod javax/wsdl/Definition.removeService:(Ljavax/xml/namespace/QName;)Ljavax/wsdl/Service;
      55: areturn
      56: aconst_null
      57: areturn

  public java.util.Map getServices();
    Code:
       0: getstatic     #17                 // Field isDebugEnabled:Z
       3: ifeq          16
       6: getstatic     #9                  // Field log:Lorg/apache/commons/logging/Log;
       9: ldc           #144                // String WSDLWrapperReloadImpl.getServices()
      11: invokeinterface #12,  2           // InterfaceMethod org/apache/commons/logging/Log.debug:(Ljava/lang/Object;)V
      16: aload_0
      17: getfield      #4                  // Field wsdlDefinition:Ljavax/wsdl/Definition;
      20: ifnull        33
      23: aload_0
      24: getfield      #4                  // Field wsdlDefinition:Ljavax/wsdl/Definition;
      27: invokeinterface #145,  1          // InterfaceMethod javax/wsdl/Definition.getServices:()Ljava/util/Map;
      32: areturn
      33: aconst_null
      34: areturn

  public java.util.Map getAllServices();
    Code:
       0: getstatic     #17                 // Field isDebugEnabled:Z
       3: ifeq          16
       6: getstatic     #9                  // Field log:Lorg/apache/commons/logging/Log;
       9: ldc           #146                // String WSDLWrapperReloadImpl.getAllServices()
      11: invokeinterface #12,  2           // InterfaceMethod org/apache/commons/logging/Log.debug:(Ljava/lang/Object;)V
      16: aload_0
      17: getfield      #4                  // Field wsdlDefinition:Ljavax/wsdl/Definition;
      20: ifnull        33
      23: aload_0
      24: getfield      #4                  // Field wsdlDefinition:Ljavax/wsdl/Definition;
      27: invokeinterface #147,  1          // InterfaceMethod javax/wsdl/Definition.getAllServices:()Ljava/util/Map;
      32: areturn
      33: aconst_null
      34: areturn

  public void setDocumentationElement(org.w3c.dom.Element);
    Code:
       0: aload_0
       1: getfield      #4                  // Field wsdlDefinition:Ljavax/wsdl/Definition;
       4: ifnull        46
       7: getstatic     #17                 // Field isDebugEnabled:Z
      10: ifeq          23
      13: getstatic     #9                  // Field log:Lorg/apache/commons/logging/Log;
      16: ldc           #148                // String WSDLWrapperReloadImpl.setDocumentationElement(docEl) from wsdl Definition
      18: invokeinterface #12,  2           // InterfaceMethod org/apache/commons/logging/Log.debug:(Ljava/lang/Object;)V
      23: aload_0
      24: getfield      #4                  // Field wsdlDefinition:Ljavax/wsdl/Definition;
      27: aload_1
      28: invokeinterface #52,  2           // InterfaceMethod javax/wsdl/Definition.setDocumentationElement:(Lorg/w3c/dom/Element;)V
      33: aload_0
      34: getfield      #4                  // Field wsdlDefinition:Ljavax/wsdl/Definition;
      37: aconst_null
      38: invokeinterface #52,  2           // InterfaceMethod javax/wsdl/Definition.setDocumentationElement:(Lorg/w3c/dom/Element;)V
      43: goto          62
      46: getstatic     #17                 // Field isDebugEnabled:Z
      49: ifeq          62
      52: getstatic     #9                  // Field log:Lorg/apache/commons/logging/Log;
      55: ldc           #149                // String WSDLWrapperReloadImpl.setDocumentationElement(docEl): nothing to set
      57: invokeinterface #12,  2           // InterfaceMethod org/apache/commons/logging/Log.debug:(Ljava/lang/Object;)V
      62: return

  public org.w3c.dom.Element getDocumentationElement();
    Code:
       0: getstatic     #17                 // Field isDebugEnabled:Z
       3: ifeq          35
       6: getstatic     #9                  // Field log:Lorg/apache/commons/logging/Log;
       9: new           #18                 // class java/lang/StringBuilder
      12: dup
      13: invokespecial #19                 // Method java/lang/StringBuilder."<init>":()V
      16: ldc           #150                // String WSDLWrapperReloadImpl.getDocumentationElement() call stack =
      18: invokevirtual #22                 // Method java/lang/StringBuilder.append:(Ljava/lang/String;)Ljava/lang/StringBuilder;
      21: invokestatic  #13                 // Method org/apache/axis2/util/JavaUtils.callStackToString:()Ljava/lang/String;
      24: invokevirtual #22                 // Method java/lang/StringBuilder.append:(Ljava/lang/String;)Ljava/lang/StringBuilder;
      27: invokevirtual #24                 // Method java/lang/StringBuilder.toString:()Ljava/lang/String;
      30: invokeinterface #14,  2           // InterfaceMethod org/apache/commons/logging/Log.trace:(Ljava/lang/Object;)V
      35: aload_0
      36: invokespecial #151                // Method hasCachedDocElement:()Z
      39: ifeq          70
      42: aload_0
      43: invokespecial #152                // Method getCachedDocElement:()Lorg/w3c/dom/Element;
      46: astore_1
      47: getstatic     #9                  // Field log:Lorg/apache/commons/logging/Log;
      50: invokeinterface #10,  1           // InterfaceMethod org/apache/commons/logging/Log.isDebugEnabled:()Z
      55: ifeq          68
      58: getstatic     #9                  // Field log:Lorg/apache/commons/logging/Log;
      61: ldc           #153                // String WSDLWrapperReloadImpl.getDocumentationElement() from soft reference
      63: invokeinterface #12,  2           // InterfaceMethod org/apache/commons/logging/Log.debug:(Ljava/lang/Object;)V
      68: aload_1
      69: areturn
      70: getstatic     #17                 // Field isDebugEnabled:Z
      73: ifeq          86
      76: getstatic     #9                  // Field log:Lorg/apache/commons/logging/Log;
      79: ldc           #154                // String WSDLWrapperReloadImpl.getDocumentationElement() from reloaded wsdl Definition
      81: invokeinterface #12,  2           // InterfaceMethod org/apache/commons/logging/Log.debug:(Ljava/lang/Object;)V
      86: aconst_null
      87: astore_1
      88: aload_0
      89: invokespecial #62                 // Method loadDefinition:()Ljavax/wsdl/Definition;
      92: astore_1
      93: goto          154
      96: astore_2
      97: getstatic     #17                 // Field isDebugEnabled:Z
     100: ifeq          154
     103: getstatic     #9                  // Field log:Lorg/apache/commons/logging/Log;
     106: new           #18                 // class java/lang/StringBuilder
     109: dup
     110: invokespecial #19                 // Method java/lang/StringBuilder."<init>":()V
     113: ldc           #155                // String WSDLWrapperReloadImpl.getDocumentationElement(): error trying to load Definition    [
     115: invokevirtual #22                 // Method java/lang/StringBuilder.append:(Ljava/lang/String;)Ljava/lang/StringBuilder;
     118: aload_2
     119: invokevirtual #31                 // Method java/lang/Object.getClass:()Ljava/lang/Class;
     122: invokevirtual #32                 // Method java/lang/Class.getName:()Ljava/lang/String;
     125: invokevirtual #22                 // Method java/lang/StringBuilder.append:(Ljava/lang/String;)Ljava/lang/StringBuilder;
     128: ldc           #33                 // String ]  error [
     130: invokevirtual #22                 // Method java/lang/StringBuilder.append:(Ljava/lang/String;)Ljava/lang/StringBuilder;
     133: aload_2
     134: invokevirtual #34                 // Method java/lang/Exception.getMessage:()Ljava/lang/String;
     137: invokevirtual #22                 // Method java/lang/StringBuilder.append:(Ljava/lang/String;)Ljava/lang/StringBuilder;
     140: ldc           #64                 // String ]
     142: invokevirtual #22                 // Method java/lang/StringBuilder.append:(Ljava/lang/String;)Ljava/lang/StringBuilder;
     145: invokevirtual #24                 // Method java/lang/StringBuilder.toString:()Ljava/lang/String;
     148: aload_2
     149: invokeinterface #36,  3           // InterfaceMethod org/apache/commons/logging/Log.debug:(Ljava/lang/Object;Ljava/lang/Throwable;)V
     154: aload_1
     155: ifnull        215
     158: aload_1
     159: invokeinterface #51,  1           // InterfaceMethod javax/wsdl/Definition.getDocumentationElement:()Lorg/w3c/dom/Element;
     164: astore_2
     165: aload_0
     166: aload_2
     167: invokespecial #53                 // Method setCachedDocElement:(Lorg/w3c/dom/Element;)V
     170: aload_0
     171: aload_1
     172: invokeinterface #48,  1           // InterfaceMethod javax/wsdl/Definition.getTypes:()Ljavax/wsdl/Types;
     177: invokespecial #50                 // Method setCachedTypes:(Ljavax/wsdl/Types;)V
     180: getstatic     #17                 // Field isDebugEnabled:Z
     183: ifeq          213
     186: aload_2
     187: ifnull        203
     190: getstatic     #9                  // Field log:Lorg/apache/commons/logging/Log;
     193: ldc           #156                // String WSDLWrapperReloadImpl.getDocumentationElement() from reloaded wsdl Definition returning  NON-NULL org.w3c.dom.Element
     195: invokeinterface #12,  2           // InterfaceMethod org/apache/commons/logging/Log.debug:(Ljava/lang/Object;)V
     200: goto          213
     203: getstatic     #9                  // Field log:Lorg/apache/commons/logging/Log;
     206: ldc           #157                // String WSDLWrapperReloadImpl.getDocumentationElement() from reloaded wsdl Definition returning  NULL org.w3c.dom.Element
     208: invokeinterface #12,  2           // InterfaceMethod org/apache/commons/logging/Log.debug:(Ljava/lang/Object;)V
     213: aload_2
     214: areturn
     215: getstatic     #17                 // Field isDebugEnabled:Z
     218: ifeq          231
     221: getstatic     #9                  // Field log:Lorg/apache/commons/logging/Log;
     224: ldc           #158                // String WSDLWrapperReloadImpl.getDocumentationElement() returning NULL
     226: invokeinterface #12,  2           // InterfaceMethod org/apache/commons/logging/Log.debug:(Ljava/lang/Object;)V
     231: aconst_null
     232: areturn
    Exception table:
       from    to  target type
          88    93    96   Class java/lang/Exception

  public void addExtensibilityElement(javax.wsdl.extensions.ExtensibilityElement);
    Code:
       0: getstatic     #17                 // Field isDebugEnabled:Z
       3: ifeq          38
       6: getstatic     #9                  // Field log:Lorg/apache/commons/logging/Log;
       9: new           #18                 // class java/lang/StringBuilder
      12: dup
      13: invokespecial #19                 // Method java/lang/StringBuilder."<init>":()V
      16: ldc           #159                // String WSDLWrapperReloadImpl.addExtensibilityElement(
      18: invokevirtual #22                 // Method java/lang/StringBuilder.append:(Ljava/lang/String;)Ljava/lang/StringBuilder;
      21: aload_1
      22: invokevirtual #23                 // Method java/lang/StringBuilder.append:(Ljava/lang/Object;)Ljava/lang/StringBuilder;
      25: ldc           #69                 // String )
      27: invokevirtual #22                 // Method java/lang/StringBuilder.append:(Ljava/lang/String;)Ljava/lang/StringBuilder;
      30: invokevirtual #24                 // Method java/lang/StringBuilder.toString:()Ljava/lang/String;
      33: invokeinterface #12,  2           // InterfaceMethod org/apache/commons/logging/Log.debug:(Ljava/lang/Object;)V
      38: aload_0
      39: getfield      #4                  // Field wsdlDefinition:Ljavax/wsdl/Definition;
      42: ifnull        55
      45: aload_0
      46: getfield      #4                  // Field wsdlDefinition:Ljavax/wsdl/Definition;
      49: aload_1
      50: invokeinterface #160,  2          // InterfaceMethod javax/wsdl/Definition.addExtensibilityElement:(Ljavax/wsdl/extensions/ExtensibilityElement;)V
      55: return

  public java.util.List getExtensibilityElements();
    Code:
       0: getstatic     #17                 // Field isDebugEnabled:Z
       3: ifeq          16
       6: getstatic     #9                  // Field log:Lorg/apache/commons/logging/Log;
       9: ldc           #161                // String WSDLWrapperReloadImpl.getExtensibilityElements()
      11: invokeinterface #12,  2           // InterfaceMethod org/apache/commons/logging/Log.debug:(Ljava/lang/Object;)V
      16: aload_0
      17: getfield      #4                  // Field wsdlDefinition:Ljavax/wsdl/Definition;
      20: ifnull        33
      23: aload_0
      24: getfield      #4                  // Field wsdlDefinition:Ljavax/wsdl/Definition;
      27: invokeinterface #162,  1          // InterfaceMethod javax/wsdl/Definition.getExtensibilityElements:()Ljava/util/List;
      32: areturn
      33: aconst_null
      34: areturn

  public javax.wsdl.Binding createBinding();
    Code:
       0: getstatic     #17                 // Field isDebugEnabled:Z
       3: ifeq          16
       6: getstatic     #9                  // Field log:Lorg/apache/commons/logging/Log;
       9: ldc           #163                // String WSDLWrapperReloadImpl.createBinding()
      11: invokeinterface #12,  2           // InterfaceMethod org/apache/commons/logging/Log.debug:(Ljava/lang/Object;)V
      16: aload_0
      17: getfield      #4                  // Field wsdlDefinition:Ljavax/wsdl/Definition;
      20: ifnull        33
      23: aload_0
      24: getfield      #4                  // Field wsdlDefinition:Ljavax/wsdl/Definition;
      27: invokeinterface #164,  1          // InterfaceMethod javax/wsdl/Definition.createBinding:()Ljavax/wsdl/Binding;
      32: areturn
      33: aconst_null
      34: areturn

  public javax.wsdl.BindingFault createBindingFault();
    Code:
       0: getstatic     #17                 // Field isDebugEnabled:Z
       3: ifeq          16
       6: getstatic     #9                  // Field log:Lorg/apache/commons/logging/Log;
       9: ldc           #165                // String WSDLWrapperReloadImpl.createBindingFault()
      11: invokeinterface #12,  2           // InterfaceMethod org/apache/commons/logging/Log.debug:(Ljava/lang/Object;)V
      16: aload_0
      17: getfield      #4                  // Field wsdlDefinition:Ljavax/wsdl/Definition;
      20: ifnull        33
      23: aload_0
      24: getfield      #4                  // Field wsdlDefinition:Ljavax/wsdl/Definition;
      27: invokeinterface #166,  1          // InterfaceMethod javax/wsdl/Definition.createBindingFault:()Ljavax/wsdl/BindingFault;
      32: areturn
      33: aconst_null
      34: areturn

  public javax.wsdl.BindingInput createBindingInput();
    Code:
       0: getstatic     #17                 // Field isDebugEnabled:Z
       3: ifeq          16
       6: getstatic     #9                  // Field log:Lorg/apache/commons/logging/Log;
       9: ldc           #167                // String WSDLWrapperReloadImpl.createBindingInput()
      11: invokeinterface #12,  2           // InterfaceMethod org/apache/commons/logging/Log.debug:(Ljava/lang/Object;)V
      16: aload_0
      17: getfield      #4                  // Field wsdlDefinition:Ljavax/wsdl/Definition;
      20: ifnull        33
      23: aload_0
      24: getfield      #4                  // Field wsdlDefinition:Ljavax/wsdl/Definition;
      27: invokeinterface #168,  1          // InterfaceMethod javax/wsdl/Definition.createBindingInput:()Ljavax/wsdl/BindingInput;
      32: areturn
      33: aconst_null
      34: areturn

  public javax.wsdl.BindingOperation createBindingOperation();
    Code:
       0: getstatic     #17                 // Field isDebugEnabled:Z
       3: ifeq          16
       6: getstatic     #9                  // Field log:Lorg/apache/commons/logging/Log;
       9: ldc           #169                // String WSDLWrapperReloadImpl.createBindingOperation()
      11: invokeinterface #12,  2           // InterfaceMethod org/apache/commons/logging/Log.debug:(Ljava/lang/Object;)V
      16: aload_0
      17: getfield      #4                  // Field wsdlDefinition:Ljavax/wsdl/Definition;
      20: ifnull        33
      23: aload_0
      24: getfield      #4                  // Field wsdlDefinition:Ljavax/wsdl/Definition;
      27: invokeinterface #170,  1          // InterfaceMethod javax/wsdl/Definition.createBindingOperation:()Ljavax/wsdl/BindingOperation;
      32: areturn
      33: aconst_null
      34: areturn

  public javax.wsdl.BindingOutput createBindingOutput();
    Code:
       0: getstatic     #17                 // Field isDebugEnabled:Z
       3: ifeq          16
       6: getstatic     #9                  // Field log:Lorg/apache/commons/logging/Log;
       9: ldc           #171                // String WSDLWrapperReloadImpl.createBindingOutput()
      11: invokeinterface #12,  2           // InterfaceMethod org/apache/commons/logging/Log.debug:(Ljava/lang/Object;)V
      16: aload_0
      17: getfield      #4                  // Field wsdlDefinition:Ljavax/wsdl/Definition;
      20: ifnull        33
      23: aload_0
      24: getfield      #4                  // Field wsdlDefinition:Ljavax/wsdl/Definition;
      27: invokeinterface #172,  1          // InterfaceMethod javax/wsdl/Definition.createBindingOutput:()Ljavax/wsdl/BindingOutput;
      32: areturn
      33: aconst_null
      34: areturn

  public javax.wsdl.Fault createFault();
    Code:
       0: getstatic     #17                 // Field isDebugEnabled:Z
       3: ifeq          16
       6: getstatic     #9                  // Field log:Lorg/apache/commons/logging/Log;
       9: ldc           #173                // String WSDLWrapperReloadImpl.createFault()
      11: invokeinterface #12,  2           // InterfaceMethod org/apache/commons/logging/Log.debug:(Ljava/lang/Object;)V
      16: aload_0
      17: getfield      #4                  // Field wsdlDefinition:Ljavax/wsdl/Definition;
      20: ifnull        33
      23: aload_0
      24: getfield      #4                  // Field wsdlDefinition:Ljavax/wsdl/Definition;
      27: invokeinterface #174,  1          // InterfaceMethod javax/wsdl/Definition.createFault:()Ljavax/wsdl/Fault;
      32: areturn
      33: aconst_null
      34: areturn

  public javax.wsdl.Import createImport();
    Code:
       0: getstatic     #17                 // Field isDebugEnabled:Z
       3: ifeq          16
       6: getstatic     #9                  // Field log:Lorg/apache/commons/logging/Log;
       9: ldc           #175                // String WSDLWrapperReloadImpl.createImport()
      11: invokeinterface #12,  2           // InterfaceMethod org/apache/commons/logging/Log.debug:(Ljava/lang/Object;)V
      16: aload_0
      17: getfield      #4                  // Field wsdlDefinition:Ljavax/wsdl/Definition;
      20: ifnull        33
      23: aload_0
      24: getfield      #4                  // Field wsdlDefinition:Ljavax/wsdl/Definition;
      27: invokeinterface #176,  1          // InterfaceMethod javax/wsdl/Definition.createImport:()Ljavax/wsdl/Import;
      32: areturn
      33: aconst_null
      34: areturn

  public javax.wsdl.Input createInput();
    Code:
       0: getstatic     #17                 // Field isDebugEnabled:Z
       3: ifeq          16
       6: getstatic     #9                  // Field log:Lorg/apache/commons/logging/Log;
       9: ldc           #177                // String WSDLWrapperReloadImpl.createInput()
      11: invokeinterface #12,  2           // InterfaceMethod org/apache/commons/logging/Log.debug:(Ljava/lang/Object;)V
      16: aload_0
      17: getfield      #4                  // Field wsdlDefinition:Ljavax/wsdl/Definition;
      20: ifnull        33
      23: aload_0
      24: getfield      #4                  // Field wsdlDefinition:Ljavax/wsdl/Definition;
      27: invokeinterface #178,  1          // InterfaceMethod javax/wsdl/Definition.createInput:()Ljavax/wsdl/Input;
      32: areturn
      33: aconst_null
      34: areturn

  public javax.wsdl.Message createMessage();
    Code:
       0: getstatic     #17                 // Field isDebugEnabled:Z
       3: ifeq          16
       6: getstatic     #9                  // Field log:Lorg/apache/commons/logging/Log;
       9: ldc           #179                // String WSDLWrapperReloadImpl.createMessage()
      11: invokeinterface #12,  2           // InterfaceMethod org/apache/commons/logging/Log.debug:(Ljava/lang/Object;)V
      16: aload_0
      17: getfield      #4                  // Field wsdlDefinition:Ljavax/wsdl/Definition;
      20: ifnull        33
      23: aload_0
      24: getfield      #4                  // Field wsdlDefinition:Ljavax/wsdl/Definition;
      27: invokeinterface #180,  1          // InterfaceMethod javax/wsdl/Definition.createMessage:()Ljavax/wsdl/Message;
      32: areturn
      33: aconst_null
      34: areturn

  public javax.wsdl.Operation createOperation();
    Code:
       0: getstatic     #17                 // Field isDebugEnabled:Z
       3: ifeq          16
       6: getstatic     #9                  // Field log:Lorg/apache/commons/logging/Log;
       9: ldc           #181                // String WSDLWrapperReloadImpl.createOperation()
      11: invokeinterface #12,  2           // InterfaceMethod org/apache/commons/logging/Log.debug:(Ljava/lang/Object;)V
      16: aload_0
      17: getfield      #4                  // Field wsdlDefinition:Ljavax/wsdl/Definition;
      20: ifnull        33
      23: aload_0
      24: getfield      #4                  // Field wsdlDefinition:Ljavax/wsdl/Definition;
      27: invokeinterface #182,  1          // InterfaceMethod javax/wsdl/Definition.createOperation:()Ljavax/wsdl/Operation;
      32: areturn
      33: aconst_null
      34: areturn

  public javax.wsdl.Output createOutput();
    Code:
       0: getstatic     #17                 // Field isDebugEnabled:Z
       3: ifeq          16
       6: getstatic     #9                  // Field log:Lorg/apache/commons/logging/Log;
       9: ldc           #183                // String WSDLWrapperReloadImpl.createOutput()
      11: invokeinterface #12,  2           // InterfaceMethod org/apache/commons/logging/Log.debug:(Ljava/lang/Object;)V
      16: aload_0
      17: getfield      #4                  // Field wsdlDefinition:Ljavax/wsdl/Definition;
      20: ifnull        33
      23: aload_0
      24: getfield      #4                  // Field wsdlDefinition:Ljavax/wsdl/Definition;
      27: invokeinterface #184,  1          // InterfaceMethod javax/wsdl/Definition.createOutput:()Ljavax/wsdl/Output;
      32: areturn
      33: aconst_null
      34: areturn

  public javax.wsdl.Part createPart();
    Code:
       0: getstatic     #17                 // Field isDebugEnabled:Z
       3: ifeq          16
       6: getstatic     #9                  // Field log:Lorg/apache/commons/logging/Log;
       9: ldc           #185                // String WSDLWrapperReloadImpl.createPart()
      11: invokeinterface #12,  2           // InterfaceMethod org/apache/commons/logging/Log.debug:(Ljava/lang/Object;)V
      16: aload_0
      17: getfield      #4                  // Field wsdlDefinition:Ljavax/wsdl/Definition;
      20: ifnull        33
      23: aload_0
      24: getfield      #4                  // Field wsdlDefinition:Ljavax/wsdl/Definition;
      27: invokeinterface #186,  1          // InterfaceMethod javax/wsdl/Definition.createPart:()Ljavax/wsdl/Part;
      32: areturn
      33: aconst_null
      34: areturn

  public javax.wsdl.Port createPort();
    Code:
       0: getstatic     #17                 // Field isDebugEnabled:Z
       3: ifeq          16
       6: getstatic     #9                  // Field log:Lorg/apache/commons/logging/Log;
       9: ldc           #187                // String WSDLWrapperReloadImpl.createPort()
      11: invokeinterface #12,  2           // InterfaceMethod org/apache/commons/logging/Log.debug:(Ljava/lang/Object;)V
      16: aload_0
      17: getfield      #4                  // Field wsdlDefinition:Ljavax/wsdl/Definition;
      20: ifnull        33
      23: aload_0
      24: getfield      #4                  // Field wsdlDefinition:Ljavax/wsdl/Definition;
      27: invokeinterface #188,  1          // InterfaceMethod javax/wsdl/Definition.createPort:()Ljavax/wsdl/Port;
      32: areturn
      33: aconst_null
      34: areturn

  public javax.wsdl.PortType createPortType();
    Code:
       0: getstatic     #17                 // Field isDebugEnabled:Z
       3: ifeq          16
       6: getstatic     #9                  // Field log:Lorg/apache/commons/logging/Log;
       9: ldc           #189                // String WSDLWrapperReloadImpl.createPortType()
      11: invokeinterface #12,  2           // InterfaceMethod org/apache/commons/logging/Log.debug:(Ljava/lang/Object;)V
      16: aload_0
      17: getfield      #4                  // Field wsdlDefinition:Ljavax/wsdl/Definition;
      20: ifnull        33
      23: aload_0
      24: getfield      #4                  // Field wsdlDefinition:Ljavax/wsdl/Definition;
      27: invokeinterface #190,  1          // InterfaceMethod javax/wsdl/Definition.createPortType:()Ljavax/wsdl/PortType;
      32: areturn
      33: aconst_null
      34: areturn

  public javax.wsdl.Service createService();
    Code:
       0: getstatic     #17                 // Field isDebugEnabled:Z
       3: ifeq          16
       6: getstatic     #9                  // Field log:Lorg/apache/commons/logging/Log;
       9: ldc           #191                // String WSDLWrapperReloadImpl.createService()
      11: invokeinterface #12,  2           // InterfaceMethod org/apache/commons/logging/Log.debug:(Ljava/lang/Object;)V
      16: aload_0
      17: getfield      #4                  // Field wsdlDefinition:Ljavax/wsdl/Definition;
      20: ifnull        33
      23: aload_0
      24: getfield      #4                  // Field wsdlDefinition:Ljavax/wsdl/Definition;
      27: invokeinterface #192,  1          // InterfaceMethod javax/wsdl/Definition.createService:()Ljavax/wsdl/Service;
      32: areturn
      33: aconst_null
      34: areturn

  public javax.wsdl.Types createTypes();
    Code:
       0: getstatic     #17                 // Field isDebugEnabled:Z
       3: ifeq          16
       6: getstatic     #9                  // Field log:Lorg/apache/commons/logging/Log;
       9: ldc           #193                // String WSDLWrapperReloadImpl.createTypes()
      11: invokeinterface #12,  2           // InterfaceMethod org/apache/commons/logging/Log.debug:(Ljava/lang/Object;)V
      16: aload_0
      17: getfield      #4                  // Field wsdlDefinition:Ljavax/wsdl/Definition;
      20: ifnull        33
      23: aload_0
      24: getfield      #4                  // Field wsdlDefinition:Ljavax/wsdl/Definition;
      27: invokeinterface #194,  1          // InterfaceMethod javax/wsdl/Definition.createTypes:()Ljavax/wsdl/Types;
      32: areturn
      33: aconst_null
      34: areturn

  public void setExtensionRegistry(javax.wsdl.extensions.ExtensionRegistry);
    Code:
       0: getstatic     #17                 // Field isDebugEnabled:Z
       3: ifeq          38
       6: getstatic     #9                  // Field log:Lorg/apache/commons/logging/Log;
       9: new           #18                 // class java/lang/StringBuilder
      12: dup
      13: invokespecial #19                 // Method java/lang/StringBuilder."<init>":()V
      16: ldc           #195                // String WSDLWrapperReloadImpl.setExtensionRegistry(
      18: invokevirtual #22                 // Method java/lang/StringBuilder.append:(Ljava/lang/String;)Ljava/lang/StringBuilder;
      21: aload_1
      22: invokevirtual #23                 // Method java/lang/StringBuilder.append:(Ljava/lang/Object;)Ljava/lang/StringBuilder;
      25: ldc           #69                 // String )
      27: invokevirtual #22                 // Method java/lang/StringBuilder.append:(Ljava/lang/String;)Ljava/lang/StringBuilder;
      30: invokevirtual #24                 // Method java/lang/StringBuilder.toString:()Ljava/lang/String;
      33: invokeinterface #12,  2           // InterfaceMethod org/apache/commons/logging/Log.debug:(Ljava/lang/Object;)V
      38: aload_0
      39: getfield      #4                  // Field wsdlDefinition:Ljavax/wsdl/Definition;
      42: ifnull        55
      45: aload_0
      46: getfield      #4                  // Field wsdlDefinition:Ljavax/wsdl/Definition;
      49: aload_1
      50: invokeinterface #196,  2          // InterfaceMethod javax/wsdl/Definition.setExtensionRegistry:(Ljavax/wsdl/extensions/ExtensionRegistry;)V
      55: return

  public javax.wsdl.extensions.ExtensionRegistry getExtensionRegistry();
    Code:
       0: getstatic     #17                 // Field isDebugEnabled:Z
       3: ifeq          16
       6: getstatic     #9                  // Field log:Lorg/apache/commons/logging/Log;
       9: ldc           #197                // String WSDLWrapperReloadImpl.getExtensionRegistry()
      11: invokeinterface #12,  2           // InterfaceMethod org/apache/commons/logging/Log.debug:(Ljava/lang/Object;)V
      16: aload_0
      17: getfield      #4                  // Field wsdlDefinition:Ljavax/wsdl/Definition;
      20: ifnull        33
      23: aload_0
      24: getfield      #4                  // Field wsdlDefinition:Ljavax/wsdl/Definition;
      27: invokeinterface #198,  1          // InterfaceMethod javax/wsdl/Definition.getExtensionRegistry:()Ljavax/wsdl/extensions/ExtensionRegistry;
      32: areturn
      33: aconst_null
      34: areturn

  public java.lang.String toString();
    Code:
       0: aload_0
       1: getfield      #4                  // Field wsdlDefinition:Ljavax/wsdl/Definition;
       4: ifnull        43
       7: new           #18                 // class java/lang/StringBuilder
      10: dup
      11: invokespecial #19                 // Method java/lang/StringBuilder."<init>":()V
      14: aload_0
      15: invokevirtual #31                 // Method java/lang/Object.getClass:()Ljava/lang/Class;
      18: invokevirtual #32                 // Method java/lang/Class.getName:()Ljava/lang/String;
      21: invokevirtual #22                 // Method java/lang/StringBuilder.append:(Ljava/lang/String;)Ljava/lang/StringBuilder;
      24: ldc           #199                // String \n
      26: invokevirtual #22                 // Method java/lang/StringBuilder.append:(Ljava/lang/String;)Ljava/lang/StringBuilder;
      29: aload_0
      30: getfield      #4                  // Field wsdlDefinition:Ljavax/wsdl/Definition;
      33: invokevirtual #200                // Method java/lang/Object.toString:()Ljava/lang/String;
      36: invokevirtual #22                 // Method java/lang/StringBuilder.append:(Ljava/lang/String;)Ljava/lang/StringBuilder;
      39: invokevirtual #24                 // Method java/lang/StringBuilder.toString:()Ljava/lang/String;
      42: areturn
      43: aload_0
      44: invokevirtual #31                 // Method java/lang/Object.getClass:()Ljava/lang/Class;
      47: invokevirtual #32                 // Method java/lang/Class.getName:()Ljava/lang/String;
      50: areturn

  public javax.wsdl.extensions.ExtensibilityElement removeExtensibilityElement(javax.wsdl.extensions.ExtensibilityElement);
    Code:
       0: getstatic     #17                 // Field isDebugEnabled:Z
       3: ifeq          38
       6: getstatic     #9                  // Field log:Lorg/apache/commons/logging/Log;
       9: new           #18                 // class java/lang/StringBuilder
      12: dup
      13: invokespecial #19                 // Method java/lang/StringBuilder."<init>":()V
      16: ldc           #201                // String WSDLWrapperReloadImpl.removeExtensibilityElement(
      18: invokevirtual #22                 // Method java/lang/StringBuilder.append:(Ljava/lang/String;)Ljava/lang/StringBuilder;
      21: aload_1
      22: invokevirtual #23                 // Method java/lang/StringBuilder.append:(Ljava/lang/Object;)Ljava/lang/StringBuilder;
      25: ldc           #69                 // String )
      27: invokevirtual #22                 // Method java/lang/StringBuilder.append:(Ljava/lang/String;)Ljava/lang/StringBuilder;
      30: invokevirtual #24                 // Method java/lang/StringBuilder.toString:()Ljava/lang/String;
      33: invokeinterface #12,  2           // InterfaceMethod org/apache/commons/logging/Log.debug:(Ljava/lang/Object;)V
      38: aload_0
      39: getfield      #4                  // Field wsdlDefinition:Ljavax/wsdl/Definition;
      42: ifnull        56
      45: aload_0
      46: getfield      #4                  // Field wsdlDefinition:Ljavax/wsdl/Definition;
      49: aload_1
      50: invokeinterface #202,  2          // InterfaceMethod javax/wsdl/Definition.removeExtensibilityElement:(Ljavax/wsdl/extensions/ExtensibilityElement;)Ljavax/wsdl/extensions/ExtensibilityElement;
      55: areturn
      56: aconst_null
      57: areturn

  public java.lang.Object getExtensionAttribute(javax.xml.namespace.QName);
    Code:
       0: getstatic     #17                 // Field isDebugEnabled:Z
       3: ifeq          38
       6: getstatic     #9                  // Field log:Lorg/apache/commons/logging/Log;
       9: new           #18                 // class java/lang/StringBuilder
      12: dup
      13: invokespecial #19                 // Method java/lang/StringBuilder."<init>":()V
      16: ldc           #203                // String WSDLWrapperReloadImpl.getExtensionAttribute(
      18: invokevirtual #22                 // Method java/lang/StringBuilder.append:(Ljava/lang/String;)Ljava/lang/StringBuilder;
      21: aload_1
      22: invokevirtual #23                 // Method java/lang/StringBuilder.append:(Ljava/lang/Object;)Ljava/lang/StringBuilder;
      25: ldc           #69                 // String )
      27: invokevirtual #22                 // Method java/lang/StringBuilder.append:(Ljava/lang/String;)Ljava/lang/StringBuilder;
      30: invokevirtual #24                 // Method java/lang/StringBuilder.toString:()Ljava/lang/String;
      33: invokeinterface #12,  2           // InterfaceMethod org/apache/commons/logging/Log.debug:(Ljava/lang/Object;)V
      38: aload_0
      39: getfield      #4                  // Field wsdlDefinition:Ljavax/wsdl/Definition;
      42: ifnull        56
      45: aload_0
      46: getfield      #4                  // Field wsdlDefinition:Ljavax/wsdl/Definition;
      49: aload_1
      50: invokeinterface #204,  2          // InterfaceMethod javax/wsdl/Definition.getExtensionAttribute:(Ljavax/xml/namespace/QName;)Ljava/lang/Object;
      55: areturn
      56: aconst_null
      57: areturn

  public java.util.Map getExtensionAttributes();
    Code:
       0: getstatic     #17                 // Field isDebugEnabled:Z
       3: ifeq          16
       6: getstatic     #9                  // Field log:Lorg/apache/commons/logging/Log;
       9: ldc           #205                // String WSDLWrapperReloadImpl.getExtensionAttributes()
      11: invokeinterface #12,  2           // InterfaceMethod org/apache/commons/logging/Log.debug:(Ljava/lang/Object;)V
      16: aload_0
      17: getfield      #4                  // Field wsdlDefinition:Ljavax/wsdl/Definition;
      20: ifnull        33
      23: aload_0
      24: getfield      #4                  // Field wsdlDefinition:Ljavax/wsdl/Definition;
      27: invokeinterface #206,  1          // InterfaceMethod javax/wsdl/Definition.getExtensionAttributes:()Ljava/util/Map;
      32: areturn
      33: aconst_null
      34: areturn

  public void setExtensionAttribute(javax.xml.namespace.QName, java.lang.Object);
    Code:
       0: getstatic     #17                 // Field isDebugEnabled:Z
       3: ifeq          47
       6: getstatic     #9                  // Field log:Lorg/apache/commons/logging/Log;
       9: new           #18                 // class java/lang/StringBuilder
      12: dup
      13: invokespecial #19                 // Method java/lang/StringBuilder."<init>":()V
      16: ldc           #207                // String WSDLWrapperReloadImpl.setExtensionAttribute(
      18: invokevirtual #22                 // Method java/lang/StringBuilder.append:(Ljava/lang/String;)Ljava/lang/StringBuilder;
      21: aload_1
      22: invokevirtual #23                 // Method java/lang/StringBuilder.append:(Ljava/lang/Object;)Ljava/lang/StringBuilder;
      25: ldc           #208                // String ,
      27: invokevirtual #22                 // Method java/lang/StringBuilder.append:(Ljava/lang/String;)Ljava/lang/StringBuilder;
      30: aload_2
      31: invokevirtual #23                 // Method java/lang/StringBuilder.append:(Ljava/lang/Object;)Ljava/lang/StringBuilder;
      34: ldc           #69                 // String )
      36: invokevirtual #22                 // Method java/lang/StringBuilder.append:(Ljava/lang/String;)Ljava/lang/StringBuilder;
      39: invokevirtual #24                 // Method java/lang/StringBuilder.toString:()Ljava/lang/String;
      42: invokeinterface #12,  2           // InterfaceMethod org/apache/commons/logging/Log.debug:(Ljava/lang/Object;)V
      47: aload_0
      48: getfield      #4                  // Field wsdlDefinition:Ljavax/wsdl/Definition;
      51: ifnull        65
      54: aload_0
      55: getfield      #4                  // Field wsdlDefinition:Ljavax/wsdl/Definition;
      58: aload_1
      59: aload_2
      60: invokeinterface #209,  3          // InterfaceMethod javax/wsdl/Definition.setExtensionAttribute:(Ljavax/xml/namespace/QName;Ljava/lang/Object;)V
      65: return

  private static java.lang.String getExplicitURI(java.net.URL) throws javax.wsdl.WSDLException;
    Code:
       0: getstatic     #17                 // Field isDebugEnabled:Z
       3: ifeq          38
       6: getstatic     #9                  // Field log:Lorg/apache/commons/logging/Log;
       9: new           #18                 // class java/lang/StringBuilder
      12: dup
      13: invokespecial #19                 // Method java/lang/StringBuilder."<init>":()V
      16: ldc           #210                // String WSDLWrapperReloadImpl.getExplicitURI(
      18: invokevirtual #22                 // Method java/lang/StringBuilder.append:(Ljava/lang/String;)Ljava/lang/StringBuilder;
      21: aload_0
      22: invokevirtual #23                 // Method java/lang/StringBuilder.append:(Ljava/lang/Object;)Ljava/lang/StringBuilder;
      25: ldc           #211                // String )
      27: invokevirtual #22                 // Method java/lang/StringBuilder.append:(Ljava/lang/String;)Ljava/lang/StringBuilder;
      30: invokevirtual #24                 // Method java/lang/StringBuilder.toString:()Ljava/lang/String;
      33: invokeinterface #12,  2           // InterfaceMethod org/apache/commons/logging/Log.debug:(Ljava/lang/Object;)V
      38: aconst_null
      39: astore_1
      40: new           #212                // class org/apache/axis2/wsdl/util/WSDLWrapperReloadImpl$1
      43: dup
      44: invokespecial #213                // Method org/apache/axis2/wsdl/util/WSDLWrapperReloadImpl$1."<init>":()V
      47: invokestatic  #214                // Method org/apache/axis2/java/security/AccessController.doPrivileged:(Ljava/security/PrivilegedAction;)Ljava/lang/Object;
      50: checkcast     #215                // class java/lang/ClassLoader
      53: astore_2
      54: aload_0
      55: astore_3
      56: aconst_null
      57: astore        4
      59: aload_3
      60: ifnull        79
      63: ldc           #216                // String file
      65: aload_3
      66: invokevirtual #217                // Method java/net/URL.getProtocol:()Ljava/lang/String;
      69: invokevirtual #218                // Method java/lang/String.equals:(Ljava/lang/Object;)Z
      72: ifeq          79
      75: iconst_1
      76: goto          80
      79: iconst_0
      80: istore        5
      82: iload         5
      84: ifeq          398
      87: aload_3
      88: ifnull        98
      91: aload_3
      92: invokevirtual #219                // Method java/net/URL.getPath:()Ljava/lang/String;
      95: goto          99
      98: aconst_null
      99: astore        4
     101: aconst_null
     102: astore        6
     104: aload_3
     105: ifnull        121
     108: new           #220                // class java/net/URI
     111: dup
     112: aload_3
     113: invokevirtual #67                 // Method java/net/URL.toString:()Ljava/lang/String;
     116: invokespecial #221                // Method java/net/URI."<init>":(Ljava/lang/String;)V
     119: astore        6
     121: aload         4
     123: ifnull        145
     126: new           #222                // class java/io/File
     129: dup
     130: aload         4
     132: invokespecial #223                // Method java/io/File."<init>":(Ljava/lang/String;)V
     135: invokevirtual #224                // Method java/io/File.isAbsolute:()Z
     138: ifne          145
     141: iconst_1
     142: goto          146
     145: iconst_0
     146: istore        7
     148: iload         7
     150: ifeq          398
     153: getstatic     #17                 // Field isDebugEnabled:Z
     156: ifeq          191
     159: getstatic     #9                  // Field log:Lorg/apache/commons/logging/Log;
     162: new           #18                 // class java/lang/StringBuilder
     165: dup
     166: invokespecial #19                 // Method java/lang/StringBuilder."<init>":()V
     169: ldc           #210                // String WSDLWrapperReloadImpl.getExplicitURI(
     171: invokevirtual #22                 // Method java/lang/StringBuilder.append:(Ljava/lang/String;)Ljava/lang/StringBuilder;
     174: aload_0
     175: invokevirtual #23                 // Method java/lang/StringBuilder.append:(Ljava/lang/Object;)Ljava/lang/StringBuilder;
     178: ldc           #225                // String ): WSDL URL has a relative path
     180: invokevirtual #22                 // Method java/lang/StringBuilder.append:(Ljava/lang/String;)Ljava/lang/StringBuilder;
     183: invokevirtual #24                 // Method java/lang/StringBuilder.toString:()Ljava/lang/String;
     186: invokeinterface #12,  2           // InterfaceMethod org/apache/commons/logging/Log.debug:(Ljava/lang/Object;)V
     191: aload_2
     192: aload         4
     194: aload_0
     195: invokestatic  #226                // Method getAbsoluteURL:(Ljava/lang/ClassLoader;Ljava/lang/String;Ljava/net/URL;)Ljava/net/URL;
     198: astore_3
     199: aload_3
     200: ifnonnull     342
     203: getstatic     #17                 // Field isDebugEnabled:Z
     206: ifeq          337
     209: getstatic     #9                  // Field log:Lorg/apache/commons/logging/Log;
     212: new           #18                 // class java/lang/StringBuilder
     215: dup
     216: invokespecial #19                 // Method java/lang/StringBuilder."<init>":()V
     219: ldc           #210                // String WSDLWrapperReloadImpl.getExplicitURI(
     221: invokevirtual #22                 // Method java/lang/StringBuilder.append:(Ljava/lang/String;)Ljava/lang/StringBuilder;
     224: aload_0
     225: invokevirtual #23                 // Method java/lang/StringBuilder.append:(Ljava/lang/Object;)Ljava/lang/StringBuilder;
     228: ldc           #227                // String ): WSDL URL for relative path not found in ClassLoader
     230: invokevirtual #22                 // Method java/lang/StringBuilder.append:(Ljava/lang/String;)Ljava/lang/StringBuilder;
     233: invokevirtual #24                 // Method java/lang/StringBuilder.toString:()Ljava/lang/String;
     236: invokeinterface #12,  2           // InterfaceMethod org/apache/commons/logging/Log.debug:(Ljava/lang/Object;)V
     241: getstatic     #9                  // Field log:Lorg/apache/commons/logging/Log;
     244: new           #18                 // class java/lang/StringBuilder
     247: dup
     248: invokespecial #19                 // Method java/lang/StringBuilder."<init>":()V
     251: ldc           #210                // String WSDLWrapperReloadImpl.getExplicitURI(
     253: invokevirtual #22                 // Method java/lang/StringBuilder.append:(Ljava/lang/String;)Ljava/lang/StringBuilder;
     256: aload_0
     257: invokevirtual #23                 // Method java/lang/StringBuilder.append:(Ljava/lang/Object;)Ljava/lang/StringBuilder;
     260: ldc           #228                // String ): Unable to read WSDL from relative path, check the relative path
     262: invokevirtual #22                 // Method java/lang/StringBuilder.append:(Ljava/lang/String;)Ljava/lang/StringBuilder;
     265: invokevirtual #24                 // Method java/lang/StringBuilder.toString:()Ljava/lang/String;
     268: invokeinterface #12,  2           // InterfaceMethod org/apache/commons/logging/Log.debug:(Ljava/lang/Object;)V
     273: getstatic     #9                  // Field log:Lorg/apache/commons/logging/Log;
     276: new           #18                 // class java/lang/StringBuilder
     279: dup
     280: invokespecial #19                 // Method java/lang/StringBuilder."<init>":()V
     283: ldc           #210                // String WSDLWrapperReloadImpl.getExplicitURI(
     285: invokevirtual #22                 // Method java/lang/StringBuilder.append:(Ljava/lang/String;)Ljava/lang/StringBuilder;
     288: aload_0
     289: invokevirtual #23                 // Method java/lang/StringBuilder.append:(Ljava/lang/Object;)Ljava/lang/StringBuilder;
     292: ldc           #229                // String ): Relative path example: file:/WEB-INF/wsdl/<wsdlfilename>
     294: invokevirtual #22                 // Method java/lang/StringBuilder.append:(Ljava/lang/String;)Ljava/lang/StringBuilder;
     297: invokevirtual #24                 // Method java/lang/StringBuilder.toString:()Ljava/lang/String;
     300: invokeinterface #12,  2           // InterfaceMethod org/apache/commons/logging/Log.debug:(Ljava/lang/Object;)V
     305: getstatic     #9                  // Field log:Lorg/apache/commons/logging/Log;
     308: new           #18                 // class java/lang/StringBuilder
     311: dup
     312: invokespecial #19                 // Method java/lang/StringBuilder."<init>":()V
     315: ldc           #210                // String WSDLWrapperReloadImpl.getExplicitURI(
     317: invokevirtual #22                 // Method java/lang/StringBuilder.append:(Ljava/lang/String;)Ljava/lang/StringBuilder;
     320: aload_0
     321: invokevirtual #23                 // Method java/lang/StringBuilder.append:(Ljava/lang/Object;)Ljava/lang/StringBuilder;
     324: ldc           #230                // String ): Using relative path as default wsdl URL to load wsdl Definition.
     326: invokevirtual #22                 // Method java/lang/StringBuilder.append:(Ljava/lang/String;)Ljava/lang/StringBuilder;
     329: invokevirtual #24                 // Method java/lang/StringBuilder.toString:()Ljava/lang/String;
     332: invokeinterface #12,  2           // InterfaceMethod org/apache/commons/logging/Log.debug:(Ljava/lang/Object;)V
     337: aload_0
     338: astore_3
     339: goto          398
     342: getstatic     #17                 // Field isDebugEnabled:Z
     345: ifeq          398
     348: getstatic     #9                  // Field log:Lorg/apache/commons/logging/Log;
     351: new           #18                 // class java/lang/StringBuilder
     354: dup
     355: invokespecial #19                 // Method java/lang/StringBuilder."<init>":()V
     358: ldc           #210                // String WSDLWrapperReloadImpl.getExplicitURI(
     360: invokevirtual #22                 // Method java/lang/StringBuilder.append:(Ljava/lang/String;)Ljava/lang/StringBuilder;
     363: aload_0
     364: invokevirtual #23                 // Method java/lang/StringBuilder.append:(Ljava/lang/Object;)Ljava/lang/StringBuilder;
     367: ldc           #231                // String ): WSDL URL found for relative path:
     369: invokevirtual #22                 // Method java/lang/StringBuilder.append:(Ljava/lang/String;)Ljava/lang/StringBuilder;
     372: aload         4
     374: invokevirtual #22                 // Method java/lang/StringBuilder.append:(Ljava/lang/String;)Ljava/lang/StringBuilder;
     377: ldc           #232                // String  scheme:
     379: invokevirtual #22                 // Method java/lang/StringBuilder.append:(Ljava/lang/String;)Ljava/lang/StringBuilder;
     382: aload         6
     384: invokevirtual #233                // Method java/net/URI.getScheme:()Ljava/lang/String;
     387: invokevirtual #22                 // Method java/lang/StringBuilder.append:(Ljava/lang/String;)Ljava/lang/StringBuilder;
     390: invokevirtual #24                 // Method java/lang/StringBuilder.toString:()Ljava/lang/String;
     393: invokeinterface #12,  2           // InterfaceMethod org/apache/commons/logging/Log.debug:(Ljava/lang/Object;)V
     398: aload_3
     399: invokevirtual #234                // Method java/net/URL.openConnection:()Ljava/net/URLConnection;
     402: astore        6
     404: aconst_null
     405: astore        7
     407: aload         6
     409: invokestatic  #235                // Method getInputStream:(Ljava/net/URLConnection;)Ljava/io/InputStream;
     412: astore        7
     414: goto          597
     417: astore        8
     419: getstatic     #17                 // Field isDebugEnabled:Z
     422: ifeq          457
     425: getstatic     #9                  // Field log:Lorg/apache/commons/logging/Log;
     428: new           #18                 // class java/lang/StringBuilder
     431: dup
     432: invokespecial #19                 // Method java/lang/StringBuilder."<init>":()V
     435: ldc           #210                // String WSDLWrapperReloadImpl.getExplicitURI(
     437: invokevirtual #22                 // Method java/lang/StringBuilder.append:(Ljava/lang/String;)Ljava/lang/StringBuilder;
     440: aload_0
     441: invokevirtual #23                 // Method java/lang/StringBuilder.append:(Ljava/lang/Object;)Ljava/lang/StringBuilder;
     444: ldc           #237                // String ): Could not open url connection. Trying to use classloader to get another URL.
     446: invokevirtual #22                 // Method java/lang/StringBuilder.append:(Ljava/lang/String;)Ljava/lang/StringBuilder;
     449: invokevirtual #24                 // Method java/lang/StringBuilder.toString:()Ljava/lang/String;
     452: invokeinterface #12,  2           // InterfaceMethod org/apache/commons/logging/Log.debug:(Ljava/lang/Object;)V
     457: aload         4
     459: ifnull        542
     462: aload_2
     463: aload         4
     465: aload_0
     466: invokestatic  #226                // Method getAbsoluteURL:(Ljava/lang/ClassLoader;Ljava/lang/String;Ljava/net/URL;)Ljava/net/URL;
     469: astore_3
     470: aload_3
     471: ifnonnull     512
     474: getstatic     #9                  // Field log:Lorg/apache/commons/logging/Log;
     477: invokeinterface #10,  1           // InterfaceMethod org/apache/commons/logging/Log.isDebugEnabled:()Z
     482: ifeq          495
     485: getstatic     #9                  // Field log:Lorg/apache/commons/logging/Log;
     488: ldc           #238                // String Could not locate URL for wsdl. Reporting error
     490: invokeinterface #12,  2           // InterfaceMethod org/apache/commons/logging/Log.debug:(Ljava/lang/Object;)V
     495: new           #239                // class javax/wsdl/WSDLException
     498: dup
     499: ldc           #240                // String WSDL4JWrapper :
     501: aload         8
     503: invokevirtual #241                // Method java/io/IOException.getMessage:()Ljava/lang/String;
     506: aload         8
     508: invokespecial #242                // Method javax/wsdl/WSDLException."<init>":(Ljava/lang/String;Ljava/lang/String;Ljava/lang/Throwable;)V
     511: athrow
     512: aload_3
     513: invokevirtual #234                // Method java/net/URL.openConnection:()Ljava/net/URLConnection;
     516: astore        6
     518: getstatic     #9                  // Field log:Lorg/apache/commons/logging/Log;
     521: invokeinterface #10,  1           // InterfaceMethod org/apache/commons/logging/Log.isDebugEnabled:()Z
     526: ifeq          597
     529: getstatic     #9                  // Field log:Lorg/apache/commons/logging/Log;
     532: ldc           #243                // String Found URL for WSDL from jar
     534: invokeinterface #12,  2           // InterfaceMethod org/apache/commons/logging/Log.debug:(Ljava/lang/Object;)V
     539: goto          597
     542: getstatic     #17                 // Field isDebugEnabled:Z
     545: ifeq          580
     548: getstatic     #9                  // Field log:Lorg/apache/commons/logging/Log;
     551: new           #18                 // class java/lang/StringBuilder
     554: dup
     555: invokespecial #19                 // Method java/lang/StringBuilder."<init>":()V
     558: ldc           #210                // String WSDLWrapperReloadImpl.getExplicitURI(
     560: invokevirtual #22                 // Method java/lang/StringBuilder.append:(Ljava/lang/String;)Ljava/lang/StringBuilder;
     563: aload_0
     564: invokevirtual #23                 // Method java/lang/StringBuilder.append:(Ljava/lang/Object;)Ljava/lang/StringBuilder;
     567: ldc           #244                // String ): Could not get URL from classloader. Reporting error due to no file path.
     569: invokevirtual #22                 // Method java/lang/StringBuilder.append:(Ljava/lang/String;)Ljava/lang/StringBuilder;
     572: invokevirtual #24                 // Method java/lang/StringBuilder.toString:()Ljava/lang/String;
     575: invokeinterface #12,  2           // InterfaceMethod org/apache/commons/logging/Log.debug:(Ljava/lang/Object;)V
     580: new           #239                // class javax/wsdl/WSDLException
     583: dup
     584: ldc           #245                // String WSDLWrapperReloadImpl :
     586: aload         8
     588: invokevirtual #241                // Method java/io/IOException.getMessage:()Ljava/lang/String;
     591: aload         8
     593: invokespecial #242                // Method javax/wsdl/WSDLException."<init>":(Ljava/lang/String;Ljava/lang/String;Ljava/lang/Throwable;)V
     596: athrow
     597: aload         7
     599: ifnull        607
     602: aload         7
     604: invokevirtual #246                // Method java/io/InputStream.close:()V
     607: aload         6
     609: invokevirtual #247                // Method java/net/URLConnection.getURL:()Ljava/net/URL;
     612: invokevirtual #67                 // Method java/net/URL.toString:()Ljava/lang/String;
     615: astore_1
     616: goto          635
     619: astore_3
     620: new           #239                // class javax/wsdl/WSDLException
     623: dup
     624: ldc           #245                // String WSDLWrapperReloadImpl :
     626: aload_3
     627: invokevirtual #34                 // Method java/lang/Exception.getMessage:()Ljava/lang/String;
     630: aload_3
     631: invokespecial #242                // Method javax/wsdl/WSDLException."<init>":(Ljava/lang/String;Ljava/lang/String;Ljava/lang/Throwable;)V
     634: athrow
     635: aload_1
     636: areturn
    Exception table:
       from    to  target type
         407   414   417   Class java/io/IOException
          54   616   619   Class java/lang/Exception

  private static java.net.URL getAbsoluteURL(java.lang.ClassLoader, java.lang.String, java.net.URL) throws javax.wsdl.WSDLException;
    Code:
       0: new           #248                // class org/apache/axis2/wsdl/util/WSDLWrapperReloadImpl$2
       3: dup
       4: aload_0
       5: aload_1
       6: invokespecial #249                // Method org/apache/axis2/wsdl/util/WSDLWrapperReloadImpl$2."<init>":(Ljava/lang/ClassLoader;Ljava/lang/String;)V
       9: invokestatic  #214                // Method org/apache/axis2/java/security/AccessController.doPrivileged:(Ljava/security/PrivilegedAction;)Ljava/lang/Object;
      12: checkcast     #26                 // class java/net/URL
      15: astore_3
      16: aload_3
      17: ifnonnull     61
      20: getstatic     #9                  // Field log:Lorg/apache/commons/logging/Log;
      23: invokeinterface #10,  1           // InterfaceMethod org/apache/commons/logging/Log.isDebugEnabled:()Z
      28: ifeq          41
      31: getstatic     #9                  // Field log:Lorg/apache/commons/logging/Log;
      34: ldc           #250                // String Could not get URL from classloader. Looking in a jar.
      36: invokeinterface #12,  2           // InterfaceMethod org/apache/commons/logging/Log.debug:(Ljava/lang/Object;)V
      41: aload_0
      42: instanceof    #251                // class java/net/URLClassLoader
      45: ifeq          61
      48: aload_0
      49: checkcast     #251                // class java/net/URLClassLoader
      52: astore        4
      54: aload         4
      56: aload_2
      57: invokestatic  #252                // Method getURLFromJAR:(Ljava/net/URLClassLoader;Ljava/net/URL;)Ljava/net/URL;
      60: astore_3
      61: aload_3
      62: areturn

  private javax.wsdl.Definition loadDefinition() throws javax.wsdl.WSDLException;
    Code:
       0: aconst_null
       1: astore_1
       2: aload_0
       3: getfield      #1                  // Field wsdlExplicitURI:Ljava/lang/String;
       6: ifnull        109
       9: new           #253                // class org/apache/axis2/wsdl/util/WSDLWrapperReloadImpl$3
      12: dup
      13: aload_0
      14: invokespecial #254                // Method org/apache/axis2/wsdl/util/WSDLWrapperReloadImpl$3."<init>":(Lorg/apache/axis2/wsdl/util/WSDLWrapperReloadImpl;)V
      17: invokestatic  #255                // Method org/apache/axis2/java/security/AccessController.doPrivileged:(Ljava/security/PrivilegedExceptionAction;)Ljava/lang/Object;
      20: checkcast     #256                // class javax/wsdl/Definition
      23: astore_1
      24: goto          109
      27: astore_2
      28: getstatic     #17                 // Field isDebugEnabled:Z
      31: ifeq          92
      34: getstatic     #9                  // Field log:Lorg/apache/commons/logging/Log;
      37: new           #18                 // class java/lang/StringBuilder
      40: dup
      41: invokespecial #19                 // Method java/lang/StringBuilder."<init>":()V
      44: ldc_w         #258                // String WSDLWrapperReloadImpl.loadDefinition(): Exception thrown from AccessController:
      47: invokevirtual #22                 // Method java/lang/StringBuilder.append:(Ljava/lang/String;)Ljava/lang/StringBuilder;
      50: aload_2
      51: invokevirtual #23                 // Method java/lang/StringBuilder.append:(Ljava/lang/Object;)Ljava/lang/StringBuilder;
      54: invokevirtual #24                 // Method java/lang/StringBuilder.toString:()Ljava/lang/String;
      57: invokeinterface #12,  2           // InterfaceMethod org/apache/commons/logging/Log.debug:(Ljava/lang/Object;)V
      62: getstatic     #9                  // Field log:Lorg/apache/commons/logging/Log;
      65: new           #18                 // class java/lang/StringBuilder
      68: dup
      69: invokespecial #19                 // Method java/lang/StringBuilder."<init>":()V
      72: ldc_w         #259                // String Call Stack =
      75: invokevirtual #22                 // Method java/lang/StringBuilder.append:(Ljava/lang/String;)Ljava/lang/StringBuilder;
      78: invokestatic  #13                 // Method org/apache/axis2/util/JavaUtils.callStackToString:()Ljava/lang/String;
      81: invokevirtual #22                 // Method java/lang/StringBuilder.append:(Ljava/lang/String;)Ljava/lang/StringBuilder;
      84: invokevirtual #24                 // Method java/lang/StringBuilder.toString:()Ljava/lang/String;
      87: invokeinterface #14,  2           // InterfaceMethod org/apache/commons/logging/Log.trace:(Ljava/lang/Object;)V
      92: new           #239                // class javax/wsdl/WSDLException
      95: dup
      96: ldc           #245                // String WSDLWrapperReloadImpl :
      98: aload_2
      99: invokevirtual #260                // Method java/security/PrivilegedActionException.getMessage:()Ljava/lang/String;
     102: aload_2
     103: invokespecial #242                // Method javax/wsdl/WSDLException."<init>":(Ljava/lang/String;Ljava/lang/String;Ljava/lang/Throwable;)V
     106: astore_3
     107: aload_3
     108: athrow
     109: getstatic     #17                 // Field isDebugEnabled:Z
     112: ifeq          178
     115: getstatic     #9                  // Field log:Lorg/apache/commons/logging/Log;
     118: new           #18                 // class java/lang/StringBuilder
     121: dup
     122: invokespecial #19                 // Method java/lang/StringBuilder."<init>":()V
     125: ldc_w         #261                // String WSDLWrapperReloadImpl.loadDefinition():  returning Definition [
     128: invokevirtual #22                 // Method java/lang/StringBuilder.append:(Ljava/lang/String;)Ljava/lang/StringBuilder;
     131: aload_1
     132: invokevirtual #23                 // Method java/lang/StringBuilder.append:(Ljava/lang/Object;)Ljava/lang/StringBuilder;
     135: ldc           #35                 // String ]
     137: invokevirtual #22                 // Method java/lang/StringBuilder.append:(Ljava/lang/String;)Ljava/lang/StringBuilder;
     140: invokevirtual #24                 // Method java/lang/StringBuilder.toString:()Ljava/lang/String;
     143: invokeinterface #12,  2           // InterfaceMethod org/apache/commons/logging/Log.debug:(Ljava/lang/Object;)V
     148: getstatic     #9                  // Field log:Lorg/apache/commons/logging/Log;
     151: new           #18                 // class java/lang/StringBuilder
     154: dup
     155: invokespecial #19                 // Method java/lang/StringBuilder."<init>":()V
     158: ldc_w         #259                // String Call Stack =
     161: invokevirtual #22                 // Method java/lang/StringBuilder.append:(Ljava/lang/String;)Ljava/lang/StringBuilder;
     164: invokestatic  #13                 // Method org/apache/axis2/util/JavaUtils.callStackToString:()Ljava/lang/String;
     167: invokevirtual #22                 // Method java/lang/StringBuilder.append:(Ljava/lang/String;)Ljava/lang/StringBuilder;
     170: invokevirtual #24                 // Method java/lang/StringBuilder.toString:()Ljava/lang/String;
     173: invokeinterface #14,  2           // InterfaceMethod org/apache/commons/logging/Log.trace:(Ljava/lang/Object;)V
     178: aload_1
     179: areturn
    Exception table:
       from    to  target type
           9    24    27   Class java/security/PrivilegedActionException

  private static java.net.URL getURLFromJAR(java.net.URLClassLoader, java.net.URL) throws javax.wsdl.WSDLException;
    Code:
       0: aload_0
       1: invokevirtual #262                // Method java/net/URLClassLoader.getURLs:()[Ljava/net/URL;
       4: astore_2
       5: aload_2
       6: ifnonnull     11
       9: aconst_null
      10: areturn
      11: iconst_0
      12: istore_3
      13: iload_3
      14: aload_2
      15: arraylength
      16: if_icmpge     266
      19: aload_2
      20: iload_3
      21: aaload
      22: astore        4
      24: aload         4
      26: ifnonnull     31
      29: aconst_null
      30: areturn
      31: ldc           #216                // String file
      33: aload         4
      35: invokevirtual #217                // Method java/net/URL.getProtocol:()Ljava/lang/String;
      38: invokevirtual #218                // Method java/lang/String.equals:(Ljava/lang/Object;)Z
      41: ifeq          260
      44: new           #222                // class java/io/File
      47: dup
      48: aload         4
      50: invokevirtual #219                // Method java/net/URL.getPath:()Ljava/lang/String;
      53: invokespecial #223                // Method java/io/File."<init>":(Ljava/lang/String;)V
      56: astore        5
      58: aload         5
      60: invokevirtual #263                // Method java/io/File.exists:()Z
      63: ifeq          260
      66: aload         5
      68: invokevirtual #264                // Method java/io/File.isDirectory:()Z
      71: ifne          260
      74: new           #265                // class java/util/jar/JarFile
      77: dup
      78: aload         5
      80: invokespecial #266                // Method java/util/jar/JarFile."<init>":(Ljava/io/File;)V
      83: astore        6
      85: aload         6
      87: invokevirtual #267                // Method java/util/jar/JarFile.entries:()Ljava/util/Enumeration;
      90: astore        7
      92: aload         7
      94: invokeinterface #268,  1          // InterfaceMethod java/util/Enumeration.hasMoreElements:()Z
      99: ifeq          234
     102: aload         7
     104: invokeinterface #269,  1          // InterfaceMethod java/util/Enumeration.nextElement:()Ljava/lang/Object;
     109: checkcast     #270                // class java/util/jar/JarEntry
     112: astore        8
     114: aload         8
     116: invokevirtual #271                // Method java/util/jar/JarEntry.getName:()Ljava/lang/String;
     119: astore        9
     121: aload         9
     123: ldc_w         #272                // String .wsdl
     126: invokevirtual #273                // Method java/lang/String.endsWith:(Ljava/lang/String;)Z
     129: ifeq          231
     132: aload_1
     133: invokevirtual #219                // Method java/net/URL.getPath:()Ljava/lang/String;
     136: astore        10
     138: aload         10
     140: aload         9
     142: invokevirtual #273                // Method java/lang/String.endsWith:(Ljava/lang/String;)Z
     145: ifeq          231
     148: aload         5
     150: invokevirtual #274                // Method java/io/File.getAbsolutePath:()Ljava/lang/String;
     153: astore        11
     155: aload         11
     157: ifnull        184
     160: aload         11
     162: ldc_w         #275                // String /
     165: invokevirtual #276                // Method java/lang/String.indexOf:(Ljava/lang/String;)I
     168: ifne          184
     171: aload         11
     173: iconst_1
     174: aload         11
     176: invokevirtual #39                 // Method java/lang/String.length:()I
     179: invokevirtual #277                // Method java/lang/String.substring:(II)Ljava/lang/String;
     182: astore        11
     184: new           #26                 // class java/net/URL
     187: dup
     188: new           #18                 // class java/lang/StringBuilder
     191: dup
     192: invokespecial #19                 // Method java/lang/StringBuilder."<init>":()V
     195: ldc_w         #278                // String jar:file:/
     198: invokevirtual #22                 // Method java/lang/StringBuilder.append:(Ljava/lang/String;)Ljava/lang/StringBuilder;
     201: aload         11
     203: invokevirtual #22                 // Method java/lang/StringBuilder.append:(Ljava/lang/String;)Ljava/lang/StringBuilder;
     206: ldc_w         #279                // String !/
     209: invokevirtual #22                 // Method java/lang/StringBuilder.append:(Ljava/lang/String;)Ljava/lang/StringBuilder;
     212: aload         8
     214: invokevirtual #271                // Method java/util/jar/JarEntry.getName:()Ljava/lang/String;
     217: invokevirtual #22                 // Method java/lang/StringBuilder.append:(Ljava/lang/String;)Ljava/lang/StringBuilder;
     220: invokevirtual #24                 // Method java/lang/StringBuilder.toString:()Ljava/lang/String;
     223: invokespecial #27                 // Method java/net/URL."<init>":(Ljava/lang/String;)V
     226: astore        12
     228: aload         12
     230: areturn
     231: goto          92
     234: goto          260
     237: astore        6
     239: new           #239                // class javax/wsdl/WSDLException
     242: dup
     243: ldc           #245                // String WSDLWrapperReloadImpl :
     245: aload         6
     247: invokevirtual #34                 // Method java/lang/Exception.getMessage:()Ljava/lang/String;
     250: aload         6
     252: invokespecial #242                // Method javax/wsdl/WSDLException."<init>":(Ljava/lang/String;Ljava/lang/String;Ljava/lang/Throwable;)V
     255: astore        7
     257: aload         7
     259: athrow
     260: iinc          3, 1
     263: goto          13
     266: aconst_null
     267: areturn
    Exception table:
       from    to  target type
          74   230   237   Class java/lang/Exception
         231   234   237   Class java/lang/Exception

  private javax.wsdl.xml.WSDLReader getWSDLReader() throws javax.wsdl.WSDLException;
    Code:
       0: new           #280                // class org/apache/axis2/wsdl/util/WSDLWrapperReloadImpl$4
       3: dup
       4: aload_0
       5: invokespecial #281                // Method org/apache/axis2/wsdl/util/WSDLWrapperReloadImpl$4."<init>":(Lorg/apache/axis2/wsdl/util/WSDLWrapperReloadImpl;)V
       8: invokestatic  #255                // Method org/apache/axis2/java/security/AccessController.doPrivileged:(Ljava/security/PrivilegedExceptionAction;)Ljava/lang/Object;
      11: checkcast     #282                // class javax/wsdl/xml/WSDLReader
      14: astore_1
      15: goto          27
      18: astore_2
      19: aload_2
      20: invokevirtual #283                // Method java/security/PrivilegedActionException.getException:()Ljava/lang/Exception;
      23: checkcast     #239                // class javax/wsdl/WSDLException
      26: athrow
      27: aload_1
      28: ldc_w         #285                // String javax.wsdl.verbose
      31: iconst_0
      32: invokeinterface #286,  3          // InterfaceMethod javax/wsdl/xml/WSDLReader.setFeature:(Ljava/lang/String;Z)V
      37: aload_1
      38: areturn
    Exception table:
       from    to  target type
           0    15    18   Class java/security/PrivilegedActionException

  private static java.io.InputStream getInputStream(java.net.URLConnection) throws java.lang.Exception;
    Code:
       0: aload_0
       1: astore_1
       2: aconst_null
       3: astore_2
       4: new           #287                // class org/apache/axis2/wsdl/util/WSDLWrapperReloadImpl$5
       7: dup
       8: aload_1
       9: invokespecial #288                // Method org/apache/axis2/wsdl/util/WSDLWrapperReloadImpl$5."<init>":(Ljava/net/URLConnection;)V
      12: invokestatic  #255                // Method org/apache/axis2/java/security/AccessController.doPrivileged:(Ljava/security/PrivilegedExceptionAction;)Ljava/lang/Object;
      15: checkcast     #289                // class java/io/InputStream
      18: astore_2
      19: goto          28
      22: astore_3
      23: aload_3
      24: invokevirtual #283                // Method java/security/PrivilegedActionException.getException:()Ljava/lang/Exception;
      27: athrow
      28: aload_2
      29: areturn
    Exception table:
       from    to  target type
           4    19    22   Class java/security/PrivilegedActionException

  static javax.wsdl.xml.WSDLReader access$000(org.apache.axis2.wsdl.util.WSDLWrapperReloadImpl) throws javax.wsdl.WSDLException;
    Code:
       0: aload_0
       1: invokespecial #2                  // Method getWSDLReader:()Ljavax/wsdl/xml/WSDLReader;
       4: areturn

  static java.lang.String access$100(org.apache.axis2.wsdl.util.WSDLWrapperReloadImpl);
    Code:
       0: aload_0
       1: getfield      #1                  // Field wsdlExplicitURI:Ljava/lang/String;
       4: areturn

  static {};
    Code:
       0: ldc           #20                 // class org/apache/axis2/wsdl/util/WSDLWrapperReloadImpl
       2: invokestatic  #290                // Method org/apache/commons/logging/LogFactory.getLog:(Ljava/lang/Class;)Lorg/apache/commons/logging/Log;
       5: putstatic     #9                  // Field log:Lorg/apache/commons/logging/Log;
       8: getstatic     #9                  // Field log:Lorg/apache/commons/logging/Log;
      11: invokeinterface #10,  1           // InterfaceMethod org/apache/commons/logging/Log.isDebugEnabled:()Z
      16: putstatic     #17                 // Field isDebugEnabled:Z
      19: iconst_1
      20: putstatic     #54                 // Field USE_SOFT_REFERENCES:Z
      23: return
}
