Compiled from "PipelineSpecFluentImpl.java"
public class io.dekorate.deps.tekton.pipeline.v1beta1.PipelineSpecFluentImpl<A extends io.dekorate.deps.tekton.pipeline.v1beta1.PipelineSpecFluent<A>> extends io.dekorate.deps.kubernetes.api.builder.BaseFluent<A> implements io.dekorate.deps.tekton.pipeline.v1beta1.PipelineSpecFluent<A> {
  private java.lang.String description;

  private java.util.List<io.dekorate.deps.tekton.pipeline.v1beta1.ParamSpecBuilder> params;

  private java.util.List<io.dekorate.deps.tekton.pipeline.v1beta1.PipelineDeclaredResourceBuilder> resources;

  private java.util.List<io.dekorate.deps.tekton.pipeline.v1beta1.PipelineTaskBuilder> tasks;

  private java.util.List<io.dekorate.deps.tekton.pipeline.v1beta1.WorkspacePipelineDeclarationBuilder> workspaces;

  public io.dekorate.deps.tekton.pipeline.v1beta1.PipelineSpecFluentImpl();
    Code:
       0: aload_0
       1: invokespecial #47                 // Method io/dekorate/deps/kubernetes/api/builder/BaseFluent."<init>":()V
       4: return

  public io.dekorate.deps.tekton.pipeline.v1beta1.PipelineSpecFluentImpl(io.dekorate.deps.tekton.pipeline.v1beta1.PipelineSpec);
    Code:
       0: aload_0
       1: invokespecial #47                 // Method io/dekorate/deps/kubernetes/api/builder/BaseFluent."<init>":()V
       4: aload_0
       5: aload_1
       6: invokevirtual #57                 // Method io/dekorate/deps/tekton/pipeline/v1beta1/PipelineSpec.getDescription:()Ljava/lang/String;
       9: invokevirtual #61                 // Method withDescription:(Ljava/lang/String;)Lio/dekorate/deps/tekton/pipeline/v1beta1/PipelineSpecFluent;
      12: pop
      13: aload_0
      14: aload_1
      15: invokevirtual #65                 // Method io/dekorate/deps/tekton/pipeline/v1beta1/PipelineSpec.getParams:()Ljava/util/List;
      18: invokevirtual #69                 // Method withParams:(Ljava/util/List;)Lio/dekorate/deps/tekton/pipeline/v1beta1/PipelineSpecFluent;
      21: pop
      22: aload_0
      23: aload_1
      24: invokevirtual #72                 // Method io/dekorate/deps/tekton/pipeline/v1beta1/PipelineSpec.getResources:()Ljava/util/List;
      27: invokevirtual #75                 // Method withResources:(Ljava/util/List;)Lio/dekorate/deps/tekton/pipeline/v1beta1/PipelineSpecFluent;
      30: pop
      31: aload_0
      32: aload_1
      33: invokevirtual #78                 // Method io/dekorate/deps/tekton/pipeline/v1beta1/PipelineSpec.getTasks:()Ljava/util/List;
      36: invokevirtual #81                 // Method withTasks:(Ljava/util/List;)Lio/dekorate/deps/tekton/pipeline/v1beta1/PipelineSpecFluent;
      39: pop
      40: aload_0
      41: aload_1
      42: invokevirtual #84                 // Method io/dekorate/deps/tekton/pipeline/v1beta1/PipelineSpec.getWorkspaces:()Ljava/util/List;
      45: invokevirtual #87                 // Method withWorkspaces:(Ljava/util/List;)Lio/dekorate/deps/tekton/pipeline/v1beta1/PipelineSpecFluent;
      48: pop
      49: return

  public java.lang.String getDescription();
    Code:
       0: aload_0
       1: getfield      #91                 // Field description:Ljava/lang/String;
       4: areturn

  public A withDescription(java.lang.String);
    Code:
       0: aload_0
       1: aload_1
       2: putfield      #91                 // Field description:Ljava/lang/String;
       5: aload_0
       6: areturn

  public java.lang.Boolean hasDescription();
    Code:
       0: aload_0
       1: getfield      #91                 // Field description:Ljava/lang/String;
       4: ifnull        11
       7: iconst_1
       8: goto          12
      11: iconst_0
      12: invokestatic  #100                // Method java/lang/Boolean.valueOf:(Z)Ljava/lang/Boolean;
      15: areturn

  public A withNewDescription(java.lang.String);
    Code:
       0: aload_0
       1: new           #103                // class java/lang/String
       4: dup
       5: aload_1
       6: invokespecial #106                // Method java/lang/String."<init>":(Ljava/lang/String;)V
       9: invokevirtual #61                 // Method withDescription:(Ljava/lang/String;)Lio/dekorate/deps/tekton/pipeline/v1beta1/PipelineSpecFluent;
      12: areturn

  public A withNewDescription(java.lang.StringBuilder);
    Code:
       0: aload_0
       1: new           #103                // class java/lang/String
       4: dup
       5: aload_1
       6: invokespecial #112                // Method java/lang/String."<init>":(Ljava/lang/StringBuilder;)V
       9: invokevirtual #61                 // Method withDescription:(Ljava/lang/String;)Lio/dekorate/deps/tekton/pipeline/v1beta1/PipelineSpecFluent;
      12: areturn

  public A withNewDescription(java.lang.StringBuffer);
    Code:
       0: aload_0
       1: new           #103                // class java/lang/String
       4: dup
       5: aload_1
       6: invokespecial #118                // Method java/lang/String."<init>":(Ljava/lang/StringBuffer;)V
       9: invokevirtual #61                 // Method withDescription:(Ljava/lang/String;)Lio/dekorate/deps/tekton/pipeline/v1beta1/PipelineSpecFluent;
      12: areturn

  public A addToParams(int, io.dekorate.deps.tekton.pipeline.v1beta1.ParamSpec);
    Code:
       0: aload_0
       1: getfield      #124                // Field params:Ljava/util/List;
       4: ifnonnull     18
       7: aload_0
       8: new           #126                // class java/util/ArrayList
      11: dup
      12: invokespecial #127                // Method java/util/ArrayList."<init>":()V
      15: putfield      #124                // Field params:Ljava/util/List;
      18: new           #129                // class io/dekorate/deps/tekton/pipeline/v1beta1/ParamSpecBuilder
      21: dup
      22: aload_2
      23: invokespecial #132                // Method io/dekorate/deps/tekton/pipeline/v1beta1/ParamSpecBuilder."<init>":(Lio/dekorate/deps/tekton/pipeline/v1beta1/ParamSpec;)V
      26: astore_3
      27: aload_0
      28: getfield      #136                // Field _visitables:Lio/dekorate/deps/kubernetes/api/builder/VisitableMap;
      31: ldc           #137                // String params
      33: invokevirtual #143                // Method io/dekorate/deps/kubernetes/api/builder/VisitableMap.get:(Ljava/lang/Object;)Ljava/util/List;
      36: iload_1
      37: iflt          44
      40: iload_1
      41: goto          58
      44: aload_0
      45: getfield      #136                // Field _visitables:Lio/dekorate/deps/kubernetes/api/builder/VisitableMap;
      48: ldc           #137                // String params
      50: invokevirtual #143                // Method io/dekorate/deps/kubernetes/api/builder/VisitableMap.get:(Ljava/lang/Object;)Ljava/util/List;
      53: invokeinterface #151,  1          // InterfaceMethod java/util/List.size:()I
      58: aload_3
      59: invokeinterface #155,  3          // InterfaceMethod java/util/List.add:(ILjava/lang/Object;)V
      64: aload_0
      65: getfield      #124                // Field params:Ljava/util/List;
      68: iload_1
      69: iflt          76
      72: iload_1
      73: goto          85
      76: aload_0
      77: getfield      #124                // Field params:Ljava/util/List;
      80: invokeinterface #151,  1          // InterfaceMethod java/util/List.size:()I
      85: aload_3
      86: invokeinterface #155,  3          // InterfaceMethod java/util/List.add:(ILjava/lang/Object;)V
      91: aload_0
      92: areturn

  public A setToParams(int, io.dekorate.deps.tekton.pipeline.v1beta1.ParamSpec);
    Code:
       0: aload_0
       1: getfield      #124                // Field params:Ljava/util/List;
       4: ifnonnull     18
       7: aload_0
       8: new           #126                // class java/util/ArrayList
      11: dup
      12: invokespecial #127                // Method java/util/ArrayList."<init>":()V
      15: putfield      #124                // Field params:Ljava/util/List;
      18: new           #129                // class io/dekorate/deps/tekton/pipeline/v1beta1/ParamSpecBuilder
      21: dup
      22: aload_2
      23: invokespecial #132                // Method io/dekorate/deps/tekton/pipeline/v1beta1/ParamSpecBuilder."<init>":(Lio/dekorate/deps/tekton/pipeline/v1beta1/ParamSpec;)V
      26: astore_3
      27: iload_1
      28: iflt          49
      31: iload_1
      32: aload_0
      33: getfield      #136                // Field _visitables:Lio/dekorate/deps/kubernetes/api/builder/VisitableMap;
      36: ldc           #137                // String params
      38: invokevirtual #143                // Method io/dekorate/deps/kubernetes/api/builder/VisitableMap.get:(Ljava/lang/Object;)Ljava/util/List;
      41: invokeinterface #151,  1          // InterfaceMethod java/util/List.size:()I
      46: if_icmplt     68
      49: aload_0
      50: getfield      #136                // Field _visitables:Lio/dekorate/deps/kubernetes/api/builder/VisitableMap;
      53: ldc           #137                // String params
      55: invokevirtual #143                // Method io/dekorate/deps/kubernetes/api/builder/VisitableMap.get:(Ljava/lang/Object;)Ljava/util/List;
      58: aload_3
      59: invokeinterface #165,  2          // InterfaceMethod java/util/List.add:(Ljava/lang/Object;)Z
      64: pop
      65: goto          85
      68: aload_0
      69: getfield      #136                // Field _visitables:Lio/dekorate/deps/kubernetes/api/builder/VisitableMap;
      72: ldc           #137                // String params
      74: invokevirtual #143                // Method io/dekorate/deps/kubernetes/api/builder/VisitableMap.get:(Ljava/lang/Object;)Ljava/util/List;
      77: iload_1
      78: aload_3
      79: invokeinterface #169,  3          // InterfaceMethod java/util/List.set:(ILjava/lang/Object;)Ljava/lang/Object;
      84: pop
      85: iload_1
      86: iflt          102
      89: iload_1
      90: aload_0
      91: getfield      #124                // Field params:Ljava/util/List;
      94: invokeinterface #151,  1          // InterfaceMethod java/util/List.size:()I
      99: if_icmplt     116
     102: aload_0
     103: getfield      #124                // Field params:Ljava/util/List;
     106: aload_3
     107: invokeinterface #165,  2          // InterfaceMethod java/util/List.add:(Ljava/lang/Object;)Z
     112: pop
     113: goto          128
     116: aload_0
     117: getfield      #124                // Field params:Ljava/util/List;
     120: iload_1
     121: aload_3
     122: invokeinterface #169,  3          // InterfaceMethod java/util/List.set:(ILjava/lang/Object;)Ljava/lang/Object;
     127: pop
     128: aload_0
     129: areturn

  public A addToParams(io.dekorate.deps.tekton.pipeline.v1beta1.ParamSpec...);
    Code:
       0: aload_0
       1: getfield      #124                // Field params:Ljava/util/List;
       4: ifnonnull     18
       7: aload_0
       8: new           #126                // class java/util/ArrayList
      11: dup
      12: invokespecial #127                // Method java/util/ArrayList."<init>":()V
      15: putfield      #124                // Field params:Ljava/util/List;
      18: aload_1
      19: astore_2
      20: aload_2
      21: arraylength
      22: istore_3
      23: iconst_0
      24: istore        4
      26: iload         4
      28: iload_3
      29: if_icmpge     84
      32: aload_2
      33: iload         4
      35: aaload
      36: astore        5
      38: new           #129                // class io/dekorate/deps/tekton/pipeline/v1beta1/ParamSpecBuilder
      41: dup
      42: aload         5
      44: invokespecial #132                // Method io/dekorate/deps/tekton/pipeline/v1beta1/ParamSpecBuilder."<init>":(Lio/dekorate/deps/tekton/pipeline/v1beta1/ParamSpec;)V
      47: astore        6
      49: aload_0
      50: getfield      #136                // Field _visitables:Lio/dekorate/deps/kubernetes/api/builder/VisitableMap;
      53: ldc           #137                // String params
      55: invokevirtual #143                // Method io/dekorate/deps/kubernetes/api/builder/VisitableMap.get:(Ljava/lang/Object;)Ljava/util/List;
      58: aload         6
      60: invokeinterface #165,  2          // InterfaceMethod java/util/List.add:(Ljava/lang/Object;)Z
      65: pop
      66: aload_0
      67: getfield      #124                // Field params:Ljava/util/List;
      70: aload         6
      72: invokeinterface #165,  2          // InterfaceMethod java/util/List.add:(Ljava/lang/Object;)Z
      77: pop
      78: iinc          4, 1
      81: goto          26
      84: aload_0
      85: areturn

  public A addAllToParams(java.util.Collection<io.dekorate.deps.tekton.pipeline.v1beta1.ParamSpec>);
    Code:
       0: aload_0
       1: getfield      #124                // Field params:Ljava/util/List;
       4: ifnonnull     18
       7: aload_0
       8: new           #126                // class java/util/ArrayList
      11: dup
      12: invokespecial #127                // Method java/util/ArrayList."<init>":()V
      15: putfield      #124                // Field params:Ljava/util/List;
      18: aload_1
      19: invokeinterface #183,  1          // InterfaceMethod java/util/Collection.iterator:()Ljava/util/Iterator;
      24: astore_2
      25: aload_2
      26: invokeinterface #189,  1          // InterfaceMethod java/util/Iterator.hasNext:()Z
      31: ifeq          86
      34: aload_2
      35: invokeinterface #193,  1          // InterfaceMethod java/util/Iterator.next:()Ljava/lang/Object;
      40: checkcast     #145                // class io/dekorate/deps/tekton/pipeline/v1beta1/ParamSpec
      43: astore_3
      44: new           #129                // class io/dekorate/deps/tekton/pipeline/v1beta1/ParamSpecBuilder
      47: dup
      48: aload_3
      49: invokespecial #132                // Method io/dekorate/deps/tekton/pipeline/v1beta1/ParamSpecBuilder."<init>":(Lio/dekorate/deps/tekton/pipeline/v1beta1/ParamSpec;)V
      52: astore        4
      54: aload_0
      55: getfield      #136                // Field _visitables:Lio/dekorate/deps/kubernetes/api/builder/VisitableMap;
      58: ldc           #137                // String params
      60: invokevirtual #143                // Method io/dekorate/deps/kubernetes/api/builder/VisitableMap.get:(Ljava/lang/Object;)Ljava/util/List;
      63: aload         4
      65: invokeinterface #165,  2          // InterfaceMethod java/util/List.add:(Ljava/lang/Object;)Z
      70: pop
      71: aload_0
      72: getfield      #124                // Field params:Ljava/util/List;
      75: aload         4
      77: invokeinterface #165,  2          // InterfaceMethod java/util/List.add:(Ljava/lang/Object;)Z
      82: pop
      83: goto          25
      86: aload_0
      87: areturn

  public A removeFromParams(io.dekorate.deps.tekton.pipeline.v1beta1.ParamSpec...);
    Code:
       0: aload_1
       1: astore_2
       2: aload_2
       3: arraylength
       4: istore_3
       5: iconst_0
       6: istore        4
       8: iload         4
      10: iload_3
      11: if_icmpge     73
      14: aload_2
      15: iload         4
      17: aaload
      18: astore        5
      20: new           #129                // class io/dekorate/deps/tekton/pipeline/v1beta1/ParamSpecBuilder
      23: dup
      24: aload         5
      26: invokespecial #132                // Method io/dekorate/deps/tekton/pipeline/v1beta1/ParamSpecBuilder."<init>":(Lio/dekorate/deps/tekton/pipeline/v1beta1/ParamSpec;)V
      29: astore        6
      31: aload_0
      32: getfield      #136                // Field _visitables:Lio/dekorate/deps/kubernetes/api/builder/VisitableMap;
      35: ldc           #137                // String params
      37: invokevirtual #143                // Method io/dekorate/deps/kubernetes/api/builder/VisitableMap.get:(Ljava/lang/Object;)Ljava/util/List;
      40: aload         6
      42: invokeinterface #199,  2          // InterfaceMethod java/util/List.remove:(Ljava/lang/Object;)Z
      47: pop
      48: aload_0
      49: getfield      #124                // Field params:Ljava/util/List;
      52: ifnull        67
      55: aload_0
      56: getfield      #124                // Field params:Ljava/util/List;
      59: aload         6
      61: invokeinterface #199,  2          // InterfaceMethod java/util/List.remove:(Ljava/lang/Object;)Z
      66: pop
      67: iinc          4, 1
      70: goto          8
      73: aload_0
      74: areturn

  public A removeAllFromParams(java.util.Collection<io.dekorate.deps.tekton.pipeline.v1beta1.ParamSpec>);
    Code:
       0: aload_1
       1: invokeinterface #183,  1          // InterfaceMethod java/util/Collection.iterator:()Ljava/util/Iterator;
       6: astore_2
       7: aload_2
       8: invokeinterface #189,  1          // InterfaceMethod java/util/Iterator.hasNext:()Z
      13: ifeq          75
      16: aload_2
      17: invokeinterface #193,  1          // InterfaceMethod java/util/Iterator.next:()Ljava/lang/Object;
      22: checkcast     #145                // class io/dekorate/deps/tekton/pipeline/v1beta1/ParamSpec
      25: astore_3
      26: new           #129                // class io/dekorate/deps/tekton/pipeline/v1beta1/ParamSpecBuilder
      29: dup
      30: aload_3
      31: invokespecial #132                // Method io/dekorate/deps/tekton/pipeline/v1beta1/ParamSpecBuilder."<init>":(Lio/dekorate/deps/tekton/pipeline/v1beta1/ParamSpec;)V
      34: astore        4
      36: aload_0
      37: getfield      #136                // Field _visitables:Lio/dekorate/deps/kubernetes/api/builder/VisitableMap;
      40: ldc           #137                // String params
      42: invokevirtual #143                // Method io/dekorate/deps/kubernetes/api/builder/VisitableMap.get:(Ljava/lang/Object;)Ljava/util/List;
      45: aload         4
      47: invokeinterface #199,  2          // InterfaceMethod java/util/List.remove:(Ljava/lang/Object;)Z
      52: pop
      53: aload_0
      54: getfield      #124                // Field params:Ljava/util/List;
      57: ifnull        72
      60: aload_0
      61: getfield      #124                // Field params:Ljava/util/List;
      64: aload         4
      66: invokeinterface #199,  2          // InterfaceMethod java/util/List.remove:(Ljava/lang/Object;)Z
      71: pop
      72: goto          7
      75: aload_0
      76: areturn

  public A removeMatchingFromParams(io.dekorate.deps.kubernetes.api.builder.Predicate<io.dekorate.deps.tekton.pipeline.v1beta1.ParamSpecBuilder>);
    Code:
       0: aload_0
       1: getfield      #124                // Field params:Ljava/util/List;
       4: ifnonnull     9
       7: aload_0
       8: areturn
       9: aload_0
      10: getfield      #124                // Field params:Ljava/util/List;
      13: invokeinterface #204,  1          // InterfaceMethod java/util/List.iterator:()Ljava/util/Iterator;
      18: astore_2
      19: aload_0
      20: getfield      #136                // Field _visitables:Lio/dekorate/deps/kubernetes/api/builder/VisitableMap;
      23: ldc           #137                // String params
      25: invokevirtual #143                // Method io/dekorate/deps/kubernetes/api/builder/VisitableMap.get:(Ljava/lang/Object;)Ljava/util/List;
      28: astore_3
      29: aload_2
      30: invokeinterface #189,  1          // InterfaceMethod java/util/Iterator.hasNext:()Z
      35: ifeq          81
      38: aload_2
      39: invokeinterface #193,  1          // InterfaceMethod java/util/Iterator.next:()Ljava/lang/Object;
      44: checkcast     #129                // class io/dekorate/deps/tekton/pipeline/v1beta1/ParamSpecBuilder
      47: astore        4
      49: aload_1
      50: aload         4
      52: invokeinterface #210,  2          // InterfaceMethod io/dekorate/deps/kubernetes/api/builder/Predicate.apply:(Ljava/lang/Object;)Ljava/lang/Boolean;
      57: invokevirtual #213                // Method java/lang/Boolean.booleanValue:()Z
      60: ifeq          78
      63: aload_3
      64: aload         4
      66: invokeinterface #199,  2          // InterfaceMethod java/util/List.remove:(Ljava/lang/Object;)Z
      71: pop
      72: aload_2
      73: invokeinterface #215,  1          // InterfaceMethod java/util/Iterator.remove:()V
      78: goto          29
      81: aload_0
      82: areturn

  public java.util.List<io.dekorate.deps.tekton.pipeline.v1beta1.ParamSpec> getParams();
    Code:
       0: aload_0
       1: getfield      #124                // Field params:Ljava/util/List;
       4: invokestatic  #228                // Method build:(Ljava/util/List;)Ljava/util/ArrayList;
       7: areturn

  public java.util.List<io.dekorate.deps.tekton.pipeline.v1beta1.ParamSpec> buildParams();
    Code:
       0: aload_0
       1: getfield      #124                // Field params:Ljava/util/List;
       4: invokestatic  #228                // Method build:(Ljava/util/List;)Ljava/util/ArrayList;
       7: areturn

  public io.dekorate.deps.tekton.pipeline.v1beta1.ParamSpec buildParam(int);
    Code:
       0: aload_0
       1: getfield      #124                // Field params:Ljava/util/List;
       4: iload_1
       5: invokeinterface #234,  2          // InterfaceMethod java/util/List.get:(I)Ljava/lang/Object;
      10: checkcast     #129                // class io/dekorate/deps/tekton/pipeline/v1beta1/ParamSpecBuilder
      13: invokevirtual #237                // Method io/dekorate/deps/tekton/pipeline/v1beta1/ParamSpecBuilder.build:()Lio/dekorate/deps/tekton/pipeline/v1beta1/ParamSpec;
      16: areturn

  public io.dekorate.deps.tekton.pipeline.v1beta1.ParamSpec buildFirstParam();
    Code:
       0: aload_0
       1: getfield      #124                // Field params:Ljava/util/List;
       4: iconst_0
       5: invokeinterface #234,  2          // InterfaceMethod java/util/List.get:(I)Ljava/lang/Object;
      10: checkcast     #129                // class io/dekorate/deps/tekton/pipeline/v1beta1/ParamSpecBuilder
      13: invokevirtual #237                // Method io/dekorate/deps/tekton/pipeline/v1beta1/ParamSpecBuilder.build:()Lio/dekorate/deps/tekton/pipeline/v1beta1/ParamSpec;
      16: areturn

  public io.dekorate.deps.tekton.pipeline.v1beta1.ParamSpec buildLastParam();
    Code:
       0: aload_0
       1: getfield      #124                // Field params:Ljava/util/List;
       4: aload_0
       5: getfield      #124                // Field params:Ljava/util/List;
       8: invokeinterface #151,  1          // InterfaceMethod java/util/List.size:()I
      13: iconst_1
      14: isub
      15: invokeinterface #234,  2          // InterfaceMethod java/util/List.get:(I)Ljava/lang/Object;
      20: checkcast     #129                // class io/dekorate/deps/tekton/pipeline/v1beta1/ParamSpecBuilder
      23: invokevirtual #237                // Method io/dekorate/deps/tekton/pipeline/v1beta1/ParamSpecBuilder.build:()Lio/dekorate/deps/tekton/pipeline/v1beta1/ParamSpec;
      26: areturn

  public io.dekorate.deps.tekton.pipeline.v1beta1.ParamSpec buildMatchingParam(io.dekorate.deps.kubernetes.api.builder.Predicate<io.dekorate.deps.tekton.pipeline.v1beta1.ParamSpecBuilder>);
    Code:
       0: aload_0
       1: getfield      #124                // Field params:Ljava/util/List;
       4: invokeinterface #204,  1          // InterfaceMethod java/util/List.iterator:()Ljava/util/Iterator;
       9: astore_2
      10: aload_2
      11: invokeinterface #189,  1          // InterfaceMethod java/util/Iterator.hasNext:()Z
      16: ifeq          50
      19: aload_2
      20: invokeinterface #193,  1          // InterfaceMethod java/util/Iterator.next:()Ljava/lang/Object;
      25: checkcast     #129                // class io/dekorate/deps/tekton/pipeline/v1beta1/ParamSpecBuilder
      28: astore_3
      29: aload_1
      30: aload_3
      31: invokeinterface #210,  2          // InterfaceMethod io/dekorate/deps/kubernetes/api/builder/Predicate.apply:(Ljava/lang/Object;)Ljava/lang/Boolean;
      36: invokevirtual #213                // Method java/lang/Boolean.booleanValue:()Z
      39: ifeq          47
      42: aload_3
      43: invokevirtual #237                // Method io/dekorate/deps/tekton/pipeline/v1beta1/ParamSpecBuilder.build:()Lio/dekorate/deps/tekton/pipeline/v1beta1/ParamSpec;
      46: areturn
      47: goto          10
      50: aconst_null
      51: areturn

  public java.lang.Boolean hasMatchingParam(io.dekorate.deps.kubernetes.api.builder.Predicate<io.dekorate.deps.tekton.pipeline.v1beta1.ParamSpecBuilder>);
    Code:
       0: aload_0
       1: getfield      #124                // Field params:Ljava/util/List;
       4: invokeinterface #204,  1          // InterfaceMethod java/util/List.iterator:()Ljava/util/Iterator;
       9: astore_2
      10: aload_2
      11: invokeinterface #189,  1          // InterfaceMethod java/util/Iterator.hasNext:()Z
      16: ifeq          50
      19: aload_2
      20: invokeinterface #193,  1          // InterfaceMethod java/util/Iterator.next:()Ljava/lang/Object;
      25: checkcast     #129                // class io/dekorate/deps/tekton/pipeline/v1beta1/ParamSpecBuilder
      28: astore_3
      29: aload_1
      30: aload_3
      31: invokeinterface #210,  2          // InterfaceMethod io/dekorate/deps/kubernetes/api/builder/Predicate.apply:(Ljava/lang/Object;)Ljava/lang/Boolean;
      36: invokevirtual #213                // Method java/lang/Boolean.booleanValue:()Z
      39: ifeq          47
      42: iconst_1
      43: invokestatic  #100                // Method java/lang/Boolean.valueOf:(Z)Ljava/lang/Boolean;
      46: areturn
      47: goto          10
      50: iconst_0
      51: invokestatic  #100                // Method java/lang/Boolean.valueOf:(Z)Ljava/lang/Boolean;
      54: areturn

  public A withParams(java.util.List<io.dekorate.deps.tekton.pipeline.v1beta1.ParamSpec>);
    Code:
       0: aload_0
       1: getfield      #124                // Field params:Ljava/util/List;
       4: ifnull        26
       7: aload_0
       8: getfield      #136                // Field _visitables:Lio/dekorate/deps/kubernetes/api/builder/VisitableMap;
      11: ldc           #137                // String params
      13: invokevirtual #143                // Method io/dekorate/deps/kubernetes/api/builder/VisitableMap.get:(Ljava/lang/Object;)Ljava/util/List;
      16: aload_0
      17: getfield      #124                // Field params:Ljava/util/List;
      20: invokeinterface #250,  2          // InterfaceMethod java/util/List.removeAll:(Ljava/util/Collection;)Z
      25: pop
      26: aload_1
      27: ifnull        86
      30: aload_0
      31: new           #126                // class java/util/ArrayList
      34: dup
      35: invokespecial #127                // Method java/util/ArrayList."<init>":()V
      38: putfield      #124                // Field params:Ljava/util/List;
      41: aload_1
      42: invokeinterface #204,  1          // InterfaceMethod java/util/List.iterator:()Ljava/util/Iterator;
      47: astore_2
      48: aload_2
      49: invokeinterface #189,  1          // InterfaceMethod java/util/Iterator.hasNext:()Z
      54: ifeq          83
      57: aload_2
      58: invokeinterface #193,  1          // InterfaceMethod java/util/Iterator.next:()Ljava/lang/Object;
      63: checkcast     #145                // class io/dekorate/deps/tekton/pipeline/v1beta1/ParamSpec
      66: astore_3
      67: aload_0
      68: iconst_1
      69: anewarray     #145                // class io/dekorate/deps/tekton/pipeline/v1beta1/ParamSpec
      72: dup
      73: iconst_0
      74: aload_3
      75: aastore
      76: invokevirtual #252                // Method addToParams:([Lio/dekorate/deps/tekton/pipeline/v1beta1/ParamSpec;)Lio/dekorate/deps/tekton/pipeline/v1beta1/PipelineSpecFluent;
      79: pop
      80: goto          48
      83: goto          91
      86: aload_0
      87: aconst_null
      88: putfield      #124                // Field params:Ljava/util/List;
      91: aload_0
      92: areturn

  public A withParams(io.dekorate.deps.tekton.pipeline.v1beta1.ParamSpec...);
    Code:
       0: aload_0
       1: getfield      #124                // Field params:Ljava/util/List;
       4: ifnull        16
       7: aload_0
       8: getfield      #124                // Field params:Ljava/util/List;
      11: invokeinterface #256,  1          // InterfaceMethod java/util/List.clear:()V
      16: aload_1
      17: ifnull        60
      20: aload_1
      21: astore_2
      22: aload_2
      23: arraylength
      24: istore_3
      25: iconst_0
      26: istore        4
      28: iload         4
      30: iload_3
      31: if_icmpge     60
      34: aload_2
      35: iload         4
      37: aaload
      38: astore        5
      40: aload_0
      41: iconst_1
      42: anewarray     #145                // class io/dekorate/deps/tekton/pipeline/v1beta1/ParamSpec
      45: dup
      46: iconst_0
      47: aload         5
      49: aastore
      50: invokevirtual #252                // Method addToParams:([Lio/dekorate/deps/tekton/pipeline/v1beta1/ParamSpec;)Lio/dekorate/deps/tekton/pipeline/v1beta1/PipelineSpecFluent;
      53: pop
      54: iinc          4, 1
      57: goto          28
      60: aload_0
      61: areturn

  public java.lang.Boolean hasParams();
    Code:
       0: aload_0
       1: getfield      #124                // Field params:Ljava/util/List;
       4: ifnull        23
       7: aload_0
       8: getfield      #124                // Field params:Ljava/util/List;
      11: invokeinterface #260,  1          // InterfaceMethod java/util/List.isEmpty:()Z
      16: ifne          23
      19: iconst_1
      20: goto          24
      23: iconst_0
      24: invokestatic  #100                // Method java/lang/Boolean.valueOf:(Z)Ljava/lang/Boolean;
      27: areturn

  public io.dekorate.deps.tekton.pipeline.v1beta1.PipelineSpecFluent$ParamsNested<A> addNewParam();
    Code:
       0: new           #19                 // class io/dekorate/deps/tekton/pipeline/v1beta1/PipelineSpecFluentImpl$ParamsNestedImpl
       3: dup
       4: aload_0
       5: invokespecial #266                // Method io/dekorate/deps/tekton/pipeline/v1beta1/PipelineSpecFluentImpl$ParamsNestedImpl."<init>":(Lio/dekorate/deps/tekton/pipeline/v1beta1/PipelineSpecFluentImpl;)V
       8: areturn

  public io.dekorate.deps.tekton.pipeline.v1beta1.PipelineSpecFluent$ParamsNested<A> addNewParamLike(io.dekorate.deps.tekton.pipeline.v1beta1.ParamSpec);
    Code:
       0: new           #19                 // class io/dekorate/deps/tekton/pipeline/v1beta1/PipelineSpecFluentImpl$ParamsNestedImpl
       3: dup
       4: aload_0
       5: iconst_m1
       6: aload_1
       7: invokespecial #272                // Method io/dekorate/deps/tekton/pipeline/v1beta1/PipelineSpecFluentImpl$ParamsNestedImpl."<init>":(Lio/dekorate/deps/tekton/pipeline/v1beta1/PipelineSpecFluentImpl;ILio/dekorate/deps/tekton/pipeline/v1beta1/ParamSpec;)V
      10: areturn

  public io.dekorate.deps.tekton.pipeline.v1beta1.PipelineSpecFluent$ParamsNested<A> setNewParamLike(int, io.dekorate.deps.tekton.pipeline.v1beta1.ParamSpec);
    Code:
       0: new           #19                 // class io/dekorate/deps/tekton/pipeline/v1beta1/PipelineSpecFluentImpl$ParamsNestedImpl
       3: dup
       4: aload_0
       5: iload_1
       6: aload_2
       7: invokespecial #272                // Method io/dekorate/deps/tekton/pipeline/v1beta1/PipelineSpecFluentImpl$ParamsNestedImpl."<init>":(Lio/dekorate/deps/tekton/pipeline/v1beta1/PipelineSpecFluentImpl;ILio/dekorate/deps/tekton/pipeline/v1beta1/ParamSpec;)V
      10: areturn

  public io.dekorate.deps.tekton.pipeline.v1beta1.PipelineSpecFluent$ParamsNested<A> editParam(int);
    Code:
       0: aload_0
       1: getfield      #124                // Field params:Ljava/util/List;
       4: invokeinterface #151,  1          // InterfaceMethod java/util/List.size:()I
       9: iload_1
      10: if_icmpgt     24
      13: new           #280                // class java/lang/RuntimeException
      16: dup
      17: ldc_w         #282                // String Can\'t edit params. Index exceeds size.
      20: invokespecial #283                // Method java/lang/RuntimeException."<init>":(Ljava/lang/String;)V
      23: athrow
      24: aload_0
      25: iload_1
      26: aload_0
      27: iload_1
      28: invokevirtual #285                // Method buildParam:(I)Lio/dekorate/deps/tekton/pipeline/v1beta1/ParamSpec;
      31: invokevirtual #287                // Method setNewParamLike:(ILio/dekorate/deps/tekton/pipeline/v1beta1/ParamSpec;)Lio/dekorate/deps/tekton/pipeline/v1beta1/PipelineSpecFluent$ParamsNested;
      34: areturn

  public io.dekorate.deps.tekton.pipeline.v1beta1.PipelineSpecFluent$ParamsNested<A> editFirstParam();
    Code:
       0: aload_0
       1: getfield      #124                // Field params:Ljava/util/List;
       4: invokeinterface #151,  1          // InterfaceMethod java/util/List.size:()I
       9: ifne          23
      12: new           #280                // class java/lang/RuntimeException
      15: dup
      16: ldc_w         #290                // String Can\'t edit first params. The list is empty.
      19: invokespecial #283                // Method java/lang/RuntimeException."<init>":(Ljava/lang/String;)V
      22: athrow
      23: aload_0
      24: iconst_0
      25: aload_0
      26: iconst_0
      27: invokevirtual #285                // Method buildParam:(I)Lio/dekorate/deps/tekton/pipeline/v1beta1/ParamSpec;
      30: invokevirtual #287                // Method setNewParamLike:(ILio/dekorate/deps/tekton/pipeline/v1beta1/ParamSpec;)Lio/dekorate/deps/tekton/pipeline/v1beta1/PipelineSpecFluent$ParamsNested;
      33: areturn

  public io.dekorate.deps.tekton.pipeline.v1beta1.PipelineSpecFluent$ParamsNested<A> editLastParam();
    Code:
       0: aload_0
       1: getfield      #124                // Field params:Ljava/util/List;
       4: invokeinterface #151,  1          // InterfaceMethod java/util/List.size:()I
       9: iconst_1
      10: isub
      11: istore_1
      12: iload_1
      13: ifge          27
      16: new           #280                // class java/lang/RuntimeException
      19: dup
      20: ldc_w         #293                // String Can\'t edit last params. The list is empty.
      23: invokespecial #283                // Method java/lang/RuntimeException."<init>":(Ljava/lang/String;)V
      26: athrow
      27: aload_0
      28: iload_1
      29: aload_0
      30: iload_1
      31: invokevirtual #285                // Method buildParam:(I)Lio/dekorate/deps/tekton/pipeline/v1beta1/ParamSpec;
      34: invokevirtual #287                // Method setNewParamLike:(ILio/dekorate/deps/tekton/pipeline/v1beta1/ParamSpec;)Lio/dekorate/deps/tekton/pipeline/v1beta1/PipelineSpecFluent$ParamsNested;
      37: areturn

  public io.dekorate.deps.tekton.pipeline.v1beta1.PipelineSpecFluent$ParamsNested<A> editMatchingParam(io.dekorate.deps.kubernetes.api.builder.Predicate<io.dekorate.deps.tekton.pipeline.v1beta1.ParamSpecBuilder>);
    Code:
       0: iconst_m1
       1: istore_2
       2: iconst_0
       3: istore_3
       4: iload_3
       5: aload_0
       6: getfield      #124                // Field params:Ljava/util/List;
       9: invokeinterface #151,  1          // InterfaceMethod java/util/List.size:()I
      14: if_icmpge     50
      17: aload_1
      18: aload_0
      19: getfield      #124                // Field params:Ljava/util/List;
      22: iload_3
      23: invokeinterface #234,  2          // InterfaceMethod java/util/List.get:(I)Ljava/lang/Object;
      28: invokeinterface #210,  2          // InterfaceMethod io/dekorate/deps/kubernetes/api/builder/Predicate.apply:(Ljava/lang/Object;)Ljava/lang/Boolean;
      33: invokevirtual #213                // Method java/lang/Boolean.booleanValue:()Z
      36: ifeq          44
      39: iload_3
      40: istore_2
      41: goto          50
      44: iinc          3, 1
      47: goto          4
      50: iload_2
      51: ifge          65
      54: new           #280                // class java/lang/RuntimeException
      57: dup
      58: ldc_w         #298                // String Can\'t edit matching params. No match found.
      61: invokespecial #283                // Method java/lang/RuntimeException."<init>":(Ljava/lang/String;)V
      64: athrow
      65: aload_0
      66: iload_2
      67: aload_0
      68: iload_2
      69: invokevirtual #285                // Method buildParam:(I)Lio/dekorate/deps/tekton/pipeline/v1beta1/ParamSpec;
      72: invokevirtual #287                // Method setNewParamLike:(ILio/dekorate/deps/tekton/pipeline/v1beta1/ParamSpec;)Lio/dekorate/deps/tekton/pipeline/v1beta1/PipelineSpecFluent$ParamsNested;
      75: areturn

  public A addToResources(int, io.dekorate.deps.tekton.pipeline.v1beta1.PipelineDeclaredResource);
    Code:
       0: aload_0
       1: getfield      #304                // Field resources:Ljava/util/List;
       4: ifnonnull     18
       7: aload_0
       8: new           #126                // class java/util/ArrayList
      11: dup
      12: invokespecial #127                // Method java/util/ArrayList."<init>":()V
      15: putfield      #304                // Field resources:Ljava/util/List;
      18: new           #306                // class io/dekorate/deps/tekton/pipeline/v1beta1/PipelineDeclaredResourceBuilder
      21: dup
      22: aload_2
      23: invokespecial #309                // Method io/dekorate/deps/tekton/pipeline/v1beta1/PipelineDeclaredResourceBuilder."<init>":(Lio/dekorate/deps/tekton/pipeline/v1beta1/PipelineDeclaredResource;)V
      26: astore_3
      27: aload_0
      28: getfield      #136                // Field _visitables:Lio/dekorate/deps/kubernetes/api/builder/VisitableMap;
      31: ldc_w         #310                // String resources
      34: invokevirtual #143                // Method io/dekorate/deps/kubernetes/api/builder/VisitableMap.get:(Ljava/lang/Object;)Ljava/util/List;
      37: iload_1
      38: iflt          45
      41: iload_1
      42: goto          60
      45: aload_0
      46: getfield      #136                // Field _visitables:Lio/dekorate/deps/kubernetes/api/builder/VisitableMap;
      49: ldc_w         #310                // String resources
      52: invokevirtual #143                // Method io/dekorate/deps/kubernetes/api/builder/VisitableMap.get:(Ljava/lang/Object;)Ljava/util/List;
      55: invokeinterface #151,  1          // InterfaceMethod java/util/List.size:()I
      60: aload_3
      61: invokeinterface #155,  3          // InterfaceMethod java/util/List.add:(ILjava/lang/Object;)V
      66: aload_0
      67: getfield      #304                // Field resources:Ljava/util/List;
      70: iload_1
      71: iflt          78
      74: iload_1
      75: goto          87
      78: aload_0
      79: getfield      #304                // Field resources:Ljava/util/List;
      82: invokeinterface #151,  1          // InterfaceMethod java/util/List.size:()I
      87: aload_3
      88: invokeinterface #155,  3          // InterfaceMethod java/util/List.add:(ILjava/lang/Object;)V
      93: aload_0
      94: areturn

  public A setToResources(int, io.dekorate.deps.tekton.pipeline.v1beta1.PipelineDeclaredResource);
    Code:
       0: aload_0
       1: getfield      #304                // Field resources:Ljava/util/List;
       4: ifnonnull     18
       7: aload_0
       8: new           #126                // class java/util/ArrayList
      11: dup
      12: invokespecial #127                // Method java/util/ArrayList."<init>":()V
      15: putfield      #304                // Field resources:Ljava/util/List;
      18: new           #306                // class io/dekorate/deps/tekton/pipeline/v1beta1/PipelineDeclaredResourceBuilder
      21: dup
      22: aload_2
      23: invokespecial #309                // Method io/dekorate/deps/tekton/pipeline/v1beta1/PipelineDeclaredResourceBuilder."<init>":(Lio/dekorate/deps/tekton/pipeline/v1beta1/PipelineDeclaredResource;)V
      26: astore_3
      27: iload_1
      28: iflt          50
      31: iload_1
      32: aload_0
      33: getfield      #136                // Field _visitables:Lio/dekorate/deps/kubernetes/api/builder/VisitableMap;
      36: ldc_w         #310                // String resources
      39: invokevirtual #143                // Method io/dekorate/deps/kubernetes/api/builder/VisitableMap.get:(Ljava/lang/Object;)Ljava/util/List;
      42: invokeinterface #151,  1          // InterfaceMethod java/util/List.size:()I
      47: if_icmplt     70
      50: aload_0
      51: getfield      #136                // Field _visitables:Lio/dekorate/deps/kubernetes/api/builder/VisitableMap;
      54: ldc_w         #310                // String resources
      57: invokevirtual #143                // Method io/dekorate/deps/kubernetes/api/builder/VisitableMap.get:(Ljava/lang/Object;)Ljava/util/List;
      60: aload_3
      61: invokeinterface #165,  2          // InterfaceMethod java/util/List.add:(Ljava/lang/Object;)Z
      66: pop
      67: goto          88
      70: aload_0
      71: getfield      #136                // Field _visitables:Lio/dekorate/deps/kubernetes/api/builder/VisitableMap;
      74: ldc_w         #310                // String resources
      77: invokevirtual #143                // Method io/dekorate/deps/kubernetes/api/builder/VisitableMap.get:(Ljava/lang/Object;)Ljava/util/List;
      80: iload_1
      81: aload_3
      82: invokeinterface #169,  3          // InterfaceMethod java/util/List.set:(ILjava/lang/Object;)Ljava/lang/Object;
      87: pop
      88: iload_1
      89: iflt          105
      92: iload_1
      93: aload_0
      94: getfield      #304                // Field resources:Ljava/util/List;
      97: invokeinterface #151,  1          // InterfaceMethod java/util/List.size:()I
     102: if_icmplt     119
     105: aload_0
     106: getfield      #304                // Field resources:Ljava/util/List;
     109: aload_3
     110: invokeinterface #165,  2          // InterfaceMethod java/util/List.add:(Ljava/lang/Object;)Z
     115: pop
     116: goto          131
     119: aload_0
     120: getfield      #304                // Field resources:Ljava/util/List;
     123: iload_1
     124: aload_3
     125: invokeinterface #169,  3          // InterfaceMethod java/util/List.set:(ILjava/lang/Object;)Ljava/lang/Object;
     130: pop
     131: aload_0
     132: areturn

  public A addToResources(io.dekorate.deps.tekton.pipeline.v1beta1.PipelineDeclaredResource...);
    Code:
       0: aload_0
       1: getfield      #304                // Field resources:Ljava/util/List;
       4: ifnonnull     18
       7: aload_0
       8: new           #126                // class java/util/ArrayList
      11: dup
      12: invokespecial #127                // Method java/util/ArrayList."<init>":()V
      15: putfield      #304                // Field resources:Ljava/util/List;
      18: aload_1
      19: astore_2
      20: aload_2
      21: arraylength
      22: istore_3
      23: iconst_0
      24: istore        4
      26: iload         4
      28: iload_3
      29: if_icmpge     85
      32: aload_2
      33: iload         4
      35: aaload
      36: astore        5
      38: new           #306                // class io/dekorate/deps/tekton/pipeline/v1beta1/PipelineDeclaredResourceBuilder
      41: dup
      42: aload         5
      44: invokespecial #309                // Method io/dekorate/deps/tekton/pipeline/v1beta1/PipelineDeclaredResourceBuilder."<init>":(Lio/dekorate/deps/tekton/pipeline/v1beta1/PipelineDeclaredResource;)V
      47: astore        6
      49: aload_0
      50: getfield      #136                // Field _visitables:Lio/dekorate/deps/kubernetes/api/builder/VisitableMap;
      53: ldc_w         #310                // String resources
      56: invokevirtual #143                // Method io/dekorate/deps/kubernetes/api/builder/VisitableMap.get:(Ljava/lang/Object;)Ljava/util/List;
      59: aload         6
      61: invokeinterface #165,  2          // InterfaceMethod java/util/List.add:(Ljava/lang/Object;)Z
      66: pop
      67: aload_0
      68: getfield      #304                // Field resources:Ljava/util/List;
      71: aload         6
      73: invokeinterface #165,  2          // InterfaceMethod java/util/List.add:(Ljava/lang/Object;)Z
      78: pop
      79: iinc          4, 1
      82: goto          26
      85: aload_0
      86: areturn

  public A addAllToResources(java.util.Collection<io.dekorate.deps.tekton.pipeline.v1beta1.PipelineDeclaredResource>);
    Code:
       0: aload_0
       1: getfield      #304                // Field resources:Ljava/util/List;
       4: ifnonnull     18
       7: aload_0
       8: new           #126                // class java/util/ArrayList
      11: dup
      12: invokespecial #127                // Method java/util/ArrayList."<init>":()V
      15: putfield      #304                // Field resources:Ljava/util/List;
      18: aload_1
      19: invokeinterface #183,  1          // InterfaceMethod java/util/Collection.iterator:()Ljava/util/Iterator;
      24: astore_2
      25: aload_2
      26: invokeinterface #189,  1          // InterfaceMethod java/util/Iterator.hasNext:()Z
      31: ifeq          87
      34: aload_2
      35: invokeinterface #193,  1          // InterfaceMethod java/util/Iterator.next:()Ljava/lang/Object;
      40: checkcast     #312                // class io/dekorate/deps/tekton/pipeline/v1beta1/PipelineDeclaredResource
      43: astore_3
      44: new           #306                // class io/dekorate/deps/tekton/pipeline/v1beta1/PipelineDeclaredResourceBuilder
      47: dup
      48: aload_3
      49: invokespecial #309                // Method io/dekorate/deps/tekton/pipeline/v1beta1/PipelineDeclaredResourceBuilder."<init>":(Lio/dekorate/deps/tekton/pipeline/v1beta1/PipelineDeclaredResource;)V
      52: astore        4
      54: aload_0
      55: getfield      #136                // Field _visitables:Lio/dekorate/deps/kubernetes/api/builder/VisitableMap;
      58: ldc_w         #310                // String resources
      61: invokevirtual #143                // Method io/dekorate/deps/kubernetes/api/builder/VisitableMap.get:(Ljava/lang/Object;)Ljava/util/List;
      64: aload         4
      66: invokeinterface #165,  2          // InterfaceMethod java/util/List.add:(Ljava/lang/Object;)Z
      71: pop
      72: aload_0
      73: getfield      #304                // Field resources:Ljava/util/List;
      76: aload         4
      78: invokeinterface #165,  2          // InterfaceMethod java/util/List.add:(Ljava/lang/Object;)Z
      83: pop
      84: goto          25
      87: aload_0
      88: areturn

  public A removeFromResources(io.dekorate.deps.tekton.pipeline.v1beta1.PipelineDeclaredResource...);
    Code:
       0: aload_1
       1: astore_2
       2: aload_2
       3: arraylength
       4: istore_3
       5: iconst_0
       6: istore        4
       8: iload         4
      10: iload_3
      11: if_icmpge     74
      14: aload_2
      15: iload         4
      17: aaload
      18: astore        5
      20: new           #306                // class io/dekorate/deps/tekton/pipeline/v1beta1/PipelineDeclaredResourceBuilder
      23: dup
      24: aload         5
      26: invokespecial #309                // Method io/dekorate/deps/tekton/pipeline/v1beta1/PipelineDeclaredResourceBuilder."<init>":(Lio/dekorate/deps/tekton/pipeline/v1beta1/PipelineDeclaredResource;)V
      29: astore        6
      31: aload_0
      32: getfield      #136                // Field _visitables:Lio/dekorate/deps/kubernetes/api/builder/VisitableMap;
      35: ldc_w         #310                // String resources
      38: invokevirtual #143                // Method io/dekorate/deps/kubernetes/api/builder/VisitableMap.get:(Ljava/lang/Object;)Ljava/util/List;
      41: aload         6
      43: invokeinterface #199,  2          // InterfaceMethod java/util/List.remove:(Ljava/lang/Object;)Z
      48: pop
      49: aload_0
      50: getfield      #304                // Field resources:Ljava/util/List;
      53: ifnull        68
      56: aload_0
      57: getfield      #304                // Field resources:Ljava/util/List;
      60: aload         6
      62: invokeinterface #199,  2          // InterfaceMethod java/util/List.remove:(Ljava/lang/Object;)Z
      67: pop
      68: iinc          4, 1
      71: goto          8
      74: aload_0
      75: areturn

  public A removeAllFromResources(java.util.Collection<io.dekorate.deps.tekton.pipeline.v1beta1.PipelineDeclaredResource>);
    Code:
       0: aload_1
       1: invokeinterface #183,  1          // InterfaceMethod java/util/Collection.iterator:()Ljava/util/Iterator;
       6: astore_2
       7: aload_2
       8: invokeinterface #189,  1          // InterfaceMethod java/util/Iterator.hasNext:()Z
      13: ifeq          76
      16: aload_2
      17: invokeinterface #193,  1          // InterfaceMethod java/util/Iterator.next:()Ljava/lang/Object;
      22: checkcast     #312                // class io/dekorate/deps/tekton/pipeline/v1beta1/PipelineDeclaredResource
      25: astore_3
      26: new           #306                // class io/dekorate/deps/tekton/pipeline/v1beta1/PipelineDeclaredResourceBuilder
      29: dup
      30: aload_3
      31: invokespecial #309                // Method io/dekorate/deps/tekton/pipeline/v1beta1/PipelineDeclaredResourceBuilder."<init>":(Lio/dekorate/deps/tekton/pipeline/v1beta1/PipelineDeclaredResource;)V
      34: astore        4
      36: aload_0
      37: getfield      #136                // Field _visitables:Lio/dekorate/deps/kubernetes/api/builder/VisitableMap;
      40: ldc_w         #310                // String resources
      43: invokevirtual #143                // Method io/dekorate/deps/kubernetes/api/builder/VisitableMap.get:(Ljava/lang/Object;)Ljava/util/List;
      46: aload         4
      48: invokeinterface #199,  2          // InterfaceMethod java/util/List.remove:(Ljava/lang/Object;)Z
      53: pop
      54: aload_0
      55: getfield      #304                // Field resources:Ljava/util/List;
      58: ifnull        73
      61: aload_0
      62: getfield      #304                // Field resources:Ljava/util/List;
      65: aload         4
      67: invokeinterface #199,  2          // InterfaceMethod java/util/List.remove:(Ljava/lang/Object;)Z
      72: pop
      73: goto          7
      76: aload_0
      77: areturn

  public A removeMatchingFromResources(io.dekorate.deps.kubernetes.api.builder.Predicate<io.dekorate.deps.tekton.pipeline.v1beta1.PipelineDeclaredResourceBuilder>);
    Code:
       0: aload_0
       1: getfield      #304                // Field resources:Ljava/util/List;
       4: ifnonnull     9
       7: aload_0
       8: areturn
       9: aload_0
      10: getfield      #304                // Field resources:Ljava/util/List;
      13: invokeinterface #204,  1          // InterfaceMethod java/util/List.iterator:()Ljava/util/Iterator;
      18: astore_2
      19: aload_0
      20: getfield      #136                // Field _visitables:Lio/dekorate/deps/kubernetes/api/builder/VisitableMap;
      23: ldc_w         #310                // String resources
      26: invokevirtual #143                // Method io/dekorate/deps/kubernetes/api/builder/VisitableMap.get:(Ljava/lang/Object;)Ljava/util/List;
      29: astore_3
      30: aload_2
      31: invokeinterface #189,  1          // InterfaceMethod java/util/Iterator.hasNext:()Z
      36: ifeq          82
      39: aload_2
      40: invokeinterface #193,  1          // InterfaceMethod java/util/Iterator.next:()Ljava/lang/Object;
      45: checkcast     #306                // class io/dekorate/deps/tekton/pipeline/v1beta1/PipelineDeclaredResourceBuilder
      48: astore        4
      50: aload_1
      51: aload         4
      53: invokeinterface #210,  2          // InterfaceMethod io/dekorate/deps/kubernetes/api/builder/Predicate.apply:(Ljava/lang/Object;)Ljava/lang/Boolean;
      58: invokevirtual #213                // Method java/lang/Boolean.booleanValue:()Z
      61: ifeq          79
      64: aload_3
      65: aload         4
      67: invokeinterface #199,  2          // InterfaceMethod java/util/List.remove:(Ljava/lang/Object;)Z
      72: pop
      73: aload_2
      74: invokeinterface #215,  1          // InterfaceMethod java/util/Iterator.remove:()V
      79: goto          30
      82: aload_0
      83: areturn

  public java.util.List<io.dekorate.deps.tekton.pipeline.v1beta1.PipelineDeclaredResource> getResources();
    Code:
       0: aload_0
       1: getfield      #304                // Field resources:Ljava/util/List;
       4: invokestatic  #228                // Method build:(Ljava/util/List;)Ljava/util/ArrayList;
       7: areturn

  public java.util.List<io.dekorate.deps.tekton.pipeline.v1beta1.PipelineDeclaredResource> buildResources();
    Code:
       0: aload_0
       1: getfield      #304                // Field resources:Ljava/util/List;
       4: invokestatic  #228                // Method build:(Ljava/util/List;)Ljava/util/ArrayList;
       7: areturn

  public io.dekorate.deps.tekton.pipeline.v1beta1.PipelineDeclaredResource buildResource(int);
    Code:
       0: aload_0
       1: getfield      #304                // Field resources:Ljava/util/List;
       4: iload_1
       5: invokeinterface #234,  2          // InterfaceMethod java/util/List.get:(I)Ljava/lang/Object;
      10: checkcast     #306                // class io/dekorate/deps/tekton/pipeline/v1beta1/PipelineDeclaredResourceBuilder
      13: invokevirtual #335                // Method io/dekorate/deps/tekton/pipeline/v1beta1/PipelineDeclaredResourceBuilder.build:()Lio/dekorate/deps/tekton/pipeline/v1beta1/PipelineDeclaredResource;
      16: areturn

  public io.dekorate.deps.tekton.pipeline.v1beta1.PipelineDeclaredResource buildFirstResource();
    Code:
       0: aload_0
       1: getfield      #304                // Field resources:Ljava/util/List;
       4: iconst_0
       5: invokeinterface #234,  2          // InterfaceMethod java/util/List.get:(I)Ljava/lang/Object;
      10: checkcast     #306                // class io/dekorate/deps/tekton/pipeline/v1beta1/PipelineDeclaredResourceBuilder
      13: invokevirtual #335                // Method io/dekorate/deps/tekton/pipeline/v1beta1/PipelineDeclaredResourceBuilder.build:()Lio/dekorate/deps/tekton/pipeline/v1beta1/PipelineDeclaredResource;
      16: areturn

  public io.dekorate.deps.tekton.pipeline.v1beta1.PipelineDeclaredResource buildLastResource();
    Code:
       0: aload_0
       1: getfield      #304                // Field resources:Ljava/util/List;
       4: aload_0
       5: getfield      #304                // Field resources:Ljava/util/List;
       8: invokeinterface #151,  1          // InterfaceMethod java/util/List.size:()I
      13: iconst_1
      14: isub
      15: invokeinterface #234,  2          // InterfaceMethod java/util/List.get:(I)Ljava/lang/Object;
      20: checkcast     #306                // class io/dekorate/deps/tekton/pipeline/v1beta1/PipelineDeclaredResourceBuilder
      23: invokevirtual #335                // Method io/dekorate/deps/tekton/pipeline/v1beta1/PipelineDeclaredResourceBuilder.build:()Lio/dekorate/deps/tekton/pipeline/v1beta1/PipelineDeclaredResource;
      26: areturn

  public io.dekorate.deps.tekton.pipeline.v1beta1.PipelineDeclaredResource buildMatchingResource(io.dekorate.deps.kubernetes.api.builder.Predicate<io.dekorate.deps.tekton.pipeline.v1beta1.PipelineDeclaredResourceBuilder>);
    Code:
       0: aload_0
       1: getfield      #304                // Field resources:Ljava/util/List;
       4: invokeinterface #204,  1          // InterfaceMethod java/util/List.iterator:()Ljava/util/Iterator;
       9: astore_2
      10: aload_2
      11: invokeinterface #189,  1          // InterfaceMethod java/util/Iterator.hasNext:()Z
      16: ifeq          50
      19: aload_2
      20: invokeinterface #193,  1          // InterfaceMethod java/util/Iterator.next:()Ljava/lang/Object;
      25: checkcast     #306                // class io/dekorate/deps/tekton/pipeline/v1beta1/PipelineDeclaredResourceBuilder
      28: astore_3
      29: aload_1
      30: aload_3
      31: invokeinterface #210,  2          // InterfaceMethod io/dekorate/deps/kubernetes/api/builder/Predicate.apply:(Ljava/lang/Object;)Ljava/lang/Boolean;
      36: invokevirtual #213                // Method java/lang/Boolean.booleanValue:()Z
      39: ifeq          47
      42: aload_3
      43: invokevirtual #335                // Method io/dekorate/deps/tekton/pipeline/v1beta1/PipelineDeclaredResourceBuilder.build:()Lio/dekorate/deps/tekton/pipeline/v1beta1/PipelineDeclaredResource;
      46: areturn
      47: goto          10
      50: aconst_null
      51: areturn

  public java.lang.Boolean hasMatchingResource(io.dekorate.deps.kubernetes.api.builder.Predicate<io.dekorate.deps.tekton.pipeline.v1beta1.PipelineDeclaredResourceBuilder>);
    Code:
       0: aload_0
       1: getfield      #304                // Field resources:Ljava/util/List;
       4: invokeinterface #204,  1          // InterfaceMethod java/util/List.iterator:()Ljava/util/Iterator;
       9: astore_2
      10: aload_2
      11: invokeinterface #189,  1          // InterfaceMethod java/util/Iterator.hasNext:()Z
      16: ifeq          50
      19: aload_2
      20: invokeinterface #193,  1          // InterfaceMethod java/util/Iterator.next:()Ljava/lang/Object;
      25: checkcast     #306                // class io/dekorate/deps/tekton/pipeline/v1beta1/PipelineDeclaredResourceBuilder
      28: astore_3
      29: aload_1
      30: aload_3
      31: invokeinterface #210,  2          // InterfaceMethod io/dekorate/deps/kubernetes/api/builder/Predicate.apply:(Ljava/lang/Object;)Ljava/lang/Boolean;
      36: invokevirtual #213                // Method java/lang/Boolean.booleanValue:()Z
      39: ifeq          47
      42: iconst_1
      43: invokestatic  #100                // Method java/lang/Boolean.valueOf:(Z)Ljava/lang/Boolean;
      46: areturn
      47: goto          10
      50: iconst_0
      51: invokestatic  #100                // Method java/lang/Boolean.valueOf:(Z)Ljava/lang/Boolean;
      54: areturn

  public A withResources(java.util.List<io.dekorate.deps.tekton.pipeline.v1beta1.PipelineDeclaredResource>);
    Code:
       0: aload_0
       1: getfield      #304                // Field resources:Ljava/util/List;
       4: ifnull        27
       7: aload_0
       8: getfield      #136                // Field _visitables:Lio/dekorate/deps/kubernetes/api/builder/VisitableMap;
      11: ldc_w         #310                // String resources
      14: invokevirtual #143                // Method io/dekorate/deps/kubernetes/api/builder/VisitableMap.get:(Ljava/lang/Object;)Ljava/util/List;
      17: aload_0
      18: getfield      #304                // Field resources:Ljava/util/List;
      21: invokeinterface #250,  2          // InterfaceMethod java/util/List.removeAll:(Ljava/util/Collection;)Z
      26: pop
      27: aload_1
      28: ifnull        87
      31: aload_0
      32: new           #126                // class java/util/ArrayList
      35: dup
      36: invokespecial #127                // Method java/util/ArrayList."<init>":()V
      39: putfield      #304                // Field resources:Ljava/util/List;
      42: aload_1
      43: invokeinterface #204,  1          // InterfaceMethod java/util/List.iterator:()Ljava/util/Iterator;
      48: astore_2
      49: aload_2
      50: invokeinterface #189,  1          // InterfaceMethod java/util/Iterator.hasNext:()Z
      55: ifeq          84
      58: aload_2
      59: invokeinterface #193,  1          // InterfaceMethod java/util/Iterator.next:()Ljava/lang/Object;
      64: checkcast     #312                // class io/dekorate/deps/tekton/pipeline/v1beta1/PipelineDeclaredResource
      67: astore_3
      68: aload_0
      69: iconst_1
      70: anewarray     #312                // class io/dekorate/deps/tekton/pipeline/v1beta1/PipelineDeclaredResource
      73: dup
      74: iconst_0
      75: aload_3
      76: aastore
      77: invokevirtual #345                // Method addToResources:([Lio/dekorate/deps/tekton/pipeline/v1beta1/PipelineDeclaredResource;)Lio/dekorate/deps/tekton/pipeline/v1beta1/PipelineSpecFluent;
      80: pop
      81: goto          49
      84: goto          92
      87: aload_0
      88: aconst_null
      89: putfield      #304                // Field resources:Ljava/util/List;
      92: aload_0
      93: areturn

  public A withResources(io.dekorate.deps.tekton.pipeline.v1beta1.PipelineDeclaredResource...);
    Code:
       0: aload_0
       1: getfield      #304                // Field resources:Ljava/util/List;
       4: ifnull        16
       7: aload_0
       8: getfield      #304                // Field resources:Ljava/util/List;
      11: invokeinterface #256,  1          // InterfaceMethod java/util/List.clear:()V
      16: aload_1
      17: ifnull        60
      20: aload_1
      21: astore_2
      22: aload_2
      23: arraylength
      24: istore_3
      25: iconst_0
      26: istore        4
      28: iload         4
      30: iload_3
      31: if_icmpge     60
      34: aload_2
      35: iload         4
      37: aaload
      38: astore        5
      40: aload_0
      41: iconst_1
      42: anewarray     #312                // class io/dekorate/deps/tekton/pipeline/v1beta1/PipelineDeclaredResource
      45: dup
      46: iconst_0
      47: aload         5
      49: aastore
      50: invokevirtual #345                // Method addToResources:([Lio/dekorate/deps/tekton/pipeline/v1beta1/PipelineDeclaredResource;)Lio/dekorate/deps/tekton/pipeline/v1beta1/PipelineSpecFluent;
      53: pop
      54: iinc          4, 1
      57: goto          28
      60: aload_0
      61: areturn

  public java.lang.Boolean hasResources();
    Code:
       0: aload_0
       1: getfield      #304                // Field resources:Ljava/util/List;
       4: ifnull        23
       7: aload_0
       8: getfield      #304                // Field resources:Ljava/util/List;
      11: invokeinterface #260,  1          // InterfaceMethod java/util/List.isEmpty:()Z
      16: ifne          23
      19: iconst_1
      20: goto          24
      23: iconst_0
      24: invokestatic  #100                // Method java/lang/Boolean.valueOf:(Z)Ljava/lang/Boolean;
      27: areturn

  public A addNewResource(java.lang.String, java.lang.Boolean, java.lang.String);
    Code:
       0: aload_0
       1: iconst_1
       2: anewarray     #312                // class io/dekorate/deps/tekton/pipeline/v1beta1/PipelineDeclaredResource
       5: dup
       6: iconst_0
       7: new           #312                // class io/dekorate/deps/tekton/pipeline/v1beta1/PipelineDeclaredResource
      10: dup
      11: aload_1
      12: aload_2
      13: aload_3
      14: invokespecial #353                // Method io/dekorate/deps/tekton/pipeline/v1beta1/PipelineDeclaredResource."<init>":(Ljava/lang/String;Ljava/lang/Boolean;Ljava/lang/String;)V
      17: aastore
      18: invokevirtual #345                // Method addToResources:([Lio/dekorate/deps/tekton/pipeline/v1beta1/PipelineDeclaredResource;)Lio/dekorate/deps/tekton/pipeline/v1beta1/PipelineSpecFluent;
      21: areturn

  public io.dekorate.deps.tekton.pipeline.v1beta1.PipelineSpecFluent$ResourcesNested<A> addNewResource();
    Code:
       0: new           #16                 // class io/dekorate/deps/tekton/pipeline/v1beta1/PipelineSpecFluentImpl$ResourcesNestedImpl
       3: dup
       4: aload_0
       5: invokespecial #360                // Method io/dekorate/deps/tekton/pipeline/v1beta1/PipelineSpecFluentImpl$ResourcesNestedImpl."<init>":(Lio/dekorate/deps/tekton/pipeline/v1beta1/PipelineSpecFluentImpl;)V
       8: areturn

  public io.dekorate.deps.tekton.pipeline.v1beta1.PipelineSpecFluent$ResourcesNested<A> addNewResourceLike(io.dekorate.deps.tekton.pipeline.v1beta1.PipelineDeclaredResource);
    Code:
       0: new           #16                 // class io/dekorate/deps/tekton/pipeline/v1beta1/PipelineSpecFluentImpl$ResourcesNestedImpl
       3: dup
       4: aload_0
       5: iconst_m1
       6: aload_1
       7: invokespecial #366                // Method io/dekorate/deps/tekton/pipeline/v1beta1/PipelineSpecFluentImpl$ResourcesNestedImpl."<init>":(Lio/dekorate/deps/tekton/pipeline/v1beta1/PipelineSpecFluentImpl;ILio/dekorate/deps/tekton/pipeline/v1beta1/PipelineDeclaredResource;)V
      10: areturn

  public io.dekorate.deps.tekton.pipeline.v1beta1.PipelineSpecFluent$ResourcesNested<A> setNewResourceLike(int, io.dekorate.deps.tekton.pipeline.v1beta1.PipelineDeclaredResource);
    Code:
       0: new           #16                 // class io/dekorate/deps/tekton/pipeline/v1beta1/PipelineSpecFluentImpl$ResourcesNestedImpl
       3: dup
       4: aload_0
       5: iload_1
       6: aload_2
       7: invokespecial #366                // Method io/dekorate/deps/tekton/pipeline/v1beta1/PipelineSpecFluentImpl$ResourcesNestedImpl."<init>":(Lio/dekorate/deps/tekton/pipeline/v1beta1/PipelineSpecFluentImpl;ILio/dekorate/deps/tekton/pipeline/v1beta1/PipelineDeclaredResource;)V
      10: areturn

  public io.dekorate.deps.tekton.pipeline.v1beta1.PipelineSpecFluent$ResourcesNested<A> editResource(int);
    Code:
       0: aload_0
       1: getfield      #304                // Field resources:Ljava/util/List;
       4: invokeinterface #151,  1          // InterfaceMethod java/util/List.size:()I
       9: iload_1
      10: if_icmpgt     24
      13: new           #280                // class java/lang/RuntimeException
      16: dup
      17: ldc_w         #374                // String Can\'t edit resources. Index exceeds size.
      20: invokespecial #283                // Method java/lang/RuntimeException."<init>":(Ljava/lang/String;)V
      23: athrow
      24: aload_0
      25: iload_1
      26: aload_0
      27: iload_1
      28: invokevirtual #376                // Method buildResource:(I)Lio/dekorate/deps/tekton/pipeline/v1beta1/PipelineDeclaredResource;
      31: invokevirtual #378                // Method setNewResourceLike:(ILio/dekorate/deps/tekton/pipeline/v1beta1/PipelineDeclaredResource;)Lio/dekorate/deps/tekton/pipeline/v1beta1/PipelineSpecFluent$ResourcesNested;
      34: areturn

  public io.dekorate.deps.tekton.pipeline.v1beta1.PipelineSpecFluent$ResourcesNested<A> editFirstResource();
    Code:
       0: aload_0
       1: getfield      #304                // Field resources:Ljava/util/List;
       4: invokeinterface #151,  1          // InterfaceMethod java/util/List.size:()I
       9: ifne          23
      12: new           #280                // class java/lang/RuntimeException
      15: dup
      16: ldc_w         #381                // String Can\'t edit first resources. The list is empty.
      19: invokespecial #283                // Method java/lang/RuntimeException."<init>":(Ljava/lang/String;)V
      22: athrow
      23: aload_0
      24: iconst_0
      25: aload_0
      26: iconst_0
      27: invokevirtual #376                // Method buildResource:(I)Lio/dekorate/deps/tekton/pipeline/v1beta1/PipelineDeclaredResource;
      30: invokevirtual #378                // Method setNewResourceLike:(ILio/dekorate/deps/tekton/pipeline/v1beta1/PipelineDeclaredResource;)Lio/dekorate/deps/tekton/pipeline/v1beta1/PipelineSpecFluent$ResourcesNested;
      33: areturn

  public io.dekorate.deps.tekton.pipeline.v1beta1.PipelineSpecFluent$ResourcesNested<A> editLastResource();
    Code:
       0: aload_0
       1: getfield      #304                // Field resources:Ljava/util/List;
       4: invokeinterface #151,  1          // InterfaceMethod java/util/List.size:()I
       9: iconst_1
      10: isub
      11: istore_1
      12: iload_1
      13: ifge          27
      16: new           #280                // class java/lang/RuntimeException
      19: dup
      20: ldc_w         #384                // String Can\'t edit last resources. The list is empty.
      23: invokespecial #283                // Method java/lang/RuntimeException."<init>":(Ljava/lang/String;)V
      26: athrow
      27: aload_0
      28: iload_1
      29: aload_0
      30: iload_1
      31: invokevirtual #376                // Method buildResource:(I)Lio/dekorate/deps/tekton/pipeline/v1beta1/PipelineDeclaredResource;
      34: invokevirtual #378                // Method setNewResourceLike:(ILio/dekorate/deps/tekton/pipeline/v1beta1/PipelineDeclaredResource;)Lio/dekorate/deps/tekton/pipeline/v1beta1/PipelineSpecFluent$ResourcesNested;
      37: areturn

  public io.dekorate.deps.tekton.pipeline.v1beta1.PipelineSpecFluent$ResourcesNested<A> editMatchingResource(io.dekorate.deps.kubernetes.api.builder.Predicate<io.dekorate.deps.tekton.pipeline.v1beta1.PipelineDeclaredResourceBuilder>);
    Code:
       0: iconst_m1
       1: istore_2
       2: iconst_0
       3: istore_3
       4: iload_3
       5: aload_0
       6: getfield      #304                // Field resources:Ljava/util/List;
       9: invokeinterface #151,  1          // InterfaceMethod java/util/List.size:()I
      14: if_icmpge     50
      17: aload_1
      18: aload_0
      19: getfield      #304                // Field resources:Ljava/util/List;
      22: iload_3
      23: invokeinterface #234,  2          // InterfaceMethod java/util/List.get:(I)Ljava/lang/Object;
      28: invokeinterface #210,  2          // InterfaceMethod io/dekorate/deps/kubernetes/api/builder/Predicate.apply:(Ljava/lang/Object;)Ljava/lang/Boolean;
      33: invokevirtual #213                // Method java/lang/Boolean.booleanValue:()Z
      36: ifeq          44
      39: iload_3
      40: istore_2
      41: goto          50
      44: iinc          3, 1
      47: goto          4
      50: iload_2
      51: ifge          65
      54: new           #280                // class java/lang/RuntimeException
      57: dup
      58: ldc_w         #389                // String Can\'t edit matching resources. No match found.
      61: invokespecial #283                // Method java/lang/RuntimeException."<init>":(Ljava/lang/String;)V
      64: athrow
      65: aload_0
      66: iload_2
      67: aload_0
      68: iload_2
      69: invokevirtual #376                // Method buildResource:(I)Lio/dekorate/deps/tekton/pipeline/v1beta1/PipelineDeclaredResource;
      72: invokevirtual #378                // Method setNewResourceLike:(ILio/dekorate/deps/tekton/pipeline/v1beta1/PipelineDeclaredResource;)Lio/dekorate/deps/tekton/pipeline/v1beta1/PipelineSpecFluent$ResourcesNested;
      75: areturn

  public A addToTasks(int, io.dekorate.deps.tekton.pipeline.v1beta1.PipelineTask);
    Code:
       0: aload_0
       1: getfield      #394                // Field tasks:Ljava/util/List;
       4: ifnonnull     18
       7: aload_0
       8: new           #126                // class java/util/ArrayList
      11: dup
      12: invokespecial #127                // Method java/util/ArrayList."<init>":()V
      15: putfield      #394                // Field tasks:Ljava/util/List;
      18: new           #396                // class io/dekorate/deps/tekton/pipeline/v1beta1/PipelineTaskBuilder
      21: dup
      22: aload_2
      23: invokespecial #399                // Method io/dekorate/deps/tekton/pipeline/v1beta1/PipelineTaskBuilder."<init>":(Lio/dekorate/deps/tekton/pipeline/v1beta1/PipelineTask;)V
      26: astore_3
      27: aload_0
      28: getfield      #136                // Field _visitables:Lio/dekorate/deps/kubernetes/api/builder/VisitableMap;
      31: ldc_w         #400                // String tasks
      34: invokevirtual #143                // Method io/dekorate/deps/kubernetes/api/builder/VisitableMap.get:(Ljava/lang/Object;)Ljava/util/List;
      37: iload_1
      38: iflt          45
      41: iload_1
      42: goto          60
      45: aload_0
      46: getfield      #136                // Field _visitables:Lio/dekorate/deps/kubernetes/api/builder/VisitableMap;
      49: ldc_w         #400                // String tasks
      52: invokevirtual #143                // Method io/dekorate/deps/kubernetes/api/builder/VisitableMap.get:(Ljava/lang/Object;)Ljava/util/List;
      55: invokeinterface #151,  1          // InterfaceMethod java/util/List.size:()I
      60: aload_3
      61: invokeinterface #155,  3          // InterfaceMethod java/util/List.add:(ILjava/lang/Object;)V
      66: aload_0
      67: getfield      #394                // Field tasks:Ljava/util/List;
      70: iload_1
      71: iflt          78
      74: iload_1
      75: goto          87
      78: aload_0
      79: getfield      #394                // Field tasks:Ljava/util/List;
      82: invokeinterface #151,  1          // InterfaceMethod java/util/List.size:()I
      87: aload_3
      88: invokeinterface #155,  3          // InterfaceMethod java/util/List.add:(ILjava/lang/Object;)V
      93: aload_0
      94: areturn

  public A setToTasks(int, io.dekorate.deps.tekton.pipeline.v1beta1.PipelineTask);
    Code:
       0: aload_0
       1: getfield      #394                // Field tasks:Ljava/util/List;
       4: ifnonnull     18
       7: aload_0
       8: new           #126                // class java/util/ArrayList
      11: dup
      12: invokespecial #127                // Method java/util/ArrayList."<init>":()V
      15: putfield      #394                // Field tasks:Ljava/util/List;
      18: new           #396                // class io/dekorate/deps/tekton/pipeline/v1beta1/PipelineTaskBuilder
      21: dup
      22: aload_2
      23: invokespecial #399                // Method io/dekorate/deps/tekton/pipeline/v1beta1/PipelineTaskBuilder."<init>":(Lio/dekorate/deps/tekton/pipeline/v1beta1/PipelineTask;)V
      26: astore_3
      27: iload_1
      28: iflt          50
      31: iload_1
      32: aload_0
      33: getfield      #136                // Field _visitables:Lio/dekorate/deps/kubernetes/api/builder/VisitableMap;
      36: ldc_w         #400                // String tasks
      39: invokevirtual #143                // Method io/dekorate/deps/kubernetes/api/builder/VisitableMap.get:(Ljava/lang/Object;)Ljava/util/List;
      42: invokeinterface #151,  1          // InterfaceMethod java/util/List.size:()I
      47: if_icmplt     70
      50: aload_0
      51: getfield      #136                // Field _visitables:Lio/dekorate/deps/kubernetes/api/builder/VisitableMap;
      54: ldc_w         #400                // String tasks
      57: invokevirtual #143                // Method io/dekorate/deps/kubernetes/api/builder/VisitableMap.get:(Ljava/lang/Object;)Ljava/util/List;
      60: aload_3
      61: invokeinterface #165,  2          // InterfaceMethod java/util/List.add:(Ljava/lang/Object;)Z
      66: pop
      67: goto          88
      70: aload_0
      71: getfield      #136                // Field _visitables:Lio/dekorate/deps/kubernetes/api/builder/VisitableMap;
      74: ldc_w         #400                // String tasks
      77: invokevirtual #143                // Method io/dekorate/deps/kubernetes/api/builder/VisitableMap.get:(Ljava/lang/Object;)Ljava/util/List;
      80: iload_1
      81: aload_3
      82: invokeinterface #169,  3          // InterfaceMethod java/util/List.set:(ILjava/lang/Object;)Ljava/lang/Object;
      87: pop
      88: iload_1
      89: iflt          105
      92: iload_1
      93: aload_0
      94: getfield      #394                // Field tasks:Ljava/util/List;
      97: invokeinterface #151,  1          // InterfaceMethod java/util/List.size:()I
     102: if_icmplt     119
     105: aload_0
     106: getfield      #394                // Field tasks:Ljava/util/List;
     109: aload_3
     110: invokeinterface #165,  2          // InterfaceMethod java/util/List.add:(Ljava/lang/Object;)Z
     115: pop
     116: goto          131
     119: aload_0
     120: getfield      #394                // Field tasks:Ljava/util/List;
     123: iload_1
     124: aload_3
     125: invokeinterface #169,  3          // InterfaceMethod java/util/List.set:(ILjava/lang/Object;)Ljava/lang/Object;
     130: pop
     131: aload_0
     132: areturn

  public A addToTasks(io.dekorate.deps.tekton.pipeline.v1beta1.PipelineTask...);
    Code:
       0: aload_0
       1: getfield      #394                // Field tasks:Ljava/util/List;
       4: ifnonnull     18
       7: aload_0
       8: new           #126                // class java/util/ArrayList
      11: dup
      12: invokespecial #127                // Method java/util/ArrayList."<init>":()V
      15: putfield      #394                // Field tasks:Ljava/util/List;
      18: aload_1
      19: astore_2
      20: aload_2
      21: arraylength
      22: istore_3
      23: iconst_0
      24: istore        4
      26: iload         4
      28: iload_3
      29: if_icmpge     85
      32: aload_2
      33: iload         4
      35: aaload
      36: astore        5
      38: new           #396                // class io/dekorate/deps/tekton/pipeline/v1beta1/PipelineTaskBuilder
      41: dup
      42: aload         5
      44: invokespecial #399                // Method io/dekorate/deps/tekton/pipeline/v1beta1/PipelineTaskBuilder."<init>":(Lio/dekorate/deps/tekton/pipeline/v1beta1/PipelineTask;)V
      47: astore        6
      49: aload_0
      50: getfield      #136                // Field _visitables:Lio/dekorate/deps/kubernetes/api/builder/VisitableMap;
      53: ldc_w         #400                // String tasks
      56: invokevirtual #143                // Method io/dekorate/deps/kubernetes/api/builder/VisitableMap.get:(Ljava/lang/Object;)Ljava/util/List;
      59: aload         6
      61: invokeinterface #165,  2          // InterfaceMethod java/util/List.add:(Ljava/lang/Object;)Z
      66: pop
      67: aload_0
      68: getfield      #394                // Field tasks:Ljava/util/List;
      71: aload         6
      73: invokeinterface #165,  2          // InterfaceMethod java/util/List.add:(Ljava/lang/Object;)Z
      78: pop
      79: iinc          4, 1
      82: goto          26
      85: aload_0
      86: areturn

  public A addAllToTasks(java.util.Collection<io.dekorate.deps.tekton.pipeline.v1beta1.PipelineTask>);
    Code:
       0: aload_0
       1: getfield      #394                // Field tasks:Ljava/util/List;
       4: ifnonnull     18
       7: aload_0
       8: new           #126                // class java/util/ArrayList
      11: dup
      12: invokespecial #127                // Method java/util/ArrayList."<init>":()V
      15: putfield      #394                // Field tasks:Ljava/util/List;
      18: aload_1
      19: invokeinterface #183,  1          // InterfaceMethod java/util/Collection.iterator:()Ljava/util/Iterator;
      24: astore_2
      25: aload_2
      26: invokeinterface #189,  1          // InterfaceMethod java/util/Iterator.hasNext:()Z
      31: ifeq          87
      34: aload_2
      35: invokeinterface #193,  1          // InterfaceMethod java/util/Iterator.next:()Ljava/lang/Object;
      40: checkcast     #402                // class io/dekorate/deps/tekton/pipeline/v1beta1/PipelineTask
      43: astore_3
      44: new           #396                // class io/dekorate/deps/tekton/pipeline/v1beta1/PipelineTaskBuilder
      47: dup
      48: aload_3
      49: invokespecial #399                // Method io/dekorate/deps/tekton/pipeline/v1beta1/PipelineTaskBuilder."<init>":(Lio/dekorate/deps/tekton/pipeline/v1beta1/PipelineTask;)V
      52: astore        4
      54: aload_0
      55: getfield      #136                // Field _visitables:Lio/dekorate/deps/kubernetes/api/builder/VisitableMap;
      58: ldc_w         #400                // String tasks
      61: invokevirtual #143                // Method io/dekorate/deps/kubernetes/api/builder/VisitableMap.get:(Ljava/lang/Object;)Ljava/util/List;
      64: aload         4
      66: invokeinterface #165,  2          // InterfaceMethod java/util/List.add:(Ljava/lang/Object;)Z
      71: pop
      72: aload_0
      73: getfield      #394                // Field tasks:Ljava/util/List;
      76: aload         4
      78: invokeinterface #165,  2          // InterfaceMethod java/util/List.add:(Ljava/lang/Object;)Z
      83: pop
      84: goto          25
      87: aload_0
      88: areturn

  public A removeFromTasks(io.dekorate.deps.tekton.pipeline.v1beta1.PipelineTask...);
    Code:
       0: aload_1
       1: astore_2
       2: aload_2
       3: arraylength
       4: istore_3
       5: iconst_0
       6: istore        4
       8: iload         4
      10: iload_3
      11: if_icmpge     74
      14: aload_2
      15: iload         4
      17: aaload
      18: astore        5
      20: new           #396                // class io/dekorate/deps/tekton/pipeline/v1beta1/PipelineTaskBuilder
      23: dup
      24: aload         5
      26: invokespecial #399                // Method io/dekorate/deps/tekton/pipeline/v1beta1/PipelineTaskBuilder."<init>":(Lio/dekorate/deps/tekton/pipeline/v1beta1/PipelineTask;)V
      29: astore        6
      31: aload_0
      32: getfield      #136                // Field _visitables:Lio/dekorate/deps/kubernetes/api/builder/VisitableMap;
      35: ldc_w         #400                // String tasks
      38: invokevirtual #143                // Method io/dekorate/deps/kubernetes/api/builder/VisitableMap.get:(Ljava/lang/Object;)Ljava/util/List;
      41: aload         6
      43: invokeinterface #199,  2          // InterfaceMethod java/util/List.remove:(Ljava/lang/Object;)Z
      48: pop
      49: aload_0
      50: getfield      #394                // Field tasks:Ljava/util/List;
      53: ifnull        68
      56: aload_0
      57: getfield      #394                // Field tasks:Ljava/util/List;
      60: aload         6
      62: invokeinterface #199,  2          // InterfaceMethod java/util/List.remove:(Ljava/lang/Object;)Z
      67: pop
      68: iinc          4, 1
      71: goto          8
      74: aload_0
      75: areturn

  public A removeAllFromTasks(java.util.Collection<io.dekorate.deps.tekton.pipeline.v1beta1.PipelineTask>);
    Code:
       0: aload_1
       1: invokeinterface #183,  1          // InterfaceMethod java/util/Collection.iterator:()Ljava/util/Iterator;
       6: astore_2
       7: aload_2
       8: invokeinterface #189,  1          // InterfaceMethod java/util/Iterator.hasNext:()Z
      13: ifeq          76
      16: aload_2
      17: invokeinterface #193,  1          // InterfaceMethod java/util/Iterator.next:()Ljava/lang/Object;
      22: checkcast     #402                // class io/dekorate/deps/tekton/pipeline/v1beta1/PipelineTask
      25: astore_3
      26: new           #396                // class io/dekorate/deps/tekton/pipeline/v1beta1/PipelineTaskBuilder
      29: dup
      30: aload_3
      31: invokespecial #399                // Method io/dekorate/deps/tekton/pipeline/v1beta1/PipelineTaskBuilder."<init>":(Lio/dekorate/deps/tekton/pipeline/v1beta1/PipelineTask;)V
      34: astore        4
      36: aload_0
      37: getfield      #136                // Field _visitables:Lio/dekorate/deps/kubernetes/api/builder/VisitableMap;
      40: ldc_w         #400                // String tasks
      43: invokevirtual #143                // Method io/dekorate/deps/kubernetes/api/builder/VisitableMap.get:(Ljava/lang/Object;)Ljava/util/List;
      46: aload         4
      48: invokeinterface #199,  2          // InterfaceMethod java/util/List.remove:(Ljava/lang/Object;)Z
      53: pop
      54: aload_0
      55: getfield      #394                // Field tasks:Ljava/util/List;
      58: ifnull        73
      61: aload_0
      62: getfield      #394                // Field tasks:Ljava/util/List;
      65: aload         4
      67: invokeinterface #199,  2          // InterfaceMethod java/util/List.remove:(Ljava/lang/Object;)Z
      72: pop
      73: goto          7
      76: aload_0
      77: areturn

  public A removeMatchingFromTasks(io.dekorate.deps.kubernetes.api.builder.Predicate<io.dekorate.deps.tekton.pipeline.v1beta1.PipelineTaskBuilder>);
    Code:
       0: aload_0
       1: getfield      #394                // Field tasks:Ljava/util/List;
       4: ifnonnull     9
       7: aload_0
       8: areturn
       9: aload_0
      10: getfield      #394                // Field tasks:Ljava/util/List;
      13: invokeinterface #204,  1          // InterfaceMethod java/util/List.iterator:()Ljava/util/Iterator;
      18: astore_2
      19: aload_0
      20: getfield      #136                // Field _visitables:Lio/dekorate/deps/kubernetes/api/builder/VisitableMap;
      23: ldc_w         #400                // String tasks
      26: invokevirtual #143                // Method io/dekorate/deps/kubernetes/api/builder/VisitableMap.get:(Ljava/lang/Object;)Ljava/util/List;
      29: astore_3
      30: aload_2
      31: invokeinterface #189,  1          // InterfaceMethod java/util/Iterator.hasNext:()Z
      36: ifeq          82
      39: aload_2
      40: invokeinterface #193,  1          // InterfaceMethod java/util/Iterator.next:()Ljava/lang/Object;
      45: checkcast     #396                // class io/dekorate/deps/tekton/pipeline/v1beta1/PipelineTaskBuilder
      48: astore        4
      50: aload_1
      51: aload         4
      53: invokeinterface #210,  2          // InterfaceMethod io/dekorate/deps/kubernetes/api/builder/Predicate.apply:(Ljava/lang/Object;)Ljava/lang/Boolean;
      58: invokevirtual #213                // Method java/lang/Boolean.booleanValue:()Z
      61: ifeq          79
      64: aload_3
      65: aload         4
      67: invokeinterface #199,  2          // InterfaceMethod java/util/List.remove:(Ljava/lang/Object;)Z
      72: pop
      73: aload_2
      74: invokeinterface #215,  1          // InterfaceMethod java/util/Iterator.remove:()V
      79: goto          30
      82: aload_0
      83: areturn

  public java.util.List<io.dekorate.deps.tekton.pipeline.v1beta1.PipelineTask> getTasks();
    Code:
       0: aload_0
       1: getfield      #394                // Field tasks:Ljava/util/List;
       4: invokestatic  #228                // Method build:(Ljava/util/List;)Ljava/util/ArrayList;
       7: areturn

  public java.util.List<io.dekorate.deps.tekton.pipeline.v1beta1.PipelineTask> buildTasks();
    Code:
       0: aload_0
       1: getfield      #394                // Field tasks:Ljava/util/List;
       4: invokestatic  #228                // Method build:(Ljava/util/List;)Ljava/util/ArrayList;
       7: areturn

  public io.dekorate.deps.tekton.pipeline.v1beta1.PipelineTask buildTask(int);
    Code:
       0: aload_0
       1: getfield      #394                // Field tasks:Ljava/util/List;
       4: iload_1
       5: invokeinterface #234,  2          // InterfaceMethod java/util/List.get:(I)Ljava/lang/Object;
      10: checkcast     #396                // class io/dekorate/deps/tekton/pipeline/v1beta1/PipelineTaskBuilder
      13: invokevirtual #425                // Method io/dekorate/deps/tekton/pipeline/v1beta1/PipelineTaskBuilder.build:()Lio/dekorate/deps/tekton/pipeline/v1beta1/PipelineTask;
      16: areturn

  public io.dekorate.deps.tekton.pipeline.v1beta1.PipelineTask buildFirstTask();
    Code:
       0: aload_0
       1: getfield      #394                // Field tasks:Ljava/util/List;
       4: iconst_0
       5: invokeinterface #234,  2          // InterfaceMethod java/util/List.get:(I)Ljava/lang/Object;
      10: checkcast     #396                // class io/dekorate/deps/tekton/pipeline/v1beta1/PipelineTaskBuilder
      13: invokevirtual #425                // Method io/dekorate/deps/tekton/pipeline/v1beta1/PipelineTaskBuilder.build:()Lio/dekorate/deps/tekton/pipeline/v1beta1/PipelineTask;
      16: areturn

  public io.dekorate.deps.tekton.pipeline.v1beta1.PipelineTask buildLastTask();
    Code:
       0: aload_0
       1: getfield      #394                // Field tasks:Ljava/util/List;
       4: aload_0
       5: getfield      #394                // Field tasks:Ljava/util/List;
       8: invokeinterface #151,  1          // InterfaceMethod java/util/List.size:()I
      13: iconst_1
      14: isub
      15: invokeinterface #234,  2          // InterfaceMethod java/util/List.get:(I)Ljava/lang/Object;
      20: checkcast     #396                // class io/dekorate/deps/tekton/pipeline/v1beta1/PipelineTaskBuilder
      23: invokevirtual #425                // Method io/dekorate/deps/tekton/pipeline/v1beta1/PipelineTaskBuilder.build:()Lio/dekorate/deps/tekton/pipeline/v1beta1/PipelineTask;
      26: areturn

  public io.dekorate.deps.tekton.pipeline.v1beta1.PipelineTask buildMatchingTask(io.dekorate.deps.kubernetes.api.builder.Predicate<io.dekorate.deps.tekton.pipeline.v1beta1.PipelineTaskBuilder>);
    Code:
       0: aload_0
       1: getfield      #394                // Field tasks:Ljava/util/List;
       4: invokeinterface #204,  1          // InterfaceMethod java/util/List.iterator:()Ljava/util/Iterator;
       9: astore_2
      10: aload_2
      11: invokeinterface #189,  1          // InterfaceMethod java/util/Iterator.hasNext:()Z
      16: ifeq          50
      19: aload_2
      20: invokeinterface #193,  1          // InterfaceMethod java/util/Iterator.next:()Ljava/lang/Object;
      25: checkcast     #396                // class io/dekorate/deps/tekton/pipeline/v1beta1/PipelineTaskBuilder
      28: astore_3
      29: aload_1
      30: aload_3
      31: invokeinterface #210,  2          // InterfaceMethod io/dekorate/deps/kubernetes/api/builder/Predicate.apply:(Ljava/lang/Object;)Ljava/lang/Boolean;
      36: invokevirtual #213                // Method java/lang/Boolean.booleanValue:()Z
      39: ifeq          47
      42: aload_3
      43: invokevirtual #425                // Method io/dekorate/deps/tekton/pipeline/v1beta1/PipelineTaskBuilder.build:()Lio/dekorate/deps/tekton/pipeline/v1beta1/PipelineTask;
      46: areturn
      47: goto          10
      50: aconst_null
      51: areturn

  public java.lang.Boolean hasMatchingTask(io.dekorate.deps.kubernetes.api.builder.Predicate<io.dekorate.deps.tekton.pipeline.v1beta1.PipelineTaskBuilder>);
    Code:
       0: aload_0
       1: getfield      #394                // Field tasks:Ljava/util/List;
       4: invokeinterface #204,  1          // InterfaceMethod java/util/List.iterator:()Ljava/util/Iterator;
       9: astore_2
      10: aload_2
      11: invokeinterface #189,  1          // InterfaceMethod java/util/Iterator.hasNext:()Z
      16: ifeq          50
      19: aload_2
      20: invokeinterface #193,  1          // InterfaceMethod java/util/Iterator.next:()Ljava/lang/Object;
      25: checkcast     #396                // class io/dekorate/deps/tekton/pipeline/v1beta1/PipelineTaskBuilder
      28: astore_3
      29: aload_1
      30: aload_3
      31: invokeinterface #210,  2          // InterfaceMethod io/dekorate/deps/kubernetes/api/builder/Predicate.apply:(Ljava/lang/Object;)Ljava/lang/Boolean;
      36: invokevirtual #213                // Method java/lang/Boolean.booleanValue:()Z
      39: ifeq          47
      42: iconst_1
      43: invokestatic  #100                // Method java/lang/Boolean.valueOf:(Z)Ljava/lang/Boolean;
      46: areturn
      47: goto          10
      50: iconst_0
      51: invokestatic  #100                // Method java/lang/Boolean.valueOf:(Z)Ljava/lang/Boolean;
      54: areturn

  public A withTasks(java.util.List<io.dekorate.deps.tekton.pipeline.v1beta1.PipelineTask>);
    Code:
       0: aload_0
       1: getfield      #394                // Field tasks:Ljava/util/List;
       4: ifnull        27
       7: aload_0
       8: getfield      #136                // Field _visitables:Lio/dekorate/deps/kubernetes/api/builder/VisitableMap;
      11: ldc_w         #400                // String tasks
      14: invokevirtual #143                // Method io/dekorate/deps/kubernetes/api/builder/VisitableMap.get:(Ljava/lang/Object;)Ljava/util/List;
      17: aload_0
      18: getfield      #394                // Field tasks:Ljava/util/List;
      21: invokeinterface #250,  2          // InterfaceMethod java/util/List.removeAll:(Ljava/util/Collection;)Z
      26: pop
      27: aload_1
      28: ifnull        87
      31: aload_0
      32: new           #126                // class java/util/ArrayList
      35: dup
      36: invokespecial #127                // Method java/util/ArrayList."<init>":()V
      39: putfield      #394                // Field tasks:Ljava/util/List;
      42: aload_1
      43: invokeinterface #204,  1          // InterfaceMethod java/util/List.iterator:()Ljava/util/Iterator;
      48: astore_2
      49: aload_2
      50: invokeinterface #189,  1          // InterfaceMethod java/util/Iterator.hasNext:()Z
      55: ifeq          84
      58: aload_2
      59: invokeinterface #193,  1          // InterfaceMethod java/util/Iterator.next:()Ljava/lang/Object;
      64: checkcast     #402                // class io/dekorate/deps/tekton/pipeline/v1beta1/PipelineTask
      67: astore_3
      68: aload_0
      69: iconst_1
      70: anewarray     #402                // class io/dekorate/deps/tekton/pipeline/v1beta1/PipelineTask
      73: dup
      74: iconst_0
      75: aload_3
      76: aastore
      77: invokevirtual #435                // Method addToTasks:([Lio/dekorate/deps/tekton/pipeline/v1beta1/PipelineTask;)Lio/dekorate/deps/tekton/pipeline/v1beta1/PipelineSpecFluent;
      80: pop
      81: goto          49
      84: goto          92
      87: aload_0
      88: aconst_null
      89: putfield      #394                // Field tasks:Ljava/util/List;
      92: aload_0
      93: areturn

  public A withTasks(io.dekorate.deps.tekton.pipeline.v1beta1.PipelineTask...);
    Code:
       0: aload_0
       1: getfield      #394                // Field tasks:Ljava/util/List;
       4: ifnull        16
       7: aload_0
       8: getfield      #394                // Field tasks:Ljava/util/List;
      11: invokeinterface #256,  1          // InterfaceMethod java/util/List.clear:()V
      16: aload_1
      17: ifnull        60
      20: aload_1
      21: astore_2
      22: aload_2
      23: arraylength
      24: istore_3
      25: iconst_0
      26: istore        4
      28: iload         4
      30: iload_3
      31: if_icmpge     60
      34: aload_2
      35: iload         4
      37: aaload
      38: astore        5
      40: aload_0
      41: iconst_1
      42: anewarray     #402                // class io/dekorate/deps/tekton/pipeline/v1beta1/PipelineTask
      45: dup
      46: iconst_0
      47: aload         5
      49: aastore
      50: invokevirtual #435                // Method addToTasks:([Lio/dekorate/deps/tekton/pipeline/v1beta1/PipelineTask;)Lio/dekorate/deps/tekton/pipeline/v1beta1/PipelineSpecFluent;
      53: pop
      54: iinc          4, 1
      57: goto          28
      60: aload_0
      61: areturn

  public java.lang.Boolean hasTasks();
    Code:
       0: aload_0
       1: getfield      #394                // Field tasks:Ljava/util/List;
       4: ifnull        23
       7: aload_0
       8: getfield      #394                // Field tasks:Ljava/util/List;
      11: invokeinterface #260,  1          // InterfaceMethod java/util/List.isEmpty:()Z
      16: ifne          23
      19: iconst_1
      20: goto          24
      23: iconst_0
      24: invokestatic  #100                // Method java/lang/Boolean.valueOf:(Z)Ljava/lang/Boolean;
      27: areturn

  public io.dekorate.deps.tekton.pipeline.v1beta1.PipelineSpecFluent$TasksNested<A> addNewTask();
    Code:
       0: new           #13                 // class io/dekorate/deps/tekton/pipeline/v1beta1/PipelineSpecFluentImpl$TasksNestedImpl
       3: dup
       4: aload_0
       5: invokespecial #441                // Method io/dekorate/deps/tekton/pipeline/v1beta1/PipelineSpecFluentImpl$TasksNestedImpl."<init>":(Lio/dekorate/deps/tekton/pipeline/v1beta1/PipelineSpecFluentImpl;)V
       8: areturn

  public io.dekorate.deps.tekton.pipeline.v1beta1.PipelineSpecFluent$TasksNested<A> addNewTaskLike(io.dekorate.deps.tekton.pipeline.v1beta1.PipelineTask);
    Code:
       0: new           #13                 // class io/dekorate/deps/tekton/pipeline/v1beta1/PipelineSpecFluentImpl$TasksNestedImpl
       3: dup
       4: aload_0
       5: iconst_m1
       6: aload_1
       7: invokespecial #447                // Method io/dekorate/deps/tekton/pipeline/v1beta1/PipelineSpecFluentImpl$TasksNestedImpl."<init>":(Lio/dekorate/deps/tekton/pipeline/v1beta1/PipelineSpecFluentImpl;ILio/dekorate/deps/tekton/pipeline/v1beta1/PipelineTask;)V
      10: areturn

  public io.dekorate.deps.tekton.pipeline.v1beta1.PipelineSpecFluent$TasksNested<A> setNewTaskLike(int, io.dekorate.deps.tekton.pipeline.v1beta1.PipelineTask);
    Code:
       0: new           #13                 // class io/dekorate/deps/tekton/pipeline/v1beta1/PipelineSpecFluentImpl$TasksNestedImpl
       3: dup
       4: aload_0
       5: iload_1
       6: aload_2
       7: invokespecial #447                // Method io/dekorate/deps/tekton/pipeline/v1beta1/PipelineSpecFluentImpl$TasksNestedImpl."<init>":(Lio/dekorate/deps/tekton/pipeline/v1beta1/PipelineSpecFluentImpl;ILio/dekorate/deps/tekton/pipeline/v1beta1/PipelineTask;)V
      10: areturn

  public io.dekorate.deps.tekton.pipeline.v1beta1.PipelineSpecFluent$TasksNested<A> editTask(int);
    Code:
       0: aload_0
       1: getfield      #394                // Field tasks:Ljava/util/List;
       4: invokeinterface #151,  1          // InterfaceMethod java/util/List.size:()I
       9: iload_1
      10: if_icmpgt     24
      13: new           #280                // class java/lang/RuntimeException
      16: dup
      17: ldc_w         #455                // String Can\'t edit tasks. Index exceeds size.
      20: invokespecial #283                // Method java/lang/RuntimeException."<init>":(Ljava/lang/String;)V
      23: athrow
      24: aload_0
      25: iload_1
      26: aload_0
      27: iload_1
      28: invokevirtual #457                // Method buildTask:(I)Lio/dekorate/deps/tekton/pipeline/v1beta1/PipelineTask;
      31: invokevirtual #459                // Method setNewTaskLike:(ILio/dekorate/deps/tekton/pipeline/v1beta1/PipelineTask;)Lio/dekorate/deps/tekton/pipeline/v1beta1/PipelineSpecFluent$TasksNested;
      34: areturn

  public io.dekorate.deps.tekton.pipeline.v1beta1.PipelineSpecFluent$TasksNested<A> editFirstTask();
    Code:
       0: aload_0
       1: getfield      #394                // Field tasks:Ljava/util/List;
       4: invokeinterface #151,  1          // InterfaceMethod java/util/List.size:()I
       9: ifne          23
      12: new           #280                // class java/lang/RuntimeException
      15: dup
      16: ldc_w         #462                // String Can\'t edit first tasks. The list is empty.
      19: invokespecial #283                // Method java/lang/RuntimeException."<init>":(Ljava/lang/String;)V
      22: athrow
      23: aload_0
      24: iconst_0
      25: aload_0
      26: iconst_0
      27: invokevirtual #457                // Method buildTask:(I)Lio/dekorate/deps/tekton/pipeline/v1beta1/PipelineTask;
      30: invokevirtual #459                // Method setNewTaskLike:(ILio/dekorate/deps/tekton/pipeline/v1beta1/PipelineTask;)Lio/dekorate/deps/tekton/pipeline/v1beta1/PipelineSpecFluent$TasksNested;
      33: areturn

  public io.dekorate.deps.tekton.pipeline.v1beta1.PipelineSpecFluent$TasksNested<A> editLastTask();
    Code:
       0: aload_0
       1: getfield      #394                // Field tasks:Ljava/util/List;
       4: invokeinterface #151,  1          // InterfaceMethod java/util/List.size:()I
       9: iconst_1
      10: isub
      11: istore_1
      12: iload_1
      13: ifge          27
      16: new           #280                // class java/lang/RuntimeException
      19: dup
      20: ldc_w         #465                // String Can\'t edit last tasks. The list is empty.
      23: invokespecial #283                // Method java/lang/RuntimeException."<init>":(Ljava/lang/String;)V
      26: athrow
      27: aload_0
      28: iload_1
      29: aload_0
      30: iload_1
      31: invokevirtual #457                // Method buildTask:(I)Lio/dekorate/deps/tekton/pipeline/v1beta1/PipelineTask;
      34: invokevirtual #459                // Method setNewTaskLike:(ILio/dekorate/deps/tekton/pipeline/v1beta1/PipelineTask;)Lio/dekorate/deps/tekton/pipeline/v1beta1/PipelineSpecFluent$TasksNested;
      37: areturn

  public io.dekorate.deps.tekton.pipeline.v1beta1.PipelineSpecFluent$TasksNested<A> editMatchingTask(io.dekorate.deps.kubernetes.api.builder.Predicate<io.dekorate.deps.tekton.pipeline.v1beta1.PipelineTaskBuilder>);
    Code:
       0: iconst_m1
       1: istore_2
       2: iconst_0
       3: istore_3
       4: iload_3
       5: aload_0
       6: getfield      #394                // Field tasks:Ljava/util/List;
       9: invokeinterface #151,  1          // InterfaceMethod java/util/List.size:()I
      14: if_icmpge     50
      17: aload_1
      18: aload_0
      19: getfield      #394                // Field tasks:Ljava/util/List;
      22: iload_3
      23: invokeinterface #234,  2          // InterfaceMethod java/util/List.get:(I)Ljava/lang/Object;
      28: invokeinterface #210,  2          // InterfaceMethod io/dekorate/deps/kubernetes/api/builder/Predicate.apply:(Ljava/lang/Object;)Ljava/lang/Boolean;
      33: invokevirtual #213                // Method java/lang/Boolean.booleanValue:()Z
      36: ifeq          44
      39: iload_3
      40: istore_2
      41: goto          50
      44: iinc          3, 1
      47: goto          4
      50: iload_2
      51: ifge          65
      54: new           #280                // class java/lang/RuntimeException
      57: dup
      58: ldc_w         #470                // String Can\'t edit matching tasks. No match found.
      61: invokespecial #283                // Method java/lang/RuntimeException."<init>":(Ljava/lang/String;)V
      64: athrow
      65: aload_0
      66: iload_2
      67: aload_0
      68: iload_2
      69: invokevirtual #457                // Method buildTask:(I)Lio/dekorate/deps/tekton/pipeline/v1beta1/PipelineTask;
      72: invokevirtual #459                // Method setNewTaskLike:(ILio/dekorate/deps/tekton/pipeline/v1beta1/PipelineTask;)Lio/dekorate/deps/tekton/pipeline/v1beta1/PipelineSpecFluent$TasksNested;
      75: areturn

  public A addToWorkspaces(int, io.dekorate.deps.tekton.pipeline.v1beta1.WorkspacePipelineDeclaration);
    Code:
       0: aload_0
       1: getfield      #475                // Field workspaces:Ljava/util/List;
       4: ifnonnull     18
       7: aload_0
       8: new           #126                // class java/util/ArrayList
      11: dup
      12: invokespecial #127                // Method java/util/ArrayList."<init>":()V
      15: putfield      #475                // Field workspaces:Ljava/util/List;
      18: new           #477                // class io/dekorate/deps/tekton/pipeline/v1beta1/WorkspacePipelineDeclarationBuilder
      21: dup
      22: aload_2
      23: invokespecial #480                // Method io/dekorate/deps/tekton/pipeline/v1beta1/WorkspacePipelineDeclarationBuilder."<init>":(Lio/dekorate/deps/tekton/pipeline/v1beta1/WorkspacePipelineDeclaration;)V
      26: astore_3
      27: aload_0
      28: getfield      #136                // Field _visitables:Lio/dekorate/deps/kubernetes/api/builder/VisitableMap;
      31: ldc_w         #481                // String workspaces
      34: invokevirtual #143                // Method io/dekorate/deps/kubernetes/api/builder/VisitableMap.get:(Ljava/lang/Object;)Ljava/util/List;
      37: iload_1
      38: iflt          45
      41: iload_1
      42: goto          60
      45: aload_0
      46: getfield      #136                // Field _visitables:Lio/dekorate/deps/kubernetes/api/builder/VisitableMap;
      49: ldc_w         #481                // String workspaces
      52: invokevirtual #143                // Method io/dekorate/deps/kubernetes/api/builder/VisitableMap.get:(Ljava/lang/Object;)Ljava/util/List;
      55: invokeinterface #151,  1          // InterfaceMethod java/util/List.size:()I
      60: aload_3
      61: invokeinterface #155,  3          // InterfaceMethod java/util/List.add:(ILjava/lang/Object;)V
      66: aload_0
      67: getfield      #475                // Field workspaces:Ljava/util/List;
      70: iload_1
      71: iflt          78
      74: iload_1
      75: goto          87
      78: aload_0
      79: getfield      #475                // Field workspaces:Ljava/util/List;
      82: invokeinterface #151,  1          // InterfaceMethod java/util/List.size:()I
      87: aload_3
      88: invokeinterface #155,  3          // InterfaceMethod java/util/List.add:(ILjava/lang/Object;)V
      93: aload_0
      94: areturn

  public A setToWorkspaces(int, io.dekorate.deps.tekton.pipeline.v1beta1.WorkspacePipelineDeclaration);
    Code:
       0: aload_0
       1: getfield      #475                // Field workspaces:Ljava/util/List;
       4: ifnonnull     18
       7: aload_0
       8: new           #126                // class java/util/ArrayList
      11: dup
      12: invokespecial #127                // Method java/util/ArrayList."<init>":()V
      15: putfield      #475                // Field workspaces:Ljava/util/List;
      18: new           #477                // class io/dekorate/deps/tekton/pipeline/v1beta1/WorkspacePipelineDeclarationBuilder
      21: dup
      22: aload_2
      23: invokespecial #480                // Method io/dekorate/deps/tekton/pipeline/v1beta1/WorkspacePipelineDeclarationBuilder."<init>":(Lio/dekorate/deps/tekton/pipeline/v1beta1/WorkspacePipelineDeclaration;)V
      26: astore_3
      27: iload_1
      28: iflt          50
      31: iload_1
      32: aload_0
      33: getfield      #136                // Field _visitables:Lio/dekorate/deps/kubernetes/api/builder/VisitableMap;
      36: ldc_w         #481                // String workspaces
      39: invokevirtual #143                // Method io/dekorate/deps/kubernetes/api/builder/VisitableMap.get:(Ljava/lang/Object;)Ljava/util/List;
      42: invokeinterface #151,  1          // InterfaceMethod java/util/List.size:()I
      47: if_icmplt     70
      50: aload_0
      51: getfield      #136                // Field _visitables:Lio/dekorate/deps/kubernetes/api/builder/VisitableMap;
      54: ldc_w         #481                // String workspaces
      57: invokevirtual #143                // Method io/dekorate/deps/kubernetes/api/builder/VisitableMap.get:(Ljava/lang/Object;)Ljava/util/List;
      60: aload_3
      61: invokeinterface #165,  2          // InterfaceMethod java/util/List.add:(Ljava/lang/Object;)Z
      66: pop
      67: goto          88
      70: aload_0
      71: getfield      #136                // Field _visitables:Lio/dekorate/deps/kubernetes/api/builder/VisitableMap;
      74: ldc_w         #481                // String workspaces
      77: invokevirtual #143                // Method io/dekorate/deps/kubernetes/api/builder/VisitableMap.get:(Ljava/lang/Object;)Ljava/util/List;
      80: iload_1
      81: aload_3
      82: invokeinterface #169,  3          // InterfaceMethod java/util/List.set:(ILjava/lang/Object;)Ljava/lang/Object;
      87: pop
      88: iload_1
      89: iflt          105
      92: iload_1
      93: aload_0
      94: getfield      #475                // Field workspaces:Ljava/util/List;
      97: invokeinterface #151,  1          // InterfaceMethod java/util/List.size:()I
     102: if_icmplt     119
     105: aload_0
     106: getfield      #475                // Field workspaces:Ljava/util/List;
     109: aload_3
     110: invokeinterface #165,  2          // InterfaceMethod java/util/List.add:(Ljava/lang/Object;)Z
     115: pop
     116: goto          131
     119: aload_0
     120: getfield      #475                // Field workspaces:Ljava/util/List;
     123: iload_1
     124: aload_3
     125: invokeinterface #169,  3          // InterfaceMethod java/util/List.set:(ILjava/lang/Object;)Ljava/lang/Object;
     130: pop
     131: aload_0
     132: areturn

  public A addToWorkspaces(io.dekorate.deps.tekton.pipeline.v1beta1.WorkspacePipelineDeclaration...);
    Code:
       0: aload_0
       1: getfield      #475                // Field workspaces:Ljava/util/List;
       4: ifnonnull     18
       7: aload_0
       8: new           #126                // class java/util/ArrayList
      11: dup
      12: invokespecial #127                // Method java/util/ArrayList."<init>":()V
      15: putfield      #475                // Field workspaces:Ljava/util/List;
      18: aload_1
      19: astore_2
      20: aload_2
      21: arraylength
      22: istore_3
      23: iconst_0
      24: istore        4
      26: iload         4
      28: iload_3
      29: if_icmpge     85
      32: aload_2
      33: iload         4
      35: aaload
      36: astore        5
      38: new           #477                // class io/dekorate/deps/tekton/pipeline/v1beta1/WorkspacePipelineDeclarationBuilder
      41: dup
      42: aload         5
      44: invokespecial #480                // Method io/dekorate/deps/tekton/pipeline/v1beta1/WorkspacePipelineDeclarationBuilder."<init>":(Lio/dekorate/deps/tekton/pipeline/v1beta1/WorkspacePipelineDeclaration;)V
      47: astore        6
      49: aload_0
      50: getfield      #136                // Field _visitables:Lio/dekorate/deps/kubernetes/api/builder/VisitableMap;
      53: ldc_w         #481                // String workspaces
      56: invokevirtual #143                // Method io/dekorate/deps/kubernetes/api/builder/VisitableMap.get:(Ljava/lang/Object;)Ljava/util/List;
      59: aload         6
      61: invokeinterface #165,  2          // InterfaceMethod java/util/List.add:(Ljava/lang/Object;)Z
      66: pop
      67: aload_0
      68: getfield      #475                // Field workspaces:Ljava/util/List;
      71: aload         6
      73: invokeinterface #165,  2          // InterfaceMethod java/util/List.add:(Ljava/lang/Object;)Z
      78: pop
      79: iinc          4, 1
      82: goto          26
      85: aload_0
      86: areturn

  public A addAllToWorkspaces(java.util.Collection<io.dekorate.deps.tekton.pipeline.v1beta1.WorkspacePipelineDeclaration>);
    Code:
       0: aload_0
       1: getfield      #475                // Field workspaces:Ljava/util/List;
       4: ifnonnull     18
       7: aload_0
       8: new           #126                // class java/util/ArrayList
      11: dup
      12: invokespecial #127                // Method java/util/ArrayList."<init>":()V
      15: putfield      #475                // Field workspaces:Ljava/util/List;
      18: aload_1
      19: invokeinterface #183,  1          // InterfaceMethod java/util/Collection.iterator:()Ljava/util/Iterator;
      24: astore_2
      25: aload_2
      26: invokeinterface #189,  1          // InterfaceMethod java/util/Iterator.hasNext:()Z
      31: ifeq          87
      34: aload_2
      35: invokeinterface #193,  1          // InterfaceMethod java/util/Iterator.next:()Ljava/lang/Object;
      40: checkcast     #483                // class io/dekorate/deps/tekton/pipeline/v1beta1/WorkspacePipelineDeclaration
      43: astore_3
      44: new           #477                // class io/dekorate/deps/tekton/pipeline/v1beta1/WorkspacePipelineDeclarationBuilder
      47: dup
      48: aload_3
      49: invokespecial #480                // Method io/dekorate/deps/tekton/pipeline/v1beta1/WorkspacePipelineDeclarationBuilder."<init>":(Lio/dekorate/deps/tekton/pipeline/v1beta1/WorkspacePipelineDeclaration;)V
      52: astore        4
      54: aload_0
      55: getfield      #136                // Field _visitables:Lio/dekorate/deps/kubernetes/api/builder/VisitableMap;
      58: ldc_w         #481                // String workspaces
      61: invokevirtual #143                // Method io/dekorate/deps/kubernetes/api/builder/VisitableMap.get:(Ljava/lang/Object;)Ljava/util/List;
      64: aload         4
      66: invokeinterface #165,  2          // InterfaceMethod java/util/List.add:(Ljava/lang/Object;)Z
      71: pop
      72: aload_0
      73: getfield      #475                // Field workspaces:Ljava/util/List;
      76: aload         4
      78: invokeinterface #165,  2          // InterfaceMethod java/util/List.add:(Ljava/lang/Object;)Z
      83: pop
      84: goto          25
      87: aload_0
      88: areturn

  public A removeFromWorkspaces(io.dekorate.deps.tekton.pipeline.v1beta1.WorkspacePipelineDeclaration...);
    Code:
       0: aload_1
       1: astore_2
       2: aload_2
       3: arraylength
       4: istore_3
       5: iconst_0
       6: istore        4
       8: iload         4
      10: iload_3
      11: if_icmpge     74
      14: aload_2
      15: iload         4
      17: aaload
      18: astore        5
      20: new           #477                // class io/dekorate/deps/tekton/pipeline/v1beta1/WorkspacePipelineDeclarationBuilder
      23: dup
      24: aload         5
      26: invokespecial #480                // Method io/dekorate/deps/tekton/pipeline/v1beta1/WorkspacePipelineDeclarationBuilder."<init>":(Lio/dekorate/deps/tekton/pipeline/v1beta1/WorkspacePipelineDeclaration;)V
      29: astore        6
      31: aload_0
      32: getfield      #136                // Field _visitables:Lio/dekorate/deps/kubernetes/api/builder/VisitableMap;
      35: ldc_w         #481                // String workspaces
      38: invokevirtual #143                // Method io/dekorate/deps/kubernetes/api/builder/VisitableMap.get:(Ljava/lang/Object;)Ljava/util/List;
      41: aload         6
      43: invokeinterface #199,  2          // InterfaceMethod java/util/List.remove:(Ljava/lang/Object;)Z
      48: pop
      49: aload_0
      50: getfield      #475                // Field workspaces:Ljava/util/List;
      53: ifnull        68
      56: aload_0
      57: getfield      #475                // Field workspaces:Ljava/util/List;
      60: aload         6
      62: invokeinterface #199,  2          // InterfaceMethod java/util/List.remove:(Ljava/lang/Object;)Z
      67: pop
      68: iinc          4, 1
      71: goto          8
      74: aload_0
      75: areturn

  public A removeAllFromWorkspaces(java.util.Collection<io.dekorate.deps.tekton.pipeline.v1beta1.WorkspacePipelineDeclaration>);
    Code:
       0: aload_1
       1: invokeinterface #183,  1          // InterfaceMethod java/util/Collection.iterator:()Ljava/util/Iterator;
       6: astore_2
       7: aload_2
       8: invokeinterface #189,  1          // InterfaceMethod java/util/Iterator.hasNext:()Z
      13: ifeq          76
      16: aload_2
      17: invokeinterface #193,  1          // InterfaceMethod java/util/Iterator.next:()Ljava/lang/Object;
      22: checkcast     #483                // class io/dekorate/deps/tekton/pipeline/v1beta1/WorkspacePipelineDeclaration
      25: astore_3
      26: new           #477                // class io/dekorate/deps/tekton/pipeline/v1beta1/WorkspacePipelineDeclarationBuilder
      29: dup
      30: aload_3
      31: invokespecial #480                // Method io/dekorate/deps/tekton/pipeline/v1beta1/WorkspacePipelineDeclarationBuilder."<init>":(Lio/dekorate/deps/tekton/pipeline/v1beta1/WorkspacePipelineDeclaration;)V
      34: astore        4
      36: aload_0
      37: getfield      #136                // Field _visitables:Lio/dekorate/deps/kubernetes/api/builder/VisitableMap;
      40: ldc_w         #481                // String workspaces
      43: invokevirtual #143                // Method io/dekorate/deps/kubernetes/api/builder/VisitableMap.get:(Ljava/lang/Object;)Ljava/util/List;
      46: aload         4
      48: invokeinterface #199,  2          // InterfaceMethod java/util/List.remove:(Ljava/lang/Object;)Z
      53: pop
      54: aload_0
      55: getfield      #475                // Field workspaces:Ljava/util/List;
      58: ifnull        73
      61: aload_0
      62: getfield      #475                // Field workspaces:Ljava/util/List;
      65: aload         4
      67: invokeinterface #199,  2          // InterfaceMethod java/util/List.remove:(Ljava/lang/Object;)Z
      72: pop
      73: goto          7
      76: aload_0
      77: areturn

  public A removeMatchingFromWorkspaces(io.dekorate.deps.kubernetes.api.builder.Predicate<io.dekorate.deps.tekton.pipeline.v1beta1.WorkspacePipelineDeclarationBuilder>);
    Code:
       0: aload_0
       1: getfield      #475                // Field workspaces:Ljava/util/List;
       4: ifnonnull     9
       7: aload_0
       8: areturn
       9: aload_0
      10: getfield      #475                // Field workspaces:Ljava/util/List;
      13: invokeinterface #204,  1          // InterfaceMethod java/util/List.iterator:()Ljava/util/Iterator;
      18: astore_2
      19: aload_0
      20: getfield      #136                // Field _visitables:Lio/dekorate/deps/kubernetes/api/builder/VisitableMap;
      23: ldc_w         #481                // String workspaces
      26: invokevirtual #143                // Method io/dekorate/deps/kubernetes/api/builder/VisitableMap.get:(Ljava/lang/Object;)Ljava/util/List;
      29: astore_3
      30: aload_2
      31: invokeinterface #189,  1          // InterfaceMethod java/util/Iterator.hasNext:()Z
      36: ifeq          82
      39: aload_2
      40: invokeinterface #193,  1          // InterfaceMethod java/util/Iterator.next:()Ljava/lang/Object;
      45: checkcast     #477                // class io/dekorate/deps/tekton/pipeline/v1beta1/WorkspacePipelineDeclarationBuilder
      48: astore        4
      50: aload_1
      51: aload         4
      53: invokeinterface #210,  2          // InterfaceMethod io/dekorate/deps/kubernetes/api/builder/Predicate.apply:(Ljava/lang/Object;)Ljava/lang/Boolean;
      58: invokevirtual #213                // Method java/lang/Boolean.booleanValue:()Z
      61: ifeq          79
      64: aload_3
      65: aload         4
      67: invokeinterface #199,  2          // InterfaceMethod java/util/List.remove:(Ljava/lang/Object;)Z
      72: pop
      73: aload_2
      74: invokeinterface #215,  1          // InterfaceMethod java/util/Iterator.remove:()V
      79: goto          30
      82: aload_0
      83: areturn

  public java.util.List<io.dekorate.deps.tekton.pipeline.v1beta1.WorkspacePipelineDeclaration> getWorkspaces();
    Code:
       0: aload_0
       1: getfield      #475                // Field workspaces:Ljava/util/List;
       4: invokestatic  #228                // Method build:(Ljava/util/List;)Ljava/util/ArrayList;
       7: areturn

  public java.util.List<io.dekorate.deps.tekton.pipeline.v1beta1.WorkspacePipelineDeclaration> buildWorkspaces();
    Code:
       0: aload_0
       1: getfield      #475                // Field workspaces:Ljava/util/List;
       4: invokestatic  #228                // Method build:(Ljava/util/List;)Ljava/util/ArrayList;
       7: areturn

  public io.dekorate.deps.tekton.pipeline.v1beta1.WorkspacePipelineDeclaration buildWorkspace(int);
    Code:
       0: aload_0
       1: getfield      #475                // Field workspaces:Ljava/util/List;
       4: iload_1
       5: invokeinterface #234,  2          // InterfaceMethod java/util/List.get:(I)Ljava/lang/Object;
      10: checkcast     #477                // class io/dekorate/deps/tekton/pipeline/v1beta1/WorkspacePipelineDeclarationBuilder
      13: invokevirtual #506                // Method io/dekorate/deps/tekton/pipeline/v1beta1/WorkspacePipelineDeclarationBuilder.build:()Lio/dekorate/deps/tekton/pipeline/v1beta1/WorkspacePipelineDeclaration;
      16: areturn

  public io.dekorate.deps.tekton.pipeline.v1beta1.WorkspacePipelineDeclaration buildFirstWorkspace();
    Code:
       0: aload_0
       1: getfield      #475                // Field workspaces:Ljava/util/List;
       4: iconst_0
       5: invokeinterface #234,  2          // InterfaceMethod java/util/List.get:(I)Ljava/lang/Object;
      10: checkcast     #477                // class io/dekorate/deps/tekton/pipeline/v1beta1/WorkspacePipelineDeclarationBuilder
      13: invokevirtual #506                // Method io/dekorate/deps/tekton/pipeline/v1beta1/WorkspacePipelineDeclarationBuilder.build:()Lio/dekorate/deps/tekton/pipeline/v1beta1/WorkspacePipelineDeclaration;
      16: areturn

  public io.dekorate.deps.tekton.pipeline.v1beta1.WorkspacePipelineDeclaration buildLastWorkspace();
    Code:
       0: aload_0
       1: getfield      #475                // Field workspaces:Ljava/util/List;
       4: aload_0
       5: getfield      #475                // Field workspaces:Ljava/util/List;
       8: invokeinterface #151,  1          // InterfaceMethod java/util/List.size:()I
      13: iconst_1
      14: isub
      15: invokeinterface #234,  2          // InterfaceMethod java/util/List.get:(I)Ljava/lang/Object;
      20: checkcast     #477                // class io/dekorate/deps/tekton/pipeline/v1beta1/WorkspacePipelineDeclarationBuilder
      23: invokevirtual #506                // Method io/dekorate/deps/tekton/pipeline/v1beta1/WorkspacePipelineDeclarationBuilder.build:()Lio/dekorate/deps/tekton/pipeline/v1beta1/WorkspacePipelineDeclaration;
      26: areturn

  public io.dekorate.deps.tekton.pipeline.v1beta1.WorkspacePipelineDeclaration buildMatchingWorkspace(io.dekorate.deps.kubernetes.api.builder.Predicate<io.dekorate.deps.tekton.pipeline.v1beta1.WorkspacePipelineDeclarationBuilder>);
    Code:
       0: aload_0
       1: getfield      #475                // Field workspaces:Ljava/util/List;
       4: invokeinterface #204,  1          // InterfaceMethod java/util/List.iterator:()Ljava/util/Iterator;
       9: astore_2
      10: aload_2
      11: invokeinterface #189,  1          // InterfaceMethod java/util/Iterator.hasNext:()Z
      16: ifeq          50
      19: aload_2
      20: invokeinterface #193,  1          // InterfaceMethod java/util/Iterator.next:()Ljava/lang/Object;
      25: checkcast     #477                // class io/dekorate/deps/tekton/pipeline/v1beta1/WorkspacePipelineDeclarationBuilder
      28: astore_3
      29: aload_1
      30: aload_3
      31: invokeinterface #210,  2          // InterfaceMethod io/dekorate/deps/kubernetes/api/builder/Predicate.apply:(Ljava/lang/Object;)Ljava/lang/Boolean;
      36: invokevirtual #213                // Method java/lang/Boolean.booleanValue:()Z
      39: ifeq          47
      42: aload_3
      43: invokevirtual #506                // Method io/dekorate/deps/tekton/pipeline/v1beta1/WorkspacePipelineDeclarationBuilder.build:()Lio/dekorate/deps/tekton/pipeline/v1beta1/WorkspacePipelineDeclaration;
      46: areturn
      47: goto          10
      50: aconst_null
      51: areturn

  public java.lang.Boolean hasMatchingWorkspace(io.dekorate.deps.kubernetes.api.builder.Predicate<io.dekorate.deps.tekton.pipeline.v1beta1.WorkspacePipelineDeclarationBuilder>);
    Code:
       0: aload_0
       1: getfield      #475                // Field workspaces:Ljava/util/List;
       4: invokeinterface #204,  1          // InterfaceMethod java/util/List.iterator:()Ljava/util/Iterator;
       9: astore_2
      10: aload_2
      11: invokeinterface #189,  1          // InterfaceMethod java/util/Iterator.hasNext:()Z
      16: ifeq          50
      19: aload_2
      20: invokeinterface #193,  1          // InterfaceMethod java/util/Iterator.next:()Ljava/lang/Object;
      25: checkcast     #477                // class io/dekorate/deps/tekton/pipeline/v1beta1/WorkspacePipelineDeclarationBuilder
      28: astore_3
      29: aload_1
      30: aload_3
      31: invokeinterface #210,  2          // InterfaceMethod io/dekorate/deps/kubernetes/api/builder/Predicate.apply:(Ljava/lang/Object;)Ljava/lang/Boolean;
      36: invokevirtual #213                // Method java/lang/Boolean.booleanValue:()Z
      39: ifeq          47
      42: iconst_1
      43: invokestatic  #100                // Method java/lang/Boolean.valueOf:(Z)Ljava/lang/Boolean;
      46: areturn
      47: goto          10
      50: iconst_0
      51: invokestatic  #100                // Method java/lang/Boolean.valueOf:(Z)Ljava/lang/Boolean;
      54: areturn

  public A withWorkspaces(java.util.List<io.dekorate.deps.tekton.pipeline.v1beta1.WorkspacePipelineDeclaration>);
    Code:
       0: aload_0
       1: getfield      #475                // Field workspaces:Ljava/util/List;
       4: ifnull        27
       7: aload_0
       8: getfield      #136                // Field _visitables:Lio/dekorate/deps/kubernetes/api/builder/VisitableMap;
      11: ldc_w         #481                // String workspaces
      14: invokevirtual #143                // Method io/dekorate/deps/kubernetes/api/builder/VisitableMap.get:(Ljava/lang/Object;)Ljava/util/List;
      17: aload_0
      18: getfield      #475                // Field workspaces:Ljava/util/List;
      21: invokeinterface #250,  2          // InterfaceMethod java/util/List.removeAll:(Ljava/util/Collection;)Z
      26: pop
      27: aload_1
      28: ifnull        87
      31: aload_0
      32: new           #126                // class java/util/ArrayList
      35: dup
      36: invokespecial #127                // Method java/util/ArrayList."<init>":()V
      39: putfield      #475                // Field workspaces:Ljava/util/List;
      42: aload_1
      43: invokeinterface #204,  1          // InterfaceMethod java/util/List.iterator:()Ljava/util/Iterator;
      48: astore_2
      49: aload_2
      50: invokeinterface #189,  1          // InterfaceMethod java/util/Iterator.hasNext:()Z
      55: ifeq          84
      58: aload_2
      59: invokeinterface #193,  1          // InterfaceMethod java/util/Iterator.next:()Ljava/lang/Object;
      64: checkcast     #483                // class io/dekorate/deps/tekton/pipeline/v1beta1/WorkspacePipelineDeclaration
      67: astore_3
      68: aload_0
      69: iconst_1
      70: anewarray     #483                // class io/dekorate/deps/tekton/pipeline/v1beta1/WorkspacePipelineDeclaration
      73: dup
      74: iconst_0
      75: aload_3
      76: aastore
      77: invokevirtual #516                // Method addToWorkspaces:([Lio/dekorate/deps/tekton/pipeline/v1beta1/WorkspacePipelineDeclaration;)Lio/dekorate/deps/tekton/pipeline/v1beta1/PipelineSpecFluent;
      80: pop
      81: goto          49
      84: goto          92
      87: aload_0
      88: aconst_null
      89: putfield      #475                // Field workspaces:Ljava/util/List;
      92: aload_0
      93: areturn

  public A withWorkspaces(io.dekorate.deps.tekton.pipeline.v1beta1.WorkspacePipelineDeclaration...);
    Code:
       0: aload_0
       1: getfield      #475                // Field workspaces:Ljava/util/List;
       4: ifnull        16
       7: aload_0
       8: getfield      #475                // Field workspaces:Ljava/util/List;
      11: invokeinterface #256,  1          // InterfaceMethod java/util/List.clear:()V
      16: aload_1
      17: ifnull        60
      20: aload_1
      21: astore_2
      22: aload_2
      23: arraylength
      24: istore_3
      25: iconst_0
      26: istore        4
      28: iload         4
      30: iload_3
      31: if_icmpge     60
      34: aload_2
      35: iload         4
      37: aaload
      38: astore        5
      40: aload_0
      41: iconst_1
      42: anewarray     #483                // class io/dekorate/deps/tekton/pipeline/v1beta1/WorkspacePipelineDeclaration
      45: dup
      46: iconst_0
      47: aload         5
      49: aastore
      50: invokevirtual #516                // Method addToWorkspaces:([Lio/dekorate/deps/tekton/pipeline/v1beta1/WorkspacePipelineDeclaration;)Lio/dekorate/deps/tekton/pipeline/v1beta1/PipelineSpecFluent;
      53: pop
      54: iinc          4, 1
      57: goto          28
      60: aload_0
      61: areturn

  public java.lang.Boolean hasWorkspaces();
    Code:
       0: aload_0
       1: getfield      #475                // Field workspaces:Ljava/util/List;
       4: ifnull        23
       7: aload_0
       8: getfield      #475                // Field workspaces:Ljava/util/List;
      11: invokeinterface #260,  1          // InterfaceMethod java/util/List.isEmpty:()Z
      16: ifne          23
      19: iconst_1
      20: goto          24
      23: iconst_0
      24: invokestatic  #100                // Method java/lang/Boolean.valueOf:(Z)Ljava/lang/Boolean;
      27: areturn

  public A addNewWorkspace(java.lang.String, java.lang.String);
    Code:
       0: aload_0
       1: iconst_1
       2: anewarray     #483                // class io/dekorate/deps/tekton/pipeline/v1beta1/WorkspacePipelineDeclaration
       5: dup
       6: iconst_0
       7: new           #483                // class io/dekorate/deps/tekton/pipeline/v1beta1/WorkspacePipelineDeclaration
      10: dup
      11: aload_1
      12: aload_2
      13: invokespecial #524                // Method io/dekorate/deps/tekton/pipeline/v1beta1/WorkspacePipelineDeclaration."<init>":(Ljava/lang/String;Ljava/lang/String;)V
      16: aastore
      17: invokevirtual #516                // Method addToWorkspaces:([Lio/dekorate/deps/tekton/pipeline/v1beta1/WorkspacePipelineDeclaration;)Lio/dekorate/deps/tekton/pipeline/v1beta1/PipelineSpecFluent;
      20: areturn

  public io.dekorate.deps.tekton.pipeline.v1beta1.PipelineSpecFluent$WorkspacesNested<A> addNewWorkspace();
    Code:
       0: new           #10                 // class io/dekorate/deps/tekton/pipeline/v1beta1/PipelineSpecFluentImpl$WorkspacesNestedImpl
       3: dup
       4: aload_0
       5: invokespecial #527                // Method io/dekorate/deps/tekton/pipeline/v1beta1/PipelineSpecFluentImpl$WorkspacesNestedImpl."<init>":(Lio/dekorate/deps/tekton/pipeline/v1beta1/PipelineSpecFluentImpl;)V
       8: areturn

  public io.dekorate.deps.tekton.pipeline.v1beta1.PipelineSpecFluent$WorkspacesNested<A> addNewWorkspaceLike(io.dekorate.deps.tekton.pipeline.v1beta1.WorkspacePipelineDeclaration);
    Code:
       0: new           #10                 // class io/dekorate/deps/tekton/pipeline/v1beta1/PipelineSpecFluentImpl$WorkspacesNestedImpl
       3: dup
       4: aload_0
       5: iconst_m1
       6: aload_1
       7: invokespecial #533                // Method io/dekorate/deps/tekton/pipeline/v1beta1/PipelineSpecFluentImpl$WorkspacesNestedImpl."<init>":(Lio/dekorate/deps/tekton/pipeline/v1beta1/PipelineSpecFluentImpl;ILio/dekorate/deps/tekton/pipeline/v1beta1/WorkspacePipelineDeclaration;)V
      10: areturn

  public io.dekorate.deps.tekton.pipeline.v1beta1.PipelineSpecFluent$WorkspacesNested<A> setNewWorkspaceLike(int, io.dekorate.deps.tekton.pipeline.v1beta1.WorkspacePipelineDeclaration);
    Code:
       0: new           #10                 // class io/dekorate/deps/tekton/pipeline/v1beta1/PipelineSpecFluentImpl$WorkspacesNestedImpl
       3: dup
       4: aload_0
       5: iload_1
       6: aload_2
       7: invokespecial #533                // Method io/dekorate/deps/tekton/pipeline/v1beta1/PipelineSpecFluentImpl$WorkspacesNestedImpl."<init>":(Lio/dekorate/deps/tekton/pipeline/v1beta1/PipelineSpecFluentImpl;ILio/dekorate/deps/tekton/pipeline/v1beta1/WorkspacePipelineDeclaration;)V
      10: areturn

  public io.dekorate.deps.tekton.pipeline.v1beta1.PipelineSpecFluent$WorkspacesNested<A> editWorkspace(int);
    Code:
       0: aload_0
       1: getfield      #475                // Field workspaces:Ljava/util/List;
       4: invokeinterface #151,  1          // InterfaceMethod java/util/List.size:()I
       9: iload_1
      10: if_icmpgt     24
      13: new           #280                // class java/lang/RuntimeException
      16: dup
      17: ldc_w         #541                // String Can\'t edit workspaces. Index exceeds size.
      20: invokespecial #283                // Method java/lang/RuntimeException."<init>":(Ljava/lang/String;)V
      23: athrow
      24: aload_0
      25: iload_1
      26: aload_0
      27: iload_1
      28: invokevirtual #543                // Method buildWorkspace:(I)Lio/dekorate/deps/tekton/pipeline/v1beta1/WorkspacePipelineDeclaration;
      31: invokevirtual #545                // Method setNewWorkspaceLike:(ILio/dekorate/deps/tekton/pipeline/v1beta1/WorkspacePipelineDeclaration;)Lio/dekorate/deps/tekton/pipeline/v1beta1/PipelineSpecFluent$WorkspacesNested;
      34: areturn

  public io.dekorate.deps.tekton.pipeline.v1beta1.PipelineSpecFluent$WorkspacesNested<A> editFirstWorkspace();
    Code:
       0: aload_0
       1: getfield      #475                // Field workspaces:Ljava/util/List;
       4: invokeinterface #151,  1          // InterfaceMethod java/util/List.size:()I
       9: ifne          23
      12: new           #280                // class java/lang/RuntimeException
      15: dup
      16: ldc_w         #548                // String Can\'t edit first workspaces. The list is empty.
      19: invokespecial #283                // Method java/lang/RuntimeException."<init>":(Ljava/lang/String;)V
      22: athrow
      23: aload_0
      24: iconst_0
      25: aload_0
      26: iconst_0
      27: invokevirtual #543                // Method buildWorkspace:(I)Lio/dekorate/deps/tekton/pipeline/v1beta1/WorkspacePipelineDeclaration;
      30: invokevirtual #545                // Method setNewWorkspaceLike:(ILio/dekorate/deps/tekton/pipeline/v1beta1/WorkspacePipelineDeclaration;)Lio/dekorate/deps/tekton/pipeline/v1beta1/PipelineSpecFluent$WorkspacesNested;
      33: areturn

  public io.dekorate.deps.tekton.pipeline.v1beta1.PipelineSpecFluent$WorkspacesNested<A> editLastWorkspace();
    Code:
       0: aload_0
       1: getfield      #475                // Field workspaces:Ljava/util/List;
       4: invokeinterface #151,  1          // InterfaceMethod java/util/List.size:()I
       9: iconst_1
      10: isub
      11: istore_1
      12: iload_1
      13: ifge          27
      16: new           #280                // class java/lang/RuntimeException
      19: dup
      20: ldc_w         #551                // String Can\'t edit last workspaces. The list is empty.
      23: invokespecial #283                // Method java/lang/RuntimeException."<init>":(Ljava/lang/String;)V
      26: athrow
      27: aload_0
      28: iload_1
      29: aload_0
      30: iload_1
      31: invokevirtual #543                // Method buildWorkspace:(I)Lio/dekorate/deps/tekton/pipeline/v1beta1/WorkspacePipelineDeclaration;
      34: invokevirtual #545                // Method setNewWorkspaceLike:(ILio/dekorate/deps/tekton/pipeline/v1beta1/WorkspacePipelineDeclaration;)Lio/dekorate/deps/tekton/pipeline/v1beta1/PipelineSpecFluent$WorkspacesNested;
      37: areturn

  public io.dekorate.deps.tekton.pipeline.v1beta1.PipelineSpecFluent$WorkspacesNested<A> editMatchingWorkspace(io.dekorate.deps.kubernetes.api.builder.Predicate<io.dekorate.deps.tekton.pipeline.v1beta1.WorkspacePipelineDeclarationBuilder>);
    Code:
       0: iconst_m1
       1: istore_2
       2: iconst_0
       3: istore_3
       4: iload_3
       5: aload_0
       6: getfield      #475                // Field workspaces:Ljava/util/List;
       9: invokeinterface #151,  1          // InterfaceMethod java/util/List.size:()I
      14: if_icmpge     50
      17: aload_1
      18: aload_0
      19: getfield      #475                // Field workspaces:Ljava/util/List;
      22: iload_3
      23: invokeinterface #234,  2          // InterfaceMethod java/util/List.get:(I)Ljava/lang/Object;
      28: invokeinterface #210,  2          // InterfaceMethod io/dekorate/deps/kubernetes/api/builder/Predicate.apply:(Ljava/lang/Object;)Ljava/lang/Boolean;
      33: invokevirtual #213                // Method java/lang/Boolean.booleanValue:()Z
      36: ifeq          44
      39: iload_3
      40: istore_2
      41: goto          50
      44: iinc          3, 1
      47: goto          4
      50: iload_2
      51: ifge          65
      54: new           #280                // class java/lang/RuntimeException
      57: dup
      58: ldc_w         #556                // String Can\'t edit matching workspaces. No match found.
      61: invokespecial #283                // Method java/lang/RuntimeException."<init>":(Ljava/lang/String;)V
      64: athrow
      65: aload_0
      66: iload_2
      67: aload_0
      68: iload_2
      69: invokevirtual #543                // Method buildWorkspace:(I)Lio/dekorate/deps/tekton/pipeline/v1beta1/WorkspacePipelineDeclaration;
      72: invokevirtual #545                // Method setNewWorkspaceLike:(ILio/dekorate/deps/tekton/pipeline/v1beta1/WorkspacePipelineDeclaration;)Lio/dekorate/deps/tekton/pipeline/v1beta1/PipelineSpecFluent$WorkspacesNested;
      75: areturn

  public boolean equals(java.lang.Object);
    Code:
       0: aload_0
       1: aload_1
       2: if_acmpne     7
       5: iconst_1
       6: ireturn
       7: aload_1
       8: ifnull        22
      11: aload_0
      12: invokevirtual #563                // Method java/lang/Object.getClass:()Ljava/lang/Class;
      15: aload_1
      16: invokevirtual #563                // Method java/lang/Object.getClass:()Ljava/lang/Class;
      19: if_acmpeq     24
      22: iconst_0
      23: ireturn
      24: aload_1
      25: checkcast     #2                  // class io/dekorate/deps/tekton/pipeline/v1beta1/PipelineSpecFluentImpl
      28: astore_2
      29: aload_0
      30: getfield      #91                 // Field description:Ljava/lang/String;
      33: ifnull        53
      36: aload_0
      37: getfield      #91                 // Field description:Ljava/lang/String;
      40: aload_2
      41: getfield      #91                 // Field description:Ljava/lang/String;
      44: invokevirtual #565                // Method java/lang/String.equals:(Ljava/lang/Object;)Z
      47: ifne          62
      50: goto          60
      53: aload_2
      54: getfield      #91                 // Field description:Ljava/lang/String;
      57: ifnull        62
      60: iconst_0
      61: ireturn
      62: aload_0
      63: getfield      #124                // Field params:Ljava/util/List;
      66: ifnull        88
      69: aload_0
      70: getfield      #124                // Field params:Ljava/util/List;
      73: aload_2
      74: getfield      #124                // Field params:Ljava/util/List;
      77: invokeinterface #566,  2          // InterfaceMethod java/util/List.equals:(Ljava/lang/Object;)Z
      82: ifne          97
      85: goto          95
      88: aload_2
      89: getfield      #124                // Field params:Ljava/util/List;
      92: ifnull        97
      95: iconst_0
      96: ireturn
      97: aload_0
      98: getfield      #304                // Field resources:Ljava/util/List;
     101: ifnull        123
     104: aload_0
     105: getfield      #304                // Field resources:Ljava/util/List;
     108: aload_2
     109: getfield      #304                // Field resources:Ljava/util/List;
     112: invokeinterface #566,  2          // InterfaceMethod java/util/List.equals:(Ljava/lang/Object;)Z
     117: ifne          132
     120: goto          130
     123: aload_2
     124: getfield      #304                // Field resources:Ljava/util/List;
     127: ifnull        132
     130: iconst_0
     131: ireturn
     132: aload_0
     133: getfield      #394                // Field tasks:Ljava/util/List;
     136: ifnull        158
     139: aload_0
     140: getfield      #394                // Field tasks:Ljava/util/List;
     143: aload_2
     144: getfield      #394                // Field tasks:Ljava/util/List;
     147: invokeinterface #566,  2          // InterfaceMethod java/util/List.equals:(Ljava/lang/Object;)Z
     152: ifne          167
     155: goto          165
     158: aload_2
     159: getfield      #394                // Field tasks:Ljava/util/List;
     162: ifnull        167
     165: iconst_0
     166: ireturn
     167: aload_0
     168: getfield      #475                // Field workspaces:Ljava/util/List;
     171: ifnull        193
     174: aload_0
     175: getfield      #475                // Field workspaces:Ljava/util/List;
     178: aload_2
     179: getfield      #475                // Field workspaces:Ljava/util/List;
     182: invokeinterface #566,  2          // InterfaceMethod java/util/List.equals:(Ljava/lang/Object;)Z
     187: ifne          202
     190: goto          200
     193: aload_2
     194: getfield      #475                // Field workspaces:Ljava/util/List;
     197: ifnull        202
     200: iconst_0
     201: ireturn
     202: iconst_1
     203: ireturn
}
