Compiled from "SpringProfileDocumentMatcher.java"
abstract class org.springframework.boot.yaml.SpringProfileDocumentMatcher$AbstractProfileDocumentMatcher implements org.springframework.beans.factory.config.YamlProcessor$DocumentMatcher {
  private org.springframework.boot.yaml.SpringProfileDocumentMatcher$AbstractProfileDocumentMatcher();
    Code:
       0: aload_0
       1: invokespecial #3                  // Method java/lang/Object."<init>":()V
       4: return

  public final org.springframework.beans.factory.config.YamlProcessor$MatchStatus matches(java.util.Properties);
    Code:
       0: aload_1
       1: ldc           #4                  // String spring.profiles
       3: invokevirtual #5                  // Method java/util/Properties.containsKey:(Ljava/lang/Object;)Z
       6: ifne          13
       9: getstatic     #6                  // Field org/springframework/beans/factory/config/YamlProcessor$MatchStatus.ABSTAIN:Lorg/springframework/beans/factory/config/YamlProcessor$MatchStatus;
      12: areturn
      13: aload_1
      14: ldc           #4                  // String spring.profiles
      16: invokevirtual #7                  // Method java/util/Properties.getProperty:(Ljava/lang/String;)Ljava/lang/String;
      19: invokestatic  #8                  // Method org/springframework/util/StringUtils.commaDelimitedListToSet:(Ljava/lang/String;)Ljava/util/Set;
      22: astore_2
      23: aload_0
      24: aload_2
      25: invokevirtual #9                  // Method matches:(Ljava/util/Set;)Lorg/springframework/beans/factory/config/YamlProcessor$MatchStatus;
      28: areturn

  protected abstract org.springframework.beans.factory.config.YamlProcessor$MatchStatus matches(java.util.Set<java.lang.String>);

  org.springframework.boot.yaml.SpringProfileDocumentMatcher$AbstractProfileDocumentMatcher(org.springframework.boot.yaml.SpringProfileDocumentMatcher$1);
    Code:
       0: aload_0
       1: invokespecial #2                  // Method "<init>":()V
       4: return
}
