Compiled from "EsTokenIdentifier.java"
public class org.elasticsearch.hadoop.mr.security.EsTokenIdentifier extends org.apache.hadoop.security.token.delegation.AbstractDelegationTokenIdentifier {
  public static final org.apache.hadoop.io.Text KIND_NAME;

  public org.elasticsearch.hadoop.mr.security.EsTokenIdentifier();
    Code:
       0: aload_0
       1: invokespecial #1                  // Method org/apache/hadoop/security/token/delegation/AbstractDelegationTokenIdentifier."<init>":()V
       4: return

  public static org.apache.hadoop.security.token.Token<org.elasticsearch.hadoop.mr.security.EsTokenIdentifier> createTokenFrom(org.elasticsearch.hadoop.security.EsToken);
    Code:
       0: new           #7                  // class org/elasticsearch/hadoop/mr/security/EsTokenIdentifier
       3: dup
       4: invokespecial #9                  // Method "<init>":()V
       7: astore_1
       8: new           #10                 // class java/io/ByteArrayOutputStream
      11: dup
      12: invokespecial #12                 // Method java/io/ByteArrayOutputStream."<init>":()V
      15: astore_2
      16: aload_0
      17: new           #13                 // class java/io/DataOutputStream
      20: dup
      21: aload_2
      22: invokespecial #15                 // Method java/io/DataOutputStream."<init>":(Ljava/io/OutputStream;)V
      25: invokevirtual #18                 // Method org/elasticsearch/hadoop/security/EsToken.writeOut:(Ljava/io/DataOutput;)V
      28: goto          43
      31: astore_3
      32: new           #26                 // class org/elasticsearch/hadoop/EsHadoopException
      35: dup
      36: ldc           #28                 // String Could not serialize token information
      38: aload_3
      39: invokespecial #30                 // Method org/elasticsearch/hadoop/EsHadoopException."<init>":(Ljava/lang/String;Ljava/lang/Throwable;)V
      42: athrow
      43: aload_1
      44: invokevirtual #33                 // Method getBytes:()[B
      47: astore_3
      48: aload_2
      49: invokevirtual #37                 // Method java/io/ByteArrayOutputStream.toByteArray:()[B
      52: astore        4
      54: aload_1
      55: invokevirtual #40                 // Method getKind:()Lorg/apache/hadoop/io/Text;
      58: astore        5
      60: new           #44                 // class org/apache/hadoop/io/Text
      63: dup
      64: aload_0
      65: invokevirtual #46                 // Method org/elasticsearch/hadoop/security/EsToken.getClusterName:()Ljava/lang/String;
      68: invokespecial #50                 // Method org/apache/hadoop/io/Text."<init>":(Ljava/lang/String;)V
      71: astore        6
      73: new           #53                 // class org/apache/hadoop/security/token/Token
      76: dup
      77: aload_3
      78: aload         4
      80: aload         5
      82: aload         6
      84: invokespecial #55                 // Method org/apache/hadoop/security/token/Token."<init>":([B[BLorg/apache/hadoop/io/Text;Lorg/apache/hadoop/io/Text;)V
      87: areturn
    Exception table:
       from    to  target type
          16    28    31   Class java/io/IOException

  public org.apache.hadoop.io.Text getKind();
    Code:
       0: getstatic     #58                 // Field KIND_NAME:Lorg/apache/hadoop/io/Text;
       3: areturn

  static {};
    Code:
       0: new           #44                 // class org/apache/hadoop/io/Text
       3: dup
       4: ldc           #62                 // String ELASTICSEARCH_AUTH_TOKEN
       6: invokespecial #50                 // Method org/apache/hadoop/io/Text."<init>":(Ljava/lang/String;)V
       9: putstatic     #58                 // Field KIND_NAME:Lorg/apache/hadoop/io/Text;
      12: return
}
