Compiled from "ResolvedType.java"
public abstract class software.amazon.awssdk.thirdparty.jackson.core.type.ResolvedType {
  public software.amazon.awssdk.thirdparty.jackson.core.type.ResolvedType();
    Code:
       0: aload_0
       1: invokespecial #9                  // Method java/lang/Object."<init>":()V
       4: return

  public abstract java.lang.Class<?> getRawClass();

  public abstract boolean hasRawClass(java.lang.Class<?>);

  public abstract boolean isAbstract();

  public abstract boolean isConcrete();

  public abstract boolean isThrowable();

  public abstract boolean isArrayType();

  public abstract boolean isEnumType();

  public abstract boolean isInterface();

  public abstract boolean isPrimitive();

  public abstract boolean isFinal();

  public abstract boolean isContainerType();

  public abstract boolean isCollectionLikeType();

  public boolean isReferenceType();
    Code:
       0: aload_0
       1: invokevirtual #31                 // Method getReferencedType:()Lsoftware/amazon/awssdk/thirdparty/jackson/core/type/ResolvedType;
       4: ifnull        11
       7: iconst_1
       8: goto          12
      11: iconst_0
      12: ireturn

  public abstract boolean isMapLikeType();

  public abstract boolean hasGenericTypes();

  public java.lang.Class<?> getParameterSource();
    Code:
       0: aconst_null
       1: areturn

  public abstract software.amazon.awssdk.thirdparty.jackson.core.type.ResolvedType getKeyType();

  public abstract software.amazon.awssdk.thirdparty.jackson.core.type.ResolvedType getContentType();

  public abstract software.amazon.awssdk.thirdparty.jackson.core.type.ResolvedType getReferencedType();

  public abstract int containedTypeCount();

  public abstract software.amazon.awssdk.thirdparty.jackson.core.type.ResolvedType containedType(int);

  public abstract java.lang.String containedTypeName(int);

  public abstract java.lang.String toCanonical();
}
