Compiled from "AbstractParameterValidator.java"
public abstract class org.jboss.as.controller.operations.validation.AbstractParameterValidator implements org.jboss.as.controller.operations.validation.ParameterValidator {
  public org.jboss.as.controller.operations.validation.AbstractParameterValidator();
    Code:
       0: aload_0
       1: invokespecial #1                  // Method java/lang/Object."<init>":()V
       4: return

  public void validateResolvedParameter(java.lang.String, org.jboss.dmr.ModelNode) throws org.jboss.as.controller.OperationFailedException;
    Code:
       0: aload_0
       1: aload_1
       2: aload_2
       3: invokevirtual #2                  // Method validateParameter:(Ljava/lang/String;Lorg/jboss/dmr/ModelNode;)V
       6: return
}
