Compiled from "ArraySchema.java"
public abstract class com.fasterxml.jackson.module.jsonSchema.types.ArraySchema$Items {
  public com.fasterxml.jackson.module.jsonSchema.types.ArraySchema$Items();
    Code:
       0: aload_0
       1: invokespecial #1                  // Method java/lang/Object."<init>":()V
       4: return

  public boolean isSingleItems();
    Code:
       0: iconst_0
       1: ireturn

  public boolean isArrayItems();
    Code:
       0: iconst_0
       1: ireturn

  public com.fasterxml.jackson.module.jsonSchema.types.ArraySchema$SingleItems asSingleItems();
    Code:
       0: aconst_null
       1: areturn

  public com.fasterxml.jackson.module.jsonSchema.types.ArraySchema$ArrayItems asArrayItems();
    Code:
       0: aconst_null
       1: areturn
}
