Compiled from "DifferenceEvaluators.java"
public final class org.xmlunit.diff.DifferenceEvaluators {
  private static final java.lang.Short CDATA;

  private static final java.lang.Short TEXT;

  public static final org.xmlunit.diff.DifferenceEvaluator Accept;

  public static final org.xmlunit.diff.DifferenceEvaluator Default;

  private org.xmlunit.diff.DifferenceEvaluators();
    Code:
       0: aload_0
       1: invokespecial #5                  // Method java/lang/Object."<init>":()V
       4: return

  public static org.xmlunit.diff.DifferenceEvaluator first(org.xmlunit.diff.DifferenceEvaluator...);
    Code:
       0: new           #6                  // class org/xmlunit/diff/DifferenceEvaluators$3
       3: dup
       4: aload_0
       5: invokespecial #7                  // Method org/xmlunit/diff/DifferenceEvaluators$3."<init>":([Lorg/xmlunit/diff/DifferenceEvaluator;)V
       8: areturn

  public static org.xmlunit.diff.DifferenceEvaluator chain(org.xmlunit.diff.DifferenceEvaluator...);
    Code:
       0: new           #8                  // class org/xmlunit/diff/DifferenceEvaluators$4
       3: dup
       4: aload_0
       5: invokespecial #9                  // Method org/xmlunit/diff/DifferenceEvaluators$4."<init>":([Lorg/xmlunit/diff/DifferenceEvaluator;)V
       8: areturn

  public static org.xmlunit.diff.DifferenceEvaluator downgradeDifferencesToEqual(org.xmlunit.diff.ComparisonType...);
    Code:
       0: getstatic     #10                 // Field org/xmlunit/diff/ComparisonResult.EQUAL:Lorg/xmlunit/diff/ComparisonResult;
       3: aload_0
       4: invokestatic  #11                 // Method recordDifferencesAs:(Lorg/xmlunit/diff/ComparisonResult;[Lorg/xmlunit/diff/ComparisonType;)Lorg/xmlunit/diff/DifferenceEvaluator;
       7: areturn

  public static org.xmlunit.diff.DifferenceEvaluator downgradeDifferencesToSimilar(org.xmlunit.diff.ComparisonType...);
    Code:
       0: getstatic     #12                 // Field org/xmlunit/diff/ComparisonResult.SIMILAR:Lorg/xmlunit/diff/ComparisonResult;
       3: aload_0
       4: invokestatic  #11                 // Method recordDifferencesAs:(Lorg/xmlunit/diff/ComparisonResult;[Lorg/xmlunit/diff/ComparisonType;)Lorg/xmlunit/diff/DifferenceEvaluator;
       7: areturn

  public static org.xmlunit.diff.DifferenceEvaluator upgradeDifferencesToDifferent(org.xmlunit.diff.ComparisonType...);
    Code:
       0: getstatic     #13                 // Field org/xmlunit/diff/ComparisonResult.DIFFERENT:Lorg/xmlunit/diff/ComparisonResult;
       3: aload_0
       4: invokestatic  #11                 // Method recordDifferencesAs:(Lorg/xmlunit/diff/ComparisonResult;[Lorg/xmlunit/diff/ComparisonType;)Lorg/xmlunit/diff/DifferenceEvaluator;
       7: areturn

  public static org.xmlunit.diff.DifferenceEvaluator ignorePrologDifferences();
    Code:
       0: new           #14                 // class org/xmlunit/diff/DifferenceEvaluators$5
       3: dup
       4: invokespecial #15                 // Method org/xmlunit/diff/DifferenceEvaluators$5."<init>":()V
       7: areturn

  public static org.xmlunit.diff.DifferenceEvaluator ignorePrologDifferencesExceptDoctype();
    Code:
       0: new           #16                 // class org/xmlunit/diff/DifferenceEvaluators$6
       3: dup
       4: invokespecial #17                 // Method org/xmlunit/diff/DifferenceEvaluators$6."<init>":()V
       7: areturn

  private static org.xmlunit.diff.DifferenceEvaluator recordDifferencesAs(org.xmlunit.diff.ComparisonResult, org.xmlunit.diff.ComparisonType...);
    Code:
       0: aload_1
       1: invokestatic  #18                 // Method java/util/Arrays.asList:([Ljava/lang/Object;)Ljava/util/List;
       4: invokestatic  #19                 // Method java/util/EnumSet.copyOf:(Ljava/util/Collection;)Ljava/util/EnumSet;
       7: astore_2
       8: new           #20                 // class org/xmlunit/diff/DifferenceEvaluators$7
      11: dup
      12: aload_2
      13: aload_0
      14: invokespecial #21                 // Method org/xmlunit/diff/DifferenceEvaluators$7."<init>":(Ljava/util/EnumSet;Lorg/xmlunit/diff/ComparisonResult;)V
      17: areturn

  private static boolean belongsToProlog(org.xmlunit.diff.Comparison, boolean);
    Code:
       0: aload_0
       1: invokevirtual #22                 // Method org/xmlunit/diff/Comparison.getType:()Lorg/xmlunit/diff/ComparisonType;
       4: invokevirtual #23                 // Method org/xmlunit/diff/ComparisonType.isDoctypeComparison:()Z
       7: ifeq          12
      10: iload_1
      11: ireturn
      12: aload_0
      13: invokevirtual #24                 // Method org/xmlunit/diff/Comparison.getControlDetails:()Lorg/xmlunit/diff/Comparison$Detail;
      16: invokevirtual #25                 // Method org/xmlunit/diff/Comparison$Detail.getTarget:()Lorg/w3c/dom/Node;
      19: iload_1
      20: invokestatic  #26                 // Method belongsToProlog:(Lorg/w3c/dom/Node;Z)Z
      23: ifne          40
      26: aload_0
      27: invokevirtual #27                 // Method org/xmlunit/diff/Comparison.getTestDetails:()Lorg/xmlunit/diff/Comparison$Detail;
      30: invokevirtual #25                 // Method org/xmlunit/diff/Comparison$Detail.getTarget:()Lorg/w3c/dom/Node;
      33: iload_1
      34: invokestatic  #26                 // Method belongsToProlog:(Lorg/w3c/dom/Node;Z)Z
      37: ifeq          44
      40: iconst_1
      41: goto          45
      44: iconst_0
      45: ireturn

  private static boolean belongsToProlog(org.w3c.dom.Node, boolean);
    Code:
       0: aload_0
       1: ifnull        11
       4: aload_0
       5: instanceof    #28                 // class org/w3c/dom/Element
       8: ifeq          13
      11: iconst_0
      12: ireturn
      13: iload_1
      14: ifne          26
      17: aload_0
      18: instanceof    #29                 // class org/w3c/dom/DocumentType
      21: ifeq          26
      24: iconst_0
      25: ireturn
      26: aload_0
      27: instanceof    #30                 // class org/w3c/dom/Document
      30: ifeq          35
      33: iconst_1
      34: ireturn
      35: aload_0
      36: invokeinterface #31,  1           // InterfaceMethod org/w3c/dom/Node.getParentNode:()Lorg/w3c/dom/Node;
      41: iload_1
      42: invokestatic  #26                 // Method belongsToProlog:(Lorg/w3c/dom/Node;Z)Z
      45: ireturn

  private static boolean isSequenceOfRootElement(org.xmlunit.diff.Comparison);
    Code:
       0: aload_0
       1: invokevirtual #22                 // Method org/xmlunit/diff/Comparison.getType:()Lorg/xmlunit/diff/ComparisonType;
       4: getstatic     #32                 // Field org/xmlunit/diff/ComparisonType.CHILD_NODELIST_SEQUENCE:Lorg/xmlunit/diff/ComparisonType;
       7: if_acmpne     45
      10: aload_0
      11: invokevirtual #24                 // Method org/xmlunit/diff/Comparison.getControlDetails:()Lorg/xmlunit/diff/Comparison$Detail;
      14: invokevirtual #25                 // Method org/xmlunit/diff/Comparison$Detail.getTarget:()Lorg/w3c/dom/Node;
      17: instanceof    #28                 // class org/w3c/dom/Element
      20: ifeq          45
      23: aload_0
      24: invokevirtual #24                 // Method org/xmlunit/diff/Comparison.getControlDetails:()Lorg/xmlunit/diff/Comparison$Detail;
      27: invokevirtual #25                 // Method org/xmlunit/diff/Comparison$Detail.getTarget:()Lorg/w3c/dom/Node;
      30: invokeinterface #31,  1           // InterfaceMethod org/w3c/dom/Node.getParentNode:()Lorg/w3c/dom/Node;
      35: instanceof    #30                 // class org/w3c/dom/Document
      38: ifeq          45
      41: iconst_1
      42: goto          46
      45: iconst_0
      46: ireturn

  static java.lang.Short access$000();
    Code:
       0: getstatic     #4                  // Field TEXT:Ljava/lang/Short;
       3: areturn

  static java.lang.Short access$100();
    Code:
       0: getstatic     #3                  // Field CDATA:Ljava/lang/Short;
       3: areturn

  static boolean access$200(org.xmlunit.diff.Comparison, boolean);
    Code:
       0: aload_0
       1: iload_1
       2: invokestatic  #2                  // Method belongsToProlog:(Lorg/xmlunit/diff/Comparison;Z)Z
       5: ireturn

  static boolean access$300(org.xmlunit.diff.Comparison);
    Code:
       0: aload_0
       1: invokestatic  #1                  // Method isSequenceOfRootElement:(Lorg/xmlunit/diff/Comparison;)Z
       4: ireturn

  static {};
    Code:
       0: iconst_4
       1: invokestatic  #34                 // Method java/lang/Short.valueOf:(S)Ljava/lang/Short;
       4: putstatic     #3                  // Field CDATA:Ljava/lang/Short;
       7: iconst_3
       8: invokestatic  #34                 // Method java/lang/Short.valueOf:(S)Ljava/lang/Short;
      11: putstatic     #4                  // Field TEXT:Ljava/lang/Short;
      14: new           #35                 // class org/xmlunit/diff/DifferenceEvaluators$1
      17: dup
      18: invokespecial #36                 // Method org/xmlunit/diff/DifferenceEvaluators$1."<init>":()V
      21: putstatic     #37                 // Field Accept:Lorg/xmlunit/diff/DifferenceEvaluator;
      24: new           #38                 // class org/xmlunit/diff/DifferenceEvaluators$2
      27: dup
      28: invokespecial #39                 // Method org/xmlunit/diff/DifferenceEvaluators$2."<init>":()V
      31: putstatic     #40                 // Field Default:Lorg/xmlunit/diff/DifferenceEvaluator;
      34: return
}
