Compiled from "DifferenceEvaluators.java"
final class org.xmlunit.diff.DifferenceEvaluators$7 implements org.xmlunit.diff.DifferenceEvaluator {
  final java.util.EnumSet val$comparisonTypes;

  final org.xmlunit.diff.ComparisonResult val$outcome;

  org.xmlunit.diff.DifferenceEvaluators$7(java.util.EnumSet, org.xmlunit.diff.ComparisonResult);
    Code:
       0: aload_0
       1: aload_1
       2: putfield      #1                  // Field val$comparisonTypes:Ljava/util/EnumSet;
       5: aload_0
       6: aload_2
       7: putfield      #2                  // Field val$outcome:Lorg/xmlunit/diff/ComparisonResult;
      10: aload_0
      11: invokespecial #3                  // Method java/lang/Object."<init>":()V
      14: return

  public org.xmlunit.diff.ComparisonResult evaluate(org.xmlunit.diff.Comparison, org.xmlunit.diff.ComparisonResult);
    Code:
       0: aload_2
       1: getstatic     #4                  // Field org/xmlunit/diff/ComparisonResult.EQUAL:Lorg/xmlunit/diff/ComparisonResult;
       4: if_acmpeq     28
       7: aload_0
       8: getfield      #1                  // Field val$comparisonTypes:Ljava/util/EnumSet;
      11: aload_1
      12: invokevirtual #5                  // Method org/xmlunit/diff/Comparison.getType:()Lorg/xmlunit/diff/ComparisonType;
      15: invokevirtual #6                  // Method java/util/EnumSet.contains:(Ljava/lang/Object;)Z
      18: ifeq          28
      21: aload_0
      22: getfield      #2                  // Field val$outcome:Lorg/xmlunit/diff/ComparisonResult;
      25: goto          29
      28: aload_2
      29: areturn
}
