public class org.bouncycastle.cert.ocsp.OCSPResp {
  public static final int SUCCESSFUL;

  public static final int MALFORMED_REQUEST;

  public static final int INTERNAL_ERROR;

  public static final int TRY_LATER;

  public static final int SIG_REQUIRED;

  public static final int UNAUTHORIZED;

  private org.bouncycastle.asn1.ocsp.OCSPResponse resp;

  public org.bouncycastle.cert.ocsp.OCSPResp(org.bouncycastle.asn1.ocsp.OCSPResponse);
    Code:
       0: aload_0
       1: invokespecial #147                // Method java/lang/Object."<init>":()V
       4: aload_0
       5: aload_1
       6: putfield      #143                // Field resp:Lorg/bouncycastle/asn1/ocsp/OCSPResponse;
       9: return

  public org.bouncycastle.cert.ocsp.OCSPResp(byte[]) throws java.io.IOException;
    Code:
       0: aload_0
       1: new           #68                 // class java/io/ByteArrayInputStream
       4: dup
       5: aload_1
       6: invokespecial #144                // Method java/io/ByteArrayInputStream."<init>":([B)V
       9: invokespecial #173                // Method "<init>":(Ljava/io/InputStream;)V
      12: return

  public org.bouncycastle.cert.ocsp.OCSPResp(java.io.InputStream) throws java.io.IOException;
    Code:
       0: aload_0
       1: new           #77                 // class org/bouncycastle/asn1/ASN1InputStream
       4: dup
       5: aload_1
       6: invokespecial #154                // Method org/bouncycastle/asn1/ASN1InputStream."<init>":(Ljava/io/InputStream;)V
       9: invokespecial #174                // Method "<init>":(Lorg/bouncycastle/asn1/ASN1InputStream;)V
      12: return

  private org.bouncycastle.cert.ocsp.OCSPResp(org.bouncycastle.asn1.ASN1InputStream) throws java.io.IOException;
    Code:
       0: aload_0
       1: invokespecial #147                // Method java/lang/Object."<init>":()V
       4: aload_0
       5: aload_1
       6: invokevirtual #155                // Method org/bouncycastle/asn1/ASN1InputStream.readObject:()Lorg/bouncycastle/asn1/ASN1Primitive;
       9: invokestatic  #165                // Method org/bouncycastle/asn1/ocsp/OCSPResponse.getInstance:(Ljava/lang/Object;)Lorg/bouncycastle/asn1/ocsp/OCSPResponse;
      12: putfield      #143                // Field resp:Lorg/bouncycastle/asn1/ocsp/OCSPResponse;
      15: goto          114
      18: astore_2
      19: new           #86                 // class org/bouncycastle/cert/CertIOException
      22: dup
      23: new           #74                 // class java/lang/StringBuilder
      26: dup
      27: invokespecial #148                // Method java/lang/StringBuilder."<init>":()V
      30: ldc           #1                  // String malformed response:
      32: invokevirtual #151                // Method java/lang/StringBuilder.append:(Ljava/lang/String;)Ljava/lang/StringBuilder;
      35: aload_2
      36: invokevirtual #146                // Method java/lang/IllegalArgumentException.getMessage:()Ljava/lang/String;
      39: invokevirtual #151                // Method java/lang/StringBuilder.append:(Ljava/lang/String;)Ljava/lang/StringBuilder;
      42: invokevirtual #149                // Method java/lang/StringBuilder.toString:()Ljava/lang/String;
      45: aload_2
      46: invokespecial #170                // Method org/bouncycastle/cert/CertIOException."<init>":(Ljava/lang/String;Ljava/lang/Throwable;)V
      49: athrow
      50: astore_2
      51: new           #86                 // class org/bouncycastle/cert/CertIOException
      54: dup
      55: new           #74                 // class java/lang/StringBuilder
      58: dup
      59: invokespecial #148                // Method java/lang/StringBuilder."<init>":()V
      62: ldc           #1                  // String malformed response:
      64: invokevirtual #151                // Method java/lang/StringBuilder.append:(Ljava/lang/String;)Ljava/lang/StringBuilder;
      67: aload_2
      68: invokevirtual #145                // Method java/lang/ClassCastException.getMessage:()Ljava/lang/String;
      71: invokevirtual #151                // Method java/lang/StringBuilder.append:(Ljava/lang/String;)Ljava/lang/StringBuilder;
      74: invokevirtual #149                // Method java/lang/StringBuilder.toString:()Ljava/lang/String;
      77: aload_2
      78: invokespecial #170                // Method org/bouncycastle/cert/CertIOException."<init>":(Ljava/lang/String;Ljava/lang/Throwable;)V
      81: athrow
      82: astore_2
      83: new           #86                 // class org/bouncycastle/cert/CertIOException
      86: dup
      87: new           #74                 // class java/lang/StringBuilder
      90: dup
      91: invokespecial #148                // Method java/lang/StringBuilder."<init>":()V
      94: ldc           #1                  // String malformed response:
      96: invokevirtual #151                // Method java/lang/StringBuilder.append:(Ljava/lang/String;)Ljava/lang/StringBuilder;
      99: aload_2
     100: invokevirtual #153                // Method org/bouncycastle/asn1/ASN1Exception.getMessage:()Ljava/lang/String;
     103: invokevirtual #151                // Method java/lang/StringBuilder.append:(Ljava/lang/String;)Ljava/lang/StringBuilder;
     106: invokevirtual #149                // Method java/lang/StringBuilder.toString:()Ljava/lang/String;
     109: aload_2
     110: invokespecial #170                // Method org/bouncycastle/cert/CertIOException."<init>":(Ljava/lang/String;Ljava/lang/Throwable;)V
     113: athrow
     114: aload_0
     115: getfield      #143                // Field resp:Lorg/bouncycastle/asn1/ocsp/OCSPResponse;
     118: ifnonnull     131
     121: new           #86                 // class org/bouncycastle/cert/CertIOException
     124: dup
     125: ldc           #2                  // String malformed response: no response data found
     127: invokespecial #169                // Method org/bouncycastle/cert/CertIOException."<init>":(Ljava/lang/String;)V
     130: athrow
     131: return
    Exception table:
       from    to  target type
           4    15    18   Class java/lang/IllegalArgumentException
           4    15    50   Class java/lang/ClassCastException
           4    15    82   Class org/bouncycastle/asn1/ASN1Exception

  public int getStatus();
    Code:
       0: aload_0
       1: getfield      #143                // Field resp:Lorg/bouncycastle/asn1/ocsp/OCSPResponse;
       4: invokevirtual #163                // Method org/bouncycastle/asn1/ocsp/OCSPResponse.getResponseStatus:()Lorg/bouncycastle/asn1/ocsp/OCSPResponseStatus;
       7: invokevirtual #166                // Method org/bouncycastle/asn1/ocsp/OCSPResponseStatus.getValue:()Ljava/math/BigInteger;
      10: invokevirtual #152                // Method java/math/BigInteger.intValue:()I
      13: ireturn

  public java.lang.Object getResponseObject() throws org.bouncycastle.cert.ocsp.OCSPException;
    Code:
       0: aload_0
       1: getfield      #143                // Field resp:Lorg/bouncycastle/asn1/ocsp/OCSPResponse;
       4: invokevirtual #164                // Method org/bouncycastle/asn1/ocsp/OCSPResponse.getResponseBytes:()Lorg/bouncycastle/asn1/ocsp/ResponseBytes;
       7: astore_1
       8: aload_1
       9: ifnonnull     14
      12: aconst_null
      13: areturn
      14: aload_1
      15: invokevirtual #167                // Method org/bouncycastle/asn1/ocsp/ResponseBytes.getResponseType:()Lorg/bouncycastle/asn1/ASN1ObjectIdentifier;
      18: getstatic     #142                // Field org/bouncycastle/asn1/ocsp/OCSPObjectIdentifiers.id_pkix_ocsp_basic:Lorg/bouncycastle/asn1/ASN1ObjectIdentifier;
      21: invokevirtual #156                // Method org/bouncycastle/asn1/ASN1ObjectIdentifier.equals:(Lorg/bouncycastle/asn1/ASN1Primitive;)Z
      24: ifeq          79
      27: aload_1
      28: invokevirtual #168                // Method org/bouncycastle/asn1/ocsp/ResponseBytes.getResponse:()Lorg/bouncycastle/asn1/ASN1OctetString;
      31: invokevirtual #157                // Method org/bouncycastle/asn1/ASN1OctetString.getOctets:()[B
      34: invokestatic  #158                // Method org/bouncycastle/asn1/ASN1Primitive.fromByteArray:([B)Lorg/bouncycastle/asn1/ASN1Primitive;
      37: astore_2
      38: new           #87                 // class org/bouncycastle/cert/ocsp/BasicOCSPResp
      41: dup
      42: aload_2
      43: invokestatic  #159                // Method org/bouncycastle/asn1/ocsp/BasicOCSPResponse.getInstance:(Ljava/lang/Object;)Lorg/bouncycastle/asn1/ocsp/BasicOCSPResponse;
      46: invokespecial #171                // Method org/bouncycastle/cert/ocsp/BasicOCSPResp."<init>":(Lorg/bouncycastle/asn1/ocsp/BasicOCSPResponse;)V
      49: areturn
      50: astore_2
      51: new           #88                 // class org/bouncycastle/cert/ocsp/OCSPException
      54: dup
      55: new           #74                 // class java/lang/StringBuilder
      58: dup
      59: invokespecial #148                // Method java/lang/StringBuilder."<init>":()V
      62: ldc           #3                  // String problem decoding object:
      64: invokevirtual #151                // Method java/lang/StringBuilder.append:(Ljava/lang/String;)Ljava/lang/StringBuilder;
      67: aload_2
      68: invokevirtual #150                // Method java/lang/StringBuilder.append:(Ljava/lang/Object;)Ljava/lang/StringBuilder;
      71: invokevirtual #149                // Method java/lang/StringBuilder.toString:()Ljava/lang/String;
      74: aload_2
      75: invokespecial #172                // Method org/bouncycastle/cert/ocsp/OCSPException."<init>":(Ljava/lang/String;Ljava/lang/Throwable;)V
      78: athrow
      79: aload_1
      80: invokevirtual #168                // Method org/bouncycastle/asn1/ocsp/ResponseBytes.getResponse:()Lorg/bouncycastle/asn1/ASN1OctetString;
      83: areturn
    Exception table:
       from    to  target type
          27    49    50   Class java/lang/Exception

  public byte[] getEncoded() throws java.io.IOException;
    Code:
       0: aload_0
       1: getfield      #143                // Field resp:Lorg/bouncycastle/asn1/ocsp/OCSPResponse;
       4: invokevirtual #161                // Method org/bouncycastle/asn1/ocsp/OCSPResponse.getEncoded:()[B
       7: areturn

  public boolean equals(java.lang.Object);
    Code:
       0: aload_1
       1: aload_0
       2: if_acmpne     7
       5: iconst_1
       6: ireturn
       7: aload_1
       8: instanceof    #89                 // class org/bouncycastle/cert/ocsp/OCSPResp
      11: ifne          16
      14: iconst_0
      15: ireturn
      16: aload_1
      17: checkcast     #89                 // class org/bouncycastle/cert/ocsp/OCSPResp
      20: astore_2
      21: aload_0
      22: getfield      #143                // Field resp:Lorg/bouncycastle/asn1/ocsp/OCSPResponse;
      25: aload_2
      26: getfield      #143                // Field resp:Lorg/bouncycastle/asn1/ocsp/OCSPResponse;
      29: invokevirtual #162                // Method org/bouncycastle/asn1/ocsp/OCSPResponse.equals:(Ljava/lang/Object;)Z
      32: ireturn

  public int hashCode();
    Code:
       0: aload_0
       1: getfield      #143                // Field resp:Lorg/bouncycastle/asn1/ocsp/OCSPResponse;
       4: invokevirtual #160                // Method org/bouncycastle/asn1/ocsp/OCSPResponse.hashCode:()I
       7: ireturn

  public org.bouncycastle.asn1.ocsp.OCSPResponse toASN1Structure();
    Code:
       0: aload_0
       1: getfield      #143                // Field resp:Lorg/bouncycastle/asn1/ocsp/OCSPResponse;
       4: areturn
}
