Compiled from "DropwizardFunctionTimer.java"
class io.micrometer.core.instrument.dropwizard.DropwizardFunctionTimer$1 extends com.codahale.metrics.Timer {
  final io.micrometer.core.instrument.dropwizard.DropwizardFunctionTimer this$0;

  io.micrometer.core.instrument.dropwizard.DropwizardFunctionTimer$1(io.micrometer.core.instrument.dropwizard.DropwizardFunctionTimer, com.codahale.metrics.Reservoir, com.codahale.metrics.Clock);
    Code:
       0: aload_0
       1: aload_1
       2: putfield      #22                 // Field this$0:Lio/micrometer/core/instrument/dropwizard/DropwizardFunctionTimer;
       5: aload_0
       6: aload_2
       7: aload_3
       8: invokespecial #25                 // Method com/codahale/metrics/Timer."<init>":(Lcom/codahale/metrics/Reservoir;Lcom/codahale/metrics/Clock;)V
      11: return

  public double getFifteenMinuteRate();
    Code:
       0: aload_0
       1: getfield      #22                 // Field this$0:Lio/micrometer/core/instrument/dropwizard/DropwizardFunctionTimer;
       4: invokevirtual #36                 // Method io/micrometer/core/instrument/dropwizard/DropwizardFunctionTimer.count:()D
       7: pop2
       8: aload_0
       9: getfield      #22                 // Field this$0:Lio/micrometer/core/instrument/dropwizard/DropwizardFunctionTimer;
      12: invokestatic  #40                 // Method io/micrometer/core/instrument/dropwizard/DropwizardFunctionTimer.access$000:(Lio/micrometer/core/instrument/dropwizard/DropwizardFunctionTimer;)Lio/micrometer/core/instrument/dropwizard/DropwizardRate;
      15: invokevirtual #44                 // Method io/micrometer/core/instrument/dropwizard/DropwizardRate.getFifteenMinuteRate:()D
      18: dreturn

  public double getFiveMinuteRate();
    Code:
       0: aload_0
       1: getfield      #22                 // Field this$0:Lio/micrometer/core/instrument/dropwizard/DropwizardFunctionTimer;
       4: invokevirtual #36                 // Method io/micrometer/core/instrument/dropwizard/DropwizardFunctionTimer.count:()D
       7: pop2
       8: aload_0
       9: getfield      #22                 // Field this$0:Lio/micrometer/core/instrument/dropwizard/DropwizardFunctionTimer;
      12: invokestatic  #40                 // Method io/micrometer/core/instrument/dropwizard/DropwizardFunctionTimer.access$000:(Lio/micrometer/core/instrument/dropwizard/DropwizardFunctionTimer;)Lio/micrometer/core/instrument/dropwizard/DropwizardRate;
      15: invokevirtual #47                 // Method io/micrometer/core/instrument/dropwizard/DropwizardRate.getFiveMinuteRate:()D
      18: dreturn

  public double getOneMinuteRate();
    Code:
       0: aload_0
       1: getfield      #22                 // Field this$0:Lio/micrometer/core/instrument/dropwizard/DropwizardFunctionTimer;
       4: invokevirtual #36                 // Method io/micrometer/core/instrument/dropwizard/DropwizardFunctionTimer.count:()D
       7: pop2
       8: aload_0
       9: getfield      #22                 // Field this$0:Lio/micrometer/core/instrument/dropwizard/DropwizardFunctionTimer;
      12: invokestatic  #40                 // Method io/micrometer/core/instrument/dropwizard/DropwizardFunctionTimer.access$000:(Lio/micrometer/core/instrument/dropwizard/DropwizardFunctionTimer;)Lio/micrometer/core/instrument/dropwizard/DropwizardRate;
      15: invokevirtual #50                 // Method io/micrometer/core/instrument/dropwizard/DropwizardRate.getOneMinuteRate:()D
      18: dreturn

  public long getCount();
    Code:
       0: aload_0
       1: getfield      #22                 // Field this$0:Lio/micrometer/core/instrument/dropwizard/DropwizardFunctionTimer;
       4: invokevirtual #36                 // Method io/micrometer/core/instrument/dropwizard/DropwizardFunctionTimer.count:()D
       7: d2l
       8: lreturn

  public com.codahale.metrics.Snapshot getSnapshot();
    Code:
       0: new           #12                 // class io/micrometer/core/instrument/dropwizard/DropwizardFunctionTimer$1$1
       3: dup
       4: aload_0
       5: invokespecial #57                 // Method io/micrometer/core/instrument/dropwizard/DropwizardFunctionTimer$1$1."<init>":(Lio/micrometer/core/instrument/dropwizard/DropwizardFunctionTimer$1;)V
       8: areturn
}
