Compiled from "DoneableParallelStatus.java"
public class io.dekorate.deps.knative.flows.v1alpha1.DoneableParallelStatus extends io.dekorate.deps.knative.flows.v1alpha1.ParallelStatusFluentImpl<io.dekorate.deps.knative.flows.v1alpha1.DoneableParallelStatus> implements io.dekorate.deps.kubernetes.api.model.Doneable<io.dekorate.deps.knative.flows.v1alpha1.ParallelStatus> {
  private final io.dekorate.deps.knative.flows.v1alpha1.ParallelStatusBuilder builder;

  private final io.dekorate.deps.kubernetes.api.builder.Function<io.dekorate.deps.knative.flows.v1alpha1.ParallelStatus, io.dekorate.deps.knative.flows.v1alpha1.ParallelStatus> function;

  public io.dekorate.deps.knative.flows.v1alpha1.DoneableParallelStatus(io.dekorate.deps.kubernetes.api.builder.Function<io.dekorate.deps.knative.flows.v1alpha1.ParallelStatus, io.dekorate.deps.knative.flows.v1alpha1.ParallelStatus>);
    Code:
       0: aload_0
       1: invokespecial #21                 // Method io/dekorate/deps/knative/flows/v1alpha1/ParallelStatusFluentImpl."<init>":()V
       4: aload_0
       5: new           #23                 // class io/dekorate/deps/knative/flows/v1alpha1/ParallelStatusBuilder
       8: dup
       9: aload_0
      10: invokespecial #26                 // Method io/dekorate/deps/knative/flows/v1alpha1/ParallelStatusBuilder."<init>":(Lio/dekorate/deps/knative/flows/v1alpha1/ParallelStatusFluent;)V
      13: putfield      #28                 // Field builder:Lio/dekorate/deps/knative/flows/v1alpha1/ParallelStatusBuilder;
      16: aload_0
      17: aload_1
      18: putfield      #30                 // Field function:Lio/dekorate/deps/kubernetes/api/builder/Function;
      21: return

  public io.dekorate.deps.knative.flows.v1alpha1.DoneableParallelStatus(io.dekorate.deps.knative.flows.v1alpha1.ParallelStatus, io.dekorate.deps.kubernetes.api.builder.Function<io.dekorate.deps.knative.flows.v1alpha1.ParallelStatus, io.dekorate.deps.knative.flows.v1alpha1.ParallelStatus>);
    Code:
       0: aload_0
       1: aload_1
       2: invokespecial #37                 // Method io/dekorate/deps/knative/flows/v1alpha1/ParallelStatusFluentImpl."<init>":(Lio/dekorate/deps/knative/flows/v1alpha1/ParallelStatus;)V
       5: aload_0
       6: new           #23                 // class io/dekorate/deps/knative/flows/v1alpha1/ParallelStatusBuilder
       9: dup
      10: aload_0
      11: aload_1
      12: invokespecial #40                 // Method io/dekorate/deps/knative/flows/v1alpha1/ParallelStatusBuilder."<init>":(Lio/dekorate/deps/knative/flows/v1alpha1/ParallelStatusFluent;Lio/dekorate/deps/knative/flows/v1alpha1/ParallelStatus;)V
      15: putfield      #28                 // Field builder:Lio/dekorate/deps/knative/flows/v1alpha1/ParallelStatusBuilder;
      18: aload_0
      19: aload_2
      20: putfield      #30                 // Field function:Lio/dekorate/deps/kubernetes/api/builder/Function;
      23: return

  public io.dekorate.deps.knative.flows.v1alpha1.DoneableParallelStatus(io.dekorate.deps.knative.flows.v1alpha1.ParallelStatus);
    Code:
       0: aload_0
       1: aload_1
       2: invokespecial #37                 // Method io/dekorate/deps/knative/flows/v1alpha1/ParallelStatusFluentImpl."<init>":(Lio/dekorate/deps/knative/flows/v1alpha1/ParallelStatus;)V
       5: aload_0
       6: new           #23                 // class io/dekorate/deps/knative/flows/v1alpha1/ParallelStatusBuilder
       9: dup
      10: aload_0
      11: aload_1
      12: invokespecial #40                 // Method io/dekorate/deps/knative/flows/v1alpha1/ParallelStatusBuilder."<init>":(Lio/dekorate/deps/knative/flows/v1alpha1/ParallelStatusFluent;Lio/dekorate/deps/knative/flows/v1alpha1/ParallelStatus;)V
      15: putfield      #28                 // Field builder:Lio/dekorate/deps/knative/flows/v1alpha1/ParallelStatusBuilder;
      18: aload_0
      19: new           #10                 // class io/dekorate/deps/knative/flows/v1alpha1/DoneableParallelStatus$1
      22: dup
      23: aload_0
      24: invokespecial #45                 // Method io/dekorate/deps/knative/flows/v1alpha1/DoneableParallelStatus$1."<init>":(Lio/dekorate/deps/knative/flows/v1alpha1/DoneableParallelStatus;)V
      27: putfield      #30                 // Field function:Lio/dekorate/deps/kubernetes/api/builder/Function;
      30: return

  public io.dekorate.deps.knative.flows.v1alpha1.ParallelStatus done();
    Code:
       0: aload_0
       1: getfield      #30                 // Field function:Lio/dekorate/deps/kubernetes/api/builder/Function;
       4: aload_0
       5: getfield      #28                 // Field builder:Lio/dekorate/deps/knative/flows/v1alpha1/ParallelStatusBuilder;
       8: invokevirtual #50                 // Method io/dekorate/deps/knative/flows/v1alpha1/ParallelStatusBuilder.build:()Lio/dekorate/deps/knative/flows/v1alpha1/ParallelStatus;
      11: invokeinterface #56,  2           // InterfaceMethod io/dekorate/deps/kubernetes/api/builder/Function.apply:(Ljava/lang/Object;)Ljava/lang/Object;
      16: checkcast     #58                 // class io/dekorate/deps/knative/flows/v1alpha1/ParallelStatus
      19: areturn

  public java.lang.Object done();
    Code:
       0: aload_0
       1: invokevirtual #61                 // Method done:()Lio/dekorate/deps/knative/flows/v1alpha1/ParallelStatus;
       4: areturn
}
