Compiled from "ParallelBranchStatusFluentImpl.java"
public class io.dekorate.deps.knative.flows.v1alpha1.ParallelBranchStatusFluentImpl$FilterSubscriptionStatusNestedImpl<N> extends io.dekorate.deps.knative.flows.v1alpha1.ParallelSubscriptionStatusFluentImpl<io.dekorate.deps.knative.flows.v1alpha1.ParallelBranchStatusFluent$FilterSubscriptionStatusNested<N>> implements io.dekorate.deps.knative.flows.v1alpha1.ParallelBranchStatusFluent$FilterSubscriptionStatusNested<N>, io.dekorate.deps.kubernetes.api.builder.Nested<N> {
  private final io.dekorate.deps.knative.flows.v1alpha1.ParallelSubscriptionStatusBuilder builder;

  final io.dekorate.deps.knative.flows.v1alpha1.ParallelBranchStatusFluentImpl this$0;

  io.dekorate.deps.knative.flows.v1alpha1.ParallelBranchStatusFluentImpl$FilterSubscriptionStatusNestedImpl(io.dekorate.deps.knative.flows.v1alpha1.ParallelBranchStatusFluentImpl, io.dekorate.deps.knative.flows.v1alpha1.ParallelSubscriptionStatus);
    Code:
       0: aload_0
       1: aload_1
       2: putfield      #24                 // Field this$0:Lio/dekorate/deps/knative/flows/v1alpha1/ParallelBranchStatusFluentImpl;
       5: aload_0
       6: invokespecial #27                 // Method io/dekorate/deps/knative/flows/v1alpha1/ParallelSubscriptionStatusFluentImpl."<init>":()V
       9: aload_0
      10: new           #29                 // class io/dekorate/deps/knative/flows/v1alpha1/ParallelSubscriptionStatusBuilder
      13: dup
      14: aload_0
      15: aload_2
      16: invokespecial #32                 // Method io/dekorate/deps/knative/flows/v1alpha1/ParallelSubscriptionStatusBuilder."<init>":(Lio/dekorate/deps/knative/flows/v1alpha1/ParallelSubscriptionStatusFluent;Lio/dekorate/deps/knative/flows/v1alpha1/ParallelSubscriptionStatus;)V
      19: putfield      #34                 // Field builder:Lio/dekorate/deps/knative/flows/v1alpha1/ParallelSubscriptionStatusBuilder;
      22: return

  io.dekorate.deps.knative.flows.v1alpha1.ParallelBranchStatusFluentImpl$FilterSubscriptionStatusNestedImpl(io.dekorate.deps.knative.flows.v1alpha1.ParallelBranchStatusFluentImpl);
    Code:
       0: aload_0
       1: aload_1
       2: putfield      #24                 // Field this$0:Lio/dekorate/deps/knative/flows/v1alpha1/ParallelBranchStatusFluentImpl;
       5: aload_0
       6: invokespecial #27                 // Method io/dekorate/deps/knative/flows/v1alpha1/ParallelSubscriptionStatusFluentImpl."<init>":()V
       9: aload_0
      10: new           #29                 // class io/dekorate/deps/knative/flows/v1alpha1/ParallelSubscriptionStatusBuilder
      13: dup
      14: aload_0
      15: invokespecial #43                 // Method io/dekorate/deps/knative/flows/v1alpha1/ParallelSubscriptionStatusBuilder."<init>":(Lio/dekorate/deps/knative/flows/v1alpha1/ParallelSubscriptionStatusFluent;)V
      18: putfield      #34                 // Field builder:Lio/dekorate/deps/knative/flows/v1alpha1/ParallelSubscriptionStatusBuilder;
      21: return

  public N and();
    Code:
       0: aload_0
       1: getfield      #24                 // Field this$0:Lio/dekorate/deps/knative/flows/v1alpha1/ParallelBranchStatusFluentImpl;
       4: aload_0
       5: getfield      #34                 // Field builder:Lio/dekorate/deps/knative/flows/v1alpha1/ParallelSubscriptionStatusBuilder;
       8: invokevirtual #50                 // Method io/dekorate/deps/knative/flows/v1alpha1/ParallelSubscriptionStatusBuilder.build:()Lio/dekorate/deps/knative/flows/v1alpha1/ParallelSubscriptionStatus;
      11: invokevirtual #54                 // Method io/dekorate/deps/knative/flows/v1alpha1/ParallelBranchStatusFluentImpl.withFilterSubscriptionStatus:(Lio/dekorate/deps/knative/flows/v1alpha1/ParallelSubscriptionStatus;)Lio/dekorate/deps/knative/flows/v1alpha1/ParallelBranchStatusFluent;
      14: areturn

  public N endFilterSubscriptionStatus();
    Code:
       0: aload_0
       1: invokevirtual #57                 // Method and:()Ljava/lang/Object;
       4: areturn
}
