Compiled from "SequenceStatusFluentImpl.java"
public class io.dekorate.deps.knative.flows.v1alpha1.SequenceStatusFluentImpl<A extends io.dekorate.deps.knative.flows.v1alpha1.SequenceStatusFluent<A>> extends io.dekorate.deps.kubernetes.api.builder.BaseFluent<A> implements io.dekorate.deps.knative.flows.v1alpha1.SequenceStatusFluent<A> {
  private io.dekorate.deps.knative.duck.v1.AddressableBuilder address;

  private java.util.List<io.dekorate.deps.knative.flows.v1alpha1.SequenceChannelStatusBuilder> channelStatuses;

  private java.util.List<io.dekorate.deps.knative.v1.ConditionBuilder> conditions;

  private java.lang.Long observedGeneration;

  private java.util.List<io.dekorate.deps.knative.flows.v1alpha1.SequenceSubscriptionStatusBuilder> subscriptionStatuses;

  public io.dekorate.deps.knative.flows.v1alpha1.SequenceStatusFluentImpl();
    Code:
       0: aload_0
       1: invokespecial #47                 // Method io/dekorate/deps/kubernetes/api/builder/BaseFluent."<init>":()V
       4: return

  public io.dekorate.deps.knative.flows.v1alpha1.SequenceStatusFluentImpl(io.dekorate.deps.knative.flows.v1alpha1.SequenceStatus);
    Code:
       0: aload_0
       1: invokespecial #47                 // Method io/dekorate/deps/kubernetes/api/builder/BaseFluent."<init>":()V
       4: aload_0
       5: aload_1
       6: invokevirtual #57                 // Method io/dekorate/deps/knative/flows/v1alpha1/SequenceStatus.getAddress:()Lio/dekorate/deps/knative/duck/v1/Addressable;
       9: invokevirtual #61                 // Method withAddress:(Lio/dekorate/deps/knative/duck/v1/Addressable;)Lio/dekorate/deps/knative/flows/v1alpha1/SequenceStatusFluent;
      12: pop
      13: aload_0
      14: aload_1
      15: invokevirtual #65                 // Method io/dekorate/deps/knative/flows/v1alpha1/SequenceStatus.getChannelStatuses:()Ljava/util/List;
      18: invokevirtual #69                 // Method withChannelStatuses:(Ljava/util/List;)Lio/dekorate/deps/knative/flows/v1alpha1/SequenceStatusFluent;
      21: pop
      22: aload_0
      23: aload_1
      24: invokevirtual #72                 // Method io/dekorate/deps/knative/flows/v1alpha1/SequenceStatus.getConditions:()Ljava/util/List;
      27: invokevirtual #75                 // Method withConditions:(Ljava/util/List;)Lio/dekorate/deps/knative/flows/v1alpha1/SequenceStatusFluent;
      30: pop
      31: aload_0
      32: aload_1
      33: invokevirtual #79                 // Method io/dekorate/deps/knative/flows/v1alpha1/SequenceStatus.getObservedGeneration:()Ljava/lang/Long;
      36: invokevirtual #83                 // Method withObservedGeneration:(Ljava/lang/Long;)Lio/dekorate/deps/knative/flows/v1alpha1/SequenceStatusFluent;
      39: pop
      40: aload_0
      41: aload_1
      42: invokevirtual #86                 // Method io/dekorate/deps/knative/flows/v1alpha1/SequenceStatus.getSubscriptionStatuses:()Ljava/util/List;
      45: invokevirtual #89                 // Method withSubscriptionStatuses:(Ljava/util/List;)Lio/dekorate/deps/knative/flows/v1alpha1/SequenceStatusFluent;
      48: pop
      49: return

  public io.dekorate.deps.knative.duck.v1.Addressable getAddress();
    Code:
       0: aload_0
       1: getfield      #94                 // Field address:Lio/dekorate/deps/knative/duck/v1/AddressableBuilder;
       4: ifnull        17
       7: aload_0
       8: getfield      #94                 // Field address:Lio/dekorate/deps/knative/duck/v1/AddressableBuilder;
      11: invokevirtual #99                 // Method io/dekorate/deps/knative/duck/v1/AddressableBuilder.build:()Lio/dekorate/deps/knative/duck/v1/Addressable;
      14: goto          18
      17: aconst_null
      18: areturn

  public io.dekorate.deps.knative.duck.v1.Addressable buildAddress();
    Code:
       0: aload_0
       1: getfield      #94                 // Field address:Lio/dekorate/deps/knative/duck/v1/AddressableBuilder;
       4: ifnull        17
       7: aload_0
       8: getfield      #94                 // Field address:Lio/dekorate/deps/knative/duck/v1/AddressableBuilder;
      11: invokevirtual #99                 // Method io/dekorate/deps/knative/duck/v1/AddressableBuilder.build:()Lio/dekorate/deps/knative/duck/v1/Addressable;
      14: goto          18
      17: aconst_null
      18: areturn

  public A withAddress(io.dekorate.deps.knative.duck.v1.Addressable);
    Code:
       0: aload_0
       1: getfield      #107                // Field _visitables:Lio/dekorate/deps/kubernetes/api/builder/VisitableMap;
       4: ldc           #108                // String address
       6: invokevirtual #114                // Method io/dekorate/deps/kubernetes/api/builder/VisitableMap.get:(Ljava/lang/Object;)Ljava/util/List;
       9: aload_0
      10: getfield      #94                 // Field address:Lio/dekorate/deps/knative/duck/v1/AddressableBuilder;
      13: invokeinterface #120,  2          // InterfaceMethod java/util/List.remove:(Ljava/lang/Object;)Z
      18: pop
      19: aload_1
      20: ifnull        54
      23: aload_0
      24: new           #96                 // class io/dekorate/deps/knative/duck/v1/AddressableBuilder
      27: dup
      28: aload_1
      29: invokespecial #123                // Method io/dekorate/deps/knative/duck/v1/AddressableBuilder."<init>":(Lio/dekorate/deps/knative/duck/v1/Addressable;)V
      32: putfield      #94                 // Field address:Lio/dekorate/deps/knative/duck/v1/AddressableBuilder;
      35: aload_0
      36: getfield      #107                // Field _visitables:Lio/dekorate/deps/kubernetes/api/builder/VisitableMap;
      39: ldc           #108                // String address
      41: invokevirtual #114                // Method io/dekorate/deps/kubernetes/api/builder/VisitableMap.get:(Ljava/lang/Object;)Ljava/util/List;
      44: aload_0
      45: getfield      #94                 // Field address:Lio/dekorate/deps/knative/duck/v1/AddressableBuilder;
      48: invokeinterface #126,  2          // InterfaceMethod java/util/List.add:(Ljava/lang/Object;)Z
      53: pop
      54: aload_0
      55: areturn

  public java.lang.Boolean hasAddress();
    Code:
       0: aload_0
       1: getfield      #94                 // Field address:Lio/dekorate/deps/knative/duck/v1/AddressableBuilder;
       4: ifnull        11
       7: iconst_1
       8: goto          12
      11: iconst_0
      12: invokestatic  #135                // Method java/lang/Boolean.valueOf:(Z)Ljava/lang/Boolean;
      15: areturn

  public A withNewAddress(java.lang.String);
    Code:
       0: aload_0
       1: new           #101                // class io/dekorate/deps/knative/duck/v1/Addressable
       4: dup
       5: aload_1
       6: invokespecial #141                // Method io/dekorate/deps/knative/duck/v1/Addressable."<init>":(Ljava/lang/String;)V
       9: invokevirtual #61                 // Method withAddress:(Lio/dekorate/deps/knative/duck/v1/Addressable;)Lio/dekorate/deps/knative/flows/v1alpha1/SequenceStatusFluent;
      12: areturn

  public io.dekorate.deps.knative.flows.v1alpha1.SequenceStatusFluent$AddressNested<A> withNewAddress();
    Code:
       0: new           #19                 // class io/dekorate/deps/knative/flows/v1alpha1/SequenceStatusFluentImpl$AddressNestedImpl
       3: dup
       4: aload_0
       5: invokespecial #148                // Method io/dekorate/deps/knative/flows/v1alpha1/SequenceStatusFluentImpl$AddressNestedImpl."<init>":(Lio/dekorate/deps/knative/flows/v1alpha1/SequenceStatusFluentImpl;)V
       8: areturn

  public io.dekorate.deps.knative.flows.v1alpha1.SequenceStatusFluent$AddressNested<A> withNewAddressLike(io.dekorate.deps.knative.duck.v1.Addressable);
    Code:
       0: new           #19                 // class io/dekorate/deps/knative/flows/v1alpha1/SequenceStatusFluentImpl$AddressNestedImpl
       3: dup
       4: aload_0
       5: aload_1
       6: invokespecial #154                // Method io/dekorate/deps/knative/flows/v1alpha1/SequenceStatusFluentImpl$AddressNestedImpl."<init>":(Lio/dekorate/deps/knative/flows/v1alpha1/SequenceStatusFluentImpl;Lio/dekorate/deps/knative/duck/v1/Addressable;)V
       9: areturn

  public io.dekorate.deps.knative.flows.v1alpha1.SequenceStatusFluent$AddressNested<A> editAddress();
    Code:
       0: aload_0
       1: aload_0
       2: invokevirtual #157                // Method getAddress:()Lio/dekorate/deps/knative/duck/v1/Addressable;
       5: invokevirtual #159                // Method withNewAddressLike:(Lio/dekorate/deps/knative/duck/v1/Addressable;)Lio/dekorate/deps/knative/flows/v1alpha1/SequenceStatusFluent$AddressNested;
       8: areturn

  public io.dekorate.deps.knative.flows.v1alpha1.SequenceStatusFluent$AddressNested<A> editOrNewAddress();
    Code:
       0: aload_0
       1: aload_0
       2: invokevirtual #157                // Method getAddress:()Lio/dekorate/deps/knative/duck/v1/Addressable;
       5: ifnull        15
       8: aload_0
       9: invokevirtual #157                // Method getAddress:()Lio/dekorate/deps/knative/duck/v1/Addressable;
      12: goto          25
      15: new           #96                 // class io/dekorate/deps/knative/duck/v1/AddressableBuilder
      18: dup
      19: invokespecial #161                // Method io/dekorate/deps/knative/duck/v1/AddressableBuilder."<init>":()V
      22: invokevirtual #99                 // Method io/dekorate/deps/knative/duck/v1/AddressableBuilder.build:()Lio/dekorate/deps/knative/duck/v1/Addressable;
      25: invokevirtual #159                // Method withNewAddressLike:(Lio/dekorate/deps/knative/duck/v1/Addressable;)Lio/dekorate/deps/knative/flows/v1alpha1/SequenceStatusFluent$AddressNested;
      28: areturn

  public io.dekorate.deps.knative.flows.v1alpha1.SequenceStatusFluent$AddressNested<A> editOrNewAddressLike(io.dekorate.deps.knative.duck.v1.Addressable);
    Code:
       0: aload_0
       1: aload_0
       2: invokevirtual #157                // Method getAddress:()Lio/dekorate/deps/knative/duck/v1/Addressable;
       5: ifnull        15
       8: aload_0
       9: invokevirtual #157                // Method getAddress:()Lio/dekorate/deps/knative/duck/v1/Addressable;
      12: goto          16
      15: aload_1
      16: invokevirtual #159                // Method withNewAddressLike:(Lio/dekorate/deps/knative/duck/v1/Addressable;)Lio/dekorate/deps/knative/flows/v1alpha1/SequenceStatusFluent$AddressNested;
      19: areturn

  public A addToChannelStatuses(int, io.dekorate.deps.knative.flows.v1alpha1.SequenceChannelStatus);
    Code:
       0: aload_0
       1: getfield      #167                // Field channelStatuses:Ljava/util/List;
       4: ifnonnull     18
       7: aload_0
       8: new           #169                // class java/util/ArrayList
      11: dup
      12: invokespecial #170                // Method java/util/ArrayList."<init>":()V
      15: putfield      #167                // Field channelStatuses:Ljava/util/List;
      18: new           #172                // class io/dekorate/deps/knative/flows/v1alpha1/SequenceChannelStatusBuilder
      21: dup
      22: aload_2
      23: invokespecial #175                // Method io/dekorate/deps/knative/flows/v1alpha1/SequenceChannelStatusBuilder."<init>":(Lio/dekorate/deps/knative/flows/v1alpha1/SequenceChannelStatus;)V
      26: astore_3
      27: aload_0
      28: getfield      #107                // Field _visitables:Lio/dekorate/deps/kubernetes/api/builder/VisitableMap;
      31: ldc           #176                // String channelStatuses
      33: invokevirtual #114                // Method io/dekorate/deps/kubernetes/api/builder/VisitableMap.get:(Ljava/lang/Object;)Ljava/util/List;
      36: iload_1
      37: iflt          44
      40: iload_1
      41: goto          58
      44: aload_0
      45: getfield      #107                // Field _visitables:Lio/dekorate/deps/kubernetes/api/builder/VisitableMap;
      48: ldc           #176                // String channelStatuses
      50: invokevirtual #114                // Method io/dekorate/deps/kubernetes/api/builder/VisitableMap.get:(Ljava/lang/Object;)Ljava/util/List;
      53: invokeinterface #182,  1          // InterfaceMethod java/util/List.size:()I
      58: aload_3
      59: invokeinterface #185,  3          // InterfaceMethod java/util/List.add:(ILjava/lang/Object;)V
      64: aload_0
      65: getfield      #167                // Field channelStatuses:Ljava/util/List;
      68: iload_1
      69: iflt          76
      72: iload_1
      73: goto          85
      76: aload_0
      77: getfield      #167                // Field channelStatuses:Ljava/util/List;
      80: invokeinterface #182,  1          // InterfaceMethod java/util/List.size:()I
      85: aload_3
      86: invokeinterface #185,  3          // InterfaceMethod java/util/List.add:(ILjava/lang/Object;)V
      91: aload_0
      92: areturn

  public A setToChannelStatuses(int, io.dekorate.deps.knative.flows.v1alpha1.SequenceChannelStatus);
    Code:
       0: aload_0
       1: getfield      #167                // Field channelStatuses:Ljava/util/List;
       4: ifnonnull     18
       7: aload_0
       8: new           #169                // class java/util/ArrayList
      11: dup
      12: invokespecial #170                // Method java/util/ArrayList."<init>":()V
      15: putfield      #167                // Field channelStatuses:Ljava/util/List;
      18: new           #172                // class io/dekorate/deps/knative/flows/v1alpha1/SequenceChannelStatusBuilder
      21: dup
      22: aload_2
      23: invokespecial #175                // Method io/dekorate/deps/knative/flows/v1alpha1/SequenceChannelStatusBuilder."<init>":(Lio/dekorate/deps/knative/flows/v1alpha1/SequenceChannelStatus;)V
      26: astore_3
      27: iload_1
      28: iflt          49
      31: iload_1
      32: aload_0
      33: getfield      #107                // Field _visitables:Lio/dekorate/deps/kubernetes/api/builder/VisitableMap;
      36: ldc           #176                // String channelStatuses
      38: invokevirtual #114                // Method io/dekorate/deps/kubernetes/api/builder/VisitableMap.get:(Ljava/lang/Object;)Ljava/util/List;
      41: invokeinterface #182,  1          // InterfaceMethod java/util/List.size:()I
      46: if_icmplt     68
      49: aload_0
      50: getfield      #107                // Field _visitables:Lio/dekorate/deps/kubernetes/api/builder/VisitableMap;
      53: ldc           #176                // String channelStatuses
      55: invokevirtual #114                // Method io/dekorate/deps/kubernetes/api/builder/VisitableMap.get:(Ljava/lang/Object;)Ljava/util/List;
      58: aload_3
      59: invokeinterface #126,  2          // InterfaceMethod java/util/List.add:(Ljava/lang/Object;)Z
      64: pop
      65: goto          85
      68: aload_0
      69: getfield      #107                // Field _visitables:Lio/dekorate/deps/kubernetes/api/builder/VisitableMap;
      72: ldc           #176                // String channelStatuses
      74: invokevirtual #114                // Method io/dekorate/deps/kubernetes/api/builder/VisitableMap.get:(Ljava/lang/Object;)Ljava/util/List;
      77: iload_1
      78: aload_3
      79: invokeinterface #195,  3          // InterfaceMethod java/util/List.set:(ILjava/lang/Object;)Ljava/lang/Object;
      84: pop
      85: iload_1
      86: iflt          102
      89: iload_1
      90: aload_0
      91: getfield      #167                // Field channelStatuses:Ljava/util/List;
      94: invokeinterface #182,  1          // InterfaceMethod java/util/List.size:()I
      99: if_icmplt     116
     102: aload_0
     103: getfield      #167                // Field channelStatuses:Ljava/util/List;
     106: aload_3
     107: invokeinterface #126,  2          // InterfaceMethod java/util/List.add:(Ljava/lang/Object;)Z
     112: pop
     113: goto          128
     116: aload_0
     117: getfield      #167                // Field channelStatuses:Ljava/util/List;
     120: iload_1
     121: aload_3
     122: invokeinterface #195,  3          // InterfaceMethod java/util/List.set:(ILjava/lang/Object;)Ljava/lang/Object;
     127: pop
     128: aload_0
     129: areturn

  public A addToChannelStatuses(io.dekorate.deps.knative.flows.v1alpha1.SequenceChannelStatus...);
    Code:
       0: aload_0
       1: getfield      #167                // Field channelStatuses:Ljava/util/List;
       4: ifnonnull     18
       7: aload_0
       8: new           #169                // class java/util/ArrayList
      11: dup
      12: invokespecial #170                // Method java/util/ArrayList."<init>":()V
      15: putfield      #167                // Field channelStatuses:Ljava/util/List;
      18: aload_1
      19: astore_2
      20: aload_2
      21: arraylength
      22: istore_3
      23: iconst_0
      24: istore        4
      26: iload         4
      28: iload_3
      29: if_icmpge     84
      32: aload_2
      33: iload         4
      35: aaload
      36: astore        5
      38: new           #172                // class io/dekorate/deps/knative/flows/v1alpha1/SequenceChannelStatusBuilder
      41: dup
      42: aload         5
      44: invokespecial #175                // Method io/dekorate/deps/knative/flows/v1alpha1/SequenceChannelStatusBuilder."<init>":(Lio/dekorate/deps/knative/flows/v1alpha1/SequenceChannelStatus;)V
      47: astore        6
      49: aload_0
      50: getfield      #107                // Field _visitables:Lio/dekorate/deps/kubernetes/api/builder/VisitableMap;
      53: ldc           #176                // String channelStatuses
      55: invokevirtual #114                // Method io/dekorate/deps/kubernetes/api/builder/VisitableMap.get:(Ljava/lang/Object;)Ljava/util/List;
      58: aload         6
      60: invokeinterface #126,  2          // InterfaceMethod java/util/List.add:(Ljava/lang/Object;)Z
      65: pop
      66: aload_0
      67: getfield      #167                // Field channelStatuses:Ljava/util/List;
      70: aload         6
      72: invokeinterface #126,  2          // InterfaceMethod java/util/List.add:(Ljava/lang/Object;)Z
      77: pop
      78: iinc          4, 1
      81: goto          26
      84: aload_0
      85: areturn

  public A addAllToChannelStatuses(java.util.Collection<io.dekorate.deps.knative.flows.v1alpha1.SequenceChannelStatus>);
    Code:
       0: aload_0
       1: getfield      #167                // Field channelStatuses:Ljava/util/List;
       4: ifnonnull     18
       7: aload_0
       8: new           #169                // class java/util/ArrayList
      11: dup
      12: invokespecial #170                // Method java/util/ArrayList."<init>":()V
      15: putfield      #167                // Field channelStatuses:Ljava/util/List;
      18: aload_1
      19: invokeinterface #209,  1          // InterfaceMethod java/util/Collection.iterator:()Ljava/util/Iterator;
      24: astore_2
      25: aload_2
      26: invokeinterface #215,  1          // InterfaceMethod java/util/Iterator.hasNext:()Z
      31: ifeq          86
      34: aload_2
      35: invokeinterface #219,  1          // InterfaceMethod java/util/Iterator.next:()Ljava/lang/Object;
      40: checkcast     #178                // class io/dekorate/deps/knative/flows/v1alpha1/SequenceChannelStatus
      43: astore_3
      44: new           #172                // class io/dekorate/deps/knative/flows/v1alpha1/SequenceChannelStatusBuilder
      47: dup
      48: aload_3
      49: invokespecial #175                // Method io/dekorate/deps/knative/flows/v1alpha1/SequenceChannelStatusBuilder."<init>":(Lio/dekorate/deps/knative/flows/v1alpha1/SequenceChannelStatus;)V
      52: astore        4
      54: aload_0
      55: getfield      #107                // Field _visitables:Lio/dekorate/deps/kubernetes/api/builder/VisitableMap;
      58: ldc           #176                // String channelStatuses
      60: invokevirtual #114                // Method io/dekorate/deps/kubernetes/api/builder/VisitableMap.get:(Ljava/lang/Object;)Ljava/util/List;
      63: aload         4
      65: invokeinterface #126,  2          // InterfaceMethod java/util/List.add:(Ljava/lang/Object;)Z
      70: pop
      71: aload_0
      72: getfield      #167                // Field channelStatuses:Ljava/util/List;
      75: aload         4
      77: invokeinterface #126,  2          // InterfaceMethod java/util/List.add:(Ljava/lang/Object;)Z
      82: pop
      83: goto          25
      86: aload_0
      87: areturn

  public A removeFromChannelStatuses(io.dekorate.deps.knative.flows.v1alpha1.SequenceChannelStatus...);
    Code:
       0: aload_1
       1: astore_2
       2: aload_2
       3: arraylength
       4: istore_3
       5: iconst_0
       6: istore        4
       8: iload         4
      10: iload_3
      11: if_icmpge     73
      14: aload_2
      15: iload         4
      17: aaload
      18: astore        5
      20: new           #172                // class io/dekorate/deps/knative/flows/v1alpha1/SequenceChannelStatusBuilder
      23: dup
      24: aload         5
      26: invokespecial #175                // Method io/dekorate/deps/knative/flows/v1alpha1/SequenceChannelStatusBuilder."<init>":(Lio/dekorate/deps/knative/flows/v1alpha1/SequenceChannelStatus;)V
      29: astore        6
      31: aload_0
      32: getfield      #107                // Field _visitables:Lio/dekorate/deps/kubernetes/api/builder/VisitableMap;
      35: ldc           #176                // String channelStatuses
      37: invokevirtual #114                // Method io/dekorate/deps/kubernetes/api/builder/VisitableMap.get:(Ljava/lang/Object;)Ljava/util/List;
      40: aload         6
      42: invokeinterface #120,  2          // InterfaceMethod java/util/List.remove:(Ljava/lang/Object;)Z
      47: pop
      48: aload_0
      49: getfield      #167                // Field channelStatuses:Ljava/util/List;
      52: ifnull        67
      55: aload_0
      56: getfield      #167                // Field channelStatuses:Ljava/util/List;
      59: aload         6
      61: invokeinterface #120,  2          // InterfaceMethod java/util/List.remove:(Ljava/lang/Object;)Z
      66: pop
      67: iinc          4, 1
      70: goto          8
      73: aload_0
      74: areturn

  public A removeAllFromChannelStatuses(java.util.Collection<io.dekorate.deps.knative.flows.v1alpha1.SequenceChannelStatus>);
    Code:
       0: aload_1
       1: invokeinterface #209,  1          // InterfaceMethod java/util/Collection.iterator:()Ljava/util/Iterator;
       6: astore_2
       7: aload_2
       8: invokeinterface #215,  1          // InterfaceMethod java/util/Iterator.hasNext:()Z
      13: ifeq          75
      16: aload_2
      17: invokeinterface #219,  1          // InterfaceMethod java/util/Iterator.next:()Ljava/lang/Object;
      22: checkcast     #178                // class io/dekorate/deps/knative/flows/v1alpha1/SequenceChannelStatus
      25: astore_3
      26: new           #172                // class io/dekorate/deps/knative/flows/v1alpha1/SequenceChannelStatusBuilder
      29: dup
      30: aload_3
      31: invokespecial #175                // Method io/dekorate/deps/knative/flows/v1alpha1/SequenceChannelStatusBuilder."<init>":(Lio/dekorate/deps/knative/flows/v1alpha1/SequenceChannelStatus;)V
      34: astore        4
      36: aload_0
      37: getfield      #107                // Field _visitables:Lio/dekorate/deps/kubernetes/api/builder/VisitableMap;
      40: ldc           #176                // String channelStatuses
      42: invokevirtual #114                // Method io/dekorate/deps/kubernetes/api/builder/VisitableMap.get:(Ljava/lang/Object;)Ljava/util/List;
      45: aload         4
      47: invokeinterface #120,  2          // InterfaceMethod java/util/List.remove:(Ljava/lang/Object;)Z
      52: pop
      53: aload_0
      54: getfield      #167                // Field channelStatuses:Ljava/util/List;
      57: ifnull        72
      60: aload_0
      61: getfield      #167                // Field channelStatuses:Ljava/util/List;
      64: aload         4
      66: invokeinterface #120,  2          // InterfaceMethod java/util/List.remove:(Ljava/lang/Object;)Z
      71: pop
      72: goto          7
      75: aload_0
      76: areturn

  public A removeMatchingFromChannelStatuses(io.dekorate.deps.kubernetes.api.builder.Predicate<io.dekorate.deps.knative.flows.v1alpha1.SequenceChannelStatusBuilder>);
    Code:
       0: aload_0
       1: getfield      #167                // Field channelStatuses:Ljava/util/List;
       4: ifnonnull     9
       7: aload_0
       8: areturn
       9: aload_0
      10: getfield      #167                // Field channelStatuses:Ljava/util/List;
      13: invokeinterface #227,  1          // InterfaceMethod java/util/List.iterator:()Ljava/util/Iterator;
      18: astore_2
      19: aload_0
      20: getfield      #107                // Field _visitables:Lio/dekorate/deps/kubernetes/api/builder/VisitableMap;
      23: ldc           #176                // String channelStatuses
      25: invokevirtual #114                // Method io/dekorate/deps/kubernetes/api/builder/VisitableMap.get:(Ljava/lang/Object;)Ljava/util/List;
      28: astore_3
      29: aload_2
      30: invokeinterface #215,  1          // InterfaceMethod java/util/Iterator.hasNext:()Z
      35: ifeq          81
      38: aload_2
      39: invokeinterface #219,  1          // InterfaceMethod java/util/Iterator.next:()Ljava/lang/Object;
      44: checkcast     #172                // class io/dekorate/deps/knative/flows/v1alpha1/SequenceChannelStatusBuilder
      47: astore        4
      49: aload_1
      50: aload         4
      52: invokeinterface #233,  2          // InterfaceMethod io/dekorate/deps/kubernetes/api/builder/Predicate.apply:(Ljava/lang/Object;)Ljava/lang/Boolean;
      57: invokevirtual #236                // Method java/lang/Boolean.booleanValue:()Z
      60: ifeq          78
      63: aload_3
      64: aload         4
      66: invokeinterface #120,  2          // InterfaceMethod java/util/List.remove:(Ljava/lang/Object;)Z
      71: pop
      72: aload_2
      73: invokeinterface #238,  1          // InterfaceMethod java/util/Iterator.remove:()V
      78: goto          29
      81: aload_0
      82: areturn

  public java.util.List<io.dekorate.deps.knative.flows.v1alpha1.SequenceChannelStatus> getChannelStatuses();
    Code:
       0: aload_0
       1: getfield      #167                // Field channelStatuses:Ljava/util/List;
       4: invokestatic  #249                // Method build:(Ljava/util/List;)Ljava/util/ArrayList;
       7: areturn

  public java.util.List<io.dekorate.deps.knative.flows.v1alpha1.SequenceChannelStatus> buildChannelStatuses();
    Code:
       0: aload_0
       1: getfield      #167                // Field channelStatuses:Ljava/util/List;
       4: invokestatic  #249                // Method build:(Ljava/util/List;)Ljava/util/ArrayList;
       7: areturn

  public io.dekorate.deps.knative.flows.v1alpha1.SequenceChannelStatus buildChannelStatus(int);
    Code:
       0: aload_0
       1: getfield      #167                // Field channelStatuses:Ljava/util/List;
       4: iload_1
       5: invokeinterface #255,  2          // InterfaceMethod java/util/List.get:(I)Ljava/lang/Object;
      10: checkcast     #172                // class io/dekorate/deps/knative/flows/v1alpha1/SequenceChannelStatusBuilder
      13: invokevirtual #258                // Method io/dekorate/deps/knative/flows/v1alpha1/SequenceChannelStatusBuilder.build:()Lio/dekorate/deps/knative/flows/v1alpha1/SequenceChannelStatus;
      16: areturn

  public io.dekorate.deps.knative.flows.v1alpha1.SequenceChannelStatus buildFirstChannelStatus();
    Code:
       0: aload_0
       1: getfield      #167                // Field channelStatuses:Ljava/util/List;
       4: iconst_0
       5: invokeinterface #255,  2          // InterfaceMethod java/util/List.get:(I)Ljava/lang/Object;
      10: checkcast     #172                // class io/dekorate/deps/knative/flows/v1alpha1/SequenceChannelStatusBuilder
      13: invokevirtual #258                // Method io/dekorate/deps/knative/flows/v1alpha1/SequenceChannelStatusBuilder.build:()Lio/dekorate/deps/knative/flows/v1alpha1/SequenceChannelStatus;
      16: areturn

  public io.dekorate.deps.knative.flows.v1alpha1.SequenceChannelStatus buildLastChannelStatus();
    Code:
       0: aload_0
       1: getfield      #167                // Field channelStatuses:Ljava/util/List;
       4: aload_0
       5: getfield      #167                // Field channelStatuses:Ljava/util/List;
       8: invokeinterface #182,  1          // InterfaceMethod java/util/List.size:()I
      13: iconst_1
      14: isub
      15: invokeinterface #255,  2          // InterfaceMethod java/util/List.get:(I)Ljava/lang/Object;
      20: checkcast     #172                // class io/dekorate/deps/knative/flows/v1alpha1/SequenceChannelStatusBuilder
      23: invokevirtual #258                // Method io/dekorate/deps/knative/flows/v1alpha1/SequenceChannelStatusBuilder.build:()Lio/dekorate/deps/knative/flows/v1alpha1/SequenceChannelStatus;
      26: areturn

  public io.dekorate.deps.knative.flows.v1alpha1.SequenceChannelStatus buildMatchingChannelStatus(io.dekorate.deps.kubernetes.api.builder.Predicate<io.dekorate.deps.knative.flows.v1alpha1.SequenceChannelStatusBuilder>);
    Code:
       0: aload_0
       1: getfield      #167                // Field channelStatuses:Ljava/util/List;
       4: invokeinterface #227,  1          // InterfaceMethod java/util/List.iterator:()Ljava/util/Iterator;
       9: astore_2
      10: aload_2
      11: invokeinterface #215,  1          // InterfaceMethod java/util/Iterator.hasNext:()Z
      16: ifeq          50
      19: aload_2
      20: invokeinterface #219,  1          // InterfaceMethod java/util/Iterator.next:()Ljava/lang/Object;
      25: checkcast     #172                // class io/dekorate/deps/knative/flows/v1alpha1/SequenceChannelStatusBuilder
      28: astore_3
      29: aload_1
      30: aload_3
      31: invokeinterface #233,  2          // InterfaceMethod io/dekorate/deps/kubernetes/api/builder/Predicate.apply:(Ljava/lang/Object;)Ljava/lang/Boolean;
      36: invokevirtual #236                // Method java/lang/Boolean.booleanValue:()Z
      39: ifeq          47
      42: aload_3
      43: invokevirtual #258                // Method io/dekorate/deps/knative/flows/v1alpha1/SequenceChannelStatusBuilder.build:()Lio/dekorate/deps/knative/flows/v1alpha1/SequenceChannelStatus;
      46: areturn
      47: goto          10
      50: aconst_null
      51: areturn

  public java.lang.Boolean hasMatchingChannelStatus(io.dekorate.deps.kubernetes.api.builder.Predicate<io.dekorate.deps.knative.flows.v1alpha1.SequenceChannelStatusBuilder>);
    Code:
       0: aload_0
       1: getfield      #167                // Field channelStatuses:Ljava/util/List;
       4: invokeinterface #227,  1          // InterfaceMethod java/util/List.iterator:()Ljava/util/Iterator;
       9: astore_2
      10: aload_2
      11: invokeinterface #215,  1          // InterfaceMethod java/util/Iterator.hasNext:()Z
      16: ifeq          50
      19: aload_2
      20: invokeinterface #219,  1          // InterfaceMethod java/util/Iterator.next:()Ljava/lang/Object;
      25: checkcast     #172                // class io/dekorate/deps/knative/flows/v1alpha1/SequenceChannelStatusBuilder
      28: astore_3
      29: aload_1
      30: aload_3
      31: invokeinterface #233,  2          // InterfaceMethod io/dekorate/deps/kubernetes/api/builder/Predicate.apply:(Ljava/lang/Object;)Ljava/lang/Boolean;
      36: invokevirtual #236                // Method java/lang/Boolean.booleanValue:()Z
      39: ifeq          47
      42: iconst_1
      43: invokestatic  #135                // Method java/lang/Boolean.valueOf:(Z)Ljava/lang/Boolean;
      46: areturn
      47: goto          10
      50: iconst_0
      51: invokestatic  #135                // Method java/lang/Boolean.valueOf:(Z)Ljava/lang/Boolean;
      54: areturn

  public A withChannelStatuses(java.util.List<io.dekorate.deps.knative.flows.v1alpha1.SequenceChannelStatus>);
    Code:
       0: aload_0
       1: getfield      #167                // Field channelStatuses:Ljava/util/List;
       4: ifnull        26
       7: aload_0
       8: getfield      #107                // Field _visitables:Lio/dekorate/deps/kubernetes/api/builder/VisitableMap;
      11: ldc           #176                // String channelStatuses
      13: invokevirtual #114                // Method io/dekorate/deps/kubernetes/api/builder/VisitableMap.get:(Ljava/lang/Object;)Ljava/util/List;
      16: aload_0
      17: getfield      #167                // Field channelStatuses:Ljava/util/List;
      20: invokeinterface #271,  2          // InterfaceMethod java/util/List.removeAll:(Ljava/util/Collection;)Z
      25: pop
      26: aload_1
      27: ifnull        86
      30: aload_0
      31: new           #169                // class java/util/ArrayList
      34: dup
      35: invokespecial #170                // Method java/util/ArrayList."<init>":()V
      38: putfield      #167                // Field channelStatuses:Ljava/util/List;
      41: aload_1
      42: invokeinterface #227,  1          // InterfaceMethod java/util/List.iterator:()Ljava/util/Iterator;
      47: astore_2
      48: aload_2
      49: invokeinterface #215,  1          // InterfaceMethod java/util/Iterator.hasNext:()Z
      54: ifeq          83
      57: aload_2
      58: invokeinterface #219,  1          // InterfaceMethod java/util/Iterator.next:()Ljava/lang/Object;
      63: checkcast     #178                // class io/dekorate/deps/knative/flows/v1alpha1/SequenceChannelStatus
      66: astore_3
      67: aload_0
      68: iconst_1
      69: anewarray     #178                // class io/dekorate/deps/knative/flows/v1alpha1/SequenceChannelStatus
      72: dup
      73: iconst_0
      74: aload_3
      75: aastore
      76: invokevirtual #273                // Method addToChannelStatuses:([Lio/dekorate/deps/knative/flows/v1alpha1/SequenceChannelStatus;)Lio/dekorate/deps/knative/flows/v1alpha1/SequenceStatusFluent;
      79: pop
      80: goto          48
      83: goto          91
      86: aload_0
      87: aconst_null
      88: putfield      #167                // Field channelStatuses:Ljava/util/List;
      91: aload_0
      92: areturn

  public A withChannelStatuses(io.dekorate.deps.knative.flows.v1alpha1.SequenceChannelStatus...);
    Code:
       0: aload_0
       1: getfield      #167                // Field channelStatuses:Ljava/util/List;
       4: ifnull        16
       7: aload_0
       8: getfield      #167                // Field channelStatuses:Ljava/util/List;
      11: invokeinterface #277,  1          // InterfaceMethod java/util/List.clear:()V
      16: aload_1
      17: ifnull        60
      20: aload_1
      21: astore_2
      22: aload_2
      23: arraylength
      24: istore_3
      25: iconst_0
      26: istore        4
      28: iload         4
      30: iload_3
      31: if_icmpge     60
      34: aload_2
      35: iload         4
      37: aaload
      38: astore        5
      40: aload_0
      41: iconst_1
      42: anewarray     #178                // class io/dekorate/deps/knative/flows/v1alpha1/SequenceChannelStatus
      45: dup
      46: iconst_0
      47: aload         5
      49: aastore
      50: invokevirtual #273                // Method addToChannelStatuses:([Lio/dekorate/deps/knative/flows/v1alpha1/SequenceChannelStatus;)Lio/dekorate/deps/knative/flows/v1alpha1/SequenceStatusFluent;
      53: pop
      54: iinc          4, 1
      57: goto          28
      60: aload_0
      61: areturn

  public java.lang.Boolean hasChannelStatuses();
    Code:
       0: aload_0
       1: getfield      #167                // Field channelStatuses:Ljava/util/List;
       4: ifnull        23
       7: aload_0
       8: getfield      #167                // Field channelStatuses:Ljava/util/List;
      11: invokeinterface #281,  1          // InterfaceMethod java/util/List.isEmpty:()Z
      16: ifne          23
      19: iconst_1
      20: goto          24
      23: iconst_0
      24: invokestatic  #135                // Method java/lang/Boolean.valueOf:(Z)Ljava/lang/Boolean;
      27: areturn

  public io.dekorate.deps.knative.flows.v1alpha1.SequenceStatusFluent$ChannelStatusesNested<A> addNewChannelStatus();
    Code:
       0: new           #16                 // class io/dekorate/deps/knative/flows/v1alpha1/SequenceStatusFluentImpl$ChannelStatusesNestedImpl
       3: dup
       4: aload_0
       5: invokespecial #285                // Method io/dekorate/deps/knative/flows/v1alpha1/SequenceStatusFluentImpl$ChannelStatusesNestedImpl."<init>":(Lio/dekorate/deps/knative/flows/v1alpha1/SequenceStatusFluentImpl;)V
       8: areturn

  public io.dekorate.deps.knative.flows.v1alpha1.SequenceStatusFluent$ChannelStatusesNested<A> addNewChannelStatusLike(io.dekorate.deps.knative.flows.v1alpha1.SequenceChannelStatus);
    Code:
       0: new           #16                 // class io/dekorate/deps/knative/flows/v1alpha1/SequenceStatusFluentImpl$ChannelStatusesNestedImpl
       3: dup
       4: aload_0
       5: iconst_m1
       6: aload_1
       7: invokespecial #291                // Method io/dekorate/deps/knative/flows/v1alpha1/SequenceStatusFluentImpl$ChannelStatusesNestedImpl."<init>":(Lio/dekorate/deps/knative/flows/v1alpha1/SequenceStatusFluentImpl;ILio/dekorate/deps/knative/flows/v1alpha1/SequenceChannelStatus;)V
      10: areturn

  public io.dekorate.deps.knative.flows.v1alpha1.SequenceStatusFluent$ChannelStatusesNested<A> setNewChannelStatusLike(int, io.dekorate.deps.knative.flows.v1alpha1.SequenceChannelStatus);
    Code:
       0: new           #16                 // class io/dekorate/deps/knative/flows/v1alpha1/SequenceStatusFluentImpl$ChannelStatusesNestedImpl
       3: dup
       4: aload_0
       5: iload_1
       6: aload_2
       7: invokespecial #291                // Method io/dekorate/deps/knative/flows/v1alpha1/SequenceStatusFluentImpl$ChannelStatusesNestedImpl."<init>":(Lio/dekorate/deps/knative/flows/v1alpha1/SequenceStatusFluentImpl;ILio/dekorate/deps/knative/flows/v1alpha1/SequenceChannelStatus;)V
      10: areturn

  public io.dekorate.deps.knative.flows.v1alpha1.SequenceStatusFluent$ChannelStatusesNested<A> editChannelStatus(int);
    Code:
       0: aload_0
       1: getfield      #167                // Field channelStatuses:Ljava/util/List;
       4: invokeinterface #182,  1          // InterfaceMethod java/util/List.size:()I
       9: iload_1
      10: if_icmpgt     24
      13: new           #299                // class java/lang/RuntimeException
      16: dup
      17: ldc_w         #301                // String Can\'t edit channelStatuses. Index exceeds size.
      20: invokespecial #302                // Method java/lang/RuntimeException."<init>":(Ljava/lang/String;)V
      23: athrow
      24: aload_0
      25: iload_1
      26: aload_0
      27: iload_1
      28: invokevirtual #304                // Method buildChannelStatus:(I)Lio/dekorate/deps/knative/flows/v1alpha1/SequenceChannelStatus;
      31: invokevirtual #306                // Method setNewChannelStatusLike:(ILio/dekorate/deps/knative/flows/v1alpha1/SequenceChannelStatus;)Lio/dekorate/deps/knative/flows/v1alpha1/SequenceStatusFluent$ChannelStatusesNested;
      34: areturn

  public io.dekorate.deps.knative.flows.v1alpha1.SequenceStatusFluent$ChannelStatusesNested<A> editFirstChannelStatus();
    Code:
       0: aload_0
       1: getfield      #167                // Field channelStatuses:Ljava/util/List;
       4: invokeinterface #182,  1          // InterfaceMethod java/util/List.size:()I
       9: ifne          23
      12: new           #299                // class java/lang/RuntimeException
      15: dup
      16: ldc_w         #309                // String Can\'t edit first channelStatuses. The list is empty.
      19: invokespecial #302                // Method java/lang/RuntimeException."<init>":(Ljava/lang/String;)V
      22: athrow
      23: aload_0
      24: iconst_0
      25: aload_0
      26: iconst_0
      27: invokevirtual #304                // Method buildChannelStatus:(I)Lio/dekorate/deps/knative/flows/v1alpha1/SequenceChannelStatus;
      30: invokevirtual #306                // Method setNewChannelStatusLike:(ILio/dekorate/deps/knative/flows/v1alpha1/SequenceChannelStatus;)Lio/dekorate/deps/knative/flows/v1alpha1/SequenceStatusFluent$ChannelStatusesNested;
      33: areturn

  public io.dekorate.deps.knative.flows.v1alpha1.SequenceStatusFluent$ChannelStatusesNested<A> editLastChannelStatus();
    Code:
       0: aload_0
       1: getfield      #167                // Field channelStatuses:Ljava/util/List;
       4: invokeinterface #182,  1          // InterfaceMethod java/util/List.size:()I
       9: iconst_1
      10: isub
      11: istore_1
      12: iload_1
      13: ifge          27
      16: new           #299                // class java/lang/RuntimeException
      19: dup
      20: ldc_w         #312                // String Can\'t edit last channelStatuses. The list is empty.
      23: invokespecial #302                // Method java/lang/RuntimeException."<init>":(Ljava/lang/String;)V
      26: athrow
      27: aload_0
      28: iload_1
      29: aload_0
      30: iload_1
      31: invokevirtual #304                // Method buildChannelStatus:(I)Lio/dekorate/deps/knative/flows/v1alpha1/SequenceChannelStatus;
      34: invokevirtual #306                // Method setNewChannelStatusLike:(ILio/dekorate/deps/knative/flows/v1alpha1/SequenceChannelStatus;)Lio/dekorate/deps/knative/flows/v1alpha1/SequenceStatusFluent$ChannelStatusesNested;
      37: areturn

  public io.dekorate.deps.knative.flows.v1alpha1.SequenceStatusFluent$ChannelStatusesNested<A> editMatchingChannelStatus(io.dekorate.deps.kubernetes.api.builder.Predicate<io.dekorate.deps.knative.flows.v1alpha1.SequenceChannelStatusBuilder>);
    Code:
       0: iconst_m1
       1: istore_2
       2: iconst_0
       3: istore_3
       4: iload_3
       5: aload_0
       6: getfield      #167                // Field channelStatuses:Ljava/util/List;
       9: invokeinterface #182,  1          // InterfaceMethod java/util/List.size:()I
      14: if_icmpge     50
      17: aload_1
      18: aload_0
      19: getfield      #167                // Field channelStatuses:Ljava/util/List;
      22: iload_3
      23: invokeinterface #255,  2          // InterfaceMethod java/util/List.get:(I)Ljava/lang/Object;
      28: invokeinterface #233,  2          // InterfaceMethod io/dekorate/deps/kubernetes/api/builder/Predicate.apply:(Ljava/lang/Object;)Ljava/lang/Boolean;
      33: invokevirtual #236                // Method java/lang/Boolean.booleanValue:()Z
      36: ifeq          44
      39: iload_3
      40: istore_2
      41: goto          50
      44: iinc          3, 1
      47: goto          4
      50: iload_2
      51: ifge          65
      54: new           #299                // class java/lang/RuntimeException
      57: dup
      58: ldc_w         #317                // String Can\'t edit matching channelStatuses. No match found.
      61: invokespecial #302                // Method java/lang/RuntimeException."<init>":(Ljava/lang/String;)V
      64: athrow
      65: aload_0
      66: iload_2
      67: aload_0
      68: iload_2
      69: invokevirtual #304                // Method buildChannelStatus:(I)Lio/dekorate/deps/knative/flows/v1alpha1/SequenceChannelStatus;
      72: invokevirtual #306                // Method setNewChannelStatusLike:(ILio/dekorate/deps/knative/flows/v1alpha1/SequenceChannelStatus;)Lio/dekorate/deps/knative/flows/v1alpha1/SequenceStatusFluent$ChannelStatusesNested;
      75: areturn

  public A addToConditions(int, io.dekorate.deps.knative.v1.Condition);
    Code:
       0: aload_0
       1: getfield      #323                // Field conditions:Ljava/util/List;
       4: ifnonnull     18
       7: aload_0
       8: new           #169                // class java/util/ArrayList
      11: dup
      12: invokespecial #170                // Method java/util/ArrayList."<init>":()V
      15: putfield      #323                // Field conditions:Ljava/util/List;
      18: new           #325                // class io/dekorate/deps/knative/v1/ConditionBuilder
      21: dup
      22: aload_2
      23: invokespecial #328                // Method io/dekorate/deps/knative/v1/ConditionBuilder."<init>":(Lio/dekorate/deps/knative/v1/Condition;)V
      26: astore_3
      27: aload_0
      28: getfield      #107                // Field _visitables:Lio/dekorate/deps/kubernetes/api/builder/VisitableMap;
      31: ldc_w         #329                // String conditions
      34: invokevirtual #114                // Method io/dekorate/deps/kubernetes/api/builder/VisitableMap.get:(Ljava/lang/Object;)Ljava/util/List;
      37: iload_1
      38: iflt          45
      41: iload_1
      42: goto          60
      45: aload_0
      46: getfield      #107                // Field _visitables:Lio/dekorate/deps/kubernetes/api/builder/VisitableMap;
      49: ldc_w         #329                // String conditions
      52: invokevirtual #114                // Method io/dekorate/deps/kubernetes/api/builder/VisitableMap.get:(Ljava/lang/Object;)Ljava/util/List;
      55: invokeinterface #182,  1          // InterfaceMethod java/util/List.size:()I
      60: aload_3
      61: invokeinterface #185,  3          // InterfaceMethod java/util/List.add:(ILjava/lang/Object;)V
      66: aload_0
      67: getfield      #323                // Field conditions:Ljava/util/List;
      70: iload_1
      71: iflt          78
      74: iload_1
      75: goto          87
      78: aload_0
      79: getfield      #323                // Field conditions:Ljava/util/List;
      82: invokeinterface #182,  1          // InterfaceMethod java/util/List.size:()I
      87: aload_3
      88: invokeinterface #185,  3          // InterfaceMethod java/util/List.add:(ILjava/lang/Object;)V
      93: aload_0
      94: areturn

  public A setToConditions(int, io.dekorate.deps.knative.v1.Condition);
    Code:
       0: aload_0
       1: getfield      #323                // Field conditions:Ljava/util/List;
       4: ifnonnull     18
       7: aload_0
       8: new           #169                // class java/util/ArrayList
      11: dup
      12: invokespecial #170                // Method java/util/ArrayList."<init>":()V
      15: putfield      #323                // Field conditions:Ljava/util/List;
      18: new           #325                // class io/dekorate/deps/knative/v1/ConditionBuilder
      21: dup
      22: aload_2
      23: invokespecial #328                // Method io/dekorate/deps/knative/v1/ConditionBuilder."<init>":(Lio/dekorate/deps/knative/v1/Condition;)V
      26: astore_3
      27: iload_1
      28: iflt          50
      31: iload_1
      32: aload_0
      33: getfield      #107                // Field _visitables:Lio/dekorate/deps/kubernetes/api/builder/VisitableMap;
      36: ldc_w         #329                // String conditions
      39: invokevirtual #114                // Method io/dekorate/deps/kubernetes/api/builder/VisitableMap.get:(Ljava/lang/Object;)Ljava/util/List;
      42: invokeinterface #182,  1          // InterfaceMethod java/util/List.size:()I
      47: if_icmplt     70
      50: aload_0
      51: getfield      #107                // Field _visitables:Lio/dekorate/deps/kubernetes/api/builder/VisitableMap;
      54: ldc_w         #329                // String conditions
      57: invokevirtual #114                // Method io/dekorate/deps/kubernetes/api/builder/VisitableMap.get:(Ljava/lang/Object;)Ljava/util/List;
      60: aload_3
      61: invokeinterface #126,  2          // InterfaceMethod java/util/List.add:(Ljava/lang/Object;)Z
      66: pop
      67: goto          88
      70: aload_0
      71: getfield      #107                // Field _visitables:Lio/dekorate/deps/kubernetes/api/builder/VisitableMap;
      74: ldc_w         #329                // String conditions
      77: invokevirtual #114                // Method io/dekorate/deps/kubernetes/api/builder/VisitableMap.get:(Ljava/lang/Object;)Ljava/util/List;
      80: iload_1
      81: aload_3
      82: invokeinterface #195,  3          // InterfaceMethod java/util/List.set:(ILjava/lang/Object;)Ljava/lang/Object;
      87: pop
      88: iload_1
      89: iflt          105
      92: iload_1
      93: aload_0
      94: getfield      #323                // Field conditions:Ljava/util/List;
      97: invokeinterface #182,  1          // InterfaceMethod java/util/List.size:()I
     102: if_icmplt     119
     105: aload_0
     106: getfield      #323                // Field conditions:Ljava/util/List;
     109: aload_3
     110: invokeinterface #126,  2          // InterfaceMethod java/util/List.add:(Ljava/lang/Object;)Z
     115: pop
     116: goto          131
     119: aload_0
     120: getfield      #323                // Field conditions:Ljava/util/List;
     123: iload_1
     124: aload_3
     125: invokeinterface #195,  3          // InterfaceMethod java/util/List.set:(ILjava/lang/Object;)Ljava/lang/Object;
     130: pop
     131: aload_0
     132: areturn

  public A addToConditions(io.dekorate.deps.knative.v1.Condition...);
    Code:
       0: aload_0
       1: getfield      #323                // Field conditions:Ljava/util/List;
       4: ifnonnull     18
       7: aload_0
       8: new           #169                // class java/util/ArrayList
      11: dup
      12: invokespecial #170                // Method java/util/ArrayList."<init>":()V
      15: putfield      #323                // Field conditions:Ljava/util/List;
      18: aload_1
      19: astore_2
      20: aload_2
      21: arraylength
      22: istore_3
      23: iconst_0
      24: istore        4
      26: iload         4
      28: iload_3
      29: if_icmpge     85
      32: aload_2
      33: iload         4
      35: aaload
      36: astore        5
      38: new           #325                // class io/dekorate/deps/knative/v1/ConditionBuilder
      41: dup
      42: aload         5
      44: invokespecial #328                // Method io/dekorate/deps/knative/v1/ConditionBuilder."<init>":(Lio/dekorate/deps/knative/v1/Condition;)V
      47: astore        6
      49: aload_0
      50: getfield      #107                // Field _visitables:Lio/dekorate/deps/kubernetes/api/builder/VisitableMap;
      53: ldc_w         #329                // String conditions
      56: invokevirtual #114                // Method io/dekorate/deps/kubernetes/api/builder/VisitableMap.get:(Ljava/lang/Object;)Ljava/util/List;
      59: aload         6
      61: invokeinterface #126,  2          // InterfaceMethod java/util/List.add:(Ljava/lang/Object;)Z
      66: pop
      67: aload_0
      68: getfield      #323                // Field conditions:Ljava/util/List;
      71: aload         6
      73: invokeinterface #126,  2          // InterfaceMethod java/util/List.add:(Ljava/lang/Object;)Z
      78: pop
      79: iinc          4, 1
      82: goto          26
      85: aload_0
      86: areturn

  public A addAllToConditions(java.util.Collection<io.dekorate.deps.knative.v1.Condition>);
    Code:
       0: aload_0
       1: getfield      #323                // Field conditions:Ljava/util/List;
       4: ifnonnull     18
       7: aload_0
       8: new           #169                // class java/util/ArrayList
      11: dup
      12: invokespecial #170                // Method java/util/ArrayList."<init>":()V
      15: putfield      #323                // Field conditions:Ljava/util/List;
      18: aload_1
      19: invokeinterface #209,  1          // InterfaceMethod java/util/Collection.iterator:()Ljava/util/Iterator;
      24: astore_2
      25: aload_2
      26: invokeinterface #215,  1          // InterfaceMethod java/util/Iterator.hasNext:()Z
      31: ifeq          87
      34: aload_2
      35: invokeinterface #219,  1          // InterfaceMethod java/util/Iterator.next:()Ljava/lang/Object;
      40: checkcast     #331                // class io/dekorate/deps/knative/v1/Condition
      43: astore_3
      44: new           #325                // class io/dekorate/deps/knative/v1/ConditionBuilder
      47: dup
      48: aload_3
      49: invokespecial #328                // Method io/dekorate/deps/knative/v1/ConditionBuilder."<init>":(Lio/dekorate/deps/knative/v1/Condition;)V
      52: astore        4
      54: aload_0
      55: getfield      #107                // Field _visitables:Lio/dekorate/deps/kubernetes/api/builder/VisitableMap;
      58: ldc_w         #329                // String conditions
      61: invokevirtual #114                // Method io/dekorate/deps/kubernetes/api/builder/VisitableMap.get:(Ljava/lang/Object;)Ljava/util/List;
      64: aload         4
      66: invokeinterface #126,  2          // InterfaceMethod java/util/List.add:(Ljava/lang/Object;)Z
      71: pop
      72: aload_0
      73: getfield      #323                // Field conditions:Ljava/util/List;
      76: aload         4
      78: invokeinterface #126,  2          // InterfaceMethod java/util/List.add:(Ljava/lang/Object;)Z
      83: pop
      84: goto          25
      87: aload_0
      88: areturn

  public A removeFromConditions(io.dekorate.deps.knative.v1.Condition...);
    Code:
       0: aload_1
       1: astore_2
       2: aload_2
       3: arraylength
       4: istore_3
       5: iconst_0
       6: istore        4
       8: iload         4
      10: iload_3
      11: if_icmpge     74
      14: aload_2
      15: iload         4
      17: aaload
      18: astore        5
      20: new           #325                // class io/dekorate/deps/knative/v1/ConditionBuilder
      23: dup
      24: aload         5
      26: invokespecial #328                // Method io/dekorate/deps/knative/v1/ConditionBuilder."<init>":(Lio/dekorate/deps/knative/v1/Condition;)V
      29: astore        6
      31: aload_0
      32: getfield      #107                // Field _visitables:Lio/dekorate/deps/kubernetes/api/builder/VisitableMap;
      35: ldc_w         #329                // String conditions
      38: invokevirtual #114                // Method io/dekorate/deps/kubernetes/api/builder/VisitableMap.get:(Ljava/lang/Object;)Ljava/util/List;
      41: aload         6
      43: invokeinterface #120,  2          // InterfaceMethod java/util/List.remove:(Ljava/lang/Object;)Z
      48: pop
      49: aload_0
      50: getfield      #323                // Field conditions:Ljava/util/List;
      53: ifnull        68
      56: aload_0
      57: getfield      #323                // Field conditions:Ljava/util/List;
      60: aload         6
      62: invokeinterface #120,  2          // InterfaceMethod java/util/List.remove:(Ljava/lang/Object;)Z
      67: pop
      68: iinc          4, 1
      71: goto          8
      74: aload_0
      75: areturn

  public A removeAllFromConditions(java.util.Collection<io.dekorate.deps.knative.v1.Condition>);
    Code:
       0: aload_1
       1: invokeinterface #209,  1          // InterfaceMethod java/util/Collection.iterator:()Ljava/util/Iterator;
       6: astore_2
       7: aload_2
       8: invokeinterface #215,  1          // InterfaceMethod java/util/Iterator.hasNext:()Z
      13: ifeq          76
      16: aload_2
      17: invokeinterface #219,  1          // InterfaceMethod java/util/Iterator.next:()Ljava/lang/Object;
      22: checkcast     #331                // class io/dekorate/deps/knative/v1/Condition
      25: astore_3
      26: new           #325                // class io/dekorate/deps/knative/v1/ConditionBuilder
      29: dup
      30: aload_3
      31: invokespecial #328                // Method io/dekorate/deps/knative/v1/ConditionBuilder."<init>":(Lio/dekorate/deps/knative/v1/Condition;)V
      34: astore        4
      36: aload_0
      37: getfield      #107                // Field _visitables:Lio/dekorate/deps/kubernetes/api/builder/VisitableMap;
      40: ldc_w         #329                // String conditions
      43: invokevirtual #114                // Method io/dekorate/deps/kubernetes/api/builder/VisitableMap.get:(Ljava/lang/Object;)Ljava/util/List;
      46: aload         4
      48: invokeinterface #120,  2          // InterfaceMethod java/util/List.remove:(Ljava/lang/Object;)Z
      53: pop
      54: aload_0
      55: getfield      #323                // Field conditions:Ljava/util/List;
      58: ifnull        73
      61: aload_0
      62: getfield      #323                // Field conditions:Ljava/util/List;
      65: aload         4
      67: invokeinterface #120,  2          // InterfaceMethod java/util/List.remove:(Ljava/lang/Object;)Z
      72: pop
      73: goto          7
      76: aload_0
      77: areturn

  public A removeMatchingFromConditions(io.dekorate.deps.kubernetes.api.builder.Predicate<io.dekorate.deps.knative.v1.ConditionBuilder>);
    Code:
       0: aload_0
       1: getfield      #323                // Field conditions:Ljava/util/List;
       4: ifnonnull     9
       7: aload_0
       8: areturn
       9: aload_0
      10: getfield      #323                // Field conditions:Ljava/util/List;
      13: invokeinterface #227,  1          // InterfaceMethod java/util/List.iterator:()Ljava/util/Iterator;
      18: astore_2
      19: aload_0
      20: getfield      #107                // Field _visitables:Lio/dekorate/deps/kubernetes/api/builder/VisitableMap;
      23: ldc_w         #329                // String conditions
      26: invokevirtual #114                // Method io/dekorate/deps/kubernetes/api/builder/VisitableMap.get:(Ljava/lang/Object;)Ljava/util/List;
      29: astore_3
      30: aload_2
      31: invokeinterface #215,  1          // InterfaceMethod java/util/Iterator.hasNext:()Z
      36: ifeq          82
      39: aload_2
      40: invokeinterface #219,  1          // InterfaceMethod java/util/Iterator.next:()Ljava/lang/Object;
      45: checkcast     #325                // class io/dekorate/deps/knative/v1/ConditionBuilder
      48: astore        4
      50: aload_1
      51: aload         4
      53: invokeinterface #233,  2          // InterfaceMethod io/dekorate/deps/kubernetes/api/builder/Predicate.apply:(Ljava/lang/Object;)Ljava/lang/Boolean;
      58: invokevirtual #236                // Method java/lang/Boolean.booleanValue:()Z
      61: ifeq          79
      64: aload_3
      65: aload         4
      67: invokeinterface #120,  2          // InterfaceMethod java/util/List.remove:(Ljava/lang/Object;)Z
      72: pop
      73: aload_2
      74: invokeinterface #238,  1          // InterfaceMethod java/util/Iterator.remove:()V
      79: goto          30
      82: aload_0
      83: areturn

  public java.util.List<io.dekorate.deps.knative.v1.Condition> getConditions();
    Code:
       0: aload_0
       1: getfield      #323                // Field conditions:Ljava/util/List;
       4: invokestatic  #249                // Method build:(Ljava/util/List;)Ljava/util/ArrayList;
       7: areturn

  public java.util.List<io.dekorate.deps.knative.v1.Condition> buildConditions();
    Code:
       0: aload_0
       1: getfield      #323                // Field conditions:Ljava/util/List;
       4: invokestatic  #249                // Method build:(Ljava/util/List;)Ljava/util/ArrayList;
       7: areturn

  public io.dekorate.deps.knative.v1.Condition buildCondition(int);
    Code:
       0: aload_0
       1: getfield      #323                // Field conditions:Ljava/util/List;
       4: iload_1
       5: invokeinterface #255,  2          // InterfaceMethod java/util/List.get:(I)Ljava/lang/Object;
      10: checkcast     #325                // class io/dekorate/deps/knative/v1/ConditionBuilder
      13: invokevirtual #354                // Method io/dekorate/deps/knative/v1/ConditionBuilder.build:()Lio/dekorate/deps/knative/v1/Condition;
      16: areturn

  public io.dekorate.deps.knative.v1.Condition buildFirstCondition();
    Code:
       0: aload_0
       1: getfield      #323                // Field conditions:Ljava/util/List;
       4: iconst_0
       5: invokeinterface #255,  2          // InterfaceMethod java/util/List.get:(I)Ljava/lang/Object;
      10: checkcast     #325                // class io/dekorate/deps/knative/v1/ConditionBuilder
      13: invokevirtual #354                // Method io/dekorate/deps/knative/v1/ConditionBuilder.build:()Lio/dekorate/deps/knative/v1/Condition;
      16: areturn

  public io.dekorate.deps.knative.v1.Condition buildLastCondition();
    Code:
       0: aload_0
       1: getfield      #323                // Field conditions:Ljava/util/List;
       4: aload_0
       5: getfield      #323                // Field conditions:Ljava/util/List;
       8: invokeinterface #182,  1          // InterfaceMethod java/util/List.size:()I
      13: iconst_1
      14: isub
      15: invokeinterface #255,  2          // InterfaceMethod java/util/List.get:(I)Ljava/lang/Object;
      20: checkcast     #325                // class io/dekorate/deps/knative/v1/ConditionBuilder
      23: invokevirtual #354                // Method io/dekorate/deps/knative/v1/ConditionBuilder.build:()Lio/dekorate/deps/knative/v1/Condition;
      26: areturn

  public io.dekorate.deps.knative.v1.Condition buildMatchingCondition(io.dekorate.deps.kubernetes.api.builder.Predicate<io.dekorate.deps.knative.v1.ConditionBuilder>);
    Code:
       0: aload_0
       1: getfield      #323                // Field conditions:Ljava/util/List;
       4: invokeinterface #227,  1          // InterfaceMethod java/util/List.iterator:()Ljava/util/Iterator;
       9: astore_2
      10: aload_2
      11: invokeinterface #215,  1          // InterfaceMethod java/util/Iterator.hasNext:()Z
      16: ifeq          50
      19: aload_2
      20: invokeinterface #219,  1          // InterfaceMethod java/util/Iterator.next:()Ljava/lang/Object;
      25: checkcast     #325                // class io/dekorate/deps/knative/v1/ConditionBuilder
      28: astore_3
      29: aload_1
      30: aload_3
      31: invokeinterface #233,  2          // InterfaceMethod io/dekorate/deps/kubernetes/api/builder/Predicate.apply:(Ljava/lang/Object;)Ljava/lang/Boolean;
      36: invokevirtual #236                // Method java/lang/Boolean.booleanValue:()Z
      39: ifeq          47
      42: aload_3
      43: invokevirtual #354                // Method io/dekorate/deps/knative/v1/ConditionBuilder.build:()Lio/dekorate/deps/knative/v1/Condition;
      46: areturn
      47: goto          10
      50: aconst_null
      51: areturn

  public java.lang.Boolean hasMatchingCondition(io.dekorate.deps.kubernetes.api.builder.Predicate<io.dekorate.deps.knative.v1.ConditionBuilder>);
    Code:
       0: aload_0
       1: getfield      #323                // Field conditions:Ljava/util/List;
       4: invokeinterface #227,  1          // InterfaceMethod java/util/List.iterator:()Ljava/util/Iterator;
       9: astore_2
      10: aload_2
      11: invokeinterface #215,  1          // InterfaceMethod java/util/Iterator.hasNext:()Z
      16: ifeq          50
      19: aload_2
      20: invokeinterface #219,  1          // InterfaceMethod java/util/Iterator.next:()Ljava/lang/Object;
      25: checkcast     #325                // class io/dekorate/deps/knative/v1/ConditionBuilder
      28: astore_3
      29: aload_1
      30: aload_3
      31: invokeinterface #233,  2          // InterfaceMethod io/dekorate/deps/kubernetes/api/builder/Predicate.apply:(Ljava/lang/Object;)Ljava/lang/Boolean;
      36: invokevirtual #236                // Method java/lang/Boolean.booleanValue:()Z
      39: ifeq          47
      42: iconst_1
      43: invokestatic  #135                // Method java/lang/Boolean.valueOf:(Z)Ljava/lang/Boolean;
      46: areturn
      47: goto          10
      50: iconst_0
      51: invokestatic  #135                // Method java/lang/Boolean.valueOf:(Z)Ljava/lang/Boolean;
      54: areturn

  public A withConditions(java.util.List<io.dekorate.deps.knative.v1.Condition>);
    Code:
       0: aload_0
       1: getfield      #323                // Field conditions:Ljava/util/List;
       4: ifnull        27
       7: aload_0
       8: getfield      #107                // Field _visitables:Lio/dekorate/deps/kubernetes/api/builder/VisitableMap;
      11: ldc_w         #329                // String conditions
      14: invokevirtual #114                // Method io/dekorate/deps/kubernetes/api/builder/VisitableMap.get:(Ljava/lang/Object;)Ljava/util/List;
      17: aload_0
      18: getfield      #323                // Field conditions:Ljava/util/List;
      21: invokeinterface #271,  2          // InterfaceMethod java/util/List.removeAll:(Ljava/util/Collection;)Z
      26: pop
      27: aload_1
      28: ifnull        87
      31: aload_0
      32: new           #169                // class java/util/ArrayList
      35: dup
      36: invokespecial #170                // Method java/util/ArrayList."<init>":()V
      39: putfield      #323                // Field conditions:Ljava/util/List;
      42: aload_1
      43: invokeinterface #227,  1          // InterfaceMethod java/util/List.iterator:()Ljava/util/Iterator;
      48: astore_2
      49: aload_2
      50: invokeinterface #215,  1          // InterfaceMethod java/util/Iterator.hasNext:()Z
      55: ifeq          84
      58: aload_2
      59: invokeinterface #219,  1          // InterfaceMethod java/util/Iterator.next:()Ljava/lang/Object;
      64: checkcast     #331                // class io/dekorate/deps/knative/v1/Condition
      67: astore_3
      68: aload_0
      69: iconst_1
      70: anewarray     #331                // class io/dekorate/deps/knative/v1/Condition
      73: dup
      74: iconst_0
      75: aload_3
      76: aastore
      77: invokevirtual #364                // Method addToConditions:([Lio/dekorate/deps/knative/v1/Condition;)Lio/dekorate/deps/knative/flows/v1alpha1/SequenceStatusFluent;
      80: pop
      81: goto          49
      84: goto          92
      87: aload_0
      88: aconst_null
      89: putfield      #323                // Field conditions:Ljava/util/List;
      92: aload_0
      93: areturn

  public A withConditions(io.dekorate.deps.knative.v1.Condition...);
    Code:
       0: aload_0
       1: getfield      #323                // Field conditions:Ljava/util/List;
       4: ifnull        16
       7: aload_0
       8: getfield      #323                // Field conditions:Ljava/util/List;
      11: invokeinterface #277,  1          // InterfaceMethod java/util/List.clear:()V
      16: aload_1
      17: ifnull        60
      20: aload_1
      21: astore_2
      22: aload_2
      23: arraylength
      24: istore_3
      25: iconst_0
      26: istore        4
      28: iload         4
      30: iload_3
      31: if_icmpge     60
      34: aload_2
      35: iload         4
      37: aaload
      38: astore        5
      40: aload_0
      41: iconst_1
      42: anewarray     #331                // class io/dekorate/deps/knative/v1/Condition
      45: dup
      46: iconst_0
      47: aload         5
      49: aastore
      50: invokevirtual #364                // Method addToConditions:([Lio/dekorate/deps/knative/v1/Condition;)Lio/dekorate/deps/knative/flows/v1alpha1/SequenceStatusFluent;
      53: pop
      54: iinc          4, 1
      57: goto          28
      60: aload_0
      61: areturn

  public java.lang.Boolean hasConditions();
    Code:
       0: aload_0
       1: getfield      #323                // Field conditions:Ljava/util/List;
       4: ifnull        23
       7: aload_0
       8: getfield      #323                // Field conditions:Ljava/util/List;
      11: invokeinterface #281,  1          // InterfaceMethod java/util/List.isEmpty:()Z
      16: ifne          23
      19: iconst_1
      20: goto          24
      23: iconst_0
      24: invokestatic  #135                // Method java/lang/Boolean.valueOf:(Z)Ljava/lang/Boolean;
      27: areturn

  public io.dekorate.deps.knative.flows.v1alpha1.SequenceStatusFluent$ConditionsNested<A> addNewCondition();
    Code:
       0: new           #13                 // class io/dekorate/deps/knative/flows/v1alpha1/SequenceStatusFluentImpl$ConditionsNestedImpl
       3: dup
       4: aload_0
       5: invokespecial #370                // Method io/dekorate/deps/knative/flows/v1alpha1/SequenceStatusFluentImpl$ConditionsNestedImpl."<init>":(Lio/dekorate/deps/knative/flows/v1alpha1/SequenceStatusFluentImpl;)V
       8: areturn

  public io.dekorate.deps.knative.flows.v1alpha1.SequenceStatusFluent$ConditionsNested<A> addNewConditionLike(io.dekorate.deps.knative.v1.Condition);
    Code:
       0: new           #13                 // class io/dekorate/deps/knative/flows/v1alpha1/SequenceStatusFluentImpl$ConditionsNestedImpl
       3: dup
       4: aload_0
       5: iconst_m1
       6: aload_1
       7: invokespecial #376                // Method io/dekorate/deps/knative/flows/v1alpha1/SequenceStatusFluentImpl$ConditionsNestedImpl."<init>":(Lio/dekorate/deps/knative/flows/v1alpha1/SequenceStatusFluentImpl;ILio/dekorate/deps/knative/v1/Condition;)V
      10: areturn

  public io.dekorate.deps.knative.flows.v1alpha1.SequenceStatusFluent$ConditionsNested<A> setNewConditionLike(int, io.dekorate.deps.knative.v1.Condition);
    Code:
       0: new           #13                 // class io/dekorate/deps/knative/flows/v1alpha1/SequenceStatusFluentImpl$ConditionsNestedImpl
       3: dup
       4: aload_0
       5: iload_1
       6: aload_2
       7: invokespecial #376                // Method io/dekorate/deps/knative/flows/v1alpha1/SequenceStatusFluentImpl$ConditionsNestedImpl."<init>":(Lio/dekorate/deps/knative/flows/v1alpha1/SequenceStatusFluentImpl;ILio/dekorate/deps/knative/v1/Condition;)V
      10: areturn

  public io.dekorate.deps.knative.flows.v1alpha1.SequenceStatusFluent$ConditionsNested<A> editCondition(int);
    Code:
       0: aload_0
       1: getfield      #323                // Field conditions:Ljava/util/List;
       4: invokeinterface #182,  1          // InterfaceMethod java/util/List.size:()I
       9: iload_1
      10: if_icmpgt     24
      13: new           #299                // class java/lang/RuntimeException
      16: dup
      17: ldc_w         #384                // String Can\'t edit conditions. Index exceeds size.
      20: invokespecial #302                // Method java/lang/RuntimeException."<init>":(Ljava/lang/String;)V
      23: athrow
      24: aload_0
      25: iload_1
      26: aload_0
      27: iload_1
      28: invokevirtual #386                // Method buildCondition:(I)Lio/dekorate/deps/knative/v1/Condition;
      31: invokevirtual #388                // Method setNewConditionLike:(ILio/dekorate/deps/knative/v1/Condition;)Lio/dekorate/deps/knative/flows/v1alpha1/SequenceStatusFluent$ConditionsNested;
      34: areturn

  public io.dekorate.deps.knative.flows.v1alpha1.SequenceStatusFluent$ConditionsNested<A> editFirstCondition();
    Code:
       0: aload_0
       1: getfield      #323                // Field conditions:Ljava/util/List;
       4: invokeinterface #182,  1          // InterfaceMethod java/util/List.size:()I
       9: ifne          23
      12: new           #299                // class java/lang/RuntimeException
      15: dup
      16: ldc_w         #391                // String Can\'t edit first conditions. The list is empty.
      19: invokespecial #302                // Method java/lang/RuntimeException."<init>":(Ljava/lang/String;)V
      22: athrow
      23: aload_0
      24: iconst_0
      25: aload_0
      26: iconst_0
      27: invokevirtual #386                // Method buildCondition:(I)Lio/dekorate/deps/knative/v1/Condition;
      30: invokevirtual #388                // Method setNewConditionLike:(ILio/dekorate/deps/knative/v1/Condition;)Lio/dekorate/deps/knative/flows/v1alpha1/SequenceStatusFluent$ConditionsNested;
      33: areturn

  public io.dekorate.deps.knative.flows.v1alpha1.SequenceStatusFluent$ConditionsNested<A> editLastCondition();
    Code:
       0: aload_0
       1: getfield      #323                // Field conditions:Ljava/util/List;
       4: invokeinterface #182,  1          // InterfaceMethod java/util/List.size:()I
       9: iconst_1
      10: isub
      11: istore_1
      12: iload_1
      13: ifge          27
      16: new           #299                // class java/lang/RuntimeException
      19: dup
      20: ldc_w         #394                // String Can\'t edit last conditions. The list is empty.
      23: invokespecial #302                // Method java/lang/RuntimeException."<init>":(Ljava/lang/String;)V
      26: athrow
      27: aload_0
      28: iload_1
      29: aload_0
      30: iload_1
      31: invokevirtual #386                // Method buildCondition:(I)Lio/dekorate/deps/knative/v1/Condition;
      34: invokevirtual #388                // Method setNewConditionLike:(ILio/dekorate/deps/knative/v1/Condition;)Lio/dekorate/deps/knative/flows/v1alpha1/SequenceStatusFluent$ConditionsNested;
      37: areturn

  public io.dekorate.deps.knative.flows.v1alpha1.SequenceStatusFluent$ConditionsNested<A> editMatchingCondition(io.dekorate.deps.kubernetes.api.builder.Predicate<io.dekorate.deps.knative.v1.ConditionBuilder>);
    Code:
       0: iconst_m1
       1: istore_2
       2: iconst_0
       3: istore_3
       4: iload_3
       5: aload_0
       6: getfield      #323                // Field conditions:Ljava/util/List;
       9: invokeinterface #182,  1          // InterfaceMethod java/util/List.size:()I
      14: if_icmpge     50
      17: aload_1
      18: aload_0
      19: getfield      #323                // Field conditions:Ljava/util/List;
      22: iload_3
      23: invokeinterface #255,  2          // InterfaceMethod java/util/List.get:(I)Ljava/lang/Object;
      28: invokeinterface #233,  2          // InterfaceMethod io/dekorate/deps/kubernetes/api/builder/Predicate.apply:(Ljava/lang/Object;)Ljava/lang/Boolean;
      33: invokevirtual #236                // Method java/lang/Boolean.booleanValue:()Z
      36: ifeq          44
      39: iload_3
      40: istore_2
      41: goto          50
      44: iinc          3, 1
      47: goto          4
      50: iload_2
      51: ifge          65
      54: new           #299                // class java/lang/RuntimeException
      57: dup
      58: ldc_w         #399                // String Can\'t edit matching conditions. No match found.
      61: invokespecial #302                // Method java/lang/RuntimeException."<init>":(Ljava/lang/String;)V
      64: athrow
      65: aload_0
      66: iload_2
      67: aload_0
      68: iload_2
      69: invokevirtual #386                // Method buildCondition:(I)Lio/dekorate/deps/knative/v1/Condition;
      72: invokevirtual #388                // Method setNewConditionLike:(ILio/dekorate/deps/knative/v1/Condition;)Lio/dekorate/deps/knative/flows/v1alpha1/SequenceStatusFluent$ConditionsNested;
      75: areturn

  public java.lang.Long getObservedGeneration();
    Code:
       0: aload_0
       1: getfield      #401                // Field observedGeneration:Ljava/lang/Long;
       4: areturn

  public A withObservedGeneration(java.lang.Long);
    Code:
       0: aload_0
       1: aload_1
       2: putfield      #401                // Field observedGeneration:Ljava/lang/Long;
       5: aload_0
       6: areturn

  public java.lang.Boolean hasObservedGeneration();
    Code:
       0: aload_0
       1: getfield      #401                // Field observedGeneration:Ljava/lang/Long;
       4: ifnull        11
       7: iconst_1
       8: goto          12
      11: iconst_0
      12: invokestatic  #135                // Method java/lang/Boolean.valueOf:(Z)Ljava/lang/Boolean;
      15: areturn

  public A addToSubscriptionStatuses(int, io.dekorate.deps.knative.flows.v1alpha1.SequenceSubscriptionStatus);
    Code:
       0: aload_0
       1: getfield      #408                // Field subscriptionStatuses:Ljava/util/List;
       4: ifnonnull     18
       7: aload_0
       8: new           #169                // class java/util/ArrayList
      11: dup
      12: invokespecial #170                // Method java/util/ArrayList."<init>":()V
      15: putfield      #408                // Field subscriptionStatuses:Ljava/util/List;
      18: new           #410                // class io/dekorate/deps/knative/flows/v1alpha1/SequenceSubscriptionStatusBuilder
      21: dup
      22: aload_2
      23: invokespecial #413                // Method io/dekorate/deps/knative/flows/v1alpha1/SequenceSubscriptionStatusBuilder."<init>":(Lio/dekorate/deps/knative/flows/v1alpha1/SequenceSubscriptionStatus;)V
      26: astore_3
      27: aload_0
      28: getfield      #107                // Field _visitables:Lio/dekorate/deps/kubernetes/api/builder/VisitableMap;
      31: ldc_w         #414                // String subscriptionStatuses
      34: invokevirtual #114                // Method io/dekorate/deps/kubernetes/api/builder/VisitableMap.get:(Ljava/lang/Object;)Ljava/util/List;
      37: iload_1
      38: iflt          45
      41: iload_1
      42: goto          60
      45: aload_0
      46: getfield      #107                // Field _visitables:Lio/dekorate/deps/kubernetes/api/builder/VisitableMap;
      49: ldc_w         #414                // String subscriptionStatuses
      52: invokevirtual #114                // Method io/dekorate/deps/kubernetes/api/builder/VisitableMap.get:(Ljava/lang/Object;)Ljava/util/List;
      55: invokeinterface #182,  1          // InterfaceMethod java/util/List.size:()I
      60: aload_3
      61: invokeinterface #185,  3          // InterfaceMethod java/util/List.add:(ILjava/lang/Object;)V
      66: aload_0
      67: getfield      #408                // Field subscriptionStatuses:Ljava/util/List;
      70: iload_1
      71: iflt          78
      74: iload_1
      75: goto          87
      78: aload_0
      79: getfield      #408                // Field subscriptionStatuses:Ljava/util/List;
      82: invokeinterface #182,  1          // InterfaceMethod java/util/List.size:()I
      87: aload_3
      88: invokeinterface #185,  3          // InterfaceMethod java/util/List.add:(ILjava/lang/Object;)V
      93: aload_0
      94: areturn

  public A setToSubscriptionStatuses(int, io.dekorate.deps.knative.flows.v1alpha1.SequenceSubscriptionStatus);
    Code:
       0: aload_0
       1: getfield      #408                // Field subscriptionStatuses:Ljava/util/List;
       4: ifnonnull     18
       7: aload_0
       8: new           #169                // class java/util/ArrayList
      11: dup
      12: invokespecial #170                // Method java/util/ArrayList."<init>":()V
      15: putfield      #408                // Field subscriptionStatuses:Ljava/util/List;
      18: new           #410                // class io/dekorate/deps/knative/flows/v1alpha1/SequenceSubscriptionStatusBuilder
      21: dup
      22: aload_2
      23: invokespecial #413                // Method io/dekorate/deps/knative/flows/v1alpha1/SequenceSubscriptionStatusBuilder."<init>":(Lio/dekorate/deps/knative/flows/v1alpha1/SequenceSubscriptionStatus;)V
      26: astore_3
      27: iload_1
      28: iflt          50
      31: iload_1
      32: aload_0
      33: getfield      #107                // Field _visitables:Lio/dekorate/deps/kubernetes/api/builder/VisitableMap;
      36: ldc_w         #414                // String subscriptionStatuses
      39: invokevirtual #114                // Method io/dekorate/deps/kubernetes/api/builder/VisitableMap.get:(Ljava/lang/Object;)Ljava/util/List;
      42: invokeinterface #182,  1          // InterfaceMethod java/util/List.size:()I
      47: if_icmplt     70
      50: aload_0
      51: getfield      #107                // Field _visitables:Lio/dekorate/deps/kubernetes/api/builder/VisitableMap;
      54: ldc_w         #414                // String subscriptionStatuses
      57: invokevirtual #114                // Method io/dekorate/deps/kubernetes/api/builder/VisitableMap.get:(Ljava/lang/Object;)Ljava/util/List;
      60: aload_3
      61: invokeinterface #126,  2          // InterfaceMethod java/util/List.add:(Ljava/lang/Object;)Z
      66: pop
      67: goto          88
      70: aload_0
      71: getfield      #107                // Field _visitables:Lio/dekorate/deps/kubernetes/api/builder/VisitableMap;
      74: ldc_w         #414                // String subscriptionStatuses
      77: invokevirtual #114                // Method io/dekorate/deps/kubernetes/api/builder/VisitableMap.get:(Ljava/lang/Object;)Ljava/util/List;
      80: iload_1
      81: aload_3
      82: invokeinterface #195,  3          // InterfaceMethod java/util/List.set:(ILjava/lang/Object;)Ljava/lang/Object;
      87: pop
      88: iload_1
      89: iflt          105
      92: iload_1
      93: aload_0
      94: getfield      #408                // Field subscriptionStatuses:Ljava/util/List;
      97: invokeinterface #182,  1          // InterfaceMethod java/util/List.size:()I
     102: if_icmplt     119
     105: aload_0
     106: getfield      #408                // Field subscriptionStatuses:Ljava/util/List;
     109: aload_3
     110: invokeinterface #126,  2          // InterfaceMethod java/util/List.add:(Ljava/lang/Object;)Z
     115: pop
     116: goto          131
     119: aload_0
     120: getfield      #408                // Field subscriptionStatuses:Ljava/util/List;
     123: iload_1
     124: aload_3
     125: invokeinterface #195,  3          // InterfaceMethod java/util/List.set:(ILjava/lang/Object;)Ljava/lang/Object;
     130: pop
     131: aload_0
     132: areturn

  public A addToSubscriptionStatuses(io.dekorate.deps.knative.flows.v1alpha1.SequenceSubscriptionStatus...);
    Code:
       0: aload_0
       1: getfield      #408                // Field subscriptionStatuses:Ljava/util/List;
       4: ifnonnull     18
       7: aload_0
       8: new           #169                // class java/util/ArrayList
      11: dup
      12: invokespecial #170                // Method java/util/ArrayList."<init>":()V
      15: putfield      #408                // Field subscriptionStatuses:Ljava/util/List;
      18: aload_1
      19: astore_2
      20: aload_2
      21: arraylength
      22: istore_3
      23: iconst_0
      24: istore        4
      26: iload         4
      28: iload_3
      29: if_icmpge     85
      32: aload_2
      33: iload         4
      35: aaload
      36: astore        5
      38: new           #410                // class io/dekorate/deps/knative/flows/v1alpha1/SequenceSubscriptionStatusBuilder
      41: dup
      42: aload         5
      44: invokespecial #413                // Method io/dekorate/deps/knative/flows/v1alpha1/SequenceSubscriptionStatusBuilder."<init>":(Lio/dekorate/deps/knative/flows/v1alpha1/SequenceSubscriptionStatus;)V
      47: astore        6
      49: aload_0
      50: getfield      #107                // Field _visitables:Lio/dekorate/deps/kubernetes/api/builder/VisitableMap;
      53: ldc_w         #414                // String subscriptionStatuses
      56: invokevirtual #114                // Method io/dekorate/deps/kubernetes/api/builder/VisitableMap.get:(Ljava/lang/Object;)Ljava/util/List;
      59: aload         6
      61: invokeinterface #126,  2          // InterfaceMethod java/util/List.add:(Ljava/lang/Object;)Z
      66: pop
      67: aload_0
      68: getfield      #408                // Field subscriptionStatuses:Ljava/util/List;
      71: aload         6
      73: invokeinterface #126,  2          // InterfaceMethod java/util/List.add:(Ljava/lang/Object;)Z
      78: pop
      79: iinc          4, 1
      82: goto          26
      85: aload_0
      86: areturn

  public A addAllToSubscriptionStatuses(java.util.Collection<io.dekorate.deps.knative.flows.v1alpha1.SequenceSubscriptionStatus>);
    Code:
       0: aload_0
       1: getfield      #408                // Field subscriptionStatuses:Ljava/util/List;
       4: ifnonnull     18
       7: aload_0
       8: new           #169                // class java/util/ArrayList
      11: dup
      12: invokespecial #170                // Method java/util/ArrayList."<init>":()V
      15: putfield      #408                // Field subscriptionStatuses:Ljava/util/List;
      18: aload_1
      19: invokeinterface #209,  1          // InterfaceMethod java/util/Collection.iterator:()Ljava/util/Iterator;
      24: astore_2
      25: aload_2
      26: invokeinterface #215,  1          // InterfaceMethod java/util/Iterator.hasNext:()Z
      31: ifeq          87
      34: aload_2
      35: invokeinterface #219,  1          // InterfaceMethod java/util/Iterator.next:()Ljava/lang/Object;
      40: checkcast     #416                // class io/dekorate/deps/knative/flows/v1alpha1/SequenceSubscriptionStatus
      43: astore_3
      44: new           #410                // class io/dekorate/deps/knative/flows/v1alpha1/SequenceSubscriptionStatusBuilder
      47: dup
      48: aload_3
      49: invokespecial #413                // Method io/dekorate/deps/knative/flows/v1alpha1/SequenceSubscriptionStatusBuilder."<init>":(Lio/dekorate/deps/knative/flows/v1alpha1/SequenceSubscriptionStatus;)V
      52: astore        4
      54: aload_0
      55: getfield      #107                // Field _visitables:Lio/dekorate/deps/kubernetes/api/builder/VisitableMap;
      58: ldc_w         #414                // String subscriptionStatuses
      61: invokevirtual #114                // Method io/dekorate/deps/kubernetes/api/builder/VisitableMap.get:(Ljava/lang/Object;)Ljava/util/List;
      64: aload         4
      66: invokeinterface #126,  2          // InterfaceMethod java/util/List.add:(Ljava/lang/Object;)Z
      71: pop
      72: aload_0
      73: getfield      #408                // Field subscriptionStatuses:Ljava/util/List;
      76: aload         4
      78: invokeinterface #126,  2          // InterfaceMethod java/util/List.add:(Ljava/lang/Object;)Z
      83: pop
      84: goto          25
      87: aload_0
      88: areturn

  public A removeFromSubscriptionStatuses(io.dekorate.deps.knative.flows.v1alpha1.SequenceSubscriptionStatus...);
    Code:
       0: aload_1
       1: astore_2
       2: aload_2
       3: arraylength
       4: istore_3
       5: iconst_0
       6: istore        4
       8: iload         4
      10: iload_3
      11: if_icmpge     74
      14: aload_2
      15: iload         4
      17: aaload
      18: astore        5
      20: new           #410                // class io/dekorate/deps/knative/flows/v1alpha1/SequenceSubscriptionStatusBuilder
      23: dup
      24: aload         5
      26: invokespecial #413                // Method io/dekorate/deps/knative/flows/v1alpha1/SequenceSubscriptionStatusBuilder."<init>":(Lio/dekorate/deps/knative/flows/v1alpha1/SequenceSubscriptionStatus;)V
      29: astore        6
      31: aload_0
      32: getfield      #107                // Field _visitables:Lio/dekorate/deps/kubernetes/api/builder/VisitableMap;
      35: ldc_w         #414                // String subscriptionStatuses
      38: invokevirtual #114                // Method io/dekorate/deps/kubernetes/api/builder/VisitableMap.get:(Ljava/lang/Object;)Ljava/util/List;
      41: aload         6
      43: invokeinterface #120,  2          // InterfaceMethod java/util/List.remove:(Ljava/lang/Object;)Z
      48: pop
      49: aload_0
      50: getfield      #408                // Field subscriptionStatuses:Ljava/util/List;
      53: ifnull        68
      56: aload_0
      57: getfield      #408                // Field subscriptionStatuses:Ljava/util/List;
      60: aload         6
      62: invokeinterface #120,  2          // InterfaceMethod java/util/List.remove:(Ljava/lang/Object;)Z
      67: pop
      68: iinc          4, 1
      71: goto          8
      74: aload_0
      75: areturn

  public A removeAllFromSubscriptionStatuses(java.util.Collection<io.dekorate.deps.knative.flows.v1alpha1.SequenceSubscriptionStatus>);
    Code:
       0: aload_1
       1: invokeinterface #209,  1          // InterfaceMethod java/util/Collection.iterator:()Ljava/util/Iterator;
       6: astore_2
       7: aload_2
       8: invokeinterface #215,  1          // InterfaceMethod java/util/Iterator.hasNext:()Z
      13: ifeq          76
      16: aload_2
      17: invokeinterface #219,  1          // InterfaceMethod java/util/Iterator.next:()Ljava/lang/Object;
      22: checkcast     #416                // class io/dekorate/deps/knative/flows/v1alpha1/SequenceSubscriptionStatus
      25: astore_3
      26: new           #410                // class io/dekorate/deps/knative/flows/v1alpha1/SequenceSubscriptionStatusBuilder
      29: dup
      30: aload_3
      31: invokespecial #413                // Method io/dekorate/deps/knative/flows/v1alpha1/SequenceSubscriptionStatusBuilder."<init>":(Lio/dekorate/deps/knative/flows/v1alpha1/SequenceSubscriptionStatus;)V
      34: astore        4
      36: aload_0
      37: getfield      #107                // Field _visitables:Lio/dekorate/deps/kubernetes/api/builder/VisitableMap;
      40: ldc_w         #414                // String subscriptionStatuses
      43: invokevirtual #114                // Method io/dekorate/deps/kubernetes/api/builder/VisitableMap.get:(Ljava/lang/Object;)Ljava/util/List;
      46: aload         4
      48: invokeinterface #120,  2          // InterfaceMethod java/util/List.remove:(Ljava/lang/Object;)Z
      53: pop
      54: aload_0
      55: getfield      #408                // Field subscriptionStatuses:Ljava/util/List;
      58: ifnull        73
      61: aload_0
      62: getfield      #408                // Field subscriptionStatuses:Ljava/util/List;
      65: aload         4
      67: invokeinterface #120,  2          // InterfaceMethod java/util/List.remove:(Ljava/lang/Object;)Z
      72: pop
      73: goto          7
      76: aload_0
      77: areturn

  public A removeMatchingFromSubscriptionStatuses(io.dekorate.deps.kubernetes.api.builder.Predicate<io.dekorate.deps.knative.flows.v1alpha1.SequenceSubscriptionStatusBuilder>);
    Code:
       0: aload_0
       1: getfield      #408                // Field subscriptionStatuses:Ljava/util/List;
       4: ifnonnull     9
       7: aload_0
       8: areturn
       9: aload_0
      10: getfield      #408                // Field subscriptionStatuses:Ljava/util/List;
      13: invokeinterface #227,  1          // InterfaceMethod java/util/List.iterator:()Ljava/util/Iterator;
      18: astore_2
      19: aload_0
      20: getfield      #107                // Field _visitables:Lio/dekorate/deps/kubernetes/api/builder/VisitableMap;
      23: ldc_w         #414                // String subscriptionStatuses
      26: invokevirtual #114                // Method io/dekorate/deps/kubernetes/api/builder/VisitableMap.get:(Ljava/lang/Object;)Ljava/util/List;
      29: astore_3
      30: aload_2
      31: invokeinterface #215,  1          // InterfaceMethod java/util/Iterator.hasNext:()Z
      36: ifeq          82
      39: aload_2
      40: invokeinterface #219,  1          // InterfaceMethod java/util/Iterator.next:()Ljava/lang/Object;
      45: checkcast     #410                // class io/dekorate/deps/knative/flows/v1alpha1/SequenceSubscriptionStatusBuilder
      48: astore        4
      50: aload_1
      51: aload         4
      53: invokeinterface #233,  2          // InterfaceMethod io/dekorate/deps/kubernetes/api/builder/Predicate.apply:(Ljava/lang/Object;)Ljava/lang/Boolean;
      58: invokevirtual #236                // Method java/lang/Boolean.booleanValue:()Z
      61: ifeq          79
      64: aload_3
      65: aload         4
      67: invokeinterface #120,  2          // InterfaceMethod java/util/List.remove:(Ljava/lang/Object;)Z
      72: pop
      73: aload_2
      74: invokeinterface #238,  1          // InterfaceMethod java/util/Iterator.remove:()V
      79: goto          30
      82: aload_0
      83: areturn

  public java.util.List<io.dekorate.deps.knative.flows.v1alpha1.SequenceSubscriptionStatus> getSubscriptionStatuses();
    Code:
       0: aload_0
       1: getfield      #408                // Field subscriptionStatuses:Ljava/util/List;
       4: invokestatic  #249                // Method build:(Ljava/util/List;)Ljava/util/ArrayList;
       7: areturn

  public java.util.List<io.dekorate.deps.knative.flows.v1alpha1.SequenceSubscriptionStatus> buildSubscriptionStatuses();
    Code:
       0: aload_0
       1: getfield      #408                // Field subscriptionStatuses:Ljava/util/List;
       4: invokestatic  #249                // Method build:(Ljava/util/List;)Ljava/util/ArrayList;
       7: areturn

  public io.dekorate.deps.knative.flows.v1alpha1.SequenceSubscriptionStatus buildSubscriptionStatus(int);
    Code:
       0: aload_0
       1: getfield      #408                // Field subscriptionStatuses:Ljava/util/List;
       4: iload_1
       5: invokeinterface #255,  2          // InterfaceMethod java/util/List.get:(I)Ljava/lang/Object;
      10: checkcast     #410                // class io/dekorate/deps/knative/flows/v1alpha1/SequenceSubscriptionStatusBuilder
      13: invokevirtual #439                // Method io/dekorate/deps/knative/flows/v1alpha1/SequenceSubscriptionStatusBuilder.build:()Lio/dekorate/deps/knative/flows/v1alpha1/SequenceSubscriptionStatus;
      16: areturn

  public io.dekorate.deps.knative.flows.v1alpha1.SequenceSubscriptionStatus buildFirstSubscriptionStatus();
    Code:
       0: aload_0
       1: getfield      #408                // Field subscriptionStatuses:Ljava/util/List;
       4: iconst_0
       5: invokeinterface #255,  2          // InterfaceMethod java/util/List.get:(I)Ljava/lang/Object;
      10: checkcast     #410                // class io/dekorate/deps/knative/flows/v1alpha1/SequenceSubscriptionStatusBuilder
      13: invokevirtual #439                // Method io/dekorate/deps/knative/flows/v1alpha1/SequenceSubscriptionStatusBuilder.build:()Lio/dekorate/deps/knative/flows/v1alpha1/SequenceSubscriptionStatus;
      16: areturn

  public io.dekorate.deps.knative.flows.v1alpha1.SequenceSubscriptionStatus buildLastSubscriptionStatus();
    Code:
       0: aload_0
       1: getfield      #408                // Field subscriptionStatuses:Ljava/util/List;
       4: aload_0
       5: getfield      #408                // Field subscriptionStatuses:Ljava/util/List;
       8: invokeinterface #182,  1          // InterfaceMethod java/util/List.size:()I
      13: iconst_1
      14: isub
      15: invokeinterface #255,  2          // InterfaceMethod java/util/List.get:(I)Ljava/lang/Object;
      20: checkcast     #410                // class io/dekorate/deps/knative/flows/v1alpha1/SequenceSubscriptionStatusBuilder
      23: invokevirtual #439                // Method io/dekorate/deps/knative/flows/v1alpha1/SequenceSubscriptionStatusBuilder.build:()Lio/dekorate/deps/knative/flows/v1alpha1/SequenceSubscriptionStatus;
      26: areturn

  public io.dekorate.deps.knative.flows.v1alpha1.SequenceSubscriptionStatus buildMatchingSubscriptionStatus(io.dekorate.deps.kubernetes.api.builder.Predicate<io.dekorate.deps.knative.flows.v1alpha1.SequenceSubscriptionStatusBuilder>);
    Code:
       0: aload_0
       1: getfield      #408                // Field subscriptionStatuses:Ljava/util/List;
       4: invokeinterface #227,  1          // InterfaceMethod java/util/List.iterator:()Ljava/util/Iterator;
       9: astore_2
      10: aload_2
      11: invokeinterface #215,  1          // InterfaceMethod java/util/Iterator.hasNext:()Z
      16: ifeq          50
      19: aload_2
      20: invokeinterface #219,  1          // InterfaceMethod java/util/Iterator.next:()Ljava/lang/Object;
      25: checkcast     #410                // class io/dekorate/deps/knative/flows/v1alpha1/SequenceSubscriptionStatusBuilder
      28: astore_3
      29: aload_1
      30: aload_3
      31: invokeinterface #233,  2          // InterfaceMethod io/dekorate/deps/kubernetes/api/builder/Predicate.apply:(Ljava/lang/Object;)Ljava/lang/Boolean;
      36: invokevirtual #236                // Method java/lang/Boolean.booleanValue:()Z
      39: ifeq          47
      42: aload_3
      43: invokevirtual #439                // Method io/dekorate/deps/knative/flows/v1alpha1/SequenceSubscriptionStatusBuilder.build:()Lio/dekorate/deps/knative/flows/v1alpha1/SequenceSubscriptionStatus;
      46: areturn
      47: goto          10
      50: aconst_null
      51: areturn

  public java.lang.Boolean hasMatchingSubscriptionStatus(io.dekorate.deps.kubernetes.api.builder.Predicate<io.dekorate.deps.knative.flows.v1alpha1.SequenceSubscriptionStatusBuilder>);
    Code:
       0: aload_0
       1: getfield      #408                // Field subscriptionStatuses:Ljava/util/List;
       4: invokeinterface #227,  1          // InterfaceMethod java/util/List.iterator:()Ljava/util/Iterator;
       9: astore_2
      10: aload_2
      11: invokeinterface #215,  1          // InterfaceMethod java/util/Iterator.hasNext:()Z
      16: ifeq          50
      19: aload_2
      20: invokeinterface #219,  1          // InterfaceMethod java/util/Iterator.next:()Ljava/lang/Object;
      25: checkcast     #410                // class io/dekorate/deps/knative/flows/v1alpha1/SequenceSubscriptionStatusBuilder
      28: astore_3
      29: aload_1
      30: aload_3
      31: invokeinterface #233,  2          // InterfaceMethod io/dekorate/deps/kubernetes/api/builder/Predicate.apply:(Ljava/lang/Object;)Ljava/lang/Boolean;
      36: invokevirtual #236                // Method java/lang/Boolean.booleanValue:()Z
      39: ifeq          47
      42: iconst_1
      43: invokestatic  #135                // Method java/lang/Boolean.valueOf:(Z)Ljava/lang/Boolean;
      46: areturn
      47: goto          10
      50: iconst_0
      51: invokestatic  #135                // Method java/lang/Boolean.valueOf:(Z)Ljava/lang/Boolean;
      54: areturn

  public A withSubscriptionStatuses(java.util.List<io.dekorate.deps.knative.flows.v1alpha1.SequenceSubscriptionStatus>);
    Code:
       0: aload_0
       1: getfield      #408                // Field subscriptionStatuses:Ljava/util/List;
       4: ifnull        27
       7: aload_0
       8: getfield      #107                // Field _visitables:Lio/dekorate/deps/kubernetes/api/builder/VisitableMap;
      11: ldc_w         #414                // String subscriptionStatuses
      14: invokevirtual #114                // Method io/dekorate/deps/kubernetes/api/builder/VisitableMap.get:(Ljava/lang/Object;)Ljava/util/List;
      17: aload_0
      18: getfield      #408                // Field subscriptionStatuses:Ljava/util/List;
      21: invokeinterface #271,  2          // InterfaceMethod java/util/List.removeAll:(Ljava/util/Collection;)Z
      26: pop
      27: aload_1
      28: ifnull        87
      31: aload_0
      32: new           #169                // class java/util/ArrayList
      35: dup
      36: invokespecial #170                // Method java/util/ArrayList."<init>":()V
      39: putfield      #408                // Field subscriptionStatuses:Ljava/util/List;
      42: aload_1
      43: invokeinterface #227,  1          // InterfaceMethod java/util/List.iterator:()Ljava/util/Iterator;
      48: astore_2
      49: aload_2
      50: invokeinterface #215,  1          // InterfaceMethod java/util/Iterator.hasNext:()Z
      55: ifeq          84
      58: aload_2
      59: invokeinterface #219,  1          // InterfaceMethod java/util/Iterator.next:()Ljava/lang/Object;
      64: checkcast     #416                // class io/dekorate/deps/knative/flows/v1alpha1/SequenceSubscriptionStatus
      67: astore_3
      68: aload_0
      69: iconst_1
      70: anewarray     #416                // class io/dekorate/deps/knative/flows/v1alpha1/SequenceSubscriptionStatus
      73: dup
      74: iconst_0
      75: aload_3
      76: aastore
      77: invokevirtual #449                // Method addToSubscriptionStatuses:([Lio/dekorate/deps/knative/flows/v1alpha1/SequenceSubscriptionStatus;)Lio/dekorate/deps/knative/flows/v1alpha1/SequenceStatusFluent;
      80: pop
      81: goto          49
      84: goto          92
      87: aload_0
      88: aconst_null
      89: putfield      #408                // Field subscriptionStatuses:Ljava/util/List;
      92: aload_0
      93: areturn

  public A withSubscriptionStatuses(io.dekorate.deps.knative.flows.v1alpha1.SequenceSubscriptionStatus...);
    Code:
       0: aload_0
       1: getfield      #408                // Field subscriptionStatuses:Ljava/util/List;
       4: ifnull        16
       7: aload_0
       8: getfield      #408                // Field subscriptionStatuses:Ljava/util/List;
      11: invokeinterface #277,  1          // InterfaceMethod java/util/List.clear:()V
      16: aload_1
      17: ifnull        60
      20: aload_1
      21: astore_2
      22: aload_2
      23: arraylength
      24: istore_3
      25: iconst_0
      26: istore        4
      28: iload         4
      30: iload_3
      31: if_icmpge     60
      34: aload_2
      35: iload         4
      37: aaload
      38: astore        5
      40: aload_0
      41: iconst_1
      42: anewarray     #416                // class io/dekorate/deps/knative/flows/v1alpha1/SequenceSubscriptionStatus
      45: dup
      46: iconst_0
      47: aload         5
      49: aastore
      50: invokevirtual #449                // Method addToSubscriptionStatuses:([Lio/dekorate/deps/knative/flows/v1alpha1/SequenceSubscriptionStatus;)Lio/dekorate/deps/knative/flows/v1alpha1/SequenceStatusFluent;
      53: pop
      54: iinc          4, 1
      57: goto          28
      60: aload_0
      61: areturn

  public java.lang.Boolean hasSubscriptionStatuses();
    Code:
       0: aload_0
       1: getfield      #408                // Field subscriptionStatuses:Ljava/util/List;
       4: ifnull        23
       7: aload_0
       8: getfield      #408                // Field subscriptionStatuses:Ljava/util/List;
      11: invokeinterface #281,  1          // InterfaceMethod java/util/List.isEmpty:()Z
      16: ifne          23
      19: iconst_1
      20: goto          24
      23: iconst_0
      24: invokestatic  #135                // Method java/lang/Boolean.valueOf:(Z)Ljava/lang/Boolean;
      27: areturn

  public io.dekorate.deps.knative.flows.v1alpha1.SequenceStatusFluent$SubscriptionStatusesNested<A> addNewSubscriptionStatus();
    Code:
       0: new           #10                 // class io/dekorate/deps/knative/flows/v1alpha1/SequenceStatusFluentImpl$SubscriptionStatusesNestedImpl
       3: dup
       4: aload_0
       5: invokespecial #455                // Method io/dekorate/deps/knative/flows/v1alpha1/SequenceStatusFluentImpl$SubscriptionStatusesNestedImpl."<init>":(Lio/dekorate/deps/knative/flows/v1alpha1/SequenceStatusFluentImpl;)V
       8: areturn

  public io.dekorate.deps.knative.flows.v1alpha1.SequenceStatusFluent$SubscriptionStatusesNested<A> addNewSubscriptionStatusLike(io.dekorate.deps.knative.flows.v1alpha1.SequenceSubscriptionStatus);
    Code:
       0: new           #10                 // class io/dekorate/deps/knative/flows/v1alpha1/SequenceStatusFluentImpl$SubscriptionStatusesNestedImpl
       3: dup
       4: aload_0
       5: iconst_m1
       6: aload_1
       7: invokespecial #461                // Method io/dekorate/deps/knative/flows/v1alpha1/SequenceStatusFluentImpl$SubscriptionStatusesNestedImpl."<init>":(Lio/dekorate/deps/knative/flows/v1alpha1/SequenceStatusFluentImpl;ILio/dekorate/deps/knative/flows/v1alpha1/SequenceSubscriptionStatus;)V
      10: areturn

  public io.dekorate.deps.knative.flows.v1alpha1.SequenceStatusFluent$SubscriptionStatusesNested<A> setNewSubscriptionStatusLike(int, io.dekorate.deps.knative.flows.v1alpha1.SequenceSubscriptionStatus);
    Code:
       0: new           #10                 // class io/dekorate/deps/knative/flows/v1alpha1/SequenceStatusFluentImpl$SubscriptionStatusesNestedImpl
       3: dup
       4: aload_0
       5: iload_1
       6: aload_2
       7: invokespecial #461                // Method io/dekorate/deps/knative/flows/v1alpha1/SequenceStatusFluentImpl$SubscriptionStatusesNestedImpl."<init>":(Lio/dekorate/deps/knative/flows/v1alpha1/SequenceStatusFluentImpl;ILio/dekorate/deps/knative/flows/v1alpha1/SequenceSubscriptionStatus;)V
      10: areturn

  public io.dekorate.deps.knative.flows.v1alpha1.SequenceStatusFluent$SubscriptionStatusesNested<A> editSubscriptionStatus(int);
    Code:
       0: aload_0
       1: getfield      #408                // Field subscriptionStatuses:Ljava/util/List;
       4: invokeinterface #182,  1          // InterfaceMethod java/util/List.size:()I
       9: iload_1
      10: if_icmpgt     24
      13: new           #299                // class java/lang/RuntimeException
      16: dup
      17: ldc_w         #469                // String Can\'t edit subscriptionStatuses. Index exceeds size.
      20: invokespecial #302                // Method java/lang/RuntimeException."<init>":(Ljava/lang/String;)V
      23: athrow
      24: aload_0
      25: iload_1
      26: aload_0
      27: iload_1
      28: invokevirtual #471                // Method buildSubscriptionStatus:(I)Lio/dekorate/deps/knative/flows/v1alpha1/SequenceSubscriptionStatus;
      31: invokevirtual #473                // Method setNewSubscriptionStatusLike:(ILio/dekorate/deps/knative/flows/v1alpha1/SequenceSubscriptionStatus;)Lio/dekorate/deps/knative/flows/v1alpha1/SequenceStatusFluent$SubscriptionStatusesNested;
      34: areturn

  public io.dekorate.deps.knative.flows.v1alpha1.SequenceStatusFluent$SubscriptionStatusesNested<A> editFirstSubscriptionStatus();
    Code:
       0: aload_0
       1: getfield      #408                // Field subscriptionStatuses:Ljava/util/List;
       4: invokeinterface #182,  1          // InterfaceMethod java/util/List.size:()I
       9: ifne          23
      12: new           #299                // class java/lang/RuntimeException
      15: dup
      16: ldc_w         #476                // String Can\'t edit first subscriptionStatuses. The list is empty.
      19: invokespecial #302                // Method java/lang/RuntimeException."<init>":(Ljava/lang/String;)V
      22: athrow
      23: aload_0
      24: iconst_0
      25: aload_0
      26: iconst_0
      27: invokevirtual #471                // Method buildSubscriptionStatus:(I)Lio/dekorate/deps/knative/flows/v1alpha1/SequenceSubscriptionStatus;
      30: invokevirtual #473                // Method setNewSubscriptionStatusLike:(ILio/dekorate/deps/knative/flows/v1alpha1/SequenceSubscriptionStatus;)Lio/dekorate/deps/knative/flows/v1alpha1/SequenceStatusFluent$SubscriptionStatusesNested;
      33: areturn

  public io.dekorate.deps.knative.flows.v1alpha1.SequenceStatusFluent$SubscriptionStatusesNested<A> editLastSubscriptionStatus();
    Code:
       0: aload_0
       1: getfield      #408                // Field subscriptionStatuses:Ljava/util/List;
       4: invokeinterface #182,  1          // InterfaceMethod java/util/List.size:()I
       9: iconst_1
      10: isub
      11: istore_1
      12: iload_1
      13: ifge          27
      16: new           #299                // class java/lang/RuntimeException
      19: dup
      20: ldc_w         #479                // String Can\'t edit last subscriptionStatuses. The list is empty.
      23: invokespecial #302                // Method java/lang/RuntimeException."<init>":(Ljava/lang/String;)V
      26: athrow
      27: aload_0
      28: iload_1
      29: aload_0
      30: iload_1
      31: invokevirtual #471                // Method buildSubscriptionStatus:(I)Lio/dekorate/deps/knative/flows/v1alpha1/SequenceSubscriptionStatus;
      34: invokevirtual #473                // Method setNewSubscriptionStatusLike:(ILio/dekorate/deps/knative/flows/v1alpha1/SequenceSubscriptionStatus;)Lio/dekorate/deps/knative/flows/v1alpha1/SequenceStatusFluent$SubscriptionStatusesNested;
      37: areturn

  public io.dekorate.deps.knative.flows.v1alpha1.SequenceStatusFluent$SubscriptionStatusesNested<A> editMatchingSubscriptionStatus(io.dekorate.deps.kubernetes.api.builder.Predicate<io.dekorate.deps.knative.flows.v1alpha1.SequenceSubscriptionStatusBuilder>);
    Code:
       0: iconst_m1
       1: istore_2
       2: iconst_0
       3: istore_3
       4: iload_3
       5: aload_0
       6: getfield      #408                // Field subscriptionStatuses:Ljava/util/List;
       9: invokeinterface #182,  1          // InterfaceMethod java/util/List.size:()I
      14: if_icmpge     50
      17: aload_1
      18: aload_0
      19: getfield      #408                // Field subscriptionStatuses:Ljava/util/List;
      22: iload_3
      23: invokeinterface #255,  2          // InterfaceMethod java/util/List.get:(I)Ljava/lang/Object;
      28: invokeinterface #233,  2          // InterfaceMethod io/dekorate/deps/kubernetes/api/builder/Predicate.apply:(Ljava/lang/Object;)Ljava/lang/Boolean;
      33: invokevirtual #236                // Method java/lang/Boolean.booleanValue:()Z
      36: ifeq          44
      39: iload_3
      40: istore_2
      41: goto          50
      44: iinc          3, 1
      47: goto          4
      50: iload_2
      51: ifge          65
      54: new           #299                // class java/lang/RuntimeException
      57: dup
      58: ldc_w         #484                // String Can\'t edit matching subscriptionStatuses. No match found.
      61: invokespecial #302                // Method java/lang/RuntimeException."<init>":(Ljava/lang/String;)V
      64: athrow
      65: aload_0
      66: iload_2
      67: aload_0
      68: iload_2
      69: invokevirtual #471                // Method buildSubscriptionStatus:(I)Lio/dekorate/deps/knative/flows/v1alpha1/SequenceSubscriptionStatus;
      72: invokevirtual #473                // Method setNewSubscriptionStatusLike:(ILio/dekorate/deps/knative/flows/v1alpha1/SequenceSubscriptionStatus;)Lio/dekorate/deps/knative/flows/v1alpha1/SequenceStatusFluent$SubscriptionStatusesNested;
      75: areturn

  public boolean equals(java.lang.Object);
    Code:
       0: aload_0
       1: aload_1
       2: if_acmpne     7
       5: iconst_1
       6: ireturn
       7: aload_1
       8: ifnull        22
      11: aload_0
      12: invokevirtual #491                // Method java/lang/Object.getClass:()Ljava/lang/Class;
      15: aload_1
      16: invokevirtual #491                // Method java/lang/Object.getClass:()Ljava/lang/Class;
      19: if_acmpeq     24
      22: iconst_0
      23: ireturn
      24: aload_1
      25: checkcast     #2                  // class io/dekorate/deps/knative/flows/v1alpha1/SequenceStatusFluentImpl
      28: astore_2
      29: aload_0
      30: getfield      #94                 // Field address:Lio/dekorate/deps/knative/duck/v1/AddressableBuilder;
      33: ifnull        53
      36: aload_0
      37: getfield      #94                 // Field address:Lio/dekorate/deps/knative/duck/v1/AddressableBuilder;
      40: aload_2
      41: getfield      #94                 // Field address:Lio/dekorate/deps/knative/duck/v1/AddressableBuilder;
      44: invokevirtual #493                // Method io/dekorate/deps/knative/duck/v1/AddressableBuilder.equals:(Ljava/lang/Object;)Z
      47: ifne          62
      50: goto          60
      53: aload_2
      54: getfield      #94                 // Field address:Lio/dekorate/deps/knative/duck/v1/AddressableBuilder;
      57: ifnull        62
      60: iconst_0
      61: ireturn
      62: aload_0
      63: getfield      #167                // Field channelStatuses:Ljava/util/List;
      66: ifnull        88
      69: aload_0
      70: getfield      #167                // Field channelStatuses:Ljava/util/List;
      73: aload_2
      74: getfield      #167                // Field channelStatuses:Ljava/util/List;
      77: invokeinterface #494,  2          // InterfaceMethod java/util/List.equals:(Ljava/lang/Object;)Z
      82: ifne          97
      85: goto          95
      88: aload_2
      89: getfield      #167                // Field channelStatuses:Ljava/util/List;
      92: ifnull        97
      95: iconst_0
      96: ireturn
      97: aload_0
      98: getfield      #323                // Field conditions:Ljava/util/List;
     101: ifnull        123
     104: aload_0
     105: getfield      #323                // Field conditions:Ljava/util/List;
     108: aload_2
     109: getfield      #323                // Field conditions:Ljava/util/List;
     112: invokeinterface #494,  2          // InterfaceMethod java/util/List.equals:(Ljava/lang/Object;)Z
     117: ifne          132
     120: goto          130
     123: aload_2
     124: getfield      #323                // Field conditions:Ljava/util/List;
     127: ifnull        132
     130: iconst_0
     131: ireturn
     132: aload_0
     133: getfield      #401                // Field observedGeneration:Ljava/lang/Long;
     136: ifnull        156
     139: aload_0
     140: getfield      #401                // Field observedGeneration:Ljava/lang/Long;
     143: aload_2
     144: getfield      #401                // Field observedGeneration:Ljava/lang/Long;
     147: invokevirtual #497                // Method java/lang/Long.equals:(Ljava/lang/Object;)Z
     150: ifne          165
     153: goto          163
     156: aload_2
     157: getfield      #401                // Field observedGeneration:Ljava/lang/Long;
     160: ifnull        165
     163: iconst_0
     164: ireturn
     165: aload_0
     166: getfield      #408                // Field subscriptionStatuses:Ljava/util/List;
     169: ifnull        191
     172: aload_0
     173: getfield      #408                // Field subscriptionStatuses:Ljava/util/List;
     176: aload_2
     177: getfield      #408                // Field subscriptionStatuses:Ljava/util/List;
     180: invokeinterface #494,  2          // InterfaceMethod java/util/List.equals:(Ljava/lang/Object;)Z
     185: ifne          200
     188: goto          198
     191: aload_2
     192: getfield      #408                // Field subscriptionStatuses:Ljava/util/List;
     195: ifnull        200
     198: iconst_0
     199: ireturn
     200: iconst_1
     201: ireturn
}
