Compiled from "CamelContextFactoryBean.java"
public class org.apache.camel.osgi.CamelContextFactoryBean extends org.apache.camel.spring.CamelContextFactoryBean implements org.springframework.osgi.context.BundleContextAware {
  private static final org.slf4j.Logger LOG;

  private org.osgi.framework.BundleContext bundleContext;

  public org.apache.camel.osgi.CamelContextFactoryBean();
    Code:
       0: aload_0
       1: invokespecial #1                  // Method org/apache/camel/spring/CamelContextFactoryBean."<init>":()V
       4: return

  public org.osgi.framework.BundleContext getBundleContext();
    Code:
       0: aload_0
       1: getfield      #2                  // Field bundleContext:Lorg/osgi/framework/BundleContext;
       4: areturn

  public void setBundleContext(org.osgi.framework.BundleContext);
    Code:
       0: getstatic     #3                  // Field LOG:Lorg/slf4j/Logger;
       3: ldc           #4                  // String Using BundleContext: {}
       5: aload_1
       6: invokeinterface #5,  3            // InterfaceMethod org/slf4j/Logger.debug:(Ljava/lang/String;Ljava/lang/Object;)V
      11: aload_0
      12: aload_1
      13: putfield      #2                  // Field bundleContext:Lorg/osgi/framework/BundleContext;
      16: return

  protected org.apache.camel.spring.SpringCamelContext createContext();
    Code:
       0: aload_0
       1: invokevirtual #6                  // Method newCamelContext:()Lorg/apache/camel/spring/SpringCamelContext;
       4: astore_1
       5: aload_0
       6: invokevirtual #7                  // Method isImplicitId:()Z
       9: ifne          20
      12: aload_1
      13: aload_0
      14: invokevirtual #8                  // Method getId:()Ljava/lang/String;
      17: invokevirtual #9                  // Method org/apache/camel/spring/SpringCamelContext.setName:(Ljava/lang/String;)V
      20: aload_1
      21: areturn

  protected org.apache.camel.spring.SpringCamelContext newCamelContext();
    Code:
       0: new           #10                 // class org/apache/camel/osgi/OsgiSpringCamelContext
       3: dup
       4: aload_0
       5: invokevirtual #11                 // Method getApplicationContext:()Lorg/springframework/context/ApplicationContext;
       8: aload_0
       9: invokevirtual #12                 // Method getBundleContext:()Lorg/osgi/framework/BundleContext;
      12: invokespecial #13                 // Method org/apache/camel/osgi/OsgiSpringCamelContext."<init>":(Lorg/springframework/context/ApplicationContext;Lorg/osgi/framework/BundleContext;)V
      15: areturn

  public void afterPropertiesSet() throws java.lang.Exception;
    Code:
       0: aload_0
       1: invokespecial #14                 // Method org/apache/camel/spring/CamelContextFactoryBean.afterPropertiesSet:()V
       4: aload_0
       5: invokevirtual #15                 // Method getContext:()Lorg/apache/camel/model/ModelCamelContext;
       8: checkcast     #16                 // class org/apache/camel/spring/SpringCamelContext
      11: invokevirtual #17                 // Method org/apache/camel/spring/SpringCamelContext.getManagementStrategy:()Lorg/apache/camel/spi/ManagementStrategy;
      14: new           #18                 // class org/apache/camel/core/osgi/OsgiCamelContextPublisher
      17: dup
      18: aload_0
      19: getfield      #2                  // Field bundleContext:Lorg/osgi/framework/BundleContext;
      22: invokespecial #19                 // Method org/apache/camel/core/osgi/OsgiCamelContextPublisher."<init>":(Lorg/osgi/framework/BundleContext;)V
      25: invokeinterface #20,  2           // InterfaceMethod org/apache/camel/spi/ManagementStrategy.addEventNotifier:(Lorg/apache/camel/spi/EventNotifier;)V
      30: aload_0
      31: invokevirtual #21                 // Method java/lang/Object.getClass:()Ljava/lang/Class;
      34: invokevirtual #22                 // Method java/lang/Class.getClassLoader:()Ljava/lang/ClassLoader;
      37: ldc           #23                 // String org.osgi.service.event.EventAdmin
      39: invokevirtual #24                 // Method java/lang/ClassLoader.loadClass:(Ljava/lang/String;)Ljava/lang/Class;
      42: pop
      43: aload_0
      44: invokevirtual #15                 // Method getContext:()Lorg/apache/camel/model/ModelCamelContext;
      47: checkcast     #16                 // class org/apache/camel/spring/SpringCamelContext
      50: invokevirtual #17                 // Method org/apache/camel/spring/SpringCamelContext.getManagementStrategy:()Lorg/apache/camel/spi/ManagementStrategy;
      53: new           #25                 // class org/apache/camel/core/osgi/OsgiEventAdminNotifier
      56: dup
      57: aload_0
      58: getfield      #2                  // Field bundleContext:Lorg/osgi/framework/BundleContext;
      61: invokespecial #26                 // Method org/apache/camel/core/osgi/OsgiEventAdminNotifier."<init>":(Lorg/osgi/framework/BundleContext;)V
      64: invokeinterface #20,  2           // InterfaceMethod org/apache/camel/spi/ManagementStrategy.addEventNotifier:(Lorg/apache/camel/spi/EventNotifier;)V
      69: goto          83
      72: astore_1
      73: getstatic     #3                  // Field LOG:Lorg/slf4j/Logger;
      76: ldc           #28                 // String EventAdmin package is not available, just don\'t use it
      78: invokeinterface #29,  2           // InterfaceMethod org/slf4j/Logger.debug:(Ljava/lang/String;)V
      83: return
    Exception table:
       from    to  target type
          30    69    72   Class java/lang/Throwable

  static {};
    Code:
       0: ldc_w         #30                 // class org/apache/camel/osgi/CamelContextFactoryBean
       3: invokestatic  #31                 // Method org/slf4j/LoggerFactory.getLogger:(Ljava/lang/Class;)Lorg/slf4j/Logger;
       6: putstatic     #3                  // Field LOG:Lorg/slf4j/Logger;
       9: return
}
