Compiled from "OsgiSpringCamelContext.java"
public class org.apache.camel.osgi.OsgiSpringCamelContext extends org.apache.camel.spring.SpringCamelContext {
  private final org.osgi.framework.BundleContext bundleContext;

  public org.apache.camel.osgi.OsgiSpringCamelContext(org.springframework.context.ApplicationContext, org.osgi.framework.BundleContext);
    Code:
       0: aload_0
       1: aload_1
       2: invokespecial #1                  // Method org/apache/camel/spring/SpringCamelContext."<init>":(Lorg/springframework/context/ApplicationContext;)V
       5: aload_0
       6: aload_2
       7: putfield      #2                  // Field bundleContext:Lorg/osgi/framework/BundleContext;
      10: aload_0
      11: aload_2
      12: invokestatic  #3                  // Method org/apache/camel/core/osgi/OsgiCamelContextHelper.osgiUpdate:(Lorg/apache/camel/impl/DefaultCamelContext;Lorg/osgi/framework/BundleContext;)V
      15: return

  protected org.apache.camel.TypeConverter createTypeConverter();
    Code:
       0: aload_0
       1: invokevirtual #4                  // Method java/lang/Object.getClass:()Ljava/lang/Class;
       4: invokestatic  #5                  // Method org/apache/camel/core/osgi/utils/BundleContextUtils.getBundleContext:(Ljava/lang/Class;)Lorg/osgi/framework/BundleContext;
       7: astore_1
       8: aload_1
       9: ifnonnull     17
      12: aload_0
      13: getfield      #2                  // Field bundleContext:Lorg/osgi/framework/BundleContext;
      16: astore_1
      17: new           #6                  // class org/apache/camel/core/osgi/OsgiFactoryFinderResolver
      20: dup
      21: aload_0
      22: getfield      #2                  // Field bundleContext:Lorg/osgi/framework/BundleContext;
      25: invokespecial #7                  // Method org/apache/camel/core/osgi/OsgiFactoryFinderResolver."<init>":(Lorg/osgi/framework/BundleContext;)V
      28: aload_0
      29: invokevirtual #8                  // Method getClassResolver:()Lorg/apache/camel/spi/ClassResolver;
      32: invokevirtual #9                  // Method org/apache/camel/core/osgi/OsgiFactoryFinderResolver.resolveDefaultFactoryFinder:(Lorg/apache/camel/spi/ClassResolver;)Lorg/apache/camel/spi/FactoryFinder;
      35: astore_2
      36: new           #10                 // class org/apache/camel/core/osgi/OsgiTypeConverter
      39: dup
      40: aload_1
      41: aload_0
      42: invokevirtual #11                 // Method getInjector:()Lorg/apache/camel/spi/Injector;
      45: aload_2
      46: invokespecial #12                 // Method org/apache/camel/core/osgi/OsgiTypeConverter."<init>":(Lorg/osgi/framework/BundleContext;Lorg/apache/camel/spi/Injector;Lorg/apache/camel/spi/FactoryFinder;)V
      49: areturn

  protected org.apache.camel.spi.Registry createRegistry();
    Code:
       0: aload_0
       1: aload_0
       2: invokespecial #13                 // Method org/apache/camel/spring/SpringCamelContext.createRegistry:()Lorg/apache/camel/spi/Registry;
       5: aload_0
       6: getfield      #2                  // Field bundleContext:Lorg/osgi/framework/BundleContext;
       9: invokestatic  #14                 // Method org/apache/camel/core/osgi/OsgiCamelContextHelper.wrapRegistry:(Lorg/apache/camel/CamelContext;Lorg/apache/camel/spi/Registry;Lorg/osgi/framework/BundleContext;)Lorg/apache/camel/spi/Registry;
      12: areturn

  public void setName(java.lang.String);
    Code:
       0: aload_0
       1: aload_1
       2: invokespecial #15                 // Method org/apache/camel/spring/SpringCamelContext.setName:(Ljava/lang/String;)V
       5: aload_0
       6: new           #16                 // class java/lang/StringBuilder
       9: dup
      10: invokespecial #17                 // Method java/lang/StringBuilder."<init>":()V
      13: aload_0
      14: getfield      #2                  // Field bundleContext:Lorg/osgi/framework/BundleContext;
      17: invokeinterface #18,  1           // InterfaceMethod org/osgi/framework/BundleContext.getBundle:()Lorg/osgi/framework/Bundle;
      22: invokeinterface #19,  1           // InterfaceMethod org/osgi/framework/Bundle.getBundleId:()J
      27: invokevirtual #20                 // Method java/lang/StringBuilder.append:(J)Ljava/lang/StringBuilder;
      30: ldc           #21                 // String -
      32: invokevirtual #22                 // Method java/lang/StringBuilder.append:(Ljava/lang/String;)Ljava/lang/StringBuilder;
      35: aload_1
      36: invokevirtual #22                 // Method java/lang/StringBuilder.append:(Ljava/lang/String;)Ljava/lang/StringBuilder;
      39: invokevirtual #23                 // Method java/lang/StringBuilder.toString:()Ljava/lang/String;
      42: invokespecial #24                 // Method org/apache/camel/spring/SpringCamelContext.setManagementName:(Ljava/lang/String;)V
      45: return
}
