Compiled from "CPU.java"
final class software.amazon.awssdk.services.mgn.model.CPU$BuilderImpl implements software.amazon.awssdk.services.mgn.model.CPU$Builder {
  private java.lang.Long cores;

  private java.lang.String modelName;

  private software.amazon.awssdk.services.mgn.model.CPU$BuilderImpl();
    Code:
       0: aload_0
       1: invokespecial #5                  // Method java/lang/Object."<init>":()V
       4: return

  private software.amazon.awssdk.services.mgn.model.CPU$BuilderImpl(software.amazon.awssdk.services.mgn.model.CPU);
    Code:
       0: aload_0
       1: invokespecial #5                  // Method java/lang/Object."<init>":()V
       4: aload_0
       5: aload_1
       6: invokestatic  #6                  // Method software/amazon/awssdk/services/mgn/model/CPU.access$400:(Lsoftware/amazon/awssdk/services/mgn/model/CPU;)Ljava/lang/Long;
       9: invokevirtual #7                  // Method cores:(Ljava/lang/Long;)Lsoftware/amazon/awssdk/services/mgn/model/CPU$Builder;
      12: pop
      13: aload_0
      14: aload_1
      15: invokestatic  #8                  // Method software/amazon/awssdk/services/mgn/model/CPU.access$500:(Lsoftware/amazon/awssdk/services/mgn/model/CPU;)Ljava/lang/String;
      18: invokevirtual #9                  // Method modelName:(Ljava/lang/String;)Lsoftware/amazon/awssdk/services/mgn/model/CPU$Builder;
      21: pop
      22: return

  public final java.lang.Long getCores();
    Code:
       0: aload_0
       1: getfield      #4                  // Field cores:Ljava/lang/Long;
       4: areturn

  public final software.amazon.awssdk.services.mgn.model.CPU$Builder cores(java.lang.Long);
    Code:
       0: aload_0
       1: aload_1
       2: putfield      #4                  // Field cores:Ljava/lang/Long;
       5: aload_0
       6: areturn

  public final void setCores(java.lang.Long);
    Code:
       0: aload_0
       1: aload_1
       2: putfield      #4                  // Field cores:Ljava/lang/Long;
       5: return

  public final java.lang.String getModelName();
    Code:
       0: aload_0
       1: getfield      #3                  // Field modelName:Ljava/lang/String;
       4: areturn

  public final software.amazon.awssdk.services.mgn.model.CPU$Builder modelName(java.lang.String);
    Code:
       0: aload_0
       1: aload_1
       2: putfield      #3                  // Field modelName:Ljava/lang/String;
       5: aload_0
       6: areturn

  public final void setModelName(java.lang.String);
    Code:
       0: aload_0
       1: aload_1
       2: putfield      #3                  // Field modelName:Ljava/lang/String;
       5: return

  public software.amazon.awssdk.services.mgn.model.CPU build();
    Code:
       0: new           #10                 // class software/amazon/awssdk/services/mgn/model/CPU
       3: dup
       4: aload_0
       5: aconst_null
       6: invokespecial #11                 // Method software/amazon/awssdk/services/mgn/model/CPU."<init>":(Lsoftware/amazon/awssdk/services/mgn/model/CPU$BuilderImpl;Lsoftware/amazon/awssdk/services/mgn/model/CPU$1;)V
       9: areturn

  public java.util.List<software.amazon.awssdk.core.SdkField<?>> sdkFields();
    Code:
       0: invokestatic  #12                 // Method software/amazon/awssdk/services/mgn/model/CPU.access$700:()Ljava/util/List;
       3: areturn

  public java.lang.Object build();
    Code:
       0: aload_0
       1: invokevirtual #13                 // Method build:()Lsoftware/amazon/awssdk/services/mgn/model/CPU;
       4: areturn

  static java.lang.Long access$000(software.amazon.awssdk.services.mgn.model.CPU$BuilderImpl);
    Code:
       0: aload_0
       1: getfield      #4                  // Field cores:Ljava/lang/Long;
       4: areturn

  static java.lang.String access$100(software.amazon.awssdk.services.mgn.model.CPU$BuilderImpl);
    Code:
       0: aload_0
       1: getfield      #3                  // Field modelName:Ljava/lang/String;
       4: areturn

  software.amazon.awssdk.services.mgn.model.CPU$BuilderImpl(software.amazon.awssdk.services.mgn.model.CPU, software.amazon.awssdk.services.mgn.model.CPU$1);
    Code:
       0: aload_0
       1: aload_1
       2: invokespecial #2                  // Method "<init>":(Lsoftware/amazon/awssdk/services/mgn/model/CPU;)V
       5: return

  software.amazon.awssdk.services.mgn.model.CPU$BuilderImpl(software.amazon.awssdk.services.mgn.model.CPU$1);
    Code:
       0: aload_0
       1: invokespecial #1                  // Method "<init>":()V
       4: return
}
