Compiled from "SourceServer.java"
final class software.amazon.awssdk.services.mgn.model.SourceServer$BuilderImpl implements software.amazon.awssdk.services.mgn.model.SourceServer$Builder {
  private java.lang.String arn;

  private software.amazon.awssdk.services.mgn.model.DataReplicationInfo dataReplicationInfo;

  private java.lang.Boolean isArchived;

  private software.amazon.awssdk.services.mgn.model.LaunchedInstance launchedInstance;

  private software.amazon.awssdk.services.mgn.model.LifeCycle lifeCycle;

  private software.amazon.awssdk.services.mgn.model.SourceProperties sourceProperties;

  private java.lang.String sourceServerID;

  private java.util.Map<java.lang.String, java.lang.String> tags;

  private software.amazon.awssdk.services.mgn.model.SourceServer$BuilderImpl();
    Code:
       0: aload_0
       1: invokespecial #11                 // Method java/lang/Object."<init>":()V
       4: aload_0
       5: invokestatic  #12                 // Method software/amazon/awssdk/core/util/DefaultSdkAutoConstructMap.getInstance:()Lsoftware/amazon/awssdk/core/util/DefaultSdkAutoConstructMap;
       8: putfield      #3                  // Field tags:Ljava/util/Map;
      11: return

  private software.amazon.awssdk.services.mgn.model.SourceServer$BuilderImpl(software.amazon.awssdk.services.mgn.model.SourceServer);
    Code:
       0: aload_0
       1: invokespecial #11                 // Method java/lang/Object."<init>":()V
       4: aload_0
       5: invokestatic  #12                 // Method software/amazon/awssdk/core/util/DefaultSdkAutoConstructMap.getInstance:()Lsoftware/amazon/awssdk/core/util/DefaultSdkAutoConstructMap;
       8: putfield      #3                  // Field tags:Ljava/util/Map;
      11: aload_0
      12: aload_1
      13: invokestatic  #13                 // Method software/amazon/awssdk/services/mgn/model/SourceServer.access$1000:(Lsoftware/amazon/awssdk/services/mgn/model/SourceServer;)Ljava/lang/String;
      16: invokevirtual #14                 // Method arn:(Ljava/lang/String;)Lsoftware/amazon/awssdk/services/mgn/model/SourceServer$Builder;
      19: pop
      20: aload_0
      21: aload_1
      22: invokestatic  #15                 // Method software/amazon/awssdk/services/mgn/model/SourceServer.access$1100:(Lsoftware/amazon/awssdk/services/mgn/model/SourceServer;)Lsoftware/amazon/awssdk/services/mgn/model/DataReplicationInfo;
      25: invokevirtual #16                 // Method dataReplicationInfo:(Lsoftware/amazon/awssdk/services/mgn/model/DataReplicationInfo;)Lsoftware/amazon/awssdk/services/mgn/model/SourceServer$Builder;
      28: pop
      29: aload_0
      30: aload_1
      31: invokestatic  #17                 // Method software/amazon/awssdk/services/mgn/model/SourceServer.access$1200:(Lsoftware/amazon/awssdk/services/mgn/model/SourceServer;)Ljava/lang/Boolean;
      34: invokevirtual #18                 // Method isArchived:(Ljava/lang/Boolean;)Lsoftware/amazon/awssdk/services/mgn/model/SourceServer$Builder;
      37: pop
      38: aload_0
      39: aload_1
      40: invokestatic  #19                 // Method software/amazon/awssdk/services/mgn/model/SourceServer.access$1300:(Lsoftware/amazon/awssdk/services/mgn/model/SourceServer;)Lsoftware/amazon/awssdk/services/mgn/model/LaunchedInstance;
      43: invokevirtual #20                 // Method launchedInstance:(Lsoftware/amazon/awssdk/services/mgn/model/LaunchedInstance;)Lsoftware/amazon/awssdk/services/mgn/model/SourceServer$Builder;
      46: pop
      47: aload_0
      48: aload_1
      49: invokestatic  #21                 // Method software/amazon/awssdk/services/mgn/model/SourceServer.access$1400:(Lsoftware/amazon/awssdk/services/mgn/model/SourceServer;)Lsoftware/amazon/awssdk/services/mgn/model/LifeCycle;
      52: invokevirtual #22                 // Method lifeCycle:(Lsoftware/amazon/awssdk/services/mgn/model/LifeCycle;)Lsoftware/amazon/awssdk/services/mgn/model/SourceServer$Builder;
      55: pop
      56: aload_0
      57: aload_1
      58: invokestatic  #23                 // Method software/amazon/awssdk/services/mgn/model/SourceServer.access$1500:(Lsoftware/amazon/awssdk/services/mgn/model/SourceServer;)Lsoftware/amazon/awssdk/services/mgn/model/SourceProperties;
      61: invokevirtual #24                 // Method sourceProperties:(Lsoftware/amazon/awssdk/services/mgn/model/SourceProperties;)Lsoftware/amazon/awssdk/services/mgn/model/SourceServer$Builder;
      64: pop
      65: aload_0
      66: aload_1
      67: invokestatic  #25                 // Method software/amazon/awssdk/services/mgn/model/SourceServer.access$1600:(Lsoftware/amazon/awssdk/services/mgn/model/SourceServer;)Ljava/lang/String;
      70: invokevirtual #26                 // Method sourceServerID:(Ljava/lang/String;)Lsoftware/amazon/awssdk/services/mgn/model/SourceServer$Builder;
      73: pop
      74: aload_0
      75: aload_1
      76: invokestatic  #27                 // Method software/amazon/awssdk/services/mgn/model/SourceServer.access$1700:(Lsoftware/amazon/awssdk/services/mgn/model/SourceServer;)Ljava/util/Map;
      79: invokevirtual #28                 // Method tags:(Ljava/util/Map;)Lsoftware/amazon/awssdk/services/mgn/model/SourceServer$Builder;
      82: pop
      83: return

  public final java.lang.String getArn();
    Code:
       0: aload_0
       1: getfield      #10                 // Field arn:Ljava/lang/String;
       4: areturn

  public final software.amazon.awssdk.services.mgn.model.SourceServer$Builder arn(java.lang.String);
    Code:
       0: aload_0
       1: aload_1
       2: putfield      #10                 // Field arn:Ljava/lang/String;
       5: aload_0
       6: areturn

  public final void setArn(java.lang.String);
    Code:
       0: aload_0
       1: aload_1
       2: putfield      #10                 // Field arn:Ljava/lang/String;
       5: return

  public final software.amazon.awssdk.services.mgn.model.DataReplicationInfo$Builder getDataReplicationInfo();
    Code:
       0: aload_0
       1: getfield      #9                  // Field dataReplicationInfo:Lsoftware/amazon/awssdk/services/mgn/model/DataReplicationInfo;
       4: ifnull        17
       7: aload_0
       8: getfield      #9                  // Field dataReplicationInfo:Lsoftware/amazon/awssdk/services/mgn/model/DataReplicationInfo;
      11: invokevirtual #29                 // Method software/amazon/awssdk/services/mgn/model/DataReplicationInfo.toBuilder:()Lsoftware/amazon/awssdk/services/mgn/model/DataReplicationInfo$Builder;
      14: goto          18
      17: aconst_null
      18: areturn

  public final software.amazon.awssdk.services.mgn.model.SourceServer$Builder dataReplicationInfo(software.amazon.awssdk.services.mgn.model.DataReplicationInfo);
    Code:
       0: aload_0
       1: aload_1
       2: putfield      #9                  // Field dataReplicationInfo:Lsoftware/amazon/awssdk/services/mgn/model/DataReplicationInfo;
       5: aload_0
       6: areturn

  public final void setDataReplicationInfo(software.amazon.awssdk.services.mgn.model.DataReplicationInfo$BuilderImpl);
    Code:
       0: aload_0
       1: aload_1
       2: ifnull        12
       5: aload_1
       6: invokevirtual #30                 // Method software/amazon/awssdk/services/mgn/model/DataReplicationInfo$BuilderImpl.build:()Lsoftware/amazon/awssdk/services/mgn/model/DataReplicationInfo;
       9: goto          13
      12: aconst_null
      13: putfield      #9                  // Field dataReplicationInfo:Lsoftware/amazon/awssdk/services/mgn/model/DataReplicationInfo;
      16: return

  public final java.lang.Boolean getIsArchived();
    Code:
       0: aload_0
       1: getfield      #8                  // Field isArchived:Ljava/lang/Boolean;
       4: areturn

  public final software.amazon.awssdk.services.mgn.model.SourceServer$Builder isArchived(java.lang.Boolean);
    Code:
       0: aload_0
       1: aload_1
       2: putfield      #8                  // Field isArchived:Ljava/lang/Boolean;
       5: aload_0
       6: areturn

  public final void setIsArchived(java.lang.Boolean);
    Code:
       0: aload_0
       1: aload_1
       2: putfield      #8                  // Field isArchived:Ljava/lang/Boolean;
       5: return

  public final software.amazon.awssdk.services.mgn.model.LaunchedInstance$Builder getLaunchedInstance();
    Code:
       0: aload_0
       1: getfield      #7                  // Field launchedInstance:Lsoftware/amazon/awssdk/services/mgn/model/LaunchedInstance;
       4: ifnull        17
       7: aload_0
       8: getfield      #7                  // Field launchedInstance:Lsoftware/amazon/awssdk/services/mgn/model/LaunchedInstance;
      11: invokevirtual #31                 // Method software/amazon/awssdk/services/mgn/model/LaunchedInstance.toBuilder:()Lsoftware/amazon/awssdk/services/mgn/model/LaunchedInstance$Builder;
      14: goto          18
      17: aconst_null
      18: areturn

  public final software.amazon.awssdk.services.mgn.model.SourceServer$Builder launchedInstance(software.amazon.awssdk.services.mgn.model.LaunchedInstance);
    Code:
       0: aload_0
       1: aload_1
       2: putfield      #7                  // Field launchedInstance:Lsoftware/amazon/awssdk/services/mgn/model/LaunchedInstance;
       5: aload_0
       6: areturn

  public final void setLaunchedInstance(software.amazon.awssdk.services.mgn.model.LaunchedInstance$BuilderImpl);
    Code:
       0: aload_0
       1: aload_1
       2: ifnull        12
       5: aload_1
       6: invokevirtual #32                 // Method software/amazon/awssdk/services/mgn/model/LaunchedInstance$BuilderImpl.build:()Lsoftware/amazon/awssdk/services/mgn/model/LaunchedInstance;
       9: goto          13
      12: aconst_null
      13: putfield      #7                  // Field launchedInstance:Lsoftware/amazon/awssdk/services/mgn/model/LaunchedInstance;
      16: return

  public final software.amazon.awssdk.services.mgn.model.LifeCycle$Builder getLifeCycle();
    Code:
       0: aload_0
       1: getfield      #6                  // Field lifeCycle:Lsoftware/amazon/awssdk/services/mgn/model/LifeCycle;
       4: ifnull        17
       7: aload_0
       8: getfield      #6                  // Field lifeCycle:Lsoftware/amazon/awssdk/services/mgn/model/LifeCycle;
      11: invokevirtual #33                 // Method software/amazon/awssdk/services/mgn/model/LifeCycle.toBuilder:()Lsoftware/amazon/awssdk/services/mgn/model/LifeCycle$Builder;
      14: goto          18
      17: aconst_null
      18: areturn

  public final software.amazon.awssdk.services.mgn.model.SourceServer$Builder lifeCycle(software.amazon.awssdk.services.mgn.model.LifeCycle);
    Code:
       0: aload_0
       1: aload_1
       2: putfield      #6                  // Field lifeCycle:Lsoftware/amazon/awssdk/services/mgn/model/LifeCycle;
       5: aload_0
       6: areturn

  public final void setLifeCycle(software.amazon.awssdk.services.mgn.model.LifeCycle$BuilderImpl);
    Code:
       0: aload_0
       1: aload_1
       2: ifnull        12
       5: aload_1
       6: invokevirtual #34                 // Method software/amazon/awssdk/services/mgn/model/LifeCycle$BuilderImpl.build:()Lsoftware/amazon/awssdk/services/mgn/model/LifeCycle;
       9: goto          13
      12: aconst_null
      13: putfield      #6                  // Field lifeCycle:Lsoftware/amazon/awssdk/services/mgn/model/LifeCycle;
      16: return

  public final software.amazon.awssdk.services.mgn.model.SourceProperties$Builder getSourceProperties();
    Code:
       0: aload_0
       1: getfield      #5                  // Field sourceProperties:Lsoftware/amazon/awssdk/services/mgn/model/SourceProperties;
       4: ifnull        17
       7: aload_0
       8: getfield      #5                  // Field sourceProperties:Lsoftware/amazon/awssdk/services/mgn/model/SourceProperties;
      11: invokevirtual #35                 // Method software/amazon/awssdk/services/mgn/model/SourceProperties.toBuilder:()Lsoftware/amazon/awssdk/services/mgn/model/SourceProperties$Builder;
      14: goto          18
      17: aconst_null
      18: areturn

  public final software.amazon.awssdk.services.mgn.model.SourceServer$Builder sourceProperties(software.amazon.awssdk.services.mgn.model.SourceProperties);
    Code:
       0: aload_0
       1: aload_1
       2: putfield      #5                  // Field sourceProperties:Lsoftware/amazon/awssdk/services/mgn/model/SourceProperties;
       5: aload_0
       6: areturn

  public final void setSourceProperties(software.amazon.awssdk.services.mgn.model.SourceProperties$BuilderImpl);
    Code:
       0: aload_0
       1: aload_1
       2: ifnull        12
       5: aload_1
       6: invokevirtual #36                 // Method software/amazon/awssdk/services/mgn/model/SourceProperties$BuilderImpl.build:()Lsoftware/amazon/awssdk/services/mgn/model/SourceProperties;
       9: goto          13
      12: aconst_null
      13: putfield      #5                  // Field sourceProperties:Lsoftware/amazon/awssdk/services/mgn/model/SourceProperties;
      16: return

  public final java.lang.String getSourceServerID();
    Code:
       0: aload_0
       1: getfield      #4                  // Field sourceServerID:Ljava/lang/String;
       4: areturn

  public final software.amazon.awssdk.services.mgn.model.SourceServer$Builder sourceServerID(java.lang.String);
    Code:
       0: aload_0
       1: aload_1
       2: putfield      #4                  // Field sourceServerID:Ljava/lang/String;
       5: aload_0
       6: areturn

  public final void setSourceServerID(java.lang.String);
    Code:
       0: aload_0
       1: aload_1
       2: putfield      #4                  // Field sourceServerID:Ljava/lang/String;
       5: return

  public final java.util.Map<java.lang.String, java.lang.String> getTags();
    Code:
       0: aload_0
       1: getfield      #3                  // Field tags:Ljava/util/Map;
       4: instanceof    #37                 // class software/amazon/awssdk/core/util/SdkAutoConstructMap
       7: ifeq          12
      10: aconst_null
      11: areturn
      12: aload_0
      13: getfield      #3                  // Field tags:Ljava/util/Map;
      16: areturn

  public final software.amazon.awssdk.services.mgn.model.SourceServer$Builder tags(java.util.Map<java.lang.String, java.lang.String>);
    Code:
       0: aload_0
       1: aload_1
       2: invokestatic  #38                 // Method software/amazon/awssdk/services/mgn/model/TagsMapCopier.copy:(Ljava/util/Map;)Ljava/util/Map;
       5: putfield      #3                  // Field tags:Ljava/util/Map;
       8: aload_0
       9: areturn

  public final void setTags(java.util.Map<java.lang.String, java.lang.String>);
    Code:
       0: aload_0
       1: aload_1
       2: invokestatic  #38                 // Method software/amazon/awssdk/services/mgn/model/TagsMapCopier.copy:(Ljava/util/Map;)Ljava/util/Map;
       5: putfield      #3                  // Field tags:Ljava/util/Map;
       8: return

  public software.amazon.awssdk.services.mgn.model.SourceServer build();
    Code:
       0: new           #39                 // class software/amazon/awssdk/services/mgn/model/SourceServer
       3: dup
       4: aload_0
       5: aconst_null
       6: invokespecial #40                 // Method software/amazon/awssdk/services/mgn/model/SourceServer."<init>":(Lsoftware/amazon/awssdk/services/mgn/model/SourceServer$BuilderImpl;Lsoftware/amazon/awssdk/services/mgn/model/SourceServer$1;)V
       9: areturn

  public java.util.List<software.amazon.awssdk.core.SdkField<?>> sdkFields();
    Code:
       0: invokestatic  #41                 // Method software/amazon/awssdk/services/mgn/model/SourceServer.access$1900:()Ljava/util/List;
       3: areturn

  public java.lang.Object build();
    Code:
       0: aload_0
       1: invokevirtual #42                 // Method build:()Lsoftware/amazon/awssdk/services/mgn/model/SourceServer;
       4: areturn

  static java.lang.String access$000(software.amazon.awssdk.services.mgn.model.SourceServer$BuilderImpl);
    Code:
       0: aload_0
       1: getfield      #10                 // Field arn:Ljava/lang/String;
       4: areturn

  static software.amazon.awssdk.services.mgn.model.DataReplicationInfo access$100(software.amazon.awssdk.services.mgn.model.SourceServer$BuilderImpl);
    Code:
       0: aload_0
       1: getfield      #9                  // Field dataReplicationInfo:Lsoftware/amazon/awssdk/services/mgn/model/DataReplicationInfo;
       4: areturn

  static java.lang.Boolean access$200(software.amazon.awssdk.services.mgn.model.SourceServer$BuilderImpl);
    Code:
       0: aload_0
       1: getfield      #8                  // Field isArchived:Ljava/lang/Boolean;
       4: areturn

  static software.amazon.awssdk.services.mgn.model.LaunchedInstance access$300(software.amazon.awssdk.services.mgn.model.SourceServer$BuilderImpl);
    Code:
       0: aload_0
       1: getfield      #7                  // Field launchedInstance:Lsoftware/amazon/awssdk/services/mgn/model/LaunchedInstance;
       4: areturn

  static software.amazon.awssdk.services.mgn.model.LifeCycle access$400(software.amazon.awssdk.services.mgn.model.SourceServer$BuilderImpl);
    Code:
       0: aload_0
       1: getfield      #6                  // Field lifeCycle:Lsoftware/amazon/awssdk/services/mgn/model/LifeCycle;
       4: areturn

  static software.amazon.awssdk.services.mgn.model.SourceProperties access$500(software.amazon.awssdk.services.mgn.model.SourceServer$BuilderImpl);
    Code:
       0: aload_0
       1: getfield      #5                  // Field sourceProperties:Lsoftware/amazon/awssdk/services/mgn/model/SourceProperties;
       4: areturn

  static java.lang.String access$600(software.amazon.awssdk.services.mgn.model.SourceServer$BuilderImpl);
    Code:
       0: aload_0
       1: getfield      #4                  // Field sourceServerID:Ljava/lang/String;
       4: areturn

  static java.util.Map access$700(software.amazon.awssdk.services.mgn.model.SourceServer$BuilderImpl);
    Code:
       0: aload_0
       1: getfield      #3                  // Field tags:Ljava/util/Map;
       4: areturn

  software.amazon.awssdk.services.mgn.model.SourceServer$BuilderImpl(software.amazon.awssdk.services.mgn.model.SourceServer, software.amazon.awssdk.services.mgn.model.SourceServer$1);
    Code:
       0: aload_0
       1: aload_1
       2: invokespecial #2                  // Method "<init>":(Lsoftware/amazon/awssdk/services/mgn/model/SourceServer;)V
       5: return

  software.amazon.awssdk.services.mgn.model.SourceServer$BuilderImpl(software.amazon.awssdk.services.mgn.model.SourceServer$1);
    Code:
       0: aload_0
       1: invokespecial #1                  // Method "<init>":()V
       4: return
}
