Compiled from "UpdateLaunchConfigurationResponse.java"
public interface software.amazon.awssdk.services.mgn.model.UpdateLaunchConfigurationResponse$Builder extends software.amazon.awssdk.services.mgn.model.MgnResponse$Builder, software.amazon.awssdk.core.SdkPojo, software.amazon.awssdk.utils.builder.CopyableBuilder<software.amazon.awssdk.services.mgn.model.UpdateLaunchConfigurationResponse$Builder, software.amazon.awssdk.services.mgn.model.UpdateLaunchConfigurationResponse> {
  public abstract software.amazon.awssdk.services.mgn.model.UpdateLaunchConfigurationResponse$Builder copyPrivateIp(java.lang.Boolean);

  public abstract software.amazon.awssdk.services.mgn.model.UpdateLaunchConfigurationResponse$Builder copyTags(java.lang.Boolean);

  public abstract software.amazon.awssdk.services.mgn.model.UpdateLaunchConfigurationResponse$Builder ec2LaunchTemplateID(java.lang.String);

  public abstract software.amazon.awssdk.services.mgn.model.UpdateLaunchConfigurationResponse$Builder launchDisposition(java.lang.String);

  public abstract software.amazon.awssdk.services.mgn.model.UpdateLaunchConfigurationResponse$Builder launchDisposition(software.amazon.awssdk.services.mgn.model.LaunchDisposition);

  public abstract software.amazon.awssdk.services.mgn.model.UpdateLaunchConfigurationResponse$Builder licensing(software.amazon.awssdk.services.mgn.model.Licensing);

  public default software.amazon.awssdk.services.mgn.model.UpdateLaunchConfigurationResponse$Builder licensing(java.util.function.Consumer<software.amazon.awssdk.services.mgn.model.Licensing$Builder>);
    Code:
       0: aload_0
       1: invokestatic  #1                  // Method software/amazon/awssdk/services/mgn/model/Licensing.builder:()Lsoftware/amazon/awssdk/services/mgn/model/Licensing$Builder;
       4: aload_1
       5: invokeinterface #2,  2            // InterfaceMethod software/amazon/awssdk/services/mgn/model/Licensing$Builder.applyMutation:(Ljava/util/function/Consumer;)Lsoftware/amazon/awssdk/utils/builder/SdkBuilder;
      10: checkcast     #3                  // class software/amazon/awssdk/services/mgn/model/Licensing$Builder
      13: invokeinterface #4,  1            // InterfaceMethod software/amazon/awssdk/services/mgn/model/Licensing$Builder.build:()Ljava/lang/Object;
      18: checkcast     #5                  // class software/amazon/awssdk/services/mgn/model/Licensing
      21: invokeinterface #6,  2            // InterfaceMethod licensing:(Lsoftware/amazon/awssdk/services/mgn/model/Licensing;)Lsoftware/amazon/awssdk/services/mgn/model/UpdateLaunchConfigurationResponse$Builder;
      26: areturn

  public abstract software.amazon.awssdk.services.mgn.model.UpdateLaunchConfigurationResponse$Builder name(java.lang.String);

  public abstract software.amazon.awssdk.services.mgn.model.UpdateLaunchConfigurationResponse$Builder sourceServerID(java.lang.String);

  public abstract software.amazon.awssdk.services.mgn.model.UpdateLaunchConfigurationResponse$Builder targetInstanceTypeRightSizingMethod(java.lang.String);

  public abstract software.amazon.awssdk.services.mgn.model.UpdateLaunchConfigurationResponse$Builder targetInstanceTypeRightSizingMethod(software.amazon.awssdk.services.mgn.model.TargetInstanceTypeRightSizingMethod);
}
