Compiled from "ContextLifecycleScheduledTaskRegistrar.java"
public class org.springframework.scheduling.config.ContextLifecycleScheduledTaskRegistrar extends org.springframework.scheduling.config.ScheduledTaskRegistrar implements org.springframework.context.ApplicationContextAware, org.springframework.context.ApplicationListener<org.springframework.context.event.ContextRefreshedEvent> {
  private org.springframework.context.ApplicationContext applicationContext;

  public org.springframework.scheduling.config.ContextLifecycleScheduledTaskRegistrar();
    Code:
       0: aload_0
       1: invokespecial #1                  // Method org/springframework/scheduling/config/ScheduledTaskRegistrar."<init>":()V
       4: return

  public void setApplicationContext(org.springframework.context.ApplicationContext);
    Code:
       0: aload_0
       1: aload_1
       2: putfield      #2                  // Field applicationContext:Lorg/springframework/context/ApplicationContext;
       5: return

  public void afterPropertiesSet();
    Code:
       0: aload_0
       1: getfield      #2                  // Field applicationContext:Lorg/springframework/context/ApplicationContext;
       4: ifnonnull     11
       7: aload_0
       8: invokevirtual #3                  // Method scheduleTasks:()V
      11: return

  public void onApplicationEvent(org.springframework.context.event.ContextRefreshedEvent);
    Code:
       0: aload_1
       1: invokevirtual #4                  // Method org/springframework/context/event/ContextRefreshedEvent.getApplicationContext:()Lorg/springframework/context/ApplicationContext;
       4: aload_0
       5: getfield      #2                  // Field applicationContext:Lorg/springframework/context/ApplicationContext;
       8: if_acmpeq     12
      11: return
      12: aload_0
      13: invokevirtual #3                  // Method scheduleTasks:()V
      16: return

  public void onApplicationEvent(org.springframework.context.ApplicationEvent);
    Code:
       0: aload_0
       1: aload_1
       2: checkcast     #5                  // class org/springframework/context/event/ContextRefreshedEvent
       5: invokevirtual #6                  // Method onApplicationEvent:(Lorg/springframework/context/event/ContextRefreshedEvent;)V
       8: return
}
