Compiled from "UndertowHeaderMap.java"
class org.jboss.ws.undertow_httpspi.UndertowHeaderMap$1 implements java.util.Map$Entry<java.lang.String, java.util.List<java.lang.String>> {
  final java.lang.String val$key;

  final java.util.List val$headerValueList;

  final org.jboss.ws.undertow_httpspi.UndertowHeaderMap this$0;

  org.jboss.ws.undertow_httpspi.UndertowHeaderMap$1(org.jboss.ws.undertow_httpspi.UndertowHeaderMap, java.lang.String, java.util.List);
    Code:
       0: aload_0
       1: aload_1
       2: putfield      #1                  // Field this$0:Lorg/jboss/ws/undertow_httpspi/UndertowHeaderMap;
       5: aload_0
       6: aload_2
       7: putfield      #2                  // Field val$key:Ljava/lang/String;
      10: aload_0
      11: aload_3
      12: putfield      #3                  // Field val$headerValueList:Ljava/util/List;
      15: aload_0
      16: invokespecial #4                  // Method java/lang/Object."<init>":()V
      19: return

  public java.lang.String getKey();
    Code:
       0: aload_0
       1: getfield      #2                  // Field val$key:Ljava/lang/String;
       4: areturn

  public java.util.List<java.lang.String> getValue();
    Code:
       0: aload_0
       1: getfield      #3                  // Field val$headerValueList:Ljava/util/List;
       4: areturn

  public java.util.List<java.lang.String> setValue(java.util.List<java.lang.String>);
    Code:
       0: aload_0
       1: getfield      #1                  // Field this$0:Lorg/jboss/ws/undertow_httpspi/UndertowHeaderMap;
       4: invokestatic  #5                  // Method org/jboss/ws/undertow_httpspi/UndertowHeaderMap.access$000:(Lorg/jboss/ws/undertow_httpspi/UndertowHeaderMap;)Lio/undertow/util/HeaderMap;
       7: aload_0
       8: getfield      #2                  // Field val$key:Ljava/lang/String;
      11: invokevirtual #6                  // Method io/undertow/util/HeaderMap.get:(Ljava/lang/String;)Lio/undertow/util/HeaderValues;
      14: astore_2
      15: aload_2
      16: invokeinterface #7,  1            // InterfaceMethod java/util/List.isEmpty:()Z
      21: ifeq          26
      24: aconst_null
      25: astore_2
      26: aload_0
      27: getfield      #1                  // Field this$0:Lorg/jboss/ws/undertow_httpspi/UndertowHeaderMap;
      30: invokestatic  #5                  // Method org/jboss/ws/undertow_httpspi/UndertowHeaderMap.access$000:(Lorg/jboss/ws/undertow_httpspi/UndertowHeaderMap;)Lio/undertow/util/HeaderMap;
      33: new           #8                  // class io/undertow/util/HttpString
      36: dup
      37: aload_0
      38: getfield      #2                  // Field val$key:Ljava/lang/String;
      41: invokespecial #9                  // Method io/undertow/util/HttpString."<init>":(Ljava/lang/String;)V
      44: aload_1
      45: invokevirtual #10                 // Method io/undertow/util/HeaderMap.addAll:(Lio/undertow/util/HttpString;Ljava/util/Collection;)Lio/undertow/util/HeaderMap;
      48: pop
      49: aload_2
      50: areturn

  public java.lang.Object setValue(java.lang.Object);
    Code:
       0: aload_0
       1: aload_1
       2: checkcast     #11                 // class java/util/List
       5: invokevirtual #12                 // Method setValue:(Ljava/util/List;)Ljava/util/List;
       8: areturn

  public java.lang.Object getValue();
    Code:
       0: aload_0
       1: invokevirtual #13                 // Method getValue:()Ljava/util/List;
       4: areturn

  public java.lang.Object getKey();
    Code:
       0: aload_0
       1: invokevirtual #14                 // Method getKey:()Ljava/lang/String;
       4: areturn
}
