Compiled from "JwtAuthProvider.kt"
final class dev.neeffect.nee.ctx.web.jwt.JwtAuthProvider$getSecurityContext$1$1$2<T> implements java.util.function.Supplier<dev.neeffect.nee.effects.Out<dev.neeffect.nee.effects.security.SecurityError, ? extends dev.neeffect.nee.effects.security.SecurityCtx<USER, ROLE>>> {
  final io.fusionauth.jwt.domain.JWT $jwt;

  public java.lang.Object get();
    Code:
       0: aload_0
       1: invokevirtual #12                 // Method get:()Ldev/neeffect/nee/effects/Out;
       4: areturn

  public final dev.neeffect.nee.effects.Out<dev.neeffect.nee.effects.security.SecurityError, dev.neeffect.nee.effects.security.SecurityCtx<USER, ROLE>> get();
    Code:
       0: getstatic     #19                 // Field dev/neeffect/nee/effects/Out.Companion:Ldev/neeffect/nee/effects/Out$Companion;
       3: new           #21                 // class dev/neeffect/nee/effects/security/SecurityErrorType$MalformedCredentials
       6: dup
       7: new           #23                 // class java/lang/StringBuilder
      10: dup
      11: invokespecial #27                 // Method java/lang/StringBuilder."<init>":()V
      14: ldc           #29                 // String user not decoded from
      16: invokevirtual #33                 // Method java/lang/StringBuilder.append:(Ljava/lang/String;)Ljava/lang/StringBuilder;
      19: aload_0
      20: getfield      #37                 // Field $jwt:Lio/fusionauth/jwt/domain/JWT;
      23: invokevirtual #40                 // Method java/lang/StringBuilder.append:(Ljava/lang/Object;)Ljava/lang/StringBuilder;
      26: invokevirtual #44                 // Method java/lang/StringBuilder.toString:()Ljava/lang/String;
      29: invokespecial #47                 // Method dev/neeffect/nee/effects/security/SecurityErrorType$MalformedCredentials."<init>":(Ljava/lang/String;)V
      32: invokevirtual #53                 // Method dev/neeffect/nee/effects/Out$Companion.left:(Ljava/lang/Object;)Ldev/neeffect/nee/effects/Out;
      35: areturn

  dev.neeffect.nee.ctx.web.jwt.JwtAuthProvider$getSecurityContext$1$1$2(io.fusionauth.jwt.domain.JWT);
    Code:
       0: aload_0
       1: aload_1
       2: putfield      #37                 // Field $jwt:Lio/fusionauth/jwt/domain/JWT;
       5: aload_0
       6: invokespecial #57                 // Method java/lang/Object."<init>":()V
       9: return
}
