Compiled from "CacheSupport.java"
public abstract class org.infinispan.cache.impl.CacheSupport<K, V> implements org.infinispan.commons.api.BasicCache<K, V> {
  protected long defaultLifespan;

  protected long defaultMaxIdleTime;

  protected org.infinispan.cache.impl.CacheSupport();
    Code:
       0: aload_0
       1: lconst_0
       2: lconst_0
       3: invokespecial #1                  // Method "<init>":(JJ)V
       6: return

  protected org.infinispan.cache.impl.CacheSupport(long, long);
    Code:
       0: aload_0
       1: invokespecial #2                  // Method java/lang/Object."<init>":()V
       4: aload_0
       5: lload_1
       6: putfield      #3                  // Field defaultLifespan:J
       9: aload_0
      10: lload_3
      11: putfield      #4                  // Field defaultMaxIdleTime:J
      14: return

  public final V put(K, V);
    Code:
       0: aload_0
       1: aload_1
       2: aload_2
       3: aload_0
       4: getfield      #3                  // Field defaultLifespan:J
       7: getstatic     #5                  // Field java/util/concurrent/TimeUnit.MILLISECONDS:Ljava/util/concurrent/TimeUnit;
      10: aload_0
      11: getfield      #4                  // Field defaultMaxIdleTime:J
      14: getstatic     #5                  // Field java/util/concurrent/TimeUnit.MILLISECONDS:Ljava/util/concurrent/TimeUnit;
      17: invokevirtual #6                  // Method put:(Ljava/lang/Object;Ljava/lang/Object;JLjava/util/concurrent/TimeUnit;JLjava/util/concurrent/TimeUnit;)Ljava/lang/Object;
      20: areturn

  protected abstract void set(K, V);

  public final void putAll(java.util.Map<? extends K, ? extends V>);
    Code:
       0: aload_0
       1: aload_1
       2: aload_0
       3: getfield      #3                  // Field defaultLifespan:J
       6: getstatic     #5                  // Field java/util/concurrent/TimeUnit.MILLISECONDS:Ljava/util/concurrent/TimeUnit;
       9: aload_0
      10: getfield      #4                  // Field defaultMaxIdleTime:J
      13: getstatic     #5                  // Field java/util/concurrent/TimeUnit.MILLISECONDS:Ljava/util/concurrent/TimeUnit;
      16: invokevirtual #7                  // Method putAll:(Ljava/util/Map;JLjava/util/concurrent/TimeUnit;JLjava/util/concurrent/TimeUnit;)V
      19: return

  public final org.infinispan.commons.util.concurrent.NotifyingFuture<V> putAsync(K, V);
    Code:
       0: aload_0
       1: aload_1
       2: aload_2
       3: aload_0
       4: getfield      #3                  // Field defaultLifespan:J
       7: getstatic     #5                  // Field java/util/concurrent/TimeUnit.MILLISECONDS:Ljava/util/concurrent/TimeUnit;
      10: aload_0
      11: getfield      #4                  // Field defaultMaxIdleTime:J
      14: getstatic     #5                  // Field java/util/concurrent/TimeUnit.MILLISECONDS:Ljava/util/concurrent/TimeUnit;
      17: invokevirtual #8                  // Method putAsync:(Ljava/lang/Object;Ljava/lang/Object;JLjava/util/concurrent/TimeUnit;JLjava/util/concurrent/TimeUnit;)Lorg/infinispan/commons/util/concurrent/NotifyingFuture;
      20: areturn

  public final V putIfAbsent(K, V);
    Code:
       0: aload_0
       1: aload_1
       2: aload_2
       3: aload_0
       4: getfield      #3                  // Field defaultLifespan:J
       7: getstatic     #5                  // Field java/util/concurrent/TimeUnit.MILLISECONDS:Ljava/util/concurrent/TimeUnit;
      10: aload_0
      11: getfield      #4                  // Field defaultMaxIdleTime:J
      14: getstatic     #5                  // Field java/util/concurrent/TimeUnit.MILLISECONDS:Ljava/util/concurrent/TimeUnit;
      17: invokevirtual #9                  // Method putIfAbsent:(Ljava/lang/Object;Ljava/lang/Object;JLjava/util/concurrent/TimeUnit;JLjava/util/concurrent/TimeUnit;)Ljava/lang/Object;
      20: areturn

  public final org.infinispan.commons.util.concurrent.NotifyingFuture<V> putAsync(K, V, long, java.util.concurrent.TimeUnit);
    Code:
       0: aload_0
       1: aload_1
       2: aload_2
       3: lload_3
       4: aload         5
       6: aload_0
       7: getfield      #4                  // Field defaultMaxIdleTime:J
      10: getstatic     #5                  // Field java/util/concurrent/TimeUnit.MILLISECONDS:Ljava/util/concurrent/TimeUnit;
      13: invokevirtual #8                  // Method putAsync:(Ljava/lang/Object;Ljava/lang/Object;JLjava/util/concurrent/TimeUnit;JLjava/util/concurrent/TimeUnit;)Lorg/infinispan/commons/util/concurrent/NotifyingFuture;
      16: areturn

  public final org.infinispan.commons.util.concurrent.NotifyingFuture<java.lang.Void> putAllAsync(java.util.Map<? extends K, ? extends V>);
    Code:
       0: aload_0
       1: aload_1
       2: aload_0
       3: getfield      #3                  // Field defaultLifespan:J
       6: getstatic     #5                  // Field java/util/concurrent/TimeUnit.MILLISECONDS:Ljava/util/concurrent/TimeUnit;
       9: aload_0
      10: getfield      #4                  // Field defaultMaxIdleTime:J
      13: getstatic     #5                  // Field java/util/concurrent/TimeUnit.MILLISECONDS:Ljava/util/concurrent/TimeUnit;
      16: invokevirtual #10                 // Method putAllAsync:(Ljava/util/Map;JLjava/util/concurrent/TimeUnit;JLjava/util/concurrent/TimeUnit;)Lorg/infinispan/commons/util/concurrent/NotifyingFuture;
      19: areturn

  public final org.infinispan.commons.util.concurrent.NotifyingFuture<java.lang.Void> putAllAsync(java.util.Map<? extends K, ? extends V>, long, java.util.concurrent.TimeUnit);
    Code:
       0: aload_0
       1: aload_1
       2: lload_2
       3: aload         4
       5: aload_0
       6: getfield      #4                  // Field defaultMaxIdleTime:J
       9: getstatic     #5                  // Field java/util/concurrent/TimeUnit.MILLISECONDS:Ljava/util/concurrent/TimeUnit;
      12: invokevirtual #10                 // Method putAllAsync:(Ljava/util/Map;JLjava/util/concurrent/TimeUnit;JLjava/util/concurrent/TimeUnit;)Lorg/infinispan/commons/util/concurrent/NotifyingFuture;
      15: areturn

  public final org.infinispan.commons.util.concurrent.NotifyingFuture<V> putIfAbsentAsync(K, V);
    Code:
       0: aload_0
       1: aload_1
       2: aload_2
       3: aload_0
       4: getfield      #3                  // Field defaultLifespan:J
       7: getstatic     #5                  // Field java/util/concurrent/TimeUnit.MILLISECONDS:Ljava/util/concurrent/TimeUnit;
      10: aload_0
      11: getfield      #4                  // Field defaultMaxIdleTime:J
      14: getstatic     #5                  // Field java/util/concurrent/TimeUnit.MILLISECONDS:Ljava/util/concurrent/TimeUnit;
      17: invokevirtual #11                 // Method putIfAbsentAsync:(Ljava/lang/Object;Ljava/lang/Object;JLjava/util/concurrent/TimeUnit;JLjava/util/concurrent/TimeUnit;)Lorg/infinispan/commons/util/concurrent/NotifyingFuture;
      20: areturn

  public final org.infinispan.commons.util.concurrent.NotifyingFuture<V> putIfAbsentAsync(K, V, long, java.util.concurrent.TimeUnit);
    Code:
       0: aload_0
       1: aload_1
       2: aload_2
       3: lload_3
       4: aload         5
       6: aload_0
       7: getfield      #4                  // Field defaultMaxIdleTime:J
      10: getstatic     #5                  // Field java/util/concurrent/TimeUnit.MILLISECONDS:Ljava/util/concurrent/TimeUnit;
      13: invokevirtual #11                 // Method putIfAbsentAsync:(Ljava/lang/Object;Ljava/lang/Object;JLjava/util/concurrent/TimeUnit;JLjava/util/concurrent/TimeUnit;)Lorg/infinispan/commons/util/concurrent/NotifyingFuture;
      16: areturn

  public final org.infinispan.commons.util.concurrent.NotifyingFuture<V> replaceAsync(K, V, long, java.util.concurrent.TimeUnit);
    Code:
       0: aload_0
       1: aload_1
       2: aload_2
       3: lload_3
       4: aload         5
       6: aload_0
       7: getfield      #4                  // Field defaultMaxIdleTime:J
      10: getstatic     #5                  // Field java/util/concurrent/TimeUnit.MILLISECONDS:Ljava/util/concurrent/TimeUnit;
      13: invokevirtual #12                 // Method replaceAsync:(Ljava/lang/Object;Ljava/lang/Object;JLjava/util/concurrent/TimeUnit;JLjava/util/concurrent/TimeUnit;)Lorg/infinispan/commons/util/concurrent/NotifyingFuture;
      16: areturn

  public final org.infinispan.commons.util.concurrent.NotifyingFuture<java.lang.Boolean> replaceAsync(K, V, V);
    Code:
       0: aload_0
       1: aload_1
       2: aload_2
       3: aload_3
       4: aload_0
       5: getfield      #3                  // Field defaultLifespan:J
       8: getstatic     #5                  // Field java/util/concurrent/TimeUnit.MILLISECONDS:Ljava/util/concurrent/TimeUnit;
      11: aload_0
      12: getfield      #4                  // Field defaultMaxIdleTime:J
      15: getstatic     #5                  // Field java/util/concurrent/TimeUnit.MILLISECONDS:Ljava/util/concurrent/TimeUnit;
      18: invokevirtual #13                 // Method replaceAsync:(Ljava/lang/Object;Ljava/lang/Object;Ljava/lang/Object;JLjava/util/concurrent/TimeUnit;JLjava/util/concurrent/TimeUnit;)Lorg/infinispan/commons/util/concurrent/NotifyingFuture;
      21: areturn

  public final org.infinispan.commons.util.concurrent.NotifyingFuture<V> replaceAsync(K, V);
    Code:
       0: aload_0
       1: aload_1
       2: aload_2
       3: aload_0
       4: getfield      #3                  // Field defaultLifespan:J
       7: getstatic     #5                  // Field java/util/concurrent/TimeUnit.MILLISECONDS:Ljava/util/concurrent/TimeUnit;
      10: aload_0
      11: getfield      #4                  // Field defaultMaxIdleTime:J
      14: getstatic     #5                  // Field java/util/concurrent/TimeUnit.MILLISECONDS:Ljava/util/concurrent/TimeUnit;
      17: invokevirtual #12                 // Method replaceAsync:(Ljava/lang/Object;Ljava/lang/Object;JLjava/util/concurrent/TimeUnit;JLjava/util/concurrent/TimeUnit;)Lorg/infinispan/commons/util/concurrent/NotifyingFuture;
      20: areturn

  public final org.infinispan.commons.util.concurrent.NotifyingFuture<java.lang.Boolean> replaceAsync(K, V, V, long, java.util.concurrent.TimeUnit);
    Code:
       0: aload_0
       1: aload_1
       2: aload_2
       3: aload_3
       4: lload         4
       6: aload         6
       8: aload_0
       9: getfield      #4                  // Field defaultMaxIdleTime:J
      12: getstatic     #5                  // Field java/util/concurrent/TimeUnit.MILLISECONDS:Ljava/util/concurrent/TimeUnit;
      15: invokevirtual #13                 // Method replaceAsync:(Ljava/lang/Object;Ljava/lang/Object;Ljava/lang/Object;JLjava/util/concurrent/TimeUnit;JLjava/util/concurrent/TimeUnit;)Lorg/infinispan/commons/util/concurrent/NotifyingFuture;
      18: areturn

  public final V put(K, V, long, java.util.concurrent.TimeUnit);
    Code:
       0: aload_0
       1: aload_1
       2: aload_2
       3: lload_3
       4: aload         5
       6: aload_0
       7: getfield      #4                  // Field defaultMaxIdleTime:J
      10: getstatic     #5                  // Field java/util/concurrent/TimeUnit.MILLISECONDS:Ljava/util/concurrent/TimeUnit;
      13: invokevirtual #6                  // Method put:(Ljava/lang/Object;Ljava/lang/Object;JLjava/util/concurrent/TimeUnit;JLjava/util/concurrent/TimeUnit;)Ljava/lang/Object;
      16: areturn

  public final V putIfAbsent(K, V, long, java.util.concurrent.TimeUnit);
    Code:
       0: aload_0
       1: aload_1
       2: aload_2
       3: lload_3
       4: aload         5
       6: aload_0
       7: getfield      #4                  // Field defaultMaxIdleTime:J
      10: getstatic     #5                  // Field java/util/concurrent/TimeUnit.MILLISECONDS:Ljava/util/concurrent/TimeUnit;
      13: invokevirtual #9                  // Method putIfAbsent:(Ljava/lang/Object;Ljava/lang/Object;JLjava/util/concurrent/TimeUnit;JLjava/util/concurrent/TimeUnit;)Ljava/lang/Object;
      16: areturn

  public final void putAll(java.util.Map<? extends K, ? extends V>, long, java.util.concurrent.TimeUnit);
    Code:
       0: aload_0
       1: aload_1
       2: lload_2
       3: aload         4
       5: aload_0
       6: getfield      #4                  // Field defaultMaxIdleTime:J
       9: getstatic     #5                  // Field java/util/concurrent/TimeUnit.MILLISECONDS:Ljava/util/concurrent/TimeUnit;
      12: invokevirtual #7                  // Method putAll:(Ljava/util/Map;JLjava/util/concurrent/TimeUnit;JLjava/util/concurrent/TimeUnit;)V
      15: return

  public final V replace(K, V, long, java.util.concurrent.TimeUnit);
    Code:
       0: aload_0
       1: aload_1
       2: aload_2
       3: lload_3
       4: aload         5
       6: aload_0
       7: getfield      #4                  // Field defaultMaxIdleTime:J
      10: getstatic     #5                  // Field java/util/concurrent/TimeUnit.MILLISECONDS:Ljava/util/concurrent/TimeUnit;
      13: invokevirtual #14                 // Method replace:(Ljava/lang/Object;Ljava/lang/Object;JLjava/util/concurrent/TimeUnit;JLjava/util/concurrent/TimeUnit;)Ljava/lang/Object;
      16: areturn

  public final boolean replace(K, V, V);
    Code:
       0: aload_0
       1: aload_1
       2: aload_2
       3: aload_3
       4: aload_0
       5: getfield      #3                  // Field defaultLifespan:J
       8: getstatic     #5                  // Field java/util/concurrent/TimeUnit.MILLISECONDS:Ljava/util/concurrent/TimeUnit;
      11: aload_0
      12: getfield      #4                  // Field defaultMaxIdleTime:J
      15: getstatic     #5                  // Field java/util/concurrent/TimeUnit.MILLISECONDS:Ljava/util/concurrent/TimeUnit;
      18: invokevirtual #15                 // Method replace:(Ljava/lang/Object;Ljava/lang/Object;Ljava/lang/Object;JLjava/util/concurrent/TimeUnit;JLjava/util/concurrent/TimeUnit;)Z
      21: ireturn

  public final V replace(K, V);
    Code:
       0: aload_0
       1: aload_1
       2: aload_2
       3: aload_0
       4: getfield      #3                  // Field defaultLifespan:J
       7: getstatic     #5                  // Field java/util/concurrent/TimeUnit.MILLISECONDS:Ljava/util/concurrent/TimeUnit;
      10: aload_0
      11: getfield      #4                  // Field defaultMaxIdleTime:J
      14: getstatic     #5                  // Field java/util/concurrent/TimeUnit.MILLISECONDS:Ljava/util/concurrent/TimeUnit;
      17: invokevirtual #14                 // Method replace:(Ljava/lang/Object;Ljava/lang/Object;JLjava/util/concurrent/TimeUnit;JLjava/util/concurrent/TimeUnit;)Ljava/lang/Object;
      20: areturn

  public final boolean replace(K, V, V, long, java.util.concurrent.TimeUnit);
    Code:
       0: aload_0
       1: aload_1
       2: aload_2
       3: aload_3
       4: lload         4
       6: aload         6
       8: aload_0
       9: getfield      #4                  // Field defaultMaxIdleTime:J
      12: getstatic     #5                  // Field java/util/concurrent/TimeUnit.MILLISECONDS:Ljava/util/concurrent/TimeUnit;
      15: invokevirtual #15                 // Method replace:(Ljava/lang/Object;Ljava/lang/Object;Ljava/lang/Object;JLjava/util/concurrent/TimeUnit;JLjava/util/concurrent/TimeUnit;)Z
      18: ireturn
}
