Compiled from "Proxy.java"
public class net.oneandone.sushi.fs.http.Proxy {
  private static final net.oneandone.sushi.util.Separator NON_PROXY_SEP;

  public final java.lang.String host;

  public final int port;

  public final java.util.List<java.lang.String> excludes;

  public static net.oneandone.sushi.fs.http.Proxy forPropertiesOpt(java.lang.String);
    Code:
       0: new           #1                  // class java/lang/StringBuilder
       3: dup
       4: invokespecial #2                  // Method java/lang/StringBuilder."<init>":()V
       7: aload_0
       8: invokevirtual #3                  // Method java/lang/StringBuilder.append:(Ljava/lang/String;)Ljava/lang/StringBuilder;
      11: ldc           #4                  // String .proxyHost
      13: invokevirtual #3                  // Method java/lang/StringBuilder.append:(Ljava/lang/String;)Ljava/lang/StringBuilder;
      16: invokevirtual #5                  // Method java/lang/StringBuilder.toString:()Ljava/lang/String;
      19: invokestatic  #6                  // Method java/lang/System.getProperty:(Ljava/lang/String;)Ljava/lang/String;
      22: astore_1
      23: aload_1
      24: ifnonnull     29
      27: aconst_null
      28: areturn
      29: new           #1                  // class java/lang/StringBuilder
      32: dup
      33: invokespecial #2                  // Method java/lang/StringBuilder."<init>":()V
      36: aload_0
      37: invokevirtual #3                  // Method java/lang/StringBuilder.append:(Ljava/lang/String;)Ljava/lang/StringBuilder;
      40: ldc           #7                  // String .proxyPort
      42: invokevirtual #3                  // Method java/lang/StringBuilder.append:(Ljava/lang/String;)Ljava/lang/StringBuilder;
      45: invokevirtual #5                  // Method java/lang/StringBuilder.toString:()Ljava/lang/String;
      48: invokestatic  #6                  // Method java/lang/System.getProperty:(Ljava/lang/String;)Ljava/lang/String;
      51: astore_2
      52: aload_2
      53: ifnonnull     83
      56: new           #8                  // class java/lang/IllegalStateException
      59: dup
      60: new           #1                  // class java/lang/StringBuilder
      63: dup
      64: invokespecial #2                  // Method java/lang/StringBuilder."<init>":()V
      67: ldc           #9                  // String missing proxy port for host
      69: invokevirtual #3                  // Method java/lang/StringBuilder.append:(Ljava/lang/String;)Ljava/lang/StringBuilder;
      72: aload_1
      73: invokevirtual #3                  // Method java/lang/StringBuilder.append:(Ljava/lang/String;)Ljava/lang/StringBuilder;
      76: invokevirtual #5                  // Method java/lang/StringBuilder.toString:()Ljava/lang/String;
      79: invokespecial #10                 // Method java/lang/IllegalStateException."<init>":(Ljava/lang/String;)V
      82: athrow
      83: new           #11                 // class net/oneandone/sushi/fs/http/Proxy
      86: dup
      87: aload_1
      88: aload_2
      89: invokestatic  #12                 // Method java/lang/Integer.parseInt:(Ljava/lang/String;)I
      92: invokespecial #13                 // Method "<init>":(Ljava/lang/String;I)V
      95: astore_3
      96: aload_3
      97: getfield      #14                 // Field excludes:Ljava/util/List;
     100: getstatic     #15                 // Field NON_PROXY_SEP:Lnet/oneandone/sushi/util/Separator;
     103: new           #1                  // class java/lang/StringBuilder
     106: dup
     107: invokespecial #2                  // Method java/lang/StringBuilder."<init>":()V
     110: aload_0
     111: invokevirtual #3                  // Method java/lang/StringBuilder.append:(Ljava/lang/String;)Ljava/lang/StringBuilder;
     114: ldc           #16                 // String .nonProxyHosts
     116: invokevirtual #3                  // Method java/lang/StringBuilder.append:(Ljava/lang/String;)Ljava/lang/StringBuilder;
     119: invokevirtual #5                  // Method java/lang/StringBuilder.toString:()Ljava/lang/String;
     122: ldc           #17                 // String
     124: invokestatic  #18                 // Method java/lang/System.getProperty:(Ljava/lang/String;Ljava/lang/String;)Ljava/lang/String;
     127: invokevirtual #19                 // Method net/oneandone/sushi/util/Separator.split:(Ljava/lang/CharSequence;)Ljava/util/List;
     130: invokeinterface #20,  2           // InterfaceMethod java/util/List.addAll:(Ljava/util/Collection;)Z
     135: pop
     136: aload_3
     137: areturn

  public static net.oneandone.sushi.fs.http.Proxy forEnvOpt(java.lang.String);
    Code:
       0: new           #1                  // class java/lang/StringBuilder
       3: dup
       4: invokespecial #2                  // Method java/lang/StringBuilder."<init>":()V
       7: aload_0
       8: invokevirtual #3                  // Method java/lang/StringBuilder.append:(Ljava/lang/String;)Ljava/lang/StringBuilder;
      11: ldc           #21                 // String _proxy
      13: invokevirtual #3                  // Method java/lang/StringBuilder.append:(Ljava/lang/String;)Ljava/lang/StringBuilder;
      16: invokevirtual #5                  // Method java/lang/StringBuilder.toString:()Ljava/lang/String;
      19: invokestatic  #22                 // Method java/lang/System.getenv:(Ljava/lang/String;)Ljava/lang/String;
      22: ldc           #23                 // String no_proxy
      24: invokestatic  #22                 // Method java/lang/System.getenv:(Ljava/lang/String;)Ljava/lang/String;
      27: invokestatic  #24                 // Method forEnvOpt:(Ljava/lang/String;Ljava/lang/String;)Lnet/oneandone/sushi/fs/http/Proxy;
      30: areturn

  private static net.oneandone.sushi.fs.http.Proxy forEnvOpt(java.lang.String, java.lang.String);
    Code:
       0: aload_0
       1: ifnonnull     6
       4: aconst_null
       5: areturn
       6: new           #25                 // class java/net/URI
       9: dup
      10: aload_0
      11: invokespecial #26                 // Method java/net/URI."<init>":(Ljava/lang/String;)V
      14: astore_2
      15: goto          49
      18: astore        5
      20: new           #28                 // class java/lang/IllegalArgumentException
      23: dup
      24: new           #1                  // class java/lang/StringBuilder
      27: dup
      28: invokespecial #2                  // Method java/lang/StringBuilder."<init>":()V
      31: ldc           #29                 // String invalid value for http_proxy:
      33: invokevirtual #3                  // Method java/lang/StringBuilder.append:(Ljava/lang/String;)Ljava/lang/StringBuilder;
      36: aload_0
      37: invokevirtual #3                  // Method java/lang/StringBuilder.append:(Ljava/lang/String;)Ljava/lang/StringBuilder;
      40: invokevirtual #5                  // Method java/lang/StringBuilder.toString:()Ljava/lang/String;
      43: aload         5
      45: invokespecial #30                 // Method java/lang/IllegalArgumentException."<init>":(Ljava/lang/String;Ljava/lang/Throwable;)V
      48: athrow
      49: aload_2
      50: invokevirtual #31                 // Method java/net/URI.getPort:()I
      53: istore_3
      54: iload_3
      55: iconst_m1
      56: if_icmpne     62
      59: bipush        80
      61: istore_3
      62: new           #11                 // class net/oneandone/sushi/fs/http/Proxy
      65: dup
      66: aload_2
      67: invokevirtual #32                 // Method java/net/URI.getHost:()Ljava/lang/String;
      70: iload_3
      71: invokespecial #13                 // Method "<init>":(Ljava/lang/String;I)V
      74: astore        4
      76: getstatic     #33                 // Field net/oneandone/sushi/util/Separator.COMMA:Lnet/oneandone/sushi/util/Separator;
      79: aload_1
      80: ifnonnull     88
      83: ldc           #17                 // String
      85: goto          89
      88: aload_1
      89: invokevirtual #19                 // Method net/oneandone/sushi/util/Separator.split:(Ljava/lang/CharSequence;)Ljava/util/List;
      92: invokeinterface #34,  1           // InterfaceMethod java/util/List.iterator:()Ljava/util/Iterator;
      97: astore        5
      99: aload         5
     101: invokeinterface #35,  1           // InterfaceMethod java/util/Iterator.hasNext:()Z
     106: ifeq          169
     109: aload         5
     111: invokeinterface #36,  1           // InterfaceMethod java/util/Iterator.next:()Ljava/lang/Object;
     116: checkcast     #37                 // class java/lang/String
     119: astore        6
     121: aload         6
     123: ldc           #38                 // String .
     125: invokevirtual #39                 // Method java/lang/String.startsWith:(Ljava/lang/String;)Z
     128: ifeq          153
     131: new           #1                  // class java/lang/StringBuilder
     134: dup
     135: invokespecial #2                  // Method java/lang/StringBuilder."<init>":()V
     138: bipush        42
     140: invokevirtual #40                 // Method java/lang/StringBuilder.append:(C)Ljava/lang/StringBuilder;
     143: aload         6
     145: invokevirtual #3                  // Method java/lang/StringBuilder.append:(Ljava/lang/String;)Ljava/lang/StringBuilder;
     148: invokevirtual #5                  // Method java/lang/StringBuilder.toString:()Ljava/lang/String;
     151: astore        6
     153: aload         4
     155: getfield      #14                 // Field excludes:Ljava/util/List;
     158: aload         6
     160: invokeinterface #41,  2           // InterfaceMethod java/util/List.add:(Ljava/lang/Object;)Z
     165: pop
     166: goto          99
     169: aload         4
     171: areturn
    Exception table:
       from    to  target type
           6    15    18   Class java/net/URISyntaxException

  public net.oneandone.sushi.fs.http.Proxy(java.lang.String, int);
    Code:
       0: aload_0
       1: invokespecial #42                 // Method java/lang/Object."<init>":()V
       4: aload_0
       5: aload_1
       6: putfield      #43                 // Field host:Ljava/lang/String;
       9: aload_0
      10: iload_2
      11: putfield      #44                 // Field port:I
      14: aload_0
      15: new           #45                 // class java/util/ArrayList
      18: dup
      19: invokespecial #46                 // Method java/util/ArrayList."<init>":()V
      22: putfield      #14                 // Field excludes:Ljava/util/List;
      25: return

  public boolean excludes(java.net.URI);
    Code:
       0: aload_1
       1: invokevirtual #32                 // Method java/net/URI.getHost:()Ljava/lang/String;
       4: astore_2
       5: aload_0
       6: getfield      #14                 // Field excludes:Ljava/util/List;
       9: invokeinterface #34,  1           // InterfaceMethod java/util/List.iterator:()Ljava/util/Iterator;
      14: astore_3
      15: aload_3
      16: invokeinterface #35,  1           // InterfaceMethod java/util/Iterator.hasNext:()Z
      21: ifeq          74
      24: aload_3
      25: invokeinterface #36,  1           // InterfaceMethod java/util/Iterator.next:()Ljava/lang/Object;
      30: checkcast     #37                 // class java/lang/String
      33: astore        4
      35: aload         4
      37: ldc           #47                 // String *
      39: invokevirtual #39                 // Method java/lang/String.startsWith:(Ljava/lang/String;)Z
      42: ifeq          60
      45: aload_2
      46: aload         4
      48: iconst_1
      49: invokevirtual #48                 // Method java/lang/String.substring:(I)Ljava/lang/String;
      52: invokevirtual #49                 // Method java/lang/String.endsWith:(Ljava/lang/String;)Z
      55: ifeq          71
      58: iconst_1
      59: ireturn
      60: aload_2
      61: aload         4
      63: invokevirtual #50                 // Method java/lang/String.equals:(Ljava/lang/Object;)Z
      66: ifeq          71
      69: iconst_1
      70: ireturn
      71: goto          15
      74: iconst_0
      75: ireturn

  static {};
    Code:
       0: bipush        124
       2: invokestatic  #51                 // Method net/oneandone/sushi/util/Separator.on:(C)Lnet/oneandone/sushi/util/Separator;
       5: invokevirtual #52                 // Method net/oneandone/sushi/util/Separator.trim:()Lnet/oneandone/sushi/util/Separator;
       8: invokevirtual #53                 // Method net/oneandone/sushi/util/Separator.skipEmpty:()Lnet/oneandone/sushi/util/Separator;
      11: putstatic     #15                 // Field NON_PROXY_SEP:Lnet/oneandone/sushi/util/Separator;
      14: return
}
