Compiled from "ConcurrencyDependencyGraph.java"
public class org.apache.maven.lifecycle.internal.ConcurrencyDependencyGraph {
  private final org.apache.maven.lifecycle.internal.ProjectBuildList projectBuilds;

  private final org.apache.maven.execution.ProjectDependencyGraph projectDependencyGraph;

  private final java.util.HashSet<org.apache.maven.project.MavenProject> finishedProjects;

  public org.apache.maven.lifecycle.internal.ConcurrencyDependencyGraph(org.apache.maven.lifecycle.internal.ProjectBuildList, org.apache.maven.execution.ProjectDependencyGraph);
    Code:
       0: aload_0
       1: invokespecial #1                  // Method java/lang/Object."<init>":()V
       4: aload_0
       5: new           #2                  // class java/util/HashSet
       8: dup
       9: invokespecial #3                  // Method java/util/HashSet."<init>":()V
      12: putfield      #4                  // Field finishedProjects:Ljava/util/HashSet;
      15: aload_0
      16: aload_2
      17: putfield      #5                  // Field projectDependencyGraph:Lorg/apache/maven/execution/ProjectDependencyGraph;
      20: aload_0
      21: aload_1
      22: putfield      #6                  // Field projectBuilds:Lorg/apache/maven/lifecycle/internal/ProjectBuildList;
      25: return

  public int getNumberOfBuilds();
    Code:
       0: aload_0
       1: getfield      #6                  // Field projectBuilds:Lorg/apache/maven/lifecycle/internal/ProjectBuildList;
       4: invokevirtual #7                  // Method org/apache/maven/lifecycle/internal/ProjectBuildList.size:()I
       7: ireturn

  public java.util.List<org.apache.maven.project.MavenProject> getRootSchedulableBuilds();
    Code:
       0: new           #8                  // class java/util/ArrayList
       3: dup
       4: invokespecial #9                  // Method java/util/ArrayList."<init>":()V
       7: astore_1
       8: aload_0
       9: getfield      #6                  // Field projectBuilds:Lorg/apache/maven/lifecycle/internal/ProjectBuildList;
      12: invokevirtual #10                 // Method org/apache/maven/lifecycle/internal/ProjectBuildList.iterator:()Ljava/util/Iterator;
      15: astore_2
      16: aload_2
      17: invokeinterface #11,  1           // InterfaceMethod java/util/Iterator.hasNext:()Z
      22: ifeq          71
      25: aload_2
      26: invokeinterface #12,  1           // InterfaceMethod java/util/Iterator.next:()Ljava/lang/Object;
      31: checkcast     #13                 // class org/apache/maven/lifecycle/internal/ProjectSegment
      34: astore_3
      35: aload_0
      36: getfield      #5                  // Field projectDependencyGraph:Lorg/apache/maven/execution/ProjectDependencyGraph;
      39: aload_3
      40: invokevirtual #14                 // Method org/apache/maven/lifecycle/internal/ProjectSegment.getProject:()Lorg/apache/maven/project/MavenProject;
      43: iconst_0
      44: invokeinterface #15,  3           // InterfaceMethod org/apache/maven/execution/ProjectDependencyGraph.getUpstreamProjects:(Lorg/apache/maven/project/MavenProject;Z)Ljava/util/List;
      49: invokeinterface #16,  1           // InterfaceMethod java/util/List.size:()I
      54: ifne          68
      57: aload_1
      58: aload_3
      59: invokevirtual #14                 // Method org/apache/maven/lifecycle/internal/ProjectSegment.getProject:()Lorg/apache/maven/project/MavenProject;
      62: invokeinterface #17,  2           // InterfaceMethod java/util/List.add:(Ljava/lang/Object;)Z
      67: pop
      68: goto          16
      71: aload_1
      72: areturn

  public java.util.List<org.apache.maven.project.MavenProject> markAsFinished(org.apache.maven.project.MavenProject);
    Code:
       0: aload_0
       1: getfield      #4                  // Field finishedProjects:Ljava/util/HashSet;
       4: aload_1
       5: invokevirtual #18                 // Method java/util/HashSet.add:(Ljava/lang/Object;)Z
       8: pop
       9: aload_0
      10: aload_1
      11: invokespecial #19                 // Method getSchedulableNewProcesses:(Lorg/apache/maven/project/MavenProject;)Ljava/util/List;
      14: areturn

  private java.util.List<org.apache.maven.project.MavenProject> getSchedulableNewProcesses(org.apache.maven.project.MavenProject);
    Code:
       0: new           #8                  // class java/util/ArrayList
       3: dup
       4: invokespecial #9                  // Method java/util/ArrayList."<init>":()V
       7: astore_2
       8: aload_0
       9: getfield      #5                  // Field projectDependencyGraph:Lorg/apache/maven/execution/ProjectDependencyGraph;
      12: aload_1
      13: iconst_0
      14: invokeinterface #20,  3           // InterfaceMethod org/apache/maven/execution/ProjectDependencyGraph.getDownstreamProjects:(Lorg/apache/maven/project/MavenProject;Z)Ljava/util/List;
      19: invokeinterface #21,  1           // InterfaceMethod java/util/List.iterator:()Ljava/util/Iterator;
      24: astore_3
      25: aload_3
      26: invokeinterface #11,  1           // InterfaceMethod java/util/Iterator.hasNext:()Z
      31: ifeq          83
      34: aload_3
      35: invokeinterface #12,  1           // InterfaceMethod java/util/Iterator.next:()Ljava/lang/Object;
      40: checkcast     #22                 // class org/apache/maven/project/MavenProject
      43: astore        4
      45: aload_0
      46: getfield      #5                  // Field projectDependencyGraph:Lorg/apache/maven/execution/ProjectDependencyGraph;
      49: aload         4
      51: iconst_0
      52: invokeinterface #15,  3           // InterfaceMethod org/apache/maven/execution/ProjectDependencyGraph.getUpstreamProjects:(Lorg/apache/maven/project/MavenProject;Z)Ljava/util/List;
      57: astore        5
      59: aload_0
      60: getfield      #4                  // Field finishedProjects:Ljava/util/HashSet;
      63: aload         5
      65: invokevirtual #23                 // Method java/util/HashSet.containsAll:(Ljava/util/Collection;)Z
      68: ifeq          80
      71: aload_2
      72: aload         4
      74: invokeinterface #17,  2           // InterfaceMethod java/util/List.add:(Ljava/lang/Object;)Z
      79: pop
      80: goto          25
      83: aload_2
      84: areturn

  public org.apache.maven.lifecycle.internal.ProjectBuildList getProjectBuilds();
    Code:
       0: aload_0
       1: getfield      #6                  // Field projectBuilds:Lorg/apache/maven/lifecycle/internal/ProjectBuildList;
       4: areturn
}
