Compiled from "LifecycleDependencyResolver.java"
public class org.apache.maven.lifecycle.internal.LifecycleDependencyResolver {
  private org.apache.maven.project.ProjectDependenciesResolver dependenciesResolver;

  private org.codehaus.plexus.logging.Logger logger;

  private org.apache.maven.artifact.factory.ArtifactFactory artifactFactory;

  private org.apache.maven.eventspy.internal.EventSpyDispatcher eventSpyDispatcher;

  public org.apache.maven.lifecycle.internal.LifecycleDependencyResolver();
    Code:
       0: aload_0
       1: invokespecial #1                  // Method java/lang/Object."<init>":()V
       4: return

  public org.apache.maven.lifecycle.internal.LifecycleDependencyResolver(org.apache.maven.project.ProjectDependenciesResolver, org.codehaus.plexus.logging.Logger);
    Code:
       0: aload_0
       1: invokespecial #1                  // Method java/lang/Object."<init>":()V
       4: aload_0
       5: aload_1
       6: putfield      #2                  // Field dependenciesResolver:Lorg/apache/maven/project/ProjectDependenciesResolver;
       9: aload_0
      10: aload_2
      11: putfield      #3                  // Field logger:Lorg/codehaus/plexus/logging/Logger;
      14: return

  public static java.util.List<org.apache.maven.project.MavenProject> getProjects(org.apache.maven.project.MavenProject, org.apache.maven.execution.MavenSession, boolean);
    Code:
       0: iload_2
       1: ifeq          9
       4: aload_1
       5: invokevirtual #4                  // Method org/apache/maven/execution/MavenSession.getProjects:()Ljava/util/List;
       8: areturn
       9: aload_0
      10: invokestatic  #5                  // Method java/util/Collections.singletonList:(Ljava/lang/Object;)Ljava/util/List;
      13: areturn

  public void resolveProjectDependencies(org.apache.maven.project.MavenProject, java.util.Collection<java.lang.String>, java.util.Collection<java.lang.String>, org.apache.maven.execution.MavenSession, boolean, java.util.Set<org.apache.maven.artifact.Artifact>) throws org.apache.maven.lifecycle.LifecycleExecutionException;
    Code:
       0: invokestatic  #6                  // Method java/lang/Thread.currentThread:()Ljava/lang/Thread;
       3: invokevirtual #7                  // Method java/lang/Thread.getContextClassLoader:()Ljava/lang/ClassLoader;
       6: astore        7
       8: aload_1
       9: invokevirtual #8                  // Method org/apache/maven/project/MavenProject.getClassRealm:()Lorg/codehaus/plexus/classworlds/realm/ClassRealm;
      12: astore        8
      14: aload         8
      16: ifnull        34
      19: aload         8
      21: aload         7
      23: if_acmpeq     34
      26: invokestatic  #6                  // Method java/lang/Thread.currentThread:()Ljava/lang/Thread;
      29: aload         8
      31: invokevirtual #9                  // Method java/lang/Thread.setContextClassLoader:(Ljava/lang/ClassLoader;)V
      34: aload_1
      35: invokevirtual #10                 // Method org/apache/maven/project/MavenProject.getDependencyArtifacts:()Ljava/util/Set;
      38: ifnonnull     70
      41: aload_1
      42: aload_1
      43: aload_0
      44: getfield      #11                 // Field artifactFactory:Lorg/apache/maven/artifact/factory/ArtifactFactory;
      47: aconst_null
      48: aconst_null
      49: invokevirtual #12                 // Method org/apache/maven/project/MavenProject.createArtifacts:(Lorg/apache/maven/artifact/factory/ArtifactFactory;Ljava/lang/String;Lorg/apache/maven/artifact/resolver/filter/ArtifactFilter;)Ljava/util/Set;
      52: invokevirtual #13                 // Method org/apache/maven/project/MavenProject.setDependencyArtifacts:(Ljava/util/Set;)V
      55: goto          70
      58: astore        9
      60: new           #15                 // class org/apache/maven/lifecycle/LifecycleExecutionException
      63: dup
      64: aload         9
      66: invokespecial #16                 // Method org/apache/maven/lifecycle/LifecycleExecutionException."<init>":(Ljava/lang/Throwable;)V
      69: athrow
      70: aload_0
      71: aload_1
      72: aload_2
      73: aload_3
      74: aload         4
      76: iload         5
      78: aload         6
      80: invokespecial #17                 // Method getDependencies:(Lorg/apache/maven/project/MavenProject;Ljava/util/Collection;Ljava/util/Collection;Lorg/apache/maven/execution/MavenSession;ZLjava/util/Set;)Ljava/util/Set;
      83: astore        9
      85: aload_1
      86: aload         9
      88: invokevirtual #18                 // Method org/apache/maven/project/MavenProject.setResolvedArtifacts:(Ljava/util/Set;)V
      91: new           #19                 // class java/util/HashMap
      94: dup
      95: invokespecial #20                 // Method java/util/HashMap."<init>":()V
      98: astore        10
     100: aload         9
     102: invokeinterface #21,  1           // InterfaceMethod java/util/Set.iterator:()Ljava/util/Iterator;
     107: astore        11
     109: aload         11
     111: invokeinterface #22,  1           // InterfaceMethod java/util/Iterator.hasNext:()Z
     116: ifeq          151
     119: aload         11
     121: invokeinterface #23,  1           // InterfaceMethod java/util/Iterator.next:()Ljava/lang/Object;
     126: checkcast     #24                 // class org/apache/maven/artifact/Artifact
     129: astore        12
     131: aload         10
     133: aload         12
     135: invokeinterface #25,  1           // InterfaceMethod org/apache/maven/artifact/Artifact.getDependencyConflictId:()Ljava/lang/String;
     140: aload         12
     142: invokeinterface #26,  3           // InterfaceMethod java/util/Map.put:(Ljava/lang/Object;Ljava/lang/Object;)Ljava/lang/Object;
     147: pop
     148: goto          109
     151: aload_1
     152: invokevirtual #10                 // Method org/apache/maven/project/MavenProject.getDependencyArtifacts:()Ljava/util/Set;
     155: invokeinterface #21,  1           // InterfaceMethod java/util/Set.iterator:()Ljava/util/Iterator;
     160: astore        11
     162: aload         11
     164: invokeinterface #22,  1           // InterfaceMethod java/util/Iterator.hasNext:()Z
     169: ifeq          271
     172: aload         11
     174: invokeinterface #23,  1           // InterfaceMethod java/util/Iterator.next:()Ljava/lang/Object;
     179: checkcast     #24                 // class org/apache/maven/artifact/Artifact
     182: astore        12
     184: aload         12
     186: invokeinterface #27,  1           // InterfaceMethod org/apache/maven/artifact/Artifact.getFile:()Ljava/io/File;
     191: ifnonnull     268
     194: aload         10
     196: aload         12
     198: invokeinterface #25,  1           // InterfaceMethod org/apache/maven/artifact/Artifact.getDependencyConflictId:()Ljava/lang/String;
     203: invokeinterface #28,  2           // InterfaceMethod java/util/Map.get:(Ljava/lang/Object;)Ljava/lang/Object;
     208: checkcast     #24                 // class org/apache/maven/artifact/Artifact
     211: astore        13
     213: aload         13
     215: ifnull        268
     218: aload         12
     220: aload         13
     222: invokeinterface #27,  1           // InterfaceMethod org/apache/maven/artifact/Artifact.getFile:()Ljava/io/File;
     227: invokeinterface #29,  2           // InterfaceMethod org/apache/maven/artifact/Artifact.setFile:(Ljava/io/File;)V
     232: aload         12
     234: aload         13
     236: invokeinterface #30,  1           // InterfaceMethod org/apache/maven/artifact/Artifact.getDependencyTrail:()Ljava/util/List;
     241: invokeinterface #31,  2           // InterfaceMethod org/apache/maven/artifact/Artifact.setDependencyTrail:(Ljava/util/List;)V
     246: aload         12
     248: aload         13
     250: invokeinterface #32,  1           // InterfaceMethod org/apache/maven/artifact/Artifact.getVersion:()Ljava/lang/String;
     255: invokeinterface #33,  2           // InterfaceMethod org/apache/maven/artifact/Artifact.setResolvedVersion:(Ljava/lang/String;)V
     260: aload         12
     262: iconst_1
     263: invokeinterface #34,  2           // InterfaceMethod org/apache/maven/artifact/Artifact.setResolved:(Z)V
     268: goto          162
     271: invokestatic  #6                  // Method java/lang/Thread.currentThread:()Ljava/lang/Thread;
     274: aload         7
     276: invokevirtual #9                  // Method java/lang/Thread.setContextClassLoader:(Ljava/lang/ClassLoader;)V
     279: goto          295
     282: astore        14
     284: invokestatic  #6                  // Method java/lang/Thread.currentThread:()Ljava/lang/Thread;
     287: aload         7
     289: invokevirtual #9                  // Method java/lang/Thread.setContextClassLoader:(Ljava/lang/ClassLoader;)V
     292: aload         14
     294: athrow
     295: return
    Exception table:
       from    to  target type
          41    55    58   Class org/apache/maven/project/artifact/InvalidDependencyVersionException
           8   271   282   any
         282   284   282   any

  private java.util.Set<org.apache.maven.artifact.Artifact> getDependencies(org.apache.maven.project.MavenProject, java.util.Collection<java.lang.String>, java.util.Collection<java.lang.String>, org.apache.maven.execution.MavenSession, boolean, java.util.Set<org.apache.maven.artifact.Artifact>) throws org.apache.maven.lifecycle.LifecycleExecutionException;
    Code:
       0: aload_2
       1: ifnonnull     8
       4: invokestatic  #35                 // Method java/util/Collections.emptySet:()Ljava/util/Set;
       7: astore_2
       8: aload_3
       9: ifnonnull     16
      12: invokestatic  #35                 // Method java/util/Collections.emptySet:()Ljava/util/Set;
      15: astore_3
      16: aload_2
      17: invokeinterface #36,  1           // InterfaceMethod java/util/Collection.isEmpty:()Z
      22: ifeq          42
      25: aload_3
      26: invokeinterface #36,  1           // InterfaceMethod java/util/Collection.isEmpty:()Z
      31: ifeq          42
      34: new           #37                 // class java/util/LinkedHashSet
      37: dup
      38: invokespecial #38                 // Method java/util/LinkedHashSet."<init>":()V
      41: areturn
      42: new           #39                 // class java/util/HashSet
      45: dup
      46: aload_2
      47: invokespecial #40                 // Method java/util/HashSet."<init>":(Ljava/util/Collection;)V
      50: astore_2
      51: aload_2
      52: aload_3
      53: invokeinterface #41,  2           // InterfaceMethod java/util/Collection.addAll:(Ljava/util/Collection;)Z
      58: pop
      59: new           #42                 // class org/sonatype/aether/util/filter/ScopeDependencyFilter
      62: dup
      63: aconst_null
      64: aload_0
      65: aload_2
      66: invokespecial #43                 // Method negate:(Ljava/util/Collection;)Ljava/util/Collection;
      69: invokespecial #44                 // Method org/sonatype/aether/util/filter/ScopeDependencyFilter."<init>":(Ljava/util/Collection;Ljava/util/Collection;)V
      72: astore        7
      74: new           #42                 // class org/sonatype/aether/util/filter/ScopeDependencyFilter
      77: dup
      78: aconst_null
      79: aload_0
      80: aload_3
      81: invokespecial #43                 // Method negate:(Ljava/util/Collection;)Ljava/util/Collection;
      84: invokespecial #44                 // Method org/sonatype/aether/util/filter/ScopeDependencyFilter."<init>":(Ljava/util/Collection;Ljava/util/Collection;)V
      87: astore        8
      89: aload         7
      91: aload         8
      93: invokestatic  #45                 // Method org/sonatype/aether/util/filter/AndDependencyFilter.newInstance:(Lorg/sonatype/aether/graph/DependencyFilter;Lorg/sonatype/aether/graph/DependencyFilter;)Lorg/sonatype/aether/graph/DependencyFilter;
      96: astore        8
      98: aload         8
     100: new           #46                 // class org/apache/maven/lifecycle/internal/LifecycleDependencyResolver$ReactorDependencyFilter
     103: dup
     104: aload         6
     106: invokespecial #47                 // Method org/apache/maven/lifecycle/internal/LifecycleDependencyResolver$ReactorDependencyFilter."<init>":(Ljava/util/Collection;)V
     109: invokestatic  #45                 // Method org/sonatype/aether/util/filter/AndDependencyFilter.newInstance:(Lorg/sonatype/aether/graph/DependencyFilter;Lorg/sonatype/aether/graph/DependencyFilter;)Lorg/sonatype/aether/graph/DependencyFilter;
     112: astore        8
     114: new           #48                 // class org/apache/maven/project/DefaultDependencyResolutionRequest
     117: dup
     118: aload_1
     119: aload         4
     121: invokevirtual #49                 // Method org/apache/maven/execution/MavenSession.getRepositorySession:()Lorg/sonatype/aether/RepositorySystemSession;
     124: invokespecial #50                 // Method org/apache/maven/project/DefaultDependencyResolutionRequest."<init>":(Lorg/apache/maven/project/MavenProject;Lorg/sonatype/aether/RepositorySystemSession;)V
     127: astore        10
     129: aload         10
     131: aload         8
     133: invokevirtual #51                 // Method org/apache/maven/project/DefaultDependencyResolutionRequest.setResolutionFilter:(Lorg/sonatype/aether/graph/DependencyFilter;)Lorg/apache/maven/project/DependencyResolutionRequest;
     136: pop
     137: aload_0
     138: getfield      #52                 // Field eventSpyDispatcher:Lorg/apache/maven/eventspy/internal/EventSpyDispatcher;
     141: aload         10
     143: invokevirtual #53                 // Method org/apache/maven/eventspy/internal/EventSpyDispatcher.onEvent:(Ljava/lang/Object;)V
     146: aload_0
     147: getfield      #2                  // Field dependenciesResolver:Lorg/apache/maven/project/ProjectDependenciesResolver;
     150: aload         10
     152: invokeinterface #54,  2           // InterfaceMethod org/apache/maven/project/ProjectDependenciesResolver.resolve:(Lorg/apache/maven/project/DependencyResolutionRequest;)Lorg/apache/maven/project/DependencyResolutionResult;
     157: astore        9
     159: goto          300
     162: astore        10
     164: aload         10
     166: invokevirtual #56                 // Method org/apache/maven/project/DependencyResolutionException.getResult:()Lorg/apache/maven/project/DependencyResolutionResult;
     169: astore        9
     171: iload         5
     173: ifeq          288
     176: aload_0
     177: aload         4
     179: invokevirtual #4                  // Method org/apache/maven/execution/MavenSession.getProjects:()Ljava/util/List;
     182: aload         9
     184: invokeinterface #57,  1           // InterfaceMethod org/apache/maven/project/DependencyResolutionResult.getUnresolvedDependencies:()Ljava/util/List;
     189: invokespecial #58                 // Method areAllDependenciesInReactor:(Ljava/util/Collection;Ljava/util/Collection;)Z
     192: ifeq          288
     195: aload_0
     196: getfield      #3                  // Field logger:Lorg/codehaus/plexus/logging/Logger;
     199: ldc           #59                 // String The following dependencies could not be resolved at this point of the build but seem to be part of the reactor:
     201: invokeinterface #60,  2           // InterfaceMethod org/codehaus/plexus/logging/Logger.warn:(Ljava/lang/String;)V
     206: aload         9
     208: invokeinterface #57,  1           // InterfaceMethod org/apache/maven/project/DependencyResolutionResult.getUnresolvedDependencies:()Ljava/util/List;
     213: invokeinterface #61,  1           // InterfaceMethod java/util/List.iterator:()Ljava/util/Iterator;
     218: astore        11
     220: aload         11
     222: invokeinterface #22,  1           // InterfaceMethod java/util/Iterator.hasNext:()Z
     227: ifeq          274
     230: aload         11
     232: invokeinterface #23,  1           // InterfaceMethod java/util/Iterator.next:()Ljava/lang/Object;
     237: checkcast     #62                 // class org/sonatype/aether/graph/Dependency
     240: astore        12
     242: aload_0
     243: getfield      #3                  // Field logger:Lorg/codehaus/plexus/logging/Logger;
     246: new           #63                 // class java/lang/StringBuilder
     249: dup
     250: invokespecial #64                 // Method java/lang/StringBuilder."<init>":()V
     253: ldc           #65                 // String o
     255: invokevirtual #66                 // Method java/lang/StringBuilder.append:(Ljava/lang/String;)Ljava/lang/StringBuilder;
     258: aload         12
     260: invokevirtual #67                 // Method java/lang/StringBuilder.append:(Ljava/lang/Object;)Ljava/lang/StringBuilder;
     263: invokevirtual #68                 // Method java/lang/StringBuilder.toString:()Ljava/lang/String;
     266: invokeinterface #60,  2           // InterfaceMethod org/codehaus/plexus/logging/Logger.warn:(Ljava/lang/String;)V
     271: goto          220
     274: aload_0
     275: getfield      #3                  // Field logger:Lorg/codehaus/plexus/logging/Logger;
     278: ldc           #69                 // String Try running the build up to the lifecycle phase \"package\"
     280: invokeinterface #60,  2           // InterfaceMethod org/codehaus/plexus/logging/Logger.warn:(Ljava/lang/String;)V
     285: goto          300
     288: new           #15                 // class org/apache/maven/lifecycle/LifecycleExecutionException
     291: dup
     292: aconst_null
     293: aload_1
     294: aload         10
     296: invokespecial #70                 // Method org/apache/maven/lifecycle/LifecycleExecutionException."<init>":(Lorg/apache/maven/plugin/MojoExecution;Lorg/apache/maven/project/MavenProject;Ljava/lang/Throwable;)V
     299: athrow
     300: aload_0
     301: getfield      #52                 // Field eventSpyDispatcher:Lorg/apache/maven/eventspy/internal/EventSpyDispatcher;
     304: aload         9
     306: invokevirtual #53                 // Method org/apache/maven/eventspy/internal/EventSpyDispatcher.onEvent:(Ljava/lang/Object;)V
     309: new           #37                 // class java/util/LinkedHashSet
     312: dup
     313: invokespecial #38                 // Method java/util/LinkedHashSet."<init>":()V
     316: astore        10
     318: aload         9
     320: invokeinterface #71,  1           // InterfaceMethod org/apache/maven/project/DependencyResolutionResult.getDependencyGraph:()Lorg/sonatype/aether/graph/DependencyNode;
     325: ifnull        379
     328: aload         9
     330: invokeinterface #71,  1           // InterfaceMethod org/apache/maven/project/DependencyResolutionResult.getDependencyGraph:()Lorg/sonatype/aether/graph/DependencyNode;
     335: invokeinterface #72,  1           // InterfaceMethod org/sonatype/aether/graph/DependencyNode.getChildren:()Ljava/util/List;
     340: invokeinterface #73,  1           // InterfaceMethod java/util/List.isEmpty:()Z
     345: ifne          379
     348: aload         10
     350: aload         9
     352: invokeinterface #71,  1           // InterfaceMethod org/apache/maven/project/DependencyResolutionResult.getDependencyGraph:()Lorg/sonatype/aether/graph/DependencyNode;
     357: invokeinterface #72,  1           // InterfaceMethod org/sonatype/aether/graph/DependencyNode.getChildren:()Ljava/util/List;
     362: aload_1
     363: invokevirtual #74                 // Method org/apache/maven/project/MavenProject.getArtifact:()Lorg/apache/maven/artifact/Artifact;
     366: invokeinterface #75,  1           // InterfaceMethod org/apache/maven/artifact/Artifact.getId:()Ljava/lang/String;
     371: invokestatic  #5                  // Method java/util/Collections.singletonList:(Ljava/lang/Object;)Ljava/util/List;
     374: aload         7
     376: invokestatic  #76                 // Method org/apache/maven/RepositoryUtils.toArtifacts:(Ljava/util/Collection;Ljava/util/Collection;Ljava/util/List;Lorg/sonatype/aether/graph/DependencyFilter;)V
     379: aload         10
     381: areturn
    Exception table:
       from    to  target type
         114   159   162   Class org/apache/maven/project/DependencyResolutionException

  private boolean areAllDependenciesInReactor(java.util.Collection<org.apache.maven.project.MavenProject>, java.util.Collection<org.sonatype.aether.graph.Dependency>);
    Code:
       0: aload_0
       1: aload_1
       2: invokespecial #77                 // Method getReactorProjectKeys:(Ljava/util/Collection;)Ljava/util/Set;
       5: astore_3
       6: aload_2
       7: invokeinterface #78,  1           // InterfaceMethod java/util/Collection.iterator:()Ljava/util/Iterator;
      12: astore        4
      14: aload         4
      16: invokeinterface #22,  1           // InterfaceMethod java/util/Iterator.hasNext:()Z
      21: ifeq          85
      24: aload         4
      26: invokeinterface #23,  1           // InterfaceMethod java/util/Iterator.next:()Ljava/lang/Object;
      31: checkcast     #62                 // class org/sonatype/aether/graph/Dependency
      34: astore        5
      36: aload         5
      38: invokevirtual #79                 // Method org/sonatype/aether/graph/Dependency.getArtifact:()Lorg/sonatype/aether/artifact/Artifact;
      41: astore        6
      43: aload         6
      45: invokeinterface #80,  1           // InterfaceMethod org/sonatype/aether/artifact/Artifact.getGroupId:()Ljava/lang/String;
      50: aload         6
      52: invokeinterface #81,  1           // InterfaceMethod org/sonatype/aether/artifact/Artifact.getArtifactId:()Ljava/lang/String;
      57: aload         6
      59: invokeinterface #82,  1           // InterfaceMethod org/sonatype/aether/artifact/Artifact.getVersion:()Ljava/lang/String;
      64: invokestatic  #83                 // Method org/apache/maven/artifact/ArtifactUtils.key:(Ljava/lang/String;Ljava/lang/String;Ljava/lang/String;)Ljava/lang/String;
      67: astore        7
      69: aload_3
      70: aload         7
      72: invokeinterface #84,  2           // InterfaceMethod java/util/Set.contains:(Ljava/lang/Object;)Z
      77: ifne          82
      80: iconst_0
      81: ireturn
      82: goto          14
      85: iconst_1
      86: ireturn

  private java.util.Set<java.lang.String> getReactorProjectKeys(java.util.Collection<org.apache.maven.project.MavenProject>);
    Code:
       0: new           #39                 // class java/util/HashSet
       3: dup
       4: aload_1
       5: invokeinterface #85,  1           // InterfaceMethod java/util/Collection.size:()I
      10: iconst_2
      11: imul
      12: invokespecial #86                 // Method java/util/HashSet."<init>":(I)V
      15: astore_2
      16: aload_1
      17: invokeinterface #78,  1           // InterfaceMethod java/util/Collection.iterator:()Ljava/util/Iterator;
      22: astore_3
      23: aload_3
      24: invokeinterface #22,  1           // InterfaceMethod java/util/Iterator.hasNext:()Z
      29: ifeq          75
      32: aload_3
      33: invokeinterface #23,  1           // InterfaceMethod java/util/Iterator.next:()Ljava/lang/Object;
      38: checkcast     #87                 // class org/apache/maven/project/MavenProject
      41: astore        4
      43: aload         4
      45: invokevirtual #88                 // Method org/apache/maven/project/MavenProject.getGroupId:()Ljava/lang/String;
      48: aload         4
      50: invokevirtual #89                 // Method org/apache/maven/project/MavenProject.getArtifactId:()Ljava/lang/String;
      53: aload         4
      55: invokevirtual #90                 // Method org/apache/maven/project/MavenProject.getVersion:()Ljava/lang/String;
      58: invokestatic  #83                 // Method org/apache/maven/artifact/ArtifactUtils.key:(Ljava/lang/String;Ljava/lang/String;Ljava/lang/String;)Ljava/lang/String;
      61: astore        5
      63: aload_2
      64: aload         5
      66: invokeinterface #91,  2           // InterfaceMethod java/util/Set.add:(Ljava/lang/Object;)Z
      71: pop
      72: goto          23
      75: aload_2
      76: areturn

  private java.util.Collection<java.lang.String> negate(java.util.Collection<java.lang.String>);
    Code:
       0: new           #39                 // class java/util/HashSet
       3: dup
       4: invokespecial #92                 // Method java/util/HashSet."<init>":()V
       7: astore_2
       8: aload_2
       9: iconst_5
      10: anewarray     #93                 // class java/lang/String
      13: dup
      14: iconst_0
      15: ldc           #94                 // String system
      17: aastore
      18: dup
      19: iconst_1
      20: ldc           #95                 // String compile
      22: aastore
      23: dup
      24: iconst_2
      25: ldc           #96                 // String provided
      27: aastore
      28: dup
      29: iconst_3
      30: ldc           #97                 // String runtime
      32: aastore
      33: dup
      34: iconst_4
      35: ldc           #98                 // String test
      37: aastore
      38: invokestatic  #99                 // Method java/util/Collections.addAll:(Ljava/util/Collection;[Ljava/lang/Object;)Z
      41: pop
      42: aload_1
      43: invokeinterface #78,  1           // InterfaceMethod java/util/Collection.iterator:()Ljava/util/Iterator;
      48: astore_3
      49: aload_3
      50: invokeinterface #22,  1           // InterfaceMethod java/util/Iterator.hasNext:()Z
      55: ifeq          248
      58: aload_3
      59: invokeinterface #23,  1           // InterfaceMethod java/util/Iterator.next:()Ljava/lang/Object;
      64: checkcast     #93                 // class java/lang/String
      67: astore        4
      69: ldc           #95                 // String compile
      71: aload         4
      73: invokevirtual #100                // Method java/lang/String.equals:(Ljava/lang/Object;)Z
      76: ifeq          109
      79: aload_2
      80: ldc           #95                 // String compile
      82: invokeinterface #101,  2          // InterfaceMethod java/util/Collection.remove:(Ljava/lang/Object;)Z
      87: pop
      88: aload_2
      89: ldc           #94                 // String system
      91: invokeinterface #101,  2          // InterfaceMethod java/util/Collection.remove:(Ljava/lang/Object;)Z
      96: pop
      97: aload_2
      98: ldc           #96                 // String provided
     100: invokeinterface #101,  2          // InterfaceMethod java/util/Collection.remove:(Ljava/lang/Object;)Z
     105: pop
     106: goto          245
     109: ldc           #97                 // String runtime
     111: aload         4
     113: invokevirtual #100                // Method java/lang/String.equals:(Ljava/lang/Object;)Z
     116: ifeq          140
     119: aload_2
     120: ldc           #95                 // String compile
     122: invokeinterface #101,  2          // InterfaceMethod java/util/Collection.remove:(Ljava/lang/Object;)Z
     127: pop
     128: aload_2
     129: ldc           #97                 // String runtime
     131: invokeinterface #101,  2          // InterfaceMethod java/util/Collection.remove:(Ljava/lang/Object;)Z
     136: pop
     137: goto          245
     140: ldc           #102                // String compile+runtime
     142: aload         4
     144: invokevirtual #100                // Method java/lang/String.equals:(Ljava/lang/Object;)Z
     147: ifeq          189
     150: aload_2
     151: ldc           #95                 // String compile
     153: invokeinterface #101,  2          // InterfaceMethod java/util/Collection.remove:(Ljava/lang/Object;)Z
     158: pop
     159: aload_2
     160: ldc           #94                 // String system
     162: invokeinterface #101,  2          // InterfaceMethod java/util/Collection.remove:(Ljava/lang/Object;)Z
     167: pop
     168: aload_2
     169: ldc           #96                 // String provided
     171: invokeinterface #101,  2          // InterfaceMethod java/util/Collection.remove:(Ljava/lang/Object;)Z
     176: pop
     177: aload_2
     178: ldc           #97                 // String runtime
     180: invokeinterface #101,  2          // InterfaceMethod java/util/Collection.remove:(Ljava/lang/Object;)Z
     185: pop
     186: goto          245
     189: ldc           #103                // String runtime+system
     191: aload         4
     193: invokevirtual #100                // Method java/lang/String.equals:(Ljava/lang/Object;)Z
     196: ifeq          229
     199: aload_2
     200: ldc           #95                 // String compile
     202: invokeinterface #101,  2          // InterfaceMethod java/util/Collection.remove:(Ljava/lang/Object;)Z
     207: pop
     208: aload_2
     209: ldc           #94                 // String system
     211: invokeinterface #101,  2          // InterfaceMethod java/util/Collection.remove:(Ljava/lang/Object;)Z
     216: pop
     217: aload_2
     218: ldc           #97                 // String runtime
     220: invokeinterface #101,  2          // InterfaceMethod java/util/Collection.remove:(Ljava/lang/Object;)Z
     225: pop
     226: goto          245
     229: ldc           #98                 // String test
     231: aload         4
     233: invokevirtual #100                // Method java/lang/String.equals:(Ljava/lang/Object;)Z
     236: ifeq          245
     239: aload_2
     240: invokeinterface #104,  1          // InterfaceMethod java/util/Collection.clear:()V
     245: goto          49
     248: aload_2
     249: areturn
}
