Compiled from "LifecyclePluginResolver.java"
public class org.apache.maven.lifecycle.internal.LifecyclePluginResolver {
  private org.apache.maven.plugin.version.PluginVersionResolver pluginVersionResolver;

  public org.apache.maven.lifecycle.internal.LifecyclePluginResolver(org.apache.maven.plugin.version.PluginVersionResolver);
    Code:
       0: aload_0
       1: invokespecial #1                  // Method java/lang/Object."<init>":()V
       4: aload_0
       5: aload_1
       6: putfield      #2                  // Field pluginVersionResolver:Lorg/apache/maven/plugin/version/PluginVersionResolver;
       9: return

  public org.apache.maven.lifecycle.internal.LifecyclePluginResolver();
    Code:
       0: aload_0
       1: invokespecial #1                  // Method java/lang/Object."<init>":()V
       4: return

  public void resolveMissingPluginVersions(org.apache.maven.project.MavenProject, org.apache.maven.execution.MavenSession) throws org.apache.maven.plugin.version.PluginVersionResolutionException;
    Code:
       0: new           #3                  // class java/util/HashMap
       3: dup
       4: bipush        64
       6: invokespecial #4                  // Method java/util/HashMap."<init>":(I)V
       9: astore_3
      10: aload_1
      11: invokevirtual #5                  // Method org/apache/maven/project/MavenProject.getBuildPlugins:()Ljava/util/List;
      14: invokeinterface #6,  1            // InterfaceMethod java/util/List.iterator:()Ljava/util/Iterator;
      19: astore        4
      21: aload         4
      23: invokeinterface #7,  1            // InterfaceMethod java/util/Iterator.hasNext:()Z
      28: ifeq          111
      31: aload         4
      33: invokeinterface #8,  1            // InterfaceMethod java/util/Iterator.next:()Ljava/lang/Object;
      38: checkcast     #9                  // class org/apache/maven/model/Plugin
      41: astore        5
      43: aload         5
      45: invokevirtual #10                 // Method org/apache/maven/model/Plugin.getVersion:()Ljava/lang/String;
      48: ifnonnull     91
      51: new           #11                 // class org/apache/maven/plugin/version/DefaultPluginVersionRequest
      54: dup
      55: aload         5
      57: aload_2
      58: invokevirtual #12                 // Method org/apache/maven/execution/MavenSession.getRepositorySession:()Lorg/sonatype/aether/RepositorySystemSession;
      61: aload_1
      62: invokevirtual #13                 // Method org/apache/maven/project/MavenProject.getRemotePluginRepositories:()Ljava/util/List;
      65: invokespecial #14                 // Method org/apache/maven/plugin/version/DefaultPluginVersionRequest."<init>":(Lorg/apache/maven/model/Plugin;Lorg/sonatype/aether/RepositorySystemSession;Ljava/util/List;)V
      68: astore        6
      70: aload         5
      72: aload_0
      73: getfield      #2                  // Field pluginVersionResolver:Lorg/apache/maven/plugin/version/PluginVersionResolver;
      76: aload         6
      78: invokeinterface #15,  2           // InterfaceMethod org/apache/maven/plugin/version/PluginVersionResolver.resolve:(Lorg/apache/maven/plugin/version/PluginVersionRequest;)Lorg/apache/maven/plugin/version/PluginVersionResult;
      83: invokeinterface #16,  1           // InterfaceMethod org/apache/maven/plugin/version/PluginVersionResult.getVersion:()Ljava/lang/String;
      88: invokevirtual #17                 // Method org/apache/maven/model/Plugin.setVersion:(Ljava/lang/String;)V
      91: aload_3
      92: aload         5
      94: invokevirtual #18                 // Method org/apache/maven/model/Plugin.getKey:()Ljava/lang/String;
      97: aload         5
      99: invokevirtual #10                 // Method org/apache/maven/model/Plugin.getVersion:()Ljava/lang/String;
     102: invokeinterface #19,  3           // InterfaceMethod java/util/Map.put:(Ljava/lang/Object;Ljava/lang/Object;)Ljava/lang/Object;
     107: pop
     108: goto          21
     111: aload_1
     112: invokevirtual #20                 // Method org/apache/maven/project/MavenProject.getPluginManagement:()Lorg/apache/maven/model/PluginManagement;
     115: astore        4
     117: aload         4
     119: ifnull        234
     122: aload         4
     124: invokevirtual #21                 // Method org/apache/maven/model/PluginManagement.getPlugins:()Ljava/util/List;
     127: invokeinterface #6,  1            // InterfaceMethod java/util/List.iterator:()Ljava/util/Iterator;
     132: astore        5
     134: aload         5
     136: invokeinterface #7,  1            // InterfaceMethod java/util/Iterator.hasNext:()Z
     141: ifeq          234
     144: aload         5
     146: invokeinterface #8,  1            // InterfaceMethod java/util/Iterator.next:()Ljava/lang/Object;
     151: checkcast     #9                  // class org/apache/maven/model/Plugin
     154: astore        6
     156: aload         6
     158: invokevirtual #10                 // Method org/apache/maven/model/Plugin.getVersion:()Ljava/lang/String;
     161: ifnonnull     231
     164: aload         6
     166: aload_3
     167: aload         6
     169: invokevirtual #18                 // Method org/apache/maven/model/Plugin.getKey:()Ljava/lang/String;
     172: invokeinterface #22,  2           // InterfaceMethod java/util/Map.get:(Ljava/lang/Object;)Ljava/lang/Object;
     177: checkcast     #23                 // class java/lang/String
     180: invokevirtual #17                 // Method org/apache/maven/model/Plugin.setVersion:(Ljava/lang/String;)V
     183: aload         6
     185: invokevirtual #10                 // Method org/apache/maven/model/Plugin.getVersion:()Ljava/lang/String;
     188: ifnonnull     231
     191: new           #11                 // class org/apache/maven/plugin/version/DefaultPluginVersionRequest
     194: dup
     195: aload         6
     197: aload_2
     198: invokevirtual #12                 // Method org/apache/maven/execution/MavenSession.getRepositorySession:()Lorg/sonatype/aether/RepositorySystemSession;
     201: aload_1
     202: invokevirtual #13                 // Method org/apache/maven/project/MavenProject.getRemotePluginRepositories:()Ljava/util/List;
     205: invokespecial #14                 // Method org/apache/maven/plugin/version/DefaultPluginVersionRequest."<init>":(Lorg/apache/maven/model/Plugin;Lorg/sonatype/aether/RepositorySystemSession;Ljava/util/List;)V
     208: astore        7
     210: aload         6
     212: aload_0
     213: getfield      #2                  // Field pluginVersionResolver:Lorg/apache/maven/plugin/version/PluginVersionResolver;
     216: aload         7
     218: invokeinterface #15,  2           // InterfaceMethod org/apache/maven/plugin/version/PluginVersionResolver.resolve:(Lorg/apache/maven/plugin/version/PluginVersionRequest;)Lorg/apache/maven/plugin/version/PluginVersionResult;
     223: invokeinterface #16,  1           // InterfaceMethod org/apache/maven/plugin/version/PluginVersionResult.getVersion:()Ljava/lang/String;
     228: invokevirtual #17                 // Method org/apache/maven/model/Plugin.setVersion:(Ljava/lang/String;)V
     231: goto          134
     234: return
}
