Compiled from "ProjectIndex.java"
public final class org.apache.maven.lifecycle.internal.ProjectIndex {
  private final java.util.Map<java.lang.String, org.apache.maven.project.MavenProject> projects;

  private final java.util.Map<java.lang.String, java.lang.Integer> indices;

  public org.apache.maven.lifecycle.internal.ProjectIndex(java.util.List<org.apache.maven.project.MavenProject>);
    Code:
       0: aload_0
       1: invokespecial #1                  // Method java/lang/Object."<init>":()V
       4: aload_0
       5: new           #2                  // class java/util/HashMap
       8: dup
       9: aload_1
      10: invokeinterface #3,  1            // InterfaceMethod java/util/List.size:()I
      15: iconst_2
      16: imul
      17: invokespecial #4                  // Method java/util/HashMap."<init>":(I)V
      20: putfield      #5                  // Field projects:Ljava/util/Map;
      23: aload_0
      24: new           #2                  // class java/util/HashMap
      27: dup
      28: aload_1
      29: invokeinterface #3,  1            // InterfaceMethod java/util/List.size:()I
      34: iconst_2
      35: imul
      36: invokespecial #4                  // Method java/util/HashMap."<init>":(I)V
      39: putfield      #6                  // Field indices:Ljava/util/Map;
      42: iconst_0
      43: istore_2
      44: iload_2
      45: aload_1
      46: invokeinterface #3,  1            // InterfaceMethod java/util/List.size:()I
      51: if_icmpge     106
      54: aload_1
      55: iload_2
      56: invokeinterface #7,  2            // InterfaceMethod java/util/List.get:(I)Ljava/lang/Object;
      61: checkcast     #8                  // class org/apache/maven/project/MavenProject
      64: astore_3
      65: aload_3
      66: invokestatic  #9                  // Method org/apache/maven/lifecycle/internal/BuilderCommon.getKey:(Lorg/apache/maven/project/MavenProject;)Ljava/lang/String;
      69: astore        4
      71: aload_0
      72: invokevirtual #10                 // Method getProjects:()Ljava/util/Map;
      75: aload         4
      77: aload_3
      78: invokeinterface #11,  3           // InterfaceMethod java/util/Map.put:(Ljava/lang/Object;Ljava/lang/Object;)Ljava/lang/Object;
      83: pop
      84: aload_0
      85: invokevirtual #12                 // Method getIndices:()Ljava/util/Map;
      88: aload         4
      90: iload_2
      91: invokestatic  #13                 // Method java/lang/Integer.valueOf:(I)Ljava/lang/Integer;
      94: invokeinterface #11,  3           // InterfaceMethod java/util/Map.put:(Ljava/lang/Object;Ljava/lang/Object;)Ljava/lang/Object;
      99: pop
     100: iinc          2, 1
     103: goto          44
     106: return

  public java.util.Map<java.lang.String, org.apache.maven.project.MavenProject> getProjects();
    Code:
       0: aload_0
       1: getfield      #5                  // Field projects:Ljava/util/Map;
       4: areturn

  public java.util.Map<java.lang.String, java.lang.Integer> getIndices();
    Code:
       0: aload_0
       1: getfield      #6                  // Field indices:Ljava/util/Map;
       4: areturn
}
