Compiled from "OpenApi.scala"
public final class io.udash.rest.openapi.Components$$anon$27$$anon$28$$anon$29 extends com.avsystem.commons.serialization.ApplyUnapplyCodec<io.udash.rest.openapi.Components> {
  private final io.udash.rest.openapi.Components$$anon$27$$anon$28 $outer;

  public com.avsystem.commons.serialization.GenCodec<?>[] dependencies();
    Code:
       0: getstatic     #29                 // Field com/avsystem/commons/serialization/GenCodec$.MODULE$:Lcom/avsystem/commons/serialization/GenCodec$;
       3: getstatic     #34                 // Field com/avsystem/commons/serialization/GenKeyCodec$.MODULE$:Lcom/avsystem/commons/serialization/GenKeyCodec$;
       6: invokevirtual #38                 // Method com/avsystem/commons/serialization/GenKeyCodec$.StringKeyCodec:()Lcom/avsystem/commons/serialization/GenKeyCodec;
       9: getstatic     #43                 // Field io/udash/rest/openapi/RefOr$.MODULE$:Lio/udash/rest/openapi/RefOr$;
      12: getstatic     #48                 // Field io/udash/rest/openapi/Schema$.MODULE$:Lio/udash/rest/openapi/Schema$;
      15: invokevirtual #51                 // Method io/udash/rest/openapi/Schema$.codec:()Lcom/avsystem/commons/serialization/GenObjectCodec;
      18: invokevirtual #54                 // Method io/udash/rest/openapi/RefOr$.codec:(Lcom/avsystem/commons/serialization/GenObjectCodec;)Lcom/avsystem/commons/serialization/GenObjectCodec;
      21: getstatic     #59                 // Field scala/collection/immutable/Map$.MODULE$:Lscala/collection/immutable/Map$;
      24: invokevirtual #63                 // Method scala/collection/immutable/Map$.canBuildFrom:()Lscala/collection/generic/CanBuildFrom;
      27: invokevirtual #67                 // Method com/avsystem/commons/serialization/GenCodec$.mapCodec:(Lcom/avsystem/commons/serialization/GenKeyCodec;Lcom/avsystem/commons/serialization/GenCodec;Lscala/collection/generic/CanBuildFrom;)Lcom/avsystem/commons/serialization/GenObjectCodec;
      30: astore_1
      31: getstatic     #29                 // Field com/avsystem/commons/serialization/GenCodec$.MODULE$:Lcom/avsystem/commons/serialization/GenCodec$;
      34: getstatic     #34                 // Field com/avsystem/commons/serialization/GenKeyCodec$.MODULE$:Lcom/avsystem/commons/serialization/GenKeyCodec$;
      37: invokevirtual #38                 // Method com/avsystem/commons/serialization/GenKeyCodec$.StringKeyCodec:()Lcom/avsystem/commons/serialization/GenKeyCodec;
      40: getstatic     #43                 // Field io/udash/rest/openapi/RefOr$.MODULE$:Lio/udash/rest/openapi/RefOr$;
      43: getstatic     #72                 // Field io/udash/rest/openapi/Response$.MODULE$:Lio/udash/rest/openapi/Response$;
      46: invokevirtual #73                 // Method io/udash/rest/openapi/Response$.codec:()Lcom/avsystem/commons/serialization/GenObjectCodec;
      49: invokevirtual #54                 // Method io/udash/rest/openapi/RefOr$.codec:(Lcom/avsystem/commons/serialization/GenObjectCodec;)Lcom/avsystem/commons/serialization/GenObjectCodec;
      52: getstatic     #59                 // Field scala/collection/immutable/Map$.MODULE$:Lscala/collection/immutable/Map$;
      55: invokevirtual #63                 // Method scala/collection/immutable/Map$.canBuildFrom:()Lscala/collection/generic/CanBuildFrom;
      58: invokevirtual #67                 // Method com/avsystem/commons/serialization/GenCodec$.mapCodec:(Lcom/avsystem/commons/serialization/GenKeyCodec;Lcom/avsystem/commons/serialization/GenCodec;Lscala/collection/generic/CanBuildFrom;)Lcom/avsystem/commons/serialization/GenObjectCodec;
      61: astore_2
      62: getstatic     #29                 // Field com/avsystem/commons/serialization/GenCodec$.MODULE$:Lcom/avsystem/commons/serialization/GenCodec$;
      65: getstatic     #34                 // Field com/avsystem/commons/serialization/GenKeyCodec$.MODULE$:Lcom/avsystem/commons/serialization/GenKeyCodec$;
      68: invokevirtual #38                 // Method com/avsystem/commons/serialization/GenKeyCodec$.StringKeyCodec:()Lcom/avsystem/commons/serialization/GenKeyCodec;
      71: getstatic     #43                 // Field io/udash/rest/openapi/RefOr$.MODULE$:Lio/udash/rest/openapi/RefOr$;
      74: getstatic     #78                 // Field io/udash/rest/openapi/Parameter$.MODULE$:Lio/udash/rest/openapi/Parameter$;
      77: invokevirtual #79                 // Method io/udash/rest/openapi/Parameter$.codec:()Lcom/avsystem/commons/serialization/GenObjectCodec;
      80: invokevirtual #54                 // Method io/udash/rest/openapi/RefOr$.codec:(Lcom/avsystem/commons/serialization/GenObjectCodec;)Lcom/avsystem/commons/serialization/GenObjectCodec;
      83: getstatic     #59                 // Field scala/collection/immutable/Map$.MODULE$:Lscala/collection/immutable/Map$;
      86: invokevirtual #63                 // Method scala/collection/immutable/Map$.canBuildFrom:()Lscala/collection/generic/CanBuildFrom;
      89: invokevirtual #67                 // Method com/avsystem/commons/serialization/GenCodec$.mapCodec:(Lcom/avsystem/commons/serialization/GenKeyCodec;Lcom/avsystem/commons/serialization/GenCodec;Lscala/collection/generic/CanBuildFrom;)Lcom/avsystem/commons/serialization/GenObjectCodec;
      92: astore_3
      93: getstatic     #29                 // Field com/avsystem/commons/serialization/GenCodec$.MODULE$:Lcom/avsystem/commons/serialization/GenCodec$;
      96: getstatic     #34                 // Field com/avsystem/commons/serialization/GenKeyCodec$.MODULE$:Lcom/avsystem/commons/serialization/GenKeyCodec$;
      99: invokevirtual #38                 // Method com/avsystem/commons/serialization/GenKeyCodec$.StringKeyCodec:()Lcom/avsystem/commons/serialization/GenKeyCodec;
     102: getstatic     #43                 // Field io/udash/rest/openapi/RefOr$.MODULE$:Lio/udash/rest/openapi/RefOr$;
     105: getstatic     #84                 // Field io/udash/rest/openapi/Example$.MODULE$:Lio/udash/rest/openapi/Example$;
     108: invokevirtual #85                 // Method io/udash/rest/openapi/Example$.codec:()Lcom/avsystem/commons/serialization/GenObjectCodec;
     111: invokevirtual #54                 // Method io/udash/rest/openapi/RefOr$.codec:(Lcom/avsystem/commons/serialization/GenObjectCodec;)Lcom/avsystem/commons/serialization/GenObjectCodec;
     114: getstatic     #59                 // Field scala/collection/immutable/Map$.MODULE$:Lscala/collection/immutable/Map$;
     117: invokevirtual #63                 // Method scala/collection/immutable/Map$.canBuildFrom:()Lscala/collection/generic/CanBuildFrom;
     120: invokevirtual #67                 // Method com/avsystem/commons/serialization/GenCodec$.mapCodec:(Lcom/avsystem/commons/serialization/GenKeyCodec;Lcom/avsystem/commons/serialization/GenCodec;Lscala/collection/generic/CanBuildFrom;)Lcom/avsystem/commons/serialization/GenObjectCodec;
     123: astore        4
     125: getstatic     #29                 // Field com/avsystem/commons/serialization/GenCodec$.MODULE$:Lcom/avsystem/commons/serialization/GenCodec$;
     128: getstatic     #34                 // Field com/avsystem/commons/serialization/GenKeyCodec$.MODULE$:Lcom/avsystem/commons/serialization/GenKeyCodec$;
     131: invokevirtual #38                 // Method com/avsystem/commons/serialization/GenKeyCodec$.StringKeyCodec:()Lcom/avsystem/commons/serialization/GenKeyCodec;
     134: getstatic     #43                 // Field io/udash/rest/openapi/RefOr$.MODULE$:Lio/udash/rest/openapi/RefOr$;
     137: getstatic     #90                 // Field io/udash/rest/openapi/RequestBody$.MODULE$:Lio/udash/rest/openapi/RequestBody$;
     140: invokevirtual #91                 // Method io/udash/rest/openapi/RequestBody$.codec:()Lcom/avsystem/commons/serialization/GenObjectCodec;
     143: invokevirtual #54                 // Method io/udash/rest/openapi/RefOr$.codec:(Lcom/avsystem/commons/serialization/GenObjectCodec;)Lcom/avsystem/commons/serialization/GenObjectCodec;
     146: getstatic     #59                 // Field scala/collection/immutable/Map$.MODULE$:Lscala/collection/immutable/Map$;
     149: invokevirtual #63                 // Method scala/collection/immutable/Map$.canBuildFrom:()Lscala/collection/generic/CanBuildFrom;
     152: invokevirtual #67                 // Method com/avsystem/commons/serialization/GenCodec$.mapCodec:(Lcom/avsystem/commons/serialization/GenKeyCodec;Lcom/avsystem/commons/serialization/GenCodec;Lscala/collection/generic/CanBuildFrom;)Lcom/avsystem/commons/serialization/GenObjectCodec;
     155: astore        5
     157: getstatic     #29                 // Field com/avsystem/commons/serialization/GenCodec$.MODULE$:Lcom/avsystem/commons/serialization/GenCodec$;
     160: getstatic     #34                 // Field com/avsystem/commons/serialization/GenKeyCodec$.MODULE$:Lcom/avsystem/commons/serialization/GenKeyCodec$;
     163: invokevirtual #38                 // Method com/avsystem/commons/serialization/GenKeyCodec$.StringKeyCodec:()Lcom/avsystem/commons/serialization/GenKeyCodec;
     166: getstatic     #43                 // Field io/udash/rest/openapi/RefOr$.MODULE$:Lio/udash/rest/openapi/RefOr$;
     169: getstatic     #96                 // Field io/udash/rest/openapi/Header$.MODULE$:Lio/udash/rest/openapi/Header$;
     172: invokevirtual #97                 // Method io/udash/rest/openapi/Header$.codec:()Lcom/avsystem/commons/serialization/GenObjectCodec;
     175: invokevirtual #54                 // Method io/udash/rest/openapi/RefOr$.codec:(Lcom/avsystem/commons/serialization/GenObjectCodec;)Lcom/avsystem/commons/serialization/GenObjectCodec;
     178: getstatic     #59                 // Field scala/collection/immutable/Map$.MODULE$:Lscala/collection/immutable/Map$;
     181: invokevirtual #63                 // Method scala/collection/immutable/Map$.canBuildFrom:()Lscala/collection/generic/CanBuildFrom;
     184: invokevirtual #67                 // Method com/avsystem/commons/serialization/GenCodec$.mapCodec:(Lcom/avsystem/commons/serialization/GenKeyCodec;Lcom/avsystem/commons/serialization/GenCodec;Lscala/collection/generic/CanBuildFrom;)Lcom/avsystem/commons/serialization/GenObjectCodec;
     187: astore        6
     189: getstatic     #29                 // Field com/avsystem/commons/serialization/GenCodec$.MODULE$:Lcom/avsystem/commons/serialization/GenCodec$;
     192: getstatic     #34                 // Field com/avsystem/commons/serialization/GenKeyCodec$.MODULE$:Lcom/avsystem/commons/serialization/GenKeyCodec$;
     195: invokevirtual #38                 // Method com/avsystem/commons/serialization/GenKeyCodec$.StringKeyCodec:()Lcom/avsystem/commons/serialization/GenKeyCodec;
     198: getstatic     #43                 // Field io/udash/rest/openapi/RefOr$.MODULE$:Lio/udash/rest/openapi/RefOr$;
     201: getstatic     #102                // Field io/udash/rest/openapi/SecurityScheme$.MODULE$:Lio/udash/rest/openapi/SecurityScheme$;
     204: invokevirtual #103                // Method io/udash/rest/openapi/SecurityScheme$.codec:()Lcom/avsystem/commons/serialization/GenObjectCodec;
     207: invokevirtual #54                 // Method io/udash/rest/openapi/RefOr$.codec:(Lcom/avsystem/commons/serialization/GenObjectCodec;)Lcom/avsystem/commons/serialization/GenObjectCodec;
     210: getstatic     #59                 // Field scala/collection/immutable/Map$.MODULE$:Lscala/collection/immutable/Map$;
     213: invokevirtual #63                 // Method scala/collection/immutable/Map$.canBuildFrom:()Lscala/collection/generic/CanBuildFrom;
     216: invokevirtual #67                 // Method com/avsystem/commons/serialization/GenCodec$.mapCodec:(Lcom/avsystem/commons/serialization/GenKeyCodec;Lcom/avsystem/commons/serialization/GenCodec;Lscala/collection/generic/CanBuildFrom;)Lcom/avsystem/commons/serialization/GenObjectCodec;
     219: astore        7
     221: getstatic     #29                 // Field com/avsystem/commons/serialization/GenCodec$.MODULE$:Lcom/avsystem/commons/serialization/GenCodec$;
     224: getstatic     #34                 // Field com/avsystem/commons/serialization/GenKeyCodec$.MODULE$:Lcom/avsystem/commons/serialization/GenKeyCodec$;
     227: invokevirtual #38                 // Method com/avsystem/commons/serialization/GenKeyCodec$.StringKeyCodec:()Lcom/avsystem/commons/serialization/GenKeyCodec;
     230: getstatic     #43                 // Field io/udash/rest/openapi/RefOr$.MODULE$:Lio/udash/rest/openapi/RefOr$;
     233: getstatic     #108                // Field io/udash/rest/openapi/Link$.MODULE$:Lio/udash/rest/openapi/Link$;
     236: invokevirtual #109                // Method io/udash/rest/openapi/Link$.codec:()Lcom/avsystem/commons/serialization/GenObjectCodec;
     239: invokevirtual #54                 // Method io/udash/rest/openapi/RefOr$.codec:(Lcom/avsystem/commons/serialization/GenObjectCodec;)Lcom/avsystem/commons/serialization/GenObjectCodec;
     242: getstatic     #59                 // Field scala/collection/immutable/Map$.MODULE$:Lscala/collection/immutable/Map$;
     245: invokevirtual #63                 // Method scala/collection/immutable/Map$.canBuildFrom:()Lscala/collection/generic/CanBuildFrom;
     248: invokevirtual #67                 // Method com/avsystem/commons/serialization/GenCodec$.mapCodec:(Lcom/avsystem/commons/serialization/GenKeyCodec;Lcom/avsystem/commons/serialization/GenCodec;Lscala/collection/generic/CanBuildFrom;)Lcom/avsystem/commons/serialization/GenObjectCodec;
     251: astore        8
     253: getstatic     #29                 // Field com/avsystem/commons/serialization/GenCodec$.MODULE$:Lcom/avsystem/commons/serialization/GenCodec$;
     256: getstatic     #34                 // Field com/avsystem/commons/serialization/GenKeyCodec$.MODULE$:Lcom/avsystem/commons/serialization/GenKeyCodec$;
     259: invokevirtual #38                 // Method com/avsystem/commons/serialization/GenKeyCodec$.StringKeyCodec:()Lcom/avsystem/commons/serialization/GenKeyCodec;
     262: getstatic     #43                 // Field io/udash/rest/openapi/RefOr$.MODULE$:Lio/udash/rest/openapi/RefOr$;
     265: getstatic     #114                // Field io/udash/rest/openapi/Callback$.MODULE$:Lio/udash/rest/openapi/Callback$;
     268: invokevirtual #115                // Method io/udash/rest/openapi/Callback$.codec:()Lcom/avsystem/commons/serialization/GenObjectCodec;
     271: invokevirtual #54                 // Method io/udash/rest/openapi/RefOr$.codec:(Lcom/avsystem/commons/serialization/GenObjectCodec;)Lcom/avsystem/commons/serialization/GenObjectCodec;
     274: getstatic     #59                 // Field scala/collection/immutable/Map$.MODULE$:Lscala/collection/immutable/Map$;
     277: invokevirtual #63                 // Method scala/collection/immutable/Map$.canBuildFrom:()Lscala/collection/generic/CanBuildFrom;
     280: invokevirtual #67                 // Method com/avsystem/commons/serialization/GenCodec$.mapCodec:(Lcom/avsystem/commons/serialization/GenKeyCodec;Lcom/avsystem/commons/serialization/GenCodec;Lscala/collection/generic/CanBuildFrom;)Lcom/avsystem/commons/serialization/GenObjectCodec;
     283: astore        9
     285: bipush        9
     287: anewarray     #117                // class com/avsystem/commons/serialization/GenCodec
     290: astore        10
     292: aload         10
     294: iconst_0
     295: aload_1
     296: aastore
     297: aload         10
     299: iconst_1
     300: aload_2
     301: aastore
     302: aload         10
     304: iconst_2
     305: aload_3
     306: aastore
     307: aload         10
     309: iconst_3
     310: aload         4
     312: aastore
     313: aload         10
     315: iconst_4
     316: aload         5
     318: aastore
     319: aload         10
     321: iconst_5
     322: aload         6
     324: aastore
     325: aload         10
     327: bipush        6
     329: aload         7
     331: aastore
     332: aload         10
     334: bipush        7
     336: aload         8
     338: aastore
     339: aload         10
     341: bipush        8
     343: aload         9
     345: aastore
     346: aload         10
     348: areturn

  public io.udash.rest.openapi.Components instantiate(com.avsystem.commons.serialization.FieldValues);
    Code:
       0: new           #136                // class io/udash/rest/openapi/Components
       3: dup
       4: aload_0
       5: aload_1
       6: iconst_0
       7: aload_0
       8: invokedynamic #159,  0            // InvokeDynamic #0:apply:(Lio/udash/rest/openapi/Components$$anon$27$$anon$28$$anon$29;)Lscala/Function0;
      13: invokevirtual #163                // Method getField:(Lcom/avsystem/commons/serialization/FieldValues;ILscala/Function0;)Ljava/lang/Object;
      16: checkcast     #165                // class scala/collection/immutable/Map
      19: aload_0
      20: aload_1
      21: iconst_1
      22: aload_0
      23: invokedynamic #170,  0            // InvokeDynamic #1:apply:(Lio/udash/rest/openapi/Components$$anon$27$$anon$28$$anon$29;)Lscala/Function0;
      28: invokevirtual #163                // Method getField:(Lcom/avsystem/commons/serialization/FieldValues;ILscala/Function0;)Ljava/lang/Object;
      31: checkcast     #165                // class scala/collection/immutable/Map
      34: aload_0
      35: aload_1
      36: iconst_2
      37: aload_0
      38: invokedynamic #175,  0            // InvokeDynamic #2:apply:(Lio/udash/rest/openapi/Components$$anon$27$$anon$28$$anon$29;)Lscala/Function0;
      43: invokevirtual #163                // Method getField:(Lcom/avsystem/commons/serialization/FieldValues;ILscala/Function0;)Ljava/lang/Object;
      46: checkcast     #165                // class scala/collection/immutable/Map
      49: aload_0
      50: aload_1
      51: iconst_3
      52: aload_0
      53: invokedynamic #180,  0            // InvokeDynamic #3:apply:(Lio/udash/rest/openapi/Components$$anon$27$$anon$28$$anon$29;)Lscala/Function0;
      58: invokevirtual #163                // Method getField:(Lcom/avsystem/commons/serialization/FieldValues;ILscala/Function0;)Ljava/lang/Object;
      61: checkcast     #165                // class scala/collection/immutable/Map
      64: aload_0
      65: aload_1
      66: iconst_4
      67: aload_0
      68: invokedynamic #185,  0            // InvokeDynamic #4:apply:(Lio/udash/rest/openapi/Components$$anon$27$$anon$28$$anon$29;)Lscala/Function0;
      73: invokevirtual #163                // Method getField:(Lcom/avsystem/commons/serialization/FieldValues;ILscala/Function0;)Ljava/lang/Object;
      76: checkcast     #165                // class scala/collection/immutable/Map
      79: aload_0
      80: aload_1
      81: iconst_5
      82: aload_0
      83: invokedynamic #190,  0            // InvokeDynamic #5:apply:(Lio/udash/rest/openapi/Components$$anon$27$$anon$28$$anon$29;)Lscala/Function0;
      88: invokevirtual #163                // Method getField:(Lcom/avsystem/commons/serialization/FieldValues;ILscala/Function0;)Ljava/lang/Object;
      91: checkcast     #165                // class scala/collection/immutable/Map
      94: aload_0
      95: aload_1
      96: bipush        6
      98: aload_0
      99: invokedynamic #195,  0            // InvokeDynamic #6:apply:(Lio/udash/rest/openapi/Components$$anon$27$$anon$28$$anon$29;)Lscala/Function0;
     104: invokevirtual #163                // Method getField:(Lcom/avsystem/commons/serialization/FieldValues;ILscala/Function0;)Ljava/lang/Object;
     107: checkcast     #165                // class scala/collection/immutable/Map
     110: aload_0
     111: aload_1
     112: bipush        7
     114: aload_0
     115: invokedynamic #200,  0            // InvokeDynamic #7:apply:(Lio/udash/rest/openapi/Components$$anon$27$$anon$28$$anon$29;)Lscala/Function0;
     120: invokevirtual #163                // Method getField:(Lcom/avsystem/commons/serialization/FieldValues;ILscala/Function0;)Ljava/lang/Object;
     123: checkcast     #165                // class scala/collection/immutable/Map
     126: aload_0
     127: aload_1
     128: bipush        8
     130: aload_0
     131: invokedynamic #205,  0            // InvokeDynamic #8:apply:(Lio/udash/rest/openapi/Components$$anon$27$$anon$28$$anon$29;)Lscala/Function0;
     136: invokevirtual #163                // Method getField:(Lcom/avsystem/commons/serialization/FieldValues;ILscala/Function0;)Ljava/lang/Object;
     139: checkcast     #165                // class scala/collection/immutable/Map
     142: invokespecial #209                // Method io/udash/rest/openapi/Components."<init>":(Lscala/collection/immutable/Map;Lscala/collection/immutable/Map;Lscala/collection/immutable/Map;Lscala/collection/immutable/Map;Lscala/collection/immutable/Map;Lscala/collection/immutable/Map;Lscala/collection/immutable/Map;Lscala/collection/immutable/Map;Lscala/collection/immutable/Map;)V
     145: areturn

  public int size(io.udash.rest.openapi.Components);
    Code:
       0: bipush        9
       2: iconst_0
       3: aload_1
       4: invokevirtual #216                // Method io/udash/rest/openapi/Components.schemas:()Lscala/collection/immutable/Map;
       7: aload_0
       8: getfield      #218                // Field $outer:Lio/udash/rest/openapi/Components$$anon$27$$anon$28;
      11: getfield      #222                // Field io/udash/rest/openapi/Components$$anon$27$$anon$28.companion$macro$1$9:Ljava/lang/Object;
      14: checkcast     #224                // class io/udash/rest/openapi/Components$
      17: invokevirtual #227                // Method io/udash/rest/openapi/Components$.$lessinit$greater$default$1:()Lscala/collection/immutable/Map;
      20: astore_2
      21: dup
      22: ifnonnull     33
      25: pop
      26: aload_2
      27: ifnull        40
      30: goto          44
      33: aload_2
      34: invokevirtual #233                // Method java/lang/Object.equals:(Ljava/lang/Object;)Z
      37: ifeq          44
      40: iconst_1
      41: goto          45
      44: iconst_0
      45: iadd
      46: aload_1
      47: invokevirtual #236                // Method io/udash/rest/openapi/Components.responses:()Lscala/collection/immutable/Map;
      50: aload_0
      51: getfield      #218                // Field $outer:Lio/udash/rest/openapi/Components$$anon$27$$anon$28;
      54: getfield      #222                // Field io/udash/rest/openapi/Components$$anon$27$$anon$28.companion$macro$1$9:Ljava/lang/Object;
      57: checkcast     #224                // class io/udash/rest/openapi/Components$
      60: invokevirtual #239                // Method io/udash/rest/openapi/Components$.$lessinit$greater$default$2:()Lscala/collection/immutable/Map;
      63: astore_3
      64: dup
      65: ifnonnull     76
      68: pop
      69: aload_3
      70: ifnull        83
      73: goto          87
      76: aload_3
      77: invokevirtual #233                // Method java/lang/Object.equals:(Ljava/lang/Object;)Z
      80: ifeq          87
      83: iconst_1
      84: goto          88
      87: iconst_0
      88: iadd
      89: aload_1
      90: invokevirtual #242                // Method io/udash/rest/openapi/Components.parameters:()Lscala/collection/immutable/Map;
      93: aload_0
      94: getfield      #218                // Field $outer:Lio/udash/rest/openapi/Components$$anon$27$$anon$28;
      97: getfield      #222                // Field io/udash/rest/openapi/Components$$anon$27$$anon$28.companion$macro$1$9:Ljava/lang/Object;
     100: checkcast     #224                // class io/udash/rest/openapi/Components$
     103: invokevirtual #245                // Method io/udash/rest/openapi/Components$.$lessinit$greater$default$3:()Lscala/collection/immutable/Map;
     106: astore        4
     108: dup
     109: ifnonnull     121
     112: pop
     113: aload         4
     115: ifnull        129
     118: goto          133
     121: aload         4
     123: invokevirtual #233                // Method java/lang/Object.equals:(Ljava/lang/Object;)Z
     126: ifeq          133
     129: iconst_1
     130: goto          134
     133: iconst_0
     134: iadd
     135: aload_1
     136: invokevirtual #248                // Method io/udash/rest/openapi/Components.examples:()Lscala/collection/immutable/Map;
     139: aload_0
     140: getfield      #218                // Field $outer:Lio/udash/rest/openapi/Components$$anon$27$$anon$28;
     143: getfield      #222                // Field io/udash/rest/openapi/Components$$anon$27$$anon$28.companion$macro$1$9:Ljava/lang/Object;
     146: checkcast     #224                // class io/udash/rest/openapi/Components$
     149: invokevirtual #251                // Method io/udash/rest/openapi/Components$.$lessinit$greater$default$4:()Lscala/collection/immutable/Map;
     152: astore        5
     154: dup
     155: ifnonnull     167
     158: pop
     159: aload         5
     161: ifnull        175
     164: goto          179
     167: aload         5
     169: invokevirtual #233                // Method java/lang/Object.equals:(Ljava/lang/Object;)Z
     172: ifeq          179
     175: iconst_1
     176: goto          180
     179: iconst_0
     180: iadd
     181: aload_1
     182: invokevirtual #254                // Method io/udash/rest/openapi/Components.requestBodies:()Lscala/collection/immutable/Map;
     185: aload_0
     186: getfield      #218                // Field $outer:Lio/udash/rest/openapi/Components$$anon$27$$anon$28;
     189: getfield      #222                // Field io/udash/rest/openapi/Components$$anon$27$$anon$28.companion$macro$1$9:Ljava/lang/Object;
     192: checkcast     #224                // class io/udash/rest/openapi/Components$
     195: invokevirtual #257                // Method io/udash/rest/openapi/Components$.$lessinit$greater$default$5:()Lscala/collection/immutable/Map;
     198: astore        6
     200: dup
     201: ifnonnull     213
     204: pop
     205: aload         6
     207: ifnull        221
     210: goto          225
     213: aload         6
     215: invokevirtual #233                // Method java/lang/Object.equals:(Ljava/lang/Object;)Z
     218: ifeq          225
     221: iconst_1
     222: goto          226
     225: iconst_0
     226: iadd
     227: aload_1
     228: invokevirtual #260                // Method io/udash/rest/openapi/Components.headers:()Lscala/collection/immutable/Map;
     231: aload_0
     232: getfield      #218                // Field $outer:Lio/udash/rest/openapi/Components$$anon$27$$anon$28;
     235: getfield      #222                // Field io/udash/rest/openapi/Components$$anon$27$$anon$28.companion$macro$1$9:Ljava/lang/Object;
     238: checkcast     #224                // class io/udash/rest/openapi/Components$
     241: invokevirtual #263                // Method io/udash/rest/openapi/Components$.$lessinit$greater$default$6:()Lscala/collection/immutable/Map;
     244: astore        7
     246: dup
     247: ifnonnull     259
     250: pop
     251: aload         7
     253: ifnull        267
     256: goto          271
     259: aload         7
     261: invokevirtual #233                // Method java/lang/Object.equals:(Ljava/lang/Object;)Z
     264: ifeq          271
     267: iconst_1
     268: goto          272
     271: iconst_0
     272: iadd
     273: aload_1
     274: invokevirtual #266                // Method io/udash/rest/openapi/Components.securitySchemes:()Lscala/collection/immutable/Map;
     277: aload_0
     278: getfield      #218                // Field $outer:Lio/udash/rest/openapi/Components$$anon$27$$anon$28;
     281: getfield      #222                // Field io/udash/rest/openapi/Components$$anon$27$$anon$28.companion$macro$1$9:Ljava/lang/Object;
     284: checkcast     #224                // class io/udash/rest/openapi/Components$
     287: invokevirtual #269                // Method io/udash/rest/openapi/Components$.$lessinit$greater$default$7:()Lscala/collection/immutable/Map;
     290: astore        8
     292: dup
     293: ifnonnull     305
     296: pop
     297: aload         8
     299: ifnull        313
     302: goto          317
     305: aload         8
     307: invokevirtual #233                // Method java/lang/Object.equals:(Ljava/lang/Object;)Z
     310: ifeq          317
     313: iconst_1
     314: goto          318
     317: iconst_0
     318: iadd
     319: aload_1
     320: invokevirtual #272                // Method io/udash/rest/openapi/Components.links:()Lscala/collection/immutable/Map;
     323: aload_0
     324: getfield      #218                // Field $outer:Lio/udash/rest/openapi/Components$$anon$27$$anon$28;
     327: getfield      #222                // Field io/udash/rest/openapi/Components$$anon$27$$anon$28.companion$macro$1$9:Ljava/lang/Object;
     330: checkcast     #224                // class io/udash/rest/openapi/Components$
     333: invokevirtual #275                // Method io/udash/rest/openapi/Components$.$lessinit$greater$default$8:()Lscala/collection/immutable/Map;
     336: astore        9
     338: dup
     339: ifnonnull     351
     342: pop
     343: aload         9
     345: ifnull        359
     348: goto          363
     351: aload         9
     353: invokevirtual #233                // Method java/lang/Object.equals:(Ljava/lang/Object;)Z
     356: ifeq          363
     359: iconst_1
     360: goto          364
     363: iconst_0
     364: iadd
     365: aload_1
     366: invokevirtual #278                // Method io/udash/rest/openapi/Components.callbacks:()Lscala/collection/immutable/Map;
     369: aload_0
     370: getfield      #218                // Field $outer:Lio/udash/rest/openapi/Components$$anon$27$$anon$28;
     373: getfield      #222                // Field io/udash/rest/openapi/Components$$anon$27$$anon$28.companion$macro$1$9:Ljava/lang/Object;
     376: checkcast     #224                // class io/udash/rest/openapi/Components$
     379: invokevirtual #281                // Method io/udash/rest/openapi/Components$.$lessinit$greater$default$9:()Lscala/collection/immutable/Map;
     382: astore        10
     384: dup
     385: ifnonnull     397
     388: pop
     389: aload         10
     391: ifnull        405
     394: goto          409
     397: aload         10
     399: invokevirtual #233                // Method java/lang/Object.equals:(Ljava/lang/Object;)Z
     402: ifeq          409
     405: iconst_1
     406: goto          410
     409: iconst_0
     410: iadd
     411: isub
     412: ireturn

  public void writeFields(com.avsystem.commons.serialization.ObjectOutput, io.udash.rest.openapi.Components);
    Code:
       0: aload_0
       1: aload_1
       2: iconst_0
       3: aload_2
       4: invokevirtual #216                // Method io/udash/rest/openapi/Components.schemas:()Lscala/collection/immutable/Map;
       7: aload_0
       8: getfield      #218                // Field $outer:Lio/udash/rest/openapi/Components$$anon$27$$anon$28;
      11: getfield      #222                // Field io/udash/rest/openapi/Components$$anon$27$$anon$28.companion$macro$1$9:Ljava/lang/Object;
      14: checkcast     #224                // class io/udash/rest/openapi/Components$
      17: invokevirtual #227                // Method io/udash/rest/openapi/Components$.$lessinit$greater$default$1:()Lscala/collection/immutable/Map;
      20: invokevirtual #289                // Method writeField:(Lcom/avsystem/commons/serialization/ObjectOutput;ILjava/lang/Object;Ljava/lang/Object;)V
      23: aload_0
      24: aload_1
      25: iconst_1
      26: aload_2
      27: invokevirtual #236                // Method io/udash/rest/openapi/Components.responses:()Lscala/collection/immutable/Map;
      30: aload_0
      31: getfield      #218                // Field $outer:Lio/udash/rest/openapi/Components$$anon$27$$anon$28;
      34: getfield      #222                // Field io/udash/rest/openapi/Components$$anon$27$$anon$28.companion$macro$1$9:Ljava/lang/Object;
      37: checkcast     #224                // class io/udash/rest/openapi/Components$
      40: invokevirtual #239                // Method io/udash/rest/openapi/Components$.$lessinit$greater$default$2:()Lscala/collection/immutable/Map;
      43: invokevirtual #289                // Method writeField:(Lcom/avsystem/commons/serialization/ObjectOutput;ILjava/lang/Object;Ljava/lang/Object;)V
      46: aload_0
      47: aload_1
      48: iconst_2
      49: aload_2
      50: invokevirtual #242                // Method io/udash/rest/openapi/Components.parameters:()Lscala/collection/immutable/Map;
      53: aload_0
      54: getfield      #218                // Field $outer:Lio/udash/rest/openapi/Components$$anon$27$$anon$28;
      57: getfield      #222                // Field io/udash/rest/openapi/Components$$anon$27$$anon$28.companion$macro$1$9:Ljava/lang/Object;
      60: checkcast     #224                // class io/udash/rest/openapi/Components$
      63: invokevirtual #245                // Method io/udash/rest/openapi/Components$.$lessinit$greater$default$3:()Lscala/collection/immutable/Map;
      66: invokevirtual #289                // Method writeField:(Lcom/avsystem/commons/serialization/ObjectOutput;ILjava/lang/Object;Ljava/lang/Object;)V
      69: aload_0
      70: aload_1
      71: iconst_3
      72: aload_2
      73: invokevirtual #248                // Method io/udash/rest/openapi/Components.examples:()Lscala/collection/immutable/Map;
      76: aload_0
      77: getfield      #218                // Field $outer:Lio/udash/rest/openapi/Components$$anon$27$$anon$28;
      80: getfield      #222                // Field io/udash/rest/openapi/Components$$anon$27$$anon$28.companion$macro$1$9:Ljava/lang/Object;
      83: checkcast     #224                // class io/udash/rest/openapi/Components$
      86: invokevirtual #251                // Method io/udash/rest/openapi/Components$.$lessinit$greater$default$4:()Lscala/collection/immutable/Map;
      89: invokevirtual #289                // Method writeField:(Lcom/avsystem/commons/serialization/ObjectOutput;ILjava/lang/Object;Ljava/lang/Object;)V
      92: aload_0
      93: aload_1
      94: iconst_4
      95: aload_2
      96: invokevirtual #254                // Method io/udash/rest/openapi/Components.requestBodies:()Lscala/collection/immutable/Map;
      99: aload_0
     100: getfield      #218                // Field $outer:Lio/udash/rest/openapi/Components$$anon$27$$anon$28;
     103: getfield      #222                // Field io/udash/rest/openapi/Components$$anon$27$$anon$28.companion$macro$1$9:Ljava/lang/Object;
     106: checkcast     #224                // class io/udash/rest/openapi/Components$
     109: invokevirtual #257                // Method io/udash/rest/openapi/Components$.$lessinit$greater$default$5:()Lscala/collection/immutable/Map;
     112: invokevirtual #289                // Method writeField:(Lcom/avsystem/commons/serialization/ObjectOutput;ILjava/lang/Object;Ljava/lang/Object;)V
     115: aload_0
     116: aload_1
     117: iconst_5
     118: aload_2
     119: invokevirtual #260                // Method io/udash/rest/openapi/Components.headers:()Lscala/collection/immutable/Map;
     122: aload_0
     123: getfield      #218                // Field $outer:Lio/udash/rest/openapi/Components$$anon$27$$anon$28;
     126: getfield      #222                // Field io/udash/rest/openapi/Components$$anon$27$$anon$28.companion$macro$1$9:Ljava/lang/Object;
     129: checkcast     #224                // class io/udash/rest/openapi/Components$
     132: invokevirtual #263                // Method io/udash/rest/openapi/Components$.$lessinit$greater$default$6:()Lscala/collection/immutable/Map;
     135: invokevirtual #289                // Method writeField:(Lcom/avsystem/commons/serialization/ObjectOutput;ILjava/lang/Object;Ljava/lang/Object;)V
     138: aload_0
     139: aload_1
     140: bipush        6
     142: aload_2
     143: invokevirtual #266                // Method io/udash/rest/openapi/Components.securitySchemes:()Lscala/collection/immutable/Map;
     146: aload_0
     147: getfield      #218                // Field $outer:Lio/udash/rest/openapi/Components$$anon$27$$anon$28;
     150: getfield      #222                // Field io/udash/rest/openapi/Components$$anon$27$$anon$28.companion$macro$1$9:Ljava/lang/Object;
     153: checkcast     #224                // class io/udash/rest/openapi/Components$
     156: invokevirtual #269                // Method io/udash/rest/openapi/Components$.$lessinit$greater$default$7:()Lscala/collection/immutable/Map;
     159: invokevirtual #289                // Method writeField:(Lcom/avsystem/commons/serialization/ObjectOutput;ILjava/lang/Object;Ljava/lang/Object;)V
     162: aload_0
     163: aload_1
     164: bipush        7
     166: aload_2
     167: invokevirtual #272                // Method io/udash/rest/openapi/Components.links:()Lscala/collection/immutable/Map;
     170: aload_0
     171: getfield      #218                // Field $outer:Lio/udash/rest/openapi/Components$$anon$27$$anon$28;
     174: getfield      #222                // Field io/udash/rest/openapi/Components$$anon$27$$anon$28.companion$macro$1$9:Ljava/lang/Object;
     177: checkcast     #224                // class io/udash/rest/openapi/Components$
     180: invokevirtual #275                // Method io/udash/rest/openapi/Components$.$lessinit$greater$default$8:()Lscala/collection/immutable/Map;
     183: invokevirtual #289                // Method writeField:(Lcom/avsystem/commons/serialization/ObjectOutput;ILjava/lang/Object;Ljava/lang/Object;)V
     186: aload_0
     187: aload_1
     188: bipush        8
     190: aload_2
     191: invokevirtual #278                // Method io/udash/rest/openapi/Components.callbacks:()Lscala/collection/immutable/Map;
     194: aload_0
     195: getfield      #218                // Field $outer:Lio/udash/rest/openapi/Components$$anon$27$$anon$28;
     198: getfield      #222                // Field io/udash/rest/openapi/Components$$anon$27$$anon$28.companion$macro$1$9:Ljava/lang/Object;
     201: checkcast     #224                // class io/udash/rest/openapi/Components$
     204: invokevirtual #281                // Method io/udash/rest/openapi/Components$.$lessinit$greater$default$9:()Lscala/collection/immutable/Map;
     207: invokevirtual #289                // Method writeField:(Lcom/avsystem/commons/serialization/ObjectOutput;ILjava/lang/Object;Ljava/lang/Object;)V
     210: return

  public void writeFields(com.avsystem.commons.serialization.ObjectOutput, java.lang.Object);
    Code:
       0: aload_0
       1: aload_1
       2: aload_2
       3: checkcast     #136                // class io/udash/rest/openapi/Components
       6: invokevirtual #293                // Method writeFields:(Lcom/avsystem/commons/serialization/ObjectOutput;Lio/udash/rest/openapi/Components;)V
       9: return

  public int size(java.lang.Object);
    Code:
       0: aload_0
       1: aload_1
       2: checkcast     #136                // class io/udash/rest/openapi/Components
       5: invokevirtual #296                // Method size:(Lio/udash/rest/openapi/Components;)I
       8: ireturn

  public java.lang.Object instantiate(com.avsystem.commons.serialization.FieldValues);
    Code:
       0: aload_0
       1: aload_1
       2: invokevirtual #299                // Method instantiate:(Lcom/avsystem/commons/serialization/FieldValues;)Lio/udash/rest/openapi/Components;
       5: areturn

  public static final scala.collection.immutable.Map $anonfun$instantiate$42(io.udash.rest.openapi.Components$$anon$27$$anon$28$$anon$29);
    Code:
       0: aload_0
       1: getfield      #218                // Field $outer:Lio/udash/rest/openapi/Components$$anon$27$$anon$28;
       4: getfield      #222                // Field io/udash/rest/openapi/Components$$anon$27$$anon$28.companion$macro$1$9:Ljava/lang/Object;
       7: checkcast     #224                // class io/udash/rest/openapi/Components$
      10: invokevirtual #227                // Method io/udash/rest/openapi/Components$.$lessinit$greater$default$1:()Lscala/collection/immutable/Map;
      13: areturn

  public static final scala.collection.immutable.Map $anonfun$instantiate$43(io.udash.rest.openapi.Components$$anon$27$$anon$28$$anon$29);
    Code:
       0: aload_0
       1: getfield      #218                // Field $outer:Lio/udash/rest/openapi/Components$$anon$27$$anon$28;
       4: getfield      #222                // Field io/udash/rest/openapi/Components$$anon$27$$anon$28.companion$macro$1$9:Ljava/lang/Object;
       7: checkcast     #224                // class io/udash/rest/openapi/Components$
      10: invokevirtual #239                // Method io/udash/rest/openapi/Components$.$lessinit$greater$default$2:()Lscala/collection/immutable/Map;
      13: areturn

  public static final scala.collection.immutable.Map $anonfun$instantiate$44(io.udash.rest.openapi.Components$$anon$27$$anon$28$$anon$29);
    Code:
       0: aload_0
       1: getfield      #218                // Field $outer:Lio/udash/rest/openapi/Components$$anon$27$$anon$28;
       4: getfield      #222                // Field io/udash/rest/openapi/Components$$anon$27$$anon$28.companion$macro$1$9:Ljava/lang/Object;
       7: checkcast     #224                // class io/udash/rest/openapi/Components$
      10: invokevirtual #245                // Method io/udash/rest/openapi/Components$.$lessinit$greater$default$3:()Lscala/collection/immutable/Map;
      13: areturn

  public static final scala.collection.immutable.Map $anonfun$instantiate$45(io.udash.rest.openapi.Components$$anon$27$$anon$28$$anon$29);
    Code:
       0: aload_0
       1: getfield      #218                // Field $outer:Lio/udash/rest/openapi/Components$$anon$27$$anon$28;
       4: getfield      #222                // Field io/udash/rest/openapi/Components$$anon$27$$anon$28.companion$macro$1$9:Ljava/lang/Object;
       7: checkcast     #224                // class io/udash/rest/openapi/Components$
      10: invokevirtual #251                // Method io/udash/rest/openapi/Components$.$lessinit$greater$default$4:()Lscala/collection/immutable/Map;
      13: areturn

  public static final scala.collection.immutable.Map $anonfun$instantiate$46(io.udash.rest.openapi.Components$$anon$27$$anon$28$$anon$29);
    Code:
       0: aload_0
       1: getfield      #218                // Field $outer:Lio/udash/rest/openapi/Components$$anon$27$$anon$28;
       4: getfield      #222                // Field io/udash/rest/openapi/Components$$anon$27$$anon$28.companion$macro$1$9:Ljava/lang/Object;
       7: checkcast     #224                // class io/udash/rest/openapi/Components$
      10: invokevirtual #257                // Method io/udash/rest/openapi/Components$.$lessinit$greater$default$5:()Lscala/collection/immutable/Map;
      13: areturn

  public static final scala.collection.immutable.Map $anonfun$instantiate$47(io.udash.rest.openapi.Components$$anon$27$$anon$28$$anon$29);
    Code:
       0: aload_0
       1: getfield      #218                // Field $outer:Lio/udash/rest/openapi/Components$$anon$27$$anon$28;
       4: getfield      #222                // Field io/udash/rest/openapi/Components$$anon$27$$anon$28.companion$macro$1$9:Ljava/lang/Object;
       7: checkcast     #224                // class io/udash/rest/openapi/Components$
      10: invokevirtual #263                // Method io/udash/rest/openapi/Components$.$lessinit$greater$default$6:()Lscala/collection/immutable/Map;
      13: areturn

  public static final scala.collection.immutable.Map $anonfun$instantiate$48(io.udash.rest.openapi.Components$$anon$27$$anon$28$$anon$29);
    Code:
       0: aload_0
       1: getfield      #218                // Field $outer:Lio/udash/rest/openapi/Components$$anon$27$$anon$28;
       4: getfield      #222                // Field io/udash/rest/openapi/Components$$anon$27$$anon$28.companion$macro$1$9:Ljava/lang/Object;
       7: checkcast     #224                // class io/udash/rest/openapi/Components$
      10: invokevirtual #269                // Method io/udash/rest/openapi/Components$.$lessinit$greater$default$7:()Lscala/collection/immutable/Map;
      13: areturn

  public static final scala.collection.immutable.Map $anonfun$instantiate$49(io.udash.rest.openapi.Components$$anon$27$$anon$28$$anon$29);
    Code:
       0: aload_0
       1: getfield      #218                // Field $outer:Lio/udash/rest/openapi/Components$$anon$27$$anon$28;
       4: getfield      #222                // Field io/udash/rest/openapi/Components$$anon$27$$anon$28.companion$macro$1$9:Ljava/lang/Object;
       7: checkcast     #224                // class io/udash/rest/openapi/Components$
      10: invokevirtual #275                // Method io/udash/rest/openapi/Components$.$lessinit$greater$default$8:()Lscala/collection/immutable/Map;
      13: areturn

  public static final scala.collection.immutable.Map $anonfun$instantiate$50(io.udash.rest.openapi.Components$$anon$27$$anon$28$$anon$29);
    Code:
       0: aload_0
       1: getfield      #218                // Field $outer:Lio/udash/rest/openapi/Components$$anon$27$$anon$28;
       4: getfield      #222                // Field io/udash/rest/openapi/Components$$anon$27$$anon$28.companion$macro$1$9:Ljava/lang/Object;
       7: checkcast     #224                // class io/udash/rest/openapi/Components$
      10: invokevirtual #281                // Method io/udash/rest/openapi/Components$.$lessinit$greater$default$9:()Lscala/collection/immutable/Map;
      13: areturn

  public io.udash.rest.openapi.Components$$anon$27$$anon$28$$anon$29(io.udash.rest.openapi.Components$$anon$27$$anon$28);
    Code:
       0: aload_1
       1: ifnonnull     6
       4: aconst_null
       5: athrow
       6: aload_0
       7: aload_1
       8: putfield      #218                // Field $outer:Lio/udash/rest/openapi/Components$$anon$27$$anon$28;
      11: aload_0
      12: ldc_w         #303                // String io.udash.rest.openapi.Components
      15: iconst_1
      16: bipush        9
      18: anewarray     #305                // class java/lang/String
      21: astore_2
      22: aload_2
      23: iconst_0
      24: ldc_w         #306                // String schemas
      27: aastore
      28: aload_2
      29: iconst_1
      30: ldc_w         #307                // String responses
      33: aastore
      34: aload_2
      35: iconst_2
      36: ldc_w         #308                // String parameters
      39: aastore
      40: aload_2
      41: iconst_3
      42: ldc_w         #309                // String examples
      45: aastore
      46: aload_2
      47: iconst_4
      48: ldc_w         #310                // String requestBodies
      51: aastore
      52: aload_2
      53: iconst_5
      54: ldc_w         #311                // String headers
      57: aastore
      58: aload_2
      59: bipush        6
      61: ldc_w         #312                // String securitySchemes
      64: aastore
      65: aload_2
      66: bipush        7
      68: ldc_w         #313                // String links
      71: aastore
      72: aload_2
      73: bipush        8
      75: ldc_w         #314                // String callbacks
      78: aastore
      79: aload_2
      80: invokespecial #317                // Method com/avsystem/commons/serialization/ApplyUnapplyCodec."<init>":(Ljava/lang/String;Z[Ljava/lang/String;)V
      83: return

  private static java.lang.Object $deserializeLambda$(java.lang.invoke.SerializedLambda);
    Code:
       0: aload_0
       1: invokedynamic #330,  0            // InvokeDynamic #9:lambdaDeserialize:(Ljava/lang/invoke/SerializedLambda;)Ljava/lang/Object;
       6: areturn
}
