Compiled from "PresignedCompleteMultipartUploadRequest.java"
final class software.amazon.awssdk.services.s3.presigner.model.PresignedCompleteMultipartUploadRequest$DefaultBuilder extends software.amazon.awssdk.awscore.presigner.PresignedRequest$DefaultBuilder<software.amazon.awssdk.services.s3.presigner.model.PresignedCompleteMultipartUploadRequest$DefaultBuilder> implements software.amazon.awssdk.services.s3.presigner.model.PresignedCompleteMultipartUploadRequest$Builder {
  private software.amazon.awssdk.services.s3.presigner.model.PresignedCompleteMultipartUploadRequest$DefaultBuilder();
    Code:
       0: aload_0
       1: invokespecial #3                  // Method software/amazon/awssdk/awscore/presigner/PresignedRequest$DefaultBuilder."<init>":()V
       4: return

  private software.amazon.awssdk.services.s3.presigner.model.PresignedCompleteMultipartUploadRequest$DefaultBuilder(software.amazon.awssdk.services.s3.presigner.model.PresignedCompleteMultipartUploadRequest);
    Code:
       0: aload_0
       1: aload_1
       2: invokespecial #4                  // Method software/amazon/awssdk/awscore/presigner/PresignedRequest$DefaultBuilder."<init>":(Lsoftware/amazon/awssdk/awscore/presigner/PresignedRequest;)V
       5: return

  public software.amazon.awssdk.services.s3.presigner.model.PresignedCompleteMultipartUploadRequest build();
    Code:
       0: new           #5                  // class software/amazon/awssdk/services/s3/presigner/model/PresignedCompleteMultipartUploadRequest
       3: dup
       4: aload_0
       5: aconst_null
       6: invokespecial #6                  // Method software/amazon/awssdk/services/s3/presigner/model/PresignedCompleteMultipartUploadRequest."<init>":(Lsoftware/amazon/awssdk/services/s3/presigner/model/PresignedCompleteMultipartUploadRequest$DefaultBuilder;Lsoftware/amazon/awssdk/services/s3/presigner/model/PresignedCompleteMultipartUploadRequest$1;)V
       9: areturn

  public software.amazon.awssdk.awscore.presigner.PresignedRequest build();
    Code:
       0: aload_0
       1: invokevirtual #7                  // Method build:()Lsoftware/amazon/awssdk/services/s3/presigner/model/PresignedCompleteMultipartUploadRequest;
       4: areturn

  public software.amazon.awssdk.services.s3.presigner.model.PresignedCompleteMultipartUploadRequest$Builder httpRequest(software.amazon.awssdk.http.SdkHttpRequest);
    Code:
       0: aload_0
       1: aload_1
       2: invokespecial #8                  // Method software/amazon/awssdk/awscore/presigner/PresignedRequest$DefaultBuilder.httpRequest:(Lsoftware/amazon/awssdk/http/SdkHttpRequest;)Lsoftware/amazon/awssdk/awscore/presigner/PresignedRequest$DefaultBuilder;
       5: checkcast     #9                  // class software/amazon/awssdk/services/s3/presigner/model/PresignedCompleteMultipartUploadRequest$Builder
       8: areturn

  public software.amazon.awssdk.services.s3.presigner.model.PresignedCompleteMultipartUploadRequest$Builder signedPayload(software.amazon.awssdk.core.SdkBytes);
    Code:
       0: aload_0
       1: aload_1
       2: invokespecial #10                 // Method software/amazon/awssdk/awscore/presigner/PresignedRequest$DefaultBuilder.signedPayload:(Lsoftware/amazon/awssdk/core/SdkBytes;)Lsoftware/amazon/awssdk/awscore/presigner/PresignedRequest$DefaultBuilder;
       5: checkcast     #9                  // class software/amazon/awssdk/services/s3/presigner/model/PresignedCompleteMultipartUploadRequest$Builder
       8: areturn

  public software.amazon.awssdk.services.s3.presigner.model.PresignedCompleteMultipartUploadRequest$Builder signedHeaders(java.util.Map);
    Code:
       0: aload_0
       1: aload_1
       2: invokespecial #11                 // Method software/amazon/awssdk/awscore/presigner/PresignedRequest$DefaultBuilder.signedHeaders:(Ljava/util/Map;)Lsoftware/amazon/awssdk/awscore/presigner/PresignedRequest$DefaultBuilder;
       5: checkcast     #9                  // class software/amazon/awssdk/services/s3/presigner/model/PresignedCompleteMultipartUploadRequest$Builder
       8: areturn

  public software.amazon.awssdk.services.s3.presigner.model.PresignedCompleteMultipartUploadRequest$Builder isBrowserExecutable(java.lang.Boolean);
    Code:
       0: aload_0
       1: aload_1
       2: invokespecial #12                 // Method software/amazon/awssdk/awscore/presigner/PresignedRequest$DefaultBuilder.isBrowserExecutable:(Ljava/lang/Boolean;)Lsoftware/amazon/awssdk/awscore/presigner/PresignedRequest$DefaultBuilder;
       5: checkcast     #9                  // class software/amazon/awssdk/services/s3/presigner/model/PresignedCompleteMultipartUploadRequest$Builder
       8: areturn

  public software.amazon.awssdk.services.s3.presigner.model.PresignedCompleteMultipartUploadRequest$Builder expiration(java.time.Instant);
    Code:
       0: aload_0
       1: aload_1
       2: invokespecial #13                 // Method software/amazon/awssdk/awscore/presigner/PresignedRequest$DefaultBuilder.expiration:(Ljava/time/Instant;)Lsoftware/amazon/awssdk/awscore/presigner/PresignedRequest$DefaultBuilder;
       5: checkcast     #9                  // class software/amazon/awssdk/services/s3/presigner/model/PresignedCompleteMultipartUploadRequest$Builder
       8: areturn

  public java.lang.Object build();
    Code:
       0: aload_0
       1: invokevirtual #7                  // Method build:()Lsoftware/amazon/awssdk/services/s3/presigner/model/PresignedCompleteMultipartUploadRequest;
       4: areturn

  software.amazon.awssdk.services.s3.presigner.model.PresignedCompleteMultipartUploadRequest$DefaultBuilder(software.amazon.awssdk.services.s3.presigner.model.PresignedCompleteMultipartUploadRequest$1);
    Code:
       0: aload_0
       1: invokespecial #2                  // Method "<init>":()V
       4: return

  software.amazon.awssdk.services.s3.presigner.model.PresignedCompleteMultipartUploadRequest$DefaultBuilder(software.amazon.awssdk.services.s3.presigner.model.PresignedCompleteMultipartUploadRequest, software.amazon.awssdk.services.s3.presigner.model.PresignedCompleteMultipartUploadRequest$1);
    Code:
       0: aload_0
       1: aload_1
       2: invokespecial #1                  // Method "<init>":(Lsoftware/amazon/awssdk/services/s3/presigner/model/PresignedCompleteMultipartUploadRequest;)V
       5: return
}
