Compiled from "BinaryOperation.java"
abstract class com.amazonaws.services.dynamodbv2.xspec.BinaryOperation extends com.amazonaws.services.dynamodbv2.xspec.UnitOfExpression {
  private final com.amazonaws.services.dynamodbv2.xspec.Operand leftOperand;

  private final java.lang.String operator;

  private final com.amazonaws.services.dynamodbv2.xspec.Operand rightOperand;

  com.amazonaws.services.dynamodbv2.xspec.BinaryOperation(com.amazonaws.services.dynamodbv2.xspec.Operand, java.lang.String, com.amazonaws.services.dynamodbv2.xspec.Operand);
    Code:
       0: aload_0
       1: invokespecial #1                  // Method com/amazonaws/services/dynamodbv2/xspec/UnitOfExpression."<init>":()V
       4: aload_0
       5: aload_1
       6: putfield      #2                  // Field leftOperand:Lcom/amazonaws/services/dynamodbv2/xspec/Operand;
       9: aload_0
      10: aload_2
      11: putfield      #3                  // Field operator:Ljava/lang/String;
      14: aload_0
      15: aload_3
      16: putfield      #4                  // Field rightOperand:Lcom/amazonaws/services/dynamodbv2/xspec/Operand;
      19: return

  final java.lang.String asSubstituted(com.amazonaws.services.dynamodbv2.xspec.SubstitutionContext);
    Code:
       0: new           #5                  // class java/lang/StringBuilder
       3: dup
       4: invokespecial #6                  // Method java/lang/StringBuilder."<init>":()V
       7: aload_0
       8: getfield      #2                  // Field leftOperand:Lcom/amazonaws/services/dynamodbv2/xspec/Operand;
      11: aload_1
      12: invokevirtual #7                  // Method com/amazonaws/services/dynamodbv2/xspec/Operand.asSubstituted:(Lcom/amazonaws/services/dynamodbv2/xspec/SubstitutionContext;)Ljava/lang/String;
      15: invokevirtual #8                  // Method java/lang/StringBuilder.append:(Ljava/lang/String;)Ljava/lang/StringBuilder;
      18: ldc           #9                  // String
      20: invokevirtual #8                  // Method java/lang/StringBuilder.append:(Ljava/lang/String;)Ljava/lang/StringBuilder;
      23: aload_0
      24: getfield      #3                  // Field operator:Ljava/lang/String;
      27: invokevirtual #8                  // Method java/lang/StringBuilder.append:(Ljava/lang/String;)Ljava/lang/StringBuilder;
      30: ldc           #9                  // String
      32: invokevirtual #8                  // Method java/lang/StringBuilder.append:(Ljava/lang/String;)Ljava/lang/StringBuilder;
      35: aload_0
      36: getfield      #4                  // Field rightOperand:Lcom/amazonaws/services/dynamodbv2/xspec/Operand;
      39: aload_1
      40: invokevirtual #7                  // Method com/amazonaws/services/dynamodbv2/xspec/Operand.asSubstituted:(Lcom/amazonaws/services/dynamodbv2/xspec/SubstitutionContext;)Ljava/lang/String;
      43: invokevirtual #8                  // Method java/lang/StringBuilder.append:(Ljava/lang/String;)Ljava/lang/StringBuilder;
      46: invokevirtual #10                 // Method java/lang/StringBuilder.toString:()Ljava/lang/String;
      49: areturn

  com.amazonaws.services.dynamodbv2.xspec.Operand getLhs();
    Code:
       0: aload_0
       1: getfield      #2                  // Field leftOperand:Lcom/amazonaws/services/dynamodbv2/xspec/Operand;
       4: areturn

  java.lang.String getOperator();
    Code:
       0: aload_0
       1: getfield      #3                  // Field operator:Ljava/lang/String;
       4: areturn

  com.amazonaws.services.dynamodbv2.xspec.Operand getRhs();
    Code:
       0: aload_0
       1: getfield      #4                  // Field rightOperand:Lcom/amazonaws/services/dynamodbv2/xspec/Operand;
       4: areturn
}
