Compiled from "ComparatorCondition.java"
public final class com.amazonaws.services.dynamodbv2.xspec.ComparatorCondition extends com.amazonaws.services.dynamodbv2.xspec.Condition {
  private final java.lang.String comparator;

  private final com.amazonaws.services.dynamodbv2.xspec.Operand lhs;

  private final com.amazonaws.services.dynamodbv2.xspec.Operand rhs;

  com.amazonaws.services.dynamodbv2.xspec.ComparatorCondition(java.lang.String, com.amazonaws.services.dynamodbv2.xspec.Operand, com.amazonaws.services.dynamodbv2.xspec.Operand);
    Code:
       0: aload_0
       1: invokespecial #1                  // Method com/amazonaws/services/dynamodbv2/xspec/Condition."<init>":()V
       4: aload_0
       5: aload_1
       6: putfield      #2                  // Field comparator:Ljava/lang/String;
       9: aload_0
      10: aload_2
      11: putfield      #3                  // Field lhs:Lcom/amazonaws/services/dynamodbv2/xspec/Operand;
      14: aload_0
      15: aload_3
      16: putfield      #4                  // Field rhs:Lcom/amazonaws/services/dynamodbv2/xspec/Operand;
      19: return

  java.lang.String asSubstituted(com.amazonaws.services.dynamodbv2.xspec.SubstitutionContext);
    Code:
       0: new           #5                  // class java/lang/StringBuilder
       3: dup
       4: invokespecial #6                  // Method java/lang/StringBuilder."<init>":()V
       7: aload_0
       8: getfield      #3                  // Field lhs:Lcom/amazonaws/services/dynamodbv2/xspec/Operand;
      11: aload_1
      12: invokevirtual #7                  // Method com/amazonaws/services/dynamodbv2/xspec/Operand.asSubstituted:(Lcom/amazonaws/services/dynamodbv2/xspec/SubstitutionContext;)Ljava/lang/String;
      15: invokevirtual #8                  // Method java/lang/StringBuilder.append:(Ljava/lang/String;)Ljava/lang/StringBuilder;
      18: ldc           #9                  // String
      20: invokevirtual #8                  // Method java/lang/StringBuilder.append:(Ljava/lang/String;)Ljava/lang/StringBuilder;
      23: aload_0
      24: getfield      #2                  // Field comparator:Ljava/lang/String;
      27: invokevirtual #8                  // Method java/lang/StringBuilder.append:(Ljava/lang/String;)Ljava/lang/StringBuilder;
      30: ldc           #9                  // String
      32: invokevirtual #8                  // Method java/lang/StringBuilder.append:(Ljava/lang/String;)Ljava/lang/StringBuilder;
      35: aload_0
      36: getfield      #4                  // Field rhs:Lcom/amazonaws/services/dynamodbv2/xspec/Operand;
      39: aload_1
      40: invokevirtual #7                  // Method com/amazonaws/services/dynamodbv2/xspec/Operand.asSubstituted:(Lcom/amazonaws/services/dynamodbv2/xspec/SubstitutionContext;)Ljava/lang/String;
      43: invokevirtual #8                  // Method java/lang/StringBuilder.append:(Ljava/lang/String;)Ljava/lang/StringBuilder;
      46: invokevirtual #10                 // Method java/lang/StringBuilder.toString:()Ljava/lang/String;
      49: areturn

  boolean atomic();
    Code:
       0: iconst_1
       1: ireturn

  int precedence();
    Code:
       0: getstatic     #11                 // Field com/amazonaws/services/dynamodbv2/xspec/Precedence.Comparator:Lcom/amazonaws/services/dynamodbv2/xspec/Precedence;
       3: invokevirtual #12                 // Method com/amazonaws/services/dynamodbv2/xspec/Precedence.value:()I
       6: ireturn
}
