Compiled from "SimpleServerAuthenticationProvider.java"
public final class org.jboss.remoting3.security.SimpleServerAuthenticationProvider implements org.jboss.remoting3.security.ServerAuthenticationProvider {
  private static final org.jboss.remoting3.security.RemotingPermission ADD_USER_PERM;

  private final java.util.Map<java.lang.String, java.util.Map<java.lang.String, org.jboss.remoting3.security.SimpleServerAuthenticationProvider$Entry>> map;

  public org.jboss.remoting3.security.SimpleServerAuthenticationProvider();
    Code:
       0: aload_0
       1: invokespecial #2                  // Method java/lang/Object."<init>":()V
       4: aload_0
       5: new           #3                  // class java/util/HashMap
       8: dup
       9: invokespecial #4                  // Method java/util/HashMap."<init>":()V
      12: putfield      #1                  // Field map:Ljava/util/Map;
      15: return

  public org.jboss.remoting3.security.AuthorizingCallbackHandler getCallbackHandler(java.lang.String);
    Code:
       0: new           #5                  // class org/jboss/remoting3/security/SimpleServerAuthenticationProvider$1
       3: dup
       4: aload_0
       5: invokespecial #6                  // Method org/jboss/remoting3/security/SimpleServerAuthenticationProvider$1."<init>":(Lorg/jboss/remoting3/security/SimpleServerAuthenticationProvider;)V
       8: areturn

  public void addUser(java.lang.String, java.lang.String, char[], java.security.KeyPair...);
    Code:
       0: aload_1
       1: ifnonnull     14
       4: new           #7                  // class java/lang/IllegalArgumentException
       7: dup
       8: ldc           #8                  // String userName is null
      10: invokespecial #9                  // Method java/lang/IllegalArgumentException."<init>":(Ljava/lang/String;)V
      13: athrow
      14: aload_2
      15: ifnonnull     28
      18: new           #7                  // class java/lang/IllegalArgumentException
      21: dup
      22: ldc           #10                 // String userRealm is null
      24: invokespecial #9                  // Method java/lang/IllegalArgumentException."<init>":(Ljava/lang/String;)V
      27: athrow
      28: aload_3
      29: ifnonnull     42
      32: new           #7                  // class java/lang/IllegalArgumentException
      35: dup
      36: ldc           #11                 // String password is null
      38: invokespecial #9                  // Method java/lang/IllegalArgumentException."<init>":(Ljava/lang/String;)V
      41: athrow
      42: aload         4
      44: ifnonnull     57
      47: new           #7                  // class java/lang/IllegalArgumentException
      50: dup
      51: ldc           #12                 // String keyPairs is null
      53: invokespecial #9                  // Method java/lang/IllegalArgumentException."<init>":(Ljava/lang/String;)V
      56: athrow
      57: invokestatic  #13                 // Method java/lang/System.getSecurityManager:()Ljava/lang/SecurityManager;
      60: astore        5
      62: aload         5
      64: ifnull        75
      67: aload         5
      69: getstatic     #14                 // Field ADD_USER_PERM:Lorg/jboss/remoting3/security/RemotingPermission;
      72: invokevirtual #15                 // Method java/lang/SecurityManager.checkPermission:(Ljava/security/Permission;)V
      75: aload_2
      76: invokevirtual #16                 // Method java/lang/String.toLowerCase:()Ljava/lang/String;
      79: invokevirtual #17                 // Method java/lang/String.trim:()Ljava/lang/String;
      82: astore        6
      84: aload_1
      85: invokevirtual #16                 // Method java/lang/String.toLowerCase:()Ljava/lang/String;
      88: invokevirtual #17                 // Method java/lang/String.trim:()Ljava/lang/String;
      91: astore        7
      93: aload_0
      94: getfield      #1                  // Field map:Ljava/util/Map;
      97: dup
      98: astore        8
     100: monitorenter
     101: aload_0
     102: getfield      #1                  // Field map:Ljava/util/Map;
     105: aload         6
     107: invokeinterface #18,  2           // InterfaceMethod java/util/Map.get:(Ljava/lang/Object;)Ljava/lang/Object;
     112: checkcast     #19                 // class java/util/Map
     115: astore        9
     117: aload         9
     119: ifnonnull     145
     122: new           #3                  // class java/util/HashMap
     125: dup
     126: invokespecial #4                  // Method java/util/HashMap."<init>":()V
     129: astore        9
     131: aload_0
     132: getfield      #1                  // Field map:Ljava/util/Map;
     135: aload         6
     137: aload         9
     139: invokeinterface #20,  3           // InterfaceMethod java/util/Map.put:(Ljava/lang/Object;Ljava/lang/Object;)Ljava/lang/Object;
     144: pop
     145: aload         9
     147: aload         7
     149: new           #21                 // class org/jboss/remoting3/security/SimpleServerAuthenticationProvider$Entry
     152: dup
     153: aload         7
     155: aload         6
     157: aload_3
     158: aload         4
     160: aconst_null
     161: invokespecial #22                 // Method org/jboss/remoting3/security/SimpleServerAuthenticationProvider$Entry."<init>":(Ljava/lang/String;Ljava/lang/String;[C[Ljava/security/KeyPair;Lorg/jboss/remoting3/security/SimpleServerAuthenticationProvider$1;)V
     164: invokeinterface #20,  3           // InterfaceMethod java/util/Map.put:(Ljava/lang/Object;Ljava/lang/Object;)Ljava/lang/Object;
     169: pop
     170: aload         8
     172: monitorexit
     173: goto          184
     176: astore        10
     178: aload         8
     180: monitorexit
     181: aload         10
     183: athrow
     184: return
    Exception table:
       from    to  target type
         101   173   176   any
         176   181   176   any

  static java.util.Map access$000(org.jboss.remoting3.security.SimpleServerAuthenticationProvider);
    Code:
       0: aload_0
       1: getfield      #1                  // Field map:Ljava/util/Map;
       4: areturn

  static {};
    Code:
       0: new           #23                 // class org/jboss/remoting3/security/RemotingPermission
       3: dup
       4: ldc           #24                 // String addServerUser
       6: invokespecial #25                 // Method org/jboss/remoting3/security/RemotingPermission."<init>":(Ljava/lang/String;)V
       9: putstatic     #14                 // Field ADD_USER_PERM:Lorg/jboss/remoting3/security/RemotingPermission;
      12: return
}
