Compiled from "UserPrincipal.java"
public final class org.jboss.remoting3.security.UserPrincipal implements java.security.Principal {
  private final java.lang.String name;

  public org.jboss.remoting3.security.UserPrincipal(java.lang.String);
    Code:
       0: aload_0
       1: invokespecial #1                  // Method java/lang/Object."<init>":()V
       4: aload_1
       5: ifnonnull     18
       8: new           #2                  // class java/lang/IllegalArgumentException
      11: dup
      12: ldc           #3                  // String name is null
      14: invokespecial #4                  // Method java/lang/IllegalArgumentException."<init>":(Ljava/lang/String;)V
      17: athrow
      18: aload_0
      19: aload_1
      20: putfield      #5                  // Field name:Ljava/lang/String;
      23: return

  public java.lang.String getName();
    Code:
       0: aload_0
       1: getfield      #5                  // Field name:Ljava/lang/String;
       4: areturn

  public int hashCode();
    Code:
       0: aload_0
       1: getfield      #5                  // Field name:Ljava/lang/String;
       4: invokevirtual #6                  // Method java/lang/String.hashCode:()I
       7: ireturn

  public boolean equals(java.lang.Object);
    Code:
       0: aload_1
       1: instanceof    #7                  // class org/jboss/remoting3/security/UserPrincipal
       4: ifeq          22
       7: aload_0
       8: aload_1
       9: checkcast     #7                  // class org/jboss/remoting3/security/UserPrincipal
      12: invokevirtual #8                  // Method equals:(Lorg/jboss/remoting3/security/UserPrincipal;)Z
      15: ifeq          22
      18: iconst_1
      19: goto          23
      22: iconst_0
      23: ireturn

  public boolean equals(org.jboss.remoting3.security.UserPrincipal);
    Code:
       0: aload_0
       1: aload_1
       2: if_acmpeq     23
       5: aload_1
       6: ifnull        27
       9: aload_0
      10: getfield      #5                  // Field name:Ljava/lang/String;
      13: aload_1
      14: getfield      #5                  // Field name:Ljava/lang/String;
      17: invokevirtual #9                  // Method java/lang/String.equals:(Ljava/lang/Object;)Z
      20: ifeq          27
      23: iconst_1
      24: goto          28
      27: iconst_0
      28: ireturn
}
