Compiled from "LabelDetection.java"
final class software.amazon.awssdk.services.rekognition.model.LabelDetection$BuilderImpl implements software.amazon.awssdk.services.rekognition.model.LabelDetection$Builder {
  private java.lang.Long timestamp;

  private software.amazon.awssdk.services.rekognition.model.Label label;

  private software.amazon.awssdk.services.rekognition.model.LabelDetection$BuilderImpl();
    Code:
       0: aload_0
       1: invokespecial #5                  // Method java/lang/Object."<init>":()V
       4: return

  private software.amazon.awssdk.services.rekognition.model.LabelDetection$BuilderImpl(software.amazon.awssdk.services.rekognition.model.LabelDetection);
    Code:
       0: aload_0
       1: invokespecial #5                  // Method java/lang/Object."<init>":()V
       4: aload_0
       5: aload_1
       6: invokestatic  #6                  // Method software/amazon/awssdk/services/rekognition/model/LabelDetection.access$400:(Lsoftware/amazon/awssdk/services/rekognition/model/LabelDetection;)Ljava/lang/Long;
       9: invokevirtual #7                  // Method timestamp:(Ljava/lang/Long;)Lsoftware/amazon/awssdk/services/rekognition/model/LabelDetection$Builder;
      12: pop
      13: aload_0
      14: aload_1
      15: invokestatic  #8                  // Method software/amazon/awssdk/services/rekognition/model/LabelDetection.access$500:(Lsoftware/amazon/awssdk/services/rekognition/model/LabelDetection;)Lsoftware/amazon/awssdk/services/rekognition/model/Label;
      18: invokevirtual #9                  // Method label:(Lsoftware/amazon/awssdk/services/rekognition/model/Label;)Lsoftware/amazon/awssdk/services/rekognition/model/LabelDetection$Builder;
      21: pop
      22: return

  public final java.lang.Long getTimestamp();
    Code:
       0: aload_0
       1: getfield      #4                  // Field timestamp:Ljava/lang/Long;
       4: areturn

  public final void setTimestamp(java.lang.Long);
    Code:
       0: aload_0
       1: aload_1
       2: putfield      #4                  // Field timestamp:Ljava/lang/Long;
       5: return

  public final software.amazon.awssdk.services.rekognition.model.LabelDetection$Builder timestamp(java.lang.Long);
    Code:
       0: aload_0
       1: aload_1
       2: putfield      #4                  // Field timestamp:Ljava/lang/Long;
       5: aload_0
       6: areturn

  public final software.amazon.awssdk.services.rekognition.model.Label$Builder getLabel();
    Code:
       0: aload_0
       1: getfield      #3                  // Field label:Lsoftware/amazon/awssdk/services/rekognition/model/Label;
       4: ifnull        17
       7: aload_0
       8: getfield      #3                  // Field label:Lsoftware/amazon/awssdk/services/rekognition/model/Label;
      11: invokevirtual #10                 // Method software/amazon/awssdk/services/rekognition/model/Label.toBuilder:()Lsoftware/amazon/awssdk/services/rekognition/model/Label$Builder;
      14: goto          18
      17: aconst_null
      18: areturn

  public final void setLabel(software.amazon.awssdk.services.rekognition.model.Label$BuilderImpl);
    Code:
       0: aload_0
       1: aload_1
       2: ifnull        12
       5: aload_1
       6: invokevirtual #11                 // Method software/amazon/awssdk/services/rekognition/model/Label$BuilderImpl.build:()Lsoftware/amazon/awssdk/services/rekognition/model/Label;
       9: goto          13
      12: aconst_null
      13: putfield      #3                  // Field label:Lsoftware/amazon/awssdk/services/rekognition/model/Label;
      16: return

  public final software.amazon.awssdk.services.rekognition.model.LabelDetection$Builder label(software.amazon.awssdk.services.rekognition.model.Label);
    Code:
       0: aload_0
       1: aload_1
       2: putfield      #3                  // Field label:Lsoftware/amazon/awssdk/services/rekognition/model/Label;
       5: aload_0
       6: areturn

  public software.amazon.awssdk.services.rekognition.model.LabelDetection build();
    Code:
       0: new           #12                 // class software/amazon/awssdk/services/rekognition/model/LabelDetection
       3: dup
       4: aload_0
       5: aconst_null
       6: invokespecial #13                 // Method software/amazon/awssdk/services/rekognition/model/LabelDetection."<init>":(Lsoftware/amazon/awssdk/services/rekognition/model/LabelDetection$BuilderImpl;Lsoftware/amazon/awssdk/services/rekognition/model/LabelDetection$1;)V
       9: areturn

  public java.util.List<software.amazon.awssdk.core.SdkField<?>> sdkFields();
    Code:
       0: invokestatic  #14                 // Method software/amazon/awssdk/services/rekognition/model/LabelDetection.access$700:()Ljava/util/List;
       3: areturn

  public java.lang.Object build();
    Code:
       0: aload_0
       1: invokevirtual #15                 // Method build:()Lsoftware/amazon/awssdk/services/rekognition/model/LabelDetection;
       4: areturn

  static java.lang.Long access$000(software.amazon.awssdk.services.rekognition.model.LabelDetection$BuilderImpl);
    Code:
       0: aload_0
       1: getfield      #4                  // Field timestamp:Ljava/lang/Long;
       4: areturn

  static software.amazon.awssdk.services.rekognition.model.Label access$100(software.amazon.awssdk.services.rekognition.model.LabelDetection$BuilderImpl);
    Code:
       0: aload_0
       1: getfield      #3                  // Field label:Lsoftware/amazon/awssdk/services/rekognition/model/Label;
       4: areturn

  software.amazon.awssdk.services.rekognition.model.LabelDetection$BuilderImpl(software.amazon.awssdk.services.rekognition.model.LabelDetection, software.amazon.awssdk.services.rekognition.model.LabelDetection$1);
    Code:
       0: aload_0
       1: aload_1
       2: invokespecial #2                  // Method "<init>":(Lsoftware/amazon/awssdk/services/rekognition/model/LabelDetection;)V
       5: return

  software.amazon.awssdk.services.rekognition.model.LabelDetection$BuilderImpl(software.amazon.awssdk.services.rekognition.model.LabelDetection$1);
    Code:
       0: aload_0
       1: invokespecial #1                  // Method "<init>":()V
       4: return
}
