Compiled from "StreamProcessorOutput.java"
public interface software.amazon.awssdk.services.rekognition.model.StreamProcessorOutput$Builder extends software.amazon.awssdk.core.SdkPojo, software.amazon.awssdk.utils.builder.CopyableBuilder<software.amazon.awssdk.services.rekognition.model.StreamProcessorOutput$Builder, software.amazon.awssdk.services.rekognition.model.StreamProcessorOutput> {
  public abstract software.amazon.awssdk.services.rekognition.model.StreamProcessorOutput$Builder kinesisDataStream(software.amazon.awssdk.services.rekognition.model.KinesisDataStream);

  public default software.amazon.awssdk.services.rekognition.model.StreamProcessorOutput$Builder kinesisDataStream(java.util.function.Consumer<software.amazon.awssdk.services.rekognition.model.KinesisDataStream$Builder>);
    Code:
       0: aload_0
       1: invokestatic  #1                  // Method software/amazon/awssdk/services/rekognition/model/KinesisDataStream.builder:()Lsoftware/amazon/awssdk/services/rekognition/model/KinesisDataStream$Builder;
       4: aload_1
       5: invokeinterface #2,  2            // InterfaceMethod software/amazon/awssdk/services/rekognition/model/KinesisDataStream$Builder.applyMutation:(Ljava/util/function/Consumer;)Lsoftware/amazon/awssdk/utils/builder/SdkBuilder;
      10: checkcast     #3                  // class software/amazon/awssdk/services/rekognition/model/KinesisDataStream$Builder
      13: invokeinterface #4,  1            // InterfaceMethod software/amazon/awssdk/services/rekognition/model/KinesisDataStream$Builder.build:()Ljava/lang/Object;
      18: checkcast     #5                  // class software/amazon/awssdk/services/rekognition/model/KinesisDataStream
      21: invokeinterface #6,  2            // InterfaceMethod kinesisDataStream:(Lsoftware/amazon/awssdk/services/rekognition/model/KinesisDataStream;)Lsoftware/amazon/awssdk/services/rekognition/model/StreamProcessorOutput$Builder;
      26: areturn

  public abstract software.amazon.awssdk.services.rekognition.model.StreamProcessorOutput$Builder s3Destination(software.amazon.awssdk.services.rekognition.model.S3Destination);

  public default software.amazon.awssdk.services.rekognition.model.StreamProcessorOutput$Builder s3Destination(java.util.function.Consumer<software.amazon.awssdk.services.rekognition.model.S3Destination$Builder>);
    Code:
       0: aload_0
       1: invokestatic  #7                  // Method software/amazon/awssdk/services/rekognition/model/S3Destination.builder:()Lsoftware/amazon/awssdk/services/rekognition/model/S3Destination$Builder;
       4: aload_1
       5: invokeinterface #8,  2            // InterfaceMethod software/amazon/awssdk/services/rekognition/model/S3Destination$Builder.applyMutation:(Ljava/util/function/Consumer;)Lsoftware/amazon/awssdk/utils/builder/SdkBuilder;
      10: checkcast     #9                  // class software/amazon/awssdk/services/rekognition/model/S3Destination$Builder
      13: invokeinterface #10,  1           // InterfaceMethod software/amazon/awssdk/services/rekognition/model/S3Destination$Builder.build:()Ljava/lang/Object;
      18: checkcast     #11                 // class software/amazon/awssdk/services/rekognition/model/S3Destination
      21: invokeinterface #12,  2           // InterfaceMethod s3Destination:(Lsoftware/amazon/awssdk/services/rekognition/model/S3Destination;)Lsoftware/amazon/awssdk/services/rekognition/model/StreamProcessorOutput$Builder;
      26: areturn
}
