Compiled from "QuerySpacesHelper.java"
public class org.hibernate.cache.spi.QuerySpacesHelper {
  public static final org.hibernate.cache.spi.QuerySpacesHelper INSTANCE;

  private org.hibernate.cache.spi.QuerySpacesHelper();
    Code:
       0: aload_0
       1: invokespecial #1                  // Method java/lang/Object."<init>":()V
       4: return

  public java.lang.String[] toStringArray(java.util.Set);
    Code:
       0: aload_1
       1: iconst_0
       2: anewarray     #2                  // class java/lang/String
       5: invokeinterface #3,  2            // InterfaceMethod java/util/Set.toArray:([Ljava/lang/Object;)[Ljava/lang/Object;
      10: checkcast     #4                  // class "[Ljava/lang/String;"
      13: checkcast     #4                  // class "[Ljava/lang/String;"
      16: areturn

  public java.util.Set<java.lang.String> toStringSet(java.lang.String[]);
    Code:
       0: new           #5                  // class java/util/HashSet
       3: dup
       4: invokespecial #6                  // Method java/util/HashSet."<init>":()V
       7: astore_2
       8: aload_2
       9: aload_1
      10: invokestatic  #7                  // Method java/util/Collections.addAll:(Ljava/util/Collection;[Ljava/lang/Object;)Z
      13: pop
      14: aload_2
      15: areturn

  public java.util.Set<java.io.Serializable> toSerializableSet(java.lang.String[]);
    Code:
       0: new           #5                  // class java/util/HashSet
       3: dup
       4: invokespecial #6                  // Method java/util/HashSet."<init>":()V
       7: astore_2
       8: aload_2
       9: aload_1
      10: invokestatic  #7                  // Method java/util/Collections.addAll:(Ljava/util/Collection;[Ljava/lang/Object;)Z
      13: pop
      14: aload_2
      15: areturn

  static {};
    Code:
       0: new           #8                  // class org/hibernate/cache/spi/QuerySpacesHelper
       3: dup
       4: invokespecial #9                  // Method "<init>":()V
       7: putstatic     #10                 // Field INSTANCE:Lorg/hibernate/cache/spi/QuerySpacesHelper;
      10: return
}
