Compiled from "AesGcmContentEncryptionAlgorithm.java"
public class org.jose4j.jwe.AesGcmContentEncryptionAlgorithm extends org.jose4j.jwa.AlgorithmInfo implements org.jose4j.jwe.ContentEncryptionAlgorithm {
  private static final int IV_BYTE_LENGTH;

  private static final int TAG_BYTE_LENGTH;

  private org.jose4j.jwe.ContentEncryptionKeyDescriptor contentEncryptionKeyDescriptor;

  private org.jose4j.jwe.SimpleAeadCipher simpleAeadCipher;

  public org.jose4j.jwe.AesGcmContentEncryptionAlgorithm(java.lang.String, int);
    Code:
       0: aload_0
       1: invokespecial #1                  // Method org/jose4j/jwa/AlgorithmInfo."<init>":()V
       4: aload_0
       5: aload_1
       6: invokevirtual #2                  // Method setAlgorithmIdentifier:(Ljava/lang/String;)V
       9: aload_0
      10: ldc           #3                  // String AES/GCM/NoPadding
      12: invokevirtual #4                  // Method setJavaAlgorithm:(Ljava/lang/String;)V
      15: aload_0
      16: getstatic     #5                  // Field org/jose4j/keys/KeyPersuasion.SYMMETRIC:Lorg/jose4j/keys/KeyPersuasion;
      19: invokevirtual #6                  // Method setKeyPersuasion:(Lorg/jose4j/keys/KeyPersuasion;)V
      22: aload_0
      23: ldc           #7                  // String AES
      25: invokevirtual #8                  // Method setKeyType:(Ljava/lang/String;)V
      28: aload_0
      29: new           #9                  // class org/jose4j/jwe/ContentEncryptionKeyDescriptor
      32: dup
      33: iload_2
      34: invokestatic  #10                 // Method org/jose4j/lang/ByteUtil.byteLength:(I)I
      37: ldc           #7                  // String AES
      39: invokespecial #11                 // Method org/jose4j/jwe/ContentEncryptionKeyDescriptor."<init>":(ILjava/lang/String;)V
      42: putfield      #12                 // Field contentEncryptionKeyDescriptor:Lorg/jose4j/jwe/ContentEncryptionKeyDescriptor;
      45: aload_0
      46: new           #13                 // class org/jose4j/jwe/SimpleAeadCipher
      49: dup
      50: aload_0
      51: invokevirtual #14                 // Method getJavaAlgorithm:()Ljava/lang/String;
      54: bipush        16
      56: invokespecial #15                 // Method org/jose4j/jwe/SimpleAeadCipher."<init>":(Ljava/lang/String;I)V
      59: putfield      #16                 // Field simpleAeadCipher:Lorg/jose4j/jwe/SimpleAeadCipher;
      62: return

  public org.jose4j.jwe.ContentEncryptionKeyDescriptor getContentEncryptionKeyDescriptor();
    Code:
       0: aload_0
       1: getfield      #12                 // Field contentEncryptionKeyDescriptor:Lorg/jose4j/jwe/ContentEncryptionKeyDescriptor;
       4: areturn

  public org.jose4j.jwe.ContentEncryptionParts encrypt(byte[], byte[], byte[], org.jose4j.jwx.Headers, byte[], org.jose4j.jca.ProviderContext) throws org.jose4j.lang.JoseException;
    Code:
       0: bipush        12
       2: aload         5
       4: aload         6
       6: invokevirtual #17                 // Method org/jose4j/jca/ProviderContext.getSecureRandom:()Ljava/security/SecureRandom;
       9: invokestatic  #18                 // Method org/jose4j/jwe/InitializationVectorHelp.iv:(I[BLjava/security/SecureRandom;)[B
      12: astore        7
      14: aload         4
      16: aload         6
      18: invokestatic  #19                 // Method org/jose4j/jwe/ContentEncryptionHelp.getCipherProvider:(Lorg/jose4j/jwx/Headers;Lorg/jose4j/jca/ProviderContext;)Ljava/lang/String;
      21: astore        8
      23: aload_0
      24: aload_1
      25: aload_2
      26: aload_3
      27: aload         7
      29: aload         8
      31: invokevirtual #20                 // Method encrypt:([B[B[B[BLjava/lang/String;)Lorg/jose4j/jwe/ContentEncryptionParts;
      34: areturn

  public org.jose4j.jwe.ContentEncryptionParts encrypt(byte[], byte[], byte[], byte[], java.lang.String) throws org.jose4j.lang.JoseException;
    Code:
       0: new           #21                 // class org/jose4j/keys/AesKey
       3: dup
       4: aload_3
       5: invokespecial #22                 // Method org/jose4j/keys/AesKey."<init>":([B)V
       8: astore        6
      10: aload_0
      11: getfield      #16                 // Field simpleAeadCipher:Lorg/jose4j/jwe/SimpleAeadCipher;
      14: aload         6
      16: aload         4
      18: aload_1
      19: aload_2
      20: aload         5
      22: invokevirtual #23                 // Method org/jose4j/jwe/SimpleAeadCipher.encrypt:(Ljava/security/Key;[B[B[BLjava/lang/String;)Lorg/jose4j/jwe/SimpleAeadCipher$CipherOutput;
      25: astore        7
      27: new           #24                 // class org/jose4j/jwe/ContentEncryptionParts
      30: dup
      31: aload         4
      33: aload         7
      35: invokevirtual #25                 // Method org/jose4j/jwe/SimpleAeadCipher$CipherOutput.getCiphertext:()[B
      38: aload         7
      40: invokevirtual #26                 // Method org/jose4j/jwe/SimpleAeadCipher$CipherOutput.getTag:()[B
      43: invokespecial #27                 // Method org/jose4j/jwe/ContentEncryptionParts."<init>":([B[B[B)V
      46: areturn

  public byte[] decrypt(org.jose4j.jwe.ContentEncryptionParts, byte[], byte[], org.jose4j.jwx.Headers, org.jose4j.jca.ProviderContext) throws org.jose4j.lang.JoseException;
    Code:
       0: aload_1
       1: invokevirtual #28                 // Method org/jose4j/jwe/ContentEncryptionParts.getIv:()[B
       4: astore        6
       6: new           #21                 // class org/jose4j/keys/AesKey
       9: dup
      10: aload_3
      11: invokespecial #22                 // Method org/jose4j/keys/AesKey."<init>":([B)V
      14: astore        7
      16: aload_1
      17: invokevirtual #29                 // Method org/jose4j/jwe/ContentEncryptionParts.getCiphertext:()[B
      20: astore        8
      22: aload_1
      23: invokevirtual #30                 // Method org/jose4j/jwe/ContentEncryptionParts.getAuthenticationTag:()[B
      26: astore        9
      28: aload         4
      30: aload         5
      32: invokestatic  #19                 // Method org/jose4j/jwe/ContentEncryptionHelp.getCipherProvider:(Lorg/jose4j/jwx/Headers;Lorg/jose4j/jca/ProviderContext;)Ljava/lang/String;
      35: astore        10
      37: aload_0
      38: getfield      #16                 // Field simpleAeadCipher:Lorg/jose4j/jwe/SimpleAeadCipher;
      41: aload         7
      43: aload         6
      45: aload         8
      47: aload         9
      49: aload_2
      50: aload         10
      52: invokevirtual #31                 // Method org/jose4j/jwe/SimpleAeadCipher.decrypt:(Ljava/security/Key;[B[B[B[BLjava/lang/String;)[B
      55: areturn

  public boolean isAvailable();
    Code:
       0: aload_0
       1: invokevirtual #32                 // Method getContentEncryptionKeyDescriptor:()Lorg/jose4j/jwe/ContentEncryptionKeyDescriptor;
       4: invokevirtual #33                 // Method org/jose4j/jwe/ContentEncryptionKeyDescriptor.getContentEncryptionKeyByteLength:()I
       7: istore_1
       8: aload_0
       9: getfield      #16                 // Field simpleAeadCipher:Lorg/jose4j/jwe/SimpleAeadCipher;
      12: aload_0
      13: getfield      #34                 // Field log:Lorg/slf4j/Logger;
      16: iload_1
      17: bipush        12
      19: aload_0
      20: invokevirtual #35                 // Method getAlgorithmIdentifier:()Ljava/lang/String;
      23: invokevirtual #36                 // Method org/jose4j/jwe/SimpleAeadCipher.isAvailable:(Lorg/slf4j/Logger;IILjava/lang/String;)Z
      26: ireturn
}
