Compiled from "ContentEncryptionKeys.java"
public class org.jose4j.jwe.ContentEncryptionKeys {
  private final byte[] contentEncryptionKey;

  private final byte[] encryptedKey;

  public org.jose4j.jwe.ContentEncryptionKeys(byte[], byte[]);
    Code:
       0: aload_0
       1: invokespecial #1                  // Method java/lang/Object."<init>":()V
       4: aload_0
       5: aload_1
       6: putfield      #2                  // Field contentEncryptionKey:[B
       9: aload_0
      10: aload_2
      11: ifnonnull     20
      14: getstatic     #3                  // Field org/jose4j/lang/ByteUtil.EMPTY_BYTES:[B
      17: goto          21
      20: aload_2
      21: putfield      #4                  // Field encryptedKey:[B
      24: return

  public byte[] getContentEncryptionKey();
    Code:
       0: aload_0
       1: getfield      #2                  // Field contentEncryptionKey:[B
       4: areturn

  public byte[] getEncryptedKey();
    Code:
       0: aload_0
       1: getfield      #4                  // Field encryptedKey:[B
       4: areturn
}
