Compiled from "JDBCMetaDataConfiguration.java"
class org.hibernate.cfg.JDBCMetaDataConfiguration$1 implements org.hibernate.engine.Mapping {
  private final org.hibernate.cfg.Configuration val$cfg;

  org.hibernate.cfg.JDBCMetaDataConfiguration$1(org.hibernate.cfg.Configuration);
    Code:
       0: aload_0
       1: aload_1
       2: putfield      #1                  // Field val$cfg:Lorg/hibernate/cfg/Configuration;
       5: aload_0
       6: invokespecial #2                  // Method java/lang/Object."<init>":()V
       9: return

  public org.hibernate.type.Type getIdentifierType(java.lang.String) throws org.hibernate.MappingException;
    Code:
       0: aload_0
       1: getfield      #1                  // Field val$cfg:Lorg/hibernate/cfg/Configuration;
       4: aload_1
       5: invokevirtual #3                  // Method org/hibernate/cfg/Configuration.getClassMapping:(Ljava/lang/String;)Lorg/hibernate/mapping/PersistentClass;
       8: astore_2
       9: aload_2
      10: ifnonnull     40
      13: new           #4                  // class org/hibernate/MappingException
      16: dup
      17: new           #5                  // class java/lang/StringBuffer
      20: dup
      21: invokespecial #6                  // Method java/lang/StringBuffer."<init>":()V
      24: ldc           #7                  // String persistent class not known:
      26: invokevirtual #8                  // Method java/lang/StringBuffer.append:(Ljava/lang/String;)Ljava/lang/StringBuffer;
      29: aload_1
      30: invokevirtual #8                  // Method java/lang/StringBuffer.append:(Ljava/lang/String;)Ljava/lang/StringBuffer;
      33: invokevirtual #9                  // Method java/lang/StringBuffer.toString:()Ljava/lang/String;
      36: invokespecial #10                 // Method org/hibernate/MappingException."<init>":(Ljava/lang/String;)V
      39: athrow
      40: aload_2
      41: invokevirtual #11                 // Method org/hibernate/mapping/PersistentClass.getIdentifier:()Lorg/hibernate/mapping/KeyValue;
      44: invokeinterface #12,  1           // InterfaceMethod org/hibernate/mapping/KeyValue.getType:()Lorg/hibernate/type/Type;
      49: areturn

  public java.lang.String getIdentifierPropertyName(java.lang.String) throws org.hibernate.MappingException;
    Code:
       0: aload_0
       1: getfield      #1                  // Field val$cfg:Lorg/hibernate/cfg/Configuration;
       4: aload_1
       5: invokevirtual #3                  // Method org/hibernate/cfg/Configuration.getClassMapping:(Ljava/lang/String;)Lorg/hibernate/mapping/PersistentClass;
       8: astore_2
       9: aload_2
      10: ifnonnull     40
      13: new           #4                  // class org/hibernate/MappingException
      16: dup
      17: new           #5                  // class java/lang/StringBuffer
      20: dup
      21: invokespecial #6                  // Method java/lang/StringBuffer."<init>":()V
      24: ldc           #7                  // String persistent class not known:
      26: invokevirtual #8                  // Method java/lang/StringBuffer.append:(Ljava/lang/String;)Ljava/lang/StringBuffer;
      29: aload_1
      30: invokevirtual #8                  // Method java/lang/StringBuffer.append:(Ljava/lang/String;)Ljava/lang/StringBuffer;
      33: invokevirtual #9                  // Method java/lang/StringBuffer.toString:()Ljava/lang/String;
      36: invokespecial #10                 // Method org/hibernate/MappingException."<init>":(Ljava/lang/String;)V
      39: athrow
      40: aload_2
      41: invokevirtual #13                 // Method org/hibernate/mapping/PersistentClass.hasIdentifierProperty:()Z
      44: ifne          49
      47: aconst_null
      48: areturn
      49: aload_2
      50: invokevirtual #14                 // Method org/hibernate/mapping/PersistentClass.getIdentifierProperty:()Lorg/hibernate/mapping/Property;
      53: invokevirtual #15                 // Method org/hibernate/mapping/Property.getName:()Ljava/lang/String;
      56: areturn

  public org.hibernate.type.Type getReferencedPropertyType(java.lang.String, java.lang.String) throws org.hibernate.MappingException;
    Code:
       0: aload_0
       1: getfield      #1                  // Field val$cfg:Lorg/hibernate/cfg/Configuration;
       4: aload_1
       5: invokevirtual #3                  // Method org/hibernate/cfg/Configuration.getClassMapping:(Ljava/lang/String;)Lorg/hibernate/mapping/PersistentClass;
       8: astore_3
       9: aload_3
      10: ifnonnull     40
      13: new           #4                  // class org/hibernate/MappingException
      16: dup
      17: new           #5                  // class java/lang/StringBuffer
      20: dup
      21: invokespecial #6                  // Method java/lang/StringBuffer."<init>":()V
      24: ldc           #7                  // String persistent class not known:
      26: invokevirtual #8                  // Method java/lang/StringBuffer.append:(Ljava/lang/String;)Ljava/lang/StringBuffer;
      29: aload_1
      30: invokevirtual #8                  // Method java/lang/StringBuffer.append:(Ljava/lang/String;)Ljava/lang/StringBuffer;
      33: invokevirtual #9                  // Method java/lang/StringBuffer.toString:()Ljava/lang/String;
      36: invokespecial #10                 // Method org/hibernate/MappingException."<init>":(Ljava/lang/String;)V
      39: athrow
      40: aload_3
      41: aload_2
      42: invokevirtual #16                 // Method org/hibernate/mapping/PersistentClass.getProperty:(Ljava/lang/String;)Lorg/hibernate/mapping/Property;
      45: astore        4
      47: aload         4
      49: ifnonnull     88
      52: new           #4                  // class org/hibernate/MappingException
      55: dup
      56: new           #5                  // class java/lang/StringBuffer
      59: dup
      60: invokespecial #6                  // Method java/lang/StringBuffer."<init>":()V
      63: ldc           #17                 // String property not known:
      65: invokevirtual #8                  // Method java/lang/StringBuffer.append:(Ljava/lang/String;)Ljava/lang/StringBuffer;
      68: aload_1
      69: invokevirtual #8                  // Method java/lang/StringBuffer.append:(Ljava/lang/String;)Ljava/lang/StringBuffer;
      72: bipush        46
      74: invokevirtual #18                 // Method java/lang/StringBuffer.append:(C)Ljava/lang/StringBuffer;
      77: aload_2
      78: invokevirtual #8                  // Method java/lang/StringBuffer.append:(Ljava/lang/String;)Ljava/lang/StringBuffer;
      81: invokevirtual #9                  // Method java/lang/StringBuffer.toString:()Ljava/lang/String;
      84: invokespecial #10                 // Method org/hibernate/MappingException."<init>":(Ljava/lang/String;)V
      87: athrow
      88: aload         4
      90: invokevirtual #19                 // Method org/hibernate/mapping/Property.getType:()Lorg/hibernate/type/Type;
      93: areturn
}
