Compiled from "JDBCBinder.java"
class org.hibernate.cfg.JDBCBinder$JDBCCollectionSecondPass extends org.hibernate.cfg.CollectionSecondPass {
  org.hibernate.cfg.JDBCBinder$JDBCCollectionSecondPass(org.hibernate.cfg.Mappings, org.hibernate.mapping.Collection);
    Code:
       0: aload_0
       1: aload_1
       2: aload_2
       3: invokespecial #1                  // Method org/hibernate/cfg/CollectionSecondPass."<init>":(Lorg/hibernate/cfg/Mappings;Lorg/hibernate/mapping/Collection;)V
       6: return

  public void secondPass(java.util.Map, java.util.Map) throws org.hibernate.MappingException;
    Code:
       0: aload_0
       1: getfield      #2                  // Field collection:Lorg/hibernate/mapping/Collection;
       4: aload_1
       5: aload_0
       6: getfield      #3                  // Field mappings:Lorg/hibernate/cfg/Mappings;
       9: aload_2
      10: invokestatic  #4                  // Method org/hibernate/cfg/JDBCBinder.bindCollectionSecondPass:(Lorg/hibernate/mapping/Collection;Ljava/util/Map;Lorg/hibernate/cfg/Mappings;Ljava/util/Map;)V
      13: return

  public void doSecondPass(java.util.Map) throws org.hibernate.MappingException;
    Code:
       0: aload_0
       1: getfield      #2                  // Field collection:Lorg/hibernate/mapping/Collection;
       4: invokevirtual #5                  // Method org/hibernate/mapping/Collection.getElement:()Lorg/hibernate/mapping/Value;
       7: astore_2
       8: aconst_null
       9: astore_3
      10: aconst_null
      11: astore        4
      13: aload_2
      14: instanceof    #6                  // class org/hibernate/mapping/DependantValue
      17: ifeq          37
      20: aload_2
      21: checkcast     #6                  // class org/hibernate/mapping/DependantValue
      24: astore_3
      25: aload_3
      26: invokevirtual #7                  // Method org/hibernate/mapping/DependantValue.getForeignKeyName:()Ljava/lang/String;
      29: astore        4
      31: aload_3
      32: ldc           #8                  // String none
      34: invokevirtual #9                  // Method org/hibernate/mapping/DependantValue.setForeignKeyName:(Ljava/lang/String;)V
      37: aload_0
      38: aload_1
      39: invokespecial #10                 // Method org/hibernate/cfg/CollectionSecondPass.doSecondPass:(Ljava/util/Map;)V
      42: aload_3
      43: ifnull        52
      46: aload_3
      47: aload         4
      49: invokevirtual #9                  // Method org/hibernate/mapping/DependantValue.setForeignKeyName:(Ljava/lang/String;)V
      52: return
}
