Compiled from "ForwardCheckSSIndicationRequestImpl.java"
public class org.mobicents.protocols.ss7.map.service.mobility.faultRecovery.ForwardCheckSSIndicationRequestImpl extends org.mobicents.protocols.ss7.map.service.mobility.MobilityMessageImpl implements org.mobicents.protocols.ss7.map.api.service.mobility.faultRecovery.ForwardCheckSSIndicationRequest {
  public static final java.lang.String _PrimitiveName;

  public org.mobicents.protocols.ss7.map.service.mobility.faultRecovery.ForwardCheckSSIndicationRequestImpl();
    Code:
       0: aload_0
       1: invokespecial #1                  // Method org/mobicents/protocols/ss7/map/service/mobility/MobilityMessageImpl."<init>":()V
       4: return

  public org.mobicents.protocols.ss7.map.api.MAPMessageType getMessageType();
    Code:
       0: getstatic     #2                  // Field org/mobicents/protocols/ss7/map/api/MAPMessageType.forwardCheckSSIndication_Request:Lorg/mobicents/protocols/ss7/map/api/MAPMessageType;
       3: areturn

  public int getOperationCode();
    Code:
       0: bipush        38
       2: ireturn

  public int getTag() throws org.mobicents.protocols.ss7.map.api.MAPException;
    Code:
       0: new           #3                  // class org/mobicents/protocols/ss7/map/api/MAPException
       3: dup
       4: ldc           #4                  // String Encoding / decoding is not supported
       6: invokespecial #5                  // Method org/mobicents/protocols/ss7/map/api/MAPException."<init>":(Ljava/lang/String;)V
       9: athrow

  public int getTagClass();
    Code:
       0: iconst_0
       1: ireturn

  public boolean getIsPrimitive();
    Code:
       0: iconst_0
       1: ireturn

  public void decodeAll(org.mobicents.protocols.asn.AsnInputStream) throws org.mobicents.protocols.ss7.map.api.MAPParsingComponentException;
    Code:
       0: new           #6                  // class org/mobicents/protocols/ss7/map/api/MAPParsingComponentException
       3: dup
       4: ldc           #4                  // String Encoding / decoding is not supported
       6: getstatic     #7                  // Field org/mobicents/protocols/ss7/map/api/MAPParsingComponentExceptionReason.MistypedParameter:Lorg/mobicents/protocols/ss7/map/api/MAPParsingComponentExceptionReason;
       9: invokespecial #8                  // Method org/mobicents/protocols/ss7/map/api/MAPParsingComponentException."<init>":(Ljava/lang/String;Lorg/mobicents/protocols/ss7/map/api/MAPParsingComponentExceptionReason;)V
      12: athrow

  public void decodeData(org.mobicents.protocols.asn.AsnInputStream, int) throws org.mobicents.protocols.ss7.map.api.MAPParsingComponentException;
    Code:
       0: new           #6                  // class org/mobicents/protocols/ss7/map/api/MAPParsingComponentException
       3: dup
       4: ldc           #4                  // String Encoding / decoding is not supported
       6: getstatic     #7                  // Field org/mobicents/protocols/ss7/map/api/MAPParsingComponentExceptionReason.MistypedParameter:Lorg/mobicents/protocols/ss7/map/api/MAPParsingComponentExceptionReason;
       9: invokespecial #8                  // Method org/mobicents/protocols/ss7/map/api/MAPParsingComponentException."<init>":(Ljava/lang/String;Lorg/mobicents/protocols/ss7/map/api/MAPParsingComponentExceptionReason;)V
      12: athrow

  public void encodeAll(org.mobicents.protocols.asn.AsnOutputStream) throws org.mobicents.protocols.ss7.map.api.MAPException;
    Code:
       0: new           #3                  // class org/mobicents/protocols/ss7/map/api/MAPException
       3: dup
       4: ldc           #4                  // String Encoding / decoding is not supported
       6: invokespecial #5                  // Method org/mobicents/protocols/ss7/map/api/MAPException."<init>":(Ljava/lang/String;)V
       9: athrow

  public void encodeAll(org.mobicents.protocols.asn.AsnOutputStream, int, int) throws org.mobicents.protocols.ss7.map.api.MAPException;
    Code:
       0: new           #3                  // class org/mobicents/protocols/ss7/map/api/MAPException
       3: dup
       4: ldc           #4                  // String Encoding / decoding is not supported
       6: invokespecial #5                  // Method org/mobicents/protocols/ss7/map/api/MAPException."<init>":(Ljava/lang/String;)V
       9: athrow

  public void encodeData(org.mobicents.protocols.asn.AsnOutputStream) throws org.mobicents.protocols.ss7.map.api.MAPException;
    Code:
       0: new           #3                  // class org/mobicents/protocols/ss7/map/api/MAPException
       3: dup
       4: ldc           #4                  // String Encoding / decoding is not supported
       6: invokespecial #5                  // Method org/mobicents/protocols/ss7/map/api/MAPException."<init>":(Ljava/lang/String;)V
       9: athrow

  public java.lang.String toString();
    Code:
       0: new           #9                  // class java/lang/StringBuilder
       3: dup
       4: invokespecial #10                 // Method java/lang/StringBuilder."<init>":()V
       7: astore_1
       8: aload_1
       9: ldc           #11                 // String ForwardCheckSSIndicationRequest
      11: invokevirtual #12                 // Method java/lang/StringBuilder.append:(Ljava/lang/String;)Ljava/lang/StringBuilder;
      14: pop
      15: aload_1
      16: ldc           #13                 // String  [
      18: invokevirtual #12                 // Method java/lang/StringBuilder.append:(Ljava/lang/String;)Ljava/lang/StringBuilder;
      21: pop
      22: aload_1
      23: ldc           #14                 // String ]
      25: invokevirtual #12                 // Method java/lang/StringBuilder.append:(Ljava/lang/String;)Ljava/lang/StringBuilder;
      28: pop
      29: aload_1
      30: invokevirtual #15                 // Method java/lang/StringBuilder.toString:()Ljava/lang/String;
      33: areturn
}
