Compiled from "BytesToNameCanonicalizer.java"
final class org.apache.htrace.shaded.fasterxml.jackson.core.sym.BytesToNameCanonicalizer$TableInfo {
  public final int count;

  public final int mainHashMask;

  public final int[] mainHash;

  public final org.apache.htrace.shaded.fasterxml.jackson.core.sym.Name[] mainNames;

  public final org.apache.htrace.shaded.fasterxml.jackson.core.sym.BytesToNameCanonicalizer$Bucket[] collList;

  public final int collCount;

  public final int collEnd;

  public final int longestCollisionList;

  public org.apache.htrace.shaded.fasterxml.jackson.core.sym.BytesToNameCanonicalizer$TableInfo(int, int, int[], org.apache.htrace.shaded.fasterxml.jackson.core.sym.Name[], org.apache.htrace.shaded.fasterxml.jackson.core.sym.BytesToNameCanonicalizer$Bucket[], int, int, int);
    Code:
       0: aload_0
       1: invokespecial #28                 // Method java/lang/Object."<init>":()V
       4: aload_0
       5: iload_1
       6: putfield      #30                 // Field count:I
       9: aload_0
      10: iload_2
      11: putfield      #32                 // Field mainHashMask:I
      14: aload_0
      15: aload_3
      16: putfield      #34                 // Field mainHash:[I
      19: aload_0
      20: aload         4
      22: putfield      #36                 // Field mainNames:[Lorg/apache/htrace/shaded/fasterxml/jackson/core/sym/Name;
      25: aload_0
      26: aload         5
      28: putfield      #38                 // Field collList:[Lorg/apache/htrace/shaded/fasterxml/jackson/core/sym/BytesToNameCanonicalizer$Bucket;
      31: aload_0
      32: iload         6
      34: putfield      #40                 // Field collCount:I
      37: aload_0
      38: iload         7
      40: putfield      #42                 // Field collEnd:I
      43: aload_0
      44: iload         8
      46: putfield      #44                 // Field longestCollisionList:I
      49: return

  public org.apache.htrace.shaded.fasterxml.jackson.core.sym.BytesToNameCanonicalizer$TableInfo(org.apache.htrace.shaded.fasterxml.jackson.core.sym.BytesToNameCanonicalizer);
    Code:
       0: aload_0
       1: invokespecial #28                 // Method java/lang/Object."<init>":()V
       4: aload_0
       5: aload_1
       6: getfield      #50                 // Field org/apache/htrace/shaded/fasterxml/jackson/core/sym/BytesToNameCanonicalizer._count:I
       9: putfield      #30                 // Field count:I
      12: aload_0
      13: aload_1
      14: getfield      #53                 // Field org/apache/htrace/shaded/fasterxml/jackson/core/sym/BytesToNameCanonicalizer._hashMask:I
      17: putfield      #32                 // Field mainHashMask:I
      20: aload_0
      21: aload_1
      22: getfield      #56                 // Field org/apache/htrace/shaded/fasterxml/jackson/core/sym/BytesToNameCanonicalizer._hash:[I
      25: putfield      #34                 // Field mainHash:[I
      28: aload_0
      29: aload_1
      30: getfield      #59                 // Field org/apache/htrace/shaded/fasterxml/jackson/core/sym/BytesToNameCanonicalizer._mainNames:[Lorg/apache/htrace/shaded/fasterxml/jackson/core/sym/Name;
      33: putfield      #36                 // Field mainNames:[Lorg/apache/htrace/shaded/fasterxml/jackson/core/sym/Name;
      36: aload_0
      37: aload_1
      38: getfield      #62                 // Field org/apache/htrace/shaded/fasterxml/jackson/core/sym/BytesToNameCanonicalizer._collList:[Lorg/apache/htrace/shaded/fasterxml/jackson/core/sym/BytesToNameCanonicalizer$Bucket;
      41: putfield      #38                 // Field collList:[Lorg/apache/htrace/shaded/fasterxml/jackson/core/sym/BytesToNameCanonicalizer$Bucket;
      44: aload_0
      45: aload_1
      46: getfield      #65                 // Field org/apache/htrace/shaded/fasterxml/jackson/core/sym/BytesToNameCanonicalizer._collCount:I
      49: putfield      #40                 // Field collCount:I
      52: aload_0
      53: aload_1
      54: getfield      #68                 // Field org/apache/htrace/shaded/fasterxml/jackson/core/sym/BytesToNameCanonicalizer._collEnd:I
      57: putfield      #42                 // Field collEnd:I
      60: aload_0
      61: aload_1
      62: getfield      #71                 // Field org/apache/htrace/shaded/fasterxml/jackson/core/sym/BytesToNameCanonicalizer._longestCollisionList:I
      65: putfield      #44                 // Field longestCollisionList:I
      68: return
}
