public class org.bouncycastle.dvcs.CCPDRequestData extends org.bouncycastle.dvcs.DVCSRequestData {
  org.bouncycastle.dvcs.CCPDRequestData(org.bouncycastle.asn1.dvcs.Data) throws org.bouncycastle.dvcs.DVCSConstructionException;
    Code:
       0: aload_0
       1: aload_1
       2: invokespecial #34                 // Method org/bouncycastle/dvcs/DVCSRequestData."<init>":(Lorg/bouncycastle/asn1/dvcs/Data;)V
       5: aload_0
       6: invokespecial #32                 // Method initDigest:()V
       9: return

  private void initDigest() throws org.bouncycastle.dvcs.DVCSConstructionException;
    Code:
       0: aload_0
       1: getfield      #30                 // Field data:Lorg/bouncycastle/asn1/dvcs/Data;
       4: invokevirtual #31                 // Method org/bouncycastle/asn1/dvcs/Data.getMessageImprint:()Lorg/bouncycastle/asn1/x509/DigestInfo;
       7: ifnonnull     20
      10: new           #15                 // class org/bouncycastle/dvcs/DVCSConstructionException
      13: dup
      14: ldc           #1                  // String DVCSRequest.data.messageImprint should be specified for CCPD service
      16: invokespecial #33                 // Method org/bouncycastle/dvcs/DVCSConstructionException."<init>":(Ljava/lang/String;)V
      19: athrow
      20: return

  public org.bouncycastle.dvcs.MessageImprint getMessageImprint();
    Code:
       0: new           #17                 // class org/bouncycastle/dvcs/MessageImprint
       3: dup
       4: aload_0
       5: getfield      #30                 // Field data:Lorg/bouncycastle/asn1/dvcs/Data;
       8: invokevirtual #31                 // Method org/bouncycastle/asn1/dvcs/Data.getMessageImprint:()Lorg/bouncycastle/asn1/x509/DigestInfo;
      11: invokespecial #35                 // Method org/bouncycastle/dvcs/MessageImprint."<init>":(Lorg/bouncycastle/asn1/x509/DigestInfo;)V
      14: areturn
}
