Compiled from "UpdateVisitorBase.java"
public class org.apache.jena.sparql.modify.request.UpdateVisitorBase implements org.apache.jena.sparql.modify.request.UpdateVisitor {
  public org.apache.jena.sparql.modify.request.UpdateVisitorBase();
    Code:
       0: aload_0
       1: invokespecial #1                  // Method java/lang/Object."<init>":()V
       4: return

  public void visit(org.apache.jena.sparql.modify.request.UpdateDrop);
    Code:
       0: return

  public void visit(org.apache.jena.sparql.modify.request.UpdateClear);
    Code:
       0: return

  public void visit(org.apache.jena.sparql.modify.request.UpdateCreate);
    Code:
       0: return

  public void visit(org.apache.jena.sparql.modify.request.UpdateLoad);
    Code:
       0: return

  public void visit(org.apache.jena.sparql.modify.request.UpdateAdd);
    Code:
       0: return

  public void visit(org.apache.jena.sparql.modify.request.UpdateCopy);
    Code:
       0: return

  public void visit(org.apache.jena.sparql.modify.request.UpdateMove);
    Code:
       0: return

  public void visit(org.apache.jena.sparql.modify.request.UpdateDataInsert);
    Code:
       0: return

  public void visit(org.apache.jena.sparql.modify.request.UpdateDataDelete);
    Code:
       0: return

  public void visit(org.apache.jena.sparql.modify.request.UpdateDeleteWhere);
    Code:
       0: return

  public void visit(org.apache.jena.sparql.modify.request.UpdateModify);
    Code:
       0: return

  public org.apache.jena.atlas.lib.Sink<org.apache.jena.sparql.core.Quad> createInsertDataSink();
    Code:
       0: aconst_null
       1: areturn

  public org.apache.jena.atlas.lib.Sink<org.apache.jena.sparql.core.Quad> createDeleteDataSink();
    Code:
       0: aconst_null
       1: areturn
}
