Compiled from "UpdateWriterVisitor.java"
public class org.apache.jena.sparql.modify.request.UpdateWriterVisitor implements org.apache.jena.sparql.modify.request.UpdateVisitor {
  protected static final int BLOCK_INDENT;

  protected final org.apache.jena.atlas.io.IndentedWriter out;

  protected final org.apache.jena.sparql.serializer.SerializationContext sCxt;

  public org.apache.jena.sparql.modify.request.UpdateWriterVisitor(org.apache.jena.atlas.io.IndentedWriter, org.apache.jena.sparql.serializer.SerializationContext);
    Code:
       0: aload_0
       1: invokespecial #1                  // Method java/lang/Object."<init>":()V
       4: aload_0
       5: aload_1
       6: putfield      #2                  // Field out:Lorg/apache/jena/atlas/io/IndentedWriter;
       9: aload_0
      10: aload_2
      11: putfield      #3                  // Field sCxt:Lorg/apache/jena/sparql/serializer/SerializationContext;
      14: return

  protected void visitDropClear(java.lang.String, org.apache.jena.sparql.modify.request.UpdateDropClear);
    Code:
       0: aload_0
       1: getfield      #2                  // Field out:Lorg/apache/jena/atlas/io/IndentedWriter;
       4: invokevirtual #4                  // Method org/apache/jena/atlas/io/IndentedWriter.ensureStartOfLine:()V
       7: aload_0
       8: getfield      #2                  // Field out:Lorg/apache/jena/atlas/io/IndentedWriter;
      11: aload_1
      12: invokevirtual #5                  // Method org/apache/jena/atlas/io/IndentedWriter.print:(Ljava/lang/String;)V
      15: aload_0
      16: getfield      #2                  // Field out:Lorg/apache/jena/atlas/io/IndentedWriter;
      19: ldc           #6                  // String
      21: invokevirtual #5                  // Method org/apache/jena/atlas/io/IndentedWriter.print:(Ljava/lang/String;)V
      24: aload_2
      25: invokevirtual #7                  // Method org/apache/jena/sparql/modify/request/UpdateDropClear.isSilent:()Z
      28: ifeq          40
      31: aload_0
      32: getfield      #2                  // Field out:Lorg/apache/jena/atlas/io/IndentedWriter;
      35: ldc           #8                  // String SILENT
      37: invokevirtual #5                  // Method org/apache/jena/atlas/io/IndentedWriter.print:(Ljava/lang/String;)V
      40: aload_0
      41: aload_2
      42: invokevirtual #9                  // Method org/apache/jena/sparql/modify/request/UpdateDropClear.getTarget:()Lorg/apache/jena/sparql/modify/request/Target;
      45: invokevirtual #10                 // Method printTarget:(Lorg/apache/jena/sparql/modify/request/Target;)V
      48: return

  protected void printTarget(org.apache.jena.sparql.modify.request.Target);
    Code:
       0: aload_1
       1: invokevirtual #11                 // Method org/apache/jena/sparql/modify/request/Target.isAll:()Z
       4: ifeq          19
       7: aload_0
       8: getfield      #2                  // Field out:Lorg/apache/jena/atlas/io/IndentedWriter;
      11: ldc           #12                 // String ALL
      13: invokevirtual #5                  // Method org/apache/jena/atlas/io/IndentedWriter.print:(Ljava/lang/String;)V
      16: goto          115
      19: aload_1
      20: invokevirtual #13                 // Method org/apache/jena/sparql/modify/request/Target.isAllNamed:()Z
      23: ifeq          38
      26: aload_0
      27: getfield      #2                  // Field out:Lorg/apache/jena/atlas/io/IndentedWriter;
      30: ldc           #14                 // String NAMED
      32: invokevirtual #5                  // Method org/apache/jena/atlas/io/IndentedWriter.print:(Ljava/lang/String;)V
      35: goto          115
      38: aload_1
      39: invokevirtual #15                 // Method org/apache/jena/sparql/modify/request/Target.isDefault:()Z
      42: ifeq          57
      45: aload_0
      46: getfield      #2                  // Field out:Lorg/apache/jena/atlas/io/IndentedWriter;
      49: ldc           #16                 // String DEFAULT
      51: invokevirtual #5                  // Method org/apache/jena/atlas/io/IndentedWriter.print:(Ljava/lang/String;)V
      54: goto          115
      57: aload_1
      58: invokevirtual #17                 // Method org/apache/jena/sparql/modify/request/Target.isOneNamedGraph:()Z
      61: ifeq          96
      64: aload_0
      65: getfield      #2                  // Field out:Lorg/apache/jena/atlas/io/IndentedWriter;
      68: ldc           #18                 // String GRAPH
      70: invokevirtual #5                  // Method org/apache/jena/atlas/io/IndentedWriter.print:(Ljava/lang/String;)V
      73: aload_1
      74: invokevirtual #19                 // Method org/apache/jena/sparql/modify/request/Target.getGraph:()Lorg/apache/jena/graph/Node;
      77: aload_0
      78: getfield      #3                  // Field sCxt:Lorg/apache/jena/sparql/serializer/SerializationContext;
      81: invokestatic  #20                 // Method org/apache/jena/sparql/util/FmtUtils.stringForNode:(Lorg/apache/jena/graph/Node;Lorg/apache/jena/sparql/serializer/SerializationContext;)Ljava/lang/String;
      84: astore_2
      85: aload_0
      86: getfield      #2                  // Field out:Lorg/apache/jena/atlas/io/IndentedWriter;
      89: aload_2
      90: invokevirtual #5                  // Method org/apache/jena/atlas/io/IndentedWriter.print:(Ljava/lang/String;)V
      93: goto          115
      96: aload_0
      97: getfield      #2                  // Field out:Lorg/apache/jena/atlas/io/IndentedWriter;
     100: ldc           #21                 // String Target BROKEN
     102: invokevirtual #5                  // Method org/apache/jena/atlas/io/IndentedWriter.print:(Ljava/lang/String;)V
     105: new           #22                 // class org/apache/jena/sparql/ARQException
     108: dup
     109: ldc           #23                 // String Malformed Target
     111: invokespecial #24                 // Method org/apache/jena/sparql/ARQException."<init>":(Ljava/lang/String;)V
     114: athrow
     115: return

  public void visit(org.apache.jena.sparql.modify.request.UpdateDrop);
    Code:
       0: aload_0
       1: ldc           #25                 // String DROP
       3: aload_1
       4: invokevirtual #26                 // Method visitDropClear:(Ljava/lang/String;Lorg/apache/jena/sparql/modify/request/UpdateDropClear;)V
       7: return

  public void visit(org.apache.jena.sparql.modify.request.UpdateClear);
    Code:
       0: aload_0
       1: ldc           #27                 // String CLEAR
       3: aload_1
       4: invokevirtual #26                 // Method visitDropClear:(Ljava/lang/String;Lorg/apache/jena/sparql/modify/request/UpdateDropClear;)V
       7: return

  public void visit(org.apache.jena.sparql.modify.request.UpdateCreate);
    Code:
       0: aload_0
       1: getfield      #2                  // Field out:Lorg/apache/jena/atlas/io/IndentedWriter;
       4: invokevirtual #4                  // Method org/apache/jena/atlas/io/IndentedWriter.ensureStartOfLine:()V
       7: aload_0
       8: getfield      #2                  // Field out:Lorg/apache/jena/atlas/io/IndentedWriter;
      11: ldc           #28                 // String CREATE
      13: invokevirtual #5                  // Method org/apache/jena/atlas/io/IndentedWriter.print:(Ljava/lang/String;)V
      16: aload_0
      17: getfield      #2                  // Field out:Lorg/apache/jena/atlas/io/IndentedWriter;
      20: ldc           #6                  // String
      22: invokevirtual #5                  // Method org/apache/jena/atlas/io/IndentedWriter.print:(Ljava/lang/String;)V
      25: aload_1
      26: invokevirtual #29                 // Method org/apache/jena/sparql/modify/request/UpdateCreate.isSilent:()Z
      29: ifeq          41
      32: aload_0
      33: getfield      #2                  // Field out:Lorg/apache/jena/atlas/io/IndentedWriter;
      36: ldc           #8                  // String SILENT
      38: invokevirtual #5                  // Method org/apache/jena/atlas/io/IndentedWriter.print:(Ljava/lang/String;)V
      41: aload_0
      42: getfield      #2                  // Field out:Lorg/apache/jena/atlas/io/IndentedWriter;
      45: ldc           #30                 // String GRAPH
      47: invokevirtual #5                  // Method org/apache/jena/atlas/io/IndentedWriter.print:(Ljava/lang/String;)V
      50: aload_0
      51: getfield      #2                  // Field out:Lorg/apache/jena/atlas/io/IndentedWriter;
      54: ldc           #6                  // String
      56: invokevirtual #5                  // Method org/apache/jena/atlas/io/IndentedWriter.print:(Ljava/lang/String;)V
      59: aload_1
      60: invokevirtual #31                 // Method org/apache/jena/sparql/modify/request/UpdateCreate.getGraph:()Lorg/apache/jena/graph/Node;
      63: aload_0
      64: getfield      #3                  // Field sCxt:Lorg/apache/jena/sparql/serializer/SerializationContext;
      67: invokestatic  #20                 // Method org/apache/jena/sparql/util/FmtUtils.stringForNode:(Lorg/apache/jena/graph/Node;Lorg/apache/jena/sparql/serializer/SerializationContext;)Ljava/lang/String;
      70: astore_2
      71: aload_0
      72: getfield      #2                  // Field out:Lorg/apache/jena/atlas/io/IndentedWriter;
      75: aload_2
      76: invokevirtual #5                  // Method org/apache/jena/atlas/io/IndentedWriter.print:(Ljava/lang/String;)V
      79: return

  public void visit(org.apache.jena.sparql.modify.request.UpdateLoad);
    Code:
       0: aload_0
       1: getfield      #2                  // Field out:Lorg/apache/jena/atlas/io/IndentedWriter;
       4: invokevirtual #4                  // Method org/apache/jena/atlas/io/IndentedWriter.ensureStartOfLine:()V
       7: aload_0
       8: getfield      #2                  // Field out:Lorg/apache/jena/atlas/io/IndentedWriter;
      11: ldc           #32                 // String LOAD
      13: invokevirtual #5                  // Method org/apache/jena/atlas/io/IndentedWriter.print:(Ljava/lang/String;)V
      16: aload_0
      17: getfield      #2                  // Field out:Lorg/apache/jena/atlas/io/IndentedWriter;
      20: ldc           #6                  // String
      22: invokevirtual #5                  // Method org/apache/jena/atlas/io/IndentedWriter.print:(Ljava/lang/String;)V
      25: aload_1
      26: invokevirtual #33                 // Method org/apache/jena/sparql/modify/request/UpdateLoad.getSilent:()Z
      29: ifeq          41
      32: aload_0
      33: getfield      #2                  // Field out:Lorg/apache/jena/atlas/io/IndentedWriter;
      36: ldc           #8                  // String SILENT
      38: invokevirtual #5                  // Method org/apache/jena/atlas/io/IndentedWriter.print:(Ljava/lang/String;)V
      41: aload_0
      42: aload_1
      43: invokevirtual #34                 // Method org/apache/jena/sparql/modify/request/UpdateLoad.getSource:()Ljava/lang/String;
      46: invokevirtual #35                 // Method outputStringAsURI:(Ljava/lang/String;)V
      49: aload_1
      50: invokevirtual #36                 // Method org/apache/jena/sparql/modify/request/UpdateLoad.getDest:()Lorg/apache/jena/graph/Node;
      53: ifnull        73
      56: aload_0
      57: getfield      #2                  // Field out:Lorg/apache/jena/atlas/io/IndentedWriter;
      60: ldc           #37                 // String  INTO GRAPH
      62: invokevirtual #5                  // Method org/apache/jena/atlas/io/IndentedWriter.print:(Ljava/lang/String;)V
      65: aload_0
      66: aload_1
      67: invokevirtual #36                 // Method org/apache/jena/sparql/modify/request/UpdateLoad.getDest:()Lorg/apache/jena/graph/Node;
      70: invokevirtual #38                 // Method output:(Lorg/apache/jena/graph/Node;)V
      73: return

  protected void outputStringAsURI(java.lang.String);
    Code:
       0: aload_1
       1: aload_0
       2: getfield      #3                  // Field sCxt:Lorg/apache/jena/sparql/serializer/SerializationContext;
       5: invokestatic  #39                 // Method org/apache/jena/sparql/util/FmtUtils.stringForURI:(Ljava/lang/String;Lorg/apache/jena/sparql/serializer/SerializationContext;)Ljava/lang/String;
       8: astore_2
       9: aload_0
      10: getfield      #2                  // Field out:Lorg/apache/jena/atlas/io/IndentedWriter;
      13: aload_2
      14: invokevirtual #5                  // Method org/apache/jena/atlas/io/IndentedWriter.print:(Ljava/lang/String;)V
      17: return

  protected void printTargetUpdate2(org.apache.jena.sparql.modify.request.Target);
    Code:
       0: aload_1
       1: invokevirtual #15                 // Method org/apache/jena/sparql/modify/request/Target.isDefault:()Z
       4: ifeq          19
       7: aload_0
       8: getfield      #2                  // Field out:Lorg/apache/jena/atlas/io/IndentedWriter;
      11: ldc           #16                 // String DEFAULT
      13: invokevirtual #5                  // Method org/apache/jena/atlas/io/IndentedWriter.print:(Ljava/lang/String;)V
      16: goto          68
      19: aload_1
      20: invokevirtual #17                 // Method org/apache/jena/sparql/modify/request/Target.isOneNamedGraph:()Z
      23: ifeq          49
      26: aload_1
      27: invokevirtual #19                 // Method org/apache/jena/sparql/modify/request/Target.getGraph:()Lorg/apache/jena/graph/Node;
      30: aload_0
      31: getfield      #3                  // Field sCxt:Lorg/apache/jena/sparql/serializer/SerializationContext;
      34: invokestatic  #20                 // Method org/apache/jena/sparql/util/FmtUtils.stringForNode:(Lorg/apache/jena/graph/Node;Lorg/apache/jena/sparql/serializer/SerializationContext;)Ljava/lang/String;
      37: astore_2
      38: aload_0
      39: getfield      #2                  // Field out:Lorg/apache/jena/atlas/io/IndentedWriter;
      42: aload_2
      43: invokevirtual #5                  // Method org/apache/jena/atlas/io/IndentedWriter.print:(Ljava/lang/String;)V
      46: goto          68
      49: aload_0
      50: getfield      #2                  // Field out:Lorg/apache/jena/atlas/io/IndentedWriter;
      53: ldc           #40                 // String Target BROKEN / Update2
      55: invokevirtual #5                  // Method org/apache/jena/atlas/io/IndentedWriter.print:(Ljava/lang/String;)V
      58: new           #22                 // class org/apache/jena/sparql/ARQException
      61: dup
      62: ldc           #41                 // String Malformed Target / Update2
      64: invokespecial #24                 // Method org/apache/jena/sparql/ARQException."<init>":(Ljava/lang/String;)V
      67: athrow
      68: return

  protected void printUpdate2(org.apache.jena.sparql.modify.request.UpdateBinaryOp, java.lang.String);
    Code:
       0: aload_0
       1: getfield      #2                  // Field out:Lorg/apache/jena/atlas/io/IndentedWriter;
       4: aload_2
       5: invokevirtual #5                  // Method org/apache/jena/atlas/io/IndentedWriter.print:(Ljava/lang/String;)V
       8: aload_1
       9: invokevirtual #42                 // Method org/apache/jena/sparql/modify/request/UpdateBinaryOp.getSilent:()Z
      12: ifeq          24
      15: aload_0
      16: getfield      #2                  // Field out:Lorg/apache/jena/atlas/io/IndentedWriter;
      19: ldc           #43                 // String  SILENT
      21: invokevirtual #5                  // Method org/apache/jena/atlas/io/IndentedWriter.print:(Ljava/lang/String;)V
      24: aload_0
      25: getfield      #2                  // Field out:Lorg/apache/jena/atlas/io/IndentedWriter;
      28: ldc           #6                  // String
      30: invokevirtual #5                  // Method org/apache/jena/atlas/io/IndentedWriter.print:(Ljava/lang/String;)V
      33: aload_0
      34: aload_1
      35: invokevirtual #44                 // Method org/apache/jena/sparql/modify/request/UpdateBinaryOp.getSrc:()Lorg/apache/jena/sparql/modify/request/Target;
      38: invokevirtual #45                 // Method printTargetUpdate2:(Lorg/apache/jena/sparql/modify/request/Target;)V
      41: aload_0
      42: getfield      #2                  // Field out:Lorg/apache/jena/atlas/io/IndentedWriter;
      45: ldc           #46                 // String  TO
      47: invokevirtual #5                  // Method org/apache/jena/atlas/io/IndentedWriter.print:(Ljava/lang/String;)V
      50: aload_0
      51: aload_1
      52: invokevirtual #47                 // Method org/apache/jena/sparql/modify/request/UpdateBinaryOp.getDest:()Lorg/apache/jena/sparql/modify/request/Target;
      55: invokevirtual #45                 // Method printTargetUpdate2:(Lorg/apache/jena/sparql/modify/request/Target;)V
      58: return

  public void visit(org.apache.jena.sparql.modify.request.UpdateAdd);
    Code:
       0: aload_0
       1: aload_1
       2: ldc           #48                 // String ADD
       4: invokevirtual #49                 // Method printUpdate2:(Lorg/apache/jena/sparql/modify/request/UpdateBinaryOp;Ljava/lang/String;)V
       7: return

  public void visit(org.apache.jena.sparql.modify.request.UpdateCopy);
    Code:
       0: aload_0
       1: aload_1
       2: ldc           #50                 // String COPY
       4: invokevirtual #49                 // Method printUpdate2:(Lorg/apache/jena/sparql/modify/request/UpdateBinaryOp;Ljava/lang/String;)V
       7: return

  public void visit(org.apache.jena.sparql.modify.request.UpdateMove);
    Code:
       0: aload_0
       1: aload_1
       2: ldc           #51                 // String MOVE
       4: invokevirtual #49                 // Method printUpdate2:(Lorg/apache/jena/sparql/modify/request/UpdateBinaryOp;Ljava/lang/String;)V
       7: return

  public org.apache.jena.atlas.lib.Sink<org.apache.jena.sparql.core.Quad> createInsertDataSink();
    Code:
       0: new           #52                 // class org/apache/jena/sparql/modify/request/UpdateDataWriter
       3: dup
       4: getstatic     #53                 // Field org/apache/jena/sparql/modify/request/UpdateDataWriter$UpdateMode.INSERT:Lorg/apache/jena/sparql/modify/request/UpdateDataWriter$UpdateMode;
       7: aload_0
       8: getfield      #2                  // Field out:Lorg/apache/jena/atlas/io/IndentedWriter;
      11: aload_0
      12: getfield      #3                  // Field sCxt:Lorg/apache/jena/sparql/serializer/SerializationContext;
      15: invokespecial #54                 // Method org/apache/jena/sparql/modify/request/UpdateDataWriter."<init>":(Lorg/apache/jena/sparql/modify/request/UpdateDataWriter$UpdateMode;Lorg/apache/jena/atlas/io/IndentedWriter;Lorg/apache/jena/sparql/serializer/SerializationContext;)V
      18: astore_1
      19: aload_1
      20: invokevirtual #55                 // Method org/apache/jena/sparql/modify/request/UpdateDataWriter.open:()V
      23: aload_1
      24: areturn

  public void visit(org.apache.jena.sparql.modify.request.UpdateDataInsert);
    Code:
       0: aload_1
       1: invokevirtual #56                 // Method org/apache/jena/sparql/modify/request/UpdateDataInsert.getQuads:()Ljava/util/List;
       4: aload_0
       5: invokevirtual #57                 // Method createInsertDataSink:()Lorg/apache/jena/atlas/lib/Sink;
       8: invokestatic  #58                 // Method org/apache/jena/atlas/iterator/Iter.sendToSink:(Ljava/lang/Iterable;Lorg/apache/jena/atlas/lib/Sink;)V
      11: return

  public org.apache.jena.atlas.lib.Sink<org.apache.jena.sparql.core.Quad> createDeleteDataSink();
    Code:
       0: new           #52                 // class org/apache/jena/sparql/modify/request/UpdateDataWriter
       3: dup
       4: getstatic     #59                 // Field org/apache/jena/sparql/modify/request/UpdateDataWriter$UpdateMode.DELETE:Lorg/apache/jena/sparql/modify/request/UpdateDataWriter$UpdateMode;
       7: aload_0
       8: getfield      #2                  // Field out:Lorg/apache/jena/atlas/io/IndentedWriter;
      11: aload_0
      12: getfield      #3                  // Field sCxt:Lorg/apache/jena/sparql/serializer/SerializationContext;
      15: invokespecial #54                 // Method org/apache/jena/sparql/modify/request/UpdateDataWriter."<init>":(Lorg/apache/jena/sparql/modify/request/UpdateDataWriter$UpdateMode;Lorg/apache/jena/atlas/io/IndentedWriter;Lorg/apache/jena/sparql/serializer/SerializationContext;)V
      18: astore_1
      19: aload_1
      20: invokevirtual #55                 // Method org/apache/jena/sparql/modify/request/UpdateDataWriter.open:()V
      23: aload_1
      24: areturn

  public void visit(org.apache.jena.sparql.modify.request.UpdateDataDelete);
    Code:
       0: aload_1
       1: invokevirtual #60                 // Method org/apache/jena/sparql/modify/request/UpdateDataDelete.getQuads:()Ljava/util/List;
       4: aload_0
       5: invokevirtual #61                 // Method createDeleteDataSink:()Lorg/apache/jena/atlas/lib/Sink;
       8: invokestatic  #58                 // Method org/apache/jena/atlas/iterator/Iter.sendToSink:(Ljava/lang/Iterable;Lorg/apache/jena/atlas/lib/Sink;)V
      11: return

  protected void outputQuadsBraced(java.util.List<org.apache.jena.sparql.core.Quad>);
    Code:
       0: aload_1
       1: invokeinterface #62,  1           // InterfaceMethod java/util/List.size:()I
       6: ifne          19
       9: aload_0
      10: getfield      #2                  // Field out:Lorg/apache/jena/atlas/io/IndentedWriter;
      13: ldc           #63                 // String { }
      15: invokevirtual #5                  // Method org/apache/jena/atlas/io/IndentedWriter.print:(Ljava/lang/String;)V
      18: return
      19: new           #64                 // class org/apache/jena/riot/out/SinkQuadBracedOutput
      22: dup
      23: aload_0
      24: getfield      #2                  // Field out:Lorg/apache/jena/atlas/io/IndentedWriter;
      27: aload_0
      28: getfield      #3                  // Field sCxt:Lorg/apache/jena/sparql/serializer/SerializationContext;
      31: invokespecial #65                 // Method org/apache/jena/riot/out/SinkQuadBracedOutput."<init>":(Lorg/apache/jena/atlas/io/IndentedWriter;Lorg/apache/jena/sparql/serializer/SerializationContext;)V
      34: astore_2
      35: aload_2
      36: invokevirtual #66                 // Method org/apache/jena/riot/out/SinkQuadBracedOutput.open:()V
      39: aload_1
      40: aload_2
      41: invokestatic  #58                 // Method org/apache/jena/atlas/iterator/Iter.sendToSink:(Ljava/lang/Iterable;Lorg/apache/jena/atlas/lib/Sink;)V
      44: return

  protected void output(org.apache.jena.graph.Node);
    Code:
       0: aload_1
       1: aload_0
       2: getfield      #3                  // Field sCxt:Lorg/apache/jena/sparql/serializer/SerializationContext;
       5: invokestatic  #20                 // Method org/apache/jena/sparql/util/FmtUtils.stringForNode:(Lorg/apache/jena/graph/Node;Lorg/apache/jena/sparql/serializer/SerializationContext;)Ljava/lang/String;
       8: astore_2
       9: aload_0
      10: getfield      #2                  // Field out:Lorg/apache/jena/atlas/io/IndentedWriter;
      13: aload_2
      14: invokevirtual #5                  // Method org/apache/jena/atlas/io/IndentedWriter.print:(Ljava/lang/String;)V
      17: return

  public void visit(org.apache.jena.sparql.modify.request.UpdateDeleteWhere);
    Code:
       0: aload_0
       1: getfield      #2                  // Field out:Lorg/apache/jena/atlas/io/IndentedWriter;
       4: invokevirtual #4                  // Method org/apache/jena/atlas/io/IndentedWriter.ensureStartOfLine:()V
       7: aload_0
       8: getfield      #2                  // Field out:Lorg/apache/jena/atlas/io/IndentedWriter;
      11: ldc           #67                 // String DELETE WHERE
      13: invokevirtual #68                 // Method org/apache/jena/atlas/io/IndentedWriter.println:(Ljava/lang/String;)V
      16: aload_0
      17: aload_1
      18: invokevirtual #69                 // Method org/apache/jena/sparql/modify/request/UpdateDeleteWhere.getQuads:()Ljava/util/List;
      21: invokevirtual #70                 // Method outputQuadsBraced:(Ljava/util/List;)V
      24: return

  public void visit(org.apache.jena.sparql.modify.request.UpdateModify);
    Code:
       0: aload_0
       1: getfield      #2                  // Field out:Lorg/apache/jena/atlas/io/IndentedWriter;
       4: invokevirtual #4                  // Method org/apache/jena/atlas/io/IndentedWriter.ensureStartOfLine:()V
       7: aload_1
       8: invokevirtual #71                 // Method org/apache/jena/sparql/modify/request/UpdateModify.getWithIRI:()Lorg/apache/jena/graph/Node;
      11: ifnull        31
      14: aload_0
      15: getfield      #2                  // Field out:Lorg/apache/jena/atlas/io/IndentedWriter;
      18: ldc           #72                 // String WITH
      20: invokevirtual #5                  // Method org/apache/jena/atlas/io/IndentedWriter.print:(Ljava/lang/String;)V
      23: aload_0
      24: aload_1
      25: invokevirtual #71                 // Method org/apache/jena/sparql/modify/request/UpdateModify.getWithIRI:()Lorg/apache/jena/graph/Node;
      28: invokevirtual #38                 // Method output:(Lorg/apache/jena/graph/Node;)V
      31: aload_1
      32: invokevirtual #73                 // Method org/apache/jena/sparql/modify/request/UpdateModify.hasDeleteClause:()Z
      35: ifeq          64
      38: aload_1
      39: invokevirtual #74                 // Method org/apache/jena/sparql/modify/request/UpdateModify.getDeleteQuads:()Ljava/util/List;
      42: astore_2
      43: aload_0
      44: getfield      #2                  // Field out:Lorg/apache/jena/atlas/io/IndentedWriter;
      47: invokevirtual #4                  // Method org/apache/jena/atlas/io/IndentedWriter.ensureStartOfLine:()V
      50: aload_0
      51: getfield      #2                  // Field out:Lorg/apache/jena/atlas/io/IndentedWriter;
      54: ldc           #75                 // String DELETE
      56: invokevirtual #5                  // Method org/apache/jena/atlas/io/IndentedWriter.print:(Ljava/lang/String;)V
      59: aload_0
      60: aload_2
      61: invokevirtual #70                 // Method outputQuadsBraced:(Ljava/util/List;)V
      64: aload_1
      65: invokevirtual #76                 // Method org/apache/jena/sparql/modify/request/UpdateModify.hasInsertClause:()Z
      68: ifeq          97
      71: aload_1
      72: invokevirtual #77                 // Method org/apache/jena/sparql/modify/request/UpdateModify.getInsertQuads:()Ljava/util/List;
      75: astore_2
      76: aload_0
      77: getfield      #2                  // Field out:Lorg/apache/jena/atlas/io/IndentedWriter;
      80: invokevirtual #4                  // Method org/apache/jena/atlas/io/IndentedWriter.ensureStartOfLine:()V
      83: aload_0
      84: getfield      #2                  // Field out:Lorg/apache/jena/atlas/io/IndentedWriter;
      87: ldc           #78                 // String INSERT
      89: invokevirtual #5                  // Method org/apache/jena/atlas/io/IndentedWriter.print:(Ljava/lang/String;)V
      92: aload_0
      93: aload_2
      94: invokevirtual #70                 // Method outputQuadsBraced:(Ljava/util/List;)V
      97: aload_1
      98: invokevirtual #76                 // Method org/apache/jena/sparql/modify/request/UpdateModify.hasInsertClause:()Z
     101: ifne          127
     104: aload_1
     105: invokevirtual #73                 // Method org/apache/jena/sparql/modify/request/UpdateModify.hasDeleteClause:()Z
     108: ifne          127
     111: aload_0
     112: getfield      #2                  // Field out:Lorg/apache/jena/atlas/io/IndentedWriter;
     115: invokevirtual #4                  // Method org/apache/jena/atlas/io/IndentedWriter.ensureStartOfLine:()V
     118: aload_0
     119: getfield      #2                  // Field out:Lorg/apache/jena/atlas/io/IndentedWriter;
     122: ldc           #79                 // String INSERT { }
     124: invokevirtual #68                 // Method org/apache/jena/atlas/io/IndentedWriter.println:(Ljava/lang/String;)V
     127: aload_1
     128: invokevirtual #80                 // Method org/apache/jena/sparql/modify/request/UpdateModify.getUsing:()Ljava/util/List;
     131: invokeinterface #81,  1           // InterfaceMethod java/util/List.iterator:()Ljava/util/Iterator;
     136: astore_2
     137: aload_2
     138: invokeinterface #82,  1           // InterfaceMethod java/util/Iterator.hasNext:()Z
     143: ifeq          180
     146: aload_2
     147: invokeinterface #83,  1           // InterfaceMethod java/util/Iterator.next:()Ljava/lang/Object;
     152: checkcast     #84                 // class org/apache/jena/graph/Node
     155: astore_3
     156: aload_0
     157: getfield      #2                  // Field out:Lorg/apache/jena/atlas/io/IndentedWriter;
     160: invokevirtual #4                  // Method org/apache/jena/atlas/io/IndentedWriter.ensureStartOfLine:()V
     163: aload_0
     164: getfield      #2                  // Field out:Lorg/apache/jena/atlas/io/IndentedWriter;
     167: ldc           #85                 // String USING
     169: invokevirtual #5                  // Method org/apache/jena/atlas/io/IndentedWriter.print:(Ljava/lang/String;)V
     172: aload_0
     173: aload_3
     174: invokevirtual #38                 // Method output:(Lorg/apache/jena/graph/Node;)V
     177: goto          137
     180: aload_1
     181: invokevirtual #86                 // Method org/apache/jena/sparql/modify/request/UpdateModify.getUsingNamed:()Ljava/util/List;
     184: invokeinterface #81,  1           // InterfaceMethod java/util/List.iterator:()Ljava/util/Iterator;
     189: astore_2
     190: aload_2
     191: invokeinterface #82,  1           // InterfaceMethod java/util/Iterator.hasNext:()Z
     196: ifeq          233
     199: aload_2
     200: invokeinterface #83,  1           // InterfaceMethod java/util/Iterator.next:()Ljava/lang/Object;
     205: checkcast     #84                 // class org/apache/jena/graph/Node
     208: astore_3
     209: aload_0
     210: getfield      #2                  // Field out:Lorg/apache/jena/atlas/io/IndentedWriter;
     213: invokevirtual #4                  // Method org/apache/jena/atlas/io/IndentedWriter.ensureStartOfLine:()V
     216: aload_0
     217: getfield      #2                  // Field out:Lorg/apache/jena/atlas/io/IndentedWriter;
     220: ldc           #87                 // String USING NAMED
     222: invokevirtual #5                  // Method org/apache/jena/atlas/io/IndentedWriter.print:(Ljava/lang/String;)V
     225: aload_0
     226: aload_3
     227: invokevirtual #38                 // Method output:(Lorg/apache/jena/graph/Node;)V
     230: goto          190
     233: aload_1
     234: invokevirtual #88                 // Method org/apache/jena/sparql/modify/request/UpdateModify.getWherePattern:()Lorg/apache/jena/sparql/syntax/Element;
     237: astore_2
     238: aload_0
     239: getfield      #2                  // Field out:Lorg/apache/jena/atlas/io/IndentedWriter;
     242: invokevirtual #4                  // Method org/apache/jena/atlas/io/IndentedWriter.ensureStartOfLine:()V
     245: aload_0
     246: getfield      #2                  // Field out:Lorg/apache/jena/atlas/io/IndentedWriter;
     249: ldc           #89                 // String WHERE
     251: invokevirtual #5                  // Method org/apache/jena/atlas/io/IndentedWriter.print:(Ljava/lang/String;)V
     254: aload_0
     255: getfield      #2                  // Field out:Lorg/apache/jena/atlas/io/IndentedWriter;
     258: iconst_2
     259: invokevirtual #91                 // Method org/apache/jena/atlas/io/IndentedWriter.incIndent:(I)V
     262: aload_0
     263: getfield      #2                  // Field out:Lorg/apache/jena/atlas/io/IndentedWriter;
     266: invokevirtual #92                 // Method org/apache/jena/atlas/io/IndentedWriter.newline:()V
     269: aload_2
     270: ifnull        286
     273: aload_0
     274: invokevirtual #93                 // Method prepareElementFormatter:()Lorg/apache/jena/sparql/serializer/FormatterElement;
     277: astore_3
     278: aload_3
     279: aload_2
     280: invokevirtual #94                 // Method org/apache/jena/sparql/serializer/FormatterElement.visitAsGroup:(Lorg/apache/jena/sparql/syntax/Element;)V
     283: goto          295
     286: aload_0
     287: getfield      #2                  // Field out:Lorg/apache/jena/atlas/io/IndentedWriter;
     290: ldc           #95                 // String {}
     292: invokevirtual #5                  // Method org/apache/jena/atlas/io/IndentedWriter.print:(Ljava/lang/String;)V
     295: aload_0
     296: getfield      #2                  // Field out:Lorg/apache/jena/atlas/io/IndentedWriter;
     299: iconst_2
     300: invokevirtual #96                 // Method org/apache/jena/atlas/io/IndentedWriter.decIndent:(I)V
     303: return

  protected org.apache.jena.sparql.serializer.FormatterElement prepareElementFormatter();
    Code:
       0: new           #97                 // class org/apache/jena/sparql/serializer/SerializationContext
       3: dup
       4: aload_0
       5: getfield      #3                  // Field sCxt:Lorg/apache/jena/sparql/serializer/SerializationContext;
       8: invokespecial #98                 // Method org/apache/jena/sparql/serializer/SerializationContext."<init>":(Lorg/apache/jena/sparql/serializer/SerializationContext;)V
      11: astore_1
      12: aload_1
      13: new           #99                 // class org/apache/jena/sparql/util/NodeToLabelMapBNode
      16: dup
      17: ldc           #100                // String x
      19: iconst_0
      20: invokespecial #101                // Method org/apache/jena/sparql/util/NodeToLabelMapBNode."<init>":(Ljava/lang/String;Z)V
      23: invokevirtual #102                // Method org/apache/jena/sparql/serializer/SerializationContext.setBNodeMap:(Lorg/apache/jena/sparql/util/NodeToLabelMap;)V
      26: new           #103                // class org/apache/jena/sparql/serializer/FormatterElement
      29: dup
      30: aload_0
      31: getfield      #2                  // Field out:Lorg/apache/jena/atlas/io/IndentedWriter;
      34: aload_1
      35: invokespecial #104                // Method org/apache/jena/sparql/serializer/FormatterElement."<init>":(Lorg/apache/jena/atlas/io/IndentedWriter;Lorg/apache/jena/sparql/serializer/SerializationContext;)V
      38: areturn
}
