Compiled from "CancelDelegationTokenResponsePBImpl.java"
public class org.apache.hadoop.mapreduce.v2.api.protocolrecords.impl.pb.CancelDelegationTokenResponsePBImpl extends org.apache.hadoop.yarn.api.records.impl.pb.ProtoBase<org.apache.hadoop.security.proto.SecurityProtos$CancelDelegationTokenResponseProto> implements org.apache.hadoop.mapreduce.v2.api.protocolrecords.CancelDelegationTokenResponse {
  org.apache.hadoop.security.proto.SecurityProtos$CancelDelegationTokenResponseProto proto;

  public org.apache.hadoop.mapreduce.v2.api.protocolrecords.impl.pb.CancelDelegationTokenResponsePBImpl();
    Code:
       0: aload_0
       1: invokespecial #1                  // Method org/apache/hadoop/yarn/api/records/impl/pb/ProtoBase."<init>":()V
       4: aload_0
       5: invokestatic  #2                  // Method org/apache/hadoop/security/proto/SecurityProtos$CancelDelegationTokenResponseProto.getDefaultInstance:()Lorg/apache/hadoop/security/proto/SecurityProtos$CancelDelegationTokenResponseProto;
       8: putfield      #3                  // Field proto:Lorg/apache/hadoop/security/proto/SecurityProtos$CancelDelegationTokenResponseProto;
      11: return

  public org.apache.hadoop.mapreduce.v2.api.protocolrecords.impl.pb.CancelDelegationTokenResponsePBImpl(org.apache.hadoop.security.proto.SecurityProtos$CancelDelegationTokenResponseProto);
    Code:
       0: aload_0
       1: invokespecial #1                  // Method org/apache/hadoop/yarn/api/records/impl/pb/ProtoBase."<init>":()V
       4: aload_0
       5: invokestatic  #2                  // Method org/apache/hadoop/security/proto/SecurityProtos$CancelDelegationTokenResponseProto.getDefaultInstance:()Lorg/apache/hadoop/security/proto/SecurityProtos$CancelDelegationTokenResponseProto;
       8: putfield      #3                  // Field proto:Lorg/apache/hadoop/security/proto/SecurityProtos$CancelDelegationTokenResponseProto;
      11: aload_0
      12: aload_1
      13: putfield      #3                  // Field proto:Lorg/apache/hadoop/security/proto/SecurityProtos$CancelDelegationTokenResponseProto;
      16: return

  public org.apache.hadoop.security.proto.SecurityProtos$CancelDelegationTokenResponseProto getProto();
    Code:
       0: aload_0
       1: getfield      #3                  // Field proto:Lorg/apache/hadoop/security/proto/SecurityProtos$CancelDelegationTokenResponseProto;
       4: areturn

  public com.google.protobuf.Message getProto();
    Code:
       0: aload_0
       1: invokevirtual #4                  // Method getProto:()Lorg/apache/hadoop/security/proto/SecurityProtos$CancelDelegationTokenResponseProto;
       4: areturn
}
