Compiled from "NodeRenderingHandlerWrapper.java"
class com.vladsch.flexmark.html.NodeRenderingHandlerWrapper {
  public final com.vladsch.flexmark.html.renderer.NodeRenderingHandler myRenderingHandler;

  public final com.vladsch.flexmark.html.NodeRenderingHandlerWrapper myPreviousRenderingHandler;

  public com.vladsch.flexmark.html.NodeRenderingHandlerWrapper(com.vladsch.flexmark.html.renderer.NodeRenderingHandler, com.vladsch.flexmark.html.NodeRenderingHandlerWrapper);
    Code:
       0: aload_0
       1: invokespecial #1                  // Method java/lang/Object."<init>":()V
       4: aload_0
       5: aload_1
       6: putfield      #2                  // Field myRenderingHandler:Lcom/vladsch/flexmark/html/renderer/NodeRenderingHandler;
       9: aload_0
      10: aload_2
      11: putfield      #3                  // Field myPreviousRenderingHandler:Lcom/vladsch/flexmark/html/NodeRenderingHandlerWrapper;
      14: return
}
