Compiled from "TgtPreauth.java"
public class org.apache.kerby.kerberos.kerb.client.preauth.builtin.TgtPreauth extends org.apache.kerby.kerberos.kerb.client.preauth.AbstractPreauthPlugin {
  public org.apache.kerby.kerberos.kerb.client.preauth.builtin.TgtPreauth();
    Code:
       0: aload_0
       1: new           #1                  // class org/apache/kerby/kerberos/kerb/preauth/builtin/TgtPreauthMeta
       4: dup
       5: invokespecial #2                  // Method org/apache/kerby/kerberos/kerb/preauth/builtin/TgtPreauthMeta."<init>":()V
       8: invokespecial #3                  // Method org/apache/kerby/kerberos/kerb/client/preauth/AbstractPreauthPlugin."<init>":(Lorg/apache/kerby/kerberos/kerb/preauth/PreauthPluginMeta;)V
      11: return

  public void tryFirst(org.apache.kerby.kerberos.kerb.client.request.KdcRequest, org.apache.kerby.kerberos.kerb.preauth.PluginRequestContext, org.apache.kerby.kerberos.kerb.type.pa.PaData) throws org.apache.kerby.kerberos.kerb.KrbException;
    Code:
       0: aload_3
       1: aload_0
       2: aload_1
       3: invokespecial #4                  // Method makeEntry:(Lorg/apache/kerby/kerberos/kerb/client/request/KdcRequest;)Lorg/apache/kerby/kerberos/kerb/type/pa/PaDataEntry;
       6: invokevirtual #5                  // Method org/apache/kerby/kerberos/kerb/type/pa/PaData.addElement:(Lorg/apache/kerby/asn1/type/Asn1Type;)V
       9: return

  public boolean process(org.apache.kerby.kerberos.kerb.client.request.KdcRequest, org.apache.kerby.kerberos.kerb.preauth.PluginRequestContext, org.apache.kerby.kerberos.kerb.type.pa.PaDataEntry, org.apache.kerby.kerberos.kerb.type.pa.PaData) throws org.apache.kerby.kerberos.kerb.KrbException;
    Code:
       0: aload         4
       2: aload_0
       3: aload_1
       4: invokespecial #4                  // Method makeEntry:(Lorg/apache/kerby/kerberos/kerb/client/request/KdcRequest;)Lorg/apache/kerby/kerberos/kerb/type/pa/PaDataEntry;
       7: invokevirtual #5                  // Method org/apache/kerby/kerberos/kerb/type/pa/PaData.addElement:(Lorg/apache/kerby/asn1/type/Asn1Type;)V
      10: iconst_1
      11: ireturn

  private org.apache.kerby.kerberos.kerb.type.pa.PaDataEntry makeEntry(org.apache.kerby.kerberos.kerb.client.request.KdcRequest) throws org.apache.kerby.kerberos.kerb.KrbException;
    Code:
       0: aload_1
       1: checkcast     #6                  // class org/apache/kerby/kerberos/kerb/client/request/TgsRequestWithTgt
       4: astore_2
       5: new           #7                  // class org/apache/kerby/kerberos/kerb/type/pa/PaDataEntry
       8: dup
       9: invokespecial #8                  // Method org/apache/kerby/kerberos/kerb/type/pa/PaDataEntry."<init>":()V
      12: astore_3
      13: aload_3
      14: getstatic     #9                  // Field org/apache/kerby/kerberos/kerb/type/pa/PaDataType.TGS_REQ:Lorg/apache/kerby/kerberos/kerb/type/pa/PaDataType;
      17: invokevirtual #10                 // Method org/apache/kerby/kerberos/kerb/type/pa/PaDataEntry.setPaDataType:(Lorg/apache/kerby/kerberos/kerb/type/pa/PaDataType;)V
      20: aload_3
      21: aload_2
      22: invokevirtual #11                 // Method org/apache/kerby/kerberos/kerb/client/request/TgsRequestWithTgt.getApReq:()Lorg/apache/kerby/kerberos/kerb/type/ap/ApReq;
      25: invokestatic  #12                 // Method org/apache/kerby/kerberos/kerb/KrbCodec.encode:(Lorg/apache/kerby/asn1/type/Asn1Type;)[B
      28: invokevirtual #13                 // Method org/apache/kerby/kerberos/kerb/type/pa/PaDataEntry.setPaDataValue:([B)V
      31: aload_3
      32: areturn
}
