Compiled from "LifecycleManagementStatusResponse.java"
public class org.elasticsearch.client.indexlifecycle.LifecycleManagementStatusResponse {
  private final org.elasticsearch.client.indexlifecycle.OperationMode operationMode;

  private static final java.lang.String OPERATION_MODE;

  private static final org.elasticsearch.common.xcontent.ConstructingObjectParser<org.elasticsearch.client.indexlifecycle.LifecycleManagementStatusResponse, java.lang.Void> PARSER;

  org.elasticsearch.client.indexlifecycle.LifecycleManagementStatusResponse(java.lang.String);
    Code:
       0: aload_0
       1: invokespecial #1                  // Method java/lang/Object."<init>":()V
       4: aload_0
       5: aload_1
       6: invokestatic  #2                  // Method org/elasticsearch/client/indexlifecycle/OperationMode.fromString:(Ljava/lang/String;)Lorg/elasticsearch/client/indexlifecycle/OperationMode;
       9: putfield      #3                  // Field operationMode:Lorg/elasticsearch/client/indexlifecycle/OperationMode;
      12: return

  public org.elasticsearch.client.indexlifecycle.OperationMode getOperationMode();
    Code:
       0: aload_0
       1: getfield      #3                  // Field operationMode:Lorg/elasticsearch/client/indexlifecycle/OperationMode;
       4: areturn

  public static org.elasticsearch.client.indexlifecycle.LifecycleManagementStatusResponse fromXContent(org.elasticsearch.common.xcontent.XContentParser);
    Code:
       0: getstatic     #4                  // Field PARSER:Lorg/elasticsearch/common/xcontent/ConstructingObjectParser;
       3: aload_0
       4: aconst_null
       5: invokevirtual #5                  // Method org/elasticsearch/common/xcontent/ConstructingObjectParser.apply:(Lorg/elasticsearch/common/xcontent/XContentParser;Ljava/lang/Object;)Ljava/lang/Object;
       8: checkcast     #6                  // class org/elasticsearch/client/indexlifecycle/LifecycleManagementStatusResponse
      11: areturn

  public boolean equals(java.lang.Object);
    Code:
       0: aload_0
       1: aload_1
       2: if_acmpne     7
       5: iconst_1
       6: ireturn
       7: aload_1
       8: ifnull        22
      11: aload_0
      12: invokevirtual #7                  // Method java/lang/Object.getClass:()Ljava/lang/Class;
      15: aload_1
      16: invokevirtual #7                  // Method java/lang/Object.getClass:()Ljava/lang/Class;
      19: if_acmpeq     24
      22: iconst_0
      23: ireturn
      24: aload_1
      25: checkcast     #6                  // class org/elasticsearch/client/indexlifecycle/LifecycleManagementStatusResponse
      28: astore_2
      29: aload_0
      30: getfield      #3                  // Field operationMode:Lorg/elasticsearch/client/indexlifecycle/OperationMode;
      33: aload_2
      34: getfield      #3                  // Field operationMode:Lorg/elasticsearch/client/indexlifecycle/OperationMode;
      37: if_acmpne     44
      40: iconst_1
      41: goto          45
      44: iconst_0
      45: ireturn

  public int hashCode();
    Code:
       0: iconst_1
       1: anewarray     #8                  // class java/lang/Object
       4: dup
       5: iconst_0
       6: aload_0
       7: getfield      #3                  // Field operationMode:Lorg/elasticsearch/client/indexlifecycle/OperationMode;
      10: aastore
      11: invokestatic  #9                  // Method java/util/Objects.hash:([Ljava/lang/Object;)I
      14: ireturn

  private static org.elasticsearch.client.indexlifecycle.LifecycleManagementStatusResponse lambda$static$0(java.lang.Object[]);
    Code:
       0: new           #6                  // class org/elasticsearch/client/indexlifecycle/LifecycleManagementStatusResponse
       3: dup
       4: aload_0
       5: iconst_0
       6: aaload
       7: checkcast     #10                 // class java/lang/String
      10: invokespecial #11                 // Method "<init>":(Ljava/lang/String;)V
      13: areturn

  static {};
    Code:
       0: new           #12                 // class org/elasticsearch/common/xcontent/ConstructingObjectParser
       3: dup
       4: ldc           #13                 // String operation_mode
       6: iconst_1
       7: invokedynamic #14,  0             // InvokeDynamic #0:apply:()Ljava/util/function/Function;
      12: invokespecial #15                 // Method org/elasticsearch/common/xcontent/ConstructingObjectParser."<init>":(Ljava/lang/String;ZLjava/util/function/Function;)V
      15: putstatic     #4                  // Field PARSER:Lorg/elasticsearch/common/xcontent/ConstructingObjectParser;
      18: getstatic     #4                  // Field PARSER:Lorg/elasticsearch/common/xcontent/ConstructingObjectParser;
      21: invokestatic  #16                 // Method org/elasticsearch/common/xcontent/ConstructingObjectParser.constructorArg:()Ljava/util/function/BiConsumer;
      24: new           #17                 // class org/elasticsearch/common/ParseField
      27: dup
      28: ldc           #13                 // String operation_mode
      30: iconst_0
      31: anewarray     #10                 // class java/lang/String
      34: invokespecial #18                 // Method org/elasticsearch/common/ParseField."<init>":(Ljava/lang/String;[Ljava/lang/String;)V
      37: invokevirtual #19                 // Method org/elasticsearch/common/xcontent/ConstructingObjectParser.declareString:(Ljava/util/function/BiConsumer;Lorg/elasticsearch/common/ParseField;)V
      40: return
}
