Compiled from "ShrinkAction.java"
public class org.elasticsearch.client.indexlifecycle.ShrinkAction implements org.elasticsearch.client.indexlifecycle.LifecycleAction,org.elasticsearch.common.xcontent.ToXContentObject {
  public static final java.lang.String NAME;

  private static final org.elasticsearch.common.ParseField NUMBER_OF_SHARDS_FIELD;

  private static final org.elasticsearch.common.xcontent.ConstructingObjectParser<org.elasticsearch.client.indexlifecycle.ShrinkAction, java.lang.Void> PARSER;

  private int numberOfShards;

  public static org.elasticsearch.client.indexlifecycle.ShrinkAction parse(org.elasticsearch.common.xcontent.XContentParser) throws java.io.IOException;
    Code:
       0: getstatic     #1                  // Field PARSER:Lorg/elasticsearch/common/xcontent/ConstructingObjectParser;
       3: aload_0
       4: aconst_null
       5: invokevirtual #2                  // Method org/elasticsearch/common/xcontent/ConstructingObjectParser.parse:(Lorg/elasticsearch/common/xcontent/XContentParser;Ljava/lang/Object;)Ljava/lang/Object;
       8: checkcast     #3                  // class org/elasticsearch/client/indexlifecycle/ShrinkAction
      11: areturn

  public org.elasticsearch.client.indexlifecycle.ShrinkAction(int);
    Code:
       0: aload_0
       1: invokespecial #4                  // Method java/lang/Object."<init>":()V
       4: iload_1
       5: ifgt          45
       8: new           #5                  // class java/lang/IllegalArgumentException
      11: dup
      12: new           #6                  // class java/lang/StringBuilder
      15: dup
      16: invokespecial #7                  // Method java/lang/StringBuilder."<init>":()V
      19: ldc           #8                  // String [
      21: invokevirtual #9                  // Method java/lang/StringBuilder.append:(Ljava/lang/String;)Ljava/lang/StringBuilder;
      24: getstatic     #10                 // Field NUMBER_OF_SHARDS_FIELD:Lorg/elasticsearch/common/ParseField;
      27: invokevirtual #11                 // Method org/elasticsearch/common/ParseField.getPreferredName:()Ljava/lang/String;
      30: invokevirtual #9                  // Method java/lang/StringBuilder.append:(Ljava/lang/String;)Ljava/lang/StringBuilder;
      33: ldc           #12                 // String ] must be greater than 0
      35: invokevirtual #9                  // Method java/lang/StringBuilder.append:(Ljava/lang/String;)Ljava/lang/StringBuilder;
      38: invokevirtual #13                 // Method java/lang/StringBuilder.toString:()Ljava/lang/String;
      41: invokespecial #14                 // Method java/lang/IllegalArgumentException."<init>":(Ljava/lang/String;)V
      44: athrow
      45: aload_0
      46: iload_1
      47: putfield      #15                 // Field numberOfShards:I
      50: return

  int getNumberOfShards();
    Code:
       0: aload_0
       1: getfield      #15                 // Field numberOfShards:I
       4: ireturn

  public java.lang.String getName();
    Code:
       0: ldc           #16                 // String shrink
       2: areturn

  public org.elasticsearch.common.xcontent.XContentBuilder toXContent(org.elasticsearch.common.xcontent.XContentBuilder, org.elasticsearch.common.xcontent.ToXContent$Params) throws java.io.IOException;
    Code:
       0: aload_1
       1: invokevirtual #17                 // Method org/elasticsearch/common/xcontent/XContentBuilder.startObject:()Lorg/elasticsearch/common/xcontent/XContentBuilder;
       4: pop
       5: aload_1
       6: getstatic     #10                 // Field NUMBER_OF_SHARDS_FIELD:Lorg/elasticsearch/common/ParseField;
       9: invokevirtual #11                 // Method org/elasticsearch/common/ParseField.getPreferredName:()Ljava/lang/String;
      12: aload_0
      13: getfield      #15                 // Field numberOfShards:I
      16: invokevirtual #18                 // Method org/elasticsearch/common/xcontent/XContentBuilder.field:(Ljava/lang/String;I)Lorg/elasticsearch/common/xcontent/XContentBuilder;
      19: pop
      20: aload_1
      21: invokevirtual #19                 // Method org/elasticsearch/common/xcontent/XContentBuilder.endObject:()Lorg/elasticsearch/common/xcontent/XContentBuilder;
      24: pop
      25: aload_1
      26: areturn

  public boolean equals(java.lang.Object);
    Code:
       0: aload_0
       1: aload_1
       2: if_acmpne     7
       5: iconst_1
       6: ireturn
       7: aload_1
       8: ifnull        22
      11: aload_0
      12: invokevirtual #20                 // Method java/lang/Object.getClass:()Ljava/lang/Class;
      15: aload_1
      16: invokevirtual #20                 // Method java/lang/Object.getClass:()Ljava/lang/Class;
      19: if_acmpeq     24
      22: iconst_0
      23: ireturn
      24: aload_1
      25: checkcast     #3                  // class org/elasticsearch/client/indexlifecycle/ShrinkAction
      28: astore_2
      29: aload_0
      30: getfield      #15                 // Field numberOfShards:I
      33: invokestatic  #21                 // Method java/lang/Integer.valueOf:(I)Ljava/lang/Integer;
      36: aload_2
      37: getfield      #15                 // Field numberOfShards:I
      40: invokestatic  #21                 // Method java/lang/Integer.valueOf:(I)Ljava/lang/Integer;
      43: invokestatic  #22                 // Method java/util/Objects.equals:(Ljava/lang/Object;Ljava/lang/Object;)Z
      46: ireturn

  public int hashCode();
    Code:
       0: iconst_1
       1: anewarray     #23                 // class java/lang/Object
       4: dup
       5: iconst_0
       6: aload_0
       7: getfield      #15                 // Field numberOfShards:I
      10: invokestatic  #21                 // Method java/lang/Integer.valueOf:(I)Ljava/lang/Integer;
      13: aastore
      14: invokestatic  #24                 // Method java/util/Objects.hash:([Ljava/lang/Object;)I
      17: ireturn

  public java.lang.String toString();
    Code:
       0: aload_0
       1: invokestatic  #25                 // Method org/elasticsearch/common/Strings.toString:(Lorg/elasticsearch/common/xcontent/ToXContent;)Ljava/lang/String;
       4: areturn

  private static org.elasticsearch.client.indexlifecycle.ShrinkAction lambda$static$0(java.lang.Object[]);
    Code:
       0: new           #3                  // class org/elasticsearch/client/indexlifecycle/ShrinkAction
       3: dup
       4: aload_0
       5: iconst_0
       6: aaload
       7: checkcast     #26                 // class java/lang/Integer
      10: invokevirtual #27                 // Method java/lang/Integer.intValue:()I
      13: invokespecial #28                 // Method "<init>":(I)V
      16: areturn

  static {};
    Code:
       0: new           #29                 // class org/elasticsearch/common/ParseField
       3: dup
       4: ldc           #30                 // String number_of_shards
       6: iconst_0
       7: anewarray     #31                 // class java/lang/String
      10: invokespecial #32                 // Method org/elasticsearch/common/ParseField."<init>":(Ljava/lang/String;[Ljava/lang/String;)V
      13: putstatic     #10                 // Field NUMBER_OF_SHARDS_FIELD:Lorg/elasticsearch/common/ParseField;
      16: new           #33                 // class org/elasticsearch/common/xcontent/ConstructingObjectParser
      19: dup
      20: ldc           #16                 // String shrink
      22: iconst_1
      23: invokedynamic #34,  0             // InvokeDynamic #0:apply:()Ljava/util/function/Function;
      28: invokespecial #35                 // Method org/elasticsearch/common/xcontent/ConstructingObjectParser."<init>":(Ljava/lang/String;ZLjava/util/function/Function;)V
      31: putstatic     #1                  // Field PARSER:Lorg/elasticsearch/common/xcontent/ConstructingObjectParser;
      34: getstatic     #1                  // Field PARSER:Lorg/elasticsearch/common/xcontent/ConstructingObjectParser;
      37: invokestatic  #36                 // Method org/elasticsearch/common/xcontent/ConstructingObjectParser.constructorArg:()Ljava/util/function/BiConsumer;
      40: getstatic     #10                 // Field NUMBER_OF_SHARDS_FIELD:Lorg/elasticsearch/common/ParseField;
      43: invokevirtual #37                 // Method org/elasticsearch/common/xcontent/ConstructingObjectParser.declareInt:(Ljava/util/function/BiConsumer;Lorg/elasticsearch/common/ParseField;)V
      46: return
}
