Compiled from "CallableStatementCreatorFactory.java"
class org.springframework.jdbc.core.CallableStatementCreatorFactory$CallableStatementCreatorImpl implements org.springframework.jdbc.core.CallableStatementCreator,org.springframework.jdbc.core.SqlProvider,org.springframework.jdbc.core.ParameterDisposer {
  private org.springframework.jdbc.core.ParameterMapper inParameterMapper;

  private java.util.Map<java.lang.String, ?> inParameters;

  final org.springframework.jdbc.core.CallableStatementCreatorFactory this$0;

  public org.springframework.jdbc.core.CallableStatementCreatorFactory$CallableStatementCreatorImpl(org.springframework.jdbc.core.CallableStatementCreatorFactory, org.springframework.jdbc.core.ParameterMapper);
    Code:
       0: aload_0
       1: aload_1
       2: putfield      #1                  // Field this$0:Lorg/springframework/jdbc/core/CallableStatementCreatorFactory;
       5: aload_0
       6: invokespecial #2                  // Method java/lang/Object."<init>":()V
       9: aload_0
      10: aload_2
      11: putfield      #3                  // Field inParameterMapper:Lorg/springframework/jdbc/core/ParameterMapper;
      14: return

  public org.springframework.jdbc.core.CallableStatementCreatorFactory$CallableStatementCreatorImpl(java.util.Map<java.lang.String, ?>);
    Code:
       0: aload_0
       1: aload_1
       2: putfield      #1                  // Field this$0:Lorg/springframework/jdbc/core/CallableStatementCreatorFactory;
       5: aload_0
       6: invokespecial #2                  // Method java/lang/Object."<init>":()V
       9: aload_0
      10: aload_2
      11: putfield      #4                  // Field inParameters:Ljava/util/Map;
      14: return

  public java.sql.CallableStatement createCallableStatement(java.sql.Connection) throws java.sql.SQLException;
    Code:
       0: aload_0
       1: getfield      #3                  // Field inParameterMapper:Lorg/springframework/jdbc/core/ParameterMapper;
       4: ifnull        24
       7: aload_0
       8: aload_0
       9: getfield      #3                  // Field inParameterMapper:Lorg/springframework/jdbc/core/ParameterMapper;
      12: aload_1
      13: invokeinterface #5,  2            // InterfaceMethod org/springframework/jdbc/core/ParameterMapper.createMap:(Ljava/sql/Connection;)Ljava/util/Map;
      18: putfield      #4                  // Field inParameters:Ljava/util/Map;
      21: goto          41
      24: aload_0
      25: getfield      #4                  // Field inParameters:Ljava/util/Map;
      28: ifnonnull     41
      31: new           #6                  // class org/springframework/dao/InvalidDataAccessApiUsageException
      34: dup
      35: ldc           #7                  // String A ParameterMapper or a Map of parameters must be provided
      37: invokespecial #8                  // Method org/springframework/dao/InvalidDataAccessApiUsageException."<init>":(Ljava/lang/String;)V
      40: athrow
      41: aconst_null
      42: astore_2
      43: aload_0
      44: getfield      #1                  // Field this$0:Lorg/springframework/jdbc/core/CallableStatementCreatorFactory;
      47: invokestatic  #9                  // Method org/springframework/jdbc/core/CallableStatementCreatorFactory.access$000:(Lorg/springframework/jdbc/core/CallableStatementCreatorFactory;)I
      50: sipush        1003
      53: if_icmpne     83
      56: aload_0
      57: getfield      #1                  // Field this$0:Lorg/springframework/jdbc/core/CallableStatementCreatorFactory;
      60: invokestatic  #11                 // Method org/springframework/jdbc/core/CallableStatementCreatorFactory.access$100:(Lorg/springframework/jdbc/core/CallableStatementCreatorFactory;)Z
      63: ifne          83
      66: aload_1
      67: aload_0
      68: getfield      #1                  // Field this$0:Lorg/springframework/jdbc/core/CallableStatementCreatorFactory;
      71: invokestatic  #12                 // Method org/springframework/jdbc/core/CallableStatementCreatorFactory.access$200:(Lorg/springframework/jdbc/core/CallableStatementCreatorFactory;)Ljava/lang/String;
      74: invokeinterface #13,  2           // InterfaceMethod java/sql/Connection.prepareCall:(Ljava/lang/String;)Ljava/sql/CallableStatement;
      79: astore_2
      80: goto          123
      83: aload_1
      84: aload_0
      85: getfield      #1                  // Field this$0:Lorg/springframework/jdbc/core/CallableStatementCreatorFactory;
      88: invokestatic  #12                 // Method org/springframework/jdbc/core/CallableStatementCreatorFactory.access$200:(Lorg/springframework/jdbc/core/CallableStatementCreatorFactory;)Ljava/lang/String;
      91: aload_0
      92: getfield      #1                  // Field this$0:Lorg/springframework/jdbc/core/CallableStatementCreatorFactory;
      95: invokestatic  #9                  // Method org/springframework/jdbc/core/CallableStatementCreatorFactory.access$000:(Lorg/springframework/jdbc/core/CallableStatementCreatorFactory;)I
      98: aload_0
      99: getfield      #1                  // Field this$0:Lorg/springframework/jdbc/core/CallableStatementCreatorFactory;
     102: invokestatic  #11                 // Method org/springframework/jdbc/core/CallableStatementCreatorFactory.access$100:(Lorg/springframework/jdbc/core/CallableStatementCreatorFactory;)Z
     105: ifeq          114
     108: sipush        1008
     111: goto          117
     114: sipush        1007
     117: invokeinterface #14,  4           // InterfaceMethod java/sql/Connection.prepareCall:(Ljava/lang/String;II)Ljava/sql/CallableStatement;
     122: astore_2
     123: iconst_1
     124: istore_3
     125: aload_0
     126: getfield      #1                  // Field this$0:Lorg/springframework/jdbc/core/CallableStatementCreatorFactory;
     129: invokestatic  #15                 // Method org/springframework/jdbc/core/CallableStatementCreatorFactory.access$300:(Lorg/springframework/jdbc/core/CallableStatementCreatorFactory;)Ljava/util/List;
     132: invokeinterface #16,  1           // InterfaceMethod java/util/List.iterator:()Ljava/util/Iterator;
     137: astore        4
     139: aload         4
     141: invokeinterface #17,  1           // InterfaceMethod java/util/Iterator.hasNext:()Z
     146: ifeq          360
     149: aload         4
     151: invokeinterface #18,  1           // InterfaceMethod java/util/Iterator.next:()Ljava/lang/Object;
     156: checkcast     #19                 // class org/springframework/jdbc/core/SqlParameter
     159: astore        5
     161: aload         5
     163: invokevirtual #20                 // Method org/springframework/jdbc/core/SqlParameter.isResultsParameter:()Z
     166: ifne          357
     169: aload_0
     170: getfield      #4                  // Field inParameters:Ljava/util/Map;
     173: aload         5
     175: invokevirtual #21                 // Method org/springframework/jdbc/core/SqlParameter.getName:()Ljava/lang/String;
     178: invokeinterface #22,  2           // InterfaceMethod java/util/Map.get:(Ljava/lang/Object;)Ljava/lang/Object;
     183: astore        6
     185: aload         5
     187: instanceof    #23                 // class org/springframework/jdbc/core/ResultSetSupportingSqlParameter
     190: ifeq          292
     193: aload         5
     195: instanceof    #24                 // class org/springframework/jdbc/core/SqlOutParameter
     198: ifeq          354
     201: aload         5
     203: invokevirtual #25                 // Method org/springframework/jdbc/core/SqlParameter.getTypeName:()Ljava/lang/String;
     206: ifnull        229
     209: aload_2
     210: iload_3
     211: aload         5
     213: invokevirtual #26                 // Method org/springframework/jdbc/core/SqlParameter.getSqlType:()I
     216: aload         5
     218: invokevirtual #25                 // Method org/springframework/jdbc/core/SqlParameter.getTypeName:()Ljava/lang/String;
     221: invokeinterface #27,  4           // InterfaceMethod java/sql/CallableStatement.registerOutParameter:(IILjava/lang/String;)V
     226: goto          272
     229: aload         5
     231: invokevirtual #28                 // Method org/springframework/jdbc/core/SqlParameter.getScale:()Ljava/lang/Integer;
     234: ifnull        260
     237: aload_2
     238: iload_3
     239: aload         5
     241: invokevirtual #26                 // Method org/springframework/jdbc/core/SqlParameter.getSqlType:()I
     244: aload         5
     246: invokevirtual #28                 // Method org/springframework/jdbc/core/SqlParameter.getScale:()Ljava/lang/Integer;
     249: invokevirtual #29                 // Method java/lang/Integer.intValue:()I
     252: invokeinterface #30,  4           // InterfaceMethod java/sql/CallableStatement.registerOutParameter:(III)V
     257: goto          272
     260: aload_2
     261: iload_3
     262: aload         5
     264: invokevirtual #26                 // Method org/springframework/jdbc/core/SqlParameter.getSqlType:()I
     267: invokeinterface #31,  3           // InterfaceMethod java/sql/CallableStatement.registerOutParameter:(II)V
     272: aload         5
     274: invokevirtual #32                 // Method org/springframework/jdbc/core/SqlParameter.isInputValueProvided:()Z
     277: ifeq          354
     280: aload_2
     281: iload_3
     282: aload         5
     284: aload         6
     286: invokestatic  #33                 // Method org/springframework/jdbc/core/StatementCreatorUtils.setParameterValue:(Ljava/sql/PreparedStatement;ILorg/springframework/jdbc/core/SqlParameter;Ljava/lang/Object;)V
     289: goto          354
     292: aload_0
     293: getfield      #4                  // Field inParameters:Ljava/util/Map;
     296: aload         5
     298: invokevirtual #21                 // Method org/springframework/jdbc/core/SqlParameter.getName:()Ljava/lang/String;
     301: invokeinterface #34,  2           // InterfaceMethod java/util/Map.containsKey:(Ljava/lang/Object;)Z
     306: ifne          345
     309: new           #6                  // class org/springframework/dao/InvalidDataAccessApiUsageException
     312: dup
     313: new           #35                 // class java/lang/StringBuilder
     316: dup
     317: invokespecial #36                 // Method java/lang/StringBuilder."<init>":()V
     320: ldc           #37                 // String Required input parameter \'
     322: invokevirtual #38                 // Method java/lang/StringBuilder.append:(Ljava/lang/String;)Ljava/lang/StringBuilder;
     325: aload         5
     327: invokevirtual #21                 // Method org/springframework/jdbc/core/SqlParameter.getName:()Ljava/lang/String;
     330: invokevirtual #38                 // Method java/lang/StringBuilder.append:(Ljava/lang/String;)Ljava/lang/StringBuilder;
     333: ldc           #39                 // String \' is missing
     335: invokevirtual #38                 // Method java/lang/StringBuilder.append:(Ljava/lang/String;)Ljava/lang/StringBuilder;
     338: invokevirtual #40                 // Method java/lang/StringBuilder.toString:()Ljava/lang/String;
     341: invokespecial #8                  // Method org/springframework/dao/InvalidDataAccessApiUsageException."<init>":(Ljava/lang/String;)V
     344: athrow
     345: aload_2
     346: iload_3
     347: aload         5
     349: aload         6
     351: invokestatic  #33                 // Method org/springframework/jdbc/core/StatementCreatorUtils.setParameterValue:(Ljava/sql/PreparedStatement;ILorg/springframework/jdbc/core/SqlParameter;Ljava/lang/Object;)V
     354: iinc          3, 1
     357: goto          139
     360: aload_2
     361: areturn

  public java.lang.String getSql();
    Code:
       0: aload_0
       1: getfield      #1                  // Field this$0:Lorg/springframework/jdbc/core/CallableStatementCreatorFactory;
       4: invokestatic  #12                 // Method org/springframework/jdbc/core/CallableStatementCreatorFactory.access$200:(Lorg/springframework/jdbc/core/CallableStatementCreatorFactory;)Ljava/lang/String;
       7: areturn

  public void cleanupParameters();
    Code:
       0: aload_0
       1: getfield      #4                  // Field inParameters:Ljava/util/Map;
       4: ifnull        19
       7: aload_0
       8: getfield      #4                  // Field inParameters:Ljava/util/Map;
      11: invokeinterface #41,  1           // InterfaceMethod java/util/Map.values:()Ljava/util/Collection;
      16: invokestatic  #42                 // Method org/springframework/jdbc/core/StatementCreatorUtils.cleanupParameters:(Ljava/util/Collection;)V
      19: return

  public java.lang.String toString();
    Code:
       0: new           #35                 // class java/lang/StringBuilder
       3: dup
       4: invokespecial #36                 // Method java/lang/StringBuilder."<init>":()V
       7: ldc           #43                 // String CallableStatementCreator: sql=[
       9: invokevirtual #38                 // Method java/lang/StringBuilder.append:(Ljava/lang/String;)Ljava/lang/StringBuilder;
      12: aload_0
      13: getfield      #1                  // Field this$0:Lorg/springframework/jdbc/core/CallableStatementCreatorFactory;
      16: invokestatic  #12                 // Method org/springframework/jdbc/core/CallableStatementCreatorFactory.access$200:(Lorg/springframework/jdbc/core/CallableStatementCreatorFactory;)Ljava/lang/String;
      19: invokevirtual #38                 // Method java/lang/StringBuilder.append:(Ljava/lang/String;)Ljava/lang/StringBuilder;
      22: ldc           #44                 // String ]; parameters=
      24: invokevirtual #38                 // Method java/lang/StringBuilder.append:(Ljava/lang/String;)Ljava/lang/StringBuilder;
      27: aload_0
      28: getfield      #4                  // Field inParameters:Ljava/util/Map;
      31: invokevirtual #45                 // Method java/lang/StringBuilder.append:(Ljava/lang/Object;)Ljava/lang/StringBuilder;
      34: invokevirtual #40                 // Method java/lang/StringBuilder.toString:()Ljava/lang/String;
      37: areturn
}
