Compiled from "SessionListenerBridge.java"
class io.undertow.servlet.core.SessionListenerBridge$1 implements io.undertow.servlet.api.ThreadSetupHandler$Action<java.lang.Void, io.undertow.server.session.Session> {
  final io.undertow.servlet.core.SessionListenerBridge this$0;

  io.undertow.servlet.core.SessionListenerBridge$1(io.undertow.servlet.core.SessionListenerBridge);
    Code:
       0: aload_0
       1: aload_1
       2: putfield      #1                  // Field this$0:Lio/undertow/servlet/core/SessionListenerBridge;
       5: aload_0
       6: invokespecial #2                  // Method java/lang/Object."<init>":()V
       9: return

  public java.lang.Void call(io.undertow.server.HttpServerExchange, io.undertow.server.session.Session) throws jakarta.servlet.ServletException;
    Code:
       0: aload_0
       1: getfield      #1                  // Field this$0:Lio/undertow/servlet/core/SessionListenerBridge;
       4: aload_2
       5: invokevirtual #3                  // Method io/undertow/servlet/core/SessionListenerBridge.doDestroy:(Lio/undertow/server/session/Session;)V
       8: aconst_null
       9: areturn

  public java.lang.Object call(io.undertow.server.HttpServerExchange, java.lang.Object) throws java.lang.Exception;
    Code:
       0: aload_0
       1: aload_1
       2: aload_2
       3: checkcast     #4                  // class io/undertow/server/session/Session
       6: invokevirtual #5                  // Method call:(Lio/undertow/server/HttpServerExchange;Lio/undertow/server/session/Session;)Ljava/lang/Void;
       9: areturn
}
