Compiled from "ConcatByteIterator.java"
final class org.wildfly.common.iteration.ConcatByteIterator extends org.wildfly.common.iteration.ByteIterator {
  private final org.wildfly.common.iteration.ByteIterator[] iterators;

  private long index;

  org.wildfly.common.iteration.ConcatByteIterator(org.wildfly.common.iteration.ByteIterator[]);
    Code:
       0: aload_0
       1: invokespecial #1                  // Method org/wildfly/common/iteration/ByteIterator."<init>":()V
       4: aload_0
       5: lconst_0
       6: putfield      #2                  // Field index:J
       9: aload_0
      10: aload_1
      11: putfield      #3                  // Field iterators:[Lorg/wildfly/common/iteration/ByteIterator;
      14: return

  private int seekNext();
    Code:
       0: iconst_0
       1: istore_1
       2: iload_1
       3: aload_0
       4: getfield      #3                  // Field iterators:[Lorg/wildfly/common/iteration/ByteIterator;
       7: arraylength
       8: if_icmpge     31
      11: aload_0
      12: getfield      #3                  // Field iterators:[Lorg/wildfly/common/iteration/ByteIterator;
      15: iload_1
      16: aaload
      17: invokevirtual #4                  // Method org/wildfly/common/iteration/ByteIterator.hasNext:()Z
      20: ifeq          25
      23: iload_1
      24: ireturn
      25: iinc          1, 1
      28: goto          2
      31: iconst_m1
      32: ireturn

  private int seekPrevious();
    Code:
       0: aload_0
       1: getfield      #3                  // Field iterators:[Lorg/wildfly/common/iteration/ByteIterator;
       4: arraylength
       5: iconst_1
       6: isub
       7: istore_1
       8: iload_1
       9: iflt          32
      12: aload_0
      13: getfield      #3                  // Field iterators:[Lorg/wildfly/common/iteration/ByteIterator;
      16: iload_1
      17: aaload
      18: invokevirtual #5                  // Method org/wildfly/common/iteration/ByteIterator.hasPrevious:()Z
      21: ifeq          26
      24: iload_1
      25: ireturn
      26: iinc          1, -1
      29: goto          8
      32: iconst_m1
      33: ireturn

  public boolean hasNext();
    Code:
       0: aload_0
       1: invokespecial #6                  // Method seekNext:()I
       4: iconst_m1
       5: if_icmpeq     12
       8: iconst_1
       9: goto          13
      12: iconst_0
      13: ireturn

  public boolean hasPrevious();
    Code:
       0: aload_0
       1: invokespecial #7                  // Method seekPrevious:()I
       4: iconst_m1
       5: if_icmpeq     12
       8: iconst_1
       9: goto          13
      12: iconst_0
      13: ireturn

  public int next() throws java.util.NoSuchElementException;
    Code:
       0: aload_0
       1: invokespecial #6                  // Method seekNext:()I
       4: istore_1
       5: iload_1
       6: iconst_m1
       7: if_icmpne     18
      10: new           #8                  // class java/util/NoSuchElementException
      13: dup
      14: invokespecial #9                  // Method java/util/NoSuchElementException."<init>":()V
      17: athrow
      18: aload_0
      19: getfield      #3                  // Field iterators:[Lorg/wildfly/common/iteration/ByteIterator;
      22: iload_1
      23: aaload
      24: invokevirtual #10                 // Method org/wildfly/common/iteration/ByteIterator.next:()I
      27: istore_2
      28: aload_0
      29: dup
      30: getfield      #2                  // Field index:J
      33: lconst_1
      34: ladd
      35: putfield      #2                  // Field index:J
      38: iload_2
      39: ireturn

  public int peekNext() throws java.util.NoSuchElementException;
    Code:
       0: aload_0
       1: invokespecial #6                  // Method seekNext:()I
       4: istore_1
       5: iload_1
       6: iconst_m1
       7: if_icmpne     18
      10: new           #8                  // class java/util/NoSuchElementException
      13: dup
      14: invokespecial #9                  // Method java/util/NoSuchElementException."<init>":()V
      17: athrow
      18: aload_0
      19: getfield      #3                  // Field iterators:[Lorg/wildfly/common/iteration/ByteIterator;
      22: iload_1
      23: aaload
      24: invokevirtual #11                 // Method org/wildfly/common/iteration/ByteIterator.peekNext:()I
      27: ireturn

  public int previous() throws java.util.NoSuchElementException;
    Code:
       0: aload_0
       1: invokespecial #7                  // Method seekPrevious:()I
       4: istore_1
       5: iload_1
       6: iconst_m1
       7: if_icmpne     18
      10: new           #8                  // class java/util/NoSuchElementException
      13: dup
      14: invokespecial #9                  // Method java/util/NoSuchElementException."<init>":()V
      17: athrow
      18: aload_0
      19: getfield      #3                  // Field iterators:[Lorg/wildfly/common/iteration/ByteIterator;
      22: iload_1
      23: aaload
      24: invokevirtual #12                 // Method org/wildfly/common/iteration/ByteIterator.previous:()I
      27: istore_2
      28: aload_0
      29: dup
      30: getfield      #2                  // Field index:J
      33: lconst_1
      34: lsub
      35: putfield      #2                  // Field index:J
      38: iload_2
      39: ireturn

  public int peekPrevious() throws java.util.NoSuchElementException;
    Code:
       0: aload_0
       1: invokespecial #7                  // Method seekPrevious:()I
       4: istore_1
       5: iload_1
       6: iconst_m1
       7: if_icmpne     18
      10: new           #8                  // class java/util/NoSuchElementException
      13: dup
      14: invokespecial #9                  // Method java/util/NoSuchElementException."<init>":()V
      17: athrow
      18: aload_0
      19: getfield      #3                  // Field iterators:[Lorg/wildfly/common/iteration/ByteIterator;
      22: iload_1
      23: aaload
      24: invokevirtual #13                 // Method org/wildfly/common/iteration/ByteIterator.peekPrevious:()I
      27: ireturn

  public long getIndex();
    Code:
       0: aload_0
       1: getfield      #2                  // Field index:J
       4: lreturn
}
