Compiled from "InterleavedByteArrayIterator.java"
final class org.wildfly.common.iteration.InterleavedByteArrayIterator extends org.wildfly.common.iteration.ByteIterator {
  private final int len;

  private final byte[] bytes;

  private final int offs;

  private final int[] interleave;

  private int idx;

  org.wildfly.common.iteration.InterleavedByteArrayIterator(int, byte[], int, int[]);
    Code:
       0: aload_0
       1: invokespecial #1                  // Method org/wildfly/common/iteration/ByteIterator."<init>":()V
       4: aload_0
       5: iload_1
       6: putfield      #2                  // Field len:I
       9: aload_0
      10: aload_2
      11: putfield      #3                  // Field bytes:[B
      14: aload_0
      15: iload_3
      16: putfield      #4                  // Field offs:I
      19: aload_0
      20: aload         4
      22: putfield      #5                  // Field interleave:[I
      25: aload_0
      26: iconst_0
      27: putfield      #6                  // Field idx:I
      30: return

  public boolean hasNext();
    Code:
       0: aload_0
       1: getfield      #6                  // Field idx:I
       4: aload_0
       5: getfield      #2                  // Field len:I
       8: if_icmpge     15
      11: iconst_1
      12: goto          16
      15: iconst_0
      16: ireturn

  public boolean hasPrevious();
    Code:
       0: aload_0
       1: getfield      #6                  // Field idx:I
       4: ifle          11
       7: iconst_1
       8: goto          12
      11: iconst_0
      12: ireturn

  public int next();
    Code:
       0: aload_0
       1: invokevirtual #7                  // Method hasNext:()Z
       4: ifne          15
       7: new           #8                  // class java/util/NoSuchElementException
      10: dup
      11: invokespecial #9                  // Method java/util/NoSuchElementException."<init>":()V
      14: athrow
      15: aload_0
      16: getfield      #3                  // Field bytes:[B
      19: aload_0
      20: getfield      #4                  // Field offs:I
      23: aload_0
      24: getfield      #5                  // Field interleave:[I
      27: aload_0
      28: dup
      29: getfield      #6                  // Field idx:I
      32: dup_x1
      33: iconst_1
      34: iadd
      35: putfield      #6                  // Field idx:I
      38: iaload
      39: iadd
      40: baload
      41: sipush        255
      44: iand
      45: ireturn

  public int previous();
    Code:
       0: aload_0
       1: invokevirtual #10                 // Method hasPrevious:()Z
       4: ifne          15
       7: new           #8                  // class java/util/NoSuchElementException
      10: dup
      11: invokespecial #9                  // Method java/util/NoSuchElementException."<init>":()V
      14: athrow
      15: aload_0
      16: getfield      #3                  // Field bytes:[B
      19: aload_0
      20: getfield      #4                  // Field offs:I
      23: aload_0
      24: getfield      #5                  // Field interleave:[I
      27: aload_0
      28: dup
      29: getfield      #6                  // Field idx:I
      32: iconst_1
      33: isub
      34: dup_x1
      35: putfield      #6                  // Field idx:I
      38: iaload
      39: iadd
      40: baload
      41: sipush        255
      44: iand
      45: ireturn

  public int peekNext() throws java.util.NoSuchElementException;
    Code:
       0: aload_0
       1: invokevirtual #7                  // Method hasNext:()Z
       4: ifne          15
       7: new           #8                  // class java/util/NoSuchElementException
      10: dup
      11: invokespecial #9                  // Method java/util/NoSuchElementException."<init>":()V
      14: athrow
      15: aload_0
      16: getfield      #3                  // Field bytes:[B
      19: aload_0
      20: getfield      #4                  // Field offs:I
      23: aload_0
      24: getfield      #5                  // Field interleave:[I
      27: aload_0
      28: getfield      #6                  // Field idx:I
      31: iaload
      32: iadd
      33: baload
      34: sipush        255
      37: iand
      38: ireturn

  public int peekPrevious() throws java.util.NoSuchElementException;
    Code:
       0: aload_0
       1: invokevirtual #10                 // Method hasPrevious:()Z
       4: ifne          15
       7: new           #8                  // class java/util/NoSuchElementException
      10: dup
      11: invokespecial #9                  // Method java/util/NoSuchElementException."<init>":()V
      14: athrow
      15: aload_0
      16: getfield      #3                  // Field bytes:[B
      19: aload_0
      20: getfield      #4                  // Field offs:I
      23: aload_0
      24: getfield      #5                  // Field interleave:[I
      27: aload_0
      28: getfield      #6                  // Field idx:I
      31: iconst_1
      32: isub
      33: iaload
      34: iadd
      35: baload
      36: sipush        255
      39: iand
      40: ireturn

  public long getIndex();
    Code:
       0: aload_0
       1: getfield      #6                  // Field idx:I
       4: i2l
       5: lreturn
}
