Compiled from "AnnotationConfiguration.java"
public class org.eclipse.jetty.ee10.osgi.annotations.AnnotationConfiguration$BundleParserTask extends org.eclipse.jetty.ee10.annotations.AnnotationConfiguration$ParserTask {
  final org.eclipse.jetty.ee10.osgi.annotations.AnnotationConfiguration this$0;

  public org.eclipse.jetty.ee10.osgi.annotations.AnnotationConfiguration$BundleParserTask(org.eclipse.jetty.ee10.osgi.annotations.AnnotationParser, java.util.Set<? extends org.eclipse.jetty.ee10.annotations.AnnotationParser$Handler>, org.eclipse.jetty.util.resource.Resource);
    Code:
       0: aload_0
       1: aload_1
       2: putfield      #1                  // Field this$0:Lorg/eclipse/jetty/ee10/osgi/annotations/AnnotationConfiguration;
       5: aload_0
       6: aload_1
       7: aload_2
       8: aload_3
       9: aload         4
      11: invokespecial #7                  // Method org/eclipse/jetty/ee10/annotations/AnnotationConfiguration$ParserTask."<init>":(Lorg/eclipse/jetty/ee10/annotations/AnnotationConfiguration;Lorg/eclipse/jetty/ee10/annotations/AnnotationParser;Ljava/util/Set;Lorg/eclipse/jetty/util/resource/Resource;)V
      14: return

  public java.lang.Void call() throws java.lang.Exception;
    Code:
       0: aload_0
       1: getfield      #13                 // Field _parser:Lorg/eclipse/jetty/ee10/annotations/AnnotationParser;
       4: ifnull        61
       7: aload_0
       8: getfield      #13                 // Field _parser:Lorg/eclipse/jetty/ee10/annotations/AnnotationParser;
      11: checkcast     #17                 // class org/eclipse/jetty/ee10/osgi/annotations/AnnotationParser
      14: astore_1
      15: aload_1
      16: aload_0
      17: getfield      #19                 // Field _resource:Lorg/eclipse/jetty/util/resource/Resource;
      20: invokevirtual #23                 // Method org/eclipse/jetty/ee10/osgi/annotations/AnnotationParser.getBundle:(Lorg/eclipse/jetty/util/resource/Resource;)Lorg/osgi/framework/Bundle;
      23: astore_2
      24: aload_0
      25: getfield      #27                 // Field _stat:Lorg/eclipse/jetty/ee10/annotations/AnnotationConfiguration$TimeStatistic;
      28: ifnull        38
      31: aload_0
      32: getfield      #27                 // Field _stat:Lorg/eclipse/jetty/ee10/annotations/AnnotationConfiguration$TimeStatistic;
      35: invokevirtual #31                 // Method org/eclipse/jetty/ee10/annotations/AnnotationConfiguration$TimeStatistic.start:()V
      38: aload_1
      39: aload_0
      40: getfield      #37                 // Field _handlers:Ljava/util/Set;
      43: aload_2
      44: invokevirtual #41                 // Method org/eclipse/jetty/ee10/osgi/annotations/AnnotationParser.parse:(Ljava/util/Set;Lorg/osgi/framework/Bundle;)V
      47: aload_0
      48: getfield      #27                 // Field _stat:Lorg/eclipse/jetty/ee10/annotations/AnnotationConfiguration$TimeStatistic;
      51: ifnull        61
      54: aload_0
      55: getfield      #27                 // Field _stat:Lorg/eclipse/jetty/ee10/annotations/AnnotationConfiguration$TimeStatistic;
      58: invokevirtual #45                 // Method org/eclipse/jetty/ee10/annotations/AnnotationConfiguration$TimeStatistic.end:()V
      61: aconst_null
      62: areturn

  public java.lang.Object call() throws java.lang.Exception;
    Code:
       0: aload_0
       1: invokevirtual #48                 // Method call:()Ljava/lang/Void;
       4: areturn
}
