Compiled from "AutoValue_NodeSummaryList.java"
final class org.graylog2.rest.models.system.cluster.responses.AutoValue_NodeSummaryList extends org.graylog2.rest.models.system.cluster.responses.$AutoValue_NodeSummaryList {
  org.graylog2.rest.models.system.cluster.responses.AutoValue_NodeSummaryList(java.util.List<org.graylog2.rest.models.system.cluster.responses.NodeSummary>, int);
    Code:
       0: aload_0
       1: aload_1
       2: iload_2
       3: invokespecial #1                  // Method org/graylog2/rest/models/system/cluster/responses/$AutoValue_NodeSummaryList."<init>":(Ljava/util/List;I)V
       6: return

  public final java.util.List<org.graylog2.rest.models.system.cluster.responses.NodeSummary> getNodes();
    Code:
       0: aload_0
       1: invokevirtual #2                  // Method nodes:()Ljava/util/List;
       4: areturn

  public final int getTotal();
    Code:
       0: aload_0
       1: invokevirtual #3                  // Method total:()I
       4: ireturn
}
