Compiled from "GuiAttributeAssign.java"
public class edu.internet2.middleware.grouper.grouperUi.beans.api.GuiAttributeAssign implements java.io.Serializable, java.lang.Comparable<edu.internet2.middleware.grouper.grouperUi.beans.api.GuiAttributeAssign> {
  private edu.internet2.middleware.grouper.grouperUi.beans.api.GuiMember guiMember;

  private edu.internet2.middleware.grouper.attr.assign.AttributeAssign attributeAssign;

  private java.lang.String screenLabelLong;

  private java.lang.String screenLabelShort;

  private boolean canUpdateAttributeDefName;

  public static final java.lang.String TIMESTAMP_FORMAT;

  static final java.text.SimpleDateFormat timestampFormat;

  public edu.internet2.middleware.grouper.grouperUi.beans.api.GuiAttributeAssign();
    Code:
       0: aload_0
       1: invokespecial #1                  // Method java/lang/Object."<init>":()V
       4: aload_0
       5: aconst_null
       6: putfield      #2                  // Field screenLabelLong:Ljava/lang/String;
       9: aload_0
      10: aconst_null
      11: putfield      #3                  // Field screenLabelShort:Ljava/lang/String;
      14: return

  public boolean equals(java.lang.Object);
    Code:
       0: aload_0
       1: aload_1
       2: if_acmpne     7
       5: iconst_1
       6: ireturn
       7: aload_1
       8: instanceof    #4                  // class edu/internet2/middleware/grouper/grouperUi/beans/api/GuiAttributeAssign
      11: ifne          16
      14: iconst_0
      15: ireturn
      16: new           #5                  // class org/apache/commons/lang/builder/EqualsBuilder
      19: dup
      20: invokespecial #6                  // Method org/apache/commons/lang/builder/EqualsBuilder."<init>":()V
      23: aload_0
      24: getfield      #7                  // Field attributeAssign:Ledu/internet2/middleware/grouper/attr/assign/AttributeAssign;
      27: aload_1
      28: checkcast     #4                  // class edu/internet2/middleware/grouper/grouperUi/beans/api/GuiAttributeAssign
      31: getfield      #7                  // Field attributeAssign:Ledu/internet2/middleware/grouper/attr/assign/AttributeAssign;
      34: invokevirtual #8                  // Method org/apache/commons/lang/builder/EqualsBuilder.append:(Ljava/lang/Object;Ljava/lang/Object;)Lorg/apache/commons/lang/builder/EqualsBuilder;
      37: invokevirtual #9                  // Method org/apache/commons/lang/builder/EqualsBuilder.isEquals:()Z
      40: ireturn

  public int hashCode();
    Code:
       0: new           #10                 // class org/apache/commons/lang/builder/HashCodeBuilder
       3: dup
       4: invokespecial #11                 // Method org/apache/commons/lang/builder/HashCodeBuilder."<init>":()V
       7: aload_0
       8: getfield      #7                  // Field attributeAssign:Ledu/internet2/middleware/grouper/attr/assign/AttributeAssign;
      11: invokevirtual #12                 // Method org/apache/commons/lang/builder/HashCodeBuilder.append:(Ljava/lang/Object;)Lorg/apache/commons/lang/builder/HashCodeBuilder;
      14: invokevirtual #13                 // Method org/apache/commons/lang/builder/HashCodeBuilder.toHashCode:()I
      17: ireturn

  public edu.internet2.middleware.grouper.attr.assign.AttributeAssign getAttributeAssign();
    Code:
       0: aload_0
       1: getfield      #7                  // Field attributeAssign:Ledu/internet2/middleware/grouper/attr/assign/AttributeAssign;
       4: areturn

  public java.util.Set<edu.internet2.middleware.grouper.grouperUi.beans.api.GuiAttributeAssign> getGuiAttributeAssigns();
    Code:
       0: aload_0
       1: getfield      #7                  // Field attributeAssign:Ledu/internet2/middleware/grouper/attr/assign/AttributeAssign;
       4: ifnonnull     11
       7: aconst_null
       8: goto          21
      11: aload_0
      12: getfield      #7                  // Field attributeAssign:Ledu/internet2/middleware/grouper/attr/assign/AttributeAssign;
      15: invokevirtual #14                 // Method edu/internet2/middleware/grouper/attr/assign/AttributeAssign.getAttributeDelegate:()Ledu/internet2/middleware/grouper/attr/assign/AttributeAssignAttrAssignDelegate;
      18: invokevirtual #15                 // Method edu/internet2/middleware/grouper/attr/assign/AttributeAssignAttrAssignDelegate.retrieveAssignments:()Ljava/util/Set;
      21: astore_1
      22: new           #16                 // class java/util/TreeSet
      25: dup
      26: invokespecial #17                 // Method java/util/TreeSet."<init>":()V
      29: astore_2
      30: aload_1
      31: invokestatic  #18                 // Method edu/internet2/middleware/grouper/util/GrouperUtil.nonNull:(Ljava/util/Set;)Ljava/util/Set;
      34: invokeinterface #19,  1           // InterfaceMethod java/util/Set.iterator:()Ljava/util/Iterator;
      39: astore_3
      40: aload_3
      41: invokeinterface #20,  1           // InterfaceMethod java/util/Iterator.hasNext:()Z
      46: ifeq          127
      49: aload_3
      50: invokeinterface #21,  1           // InterfaceMethod java/util/Iterator.next:()Ljava/lang/Object;
      55: checkcast     #22                 // class edu/internet2/middleware/grouper/attr/assign/AttributeAssign
      58: astore        4
      60: new           #4                  // class edu/internet2/middleware/grouper/grouperUi/beans/api/GuiAttributeAssign
      63: dup
      64: invokespecial #23                 // Method "<init>":()V
      67: astore        5
      69: aload_0
      70: getfield      #7                  // Field attributeAssign:Ledu/internet2/middleware/grouper/attr/assign/AttributeAssign;
      73: invokevirtual #24                 // Method edu/internet2/middleware/grouper/attr/assign/AttributeAssign.retrieveAttributeAssignable:()Ledu/internet2/middleware/grouper/attr/assign/AttributeAssignable;
      76: invokeinterface #25,  1           // InterfaceMethod edu/internet2/middleware/grouper/attr/assign/AttributeAssignable.getAttributeDelegate:()Ledu/internet2/middleware/grouper/attr/assign/AttributeAssignBaseDelegate;
      81: aload_0
      82: getfield      #7                  // Field attributeAssign:Ledu/internet2/middleware/grouper/attr/assign/AttributeAssign;
      85: invokevirtual #26                 // Method edu/internet2/middleware/grouper/attr/assign/AttributeAssign.getAttributeDefName:()Ledu/internet2/middleware/grouper/attr/AttributeDefName;
      88: invokevirtual #27                 // Method edu/internet2/middleware/grouper/attr/assign/AttributeAssignBaseDelegate.assertCanUpdateAttributeDefName:(Ledu/internet2/middleware/grouper/attr/AttributeDefName;)V
      91: aload         5
      93: iconst_1
      94: invokevirtual #28                 // Method setCanUpdateAttributeDefName:(Z)V
      97: goto          108
     100: astore        6
     102: aload         5
     104: iconst_0
     105: invokevirtual #28                 // Method setCanUpdateAttributeDefName:(Z)V
     108: aload         5
     110: aload         4
     112: invokevirtual #30                 // Method setAttributeAssign:(Ledu/internet2/middleware/grouper/attr/assign/AttributeAssign;)V
     115: aload_2
     116: aload         5
     118: invokeinterface #31,  2           // InterfaceMethod java/util/Set.add:(Ljava/lang/Object;)Z
     123: pop
     124: goto          40
     127: aload_2
     128: areturn
    Exception table:
       from    to  target type
          69    97   100   Class edu/internet2/middleware/grouper/exception/InsufficientPrivilegeException

  public java.lang.String getScreenLabelLongIfDifferent();
    Code:
       0: aload_0
       1: invokespecial #32                 // Method initScreenLabels:()V
       4: aload_0
       5: invokevirtual #33                 // Method isNeedsTooltip:()Z
       8: ifeq          16
      11: aload_0
      12: getfield      #2                  // Field screenLabelLong:Ljava/lang/String;
      15: areturn
      16: aconst_null
      17: areturn

  public java.lang.String getScreenLabelLong();
    Code:
       0: aload_0
       1: invokespecial #32                 // Method initScreenLabels:()V
       4: aload_0
       5: getfield      #2                  // Field screenLabelLong:Ljava/lang/String;
       8: areturn

  public java.lang.String getScreenLabelShort();
    Code:
       0: aload_0
       1: invokespecial #32                 // Method initScreenLabels:()V
       4: aload_0
       5: getfield      #3                  // Field screenLabelShort:Ljava/lang/String;
       8: areturn

  public boolean isNeedsTooltip();
    Code:
       0: aload_0
       1: invokespecial #32                 // Method initScreenLabels:()V
       4: aload_0
       5: getfield      #2                  // Field screenLabelLong:Ljava/lang/String;
       8: aload_0
       9: getfield      #3                  // Field screenLabelShort:Ljava/lang/String;
      12: invokestatic  #34                 // Method org/apache/commons/lang/StringUtils.equals:(Ljava/lang/String;Ljava/lang/String;)Z
      15: ifne          22
      18: iconst_1
      19: goto          23
      22: iconst_0
      23: ireturn

  private void initScreenLabels();
    Code:
       0: aload_0
       1: getfield      #2                  // Field screenLabelLong:Ljava/lang/String;
       4: ifnonnull     315
       7: aload_0
       8: getfield      #3                  // Field screenLabelShort:Ljava/lang/String;
      11: ifnonnull     315
      14: aload_0
      15: getfield      #7                  // Field attributeAssign:Ledu/internet2/middleware/grouper/attr/assign/AttributeAssign;
      18: ifnull        315
      21: getstatic     #35                 // Field edu/internet2/middleware/grouper/grouperUi/beans/api/GuiAttributeAssign$1.$SwitchMap$edu$internet2$middleware$grouper$attr$assign$AttributeAssignType:[I
      24: aload_0
      25: getfield      #7                  // Field attributeAssign:Ledu/internet2/middleware/grouper/attr/assign/AttributeAssign;
      28: invokevirtual #36                 // Method edu/internet2/middleware/grouper/attr/assign/AttributeAssign.getAttributeAssignType:()Ledu/internet2/middleware/grouper/attr/assign/AttributeAssignType;
      31: invokevirtual #37                 // Method edu/internet2/middleware/grouper/attr/assign/AttributeAssignType.ordinal:()I
      34: iaload
      35: tableswitch   { // 1 to 6
                     1: 72
                     2: 99
                     3: 126
                     4: 153
                     5: 183
                     6: 213
               default: 282
          }
      72: aload_0
      73: getfield      #7                  // Field attributeAssign:Ledu/internet2/middleware/grouper/attr/assign/AttributeAssign;
      76: invokevirtual #38                 // Method edu/internet2/middleware/grouper/attr/assign/AttributeAssign.getOwnerStem:()Ledu/internet2/middleware/grouper/Stem;
      79: astore_1
      80: aload_0
      81: aload_1
      82: invokevirtual #39                 // Method edu/internet2/middleware/grouper/Stem.getDisplayName:()Ljava/lang/String;
      85: putfield      #2                  // Field screenLabelLong:Ljava/lang/String;
      88: aload_0
      89: aload_1
      90: invokevirtual #40                 // Method edu/internet2/middleware/grouper/Stem.getDisplayExtension:()Ljava/lang/String;
      93: putfield      #3                  // Field screenLabelShort:Ljava/lang/String;
      96: goto          315
      99: aload_0
     100: getfield      #7                  // Field attributeAssign:Ledu/internet2/middleware/grouper/attr/assign/AttributeAssign;
     103: invokevirtual #41                 // Method edu/internet2/middleware/grouper/attr/assign/AttributeAssign.getOwnerAttributeDef:()Ledu/internet2/middleware/grouper/attr/AttributeDef;
     106: astore_1
     107: aload_0
     108: aload_1
     109: invokevirtual #42                 // Method edu/internet2/middleware/grouper/attr/AttributeDef.getName:()Ljava/lang/String;
     112: putfield      #2                  // Field screenLabelLong:Ljava/lang/String;
     115: aload_0
     116: aload_1
     117: invokevirtual #43                 // Method edu/internet2/middleware/grouper/attr/AttributeDef.getExtension:()Ljava/lang/String;
     120: putfield      #3                  // Field screenLabelShort:Ljava/lang/String;
     123: goto          315
     126: aload_0
     127: getfield      #7                  // Field attributeAssign:Ledu/internet2/middleware/grouper/attr/assign/AttributeAssign;
     130: invokevirtual #44                 // Method edu/internet2/middleware/grouper/attr/assign/AttributeAssign.getOwnerGroup:()Ledu/internet2/middleware/grouper/Group;
     133: astore_1
     134: aload_0
     135: aload_1
     136: invokevirtual #45                 // Method edu/internet2/middleware/grouper/Group.getDisplayName:()Ljava/lang/String;
     139: putfield      #2                  // Field screenLabelLong:Ljava/lang/String;
     142: aload_0
     143: aload_1
     144: invokevirtual #46                 // Method edu/internet2/middleware/grouper/Group.getDisplayExtension:()Ljava/lang/String;
     147: putfield      #3                  // Field screenLabelShort:Ljava/lang/String;
     150: goto          315
     153: aload_0
     154: getfield      #7                  // Field attributeAssign:Ledu/internet2/middleware/grouper/attr/assign/AttributeAssign;
     157: invokevirtual #47                 // Method edu/internet2/middleware/grouper/attr/assign/AttributeAssign.getOwnerMember:()Ledu/internet2/middleware/grouper/Member;
     160: astore_1
     161: aload_0
     162: getfield      #7                  // Field attributeAssign:Ledu/internet2/middleware/grouper/attr/assign/AttributeAssign;
     165: invokevirtual #44                 // Method edu/internet2/middleware/grouper/attr/assign/AttributeAssign.getOwnerGroup:()Ledu/internet2/middleware/grouper/Group;
     168: astore_2
     169: aload_1
     170: invokevirtual #48                 // Method edu/internet2/middleware/grouper/Member.getSubject:()Ledu/internet2/middleware/subject/Subject;
     173: astore_3
     174: aload_0
     175: aload_2
     176: aload_3
     177: invokespecial #49                 // Method initScreenLabelsMembership:(Ledu/internet2/middleware/grouper/Group;Ledu/internet2/middleware/subject/Subject;)V
     180: goto          315
     183: aload_0
     184: getfield      #7                  // Field attributeAssign:Ledu/internet2/middleware/grouper/attr/assign/AttributeAssign;
     187: invokevirtual #50                 // Method edu/internet2/middleware/grouper/attr/assign/AttributeAssign.getOwnerMembership:()Ledu/internet2/middleware/grouper/Membership;
     190: astore_1
     191: aload_1
     192: invokevirtual #51                 // Method edu/internet2/middleware/grouper/Membership.getGroup:()Ledu/internet2/middleware/grouper/Group;
     195: astore_2
     196: aload_1
     197: invokevirtual #52                 // Method edu/internet2/middleware/grouper/Membership.getMember:()Ledu/internet2/middleware/grouper/Member;
     200: invokevirtual #48                 // Method edu/internet2/middleware/grouper/Member.getSubject:()Ledu/internet2/middleware/subject/Subject;
     203: astore_3
     204: aload_0
     205: aload_2
     206: aload_3
     207: invokespecial #49                 // Method initScreenLabelsMembership:(Ledu/internet2/middleware/grouper/Group;Ledu/internet2/middleware/subject/Subject;)V
     210: goto          315
     213: aload_0
     214: getfield      #7                  // Field attributeAssign:Ledu/internet2/middleware/grouper/attr/assign/AttributeAssign;
     217: invokevirtual #47                 // Method edu/internet2/middleware/grouper/attr/assign/AttributeAssign.getOwnerMember:()Ledu/internet2/middleware/grouper/Member;
     220: astore_1
     221: new           #53                 // class edu/internet2/middleware/grouper/grouperUi/beans/api/GuiSubject
     224: dup
     225: aload_1
     226: invokevirtual #48                 // Method edu/internet2/middleware/grouper/Member.getSubject:()Ledu/internet2/middleware/subject/Subject;
     229: invokespecial #54                 // Method edu/internet2/middleware/grouper/grouperUi/beans/api/GuiSubject."<init>":(Ledu/internet2/middleware/subject/Subject;)V
     232: astore_2
     233: aload_2
     234: invokevirtual #55                 // Method edu/internet2/middleware/grouper/grouperUi/beans/api/GuiSubject.getScreenLabel:()Ljava/lang/String;
     237: astore_3
     238: aload_0
     239: aload_3
     240: putfield      #2                  // Field screenLabelLong:Ljava/lang/String;
     243: invokestatic  #56                 // Method edu/internet2/middleware/grouper/ui/util/GrouperUiConfig.retrieveConfig:()Ledu/internet2/middleware/grouper/ui/util/GrouperUiConfig;
     246: ldc           #57                 // String simpleAttributeUpdate.maxOwnerSubjectChars
     248: bipush        50
     250: invokevirtual #58                 // Method edu/internet2/middleware/grouper/ui/util/GrouperUiConfig.propertyValueInt:(Ljava/lang/String;I)I
     253: istore        4
     255: iload         4
     257: iconst_m1
     258: if_icmpne     269
     261: aload_0
     262: aload_3
     263: putfield      #3                  // Field screenLabelShort:Ljava/lang/String;
     266: goto          315
     269: aload_0
     270: aload_3
     271: iload         4
     273: invokestatic  #59                 // Method org/apache/commons/lang/StringUtils.abbreviate:(Ljava/lang/String;I)Ljava/lang/String;
     276: putfield      #3                  // Field screenLabelShort:Ljava/lang/String;
     279: goto          315
     282: new           #60                 // class java/lang/RuntimeException
     285: dup
     286: new           #61                 // class java/lang/StringBuilder
     289: dup
     290: invokespecial #62                 // Method java/lang/StringBuilder."<init>":()V
     293: ldc           #63                 // String Not expecting attributeAssignType:
     295: invokevirtual #64                 // Method java/lang/StringBuilder.append:(Ljava/lang/String;)Ljava/lang/StringBuilder;
     298: aload_0
     299: getfield      #7                  // Field attributeAssign:Ledu/internet2/middleware/grouper/attr/assign/AttributeAssign;
     302: invokevirtual #36                 // Method edu/internet2/middleware/grouper/attr/assign/AttributeAssign.getAttributeAssignType:()Ledu/internet2/middleware/grouper/attr/assign/AttributeAssignType;
     305: invokevirtual #65                 // Method java/lang/StringBuilder.append:(Ljava/lang/Object;)Ljava/lang/StringBuilder;
     308: invokevirtual #66                 // Method java/lang/StringBuilder.toString:()Ljava/lang/String;
     311: invokespecial #67                 // Method java/lang/RuntimeException."<init>":(Ljava/lang/String;)V
     314: athrow
     315: return

  private void initScreenLabelsMembership(edu.internet2.middleware.grouper.Group, edu.internet2.middleware.subject.Subject);
    Code:
       0: new           #53                 // class edu/internet2/middleware/grouper/grouperUi/beans/api/GuiSubject
       3: dup
       4: aload_2
       5: invokespecial #54                 // Method edu/internet2/middleware/grouper/grouperUi/beans/api/GuiSubject."<init>":(Ledu/internet2/middleware/subject/Subject;)V
       8: astore_3
       9: aload_3
      10: invokevirtual #55                 // Method edu/internet2/middleware/grouper/grouperUi/beans/api/GuiSubject.getScreenLabel:()Ljava/lang/String;
      13: astore        4
      15: aload_0
      16: new           #61                 // class java/lang/StringBuilder
      19: dup
      20: invokespecial #62                 // Method java/lang/StringBuilder."<init>":()V
      23: aload_1
      24: invokevirtual #45                 // Method edu/internet2/middleware/grouper/Group.getDisplayName:()Ljava/lang/String;
      27: invokevirtual #64                 // Method java/lang/StringBuilder.append:(Ljava/lang/String;)Ljava/lang/StringBuilder;
      30: ldc           #68                 // String  -
      32: invokevirtual #64                 // Method java/lang/StringBuilder.append:(Ljava/lang/String;)Ljava/lang/StringBuilder;
      35: aload         4
      37: invokevirtual #64                 // Method java/lang/StringBuilder.append:(Ljava/lang/String;)Ljava/lang/StringBuilder;
      40: invokevirtual #66                 // Method java/lang/StringBuilder.toString:()Ljava/lang/String;
      43: putfield      #2                  // Field screenLabelLong:Ljava/lang/String;
      46: invokestatic  #56                 // Method edu/internet2/middleware/grouper/ui/util/GrouperUiConfig.retrieveConfig:()Ledu/internet2/middleware/grouper/ui/util/GrouperUiConfig;
      49: ldc           #57                 // String simpleAttributeUpdate.maxOwnerSubjectChars
      51: bipush        50
      53: invokevirtual #58                 // Method edu/internet2/middleware/grouper/ui/util/GrouperUiConfig.propertyValueInt:(Ljava/lang/String;I)I
      56: istore        5
      58: aconst_null
      59: astore        6
      61: iload         5
      63: iconst_m1
      64: if_icmpne     74
      67: aload         4
      69: astore        6
      71: goto          83
      74: aload         4
      76: iload         5
      78: invokestatic  #59                 // Method org/apache/commons/lang/StringUtils.abbreviate:(Ljava/lang/String;I)Ljava/lang/String;
      81: astore        6
      83: aload_0
      84: new           #61                 // class java/lang/StringBuilder
      87: dup
      88: invokespecial #62                 // Method java/lang/StringBuilder."<init>":()V
      91: aload_1
      92: invokevirtual #46                 // Method edu/internet2/middleware/grouper/Group.getDisplayExtension:()Ljava/lang/String;
      95: invokevirtual #64                 // Method java/lang/StringBuilder.append:(Ljava/lang/String;)Ljava/lang/StringBuilder;
      98: ldc           #68                 // String  -
     100: invokevirtual #64                 // Method java/lang/StringBuilder.append:(Ljava/lang/String;)Ljava/lang/StringBuilder;
     103: aload         6
     105: invokevirtual #64                 // Method java/lang/StringBuilder.append:(Ljava/lang/String;)Ljava/lang/StringBuilder;
     108: invokevirtual #66                 // Method java/lang/StringBuilder.toString:()Ljava/lang/String;
     111: putfield      #3                  // Field screenLabelShort:Ljava/lang/String;
     114: return

  public void setAttributeAssign(edu.internet2.middleware.grouper.attr.assign.AttributeAssign);
    Code:
       0: aload_0
       1: invokespecial #69                 // Method clear:()V
       4: aload_0
       5: aload_1
       6: putfield      #7                  // Field attributeAssign:Ledu/internet2/middleware/grouper/attr/assign/AttributeAssign;
       9: return

  private void clear();
    Code:
       0: aload_0
       1: aconst_null
       2: putfield      #2                  // Field screenLabelLong:Ljava/lang/String;
       5: aload_0
       6: aconst_null
       7: putfield      #3                  // Field screenLabelShort:Ljava/lang/String;
      10: return

  public edu.internet2.middleware.grouper.grouperUi.beans.api.GuiAttributeDefName getGuiAttributeDefName();
    Code:
       0: new           #70                 // class edu/internet2/middleware/grouper/grouperUi/beans/api/GuiAttributeDefName
       3: dup
       4: aload_0
       5: getfield      #7                  // Field attributeAssign:Ledu/internet2/middleware/grouper/attr/assign/AttributeAssign;
       8: invokevirtual #26                 // Method edu/internet2/middleware/grouper/attr/assign/AttributeAssign.getAttributeDefName:()Ledu/internet2/middleware/grouper/attr/AttributeDefName;
      11: invokespecial #71                 // Method edu/internet2/middleware/grouper/grouperUi/beans/api/GuiAttributeDefName."<init>":(Ledu/internet2/middleware/grouper/attr/AttributeDefName;)V
      14: areturn

  public edu.internet2.middleware.grouper.grouperUi.beans.api.GuiAttributeDef getGuiAttributeDef();
    Code:
       0: new           #72                 // class edu/internet2/middleware/grouper/grouperUi/beans/api/GuiAttributeDef
       3: dup
       4: aload_0
       5: getfield      #7                  // Field attributeAssign:Ledu/internet2/middleware/grouper/attr/assign/AttributeAssign;
       8: invokevirtual #73                 // Method edu/internet2/middleware/grouper/attr/assign/AttributeAssign.getAttributeDef:()Ledu/internet2/middleware/grouper/attr/AttributeDef;
      11: invokespecial #74                 // Method edu/internet2/middleware/grouper/grouperUi/beans/api/GuiAttributeDef."<init>":(Ledu/internet2/middleware/grouper/attr/AttributeDef;)V
      14: areturn

  public java.lang.String getDisabledDate();
    Code:
       0: aload_0
       1: getfield      #7                  // Field attributeAssign:Ledu/internet2/middleware/grouper/attr/assign/AttributeAssign;
       4: ifnull        17
       7: aload_0
       8: getfield      #7                  // Field attributeAssign:Ledu/internet2/middleware/grouper/attr/assign/AttributeAssign;
      11: invokevirtual #75                 // Method edu/internet2/middleware/grouper/attr/assign/AttributeAssign.getDisabledTime:()Ljava/sql/Timestamp;
      14: ifnonnull     19
      17: aconst_null
      18: areturn
      19: aload_0
      20: getfield      #7                  // Field attributeAssign:Ledu/internet2/middleware/grouper/attr/assign/AttributeAssign;
      23: invokevirtual #75                 // Method edu/internet2/middleware/grouper/attr/assign/AttributeAssign.getDisabledTime:()Ljava/sql/Timestamp;
      26: invokestatic  #76                 // Method formatEnabledDisabled:(Ljava/sql/Timestamp;)Ljava/lang/String;
      29: areturn

  public java.lang.String getEnabledDate();
    Code:
       0: aload_0
       1: getfield      #7                  // Field attributeAssign:Ledu/internet2/middleware/grouper/attr/assign/AttributeAssign;
       4: ifnull        17
       7: aload_0
       8: getfield      #7                  // Field attributeAssign:Ledu/internet2/middleware/grouper/attr/assign/AttributeAssign;
      11: invokevirtual #77                 // Method edu/internet2/middleware/grouper/attr/assign/AttributeAssign.getEnabledTime:()Ljava/sql/Timestamp;
      14: ifnonnull     19
      17: aconst_null
      18: areturn
      19: aload_0
      20: getfield      #7                  // Field attributeAssign:Ledu/internet2/middleware/grouper/attr/assign/AttributeAssign;
      23: invokevirtual #77                 // Method edu/internet2/middleware/grouper/attr/assign/AttributeAssign.getEnabledTime:()Ljava/sql/Timestamp;
      26: invokestatic  #76                 // Method formatEnabledDisabled:(Ljava/sql/Timestamp;)Ljava/lang/String;
      29: areturn

  public static synchronized java.lang.String formatEnabledDisabled(java.sql.Timestamp);
    Code:
       0: getstatic     #78                 // Field timestampFormat:Ljava/text/SimpleDateFormat;
       3: aload_0
       4: invokevirtual #79                 // Method java/text/SimpleDateFormat.format:(Ljava/util/Date;)Ljava/lang/String;
       7: areturn

  public java.lang.String getEnabledDisabledKey();
    Code:
       0: aload_0
       1: getfield      #7                  // Field attributeAssign:Ledu/internet2/middleware/grouper/attr/assign/AttributeAssign;
       4: ifnull        17
       7: aload_0
       8: getfield      #7                  // Field attributeAssign:Ledu/internet2/middleware/grouper/attr/assign/AttributeAssign;
      11: invokevirtual #80                 // Method edu/internet2/middleware/grouper/attr/assign/AttributeAssign.isEnabled:()Z
      14: ifeq          20
      17: ldc           #81                 // String simpleAttributeUpdate.assignEnabled
      19: areturn
      20: ldc           #82                 // String simpleAttributeUpdate.assignDisabled
      22: areturn

  public boolean isCanUpdateAttributeDefName();
    Code:
       0: aload_0
       1: getfield      #83                 // Field canUpdateAttributeDefName:Z
       4: ireturn

  public void setCanUpdateAttributeDefName(boolean);
    Code:
       0: aload_0
       1: iload_1
       2: putfield      #83                 // Field canUpdateAttributeDefName:Z
       5: return

  public int compareTo(edu.internet2.middleware.grouper.grouperUi.beans.api.GuiAttributeAssign);
    Code:
       0: aload_0
       1: getfield      #7                  // Field attributeAssign:Ledu/internet2/middleware/grouper/attr/assign/AttributeAssign;
       4: ifnonnull     11
       7: aconst_null
       8: goto          18
      11: aload_0
      12: getfield      #7                  // Field attributeAssign:Ledu/internet2/middleware/grouper/attr/assign/AttributeAssign;
      15: invokevirtual #26                 // Method edu/internet2/middleware/grouper/attr/assign/AttributeAssign.getAttributeDefName:()Ledu/internet2/middleware/grouper/attr/AttributeDefName;
      18: astore_2
      19: aload_2
      20: ifnonnull     27
      23: aconst_null
      24: goto          31
      27: aload_2
      28: invokevirtual #84                 // Method edu/internet2/middleware/grouper/attr/AttributeDefName.getName:()Ljava/lang/String;
      31: astore_3
      32: aload_1
      33: getfield      #7                  // Field attributeAssign:Ledu/internet2/middleware/grouper/attr/assign/AttributeAssign;
      36: ifnonnull     43
      39: aconst_null
      40: goto          50
      43: aload_1
      44: getfield      #7                  // Field attributeAssign:Ledu/internet2/middleware/grouper/attr/assign/AttributeAssign;
      47: invokevirtual #26                 // Method edu/internet2/middleware/grouper/attr/assign/AttributeAssign.getAttributeDefName:()Ledu/internet2/middleware/grouper/attr/AttributeDefName;
      50: astore        4
      52: aload         4
      54: ifnonnull     61
      57: aconst_null
      58: goto          66
      61: aload         4
      63: invokevirtual #84                 // Method edu/internet2/middleware/grouper/attr/AttributeDefName.getName:()Ljava/lang/String;
      66: astore        5
      68: new           #85                 // class org/apache/commons/lang/builder/CompareToBuilder
      71: dup
      72: invokespecial #86                 // Method org/apache/commons/lang/builder/CompareToBuilder."<init>":()V
      75: aload_3
      76: aload         5
      78: invokevirtual #87                 // Method org/apache/commons/lang/builder/CompareToBuilder.append:(Ljava/lang/Object;Ljava/lang/Object;)Lorg/apache/commons/lang/builder/CompareToBuilder;
      81: aload_0
      82: getfield      #7                  // Field attributeAssign:Ledu/internet2/middleware/grouper/attr/assign/AttributeAssign;
      85: invokevirtual #88                 // Method edu/internet2/middleware/grouper/attr/assign/AttributeAssign.getId:()Ljava/lang/String;
      88: aload_1
      89: getfield      #7                  // Field attributeAssign:Ledu/internet2/middleware/grouper/attr/assign/AttributeAssign;
      92: invokevirtual #88                 // Method edu/internet2/middleware/grouper/attr/assign/AttributeAssign.getId:()Ljava/lang/String;
      95: invokevirtual #87                 // Method org/apache/commons/lang/builder/CompareToBuilder.append:(Ljava/lang/Object;Ljava/lang/Object;)Lorg/apache/commons/lang/builder/CompareToBuilder;
      98: invokevirtual #89                 // Method org/apache/commons/lang/builder/CompareToBuilder.toComparison:()I
     101: ireturn

  public edu.internet2.middleware.grouper.grouperUi.beans.api.GuiMember getGuiMember();
    Code:
       0: aload_0
       1: getfield      #90                 // Field guiMember:Ledu/internet2/middleware/grouper/grouperUi/beans/api/GuiMember;
       4: areturn

  public void setGuiMember(edu.internet2.middleware.grouper.grouperUi.beans.api.GuiMember);
    Code:
       0: aload_0
       1: aload_1
       2: putfield      #90                 // Field guiMember:Ledu/internet2/middleware/grouper/grouperUi/beans/api/GuiMember;
       5: return

  public int compareTo(java.lang.Object);
    Code:
       0: aload_0
       1: aload_1
       2: checkcast     #4                  // class edu/internet2/middleware/grouper/grouperUi/beans/api/GuiAttributeAssign
       5: invokevirtual #91                 // Method compareTo:(Ledu/internet2/middleware/grouper/grouperUi/beans/api/GuiAttributeAssign;)I
       8: ireturn

  static {};
    Code:
       0: new           #92                 // class java/text/SimpleDateFormat
       3: dup
       4: ldc           #93                 // String yyyy/MM/dd
       6: invokespecial #94                 // Method java/text/SimpleDateFormat."<init>":(Ljava/lang/String;)V
       9: putstatic     #78                 // Field timestampFormat:Ljava/text/SimpleDateFormat;
      12: return
}
