Compiled from "GuiPermissionEntryContainer.java"
public class edu.internet2.middleware.grouper.grouperUi.beans.api.GuiPermissionEntryContainer implements java.io.Serializable, java.lang.Comparable<edu.internet2.middleware.grouper.grouperUi.beans.api.GuiPermissionEntryContainer> {
  private java.util.Map<java.lang.String, edu.internet2.middleware.grouper.grouperUi.beans.api.GuiPermissionEntry> actionToGuiPermissionEntryMap;

  private java.lang.String memberId;

  private java.lang.String screenLabelLong;

  private java.lang.String screenLabelShort;

  private java.util.Set<edu.internet2.middleware.grouper.grouperUi.beans.api.GuiAttributeAssign> guiAttributeAssigns;

  private edu.internet2.middleware.grouper.permissions.role.Role role;

  private edu.internet2.middleware.grouper.grouperUi.beans.api.GuiGroup guiRole;

  private edu.internet2.middleware.grouper.attr.AttributeDef permissionDefinition;

  private edu.internet2.middleware.grouper.grouperUi.beans.api.GuiAttributeDef guiPermissionDefinition;

  private edu.internet2.middleware.grouper.attr.AttributeDefName permissionResource;

  private edu.internet2.middleware.grouper.grouperUi.beans.api.GuiAttributeDefName guiPermissionResource;

  private edu.internet2.middleware.grouper.grouperUi.beans.api.GuiSubject guiSubject;

  private java.util.List<edu.internet2.middleware.grouper.permissions.PermissionEntry> rawPermissionEntries;

  private java.util.Set<edu.internet2.middleware.grouper.grouperUi.beans.api.GuiPermissionLimitBeanContainer> guiPermissionLimitBeanContainers;

  private edu.internet2.middleware.grouper.permissions.PermissionEntry$PermissionType permissionType;

  public edu.internet2.middleware.grouper.grouperUi.beans.api.GuiPermissionEntryContainer();
    Code:
       0: aload_0
       1: invokespecial #1                  // Method java/lang/Object."<init>":()V
       4: aload_0
       5: aconst_null
       6: putfield      #2                  // Field screenLabelLong:Ljava/lang/String;
       9: aload_0
      10: aconst_null
      11: putfield      #3                  // Field screenLabelShort:Ljava/lang/String;
      14: aload_0
      15: aconst_null
      16: putfield      #4                  // Field rawPermissionEntries:Ljava/util/List;
      19: aload_0
      20: aconst_null
      21: putfield      #5                  // Field guiPermissionLimitBeanContainers:Ljava/util/Set;
      24: return

  public java.lang.String getMemberId();
    Code:
       0: aload_0
       1: getfield      #6                  // Field memberId:Ljava/lang/String;
       4: areturn

  public void setMemberId(java.lang.String);
    Code:
       0: aload_0
       1: aload_1
       2: putfield      #6                  // Field memberId:Ljava/lang/String;
       5: return

  public java.util.Map<java.lang.String, edu.internet2.middleware.grouper.grouperUi.beans.api.GuiPermissionEntry> getActionToGuiPermissionEntryMap();
    Code:
       0: aload_0
       1: getfield      #7                  // Field actionToGuiPermissionEntryMap:Ljava/util/Map;
       4: areturn

  public void setActionToGuiPermissionEntryMap(java.util.Map<java.lang.String, edu.internet2.middleware.grouper.grouperUi.beans.api.GuiPermissionEntry>);
    Code:
       0: aload_0
       1: aload_1
       2: putfield      #7                  // Field actionToGuiPermissionEntryMap:Ljava/util/Map;
       5: return

  public void setGuiAttributeAssigns(java.util.Set<edu.internet2.middleware.grouper.grouperUi.beans.api.GuiAttributeAssign>);
    Code:
       0: aload_0
       1: aload_1
       2: putfield      #8                  // Field guiAttributeAssigns:Ljava/util/Set;
       5: return

  public java.util.Set<edu.internet2.middleware.grouper.grouperUi.beans.api.GuiAttributeAssign> getGuiAttributeAssigns();
    Code:
       0: aload_0
       1: getfield      #8                  // Field guiAttributeAssigns:Ljava/util/Set;
       4: areturn

  public java.lang.String getScreenLabelLongIfDifferent();
    Code:
       0: aload_0
       1: invokespecial #9                  // Method initScreenLabels:()V
       4: aload_0
       5: invokevirtual #10                 // Method isNeedsTooltip:()Z
       8: ifeq          16
      11: aload_0
      12: getfield      #2                  // Field screenLabelLong:Ljava/lang/String;
      15: areturn
      16: aconst_null
      17: areturn

  public java.lang.String getScreenLabelLong();
    Code:
       0: aload_0
       1: invokespecial #9                  // Method initScreenLabels:()V
       4: aload_0
       5: getfield      #2                  // Field screenLabelLong:Ljava/lang/String;
       8: areturn

  public java.lang.String getScreenLabelShort();
    Code:
       0: aload_0
       1: invokespecial #9                  // Method initScreenLabels:()V
       4: aload_0
       5: getfield      #3                  // Field screenLabelShort:Ljava/lang/String;
       8: areturn

  public edu.internet2.middleware.grouper.permissions.role.Role getRole();
    Code:
       0: aload_0
       1: getfield      #11                 // Field role:Ledu/internet2/middleware/grouper/permissions/role/Role;
       4: areturn

  public void setRole(edu.internet2.middleware.grouper.permissions.role.Role);
    Code:
       0: aload_0
       1: aload_1
       2: putfield      #11                 // Field role:Ledu/internet2/middleware/grouper/permissions/role/Role;
       5: return

  public edu.internet2.middleware.grouper.grouperUi.beans.api.GuiGroup getGuiRole();
    Code:
       0: aload_0
       1: getfield      #12                 // Field guiRole:Ledu/internet2/middleware/grouper/grouperUi/beans/api/GuiGroup;
       4: areturn

  public void setGuiRole(edu.internet2.middleware.grouper.grouperUi.beans.api.GuiGroup);
    Code:
       0: aload_0
       1: aload_1
       2: putfield      #12                 // Field guiRole:Ledu/internet2/middleware/grouper/grouperUi/beans/api/GuiGroup;
       5: return

  public edu.internet2.middleware.grouper.attr.AttributeDef getPermissionDefinition();
    Code:
       0: aload_0
       1: getfield      #13                 // Field permissionDefinition:Ledu/internet2/middleware/grouper/attr/AttributeDef;
       4: areturn

  public void setPermissionDefinition(edu.internet2.middleware.grouper.attr.AttributeDef);
    Code:
       0: aload_0
       1: aload_1
       2: putfield      #13                 // Field permissionDefinition:Ledu/internet2/middleware/grouper/attr/AttributeDef;
       5: return

  public edu.internet2.middleware.grouper.grouperUi.beans.api.GuiAttributeDef getGuiPermissionDefinition();
    Code:
       0: aload_0
       1: getfield      #14                 // Field guiPermissionDefinition:Ledu/internet2/middleware/grouper/grouperUi/beans/api/GuiAttributeDef;
       4: areturn

  public void setGuiPermissionDefinition(edu.internet2.middleware.grouper.grouperUi.beans.api.GuiAttributeDef);
    Code:
       0: aload_0
       1: aload_1
       2: putfield      #14                 // Field guiPermissionDefinition:Ledu/internet2/middleware/grouper/grouperUi/beans/api/GuiAttributeDef;
       5: return

  public edu.internet2.middleware.grouper.attr.AttributeDefName getPermissionResource();
    Code:
       0: aload_0
       1: getfield      #15                 // Field permissionResource:Ledu/internet2/middleware/grouper/attr/AttributeDefName;
       4: areturn

  public void setPermissionResource(edu.internet2.middleware.grouper.attr.AttributeDefName);
    Code:
       0: aload_0
       1: aload_1
       2: putfield      #15                 // Field permissionResource:Ledu/internet2/middleware/grouper/attr/AttributeDefName;
       5: return

  public edu.internet2.middleware.grouper.grouperUi.beans.api.GuiAttributeDefName getGuiPermissionResource();
    Code:
       0: aload_0
       1: getfield      #16                 // Field guiPermissionResource:Ledu/internet2/middleware/grouper/grouperUi/beans/api/GuiAttributeDefName;
       4: areturn

  public void setGuiPermissionResource(edu.internet2.middleware.grouper.grouperUi.beans.api.GuiAttributeDefName);
    Code:
       0: aload_0
       1: aload_1
       2: putfield      #16                 // Field guiPermissionResource:Ledu/internet2/middleware/grouper/grouperUi/beans/api/GuiAttributeDefName;
       5: return

  public boolean isNeedsTooltip();
    Code:
       0: aload_0
       1: invokespecial #9                  // Method initScreenLabels:()V
       4: aload_0
       5: getfield      #2                  // Field screenLabelLong:Ljava/lang/String;
       8: aload_0
       9: getfield      #3                  // Field screenLabelShort:Ljava/lang/String;
      12: invokestatic  #17                 // Method org/apache/commons/lang/StringUtils.equals:(Ljava/lang/String;Ljava/lang/String;)Z
      15: ifne          22
      18: iconst_1
      19: goto          23
      22: iconst_0
      23: ireturn

  public java.util.Set<edu.internet2.middleware.grouper.grouperUi.beans.api.GuiPermissionLimitBeanContainer> getGuiPermissionLimitBeanContainers();
    Code:
       0: aload_0
       1: getfield      #5                  // Field guiPermissionLimitBeanContainers:Ljava/util/Set;
       4: areturn

  public edu.internet2.middleware.grouper.grouperUi.beans.api.GuiSubject getGuiSubject();
    Code:
       0: aload_0
       1: getfield      #18                 // Field guiSubject:Ledu/internet2/middleware/grouper/grouperUi/beans/api/GuiSubject;
       4: areturn

  public void setGuiSubject(edu.internet2.middleware.grouper.grouperUi.beans.api.GuiSubject);
    Code:
       0: aload_0
       1: aload_1
       2: putfield      #18                 // Field guiSubject:Ledu/internet2/middleware/grouper/grouperUi/beans/api/GuiSubject;
       5: return

  private void initScreenLabels();
    Code:
       0: aload_0
       1: getfield      #2                  // Field screenLabelLong:Ljava/lang/String;
       4: ifnonnull     75
       7: aload_0
       8: getfield      #3                  // Field screenLabelShort:Ljava/lang/String;
      11: ifnonnull     75
      14: aload_0
      15: getfield      #18                 // Field guiSubject:Ledu/internet2/middleware/grouper/grouperUi/beans/api/GuiSubject;
      18: ifnull        75
      21: aload_0
      22: getfield      #18                 // Field guiSubject:Ledu/internet2/middleware/grouper/grouperUi/beans/api/GuiSubject;
      25: invokevirtual #19                 // Method edu/internet2/middleware/grouper/grouperUi/beans/api/GuiSubject.getScreenLabelLong:()Ljava/lang/String;
      28: astore_1
      29: aload_0
      30: aload_1
      31: putfield      #2                  // Field screenLabelLong:Ljava/lang/String;
      34: aload_0
      35: getfield      #18                 // Field guiSubject:Ledu/internet2/middleware/grouper/grouperUi/beans/api/GuiSubject;
      38: invokevirtual #20                 // Method edu/internet2/middleware/grouper/grouperUi/beans/api/GuiSubject.getScreenLabel:()Ljava/lang/String;
      41: astore_1
      42: invokestatic  #21                 // Method edu/internet2/middleware/grouper/ui/util/GrouperUiConfig.retrieveConfig:()Ledu/internet2/middleware/grouper/ui/util/GrouperUiConfig;
      45: ldc           #22                 // String simplePermissionUpdate.maxOwnerSubjectChars
      47: bipush        50
      49: invokevirtual #23                 // Method edu/internet2/middleware/grouper/ui/util/GrouperUiConfig.propertyValueInt:(Ljava/lang/String;I)I
      52: istore_2
      53: iload_2
      54: iconst_m1
      55: if_icmpne     66
      58: aload_0
      59: aload_1
      60: putfield      #3                  // Field screenLabelShort:Ljava/lang/String;
      63: goto          75
      66: aload_0
      67: aload_1
      68: iload_2
      69: invokestatic  #24                 // Method org/apache/commons/lang/StringUtils.abbreviate:(Ljava/lang/String;I)Ljava/lang/String;
      72: putfield      #3                  // Field screenLabelShort:Ljava/lang/String;
      75: return

  public java.util.List<edu.internet2.middleware.grouper.permissions.PermissionEntry> getRawPermissionEntries();
    Code:
       0: aload_0
       1: getfield      #4                  // Field rawPermissionEntries:Ljava/util/List;
       4: areturn

  public void setRawPermissionEntries(java.util.List<edu.internet2.middleware.grouper.permissions.PermissionEntry>);
    Code:
       0: aload_0
       1: aload_1
       2: putfield      #4                  // Field rawPermissionEntries:Ljava/util/List;
       5: return

  public edu.internet2.middleware.grouper.permissions.PermissionEntry$PermissionType getPermissionType();
    Code:
       0: aload_0
       1: getfield      #25                 // Field permissionType:Ledu/internet2/middleware/grouper/permissions/PermissionEntry$PermissionType;
       4: areturn

  public void setPermissionType(edu.internet2.middleware.grouper.permissions.PermissionEntry$PermissionType);
    Code:
       0: aload_0
       1: aload_1
       2: putfield      #25                 // Field permissionType:Ledu/internet2/middleware/grouper/permissions/PermissionEntry$PermissionType;
       5: return

  public void processRawEntries(java.util.List<java.lang.String>, java.util.Map<edu.internet2.middleware.grouper.permissions.PermissionEntry, java.util.Set<edu.internet2.middleware.grouper.permissions.limits.PermissionLimitBean>>);
    Code:
       0: aload_0
       1: new           #26                 // class java/util/HashMap
       4: dup
       5: invokespecial #27                 // Method java/util/HashMap."<init>":()V
       8: putfield      #7                  // Field actionToGuiPermissionEntryMap:Ljava/util/Map;
      11: aload_1
      12: invokeinterface #28,  1           // InterfaceMethod java/util/List.iterator:()Ljava/util/Iterator;
      17: astore_3
      18: aload_3
      19: invokeinterface #29,  1           // InterfaceMethod java/util/Iterator.hasNext:()Z
      24: ifeq          85
      27: aload_3
      28: invokeinterface #30,  1           // InterfaceMethod java/util/Iterator.next:()Ljava/lang/Object;
      33: checkcast     #31                 // class java/lang/String
      36: astore        4
      38: new           #32                 // class edu/internet2/middleware/grouper/grouperUi/beans/api/GuiPermissionEntry
      41: dup
      42: invokespecial #33                 // Method edu/internet2/middleware/grouper/grouperUi/beans/api/GuiPermissionEntry."<init>":()V
      45: astore        5
      47: aload_0
      48: getfield      #7                  // Field actionToGuiPermissionEntryMap:Ljava/util/Map;
      51: aload         4
      53: aload         5
      55: invokeinterface #34,  3           // InterfaceMethod java/util/Map.put:(Ljava/lang/Object;Ljava/lang/Object;)Ljava/lang/Object;
      60: pop
      61: aload         5
      63: aload_0
      64: getfield      #25                 // Field permissionType:Ledu/internet2/middleware/grouper/permissions/PermissionEntry$PermissionType;
      67: invokevirtual #35                 // Method edu/internet2/middleware/grouper/grouperUi/beans/api/GuiPermissionEntry.setPermissionType:(Ledu/internet2/middleware/grouper/permissions/PermissionEntry$PermissionType;)V
      70: aload         5
      72: new           #36                 // class java/util/ArrayList
      75: dup
      76: invokespecial #37                 // Method java/util/ArrayList."<init>":()V
      79: invokevirtual #38                 // Method edu/internet2/middleware/grouper/grouperUi/beans/api/GuiPermissionEntry.setRawGuiPermissionEntries:(Ljava/util/List;)V
      82: goto          18
      85: new           #26                 // class java/util/HashMap
      88: dup
      89: invokespecial #27                 // Method java/util/HashMap."<init>":()V
      92: astore_3
      93: aload_0
      94: invokevirtual #39                 // Method getRawPermissionEntries:()Ljava/util/List;
      97: invokeinterface #28,  1           // InterfaceMethod java/util/List.iterator:()Ljava/util/Iterator;
     102: astore        4
     104: aload         4
     106: invokeinterface #29,  1           // InterfaceMethod java/util/Iterator.hasNext:()Z
     111: ifeq          428
     114: aload         4
     116: invokeinterface #30,  1           // InterfaceMethod java/util/Iterator.next:()Ljava/lang/Object;
     121: checkcast     #40                 // class edu/internet2/middleware/grouper/permissions/PermissionEntry
     124: astore        5
     126: aload_0
     127: getfield      #7                  // Field actionToGuiPermissionEntryMap:Ljava/util/Map;
     130: aload         5
     132: invokeinterface #41,  1           // InterfaceMethod edu/internet2/middleware/grouper/permissions/PermissionEntry.getAction:()Ljava/lang/String;
     137: invokeinterface #42,  2           // InterfaceMethod java/util/Map.get:(Ljava/lang/Object;)Ljava/lang/Object;
     142: checkcast     #32                 // class edu/internet2/middleware/grouper/grouperUi/beans/api/GuiPermissionEntry
     145: astore        6
     147: aload         6
     149: ifnonnull     197
     152: new           #43                 // class java/lang/RuntimeException
     155: dup
     156: new           #44                 // class java/lang/StringBuilder
     159: dup
     160: invokespecial #45                 // Method java/lang/StringBuilder."<init>":()V
     163: ldc           #46                 // String Why no guiPermissionEntry for action:
     165: invokevirtual #47                 // Method java/lang/StringBuilder.append:(Ljava/lang/String;)Ljava/lang/StringBuilder;
     168: aload         5
     170: invokeinterface #41,  1           // InterfaceMethod edu/internet2/middleware/grouper/permissions/PermissionEntry.getAction:()Ljava/lang/String;
     175: invokevirtual #47                 // Method java/lang/StringBuilder.append:(Ljava/lang/String;)Ljava/lang/StringBuilder;
     178: ldc           #48                 // String ,
     180: invokevirtual #47                 // Method java/lang/StringBuilder.append:(Ljava/lang/String;)Ljava/lang/StringBuilder;
     183: aload_1
     184: invokestatic  #49                 // Method edu/internet2/middleware/grouper/util/GrouperUtil.stringValue:(Ljava/lang/Object;)Ljava/lang/String;
     187: invokevirtual #47                 // Method java/lang/StringBuilder.append:(Ljava/lang/String;)Ljava/lang/StringBuilder;
     190: invokevirtual #50                 // Method java/lang/StringBuilder.toString:()Ljava/lang/String;
     193: invokespecial #51                 // Method java/lang/RuntimeException."<init>":(Ljava/lang/String;)V
     196: athrow
     197: new           #32                 // class edu/internet2/middleware/grouper/grouperUi/beans/api/GuiPermissionEntry
     200: dup
     201: invokespecial #33                 // Method edu/internet2/middleware/grouper/grouperUi/beans/api/GuiPermissionEntry."<init>":()V
     204: astore        7
     206: aload         7
     208: aload         5
     210: invokevirtual #52                 // Method edu/internet2/middleware/grouper/grouperUi/beans/api/GuiPermissionEntry.setPermissionEntry:(Ledu/internet2/middleware/grouper/permissions/PermissionEntry;)V
     213: aload         6
     215: invokevirtual #53                 // Method edu/internet2/middleware/grouper/grouperUi/beans/api/GuiPermissionEntry.getRawGuiPermissionEntries:()Ljava/util/List;
     218: aload         7
     220: invokeinterface #54,  2           // InterfaceMethod java/util/List.add:(Ljava/lang/Object;)Z
     225: pop
     226: aload_2
     227: aload         5
     229: invokeinterface #42,  2           // InterfaceMethod java/util/Map.get:(Ljava/lang/Object;)Ljava/lang/Object;
     234: checkcast     #55                 // class java/util/Set
     237: astore        8
     239: aload         8
     241: invokestatic  #56                 // Method edu/internet2/middleware/grouper/util/GrouperUtil.length:(Ljava/lang/Object;)I
     244: ifle          425
     247: aload_0
     248: getfield      #5                  // Field guiPermissionLimitBeanContainers:Ljava/util/Set;
     251: ifnonnull     265
     254: aload_0
     255: new           #57                 // class java/util/TreeSet
     258: dup
     259: invokespecial #58                 // Method java/util/TreeSet."<init>":()V
     262: putfield      #5                  // Field guiPermissionLimitBeanContainers:Ljava/util/Set;
     265: aload         8
     267: invokeinterface #59,  1           // InterfaceMethod java/util/Set.iterator:()Ljava/util/Iterator;
     272: astore        9
     274: aload         9
     276: invokeinterface #29,  1           // InterfaceMethod java/util/Iterator.hasNext:()Z
     281: ifeq          425
     284: aload         9
     286: invokeinterface #30,  1           // InterfaceMethod java/util/Iterator.next:()Ljava/lang/Object;
     291: checkcast     #60                 // class edu/internet2/middleware/grouper/permissions/limits/PermissionLimitBean
     294: astore        10
     296: aload_3
     297: aload         10
     299: invokevirtual #61                 // Method edu/internet2/middleware/grouper/permissions/limits/PermissionLimitBean.getLimitAssign:()Ledu/internet2/middleware/grouper/attr/assign/AttributeAssign;
     302: invokeinterface #42,  2           // InterfaceMethod java/util/Map.get:(Ljava/lang/Object;)Ljava/lang/Object;
     307: checkcast     #62                 // class edu/internet2/middleware/grouper/grouperUi/beans/api/GuiPermissionLimitBeanContainer
     310: astore        11
     312: aload         11
     314: ifnonnull     359
     317: new           #62                 // class edu/internet2/middleware/grouper/grouperUi/beans/api/GuiPermissionLimitBeanContainer
     320: dup
     321: invokespecial #63                 // Method edu/internet2/middleware/grouper/grouperUi/beans/api/GuiPermissionLimitBeanContainer."<init>":()V
     324: astore        11
     326: aload         11
     328: aload         10
     330: invokevirtual #64                 // Method edu/internet2/middleware/grouper/grouperUi/beans/api/GuiPermissionLimitBeanContainer.setPermissionLimitBean:(Ledu/internet2/middleware/grouper/permissions/limits/PermissionLimitBean;)V
     333: aload_3
     334: aload         10
     336: invokevirtual #61                 // Method edu/internet2/middleware/grouper/permissions/limits/PermissionLimitBean.getLimitAssign:()Ledu/internet2/middleware/grouper/attr/assign/AttributeAssign;
     339: aload         11
     341: invokeinterface #34,  3           // InterfaceMethod java/util/Map.put:(Ljava/lang/Object;Ljava/lang/Object;)Ljava/lang/Object;
     346: pop
     347: aload_0
     348: getfield      #5                  // Field guiPermissionLimitBeanContainers:Ljava/util/Set;
     351: aload         11
     353: invokeinterface #65,  2           // InterfaceMethod java/util/Set.add:(Ljava/lang/Object;)Z
     358: pop
     359: aload         11
     361: invokevirtual #66                 // Method edu/internet2/middleware/grouper/grouperUi/beans/api/GuiPermissionLimitBeanContainer.getActions:()Ljava/util/Set;
     364: aload         5
     366: invokeinterface #41,  1           // InterfaceMethod edu/internet2/middleware/grouper/permissions/PermissionEntry.getAction:()Ljava/lang/String;
     371: invokeinterface #65,  2           // InterfaceMethod java/util/Set.add:(Ljava/lang/Object;)Z
     376: pop
     377: aload         5
     379: aload_0
     380: getfield      #25                 // Field permissionType:Ledu/internet2/middleware/grouper/permissions/PermissionEntry$PermissionType;
     383: invokeinterface #67,  2           // InterfaceMethod edu/internet2/middleware/grouper/permissions/PermissionEntry.isImmediate:(Ledu/internet2/middleware/grouper/permissions/PermissionEntry$PermissionType;)Z
     388: ifeq          422
     391: aload         10
     393: invokevirtual #61                 // Method edu/internet2/middleware/grouper/permissions/limits/PermissionLimitBean.getLimitAssign:()Ledu/internet2/middleware/grouper/attr/assign/AttributeAssign;
     396: astore        12
     398: aload         12
     400: invokevirtual #68                 // Method edu/internet2/middleware/grouper/attr/assign/AttributeAssign.getOwnerAttributeAssignId:()Ljava/lang/String;
     403: aload         5
     405: invokeinterface #69,  1           // InterfaceMethod edu/internet2/middleware/grouper/permissions/PermissionEntry.getAttributeAssignId:()Ljava/lang/String;
     410: invokestatic  #17                 // Method org/apache/commons/lang/StringUtils.equals:(Ljava/lang/String;Ljava/lang/String;)Z
     413: ifeq          422
     416: aload         11
     418: iconst_1
     419: invokevirtual #70                 // Method edu/internet2/middleware/grouper/grouperUi/beans/api/GuiPermissionLimitBeanContainer.setImmediate:(Z)V
     422: goto          274
     425: goto          104
     428: aload_0
     429: getfield      #7                  // Field actionToGuiPermissionEntryMap:Ljava/util/Map;
     432: invokeinterface #71,  1           // InterfaceMethod java/util/Map.values:()Ljava/util/Collection;
     437: invokeinterface #72,  1           // InterfaceMethod java/util/Collection.iterator:()Ljava/util/Iterator;
     442: astore        4
     444: aload         4
     446: invokeinterface #29,  1           // InterfaceMethod java/util/Iterator.hasNext:()Z
     451: ifeq          474
     454: aload         4
     456: invokeinterface #30,  1           // InterfaceMethod java/util/Iterator.next:()Ljava/lang/Object;
     461: checkcast     #32                 // class edu/internet2/middleware/grouper/grouperUi/beans/api/GuiPermissionEntry
     464: astore        5
     466: aload         5
     468: invokevirtual #73                 // Method edu/internet2/middleware/grouper/grouperUi/beans/api/GuiPermissionEntry.processRawEntries:()V
     471: goto          444
     474: return

  public int compareTo(edu.internet2.middleware.grouper.grouperUi.beans.api.GuiPermissionEntryContainer);
    Code:
       0: new           #74                 // class org/apache/commons/lang/builder/CompareToBuilder
       3: dup
       4: invokespecial #75                 // Method org/apache/commons/lang/builder/CompareToBuilder."<init>":()V
       7: aload_0
       8: invokevirtual #76                 // Method getRole:()Ledu/internet2/middleware/grouper/permissions/role/Role;
      11: invokeinterface #77,  1           // InterfaceMethod edu/internet2/middleware/grouper/permissions/role/Role.getDisplayExtension:()Ljava/lang/String;
      16: aload_1
      17: invokevirtual #76                 // Method getRole:()Ledu/internet2/middleware/grouper/permissions/role/Role;
      20: invokeinterface #77,  1           // InterfaceMethod edu/internet2/middleware/grouper/permissions/role/Role.getDisplayExtension:()Ljava/lang/String;
      25: invokevirtual #78                 // Method org/apache/commons/lang/builder/CompareToBuilder.append:(Ljava/lang/Object;Ljava/lang/Object;)Lorg/apache/commons/lang/builder/CompareToBuilder;
      28: astore_2
      29: aload_0
      30: getfield      #25                 // Field permissionType:Ledu/internet2/middleware/grouper/permissions/PermissionEntry$PermissionType;
      33: getstatic     #79                 // Field edu/internet2/middleware/grouper/permissions/PermissionEntry$PermissionType.role_subject:Ledu/internet2/middleware/grouper/permissions/PermissionEntry$PermissionType;
      36: if_acmpne     52
      39: aload_2
      40: aload_0
      41: invokevirtual #80                 // Method getScreenLabelShort:()Ljava/lang/String;
      44: aload_1
      45: invokevirtual #80                 // Method getScreenLabelShort:()Ljava/lang/String;
      48: invokevirtual #78                 // Method org/apache/commons/lang/builder/CompareToBuilder.append:(Ljava/lang/Object;Ljava/lang/Object;)Lorg/apache/commons/lang/builder/CompareToBuilder;
      51: pop
      52: aload_2
      53: aload_0
      54: invokevirtual #81                 // Method getPermissionResource:()Ledu/internet2/middleware/grouper/attr/AttributeDefName;
      57: invokevirtual #82                 // Method edu/internet2/middleware/grouper/attr/AttributeDefName.getDisplayExtension:()Ljava/lang/String;
      60: aload_1
      61: invokevirtual #81                 // Method getPermissionResource:()Ledu/internet2/middleware/grouper/attr/AttributeDefName;
      64: invokevirtual #82                 // Method edu/internet2/middleware/grouper/attr/AttributeDefName.getDisplayExtension:()Ljava/lang/String;
      67: invokevirtual #78                 // Method org/apache/commons/lang/builder/CompareToBuilder.append:(Ljava/lang/Object;Ljava/lang/Object;)Lorg/apache/commons/lang/builder/CompareToBuilder;
      70: pop
      71: aload_2
      72: invokevirtual #83                 // Method org/apache/commons/lang/builder/CompareToBuilder.toComparison:()I
      75: ireturn

  public int compareTo(java.lang.Object);
    Code:
       0: aload_0
       1: aload_1
       2: checkcast     #84                 // class edu/internet2/middleware/grouper/grouperUi/beans/api/GuiPermissionEntryContainer
       5: invokevirtual #85                 // Method compareTo:(Ledu/internet2/middleware/grouper/grouperUi/beans/api/GuiPermissionEntryContainer;)I
       8: ireturn
}
