Compiled from "GuiSubject.java"
class edu.internet2.middleware.grouper.grouperUi.beans.api.GuiSubject$1 extends java.util.HashMap<java.lang.String, java.lang.String> {
  final edu.internet2.middleware.grouper.grouperUi.beans.api.GuiSubject this$0;

  edu.internet2.middleware.grouper.grouperUi.beans.api.GuiSubject$1(edu.internet2.middleware.grouper.grouperUi.beans.api.GuiSubject);
    Code:
       0: aload_0
       1: aload_1
       2: putfield      #1                  // Field this$0:Ledu/internet2/middleware/grouper/grouperUi/beans/api/GuiSubject;
       5: aload_0
       6: invokespecial #2                  // Method java/util/HashMap."<init>":()V
       9: return

  public java.lang.String get(java.lang.Object);
    Code:
       0: aload_0
       1: getfield      #1                  // Field this$0:Ledu/internet2/middleware/grouper/grouperUi/beans/api/GuiSubject;
       4: invokevirtual #3                  // Method edu/internet2/middleware/grouper/grouperUi/beans/api/GuiSubject.getSubject:()Ledu/internet2/middleware/subject/Subject;
       7: invokeinterface #4,  1            // InterfaceMethod edu/internet2/middleware/subject/Subject.getSourceId:()Ljava/lang/String;
      12: astore_2
      13: aload_2
      14: invokestatic  #5                  // Method edu/internet2/middleware/grouper/ui/util/GrouperUiUtils.convertSourceIdToTextId:(Ljava/lang/String;)Ljava/lang/String;
      17: astore_3
      18: aload_0
      19: getfield      #1                  // Field this$0:Ledu/internet2/middleware/grouper/grouperUi/beans/api/GuiSubject;
      22: invokestatic  #6                  // Method edu/internet2/middleware/grouper/grouperUi/beans/api/GuiSubject.access$000:(Ledu/internet2/middleware/grouper/grouperUi/beans/api/GuiSubject;)Ledu/internet2/middleware/subject/Subject;
      25: invokeinterface #4,  1            // InterfaceMethod edu/internet2/middleware/subject/Subject.getSourceId:()Ljava/lang/String;
      30: invokestatic  #7                  // Method edu/internet2/middleware/grouper/util/GrouperEmailUtils.emailAttributeNameForSource:(Ljava/lang/String;)Ljava/lang/String;
      33: astore        4
      35: new           #8                  // class java/lang/StringBuilder
      38: dup
      39: invokespecial #9                  // Method java/lang/StringBuilder."<init>":()V
      42: ldc           #10                 // String subjectViewLabel__
      44: invokevirtual #11                 // Method java/lang/StringBuilder.append:(Ljava/lang/String;)Ljava/lang/StringBuilder;
      47: aload_3
      48: invokevirtual #11                 // Method java/lang/StringBuilder.append:(Ljava/lang/String;)Ljava/lang/StringBuilder;
      51: ldc           #12                 // String __
      53: invokevirtual #11                 // Method java/lang/StringBuilder.append:(Ljava/lang/String;)Ljava/lang/StringBuilder;
      56: aload_1
      57: invokevirtual #13                 // Method java/lang/StringBuilder.append:(Ljava/lang/Object;)Ljava/lang/StringBuilder;
      60: invokevirtual #14                 // Method java/lang/StringBuilder.toString:()Ljava/lang/String;
      63: astore        5
      65: ldc           #15                 // String sourceId
      67: aload_1
      68: invokevirtual #16                 // Method java/lang/String.equals:(Ljava/lang/Object;)Z
      71: ifeq          81
      74: ldc           #17                 // String subjectViewLabelSourceId
      76: astore        5
      78: goto          182
      81: ldc           #18                 // String sourceName
      83: aload_1
      84: invokevirtual #16                 // Method java/lang/String.equals:(Ljava/lang/Object;)Z
      87: ifeq          97
      90: ldc           #19                 // String subjectViewLabelSourceName
      92: astore        5
      94: goto          182
      97: ldc           #20                 // String memberId
      99: aload_1
     100: invokevirtual #16                 // Method java/lang/String.equals:(Ljava/lang/Object;)Z
     103: ifeq          113
     106: ldc           #21                 // String subjectViewLabelMemberId
     108: astore        5
     110: goto          182
     113: ldc           #22                 // String subjectId
     115: aload_1
     116: invokevirtual #16                 // Method java/lang/String.equals:(Ljava/lang/Object;)Z
     119: ifeq          129
     122: ldc           #23                 // String subjectViewLabelId
     124: astore        5
     126: goto          182
     129: ldc           #24                 // String name
     131: aload_1
     132: invokevirtual #16                 // Method java/lang/String.equals:(Ljava/lang/Object;)Z
     135: ifeq          145
     138: ldc           #25                 // String subjectViewLabelName
     140: astore        5
     142: goto          182
     145: ldc           #26                 // String description
     147: aload_1
     148: invokevirtual #16                 // Method java/lang/String.equals:(Ljava/lang/Object;)Z
     151: ifeq          161
     154: ldc           #27                 // String subjectViewLabelDescription
     156: astore        5
     158: goto          182
     161: aload         4
     163: invokestatic  #28                 // Method edu/internet2/middleware/grouper/util/GrouperUtil.isBlank:(Ljava/lang/String;)Z
     166: ifne          182
     169: aload         4
     171: aload_1
     172: invokevirtual #16                 // Method java/lang/String.equals:(Ljava/lang/Object;)Z
     175: ifeq          182
     178: ldc           #29                 // String subjectViewLabelEmail
     180: astore        5
     182: aload         5
     184: invokestatic  #30                 // Method edu/internet2/middleware/grouper/grouperUi/beans/ui/TextContainer.textOrNull:(Ljava/lang/String;)Ljava/lang/String;
     187: astore        6
     189: aload         6
     191: invokestatic  #31                 // Method org/apache/commons/lang/StringUtils.isBlank:(Ljava/lang/String;)Z
     194: ifeq          220
     197: new           #8                  // class java/lang/StringBuilder
     200: dup
     201: invokespecial #9                  // Method java/lang/StringBuilder."<init>":()V
     204: aload_1
     205: checkcast     #32                 // class java/lang/String
     208: invokevirtual #11                 // Method java/lang/StringBuilder.append:(Ljava/lang/String;)Ljava/lang/StringBuilder;
     211: ldc           #33                 // String :
     213: invokevirtual #11                 // Method java/lang/StringBuilder.append:(Ljava/lang/String;)Ljava/lang/StringBuilder;
     216: invokevirtual #14                 // Method java/lang/StringBuilder.toString:()Ljava/lang/String;
     219: areturn
     220: aload         6
     222: areturn

  public java.lang.Object get(java.lang.Object);
    Code:
       0: aload_0
       1: aload_1
       2: invokevirtual #34                 // Method get:(Ljava/lang/Object;)Ljava/lang/String;
       5: areturn
}
