public class org.bouncycastle.asn1.ASN1OutputStream {
  private java.io.OutputStream os;

  public static org.bouncycastle.asn1.ASN1OutputStream create(java.io.OutputStream);
    Code:
       0: new           #56                 // class org/bouncycastle/asn1/ASN1OutputStream
       3: dup
       4: aload_0
       5: invokespecial #110                // Method "<init>":(Ljava/io/OutputStream;)V
       8: areturn

  public static org.bouncycastle.asn1.ASN1OutputStream create(java.io.OutputStream, java.lang.String);
    Code:
       0: aload_1
       1: ldc           #1                  // String DER
       3: invokevirtual #104                // Method java/lang/String.equals:(Ljava/lang/Object;)Z
       6: ifeq          18
       9: new           #58                 // class org/bouncycastle/asn1/DEROutputStream
      12: dup
      13: aload_0
      14: invokespecial #115                // Method org/bouncycastle/asn1/DEROutputStream."<init>":(Ljava/io/OutputStream;)V
      17: areturn
      18: aload_1
      19: ldc           #2                  // String DL
      21: invokevirtual #104                // Method java/lang/String.equals:(Ljava/lang/Object;)Z
      24: ifeq          36
      27: new           #59                 // class org/bouncycastle/asn1/DLOutputStream
      30: dup
      31: aload_0
      32: invokespecial #116                // Method org/bouncycastle/asn1/DLOutputStream."<init>":(Ljava/io/OutputStream;)V
      35: areturn
      36: new           #56                 // class org/bouncycastle/asn1/ASN1OutputStream
      39: dup
      40: aload_0
      41: invokespecial #110                // Method "<init>":(Ljava/io/OutputStream;)V
      44: areturn

  public org.bouncycastle.asn1.ASN1OutputStream(java.io.OutputStream);
    Code:
       0: aload_0
       1: invokespecial #103                // Method java/lang/Object."<init>":()V
       4: aload_0
       5: aload_1
       6: putfield      #97                 // Field os:Ljava/io/OutputStream;
       9: return

  final void writeLength(int) throws java.io.IOException;
    Code:
       0: iload_1
       1: bipush        127
       3: if_icmple     66
       6: iconst_1
       7: istore_2
       8: iload_1
       9: istore_3
      10: iload_3
      11: bipush        8
      13: iushr
      14: dup
      15: istore_3
      16: ifeq          25
      19: iinc          2, 1
      22: goto          10
      25: aload_0
      26: iload_2
      27: sipush        128
      30: ior
      31: i2b
      32: invokevirtual #106                // Method write:(I)V
      35: iload_2
      36: iconst_1
      37: isub
      38: bipush        8
      40: imul
      41: istore        4
      43: iload         4
      45: iflt          63
      48: aload_0
      49: iload_1
      50: iload         4
      52: ishr
      53: i2b
      54: invokevirtual #106                // Method write:(I)V
      57: iinc          4, -8
      60: goto          43
      63: goto          72
      66: aload_0
      67: iload_1
      68: i2b
      69: invokevirtual #106                // Method write:(I)V
      72: return

  final void write(int) throws java.io.IOException;
    Code:
       0: aload_0
       1: getfield      #97                 // Field os:Ljava/io/OutputStream;
       4: iload_1
       5: invokevirtual #101                // Method java/io/OutputStream.write:(I)V
       8: return

  final void write(byte[], int, int) throws java.io.IOException;
    Code:
       0: aload_0
       1: getfield      #97                 // Field os:Ljava/io/OutputStream;
       4: aload_1
       5: iload_2
       6: iload_3
       7: invokevirtual #102                // Method java/io/OutputStream.write:([BII)V
      10: return

  final void writeElements(org.bouncycastle.asn1.ASN1Encodable[]) throws java.io.IOException;
    Code:
       0: aload_1
       1: arraylength
       2: istore_2
       3: iconst_0
       4: istore_3
       5: iload_3
       6: iload_2
       7: if_icmpge     33
      10: aload_1
      11: iload_3
      12: aaload
      13: invokeinterface #119,  1          // InterfaceMethod org/bouncycastle/asn1/ASN1Encodable.toASN1Primitive:()Lorg/bouncycastle/asn1/ASN1Primitive;
      18: astore        4
      20: aload_0
      21: aload         4
      23: iconst_1
      24: invokevirtual #113                // Method writePrimitive:(Lorg/bouncycastle/asn1/ASN1Primitive;Z)V
      27: iinc          3, 1
      30: goto          5
      33: return

  final void writeElements(java.util.Enumeration) throws java.io.IOException;
    Code:
       0: aload_1
       1: invokeinterface #117,  1          // InterfaceMethod java/util/Enumeration.hasMoreElements:()Z
       6: ifeq          33
       9: aload_1
      10: invokeinterface #118,  1          // InterfaceMethod java/util/Enumeration.nextElement:()Ljava/lang/Object;
      15: checkcast     #55                 // class org/bouncycastle/asn1/ASN1Encodable
      18: invokeinterface #119,  1          // InterfaceMethod org/bouncycastle/asn1/ASN1Encodable.toASN1Primitive:()Lorg/bouncycastle/asn1/ASN1Primitive;
      23: astore_2
      24: aload_0
      25: aload_2
      26: iconst_1
      27: invokevirtual #113                // Method writePrimitive:(Lorg/bouncycastle/asn1/ASN1Primitive;Z)V
      30: goto          0
      33: return

  final void writeEncoded(boolean, int, byte) throws java.io.IOException;
    Code:
       0: iload_1
       1: ifeq          9
       4: aload_0
       5: iload_2
       6: invokevirtual #106                // Method write:(I)V
       9: aload_0
      10: iconst_1
      11: invokevirtual #107                // Method writeLength:(I)V
      14: aload_0
      15: iload_3
      16: invokevirtual #106                // Method write:(I)V
      19: return

  final void writeEncoded(boolean, int, byte[]) throws java.io.IOException;
    Code:
       0: iload_1
       1: ifeq          9
       4: aload_0
       5: iload_2
       6: invokevirtual #106                // Method write:(I)V
       9: aload_0
      10: aload_3
      11: arraylength
      12: invokevirtual #107                // Method writeLength:(I)V
      15: aload_0
      16: aload_3
      17: iconst_0
      18: aload_3
      19: arraylength
      20: invokevirtual #109                // Method write:([BII)V
      23: return

  final void writeEncoded(boolean, int, byte[], int, int) throws java.io.IOException;
    Code:
       0: iload_1
       1: ifeq          9
       4: aload_0
       5: iload_2
       6: invokevirtual #106                // Method write:(I)V
       9: aload_0
      10: iload         5
      12: invokevirtual #107                // Method writeLength:(I)V
      15: aload_0
      16: aload_3
      17: iload         4
      19: iload         5
      21: invokevirtual #109                // Method write:([BII)V
      24: return

  final void writeEncoded(boolean, int, byte, byte[]) throws java.io.IOException;
    Code:
       0: iload_1
       1: ifeq          9
       4: aload_0
       5: iload_2
       6: invokevirtual #106                // Method write:(I)V
       9: aload_0
      10: iconst_1
      11: aload         4
      13: arraylength
      14: iadd
      15: invokevirtual #107                // Method writeLength:(I)V
      18: aload_0
      19: iload_3
      20: invokevirtual #106                // Method write:(I)V
      23: aload_0
      24: aload         4
      26: iconst_0
      27: aload         4
      29: arraylength
      30: invokevirtual #109                // Method write:([BII)V
      33: return

  final void writeEncoded(boolean, int, byte, byte[], int, int, byte) throws java.io.IOException;
    Code:
       0: iload_1
       1: ifeq          9
       4: aload_0
       5: iload_2
       6: invokevirtual #106                // Method write:(I)V
       9: aload_0
      10: iconst_2
      11: iload         6
      13: iadd
      14: invokevirtual #107                // Method writeLength:(I)V
      17: aload_0
      18: iload_3
      19: invokevirtual #106                // Method write:(I)V
      22: aload_0
      23: aload         4
      25: iload         5
      27: iload         6
      29: invokevirtual #109                // Method write:([BII)V
      32: aload_0
      33: iload         7
      35: invokevirtual #106                // Method write:(I)V
      38: return

  final void writeEncoded(boolean, int, int, byte[]) throws java.io.IOException;
    Code:
       0: aload_0
       1: iload_1
       2: iload_2
       3: iload_3
       4: invokevirtual #108                // Method writeTag:(ZII)V
       7: aload_0
       8: aload         4
      10: arraylength
      11: invokevirtual #107                // Method writeLength:(I)V
      14: aload_0
      15: aload         4
      17: iconst_0
      18: aload         4
      20: arraylength
      21: invokevirtual #109                // Method write:([BII)V
      24: return

  final void writeEncodedIndef(boolean, int, int, byte[]) throws java.io.IOException;
    Code:
       0: aload_0
       1: iload_1
       2: iload_2
       3: iload_3
       4: invokevirtual #108                // Method writeTag:(ZII)V
       7: aload_0
       8: sipush        128
      11: invokevirtual #106                // Method write:(I)V
      14: aload_0
      15: aload         4
      17: iconst_0
      18: aload         4
      20: arraylength
      21: invokevirtual #109                // Method write:([BII)V
      24: aload_0
      25: iconst_0
      26: invokevirtual #106                // Method write:(I)V
      29: aload_0
      30: iconst_0
      31: invokevirtual #106                // Method write:(I)V
      34: return

  final void writeEncodedIndef(boolean, int, org.bouncycastle.asn1.ASN1Encodable[]) throws java.io.IOException;
    Code:
       0: iload_1
       1: ifeq          9
       4: aload_0
       5: iload_2
       6: invokevirtual #106                // Method write:(I)V
       9: aload_0
      10: sipush        128
      13: invokevirtual #106                // Method write:(I)V
      16: aload_0
      17: aload_3
      18: invokevirtual #112                // Method writeElements:([Lorg/bouncycastle/asn1/ASN1Encodable;)V
      21: aload_0
      22: iconst_0
      23: invokevirtual #106                // Method write:(I)V
      26: aload_0
      27: iconst_0
      28: invokevirtual #106                // Method write:(I)V
      31: return

  final void writeEncodedIndef(boolean, int, java.util.Enumeration) throws java.io.IOException;
    Code:
       0: iload_1
       1: ifeq          9
       4: aload_0
       5: iload_2
       6: invokevirtual #106                // Method write:(I)V
       9: aload_0
      10: sipush        128
      13: invokevirtual #106                // Method write:(I)V
      16: aload_0
      17: aload_3
      18: invokevirtual #111                // Method writeElements:(Ljava/util/Enumeration;)V
      21: aload_0
      22: iconst_0
      23: invokevirtual #106                // Method write:(I)V
      26: aload_0
      27: iconst_0
      28: invokevirtual #106                // Method write:(I)V
      31: return

  final void writeTag(boolean, int, int) throws java.io.IOException;
    Code:
       0: iload_1
       1: ifne          5
       4: return
       5: iload_3
       6: bipush        31
       8: if_icmpge     21
      11: aload_0
      12: iload_2
      13: iload_3
      14: ior
      15: invokevirtual #106                // Method write:(I)V
      18: goto          109
      21: aload_0
      22: iload_2
      23: bipush        31
      25: ior
      26: invokevirtual #106                // Method write:(I)V
      29: iload_3
      30: sipush        128
      33: if_icmpge     44
      36: aload_0
      37: iload_3
      38: invokevirtual #106                // Method write:(I)V
      41: goto          109
      44: iconst_5
      45: newarray       byte
      47: astore        4
      49: aload         4
      51: arraylength
      52: istore        5
      54: aload         4
      56: iinc          5, -1
      59: iload         5
      61: iload_3
      62: bipush        127
      64: iand
      65: i2b
      66: bastore
      67: iload_3
      68: bipush        7
      70: ishr
      71: istore_3
      72: aload         4
      74: iinc          5, -1
      77: iload         5
      79: iload_3
      80: bipush        127
      82: iand
      83: sipush        128
      86: ior
      87: i2b
      88: bastore
      89: iload_3
      90: bipush        127
      92: if_icmpgt     67
      95: aload_0
      96: aload         4
      98: iload         5
     100: aload         4
     102: arraylength
     103: iload         5
     105: isub
     106: invokevirtual #109                // Method write:([BII)V
     109: return

  protected void writeNull() throws java.io.IOException;
    Code:
       0: aload_0
       1: iconst_5
       2: invokevirtual #106                // Method write:(I)V
       5: aload_0
       6: iconst_0
       7: invokevirtual #106                // Method write:(I)V
      10: return

  public void writeObject(org.bouncycastle.asn1.ASN1Encodable) throws java.io.IOException;
    Code:
       0: aconst_null
       1: aload_1
       2: if_acmpne     15
       5: new           #50                 // class java/io/IOException
       8: dup
       9: ldc           #3                  // String null object detected
      11: invokespecial #98                 // Method java/io/IOException."<init>":(Ljava/lang/String;)V
      14: athrow
      15: aload_0
      16: aload_1
      17: invokeinterface #119,  1          // InterfaceMethod org/bouncycastle/asn1/ASN1Encodable.toASN1Primitive:()Lorg/bouncycastle/asn1/ASN1Primitive;
      22: iconst_1
      23: invokevirtual #113                // Method writePrimitive:(Lorg/bouncycastle/asn1/ASN1Primitive;Z)V
      26: aload_0
      27: invokevirtual #105                // Method flushInternal:()V
      30: return

  public void writeObject(org.bouncycastle.asn1.ASN1Primitive) throws java.io.IOException;
    Code:
       0: aconst_null
       1: aload_1
       2: if_acmpne     15
       5: new           #50                 // class java/io/IOException
       8: dup
       9: ldc           #3                  // String null object detected
      11: invokespecial #98                 // Method java/io/IOException."<init>":(Ljava/lang/String;)V
      14: athrow
      15: aload_0
      16: aload_1
      17: iconst_1
      18: invokevirtual #113                // Method writePrimitive:(Lorg/bouncycastle/asn1/ASN1Primitive;Z)V
      21: aload_0
      22: invokevirtual #105                // Method flushInternal:()V
      25: return

  void writePrimitive(org.bouncycastle.asn1.ASN1Primitive, boolean) throws java.io.IOException;
    Code:
       0: aload_1
       1: aload_0
       2: iload_2
       3: invokevirtual #114                // Method org/bouncycastle/asn1/ASN1Primitive.encode:(Lorg/bouncycastle/asn1/ASN1OutputStream;Z)V
       6: return

  public void close() throws java.io.IOException;
    Code:
       0: aload_0
       1: getfield      #97                 // Field os:Ljava/io/OutputStream;
       4: invokevirtual #99                 // Method java/io/OutputStream.close:()V
       7: return

  public void flush() throws java.io.IOException;
    Code:
       0: aload_0
       1: getfield      #97                 // Field os:Ljava/io/OutputStream;
       4: invokevirtual #100                // Method java/io/OutputStream.flush:()V
       7: return

  void flushInternal() throws java.io.IOException;
    Code:
       0: return

  org.bouncycastle.asn1.DEROutputStream getDERSubStream();
    Code:
       0: new           #58                 // class org/bouncycastle/asn1/DEROutputStream
       3: dup
       4: aload_0
       5: getfield      #97                 // Field os:Ljava/io/OutputStream;
       8: invokespecial #115                // Method org/bouncycastle/asn1/DEROutputStream."<init>":(Ljava/io/OutputStream;)V
      11: areturn

  org.bouncycastle.asn1.ASN1OutputStream getDLSubStream();
    Code:
       0: new           #59                 // class org/bouncycastle/asn1/DLOutputStream
       3: dup
       4: aload_0
       5: getfield      #97                 // Field os:Ljava/io/OutputStream;
       8: invokespecial #116                // Method org/bouncycastle/asn1/DLOutputStream."<init>":(Ljava/io/OutputStream;)V
      11: areturn
}
