Compiled from "MetricsEndpoint.java"
public final class org.springframework.boot.actuate.metrics.MetricsEndpoint$AvailableTag {
  private final java.lang.String tag;

  private final java.util.Set<java.lang.String> values;

  org.springframework.boot.actuate.metrics.MetricsEndpoint$AvailableTag(java.lang.String, java.util.Set<java.lang.String>);
    Code:
       0: aload_0
       1: invokespecial #1                  // Method java/lang/Object."<init>":()V
       4: aload_0
       5: aload_1
       6: putfield      #2                  // Field tag:Ljava/lang/String;
       9: aload_0
      10: aload_2
      11: putfield      #3                  // Field values:Ljava/util/Set;
      14: return

  public java.lang.String getTag();
    Code:
       0: aload_0
       1: getfield      #2                  // Field tag:Ljava/lang/String;
       4: areturn

  public java.util.Set<java.lang.String> getValues();
    Code:
       0: aload_0
       1: getfield      #3                  // Field values:Ljava/util/Set;
       4: areturn
}
