Compiled from "GrammarFile.java"
public class groovyjarjarantlr.preprocessor.GrammarFile {
  protected java.lang.String fileName;

  protected java.lang.String headerAction;

  protected groovyjarjarantlr.collections.impl.IndexedVector options;

  protected groovyjarjarantlr.collections.impl.IndexedVector grammars;

  protected boolean expanded;

  protected groovyjarjarantlr.Tool tool;

  public groovyjarjarantlr.preprocessor.GrammarFile(groovyjarjarantlr.Tool, java.lang.String);
    Code:
       0: aload_0
       1: invokespecial #20                 // Method java/lang/Object."<init>":()V
       4: aload_0
       5: ldc           #22                 // String
       7: putfield      #24                 // Field headerAction:Ljava/lang/String;
      10: aload_0
      11: iconst_0
      12: putfield      #26                 // Field expanded:Z
      15: aload_0
      16: aload_2
      17: putfield      #28                 // Field fileName:Ljava/lang/String;
      20: aload_0
      21: new           #30                 // class groovyjarjarantlr/collections/impl/IndexedVector
      24: dup
      25: invokespecial #31                 // Method groovyjarjarantlr/collections/impl/IndexedVector."<init>":()V
      28: putfield      #33                 // Field grammars:Lgroovyjarjarantlr/collections/impl/IndexedVector;
      31: aload_0
      32: aload_1
      33: putfield      #35                 // Field tool:Lgroovyjarjarantlr/Tool;
      36: return

  public void addGrammar(groovyjarjarantlr.preprocessor.Grammar);
    Code:
       0: aload_0
       1: getfield      #33                 // Field grammars:Lgroovyjarjarantlr/collections/impl/IndexedVector;
       4: aload_1
       5: invokevirtual #43                 // Method groovyjarjarantlr/preprocessor/Grammar.getName:()Ljava/lang/String;
       8: aload_1
       9: invokevirtual #47                 // Method groovyjarjarantlr/collections/impl/IndexedVector.appendElement:(Ljava/lang/Object;Ljava/lang/Object;)V
      12: return

  public void generateExpandedFile() throws java.io.IOException;
    Code:
       0: aload_0
       1: getfield      #26                 // Field expanded:Z
       4: ifne          8
       7: return
       8: aload_0
       9: aload_0
      10: invokevirtual #51                 // Method getName:()Ljava/lang/String;
      13: invokevirtual #55                 // Method nameForExpandedGrammarFile:(Ljava/lang/String;)Ljava/lang/String;
      16: astore_1
      17: aload_0
      18: getfield      #35                 // Field tool:Lgroovyjarjarantlr/Tool;
      21: aload_1
      22: invokevirtual #61                 // Method groovyjarjarantlr/Tool.openOutputFile:(Ljava/lang/String;)Ljava/io/PrintWriter;
      25: astore_2
      26: aload_2
      27: aload_0
      28: invokevirtual #64                 // Method toString:()Ljava/lang/String;
      31: invokevirtual #70                 // Method java/io/PrintWriter.println:(Ljava/lang/String;)V
      34: aload_2
      35: invokevirtual #73                 // Method java/io/PrintWriter.close:()V
      38: return

  public groovyjarjarantlr.collections.impl.IndexedVector getGrammars();
    Code:
       0: aload_0
       1: getfield      #33                 // Field grammars:Lgroovyjarjarantlr/collections/impl/IndexedVector;
       4: areturn

  public java.lang.String getName();
    Code:
       0: aload_0
       1: getfield      #28                 // Field fileName:Ljava/lang/String;
       4: areturn

  public java.lang.String nameForExpandedGrammarFile(java.lang.String);
    Code:
       0: aload_0
       1: getfield      #26                 // Field expanded:Z
       4: ifeq          34
       7: new           #77                 // class java/lang/StringBuffer
      10: dup
      11: invokespecial #78                 // Method java/lang/StringBuffer."<init>":()V
      14: ldc           #79                 // String expanded
      16: invokevirtual #83                 // Method java/lang/StringBuffer.append:(Ljava/lang/String;)Ljava/lang/StringBuffer;
      19: aload_0
      20: getfield      #35                 // Field tool:Lgroovyjarjarantlr/Tool;
      23: aload_1
      24: invokevirtual #86                 // Method groovyjarjarantlr/Tool.fileMinusPath:(Ljava/lang/String;)Ljava/lang/String;
      27: invokevirtual #83                 // Method java/lang/StringBuffer.append:(Ljava/lang/String;)Ljava/lang/StringBuffer;
      30: invokevirtual #87                 // Method java/lang/StringBuffer.toString:()Ljava/lang/String;
      33: areturn
      34: aload_1
      35: areturn

  public void setExpanded(boolean);
    Code:
       0: aload_0
       1: iload_1
       2: putfield      #26                 // Field expanded:Z
       5: return

  public void addHeaderAction(java.lang.String);
    Code:
       0: new           #77                 // class java/lang/StringBuffer
       3: dup
       4: invokespecial #78                 // Method java/lang/StringBuffer."<init>":()V
       7: aload_0
       8: dup_x1
       9: getfield      #24                 // Field headerAction:Ljava/lang/String;
      12: invokevirtual #83                 // Method java/lang/StringBuffer.append:(Ljava/lang/String;)Ljava/lang/StringBuffer;
      15: aload_1
      16: invokevirtual #83                 // Method java/lang/StringBuffer.append:(Ljava/lang/String;)Ljava/lang/StringBuffer;
      19: ldc           #92                 // String line.separator
      21: invokestatic  #97                 // Method java/lang/System.getProperty:(Ljava/lang/String;)Ljava/lang/String;
      24: invokevirtual #83                 // Method java/lang/StringBuffer.append:(Ljava/lang/String;)Ljava/lang/StringBuffer;
      27: invokevirtual #87                 // Method java/lang/StringBuffer.toString:()Ljava/lang/String;
      30: putfield      #24                 // Field headerAction:Ljava/lang/String;
      33: return

  public void setOptions(groovyjarjarantlr.collections.impl.IndexedVector);
    Code:
       0: aload_0
       1: aload_1
       2: putfield      #101                // Field options:Lgroovyjarjarantlr/collections/impl/IndexedVector;
       5: return

  public java.lang.String toString();
    Code:
       0: aload_0
       1: getfield      #24                 // Field headerAction:Ljava/lang/String;
       4: ifnonnull     12
       7: ldc           #22                 // String
       9: goto          16
      12: aload_0
      13: getfield      #24                 // Field headerAction:Ljava/lang/String;
      16: astore_1
      17: aload_0
      18: getfield      #101                // Field options:Lgroovyjarjarantlr/collections/impl/IndexedVector;
      21: ifnonnull     29
      24: ldc           #22                 // String
      26: goto          36
      29: aload_0
      30: getfield      #101                // Field options:Lgroovyjarjarantlr/collections/impl/IndexedVector;
      33: invokestatic  #107                // Method groovyjarjarantlr/preprocessor/Hierarchy.optionsToString:(Lgroovyjarjarantlr/collections/impl/IndexedVector;)Ljava/lang/String;
      36: astore_2
      37: new           #77                 // class java/lang/StringBuffer
      40: dup
      41: sipush        10000
      44: invokespecial #110                // Method java/lang/StringBuffer."<init>":(I)V
      47: astore_3
      48: aload_3
      49: aload_1
      50: invokevirtual #83                 // Method java/lang/StringBuffer.append:(Ljava/lang/String;)Ljava/lang/StringBuffer;
      53: pop
      54: aload_3
      55: aload_2
      56: invokevirtual #83                 // Method java/lang/StringBuffer.append:(Ljava/lang/String;)Ljava/lang/StringBuffer;
      59: pop
      60: aload_0
      61: getfield      #33                 // Field grammars:Lgroovyjarjarantlr/collections/impl/IndexedVector;
      64: invokevirtual #114                // Method groovyjarjarantlr/collections/impl/IndexedVector.elements:()Ljava/util/Enumeration;
      67: astore        4
      69: aload         4
      71: invokeinterface #120,  1          // InterfaceMethod java/util/Enumeration.hasMoreElements:()Z
      76: ifeq          104
      79: aload         4
      81: invokeinterface #124,  1          // InterfaceMethod java/util/Enumeration.nextElement:()Ljava/lang/Object;
      86: checkcast     #39                 // class groovyjarjarantlr/preprocessor/Grammar
      89: astore        5
      91: aload_3
      92: aload         5
      94: invokevirtual #125                // Method groovyjarjarantlr/preprocessor/Grammar.toString:()Ljava/lang/String;
      97: invokevirtual #83                 // Method java/lang/StringBuffer.append:(Ljava/lang/String;)Ljava/lang/StringBuffer;
     100: pop
     101: goto          69
     104: aload_3
     105: invokevirtual #87                 // Method java/lang/StringBuffer.toString:()Ljava/lang/String;
     108: areturn
}
