Compiled from "BasicParserPool.java"
public class org.opensaml.xml.parse.BasicParserPool$DocumentBuilderProxy extends javax.xml.parsers.DocumentBuilder {
  private javax.xml.parsers.DocumentBuilder builder;

  private org.opensaml.xml.parse.ParserPool owningPool;

  private long owningPoolVersion;

  private boolean returned;

  final org.opensaml.xml.parse.BasicParserPool this$0;

  public org.opensaml.xml.parse.BasicParserPool$DocumentBuilderProxy(org.opensaml.xml.parse.BasicParserPool, javax.xml.parsers.DocumentBuilder, org.opensaml.xml.parse.BasicParserPool, long);
    Code:
       0: aload_0
       1: aload_1
       2: putfield      #1                  // Field this$0:Lorg/opensaml/xml/parse/BasicParserPool;
       5: aload_0
       6: invokespecial #2                  // Method javax/xml/parsers/DocumentBuilder."<init>":()V
       9: aload_0
      10: lload         4
      12: putfield      #3                  // Field owningPoolVersion:J
      15: aload_0
      16: aload_3
      17: putfield      #4                  // Field owningPool:Lorg/opensaml/xml/parse/ParserPool;
      20: aload_0
      21: aload_2
      22: putfield      #5                  // Field builder:Ljavax/xml/parsers/DocumentBuilder;
      25: aload_0
      26: iconst_0
      27: putfield      #6                  // Field returned:Z
      30: return

  public org.w3c.dom.DOMImplementation getDOMImplementation();
    Code:
       0: aload_0
       1: invokevirtual #7                  // Method checkValidState:()V
       4: aload_0
       5: getfield      #5                  // Field builder:Ljavax/xml/parsers/DocumentBuilder;
       8: invokevirtual #8                  // Method javax/xml/parsers/DocumentBuilder.getDOMImplementation:()Lorg/w3c/dom/DOMImplementation;
      11: areturn

  public javax.xml.validation.Schema getSchema();
    Code:
       0: aload_0
       1: invokevirtual #7                  // Method checkValidState:()V
       4: aload_0
       5: getfield      #5                  // Field builder:Ljavax/xml/parsers/DocumentBuilder;
       8: invokevirtual #9                  // Method javax/xml/parsers/DocumentBuilder.getSchema:()Ljavax/xml/validation/Schema;
      11: areturn

  public boolean isNamespaceAware();
    Code:
       0: aload_0
       1: invokevirtual #7                  // Method checkValidState:()V
       4: aload_0
       5: getfield      #5                  // Field builder:Ljavax/xml/parsers/DocumentBuilder;
       8: invokevirtual #10                 // Method javax/xml/parsers/DocumentBuilder.isNamespaceAware:()Z
      11: ireturn

  public boolean isValidating();
    Code:
       0: aload_0
       1: invokevirtual #7                  // Method checkValidState:()V
       4: aload_0
       5: getfield      #5                  // Field builder:Ljavax/xml/parsers/DocumentBuilder;
       8: invokevirtual #11                 // Method javax/xml/parsers/DocumentBuilder.isValidating:()Z
      11: ireturn

  public boolean isXIncludeAware();
    Code:
       0: aload_0
       1: invokevirtual #7                  // Method checkValidState:()V
       4: aload_0
       5: getfield      #5                  // Field builder:Ljavax/xml/parsers/DocumentBuilder;
       8: invokevirtual #12                 // Method javax/xml/parsers/DocumentBuilder.isXIncludeAware:()Z
      11: ireturn

  public org.w3c.dom.Document newDocument();
    Code:
       0: aload_0
       1: invokevirtual #7                  // Method checkValidState:()V
       4: aload_0
       5: getfield      #5                  // Field builder:Ljavax/xml/parsers/DocumentBuilder;
       8: invokevirtual #13                 // Method javax/xml/parsers/DocumentBuilder.newDocument:()Lorg/w3c/dom/Document;
      11: areturn

  public org.w3c.dom.Document parse(java.io.File) throws org.xml.sax.SAXException, java.io.IOException;
    Code:
       0: aload_0
       1: invokevirtual #7                  // Method checkValidState:()V
       4: aload_0
       5: getfield      #5                  // Field builder:Ljavax/xml/parsers/DocumentBuilder;
       8: aload_1
       9: invokevirtual #14                 // Method javax/xml/parsers/DocumentBuilder.parse:(Ljava/io/File;)Lorg/w3c/dom/Document;
      12: areturn

  public org.w3c.dom.Document parse(org.xml.sax.InputSource) throws org.xml.sax.SAXException, java.io.IOException;
    Code:
       0: aload_0
       1: invokevirtual #7                  // Method checkValidState:()V
       4: aload_0
       5: getfield      #5                  // Field builder:Ljavax/xml/parsers/DocumentBuilder;
       8: aload_1
       9: invokevirtual #15                 // Method javax/xml/parsers/DocumentBuilder.parse:(Lorg/xml/sax/InputSource;)Lorg/w3c/dom/Document;
      12: areturn

  public org.w3c.dom.Document parse(java.io.InputStream) throws org.xml.sax.SAXException, java.io.IOException;
    Code:
       0: aload_0
       1: invokevirtual #7                  // Method checkValidState:()V
       4: aload_0
       5: getfield      #5                  // Field builder:Ljavax/xml/parsers/DocumentBuilder;
       8: aload_1
       9: invokevirtual #16                 // Method javax/xml/parsers/DocumentBuilder.parse:(Ljava/io/InputStream;)Lorg/w3c/dom/Document;
      12: areturn

  public org.w3c.dom.Document parse(java.io.InputStream, java.lang.String) throws org.xml.sax.SAXException, java.io.IOException;
    Code:
       0: aload_0
       1: invokevirtual #7                  // Method checkValidState:()V
       4: aload_0
       5: getfield      #5                  // Field builder:Ljavax/xml/parsers/DocumentBuilder;
       8: aload_1
       9: aload_2
      10: invokevirtual #17                 // Method javax/xml/parsers/DocumentBuilder.parse:(Ljava/io/InputStream;Ljava/lang/String;)Lorg/w3c/dom/Document;
      13: areturn

  public org.w3c.dom.Document parse(java.lang.String) throws org.xml.sax.SAXException, java.io.IOException;
    Code:
       0: aload_0
       1: invokevirtual #7                  // Method checkValidState:()V
       4: aload_0
       5: getfield      #5                  // Field builder:Ljavax/xml/parsers/DocumentBuilder;
       8: aload_1
       9: invokevirtual #18                 // Method javax/xml/parsers/DocumentBuilder.parse:(Ljava/lang/String;)Lorg/w3c/dom/Document;
      12: areturn

  public void reset();
    Code:
       0: return

  public void setEntityResolver(org.xml.sax.EntityResolver);
    Code:
       0: aload_0
       1: invokevirtual #7                  // Method checkValidState:()V
       4: return

  public void setErrorHandler(org.xml.sax.ErrorHandler);
    Code:
       0: aload_0
       1: invokevirtual #7                  // Method checkValidState:()V
       4: return

  protected org.opensaml.xml.parse.ParserPool getOwningPool();
    Code:
       0: aload_0
       1: getfield      #4                  // Field owningPool:Lorg/opensaml/xml/parse/ParserPool;
       4: areturn

  protected long getPoolVersion();
    Code:
       0: aload_0
       1: getfield      #3                  // Field owningPoolVersion:J
       4: lreturn

  protected javax.xml.parsers.DocumentBuilder getProxiedBuilder();
    Code:
       0: aload_0
       1: getfield      #5                  // Field builder:Ljavax/xml/parsers/DocumentBuilder;
       4: areturn

  protected boolean isReturned();
    Code:
       0: aload_0
       1: getfield      #6                  // Field returned:Z
       4: ireturn

  protected void setReturned(boolean);
    Code:
       0: aload_0
       1: iload_1
       2: putfield      #6                  // Field returned:Z
       5: return

  protected void checkValidState() throws java.lang.IllegalStateException;
    Code:
       0: aload_0
       1: invokevirtual #19                 // Method isReturned:()Z
       4: ifeq          17
       7: new           #20                 // class java/lang/IllegalStateException
      10: dup
      11: ldc           #21                 // String DocumentBuilderProxy has already been returned to its owning pool
      13: invokespecial #22                 // Method java/lang/IllegalStateException."<init>":(Ljava/lang/String;)V
      16: athrow
      17: return

  protected void finalize() throws java.lang.Throwable;
    Code:
       0: aload_0
       1: invokespecial #23                 // Method java/lang/Object.finalize:()V
       4: aload_0
       5: getfield      #4                  // Field owningPool:Lorg/opensaml/xml/parse/ParserPool;
       8: aload_0
       9: invokeinterface #24,  2           // InterfaceMethod org/opensaml/xml/parse/ParserPool.returnBuilder:(Ljavax/xml/parsers/DocumentBuilder;)V
      14: return
}
