Compiled from "LocalTxInvocationContext.java"
public class org.infinispan.context.impl.LocalTxInvocationContext extends org.infinispan.context.impl.AbstractTxInvocationContext<org.infinispan.transaction.impl.LocalTransaction> {
  public org.infinispan.context.impl.LocalTxInvocationContext(org.infinispan.transaction.impl.LocalTransaction);
    Code:
       0: aload_0
       1: aload_1
       2: aconst_null
       3: invokespecial #1                  // Method org/infinispan/context/impl/AbstractTxInvocationContext."<init>":(Lorg/infinispan/transaction/impl/AbstractCacheTransaction;Lorg/infinispan/remoting/transport/Address;)V
       6: return

  public final boolean isTransactionValid();
    Code:
       0: aload_0
       1: invokevirtual #2                  // Method getTransaction:()Ljavax/transaction/Transaction;
       4: astore_1
       5: iconst_m1
       6: istore_2
       7: aload_1
       8: ifnull        22
      11: aload_1
      12: invokeinterface #3,  1            // InterfaceMethod javax/transaction/Transaction.getStatus:()I
      17: istore_2
      18: goto          22
      21: astore_3
      22: iload_2
      23: ifeq          32
      26: iload_2
      27: bipush        7
      29: if_icmpne     36
      32: iconst_1
      33: goto          37
      36: iconst_0
      37: ireturn
    Exception table:
       from    to  target type
          11    18    21   Class javax/transaction/SystemException

  public final boolean isImplicitTransaction();
    Code:
       0: aload_0
       1: invokevirtual #6                  // Method getCacheTransaction:()Lorg/infinispan/transaction/impl/AbstractCacheTransaction;
       4: checkcast     #7                  // class org/infinispan/transaction/impl/LocalTransaction
       7: invokevirtual #8                  // Method org/infinispan/transaction/impl/LocalTransaction.isImplicitTransaction:()Z
      10: ireturn

  public final boolean isOriginLocal();
    Code:
       0: iconst_1
       1: ireturn

  public final boolean hasLockedKey(java.lang.Object);
    Code:
       0: aload_0
       1: invokevirtual #6                  // Method getCacheTransaction:()Lorg/infinispan/transaction/impl/AbstractCacheTransaction;
       4: checkcast     #7                  // class org/infinispan/transaction/impl/LocalTransaction
       7: aload_1
       8: invokevirtual #9                  // Method org/infinispan/transaction/impl/LocalTransaction.ownsLock:(Ljava/lang/Object;)Z
      11: ireturn

  public final void remoteLocksAcquired(java.util.Collection<org.infinispan.remoting.transport.Address>);
    Code:
       0: aload_0
       1: invokevirtual #6                  // Method getCacheTransaction:()Lorg/infinispan/transaction/impl/AbstractCacheTransaction;
       4: checkcast     #7                  // class org/infinispan/transaction/impl/LocalTransaction
       7: aload_1
       8: invokevirtual #10                 // Method org/infinispan/transaction/impl/LocalTransaction.locksAcquired:(Ljava/util/Collection;)V
      11: return

  public final java.util.Collection<org.infinispan.remoting.transport.Address> getRemoteLocksAcquired();
    Code:
       0: aload_0
       1: invokevirtual #6                  // Method getCacheTransaction:()Lorg/infinispan/transaction/impl/AbstractCacheTransaction;
       4: checkcast     #7                  // class org/infinispan/transaction/impl/LocalTransaction
       7: invokevirtual #11                 // Method org/infinispan/transaction/impl/LocalTransaction.getRemoteLocksAcquired:()Ljava/util/Collection;
      10: areturn

  public final javax.transaction.Transaction getTransaction();
    Code:
       0: aload_0
       1: invokevirtual #6                  // Method getCacheTransaction:()Lorg/infinispan/transaction/impl/AbstractCacheTransaction;
       4: checkcast     #7                  // class org/infinispan/transaction/impl/LocalTransaction
       7: invokevirtual #12                 // Method org/infinispan/transaction/impl/LocalTransaction.getTransaction:()Ljavax/transaction/Transaction;
      10: areturn
}
