Compiled from "MessageTracker.java"
class org.apache.zookeeper.server.util.MessageTracker$BufferedMessage {
  private long timestamp;

  private int messageType;

  private long getTimestamp();
    Code:
       0: aload_0
       1: getfield      #2                  // Field timestamp:J
       4: lreturn

  org.apache.zookeeper.server.util.MessageTracker$BufferedMessage(int);
    Code:
       0: aload_0
       1: invokespecial #3                  // Method java/lang/Object."<init>":()V
       4: aload_0
       5: iload_1
       6: putfield      #4                  // Field messageType:I
       9: aload_0
      10: invokestatic  #5                  // Method java/lang/System.currentTimeMillis:()J
      13: putfield      #2                  // Field timestamp:J
      16: return

  org.apache.zookeeper.server.util.MessageTracker$BufferedMessage(long);
    Code:
       0: aload_0
       1: invokespecial #3                  // Method java/lang/Object."<init>":()V
       4: aload_0
       5: iconst_m1
       6: putfield      #4                  // Field messageType:I
       9: aload_0
      10: lload_1
      11: putfield      #2                  // Field timestamp:J
      14: return

  public java.lang.String toString();
    Code:
       0: aload_0
       1: getfield      #4                  // Field messageType:I
       4: iconst_m1
       5: if_icmpne     50
       8: new           #6                  // class java/lang/StringBuilder
      11: dup
      12: invokespecial #7                  // Method java/lang/StringBuilder."<init>":()V
      15: ldc           #8                  // String TimeStamp:
      17: invokevirtual #9                  // Method java/lang/StringBuilder.append:(Ljava/lang/String;)Ljava/lang/StringBuilder;
      20: new           #10                 // class java/text/SimpleDateFormat
      23: dup
      24: ldc           #11                 // String yyyy-MM-dd HH:mm:ss,SSS
      26: invokespecial #12                 // Method java/text/SimpleDateFormat."<init>":(Ljava/lang/String;)V
      29: new           #13                 // class java/util/Date
      32: dup
      33: aload_0
      34: getfield      #2                  // Field timestamp:J
      37: invokespecial #14                 // Method java/util/Date."<init>":(J)V
      40: invokevirtual #15                 // Method java/text/SimpleDateFormat.format:(Ljava/util/Date;)Ljava/lang/String;
      43: invokevirtual #9                  // Method java/lang/StringBuilder.append:(Ljava/lang/String;)Ljava/lang/StringBuilder;
      46: invokevirtual #16                 // Method java/lang/StringBuilder.toString:()Ljava/lang/String;
      49: areturn
      50: new           #6                  // class java/lang/StringBuilder
      53: dup
      54: invokespecial #7                  // Method java/lang/StringBuilder."<init>":()V
      57: ldc           #8                  // String TimeStamp:
      59: invokevirtual #9                  // Method java/lang/StringBuilder.append:(Ljava/lang/String;)Ljava/lang/StringBuilder;
      62: new           #10                 // class java/text/SimpleDateFormat
      65: dup
      66: ldc           #11                 // String yyyy-MM-dd HH:mm:ss,SSS
      68: invokespecial #12                 // Method java/text/SimpleDateFormat."<init>":(Ljava/lang/String;)V
      71: new           #13                 // class java/util/Date
      74: dup
      75: aload_0
      76: getfield      #2                  // Field timestamp:J
      79: invokespecial #14                 // Method java/util/Date."<init>":(J)V
      82: invokevirtual #15                 // Method java/text/SimpleDateFormat.format:(Ljava/util/Date;)Ljava/lang/String;
      85: invokevirtual #9                  // Method java/lang/StringBuilder.append:(Ljava/lang/String;)Ljava/lang/StringBuilder;
      88: ldc           #17                 // String  Type:
      90: invokevirtual #9                  // Method java/lang/StringBuilder.append:(Ljava/lang/String;)Ljava/lang/StringBuilder;
      93: aload_0
      94: getfield      #4                  // Field messageType:I
      97: invokestatic  #18                 // Method org/apache/zookeeper/server/quorum/Leader.getPacketType:(I)Ljava/lang/String;
     100: invokevirtual #9                  // Method java/lang/StringBuilder.append:(Ljava/lang/String;)Ljava/lang/StringBuilder;
     103: invokevirtual #16                 // Method java/lang/StringBuilder.toString:()Ljava/lang/String;
     106: areturn

  static long access$000(org.apache.zookeeper.server.util.MessageTracker$BufferedMessage);
    Code:
       0: aload_0
       1: invokespecial #1                  // Method getTimestamp:()J
       4: lreturn
}
