Compiled from "AjcMemberMaker.java"
public class org.aspectj.weaver.AjcMemberMaker {
  private static final int PUBLIC_STATIC_FINAL;

  private static final int PRIVATE_STATIC;

  private static final int PUBLIC_STATIC;

  private static final int BRIDGE;

  private static final int VISIBILITY;

  public static final org.aspectj.weaver.UnresolvedType CFLOW_STACK_TYPE;

  public static final org.aspectj.weaver.UnresolvedType AROUND_CLOSURE_TYPE;

  public static final org.aspectj.weaver.UnresolvedType CONVERSIONS_TYPE;

  public static final org.aspectj.weaver.UnresolvedType NO_ASPECT_BOUND_EXCEPTION;

  public static final org.aspectj.weaver.UnresolvedType ASPECT_ANNOTATION;

  public static final org.aspectj.weaver.UnresolvedType BEFORE_ANNOTATION;

  public static final org.aspectj.weaver.UnresolvedType AROUND_ANNOTATION;

  public static final org.aspectj.weaver.UnresolvedType AFTERRETURNING_ANNOTATION;

  public static final org.aspectj.weaver.UnresolvedType AFTERTHROWING_ANNOTATION;

  public static final org.aspectj.weaver.UnresolvedType AFTER_ANNOTATION;

  public static final org.aspectj.weaver.UnresolvedType POINTCUT_ANNOTATION;

  public static final org.aspectj.weaver.UnresolvedType DECLAREERROR_ANNOTATION;

  public static final org.aspectj.weaver.UnresolvedType DECLAREWARNING_ANNOTATION;

  public static final org.aspectj.weaver.UnresolvedType DECLAREPRECEDENCE_ANNOTATION;

  public static final org.aspectj.weaver.UnresolvedType DECLAREPARENTS_ANNOTATION;

  public static final org.aspectj.weaver.UnresolvedType DECLAREMIXIN_ANNOTATION;

  public static final org.aspectj.weaver.UnresolvedType TYPEX_JOINPOINT;

  public static final org.aspectj.weaver.UnresolvedType TYPEX_PROCEEDINGJOINPOINT;

  public static final org.aspectj.weaver.UnresolvedType TYPEX_STATICJOINPOINT;

  public static final org.aspectj.weaver.UnresolvedType TYPEX_ENCLOSINGSTATICJOINPOINT;

  public org.aspectj.weaver.AjcMemberMaker();
    Code:
       0: aload_0
       1: invokespecial #2                  // Method java/lang/Object."<init>":()V
       4: return

  public static org.aspectj.weaver.ResolvedMember ajcPreClinitMethod(org.aspectj.weaver.UnresolvedType);
    Code:
       0: new           #3                  // class org/aspectj/weaver/ResolvedMemberImpl
       3: dup
       4: getstatic     #4                  // Field org/aspectj/weaver/Member.METHOD:Lorg/aspectj/weaver/MemberKind;
       7: aload_0
       8: bipush        10
      10: ldc           #7                  // String ajc$preClinit
      12: ldc           #8                  // String ()V
      14: invokespecial #9                  // Method org/aspectj/weaver/ResolvedMemberImpl."<init>":(Lorg/aspectj/weaver/MemberKind;Lorg/aspectj/weaver/UnresolvedType;ILjava/lang/String;Ljava/lang/String;)V
      17: areturn

  public static org.aspectj.weaver.ResolvedMember ajcPostClinitMethod(org.aspectj.weaver.UnresolvedType);
    Code:
       0: new           #3                  // class org/aspectj/weaver/ResolvedMemberImpl
       3: dup
       4: getstatic     #4                  // Field org/aspectj/weaver/Member.METHOD:Lorg/aspectj/weaver/MemberKind;
       7: aload_0
       8: bipush        10
      10: ldc           #10                 // String ajc$postClinit
      12: ldc           #8                  // String ()V
      14: invokespecial #9                  // Method org/aspectj/weaver/ResolvedMemberImpl."<init>":(Lorg/aspectj/weaver/MemberKind;Lorg/aspectj/weaver/UnresolvedType;ILjava/lang/String;Ljava/lang/String;)V
      17: areturn

  public static org.aspectj.weaver.Member noAspectBoundExceptionInit();
    Code:
       0: new           #3                  // class org/aspectj/weaver/ResolvedMemberImpl
       3: dup
       4: getstatic     #4                  // Field org/aspectj/weaver/Member.METHOD:Lorg/aspectj/weaver/MemberKind;
       7: getstatic     #11                 // Field NO_ASPECT_BOUND_EXCEPTION:Lorg/aspectj/weaver/UnresolvedType;
      10: iconst_1
      11: ldc           #12                 // String <init>
      13: ldc           #8                  // String ()V
      15: invokespecial #9                  // Method org/aspectj/weaver/ResolvedMemberImpl."<init>":(Lorg/aspectj/weaver/MemberKind;Lorg/aspectj/weaver/UnresolvedType;ILjava/lang/String;Ljava/lang/String;)V
      18: areturn

  public static org.aspectj.weaver.Member noAspectBoundExceptionInit2();
    Code:
       0: new           #3                  // class org/aspectj/weaver/ResolvedMemberImpl
       3: dup
       4: getstatic     #4                  // Field org/aspectj/weaver/Member.METHOD:Lorg/aspectj/weaver/MemberKind;
       7: getstatic     #11                 // Field NO_ASPECT_BOUND_EXCEPTION:Lorg/aspectj/weaver/UnresolvedType;
      10: iconst_1
      11: ldc           #12                 // String <init>
      13: ldc           #13                 // String (Ljava/lang/String;Ljava/lang/Throwable;)V
      15: invokespecial #9                  // Method org/aspectj/weaver/ResolvedMemberImpl."<init>":(Lorg/aspectj/weaver/MemberKind;Lorg/aspectj/weaver/UnresolvedType;ILjava/lang/String;Ljava/lang/String;)V
      18: areturn

  public static org.aspectj.weaver.Member noAspectBoundExceptionInitWithCause();
    Code:
       0: new           #3                  // class org/aspectj/weaver/ResolvedMemberImpl
       3: dup
       4: getstatic     #4                  // Field org/aspectj/weaver/Member.METHOD:Lorg/aspectj/weaver/MemberKind;
       7: getstatic     #11                 // Field NO_ASPECT_BOUND_EXCEPTION:Lorg/aspectj/weaver/UnresolvedType;
      10: iconst_1
      11: ldc           #12                 // String <init>
      13: ldc           #13                 // String (Ljava/lang/String;Ljava/lang/Throwable;)V
      15: invokespecial #9                  // Method org/aspectj/weaver/ResolvedMemberImpl."<init>":(Lorg/aspectj/weaver/MemberKind;Lorg/aspectj/weaver/UnresolvedType;ILjava/lang/String;Ljava/lang/String;)V
      18: areturn

  public static org.aspectj.weaver.ResolvedMember perCflowPush(org.aspectj.weaver.UnresolvedType);
    Code:
       0: new           #3                  // class org/aspectj/weaver/ResolvedMemberImpl
       3: dup
       4: getstatic     #4                  // Field org/aspectj/weaver/Member.METHOD:Lorg/aspectj/weaver/MemberKind;
       7: aload_0
       8: bipush        9
      10: ldc           #14                 // String ajc$perCflowPush
      12: ldc           #8                  // String ()V
      14: invokespecial #9                  // Method org/aspectj/weaver/ResolvedMemberImpl."<init>":(Lorg/aspectj/weaver/MemberKind;Lorg/aspectj/weaver/UnresolvedType;ILjava/lang/String;Ljava/lang/String;)V
      17: areturn

  public static org.aspectj.weaver.ResolvedMember perCflowField(org.aspectj.weaver.UnresolvedType);
    Code:
       0: new           #3                  // class org/aspectj/weaver/ResolvedMemberImpl
       3: dup
       4: getstatic     #15                 // Field org/aspectj/weaver/Member.FIELD:Lorg/aspectj/weaver/MemberKind;
       7: aload_0
       8: bipush        25
      10: ldc           #16                 // String ajc$perCflowStack
      12: getstatic     #17                 // Field CFLOW_STACK_TYPE:Lorg/aspectj/weaver/UnresolvedType;
      15: invokevirtual #18                 // Method org/aspectj/weaver/UnresolvedType.getSignature:()Ljava/lang/String;
      18: invokespecial #9                  // Method org/aspectj/weaver/ResolvedMemberImpl."<init>":(Lorg/aspectj/weaver/MemberKind;Lorg/aspectj/weaver/UnresolvedType;ILjava/lang/String;Ljava/lang/String;)V
      21: areturn

  public static org.aspectj.weaver.ResolvedMember perSingletonField(org.aspectj.weaver.UnresolvedType);
    Code:
       0: new           #3                  // class org/aspectj/weaver/ResolvedMemberImpl
       3: dup
       4: getstatic     #15                 // Field org/aspectj/weaver/Member.FIELD:Lorg/aspectj/weaver/MemberKind;
       7: aload_0
       8: bipush        25
      10: ldc           #19                 // String ajc$perSingletonInstance
      12: aload_0
      13: invokevirtual #18                 // Method org/aspectj/weaver/UnresolvedType.getSignature:()Ljava/lang/String;
      16: invokespecial #9                  // Method org/aspectj/weaver/ResolvedMemberImpl."<init>":(Lorg/aspectj/weaver/MemberKind;Lorg/aspectj/weaver/UnresolvedType;ILjava/lang/String;Ljava/lang/String;)V
      19: areturn

  public static org.aspectj.weaver.ResolvedMember initFailureCauseField(org.aspectj.weaver.UnresolvedType);
    Code:
       0: new           #3                  // class org/aspectj/weaver/ResolvedMemberImpl
       3: dup
       4: getstatic     #15                 // Field org/aspectj/weaver/Member.FIELD:Lorg/aspectj/weaver/MemberKind;
       7: aload_0
       8: bipush        10
      10: ldc           #20                 // String ajc$initFailureCause
      12: getstatic     #21                 // Field org/aspectj/weaver/UnresolvedType.THROWABLE:Lorg/aspectj/weaver/UnresolvedType;
      15: invokevirtual #18                 // Method org/aspectj/weaver/UnresolvedType.getSignature:()Ljava/lang/String;
      18: invokespecial #9                  // Method org/aspectj/weaver/ResolvedMemberImpl."<init>":(Lorg/aspectj/weaver/MemberKind;Lorg/aspectj/weaver/UnresolvedType;ILjava/lang/String;Ljava/lang/String;)V
      21: areturn

  public static org.aspectj.weaver.ResolvedMember perObjectField(org.aspectj.weaver.UnresolvedType, org.aspectj.weaver.ResolvedType);
    Code:
       0: iconst_2
       1: istore_2
       2: getstatic     #22                 // Field org/aspectj/weaver/UnresolvedType.SERIALIZABLE:Lorg/aspectj/weaver/UnresolvedType;
       5: aload_1
       6: invokevirtual #23                 // Method org/aspectj/weaver/ResolvedType.getWorld:()Lorg/aspectj/weaver/World;
       9: invokevirtual #24                 // Method org/aspectj/weaver/UnresolvedType.resolve:(Lorg/aspectj/weaver/World;)Lorg/aspectj/weaver/ResolvedType;
      12: aload_1
      13: invokevirtual #25                 // Method org/aspectj/weaver/ResolvedType.isAssignableFrom:(Lorg/aspectj/weaver/ResolvedType;)Z
      16: ifne          25
      19: iload_2
      20: sipush        128
      23: ior
      24: istore_2
      25: new           #3                  // class org/aspectj/weaver/ResolvedMemberImpl
      28: dup
      29: getstatic     #15                 // Field org/aspectj/weaver/Member.FIELD:Lorg/aspectj/weaver/MemberKind;
      32: aload_0
      33: iload_2
      34: aload_1
      35: aload_1
      36: invokestatic  #26                 // Method org/aspectj/weaver/NameMangler.perObjectInterfaceField:(Lorg/aspectj/weaver/UnresolvedType;)Ljava/lang/String;
      39: getstatic     #27                 // Field org/aspectj/weaver/UnresolvedType.NONE:[Lorg/aspectj/weaver/UnresolvedType;
      42: invokespecial #28                 // Method org/aspectj/weaver/ResolvedMemberImpl."<init>":(Lorg/aspectj/weaver/MemberKind;Lorg/aspectj/weaver/UnresolvedType;ILorg/aspectj/weaver/UnresolvedType;Ljava/lang/String;[Lorg/aspectj/weaver/UnresolvedType;)V
      45: areturn

  public static org.aspectj.weaver.ResolvedMember perTypeWithinField(org.aspectj.weaver.UnresolvedType, org.aspectj.weaver.ResolvedType);
    Code:
       0: bipush        10
       2: istore_2
       3: aload_1
       4: invokestatic  #29                 // Method isSerializableAspect:(Lorg/aspectj/weaver/ResolvedType;)Z
       7: ifne          16
      10: iload_2
      11: sipush        128
      14: ior
      15: istore_2
      16: new           #3                  // class org/aspectj/weaver/ResolvedMemberImpl
      19: dup
      20: getstatic     #15                 // Field org/aspectj/weaver/Member.FIELD:Lorg/aspectj/weaver/MemberKind;
      23: aload_0
      24: iload_2
      25: aload_1
      26: aload_1
      27: invokestatic  #30                 // Method org/aspectj/weaver/NameMangler.perTypeWithinFieldForTarget:(Lorg/aspectj/weaver/UnresolvedType;)Ljava/lang/String;
      30: getstatic     #27                 // Field org/aspectj/weaver/UnresolvedType.NONE:[Lorg/aspectj/weaver/UnresolvedType;
      33: invokespecial #28                 // Method org/aspectj/weaver/ResolvedMemberImpl."<init>":(Lorg/aspectj/weaver/MemberKind;Lorg/aspectj/weaver/UnresolvedType;ILorg/aspectj/weaver/UnresolvedType;Ljava/lang/String;[Lorg/aspectj/weaver/UnresolvedType;)V
      36: areturn

  public static org.aspectj.weaver.ResolvedMember perTypeWithinWithinTypeField(org.aspectj.weaver.UnresolvedType, org.aspectj.weaver.ResolvedType);
    Code:
       0: iconst_2
       1: istore_2
       2: aload_1
       3: invokestatic  #29                 // Method isSerializableAspect:(Lorg/aspectj/weaver/ResolvedType;)Z
       6: ifne          15
       9: iload_2
      10: sipush        128
      13: ior
      14: istore_2
      15: new           #3                  // class org/aspectj/weaver/ResolvedMemberImpl
      18: dup
      19: getstatic     #15                 // Field org/aspectj/weaver/Member.FIELD:Lorg/aspectj/weaver/MemberKind;
      22: aload_0
      23: iload_2
      24: getstatic     #31                 // Field org/aspectj/weaver/UnresolvedType.JL_STRING:Lorg/aspectj/weaver/UnresolvedType;
      27: ldc           #32                 // String ajc$withinType
      29: getstatic     #27                 // Field org/aspectj/weaver/UnresolvedType.NONE:[Lorg/aspectj/weaver/UnresolvedType;
      32: invokespecial #28                 // Method org/aspectj/weaver/ResolvedMemberImpl."<init>":(Lorg/aspectj/weaver/MemberKind;Lorg/aspectj/weaver/UnresolvedType;ILorg/aspectj/weaver/UnresolvedType;Ljava/lang/String;[Lorg/aspectj/weaver/UnresolvedType;)V
      35: areturn

  private static boolean isSerializableAspect(org.aspectj.weaver.ResolvedType);
    Code:
       0: getstatic     #22                 // Field org/aspectj/weaver/UnresolvedType.SERIALIZABLE:Lorg/aspectj/weaver/UnresolvedType;
       3: aload_0
       4: invokevirtual #23                 // Method org/aspectj/weaver/ResolvedType.getWorld:()Lorg/aspectj/weaver/World;
       7: invokevirtual #24                 // Method org/aspectj/weaver/UnresolvedType.resolve:(Lorg/aspectj/weaver/World;)Lorg/aspectj/weaver/ResolvedType;
      10: aload_0
      11: invokevirtual #25                 // Method org/aspectj/weaver/ResolvedType.isAssignableFrom:(Lorg/aspectj/weaver/ResolvedType;)Z
      14: ireturn

  public static org.aspectj.weaver.ResolvedMember perObjectBind(org.aspectj.weaver.UnresolvedType);
    Code:
       0: new           #3                  // class org/aspectj/weaver/ResolvedMemberImpl
       3: dup
       4: getstatic     #4                  // Field org/aspectj/weaver/Member.METHOD:Lorg/aspectj/weaver/MemberKind;
       7: aload_0
       8: bipush        41
      10: ldc           #33                 // String ajc$perObjectBind
      12: ldc           #34                 // String (Ljava/lang/Object;)V
      14: invokespecial #9                  // Method org/aspectj/weaver/ResolvedMemberImpl."<init>":(Lorg/aspectj/weaver/MemberKind;Lorg/aspectj/weaver/UnresolvedType;ILjava/lang/String;Ljava/lang/String;)V
      17: areturn

  public static org.aspectj.weaver.ResolvedMember perTypeWithinGetInstance(org.aspectj.weaver.UnresolvedType);
    Code:
       0: new           #3                  // class org/aspectj/weaver/ResolvedMemberImpl
       3: dup
       4: getstatic     #4                  // Field org/aspectj/weaver/Member.METHOD:Lorg/aspectj/weaver/MemberKind;
       7: aload_0
       8: bipush        10
      10: aload_0
      11: ldc           #35                 // String ajc$getInstance
      13: iconst_1
      14: anewarray     #36                 // class org/aspectj/weaver/UnresolvedType
      17: dup
      18: iconst_0
      19: getstatic     #37                 // Field org/aspectj/weaver/UnresolvedType.JL_CLASS:Lorg/aspectj/weaver/UnresolvedType;
      22: aastore
      23: invokespecial #28                 // Method org/aspectj/weaver/ResolvedMemberImpl."<init>":(Lorg/aspectj/weaver/MemberKind;Lorg/aspectj/weaver/UnresolvedType;ILorg/aspectj/weaver/UnresolvedType;Ljava/lang/String;[Lorg/aspectj/weaver/UnresolvedType;)V
      26: astore_1
      27: aload_1
      28: areturn

  public static org.aspectj.weaver.ResolvedMember perTypeWithinGetWithinTypeNameMethod(org.aspectj.weaver.UnresolvedType, boolean);
    Code:
       0: new           #3                  // class org/aspectj/weaver/ResolvedMemberImpl
       3: dup
       4: getstatic     #4                  // Field org/aspectj/weaver/Member.METHOD:Lorg/aspectj/weaver/MemberKind;
       7: aload_0
       8: iconst_1
       9: getstatic     #31                 // Field org/aspectj/weaver/UnresolvedType.JL_STRING:Lorg/aspectj/weaver/UnresolvedType;
      12: ldc           #38                 // String getWithinTypeName
      14: getstatic     #27                 // Field org/aspectj/weaver/UnresolvedType.NONE:[Lorg/aspectj/weaver/UnresolvedType;
      17: invokespecial #28                 // Method org/aspectj/weaver/ResolvedMemberImpl."<init>":(Lorg/aspectj/weaver/MemberKind;Lorg/aspectj/weaver/UnresolvedType;ILorg/aspectj/weaver/UnresolvedType;Ljava/lang/String;[Lorg/aspectj/weaver/UnresolvedType;)V
      20: astore_2
      21: aload_2
      22: areturn

  public static org.aspectj.weaver.ResolvedMember perTypeWithinCreateAspectInstance(org.aspectj.weaver.UnresolvedType);
    Code:
       0: new           #3                  // class org/aspectj/weaver/ResolvedMemberImpl
       3: dup
       4: getstatic     #4                  // Field org/aspectj/weaver/Member.METHOD:Lorg/aspectj/weaver/MemberKind;
       7: aload_0
       8: bipush        9
      10: aload_0
      11: ldc           #39                 // String ajc$createAspectInstance
      13: iconst_1
      14: anewarray     #36                 // class org/aspectj/weaver/UnresolvedType
      17: dup
      18: iconst_0
      19: ldc           #40                 // String Ljava/lang/String;
      21: invokestatic  #41                 // Method org/aspectj/weaver/UnresolvedType.forSignature:(Ljava/lang/String;)Lorg/aspectj/weaver/UnresolvedType;
      24: aastore
      25: iconst_0
      26: anewarray     #36                 // class org/aspectj/weaver/UnresolvedType
      29: invokespecial #42                 // Method org/aspectj/weaver/ResolvedMemberImpl."<init>":(Lorg/aspectj/weaver/MemberKind;Lorg/aspectj/weaver/UnresolvedType;ILorg/aspectj/weaver/UnresolvedType;Ljava/lang/String;[Lorg/aspectj/weaver/UnresolvedType;[Lorg/aspectj/weaver/UnresolvedType;)V
      32: astore_1
      33: aload_1
      34: areturn

  public static org.aspectj.weaver.UnresolvedType perObjectInterfaceType(org.aspectj.weaver.UnresolvedType);
    Code:
       0: new           #43                 // class java/lang/StringBuilder
       3: dup
       4: invokespecial #44                 // Method java/lang/StringBuilder."<init>":()V
       7: aload_0
       8: invokevirtual #45                 // Method org/aspectj/weaver/UnresolvedType.getName:()Ljava/lang/String;
      11: invokevirtual #46                 // Method java/lang/StringBuilder.append:(Ljava/lang/String;)Ljava/lang/StringBuilder;
      14: ldc           #47                 // String $ajcMightHaveAspect
      16: invokevirtual #46                 // Method java/lang/StringBuilder.append:(Ljava/lang/String;)Ljava/lang/StringBuilder;
      19: invokevirtual #48                 // Method java/lang/StringBuilder.toString:()Ljava/lang/String;
      22: invokestatic  #49                 // Method org/aspectj/weaver/UnresolvedType.forName:(Ljava/lang/String;)Lorg/aspectj/weaver/UnresolvedType;
      25: areturn

  public static org.aspectj.weaver.ResolvedMember perObjectInterfaceGet(org.aspectj.weaver.UnresolvedType);
    Code:
       0: new           #3                  // class org/aspectj/weaver/ResolvedMemberImpl
       3: dup
       4: getstatic     #4                  // Field org/aspectj/weaver/Member.METHOD:Lorg/aspectj/weaver/MemberKind;
       7: aload_0
       8: invokestatic  #50                 // Method perObjectInterfaceType:(Lorg/aspectj/weaver/UnresolvedType;)Lorg/aspectj/weaver/UnresolvedType;
      11: sipush        1025
      14: aload_0
      15: invokestatic  #51                 // Method org/aspectj/weaver/NameMangler.perObjectInterfaceGet:(Lorg/aspectj/weaver/UnresolvedType;)Ljava/lang/String;
      18: new           #43                 // class java/lang/StringBuilder
      21: dup
      22: invokespecial #44                 // Method java/lang/StringBuilder."<init>":()V
      25: ldc           #52                 // String ()
      27: invokevirtual #46                 // Method java/lang/StringBuilder.append:(Ljava/lang/String;)Ljava/lang/StringBuilder;
      30: aload_0
      31: invokevirtual #18                 // Method org/aspectj/weaver/UnresolvedType.getSignature:()Ljava/lang/String;
      34: invokevirtual #46                 // Method java/lang/StringBuilder.append:(Ljava/lang/String;)Ljava/lang/StringBuilder;
      37: invokevirtual #48                 // Method java/lang/StringBuilder.toString:()Ljava/lang/String;
      40: invokespecial #9                  // Method org/aspectj/weaver/ResolvedMemberImpl."<init>":(Lorg/aspectj/weaver/MemberKind;Lorg/aspectj/weaver/UnresolvedType;ILjava/lang/String;Ljava/lang/String;)V
      43: areturn

  public static org.aspectj.weaver.ResolvedMember perObjectInterfaceSet(org.aspectj.weaver.UnresolvedType);
    Code:
       0: new           #3                  // class org/aspectj/weaver/ResolvedMemberImpl
       3: dup
       4: getstatic     #4                  // Field org/aspectj/weaver/Member.METHOD:Lorg/aspectj/weaver/MemberKind;
       7: aload_0
       8: invokestatic  #50                 // Method perObjectInterfaceType:(Lorg/aspectj/weaver/UnresolvedType;)Lorg/aspectj/weaver/UnresolvedType;
      11: sipush        1025
      14: aload_0
      15: invokestatic  #53                 // Method org/aspectj/weaver/NameMangler.perObjectInterfaceSet:(Lorg/aspectj/weaver/UnresolvedType;)Ljava/lang/String;
      18: new           #43                 // class java/lang/StringBuilder
      21: dup
      22: invokespecial #44                 // Method java/lang/StringBuilder."<init>":()V
      25: ldc           #54                 // String (
      27: invokevirtual #46                 // Method java/lang/StringBuilder.append:(Ljava/lang/String;)Ljava/lang/StringBuilder;
      30: aload_0
      31: invokevirtual #18                 // Method org/aspectj/weaver/UnresolvedType.getSignature:()Ljava/lang/String;
      34: invokevirtual #46                 // Method java/lang/StringBuilder.append:(Ljava/lang/String;)Ljava/lang/StringBuilder;
      37: ldc           #55                 // String )V
      39: invokevirtual #46                 // Method java/lang/StringBuilder.append:(Ljava/lang/String;)Ljava/lang/StringBuilder;
      42: invokevirtual #48                 // Method java/lang/StringBuilder.toString:()Ljava/lang/String;
      45: invokespecial #9                  // Method org/aspectj/weaver/ResolvedMemberImpl."<init>":(Lorg/aspectj/weaver/MemberKind;Lorg/aspectj/weaver/UnresolvedType;ILjava/lang/String;Ljava/lang/String;)V
      48: areturn

  public static org.aspectj.weaver.ResolvedMember perTypeWithinLocalAspectOf(org.aspectj.weaver.UnresolvedType, org.aspectj.weaver.UnresolvedType);
    Code:
       0: new           #3                  // class org/aspectj/weaver/ResolvedMemberImpl
       3: dup
       4: getstatic     #4                  // Field org/aspectj/weaver/Member.METHOD:Lorg/aspectj/weaver/MemberKind;
       7: aload_0
       8: bipush        9
      10: aload_1
      11: invokestatic  #56                 // Method org/aspectj/weaver/NameMangler.perTypeWithinLocalAspectOf:(Lorg/aspectj/weaver/UnresolvedType;)Ljava/lang/String;
      14: new           #43                 // class java/lang/StringBuilder
      17: dup
      18: invokespecial #44                 // Method java/lang/StringBuilder."<init>":()V
      21: ldc           #52                 // String ()
      23: invokevirtual #46                 // Method java/lang/StringBuilder.append:(Ljava/lang/String;)Ljava/lang/StringBuilder;
      26: aload_1
      27: invokevirtual #18                 // Method org/aspectj/weaver/UnresolvedType.getSignature:()Ljava/lang/String;
      30: invokevirtual #46                 // Method java/lang/StringBuilder.append:(Ljava/lang/String;)Ljava/lang/StringBuilder;
      33: invokevirtual #48                 // Method java/lang/StringBuilder.toString:()Ljava/lang/String;
      36: invokespecial #9                  // Method org/aspectj/weaver/ResolvedMemberImpl."<init>":(Lorg/aspectj/weaver/MemberKind;Lorg/aspectj/weaver/UnresolvedType;ILjava/lang/String;Ljava/lang/String;)V
      39: areturn

  public static org.aspectj.weaver.ResolvedMember perSingletonAspectOfMethod(org.aspectj.weaver.UnresolvedType);
    Code:
       0: new           #3                  // class org/aspectj/weaver/ResolvedMemberImpl
       3: dup
       4: getstatic     #4                  // Field org/aspectj/weaver/Member.METHOD:Lorg/aspectj/weaver/MemberKind;
       7: aload_0
       8: bipush        9
      10: ldc           #57                 // String aspectOf
      12: new           #43                 // class java/lang/StringBuilder
      15: dup
      16: invokespecial #44                 // Method java/lang/StringBuilder."<init>":()V
      19: ldc           #52                 // String ()
      21: invokevirtual #46                 // Method java/lang/StringBuilder.append:(Ljava/lang/String;)Ljava/lang/StringBuilder;
      24: aload_0
      25: invokevirtual #18                 // Method org/aspectj/weaver/UnresolvedType.getSignature:()Ljava/lang/String;
      28: invokevirtual #46                 // Method java/lang/StringBuilder.append:(Ljava/lang/String;)Ljava/lang/StringBuilder;
      31: invokevirtual #48                 // Method java/lang/StringBuilder.toString:()Ljava/lang/String;
      34: invokespecial #9                  // Method org/aspectj/weaver/ResolvedMemberImpl."<init>":(Lorg/aspectj/weaver/MemberKind;Lorg/aspectj/weaver/UnresolvedType;ILjava/lang/String;Ljava/lang/String;)V
      37: areturn

  public static org.aspectj.weaver.ResolvedMember perSingletonHasAspectMethod(org.aspectj.weaver.UnresolvedType);
    Code:
       0: new           #3                  // class org/aspectj/weaver/ResolvedMemberImpl
       3: dup
       4: getstatic     #4                  // Field org/aspectj/weaver/Member.METHOD:Lorg/aspectj/weaver/MemberKind;
       7: aload_0
       8: bipush        9
      10: ldc           #58                 // String hasAspect
      12: ldc           #59                 // String ()Z
      14: invokespecial #9                  // Method org/aspectj/weaver/ResolvedMemberImpl."<init>":(Lorg/aspectj/weaver/MemberKind;Lorg/aspectj/weaver/UnresolvedType;ILjava/lang/String;Ljava/lang/String;)V
      17: areturn

  public static org.aspectj.weaver.ResolvedMember perCflowAspectOfMethod(org.aspectj.weaver.UnresolvedType);
    Code:
       0: aload_0
       1: invokestatic  #60                 // Method perSingletonAspectOfMethod:(Lorg/aspectj/weaver/UnresolvedType;)Lorg/aspectj/weaver/ResolvedMember;
       4: areturn

  public static org.aspectj.weaver.ResolvedMember perCflowHasAspectMethod(org.aspectj.weaver.UnresolvedType);
    Code:
       0: aload_0
       1: invokestatic  #61                 // Method perSingletonHasAspectMethod:(Lorg/aspectj/weaver/UnresolvedType;)Lorg/aspectj/weaver/ResolvedMember;
       4: areturn

  public static org.aspectj.weaver.ResolvedMember perObjectAspectOfMethod(org.aspectj.weaver.UnresolvedType);
    Code:
       0: new           #3                  // class org/aspectj/weaver/ResolvedMemberImpl
       3: dup
       4: getstatic     #4                  // Field org/aspectj/weaver/Member.METHOD:Lorg/aspectj/weaver/MemberKind;
       7: aload_0
       8: bipush        9
      10: ldc           #57                 // String aspectOf
      12: new           #43                 // class java/lang/StringBuilder
      15: dup
      16: invokespecial #44                 // Method java/lang/StringBuilder."<init>":()V
      19: ldc           #62                 // String (Ljava/lang/Object;)
      21: invokevirtual #46                 // Method java/lang/StringBuilder.append:(Ljava/lang/String;)Ljava/lang/StringBuilder;
      24: aload_0
      25: invokevirtual #18                 // Method org/aspectj/weaver/UnresolvedType.getSignature:()Ljava/lang/String;
      28: invokevirtual #46                 // Method java/lang/StringBuilder.append:(Ljava/lang/String;)Ljava/lang/StringBuilder;
      31: invokevirtual #48                 // Method java/lang/StringBuilder.toString:()Ljava/lang/String;
      34: invokespecial #9                  // Method org/aspectj/weaver/ResolvedMemberImpl."<init>":(Lorg/aspectj/weaver/MemberKind;Lorg/aspectj/weaver/UnresolvedType;ILjava/lang/String;Ljava/lang/String;)V
      37: areturn

  public static org.aspectj.weaver.ResolvedMember perObjectHasAspectMethod(org.aspectj.weaver.UnresolvedType);
    Code:
       0: new           #3                  // class org/aspectj/weaver/ResolvedMemberImpl
       3: dup
       4: getstatic     #4                  // Field org/aspectj/weaver/Member.METHOD:Lorg/aspectj/weaver/MemberKind;
       7: aload_0
       8: bipush        9
      10: ldc           #58                 // String hasAspect
      12: ldc           #63                 // String (Ljava/lang/Object;)Z
      14: invokespecial #9                  // Method org/aspectj/weaver/ResolvedMemberImpl."<init>":(Lorg/aspectj/weaver/MemberKind;Lorg/aspectj/weaver/UnresolvedType;ILjava/lang/String;Ljava/lang/String;)V
      17: areturn

  public static org.aspectj.weaver.ResolvedMember perTypeWithinAspectOfMethod(org.aspectj.weaver.UnresolvedType, boolean);
    Code:
       0: aconst_null
       1: astore_2
       2: iload_1
       3: ifeq          15
       6: ldc           #64                 // String java.lang.Class
       8: invokestatic  #65                 // Method org/aspectj/weaver/UnresolvedType.forRawTypeName:(Ljava/lang/String;)Lorg/aspectj/weaver/UnresolvedType;
      11: astore_2
      12: goto          21
      15: ldc           #66                 // String Ljava/lang/Class;
      17: invokestatic  #41                 // Method org/aspectj/weaver/UnresolvedType.forSignature:(Ljava/lang/String;)Lorg/aspectj/weaver/UnresolvedType;
      20: astore_2
      21: new           #3                  // class org/aspectj/weaver/ResolvedMemberImpl
      24: dup
      25: getstatic     #4                  // Field org/aspectj/weaver/Member.METHOD:Lorg/aspectj/weaver/MemberKind;
      28: aload_0
      29: bipush        9
      31: aload_0
      32: ldc           #57                 // String aspectOf
      34: iconst_1
      35: anewarray     #36                 // class org/aspectj/weaver/UnresolvedType
      38: dup
      39: iconst_0
      40: aload_2
      41: aastore
      42: invokespecial #28                 // Method org/aspectj/weaver/ResolvedMemberImpl."<init>":(Lorg/aspectj/weaver/MemberKind;Lorg/aspectj/weaver/UnresolvedType;ILorg/aspectj/weaver/UnresolvedType;Ljava/lang/String;[Lorg/aspectj/weaver/UnresolvedType;)V
      45: areturn

  public static org.aspectj.weaver.ResolvedMember perTypeWithinHasAspectMethod(org.aspectj.weaver.UnresolvedType, boolean);
    Code:
       0: aconst_null
       1: astore_2
       2: iload_1
       3: ifeq          15
       6: ldc           #64                 // String java.lang.Class
       8: invokestatic  #65                 // Method org/aspectj/weaver/UnresolvedType.forRawTypeName:(Ljava/lang/String;)Lorg/aspectj/weaver/UnresolvedType;
      11: astore_2
      12: goto          21
      15: ldc           #66                 // String Ljava/lang/Class;
      17: invokestatic  #41                 // Method org/aspectj/weaver/UnresolvedType.forSignature:(Ljava/lang/String;)Lorg/aspectj/weaver/UnresolvedType;
      20: astore_2
      21: new           #3                  // class org/aspectj/weaver/ResolvedMemberImpl
      24: dup
      25: getstatic     #4                  // Field org/aspectj/weaver/Member.METHOD:Lorg/aspectj/weaver/MemberKind;
      28: aload_0
      29: bipush        9
      31: getstatic     #67                 // Field org/aspectj/weaver/UnresolvedType.BOOLEAN:Lorg/aspectj/weaver/UnresolvedType;
      34: ldc           #58                 // String hasAspect
      36: iconst_1
      37: anewarray     #36                 // class org/aspectj/weaver/UnresolvedType
      40: dup
      41: iconst_0
      42: aload_2
      43: aastore
      44: invokespecial #28                 // Method org/aspectj/weaver/ResolvedMemberImpl."<init>":(Lorg/aspectj/weaver/MemberKind;Lorg/aspectj/weaver/UnresolvedType;ILorg/aspectj/weaver/UnresolvedType;Ljava/lang/String;[Lorg/aspectj/weaver/UnresolvedType;)V
      47: areturn

  public static org.aspectj.weaver.ResolvedMember privilegedAccessMethodForMethod(org.aspectj.weaver.UnresolvedType, org.aspectj.weaver.ResolvedMember);
    Code:
       0: new           #3                  // class org/aspectj/weaver/ResolvedMemberImpl
       3: dup
       4: getstatic     #4                  // Field org/aspectj/weaver/Member.METHOD:Lorg/aspectj/weaver/MemberKind;
       7: aload_1
       8: invokeinterface #68,  1           // InterfaceMethod org/aspectj/weaver/ResolvedMember.getDeclaringType:()Lorg/aspectj/weaver/UnresolvedType;
      13: iconst_1
      14: aload_1
      15: invokeinterface #69,  1           // InterfaceMethod org/aspectj/weaver/ResolvedMember.getModifiers:()I
      20: invokestatic  #70                 // Method java/lang/reflect/Modifier.isStatic:(I)Z
      23: ifeq          31
      26: bipush        8
      28: goto          32
      31: iconst_0
      32: ior
      33: aload_1
      34: invokeinterface #71,  1           // InterfaceMethod org/aspectj/weaver/ResolvedMember.getReturnType:()Lorg/aspectj/weaver/UnresolvedType;
      39: aload_1
      40: invokeinterface #72,  1           // InterfaceMethod org/aspectj/weaver/ResolvedMember.getName:()Ljava/lang/String;
      45: aload_1
      46: invokeinterface #68,  1           // InterfaceMethod org/aspectj/weaver/ResolvedMember.getDeclaringType:()Lorg/aspectj/weaver/UnresolvedType;
      51: aload_0
      52: invokestatic  #73                 // Method org/aspectj/weaver/NameMangler.privilegedAccessMethodForMethod:(Ljava/lang/String;Lorg/aspectj/weaver/UnresolvedType;Lorg/aspectj/weaver/UnresolvedType;)Ljava/lang/String;
      55: aload_1
      56: invokeinterface #74,  1           // InterfaceMethod org/aspectj/weaver/ResolvedMember.getParameterTypes:()[Lorg/aspectj/weaver/UnresolvedType;
      61: aload_1
      62: invokeinterface #75,  1           // InterfaceMethod org/aspectj/weaver/ResolvedMember.getExceptions:()[Lorg/aspectj/weaver/UnresolvedType;
      67: invokespecial #42                 // Method org/aspectj/weaver/ResolvedMemberImpl."<init>":(Lorg/aspectj/weaver/MemberKind;Lorg/aspectj/weaver/UnresolvedType;ILorg/aspectj/weaver/UnresolvedType;Ljava/lang/String;[Lorg/aspectj/weaver/UnresolvedType;[Lorg/aspectj/weaver/UnresolvedType;)V
      70: areturn

  public static org.aspectj.weaver.ResolvedMember privilegedAccessMethodForFieldGet(org.aspectj.weaver.UnresolvedType, org.aspectj.weaver.Member, boolean);
    Code:
       0: aload_1
       1: invokeinterface #76,  1           // InterfaceMethod org/aspectj/weaver/Member.getDeclaringType:()Lorg/aspectj/weaver/UnresolvedType;
       6: astore_3
       7: iload_2
       8: ifeq          94
      11: aconst_null
      12: astore        4
      14: aload_1
      15: invokeinterface #77,  1           // InterfaceMethod org/aspectj/weaver/Member.getModifiers:()I
      20: invokestatic  #70                 // Method java/lang/reflect/Modifier.isStatic:(I)Z
      23: ifeq          34
      26: getstatic     #78                 // Field org/aspectj/weaver/ResolvedType.NONE:[Lorg/aspectj/weaver/ResolvedType;
      29: astore        4
      31: goto          44
      34: iconst_1
      35: anewarray     #36                 // class org/aspectj/weaver/UnresolvedType
      38: dup
      39: iconst_0
      40: aload_3
      41: aastore
      42: astore        4
      44: new           #79                 // class java/lang/StringBuffer
      47: dup
      48: ldc           #80                 // String ajc$get$
      50: invokespecial #81                 // Method java/lang/StringBuffer."<init>":(Ljava/lang/String;)V
      53: astore        5
      55: aload         5
      57: aload_1
      58: invokeinterface #82,  1           // InterfaceMethod org/aspectj/weaver/Member.getName:()Ljava/lang/String;
      63: invokevirtual #83                 // Method java/lang/StringBuffer.append:(Ljava/lang/String;)Ljava/lang/StringBuffer;
      66: pop
      67: new           #3                  // class org/aspectj/weaver/ResolvedMemberImpl
      70: dup
      71: getstatic     #4                  // Field org/aspectj/weaver/Member.METHOD:Lorg/aspectj/weaver/MemberKind;
      74: aload_3
      75: bipush        9
      77: aload_1
      78: invokeinterface #84,  1           // InterfaceMethod org/aspectj/weaver/Member.getReturnType:()Lorg/aspectj/weaver/UnresolvedType;
      83: aload         5
      85: invokevirtual #85                 // Method java/lang/StringBuffer.toString:()Ljava/lang/String;
      88: aload         4
      90: invokespecial #28                 // Method org/aspectj/weaver/ResolvedMemberImpl."<init>":(Lorg/aspectj/weaver/MemberKind;Lorg/aspectj/weaver/UnresolvedType;ILorg/aspectj/weaver/UnresolvedType;Ljava/lang/String;[Lorg/aspectj/weaver/UnresolvedType;)V
      93: areturn
      94: aload_1
      95: invokeinterface #82,  1           // InterfaceMethod org/aspectj/weaver/Member.getName:()Ljava/lang/String;
     100: aload_3
     101: aload_0
     102: invokestatic  #86                 // Method org/aspectj/weaver/NameMangler.privilegedAccessMethodForFieldGet:(Ljava/lang/String;Lorg/aspectj/weaver/UnresolvedType;Lorg/aspectj/weaver/UnresolvedType;)Ljava/lang/String;
     105: astore        4
     107: aload_1
     108: invokeinterface #77,  1           // InterfaceMethod org/aspectj/weaver/Member.getModifiers:()I
     113: invokestatic  #70                 // Method java/lang/reflect/Modifier.isStatic:(I)Z
     116: ifeq          151
     119: new           #43                 // class java/lang/StringBuilder
     122: dup
     123: invokespecial #44                 // Method java/lang/StringBuilder."<init>":()V
     126: ldc           #52                 // String ()
     128: invokevirtual #46                 // Method java/lang/StringBuilder.append:(Ljava/lang/String;)Ljava/lang/StringBuilder;
     131: aload_1
     132: invokeinterface #84,  1           // InterfaceMethod org/aspectj/weaver/Member.getReturnType:()Lorg/aspectj/weaver/UnresolvedType;
     137: invokevirtual #18                 // Method org/aspectj/weaver/UnresolvedType.getSignature:()Ljava/lang/String;
     140: invokevirtual #46                 // Method java/lang/StringBuilder.append:(Ljava/lang/String;)Ljava/lang/StringBuilder;
     143: invokevirtual #48                 // Method java/lang/StringBuilder.toString:()Ljava/lang/String;
     146: astore        5
     148: goto          192
     151: new           #43                 // class java/lang/StringBuilder
     154: dup
     155: invokespecial #44                 // Method java/lang/StringBuilder."<init>":()V
     158: ldc           #54                 // String (
     160: invokevirtual #46                 // Method java/lang/StringBuilder.append:(Ljava/lang/String;)Ljava/lang/StringBuilder;
     163: aload_3
     164: invokevirtual #18                 // Method org/aspectj/weaver/UnresolvedType.getSignature:()Ljava/lang/String;
     167: invokevirtual #46                 // Method java/lang/StringBuilder.append:(Ljava/lang/String;)Ljava/lang/StringBuilder;
     170: ldc           #87                 // String )
     172: invokevirtual #46                 // Method java/lang/StringBuilder.append:(Ljava/lang/String;)Ljava/lang/StringBuilder;
     175: aload_1
     176: invokeinterface #84,  1           // InterfaceMethod org/aspectj/weaver/Member.getReturnType:()Lorg/aspectj/weaver/UnresolvedType;
     181: invokevirtual #18                 // Method org/aspectj/weaver/UnresolvedType.getSignature:()Ljava/lang/String;
     184: invokevirtual #46                 // Method java/lang/StringBuilder.append:(Ljava/lang/String;)Ljava/lang/StringBuilder;
     187: invokevirtual #48                 // Method java/lang/StringBuilder.toString:()Ljava/lang/String;
     190: astore        5
     192: new           #3                  // class org/aspectj/weaver/ResolvedMemberImpl
     195: dup
     196: getstatic     #4                  // Field org/aspectj/weaver/Member.METHOD:Lorg/aspectj/weaver/MemberKind;
     199: aload_3
     200: bipush        9
     202: aload         4
     204: aload         5
     206: invokespecial #9                  // Method org/aspectj/weaver/ResolvedMemberImpl."<init>":(Lorg/aspectj/weaver/MemberKind;Lorg/aspectj/weaver/UnresolvedType;ILjava/lang/String;Ljava/lang/String;)V
     209: areturn

  public static org.aspectj.weaver.ResolvedMember privilegedAccessMethodForFieldSet(org.aspectj.weaver.UnresolvedType, org.aspectj.weaver.Member, boolean);
    Code:
       0: aload_1
       1: invokeinterface #76,  1           // InterfaceMethod org/aspectj/weaver/Member.getDeclaringType:()Lorg/aspectj/weaver/UnresolvedType;
       6: astore_3
       7: iload_2
       8: ifeq          110
      11: aconst_null
      12: astore        4
      14: aload_1
      15: invokeinterface #77,  1           // InterfaceMethod org/aspectj/weaver/Member.getModifiers:()I
      20: invokestatic  #70                 // Method java/lang/reflect/Modifier.isStatic:(I)Z
      23: ifeq          44
      26: iconst_1
      27: anewarray     #36                 // class org/aspectj/weaver/UnresolvedType
      30: dup
      31: iconst_0
      32: aload_1
      33: invokeinterface #88,  1           // InterfaceMethod org/aspectj/weaver/Member.getType:()Lorg/aspectj/weaver/UnresolvedType;
      38: aastore
      39: astore        4
      41: goto          63
      44: iconst_2
      45: anewarray     #36                 // class org/aspectj/weaver/UnresolvedType
      48: dup
      49: iconst_0
      50: aload_3
      51: aastore
      52: dup
      53: iconst_1
      54: aload_1
      55: invokeinterface #88,  1           // InterfaceMethod org/aspectj/weaver/Member.getType:()Lorg/aspectj/weaver/UnresolvedType;
      60: aastore
      61: astore        4
      63: new           #79                 // class java/lang/StringBuffer
      66: dup
      67: ldc           #89                 // String ajc$set$
      69: invokespecial #81                 // Method java/lang/StringBuffer."<init>":(Ljava/lang/String;)V
      72: astore        5
      74: aload         5
      76: aload_1
      77: invokeinterface #82,  1           // InterfaceMethod org/aspectj/weaver/Member.getName:()Ljava/lang/String;
      82: invokevirtual #83                 // Method java/lang/StringBuffer.append:(Ljava/lang/String;)Ljava/lang/StringBuffer;
      85: pop
      86: new           #3                  // class org/aspectj/weaver/ResolvedMemberImpl
      89: dup
      90: getstatic     #4                  // Field org/aspectj/weaver/Member.METHOD:Lorg/aspectj/weaver/MemberKind;
      93: aload_3
      94: bipush        9
      96: getstatic     #90                 // Field org/aspectj/weaver/UnresolvedType.VOID:Lorg/aspectj/weaver/UnresolvedType;
      99: aload         5
     101: invokevirtual #85                 // Method java/lang/StringBuffer.toString:()Ljava/lang/String;
     104: aload         4
     106: invokespecial #28                 // Method org/aspectj/weaver/ResolvedMemberImpl."<init>":(Lorg/aspectj/weaver/MemberKind;Lorg/aspectj/weaver/UnresolvedType;ILorg/aspectj/weaver/UnresolvedType;Ljava/lang/String;[Lorg/aspectj/weaver/UnresolvedType;)V
     109: areturn
     110: aload_1
     111: invokeinterface #82,  1           // InterfaceMethod org/aspectj/weaver/Member.getName:()Ljava/lang/String;
     116: aload_3
     117: aload_0
     118: invokestatic  #91                 // Method org/aspectj/weaver/NameMangler.privilegedAccessMethodForFieldSet:(Ljava/lang/String;Lorg/aspectj/weaver/UnresolvedType;Lorg/aspectj/weaver/UnresolvedType;)Ljava/lang/String;
     121: astore        4
     123: aload_1
     124: invokeinterface #77,  1           // InterfaceMethod org/aspectj/weaver/Member.getModifiers:()I
     129: invokestatic  #70                 // Method java/lang/reflect/Modifier.isStatic:(I)Z
     132: ifeq          172
     135: new           #43                 // class java/lang/StringBuilder
     138: dup
     139: invokespecial #44                 // Method java/lang/StringBuilder."<init>":()V
     142: ldc           #54                 // String (
     144: invokevirtual #46                 // Method java/lang/StringBuilder.append:(Ljava/lang/String;)Ljava/lang/StringBuilder;
     147: aload_1
     148: invokeinterface #84,  1           // InterfaceMethod org/aspectj/weaver/Member.getReturnType:()Lorg/aspectj/weaver/UnresolvedType;
     153: invokevirtual #18                 // Method org/aspectj/weaver/UnresolvedType.getSignature:()Ljava/lang/String;
     156: invokevirtual #46                 // Method java/lang/StringBuilder.append:(Ljava/lang/String;)Ljava/lang/StringBuilder;
     159: ldc           #55                 // String )V
     161: invokevirtual #46                 // Method java/lang/StringBuilder.append:(Ljava/lang/String;)Ljava/lang/StringBuilder;
     164: invokevirtual #48                 // Method java/lang/StringBuilder.toString:()Ljava/lang/String;
     167: astore        5
     169: goto          213
     172: new           #43                 // class java/lang/StringBuilder
     175: dup
     176: invokespecial #44                 // Method java/lang/StringBuilder."<init>":()V
     179: ldc           #54                 // String (
     181: invokevirtual #46                 // Method java/lang/StringBuilder.append:(Ljava/lang/String;)Ljava/lang/StringBuilder;
     184: aload_3
     185: invokevirtual #18                 // Method org/aspectj/weaver/UnresolvedType.getSignature:()Ljava/lang/String;
     188: invokevirtual #46                 // Method java/lang/StringBuilder.append:(Ljava/lang/String;)Ljava/lang/StringBuilder;
     191: aload_1
     192: invokeinterface #84,  1           // InterfaceMethod org/aspectj/weaver/Member.getReturnType:()Lorg/aspectj/weaver/UnresolvedType;
     197: invokevirtual #18                 // Method org/aspectj/weaver/UnresolvedType.getSignature:()Ljava/lang/String;
     200: invokevirtual #46                 // Method java/lang/StringBuilder.append:(Ljava/lang/String;)Ljava/lang/StringBuilder;
     203: ldc           #55                 // String )V
     205: invokevirtual #46                 // Method java/lang/StringBuilder.append:(Ljava/lang/String;)Ljava/lang/StringBuilder;
     208: invokevirtual #48                 // Method java/lang/StringBuilder.toString:()Ljava/lang/String;
     211: astore        5
     213: new           #3                  // class org/aspectj/weaver/ResolvedMemberImpl
     216: dup
     217: getstatic     #4                  // Field org/aspectj/weaver/Member.METHOD:Lorg/aspectj/weaver/MemberKind;
     220: aload_3
     221: bipush        9
     223: aload         4
     225: aload         5
     227: invokespecial #9                  // Method org/aspectj/weaver/ResolvedMemberImpl."<init>":(Lorg/aspectj/weaver/MemberKind;Lorg/aspectj/weaver/UnresolvedType;ILjava/lang/String;Ljava/lang/String;)V
     230: areturn

  public static org.aspectj.weaver.ResolvedMember superAccessMethod(org.aspectj.weaver.UnresolvedType, org.aspectj.weaver.ResolvedMember);
    Code:
       0: aload_1
       1: invokeinterface #74,  1           // InterfaceMethod org/aspectj/weaver/ResolvedMember.getParameterTypes:()[Lorg/aspectj/weaver/UnresolvedType;
       6: astore_2
       7: new           #3                  // class org/aspectj/weaver/ResolvedMemberImpl
      10: dup
      11: getstatic     #4                  // Field org/aspectj/weaver/Member.METHOD:Lorg/aspectj/weaver/MemberKind;
      14: aload_0
      15: iconst_1
      16: aload_1
      17: invokeinterface #71,  1           // InterfaceMethod org/aspectj/weaver/ResolvedMember.getReturnType:()Lorg/aspectj/weaver/UnresolvedType;
      22: aload_0
      23: aload_1
      24: invokeinterface #72,  1           // InterfaceMethod org/aspectj/weaver/ResolvedMember.getName:()Ljava/lang/String;
      29: invokestatic  #92                 // Method org/aspectj/weaver/NameMangler.superDispatchMethod:(Lorg/aspectj/weaver/UnresolvedType;Ljava/lang/String;)Ljava/lang/String;
      32: aload_2
      33: aload_1
      34: invokeinterface #75,  1           // InterfaceMethod org/aspectj/weaver/ResolvedMember.getExceptions:()[Lorg/aspectj/weaver/UnresolvedType;
      39: invokespecial #42                 // Method org/aspectj/weaver/ResolvedMemberImpl."<init>":(Lorg/aspectj/weaver/MemberKind;Lorg/aspectj/weaver/UnresolvedType;ILorg/aspectj/weaver/UnresolvedType;Ljava/lang/String;[Lorg/aspectj/weaver/UnresolvedType;[Lorg/aspectj/weaver/UnresolvedType;)V
      42: areturn

  public static org.aspectj.weaver.ResolvedMember inlineAccessMethodForMethod(org.aspectj.weaver.UnresolvedType, org.aspectj.weaver.ResolvedMember);
    Code:
       0: aload_1
       1: invokeinterface #74,  1           // InterfaceMethod org/aspectj/weaver/ResolvedMember.getParameterTypes:()[Lorg/aspectj/weaver/UnresolvedType;
       6: astore_2
       7: aload_1
       8: invokeinterface #69,  1           // InterfaceMethod org/aspectj/weaver/ResolvedMember.getModifiers:()I
      13: invokestatic  #70                 // Method java/lang/reflect/Modifier.isStatic:(I)Z
      16: ifne          30
      19: aload_1
      20: invokeinterface #68,  1           // InterfaceMethod org/aspectj/weaver/ResolvedMember.getDeclaringType:()Lorg/aspectj/weaver/UnresolvedType;
      25: aload_2
      26: invokestatic  #93                 // Method org/aspectj/weaver/UnresolvedType.insert:(Lorg/aspectj/weaver/UnresolvedType;[Lorg/aspectj/weaver/UnresolvedType;)[Lorg/aspectj/weaver/UnresolvedType;
      29: astore_2
      30: new           #3                  // class org/aspectj/weaver/ResolvedMemberImpl
      33: dup
      34: getstatic     #4                  // Field org/aspectj/weaver/Member.METHOD:Lorg/aspectj/weaver/MemberKind;
      37: aload_0
      38: bipush        9
      40: aload_1
      41: invokeinterface #71,  1           // InterfaceMethod org/aspectj/weaver/ResolvedMember.getReturnType:()Lorg/aspectj/weaver/UnresolvedType;
      46: aload_1
      47: invokeinterface #72,  1           // InterfaceMethod org/aspectj/weaver/ResolvedMember.getName:()Ljava/lang/String;
      52: aload_1
      53: invokeinterface #68,  1           // InterfaceMethod org/aspectj/weaver/ResolvedMember.getDeclaringType:()Lorg/aspectj/weaver/UnresolvedType;
      58: aload_0
      59: invokestatic  #94                 // Method org/aspectj/weaver/NameMangler.inlineAccessMethodForMethod:(Ljava/lang/String;Lorg/aspectj/weaver/UnresolvedType;Lorg/aspectj/weaver/UnresolvedType;)Ljava/lang/String;
      62: aload_2
      63: aload_1
      64: invokeinterface #75,  1           // InterfaceMethod org/aspectj/weaver/ResolvedMember.getExceptions:()[Lorg/aspectj/weaver/UnresolvedType;
      69: invokespecial #42                 // Method org/aspectj/weaver/ResolvedMemberImpl."<init>":(Lorg/aspectj/weaver/MemberKind;Lorg/aspectj/weaver/UnresolvedType;ILorg/aspectj/weaver/UnresolvedType;Ljava/lang/String;[Lorg/aspectj/weaver/UnresolvedType;[Lorg/aspectj/weaver/UnresolvedType;)V
      72: areturn

  public static org.aspectj.weaver.ResolvedMember inlineAccessMethodForFieldGet(org.aspectj.weaver.UnresolvedType, org.aspectj.weaver.Member);
    Code:
       0: aload_1
       1: invokeinterface #77,  1           // InterfaceMethod org/aspectj/weaver/Member.getModifiers:()I
       6: invokestatic  #70                 // Method java/lang/reflect/Modifier.isStatic:(I)Z
       9: ifeq          43
      12: new           #43                 // class java/lang/StringBuilder
      15: dup
      16: invokespecial #44                 // Method java/lang/StringBuilder."<init>":()V
      19: ldc           #52                 // String ()
      21: invokevirtual #46                 // Method java/lang/StringBuilder.append:(Ljava/lang/String;)Ljava/lang/StringBuilder;
      24: aload_1
      25: invokeinterface #84,  1           // InterfaceMethod org/aspectj/weaver/Member.getReturnType:()Lorg/aspectj/weaver/UnresolvedType;
      30: invokevirtual #18                 // Method org/aspectj/weaver/UnresolvedType.getSignature:()Ljava/lang/String;
      33: invokevirtual #46                 // Method java/lang/StringBuilder.append:(Ljava/lang/String;)Ljava/lang/StringBuilder;
      36: invokevirtual #48                 // Method java/lang/StringBuilder.toString:()Ljava/lang/String;
      39: astore_2
      40: goto          88
      43: new           #43                 // class java/lang/StringBuilder
      46: dup
      47: invokespecial #44                 // Method java/lang/StringBuilder."<init>":()V
      50: ldc           #54                 // String (
      52: invokevirtual #46                 // Method java/lang/StringBuilder.append:(Ljava/lang/String;)Ljava/lang/StringBuilder;
      55: aload_1
      56: invokeinterface #76,  1           // InterfaceMethod org/aspectj/weaver/Member.getDeclaringType:()Lorg/aspectj/weaver/UnresolvedType;
      61: invokevirtual #18                 // Method org/aspectj/weaver/UnresolvedType.getSignature:()Ljava/lang/String;
      64: invokevirtual #46                 // Method java/lang/StringBuilder.append:(Ljava/lang/String;)Ljava/lang/StringBuilder;
      67: ldc           #87                 // String )
      69: invokevirtual #46                 // Method java/lang/StringBuilder.append:(Ljava/lang/String;)Ljava/lang/StringBuilder;
      72: aload_1
      73: invokeinterface #84,  1           // InterfaceMethod org/aspectj/weaver/Member.getReturnType:()Lorg/aspectj/weaver/UnresolvedType;
      78: invokevirtual #18                 // Method org/aspectj/weaver/UnresolvedType.getSignature:()Ljava/lang/String;
      81: invokevirtual #46                 // Method java/lang/StringBuilder.append:(Ljava/lang/String;)Ljava/lang/StringBuilder;
      84: invokevirtual #48                 // Method java/lang/StringBuilder.toString:()Ljava/lang/String;
      87: astore_2
      88: new           #3                  // class org/aspectj/weaver/ResolvedMemberImpl
      91: dup
      92: getstatic     #4                  // Field org/aspectj/weaver/Member.METHOD:Lorg/aspectj/weaver/MemberKind;
      95: aload_0
      96: bipush        9
      98: aload_1
      99: invokeinterface #82,  1           // InterfaceMethod org/aspectj/weaver/Member.getName:()Ljava/lang/String;
     104: aload_1
     105: invokeinterface #76,  1           // InterfaceMethod org/aspectj/weaver/Member.getDeclaringType:()Lorg/aspectj/weaver/UnresolvedType;
     110: aload_0
     111: invokestatic  #95                 // Method org/aspectj/weaver/NameMangler.inlineAccessMethodForFieldGet:(Ljava/lang/String;Lorg/aspectj/weaver/UnresolvedType;Lorg/aspectj/weaver/UnresolvedType;)Ljava/lang/String;
     114: aload_2
     115: invokespecial #9                  // Method org/aspectj/weaver/ResolvedMemberImpl."<init>":(Lorg/aspectj/weaver/MemberKind;Lorg/aspectj/weaver/UnresolvedType;ILjava/lang/String;Ljava/lang/String;)V
     118: areturn

  public static org.aspectj.weaver.ResolvedMember inlineAccessMethodForFieldSet(org.aspectj.weaver.UnresolvedType, org.aspectj.weaver.Member);
    Code:
       0: aload_1
       1: invokeinterface #77,  1           // InterfaceMethod org/aspectj/weaver/Member.getModifiers:()I
       6: invokestatic  #70                 // Method java/lang/reflect/Modifier.isStatic:(I)Z
       9: ifeq          48
      12: new           #43                 // class java/lang/StringBuilder
      15: dup
      16: invokespecial #44                 // Method java/lang/StringBuilder."<init>":()V
      19: ldc           #54                 // String (
      21: invokevirtual #46                 // Method java/lang/StringBuilder.append:(Ljava/lang/String;)Ljava/lang/StringBuilder;
      24: aload_1
      25: invokeinterface #84,  1           // InterfaceMethod org/aspectj/weaver/Member.getReturnType:()Lorg/aspectj/weaver/UnresolvedType;
      30: invokevirtual #18                 // Method org/aspectj/weaver/UnresolvedType.getSignature:()Ljava/lang/String;
      33: invokevirtual #46                 // Method java/lang/StringBuilder.append:(Ljava/lang/String;)Ljava/lang/StringBuilder;
      36: ldc           #55                 // String )V
      38: invokevirtual #46                 // Method java/lang/StringBuilder.append:(Ljava/lang/String;)Ljava/lang/StringBuilder;
      41: invokevirtual #48                 // Method java/lang/StringBuilder.toString:()Ljava/lang/String;
      44: astore_2
      45: goto          93
      48: new           #43                 // class java/lang/StringBuilder
      51: dup
      52: invokespecial #44                 // Method java/lang/StringBuilder."<init>":()V
      55: ldc           #54                 // String (
      57: invokevirtual #46                 // Method java/lang/StringBuilder.append:(Ljava/lang/String;)Ljava/lang/StringBuilder;
      60: aload_1
      61: invokeinterface #76,  1           // InterfaceMethod org/aspectj/weaver/Member.getDeclaringType:()Lorg/aspectj/weaver/UnresolvedType;
      66: invokevirtual #18                 // Method org/aspectj/weaver/UnresolvedType.getSignature:()Ljava/lang/String;
      69: invokevirtual #46                 // Method java/lang/StringBuilder.append:(Ljava/lang/String;)Ljava/lang/StringBuilder;
      72: aload_1
      73: invokeinterface #84,  1           // InterfaceMethod org/aspectj/weaver/Member.getReturnType:()Lorg/aspectj/weaver/UnresolvedType;
      78: invokevirtual #18                 // Method org/aspectj/weaver/UnresolvedType.getSignature:()Ljava/lang/String;
      81: invokevirtual #46                 // Method java/lang/StringBuilder.append:(Ljava/lang/String;)Ljava/lang/StringBuilder;
      84: ldc           #55                 // String )V
      86: invokevirtual #46                 // Method java/lang/StringBuilder.append:(Ljava/lang/String;)Ljava/lang/StringBuilder;
      89: invokevirtual #48                 // Method java/lang/StringBuilder.toString:()Ljava/lang/String;
      92: astore_2
      93: new           #3                  // class org/aspectj/weaver/ResolvedMemberImpl
      96: dup
      97: getstatic     #4                  // Field org/aspectj/weaver/Member.METHOD:Lorg/aspectj/weaver/MemberKind;
     100: aload_0
     101: bipush        9
     103: aload_1
     104: invokeinterface #82,  1           // InterfaceMethod org/aspectj/weaver/Member.getName:()Ljava/lang/String;
     109: aload_1
     110: invokeinterface #76,  1           // InterfaceMethod org/aspectj/weaver/Member.getDeclaringType:()Lorg/aspectj/weaver/UnresolvedType;
     115: aload_0
     116: invokestatic  #96                 // Method org/aspectj/weaver/NameMangler.inlineAccessMethodForFieldSet:(Ljava/lang/String;Lorg/aspectj/weaver/UnresolvedType;Lorg/aspectj/weaver/UnresolvedType;)Ljava/lang/String;
     119: aload_2
     120: invokespecial #9                  // Method org/aspectj/weaver/ResolvedMemberImpl."<init>":(Lorg/aspectj/weaver/MemberKind;Lorg/aspectj/weaver/UnresolvedType;ILjava/lang/String;Ljava/lang/String;)V
     123: areturn

  public static org.aspectj.weaver.Member cflowStackPeekInstance();
    Code:
       0: new           #97                 // class org/aspectj/weaver/MemberImpl
       3: dup
       4: getstatic     #4                  // Field org/aspectj/weaver/Member.METHOD:Lorg/aspectj/weaver/MemberKind;
       7: getstatic     #17                 // Field CFLOW_STACK_TYPE:Lorg/aspectj/weaver/UnresolvedType;
      10: iconst_0
      11: ldc           #98                 // String peekInstance
      13: ldc           #99                 // String ()Ljava/lang/Object;
      15: invokespecial #100                // Method org/aspectj/weaver/MemberImpl."<init>":(Lorg/aspectj/weaver/MemberKind;Lorg/aspectj/weaver/UnresolvedType;ILjava/lang/String;Ljava/lang/String;)V
      18: areturn

  public static org.aspectj.weaver.Member cflowStackPushInstance();
    Code:
       0: new           #97                 // class org/aspectj/weaver/MemberImpl
       3: dup
       4: getstatic     #4                  // Field org/aspectj/weaver/Member.METHOD:Lorg/aspectj/weaver/MemberKind;
       7: getstatic     #17                 // Field CFLOW_STACK_TYPE:Lorg/aspectj/weaver/UnresolvedType;
      10: iconst_0
      11: ldc           #101                // String pushInstance
      13: ldc           #34                 // String (Ljava/lang/Object;)V
      15: invokespecial #100                // Method org/aspectj/weaver/MemberImpl."<init>":(Lorg/aspectj/weaver/MemberKind;Lorg/aspectj/weaver/UnresolvedType;ILjava/lang/String;Ljava/lang/String;)V
      18: areturn

  public static org.aspectj.weaver.Member cflowStackIsValid();
    Code:
       0: new           #97                 // class org/aspectj/weaver/MemberImpl
       3: dup
       4: getstatic     #4                  // Field org/aspectj/weaver/Member.METHOD:Lorg/aspectj/weaver/MemberKind;
       7: getstatic     #17                 // Field CFLOW_STACK_TYPE:Lorg/aspectj/weaver/UnresolvedType;
      10: iconst_0
      11: ldc           #102                // String isValid
      13: ldc           #59                 // String ()Z
      15: invokespecial #100                // Method org/aspectj/weaver/MemberImpl."<init>":(Lorg/aspectj/weaver/MemberKind;Lorg/aspectj/weaver/UnresolvedType;ILjava/lang/String;Ljava/lang/String;)V
      18: areturn

  public static org.aspectj.weaver.Member cflowStackInit();
    Code:
       0: new           #97                 // class org/aspectj/weaver/MemberImpl
       3: dup
       4: getstatic     #103                // Field org/aspectj/weaver/Member.CONSTRUCTOR:Lorg/aspectj/weaver/MemberKind;
       7: getstatic     #17                 // Field CFLOW_STACK_TYPE:Lorg/aspectj/weaver/UnresolvedType;
      10: iconst_0
      11: ldc           #12                 // String <init>
      13: ldc           #8                  // String ()V
      15: invokespecial #100                // Method org/aspectj/weaver/MemberImpl."<init>":(Lorg/aspectj/weaver/MemberKind;Lorg/aspectj/weaver/UnresolvedType;ILjava/lang/String;Ljava/lang/String;)V
      18: areturn

  public static org.aspectj.weaver.Member aroundClosurePreInitializationField();
    Code:
       0: new           #97                 // class org/aspectj/weaver/MemberImpl
       3: dup
       4: getstatic     #15                 // Field org/aspectj/weaver/Member.FIELD:Lorg/aspectj/weaver/MemberKind;
       7: getstatic     #104                // Field AROUND_CLOSURE_TYPE:Lorg/aspectj/weaver/UnresolvedType;
      10: iconst_0
      11: ldc           #105                // String preInitializationState
      13: ldc           #106                // String [Ljava/lang/Object;
      15: invokespecial #100                // Method org/aspectj/weaver/MemberImpl."<init>":(Lorg/aspectj/weaver/MemberKind;Lorg/aspectj/weaver/UnresolvedType;ILjava/lang/String;Ljava/lang/String;)V
      18: areturn

  public static org.aspectj.weaver.Member aroundClosurePreInitializationGetter();
    Code:
       0: new           #97                 // class org/aspectj/weaver/MemberImpl
       3: dup
       4: getstatic     #4                  // Field org/aspectj/weaver/Member.METHOD:Lorg/aspectj/weaver/MemberKind;
       7: getstatic     #104                // Field AROUND_CLOSURE_TYPE:Lorg/aspectj/weaver/UnresolvedType;
      10: iconst_0
      11: ldc           #107                // String getPreInitializationState
      13: ldc           #108                // String ()[Ljava/lang/Object;
      15: invokespecial #100                // Method org/aspectj/weaver/MemberImpl."<init>":(Lorg/aspectj/weaver/MemberKind;Lorg/aspectj/weaver/UnresolvedType;ILjava/lang/String;Ljava/lang/String;)V
      18: areturn

  public static org.aspectj.weaver.ResolvedMember preIntroducedConstructor(org.aspectj.weaver.UnresolvedType, org.aspectj.weaver.UnresolvedType, org.aspectj.weaver.UnresolvedType[]);
    Code:
       0: new           #3                  // class org/aspectj/weaver/ResolvedMemberImpl
       3: dup
       4: getstatic     #4                  // Field org/aspectj/weaver/Member.METHOD:Lorg/aspectj/weaver/MemberKind;
       7: aload_0
       8: bipush        25
      10: getstatic     #109                // Field org/aspectj/weaver/UnresolvedType.OBJECTARRAY:Lorg/aspectj/weaver/UnresolvedType;
      13: aload_0
      14: aload_1
      15: invokestatic  #110                // Method org/aspectj/weaver/NameMangler.preIntroducedConstructor:(Lorg/aspectj/weaver/UnresolvedType;Lorg/aspectj/weaver/UnresolvedType;)Ljava/lang/String;
      18: aload_2
      19: invokespecial #28                 // Method org/aspectj/weaver/ResolvedMemberImpl."<init>":(Lorg/aspectj/weaver/MemberKind;Lorg/aspectj/weaver/UnresolvedType;ILorg/aspectj/weaver/UnresolvedType;Ljava/lang/String;[Lorg/aspectj/weaver/UnresolvedType;)V
      22: areturn

  public static org.aspectj.weaver.ResolvedMember postIntroducedConstructor(org.aspectj.weaver.UnresolvedType, org.aspectj.weaver.UnresolvedType, org.aspectj.weaver.UnresolvedType[]);
    Code:
       0: new           #3                  // class org/aspectj/weaver/ResolvedMemberImpl
       3: dup
       4: getstatic     #4                  // Field org/aspectj/weaver/Member.METHOD:Lorg/aspectj/weaver/MemberKind;
       7: aload_0
       8: bipush        25
      10: getstatic     #90                 // Field org/aspectj/weaver/UnresolvedType.VOID:Lorg/aspectj/weaver/UnresolvedType;
      13: aload_0
      14: aload_1
      15: invokestatic  #111                // Method org/aspectj/weaver/NameMangler.postIntroducedConstructor:(Lorg/aspectj/weaver/UnresolvedType;Lorg/aspectj/weaver/UnresolvedType;)Ljava/lang/String;
      18: aload_1
      19: aload_2
      20: invokestatic  #93                 // Method org/aspectj/weaver/UnresolvedType.insert:(Lorg/aspectj/weaver/UnresolvedType;[Lorg/aspectj/weaver/UnresolvedType;)[Lorg/aspectj/weaver/UnresolvedType;
      23: invokespecial #28                 // Method org/aspectj/weaver/ResolvedMemberImpl."<init>":(Lorg/aspectj/weaver/MemberKind;Lorg/aspectj/weaver/UnresolvedType;ILorg/aspectj/weaver/UnresolvedType;Ljava/lang/String;[Lorg/aspectj/weaver/UnresolvedType;)V
      26: areturn

  public static org.aspectj.weaver.ResolvedMember itdAtDeclareParentsField(org.aspectj.weaver.ResolvedType, org.aspectj.weaver.UnresolvedType, org.aspectj.weaver.UnresolvedType);
    Code:
       0: new           #3                  // class org/aspectj/weaver/ResolvedMemberImpl
       3: dup
       4: getstatic     #15                 // Field org/aspectj/weaver/Member.FIELD:Lorg/aspectj/weaver/MemberKind;
       7: aload_0
       8: iconst_2
       9: aload_1
      10: aload_2
      11: aload_1
      12: invokestatic  #112                // Method org/aspectj/weaver/NameMangler.itdAtDeclareParentsField:(Lorg/aspectj/weaver/UnresolvedType;Lorg/aspectj/weaver/UnresolvedType;)Ljava/lang/String;
      15: aconst_null
      16: invokespecial #28                 // Method org/aspectj/weaver/ResolvedMemberImpl."<init>":(Lorg/aspectj/weaver/MemberKind;Lorg/aspectj/weaver/UnresolvedType;ILorg/aspectj/weaver/UnresolvedType;Ljava/lang/String;[Lorg/aspectj/weaver/UnresolvedType;)V
      19: areturn

  public static org.aspectj.weaver.ResolvedMember interConstructor(org.aspectj.weaver.ResolvedType, org.aspectj.weaver.ResolvedMember, org.aspectj.weaver.UnresolvedType);
    Code:
       0: new           #3                  // class org/aspectj/weaver/ResolvedMemberImpl
       3: dup
       4: getstatic     #103                // Field org/aspectj/weaver/Member.CONSTRUCTOR:Lorg/aspectj/weaver/MemberKind;
       7: aload_0
       8: iconst_1
       9: getstatic     #90                 // Field org/aspectj/weaver/UnresolvedType.VOID:Lorg/aspectj/weaver/UnresolvedType;
      12: ldc           #12                 // String <init>
      14: aload_1
      15: invokeinterface #74,  1           // InterfaceMethod org/aspectj/weaver/ResolvedMember.getParameterTypes:()[Lorg/aspectj/weaver/UnresolvedType;
      20: aload_1
      21: invokeinterface #75,  1           // InterfaceMethod org/aspectj/weaver/ResolvedMember.getExceptions:()[Lorg/aspectj/weaver/UnresolvedType;
      26: invokespecial #42                 // Method org/aspectj/weaver/ResolvedMemberImpl."<init>":(Lorg/aspectj/weaver/MemberKind;Lorg/aspectj/weaver/UnresolvedType;ILorg/aspectj/weaver/UnresolvedType;Ljava/lang/String;[Lorg/aspectj/weaver/UnresolvedType;[Lorg/aspectj/weaver/UnresolvedType;)V
      29: astore_3
      30: aload_1
      31: invokeinterface #69,  1           // InterfaceMethod org/aspectj/weaver/ResolvedMember.getModifiers:()I
      36: invokestatic  #113                // Method java/lang/reflect/Modifier.isPublic:(I)Z
      39: ifeq          44
      42: aload_3
      43: areturn
      44: aload_3
      45: aload_2
      46: invokestatic  #114                // Method addCookieTo:(Lorg/aspectj/weaver/ResolvedMember;Lorg/aspectj/weaver/UnresolvedType;)Lorg/aspectj/weaver/ResolvedMember;
      49: astore_3
      50: aload_0
      51: aload_3
      52: invokevirtual #115                // Method org/aspectj/weaver/ResolvedType.lookupMemberNoSupers:(Lorg/aspectj/weaver/Member;)Lorg/aspectj/weaver/ResolvedMember;
      55: ifnonnull     44
      58: aload_3
      59: areturn

  public static org.aspectj.weaver.ResolvedMember interFieldInitializer(org.aspectj.weaver.ResolvedMember, org.aspectj.weaver.UnresolvedType);
    Code:
       0: new           #3                  // class org/aspectj/weaver/ResolvedMemberImpl
       3: dup
       4: getstatic     #4                  // Field org/aspectj/weaver/Member.METHOD:Lorg/aspectj/weaver/MemberKind;
       7: aload_1
       8: bipush        9
      10: aload_1
      11: aload_0
      12: invokeinterface #68,  1           // InterfaceMethod org/aspectj/weaver/ResolvedMember.getDeclaringType:()Lorg/aspectj/weaver/UnresolvedType;
      17: aload_0
      18: invokeinterface #72,  1           // InterfaceMethod org/aspectj/weaver/ResolvedMember.getName:()Ljava/lang/String;
      23: invokestatic  #116                // Method org/aspectj/weaver/NameMangler.interFieldInitializer:(Lorg/aspectj/weaver/UnresolvedType;Lorg/aspectj/weaver/UnresolvedType;Ljava/lang/String;)Ljava/lang/String;
      26: aload_0
      27: invokeinterface #69,  1           // InterfaceMethod org/aspectj/weaver/ResolvedMember.getModifiers:()I
      32: invokestatic  #70                 // Method java/lang/reflect/Modifier.isStatic:(I)Z
      35: ifeq          43
      38: ldc           #8                  // String ()V
      40: goto          75
      43: new           #43                 // class java/lang/StringBuilder
      46: dup
      47: invokespecial #44                 // Method java/lang/StringBuilder."<init>":()V
      50: ldc           #54                 // String (
      52: invokevirtual #46                 // Method java/lang/StringBuilder.append:(Ljava/lang/String;)Ljava/lang/StringBuilder;
      55: aload_0
      56: invokeinterface #68,  1           // InterfaceMethod org/aspectj/weaver/ResolvedMember.getDeclaringType:()Lorg/aspectj/weaver/UnresolvedType;
      61: invokevirtual #18                 // Method org/aspectj/weaver/UnresolvedType.getSignature:()Ljava/lang/String;
      64: invokevirtual #46                 // Method java/lang/StringBuilder.append:(Ljava/lang/String;)Ljava/lang/StringBuilder;
      67: ldc           #55                 // String )V
      69: invokevirtual #46                 // Method java/lang/StringBuilder.append:(Ljava/lang/String;)Ljava/lang/StringBuilder;
      72: invokevirtual #48                 // Method java/lang/StringBuilder.toString:()Ljava/lang/String;
      75: invokespecial #9                  // Method org/aspectj/weaver/ResolvedMemberImpl."<init>":(Lorg/aspectj/weaver/MemberKind;Lorg/aspectj/weaver/UnresolvedType;ILjava/lang/String;Ljava/lang/String;)V
      78: areturn

  private static int makePublicNonFinal(int);
    Code:
       0: iload_0
       1: bipush        -8
       3: iand
       4: bipush        -17
       6: iand
       7: iconst_1
       8: ior
       9: ireturn

  private static int makeNonFinal(int);
    Code:
       0: iload_0
       1: bipush        -17
       3: iand
       4: ireturn

  public static org.aspectj.weaver.ResolvedMember interFieldSetDispatcher(org.aspectj.weaver.ResolvedMember, org.aspectj.weaver.UnresolvedType);
    Code:
       0: new           #3                  // class org/aspectj/weaver/ResolvedMemberImpl
       3: dup
       4: getstatic     #4                  // Field org/aspectj/weaver/Member.METHOD:Lorg/aspectj/weaver/MemberKind;
       7: aload_1
       8: bipush        9
      10: getstatic     #90                 // Field org/aspectj/weaver/UnresolvedType.VOID:Lorg/aspectj/weaver/UnresolvedType;
      13: aload_1
      14: aload_0
      15: invokeinterface #68,  1           // InterfaceMethod org/aspectj/weaver/ResolvedMember.getDeclaringType:()Lorg/aspectj/weaver/UnresolvedType;
      20: aload_0
      21: invokeinterface #72,  1           // InterfaceMethod org/aspectj/weaver/ResolvedMember.getName:()Ljava/lang/String;
      26: invokestatic  #117                // Method org/aspectj/weaver/NameMangler.interFieldSetDispatcher:(Lorg/aspectj/weaver/UnresolvedType;Lorg/aspectj/weaver/UnresolvedType;Ljava/lang/String;)Ljava/lang/String;
      29: aload_0
      30: invokeinterface #69,  1           // InterfaceMethod org/aspectj/weaver/ResolvedMember.getModifiers:()I
      35: invokestatic  #70                 // Method java/lang/reflect/Modifier.isStatic:(I)Z
      38: ifeq          57
      41: iconst_1
      42: anewarray     #36                 // class org/aspectj/weaver/UnresolvedType
      45: dup
      46: iconst_0
      47: aload_0
      48: invokeinterface #71,  1           // InterfaceMethod org/aspectj/weaver/ResolvedMember.getReturnType:()Lorg/aspectj/weaver/UnresolvedType;
      53: aastore
      54: goto          79
      57: iconst_2
      58: anewarray     #36                 // class org/aspectj/weaver/UnresolvedType
      61: dup
      62: iconst_0
      63: aload_0
      64: invokeinterface #68,  1           // InterfaceMethod org/aspectj/weaver/ResolvedMember.getDeclaringType:()Lorg/aspectj/weaver/UnresolvedType;
      69: aastore
      70: dup
      71: iconst_1
      72: aload_0
      73: invokeinterface #71,  1           // InterfaceMethod org/aspectj/weaver/ResolvedMember.getReturnType:()Lorg/aspectj/weaver/UnresolvedType;
      78: aastore
      79: invokespecial #28                 // Method org/aspectj/weaver/ResolvedMemberImpl."<init>":(Lorg/aspectj/weaver/MemberKind;Lorg/aspectj/weaver/UnresolvedType;ILorg/aspectj/weaver/UnresolvedType;Ljava/lang/String;[Lorg/aspectj/weaver/UnresolvedType;)V
      82: astore_2
      83: aload_2
      84: aload_0
      85: invokeinterface #118,  1          // InterfaceMethod org/aspectj/weaver/ResolvedMember.getTypeVariables:()[Lorg/aspectj/weaver/TypeVariable;
      90: invokeinterface #119,  2          // InterfaceMethod org/aspectj/weaver/ResolvedMember.setTypeVariables:([Lorg/aspectj/weaver/TypeVariable;)V
      95: aload_2
      96: areturn

  public static org.aspectj.weaver.ResolvedMember interFieldGetDispatcher(org.aspectj.weaver.ResolvedMember, org.aspectj.weaver.UnresolvedType);
    Code:
       0: new           #3                  // class org/aspectj/weaver/ResolvedMemberImpl
       3: dup
       4: getstatic     #4                  // Field org/aspectj/weaver/Member.METHOD:Lorg/aspectj/weaver/MemberKind;
       7: aload_1
       8: bipush        9
      10: aload_0
      11: invokeinterface #71,  1           // InterfaceMethod org/aspectj/weaver/ResolvedMember.getReturnType:()Lorg/aspectj/weaver/UnresolvedType;
      16: aload_1
      17: aload_0
      18: invokeinterface #68,  1           // InterfaceMethod org/aspectj/weaver/ResolvedMember.getDeclaringType:()Lorg/aspectj/weaver/UnresolvedType;
      23: aload_0
      24: invokeinterface #72,  1           // InterfaceMethod org/aspectj/weaver/ResolvedMember.getName:()Ljava/lang/String;
      29: invokestatic  #120                // Method org/aspectj/weaver/NameMangler.interFieldGetDispatcher:(Lorg/aspectj/weaver/UnresolvedType;Lorg/aspectj/weaver/UnresolvedType;Ljava/lang/String;)Ljava/lang/String;
      32: aload_0
      33: invokeinterface #69,  1           // InterfaceMethod org/aspectj/weaver/ResolvedMember.getModifiers:()I
      38: invokestatic  #70                 // Method java/lang/reflect/Modifier.isStatic:(I)Z
      41: ifeq          50
      44: getstatic     #27                 // Field org/aspectj/weaver/UnresolvedType.NONE:[Lorg/aspectj/weaver/UnresolvedType;
      47: goto          63
      50: iconst_1
      51: anewarray     #36                 // class org/aspectj/weaver/UnresolvedType
      54: dup
      55: iconst_0
      56: aload_0
      57: invokeinterface #68,  1           // InterfaceMethod org/aspectj/weaver/ResolvedMember.getDeclaringType:()Lorg/aspectj/weaver/UnresolvedType;
      62: aastore
      63: getstatic     #27                 // Field org/aspectj/weaver/UnresolvedType.NONE:[Lorg/aspectj/weaver/UnresolvedType;
      66: invokespecial #42                 // Method org/aspectj/weaver/ResolvedMemberImpl."<init>":(Lorg/aspectj/weaver/MemberKind;Lorg/aspectj/weaver/UnresolvedType;ILorg/aspectj/weaver/UnresolvedType;Ljava/lang/String;[Lorg/aspectj/weaver/UnresolvedType;[Lorg/aspectj/weaver/UnresolvedType;)V
      69: astore_2
      70: aload_2
      71: aload_0
      72: invokeinterface #118,  1          // InterfaceMethod org/aspectj/weaver/ResolvedMember.getTypeVariables:()[Lorg/aspectj/weaver/TypeVariable;
      77: invokeinterface #119,  2          // InterfaceMethod org/aspectj/weaver/ResolvedMember.setTypeVariables:([Lorg/aspectj/weaver/TypeVariable;)V
      82: aload_2
      83: areturn

  public static org.aspectj.weaver.ResolvedMember interFieldClassField(org.aspectj.weaver.ResolvedMember, org.aspectj.weaver.UnresolvedType, boolean);
    Code:
       0: iload_2
       1: ifeq          16
       4: aload_0
       5: invokeinterface #69,  1           // InterfaceMethod org/aspectj/weaver/ResolvedMember.getModifiers:()I
      10: invokestatic  #121                // Method makeNonFinal:(I)I
      13: goto          25
      16: aload_0
      17: invokeinterface #69,  1           // InterfaceMethod org/aspectj/weaver/ResolvedMember.getModifiers:()I
      22: invokestatic  #122                // Method makePublicNonFinal:(I)I
      25: istore_3
      26: aconst_null
      27: astore        4
      29: iload_2
      30: ifeq          44
      33: aload_0
      34: invokeinterface #72,  1           // InterfaceMethod org/aspectj/weaver/ResolvedMember.getName:()Ljava/lang/String;
      39: astore        4
      41: goto          68
      44: aload_0
      45: invokeinterface #69,  1           // InterfaceMethod org/aspectj/weaver/ResolvedMember.getModifiers:()I
      50: aload_1
      51: aload_0
      52: invokeinterface #68,  1           // InterfaceMethod org/aspectj/weaver/ResolvedMember.getDeclaringType:()Lorg/aspectj/weaver/UnresolvedType;
      57: aload_0
      58: invokeinterface #72,  1           // InterfaceMethod org/aspectj/weaver/ResolvedMember.getName:()Ljava/lang/String;
      63: invokestatic  #123                // Method org/aspectj/weaver/NameMangler.interFieldClassField:(ILorg/aspectj/weaver/UnresolvedType;Lorg/aspectj/weaver/UnresolvedType;Ljava/lang/String;)Ljava/lang/String;
      66: astore        4
      68: new           #3                  // class org/aspectj/weaver/ResolvedMemberImpl
      71: dup
      72: getstatic     #15                 // Field org/aspectj/weaver/Member.FIELD:Lorg/aspectj/weaver/MemberKind;
      75: aload_0
      76: invokeinterface #68,  1           // InterfaceMethod org/aspectj/weaver/ResolvedMember.getDeclaringType:()Lorg/aspectj/weaver/UnresolvedType;
      81: iload_3
      82: aload_0
      83: invokeinterface #71,  1           // InterfaceMethod org/aspectj/weaver/ResolvedMember.getReturnType:()Lorg/aspectj/weaver/UnresolvedType;
      88: aload         4
      90: getstatic     #27                 // Field org/aspectj/weaver/UnresolvedType.NONE:[Lorg/aspectj/weaver/UnresolvedType;
      93: getstatic     #27                 // Field org/aspectj/weaver/UnresolvedType.NONE:[Lorg/aspectj/weaver/UnresolvedType;
      96: invokespecial #42                 // Method org/aspectj/weaver/ResolvedMemberImpl."<init>":(Lorg/aspectj/weaver/MemberKind;Lorg/aspectj/weaver/UnresolvedType;ILorg/aspectj/weaver/UnresolvedType;Ljava/lang/String;[Lorg/aspectj/weaver/UnresolvedType;[Lorg/aspectj/weaver/UnresolvedType;)V
      99: areturn

  public static org.aspectj.weaver.ResolvedMember interFieldInterfaceField(org.aspectj.weaver.ResolvedMember, org.aspectj.weaver.UnresolvedType, org.aspectj.weaver.UnresolvedType, boolean);
    Code:
       0: aconst_null
       1: astore        4
       3: iload_3
       4: ifeq          18
       7: aload_0
       8: invokeinterface #72,  1           // InterfaceMethod org/aspectj/weaver/ResolvedMember.getName:()Ljava/lang/String;
      13: astore        4
      15: goto          36
      18: aload_2
      19: aload_0
      20: invokeinterface #68,  1           // InterfaceMethod org/aspectj/weaver/ResolvedMember.getDeclaringType:()Lorg/aspectj/weaver/UnresolvedType;
      25: aload_0
      26: invokeinterface #72,  1           // InterfaceMethod org/aspectj/weaver/ResolvedMember.getName:()Ljava/lang/String;
      31: invokestatic  #124                // Method org/aspectj/weaver/NameMangler.interFieldInterfaceField:(Lorg/aspectj/weaver/UnresolvedType;Lorg/aspectj/weaver/UnresolvedType;Ljava/lang/String;)Ljava/lang/String;
      34: astore        4
      36: new           #3                  // class org/aspectj/weaver/ResolvedMemberImpl
      39: dup
      40: getstatic     #15                 // Field org/aspectj/weaver/Member.FIELD:Lorg/aspectj/weaver/MemberKind;
      43: aload_1
      44: aload_0
      45: invokeinterface #69,  1           // InterfaceMethod org/aspectj/weaver/ResolvedMember.getModifiers:()I
      50: invokestatic  #122                // Method makePublicNonFinal:(I)I
      53: aload_0
      54: invokeinterface #71,  1           // InterfaceMethod org/aspectj/weaver/ResolvedMember.getReturnType:()Lorg/aspectj/weaver/UnresolvedType;
      59: aload         4
      61: getstatic     #27                 // Field org/aspectj/weaver/UnresolvedType.NONE:[Lorg/aspectj/weaver/UnresolvedType;
      64: getstatic     #27                 // Field org/aspectj/weaver/UnresolvedType.NONE:[Lorg/aspectj/weaver/UnresolvedType;
      67: invokespecial #42                 // Method org/aspectj/weaver/ResolvedMemberImpl."<init>":(Lorg/aspectj/weaver/MemberKind;Lorg/aspectj/weaver/UnresolvedType;ILorg/aspectj/weaver/UnresolvedType;Ljava/lang/String;[Lorg/aspectj/weaver/UnresolvedType;[Lorg/aspectj/weaver/UnresolvedType;)V
      70: areturn

  public static org.aspectj.weaver.ResolvedMember interFieldInterfaceSetter(org.aspectj.weaver.ResolvedMember, org.aspectj.weaver.ResolvedType, org.aspectj.weaver.UnresolvedType);
    Code:
       0: iconst_1
       1: istore_3
       2: aload_1
       3: invokevirtual #125                // Method org/aspectj/weaver/ResolvedType.isInterface:()Z
       6: ifeq          15
       9: iload_3
      10: sipush        1024
      13: ior
      14: istore_3
      15: new           #3                  // class org/aspectj/weaver/ResolvedMemberImpl
      18: dup
      19: getstatic     #4                  // Field org/aspectj/weaver/Member.METHOD:Lorg/aspectj/weaver/MemberKind;
      22: aload_1
      23: iload_3
      24: getstatic     #90                 // Field org/aspectj/weaver/UnresolvedType.VOID:Lorg/aspectj/weaver/UnresolvedType;
      27: aload_2
      28: aload_0
      29: invokeinterface #68,  1           // InterfaceMethod org/aspectj/weaver/ResolvedMember.getDeclaringType:()Lorg/aspectj/weaver/UnresolvedType;
      34: aload_0
      35: invokeinterface #72,  1           // InterfaceMethod org/aspectj/weaver/ResolvedMember.getName:()Ljava/lang/String;
      40: invokestatic  #126                // Method org/aspectj/weaver/NameMangler.interFieldInterfaceSetter:(Lorg/aspectj/weaver/UnresolvedType;Lorg/aspectj/weaver/UnresolvedType;Ljava/lang/String;)Ljava/lang/String;
      43: iconst_1
      44: anewarray     #36                 // class org/aspectj/weaver/UnresolvedType
      47: dup
      48: iconst_0
      49: aload_0
      50: invokeinterface #71,  1           // InterfaceMethod org/aspectj/weaver/ResolvedMember.getReturnType:()Lorg/aspectj/weaver/UnresolvedType;
      55: aastore
      56: getstatic     #27                 // Field org/aspectj/weaver/UnresolvedType.NONE:[Lorg/aspectj/weaver/UnresolvedType;
      59: invokespecial #42                 // Method org/aspectj/weaver/ResolvedMemberImpl."<init>":(Lorg/aspectj/weaver/MemberKind;Lorg/aspectj/weaver/UnresolvedType;ILorg/aspectj/weaver/UnresolvedType;Ljava/lang/String;[Lorg/aspectj/weaver/UnresolvedType;[Lorg/aspectj/weaver/UnresolvedType;)V
      62: astore        4
      64: aload         4
      66: aload_0
      67: invokeinterface #118,  1          // InterfaceMethod org/aspectj/weaver/ResolvedMember.getTypeVariables:()[Lorg/aspectj/weaver/TypeVariable;
      72: invokeinterface #119,  2          // InterfaceMethod org/aspectj/weaver/ResolvedMember.setTypeVariables:([Lorg/aspectj/weaver/TypeVariable;)V
      77: aload         4
      79: areturn

  public static org.aspectj.weaver.ResolvedMember interFieldInterfaceGetter(org.aspectj.weaver.ResolvedMember, org.aspectj.weaver.ResolvedType, org.aspectj.weaver.UnresolvedType);
    Code:
       0: iconst_1
       1: istore_3
       2: aload_1
       3: invokevirtual #125                // Method org/aspectj/weaver/ResolvedType.isInterface:()Z
       6: ifeq          15
       9: iload_3
      10: sipush        1024
      13: ior
      14: istore_3
      15: new           #3                  // class org/aspectj/weaver/ResolvedMemberImpl
      18: dup
      19: getstatic     #4                  // Field org/aspectj/weaver/Member.METHOD:Lorg/aspectj/weaver/MemberKind;
      22: aload_1
      23: iload_3
      24: aload_0
      25: invokeinterface #71,  1           // InterfaceMethod org/aspectj/weaver/ResolvedMember.getReturnType:()Lorg/aspectj/weaver/UnresolvedType;
      30: aload_2
      31: aload_0
      32: invokeinterface #68,  1           // InterfaceMethod org/aspectj/weaver/ResolvedMember.getDeclaringType:()Lorg/aspectj/weaver/UnresolvedType;
      37: aload_0
      38: invokeinterface #72,  1           // InterfaceMethod org/aspectj/weaver/ResolvedMember.getName:()Ljava/lang/String;
      43: invokestatic  #127                // Method org/aspectj/weaver/NameMangler.interFieldInterfaceGetter:(Lorg/aspectj/weaver/UnresolvedType;Lorg/aspectj/weaver/UnresolvedType;Ljava/lang/String;)Ljava/lang/String;
      46: getstatic     #27                 // Field org/aspectj/weaver/UnresolvedType.NONE:[Lorg/aspectj/weaver/UnresolvedType;
      49: getstatic     #27                 // Field org/aspectj/weaver/UnresolvedType.NONE:[Lorg/aspectj/weaver/UnresolvedType;
      52: invokespecial #42                 // Method org/aspectj/weaver/ResolvedMemberImpl."<init>":(Lorg/aspectj/weaver/MemberKind;Lorg/aspectj/weaver/UnresolvedType;ILorg/aspectj/weaver/UnresolvedType;Ljava/lang/String;[Lorg/aspectj/weaver/UnresolvedType;[Lorg/aspectj/weaver/UnresolvedType;)V
      55: astore        4
      57: aload         4
      59: aload_0
      60: invokeinterface #118,  1          // InterfaceMethod org/aspectj/weaver/ResolvedMember.getTypeVariables:()[Lorg/aspectj/weaver/TypeVariable;
      65: invokeinterface #119,  2          // InterfaceMethod org/aspectj/weaver/ResolvedMember.setTypeVariables:([Lorg/aspectj/weaver/TypeVariable;)V
      70: aload         4
      72: areturn

  public static org.aspectj.weaver.ResolvedMember interMethod(org.aspectj.weaver.ResolvedMember, org.aspectj.weaver.UnresolvedType, boolean);
    Code:
       0: aload_0
       1: invokeinterface #69,  1           // InterfaceMethod org/aspectj/weaver/ResolvedMember.getModifiers:()I
       6: invokestatic  #113                // Method java/lang/reflect/Modifier.isPublic:(I)Z
       9: ifeq          18
      12: iload_2
      13: ifne          18
      16: aload_0
      17: areturn
      18: aload_0
      19: invokeinterface #69,  1           // InterfaceMethod org/aspectj/weaver/ResolvedMember.getModifiers:()I
      24: invokestatic  #122                // Method makePublicNonFinal:(I)I
      27: istore_3
      28: iload_2
      29: ifeq          38
      32: iload_3
      33: sipush        1024
      36: ior
      37: istore_3
      38: new           #3                  // class org/aspectj/weaver/ResolvedMemberImpl
      41: dup
      42: getstatic     #4                  // Field org/aspectj/weaver/Member.METHOD:Lorg/aspectj/weaver/MemberKind;
      45: aload_0
      46: invokeinterface #68,  1           // InterfaceMethod org/aspectj/weaver/ResolvedMember.getDeclaringType:()Lorg/aspectj/weaver/UnresolvedType;
      51: iload_3
      52: aload_0
      53: invokeinterface #71,  1           // InterfaceMethod org/aspectj/weaver/ResolvedMember.getReturnType:()Lorg/aspectj/weaver/UnresolvedType;
      58: aload_0
      59: invokeinterface #69,  1           // InterfaceMethod org/aspectj/weaver/ResolvedMember.getModifiers:()I
      64: aload_1
      65: aload_0
      66: invokeinterface #68,  1           // InterfaceMethod org/aspectj/weaver/ResolvedMember.getDeclaringType:()Lorg/aspectj/weaver/UnresolvedType;
      71: aload_0
      72: invokeinterface #72,  1           // InterfaceMethod org/aspectj/weaver/ResolvedMember.getName:()Ljava/lang/String;
      77: invokestatic  #128                // Method org/aspectj/weaver/NameMangler.interMethod:(ILorg/aspectj/weaver/UnresolvedType;Lorg/aspectj/weaver/UnresolvedType;Ljava/lang/String;)Ljava/lang/String;
      80: aload_0
      81: invokeinterface #74,  1           // InterfaceMethod org/aspectj/weaver/ResolvedMember.getParameterTypes:()[Lorg/aspectj/weaver/UnresolvedType;
      86: aload_0
      87: invokeinterface #75,  1           // InterfaceMethod org/aspectj/weaver/ResolvedMember.getExceptions:()[Lorg/aspectj/weaver/UnresolvedType;
      92: invokespecial #42                 // Method org/aspectj/weaver/ResolvedMemberImpl."<init>":(Lorg/aspectj/weaver/MemberKind;Lorg/aspectj/weaver/UnresolvedType;ILorg/aspectj/weaver/UnresolvedType;Ljava/lang/String;[Lorg/aspectj/weaver/UnresolvedType;[Lorg/aspectj/weaver/UnresolvedType;)V
      95: astore        4
      97: aload         4
      99: aload_0
     100: invokeinterface #129,  1          // InterfaceMethod org/aspectj/weaver/ResolvedMember.getParameterNames:()[Ljava/lang/String;
     105: invokevirtual #130                // Method org/aspectj/weaver/ResolvedMemberImpl.setParameterNames:([Ljava/lang/String;)V
     108: aload         4
     110: aload_0
     111: invokeinterface #118,  1          // InterfaceMethod org/aspectj/weaver/ResolvedMember.getTypeVariables:()[Lorg/aspectj/weaver/TypeVariable;
     116: invokevirtual #131                // Method org/aspectj/weaver/ResolvedMemberImpl.setTypeVariables:([Lorg/aspectj/weaver/TypeVariable;)V
     119: aload         4
     121: areturn

  public static org.aspectj.weaver.ResolvedMember interMethodBridger(org.aspectj.weaver.ResolvedMember, org.aspectj.weaver.UnresolvedType, boolean);
    Code:
       0: aload_0
       1: invokeinterface #69,  1           // InterfaceMethod org/aspectj/weaver/ResolvedMember.getModifiers:()I
       6: invokestatic  #122                // Method makePublicNonFinal:(I)I
       9: bipush        64
      11: ior
      12: istore_3
      13: iload_2
      14: ifeq          23
      17: iload_3
      18: sipush        1024
      21: ior
      22: istore_3
      23: new           #3                  // class org/aspectj/weaver/ResolvedMemberImpl
      26: dup
      27: getstatic     #4                  // Field org/aspectj/weaver/Member.METHOD:Lorg/aspectj/weaver/MemberKind;
      30: aload_0
      31: invokeinterface #68,  1           // InterfaceMethod org/aspectj/weaver/ResolvedMember.getDeclaringType:()Lorg/aspectj/weaver/UnresolvedType;
      36: iload_3
      37: aload_0
      38: invokeinterface #71,  1           // InterfaceMethod org/aspectj/weaver/ResolvedMember.getReturnType:()Lorg/aspectj/weaver/UnresolvedType;
      43: aload_0
      44: invokeinterface #69,  1           // InterfaceMethod org/aspectj/weaver/ResolvedMember.getModifiers:()I
      49: aload_1
      50: aload_0
      51: invokeinterface #68,  1           // InterfaceMethod org/aspectj/weaver/ResolvedMember.getDeclaringType:()Lorg/aspectj/weaver/UnresolvedType;
      56: aload_0
      57: invokeinterface #72,  1           // InterfaceMethod org/aspectj/weaver/ResolvedMember.getName:()Ljava/lang/String;
      62: invokestatic  #128                // Method org/aspectj/weaver/NameMangler.interMethod:(ILorg/aspectj/weaver/UnresolvedType;Lorg/aspectj/weaver/UnresolvedType;Ljava/lang/String;)Ljava/lang/String;
      65: aload_0
      66: invokeinterface #74,  1           // InterfaceMethod org/aspectj/weaver/ResolvedMember.getParameterTypes:()[Lorg/aspectj/weaver/UnresolvedType;
      71: aload_0
      72: invokeinterface #75,  1           // InterfaceMethod org/aspectj/weaver/ResolvedMember.getExceptions:()[Lorg/aspectj/weaver/UnresolvedType;
      77: invokespecial #42                 // Method org/aspectj/weaver/ResolvedMemberImpl."<init>":(Lorg/aspectj/weaver/MemberKind;Lorg/aspectj/weaver/UnresolvedType;ILorg/aspectj/weaver/UnresolvedType;Ljava/lang/String;[Lorg/aspectj/weaver/UnresolvedType;[Lorg/aspectj/weaver/UnresolvedType;)V
      80: astore        4
      82: aload         4
      84: aload_0
      85: invokeinterface #118,  1          // InterfaceMethod org/aspectj/weaver/ResolvedMember.getTypeVariables:()[Lorg/aspectj/weaver/TypeVariable;
      90: invokevirtual #131                // Method org/aspectj/weaver/ResolvedMemberImpl.setTypeVariables:([Lorg/aspectj/weaver/TypeVariable;)V
      93: aload         4
      95: areturn

  public static org.aspectj.weaver.ResolvedMember bridgerToInterMethod(org.aspectj.weaver.ResolvedMember, org.aspectj.weaver.UnresolvedType);
    Code:
       0: aload_0
       1: invokeinterface #69,  1           // InterfaceMethod org/aspectj/weaver/ResolvedMember.getModifiers:()I
       6: invokestatic  #122                // Method makePublicNonFinal:(I)I
       9: istore_2
      10: new           #3                  // class org/aspectj/weaver/ResolvedMemberImpl
      13: dup
      14: getstatic     #4                  // Field org/aspectj/weaver/Member.METHOD:Lorg/aspectj/weaver/MemberKind;
      17: aload_1
      18: iload_2
      19: aload_0
      20: invokeinterface #71,  1           // InterfaceMethod org/aspectj/weaver/ResolvedMember.getReturnType:()Lorg/aspectj/weaver/UnresolvedType;
      25: aload_0
      26: invokeinterface #69,  1           // InterfaceMethod org/aspectj/weaver/ResolvedMember.getModifiers:()I
      31: aload_1
      32: aload_0
      33: invokeinterface #68,  1           // InterfaceMethod org/aspectj/weaver/ResolvedMember.getDeclaringType:()Lorg/aspectj/weaver/UnresolvedType;
      38: aload_0
      39: invokeinterface #72,  1           // InterfaceMethod org/aspectj/weaver/ResolvedMember.getName:()Ljava/lang/String;
      44: invokestatic  #128                // Method org/aspectj/weaver/NameMangler.interMethod:(ILorg/aspectj/weaver/UnresolvedType;Lorg/aspectj/weaver/UnresolvedType;Ljava/lang/String;)Ljava/lang/String;
      47: aload_0
      48: invokeinterface #74,  1           // InterfaceMethod org/aspectj/weaver/ResolvedMember.getParameterTypes:()[Lorg/aspectj/weaver/UnresolvedType;
      53: aload_0
      54: invokeinterface #75,  1           // InterfaceMethod org/aspectj/weaver/ResolvedMember.getExceptions:()[Lorg/aspectj/weaver/UnresolvedType;
      59: invokespecial #42                 // Method org/aspectj/weaver/ResolvedMemberImpl."<init>":(Lorg/aspectj/weaver/MemberKind;Lorg/aspectj/weaver/UnresolvedType;ILorg/aspectj/weaver/UnresolvedType;Ljava/lang/String;[Lorg/aspectj/weaver/UnresolvedType;[Lorg/aspectj/weaver/UnresolvedType;)V
      62: astore_3
      63: aload_3
      64: aload_0
      65: invokeinterface #118,  1          // InterfaceMethod org/aspectj/weaver/ResolvedMember.getTypeVariables:()[Lorg/aspectj/weaver/TypeVariable;
      70: invokevirtual #131                // Method org/aspectj/weaver/ResolvedMemberImpl.setTypeVariables:([Lorg/aspectj/weaver/TypeVariable;)V
      73: aload_3
      74: areturn

  public static org.aspectj.weaver.ResolvedMember interMethodDispatcher(org.aspectj.weaver.ResolvedMember, org.aspectj.weaver.UnresolvedType);
    Code:
       0: aload_0
       1: invokeinterface #74,  1           // InterfaceMethod org/aspectj/weaver/ResolvedMember.getParameterTypes:()[Lorg/aspectj/weaver/UnresolvedType;
       6: astore_2
       7: aload_0
       8: invokeinterface #69,  1           // InterfaceMethod org/aspectj/weaver/ResolvedMember.getModifiers:()I
      13: invokestatic  #70                 // Method java/lang/reflect/Modifier.isStatic:(I)Z
      16: ifne          30
      19: aload_0
      20: invokeinterface #68,  1           // InterfaceMethod org/aspectj/weaver/ResolvedMember.getDeclaringType:()Lorg/aspectj/weaver/UnresolvedType;
      25: aload_2
      26: invokestatic  #93                 // Method org/aspectj/weaver/UnresolvedType.insert:(Lorg/aspectj/weaver/UnresolvedType;[Lorg/aspectj/weaver/UnresolvedType;)[Lorg/aspectj/weaver/UnresolvedType;
      29: astore_2
      30: new           #3                  // class org/aspectj/weaver/ResolvedMemberImpl
      33: dup
      34: getstatic     #4                  // Field org/aspectj/weaver/Member.METHOD:Lorg/aspectj/weaver/MemberKind;
      37: aload_1
      38: bipush        9
      40: aload_0
      41: invokeinterface #71,  1           // InterfaceMethod org/aspectj/weaver/ResolvedMember.getReturnType:()Lorg/aspectj/weaver/UnresolvedType;
      46: aload_1
      47: aload_0
      48: invokeinterface #68,  1           // InterfaceMethod org/aspectj/weaver/ResolvedMember.getDeclaringType:()Lorg/aspectj/weaver/UnresolvedType;
      53: aload_0
      54: invokeinterface #72,  1           // InterfaceMethod org/aspectj/weaver/ResolvedMember.getName:()Ljava/lang/String;
      59: invokestatic  #132                // Method org/aspectj/weaver/NameMangler.interMethodDispatcher:(Lorg/aspectj/weaver/UnresolvedType;Lorg/aspectj/weaver/UnresolvedType;Ljava/lang/String;)Ljava/lang/String;
      62: aload_2
      63: aload_0
      64: invokeinterface #75,  1           // InterfaceMethod org/aspectj/weaver/ResolvedMember.getExceptions:()[Lorg/aspectj/weaver/UnresolvedType;
      69: invokespecial #42                 // Method org/aspectj/weaver/ResolvedMemberImpl."<init>":(Lorg/aspectj/weaver/MemberKind;Lorg/aspectj/weaver/UnresolvedType;ILorg/aspectj/weaver/UnresolvedType;Ljava/lang/String;[Lorg/aspectj/weaver/UnresolvedType;[Lorg/aspectj/weaver/UnresolvedType;)V
      72: astore_3
      73: aload_3
      74: aload_0
      75: invokeinterface #129,  1          // InterfaceMethod org/aspectj/weaver/ResolvedMember.getParameterNames:()[Ljava/lang/String;
      80: invokevirtual #130                // Method org/aspectj/weaver/ResolvedMemberImpl.setParameterNames:([Ljava/lang/String;)V
      83: aload_3
      84: aload_0
      85: invokeinterface #118,  1          // InterfaceMethod org/aspectj/weaver/ResolvedMember.getTypeVariables:()[Lorg/aspectj/weaver/TypeVariable;
      90: invokevirtual #131                // Method org/aspectj/weaver/ResolvedMemberImpl.setTypeVariables:([Lorg/aspectj/weaver/TypeVariable;)V
      93: aload_3
      94: areturn

  public static org.aspectj.weaver.ResolvedMember interMethodBody(org.aspectj.weaver.ResolvedMember, org.aspectj.weaver.UnresolvedType);
    Code:
       0: aload_0
       1: invokeinterface #74,  1           // InterfaceMethod org/aspectj/weaver/ResolvedMember.getParameterTypes:()[Lorg/aspectj/weaver/UnresolvedType;
       6: astore_2
       7: aload_0
       8: invokeinterface #69,  1           // InterfaceMethod org/aspectj/weaver/ResolvedMember.getModifiers:()I
      13: invokestatic  #70                 // Method java/lang/reflect/Modifier.isStatic:(I)Z
      16: ifne          30
      19: aload_0
      20: invokeinterface #68,  1           // InterfaceMethod org/aspectj/weaver/ResolvedMember.getDeclaringType:()Lorg/aspectj/weaver/UnresolvedType;
      25: aload_2
      26: invokestatic  #93                 // Method org/aspectj/weaver/UnresolvedType.insert:(Lorg/aspectj/weaver/UnresolvedType;[Lorg/aspectj/weaver/UnresolvedType;)[Lorg/aspectj/weaver/UnresolvedType;
      29: astore_2
      30: bipush        9
      32: istore_3
      33: aload_0
      34: invokeinterface #69,  1           // InterfaceMethod org/aspectj/weaver/ResolvedMember.getModifiers:()I
      39: invokestatic  #133                // Method java/lang/reflect/Modifier.isStrict:(I)Z
      42: ifeq          51
      45: iload_3
      46: sipush        2048
      49: ior
      50: istore_3
      51: new           #3                  // class org/aspectj/weaver/ResolvedMemberImpl
      54: dup
      55: getstatic     #4                  // Field org/aspectj/weaver/Member.METHOD:Lorg/aspectj/weaver/MemberKind;
      58: aload_1
      59: iload_3
      60: aload_0
      61: invokeinterface #71,  1           // InterfaceMethod org/aspectj/weaver/ResolvedMember.getReturnType:()Lorg/aspectj/weaver/UnresolvedType;
      66: aload_1
      67: aload_0
      68: invokeinterface #68,  1           // InterfaceMethod org/aspectj/weaver/ResolvedMember.getDeclaringType:()Lorg/aspectj/weaver/UnresolvedType;
      73: aload_0
      74: invokeinterface #72,  1           // InterfaceMethod org/aspectj/weaver/ResolvedMember.getName:()Ljava/lang/String;
      79: invokestatic  #134                // Method org/aspectj/weaver/NameMangler.interMethodBody:(Lorg/aspectj/weaver/UnresolvedType;Lorg/aspectj/weaver/UnresolvedType;Ljava/lang/String;)Ljava/lang/String;
      82: aload_2
      83: aload_0
      84: invokeinterface #75,  1           // InterfaceMethod org/aspectj/weaver/ResolvedMember.getExceptions:()[Lorg/aspectj/weaver/UnresolvedType;
      89: invokespecial #42                 // Method org/aspectj/weaver/ResolvedMemberImpl."<init>":(Lorg/aspectj/weaver/MemberKind;Lorg/aspectj/weaver/UnresolvedType;ILorg/aspectj/weaver/UnresolvedType;Ljava/lang/String;[Lorg/aspectj/weaver/UnresolvedType;[Lorg/aspectj/weaver/UnresolvedType;)V
      92: astore        4
      94: aload         4
      96: aload_0
      97: invokeinterface #129,  1          // InterfaceMethod org/aspectj/weaver/ResolvedMember.getParameterNames:()[Ljava/lang/String;
     102: invokevirtual #130                // Method org/aspectj/weaver/ResolvedMemberImpl.setParameterNames:([Ljava/lang/String;)V
     105: aload         4
     107: aload_0
     108: invokeinterface #118,  1          // InterfaceMethod org/aspectj/weaver/ResolvedMember.getTypeVariables:()[Lorg/aspectj/weaver/TypeVariable;
     113: invokevirtual #131                // Method org/aspectj/weaver/ResolvedMemberImpl.setTypeVariables:([Lorg/aspectj/weaver/TypeVariable;)V
     116: aload         4
     118: areturn

  private static org.aspectj.weaver.ResolvedMember addCookieTo(org.aspectj.weaver.ResolvedMember, org.aspectj.weaver.UnresolvedType);
    Code:
       0: aload_0
       1: invokeinterface #74,  1           // InterfaceMethod org/aspectj/weaver/ResolvedMember.getParameterTypes:()[Lorg/aspectj/weaver/UnresolvedType;
       6: astore_2
       7: aload_2
       8: aload_1
       9: invokestatic  #135                // Method org/aspectj/weaver/UnresolvedType.add:([Lorg/aspectj/weaver/UnresolvedType;Lorg/aspectj/weaver/UnresolvedType;)[Lorg/aspectj/weaver/UnresolvedType;
      12: astore_3
      13: new           #3                  // class org/aspectj/weaver/ResolvedMemberImpl
      16: dup
      17: aload_0
      18: invokeinterface #136,  1          // InterfaceMethod org/aspectj/weaver/ResolvedMember.getKind:()Lorg/aspectj/weaver/MemberKind;
      23: aload_0
      24: invokeinterface #68,  1           // InterfaceMethod org/aspectj/weaver/ResolvedMember.getDeclaringType:()Lorg/aspectj/weaver/UnresolvedType;
      29: aload_0
      30: invokeinterface #69,  1           // InterfaceMethod org/aspectj/weaver/ResolvedMember.getModifiers:()I
      35: aload_0
      36: invokeinterface #71,  1           // InterfaceMethod org/aspectj/weaver/ResolvedMember.getReturnType:()Lorg/aspectj/weaver/UnresolvedType;
      41: aload_0
      42: invokeinterface #72,  1           // InterfaceMethod org/aspectj/weaver/ResolvedMember.getName:()Ljava/lang/String;
      47: aload_3
      48: aload_0
      49: invokeinterface #75,  1           // InterfaceMethod org/aspectj/weaver/ResolvedMember.getExceptions:()[Lorg/aspectj/weaver/UnresolvedType;
      54: invokespecial #42                 // Method org/aspectj/weaver/ResolvedMemberImpl."<init>":(Lorg/aspectj/weaver/MemberKind;Lorg/aspectj/weaver/UnresolvedType;ILorg/aspectj/weaver/UnresolvedType;Ljava/lang/String;[Lorg/aspectj/weaver/UnresolvedType;[Lorg/aspectj/weaver/UnresolvedType;)V
      57: areturn

  public static org.aspectj.weaver.ResolvedMember toObjectConversionMethod(org.aspectj.weaver.UnresolvedType);
    Code:
       0: aload_0
       1: invokevirtual #137                // Method org/aspectj/weaver/UnresolvedType.isPrimitiveType:()Z
       4: ifeq          61
       7: new           #43                 // class java/lang/StringBuilder
      10: dup
      11: invokespecial #44                 // Method java/lang/StringBuilder."<init>":()V
      14: aload_0
      15: invokevirtual #138                // Method org/aspectj/weaver/UnresolvedType.toString:()Ljava/lang/String;
      18: invokevirtual #46                 // Method java/lang/StringBuilder.append:(Ljava/lang/String;)Ljava/lang/StringBuilder;
      21: ldc           #139                // String Object
      23: invokevirtual #46                 // Method java/lang/StringBuilder.append:(Ljava/lang/String;)Ljava/lang/StringBuilder;
      26: invokevirtual #48                 // Method java/lang/StringBuilder.toString:()Ljava/lang/String;
      29: astore_1
      30: new           #3                  // class org/aspectj/weaver/ResolvedMemberImpl
      33: dup
      34: getstatic     #4                  // Field org/aspectj/weaver/Member.METHOD:Lorg/aspectj/weaver/MemberKind;
      37: getstatic     #140                // Field CONVERSIONS_TYPE:Lorg/aspectj/weaver/UnresolvedType;
      40: bipush        9
      42: getstatic     #141                // Field org/aspectj/weaver/UnresolvedType.OBJECT:Lorg/aspectj/weaver/UnresolvedType;
      45: aload_1
      46: iconst_1
      47: anewarray     #36                 // class org/aspectj/weaver/UnresolvedType
      50: dup
      51: iconst_0
      52: aload_0
      53: aastore
      54: getstatic     #27                 // Field org/aspectj/weaver/UnresolvedType.NONE:[Lorg/aspectj/weaver/UnresolvedType;
      57: invokespecial #42                 // Method org/aspectj/weaver/ResolvedMemberImpl."<init>":(Lorg/aspectj/weaver/MemberKind;Lorg/aspectj/weaver/UnresolvedType;ILorg/aspectj/weaver/UnresolvedType;Ljava/lang/String;[Lorg/aspectj/weaver/UnresolvedType;[Lorg/aspectj/weaver/UnresolvedType;)V
      60: areturn
      61: aconst_null
      62: areturn

  public static org.aspectj.weaver.Member interfaceConstructor(org.aspectj.weaver.ResolvedType);
    Code:
       0: aload_0
       1: astore_1
       2: aload_1
       3: invokevirtual #142                // Method org/aspectj/weaver/ResolvedType.isRawType:()Z
       6: ifeq          14
       9: aload_1
      10: invokevirtual #143                // Method org/aspectj/weaver/ResolvedType.getGenericType:()Lorg/aspectj/weaver/ReferenceType;
      13: astore_1
      14: new           #3                  // class org/aspectj/weaver/ResolvedMemberImpl
      17: dup
      18: getstatic     #103                // Field org/aspectj/weaver/Member.CONSTRUCTOR:Lorg/aspectj/weaver/MemberKind;
      21: aload_1
      22: iconst_1
      23: ldc           #12                 // String <init>
      25: ldc           #8                  // String ()V
      27: invokespecial #9                  // Method org/aspectj/weaver/ResolvedMemberImpl."<init>":(Lorg/aspectj/weaver/MemberKind;Lorg/aspectj/weaver/UnresolvedType;ILjava/lang/String;Ljava/lang/String;)V
      30: areturn

  static {};
    Code:
       0: ldc           #144                // String org.aspectj.runtime.internal.CFlowStack
       2: invokestatic  #49                 // Method org/aspectj/weaver/UnresolvedType.forName:(Ljava/lang/String;)Lorg/aspectj/weaver/UnresolvedType;
       5: putstatic     #17                 // Field CFLOW_STACK_TYPE:Lorg/aspectj/weaver/UnresolvedType;
       8: ldc           #145                // String Lorg/aspectj/runtime/internal/AroundClosure;
      10: invokestatic  #41                 // Method org/aspectj/weaver/UnresolvedType.forSignature:(Ljava/lang/String;)Lorg/aspectj/weaver/UnresolvedType;
      13: putstatic     #104                // Field AROUND_CLOSURE_TYPE:Lorg/aspectj/weaver/UnresolvedType;
      16: ldc           #146                // String Lorg/aspectj/runtime/internal/Conversions;
      18: invokestatic  #41                 // Method org/aspectj/weaver/UnresolvedType.forSignature:(Ljava/lang/String;)Lorg/aspectj/weaver/UnresolvedType;
      21: putstatic     #140                // Field CONVERSIONS_TYPE:Lorg/aspectj/weaver/UnresolvedType;
      24: ldc           #147                // String Lorg/aspectj/lang/NoAspectBoundException;
      26: invokestatic  #41                 // Method org/aspectj/weaver/UnresolvedType.forSignature:(Ljava/lang/String;)Lorg/aspectj/weaver/UnresolvedType;
      29: putstatic     #11                 // Field NO_ASPECT_BOUND_EXCEPTION:Lorg/aspectj/weaver/UnresolvedType;
      32: ldc           #148                // String Lorg/aspectj/lang/annotation/Aspect;
      34: invokestatic  #41                 // Method org/aspectj/weaver/UnresolvedType.forSignature:(Ljava/lang/String;)Lorg/aspectj/weaver/UnresolvedType;
      37: putstatic     #149                // Field ASPECT_ANNOTATION:Lorg/aspectj/weaver/UnresolvedType;
      40: ldc           #150                // String Lorg/aspectj/lang/annotation/Before;
      42: invokestatic  #41                 // Method org/aspectj/weaver/UnresolvedType.forSignature:(Ljava/lang/String;)Lorg/aspectj/weaver/UnresolvedType;
      45: putstatic     #151                // Field BEFORE_ANNOTATION:Lorg/aspectj/weaver/UnresolvedType;
      48: ldc           #152                // String Lorg/aspectj/lang/annotation/Around;
      50: invokestatic  #41                 // Method org/aspectj/weaver/UnresolvedType.forSignature:(Ljava/lang/String;)Lorg/aspectj/weaver/UnresolvedType;
      53: putstatic     #153                // Field AROUND_ANNOTATION:Lorg/aspectj/weaver/UnresolvedType;
      56: ldc           #154                // String Lorg/aspectj/lang/annotation/AfterReturning;
      58: invokestatic  #41                 // Method org/aspectj/weaver/UnresolvedType.forSignature:(Ljava/lang/String;)Lorg/aspectj/weaver/UnresolvedType;
      61: putstatic     #155                // Field AFTERRETURNING_ANNOTATION:Lorg/aspectj/weaver/UnresolvedType;
      64: ldc           #156                // String Lorg/aspectj/lang/annotation/AfterThrowing;
      66: invokestatic  #41                 // Method org/aspectj/weaver/UnresolvedType.forSignature:(Ljava/lang/String;)Lorg/aspectj/weaver/UnresolvedType;
      69: putstatic     #157                // Field AFTERTHROWING_ANNOTATION:Lorg/aspectj/weaver/UnresolvedType;
      72: ldc           #158                // String Lorg/aspectj/lang/annotation/After;
      74: invokestatic  #41                 // Method org/aspectj/weaver/UnresolvedType.forSignature:(Ljava/lang/String;)Lorg/aspectj/weaver/UnresolvedType;
      77: putstatic     #159                // Field AFTER_ANNOTATION:Lorg/aspectj/weaver/UnresolvedType;
      80: ldc           #160                // String Lorg/aspectj/lang/annotation/Pointcut;
      82: invokestatic  #41                 // Method org/aspectj/weaver/UnresolvedType.forSignature:(Ljava/lang/String;)Lorg/aspectj/weaver/UnresolvedType;
      85: putstatic     #161                // Field POINTCUT_ANNOTATION:Lorg/aspectj/weaver/UnresolvedType;
      88: ldc           #162                // String Lorg/aspectj/lang/annotation/DeclareError;
      90: invokestatic  #41                 // Method org/aspectj/weaver/UnresolvedType.forSignature:(Ljava/lang/String;)Lorg/aspectj/weaver/UnresolvedType;
      93: putstatic     #163                // Field DECLAREERROR_ANNOTATION:Lorg/aspectj/weaver/UnresolvedType;
      96: ldc           #164                // String Lorg/aspectj/lang/annotation/DeclareWarning;
      98: invokestatic  #41                 // Method org/aspectj/weaver/UnresolvedType.forSignature:(Ljava/lang/String;)Lorg/aspectj/weaver/UnresolvedType;
     101: putstatic     #165                // Field DECLAREWARNING_ANNOTATION:Lorg/aspectj/weaver/UnresolvedType;
     104: ldc           #166                // String Lorg/aspectj/lang/annotation/DeclarePrecedence;
     106: invokestatic  #41                 // Method org/aspectj/weaver/UnresolvedType.forSignature:(Ljava/lang/String;)Lorg/aspectj/weaver/UnresolvedType;
     109: putstatic     #167                // Field DECLAREPRECEDENCE_ANNOTATION:Lorg/aspectj/weaver/UnresolvedType;
     112: ldc           #168                // String Lorg/aspectj/lang/annotation/DeclareParents;
     114: invokestatic  #41                 // Method org/aspectj/weaver/UnresolvedType.forSignature:(Ljava/lang/String;)Lorg/aspectj/weaver/UnresolvedType;
     117: putstatic     #169                // Field DECLAREPARENTS_ANNOTATION:Lorg/aspectj/weaver/UnresolvedType;
     120: ldc           #170                // String Lorg/aspectj/lang/annotation/DeclareMixin;
     122: invokestatic  #41                 // Method org/aspectj/weaver/UnresolvedType.forSignature:(Ljava/lang/String;)Lorg/aspectj/weaver/UnresolvedType;
     125: putstatic     #171                // Field DECLAREMIXIN_ANNOTATION:Lorg/aspectj/weaver/UnresolvedType;
     128: ldc           #172                // String Lorg/aspectj/lang/JoinPoint;
     130: invokestatic  #41                 // Method org/aspectj/weaver/UnresolvedType.forSignature:(Ljava/lang/String;)Lorg/aspectj/weaver/UnresolvedType;
     133: putstatic     #173                // Field TYPEX_JOINPOINT:Lorg/aspectj/weaver/UnresolvedType;
     136: ldc           #174                // String Lorg/aspectj/lang/ProceedingJoinPoint;
     138: invokestatic  #41                 // Method org/aspectj/weaver/UnresolvedType.forSignature:(Ljava/lang/String;)Lorg/aspectj/weaver/UnresolvedType;
     141: putstatic     #175                // Field TYPEX_PROCEEDINGJOINPOINT:Lorg/aspectj/weaver/UnresolvedType;
     144: ldc           #176                // String Lorg/aspectj/lang/JoinPoint$StaticPart;
     146: invokestatic  #41                 // Method org/aspectj/weaver/UnresolvedType.forSignature:(Ljava/lang/String;)Lorg/aspectj/weaver/UnresolvedType;
     149: putstatic     #177                // Field TYPEX_STATICJOINPOINT:Lorg/aspectj/weaver/UnresolvedType;
     152: ldc           #178                // String Lorg/aspectj/lang/JoinPoint$EnclosingStaticPart;
     154: invokestatic  #41                 // Method org/aspectj/weaver/UnresolvedType.forSignature:(Ljava/lang/String;)Lorg/aspectj/weaver/UnresolvedType;
     157: putstatic     #179                // Field TYPEX_ENCLOSINGSTATICJOINPOINT:Lorg/aspectj/weaver/UnresolvedType;
     160: return
}
