Compiled from "Hashing.java"
class org.apache.curator.shaded.com.google.common.hash.Hashing$SipHash24Holder {
  static final org.apache.curator.shaded.com.google.common.hash.HashFunction SIP_HASH_24;

  private org.apache.curator.shaded.com.google.common.hash.Hashing$SipHash24Holder();
    Code:
       0: aload_0
       1: invokespecial #14                 // Method java/lang/Object."<init>":()V
       4: return

  static {};
    Code:
       0: new           #19                 // class org/apache/curator/shaded/com/google/common/hash/SipHashFunction
       3: dup
       4: iconst_2
       5: iconst_4
       6: ldc2_w        #20                 // long 506097522914230528l
       9: ldc2_w        #22                 // long 1084818905618843912l
      12: invokespecial #26                 // Method org/apache/curator/shaded/com/google/common/hash/SipHashFunction."<init>":(IIJJ)V
      15: putstatic     #28                 // Field SIP_HASH_24:Lorg/apache/curator/shaded/com/google/common/hash/HashFunction;
      18: return
}
