Compiled from "GrpcAuthorizationEngine.java"
public abstract class io.grpc.xds.internal.rbac.engine.GrpcAuthorizationEngine$AlwaysTrueMatcher implements io.grpc.xds.internal.rbac.engine.GrpcAuthorizationEngine$Matcher {
  public static io.grpc.xds.internal.rbac.engine.GrpcAuthorizationEngine$AlwaysTrueMatcher INSTANCE;

  public io.grpc.xds.internal.rbac.engine.GrpcAuthorizationEngine$AlwaysTrueMatcher();
    Code:
       0: aload_0
       1: invokespecial #21                 // Method java/lang/Object."<init>":()V
       4: return

  public boolean matches(io.grpc.xds.internal.rbac.engine.GrpcAuthorizationEngine$EvaluateArgs);
    Code:
       0: iconst_1
       1: ireturn

  static {};
    Code:
       0: new           #29                 // class io/grpc/xds/internal/rbac/engine/AutoValue_GrpcAuthorizationEngine_AlwaysTrueMatcher
       3: dup
       4: invokespecial #30                 // Method io/grpc/xds/internal/rbac/engine/AutoValue_GrpcAuthorizationEngine_AlwaysTrueMatcher."<init>":()V
       7: putstatic     #32                 // Field INSTANCE:Lio/grpc/xds/internal/rbac/engine/GrpcAuthorizationEngine$AlwaysTrueMatcher;
      10: return
}
