Compiled from "GrpcAuthorizationEngine.java"
public abstract class io.grpc.xds.internal.rbac.engine.GrpcAuthorizationEngine$AuthHeaderMatcher implements io.grpc.xds.internal.rbac.engine.GrpcAuthorizationEngine$Matcher {
  public io.grpc.xds.internal.rbac.engine.GrpcAuthorizationEngine$AuthHeaderMatcher();
    Code:
       0: aload_0
       1: invokespecial #24                 // Method java/lang/Object."<init>":()V
       4: return

  public abstract io.grpc.xds.internal.Matchers$HeaderMatcher delegate();

  public static io.grpc.xds.internal.rbac.engine.GrpcAuthorizationEngine$AuthHeaderMatcher create(io.grpc.xds.internal.Matchers$HeaderMatcher);
    Code:
       0: new           #32                 // class io/grpc/xds/internal/rbac/engine/AutoValue_GrpcAuthorizationEngine_AuthHeaderMatcher
       3: dup
       4: aload_0
       5: invokespecial #35                 // Method io/grpc/xds/internal/rbac/engine/AutoValue_GrpcAuthorizationEngine_AuthHeaderMatcher."<init>":(Lio/grpc/xds/internal/Matchers$HeaderMatcher;)V
       8: areturn

  public boolean matches(io.grpc.xds.internal.rbac.engine.GrpcAuthorizationEngine$EvaluateArgs);
    Code:
       0: aload_0
       1: invokevirtual #40                 // Method delegate:()Lio/grpc/xds/internal/Matchers$HeaderMatcher;
       4: aload_1
       5: aload_0
       6: invokevirtual #40                 // Method delegate:()Lio/grpc/xds/internal/Matchers$HeaderMatcher;
       9: invokevirtual #44                 // Method io/grpc/xds/internal/Matchers$HeaderMatcher.name:()Ljava/lang/String;
      12: invokestatic  #48                 // Method io/grpc/xds/internal/rbac/engine/GrpcAuthorizationEngine$EvaluateArgs.access$600:(Lio/grpc/xds/internal/rbac/engine/GrpcAuthorizationEngine$EvaluateArgs;Ljava/lang/String;)Ljava/lang/String;
      15: invokevirtual #51                 // Method io/grpc/xds/internal/Matchers$HeaderMatcher.matches:(Ljava/lang/String;)Z
      18: ireturn
}
