Compiled from "StringModelSource.java"
public class org.apache.maven.model.building.StringModelSource implements org.apache.maven.model.building.ModelSource {
  private java.lang.String pom;

  private java.lang.String location;

  public org.apache.maven.model.building.StringModelSource(java.lang.CharSequence);
    Code:
       0: aload_0
       1: aload_1
       2: aconst_null
       3: invokespecial #1                  // Method "<init>":(Ljava/lang/CharSequence;Ljava/lang/String;)V
       6: return

  public org.apache.maven.model.building.StringModelSource(java.lang.CharSequence, java.lang.String);
    Code:
       0: aload_0
       1: invokespecial #2                  // Method java/lang/Object."<init>":()V
       4: aload_0
       5: aload_1
       6: ifnull        16
       9: aload_1
      10: invokevirtual #3                  // Method java/lang/Object.toString:()Ljava/lang/String;
      13: goto          18
      16: ldc           #4                  // String
      18: putfield      #5                  // Field pom:Ljava/lang/String;
      21: aload_0
      22: aload_2
      23: ifnull        30
      26: aload_2
      27: goto          32
      30: ldc           #6                  // String (memory)
      32: putfield      #7                  // Field location:Ljava/lang/String;
      35: return

  public java.io.InputStream getInputStream() throws java.io.IOException;
    Code:
       0: new           #8                  // class java/io/ByteArrayInputStream
       3: dup
       4: aload_0
       5: getfield      #5                  // Field pom:Ljava/lang/String;
       8: ldc           #9                  // String UTF-8
      10: invokevirtual #10                 // Method java/lang/String.getBytes:(Ljava/lang/String;)[B
      13: invokespecial #11                 // Method java/io/ByteArrayInputStream."<init>":([B)V
      16: areturn

  public java.lang.String getLocation();
    Code:
       0: aload_0
       1: getfield      #7                  // Field location:Ljava/lang/String;
       4: areturn

  public java.lang.String getModel();
    Code:
       0: aload_0
       1: getfield      #5                  // Field pom:Ljava/lang/String;
       4: areturn

  public java.lang.String toString();
    Code:
       0: aload_0
       1: invokevirtual #12                 // Method getLocation:()Ljava/lang/String;
       4: areturn
}
