Compiled from "JsonConverter.java"
final class org.apache.kafka.connect.json.JsonConverter$10 implements org.apache.kafka.connect.json.JsonConverter$JsonToConnectTypeConverter {
  org.apache.kafka.connect.json.JsonConverter$10();
    Code:
       0: aload_0
       1: invokespecial #1                  // Method java/lang/Object."<init>":()V
       4: return

  public java.lang.Object convert(org.apache.kafka.connect.data.Schema, com.fasterxml.jackson.databind.JsonNode);
    Code:
       0: aload_1
       1: ifnonnull     8
       4: aconst_null
       5: goto          14
       8: aload_1
       9: invokeinterface #2,  1            // InterfaceMethod org/apache/kafka/connect/data/Schema.valueSchema:()Lorg/apache/kafka/connect/data/Schema;
      14: astore_3
      15: new           #3                  // class java/util/ArrayList
      18: dup
      19: invokespecial #4                  // Method java/util/ArrayList."<init>":()V
      22: astore        4
      24: aload_2
      25: invokevirtual #5                  // Method com/fasterxml/jackson/databind/JsonNode.iterator:()Ljava/util/Iterator;
      28: astore        5
      30: aload         5
      32: invokeinterface #6,  1            // InterfaceMethod java/util/Iterator.hasNext:()Z
      37: ifeq          67
      40: aload         5
      42: invokeinterface #7,  1            // InterfaceMethod java/util/Iterator.next:()Ljava/lang/Object;
      47: checkcast     #8                  // class com/fasterxml/jackson/databind/JsonNode
      50: astore        6
      52: aload         4
      54: aload_3
      55: aload         6
      57: invokestatic  #9                  // Method org/apache/kafka/connect/json/JsonConverter.access$000:(Lorg/apache/kafka/connect/data/Schema;Lcom/fasterxml/jackson/databind/JsonNode;)Ljava/lang/Object;
      60: invokevirtual #10                 // Method java/util/ArrayList.add:(Ljava/lang/Object;)Z
      63: pop
      64: goto          30
      67: aload         4
      69: areturn
}
