Compiled from "JsonSchema.java"
class org.apache.kafka.connect.json.JsonSchema$Envelope {
  public com.fasterxml.jackson.databind.JsonNode schema;

  public com.fasterxml.jackson.databind.JsonNode payload;

  public org.apache.kafka.connect.json.JsonSchema$Envelope(com.fasterxml.jackson.databind.JsonNode, com.fasterxml.jackson.databind.JsonNode);
    Code:
       0: aload_0
       1: invokespecial #1                  // Method java/lang/Object."<init>":()V
       4: aload_0
       5: aload_1
       6: putfield      #2                  // Field schema:Lcom/fasterxml/jackson/databind/JsonNode;
       9: aload_0
      10: aload_2
      11: putfield      #3                  // Field payload:Lcom/fasterxml/jackson/databind/JsonNode;
      14: return

  public com.fasterxml.jackson.databind.node.ObjectNode toJsonNode();
    Code:
       0: aload_0
       1: getfield      #2                  // Field schema:Lcom/fasterxml/jackson/databind/JsonNode;
       4: aload_0
       5: getfield      #3                  // Field payload:Lcom/fasterxml/jackson/databind/JsonNode;
       8: invokestatic  #4                  // Method org/apache/kafka/connect/json/JsonSchema.envelope:(Lcom/fasterxml/jackson/databind/JsonNode;Lcom/fasterxml/jackson/databind/JsonNode;)Lcom/fasterxml/jackson/databind/node/ObjectNode;
      11: areturn
}
