Compiled from "ValueMatcher.java"
public final class io.grpc.xds.shaded.io.envoyproxy.envoy.type.matcher.ValueMatcher extends com.google.protobuf.GeneratedMessageV3 implements io.grpc.xds.shaded.io.envoyproxy.envoy.type.matcher.ValueMatcherOrBuilder {
  private static final long serialVersionUID;

  private int matchPatternCase_;

  private java.lang.Object matchPattern_;

  public static final int NULL_MATCH_FIELD_NUMBER;

  public static final int DOUBLE_MATCH_FIELD_NUMBER;

  public static final int STRING_MATCH_FIELD_NUMBER;

  public static final int BOOL_MATCH_FIELD_NUMBER;

  public static final int PRESENT_MATCH_FIELD_NUMBER;

  public static final int LIST_MATCH_FIELD_NUMBER;

  private byte memoizedIsInitialized;

  private static final io.grpc.xds.shaded.io.envoyproxy.envoy.type.matcher.ValueMatcher DEFAULT_INSTANCE;

  private static final com.google.protobuf.Parser<io.grpc.xds.shaded.io.envoyproxy.envoy.type.matcher.ValueMatcher> PARSER;

  private io.grpc.xds.shaded.io.envoyproxy.envoy.type.matcher.ValueMatcher(com.google.protobuf.GeneratedMessageV3$Builder<?>);
    Code:
       0: aload_0
       1: aload_1
       2: invokespecial #97                 // Method com/google/protobuf/GeneratedMessageV3."<init>":(Lcom/google/protobuf/GeneratedMessageV3$Builder;)V
       5: aload_0
       6: iconst_0
       7: putfield      #99                 // Field matchPatternCase_:I
      10: aload_0
      11: iconst_m1
      12: putfield      #101                // Field memoizedIsInitialized:B
      15: return

  private io.grpc.xds.shaded.io.envoyproxy.envoy.type.matcher.ValueMatcher();
    Code:
       0: aload_0
       1: invokespecial #108                // Method com/google/protobuf/GeneratedMessageV3."<init>":()V
       4: aload_0
       5: iconst_0
       6: putfield      #99                 // Field matchPatternCase_:I
       9: aload_0
      10: iconst_m1
      11: putfield      #101                // Field memoizedIsInitialized:B
      14: return

  protected java.lang.Object newInstance(com.google.protobuf.GeneratedMessageV3$UnusedPrivateParameter);
    Code:
       0: new           #2                  // class io/grpc/xds/shaded/io/envoyproxy/envoy/type/matcher/ValueMatcher
       3: dup
       4: invokespecial #111                // Method "<init>":()V
       7: areturn

  public final com.google.protobuf.UnknownFieldSet getUnknownFields();
    Code:
       0: aload_0
       1: getfield      #119                // Field unknownFields:Lcom/google/protobuf/UnknownFieldSet;
       4: areturn

  private io.grpc.xds.shaded.io.envoyproxy.envoy.type.matcher.ValueMatcher(com.google.protobuf.CodedInputStream, com.google.protobuf.ExtensionRegistryLite) throws com.google.protobuf.InvalidProtocolBufferException;
    Code:
       0: aload_0
       1: invokespecial #111                // Method "<init>":()V
       4: aload_2
       5: ifnonnull     16
       8: new           #126                // class java/lang/NullPointerException
      11: dup
      12: invokespecial #127                // Method java/lang/NullPointerException."<init>":()V
      15: athrow
      16: invokestatic  #135                // Method com/google/protobuf/UnknownFieldSet.newBuilder:()Lcom/google/protobuf/UnknownFieldSet$Builder;
      19: astore_3
      20: iconst_0
      21: istore        4
      23: iload         4
      25: ifne          448
      28: aload_1
      29: invokevirtual #139                // Method com/google/protobuf/CodedInputStream.readTag:()I
      32: istore        5
      34: iload         5
      36: lookupswitch  { // 7
                     0: 104
                    10: 110
                    18: 180
                    26: 250
                    32: 320
                    40: 339
                    50: 358
               default: 430
          }
     104: iconst_1
     105: istore        4
     107: goto          445
     110: aconst_null
     111: astore        6
     113: aload_0
     114: getfield      #99                 // Field matchPatternCase_:I
     117: iconst_1
     118: if_icmpne     133
     121: aload_0
     122: getfield      #141                // Field matchPattern_:Ljava/lang/Object;
     125: checkcast     #17                 // class io/grpc/xds/shaded/io/envoyproxy/envoy/type/matcher/ValueMatcher$NullMatch
     128: invokevirtual #145                // Method io/grpc/xds/shaded/io/envoyproxy/envoy/type/matcher/ValueMatcher$NullMatch.toBuilder:()Lio/grpc/xds/shaded/io/envoyproxy/envoy/type/matcher/ValueMatcher$NullMatch$Builder;
     131: astore        6
     133: aload_0
     134: aload_1
     135: invokestatic  #149                // Method io/grpc/xds/shaded/io/envoyproxy/envoy/type/matcher/ValueMatcher$NullMatch.parser:()Lcom/google/protobuf/Parser;
     138: aload_2
     139: invokevirtual #153                // Method com/google/protobuf/CodedInputStream.readMessage:(Lcom/google/protobuf/Parser;Lcom/google/protobuf/ExtensionRegistryLite;)Lcom/google/protobuf/MessageLite;
     142: putfield      #141                // Field matchPattern_:Ljava/lang/Object;
     145: aload         6
     147: ifnull        172
     150: aload         6
     152: aload_0
     153: getfield      #141                // Field matchPattern_:Ljava/lang/Object;
     156: checkcast     #17                 // class io/grpc/xds/shaded/io/envoyproxy/envoy/type/matcher/ValueMatcher$NullMatch
     159: invokevirtual #157                // Method io/grpc/xds/shaded/io/envoyproxy/envoy/type/matcher/ValueMatcher$NullMatch$Builder.mergeFrom:(Lio/grpc/xds/shaded/io/envoyproxy/envoy/type/matcher/ValueMatcher$NullMatch;)Lio/grpc/xds/shaded/io/envoyproxy/envoy/type/matcher/ValueMatcher$NullMatch$Builder;
     162: pop
     163: aload_0
     164: aload         6
     166: invokevirtual #161                // Method io/grpc/xds/shaded/io/envoyproxy/envoy/type/matcher/ValueMatcher$NullMatch$Builder.buildPartial:()Lio/grpc/xds/shaded/io/envoyproxy/envoy/type/matcher/ValueMatcher$NullMatch;
     169: putfield      #141                // Field matchPattern_:Ljava/lang/Object;
     172: aload_0
     173: iconst_1
     174: putfield      #99                 // Field matchPatternCase_:I
     177: goto          445
     180: aconst_null
     181: astore        6
     183: aload_0
     184: getfield      #99                 // Field matchPatternCase_:I
     187: iconst_2
     188: if_icmpne     203
     191: aload_0
     192: getfield      #141                // Field matchPattern_:Ljava/lang/Object;
     195: checkcast     #34                 // class io/grpc/xds/shaded/io/envoyproxy/envoy/type/matcher/DoubleMatcher
     198: invokevirtual #164                // Method io/grpc/xds/shaded/io/envoyproxy/envoy/type/matcher/DoubleMatcher.toBuilder:()Lio/grpc/xds/shaded/io/envoyproxy/envoy/type/matcher/DoubleMatcher$Builder;
     201: astore        6
     203: aload_0
     204: aload_1
     205: invokestatic  #165                // Method io/grpc/xds/shaded/io/envoyproxy/envoy/type/matcher/DoubleMatcher.parser:()Lcom/google/protobuf/Parser;
     208: aload_2
     209: invokevirtual #153                // Method com/google/protobuf/CodedInputStream.readMessage:(Lcom/google/protobuf/Parser;Lcom/google/protobuf/ExtensionRegistryLite;)Lcom/google/protobuf/MessageLite;
     212: putfield      #141                // Field matchPattern_:Ljava/lang/Object;
     215: aload         6
     217: ifnull        242
     220: aload         6
     222: aload_0
     223: getfield      #141                // Field matchPattern_:Ljava/lang/Object;
     226: checkcast     #34                 // class io/grpc/xds/shaded/io/envoyproxy/envoy/type/matcher/DoubleMatcher
     229: invokevirtual #168                // Method io/grpc/xds/shaded/io/envoyproxy/envoy/type/matcher/DoubleMatcher$Builder.mergeFrom:(Lio/grpc/xds/shaded/io/envoyproxy/envoy/type/matcher/DoubleMatcher;)Lio/grpc/xds/shaded/io/envoyproxy/envoy/type/matcher/DoubleMatcher$Builder;
     232: pop
     233: aload_0
     234: aload         6
     236: invokevirtual #171                // Method io/grpc/xds/shaded/io/envoyproxy/envoy/type/matcher/DoubleMatcher$Builder.buildPartial:()Lio/grpc/xds/shaded/io/envoyproxy/envoy/type/matcher/DoubleMatcher;
     239: putfield      #141                // Field matchPattern_:Ljava/lang/Object;
     242: aload_0
     243: iconst_2
     244: putfield      #99                 // Field matchPatternCase_:I
     247: goto          445
     250: aconst_null
     251: astore        6
     253: aload_0
     254: getfield      #99                 // Field matchPatternCase_:I
     257: iconst_3
     258: if_icmpne     273
     261: aload_0
     262: getfield      #141                // Field matchPattern_:Ljava/lang/Object;
     265: checkcast     #38                 // class io/grpc/xds/shaded/io/envoyproxy/envoy/type/matcher/StringMatcher
     268: invokevirtual #174                // Method io/grpc/xds/shaded/io/envoyproxy/envoy/type/matcher/StringMatcher.toBuilder:()Lio/grpc/xds/shaded/io/envoyproxy/envoy/type/matcher/StringMatcher$Builder;
     271: astore        6
     273: aload_0
     274: aload_1
     275: invokestatic  #175                // Method io/grpc/xds/shaded/io/envoyproxy/envoy/type/matcher/StringMatcher.parser:()Lcom/google/protobuf/Parser;
     278: aload_2
     279: invokevirtual #153                // Method com/google/protobuf/CodedInputStream.readMessage:(Lcom/google/protobuf/Parser;Lcom/google/protobuf/ExtensionRegistryLite;)Lcom/google/protobuf/MessageLite;
     282: putfield      #141                // Field matchPattern_:Ljava/lang/Object;
     285: aload         6
     287: ifnull        312
     290: aload         6
     292: aload_0
     293: getfield      #141                // Field matchPattern_:Ljava/lang/Object;
     296: checkcast     #38                 // class io/grpc/xds/shaded/io/envoyproxy/envoy/type/matcher/StringMatcher
     299: invokevirtual #178                // Method io/grpc/xds/shaded/io/envoyproxy/envoy/type/matcher/StringMatcher$Builder.mergeFrom:(Lio/grpc/xds/shaded/io/envoyproxy/envoy/type/matcher/StringMatcher;)Lio/grpc/xds/shaded/io/envoyproxy/envoy/type/matcher/StringMatcher$Builder;
     302: pop
     303: aload_0
     304: aload         6
     306: invokevirtual #181                // Method io/grpc/xds/shaded/io/envoyproxy/envoy/type/matcher/StringMatcher$Builder.buildPartial:()Lio/grpc/xds/shaded/io/envoyproxy/envoy/type/matcher/StringMatcher;
     309: putfield      #141                // Field matchPattern_:Ljava/lang/Object;
     312: aload_0
     313: iconst_3
     314: putfield      #99                 // Field matchPatternCase_:I
     317: goto          445
     320: aload_0
     321: iconst_4
     322: putfield      #99                 // Field matchPatternCase_:I
     325: aload_0
     326: aload_1
     327: invokevirtual #185                // Method com/google/protobuf/CodedInputStream.readBool:()Z
     330: invokestatic  #191                // Method java/lang/Boolean.valueOf:(Z)Ljava/lang/Boolean;
     333: putfield      #141                // Field matchPattern_:Ljava/lang/Object;
     336: goto          445
     339: aload_0
     340: iconst_5
     341: putfield      #99                 // Field matchPatternCase_:I
     344: aload_0
     345: aload_1
     346: invokevirtual #185                // Method com/google/protobuf/CodedInputStream.readBool:()Z
     349: invokestatic  #191                // Method java/lang/Boolean.valueOf:(Z)Ljava/lang/Boolean;
     352: putfield      #141                // Field matchPattern_:Ljava/lang/Object;
     355: goto          445
     358: aconst_null
     359: astore        6
     361: aload_0
     362: getfield      #99                 // Field matchPatternCase_:I
     365: bipush        6
     367: if_icmpne     382
     370: aload_0
     371: getfield      #141                // Field matchPattern_:Ljava/lang/Object;
     374: checkcast     #42                 // class io/grpc/xds/shaded/io/envoyproxy/envoy/type/matcher/ListMatcher
     377: invokevirtual #194                // Method io/grpc/xds/shaded/io/envoyproxy/envoy/type/matcher/ListMatcher.toBuilder:()Lio/grpc/xds/shaded/io/envoyproxy/envoy/type/matcher/ListMatcher$Builder;
     380: astore        6
     382: aload_0
     383: aload_1
     384: invokestatic  #195                // Method io/grpc/xds/shaded/io/envoyproxy/envoy/type/matcher/ListMatcher.parser:()Lcom/google/protobuf/Parser;
     387: aload_2
     388: invokevirtual #153                // Method com/google/protobuf/CodedInputStream.readMessage:(Lcom/google/protobuf/Parser;Lcom/google/protobuf/ExtensionRegistryLite;)Lcom/google/protobuf/MessageLite;
     391: putfield      #141                // Field matchPattern_:Ljava/lang/Object;
     394: aload         6
     396: ifnull        421
     399: aload         6
     401: aload_0
     402: getfield      #141                // Field matchPattern_:Ljava/lang/Object;
     405: checkcast     #42                 // class io/grpc/xds/shaded/io/envoyproxy/envoy/type/matcher/ListMatcher
     408: invokevirtual #198                // Method io/grpc/xds/shaded/io/envoyproxy/envoy/type/matcher/ListMatcher$Builder.mergeFrom:(Lio/grpc/xds/shaded/io/envoyproxy/envoy/type/matcher/ListMatcher;)Lio/grpc/xds/shaded/io/envoyproxy/envoy/type/matcher/ListMatcher$Builder;
     411: pop
     412: aload_0
     413: aload         6
     415: invokevirtual #201                // Method io/grpc/xds/shaded/io/envoyproxy/envoy/type/matcher/ListMatcher$Builder.buildPartial:()Lio/grpc/xds/shaded/io/envoyproxy/envoy/type/matcher/ListMatcher;
     418: putfield      #141                // Field matchPattern_:Ljava/lang/Object;
     421: aload_0
     422: bipush        6
     424: putfield      #99                 // Field matchPatternCase_:I
     427: goto          445
     430: aload_0
     431: aload_1
     432: aload_3
     433: aload_2
     434: iload         5
     436: invokevirtual #205                // Method parseUnknownField:(Lcom/google/protobuf/CodedInputStream;Lcom/google/protobuf/UnknownFieldSet$Builder;Lcom/google/protobuf/ExtensionRegistryLite;I)Z
     439: ifne          445
     442: iconst_1
     443: istore        4
     445: goto          23
     448: aload_0
     449: aload_3
     450: invokevirtual #208                // Method com/google/protobuf/UnknownFieldSet$Builder.build:()Lcom/google/protobuf/UnknownFieldSet;
     453: putfield      #119                // Field unknownFields:Lcom/google/protobuf/UnknownFieldSet;
     456: aload_0
     457: invokevirtual #211                // Method makeExtensionsImmutable:()V
     460: goto          505
     463: astore        4
     465: aload         4
     467: aload_0
     468: invokevirtual #215                // Method com/google/protobuf/InvalidProtocolBufferException.setUnfinishedMessage:(Lcom/google/protobuf/MessageLite;)Lcom/google/protobuf/InvalidProtocolBufferException;
     471: athrow
     472: astore        4
     474: new           #122                // class com/google/protobuf/InvalidProtocolBufferException
     477: dup
     478: aload         4
     480: invokespecial #218                // Method com/google/protobuf/InvalidProtocolBufferException."<init>":(Ljava/io/IOException;)V
     483: aload_0
     484: invokevirtual #215                // Method com/google/protobuf/InvalidProtocolBufferException.setUnfinishedMessage:(Lcom/google/protobuf/MessageLite;)Lcom/google/protobuf/InvalidProtocolBufferException;
     487: athrow
     488: astore        7
     490: aload_0
     491: aload_3
     492: invokevirtual #208                // Method com/google/protobuf/UnknownFieldSet$Builder.build:()Lcom/google/protobuf/UnknownFieldSet;
     495: putfield      #119                // Field unknownFields:Lcom/google/protobuf/UnknownFieldSet;
     498: aload_0
     499: invokevirtual #211                // Method makeExtensionsImmutable:()V
     502: aload         7
     504: athrow
     505: return
    Exception table:
       from    to  target type
          20   448   463   Class com/google/protobuf/InvalidProtocolBufferException
          20   448   472   Class java/io/IOException
          20   448   488   any
         463   490   488   any

  public static final com.google.protobuf.Descriptors$Descriptor getDescriptor();
    Code:
       0: getstatic     #244                // Field io/grpc/xds/shaded/io/envoyproxy/envoy/type/matcher/ValueProto.internal_static_envoy_type_matcher_ValueMatcher_descriptor:Lcom/google/protobuf/Descriptors$Descriptor;
       3: areturn

  protected com.google.protobuf.GeneratedMessageV3$FieldAccessorTable internalGetFieldAccessorTable();
    Code:
       0: getstatic     #250                // Field io/grpc/xds/shaded/io/envoyproxy/envoy/type/matcher/ValueProto.internal_static_envoy_type_matcher_ValueMatcher_fieldAccessorTable:Lcom/google/protobuf/GeneratedMessageV3$FieldAccessorTable;
       3: ldc           #2                  // class io/grpc/xds/shaded/io/envoyproxy/envoy/type/matcher/ValueMatcher
       5: ldc           #11                 // class io/grpc/xds/shaded/io/envoyproxy/envoy/type/matcher/ValueMatcher$Builder
       7: invokevirtual #254                // Method com/google/protobuf/GeneratedMessageV3$FieldAccessorTable.ensureFieldAccessorsInitialized:(Ljava/lang/Class;Ljava/lang/Class;)Lcom/google/protobuf/GeneratedMessageV3$FieldAccessorTable;
      10: areturn

  public io.grpc.xds.shaded.io.envoyproxy.envoy.type.matcher.ValueMatcher$MatchPatternCase getMatchPatternCase();
    Code:
       0: aload_0
       1: getfield      #99                 // Field matchPatternCase_:I
       4: invokestatic  #260                // Method io/grpc/xds/shaded/io/envoyproxy/envoy/type/matcher/ValueMatcher$MatchPatternCase.forNumber:(I)Lio/grpc/xds/shaded/io/envoyproxy/envoy/type/matcher/ValueMatcher$MatchPatternCase;
       7: areturn

  public boolean hasNullMatch();
    Code:
       0: aload_0
       1: getfield      #99                 // Field matchPatternCase_:I
       4: iconst_1
       5: if_icmpne     12
       8: iconst_1
       9: goto          13
      12: iconst_0
      13: ireturn

  public io.grpc.xds.shaded.io.envoyproxy.envoy.type.matcher.ValueMatcher$NullMatch getNullMatch();
    Code:
       0: aload_0
       1: getfield      #99                 // Field matchPatternCase_:I
       4: iconst_1
       5: if_icmpne     16
       8: aload_0
       9: getfield      #141                // Field matchPattern_:Ljava/lang/Object;
      12: checkcast     #17                 // class io/grpc/xds/shaded/io/envoyproxy/envoy/type/matcher/ValueMatcher$NullMatch
      15: areturn
      16: invokestatic  #265                // Method io/grpc/xds/shaded/io/envoyproxy/envoy/type/matcher/ValueMatcher$NullMatch.getDefaultInstance:()Lio/grpc/xds/shaded/io/envoyproxy/envoy/type/matcher/ValueMatcher$NullMatch;
      19: areturn

  public io.grpc.xds.shaded.io.envoyproxy.envoy.type.matcher.ValueMatcher$NullMatchOrBuilder getNullMatchOrBuilder();
    Code:
       0: aload_0
       1: getfield      #99                 // Field matchPatternCase_:I
       4: iconst_1
       5: if_icmpne     16
       8: aload_0
       9: getfield      #141                // Field matchPattern_:Ljava/lang/Object;
      12: checkcast     #17                 // class io/grpc/xds/shaded/io/envoyproxy/envoy/type/matcher/ValueMatcher$NullMatch
      15: areturn
      16: invokestatic  #265                // Method io/grpc/xds/shaded/io/envoyproxy/envoy/type/matcher/ValueMatcher$NullMatch.getDefaultInstance:()Lio/grpc/xds/shaded/io/envoyproxy/envoy/type/matcher/ValueMatcher$NullMatch;
      19: areturn

  public boolean hasDoubleMatch();
    Code:
       0: aload_0
       1: getfield      #99                 // Field matchPatternCase_:I
       4: iconst_2
       5: if_icmpne     12
       8: iconst_1
       9: goto          13
      12: iconst_0
      13: ireturn

  public io.grpc.xds.shaded.io.envoyproxy.envoy.type.matcher.DoubleMatcher getDoubleMatch();
    Code:
       0: aload_0
       1: getfield      #99                 // Field matchPatternCase_:I
       4: iconst_2
       5: if_icmpne     16
       8: aload_0
       9: getfield      #141                // Field matchPattern_:Ljava/lang/Object;
      12: checkcast     #34                 // class io/grpc/xds/shaded/io/envoyproxy/envoy/type/matcher/DoubleMatcher
      15: areturn
      16: invokestatic  #271                // Method io/grpc/xds/shaded/io/envoyproxy/envoy/type/matcher/DoubleMatcher.getDefaultInstance:()Lio/grpc/xds/shaded/io/envoyproxy/envoy/type/matcher/DoubleMatcher;
      19: areturn

  public io.grpc.xds.shaded.io.envoyproxy.envoy.type.matcher.DoubleMatcherOrBuilder getDoubleMatchOrBuilder();
    Code:
       0: aload_0
       1: getfield      #99                 // Field matchPatternCase_:I
       4: iconst_2
       5: if_icmpne     16
       8: aload_0
       9: getfield      #141                // Field matchPattern_:Ljava/lang/Object;
      12: checkcast     #34                 // class io/grpc/xds/shaded/io/envoyproxy/envoy/type/matcher/DoubleMatcher
      15: areturn
      16: invokestatic  #271                // Method io/grpc/xds/shaded/io/envoyproxy/envoy/type/matcher/DoubleMatcher.getDefaultInstance:()Lio/grpc/xds/shaded/io/envoyproxy/envoy/type/matcher/DoubleMatcher;
      19: areturn

  public boolean hasStringMatch();
    Code:
       0: aload_0
       1: getfield      #99                 // Field matchPatternCase_:I
       4: iconst_3
       5: if_icmpne     12
       8: iconst_1
       9: goto          13
      12: iconst_0
      13: ireturn

  public io.grpc.xds.shaded.io.envoyproxy.envoy.type.matcher.StringMatcher getStringMatch();
    Code:
       0: aload_0
       1: getfield      #99                 // Field matchPatternCase_:I
       4: iconst_3
       5: if_icmpne     16
       8: aload_0
       9: getfield      #141                // Field matchPattern_:Ljava/lang/Object;
      12: checkcast     #38                 // class io/grpc/xds/shaded/io/envoyproxy/envoy/type/matcher/StringMatcher
      15: areturn
      16: invokestatic  #277                // Method io/grpc/xds/shaded/io/envoyproxy/envoy/type/matcher/StringMatcher.getDefaultInstance:()Lio/grpc/xds/shaded/io/envoyproxy/envoy/type/matcher/StringMatcher;
      19: areturn

  public io.grpc.xds.shaded.io.envoyproxy.envoy.type.matcher.StringMatcherOrBuilder getStringMatchOrBuilder();
    Code:
       0: aload_0
       1: getfield      #99                 // Field matchPatternCase_:I
       4: iconst_3
       5: if_icmpne     16
       8: aload_0
       9: getfield      #141                // Field matchPattern_:Ljava/lang/Object;
      12: checkcast     #38                 // class io/grpc/xds/shaded/io/envoyproxy/envoy/type/matcher/StringMatcher
      15: areturn
      16: invokestatic  #277                // Method io/grpc/xds/shaded/io/envoyproxy/envoy/type/matcher/StringMatcher.getDefaultInstance:()Lio/grpc/xds/shaded/io/envoyproxy/envoy/type/matcher/StringMatcher;
      19: areturn

  public boolean hasBoolMatch();
    Code:
       0: aload_0
       1: getfield      #99                 // Field matchPatternCase_:I
       4: iconst_4
       5: if_icmpne     12
       8: iconst_1
       9: goto          13
      12: iconst_0
      13: ireturn

  public boolean getBoolMatch();
    Code:
       0: aload_0
       1: getfield      #99                 // Field matchPatternCase_:I
       4: iconst_4
       5: if_icmpne     19
       8: aload_0
       9: getfield      #141                // Field matchPattern_:Ljava/lang/Object;
      12: checkcast     #187                // class java/lang/Boolean
      15: invokevirtual #284                // Method java/lang/Boolean.booleanValue:()Z
      18: ireturn
      19: iconst_0
      20: ireturn

  public boolean hasPresentMatch();
    Code:
       0: aload_0
       1: getfield      #99                 // Field matchPatternCase_:I
       4: iconst_5
       5: if_icmpne     12
       8: iconst_1
       9: goto          13
      12: iconst_0
      13: ireturn

  public boolean getPresentMatch();
    Code:
       0: aload_0
       1: getfield      #99                 // Field matchPatternCase_:I
       4: iconst_5
       5: if_icmpne     19
       8: aload_0
       9: getfield      #141                // Field matchPattern_:Ljava/lang/Object;
      12: checkcast     #187                // class java/lang/Boolean
      15: invokevirtual #284                // Method java/lang/Boolean.booleanValue:()Z
      18: ireturn
      19: iconst_0
      20: ireturn

  public boolean hasListMatch();
    Code:
       0: aload_0
       1: getfield      #99                 // Field matchPatternCase_:I
       4: bipush        6
       6: if_icmpne     13
       9: iconst_1
      10: goto          14
      13: iconst_0
      14: ireturn

  public io.grpc.xds.shaded.io.envoyproxy.envoy.type.matcher.ListMatcher getListMatch();
    Code:
       0: aload_0
       1: getfield      #99                 // Field matchPatternCase_:I
       4: bipush        6
       6: if_icmpne     17
       9: aload_0
      10: getfield      #141                // Field matchPattern_:Ljava/lang/Object;
      13: checkcast     #42                 // class io/grpc/xds/shaded/io/envoyproxy/envoy/type/matcher/ListMatcher
      16: areturn
      17: invokestatic  #290                // Method io/grpc/xds/shaded/io/envoyproxy/envoy/type/matcher/ListMatcher.getDefaultInstance:()Lio/grpc/xds/shaded/io/envoyproxy/envoy/type/matcher/ListMatcher;
      20: areturn

  public io.grpc.xds.shaded.io.envoyproxy.envoy.type.matcher.ListMatcherOrBuilder getListMatchOrBuilder();
    Code:
       0: aload_0
       1: getfield      #99                 // Field matchPatternCase_:I
       4: bipush        6
       6: if_icmpne     17
       9: aload_0
      10: getfield      #141                // Field matchPattern_:Ljava/lang/Object;
      13: checkcast     #42                 // class io/grpc/xds/shaded/io/envoyproxy/envoy/type/matcher/ListMatcher
      16: areturn
      17: invokestatic  #290                // Method io/grpc/xds/shaded/io/envoyproxy/envoy/type/matcher/ListMatcher.getDefaultInstance:()Lio/grpc/xds/shaded/io/envoyproxy/envoy/type/matcher/ListMatcher;
      20: areturn

  public final boolean isInitialized();
    Code:
       0: aload_0
       1: getfield      #101                // Field memoizedIsInitialized:B
       4: istore_1
       5: iload_1
       6: iconst_1
       7: if_icmpne     12
      10: iconst_1
      11: ireturn
      12: iload_1
      13: ifne          18
      16: iconst_0
      17: ireturn
      18: aload_0
      19: iconst_1
      20: putfield      #101                // Field memoizedIsInitialized:B
      23: iconst_1
      24: ireturn

  public void writeTo(com.google.protobuf.CodedOutputStream) throws java.io.IOException;
    Code:
       0: aload_0
       1: getfield      #99                 // Field matchPatternCase_:I
       4: iconst_1
       5: if_icmpne     20
       8: aload_1
       9: iconst_1
      10: aload_0
      11: getfield      #141                // Field matchPattern_:Ljava/lang/Object;
      14: checkcast     #17                 // class io/grpc/xds/shaded/io/envoyproxy/envoy/type/matcher/ValueMatcher$NullMatch
      17: invokevirtual #301                // Method com/google/protobuf/CodedOutputStream.writeMessage:(ILcom/google/protobuf/MessageLite;)V
      20: aload_0
      21: getfield      #99                 // Field matchPatternCase_:I
      24: iconst_2
      25: if_icmpne     40
      28: aload_1
      29: iconst_2
      30: aload_0
      31: getfield      #141                // Field matchPattern_:Ljava/lang/Object;
      34: checkcast     #34                 // class io/grpc/xds/shaded/io/envoyproxy/envoy/type/matcher/DoubleMatcher
      37: invokevirtual #301                // Method com/google/protobuf/CodedOutputStream.writeMessage:(ILcom/google/protobuf/MessageLite;)V
      40: aload_0
      41: getfield      #99                 // Field matchPatternCase_:I
      44: iconst_3
      45: if_icmpne     60
      48: aload_1
      49: iconst_3
      50: aload_0
      51: getfield      #141                // Field matchPattern_:Ljava/lang/Object;
      54: checkcast     #38                 // class io/grpc/xds/shaded/io/envoyproxy/envoy/type/matcher/StringMatcher
      57: invokevirtual #301                // Method com/google/protobuf/CodedOutputStream.writeMessage:(ILcom/google/protobuf/MessageLite;)V
      60: aload_0
      61: getfield      #99                 // Field matchPatternCase_:I
      64: iconst_4
      65: if_icmpne     83
      68: aload_1
      69: iconst_4
      70: aload_0
      71: getfield      #141                // Field matchPattern_:Ljava/lang/Object;
      74: checkcast     #187                // class java/lang/Boolean
      77: invokevirtual #284                // Method java/lang/Boolean.booleanValue:()Z
      80: invokevirtual #305                // Method com/google/protobuf/CodedOutputStream.writeBool:(IZ)V
      83: aload_0
      84: getfield      #99                 // Field matchPatternCase_:I
      87: iconst_5
      88: if_icmpne     106
      91: aload_1
      92: iconst_5
      93: aload_0
      94: getfield      #141                // Field matchPattern_:Ljava/lang/Object;
      97: checkcast     #187                // class java/lang/Boolean
     100: invokevirtual #284                // Method java/lang/Boolean.booleanValue:()Z
     103: invokevirtual #305                // Method com/google/protobuf/CodedOutputStream.writeBool:(IZ)V
     106: aload_0
     107: getfield      #99                 // Field matchPatternCase_:I
     110: bipush        6
     112: if_icmpne     128
     115: aload_1
     116: bipush        6
     118: aload_0
     119: getfield      #141                // Field matchPattern_:Ljava/lang/Object;
     122: checkcast     #42                 // class io/grpc/xds/shaded/io/envoyproxy/envoy/type/matcher/ListMatcher
     125: invokevirtual #301                // Method com/google/protobuf/CodedOutputStream.writeMessage:(ILcom/google/protobuf/MessageLite;)V
     128: aload_0
     129: getfield      #119                // Field unknownFields:Lcom/google/protobuf/UnknownFieldSet;
     132: aload_1
     133: invokevirtual #307                // Method com/google/protobuf/UnknownFieldSet.writeTo:(Lcom/google/protobuf/CodedOutputStream;)V
     136: return

  public int getSerializedSize();
    Code:
       0: aload_0
       1: getfield      #313                // Field memoizedSize:I
       4: istore_1
       5: iload_1
       6: iconst_m1
       7: if_icmpeq     12
      10: iload_1
      11: ireturn
      12: iconst_0
      13: istore_1
      14: aload_0
      15: getfield      #99                 // Field matchPatternCase_:I
      18: iconst_1
      19: if_icmpne     36
      22: iload_1
      23: iconst_1
      24: aload_0
      25: getfield      #141                // Field matchPattern_:Ljava/lang/Object;
      28: checkcast     #17                 // class io/grpc/xds/shaded/io/envoyproxy/envoy/type/matcher/ValueMatcher$NullMatch
      31: invokestatic  #317                // Method com/google/protobuf/CodedOutputStream.computeMessageSize:(ILcom/google/protobuf/MessageLite;)I
      34: iadd
      35: istore_1
      36: aload_0
      37: getfield      #99                 // Field matchPatternCase_:I
      40: iconst_2
      41: if_icmpne     58
      44: iload_1
      45: iconst_2
      46: aload_0
      47: getfield      #141                // Field matchPattern_:Ljava/lang/Object;
      50: checkcast     #34                 // class io/grpc/xds/shaded/io/envoyproxy/envoy/type/matcher/DoubleMatcher
      53: invokestatic  #317                // Method com/google/protobuf/CodedOutputStream.computeMessageSize:(ILcom/google/protobuf/MessageLite;)I
      56: iadd
      57: istore_1
      58: aload_0
      59: getfield      #99                 // Field matchPatternCase_:I
      62: iconst_3
      63: if_icmpne     80
      66: iload_1
      67: iconst_3
      68: aload_0
      69: getfield      #141                // Field matchPattern_:Ljava/lang/Object;
      72: checkcast     #38                 // class io/grpc/xds/shaded/io/envoyproxy/envoy/type/matcher/StringMatcher
      75: invokestatic  #317                // Method com/google/protobuf/CodedOutputStream.computeMessageSize:(ILcom/google/protobuf/MessageLite;)I
      78: iadd
      79: istore_1
      80: aload_0
      81: getfield      #99                 // Field matchPatternCase_:I
      84: iconst_4
      85: if_icmpne     105
      88: iload_1
      89: iconst_4
      90: aload_0
      91: getfield      #141                // Field matchPattern_:Ljava/lang/Object;
      94: checkcast     #187                // class java/lang/Boolean
      97: invokevirtual #284                // Method java/lang/Boolean.booleanValue:()Z
     100: invokestatic  #321                // Method com/google/protobuf/CodedOutputStream.computeBoolSize:(IZ)I
     103: iadd
     104: istore_1
     105: aload_0
     106: getfield      #99                 // Field matchPatternCase_:I
     109: iconst_5
     110: if_icmpne     130
     113: iload_1
     114: iconst_5
     115: aload_0
     116: getfield      #141                // Field matchPattern_:Ljava/lang/Object;
     119: checkcast     #187                // class java/lang/Boolean
     122: invokevirtual #284                // Method java/lang/Boolean.booleanValue:()Z
     125: invokestatic  #321                // Method com/google/protobuf/CodedOutputStream.computeBoolSize:(IZ)I
     128: iadd
     129: istore_1
     130: aload_0
     131: getfield      #99                 // Field matchPatternCase_:I
     134: bipush        6
     136: if_icmpne     154
     139: iload_1
     140: bipush        6
     142: aload_0
     143: getfield      #141                // Field matchPattern_:Ljava/lang/Object;
     146: checkcast     #42                 // class io/grpc/xds/shaded/io/envoyproxy/envoy/type/matcher/ListMatcher
     149: invokestatic  #317                // Method com/google/protobuf/CodedOutputStream.computeMessageSize:(ILcom/google/protobuf/MessageLite;)I
     152: iadd
     153: istore_1
     154: iload_1
     155: aload_0
     156: getfield      #119                // Field unknownFields:Lcom/google/protobuf/UnknownFieldSet;
     159: invokevirtual #323                // Method com/google/protobuf/UnknownFieldSet.getSerializedSize:()I
     162: iadd
     163: istore_1
     164: aload_0
     165: iload_1
     166: putfield      #313                // Field memoizedSize:I
     169: iload_1
     170: ireturn

  public boolean equals(java.lang.Object);
    Code:
       0: aload_1
       1: aload_0
       2: if_acmpne     7
       5: iconst_1
       6: ireturn
       7: aload_1
       8: instanceof    #2                  // class io/grpc/xds/shaded/io/envoyproxy/envoy/type/matcher/ValueMatcher
      11: ifne          20
      14: aload_0
      15: aload_1
      16: invokespecial #328                // Method com/google/protobuf/GeneratedMessageV3.equals:(Ljava/lang/Object;)Z
      19: ireturn
      20: aload_1
      21: checkcast     #2                  // class io/grpc/xds/shaded/io/envoyproxy/envoy/type/matcher/ValueMatcher
      24: astore_2
      25: aload_0
      26: invokevirtual #330                // Method getMatchPatternCase:()Lio/grpc/xds/shaded/io/envoyproxy/envoy/type/matcher/ValueMatcher$MatchPatternCase;
      29: aload_2
      30: invokevirtual #330                // Method getMatchPatternCase:()Lio/grpc/xds/shaded/io/envoyproxy/envoy/type/matcher/ValueMatcher$MatchPatternCase;
      33: invokevirtual #331                // Method io/grpc/xds/shaded/io/envoyproxy/envoy/type/matcher/ValueMatcher$MatchPatternCase.equals:(Ljava/lang/Object;)Z
      36: ifne          41
      39: iconst_0
      40: ireturn
      41: aload_0
      42: getfield      #99                 // Field matchPatternCase_:I
      45: tableswitch   { // 0 to 6
                     0: 178
                     1: 88
                     2: 104
                     3: 120
                     4: 136
                     5: 149
                     6: 162
               default: 178
          }
      88: aload_0
      89: invokevirtual #333                // Method getNullMatch:()Lio/grpc/xds/shaded/io/envoyproxy/envoy/type/matcher/ValueMatcher$NullMatch;
      92: aload_2
      93: invokevirtual #333                // Method getNullMatch:()Lio/grpc/xds/shaded/io/envoyproxy/envoy/type/matcher/ValueMatcher$NullMatch;
      96: invokevirtual #334                // Method io/grpc/xds/shaded/io/envoyproxy/envoy/type/matcher/ValueMatcher$NullMatch.equals:(Ljava/lang/Object;)Z
      99: ifne          178
     102: iconst_0
     103: ireturn
     104: aload_0
     105: invokevirtual #336                // Method getDoubleMatch:()Lio/grpc/xds/shaded/io/envoyproxy/envoy/type/matcher/DoubleMatcher;
     108: aload_2
     109: invokevirtual #336                // Method getDoubleMatch:()Lio/grpc/xds/shaded/io/envoyproxy/envoy/type/matcher/DoubleMatcher;
     112: invokevirtual #337                // Method io/grpc/xds/shaded/io/envoyproxy/envoy/type/matcher/DoubleMatcher.equals:(Ljava/lang/Object;)Z
     115: ifne          178
     118: iconst_0
     119: ireturn
     120: aload_0
     121: invokevirtual #339                // Method getStringMatch:()Lio/grpc/xds/shaded/io/envoyproxy/envoy/type/matcher/StringMatcher;
     124: aload_2
     125: invokevirtual #339                // Method getStringMatch:()Lio/grpc/xds/shaded/io/envoyproxy/envoy/type/matcher/StringMatcher;
     128: invokevirtual #340                // Method io/grpc/xds/shaded/io/envoyproxy/envoy/type/matcher/StringMatcher.equals:(Ljava/lang/Object;)Z
     131: ifne          178
     134: iconst_0
     135: ireturn
     136: aload_0
     137: invokevirtual #342                // Method getBoolMatch:()Z
     140: aload_2
     141: invokevirtual #342                // Method getBoolMatch:()Z
     144: if_icmpeq     178
     147: iconst_0
     148: ireturn
     149: aload_0
     150: invokevirtual #344                // Method getPresentMatch:()Z
     153: aload_2
     154: invokevirtual #344                // Method getPresentMatch:()Z
     157: if_icmpeq     178
     160: iconst_0
     161: ireturn
     162: aload_0
     163: invokevirtual #346                // Method getListMatch:()Lio/grpc/xds/shaded/io/envoyproxy/envoy/type/matcher/ListMatcher;
     166: aload_2
     167: invokevirtual #346                // Method getListMatch:()Lio/grpc/xds/shaded/io/envoyproxy/envoy/type/matcher/ListMatcher;
     170: invokevirtual #347                // Method io/grpc/xds/shaded/io/envoyproxy/envoy/type/matcher/ListMatcher.equals:(Ljava/lang/Object;)Z
     173: ifne          178
     176: iconst_0
     177: ireturn
     178: aload_0
     179: getfield      #119                // Field unknownFields:Lcom/google/protobuf/UnknownFieldSet;
     182: aload_2
     183: getfield      #119                // Field unknownFields:Lcom/google/protobuf/UnknownFieldSet;
     186: invokevirtual #348                // Method com/google/protobuf/UnknownFieldSet.equals:(Ljava/lang/Object;)Z
     189: ifne          194
     192: iconst_0
     193: ireturn
     194: iconst_1
     195: ireturn

  public int hashCode();
    Code:
       0: aload_0
       1: getfield      #354                // Field memoizedHashCode:I
       4: ifeq          12
       7: aload_0
       8: getfield      #354                // Field memoizedHashCode:I
      11: ireturn
      12: bipush        41
      14: istore_1
      15: bipush        19
      17: iload_1
      18: imul
      19: invokestatic  #356                // Method getDescriptor:()Lcom/google/protobuf/Descriptors$Descriptor;
      22: invokevirtual #360                // Method java/lang/Object.hashCode:()I
      25: iadd
      26: istore_1
      27: aload_0
      28: getfield      #99                 // Field matchPatternCase_:I
      31: tableswitch   { // 0 to 6
                     0: 211
                     1: 72
                     2: 95
                     3: 118
                     4: 141
                     5: 164
                     6: 187
               default: 211
          }
      72: bipush        37
      74: iload_1
      75: imul
      76: iconst_1
      77: iadd
      78: istore_1
      79: bipush        53
      81: iload_1
      82: imul
      83: aload_0
      84: invokevirtual #333                // Method getNullMatch:()Lio/grpc/xds/shaded/io/envoyproxy/envoy/type/matcher/ValueMatcher$NullMatch;
      87: invokevirtual #361                // Method io/grpc/xds/shaded/io/envoyproxy/envoy/type/matcher/ValueMatcher$NullMatch.hashCode:()I
      90: iadd
      91: istore_1
      92: goto          211
      95: bipush        37
      97: iload_1
      98: imul
      99: iconst_2
     100: iadd
     101: istore_1
     102: bipush        53
     104: iload_1
     105: imul
     106: aload_0
     107: invokevirtual #336                // Method getDoubleMatch:()Lio/grpc/xds/shaded/io/envoyproxy/envoy/type/matcher/DoubleMatcher;
     110: invokevirtual #362                // Method io/grpc/xds/shaded/io/envoyproxy/envoy/type/matcher/DoubleMatcher.hashCode:()I
     113: iadd
     114: istore_1
     115: goto          211
     118: bipush        37
     120: iload_1
     121: imul
     122: iconst_3
     123: iadd
     124: istore_1
     125: bipush        53
     127: iload_1
     128: imul
     129: aload_0
     130: invokevirtual #339                // Method getStringMatch:()Lio/grpc/xds/shaded/io/envoyproxy/envoy/type/matcher/StringMatcher;
     133: invokevirtual #363                // Method io/grpc/xds/shaded/io/envoyproxy/envoy/type/matcher/StringMatcher.hashCode:()I
     136: iadd
     137: istore_1
     138: goto          211
     141: bipush        37
     143: iload_1
     144: imul
     145: iconst_4
     146: iadd
     147: istore_1
     148: bipush        53
     150: iload_1
     151: imul
     152: aload_0
     153: invokevirtual #342                // Method getBoolMatch:()Z
     156: invokestatic  #369                // Method com/google/protobuf/Internal.hashBoolean:(Z)I
     159: iadd
     160: istore_1
     161: goto          211
     164: bipush        37
     166: iload_1
     167: imul
     168: iconst_5
     169: iadd
     170: istore_1
     171: bipush        53
     173: iload_1
     174: imul
     175: aload_0
     176: invokevirtual #344                // Method getPresentMatch:()Z
     179: invokestatic  #369                // Method com/google/protobuf/Internal.hashBoolean:(Z)I
     182: iadd
     183: istore_1
     184: goto          211
     187: bipush        37
     189: iload_1
     190: imul
     191: bipush        6
     193: iadd
     194: istore_1
     195: bipush        53
     197: iload_1
     198: imul
     199: aload_0
     200: invokevirtual #346                // Method getListMatch:()Lio/grpc/xds/shaded/io/envoyproxy/envoy/type/matcher/ListMatcher;
     203: invokevirtual #370                // Method io/grpc/xds/shaded/io/envoyproxy/envoy/type/matcher/ListMatcher.hashCode:()I
     206: iadd
     207: istore_1
     208: goto          211
     211: bipush        29
     213: iload_1
     214: imul
     215: aload_0
     216: getfield      #119                // Field unknownFields:Lcom/google/protobuf/UnknownFieldSet;
     219: invokevirtual #371                // Method com/google/protobuf/UnknownFieldSet.hashCode:()I
     222: iadd
     223: istore_1
     224: aload_0
     225: iload_1
     226: putfield      #354                // Field memoizedHashCode:I
     229: iload_1
     230: ireturn

  public static io.grpc.xds.shaded.io.envoyproxy.envoy.type.matcher.ValueMatcher parseFrom(java.nio.ByteBuffer) throws com.google.protobuf.InvalidProtocolBufferException;
    Code:
       0: getstatic     #376                // Field PARSER:Lcom/google/protobuf/Parser;
       3: aload_0
       4: invokeinterface #381,  2          // InterfaceMethod com/google/protobuf/Parser.parseFrom:(Ljava/nio/ByteBuffer;)Ljava/lang/Object;
       9: checkcast     #2                  // class io/grpc/xds/shaded/io/envoyproxy/envoy/type/matcher/ValueMatcher
      12: areturn

  public static io.grpc.xds.shaded.io.envoyproxy.envoy.type.matcher.ValueMatcher parseFrom(java.nio.ByteBuffer, com.google.protobuf.ExtensionRegistryLite) throws com.google.protobuf.InvalidProtocolBufferException;
    Code:
       0: getstatic     #376                // Field PARSER:Lcom/google/protobuf/Parser;
       3: aload_0
       4: aload_1
       5: invokeinterface #387,  3          // InterfaceMethod com/google/protobuf/Parser.parseFrom:(Ljava/nio/ByteBuffer;Lcom/google/protobuf/ExtensionRegistryLite;)Ljava/lang/Object;
      10: checkcast     #2                  // class io/grpc/xds/shaded/io/envoyproxy/envoy/type/matcher/ValueMatcher
      13: areturn

  public static io.grpc.xds.shaded.io.envoyproxy.envoy.type.matcher.ValueMatcher parseFrom(com.google.protobuf.ByteString) throws com.google.protobuf.InvalidProtocolBufferException;
    Code:
       0: getstatic     #376                // Field PARSER:Lcom/google/protobuf/Parser;
       3: aload_0
       4: invokeinterface #391,  2          // InterfaceMethod com/google/protobuf/Parser.parseFrom:(Lcom/google/protobuf/ByteString;)Ljava/lang/Object;
       9: checkcast     #2                  // class io/grpc/xds/shaded/io/envoyproxy/envoy/type/matcher/ValueMatcher
      12: areturn

  public static io.grpc.xds.shaded.io.envoyproxy.envoy.type.matcher.ValueMatcher parseFrom(com.google.protobuf.ByteString, com.google.protobuf.ExtensionRegistryLite) throws com.google.protobuf.InvalidProtocolBufferException;
    Code:
       0: getstatic     #376                // Field PARSER:Lcom/google/protobuf/Parser;
       3: aload_0
       4: aload_1
       5: invokeinterface #396,  3          // InterfaceMethod com/google/protobuf/Parser.parseFrom:(Lcom/google/protobuf/ByteString;Lcom/google/protobuf/ExtensionRegistryLite;)Ljava/lang/Object;
      10: checkcast     #2                  // class io/grpc/xds/shaded/io/envoyproxy/envoy/type/matcher/ValueMatcher
      13: areturn

  public static io.grpc.xds.shaded.io.envoyproxy.envoy.type.matcher.ValueMatcher parseFrom(byte[]) throws com.google.protobuf.InvalidProtocolBufferException;
    Code:
       0: getstatic     #376                // Field PARSER:Lcom/google/protobuf/Parser;
       3: aload_0
       4: invokeinterface #400,  2          // InterfaceMethod com/google/protobuf/Parser.parseFrom:([B)Ljava/lang/Object;
       9: checkcast     #2                  // class io/grpc/xds/shaded/io/envoyproxy/envoy/type/matcher/ValueMatcher
      12: areturn

  public static io.grpc.xds.shaded.io.envoyproxy.envoy.type.matcher.ValueMatcher parseFrom(byte[], com.google.protobuf.ExtensionRegistryLite) throws com.google.protobuf.InvalidProtocolBufferException;
    Code:
       0: getstatic     #376                // Field PARSER:Lcom/google/protobuf/Parser;
       3: aload_0
       4: aload_1
       5: invokeinterface #405,  3          // InterfaceMethod com/google/protobuf/Parser.parseFrom:([BLcom/google/protobuf/ExtensionRegistryLite;)Ljava/lang/Object;
      10: checkcast     #2                  // class io/grpc/xds/shaded/io/envoyproxy/envoy/type/matcher/ValueMatcher
      13: areturn

  public static io.grpc.xds.shaded.io.envoyproxy.envoy.type.matcher.ValueMatcher parseFrom(java.io.InputStream) throws java.io.IOException;
    Code:
       0: getstatic     #376                // Field PARSER:Lcom/google/protobuf/Parser;
       3: aload_0
       4: invokestatic  #410                // Method com/google/protobuf/GeneratedMessageV3.parseWithIOException:(Lcom/google/protobuf/Parser;Ljava/io/InputStream;)Lcom/google/protobuf/Message;
       7: checkcast     #2                  // class io/grpc/xds/shaded/io/envoyproxy/envoy/type/matcher/ValueMatcher
      10: areturn

  public static io.grpc.xds.shaded.io.envoyproxy.envoy.type.matcher.ValueMatcher parseFrom(java.io.InputStream, com.google.protobuf.ExtensionRegistryLite) throws java.io.IOException;
    Code:
       0: getstatic     #376                // Field PARSER:Lcom/google/protobuf/Parser;
       3: aload_0
       4: aload_1
       5: invokestatic  #415                // Method com/google/protobuf/GeneratedMessageV3.parseWithIOException:(Lcom/google/protobuf/Parser;Ljava/io/InputStream;Lcom/google/protobuf/ExtensionRegistryLite;)Lcom/google/protobuf/Message;
       8: checkcast     #2                  // class io/grpc/xds/shaded/io/envoyproxy/envoy/type/matcher/ValueMatcher
      11: areturn

  public static io.grpc.xds.shaded.io.envoyproxy.envoy.type.matcher.ValueMatcher parseDelimitedFrom(java.io.InputStream) throws java.io.IOException;
    Code:
       0: getstatic     #376                // Field PARSER:Lcom/google/protobuf/Parser;
       3: aload_0
       4: invokestatic  #419                // Method com/google/protobuf/GeneratedMessageV3.parseDelimitedWithIOException:(Lcom/google/protobuf/Parser;Ljava/io/InputStream;)Lcom/google/protobuf/Message;
       7: checkcast     #2                  // class io/grpc/xds/shaded/io/envoyproxy/envoy/type/matcher/ValueMatcher
      10: areturn

  public static io.grpc.xds.shaded.io.envoyproxy.envoy.type.matcher.ValueMatcher parseDelimitedFrom(java.io.InputStream, com.google.protobuf.ExtensionRegistryLite) throws java.io.IOException;
    Code:
       0: getstatic     #376                // Field PARSER:Lcom/google/protobuf/Parser;
       3: aload_0
       4: aload_1
       5: invokestatic  #421                // Method com/google/protobuf/GeneratedMessageV3.parseDelimitedWithIOException:(Lcom/google/protobuf/Parser;Ljava/io/InputStream;Lcom/google/protobuf/ExtensionRegistryLite;)Lcom/google/protobuf/Message;
       8: checkcast     #2                  // class io/grpc/xds/shaded/io/envoyproxy/envoy/type/matcher/ValueMatcher
      11: areturn

  public static io.grpc.xds.shaded.io.envoyproxy.envoy.type.matcher.ValueMatcher parseFrom(com.google.protobuf.CodedInputStream) throws java.io.IOException;
    Code:
       0: getstatic     #376                // Field PARSER:Lcom/google/protobuf/Parser;
       3: aload_0
       4: invokestatic  #425                // Method com/google/protobuf/GeneratedMessageV3.parseWithIOException:(Lcom/google/protobuf/Parser;Lcom/google/protobuf/CodedInputStream;)Lcom/google/protobuf/Message;
       7: checkcast     #2                  // class io/grpc/xds/shaded/io/envoyproxy/envoy/type/matcher/ValueMatcher
      10: areturn

  public static io.grpc.xds.shaded.io.envoyproxy.envoy.type.matcher.ValueMatcher parseFrom(com.google.protobuf.CodedInputStream, com.google.protobuf.ExtensionRegistryLite) throws java.io.IOException;
    Code:
       0: getstatic     #376                // Field PARSER:Lcom/google/protobuf/Parser;
       3: aload_0
       4: aload_1
       5: invokestatic  #429                // Method com/google/protobuf/GeneratedMessageV3.parseWithIOException:(Lcom/google/protobuf/Parser;Lcom/google/protobuf/CodedInputStream;Lcom/google/protobuf/ExtensionRegistryLite;)Lcom/google/protobuf/Message;
       8: checkcast     #2                  // class io/grpc/xds/shaded/io/envoyproxy/envoy/type/matcher/ValueMatcher
      11: areturn

  public io.grpc.xds.shaded.io.envoyproxy.envoy.type.matcher.ValueMatcher$Builder newBuilderForType();
    Code:
       0: invokestatic  #433                // Method newBuilder:()Lio/grpc/xds/shaded/io/envoyproxy/envoy/type/matcher/ValueMatcher$Builder;
       3: areturn

  public static io.grpc.xds.shaded.io.envoyproxy.envoy.type.matcher.ValueMatcher$Builder newBuilder();
    Code:
       0: getstatic     #435                // Field DEFAULT_INSTANCE:Lio/grpc/xds/shaded/io/envoyproxy/envoy/type/matcher/ValueMatcher;
       3: invokevirtual #437                // Method toBuilder:()Lio/grpc/xds/shaded/io/envoyproxy/envoy/type/matcher/ValueMatcher$Builder;
       6: areturn

  public static io.grpc.xds.shaded.io.envoyproxy.envoy.type.matcher.ValueMatcher$Builder newBuilder(io.grpc.xds.shaded.io.envoyproxy.envoy.type.matcher.ValueMatcher);
    Code:
       0: getstatic     #435                // Field DEFAULT_INSTANCE:Lio/grpc/xds/shaded/io/envoyproxy/envoy/type/matcher/ValueMatcher;
       3: invokevirtual #437                // Method toBuilder:()Lio/grpc/xds/shaded/io/envoyproxy/envoy/type/matcher/ValueMatcher$Builder;
       6: aload_0
       7: invokevirtual #440                // Method io/grpc/xds/shaded/io/envoyproxy/envoy/type/matcher/ValueMatcher$Builder.mergeFrom:(Lio/grpc/xds/shaded/io/envoyproxy/envoy/type/matcher/ValueMatcher;)Lio/grpc/xds/shaded/io/envoyproxy/envoy/type/matcher/ValueMatcher$Builder;
      10: areturn

  public io.grpc.xds.shaded.io.envoyproxy.envoy.type.matcher.ValueMatcher$Builder toBuilder();
    Code:
       0: aload_0
       1: getstatic     #435                // Field DEFAULT_INSTANCE:Lio/grpc/xds/shaded/io/envoyproxy/envoy/type/matcher/ValueMatcher;
       4: if_acmpne     18
       7: new           #11                 // class io/grpc/xds/shaded/io/envoyproxy/envoy/type/matcher/ValueMatcher$Builder
      10: dup
      11: aconst_null
      12: invokespecial #444                // Method io/grpc/xds/shaded/io/envoyproxy/envoy/type/matcher/ValueMatcher$Builder."<init>":(Lio/grpc/xds/shaded/io/envoyproxy/envoy/type/matcher/ValueMatcher$1;)V
      15: goto          30
      18: new           #11                 // class io/grpc/xds/shaded/io/envoyproxy/envoy/type/matcher/ValueMatcher$Builder
      21: dup
      22: aconst_null
      23: invokespecial #444                // Method io/grpc/xds/shaded/io/envoyproxy/envoy/type/matcher/ValueMatcher$Builder."<init>":(Lio/grpc/xds/shaded/io/envoyproxy/envoy/type/matcher/ValueMatcher$1;)V
      26: aload_0
      27: invokevirtual #440                // Method io/grpc/xds/shaded/io/envoyproxy/envoy/type/matcher/ValueMatcher$Builder.mergeFrom:(Lio/grpc/xds/shaded/io/envoyproxy/envoy/type/matcher/ValueMatcher;)Lio/grpc/xds/shaded/io/envoyproxy/envoy/type/matcher/ValueMatcher$Builder;
      30: areturn

  protected io.grpc.xds.shaded.io.envoyproxy.envoy.type.matcher.ValueMatcher$Builder newBuilderForType(com.google.protobuf.GeneratedMessageV3$BuilderParent);
    Code:
       0: new           #11                 // class io/grpc/xds/shaded/io/envoyproxy/envoy/type/matcher/ValueMatcher$Builder
       3: dup
       4: aload_1
       5: aconst_null
       6: invokespecial #448                // Method io/grpc/xds/shaded/io/envoyproxy/envoy/type/matcher/ValueMatcher$Builder."<init>":(Lcom/google/protobuf/GeneratedMessageV3$BuilderParent;Lio/grpc/xds/shaded/io/envoyproxy/envoy/type/matcher/ValueMatcher$1;)V
       9: astore_2
      10: aload_2
      11: areturn

  public static io.grpc.xds.shaded.io.envoyproxy.envoy.type.matcher.ValueMatcher getDefaultInstance();
    Code:
       0: getstatic     #435                // Field DEFAULT_INSTANCE:Lio/grpc/xds/shaded/io/envoyproxy/envoy/type/matcher/ValueMatcher;
       3: areturn

  public static com.google.protobuf.Parser<io.grpc.xds.shaded.io.envoyproxy.envoy.type.matcher.ValueMatcher> parser();
    Code:
       0: getstatic     #376                // Field PARSER:Lcom/google/protobuf/Parser;
       3: areturn

  public com.google.protobuf.Parser<io.grpc.xds.shaded.io.envoyproxy.envoy.type.matcher.ValueMatcher> getParserForType();
    Code:
       0: getstatic     #376                // Field PARSER:Lcom/google/protobuf/Parser;
       3: areturn

  public io.grpc.xds.shaded.io.envoyproxy.envoy.type.matcher.ValueMatcher getDefaultInstanceForType();
    Code:
       0: getstatic     #435                // Field DEFAULT_INSTANCE:Lio/grpc/xds/shaded/io/envoyproxy/envoy/type/matcher/ValueMatcher;
       3: areturn

  protected com.google.protobuf.Message$Builder newBuilderForType(com.google.protobuf.GeneratedMessageV3$BuilderParent);
    Code:
       0: aload_0
       1: aload_1
       2: invokevirtual #458                // Method newBuilderForType:(Lcom/google/protobuf/GeneratedMessageV3$BuilderParent;)Lio/grpc/xds/shaded/io/envoyproxy/envoy/type/matcher/ValueMatcher$Builder;
       5: areturn

  public com.google.protobuf.Message$Builder toBuilder();
    Code:
       0: aload_0
       1: invokevirtual #437                // Method toBuilder:()Lio/grpc/xds/shaded/io/envoyproxy/envoy/type/matcher/ValueMatcher$Builder;
       4: areturn

  public com.google.protobuf.Message$Builder newBuilderForType();
    Code:
       0: aload_0
       1: invokevirtual #461                // Method newBuilderForType:()Lio/grpc/xds/shaded/io/envoyproxy/envoy/type/matcher/ValueMatcher$Builder;
       4: areturn

  public com.google.protobuf.MessageLite$Builder toBuilder();
    Code:
       0: aload_0
       1: invokevirtual #437                // Method toBuilder:()Lio/grpc/xds/shaded/io/envoyproxy/envoy/type/matcher/ValueMatcher$Builder;
       4: areturn

  public com.google.protobuf.MessageLite$Builder newBuilderForType();
    Code:
       0: aload_0
       1: invokevirtual #461                // Method newBuilderForType:()Lio/grpc/xds/shaded/io/envoyproxy/envoy/type/matcher/ValueMatcher$Builder;
       4: areturn

  public com.google.protobuf.MessageLite getDefaultInstanceForType();
    Code:
       0: aload_0
       1: invokevirtual #465                // Method getDefaultInstanceForType:()Lio/grpc/xds/shaded/io/envoyproxy/envoy/type/matcher/ValueMatcher;
       4: areturn

  public com.google.protobuf.Message getDefaultInstanceForType();
    Code:
       0: aload_0
       1: invokevirtual #465                // Method getDefaultInstanceForType:()Lio/grpc/xds/shaded/io/envoyproxy/envoy/type/matcher/ValueMatcher;
       4: areturn

  static boolean access$900();
    Code:
       0: getstatic     #470                // Field alwaysUseFieldBuilders:Z
       3: ireturn

  io.grpc.xds.shaded.io.envoyproxy.envoy.type.matcher.ValueMatcher(com.google.protobuf.GeneratedMessageV3$Builder, io.grpc.xds.shaded.io.envoyproxy.envoy.type.matcher.ValueMatcher$1);
    Code:
       0: aload_0
       1: aload_1
       2: invokespecial #472                // Method "<init>":(Lcom/google/protobuf/GeneratedMessageV3$Builder;)V
       5: return

  static java.lang.Object access$1102(io.grpc.xds.shaded.io.envoyproxy.envoy.type.matcher.ValueMatcher, java.lang.Object);
    Code:
       0: aload_0
       1: aload_1
       2: dup_x1
       3: putfield      #141                // Field matchPattern_:Ljava/lang/Object;
       6: areturn

  static int access$1202(io.grpc.xds.shaded.io.envoyproxy.envoy.type.matcher.ValueMatcher, int);
    Code:
       0: aload_0
       1: iload_1
       2: dup_x1
       3: putfield      #99                 // Field matchPatternCase_:I
       6: ireturn

  static com.google.protobuf.UnknownFieldSet access$1300(io.grpc.xds.shaded.io.envoyproxy.envoy.type.matcher.ValueMatcher);
    Code:
       0: aload_0
       1: getfield      #119                // Field unknownFields:Lcom/google/protobuf/UnknownFieldSet;
       4: areturn

  static com.google.protobuf.Parser access$1400();
    Code:
       0: getstatic     #376                // Field PARSER:Lcom/google/protobuf/Parser;
       3: areturn

  io.grpc.xds.shaded.io.envoyproxy.envoy.type.matcher.ValueMatcher(com.google.protobuf.CodedInputStream, com.google.protobuf.ExtensionRegistryLite, io.grpc.xds.shaded.io.envoyproxy.envoy.type.matcher.ValueMatcher$1) throws com.google.protobuf.InvalidProtocolBufferException;
    Code:
       0: aload_0
       1: aload_1
       2: aload_2
       3: invokespecial #485                // Method "<init>":(Lcom/google/protobuf/CodedInputStream;Lcom/google/protobuf/ExtensionRegistryLite;)V
       6: return

  static {};
    Code:
       0: new           #2                  // class io/grpc/xds/shaded/io/envoyproxy/envoy/type/matcher/ValueMatcher
       3: dup
       4: invokespecial #111                // Method "<init>":()V
       7: putstatic     #435                // Field DEFAULT_INSTANCE:Lio/grpc/xds/shaded/io/envoyproxy/envoy/type/matcher/ValueMatcher;
      10: new           #23                 // class io/grpc/xds/shaded/io/envoyproxy/envoy/type/matcher/ValueMatcher$1
      13: dup
      14: invokespecial #488                // Method io/grpc/xds/shaded/io/envoyproxy/envoy/type/matcher/ValueMatcher$1."<init>":()V
      17: putstatic     #376                // Field PARSER:Lcom/google/protobuf/Parser;
      20: return
}
