Compiled from "KeytabConsumer.java"
public interface org.wildfly.swarm.config.management.security_realm.server_identity.KeytabConsumer<T extends org.wildfly.swarm.config.management.security_realm.server_identity.Keytab<T>> {
  public abstract void accept(T);

  public default org.wildfly.swarm.config.management.security_realm.server_identity.KeytabConsumer<T> andThen(org.wildfly.swarm.config.management.security_realm.server_identity.KeytabConsumer<T>);
    Code:
       0: aload_0
       1: aload_1
       2: invokedynamic #1,  0              // InvokeDynamic #0:accept:(Lorg/wildfly/swarm/config/management/security_realm/server_identity/KeytabConsumer;Lorg/wildfly/swarm/config/management/security_realm/server_identity/KeytabConsumer;)Lorg/wildfly/swarm/config/management/security_realm/server_identity/KeytabConsumer;
       7: areturn

  private void lambda$andThen$128(org.wildfly.swarm.config.management.security_realm.server_identity.KeytabConsumer, org.wildfly.swarm.config.management.security_realm.server_identity.Keytab);
    Code:
       0: aload_0
       1: aload_2
       2: invokeinterface #2,  2            // InterfaceMethod accept:(Lorg/wildfly/swarm/config/management/security_realm/server_identity/Keytab;)V
       7: aload_1
       8: aload_2
       9: invokeinterface #2,  2            // InterfaceMethod accept:(Lorg/wildfly/swarm/config/management/security_realm/server_identity/Keytab;)V
      14: return
}
