public final class dk.brics.automaton.Datatypes {
  private static final java.util.Map<java.lang.String, dk.brics.automaton.Automaton> automata;

  private static final dk.brics.automaton.Automaton ws;

  private static final java.util.Set<java.lang.String> unicodeblock_names;

  private static final java.util.Set<java.lang.String> unicodecategory_names;

  private static final java.util.Set<java.lang.String> xml_names;

  private static final java.lang.String[] unicodeblock_names_array;

  private static final java.lang.String[] unicodecategory_names_array;

  private static final java.lang.String[] xml_names_array;

  private dk.brics.automaton.Datatypes();
    Code:
       0: aload_0
       1: invokespecial #1                  // Method java/lang/Object."<init>":()V
       4: return

  public static void main(java.lang.String[]);
    Code:
       0: invokestatic  #2                  // Method java/lang/System.currentTimeMillis:()J
       3: lstore_1
       4: iconst_1
       5: invokestatic  #3                  // Method dk/brics/automaton/Automaton.setAllowMutate:(Z)Z
       8: istore_3
       9: invokestatic  #4                  // Method buildAll:()V
      12: iload_3
      13: invokestatic  #3                  // Method dk/brics/automaton/Automaton.setAllowMutate:(Z)Z
      16: pop
      17: getstatic     #5                  // Field java/lang/System.out:Ljava/io/PrintStream;
      20: ldc           #6                  // String Storing automata...
      22: invokevirtual #7                  // Method java/io/PrintStream.println:(Ljava/lang/String;)V
      25: getstatic     #8                  // Field automata:Ljava/util/Map;
      28: invokeinterface #9,  1            // InterfaceMethod java/util/Map.entrySet:()Ljava/util/Set;
      33: invokeinterface #10,  1           // InterfaceMethod java/util/Set.iterator:()Ljava/util/Iterator;
      38: astore        4
      40: aload         4
      42: invokeinterface #11,  1           // InterfaceMethod java/util/Iterator.hasNext:()Z
      47: ifeq          88
      50: aload         4
      52: invokeinterface #12,  1           // InterfaceMethod java/util/Iterator.next:()Ljava/lang/Object;
      57: checkcast     #13                 // class java/util/Map$Entry
      60: astore        5
      62: aload         5
      64: invokeinterface #14,  1           // InterfaceMethod java/util/Map$Entry.getKey:()Ljava/lang/Object;
      69: checkcast     #15                 // class java/lang/String
      72: aload         5
      74: invokeinterface #16,  1           // InterfaceMethod java/util/Map$Entry.getValue:()Ljava/lang/Object;
      79: checkcast     #17                 // class dk/brics/automaton/Automaton
      82: invokestatic  #18                 // Method store:(Ljava/lang/String;Ldk/brics/automaton/Automaton;)V
      85: goto          40
      88: getstatic     #5                  // Field java/lang/System.out:Ljava/io/PrintStream;
      91: new           #19                 // class java/lang/StringBuilder
      94: dup
      95: invokespecial #20                 // Method java/lang/StringBuilder."<init>":()V
      98: ldc           #21                 // String Time for building automata:
     100: invokevirtual #22                 // Method java/lang/StringBuilder.append:(Ljava/lang/String;)Ljava/lang/StringBuilder;
     103: invokestatic  #2                  // Method java/lang/System.currentTimeMillis:()J
     106: lload_1
     107: lsub
     108: invokevirtual #23                 // Method java/lang/StringBuilder.append:(J)Ljava/lang/StringBuilder;
     111: ldc           #24                 // String ms
     113: invokevirtual #22                 // Method java/lang/StringBuilder.append:(Ljava/lang/String;)Ljava/lang/StringBuilder;
     116: invokevirtual #25                 // Method java/lang/StringBuilder.toString:()Ljava/lang/String;
     119: invokevirtual #7                  // Method java/io/PrintStream.println:(Ljava/lang/String;)V
     122: return

  public static dk.brics.automaton.Automaton get(java.lang.String);
    Code:
       0: getstatic     #8                  // Field automata:Ljava/util/Map;
       3: aload_0
       4: invokeinterface #26,  2           // InterfaceMethod java/util/Map.get:(Ljava/lang/Object;)Ljava/lang/Object;
       9: checkcast     #17                 // class dk/brics/automaton/Automaton
      12: astore_1
      13: aload_1
      14: ifnonnull     33
      17: aload_0
      18: invokestatic  #27                 // Method load:(Ljava/lang/String;)Ldk/brics/automaton/Automaton;
      21: astore_1
      22: getstatic     #8                  // Field automata:Ljava/util/Map;
      25: aload_0
      26: aload_1
      27: invokeinterface #28,  3           // InterfaceMethod java/util/Map.put:(Ljava/lang/Object;Ljava/lang/Object;)Ljava/lang/Object;
      32: pop
      33: aload_1
      34: areturn

  public static boolean isUnicodeBlockName(java.lang.String);
    Code:
       0: getstatic     #29                 // Field unicodeblock_names:Ljava/util/Set;
       3: aload_0
       4: invokeinterface #30,  2           // InterfaceMethod java/util/Set.contains:(Ljava/lang/Object;)Z
       9: ireturn

  public static boolean isUnicodeCategoryName(java.lang.String);
    Code:
       0: getstatic     #31                 // Field unicodecategory_names:Ljava/util/Set;
       3: aload_0
       4: invokeinterface #30,  2           // InterfaceMethod java/util/Set.contains:(Ljava/lang/Object;)Z
       9: ireturn

  public static boolean isXMLName(java.lang.String);
    Code:
       0: getstatic     #32                 // Field xml_names:Ljava/util/Set;
       3: aload_0
       4: invokeinterface #30,  2           // InterfaceMethod java/util/Set.contains:(Ljava/lang/Object;)Z
       9: ireturn

  public static boolean exists(java.lang.String);
    Code:
       0: ldc_w         #33                 // class dk/brics/automaton/Datatypes
       3: invokevirtual #34                 // Method java/lang/Class.getClassLoader:()Ljava/lang/ClassLoader;
       6: new           #19                 // class java/lang/StringBuilder
       9: dup
      10: invokespecial #20                 // Method java/lang/StringBuilder."<init>":()V
      13: aload_0
      14: invokevirtual #22                 // Method java/lang/StringBuilder.append:(Ljava/lang/String;)Ljava/lang/StringBuilder;
      17: ldc           #35                 // String .aut
      19: invokevirtual #22                 // Method java/lang/StringBuilder.append:(Ljava/lang/String;)Ljava/lang/StringBuilder;
      22: invokevirtual #25                 // Method java/lang/StringBuilder.toString:()Ljava/lang/String;
      25: invokevirtual #36                 // Method java/lang/ClassLoader.getResource:(Ljava/lang/String;)Ljava/net/URL;
      28: invokevirtual #37                 // Method java/net/URL.openStream:()Ljava/io/InputStream;
      31: invokevirtual #38                 // Method java/io/InputStream.close:()V
      34: goto          40
      37: astore_1
      38: iconst_0
      39: ireturn
      40: iconst_1
      41: ireturn
    Exception table:
       from    to  target type
           0    34    37   Class java/io/IOException

  private static dk.brics.automaton.Automaton load(java.lang.String);
    Code:
       0: ldc_w         #33                 // class dk/brics/automaton/Datatypes
       3: invokevirtual #34                 // Method java/lang/Class.getClassLoader:()Ljava/lang/ClassLoader;
       6: new           #19                 // class java/lang/StringBuilder
       9: dup
      10: invokespecial #20                 // Method java/lang/StringBuilder."<init>":()V
      13: aload_0
      14: invokevirtual #22                 // Method java/lang/StringBuilder.append:(Ljava/lang/String;)Ljava/lang/StringBuilder;
      17: ldc           #35                 // String .aut
      19: invokevirtual #22                 // Method java/lang/StringBuilder.append:(Ljava/lang/String;)Ljava/lang/StringBuilder;
      22: invokevirtual #25                 // Method java/lang/StringBuilder.toString:()Ljava/lang/String;
      25: invokevirtual #36                 // Method java/lang/ClassLoader.getResource:(Ljava/lang/String;)Ljava/net/URL;
      28: astore_1
      29: aload_1
      30: invokevirtual #37                 // Method java/net/URL.openStream:()Ljava/io/InputStream;
      33: invokestatic  #40                 // Method dk/brics/automaton/Automaton.load:(Ljava/io/InputStream;)Ldk/brics/automaton/Automaton;
      36: areturn
      37: astore_1
      38: aload_1
      39: invokevirtual #41                 // Method java/io/IOException.printStackTrace:()V
      42: aconst_null
      43: areturn
      44: astore_1
      45: aload_1
      46: invokevirtual #43                 // Method java/lang/ClassNotFoundException.printStackTrace:()V
      49: aconst_null
      50: areturn
    Exception table:
       from    to  target type
           0    36    37   Class java/io/IOException
           0    36    44   Class java/lang/ClassNotFoundException

  private static void store(java.lang.String, dk.brics.automaton.Automaton);
    Code:
       0: ldc           #44                 // String dk.brics.automaton.datatypes
       2: invokestatic  #45                 // Method java/lang/System.getProperty:(Ljava/lang/String;)Ljava/lang/String;
       5: astore_2
       6: aload_2
       7: ifnonnull     13
      10: ldc           #46                 // String build
      12: astore_2
      13: aload_1
      14: new           #47                 // class java/io/FileOutputStream
      17: dup
      18: new           #19                 // class java/lang/StringBuilder
      21: dup
      22: invokespecial #20                 // Method java/lang/StringBuilder."<init>":()V
      25: aload_2
      26: invokevirtual #22                 // Method java/lang/StringBuilder.append:(Ljava/lang/String;)Ljava/lang/StringBuilder;
      29: ldc           #48                 // String /
      31: invokevirtual #22                 // Method java/lang/StringBuilder.append:(Ljava/lang/String;)Ljava/lang/StringBuilder;
      34: aload_0
      35: invokevirtual #22                 // Method java/lang/StringBuilder.append:(Ljava/lang/String;)Ljava/lang/StringBuilder;
      38: ldc           #35                 // String .aut
      40: invokevirtual #22                 // Method java/lang/StringBuilder.append:(Ljava/lang/String;)Ljava/lang/StringBuilder;
      43: invokevirtual #25                 // Method java/lang/StringBuilder.toString:()Ljava/lang/String;
      46: invokespecial #49                 // Method java/io/FileOutputStream."<init>":(Ljava/lang/String;)V
      49: invokevirtual #50                 // Method dk/brics/automaton/Automaton.store:(Ljava/io/OutputStream;)V
      52: goto          60
      55: astore_3
      56: aload_3
      57: invokevirtual #41                 // Method java/io/IOException.printStackTrace:()V
      60: return
    Exception table:
       from    to  target type
          13    52    55   Class java/io/IOException

  private static void buildAll();
    Code:
       0: bipush        28
       2: anewarray     #15                 // class java/lang/String
       5: dup
       6: iconst_0
       7: ldc           #51                 // String Extender
       9: aastore
      10: dup
      11: iconst_1
      12: ldc           #52                 // String [〱-〵ゝ-ゞー-ヾ·ːˑ·ـๆໆ々]
      14: aastore
      15: dup
      16: iconst_2
      17: ldc           #53                 // String CombiningChar
      19: aastore
      20: dup
      21: iconst_3
      22: ldc           #54                 // String [̀-͠ͅ-҃͡-֑҆-֣֡-ֹֻ-ֽׁ-ׂً-ْۖ-ۜ۝-۟۠-ۤۧ-۪ۨ-ۭँ-ःा-ौ॑-॔ॢ-ॣঁ-ঃী-ৄে-ৈো-্ৢ-ৣੀ-ੂੇ-ੈੋ-੍ੰ-ੱઁ-ઃા-ૅે-ૉો-્ଁ-ଃା-ୃେ-ୈୋ-୍ୖ-ୗஂ-ஃா-ூெ-ைொ-்ఁ-ఃా-ౄె-ైొ-్ౕ-ౖಂ-ಃಾ-ೄೆ-ೈೊ-್ೕ-ೖം-ഃാ-ൃെ-ൈൊ-്ิ-ฺ็-๎ິ-ູົ-ຼ່-ໍ༘-ཱ༙-྄྆-ྋྐ-ྕྙ-ྭྱ-ྷ⃐-〪⃜-़়्ֿٰ〯ׄািৗਂ਼ਾਿ઼଼ௗൗัັ༹༵༷༾༿ྗྐྵ゙゚⃡]
      24: aastore
      25: dup
      26: iconst_4
      27: ldc           #55                 // String Digit
      29: aastore
      30: dup
      31: iconst_5
      32: ldc           #56                 // String [0-9٠-٩۰-۹०-९০-৯੦-੯૦-૯୦-୯௧-௯౦-౯೦-೯൦-൯๐-๙໐-໙༠-༩]
      34: aastore
      35: dup
      36: bipush        6
      38: ldc           #57                 // String Ideographic
      40: aastore
      41: dup
      42: bipush        7
      44: ldc           #58                 // String [一-龥〡-〩〇]
      46: aastore
      47: dup
      48: bipush        8
      50: ldc           #59                 // String BaseChar
      52: aastore
      53: dup
      54: bipush        9
      56: ldc           #60                 // String [A-Za-zÀ-ÖØ-öø-ÿĀ-ıĴ-ľŁ-ňŊ-žƀ-ǃǍ-ǰǴ-ǵǺ-ȗɐ-ʨʻ-ˁΈ-ΊΎ-ΡΣ-ώϐ-ϖϢ-ϳЁ-ЌЎ-яё-ќў-ҁҐ-ӄӇ-ӈӋ-ӌӐ-ӫӮ-ӵӸ-ӹԱ-Ֆա-ֆא-תװ-ײء-غف-يٱ-ڷں-ھۀ-ێې-ۓۥ-ۦअ-हक़-ॡঅ-ঌএ-ঐও-নপ-রশ-হড়-ঢ়য়-ৡৰ-ৱਅ-ਊਏ-ਐਓ-ਨਪ-ਰਲ-ਲ਼ਵ-ਸ਼ਸ-ਹਖ਼-ੜੲ-ੴઅ-ઋએ-ઑઓ-નપ-રલ-ળવ-હଅ-ଌଏ-ଐଓ-ନପ-ରଲ-ଳଶ-ହଡ଼-ଢ଼ୟ-ୡஅ-ஊஎ-ஐஒ-கங-சஞ-டண-தந-பம-வஷ-ஹఅ-ఌఎ-ఐఒ-నప-ళవ-హౠ-ౡಅ-ಌಎ-ಐಒ-ನಪ-ಳವ-ಹೠ-ೡഅ-ഌഎ-ഐഒ-നപ-ഹൠ-ൡก-ฮา-ำเ-ๅກ-ຂງ-ຈດ-ທນ-ຟມ-ຣສ-ຫອ-ຮາ-ຳເ-ໄཀ-ཇཉ-ཀྵႠ-Ⴥა-ჶᄂ-ᄃᄅ-ᄇᄋ-ᄌᄎ-ᄒᅔ-ᅕᅟ-ᅡᅭ-ᅮᅲ-ᅳᆮ-ᆯᆷ-ᆸᆼ-ᇂḀ-ẛẠ-ỹἀ-ἕἘ-Ἕἠ-ὅὈ-Ὅὐ-ὗὟ-ώᾀ-ᾴᾶ-ᾼῂ-ῄῆ-ῌῐ-ΐῖ-Ίῠ-Ῥῲ-ῴῶ-ῼK-Åↀ-ↂぁ-ゔァ-ヺㄅ-ㄬ가-힣ΆΌϚϜϞϠՙەऽলਫ਼ઍઽૠଽஜೞะຄຊຍລວະຽᄀᄉᄼᄾᅀᅌᅎᅐᅙᅣᅥᅧᅩᅵᆞᆨᆫᆺᇫᇰᇹὙὛὝιΩ℮]
      58: aastore
      59: dup
      60: bipush        10
      62: ldc           #61                 // String Letter
      64: aastore
      65: dup
      66: bipush        11
      68: ldc           #62                 // String <BaseChar>|<Ideographic>
      70: aastore
      71: dup
      72: bipush        12
      74: ldc           #63                 // String NCNameChar
      76: aastore
      77: dup
      78: bipush        13
      80: ldc           #64                 // String <Letter>|<Digit>|[-._]|<CombiningChar>|<Extender>
      82: aastore
      83: dup
      84: bipush        14
      86: ldc           #65                 // String NameChar
      88: aastore
      89: dup
      90: bipush        15
      92: ldc           #66                 // String <NCNameChar>|:
      94: aastore
      95: dup
      96: bipush        16
      98: ldc           #67                 // String Nmtoken
     100: aastore
     101: dup
     102: bipush        17
     104: ldc           #68                 // String <NameChar>+
     106: aastore
     107: dup
     108: bipush        18
     110: ldc           #69                 // String NCName
     112: aastore
     113: dup
     114: bipush        19
     116: ldc           #70                 // String (<Letter>|_)<NCNameChar>*
     118: aastore
     119: dup
     120: bipush        20
     122: ldc           #71                 // String Name
     124: aastore
     125: dup
     126: bipush        21
     128: ldc           #72                 // String (<Letter>|[_:])<NameChar>*
     130: aastore
     131: dup
     132: bipush        22
     134: ldc           #73                 // String QName
     136: aastore
     137: dup
     138: bipush        23
     140: ldc           #74                 // String (<NCName>:)?<NCName>
     142: aastore
     143: dup
     144: bipush        24
     146: ldc           #75                 // String Char
     148: aastore
     149: dup
     150: bipush        25
     152: ldc           #76                 // String [\t\n\r -퟿-�]|[?-?][?-?]
     154: aastore
     155: dup
     156: bipush        26
     158: ldc           #77                 // String whitespacechar
     160: aastore
     161: dup
     162: bipush        27
     164: ldc           #78                 // String [ \t\n\r]
     166: aastore
     167: astore_0
     168: getstatic     #5                  // Field java/lang/System.out:Ljava/io/PrintStream;
     171: ldc           #79                 // String Building XML automata...
     173: invokevirtual #7                  // Method java/io/PrintStream.println:(Ljava/lang/String;)V
     176: aload_0
     177: invokestatic  #80                 // Method buildMap:([Ljava/lang/String;)Ljava/util/Map;
     180: astore_1
     181: ldc           #69                 // String NCName
     183: aload_1
     184: invokestatic  #81                 // Method putFrom:(Ljava/lang/String;Ljava/util/Map;)V
     187: ldc           #73                 // String QName
     189: aload_1
     190: invokestatic  #81                 // Method putFrom:(Ljava/lang/String;Ljava/util/Map;)V
     193: ldc           #75                 // String Char
     195: aload_1
     196: invokestatic  #81                 // Method putFrom:(Ljava/lang/String;Ljava/util/Map;)V
     199: ldc           #65                 // String NameChar
     201: aload_1
     202: invokestatic  #81                 // Method putFrom:(Ljava/lang/String;Ljava/util/Map;)V
     205: ldc           #61                 // String Letter
     207: aload_1
     208: invokestatic  #81                 // Method putFrom:(Ljava/lang/String;Ljava/util/Map;)V
     211: ldc           #77                 // String whitespacechar
     213: aload_1
     214: invokestatic  #81                 // Method putFrom:(Ljava/lang/String;Ljava/util/Map;)V
     217: getstatic     #8                  // Field automata:Ljava/util/Map;
     220: ldc           #82                 // String whitespace
     222: getstatic     #83                 // Field ws:Ldk/brics/automaton/Automaton;
     225: invokestatic  #84                 // Method put:(Ljava/util/Map;Ljava/lang/String;Ldk/brics/automaton/Automaton;)V
     228: bipush        84
     230: anewarray     #15                 // class java/lang/String
     233: dup
     234: iconst_0
     235: ldc           #85                 // String digit
     237: aastore
     238: dup
     239: iconst_1
     240: ldc           #86                 // String [0-9]
     242: aastore
     243: dup
     244: iconst_2
     245: ldc           #87                 // String upalpha
     247: aastore
     248: dup
     249: iconst_3
     250: ldc           #88                 // String [A-Z]
     252: aastore
     253: dup
     254: iconst_4
     255: ldc           #89                 // String lowalpha
     257: aastore
     258: dup
     259: iconst_5
     260: ldc           #90                 // String [a-z]
     262: aastore
     263: dup
     264: bipush        6
     266: ldc           #91                 // String alpha
     268: aastore
     269: dup
     270: bipush        7
     272: ldc           #92                 // String <lowalpha>|<upalpha>
     274: aastore
     275: dup
     276: bipush        8
     278: ldc           #93                 // String alphanum
     280: aastore
     281: dup
     282: bipush        9
     284: ldc           #94                 // String <alpha>|<digit>
     286: aastore
     287: dup
     288: bipush        10
     290: ldc           #95                 // String hex
     292: aastore
     293: dup
     294: bipush        11
     296: ldc           #96                 // String <digit>|[a-f]|[A-F]
     298: aastore
     299: dup
     300: bipush        12
     302: ldc           #97                 // String escaped
     304: aastore
     305: dup
     306: bipush        13
     308: ldc           #98                 // String %<hex><hex>
     310: aastore
     311: dup
     312: bipush        14
     314: ldc           #99                 // String mark
     316: aastore
     317: dup
     318: bipush        15
     320: ldc           #100                // String [-_.!~*\'()]
     322: aastore
     323: dup
     324: bipush        16
     326: ldc           #101                // String unreserved
     328: aastore
     329: dup
     330: bipush        17
     332: ldc           #102                // String <alphanum>|<mark>
     334: aastore
     335: dup
     336: bipush        18
     338: ldc           #103                // String reserved
     340: aastore
     341: dup
     342: bipush        19
     344: ldc           #104                // String [;/?:@&=+$,\\[\\]]
     346: aastore
     347: dup
     348: bipush        20
     350: ldc           #105                // String uric
     352: aastore
     353: dup
     354: bipush        21
     356: ldc           #106                // String <reserved>|<unreserved>|<escaped>
     358: aastore
     359: dup
     360: bipush        22
     362: ldc           #107                // String fragment
     364: aastore
     365: dup
     366: bipush        23
     368: ldc           #108                // String <uric>*
     370: aastore
     371: dup
     372: bipush        24
     374: ldc           #109                // String query
     376: aastore
     377: dup
     378: bipush        25
     380: ldc           #108                // String <uric>*
     382: aastore
     383: dup
     384: bipush        26
     386: ldc           #110                // String pchar
     388: aastore
     389: dup
     390: bipush        27
     392: ldc           #111                // String <unreserved>|<escaped>|[:@&=+$,]
     394: aastore
     395: dup
     396: bipush        28
     398: ldc           #112                // String param
     400: aastore
     401: dup
     402: bipush        29
     404: ldc           #113                // String <pchar>*
     406: aastore
     407: dup
     408: bipush        30
     410: ldc           #114                // String segment
     412: aastore
     413: dup
     414: bipush        31
     416: ldc           #115                // String <pchar>*(;<param>)*
     418: aastore
     419: dup
     420: bipush        32
     422: ldc           #116                // String path_segments
     424: aastore
     425: dup
     426: bipush        33
     428: ldc           #117                // String <segment>(/<segment>)*
     430: aastore
     431: dup
     432: bipush        34
     434: ldc           #118                // String abs_path
     436: aastore
     437: dup
     438: bipush        35
     440: ldc           #119                // String /<path_segments>
     442: aastore
     443: dup
     444: bipush        36
     446: ldc           #120                // String uric_no_slash
     448: aastore
     449: dup
     450: bipush        37
     452: ldc           #121                // String <unreserved>|<escaped>|[;?:@&=+$,]
     454: aastore
     455: dup
     456: bipush        38
     458: ldc           #122                // String opaque_part
     460: aastore
     461: dup
     462: bipush        39
     464: ldc           #123                // String <uric_no_slash><uric>*
     466: aastore
     467: dup
     468: bipush        40
     470: ldc           #124                // String port
     472: aastore
     473: dup
     474: bipush        41
     476: ldc           #125                // String <digit>*
     478: aastore
     479: dup
     480: bipush        42
     482: ldc           #126                // String IPv4address
     484: aastore
     485: dup
     486: bipush        43
     488: ldc           #127                // String (<digit>{1,3}\\.){3}<digit>{1,3}
     490: aastore
     491: dup
     492: bipush        44
     494: ldc           #128                // String hexseq
     496: aastore
     497: dup
     498: bipush        45
     500: ldc           #129                // String <hex>{1,4}(:<hex>{1,4})*
     502: aastore
     503: dup
     504: bipush        46
     506: ldc           #130                // String hexpart
     508: aastore
     509: dup
     510: bipush        47
     512: ldc           #131                // String <hexseq>|<hexseq>::<hexseq>?|::<hexseq>
     514: aastore
     515: dup
     516: bipush        48
     518: ldc           #132                // String IPv6address
     520: aastore
     521: dup
     522: bipush        49
     524: ldc           #133                // String <hexpart>(:<IPv4address>)?
     526: aastore
     527: dup
     528: bipush        50
     530: ldc           #134                // String toplabel
     532: aastore
     533: dup
     534: bipush        51
     536: ldc           #135                // String <alpha>|(<alpha>(<alphanum>|-)*<alphanum>)
     538: aastore
     539: dup
     540: bipush        52
     542: ldc           #136                // String domainlabel
     544: aastore
     545: dup
     546: bipush        53
     548: ldc           #137                // String <alphanum>|(<alphanum>(<alphanum>|-)*<alphanum>)
     550: aastore
     551: dup
     552: bipush        54
     554: ldc           #138                // String hostname
     556: aastore
     557: dup
     558: bipush        55
     560: ldc           #139                // String (<domainlabel>\\.)*<toplabel>\\.?
     562: aastore
     563: dup
     564: bipush        56
     566: ldc           #140                // String host
     568: aastore
     569: dup
     570: bipush        57
     572: ldc           #141                // String <hostname>|<IPv4address>|\\[<IPv6address>\\]
     574: aastore
     575: dup
     576: bipush        58
     578: ldc           #142                // String hostport
     580: aastore
     581: dup
     582: bipush        59
     584: ldc           #143                // String <host>(:<port>)?
     586: aastore
     587: dup
     588: bipush        60
     590: ldc           #144                // String userinfo
     592: aastore
     593: dup
     594: bipush        61
     596: ldc           #145                // String (<unreserved>|<escaped>|[;:&=+$,])*
     598: aastore
     599: dup
     600: bipush        62
     602: ldc           #146                // String server
     604: aastore
     605: dup
     606: bipush        63
     608: ldc           #147                // String ((<userinfo>\\@)?<hostport>)?
     610: aastore
     611: dup
     612: bipush        64
     614: ldc           #148                // String reg_name
     616: aastore
     617: dup
     618: bipush        65
     620: ldc           #149                // String (<unreserved>|<escaped>|[$,;:@&=+])+
     622: aastore
     623: dup
     624: bipush        66
     626: ldc           #150                // String authority
     628: aastore
     629: dup
     630: bipush        67
     632: ldc           #151                // String <server>|<reg_name>
     634: aastore
     635: dup
     636: bipush        68
     638: ldc           #152                // String scheme
     640: aastore
     641: dup
     642: bipush        69
     644: ldc           #153                // String <alpha>(<alpha>|<digit>|[-+.])*
     646: aastore
     647: dup
     648: bipush        70
     650: ldc           #154                // String rel_segment
     652: aastore
     653: dup
     654: bipush        71
     656: ldc           #155                // String (<unreserved>|<escaped>|[;@&=+$,])+
     658: aastore
     659: dup
     660: bipush        72
     662: ldc           #156                // String rel_path
     664: aastore
     665: dup
     666: bipush        73
     668: ldc           #157                // String <rel_segment><abs_path>?
     670: aastore
     671: dup
     672: bipush        74
     674: ldc           #158                // String net_path
     676: aastore
     677: dup
     678: bipush        75
     680: ldc           #159                // String //<authority><abs_path>?
     682: aastore
     683: dup
     684: bipush        76
     686: ldc           #160                // String hier_part
     688: aastore
     689: dup
     690: bipush        77
     692: ldc           #161                // String (<net_path>|<abs_path>)(\\?<query>)?
     694: aastore
     695: dup
     696: bipush        78
     698: ldc           #162                // String relativeURI
     700: aastore
     701: dup
     702: bipush        79
     704: ldc           #163                // String (<net_path>|<abs_path>|<rel_path>)(\\?<query>)?
     706: aastore
     707: dup
     708: bipush        80
     710: ldc           #164                // String absoluteURI
     712: aastore
     713: dup
     714: bipush        81
     716: ldc           #165                // String <scheme>:(<hier_part>|<opaque_part>)
     718: aastore
     719: dup
     720: bipush        82
     722: ldc           #166                // String URI
     724: aastore
     725: dup
     726: bipush        83
     728: ldc           #167                // String (<absoluteURI>|<relativeURI>)?(\\#<fragment>)?
     730: aastore
     731: astore_2
     732: getstatic     #5                  // Field java/lang/System.out:Ljava/io/PrintStream;
     735: ldc           #168                // String Building URI automaton...
     737: invokevirtual #7                  // Method java/io/PrintStream.println:(Ljava/lang/String;)V
     740: ldc           #166                // String URI
     742: aload_2
     743: invokestatic  #80                 // Method buildMap:([Ljava/lang/String;)Ljava/util/Map;
     746: invokestatic  #81                 // Method putFrom:(Ljava/lang/String;Ljava/util/Map;)V
     749: getstatic     #8                  // Field automata:Ljava/util/Map;
     752: ldc           #169                // String anyname
     754: bipush        123
     756: invokestatic  #170                // Method dk/brics/automaton/Automaton.makeChar:(C)Ldk/brics/automaton/Automaton;
     759: getstatic     #8                  // Field automata:Ljava/util/Map;
     762: ldc           #166                // String URI
     764: invokeinterface #26,  2           // InterfaceMethod java/util/Map.get:(Ljava/lang/Object;)Ljava/lang/Object;
     769: checkcast     #17                 // class dk/brics/automaton/Automaton
     772: invokevirtual #171                // Method dk/brics/automaton/Automaton.clone:()Ldk/brics/automaton/Automaton;
     775: invokevirtual #172                // Method dk/brics/automaton/Automaton.concatenate:(Ldk/brics/automaton/Automaton;)Ldk/brics/automaton/Automaton;
     778: bipush        125
     780: invokestatic  #170                // Method dk/brics/automaton/Automaton.makeChar:(C)Ldk/brics/automaton/Automaton;
     783: invokevirtual #172                // Method dk/brics/automaton/Automaton.concatenate:(Ldk/brics/automaton/Automaton;)Ldk/brics/automaton/Automaton;
     786: invokevirtual #173                // Method dk/brics/automaton/Automaton.optional:()Ldk/brics/automaton/Automaton;
     789: getstatic     #8                  // Field automata:Ljava/util/Map;
     792: ldc           #69                 // String NCName
     794: invokeinterface #26,  2           // InterfaceMethod java/util/Map.get:(Ljava/lang/Object;)Ljava/lang/Object;
     799: checkcast     #17                 // class dk/brics/automaton/Automaton
     802: invokevirtual #171                // Method dk/brics/automaton/Automaton.clone:()Ldk/brics/automaton/Automaton;
     805: invokevirtual #172                // Method dk/brics/automaton/Automaton.concatenate:(Ldk/brics/automaton/Automaton;)Ldk/brics/automaton/Automaton;
     808: invokestatic  #174                // Method dk/brics/automaton/Automaton.minimize:(Ldk/brics/automaton/Automaton;)Ldk/brics/automaton/Automaton;
     811: invokestatic  #84                 // Method put:(Ljava/util/Map;Ljava/lang/String;Ldk/brics/automaton/Automaton;)V
     814: getstatic     #8                  // Field automata:Ljava/util/Map;
     817: ldc           #175                // String noap
     819: new           #176                // class dk/brics/automaton/RegExp
     822: dup
     823: ldc           #177                // String ~(@[@%]@)
     825: invokespecial #178                // Method dk/brics/automaton/RegExp."<init>":(Ljava/lang/String;)V
     828: invokevirtual #179                // Method dk/brics/automaton/RegExp.toAutomaton:()Ldk/brics/automaton/Automaton;
     831: invokestatic  #84                 // Method put:(Ljava/util/Map;Ljava/lang/String;Ldk/brics/automaton/Automaton;)V
     834: bipush        26
     836: anewarray     #15                 // class java/lang/String
     839: dup
     840: iconst_0
     841: ldc           #180                // String _
     843: aastore
     844: dup
     845: iconst_1
     846: ldc           #181                // String [ \t\n\r]*
     848: aastore
     849: dup
     850: iconst_2
     851: ldc           #182                // String d
     853: aastore
     854: dup
     855: iconst_3
     856: ldc           #86                 // String [0-9]
     858: aastore
     859: dup
     860: iconst_4
     861: ldc           #183                // String Z
     863: aastore
     864: dup
     865: iconst_5
     866: ldc           #184                // String [-+](<00-13>:<00-59>|14:00)|Z
     868: aastore
     869: dup
     870: bipush        6
     872: ldc           #185                // String Y
     874: aastore
     875: dup
     876: bipush        7
     878: ldc           #186                // String (<d>{4,})&~(0000)
     880: aastore
     881: dup
     882: bipush        8
     884: ldc           #187                // String M
     886: aastore
     887: dup
     888: bipush        9
     890: ldc           #188                // String <01-12>
     892: aastore
     893: dup
     894: bipush        10
     896: ldc           #189                // String D
     898: aastore
     899: dup
     900: bipush        11
     902: ldc           #190                // String <01-31>
     904: aastore
     905: dup
     906: bipush        12
     908: ldc           #191                // String T
     910: aastore
     911: dup
     912: bipush        13
     914: ldc           #192                // String <00-23>:<00-59>:<00-59>|24:00:00
     916: aastore
     917: dup
     918: bipush        14
     920: ldc           #193                // String B64
     922: aastore
     923: dup
     924: bipush        15
     926: ldc           #194                // String [A-Za-z0-9+/]
     928: aastore
     929: dup
     930: bipush        16
     932: ldc           #195                // String B16
     934: aastore
     935: dup
     936: bipush        17
     938: ldc           #196                // String [AEIMQUYcgkosw048]
     940: aastore
     941: dup
     942: bipush        18
     944: ldc           #197                // String B04
     946: aastore
     947: dup
     948: bipush        19
     950: ldc           #198                // String [AQgw]
     952: aastore
     953: dup
     954: bipush        20
     956: ldc           #199                // String B04S
     958: aastore
     959: dup
     960: bipush        21
     962: ldc           #200                // String <B04> ?
     964: aastore
     965: dup
     966: bipush        22
     968: ldc           #201                // String B16S
     970: aastore
     971: dup
     972: bipush        23
     974: ldc           #202                // String <B16> ?
     976: aastore
     977: dup
     978: bipush        24
     980: ldc           #203                // String B64S
     982: aastore
     983: dup
     984: bipush        25
     986: ldc           #204                // String <B64> ?
     988: aastore
     989: astore_3
     990: bipush        40
     992: anewarray     #15                 // class java/lang/String
     995: dup
     996: iconst_0
     997: ldc           #205                // String boolean
     999: aastore
    1000: dup
    1001: iconst_1
    1002: ldc           #206                // String <_>(true|false|1|0)<_>
    1004: aastore
    1005: dup
    1006: iconst_2
    1007: ldc           #207                // String decimal
    1009: aastore
    1010: dup
    1011: iconst_3
    1012: ldc           #208                // String <_>([-+]?<d>+(\\.<d>+)?)<_>
    1014: aastore
    1015: dup
    1016: iconst_4
    1017: ldc           #209                // String float
    1019: aastore
    1020: dup
    1021: iconst_5
    1022: ldc           #210                // String <_>([-+]?<d>+(\\.<d>+)?([Ee][-+]?<d>+)?|INF|-INF|NaN)<_>
    1024: aastore
    1025: dup
    1026: bipush        6
    1028: ldc           #211                // String integer
    1030: aastore
    1031: dup
    1032: bipush        7
    1034: ldc           #212                // String <_>[-+]?[0-9]+<_>
    1036: aastore
    1037: dup
    1038: bipush        8
    1040: ldc           #213                // String duration
    1042: aastore
    1043: dup
    1044: bipush        9
    1046: ldc           #214                // String <_>(-?P(((<d>+Y)?(<d>+M)?(<d>+D)?(T(((<d>+H)?(<d>+M)?(<d>+(\\.<d>+)?S)?)&~()))?)&~()))<_>
    1048: aastore
    1049: dup
    1050: bipush        10
    1052: ldc           #215                // String dateTime
    1054: aastore
    1055: dup
    1056: bipush        11
    1058: ldc           #216                // String <_>(-?<Y>-<M>-<D>T<T>(\\.<d>+)?<Z>?)<_>
    1060: aastore
    1061: dup
    1062: bipush        12
    1064: ldc           #217                // String time
    1066: aastore
    1067: dup
    1068: bipush        13
    1070: ldc           #218                // String <_>(<T>(\\.<d>+)?<Z>?)<_>
    1072: aastore
    1073: dup
    1074: bipush        14
    1076: ldc           #219                // String date
    1078: aastore
    1079: dup
    1080: bipush        15
    1082: ldc           #220                // String <_>(-?<Y>-<M>-<D><Z>?)<_>
    1084: aastore
    1085: dup
    1086: bipush        16
    1088: ldc           #221                // String gYearMonth
    1090: aastore
    1091: dup
    1092: bipush        17
    1094: ldc           #222                // String <_>(-?<Y>-<M><Z>?)<_>
    1096: aastore
    1097: dup
    1098: bipush        18
    1100: ldc           #223                // String gYear
    1102: aastore
    1103: dup
    1104: bipush        19
    1106: ldc           #224                // String <_>(-?<Y><Z>?)<_>
    1108: aastore
    1109: dup
    1110: bipush        20
    1112: ldc           #225                // String gMonthDay
    1114: aastore
    1115: dup
    1116: bipush        21
    1118: ldc           #226                // String <_>(--<M>-<D><Z>?)<_>
    1120: aastore
    1121: dup
    1122: bipush        22
    1124: ldc           #227                // String gDay
    1126: aastore
    1127: dup
    1128: bipush        23
    1130: ldc           #228                // String <_>(--<D><Z>?)<_>
    1132: aastore
    1133: dup
    1134: bipush        24
    1136: ldc           #229                // String gMonth
    1138: aastore
    1139: dup
    1140: bipush        25
    1142: ldc           #230                // String <_>(--<M><Z>?)<_>
    1144: aastore
    1145: dup
    1146: bipush        26
    1148: ldc           #231                // String hexBinary
    1150: aastore
    1151: dup
    1152: bipush        27
    1154: ldc           #232                // String <_>([0-9a-fA-F]{2}*)<_>
    1156: aastore
    1157: dup
    1158: bipush        28
    1160: ldc           #233                // String base64Binary
    1162: aastore
    1163: dup
    1164: bipush        29
    1166: ldc           #234                // String <_>(((<B64S><B64S><B64S><B64S>)*((<B64S><B64S><B64S><B64>)|(<B64S><B64S><B16S>=)|(<B64S><B04S>= ?=)))?)<_>
    1168: aastore
    1169: dup
    1170: bipush        30
    1172: ldc           #235                // String language
    1174: aastore
    1175: dup
    1176: bipush        31
    1178: ldc           #236                // String <_>[a-zA-Z]{1,8}(-[a-zA-Z0-9]{1,8})*<_>
    1180: aastore
    1181: dup
    1182: bipush        32
    1184: ldc           #237                // String nonPositiveInteger
    1186: aastore
    1187: dup
    1188: bipush        33
    1190: ldc           #238                // String <_>(0+|-<d>+)<_>
    1192: aastore
    1193: dup
    1194: bipush        34
    1196: ldc           #239                // String negativeInteger
    1198: aastore
    1199: dup
    1200: bipush        35
    1202: ldc           #240                // String <_>(-[1-9]<d>*)<_>
    1204: aastore
    1205: dup
    1206: bipush        36
    1208: ldc           #241                // String nonNegativeInteger
    1210: aastore
    1211: dup
    1212: bipush        37
    1214: ldc           #242                // String <_>(<d>+)<_>
    1216: aastore
    1217: dup
    1218: bipush        38
    1220: ldc           #243                // String positiveInteger
    1222: aastore
    1223: dup
    1224: bipush        39
    1226: ldc           #244                // String <_>([1-9]<d>*)<_>
    1228: aastore
    1229: astore        4
    1231: getstatic     #5                  // Field java/lang/System.out:Ljava/io/PrintStream;
    1234: ldc           #245                // String Building XML Schema automata...
    1236: invokevirtual #7                  // Method java/io/PrintStream.println:(Ljava/lang/String;)V
    1239: aload_3
    1240: invokestatic  #80                 // Method buildMap:([Ljava/lang/String;)Ljava/util/Map;
    1243: astore        5
    1245: aload         4
    1247: aload         5
    1249: invokestatic  #246                // Method putWith:([Ljava/lang/String;Ljava/util/Map;)V
    1252: aload         5
    1254: ldc           #247                // String UNSIGNEDLONG
    1256: ldc           #248                // String 18446744073709551615
    1258: invokestatic  #249                // Method dk/brics/automaton/Automaton.makeMaxInteger:(Ljava/lang/String;)Ldk/brics/automaton/Automaton;
    1261: invokestatic  #84                 // Method put:(Ljava/util/Map;Ljava/lang/String;Ldk/brics/automaton/Automaton;)V
    1264: aload         5
    1266: ldc           #250                // String UNSIGNEDINT
    1268: ldc           #251                // String 4294967295
    1270: invokestatic  #249                // Method dk/brics/automaton/Automaton.makeMaxInteger:(Ljava/lang/String;)Ldk/brics/automaton/Automaton;
    1273: invokestatic  #84                 // Method put:(Ljava/util/Map;Ljava/lang/String;Ldk/brics/automaton/Automaton;)V
    1276: aload         5
    1278: ldc           #252                // String UNSIGNEDSHORT
    1280: ldc           #253                // String 65535
    1282: invokestatic  #249                // Method dk/brics/automaton/Automaton.makeMaxInteger:(Ljava/lang/String;)Ldk/brics/automaton/Automaton;
    1285: invokestatic  #84                 // Method put:(Ljava/util/Map;Ljava/lang/String;Ldk/brics/automaton/Automaton;)V
    1288: aload         5
    1290: ldc           #254                // String UNSIGNEDBYTE
    1292: ldc           #255                // String 255
    1294: invokestatic  #249                // Method dk/brics/automaton/Automaton.makeMaxInteger:(Ljava/lang/String;)Ldk/brics/automaton/Automaton;
    1297: invokestatic  #84                 // Method put:(Ljava/util/Map;Ljava/lang/String;Ldk/brics/automaton/Automaton;)V
    1300: aload         5
    1302: ldc_w         #256                // String LONG
    1305: ldc_w         #257                // String 9223372036854775807
    1308: invokestatic  #249                // Method dk/brics/automaton/Automaton.makeMaxInteger:(Ljava/lang/String;)Ldk/brics/automaton/Automaton;
    1311: invokestatic  #84                 // Method put:(Ljava/util/Map;Ljava/lang/String;Ldk/brics/automaton/Automaton;)V
    1314: aload         5
    1316: ldc_w         #258                // String LONG_NEG
    1319: ldc_w         #259                // String 9223372036854775808
    1322: invokestatic  #249                // Method dk/brics/automaton/Automaton.makeMaxInteger:(Ljava/lang/String;)Ldk/brics/automaton/Automaton;
    1325: invokestatic  #84                 // Method put:(Ljava/util/Map;Ljava/lang/String;Ldk/brics/automaton/Automaton;)V
    1328: aload         5
    1330: ldc_w         #260                // String INT
    1333: ldc_w         #261                // String 2147483647
    1336: invokestatic  #249                // Method dk/brics/automaton/Automaton.makeMaxInteger:(Ljava/lang/String;)Ldk/brics/automaton/Automaton;
    1339: invokestatic  #84                 // Method put:(Ljava/util/Map;Ljava/lang/String;Ldk/brics/automaton/Automaton;)V
    1342: aload         5
    1344: ldc_w         #262                // String INT_NEG
    1347: ldc_w         #263                // String 2147483648
    1350: invokestatic  #249                // Method dk/brics/automaton/Automaton.makeMaxInteger:(Ljava/lang/String;)Ldk/brics/automaton/Automaton;
    1353: invokestatic  #84                 // Method put:(Ljava/util/Map;Ljava/lang/String;Ldk/brics/automaton/Automaton;)V
    1356: aload         5
    1358: ldc_w         #264                // String SHORT
    1361: ldc_w         #265                // String 32767
    1364: invokestatic  #249                // Method dk/brics/automaton/Automaton.makeMaxInteger:(Ljava/lang/String;)Ldk/brics/automaton/Automaton;
    1367: invokestatic  #84                 // Method put:(Ljava/util/Map;Ljava/lang/String;Ldk/brics/automaton/Automaton;)V
    1370: aload         5
    1372: ldc_w         #266                // String SHORT_NEG
    1375: ldc_w         #267                // String 32768
    1378: invokestatic  #249                // Method dk/brics/automaton/Automaton.makeMaxInteger:(Ljava/lang/String;)Ldk/brics/automaton/Automaton;
    1381: invokestatic  #84                 // Method put:(Ljava/util/Map;Ljava/lang/String;Ldk/brics/automaton/Automaton;)V
    1384: aload         5
    1386: ldc_w         #268                // String BYTE
    1389: ldc_w         #269                // String 127
    1392: invokestatic  #249                // Method dk/brics/automaton/Automaton.makeMaxInteger:(Ljava/lang/String;)Ldk/brics/automaton/Automaton;
    1395: invokestatic  #84                 // Method put:(Ljava/util/Map;Ljava/lang/String;Ldk/brics/automaton/Automaton;)V
    1398: aload         5
    1400: ldc_w         #270                // String BYTE_NEG
    1403: ldc_w         #271                // String 128
    1406: invokestatic  #249                // Method dk/brics/automaton/Automaton.makeMaxInteger:(Ljava/lang/String;)Ldk/brics/automaton/Automaton;
    1409: invokestatic  #84                 // Method put:(Ljava/util/Map;Ljava/lang/String;Ldk/brics/automaton/Automaton;)V
    1412: new           #272                // class java/util/HashMap
    1415: dup
    1416: invokespecial #273                // Method java/util/HashMap."<init>":()V
    1419: astore        6
    1421: aload         6
    1423: aload_1
    1424: invokeinterface #274,  2          // InterfaceMethod java/util/Map.putAll:(Ljava/util/Map;)V
    1429: aload         6
    1431: aload         5
    1433: invokeinterface #274,  2          // InterfaceMethod java/util/Map.putAll:(Ljava/util/Map;)V
    1438: bipush        32
    1440: anewarray     #15                 // class java/lang/String
    1443: dup
    1444: iconst_0
    1445: ldc_w         #275                // String Nmtoken2
    1448: aastore
    1449: dup
    1450: iconst_1
    1451: ldc_w         #276                // String <_><Nmtoken><_>
    1454: aastore
    1455: dup
    1456: iconst_2
    1457: ldc_w         #277                // String Name2
    1460: aastore
    1461: dup
    1462: iconst_3
    1463: ldc_w         #278                // String <_><Name><_>
    1466: aastore
    1467: dup
    1468: iconst_4
    1469: ldc_w         #279                // String NCName2
    1472: aastore
    1473: dup
    1474: iconst_5
    1475: ldc_w         #280                // String <_><NCName><_>
    1478: aastore
    1479: dup
    1480: bipush        6
    1482: ldc_w         #281                // String QName2
    1485: aastore
    1486: dup
    1487: bipush        7
    1489: ldc_w         #282                // String <_><QName><_>
    1492: aastore
    1493: dup
    1494: bipush        8
    1496: ldc_w         #283                // String Nmtokens
    1499: aastore
    1500: dup
    1501: bipush        9
    1503: ldc_w         #284                // String <_>(<Nmtoken><_>)+
    1506: aastore
    1507: dup
    1508: bipush        10
    1510: ldc_w         #285                // String NCNames
    1513: aastore
    1514: dup
    1515: bipush        11
    1517: ldc_w         #286                // String <_>(<NCName><_>)+
    1520: aastore
    1521: dup
    1522: bipush        12
    1524: ldc_w         #287                // String Names
    1527: aastore
    1528: dup
    1529: bipush        13
    1531: ldc_w         #288                // String <_>(<Name><_>)+
    1534: aastore
    1535: dup
    1536: bipush        14
    1538: ldc_w         #289                // String unsignedLong
    1541: aastore
    1542: dup
    1543: bipush        15
    1545: ldc_w         #290                // String <_><UNSIGNEDLONG><_>
    1548: aastore
    1549: dup
    1550: bipush        16
    1552: ldc_w         #291                // String unsignedInt
    1555: aastore
    1556: dup
    1557: bipush        17
    1559: ldc_w         #292                // String <_><UNSIGNEDINT><_>
    1562: aastore
    1563: dup
    1564: bipush        18
    1566: ldc_w         #293                // String unsignedShort
    1569: aastore
    1570: dup
    1571: bipush        19
    1573: ldc_w         #294                // String <_><UNSIGNEDSHORT><_>
    1576: aastore
    1577: dup
    1578: bipush        20
    1580: ldc_w         #295                // String unsignedByte
    1583: aastore
    1584: dup
    1585: bipush        21
    1587: ldc_w         #296                // String <_><UNSIGNEDBYTE><_>
    1590: aastore
    1591: dup
    1592: bipush        22
    1594: ldc_w         #297                // String long
    1597: aastore
    1598: dup
    1599: bipush        23
    1601: ldc_w         #298                // String <_>(<LONG>|-<LONG_NEG>)<_>
    1604: aastore
    1605: dup
    1606: bipush        24
    1608: ldc_w         #299                // String int
    1611: aastore
    1612: dup
    1613: bipush        25
    1615: ldc_w         #300                // String <_>(<INT>|-<INT_NEG>)<_>
    1618: aastore
    1619: dup
    1620: bipush        26
    1622: ldc_w         #301                // String short
    1625: aastore
    1626: dup
    1627: bipush        27
    1629: ldc_w         #302                // String <_>(<SHORT>|-<SHORT_NEG>)<_>
    1632: aastore
    1633: dup
    1634: bipush        28
    1636: ldc_w         #303                // String byte
    1639: aastore
    1640: dup
    1641: bipush        29
    1643: ldc_w         #304                // String <_>(<BYTE>|-<BYTE_NEG>)<_>
    1646: aastore
    1647: dup
    1648: bipush        30
    1650: ldc_w         #305                // String string
    1653: aastore
    1654: dup
    1655: bipush        31
    1657: ldc_w         #306                // String <Char>*
    1660: aastore
    1661: astore        7
    1663: aload         7
    1665: aload         6
    1667: invokestatic  #246                // Method putWith:([Ljava/lang/String;Ljava/util/Map;)V
    1670: getstatic     #5                  // Field java/lang/System.out:Ljava/io/PrintStream;
    1673: ldc_w         #307                // String Building Unicode block automata...
    1676: invokevirtual #7                  // Method java/io/PrintStream.println:(Ljava/lang/String;)V
    1679: getstatic     #8                  // Field automata:Ljava/util/Map;
    1682: ldc_w         #308                // String BasicLatin
    1685: iconst_0
    1686: bipush        127
    1688: invokestatic  #309                // Method dk/brics/automaton/Automaton.makeCharRange:(CC)Ldk/brics/automaton/Automaton;
    1691: invokestatic  #84                 // Method put:(Ljava/util/Map;Ljava/lang/String;Ldk/brics/automaton/Automaton;)V
    1694: getstatic     #8                  // Field automata:Ljava/util/Map;
    1697: ldc_w         #310                // String Latin-1Supplement
    1700: sipush        128
    1703: sipush        255
    1706: invokestatic  #309                // Method dk/brics/automaton/Automaton.makeCharRange:(CC)Ldk/brics/automaton/Automaton;
    1709: invokestatic  #84                 // Method put:(Ljava/util/Map;Ljava/lang/String;Ldk/brics/automaton/Automaton;)V
    1712: getstatic     #8                  // Field automata:Ljava/util/Map;
    1715: ldc_w         #311                // String LatinExtended-A
    1718: sipush        256
    1721: sipush        383
    1724: invokestatic  #309                // Method dk/brics/automaton/Automaton.makeCharRange:(CC)Ldk/brics/automaton/Automaton;
    1727: invokestatic  #84                 // Method put:(Ljava/util/Map;Ljava/lang/String;Ldk/brics/automaton/Automaton;)V
    1730: getstatic     #8                  // Field automata:Ljava/util/Map;
    1733: ldc_w         #312                // String LatinExtended-B
    1736: sipush        384
    1739: sipush        591
    1742: invokestatic  #309                // Method dk/brics/automaton/Automaton.makeCharRange:(CC)Ldk/brics/automaton/Automaton;
    1745: invokestatic  #84                 // Method put:(Ljava/util/Map;Ljava/lang/String;Ldk/brics/automaton/Automaton;)V
    1748: getstatic     #8                  // Field automata:Ljava/util/Map;
    1751: ldc_w         #313                // String IPAExtensions
    1754: sipush        592
    1757: sipush        687
    1760: invokestatic  #309                // Method dk/brics/automaton/Automaton.makeCharRange:(CC)Ldk/brics/automaton/Automaton;
    1763: invokestatic  #84                 // Method put:(Ljava/util/Map;Ljava/lang/String;Ldk/brics/automaton/Automaton;)V
    1766: getstatic     #8                  // Field automata:Ljava/util/Map;
    1769: ldc_w         #314                // String SpacingModifierLetters
    1772: sipush        688
    1775: sipush        767
    1778: invokestatic  #309                // Method dk/brics/automaton/Automaton.makeCharRange:(CC)Ldk/brics/automaton/Automaton;
    1781: invokestatic  #84                 // Method put:(Ljava/util/Map;Ljava/lang/String;Ldk/brics/automaton/Automaton;)V
    1784: getstatic     #8                  // Field automata:Ljava/util/Map;
    1787: ldc_w         #315                // String CombiningDiacriticalMarks
    1790: sipush        768
    1793: sipush        879
    1796: invokestatic  #309                // Method dk/brics/automaton/Automaton.makeCharRange:(CC)Ldk/brics/automaton/Automaton;
    1799: invokestatic  #84                 // Method put:(Ljava/util/Map;Ljava/lang/String;Ldk/brics/automaton/Automaton;)V
    1802: getstatic     #8                  // Field automata:Ljava/util/Map;
    1805: ldc_w         #316                // String Greek
    1808: sipush        880
    1811: sipush        1023
    1814: invokestatic  #309                // Method dk/brics/automaton/Automaton.makeCharRange:(CC)Ldk/brics/automaton/Automaton;
    1817: invokestatic  #84                 // Method put:(Ljava/util/Map;Ljava/lang/String;Ldk/brics/automaton/Automaton;)V
    1820: getstatic     #8                  // Field automata:Ljava/util/Map;
    1823: ldc_w         #317                // String Cyrillic
    1826: sipush        1024
    1829: sipush        1279
    1832: invokestatic  #309                // Method dk/brics/automaton/Automaton.makeCharRange:(CC)Ldk/brics/automaton/Automaton;
    1835: invokestatic  #84                 // Method put:(Ljava/util/Map;Ljava/lang/String;Ldk/brics/automaton/Automaton;)V
    1838: getstatic     #8                  // Field automata:Ljava/util/Map;
    1841: ldc_w         #318                // String Armenian
    1844: sipush        1328
    1847: sipush        1423
    1850: invokestatic  #309                // Method dk/brics/automaton/Automaton.makeCharRange:(CC)Ldk/brics/automaton/Automaton;
    1853: invokestatic  #84                 // Method put:(Ljava/util/Map;Ljava/lang/String;Ldk/brics/automaton/Automaton;)V
    1856: getstatic     #8                  // Field automata:Ljava/util/Map;
    1859: ldc_w         #319                // String Hebrew
    1862: sipush        1424
    1865: sipush        1535
    1868: invokestatic  #309                // Method dk/brics/automaton/Automaton.makeCharRange:(CC)Ldk/brics/automaton/Automaton;
    1871: invokestatic  #84                 // Method put:(Ljava/util/Map;Ljava/lang/String;Ldk/brics/automaton/Automaton;)V
    1874: getstatic     #8                  // Field automata:Ljava/util/Map;
    1877: ldc_w         #320                // String Arabic
    1880: sipush        1536
    1883: sipush        1791
    1886: invokestatic  #309                // Method dk/brics/automaton/Automaton.makeCharRange:(CC)Ldk/brics/automaton/Automaton;
    1889: invokestatic  #84                 // Method put:(Ljava/util/Map;Ljava/lang/String;Ldk/brics/automaton/Automaton;)V
    1892: getstatic     #8                  // Field automata:Ljava/util/Map;
    1895: ldc_w         #321                // String Syriac
    1898: sipush        1792
    1901: sipush        1871
    1904: invokestatic  #309                // Method dk/brics/automaton/Automaton.makeCharRange:(CC)Ldk/brics/automaton/Automaton;
    1907: invokestatic  #84                 // Method put:(Ljava/util/Map;Ljava/lang/String;Ldk/brics/automaton/Automaton;)V
    1910: getstatic     #8                  // Field automata:Ljava/util/Map;
    1913: ldc_w         #322                // String Thaana
    1916: sipush        1920
    1919: sipush        1983
    1922: invokestatic  #309                // Method dk/brics/automaton/Automaton.makeCharRange:(CC)Ldk/brics/automaton/Automaton;
    1925: invokestatic  #84                 // Method put:(Ljava/util/Map;Ljava/lang/String;Ldk/brics/automaton/Automaton;)V
    1928: getstatic     #8                  // Field automata:Ljava/util/Map;
    1931: ldc_w         #323                // String Devanagari
    1934: sipush        2304
    1937: sipush        2431
    1940: invokestatic  #309                // Method dk/brics/automaton/Automaton.makeCharRange:(CC)Ldk/brics/automaton/Automaton;
    1943: invokestatic  #84                 // Method put:(Ljava/util/Map;Ljava/lang/String;Ldk/brics/automaton/Automaton;)V
    1946: getstatic     #8                  // Field automata:Ljava/util/Map;
    1949: ldc_w         #324                // String Bengali
    1952: sipush        2432
    1955: sipush        2559
    1958: invokestatic  #309                // Method dk/brics/automaton/Automaton.makeCharRange:(CC)Ldk/brics/automaton/Automaton;
    1961: invokestatic  #84                 // Method put:(Ljava/util/Map;Ljava/lang/String;Ldk/brics/automaton/Automaton;)V
    1964: getstatic     #8                  // Field automata:Ljava/util/Map;
    1967: ldc_w         #325                // String Gurmukhi
    1970: sipush        2560
    1973: sipush        2687
    1976: invokestatic  #309                // Method dk/brics/automaton/Automaton.makeCharRange:(CC)Ldk/brics/automaton/Automaton;
    1979: invokestatic  #84                 // Method put:(Ljava/util/Map;Ljava/lang/String;Ldk/brics/automaton/Automaton;)V
    1982: getstatic     #8                  // Field automata:Ljava/util/Map;
    1985: ldc_w         #326                // String Gujarati
    1988: sipush        2688
    1991: sipush        2815
    1994: invokestatic  #309                // Method dk/brics/automaton/Automaton.makeCharRange:(CC)Ldk/brics/automaton/Automaton;
    1997: invokestatic  #84                 // Method put:(Ljava/util/Map;Ljava/lang/String;Ldk/brics/automaton/Automaton;)V
    2000: getstatic     #8                  // Field automata:Ljava/util/Map;
    2003: ldc_w         #327                // String Oriya
    2006: sipush        2816
    2009: sipush        2943
    2012: invokestatic  #309                // Method dk/brics/automaton/Automaton.makeCharRange:(CC)Ldk/brics/automaton/Automaton;
    2015: invokestatic  #84                 // Method put:(Ljava/util/Map;Ljava/lang/String;Ldk/brics/automaton/Automaton;)V
    2018: getstatic     #8                  // Field automata:Ljava/util/Map;
    2021: ldc_w         #328                // String Tamil
    2024: sipush        2944
    2027: sipush        3071
    2030: invokestatic  #309                // Method dk/brics/automaton/Automaton.makeCharRange:(CC)Ldk/brics/automaton/Automaton;
    2033: invokestatic  #84                 // Method put:(Ljava/util/Map;Ljava/lang/String;Ldk/brics/automaton/Automaton;)V
    2036: getstatic     #8                  // Field automata:Ljava/util/Map;
    2039: ldc_w         #329                // String Telugu
    2042: sipush        3072
    2045: sipush        3199
    2048: invokestatic  #309                // Method dk/brics/automaton/Automaton.makeCharRange:(CC)Ldk/brics/automaton/Automaton;
    2051: invokestatic  #84                 // Method put:(Ljava/util/Map;Ljava/lang/String;Ldk/brics/automaton/Automaton;)V
    2054: getstatic     #8                  // Field automata:Ljava/util/Map;
    2057: ldc_w         #330                // String Kannada
    2060: sipush        3200
    2063: sipush        3327
    2066: invokestatic  #309                // Method dk/brics/automaton/Automaton.makeCharRange:(CC)Ldk/brics/automaton/Automaton;
    2069: invokestatic  #84                 // Method put:(Ljava/util/Map;Ljava/lang/String;Ldk/brics/automaton/Automaton;)V
    2072: getstatic     #8                  // Field automata:Ljava/util/Map;
    2075: ldc_w         #331                // String Malayalam
    2078: sipush        3328
    2081: sipush        3455
    2084: invokestatic  #309                // Method dk/brics/automaton/Automaton.makeCharRange:(CC)Ldk/brics/automaton/Automaton;
    2087: invokestatic  #84                 // Method put:(Ljava/util/Map;Ljava/lang/String;Ldk/brics/automaton/Automaton;)V
    2090: getstatic     #8                  // Field automata:Ljava/util/Map;
    2093: ldc_w         #332                // String Sinhala
    2096: sipush        3456
    2099: sipush        3583
    2102: invokestatic  #309                // Method dk/brics/automaton/Automaton.makeCharRange:(CC)Ldk/brics/automaton/Automaton;
    2105: invokestatic  #84                 // Method put:(Ljava/util/Map;Ljava/lang/String;Ldk/brics/automaton/Automaton;)V
    2108: getstatic     #8                  // Field automata:Ljava/util/Map;
    2111: ldc_w         #333                // String Thai
    2114: sipush        3584
    2117: sipush        3711
    2120: invokestatic  #309                // Method dk/brics/automaton/Automaton.makeCharRange:(CC)Ldk/brics/automaton/Automaton;
    2123: invokestatic  #84                 // Method put:(Ljava/util/Map;Ljava/lang/String;Ldk/brics/automaton/Automaton;)V
    2126: getstatic     #8                  // Field automata:Ljava/util/Map;
    2129: ldc_w         #334                // String Lao
    2132: sipush        3712
    2135: sipush        3839
    2138: invokestatic  #309                // Method dk/brics/automaton/Automaton.makeCharRange:(CC)Ldk/brics/automaton/Automaton;
    2141: invokestatic  #84                 // Method put:(Ljava/util/Map;Ljava/lang/String;Ldk/brics/automaton/Automaton;)V
    2144: getstatic     #8                  // Field automata:Ljava/util/Map;
    2147: ldc_w         #335                // String Tibetan
    2150: sipush        3840
    2153: sipush        4095
    2156: invokestatic  #309                // Method dk/brics/automaton/Automaton.makeCharRange:(CC)Ldk/brics/automaton/Automaton;
    2159: invokestatic  #84                 // Method put:(Ljava/util/Map;Ljava/lang/String;Ldk/brics/automaton/Automaton;)V
    2162: getstatic     #8                  // Field automata:Ljava/util/Map;
    2165: ldc_w         #336                // String Myanmar
    2168: sipush        4096
    2171: sipush        4255
    2174: invokestatic  #309                // Method dk/brics/automaton/Automaton.makeCharRange:(CC)Ldk/brics/automaton/Automaton;
    2177: invokestatic  #84                 // Method put:(Ljava/util/Map;Ljava/lang/String;Ldk/brics/automaton/Automaton;)V
    2180: getstatic     #8                  // Field automata:Ljava/util/Map;
    2183: ldc_w         #337                // String Georgian
    2186: sipush        4256
    2189: sipush        4351
    2192: invokestatic  #309                // Method dk/brics/automaton/Automaton.makeCharRange:(CC)Ldk/brics/automaton/Automaton;
    2195: invokestatic  #84                 // Method put:(Ljava/util/Map;Ljava/lang/String;Ldk/brics/automaton/Automaton;)V
    2198: getstatic     #8                  // Field automata:Ljava/util/Map;
    2201: ldc_w         #338                // String HangulJamo
    2204: sipush        4352
    2207: sipush        4607
    2210: invokestatic  #309                // Method dk/brics/automaton/Automaton.makeCharRange:(CC)Ldk/brics/automaton/Automaton;
    2213: invokestatic  #84                 // Method put:(Ljava/util/Map;Ljava/lang/String;Ldk/brics/automaton/Automaton;)V
    2216: getstatic     #8                  // Field automata:Ljava/util/Map;
    2219: ldc_w         #339                // String Ethiopic
    2222: sipush        4608
    2225: sipush        4991
    2228: invokestatic  #309                // Method dk/brics/automaton/Automaton.makeCharRange:(CC)Ldk/brics/automaton/Automaton;
    2231: invokestatic  #84                 // Method put:(Ljava/util/Map;Ljava/lang/String;Ldk/brics/automaton/Automaton;)V
    2234: getstatic     #8                  // Field automata:Ljava/util/Map;
    2237: ldc_w         #340                // String Cherokee
    2240: sipush        5024
    2243: sipush        5119
    2246: invokestatic  #309                // Method dk/brics/automaton/Automaton.makeCharRange:(CC)Ldk/brics/automaton/Automaton;
    2249: invokestatic  #84                 // Method put:(Ljava/util/Map;Ljava/lang/String;Ldk/brics/automaton/Automaton;)V
    2252: getstatic     #8                  // Field automata:Ljava/util/Map;
    2255: ldc_w         #341                // String UnifiedCanadianAboriginalSyllabics
    2258: sipush        5120
    2261: sipush        5759
    2264: invokestatic  #309                // Method dk/brics/automaton/Automaton.makeCharRange:(CC)Ldk/brics/automaton/Automaton;
    2267: invokestatic  #84                 // Method put:(Ljava/util/Map;Ljava/lang/String;Ldk/brics/automaton/Automaton;)V
    2270: getstatic     #8                  // Field automata:Ljava/util/Map;
    2273: ldc_w         #342                // String Ogham
    2276: sipush        5760
    2279: sipush        5791
    2282: invokestatic  #309                // Method dk/brics/automaton/Automaton.makeCharRange:(CC)Ldk/brics/automaton/Automaton;
    2285: invokestatic  #84                 // Method put:(Ljava/util/Map;Ljava/lang/String;Ldk/brics/automaton/Automaton;)V
    2288: getstatic     #8                  // Field automata:Ljava/util/Map;
    2291: ldc_w         #343                // String Runic
    2294: sipush        5792
    2297: sipush        5887
    2300: invokestatic  #309                // Method dk/brics/automaton/Automaton.makeCharRange:(CC)Ldk/brics/automaton/Automaton;
    2303: invokestatic  #84                 // Method put:(Ljava/util/Map;Ljava/lang/String;Ldk/brics/automaton/Automaton;)V
    2306: getstatic     #8                  // Field automata:Ljava/util/Map;
    2309: ldc_w         #344                // String Khmer
    2312: sipush        6016
    2315: sipush        6143
    2318: invokestatic  #309                // Method dk/brics/automaton/Automaton.makeCharRange:(CC)Ldk/brics/automaton/Automaton;
    2321: invokestatic  #84                 // Method put:(Ljava/util/Map;Ljava/lang/String;Ldk/brics/automaton/Automaton;)V
    2324: getstatic     #8                  // Field automata:Ljava/util/Map;
    2327: ldc_w         #345                // String Mongolian
    2330: sipush        6144
    2333: sipush        6319
    2336: invokestatic  #309                // Method dk/brics/automaton/Automaton.makeCharRange:(CC)Ldk/brics/automaton/Automaton;
    2339: invokestatic  #84                 // Method put:(Ljava/util/Map;Ljava/lang/String;Ldk/brics/automaton/Automaton;)V
    2342: getstatic     #8                  // Field automata:Ljava/util/Map;
    2345: ldc_w         #346                // String LatinExtendedAdditional
    2348: sipush        7680
    2351: sipush        7935
    2354: invokestatic  #309                // Method dk/brics/automaton/Automaton.makeCharRange:(CC)Ldk/brics/automaton/Automaton;
    2357: invokestatic  #84                 // Method put:(Ljava/util/Map;Ljava/lang/String;Ldk/brics/automaton/Automaton;)V
    2360: getstatic     #8                  // Field automata:Ljava/util/Map;
    2363: ldc_w         #347                // String GreekExtended
    2366: sipush        7936
    2369: sipush        8191
    2372: invokestatic  #309                // Method dk/brics/automaton/Automaton.makeCharRange:(CC)Ldk/brics/automaton/Automaton;
    2375: invokestatic  #84                 // Method put:(Ljava/util/Map;Ljava/lang/String;Ldk/brics/automaton/Automaton;)V
    2378: getstatic     #8                  // Field automata:Ljava/util/Map;
    2381: ldc_w         #348                // String GeneralPunctuation
    2384: sipush        8192
    2387: sipush        8303
    2390: invokestatic  #309                // Method dk/brics/automaton/Automaton.makeCharRange:(CC)Ldk/brics/automaton/Automaton;
    2393: invokestatic  #84                 // Method put:(Ljava/util/Map;Ljava/lang/String;Ldk/brics/automaton/Automaton;)V
    2396: getstatic     #8                  // Field automata:Ljava/util/Map;
    2399: ldc_w         #349                // String SuperscriptsandSubscripts
    2402: sipush        8304
    2405: sipush        8351
    2408: invokestatic  #309                // Method dk/brics/automaton/Automaton.makeCharRange:(CC)Ldk/brics/automaton/Automaton;
    2411: invokestatic  #84                 // Method put:(Ljava/util/Map;Ljava/lang/String;Ldk/brics/automaton/Automaton;)V
    2414: getstatic     #8                  // Field automata:Ljava/util/Map;
    2417: ldc_w         #350                // String CurrencySymbols
    2420: sipush        8352
    2423: sipush        8399
    2426: invokestatic  #309                // Method dk/brics/automaton/Automaton.makeCharRange:(CC)Ldk/brics/automaton/Automaton;
    2429: invokestatic  #84                 // Method put:(Ljava/util/Map;Ljava/lang/String;Ldk/brics/automaton/Automaton;)V
    2432: getstatic     #8                  // Field automata:Ljava/util/Map;
    2435: ldc_w         #351                // String CombiningMarksforSymbols
    2438: sipush        8400
    2441: sipush        8447
    2444: invokestatic  #309                // Method dk/brics/automaton/Automaton.makeCharRange:(CC)Ldk/brics/automaton/Automaton;
    2447: invokestatic  #84                 // Method put:(Ljava/util/Map;Ljava/lang/String;Ldk/brics/automaton/Automaton;)V
    2450: getstatic     #8                  // Field automata:Ljava/util/Map;
    2453: ldc_w         #352                // String LetterlikeSymbols
    2456: sipush        8448
    2459: sipush        8527
    2462: invokestatic  #309                // Method dk/brics/automaton/Automaton.makeCharRange:(CC)Ldk/brics/automaton/Automaton;
    2465: invokestatic  #84                 // Method put:(Ljava/util/Map;Ljava/lang/String;Ldk/brics/automaton/Automaton;)V
    2468: getstatic     #8                  // Field automata:Ljava/util/Map;
    2471: ldc_w         #353                // String NumberForms
    2474: sipush        8528
    2477: sipush        8591
    2480: invokestatic  #309                // Method dk/brics/automaton/Automaton.makeCharRange:(CC)Ldk/brics/automaton/Automaton;
    2483: invokestatic  #84                 // Method put:(Ljava/util/Map;Ljava/lang/String;Ldk/brics/automaton/Automaton;)V
    2486: getstatic     #8                  // Field automata:Ljava/util/Map;
    2489: ldc_w         #354                // String Arrows
    2492: sipush        8592
    2495: sipush        8703
    2498: invokestatic  #309                // Method dk/brics/automaton/Automaton.makeCharRange:(CC)Ldk/brics/automaton/Automaton;
    2501: invokestatic  #84                 // Method put:(Ljava/util/Map;Ljava/lang/String;Ldk/brics/automaton/Automaton;)V
    2504: getstatic     #8                  // Field automata:Ljava/util/Map;
    2507: ldc_w         #355                // String MathematicalOperators
    2510: sipush        8704
    2513: sipush        8959
    2516: invokestatic  #309                // Method dk/brics/automaton/Automaton.makeCharRange:(CC)Ldk/brics/automaton/Automaton;
    2519: invokestatic  #84                 // Method put:(Ljava/util/Map;Ljava/lang/String;Ldk/brics/automaton/Automaton;)V
    2522: getstatic     #8                  // Field automata:Ljava/util/Map;
    2525: ldc_w         #356                // String MiscellaneousTechnical
    2528: sipush        8960
    2531: sipush        9215
    2534: invokestatic  #309                // Method dk/brics/automaton/Automaton.makeCharRange:(CC)Ldk/brics/automaton/Automaton;
    2537: invokestatic  #84                 // Method put:(Ljava/util/Map;Ljava/lang/String;Ldk/brics/automaton/Automaton;)V
    2540: getstatic     #8                  // Field automata:Ljava/util/Map;
    2543: ldc_w         #357                // String ControlPictures
    2546: sipush        9216
    2549: sipush        9279
    2552: invokestatic  #309                // Method dk/brics/automaton/Automaton.makeCharRange:(CC)Ldk/brics/automaton/Automaton;
    2555: invokestatic  #84                 // Method put:(Ljava/util/Map;Ljava/lang/String;Ldk/brics/automaton/Automaton;)V
    2558: getstatic     #8                  // Field automata:Ljava/util/Map;
    2561: ldc_w         #358                // String OpticalCharacterRecognition
    2564: sipush        9280
    2567: sipush        9311
    2570: invokestatic  #309                // Method dk/brics/automaton/Automaton.makeCharRange:(CC)Ldk/brics/automaton/Automaton;
    2573: invokestatic  #84                 // Method put:(Ljava/util/Map;Ljava/lang/String;Ldk/brics/automaton/Automaton;)V
    2576: getstatic     #8                  // Field automata:Ljava/util/Map;
    2579: ldc_w         #359                // String EnclosedAlphanumerics
    2582: sipush        9312
    2585: sipush        9471
    2588: invokestatic  #309                // Method dk/brics/automaton/Automaton.makeCharRange:(CC)Ldk/brics/automaton/Automaton;
    2591: invokestatic  #84                 // Method put:(Ljava/util/Map;Ljava/lang/String;Ldk/brics/automaton/Automaton;)V
    2594: getstatic     #8                  // Field automata:Ljava/util/Map;
    2597: ldc_w         #360                // String BoxDrawing
    2600: sipush        9472
    2603: sipush        9599
    2606: invokestatic  #309                // Method dk/brics/automaton/Automaton.makeCharRange:(CC)Ldk/brics/automaton/Automaton;
    2609: invokestatic  #84                 // Method put:(Ljava/util/Map;Ljava/lang/String;Ldk/brics/automaton/Automaton;)V
    2612: getstatic     #8                  // Field automata:Ljava/util/Map;
    2615: ldc_w         #361                // String BlockElements
    2618: sipush        9600
    2621: sipush        9631
    2624: invokestatic  #309                // Method dk/brics/automaton/Automaton.makeCharRange:(CC)Ldk/brics/automaton/Automaton;
    2627: invokestatic  #84                 // Method put:(Ljava/util/Map;Ljava/lang/String;Ldk/brics/automaton/Automaton;)V
    2630: getstatic     #8                  // Field automata:Ljava/util/Map;
    2633: ldc_w         #362                // String GeometricShapes
    2636: sipush        9632
    2639: sipush        9727
    2642: invokestatic  #309                // Method dk/brics/automaton/Automaton.makeCharRange:(CC)Ldk/brics/automaton/Automaton;
    2645: invokestatic  #84                 // Method put:(Ljava/util/Map;Ljava/lang/String;Ldk/brics/automaton/Automaton;)V
    2648: getstatic     #8                  // Field automata:Ljava/util/Map;
    2651: ldc_w         #363                // String MiscellaneousSymbols
    2654: sipush        9728
    2657: sipush        9983
    2660: invokestatic  #309                // Method dk/brics/automaton/Automaton.makeCharRange:(CC)Ldk/brics/automaton/Automaton;
    2663: invokestatic  #84                 // Method put:(Ljava/util/Map;Ljava/lang/String;Ldk/brics/automaton/Automaton;)V
    2666: getstatic     #8                  // Field automata:Ljava/util/Map;
    2669: ldc_w         #364                // String Dingbats
    2672: sipush        9984
    2675: sipush        10175
    2678: invokestatic  #309                // Method dk/brics/automaton/Automaton.makeCharRange:(CC)Ldk/brics/automaton/Automaton;
    2681: invokestatic  #84                 // Method put:(Ljava/util/Map;Ljava/lang/String;Ldk/brics/automaton/Automaton;)V
    2684: getstatic     #8                  // Field automata:Ljava/util/Map;
    2687: ldc_w         #365                // String BraillePatterns
    2690: sipush        10240
    2693: sipush        10495
    2696: invokestatic  #309                // Method dk/brics/automaton/Automaton.makeCharRange:(CC)Ldk/brics/automaton/Automaton;
    2699: invokestatic  #84                 // Method put:(Ljava/util/Map;Ljava/lang/String;Ldk/brics/automaton/Automaton;)V
    2702: getstatic     #8                  // Field automata:Ljava/util/Map;
    2705: ldc_w         #366                // String CJKRadicalsSupplement
    2708: sipush        11904
    2711: sipush        12031
    2714: invokestatic  #309                // Method dk/brics/automaton/Automaton.makeCharRange:(CC)Ldk/brics/automaton/Automaton;
    2717: invokestatic  #84                 // Method put:(Ljava/util/Map;Ljava/lang/String;Ldk/brics/automaton/Automaton;)V
    2720: getstatic     #8                  // Field automata:Ljava/util/Map;
    2723: ldc_w         #367                // String KangxiRadicals
    2726: sipush        12032
    2729: sipush        12255
    2732: invokestatic  #309                // Method dk/brics/automaton/Automaton.makeCharRange:(CC)Ldk/brics/automaton/Automaton;
    2735: invokestatic  #84                 // Method put:(Ljava/util/Map;Ljava/lang/String;Ldk/brics/automaton/Automaton;)V
    2738: getstatic     #8                  // Field automata:Ljava/util/Map;
    2741: ldc_w         #368                // String IdeographicDescriptionCharacters
    2744: sipush        12272
    2747: sipush        12287
    2750: invokestatic  #309                // Method dk/brics/automaton/Automaton.makeCharRange:(CC)Ldk/brics/automaton/Automaton;
    2753: invokestatic  #84                 // Method put:(Ljava/util/Map;Ljava/lang/String;Ldk/brics/automaton/Automaton;)V
    2756: getstatic     #8                  // Field automata:Ljava/util/Map;
    2759: ldc_w         #369                // String CJKSymbolsandPunctuation
    2762: sipush        12288
    2765: sipush        12351
    2768: invokestatic  #309                // Method dk/brics/automaton/Automaton.makeCharRange:(CC)Ldk/brics/automaton/Automaton;
    2771: invokestatic  #84                 // Method put:(Ljava/util/Map;Ljava/lang/String;Ldk/brics/automaton/Automaton;)V
    2774: getstatic     #8                  // Field automata:Ljava/util/Map;
    2777: ldc_w         #370                // String Hiragana
    2780: sipush        12352
    2783: sipush        12447
    2786: invokestatic  #309                // Method dk/brics/automaton/Automaton.makeCharRange:(CC)Ldk/brics/automaton/Automaton;
    2789: invokestatic  #84                 // Method put:(Ljava/util/Map;Ljava/lang/String;Ldk/brics/automaton/Automaton;)V
    2792: getstatic     #8                  // Field automata:Ljava/util/Map;
    2795: ldc_w         #371                // String Katakana
    2798: sipush        12448
    2801: sipush        12543
    2804: invokestatic  #309                // Method dk/brics/automaton/Automaton.makeCharRange:(CC)Ldk/brics/automaton/Automaton;
    2807: invokestatic  #84                 // Method put:(Ljava/util/Map;Ljava/lang/String;Ldk/brics/automaton/Automaton;)V
    2810: getstatic     #8                  // Field automata:Ljava/util/Map;
    2813: ldc_w         #372                // String Bopomofo
    2816: sipush        12544
    2819: sipush        12591
    2822: invokestatic  #309                // Method dk/brics/automaton/Automaton.makeCharRange:(CC)Ldk/brics/automaton/Automaton;
    2825: invokestatic  #84                 // Method put:(Ljava/util/Map;Ljava/lang/String;Ldk/brics/automaton/Automaton;)V
    2828: getstatic     #8                  // Field automata:Ljava/util/Map;
    2831: ldc_w         #373                // String HangulCompatibilityJamo
    2834: sipush        12592
    2837: sipush        12687
    2840: invokestatic  #309                // Method dk/brics/automaton/Automaton.makeCharRange:(CC)Ldk/brics/automaton/Automaton;
    2843: invokestatic  #84                 // Method put:(Ljava/util/Map;Ljava/lang/String;Ldk/brics/automaton/Automaton;)V
    2846: getstatic     #8                  // Field automata:Ljava/util/Map;
    2849: ldc_w         #374                // String Kanbun
    2852: sipush        12688
    2855: sipush        12703
    2858: invokestatic  #309                // Method dk/brics/automaton/Automaton.makeCharRange:(CC)Ldk/brics/automaton/Automaton;
    2861: invokestatic  #84                 // Method put:(Ljava/util/Map;Ljava/lang/String;Ldk/brics/automaton/Automaton;)V
    2864: getstatic     #8                  // Field automata:Ljava/util/Map;
    2867: ldc_w         #375                // String BopomofoExtended
    2870: sipush        12704
    2873: sipush        12735
    2876: invokestatic  #309                // Method dk/brics/automaton/Automaton.makeCharRange:(CC)Ldk/brics/automaton/Automaton;
    2879: invokestatic  #84                 // Method put:(Ljava/util/Map;Ljava/lang/String;Ldk/brics/automaton/Automaton;)V
    2882: getstatic     #8                  // Field automata:Ljava/util/Map;
    2885: ldc_w         #376                // String EnclosedCJKLettersandMonths
    2888: sipush        12800
    2891: sipush        13055
    2894: invokestatic  #309                // Method dk/brics/automaton/Automaton.makeCharRange:(CC)Ldk/brics/automaton/Automaton;
    2897: invokestatic  #84                 // Method put:(Ljava/util/Map;Ljava/lang/String;Ldk/brics/automaton/Automaton;)V
    2900: getstatic     #8                  // Field automata:Ljava/util/Map;
    2903: ldc_w         #377                // String CJKCompatibility
    2906: sipush        13056
    2909: sipush        13311
    2912: invokestatic  #309                // Method dk/brics/automaton/Automaton.makeCharRange:(CC)Ldk/brics/automaton/Automaton;
    2915: invokestatic  #84                 // Method put:(Ljava/util/Map;Ljava/lang/String;Ldk/brics/automaton/Automaton;)V
    2918: getstatic     #8                  // Field automata:Ljava/util/Map;
    2921: ldc_w         #378                // String CJKUnifiedIdeographsExtensionA
    2924: sipush        13312
    2927: sipush        19893
    2930: invokestatic  #309                // Method dk/brics/automaton/Automaton.makeCharRange:(CC)Ldk/brics/automaton/Automaton;
    2933: invokestatic  #84                 // Method put:(Ljava/util/Map;Ljava/lang/String;Ldk/brics/automaton/Automaton;)V
    2936: getstatic     #8                  // Field automata:Ljava/util/Map;
    2939: ldc_w         #379                // String CJKUnifiedIdeographs
    2942: sipush        19968
    2945: ldc_w         #380                // int 40959
    2948: invokestatic  #309                // Method dk/brics/automaton/Automaton.makeCharRange:(CC)Ldk/brics/automaton/Automaton;
    2951: invokestatic  #84                 // Method put:(Ljava/util/Map;Ljava/lang/String;Ldk/brics/automaton/Automaton;)V
    2954: getstatic     #8                  // Field automata:Ljava/util/Map;
    2957: ldc_w         #381                // String YiSyllables
    2960: ldc_w         #382                // int 40960
    2963: ldc_w         #383                // int 42127
    2966: invokestatic  #309                // Method dk/brics/automaton/Automaton.makeCharRange:(CC)Ldk/brics/automaton/Automaton;
    2969: invokestatic  #84                 // Method put:(Ljava/util/Map;Ljava/lang/String;Ldk/brics/automaton/Automaton;)V
    2972: getstatic     #8                  // Field automata:Ljava/util/Map;
    2975: ldc_w         #384                // String YiRadicals
    2978: ldc_w         #385                // int 42128
    2981: ldc_w         #386                // int 42191
    2984: invokestatic  #309                // Method dk/brics/automaton/Automaton.makeCharRange:(CC)Ldk/brics/automaton/Automaton;
    2987: invokestatic  #84                 // Method put:(Ljava/util/Map;Ljava/lang/String;Ldk/brics/automaton/Automaton;)V
    2990: getstatic     #8                  // Field automata:Ljava/util/Map;
    2993: ldc_w         #387                // String HangulSyllables
    2996: ldc_w         #388                // int 44032
    2999: ldc_w         #389                // int 55203
    3002: invokestatic  #309                // Method dk/brics/automaton/Automaton.makeCharRange:(CC)Ldk/brics/automaton/Automaton;
    3005: invokestatic  #84                 // Method put:(Ljava/util/Map;Ljava/lang/String;Ldk/brics/automaton/Automaton;)V
    3008: getstatic     #8                  // Field automata:Ljava/util/Map;
    3011: ldc_w         #390                // String CJKCompatibilityIdeographs
    3014: ldc_w         #391                // int 63744
    3017: ldc_w         #392                // int 64255
    3020: invokestatic  #309                // Method dk/brics/automaton/Automaton.makeCharRange:(CC)Ldk/brics/automaton/Automaton;
    3023: invokestatic  #84                 // Method put:(Ljava/util/Map;Ljava/lang/String;Ldk/brics/automaton/Automaton;)V
    3026: getstatic     #8                  // Field automata:Ljava/util/Map;
    3029: ldc_w         #393                // String AlphabeticPresentationForms
    3032: ldc_w         #394                // int 64256
    3035: ldc_w         #395                // int 64335
    3038: invokestatic  #309                // Method dk/brics/automaton/Automaton.makeCharRange:(CC)Ldk/brics/automaton/Automaton;
    3041: invokestatic  #84                 // Method put:(Ljava/util/Map;Ljava/lang/String;Ldk/brics/automaton/Automaton;)V
    3044: getstatic     #8                  // Field automata:Ljava/util/Map;
    3047: ldc_w         #396                // String ArabicPresentationForms-A
    3050: ldc_w         #397                // int 64336
    3053: ldc_w         #398                // int 65023
    3056: invokestatic  #309                // Method dk/brics/automaton/Automaton.makeCharRange:(CC)Ldk/brics/automaton/Automaton;
    3059: invokestatic  #84                 // Method put:(Ljava/util/Map;Ljava/lang/String;Ldk/brics/automaton/Automaton;)V
    3062: getstatic     #8                  // Field automata:Ljava/util/Map;
    3065: ldc_w         #399                // String CombiningHalfMarks
    3068: ldc_w         #400                // int 65056
    3071: ldc_w         #401                // int 65071
    3074: invokestatic  #309                // Method dk/brics/automaton/Automaton.makeCharRange:(CC)Ldk/brics/automaton/Automaton;
    3077: invokestatic  #84                 // Method put:(Ljava/util/Map;Ljava/lang/String;Ldk/brics/automaton/Automaton;)V
    3080: getstatic     #8                  // Field automata:Ljava/util/Map;
    3083: ldc_w         #402                // String CJKCompatibilityForms
    3086: ldc_w         #403                // int 65072
    3089: ldc_w         #404                // int 65103
    3092: invokestatic  #309                // Method dk/brics/automaton/Automaton.makeCharRange:(CC)Ldk/brics/automaton/Automaton;
    3095: invokestatic  #84                 // Method put:(Ljava/util/Map;Ljava/lang/String;Ldk/brics/automaton/Automaton;)V
    3098: getstatic     #8                  // Field automata:Ljava/util/Map;
    3101: ldc_w         #405                // String SmallFormVariants
    3104: ldc_w         #406                // int 65104
    3107: ldc_w         #407                // int 65135
    3110: invokestatic  #309                // Method dk/brics/automaton/Automaton.makeCharRange:(CC)Ldk/brics/automaton/Automaton;
    3113: invokestatic  #84                 // Method put:(Ljava/util/Map;Ljava/lang/String;Ldk/brics/automaton/Automaton;)V
    3116: getstatic     #8                  // Field automata:Ljava/util/Map;
    3119: ldc_w         #408                // String ArabicPresentationForms-B
    3122: ldc_w         #409                // int 65136
    3125: ldc_w         #410                // int 65278
    3128: invokestatic  #309                // Method dk/brics/automaton/Automaton.makeCharRange:(CC)Ldk/brics/automaton/Automaton;
    3131: invokestatic  #84                 // Method put:(Ljava/util/Map;Ljava/lang/String;Ldk/brics/automaton/Automaton;)V
    3134: getstatic     #8                  // Field automata:Ljava/util/Map;
    3137: ldc_w         #411                // String Specials
    3140: ldc_w         #412                // int 65279
    3143: ldc_w         #412                // int 65279
    3146: invokestatic  #309                // Method dk/brics/automaton/Automaton.makeCharRange:(CC)Ldk/brics/automaton/Automaton;
    3149: invokestatic  #84                 // Method put:(Ljava/util/Map;Ljava/lang/String;Ldk/brics/automaton/Automaton;)V
    3152: getstatic     #8                  // Field automata:Ljava/util/Map;
    3155: ldc_w         #413                // String HalfwidthandFullwidthForms
    3158: ldc_w         #414                // int 65280
    3161: ldc_w         #415                // int 65519
    3164: invokestatic  #309                // Method dk/brics/automaton/Automaton.makeCharRange:(CC)Ldk/brics/automaton/Automaton;
    3167: invokestatic  #84                 // Method put:(Ljava/util/Map;Ljava/lang/String;Ldk/brics/automaton/Automaton;)V
    3170: getstatic     #8                  // Field automata:Ljava/util/Map;
    3173: ldc_w         #411                // String Specials
    3176: ldc_w         #416                // int 65520
    3179: ldc_w         #417                // int 65533
    3182: invokestatic  #309                // Method dk/brics/automaton/Automaton.makeCharRange:(CC)Ldk/brics/automaton/Automaton;
    3185: invokestatic  #84                 // Method put:(Ljava/util/Map;Ljava/lang/String;Ldk/brics/automaton/Automaton;)V
    3188: getstatic     #8                  // Field automata:Ljava/util/Map;
    3191: ldc_w         #418                // String OldItalic
    3194: ldc_w         #419                // int 55296
    3197: invokestatic  #170                // Method dk/brics/automaton/Automaton.makeChar:(C)Ldk/brics/automaton/Automaton;
    3200: ldc_w         #420                // int 57088
    3203: ldc_w         #421                // int 57135
    3206: invokestatic  #309                // Method dk/brics/automaton/Automaton.makeCharRange:(CC)Ldk/brics/automaton/Automaton;
    3209: invokevirtual #172                // Method dk/brics/automaton/Automaton.concatenate:(Ldk/brics/automaton/Automaton;)Ldk/brics/automaton/Automaton;
    3212: invokestatic  #84                 // Method put:(Ljava/util/Map;Ljava/lang/String;Ldk/brics/automaton/Automaton;)V
    3215: getstatic     #8                  // Field automata:Ljava/util/Map;
    3218: ldc_w         #422                // String Gothic
    3221: ldc_w         #419                // int 55296
    3224: invokestatic  #170                // Method dk/brics/automaton/Automaton.makeChar:(C)Ldk/brics/automaton/Automaton;
    3227: ldc_w         #423                // int 57136
    3230: ldc_w         #424                // int 57167
    3233: invokestatic  #309                // Method dk/brics/automaton/Automaton.makeCharRange:(CC)Ldk/brics/automaton/Automaton;
    3236: invokevirtual #172                // Method dk/brics/automaton/Automaton.concatenate:(Ldk/brics/automaton/Automaton;)Ldk/brics/automaton/Automaton;
    3239: invokestatic  #84                 // Method put:(Ljava/util/Map;Ljava/lang/String;Ldk/brics/automaton/Automaton;)V
    3242: getstatic     #8                  // Field automata:Ljava/util/Map;
    3245: ldc_w         #425                // String Deseret
    3248: ldc_w         #426                // int 55297
    3251: invokestatic  #170                // Method dk/brics/automaton/Automaton.makeChar:(C)Ldk/brics/automaton/Automaton;
    3254: ldc_w         #427                // int 56320
    3257: ldc_w         #428                // int 56399
    3260: invokestatic  #309                // Method dk/brics/automaton/Automaton.makeCharRange:(CC)Ldk/brics/automaton/Automaton;
    3263: invokevirtual #172                // Method dk/brics/automaton/Automaton.concatenate:(Ldk/brics/automaton/Automaton;)Ldk/brics/automaton/Automaton;
    3266: invokestatic  #84                 // Method put:(Ljava/util/Map;Ljava/lang/String;Ldk/brics/automaton/Automaton;)V
    3269: getstatic     #8                  // Field automata:Ljava/util/Map;
    3272: ldc_w         #429                // String ByzantineMusicalSymbols
    3275: ldc_w         #430                // int 55348
    3278: invokestatic  #170                // Method dk/brics/automaton/Automaton.makeChar:(C)Ldk/brics/automaton/Automaton;
    3281: ldc_w         #427                // int 56320
    3284: ldc_w         #431                // int 56575
    3287: invokestatic  #309                // Method dk/brics/automaton/Automaton.makeCharRange:(CC)Ldk/brics/automaton/Automaton;
    3290: invokevirtual #172                // Method dk/brics/automaton/Automaton.concatenate:(Ldk/brics/automaton/Automaton;)Ldk/brics/automaton/Automaton;
    3293: invokestatic  #84                 // Method put:(Ljava/util/Map;Ljava/lang/String;Ldk/brics/automaton/Automaton;)V
    3296: getstatic     #8                  // Field automata:Ljava/util/Map;
    3299: ldc_w         #432                // String MusicalSymbols
    3302: ldc_w         #430                // int 55348
    3305: invokestatic  #170                // Method dk/brics/automaton/Automaton.makeChar:(C)Ldk/brics/automaton/Automaton;
    3308: ldc_w         #433                // int 56576
    3311: ldc_w         #434                // int 56831
    3314: invokestatic  #309                // Method dk/brics/automaton/Automaton.makeCharRange:(CC)Ldk/brics/automaton/Automaton;
    3317: invokevirtual #172                // Method dk/brics/automaton/Automaton.concatenate:(Ldk/brics/automaton/Automaton;)Ldk/brics/automaton/Automaton;
    3320: invokestatic  #84                 // Method put:(Ljava/util/Map;Ljava/lang/String;Ldk/brics/automaton/Automaton;)V
    3323: getstatic     #8                  // Field automata:Ljava/util/Map;
    3326: ldc_w         #435                // String MathematicalAlphanumericSymbols
    3329: ldc_w         #436                // int 55349
    3332: invokestatic  #170                // Method dk/brics/automaton/Automaton.makeChar:(C)Ldk/brics/automaton/Automaton;
    3335: ldc_w         #427                // int 56320
    3338: ldc_w         #437                // int 57343
    3341: invokestatic  #309                // Method dk/brics/automaton/Automaton.makeCharRange:(CC)Ldk/brics/automaton/Automaton;
    3344: invokevirtual #172                // Method dk/brics/automaton/Automaton.concatenate:(Ldk/brics/automaton/Automaton;)Ldk/brics/automaton/Automaton;
    3347: invokestatic  #84                 // Method put:(Ljava/util/Map;Ljava/lang/String;Ldk/brics/automaton/Automaton;)V
    3350: getstatic     #8                  // Field automata:Ljava/util/Map;
    3353: ldc_w         #438                // String CJKUnifiedIdeographsExtensionB
    3356: ldc_w         #439                // int 55360
    3359: ldc_w         #440                // int 55400
    3362: invokestatic  #309                // Method dk/brics/automaton/Automaton.makeCharRange:(CC)Ldk/brics/automaton/Automaton;
    3365: ldc_w         #427                // int 56320
    3368: ldc_w         #437                // int 57343
    3371: invokestatic  #309                // Method dk/brics/automaton/Automaton.makeCharRange:(CC)Ldk/brics/automaton/Automaton;
    3374: invokevirtual #172                // Method dk/brics/automaton/Automaton.concatenate:(Ldk/brics/automaton/Automaton;)Ldk/brics/automaton/Automaton;
    3377: ldc_w         #441                // int 55401
    3380: invokestatic  #170                // Method dk/brics/automaton/Automaton.makeChar:(C)Ldk/brics/automaton/Automaton;
    3383: ldc_w         #427                // int 56320
    3386: ldc_w         #442                // int 57046
    3389: invokestatic  #309                // Method dk/brics/automaton/Automaton.makeCharRange:(CC)Ldk/brics/automaton/Automaton;
    3392: invokevirtual #172                // Method dk/brics/automaton/Automaton.concatenate:(Ldk/brics/automaton/Automaton;)Ldk/brics/automaton/Automaton;
    3395: invokevirtual #443                // Method dk/brics/automaton/Automaton.union:(Ldk/brics/automaton/Automaton;)Ldk/brics/automaton/Automaton;
    3398: invokestatic  #84                 // Method put:(Ljava/util/Map;Ljava/lang/String;Ldk/brics/automaton/Automaton;)V
    3401: getstatic     #8                  // Field automata:Ljava/util/Map;
    3404: ldc_w         #444                // String CJKCompatibilityIdeographsSupplement
    3407: ldc_w         #445                // int 55422
    3410: invokestatic  #170                // Method dk/brics/automaton/Automaton.makeChar:(C)Ldk/brics/automaton/Automaton;
    3413: ldc_w         #427                // int 56320
    3416: ldc_w         #446                // int 56863
    3419: invokestatic  #309                // Method dk/brics/automaton/Automaton.makeCharRange:(CC)Ldk/brics/automaton/Automaton;
    3422: invokevirtual #172                // Method dk/brics/automaton/Automaton.concatenate:(Ldk/brics/automaton/Automaton;)Ldk/brics/automaton/Automaton;
    3425: invokestatic  #84                 // Method put:(Ljava/util/Map;Ljava/lang/String;Ldk/brics/automaton/Automaton;)V
    3428: getstatic     #8                  // Field automata:Ljava/util/Map;
    3431: ldc_w         #447                // String Tags
    3434: ldc_w         #448                // int 56128
    3437: invokestatic  #170                // Method dk/brics/automaton/Automaton.makeChar:(C)Ldk/brics/automaton/Automaton;
    3440: ldc_w         #427                // int 56320
    3443: ldc_w         #449                // int 56447
    3446: invokestatic  #309                // Method dk/brics/automaton/Automaton.makeCharRange:(CC)Ldk/brics/automaton/Automaton;
    3449: invokevirtual #172                // Method dk/brics/automaton/Automaton.concatenate:(Ldk/brics/automaton/Automaton;)Ldk/brics/automaton/Automaton;
    3452: invokestatic  #84                 // Method put:(Ljava/util/Map;Ljava/lang/String;Ldk/brics/automaton/Automaton;)V
    3455: getstatic     #8                  // Field automata:Ljava/util/Map;
    3458: ldc_w         #450                // String PrivateUse
    3461: ldc_w         #451                // int 57344
    3464: ldc_w         #452                // int 63743
    3467: invokestatic  #309                // Method dk/brics/automaton/Automaton.makeCharRange:(CC)Ldk/brics/automaton/Automaton;
    3470: ldc_w         #453                // int 56192
    3473: ldc_w         #454                // int 56254
    3476: invokestatic  #309                // Method dk/brics/automaton/Automaton.makeCharRange:(CC)Ldk/brics/automaton/Automaton;
    3479: ldc_w         #427                // int 56320
    3482: ldc_w         #437                // int 57343
    3485: invokestatic  #309                // Method dk/brics/automaton/Automaton.makeCharRange:(CC)Ldk/brics/automaton/Automaton;
    3488: invokevirtual #172                // Method dk/brics/automaton/Automaton.concatenate:(Ldk/brics/automaton/Automaton;)Ldk/brics/automaton/Automaton;
    3491: ldc_w         #455                // int 56255
    3494: invokestatic  #170                // Method dk/brics/automaton/Automaton.makeChar:(C)Ldk/brics/automaton/Automaton;
    3497: ldc_w         #427                // int 56320
    3500: ldc_w         #456                // int 57341
    3503: invokestatic  #309                // Method dk/brics/automaton/Automaton.makeCharRange:(CC)Ldk/brics/automaton/Automaton;
    3506: invokevirtual #172                // Method dk/brics/automaton/Automaton.concatenate:(Ldk/brics/automaton/Automaton;)Ldk/brics/automaton/Automaton;
    3509: invokevirtual #443                // Method dk/brics/automaton/Automaton.union:(Ldk/brics/automaton/Automaton;)Ldk/brics/automaton/Automaton;
    3512: invokevirtual #443                // Method dk/brics/automaton/Automaton.union:(Ldk/brics/automaton/Automaton;)Ldk/brics/automaton/Automaton;
    3515: ldc_w         #457                // int 56256
    3518: ldc_w         #458                // int 56318
    3521: invokestatic  #309                // Method dk/brics/automaton/Automaton.makeCharRange:(CC)Ldk/brics/automaton/Automaton;
    3524: ldc_w         #427                // int 56320
    3527: ldc_w         #437                // int 57343
    3530: invokestatic  #309                // Method dk/brics/automaton/Automaton.makeCharRange:(CC)Ldk/brics/automaton/Automaton;
    3533: invokevirtual #172                // Method dk/brics/automaton/Automaton.concatenate:(Ldk/brics/automaton/Automaton;)Ldk/brics/automaton/Automaton;
    3536: ldc_w         #459                // int 56319
    3539: invokestatic  #170                // Method dk/brics/automaton/Automaton.makeChar:(C)Ldk/brics/automaton/Automaton;
    3542: ldc_w         #427                // int 56320
    3545: ldc_w         #456                // int 57341
    3548: invokestatic  #309                // Method dk/brics/automaton/Automaton.makeCharRange:(CC)Ldk/brics/automaton/Automaton;
    3551: invokevirtual #172                // Method dk/brics/automaton/Automaton.concatenate:(Ldk/brics/automaton/Automaton;)Ldk/brics/automaton/Automaton;
    3554: invokevirtual #443                // Method dk/brics/automaton/Automaton.union:(Ldk/brics/automaton/Automaton;)Ldk/brics/automaton/Automaton;
    3557: invokevirtual #443                // Method dk/brics/automaton/Automaton.union:(Ldk/brics/automaton/Automaton;)Ldk/brics/automaton/Automaton;
    3560: invokestatic  #84                 // Method put:(Ljava/util/Map;Ljava/lang/String;Ldk/brics/automaton/Automaton;)V
    3563: getstatic     #5                  // Field java/lang/System.out:Ljava/io/PrintStream;
    3566: ldc_w         #460                // String Building Unicode category automata...
    3569: invokevirtual #7                  // Method java/io/PrintStream.println:(Ljava/lang/String;)V
    3572: new           #272                // class java/util/HashMap
    3575: dup
    3576: invokespecial #273                // Method java/util/HashMap."<init>":()V
    3579: astore        8
    3581: new           #461                // class java/io/StreamTokenizer
    3584: dup
    3585: new           #462                // class java/io/BufferedReader
    3588: dup
    3589: new           #463                // class java/io/FileReader
    3592: dup
    3593: ldc_w         #464                // String src/Unicode.txt
    3596: invokespecial #465                // Method java/io/FileReader."<init>":(Ljava/lang/String;)V
    3599: invokespecial #466                // Method java/io/BufferedReader."<init>":(Ljava/io/Reader;)V
    3602: invokespecial #467                // Method java/io/StreamTokenizer."<init>":(Ljava/io/Reader;)V
    3605: astore        9
    3607: aload         9
    3609: invokevirtual #468                // Method java/io/StreamTokenizer.resetSyntax:()V
    3612: aload         9
    3614: bipush        59
    3616: bipush        59
    3618: invokevirtual #469                // Method java/io/StreamTokenizer.whitespaceChars:(II)V
    3621: aload         9
    3623: bipush        10
    3625: bipush        32
    3627: invokevirtual #469                // Method java/io/StreamTokenizer.whitespaceChars:(II)V
    3630: aload         9
    3632: bipush        48
    3634: bipush        57
    3636: invokevirtual #470                // Method java/io/StreamTokenizer.wordChars:(II)V
    3639: aload         9
    3641: bipush        97
    3643: bipush        122
    3645: invokevirtual #470                // Method java/io/StreamTokenizer.wordChars:(II)V
    3648: aload         9
    3650: bipush        65
    3652: bipush        90
    3654: invokevirtual #470                // Method java/io/StreamTokenizer.wordChars:(II)V
    3657: aload         9
    3659: invokevirtual #471                // Method java/io/StreamTokenizer.nextToken:()I
    3662: iconst_m1
    3663: if_icmpeq     3809
    3666: aload         9
    3668: getfield      #472                // Field java/io/StreamTokenizer.sval:Ljava/lang/String;
    3671: bipush        16
    3673: invokestatic  #473                // Method java/lang/Integer.parseInt:(Ljava/lang/String;I)I
    3676: istore        10
    3678: aload         9
    3680: invokevirtual #471                // Method java/io/StreamTokenizer.nextToken:()I
    3683: pop
    3684: aload         9
    3686: getfield      #472                // Field java/io/StreamTokenizer.sval:Ljava/lang/String;
    3689: astore        11
    3691: aload         8
    3693: aload         11
    3695: invokeinterface #26,  2           // InterfaceMethod java/util/Map.get:(Ljava/lang/Object;)Ljava/lang/Object;
    3700: checkcast     #474                // class java/util/Set
    3703: astore        12
    3705: aload         12
    3707: ifnonnull     3731
    3710: new           #475                // class java/util/TreeSet
    3713: dup
    3714: invokespecial #476                // Method java/util/TreeSet."<init>":()V
    3717: astore        12
    3719: aload         8
    3721: aload         11
    3723: aload         12
    3725: invokeinterface #28,  3           // InterfaceMethod java/util/Map.put:(Ljava/lang/Object;Ljava/lang/Object;)Ljava/lang/Object;
    3730: pop
    3731: aload         12
    3733: iload         10
    3735: invokestatic  #477                // Method java/lang/Integer.valueOf:(I)Ljava/lang/Integer;
    3738: invokeinterface #478,  2          // InterfaceMethod java/util/Set.add:(Ljava/lang/Object;)Z
    3743: pop
    3744: aload         11
    3746: iconst_0
    3747: iconst_1
    3748: invokevirtual #479                // Method java/lang/String.substring:(II)Ljava/lang/String;
    3751: astore        13
    3753: aload         8
    3755: aload         13
    3757: invokeinterface #26,  2           // InterfaceMethod java/util/Map.get:(Ljava/lang/Object;)Ljava/lang/Object;
    3762: checkcast     #474                // class java/util/Set
    3765: astore        12
    3767: aload         12
    3769: ifnonnull     3793
    3772: new           #475                // class java/util/TreeSet
    3775: dup
    3776: invokespecial #476                // Method java/util/TreeSet."<init>":()V
    3779: astore        12
    3781: aload         8
    3783: aload         13
    3785: aload         12
    3787: invokeinterface #28,  3           // InterfaceMethod java/util/Map.put:(Ljava/lang/Object;Ljava/lang/Object;)Ljava/lang/Object;
    3792: pop
    3793: aload         12
    3795: iload         10
    3797: invokestatic  #477                // Method java/lang/Integer.valueOf:(I)Ljava/lang/Integer;
    3800: invokeinterface #478,  2          // InterfaceMethod java/util/Set.add:(Ljava/lang/Object;)Z
    3805: pop
    3806: goto          3657
    3809: goto          3823
    3812: astore        9
    3814: aload         9
    3816: invokevirtual #41                 // Method java/io/IOException.printStackTrace:()V
    3819: iconst_m1
    3820: invokestatic  #480                // Method java/lang/System.exit:(I)V
    3823: new           #481                // class java/util/ArrayList
    3826: dup
    3827: invokespecial #482                // Method java/util/ArrayList."<init>":()V
    3830: astore        9
    3832: aload         8
    3834: invokeinterface #9,  1            // InterfaceMethod java/util/Map.entrySet:()Ljava/util/Set;
    3839: invokeinterface #10,  1           // InterfaceMethod java/util/Set.iterator:()Ljava/util/Iterator;
    3844: astore        10
    3846: aload         10
    3848: invokeinterface #11,  1           // InterfaceMethod java/util/Iterator.hasNext:()Z
    3853: ifeq          4033
    3856: aload         10
    3858: invokeinterface #12,  1           // InterfaceMethod java/util/Iterator.next:()Ljava/lang/Object;
    3863: checkcast     #13                 // class java/util/Map$Entry
    3866: astore        11
    3868: new           #481                // class java/util/ArrayList
    3871: dup
    3872: invokespecial #482                // Method java/util/ArrayList."<init>":()V
    3875: astore        12
    3877: new           #481                // class java/util/ArrayList
    3880: dup
    3881: invokespecial #482                // Method java/util/ArrayList."<init>":()V
    3884: astore        13
    3886: aload         11
    3888: invokeinterface #16,  1           // InterfaceMethod java/util/Map$Entry.getValue:()Ljava/lang/Object;
    3893: checkcast     #474                // class java/util/Set
    3896: invokeinterface #10,  1           // InterfaceMethod java/util/Set.iterator:()Ljava/util/Iterator;
    3901: astore        14
    3903: aload         14
    3905: invokeinterface #11,  1           // InterfaceMethod java/util/Iterator.hasNext:()Z
    3910: ifeq          3979
    3913: aload         14
    3915: invokeinterface #12,  1           // InterfaceMethod java/util/Iterator.next:()Ljava/lang/Object;
    3920: checkcast     #483                // class java/lang/Integer
    3923: astore        15
    3925: aload         12
    3927: aload         15
    3929: invokevirtual #484                // Method java/lang/Integer.intValue:()I
    3932: invokestatic  #485                // Method makeCodePoint:(I)Ldk/brics/automaton/Automaton;
    3935: invokeinterface #486,  2          // InterfaceMethod java/util/List.add:(Ljava/lang/Object;)Z
    3940: pop
    3941: aload         12
    3943: invokeinterface #487,  1          // InterfaceMethod java/util/List.size:()I
    3948: bipush        50
    3950: if_icmpne     3976
    3953: aload         13
    3955: aload         12
    3957: invokestatic  #488                // Method dk/brics/automaton/Automaton.union:(Ljava/util/Collection;)Ldk/brics/automaton/Automaton;
    3960: invokestatic  #174                // Method dk/brics/automaton/Automaton.minimize:(Ldk/brics/automaton/Automaton;)Ldk/brics/automaton/Automaton;
    3963: invokeinterface #486,  2          // InterfaceMethod java/util/List.add:(Ljava/lang/Object;)Z
    3968: pop
    3969: aload         12
    3971: invokeinterface #489,  1          // InterfaceMethod java/util/List.clear:()V
    3976: goto          3903
    3979: aload         13
    3981: aload         12
    3983: invokestatic  #488                // Method dk/brics/automaton/Automaton.union:(Ljava/util/Collection;)Ldk/brics/automaton/Automaton;
    3986: invokeinterface #486,  2          // InterfaceMethod java/util/List.add:(Ljava/lang/Object;)Z
    3991: pop
    3992: aload         13
    3994: invokestatic  #488                // Method dk/brics/automaton/Automaton.union:(Ljava/util/Collection;)Ldk/brics/automaton/Automaton;
    3997: invokestatic  #174                // Method dk/brics/automaton/Automaton.minimize:(Ldk/brics/automaton/Automaton;)Ldk/brics/automaton/Automaton;
    4000: astore        14
    4002: getstatic     #8                  // Field automata:Ljava/util/Map;
    4005: aload         11
    4007: invokeinterface #14,  1           // InterfaceMethod java/util/Map$Entry.getKey:()Ljava/lang/Object;
    4012: checkcast     #15                 // class java/lang/String
    4015: aload         14
    4017: invokestatic  #84                 // Method put:(Ljava/util/Map;Ljava/lang/String;Ldk/brics/automaton/Automaton;)V
    4020: aload         9
    4022: aload         14
    4024: invokeinterface #486,  2          // InterfaceMethod java/util/List.add:(Ljava/lang/Object;)Z
    4029: pop
    4030: goto          3846
    4033: getstatic     #8                  // Field automata:Ljava/util/Map;
    4036: ldc           #75                 // String Char
    4038: invokeinterface #26,  2           // InterfaceMethod java/util/Map.get:(Ljava/lang/Object;)Ljava/lang/Object;
    4043: checkcast     #17                 // class dk/brics/automaton/Automaton
    4046: invokevirtual #171                // Method dk/brics/automaton/Automaton.clone:()Ldk/brics/automaton/Automaton;
    4049: aload         9
    4051: invokestatic  #488                // Method dk/brics/automaton/Automaton.union:(Ljava/util/Collection;)Ldk/brics/automaton/Automaton;
    4054: invokevirtual #490                // Method dk/brics/automaton/Automaton.complement:()Ldk/brics/automaton/Automaton;
    4057: invokevirtual #491                // Method dk/brics/automaton/Automaton.intersection:(Ldk/brics/automaton/Automaton;)Ldk/brics/automaton/Automaton;
    4060: invokestatic  #174                // Method dk/brics/automaton/Automaton.minimize:(Ldk/brics/automaton/Automaton;)Ldk/brics/automaton/Automaton;
    4063: astore        10
    4065: getstatic     #8                  // Field automata:Ljava/util/Map;
    4068: ldc_w         #492                // String Cn
    4071: aload         10
    4073: invokestatic  #84                 // Method put:(Ljava/util/Map;Ljava/lang/String;Ldk/brics/automaton/Automaton;)V
    4076: getstatic     #8                  // Field automata:Ljava/util/Map;
    4079: ldc_w         #493                // String C
    4082: getstatic     #8                  // Field automata:Ljava/util/Map;
    4085: ldc_w         #493                // String C
    4088: invokeinterface #26,  2           // InterfaceMethod java/util/Map.get:(Ljava/lang/Object;)Ljava/lang/Object;
    4093: checkcast     #17                 // class dk/brics/automaton/Automaton
    4096: invokevirtual #171                // Method dk/brics/automaton/Automaton.clone:()Ldk/brics/automaton/Automaton;
    4099: aload         10
    4101: invokevirtual #443                // Method dk/brics/automaton/Automaton.union:(Ldk/brics/automaton/Automaton;)Ldk/brics/automaton/Automaton;
    4104: invokestatic  #84                 // Method put:(Ljava/util/Map;Ljava/lang/String;Ldk/brics/automaton/Automaton;)V
    4107: return
    Exception table:
       from    to  target type
        3581  3809  3812   Class java/io/IOException

  private static dk.brics.automaton.Automaton makeCodePoint(int);
    Code:
       0: iload_0
       1: ldc_w         #494                // int 65536
       4: if_icmplt     54
       7: iload_0
       8: ldc_w         #494                // int 65536
      11: isub
      12: istore_0
      13: iconst_2
      14: newarray       char
      16: dup
      17: iconst_0
      18: ldc_w         #419                // int 55296
      21: iload_0
      22: bipush        10
      24: ishr
      25: iadd
      26: i2c
      27: castore
      28: dup
      29: iconst_1
      30: ldc_w         #427                // int 56320
      33: iload_0
      34: sipush        1023
      37: iand
      38: iadd
      39: i2c
      40: castore
      41: astore_1
      42: new           #15                 // class java/lang/String
      45: dup
      46: aload_1
      47: invokespecial #495                // Method java/lang/String."<init>":([C)V
      50: invokestatic  #496                // Method dk/brics/automaton/Automaton.makeString:(Ljava/lang/String;)Ldk/brics/automaton/Automaton;
      53: areturn
      54: iload_0
      55: i2c
      56: invokestatic  #170                // Method dk/brics/automaton/Automaton.makeChar:(C)Ldk/brics/automaton/Automaton;
      59: areturn

  private static java.util.Map<java.lang.String, dk.brics.automaton.Automaton> buildMap(java.lang.String[]);
    Code:
       0: new           #272                // class java/util/HashMap
       3: dup
       4: invokespecial #273                // Method java/util/HashMap."<init>":()V
       7: astore_1
       8: iconst_0
       9: istore_2
      10: iload_2
      11: iconst_1
      12: iadd
      13: aload_0
      14: arraylength
      15: if_icmpge     48
      18: aload_1
      19: aload_0
      20: iload_2
      21: iinc          2, 1
      24: aaload
      25: new           #176                // class dk/brics/automaton/RegExp
      28: dup
      29: aload_0
      30: iload_2
      31: iinc          2, 1
      34: aaload
      35: invokespecial #178                // Method dk/brics/automaton/RegExp."<init>":(Ljava/lang/String;)V
      38: aload_1
      39: invokevirtual #497                // Method dk/brics/automaton/RegExp.toAutomaton:(Ljava/util/Map;)Ldk/brics/automaton/Automaton;
      42: invokestatic  #84                 // Method put:(Ljava/util/Map;Ljava/lang/String;Ldk/brics/automaton/Automaton;)V
      45: goto          10
      48: aload_1
      49: areturn

  private static void putWith(java.lang.String[], java.util.Map<java.lang.String, dk.brics.automaton.Automaton>);
    Code:
       0: iconst_0
       1: istore_2
       2: iload_2
       3: iconst_1
       4: iadd
       5: aload_0
       6: arraylength
       7: if_icmpge     42
      10: getstatic     #8                  // Field automata:Ljava/util/Map;
      13: aload_0
      14: iload_2
      15: iinc          2, 1
      18: aaload
      19: new           #176                // class dk/brics/automaton/RegExp
      22: dup
      23: aload_0
      24: iload_2
      25: iinc          2, 1
      28: aaload
      29: invokespecial #178                // Method dk/brics/automaton/RegExp."<init>":(Ljava/lang/String;)V
      32: aload_1
      33: invokevirtual #497                // Method dk/brics/automaton/RegExp.toAutomaton:(Ljava/util/Map;)Ldk/brics/automaton/Automaton;
      36: invokestatic  #84                 // Method put:(Ljava/util/Map;Ljava/lang/String;Ldk/brics/automaton/Automaton;)V
      39: goto          2
      42: return

  private static void putFrom(java.lang.String, java.util.Map<java.lang.String, dk.brics.automaton.Automaton>);
    Code:
       0: getstatic     #8                  // Field automata:Ljava/util/Map;
       3: aload_0
       4: aload_1
       5: aload_0
       6: invokeinterface #26,  2           // InterfaceMethod java/util/Map.get:(Ljava/lang/Object;)Ljava/lang/Object;
      11: invokeinterface #28,  3           // InterfaceMethod java/util/Map.put:(Ljava/lang/Object;Ljava/lang/Object;)Ljava/lang/Object;
      16: pop
      17: return

  private static void put(java.util.Map<java.lang.String, dk.brics.automaton.Automaton>, java.lang.String, dk.brics.automaton.Automaton);
    Code:
       0: aload_0
       1: aload_1
       2: aload_2
       3: invokeinterface #28,  3           // InterfaceMethod java/util/Map.put:(Ljava/lang/Object;Ljava/lang/Object;)Ljava/lang/Object;
       8: pop
       9: getstatic     #5                  // Field java/lang/System.out:Ljava/io/PrintStream;
      12: new           #19                 // class java/lang/StringBuilder
      15: dup
      16: invokespecial #20                 // Method java/lang/StringBuilder."<init>":()V
      19: ldc_w         #498                // String
      22: invokevirtual #22                 // Method java/lang/StringBuilder.append:(Ljava/lang/String;)Ljava/lang/StringBuilder;
      25: aload_1
      26: invokevirtual #22                 // Method java/lang/StringBuilder.append:(Ljava/lang/String;)Ljava/lang/StringBuilder;
      29: ldc_w         #499                // String :
      32: invokevirtual #22                 // Method java/lang/StringBuilder.append:(Ljava/lang/String;)Ljava/lang/StringBuilder;
      35: aload_2
      36: invokevirtual #500                // Method dk/brics/automaton/Automaton.getNumberOfStates:()I
      39: invokevirtual #501                // Method java/lang/StringBuilder.append:(I)Ljava/lang/StringBuilder;
      42: ldc_w         #502                // String  states,
      45: invokevirtual #22                 // Method java/lang/StringBuilder.append:(Ljava/lang/String;)Ljava/lang/StringBuilder;
      48: aload_2
      49: invokevirtual #503                // Method dk/brics/automaton/Automaton.getNumberOfTransitions:()I
      52: invokevirtual #501                // Method java/lang/StringBuilder.append:(I)Ljava/lang/StringBuilder;
      55: ldc_w         #504                // String  transitions
      58: invokevirtual #22                 // Method java/lang/StringBuilder.append:(Ljava/lang/String;)Ljava/lang/StringBuilder;
      61: invokevirtual #25                 // Method java/lang/StringBuilder.toString:()Ljava/lang/String;
      64: invokevirtual #7                  // Method java/io/PrintStream.println:(Ljava/lang/String;)V
      67: return

  static dk.brics.automaton.Automaton getWhitespaceAutomaton();
    Code:
       0: getstatic     #83                 // Field ws:Ldk/brics/automaton/Automaton;
       3: areturn

  static {};
    Code:
       0: bipush        93
       2: anewarray     #15                 // class java/lang/String
       5: dup
       6: iconst_0
       7: ldc_w         #308                // String BasicLatin
      10: aastore
      11: dup
      12: iconst_1
      13: ldc_w         #310                // String Latin-1Supplement
      16: aastore
      17: dup
      18: iconst_2
      19: ldc_w         #311                // String LatinExtended-A
      22: aastore
      23: dup
      24: iconst_3
      25: ldc_w         #312                // String LatinExtended-B
      28: aastore
      29: dup
      30: iconst_4
      31: ldc_w         #313                // String IPAExtensions
      34: aastore
      35: dup
      36: iconst_5
      37: ldc_w         #314                // String SpacingModifierLetters
      40: aastore
      41: dup
      42: bipush        6
      44: ldc_w         #315                // String CombiningDiacriticalMarks
      47: aastore
      48: dup
      49: bipush        7
      51: ldc_w         #316                // String Greek
      54: aastore
      55: dup
      56: bipush        8
      58: ldc_w         #317                // String Cyrillic
      61: aastore
      62: dup
      63: bipush        9
      65: ldc_w         #318                // String Armenian
      68: aastore
      69: dup
      70: bipush        10
      72: ldc_w         #319                // String Hebrew
      75: aastore
      76: dup
      77: bipush        11
      79: ldc_w         #320                // String Arabic
      82: aastore
      83: dup
      84: bipush        12
      86: ldc_w         #321                // String Syriac
      89: aastore
      90: dup
      91: bipush        13
      93: ldc_w         #322                // String Thaana
      96: aastore
      97: dup
      98: bipush        14
     100: ldc_w         #323                // String Devanagari
     103: aastore
     104: dup
     105: bipush        15
     107: ldc_w         #324                // String Bengali
     110: aastore
     111: dup
     112: bipush        16
     114: ldc_w         #325                // String Gurmukhi
     117: aastore
     118: dup
     119: bipush        17
     121: ldc_w         #326                // String Gujarati
     124: aastore
     125: dup
     126: bipush        18
     128: ldc_w         #327                // String Oriya
     131: aastore
     132: dup
     133: bipush        19
     135: ldc_w         #328                // String Tamil
     138: aastore
     139: dup
     140: bipush        20
     142: ldc_w         #329                // String Telugu
     145: aastore
     146: dup
     147: bipush        21
     149: ldc_w         #330                // String Kannada
     152: aastore
     153: dup
     154: bipush        22
     156: ldc_w         #331                // String Malayalam
     159: aastore
     160: dup
     161: bipush        23
     163: ldc_w         #332                // String Sinhala
     166: aastore
     167: dup
     168: bipush        24
     170: ldc_w         #333                // String Thai
     173: aastore
     174: dup
     175: bipush        25
     177: ldc_w         #334                // String Lao
     180: aastore
     181: dup
     182: bipush        26
     184: ldc_w         #335                // String Tibetan
     187: aastore
     188: dup
     189: bipush        27
     191: ldc_w         #336                // String Myanmar
     194: aastore
     195: dup
     196: bipush        28
     198: ldc_w         #337                // String Georgian
     201: aastore
     202: dup
     203: bipush        29
     205: ldc_w         #338                // String HangulJamo
     208: aastore
     209: dup
     210: bipush        30
     212: ldc_w         #339                // String Ethiopic
     215: aastore
     216: dup
     217: bipush        31
     219: ldc_w         #340                // String Cherokee
     222: aastore
     223: dup
     224: bipush        32
     226: ldc_w         #341                // String UnifiedCanadianAboriginalSyllabics
     229: aastore
     230: dup
     231: bipush        33
     233: ldc_w         #342                // String Ogham
     236: aastore
     237: dup
     238: bipush        34
     240: ldc_w         #343                // String Runic
     243: aastore
     244: dup
     245: bipush        35
     247: ldc_w         #344                // String Khmer
     250: aastore
     251: dup
     252: bipush        36
     254: ldc_w         #345                // String Mongolian
     257: aastore
     258: dup
     259: bipush        37
     261: ldc_w         #346                // String LatinExtendedAdditional
     264: aastore
     265: dup
     266: bipush        38
     268: ldc_w         #347                // String GreekExtended
     271: aastore
     272: dup
     273: bipush        39
     275: ldc_w         #348                // String GeneralPunctuation
     278: aastore
     279: dup
     280: bipush        40
     282: ldc_w         #349                // String SuperscriptsandSubscripts
     285: aastore
     286: dup
     287: bipush        41
     289: ldc_w         #350                // String CurrencySymbols
     292: aastore
     293: dup
     294: bipush        42
     296: ldc_w         #351                // String CombiningMarksforSymbols
     299: aastore
     300: dup
     301: bipush        43
     303: ldc_w         #352                // String LetterlikeSymbols
     306: aastore
     307: dup
     308: bipush        44
     310: ldc_w         #353                // String NumberForms
     313: aastore
     314: dup
     315: bipush        45
     317: ldc_w         #354                // String Arrows
     320: aastore
     321: dup
     322: bipush        46
     324: ldc_w         #355                // String MathematicalOperators
     327: aastore
     328: dup
     329: bipush        47
     331: ldc_w         #356                // String MiscellaneousTechnical
     334: aastore
     335: dup
     336: bipush        48
     338: ldc_w         #357                // String ControlPictures
     341: aastore
     342: dup
     343: bipush        49
     345: ldc_w         #358                // String OpticalCharacterRecognition
     348: aastore
     349: dup
     350: bipush        50
     352: ldc_w         #359                // String EnclosedAlphanumerics
     355: aastore
     356: dup
     357: bipush        51
     359: ldc_w         #360                // String BoxDrawing
     362: aastore
     363: dup
     364: bipush        52
     366: ldc_w         #361                // String BlockElements
     369: aastore
     370: dup
     371: bipush        53
     373: ldc_w         #362                // String GeometricShapes
     376: aastore
     377: dup
     378: bipush        54
     380: ldc_w         #363                // String MiscellaneousSymbols
     383: aastore
     384: dup
     385: bipush        55
     387: ldc_w         #364                // String Dingbats
     390: aastore
     391: dup
     392: bipush        56
     394: ldc_w         #365                // String BraillePatterns
     397: aastore
     398: dup
     399: bipush        57
     401: ldc_w         #366                // String CJKRadicalsSupplement
     404: aastore
     405: dup
     406: bipush        58
     408: ldc_w         #367                // String KangxiRadicals
     411: aastore
     412: dup
     413: bipush        59
     415: ldc_w         #368                // String IdeographicDescriptionCharacters
     418: aastore
     419: dup
     420: bipush        60
     422: ldc_w         #369                // String CJKSymbolsandPunctuation
     425: aastore
     426: dup
     427: bipush        61
     429: ldc_w         #370                // String Hiragana
     432: aastore
     433: dup
     434: bipush        62
     436: ldc_w         #371                // String Katakana
     439: aastore
     440: dup
     441: bipush        63
     443: ldc_w         #372                // String Bopomofo
     446: aastore
     447: dup
     448: bipush        64
     450: ldc_w         #373                // String HangulCompatibilityJamo
     453: aastore
     454: dup
     455: bipush        65
     457: ldc_w         #374                // String Kanbun
     460: aastore
     461: dup
     462: bipush        66
     464: ldc_w         #375                // String BopomofoExtended
     467: aastore
     468: dup
     469: bipush        67
     471: ldc_w         #376                // String EnclosedCJKLettersandMonths
     474: aastore
     475: dup
     476: bipush        68
     478: ldc_w         #377                // String CJKCompatibility
     481: aastore
     482: dup
     483: bipush        69
     485: ldc_w         #378                // String CJKUnifiedIdeographsExtensionA
     488: aastore
     489: dup
     490: bipush        70
     492: ldc_w         #379                // String CJKUnifiedIdeographs
     495: aastore
     496: dup
     497: bipush        71
     499: ldc_w         #381                // String YiSyllables
     502: aastore
     503: dup
     504: bipush        72
     506: ldc_w         #384                // String YiRadicals
     509: aastore
     510: dup
     511: bipush        73
     513: ldc_w         #387                // String HangulSyllables
     516: aastore
     517: dup
     518: bipush        74
     520: ldc_w         #390                // String CJKCompatibilityIdeographs
     523: aastore
     524: dup
     525: bipush        75
     527: ldc_w         #393                // String AlphabeticPresentationForms
     530: aastore
     531: dup
     532: bipush        76
     534: ldc_w         #396                // String ArabicPresentationForms-A
     537: aastore
     538: dup
     539: bipush        77
     541: ldc_w         #399                // String CombiningHalfMarks
     544: aastore
     545: dup
     546: bipush        78
     548: ldc_w         #402                // String CJKCompatibilityForms
     551: aastore
     552: dup
     553: bipush        79
     555: ldc_w         #405                // String SmallFormVariants
     558: aastore
     559: dup
     560: bipush        80
     562: ldc_w         #408                // String ArabicPresentationForms-B
     565: aastore
     566: dup
     567: bipush        81
     569: ldc_w         #411                // String Specials
     572: aastore
     573: dup
     574: bipush        82
     576: ldc_w         #413                // String HalfwidthandFullwidthForms
     579: aastore
     580: dup
     581: bipush        83
     583: ldc_w         #411                // String Specials
     586: aastore
     587: dup
     588: bipush        84
     590: ldc_w         #418                // String OldItalic
     593: aastore
     594: dup
     595: bipush        85
     597: ldc_w         #422                // String Gothic
     600: aastore
     601: dup
     602: bipush        86
     604: ldc_w         #425                // String Deseret
     607: aastore
     608: dup
     609: bipush        87
     611: ldc_w         #429                // String ByzantineMusicalSymbols
     614: aastore
     615: dup
     616: bipush        88
     618: ldc_w         #432                // String MusicalSymbols
     621: aastore
     622: dup
     623: bipush        89
     625: ldc_w         #435                // String MathematicalAlphanumericSymbols
     628: aastore
     629: dup
     630: bipush        90
     632: ldc_w         #438                // String CJKUnifiedIdeographsExtensionB
     635: aastore
     636: dup
     637: bipush        91
     639: ldc_w         #444                // String CJKCompatibilityIdeographsSupplement
     642: aastore
     643: dup
     644: bipush        92
     646: ldc_w         #447                // String Tags
     649: aastore
     650: putstatic     #505                // Field unicodeblock_names_array:[Ljava/lang/String;
     653: bipush        36
     655: anewarray     #15                 // class java/lang/String
     658: dup
     659: iconst_0
     660: ldc_w         #506                // String Lu
     663: aastore
     664: dup
     665: iconst_1
     666: ldc_w         #507                // String Ll
     669: aastore
     670: dup
     671: iconst_2
     672: ldc_w         #508                // String Lt
     675: aastore
     676: dup
     677: iconst_3
     678: ldc_w         #509                // String Lm
     681: aastore
     682: dup
     683: iconst_4
     684: ldc_w         #510                // String Lo
     687: aastore
     688: dup
     689: iconst_5
     690: ldc_w         #511                // String L
     693: aastore
     694: dup
     695: bipush        6
     697: ldc_w         #512                // String Mn
     700: aastore
     701: dup
     702: bipush        7
     704: ldc_w         #513                // String Mc
     707: aastore
     708: dup
     709: bipush        8
     711: ldc_w         #514                // String Me
     714: aastore
     715: dup
     716: bipush        9
     718: ldc           #187                // String M
     720: aastore
     721: dup
     722: bipush        10
     724: ldc_w         #515                // String Nd
     727: aastore
     728: dup
     729: bipush        11
     731: ldc_w         #516                // String Nl
     734: aastore
     735: dup
     736: bipush        12
     738: ldc_w         #517                // String No
     741: aastore
     742: dup
     743: bipush        13
     745: ldc_w         #518                // String N
     748: aastore
     749: dup
     750: bipush        14
     752: ldc_w         #519                // String Pc
     755: aastore
     756: dup
     757: bipush        15
     759: ldc_w         #520                // String Pd
     762: aastore
     763: dup
     764: bipush        16
     766: ldc_w         #521                // String Ps
     769: aastore
     770: dup
     771: bipush        17
     773: ldc_w         #522                // String Pe
     776: aastore
     777: dup
     778: bipush        18
     780: ldc_w         #523                // String Pi
     783: aastore
     784: dup
     785: bipush        19
     787: ldc_w         #524                // String Pf
     790: aastore
     791: dup
     792: bipush        20
     794: ldc_w         #525                // String Po
     797: aastore
     798: dup
     799: bipush        21
     801: ldc_w         #526                // String P
     804: aastore
     805: dup
     806: bipush        22
     808: ldc_w         #527                // String Zs
     811: aastore
     812: dup
     813: bipush        23
     815: ldc_w         #528                // String Zl
     818: aastore
     819: dup
     820: bipush        24
     822: ldc_w         #529                // String Zp
     825: aastore
     826: dup
     827: bipush        25
     829: ldc           #183                // String Z
     831: aastore
     832: dup
     833: bipush        26
     835: ldc_w         #530                // String Sm
     838: aastore
     839: dup
     840: bipush        27
     842: ldc_w         #531                // String Sc
     845: aastore
     846: dup
     847: bipush        28
     849: ldc_w         #532                // String Sk
     852: aastore
     853: dup
     854: bipush        29
     856: ldc_w         #533                // String So
     859: aastore
     860: dup
     861: bipush        30
     863: ldc_w         #534                // String S
     866: aastore
     867: dup
     868: bipush        31
     870: ldc_w         #535                // String Cc
     873: aastore
     874: dup
     875: bipush        32
     877: ldc_w         #536                // String Cf
     880: aastore
     881: dup
     882: bipush        33
     884: ldc_w         #537                // String Co
     887: aastore
     888: dup
     889: bipush        34
     891: ldc_w         #492                // String Cn
     894: aastore
     895: dup
     896: bipush        35
     898: ldc_w         #493                // String C
     901: aastore
     902: putstatic     #538                // Field unicodecategory_names_array:[Ljava/lang/String;
     905: bipush        32
     907: anewarray     #15                 // class java/lang/String
     910: dup
     911: iconst_0
     912: ldc           #69                 // String NCName
     914: aastore
     915: dup
     916: iconst_1
     917: ldc           #73                 // String QName
     919: aastore
     920: dup
     921: iconst_2
     922: ldc           #75                 // String Char
     924: aastore
     925: dup
     926: iconst_3
     927: ldc           #65                 // String NameChar
     929: aastore
     930: dup
     931: iconst_4
     932: ldc           #166                // String URI
     934: aastore
     935: dup
     936: iconst_5
     937: ldc           #169                // String anyname
     939: aastore
     940: dup
     941: bipush        6
     943: ldc           #175                // String noap
     945: aastore
     946: dup
     947: bipush        7
     949: ldc           #82                 // String whitespace
     951: aastore
     952: dup
     953: bipush        8
     955: ldc           #77                 // String whitespacechar
     957: aastore
     958: dup
     959: bipush        9
     961: ldc_w         #305                // String string
     964: aastore
     965: dup
     966: bipush        10
     968: ldc           #205                // String boolean
     970: aastore
     971: dup
     972: bipush        11
     974: ldc           #207                // String decimal
     976: aastore
     977: dup
     978: bipush        12
     980: ldc           #209                // String float
     982: aastore
     983: dup
     984: bipush        13
     986: ldc           #211                // String integer
     988: aastore
     989: dup
     990: bipush        14
     992: ldc           #213                // String duration
     994: aastore
     995: dup
     996: bipush        15
     998: ldc           #215                // String dateTime
    1000: aastore
    1001: dup
    1002: bipush        16
    1004: ldc           #217                // String time
    1006: aastore
    1007: dup
    1008: bipush        17
    1010: ldc           #219                // String date
    1012: aastore
    1013: dup
    1014: bipush        18
    1016: ldc           #221                // String gYearMonth
    1018: aastore
    1019: dup
    1020: bipush        19
    1022: ldc           #223                // String gYear
    1024: aastore
    1025: dup
    1026: bipush        20
    1028: ldc           #225                // String gMonthDay
    1030: aastore
    1031: dup
    1032: bipush        21
    1034: ldc           #227                // String gDay
    1036: aastore
    1037: dup
    1038: bipush        22
    1040: ldc           #231                // String hexBinary
    1042: aastore
    1043: dup
    1044: bipush        23
    1046: ldc           #233                // String base64Binary
    1048: aastore
    1049: dup
    1050: bipush        24
    1052: ldc_w         #279                // String NCName2
    1055: aastore
    1056: dup
    1057: bipush        25
    1059: ldc_w         #285                // String NCNames
    1062: aastore
    1063: dup
    1064: bipush        26
    1066: ldc_w         #281                // String QName2
    1069: aastore
    1070: dup
    1071: bipush        27
    1073: ldc_w         #275                // String Nmtoken2
    1076: aastore
    1077: dup
    1078: bipush        28
    1080: ldc_w         #283                // String Nmtokens
    1083: aastore
    1084: dup
    1085: bipush        29
    1087: ldc_w         #277                // String Name2
    1090: aastore
    1091: dup
    1092: bipush        30
    1094: ldc_w         #287                // String Names
    1097: aastore
    1098: dup
    1099: bipush        31
    1101: ldc           #235                // String language
    1103: aastore
    1104: putstatic     #539                // Field xml_names_array:[Ljava/lang/String;
    1107: new           #272                // class java/util/HashMap
    1110: dup
    1111: invokespecial #273                // Method java/util/HashMap."<init>":()V
    1114: putstatic     #8                  // Field automata:Ljava/util/Map;
    1117: ldc_w         #540                // String  \t\n\r
    1120: invokestatic  #541                // Method dk/brics/automaton/Automaton.makeCharSet:(Ljava/lang/String;)Ldk/brics/automaton/Automaton;
    1123: invokevirtual #542                // Method dk/brics/automaton/Automaton.repeat:()Ldk/brics/automaton/Automaton;
    1126: invokestatic  #174                // Method dk/brics/automaton/Automaton.minimize:(Ldk/brics/automaton/Automaton;)Ldk/brics/automaton/Automaton;
    1129: putstatic     #83                 // Field ws:Ldk/brics/automaton/Automaton;
    1132: new           #543                // class java/util/HashSet
    1135: dup
    1136: getstatic     #505                // Field unicodeblock_names_array:[Ljava/lang/String;
    1139: invokestatic  #544                // Method java/util/Arrays.asList:([Ljava/lang/Object;)Ljava/util/List;
    1142: invokespecial #545                // Method java/util/HashSet."<init>":(Ljava/util/Collection;)V
    1145: putstatic     #29                 // Field unicodeblock_names:Ljava/util/Set;
    1148: new           #543                // class java/util/HashSet
    1151: dup
    1152: getstatic     #538                // Field unicodecategory_names_array:[Ljava/lang/String;
    1155: invokestatic  #544                // Method java/util/Arrays.asList:([Ljava/lang/Object;)Ljava/util/List;
    1158: invokespecial #545                // Method java/util/HashSet."<init>":(Ljava/util/Collection;)V
    1161: putstatic     #31                 // Field unicodecategory_names:Ljava/util/Set;
    1164: new           #543                // class java/util/HashSet
    1167: dup
    1168: getstatic     #539                // Field xml_names_array:[Ljava/lang/String;
    1171: invokestatic  #544                // Method java/util/Arrays.asList:([Ljava/lang/Object;)Ljava/util/List;
    1174: invokespecial #545                // Method java/util/HashSet."<init>":(Ljava/util/Collection;)V
    1177: putstatic     #32                 // Field xml_names:Ljava/util/Set;
    1180: return
}
