Compiled from "Bs3Navbar.scala"
public abstract class net.liftmodules.FoBoBs.snippet.FoBo.Bs3Navbar$class {
  private static java.lang.Class[] reflParams$Cache1;

  private static volatile java.lang.ref.SoftReference reflPoly$Cache1;

  public static {};
    Code:
       0: iconst_3
       1: anewarray     #9                  // class java/lang/Class
       4: dup
       5: iconst_0
       6: ldc           #11                 // class scala/collection/immutable/List
       8: aastore
       9: dup
      10: iconst_1
      11: getstatic     #17                 // Field java/lang/Boolean.TYPE:Ljava/lang/Class;
      14: aastore
      15: dup
      16: iconst_2
      17: getstatic     #17                 // Field java/lang/Boolean.TYPE:Ljava/lang/Class;
      20: aastore
      21: putstatic     #21                 // Field reflParams$Cache1:[Ljava/lang/Class;
      24: new           #23                 // class java/lang/ref/SoftReference
      27: dup
      28: new           #25                 // class scala/runtime/EmptyMethodCache
      31: dup
      32: invokespecial #28                 // Method scala/runtime/EmptyMethodCache."<init>":()V
      35: invokespecial #31                 // Method java/lang/ref/SoftReference."<init>":(Ljava/lang/Object;)V
      38: putstatic     #35                 // Field reflPoly$Cache1:Ljava/lang/ref/SoftReference;
      41: return

  public static java.lang.reflect.Method reflMethod$Method1(java.lang.Class);
    Code:
       0: getstatic     #35                 // Field reflPoly$Cache1:Ljava/lang/ref/SoftReference;
       3: invokevirtual #41                 // Method java/lang/ref/SoftReference.get:()Ljava/lang/Object;
       6: checkcast     #43                 // class scala/runtime/MethodCache
       9: ifnonnull     29
      12: new           #23                 // class java/lang/ref/SoftReference
      15: dup
      16: new           #25                 // class scala/runtime/EmptyMethodCache
      19: dup
      20: invokespecial #28                 // Method scala/runtime/EmptyMethodCache."<init>":()V
      23: invokespecial #31                 // Method java/lang/ref/SoftReference."<init>":(Ljava/lang/Object;)V
      26: putstatic     #35                 // Field reflPoly$Cache1:Ljava/lang/ref/SoftReference;
      29: getstatic     #35                 // Field reflPoly$Cache1:Ljava/lang/ref/SoftReference;
      32: invokevirtual #41                 // Method java/lang/ref/SoftReference.get:()Ljava/lang/Object;
      35: checkcast     #43                 // class scala/runtime/MethodCache
      38: aload_0
      39: invokevirtual #46                 // Method scala/runtime/MethodCache.find:(Ljava/lang/Class;)Ljava/lang/reflect/Method;
      42: astore_1
      43: aload_1
      44: ifnonnull     89
      47: getstatic     #52                 // Field scala/runtime/ScalaRunTime$.MODULE$:Lscala/runtime/ScalaRunTime$;
      50: aload_0
      51: ldc           #54                 // String buildItem
      53: getstatic     #21                 // Field reflParams$Cache1:[Ljava/lang/Class;
      56: invokevirtual #58                 // Method java/lang/Class.getMethod:(Ljava/lang/String;[Ljava/lang/Class;)Ljava/lang/reflect/Method;
      59: invokevirtual #62                 // Method scala/runtime/ScalaRunTime$.ensureAccessible:(Ljava/lang/reflect/Method;)Ljava/lang/reflect/Method;
      62: astore_1
      63: new           #23                 // class java/lang/ref/SoftReference
      66: dup
      67: getstatic     #35                 // Field reflPoly$Cache1:Ljava/lang/ref/SoftReference;
      70: invokevirtual #41                 // Method java/lang/ref/SoftReference.get:()Ljava/lang/Object;
      73: checkcast     #43                 // class scala/runtime/MethodCache
      76: aload_0
      77: aload_1
      78: invokevirtual #66                 // Method scala/runtime/MethodCache.add:(Ljava/lang/Class;Ljava/lang/reflect/Method;)Lscala/runtime/MethodCache;
      81: invokespecial #31                 // Method java/lang/ref/SoftReference."<init>":(Ljava/lang/Object;)V
      84: putstatic     #35                 // Field reflPoly$Cache1:Ljava/lang/ref/SoftReference;
      87: aload_1
      88: areturn
      89: aload_1
      90: areturn

  public static scala.PartialFunction dispatch(net.liftmodules.FoBoBs.snippet.FoBo.Bs3Navbar);
    Code:
       0: aload_0
       1: invokeinterface #79,  1           // InterfaceMethod net/liftmodules/FoBoBs/snippet/FoBo/Bs3Navbar.overridenDispatch:()Lscala/PartialFunction;
       6: getstatic     #84                 // Field net/liftweb/builtin/snippet/Menu$.MODULE$:Lnet/liftweb/builtin/snippet/Menu$;
       9: invokevirtual #86                 // Method net/liftweb/builtin/snippet/Menu$.dispatch:()Lscala/PartialFunction;
      12: invokeinterface #92,  2           // InterfaceMethod scala/PartialFunction.orElse:(Lscala/PartialFunction;)Lscala/PartialFunction;
      17: areturn

  public static scala.PartialFunction overridenDispatch(net.liftmodules.FoBoBs.snippet.FoBo.Bs3Navbar);
    Code:
       0: new           #96                 // class net/liftmodules/FoBoBs/snippet/FoBo/Bs3Navbar$$anonfun$overridenDispatch$1
       3: dup
       4: aload_0
       5: invokespecial #99                 // Method net/liftmodules/FoBoBs/snippet/FoBo/Bs3Navbar$$anonfun$overridenDispatch$1."<init>":(Lnet/liftmodules/FoBoBs/snippet/FoBo/Bs3Navbar;)V
       8: areturn

  public static scala.xml.NodeSeq net$liftmodules$FoBoBs$snippet$FoBo$Bs3Navbar$$renderPullLeft(net.liftmodules.FoBoBs.snippet.FoBo.Bs3Navbar);
    Code:
       0: aload_0
       1: dup
       2: astore_1
       3: monitorenter
       4: aload_0
       5: iconst_0
       6: invokeinterface #105,  2          // InterfaceMethod net/liftmodules/FoBoBs/snippet/FoBo/Bs3Navbar.net$liftmodules$FoBoBs$snippet$FoBo$Bs3Navbar$$pullRight_$eq:(Z)V
      11: aload_0
      12: invokeinterface #109,  1          // InterfaceMethod net/liftmodules/FoBoBs/snippet/FoBo/Bs3Navbar.render:()Lscala/xml/NodeSeq;
      17: astore_2
      18: aload_1
      19: monitorexit
      20: aload_2
      21: checkcast     #111                // class scala/xml/NodeSeq
      24: areturn
      25: aload_1
      26: monitorexit
      27: athrow
    Exception table:
       from    to  target type
           4    20    25   any

  public static scala.xml.NodeSeq net$liftmodules$FoBoBs$snippet$FoBo$Bs3Navbar$$renderPullRight(net.liftmodules.FoBoBs.snippet.FoBo.Bs3Navbar);
    Code:
       0: aload_0
       1: dup
       2: astore_1
       3: monitorenter
       4: aload_0
       5: iconst_1
       6: invokeinterface #105,  2          // InterfaceMethod net/liftmodules/FoBoBs/snippet/FoBo/Bs3Navbar.net$liftmodules$FoBoBs$snippet$FoBo$Bs3Navbar$$pullRight_$eq:(Z)V
      11: aload_0
      12: invokeinterface #109,  1          // InterfaceMethod net/liftmodules/FoBoBs/snippet/FoBo/Bs3Navbar.render:()Lscala/xml/NodeSeq;
      17: astore_2
      18: aload_1
      19: monitorexit
      20: aload_2
      21: checkcast     #111                // class scala/xml/NodeSeq
      24: areturn
      25: aload_1
      26: monitorexit
      27: athrow
    Exception table:
       from    to  target type
           4    20    25   any

  public static boolean expandAll(net.liftmodules.FoBoBs.snippet.FoBo.Bs3Navbar);
    Code:
       0: iconst_1
       1: ireturn

  public static boolean linkToSelf(net.liftmodules.FoBoBs.snippet.FoBo.Bs3Navbar);
    Code:
       0: iconst_1
       1: ireturn

  public static scala.xml.NodeSeq renderOuterTag(net.liftmodules.FoBoBs.snippet.FoBo.Bs3Navbar, scala.xml.NodeSeq, boolean);
    Code:
       0: iload_2
       1: ifeq          78
       4: aload_0
       5: invokeinterface #123,  1          // InterfaceMethod net/liftmodules/FoBoBs/snippet/FoBo/Bs3Navbar.net$liftmodules$FoBoBs$snippet$FoBo$Bs3Navbar$$pullRight:()Z
      10: ifne          78
      13: getstatic     #128                // Field scala/xml/Null$.MODULE$:Lscala/xml/Null$;
      16: astore_3
      17: new           #130                // class scala/xml/UnprefixedAttribute
      20: dup
      21: ldc           #132                // String class
      23: new           #134                // class scala/xml/Text
      26: dup
      27: ldc           #136                // String nav navbar-nav
      29: invokespecial #139                // Method scala/xml/Text."<init>":(Ljava/lang/String;)V
      32: aload_3
      33: invokespecial #142                // Method scala/xml/UnprefixedAttribute."<init>":(Ljava/lang/String;Lscala/collection/Seq;Lscala/xml/MetaData;)V
      36: astore_3
      37: new           #144                // class scala/xml/Elem
      40: dup
      41: aconst_null
      42: pop
      43: aconst_null
      44: ldc           #146                // String ul
      46: aload_3
      47: getstatic     #151                // Field scala/Predef$.MODULE$:Lscala/Predef$;
      50: invokevirtual #155                // Method scala/Predef$.$scope:()Lscala/xml/TopScope$;
      53: iconst_0
      54: new           #157                // class scala/xml/NodeBuffer
      57: dup
      58: invokespecial #158                // Method scala/xml/NodeBuffer."<init>":()V
      61: astore        4
      63: aload         4
      65: aload_1
      66: invokevirtual #162                // Method scala/xml/NodeBuffer.$amp$plus:(Ljava/lang/Object;)Lscala/xml/NodeBuffer;
      69: pop
      70: aload         4
      72: invokespecial #165                // Method scala/xml/Elem."<init>":(Ljava/lang/String;Ljava/lang/String;Lscala/xml/MetaData;Lscala/xml/NamespaceBinding;ZLscala/collection/Seq;)V
      75: goto          226
      78: iload_2
      79: ifeq          160
      82: aload_0
      83: invokeinterface #123,  1          // InterfaceMethod net/liftmodules/FoBoBs/snippet/FoBo/Bs3Navbar.net$liftmodules$FoBoBs$snippet$FoBo$Bs3Navbar$$pullRight:()Z
      88: ifeq          160
      91: getstatic     #128                // Field scala/xml/Null$.MODULE$:Lscala/xml/Null$;
      94: astore        5
      96: new           #130                // class scala/xml/UnprefixedAttribute
      99: dup
     100: ldc           #132                // String class
     102: new           #134                // class scala/xml/Text
     105: dup
     106: ldc           #167                // String nav navbar-nav navbar-right
     108: invokespecial #139                // Method scala/xml/Text."<init>":(Ljava/lang/String;)V
     111: aload         5
     113: invokespecial #142                // Method scala/xml/UnprefixedAttribute."<init>":(Ljava/lang/String;Lscala/collection/Seq;Lscala/xml/MetaData;)V
     116: astore        5
     118: new           #144                // class scala/xml/Elem
     121: dup
     122: aconst_null
     123: pop
     124: aconst_null
     125: ldc           #146                // String ul
     127: aload         5
     129: getstatic     #151                // Field scala/Predef$.MODULE$:Lscala/Predef$;
     132: invokevirtual #155                // Method scala/Predef$.$scope:()Lscala/xml/TopScope$;
     135: iconst_0
     136: new           #157                // class scala/xml/NodeBuffer
     139: dup
     140: invokespecial #158                // Method scala/xml/NodeBuffer."<init>":()V
     143: astore        6
     145: aload         6
     147: aload_1
     148: invokevirtual #162                // Method scala/xml/NodeBuffer.$amp$plus:(Ljava/lang/Object;)Lscala/xml/NodeBuffer;
     151: pop
     152: aload         6
     154: invokespecial #165                // Method scala/xml/Elem."<init>":(Ljava/lang/String;Ljava/lang/String;Lscala/xml/MetaData;Lscala/xml/NamespaceBinding;ZLscala/collection/Seq;)V
     157: goto          226
     160: getstatic     #128                // Field scala/xml/Null$.MODULE$:Lscala/xml/Null$;
     163: astore        7
     165: new           #130                // class scala/xml/UnprefixedAttribute
     168: dup
     169: ldc           #132                // String class
     171: new           #134                // class scala/xml/Text
     174: dup
     175: ldc           #169                // String dropdown-menu
     177: invokespecial #139                // Method scala/xml/Text."<init>":(Ljava/lang/String;)V
     180: aload         7
     182: invokespecial #142                // Method scala/xml/UnprefixedAttribute."<init>":(Ljava/lang/String;Lscala/collection/Seq;Lscala/xml/MetaData;)V
     185: astore        7
     187: new           #144                // class scala/xml/Elem
     190: dup
     191: aconst_null
     192: pop
     193: aconst_null
     194: ldc           #146                // String ul
     196: aload         7
     198: getstatic     #151                // Field scala/Predef$.MODULE$:Lscala/Predef$;
     201: invokevirtual #155                // Method scala/Predef$.$scope:()Lscala/xml/TopScope$;
     204: iconst_0
     205: new           #157                // class scala/xml/NodeBuffer
     208: dup
     209: invokespecial #158                // Method scala/xml/NodeBuffer."<init>":()V
     212: astore        8
     214: aload         8
     216: aload_1
     217: invokevirtual #162                // Method scala/xml/NodeBuffer.$amp$plus:(Ljava/lang/Object;)Lscala/xml/NodeBuffer;
     220: pop
     221: aload         8
     223: invokespecial #165                // Method scala/xml/Elem."<init>":(Ljava/lang/String;Ljava/lang/String;Lscala/xml/MetaData;Lscala/xml/NamespaceBinding;ZLscala/collection/Seq;)V
     226: areturn

  public static scala.xml.Elem renderSelfLinked(net.liftmodules.FoBoBs.snippet.FoBo.Bs3Navbar, net.liftweb.sitemap.MenuItem, scala.Function1);
    Code:
       0: aload_0
       1: new           #181                // class scala/xml/Group
       4: dup
       5: new           #157                // class scala/xml/NodeBuffer
       8: dup
       9: invokespecial #158                // Method scala/xml/NodeBuffer."<init>":()V
      12: astore_3
      13: aload_3
      14: aload_0
      15: aload_1
      16: invokevirtual #186                // Method net/liftweb/sitemap/MenuItem.uri:()Lscala/xml/NodeSeq;
      19: aload_1
      20: invokevirtual #189                // Method net/liftweb/sitemap/MenuItem.text:()Lscala/xml/NodeSeq;
      23: aload_1
      24: invokevirtual #192                // Method net/liftweb/sitemap/MenuItem.path:()Z
      27: aload_1
      28: invokevirtual #195                // Method net/liftweb/sitemap/MenuItem.current:()Z
      31: invokeinterface #199,  5          // InterfaceMethod net/liftmodules/FoBoBs/snippet/FoBo/Bs3Navbar.renderLink:(Lscala/xml/NodeSeq;Lscala/xml/NodeSeq;ZZ)Lscala/xml/NodeSeq;
      36: invokevirtual #162                // Method scala/xml/NodeBuffer.$amp$plus:(Ljava/lang/Object;)Lscala/xml/NodeBuffer;
      39: pop
      40: aload_3
      41: aload_2
      42: aload_1
      43: invokevirtual #203                // Method net/liftweb/sitemap/MenuItem.kids:()Lscala/collection/Seq;
      46: invokeinterface #209,  2          // InterfaceMethod scala/Function1.apply:(Ljava/lang/Object;)Ljava/lang/Object;
      51: invokevirtual #162                // Method scala/xml/NodeBuffer.$amp$plus:(Ljava/lang/Object;)Lscala/xml/NodeBuffer;
      54: pop
      55: aload_3
      56: invokespecial #212                // Method scala/xml/Group."<init>":(Lscala/collection/Seq;)V
      59: aload_1
      60: invokevirtual #192                // Method net/liftweb/sitemap/MenuItem.path:()Z
      63: aload_1
      64: invokevirtual #195                // Method net/liftweb/sitemap/MenuItem.current:()Z
      67: invokeinterface #216,  4          // InterfaceMethod net/liftmodules/FoBoBs/snippet/FoBo/Bs3Navbar.buildInnerTag:(Lscala/xml/NodeSeq;ZZ)Lscala/xml/Elem;
      72: areturn

  public static scala.xml.NodeSeq renderLink(net.liftmodules.FoBoBs.snippet.FoBo.Bs3Navbar, scala.xml.NodeSeq, scala.xml.NodeSeq, boolean, boolean);
    Code:
       0: getstatic     #128                // Field scala/xml/Null$.MODULE$:Lscala/xml/Null$;
       3: astore        5
       5: new           #130                // class scala/xml/UnprefixedAttribute
       8: dup
       9: ldc           #223                // String href
      11: aload_1
      12: aload         5
      14: invokespecial #142                // Method scala/xml/UnprefixedAttribute."<init>":(Ljava/lang/String;Lscala/collection/Seq;Lscala/xml/MetaData;)V
      17: astore        5
      19: new           #144                // class scala/xml/Elem
      22: dup
      23: aconst_null
      24: pop
      25: aconst_null
      26: ldc           #225                // String a
      28: aload         5
      30: getstatic     #151                // Field scala/Predef$.MODULE$:Lscala/Predef$;
      33: invokevirtual #155                // Method scala/Predef$.$scope:()Lscala/xml/TopScope$;
      36: iconst_0
      37: new           #157                // class scala/xml/NodeBuffer
      40: dup
      41: invokespecial #158                // Method scala/xml/NodeBuffer."<init>":()V
      44: astore        6
      46: aload         6
      48: aload_2
      49: invokevirtual #162                // Method scala/xml/NodeBuffer.$amp$plus:(Ljava/lang/Object;)Lscala/xml/NodeBuffer;
      52: pop
      53: aload         6
      55: invokespecial #165                // Method scala/xml/Elem."<init>":(Ljava/lang/String;Ljava/lang/String;Lscala/xml/MetaData;Lscala/xml/NamespaceBinding;ZLscala/collection/Seq;)V
      58: areturn

  public static scala.xml.NodeSeq renderLinkWithTarget(net.liftmodules.FoBoBs.snippet.FoBo.Bs3Navbar, scala.xml.NodeSeq, scala.xml.NodeSeq, boolean, boolean, scala.Function0);
    Code:
       0: aload         5
       2: invokeinterface #231,  1          // InterfaceMethod scala/Function0.apply:()Ljava/lang/Object;
       7: checkcast     #233                // class java/lang/String
      10: astore        6
      12: getstatic     #128                // Field scala/xml/Null$.MODULE$:Lscala/xml/Null$;
      15: astore        7
      17: new           #130                // class scala/xml/UnprefixedAttribute
      20: dup
      21: ldc           #235                // String target
      23: aload         6
      25: aload         7
      27: invokespecial #238                // Method scala/xml/UnprefixedAttribute."<init>":(Ljava/lang/String;Ljava/lang/String;Lscala/xml/MetaData;)V
      30: astore        7
      32: new           #130                // class scala/xml/UnprefixedAttribute
      35: dup
      36: ldc           #223                // String href
      38: aload_1
      39: aload         7
      41: invokespecial #142                // Method scala/xml/UnprefixedAttribute."<init>":(Ljava/lang/String;Lscala/collection/Seq;Lscala/xml/MetaData;)V
      44: astore        7
      46: new           #144                // class scala/xml/Elem
      49: dup
      50: aconst_null
      51: pop
      52: aconst_null
      53: ldc           #225                // String a
      55: aload         7
      57: getstatic     #151                // Field scala/Predef$.MODULE$:Lscala/Predef$;
      60: invokevirtual #155                // Method scala/Predef$.$scope:()Lscala/xml/TopScope$;
      63: iconst_0
      64: new           #157                // class scala/xml/NodeBuffer
      67: dup
      68: invokespecial #158                // Method scala/xml/NodeBuffer."<init>":()V
      71: astore        8
      73: aload         8
      75: aload_2
      76: invokevirtual #162                // Method scala/xml/NodeBuffer.$amp$plus:(Ljava/lang/Object;)Lscala/xml/NodeBuffer;
      79: pop
      80: aload         8
      82: invokespecial #165                // Method scala/xml/Elem."<init>":(Ljava/lang/String;Ljava/lang/String;Lscala/xml/MetaData;Lscala/xml/NamespaceBinding;ZLscala/collection/Seq;)V
      85: areturn

  public static scala.xml.Elem updateForPath(net.liftmodules.FoBoBs.snippet.FoBo.Bs3Navbar, scala.xml.Elem, boolean);
    Code:
       0: aload_1
       1: areturn

  public static scala.xml.Elem updateForCurrent(net.liftmodules.FoBoBs.snippet.FoBo.Bs3Navbar, scala.xml.Elem, boolean);
    Code:
       0: aload_1
       1: areturn

  public static scala.xml.Elem renderPlaceholder(net.liftmodules.FoBoBs.snippet.FoBo.Bs3Navbar, net.liftweb.sitemap.MenuItem, scala.Function1);
    Code:
       0: aload_0
       1: getstatic     #128                // Field scala/xml/Null$.MODULE$:Lscala/xml/Null$;
       4: astore_3
       5: new           #130                // class scala/xml/UnprefixedAttribute
       8: dup
       9: ldc           #132                // String class
      11: new           #134                // class scala/xml/Text
      14: dup
      15: ldc           #250                // String dropdown
      17: invokespecial #139                // Method scala/xml/Text."<init>":(Ljava/lang/String;)V
      20: aload_3
      21: invokespecial #142                // Method scala/xml/UnprefixedAttribute."<init>":(Ljava/lang/String;Lscala/collection/Seq;Lscala/xml/MetaData;)V
      24: astore_3
      25: new           #144                // class scala/xml/Elem
      28: dup
      29: aconst_null
      30: pop
      31: aconst_null
      32: ldc           #252                // String li
      34: aload_3
      35: getstatic     #151                // Field scala/Predef$.MODULE$:Lscala/Predef$;
      38: invokevirtual #155                // Method scala/Predef$.$scope:()Lscala/xml/TopScope$;
      41: iconst_0
      42: new           #157                // class scala/xml/NodeBuffer
      45: dup
      46: invokespecial #158                // Method scala/xml/NodeBuffer."<init>":()V
      49: astore        4
      51: aload         4
      53: getstatic     #128                // Field scala/xml/Null$.MODULE$:Lscala/xml/Null$;
      56: astore        5
      58: new           #130                // class scala/xml/UnprefixedAttribute
      61: dup
      62: ldc           #254                // String data-toggle
      64: new           #134                // class scala/xml/Text
      67: dup
      68: ldc           #250                // String dropdown
      70: invokespecial #139                // Method scala/xml/Text."<init>":(Ljava/lang/String;)V
      73: aload         5
      75: invokespecial #142                // Method scala/xml/UnprefixedAttribute."<init>":(Ljava/lang/String;Lscala/collection/Seq;Lscala/xml/MetaData;)V
      78: astore        5
      80: new           #130                // class scala/xml/UnprefixedAttribute
      83: dup
      84: ldc           #132                // String class
      86: new           #134                // class scala/xml/Text
      89: dup
      90: ldc_w         #256                // String dropdown-toggle
      93: invokespecial #139                // Method scala/xml/Text."<init>":(Ljava/lang/String;)V
      96: aload         5
      98: invokespecial #142                // Method scala/xml/UnprefixedAttribute."<init>":(Ljava/lang/String;Lscala/collection/Seq;Lscala/xml/MetaData;)V
     101: astore        5
     103: new           #130                // class scala/xml/UnprefixedAttribute
     106: dup
     107: ldc           #223                // String href
     109: new           #134                // class scala/xml/Text
     112: dup
     113: ldc_w         #258                // String #
     116: invokespecial #139                // Method scala/xml/Text."<init>":(Ljava/lang/String;)V
     119: aload         5
     121: invokespecial #142                // Method scala/xml/UnprefixedAttribute."<init>":(Ljava/lang/String;Lscala/collection/Seq;Lscala/xml/MetaData;)V
     124: astore        5
     126: new           #144                // class scala/xml/Elem
     129: dup
     130: aconst_null
     131: pop
     132: aconst_null
     133: ldc           #225                // String a
     135: aload         5
     137: getstatic     #151                // Field scala/Predef$.MODULE$:Lscala/Predef$;
     140: invokevirtual #155                // Method scala/Predef$.$scope:()Lscala/xml/TopScope$;
     143: iconst_0
     144: new           #157                // class scala/xml/NodeBuffer
     147: dup
     148: invokespecial #158                // Method scala/xml/NodeBuffer."<init>":()V
     151: astore        6
     153: aload         6
     155: new           #144                // class scala/xml/Elem
     158: dup
     159: aconst_null
     160: pop
     161: aconst_null
     162: ldc_w         #260                // String span
     165: getstatic     #128                // Field scala/xml/Null$.MODULE$:Lscala/xml/Null$;
     168: getstatic     #151                // Field scala/Predef$.MODULE$:Lscala/Predef$;
     171: invokevirtual #155                // Method scala/Predef$.$scope:()Lscala/xml/TopScope$;
     174: iconst_0
     175: new           #157                // class scala/xml/NodeBuffer
     178: dup
     179: invokespecial #158                // Method scala/xml/NodeBuffer."<init>":()V
     182: astore        7
     184: aload         7
     186: aload_1
     187: invokevirtual #189                // Method net/liftweb/sitemap/MenuItem.text:()Lscala/xml/NodeSeq;
     190: invokevirtual #162                // Method scala/xml/NodeBuffer.$amp$plus:(Ljava/lang/Object;)Lscala/xml/NodeBuffer;
     193: pop
     194: aload         7
     196: invokespecial #165                // Method scala/xml/Elem."<init>":(Ljava/lang/String;Ljava/lang/String;Lscala/xml/MetaData;Lscala/xml/NamespaceBinding;ZLscala/collection/Seq;)V
     199: invokevirtual #162                // Method scala/xml/NodeBuffer.$amp$plus:(Ljava/lang/Object;)Lscala/xml/NodeBuffer;
     202: pop
     203: aload         6
     205: new           #134                // class scala/xml/Text
     208: dup
     209: ldc_w         #262                // String
     212: invokespecial #139                // Method scala/xml/Text."<init>":(Ljava/lang/String;)V
     215: invokevirtual #162                // Method scala/xml/NodeBuffer.$amp$plus:(Ljava/lang/Object;)Lscala/xml/NodeBuffer;
     218: pop
     219: aload         6
     221: getstatic     #128                // Field scala/xml/Null$.MODULE$:Lscala/xml/Null$;
     224: astore        8
     226: new           #130                // class scala/xml/UnprefixedAttribute
     229: dup
     230: ldc           #132                // String class
     232: new           #134                // class scala/xml/Text
     235: dup
     236: ldc_w         #264                // String caret
     239: invokespecial #139                // Method scala/xml/Text."<init>":(Ljava/lang/String;)V
     242: aload         8
     244: invokespecial #142                // Method scala/xml/UnprefixedAttribute."<init>":(Ljava/lang/String;Lscala/collection/Seq;Lscala/xml/MetaData;)V
     247: astore        8
     249: new           #144                // class scala/xml/Elem
     252: dup
     253: aconst_null
     254: pop
     255: aconst_null
     256: ldc_w         #266                // String b
     259: aload         8
     261: getstatic     #151                // Field scala/Predef$.MODULE$:Lscala/Predef$;
     264: invokevirtual #155                // Method scala/Predef$.$scope:()Lscala/xml/TopScope$;
     267: iconst_0
     268: getstatic     #151                // Field scala/Predef$.MODULE$:Lscala/Predef$;
     271: iconst_0
     272: anewarray     #268                // class scala/xml/Node
     275: checkcast     #270                // class "[Ljava/lang/Object;"
     278: invokevirtual #276                // Method scala/LowPriorityImplicits.wrapRefArray:([Ljava/lang/Object;)Lscala/collection/mutable/WrappedArray;
     281: invokespecial #165                // Method scala/xml/Elem."<init>":(Ljava/lang/String;Ljava/lang/String;Lscala/xml/MetaData;Lscala/xml/NamespaceBinding;ZLscala/collection/Seq;)V
     284: invokevirtual #162                // Method scala/xml/NodeBuffer.$amp$plus:(Ljava/lang/Object;)Lscala/xml/NodeBuffer;
     287: pop
     288: aload         6
     290: invokespecial #165                // Method scala/xml/Elem."<init>":(Ljava/lang/String;Ljava/lang/String;Lscala/xml/MetaData;Lscala/xml/NamespaceBinding;ZLscala/collection/Seq;)V
     293: invokevirtual #162                // Method scala/xml/NodeBuffer.$amp$plus:(Ljava/lang/Object;)Lscala/xml/NodeBuffer;
     296: pop
     297: aload         4
     299: aload_2
     300: aload_1
     301: invokevirtual #203                // Method net/liftweb/sitemap/MenuItem.kids:()Lscala/collection/Seq;
     304: invokeinterface #209,  2          // InterfaceMethod scala/Function1.apply:(Ljava/lang/Object;)Ljava/lang/Object;
     309: invokevirtual #162                // Method scala/xml/NodeBuffer.$amp$plus:(Ljava/lang/Object;)Lscala/xml/NodeBuffer;
     312: pop
     313: aload         4
     315: invokespecial #165                // Method scala/xml/Elem."<init>":(Ljava/lang/String;Ljava/lang/String;Lscala/xml/MetaData;Lscala/xml/NamespaceBinding;ZLscala/collection/Seq;)V
     318: aload_1
     319: invokevirtual #192                // Method net/liftweb/sitemap/MenuItem.path:()Z
     322: aload_1
     323: invokevirtual #195                // Method net/liftweb/sitemap/MenuItem.current:()Z
     326: invokeinterface #279,  4          // InterfaceMethod net/liftmodules/FoBoBs/snippet/FoBo/Bs3Navbar.buildTBInnerTag:(Lscala/xml/NodeSeq;ZZ)Lscala/xml/Elem;
     331: areturn

  public static scala.collection.immutable.List buildItemMenu(net.liftmodules.FoBoBs.snippet.FoBo.Bs3Navbar, net.liftweb.sitemap.Loc, net.liftweb.common.Box, boolean);
    Code:
       0: iload_3
       1: ifeq          22
       4: aload_1
       5: aload_1
       6: invokeinterface #289,  1          // InterfaceMethod net/liftweb/sitemap/Loc.menu:()Lnet/liftweb/sitemap/Menu;
      11: invokevirtual #292                // Method net/liftweb/sitemap/Menu.kids:()Lscala/collection/Seq;
      14: invokeinterface #296,  2          // InterfaceMethod net/liftweb/sitemap/Loc.buildKidMenuItems:(Lscala/collection/Seq;)Lscala/collection/immutable/List;
      19: goto          25
      22: getstatic     #301                // Field scala/collection/immutable/Nil$.MODULE$:Lscala/collection/immutable/Nil$;
      25: astore        4
      27: aload_1
      28: astore        5
      30: aload         5
      32: invokevirtual #305                // Method java/lang/Object.getClass:()Ljava/lang/Class;
      35: invokestatic  #307                // Method reflMethod$Method1:(Ljava/lang/Class;)Ljava/lang/reflect/Method;
      38: aload         5
      40: iconst_3
      41: anewarray     #4                  // class java/lang/Object
      44: dup
      45: iconst_0
      46: aload         4
      48: aastore
      49: dup
      50: iconst_1
      51: aload_2
      52: new           #309                // class net/liftweb/common/Full
      55: dup
      56: aload_1
      57: invokespecial #310                // Method net/liftweb/common/Full."<init>":(Ljava/lang/Object;)V
      60: astore        7
      62: dup
      63: ifnonnull     75
      66: pop
      67: aload         7
      69: ifnull        83
      72: goto          87
      75: aload         7
      77: invokevirtual #314                // Method java/lang/Object.equals:(Ljava/lang/Object;)Z
      80: ifeq          87
      83: iconst_1
      84: goto          88
      87: iconst_0
      88: invokestatic  #320                // Method scala/runtime/BoxesRunTime.boxToBoolean:(Z)Ljava/lang/Boolean;
      91: aastore
      92: dup
      93: iconst_2
      94: aload_2
      95: new           #309                // class net/liftweb/common/Full
      98: dup
      99: aload_1
     100: invokespecial #310                // Method net/liftweb/common/Full."<init>":(Ljava/lang/Object;)V
     103: astore        8
     105: dup
     106: ifnonnull     118
     109: pop
     110: aload         8
     112: ifnull        126
     115: goto          130
     118: aload         8
     120: invokevirtual #314                // Method java/lang/Object.equals:(Ljava/lang/Object;)Z
     123: ifeq          130
     126: iconst_1
     127: goto          131
     130: iconst_0
     131: invokestatic  #320                // Method scala/runtime/BoxesRunTime.boxToBoolean:(Z)Ljava/lang/Boolean;
     134: aastore
     135: invokevirtual #324                // Method java/lang/reflect/Method.invoke:(Ljava/lang/Object;[Ljava/lang/Object;)Ljava/lang/Object;
     138: checkcast     #326                // class net/liftweb/common/Box
     141: checkcast     #326                // class net/liftweb/common/Box
     144: invokevirtual #330                // Method net/liftweb/common/Box.toList:()Lscala/collection/immutable/List;
     147: areturn
     148: astore        6
     150: aload         6
     152: invokevirtual #334                // Method java/lang/reflect/InvocationTargetException.getCause:()Ljava/lang/Throwable;
     155: athrow
    Exception table:
       from    to  target type
          30   138   148   Class java/lang/reflect/InvocationTargetException

  public static scala.xml.NodeSeq emptyGroup(net.liftmodules.FoBoBs.snippet.FoBo.Bs3Navbar);
    Code:
       0: getstatic     #347                // Field scala/xml/NodeSeq$.MODULE$:Lscala/xml/NodeSeq$;
       3: invokevirtual #350                // Method scala/xml/NodeSeq$.Empty:()Lscala/xml/NodeSeq;
       6: areturn

  public static scala.xml.NodeSeq emptyMenu(net.liftmodules.FoBoBs.snippet.FoBo.Bs3Navbar);
    Code:
       0: getstatic     #356                // Field scala/xml/Text$.MODULE$:Lscala/xml/Text$;
       3: ldc_w         #358                // String No Navigation Defined.
       6: invokevirtual #361                // Method scala/xml/Text$.apply:(Ljava/lang/String;)Lscala/xml/Text;
       9: areturn

  public static scala.xml.NodeSeq emptyPlaceholder(net.liftmodules.FoBoBs.snippet.FoBo.Bs3Navbar);
    Code:
       0: getstatic     #347                // Field scala/xml/NodeSeq$.MODULE$:Lscala/xml/NodeSeq$;
       3: invokevirtual #350                // Method scala/xml/NodeSeq$.Empty:()Lscala/xml/NodeSeq;
       6: areturn

  public static scala.xml.Elem buildInnerTag(net.liftmodules.FoBoBs.snippet.FoBo.Bs3Navbar, scala.xml.NodeSeq, boolean, boolean);
    Code:
       0: iload_3
       1: ifeq          88
       4: aload_0
       5: aload_0
       6: getstatic     #128                // Field scala/xml/Null$.MODULE$:Lscala/xml/Null$;
       9: astore        4
      11: new           #130                // class scala/xml/UnprefixedAttribute
      14: dup
      15: ldc           #132                // String class
      17: new           #134                // class scala/xml/Text
      20: dup
      21: ldc_w         #365                // String active
      24: invokespecial #139                // Method scala/xml/Text."<init>":(Ljava/lang/String;)V
      27: aload         4
      29: invokespecial #142                // Method scala/xml/UnprefixedAttribute."<init>":(Ljava/lang/String;Lscala/collection/Seq;Lscala/xml/MetaData;)V
      32: astore        4
      34: new           #144                // class scala/xml/Elem
      37: dup
      38: aconst_null
      39: pop
      40: aconst_null
      41: ldc           #252                // String li
      43: aload         4
      45: getstatic     #151                // Field scala/Predef$.MODULE$:Lscala/Predef$;
      48: invokevirtual #155                // Method scala/Predef$.$scope:()Lscala/xml/TopScope$;
      51: iconst_0
      52: new           #157                // class scala/xml/NodeBuffer
      55: dup
      56: invokespecial #158                // Method scala/xml/NodeBuffer."<init>":()V
      59: astore        5
      61: aload         5
      63: aload_1
      64: invokevirtual #162                // Method scala/xml/NodeBuffer.$amp$plus:(Ljava/lang/Object;)Lscala/xml/NodeBuffer;
      67: pop
      68: aload         5
      70: invokespecial #165                // Method scala/xml/Elem."<init>":(Ljava/lang/String;Ljava/lang/String;Lscala/xml/MetaData;Lscala/xml/NamespaceBinding;ZLscala/collection/Seq;)V
      73: iload_2
      74: invokeinterface #368,  3          // InterfaceMethod net/liftmodules/FoBoBs/snippet/FoBo/Bs3Navbar.updateForPath:(Lscala/xml/Elem;Z)Lscala/xml/Elem;
      79: iload_3
      80: invokeinterface #370,  3          // InterfaceMethod net/liftmodules/FoBoBs/snippet/FoBo/Bs3Navbar.updateForCurrent:(Lscala/xml/Elem;Z)Lscala/xml/Elem;
      85: goto          142
      88: aload_0
      89: aload_0
      90: new           #144                // class scala/xml/Elem
      93: dup
      94: aconst_null
      95: pop
      96: aconst_null
      97: ldc           #252                // String li
      99: getstatic     #128                // Field scala/xml/Null$.MODULE$:Lscala/xml/Null$;
     102: getstatic     #151                // Field scala/Predef$.MODULE$:Lscala/Predef$;
     105: invokevirtual #155                // Method scala/Predef$.$scope:()Lscala/xml/TopScope$;
     108: iconst_0
     109: new           #157                // class scala/xml/NodeBuffer
     112: dup
     113: invokespecial #158                // Method scala/xml/NodeBuffer."<init>":()V
     116: astore        6
     118: aload         6
     120: aload_1
     121: invokevirtual #162                // Method scala/xml/NodeBuffer.$amp$plus:(Ljava/lang/Object;)Lscala/xml/NodeBuffer;
     124: pop
     125: aload         6
     127: invokespecial #165                // Method scala/xml/Elem."<init>":(Ljava/lang/String;Ljava/lang/String;Lscala/xml/MetaData;Lscala/xml/NamespaceBinding;ZLscala/collection/Seq;)V
     130: iload_2
     131: invokeinterface #368,  3          // InterfaceMethod net/liftmodules/FoBoBs/snippet/FoBo/Bs3Navbar.updateForPath:(Lscala/xml/Elem;Z)Lscala/xml/Elem;
     136: iload_3
     137: invokeinterface #370,  3          // InterfaceMethod net/liftmodules/FoBoBs/snippet/FoBo/Bs3Navbar.updateForCurrent:(Lscala/xml/Elem;Z)Lscala/xml/Elem;
     142: areturn

  public static scala.xml.Elem buildTBDivider(net.liftmodules.FoBoBs.snippet.FoBo.Bs3Navbar, scala.xml.NodeSeq, boolean, boolean);
    Code:
       0: aload_0
       1: aload_0
       2: getstatic     #128                // Field scala/xml/Null$.MODULE$:Lscala/xml/Null$;
       5: astore        4
       7: new           #130                // class scala/xml/UnprefixedAttribute
      10: dup
      11: ldc           #132                // String class
      13: new           #134                // class scala/xml/Text
      16: dup
      17: ldc_w         #374                // String divider
      20: invokespecial #139                // Method scala/xml/Text."<init>":(Ljava/lang/String;)V
      23: aload         4
      25: invokespecial #142                // Method scala/xml/UnprefixedAttribute."<init>":(Ljava/lang/String;Lscala/collection/Seq;Lscala/xml/MetaData;)V
      28: astore        4
      30: new           #144                // class scala/xml/Elem
      33: dup
      34: aconst_null
      35: pop
      36: aconst_null
      37: ldc           #252                // String li
      39: aload         4
      41: getstatic     #151                // Field scala/Predef$.MODULE$:Lscala/Predef$;
      44: invokevirtual #155                // Method scala/Predef$.$scope:()Lscala/xml/TopScope$;
      47: iconst_0
      48: getstatic     #151                // Field scala/Predef$.MODULE$:Lscala/Predef$;
      51: iconst_0
      52: anewarray     #268                // class scala/xml/Node
      55: checkcast     #270                // class "[Ljava/lang/Object;"
      58: invokevirtual #276                // Method scala/LowPriorityImplicits.wrapRefArray:([Ljava/lang/Object;)Lscala/collection/mutable/WrappedArray;
      61: invokespecial #165                // Method scala/xml/Elem."<init>":(Ljava/lang/String;Ljava/lang/String;Lscala/xml/MetaData;Lscala/xml/NamespaceBinding;ZLscala/collection/Seq;)V
      64: iload_2
      65: invokeinterface #368,  3          // InterfaceMethod net/liftmodules/FoBoBs/snippet/FoBo/Bs3Navbar.updateForPath:(Lscala/xml/Elem;Z)Lscala/xml/Elem;
      70: iload_3
      71: invokeinterface #370,  3          // InterfaceMethod net/liftmodules/FoBoBs/snippet/FoBo/Bs3Navbar.updateForCurrent:(Lscala/xml/Elem;Z)Lscala/xml/Elem;
      76: areturn

  public static scala.xml.Elem buildTBVerticalDivider(net.liftmodules.FoBoBs.snippet.FoBo.Bs3Navbar, scala.xml.NodeSeq, boolean, boolean);
    Code:
       0: aload_0
       1: aload_0
       2: getstatic     #128                // Field scala/xml/Null$.MODULE$:Lscala/xml/Null$;
       5: astore        4
       7: new           #130                // class scala/xml/UnprefixedAttribute
      10: dup
      11: ldc           #132                // String class
      13: new           #134                // class scala/xml/Text
      16: dup
      17: ldc_w         #377                // String divider-vertical
      20: invokespecial #139                // Method scala/xml/Text."<init>":(Ljava/lang/String;)V
      23: aload         4
      25: invokespecial #142                // Method scala/xml/UnprefixedAttribute."<init>":(Ljava/lang/String;Lscala/collection/Seq;Lscala/xml/MetaData;)V
      28: astore        4
      30: new           #144                // class scala/xml/Elem
      33: dup
      34: aconst_null
      35: pop
      36: aconst_null
      37: ldc           #252                // String li
      39: aload         4
      41: getstatic     #151                // Field scala/Predef$.MODULE$:Lscala/Predef$;
      44: invokevirtual #155                // Method scala/Predef$.$scope:()Lscala/xml/TopScope$;
      47: iconst_0
      48: getstatic     #151                // Field scala/Predef$.MODULE$:Lscala/Predef$;
      51: iconst_0
      52: anewarray     #268                // class scala/xml/Node
      55: checkcast     #270                // class "[Ljava/lang/Object;"
      58: invokevirtual #276                // Method scala/LowPriorityImplicits.wrapRefArray:([Ljava/lang/Object;)Lscala/collection/mutable/WrappedArray;
      61: invokespecial #165                // Method scala/xml/Elem."<init>":(Ljava/lang/String;Ljava/lang/String;Lscala/xml/MetaData;Lscala/xml/NamespaceBinding;ZLscala/collection/Seq;)V
      64: iload_2
      65: invokeinterface #368,  3          // InterfaceMethod net/liftmodules/FoBoBs/snippet/FoBo/Bs3Navbar.updateForPath:(Lscala/xml/Elem;Z)Lscala/xml/Elem;
      70: iload_3
      71: invokeinterface #370,  3          // InterfaceMethod net/liftmodules/FoBoBs/snippet/FoBo/Bs3Navbar.updateForCurrent:(Lscala/xml/Elem;Z)Lscala/xml/Elem;
      76: areturn

  public static scala.xml.Elem buildTBInnerTag(net.liftmodules.FoBoBs.snippet.FoBo.Bs3Navbar, scala.xml.NodeSeq, boolean, boolean);
    Code:
       0: aload_0
       1: aload_0
       2: aload_1
       3: checkcast     #144                // class scala/xml/Elem
       6: iload_2
       7: invokeinterface #368,  3          // InterfaceMethod net/liftmodules/FoBoBs/snippet/FoBo/Bs3Navbar.updateForPath:(Lscala/xml/Elem;Z)Lscala/xml/Elem;
      12: iload_3
      13: invokeinterface #370,  3          // InterfaceMethod net/liftmodules/FoBoBs/snippet/FoBo/Bs3Navbar.updateForCurrent:(Lscala/xml/Elem;Z)Lscala/xml/Elem;
      18: areturn

  public static scala.xml.NodeSeq renderSelf(net.liftmodules.FoBoBs.snippet.FoBo.Bs3Navbar, net.liftweb.sitemap.MenuItem);
    Code:
       0: new           #144                // class scala/xml/Elem
       3: dup
       4: aconst_null
       5: pop
       6: aconst_null
       7: ldc_w         #260                // String span
      10: getstatic     #128                // Field scala/xml/Null$.MODULE$:Lscala/xml/Null$;
      13: getstatic     #151                // Field scala/Predef$.MODULE$:Lscala/Predef$;
      16: invokevirtual #155                // Method scala/Predef$.$scope:()Lscala/xml/TopScope$;
      19: iconst_0
      20: new           #157                // class scala/xml/NodeBuffer
      23: dup
      24: invokespecial #158                // Method scala/xml/NodeBuffer."<init>":()V
      27: astore_2
      28: aload_2
      29: aload_1
      30: invokevirtual #189                // Method net/liftweb/sitemap/MenuItem.text:()Lscala/xml/NodeSeq;
      33: invokevirtual #162                // Method scala/xml/NodeBuffer.$amp$plus:(Ljava/lang/Object;)Lscala/xml/NodeBuffer;
      36: pop
      37: aload_2
      38: invokespecial #165                // Method scala/xml/Elem."<init>":(Ljava/lang/String;Ljava/lang/String;Lscala/xml/MetaData;Lscala/xml/NamespaceBinding;ZLscala/collection/Seq;)V
      41: areturn

  public static scala.xml.Elem renderSelfNotLinked(net.liftmodules.FoBoBs.snippet.FoBo.Bs3Navbar, net.liftweb.sitemap.MenuItem, scala.Function1);
    Code:
       0: aload_0
       1: new           #181                // class scala/xml/Group
       4: dup
       5: new           #157                // class scala/xml/NodeBuffer
       8: dup
       9: invokespecial #158                // Method scala/xml/NodeBuffer."<init>":()V
      12: astore_3
      13: aload_3
      14: aload_0
      15: aload_1
      16: invokeinterface #383,  2          // InterfaceMethod net/liftmodules/FoBoBs/snippet/FoBo/Bs3Navbar.renderSelf:(Lnet/liftweb/sitemap/MenuItem;)Lscala/xml/NodeSeq;
      21: invokevirtual #162                // Method scala/xml/NodeBuffer.$amp$plus:(Ljava/lang/Object;)Lscala/xml/NodeBuffer;
      24: pop
      25: aload_3
      26: aload_2
      27: aload_1
      28: invokevirtual #203                // Method net/liftweb/sitemap/MenuItem.kids:()Lscala/collection/Seq;
      31: invokeinterface #209,  2          // InterfaceMethod scala/Function1.apply:(Ljava/lang/Object;)Ljava/lang/Object;
      36: invokevirtual #162                // Method scala/xml/NodeBuffer.$amp$plus:(Ljava/lang/Object;)Lscala/xml/NodeBuffer;
      39: pop
      40: aload_3
      41: invokespecial #212                // Method scala/xml/Group."<init>":(Lscala/collection/Seq;)V
      44: aload_1
      45: invokevirtual #192                // Method net/liftweb/sitemap/MenuItem.path:()Z
      48: aload_1
      49: invokevirtual #195                // Method net/liftweb/sitemap/MenuItem.current:()Z
      52: invokeinterface #216,  4          // InterfaceMethod net/liftmodules/FoBoBs/snippet/FoBo/Bs3Navbar.buildInnerTag:(Lscala/xml/NodeSeq;ZZ)Lscala/xml/Elem;
      57: areturn

  public static scala.xml.Elem renderItemInPath(net.liftmodules.FoBoBs.snippet.FoBo.Bs3Navbar, net.liftweb.sitemap.MenuItem, scala.Function1);
    Code:
       0: aload_0
       1: new           #181                // class scala/xml/Group
       4: dup
       5: new           #157                // class scala/xml/NodeBuffer
       8: dup
       9: invokespecial #158                // Method scala/xml/NodeBuffer."<init>":()V
      12: astore_3
      13: aload_3
      14: aload_0
      15: aload_1
      16: invokevirtual #186                // Method net/liftweb/sitemap/MenuItem.uri:()Lscala/xml/NodeSeq;
      19: aload_1
      20: invokevirtual #189                // Method net/liftweb/sitemap/MenuItem.text:()Lscala/xml/NodeSeq;
      23: aload_1
      24: invokevirtual #192                // Method net/liftweb/sitemap/MenuItem.path:()Z
      27: aload_1
      28: invokevirtual #195                // Method net/liftweb/sitemap/MenuItem.current:()Z
      31: invokeinterface #199,  5          // InterfaceMethod net/liftmodules/FoBoBs/snippet/FoBo/Bs3Navbar.renderLink:(Lscala/xml/NodeSeq;Lscala/xml/NodeSeq;ZZ)Lscala/xml/NodeSeq;
      36: invokevirtual #162                // Method scala/xml/NodeBuffer.$amp$plus:(Ljava/lang/Object;)Lscala/xml/NodeBuffer;
      39: pop
      40: aload_3
      41: aload_2
      42: aload_1
      43: invokevirtual #203                // Method net/liftweb/sitemap/MenuItem.kids:()Lscala/collection/Seq;
      46: invokeinterface #209,  2          // InterfaceMethod scala/Function1.apply:(Ljava/lang/Object;)Ljava/lang/Object;
      51: invokevirtual #162                // Method scala/xml/NodeBuffer.$amp$plus:(Ljava/lang/Object;)Lscala/xml/NodeBuffer;
      54: pop
      55: aload_3
      56: invokespecial #212                // Method scala/xml/Group."<init>":(Lscala/collection/Seq;)V
      59: aload_1
      60: invokevirtual #192                // Method net/liftweb/sitemap/MenuItem.path:()Z
      63: aload_1
      64: invokevirtual #195                // Method net/liftweb/sitemap/MenuItem.current:()Z
      67: invokeinterface #216,  4          // InterfaceMethod net/liftmodules/FoBoBs/snippet/FoBo/Bs3Navbar.buildInnerTag:(Lscala/xml/NodeSeq;ZZ)Lscala/xml/Elem;
      72: areturn

  public static scala.xml.Elem renderItem(net.liftmodules.FoBoBs.snippet.FoBo.Bs3Navbar, net.liftweb.sitemap.MenuItem, scala.Function1);
    Code:
       0: aload_0
       1: aload_1
       2: invokevirtual #388                // Method net/liftweb/sitemap/MenuItem.info:()Lscala/collection/immutable/List;
       5: aload_2
       6: aload_1
       7: invokestatic  #392                // Method renderItemWithInfo:(Lnet/liftmodules/FoBoBs/snippet/FoBo/Bs3Navbar;Lscala/collection/immutable/List;Lscala/Function1;Lnet/liftweb/sitemap/MenuItem;)Lscala/xml/Elem;
      10: areturn

  private static scala.xml.Elem renderItemWithInfo(net.liftmodules.FoBoBs.snippet.FoBo.Bs3Navbar, scala.collection.immutable.List, scala.Function1, net.liftweb.sitemap.MenuItem);
    Code:
       0: iconst_0
       1: istore        5
       3: aconst_null
       4: pop
       5: aconst_null
       6: astore        6
       8: aload_1
       9: astore        7
      11: aload         7
      13: instanceof    #394                // class scala/collection/immutable/$colon$colon
      16: ifeq          379
      19: iconst_1
      20: istore        5
      22: aload         7
      24: checkcast     #394                // class scala/collection/immutable/$colon$colon
      27: astore        6
      29: aload         6
      31: ifnull        379
      34: aload         6
      36: invokevirtual #397                // Method scala/collection/immutable/$colon$colon.hd$1:()Ljava/lang/Object;
      39: checkcast     #326                // class net/liftweb/common/Box
      42: astore        8
      44: aload         6
      46: invokevirtual #400                // Method scala/collection/immutable/$colon$colon.tl$1:()Lscala/collection/immutable/List;
      49: astore        9
      51: getstatic     #301                // Field scala/collection/immutable/Nil$.MODULE$:Lscala/collection/immutable/Nil$;
      54: aload         9
      56: astore        10
      58: dup
      59: ifnonnull     71
      62: pop
      63: aload         10
      65: ifnull        79
      68: goto          379
      71: aload         10
      73: invokevirtual #314                // Method java/lang/Object.equals:(Ljava/lang/Object;)Z
      76: ifeq          379
      79: aload         9
      81: astore        11
      83: aload         8
      85: astore        13
      87: aload         13
      89: instanceof    #309                // class net/liftweb/common/Full
      92: ifeq          130
      95: aload         13
      97: checkcast     #309                // class net/liftweb/common/Full
     100: astore        14
     102: aload         14
     104: ifnull        130
     107: aload         14
     109: invokevirtual #403                // Method net/liftweb/common/Full.value:()Ljava/lang/Object;
     112: checkcast     #229                // class scala/Function0
     115: astore        15
     117: aload_0
     118: aload         15
     120: aload_2
     121: aload_3
     122: invokestatic  #407                // Method buildWithInfo$1:(Lnet/liftmodules/FoBoBs/snippet/FoBo/Bs3Navbar;Lscala/Function0;Lscala/Function1;Lnet/liftweb/sitemap/MenuItem;)Lscala/xml/Elem;
     125: astore        16
     127: goto          362
     130: getstatic     #412                // Field net/liftweb/common/Empty$.MODULE$:Lnet/liftweb/common/Empty$;
     133: aload         13
     135: astore        17
     137: dup
     138: ifnonnull     150
     141: pop
     142: aload         17
     144: ifnull        158
     147: goto          243
     150: aload         17
     152: invokevirtual #314                // Method java/lang/Object.equals:(Ljava/lang/Object;)Z
     155: ifeq          243
     158: aload         13
     160: astore        18
     162: aload_0
     163: new           #181                // class scala/xml/Group
     166: dup
     167: new           #157                // class scala/xml/NodeBuffer
     170: dup
     171: invokespecial #158                // Method scala/xml/NodeBuffer."<init>":()V
     174: astore        19
     176: aload         19
     178: aload_0
     179: aload_3
     180: invokevirtual #186                // Method net/liftweb/sitemap/MenuItem.uri:()Lscala/xml/NodeSeq;
     183: aload_3
     184: invokevirtual #189                // Method net/liftweb/sitemap/MenuItem.text:()Lscala/xml/NodeSeq;
     187: aload_3
     188: invokevirtual #192                // Method net/liftweb/sitemap/MenuItem.path:()Z
     191: aload_3
     192: invokevirtual #195                // Method net/liftweb/sitemap/MenuItem.current:()Z
     195: invokeinterface #199,  5          // InterfaceMethod net/liftmodules/FoBoBs/snippet/FoBo/Bs3Navbar.renderLink:(Lscala/xml/NodeSeq;Lscala/xml/NodeSeq;ZZ)Lscala/xml/NodeSeq;
     200: invokevirtual #162                // Method scala/xml/NodeBuffer.$amp$plus:(Ljava/lang/Object;)Lscala/xml/NodeBuffer;
     203: pop
     204: aload         19
     206: aload_2
     207: aload_3
     208: invokevirtual #203                // Method net/liftweb/sitemap/MenuItem.kids:()Lscala/collection/Seq;
     211: invokeinterface #209,  2          // InterfaceMethod scala/Function1.apply:(Ljava/lang/Object;)Ljava/lang/Object;
     216: invokevirtual #162                // Method scala/xml/NodeBuffer.$amp$plus:(Ljava/lang/Object;)Lscala/xml/NodeBuffer;
     219: pop
     220: aload         19
     222: invokespecial #212                // Method scala/xml/Group."<init>":(Lscala/collection/Seq;)V
     225: aload_3
     226: invokevirtual #192                // Method net/liftweb/sitemap/MenuItem.path:()Z
     229: aload_3
     230: invokevirtual #195                // Method net/liftweb/sitemap/MenuItem.current:()Z
     233: invokeinterface #216,  4          // InterfaceMethod net/liftmodules/FoBoBs/snippet/FoBo/Bs3Navbar.buildInnerTag:(Lscala/xml/NodeSeq;ZZ)Lscala/xml/Elem;
     238: astore        16
     240: goto          362
     243: aload         13
     245: instanceof    #414                // class net/liftweb/common/Failure
     248: ifeq          369
     251: aload         13
     253: checkcast     #414                // class net/liftweb/common/Failure
     256: astore        20
     258: aload         20
     260: ifnull        369
     263: aload         20
     265: invokevirtual #418                // Method net/liftweb/common/Failure.msg:()Ljava/lang/String;
     268: astore        21
     270: aload         20
     272: invokevirtual #422                // Method net/liftweb/common/Failure.exception:()Lnet/liftweb/common/Box;
     275: astore        22
     277: aload         20
     279: invokevirtual #425                // Method net/liftweb/common/Failure.chain:()Lnet/liftweb/common/Box;
     282: astore        23
     284: aload_0
     285: new           #181                // class scala/xml/Group
     288: dup
     289: new           #157                // class scala/xml/NodeBuffer
     292: dup
     293: invokespecial #158                // Method scala/xml/NodeBuffer."<init>":()V
     296: astore        24
     298: aload         24
     300: aload_0
     301: aload_3
     302: invokevirtual #186                // Method net/liftweb/sitemap/MenuItem.uri:()Lscala/xml/NodeSeq;
     305: aload_3
     306: invokevirtual #189                // Method net/liftweb/sitemap/MenuItem.text:()Lscala/xml/NodeSeq;
     309: aload_3
     310: invokevirtual #192                // Method net/liftweb/sitemap/MenuItem.path:()Z
     313: aload_3
     314: invokevirtual #195                // Method net/liftweb/sitemap/MenuItem.current:()Z
     317: invokeinterface #199,  5          // InterfaceMethod net/liftmodules/FoBoBs/snippet/FoBo/Bs3Navbar.renderLink:(Lscala/xml/NodeSeq;Lscala/xml/NodeSeq;ZZ)Lscala/xml/NodeSeq;
     322: invokevirtual #162                // Method scala/xml/NodeBuffer.$amp$plus:(Ljava/lang/Object;)Lscala/xml/NodeBuffer;
     325: pop
     326: aload         24
     328: aload_2
     329: aload_3
     330: invokevirtual #203                // Method net/liftweb/sitemap/MenuItem.kids:()Lscala/collection/Seq;
     333: invokeinterface #209,  2          // InterfaceMethod scala/Function1.apply:(Ljava/lang/Object;)Ljava/lang/Object;
     338: invokevirtual #162                // Method scala/xml/NodeBuffer.$amp$plus:(Ljava/lang/Object;)Lscala/xml/NodeBuffer;
     341: pop
     342: aload         24
     344: invokespecial #212                // Method scala/xml/Group."<init>":(Lscala/collection/Seq;)V
     347: aload_3
     348: invokevirtual #192                // Method net/liftweb/sitemap/MenuItem.path:()Z
     351: aload_3
     352: invokevirtual #195                // Method net/liftweb/sitemap/MenuItem.current:()Z
     355: invokeinterface #216,  4          // InterfaceMethod net/liftmodules/FoBoBs/snippet/FoBo/Bs3Navbar.buildInnerTag:(Lscala/xml/NodeSeq;ZZ)Lscala/xml/Elem;
     360: astore        16
     362: aload         16
     364: astore        12
     366: goto          670
     369: new           #427                // class scala/MatchError
     372: dup
     373: aload         13
     375: invokespecial #428                // Method scala/MatchError."<init>":(Ljava/lang/Object;)V
     378: athrow
     379: iload         5
     381: ifeq          560
     384: aload         6
     386: ifnull        560
     389: aload         6
     391: invokevirtual #397                // Method scala/collection/immutable/$colon$colon.hd$1:()Ljava/lang/Object;
     394: checkcast     #326                // class net/liftweb/common/Box
     397: astore        25
     399: aload         6
     401: invokevirtual #400                // Method scala/collection/immutable/$colon$colon.tl$1:()Lscala/collection/immutable/List;
     404: astore        26
     406: aload         25
     408: astore        27
     410: aload         27
     412: instanceof    #309                // class net/liftweb/common/Full
     415: ifeq          453
     418: aload         27
     420: checkcast     #309                // class net/liftweb/common/Full
     423: astore        28
     425: aload         28
     427: ifnull        453
     430: aload         28
     432: invokevirtual #403                // Method net/liftweb/common/Full.value:()Ljava/lang/Object;
     435: checkcast     #229                // class scala/Function0
     438: astore        29
     440: aload_0
     441: aload         29
     443: aload_2
     444: aload_3
     445: invokestatic  #407                // Method buildWithInfo$1:(Lnet/liftmodules/FoBoBs/snippet/FoBo/Bs3Navbar;Lscala/Function0;Lscala/Function1;Lnet/liftweb/sitemap/MenuItem;)Lscala/xml/Elem;
     448: astore        30
     450: goto          539
     453: getstatic     #412                // Field net/liftweb/common/Empty$.MODULE$:Lnet/liftweb/common/Empty$;
     456: aload         27
     458: astore        31
     460: dup
     461: ifnonnull     473
     464: pop
     465: aload         31
     467: ifnull        481
     470: goto          493
     473: aload         31
     475: invokevirtual #314                // Method java/lang/Object.equals:(Ljava/lang/Object;)Z
     478: ifeq          493
     481: aload         27
     483: astore        32
     485: getstatic     #434                // Field scala/runtime/BoxedUnit.UNIT:Lscala/runtime/BoxedUnit;
     488: astore        30
     490: goto          539
     493: aload         27
     495: instanceof    #414                // class net/liftweb/common/Failure
     498: ifeq          550
     501: aload         27
     503: checkcast     #414                // class net/liftweb/common/Failure
     506: astore        33
     508: aload         33
     510: ifnull        550
     513: aload         33
     515: invokevirtual #418                // Method net/liftweb/common/Failure.msg:()Ljava/lang/String;
     518: astore        34
     520: aload         33
     522: invokevirtual #422                // Method net/liftweb/common/Failure.exception:()Lnet/liftweb/common/Box;
     525: astore        35
     527: aload         33
     529: invokevirtual #425                // Method net/liftweb/common/Failure.chain:()Lnet/liftweb/common/Box;
     532: astore        36
     534: ldc_w         #436                // String
     537: astore        30
     539: aload         30
     541: pop
     542: aload_0
     543: aload         26
     545: astore_1
     546: astore_0
     547: goto          0
     550: new           #427                // class scala/MatchError
     553: dup
     554: aload         27
     556: invokespecial #428                // Method scala/MatchError."<init>":(Ljava/lang/Object;)V
     559: athrow
     560: getstatic     #301                // Field scala/collection/immutable/Nil$.MODULE$:Lscala/collection/immutable/Nil$;
     563: aload         7
     565: astore        37
     567: dup
     568: ifnonnull     580
     571: pop
     572: aload         37
     574: ifnull        588
     577: goto          673
     580: aload         37
     582: invokevirtual #314                // Method java/lang/Object.equals:(Ljava/lang/Object;)Z
     585: ifeq          673
     588: aload         7
     590: astore        38
     592: aload_0
     593: new           #181                // class scala/xml/Group
     596: dup
     597: new           #157                // class scala/xml/NodeBuffer
     600: dup
     601: invokespecial #158                // Method scala/xml/NodeBuffer."<init>":()V
     604: astore        39
     606: aload         39
     608: aload_0
     609: aload_3
     610: invokevirtual #186                // Method net/liftweb/sitemap/MenuItem.uri:()Lscala/xml/NodeSeq;
     613: aload_3
     614: invokevirtual #189                // Method net/liftweb/sitemap/MenuItem.text:()Lscala/xml/NodeSeq;
     617: aload_3
     618: invokevirtual #192                // Method net/liftweb/sitemap/MenuItem.path:()Z
     621: aload_3
     622: invokevirtual #195                // Method net/liftweb/sitemap/MenuItem.current:()Z
     625: invokeinterface #199,  5          // InterfaceMethod net/liftmodules/FoBoBs/snippet/FoBo/Bs3Navbar.renderLink:(Lscala/xml/NodeSeq;Lscala/xml/NodeSeq;ZZ)Lscala/xml/NodeSeq;
     630: invokevirtual #162                // Method scala/xml/NodeBuffer.$amp$plus:(Ljava/lang/Object;)Lscala/xml/NodeBuffer;
     633: pop
     634: aload         39
     636: aload_2
     637: aload_3
     638: invokevirtual #203                // Method net/liftweb/sitemap/MenuItem.kids:()Lscala/collection/Seq;
     641: invokeinterface #209,  2          // InterfaceMethod scala/Function1.apply:(Ljava/lang/Object;)Ljava/lang/Object;
     646: invokevirtual #162                // Method scala/xml/NodeBuffer.$amp$plus:(Ljava/lang/Object;)Lscala/xml/NodeBuffer;
     649: pop
     650: aload         39
     652: invokespecial #212                // Method scala/xml/Group."<init>":(Lscala/collection/Seq;)V
     655: aload_3
     656: invokevirtual #192                // Method net/liftweb/sitemap/MenuItem.path:()Z
     659: aload_3
     660: invokevirtual #195                // Method net/liftweb/sitemap/MenuItem.current:()Z
     663: invokeinterface #216,  4          // InterfaceMethod net/liftmodules/FoBoBs/snippet/FoBo/Bs3Navbar.buildInnerTag:(Lscala/xml/NodeSeq;ZZ)Lscala/xml/Elem;
     668: astore        12
     670: aload         12
     672: areturn
     673: new           #427                // class scala/MatchError
     676: dup
     677: aload         7
     679: invokespecial #428                // Method scala/MatchError."<init>":(Ljava/lang/Object;)V
     682: athrow

  private static final scala.xml.Elem buildWithInfo$1(net.liftmodules.FoBoBs.snippet.FoBo.Bs3Navbar, scala.Function0, scala.Function1, net.liftweb.sitemap.MenuItem);
    Code:
       0: aload_1
       1: invokeinterface #231,  1          // InterfaceMethod scala/Function0.apply:()Ljava/lang/Object;
       6: ldc_w         #374                // String divider
       9: invokevirtual #314                // Method java/lang/Object.equals:(Ljava/lang/Object;)Z
      12: ifeq          50
      15: aload_0
      16: new           #181                // class scala/xml/Group
      19: dup
      20: new           #157                // class scala/xml/NodeBuffer
      23: dup
      24: invokespecial #158                // Method scala/xml/NodeBuffer."<init>":()V
      27: astore        4
      29: aload         4
      31: invokespecial #212                // Method scala/xml/Group."<init>":(Lscala/collection/Seq;)V
      34: aload_3
      35: invokevirtual #192                // Method net/liftweb/sitemap/MenuItem.path:()Z
      38: aload_3
      39: invokevirtual #195                // Method net/liftweb/sitemap/MenuItem.current:()Z
      42: invokeinterface #452,  4          // InterfaceMethod net/liftmodules/FoBoBs/snippet/FoBo/Bs3Navbar.buildTBDivider:(Lscala/xml/NodeSeq;ZZ)Lscala/xml/Elem;
      47: goto          316
      50: aload_1
      51: invokeinterface #231,  1          // InterfaceMethod scala/Function0.apply:()Ljava/lang/Object;
      56: ldc_w         #377                // String divider-vertical
      59: invokevirtual #314                // Method java/lang/Object.equals:(Ljava/lang/Object;)Z
      62: ifeq          100
      65: aload_0
      66: new           #181                // class scala/xml/Group
      69: dup
      70: new           #157                // class scala/xml/NodeBuffer
      73: dup
      74: invokespecial #158                // Method scala/xml/NodeBuffer."<init>":()V
      77: astore        5
      79: aload         5
      81: invokespecial #212                // Method scala/xml/Group."<init>":(Lscala/collection/Seq;)V
      84: aload_3
      85: invokevirtual #192                // Method net/liftweb/sitemap/MenuItem.path:()Z
      88: aload_3
      89: invokevirtual #195                // Method net/liftweb/sitemap/MenuItem.current:()Z
      92: invokeinterface #454,  4          // InterfaceMethod net/liftmodules/FoBoBs/snippet/FoBo/Bs3Navbar.buildTBVerticalDivider:(Lscala/xml/NodeSeq;ZZ)Lscala/xml/Elem;
      97: goto          316
     100: aload_1
     101: invokeinterface #231,  1          // InterfaceMethod scala/Function0.apply:()Ljava/lang/Object;
     106: ldc_w         #456                // String _blank
     109: invokevirtual #314                // Method java/lang/Object.equals:(Ljava/lang/Object;)Z
     112: ifne          160
     115: aload_1
     116: invokeinterface #231,  1          // InterfaceMethod scala/Function0.apply:()Ljava/lang/Object;
     121: ldc_w         #458                // String _self
     124: invokevirtual #314                // Method java/lang/Object.equals:(Ljava/lang/Object;)Z
     127: ifne          160
     130: aload_1
     131: invokeinterface #231,  1          // InterfaceMethod scala/Function0.apply:()Ljava/lang/Object;
     136: ldc_w         #460                // String _parent
     139: invokevirtual #314                // Method java/lang/Object.equals:(Ljava/lang/Object;)Z
     142: ifne          160
     145: aload_1
     146: invokeinterface #231,  1          // InterfaceMethod scala/Function0.apply:()Ljava/lang/Object;
     151: ldc_w         #462                // String _top
     154: invokevirtual #314                // Method java/lang/Object.equals:(Ljava/lang/Object;)Z
     157: ifeq          240
     160: aload_0
     161: new           #181                // class scala/xml/Group
     164: dup
     165: new           #157                // class scala/xml/NodeBuffer
     168: dup
     169: invokespecial #158                // Method scala/xml/NodeBuffer."<init>":()V
     172: astore        6
     174: aload         6
     176: aload_0
     177: aload_3
     178: invokevirtual #186                // Method net/liftweb/sitemap/MenuItem.uri:()Lscala/xml/NodeSeq;
     181: aload_3
     182: invokevirtual #189                // Method net/liftweb/sitemap/MenuItem.text:()Lscala/xml/NodeSeq;
     185: aload_3
     186: invokevirtual #192                // Method net/liftweb/sitemap/MenuItem.path:()Z
     189: aload_3
     190: invokevirtual #195                // Method net/liftweb/sitemap/MenuItem.current:()Z
     193: aload_1
     194: invokeinterface #465,  6          // InterfaceMethod net/liftmodules/FoBoBs/snippet/FoBo/Bs3Navbar.renderLinkWithTarget:(Lscala/xml/NodeSeq;Lscala/xml/NodeSeq;ZZLscala/Function0;)Lscala/xml/NodeSeq;
     199: invokevirtual #162                // Method scala/xml/NodeBuffer.$amp$plus:(Ljava/lang/Object;)Lscala/xml/NodeBuffer;
     202: pop
     203: aload         6
     205: aload_2
     206: aload_3
     207: invokevirtual #203                // Method net/liftweb/sitemap/MenuItem.kids:()Lscala/collection/Seq;
     210: invokeinterface #209,  2          // InterfaceMethod scala/Function1.apply:(Ljava/lang/Object;)Ljava/lang/Object;
     215: invokevirtual #162                // Method scala/xml/NodeBuffer.$amp$plus:(Ljava/lang/Object;)Lscala/xml/NodeBuffer;
     218: pop
     219: aload         6
     221: invokespecial #212                // Method scala/xml/Group."<init>":(Lscala/collection/Seq;)V
     224: aload_3
     225: invokevirtual #192                // Method net/liftweb/sitemap/MenuItem.path:()Z
     228: aload_3
     229: invokevirtual #195                // Method net/liftweb/sitemap/MenuItem.current:()Z
     232: invokeinterface #216,  4          // InterfaceMethod net/liftmodules/FoBoBs/snippet/FoBo/Bs3Navbar.buildInnerTag:(Lscala/xml/NodeSeq;ZZ)Lscala/xml/Elem;
     237: goto          316
     240: aload_0
     241: new           #181                // class scala/xml/Group
     244: dup
     245: new           #157                // class scala/xml/NodeBuffer
     248: dup
     249: invokespecial #158                // Method scala/xml/NodeBuffer."<init>":()V
     252: astore        7
     254: aload         7
     256: aload_0
     257: aload_3
     258: invokevirtual #186                // Method net/liftweb/sitemap/MenuItem.uri:()Lscala/xml/NodeSeq;
     261: aload_3
     262: invokevirtual #189                // Method net/liftweb/sitemap/MenuItem.text:()Lscala/xml/NodeSeq;
     265: aload_3
     266: invokevirtual #192                // Method net/liftweb/sitemap/MenuItem.path:()Z
     269: aload_3
     270: invokevirtual #195                // Method net/liftweb/sitemap/MenuItem.current:()Z
     273: invokeinterface #199,  5          // InterfaceMethod net/liftmodules/FoBoBs/snippet/FoBo/Bs3Navbar.renderLink:(Lscala/xml/NodeSeq;Lscala/xml/NodeSeq;ZZ)Lscala/xml/NodeSeq;
     278: invokevirtual #162                // Method scala/xml/NodeBuffer.$amp$plus:(Ljava/lang/Object;)Lscala/xml/NodeBuffer;
     281: pop
     282: aload         7
     284: aload_2
     285: aload_3
     286: invokevirtual #203                // Method net/liftweb/sitemap/MenuItem.kids:()Lscala/collection/Seq;
     289: invokeinterface #209,  2          // InterfaceMethod scala/Function1.apply:(Ljava/lang/Object;)Ljava/lang/Object;
     294: invokevirtual #162                // Method scala/xml/NodeBuffer.$amp$plus:(Ljava/lang/Object;)Lscala/xml/NodeBuffer;
     297: pop
     298: aload         7
     300: invokespecial #212                // Method scala/xml/Group."<init>":(Lscala/collection/Seq;)V
     303: aload_3
     304: invokevirtual #192                // Method net/liftweb/sitemap/MenuItem.path:()Z
     307: aload_3
     308: invokevirtual #195                // Method net/liftweb/sitemap/MenuItem.current:()Z
     311: invokeinterface #216,  4          // InterfaceMethod net/liftmodules/FoBoBs/snippet/FoBo/Bs3Navbar.buildInnerTag:(Lscala/xml/NodeSeq;ZZ)Lscala/xml/Elem;
     316: areturn

  public static void $init$(net.liftmodules.FoBoBs.snippet.FoBo.Bs3Navbar);
    Code:
       0: aload_0
       1: iconst_0
       2: invokeinterface #105,  2          // InterfaceMethod net/liftmodules/FoBoBs/snippet/FoBo/Bs3Navbar.net$liftmodules$FoBoBs$snippet$FoBo$Bs3Navbar$$pullRight_$eq:(Z)V
       7: return
}
