Compiled from "ViewControllerRegistry.java"
public class org.springframework.web.servlet.config.annotation.ViewControllerRegistry {
  private org.springframework.context.ApplicationContext applicationContext;

  private final java.util.List<org.springframework.web.servlet.config.annotation.ViewControllerRegistration> registrations;

  private final java.util.List<org.springframework.web.servlet.config.annotation.RedirectViewControllerRegistration> redirectRegistrations;

  private int order;

  public org.springframework.web.servlet.config.annotation.ViewControllerRegistry(org.springframework.context.ApplicationContext);
    Code:
       0: aload_0
       1: invokespecial #1                  // Method java/lang/Object."<init>":()V
       4: aload_0
       5: new           #2                  // class java/util/ArrayList
       8: dup
       9: iconst_4
      10: invokespecial #3                  // Method java/util/ArrayList."<init>":(I)V
      13: putfield      #4                  // Field registrations:Ljava/util/List;
      16: aload_0
      17: new           #2                  // class java/util/ArrayList
      20: dup
      21: bipush        10
      23: invokespecial #3                  // Method java/util/ArrayList."<init>":(I)V
      26: putfield      #5                  // Field redirectRegistrations:Ljava/util/List;
      29: aload_0
      30: iconst_1
      31: putfield      #6                  // Field order:I
      34: aload_0
      35: aload_1
      36: putfield      #7                  // Field applicationContext:Lorg/springframework/context/ApplicationContext;
      39: return

  public org.springframework.web.servlet.config.annotation.ViewControllerRegistration addViewController(java.lang.String);
    Code:
       0: new           #8                  // class org/springframework/web/servlet/config/annotation/ViewControllerRegistration
       3: dup
       4: aload_1
       5: invokespecial #9                  // Method org/springframework/web/servlet/config/annotation/ViewControllerRegistration."<init>":(Ljava/lang/String;)V
       8: astore_2
       9: aload_2
      10: aload_0
      11: getfield      #7                  // Field applicationContext:Lorg/springframework/context/ApplicationContext;
      14: invokevirtual #10                 // Method org/springframework/web/servlet/config/annotation/ViewControllerRegistration.setApplicationContext:(Lorg/springframework/context/ApplicationContext;)V
      17: aload_0
      18: getfield      #4                  // Field registrations:Ljava/util/List;
      21: aload_2
      22: invokeinterface #11,  2           // InterfaceMethod java/util/List.add:(Ljava/lang/Object;)Z
      27: pop
      28: aload_2
      29: areturn

  public org.springframework.web.servlet.config.annotation.RedirectViewControllerRegistration addRedirectViewController(java.lang.String, java.lang.String);
    Code:
       0: new           #12                 // class org/springframework/web/servlet/config/annotation/RedirectViewControllerRegistration
       3: dup
       4: aload_1
       5: aload_2
       6: invokespecial #13                 // Method org/springframework/web/servlet/config/annotation/RedirectViewControllerRegistration."<init>":(Ljava/lang/String;Ljava/lang/String;)V
       9: astore_3
      10: aload_3
      11: aload_0
      12: getfield      #7                  // Field applicationContext:Lorg/springframework/context/ApplicationContext;
      15: invokevirtual #14                 // Method org/springframework/web/servlet/config/annotation/RedirectViewControllerRegistration.setApplicationContext:(Lorg/springframework/context/ApplicationContext;)V
      18: aload_0
      19: getfield      #5                  // Field redirectRegistrations:Ljava/util/List;
      22: aload_3
      23: invokeinterface #11,  2           // InterfaceMethod java/util/List.add:(Ljava/lang/Object;)Z
      28: pop
      29: aload_3
      30: areturn

  public void addStatusController(java.lang.String, org.springframework.http.HttpStatus);
    Code:
       0: new           #8                  // class org/springframework/web/servlet/config/annotation/ViewControllerRegistration
       3: dup
       4: aload_1
       5: invokespecial #9                  // Method org/springframework/web/servlet/config/annotation/ViewControllerRegistration."<init>":(Ljava/lang/String;)V
       8: astore_3
       9: aload_3
      10: aload_0
      11: getfield      #7                  // Field applicationContext:Lorg/springframework/context/ApplicationContext;
      14: invokevirtual #10                 // Method org/springframework/web/servlet/config/annotation/ViewControllerRegistration.setApplicationContext:(Lorg/springframework/context/ApplicationContext;)V
      17: aload_3
      18: aload_2
      19: invokevirtual #15                 // Method org/springframework/web/servlet/config/annotation/ViewControllerRegistration.setStatusCode:(Lorg/springframework/http/HttpStatus;)Lorg/springframework/web/servlet/config/annotation/ViewControllerRegistration;
      22: pop
      23: aload_3
      24: invokevirtual #16                 // Method org/springframework/web/servlet/config/annotation/ViewControllerRegistration.getViewController:()Lorg/springframework/web/servlet/mvc/ParameterizableViewController;
      27: iconst_1
      28: invokevirtual #17                 // Method org/springframework/web/servlet/mvc/ParameterizableViewController.setStatusOnly:(Z)V
      31: aload_0
      32: getfield      #4                  // Field registrations:Ljava/util/List;
      35: aload_3
      36: invokeinterface #11,  2           // InterfaceMethod java/util/List.add:(Ljava/lang/Object;)Z
      41: pop
      42: return

  public void setOrder(int);
    Code:
       0: aload_0
       1: iload_1
       2: putfield      #6                  // Field order:I
       5: return

  protected org.springframework.web.servlet.handler.SimpleUrlHandlerMapping buildHandlerMapping();
    Code:
       0: aload_0
       1: getfield      #4                  // Field registrations:Ljava/util/List;
       4: invokeinterface #18,  1           // InterfaceMethod java/util/List.isEmpty:()Z
       9: ifeq          26
      12: aload_0
      13: getfield      #5                  // Field redirectRegistrations:Ljava/util/List;
      16: invokeinterface #18,  1           // InterfaceMethod java/util/List.isEmpty:()Z
      21: ifeq          26
      24: aconst_null
      25: areturn
      26: new           #19                 // class java/util/LinkedHashMap
      29: dup
      30: invokespecial #20                 // Method java/util/LinkedHashMap."<init>":()V
      33: astore_1
      34: aload_0
      35: getfield      #4                  // Field registrations:Ljava/util/List;
      38: invokeinterface #21,  1           // InterfaceMethod java/util/List.iterator:()Ljava/util/Iterator;
      43: astore_2
      44: aload_2
      45: invokeinterface #22,  1           // InterfaceMethod java/util/Iterator.hasNext:()Z
      50: ifeq          81
      53: aload_2
      54: invokeinterface #23,  1           // InterfaceMethod java/util/Iterator.next:()Ljava/lang/Object;
      59: checkcast     #8                  // class org/springframework/web/servlet/config/annotation/ViewControllerRegistration
      62: astore_3
      63: aload_1
      64: aload_3
      65: invokevirtual #24                 // Method org/springframework/web/servlet/config/annotation/ViewControllerRegistration.getUrlPath:()Ljava/lang/String;
      68: aload_3
      69: invokevirtual #16                 // Method org/springframework/web/servlet/config/annotation/ViewControllerRegistration.getViewController:()Lorg/springframework/web/servlet/mvc/ParameterizableViewController;
      72: invokeinterface #25,  3           // InterfaceMethod java/util/Map.put:(Ljava/lang/Object;Ljava/lang/Object;)Ljava/lang/Object;
      77: pop
      78: goto          44
      81: aload_0
      82: getfield      #5                  // Field redirectRegistrations:Ljava/util/List;
      85: invokeinterface #21,  1           // InterfaceMethod java/util/List.iterator:()Ljava/util/Iterator;
      90: astore_2
      91: aload_2
      92: invokeinterface #22,  1           // InterfaceMethod java/util/Iterator.hasNext:()Z
      97: ifeq          128
     100: aload_2
     101: invokeinterface #23,  1           // InterfaceMethod java/util/Iterator.next:()Ljava/lang/Object;
     106: checkcast     #12                 // class org/springframework/web/servlet/config/annotation/RedirectViewControllerRegistration
     109: astore_3
     110: aload_1
     111: aload_3
     112: invokevirtual #26                 // Method org/springframework/web/servlet/config/annotation/RedirectViewControllerRegistration.getUrlPath:()Ljava/lang/String;
     115: aload_3
     116: invokevirtual #27                 // Method org/springframework/web/servlet/config/annotation/RedirectViewControllerRegistration.getViewController:()Lorg/springframework/web/servlet/mvc/ParameterizableViewController;
     119: invokeinterface #25,  3           // InterfaceMethod java/util/Map.put:(Ljava/lang/Object;Ljava/lang/Object;)Ljava/lang/Object;
     124: pop
     125: goto          91
     128: new           #28                 // class org/springframework/web/servlet/handler/SimpleUrlHandlerMapping
     131: dup
     132: aload_1
     133: aload_0
     134: getfield      #6                  // Field order:I
     137: invokespecial #29                 // Method org/springframework/web/servlet/handler/SimpleUrlHandlerMapping."<init>":(Ljava/util/Map;I)V
     140: areturn
}
