Compiled from "CatalogURIResolver.java"
public class org.apache.axis2.jaxws.util.CatalogURIResolver extends org.apache.axis2.jaxws.description.impl.URIResolverImpl {
  private static org.apache.commons.logging.Log log;

  private org.apache.xml.resolver.Catalog catalogResolver;

  public org.apache.axis2.jaxws.util.CatalogURIResolver(org.apache.axis2.jaxws.catalog.JAXWSCatalogManager);
    Code:
       0: aload_0
       1: aload_1
       2: aconst_null
       3: invokespecial #1                  // Method "<init>":(Lorg/apache/axis2/jaxws/catalog/JAXWSCatalogManager;Ljava/lang/ClassLoader;)V
       6: return

  public org.apache.axis2.jaxws.util.CatalogURIResolver(org.apache.axis2.jaxws.catalog.JAXWSCatalogManager, java.lang.ClassLoader);
    Code:
       0: aload_0
       1: aload_2
       2: invokespecial #2                  // Method org/apache/axis2/jaxws/description/impl/URIResolverImpl."<init>":(Ljava/lang/ClassLoader;)V
       5: getstatic     #3                  // Field log:Lorg/apache/commons/logging/Log;
       8: invokeinterface #4,  1            // InterfaceMethod org/apache/commons/logging/Log.isDebugEnabled:()Z
      13: ifeq          43
      16: getstatic     #3                  // Field log:Lorg/apache/commons/logging/Log;
      19: new           #5                  // class java/lang/StringBuilder
      22: dup
      23: invokespecial #6                  // Method java/lang/StringBuilder."<init>":()V
      26: ldc           #7                  // String init: catalogManager :
      28: invokevirtual #8                  // Method java/lang/StringBuilder.append:(Ljava/lang/String;)Ljava/lang/StringBuilder;
      31: aload_1
      32: invokevirtual #9                  // Method java/lang/StringBuilder.append:(Ljava/lang/Object;)Ljava/lang/StringBuilder;
      35: invokevirtual #10                 // Method java/lang/StringBuilder.toString:()Ljava/lang/String;
      38: invokeinterface #11,  2           // InterfaceMethod org/apache/commons/logging/Log.debug:(Ljava/lang/Object;)V
      43: aload_1
      44: ifnull        57
      47: aload_0
      48: aload_1
      49: invokeinterface #12,  1           // InterfaceMethod org/apache/axis2/jaxws/catalog/JAXWSCatalogManager.getCatalog:()Lorg/apache/xml/resolver/Catalog;
      54: putfield      #13                 // Field catalogResolver:Lorg/apache/xml/resolver/Catalog;
      57: return

  public java.lang.String getRedirectedURI(java.lang.String, java.lang.String, java.lang.String);
    Code:
       0: aconst_null
       1: astore        4
       3: aload_0
       4: getfield      #13                 // Field catalogResolver:Lorg/apache/xml/resolver/Catalog;
       7: aload_2
       8: invokevirtual #14                 // Method org/apache/xml/resolver/Catalog.resolveSystem:(Ljava/lang/String;)Ljava/lang/String;
      11: astore        4
      13: aload         4
      15: ifnonnull     28
      18: aload_0
      19: getfield      #13                 // Field catalogResolver:Lorg/apache/xml/resolver/Catalog;
      22: aload_1
      23: invokevirtual #14                 // Method org/apache/xml/resolver/Catalog.resolveSystem:(Ljava/lang/String;)Ljava/lang/String;
      26: astore        4
      28: aload         4
      30: ifnonnull     43
      33: aload_0
      34: getfield      #13                 // Field catalogResolver:Lorg/apache/xml/resolver/Catalog;
      37: aload_2
      38: invokevirtual #15                 // Method org/apache/xml/resolver/Catalog.resolveURI:(Ljava/lang/String;)Ljava/lang/String;
      41: astore        4
      43: aload         4
      45: ifnonnull     59
      48: aload_0
      49: getfield      #13                 // Field catalogResolver:Lorg/apache/xml/resolver/Catalog;
      52: aload_1
      53: aload_1
      54: invokevirtual #16                 // Method org/apache/xml/resolver/Catalog.resolvePublic:(Ljava/lang/String;Ljava/lang/String;)Ljava/lang/String;
      57: astore        4
      59: goto          97
      62: astore        5
      64: getstatic     #3                  // Field log:Lorg/apache/commons/logging/Log;
      67: invokeinterface #4,  1            // InterfaceMethod org/apache/commons/logging/Log.isDebugEnabled:()Z
      72: ifeq          85
      75: getstatic     #3                  // Field log:Lorg/apache/commons/logging/Log;
      78: ldc           #18                 // String getRedirectedURI error: Catalog resolution failed
      80: invokeinterface #11,  2           // InterfaceMethod org/apache/commons/logging/Log.debug:(Ljava/lang/Object;)V
      85: new           #19                 // class java/lang/RuntimeException
      88: dup
      89: ldc           #20                 // String Catalog resolution failed
      91: aload         5
      93: invokespecial #21                 // Method java/lang/RuntimeException."<init>":(Ljava/lang/String;Ljava/lang/Throwable;)V
      96: athrow
      97: getstatic     #3                  // Field log:Lorg/apache/commons/logging/Log;
     100: invokeinterface #4,  1            // InterfaceMethod org/apache/commons/logging/Log.isDebugEnabled:()Z
     105: ifeq          136
     108: getstatic     #3                  // Field log:Lorg/apache/commons/logging/Log;
     111: new           #5                  // class java/lang/StringBuilder
     114: dup
     115: invokespecial #6                  // Method java/lang/StringBuilder."<init>":()V
     118: ldc           #22                 // String getRedirectedURI exit: redirected location:
     120: invokevirtual #8                  // Method java/lang/StringBuilder.append:(Ljava/lang/String;)Ljava/lang/StringBuilder;
     123: aload         4
     125: invokevirtual #8                  // Method java/lang/StringBuilder.append:(Ljava/lang/String;)Ljava/lang/StringBuilder;
     128: invokevirtual #10                 // Method java/lang/StringBuilder.toString:()Ljava/lang/String;
     131: invokeinterface #11,  2           // InterfaceMethod org/apache/commons/logging/Log.debug:(Ljava/lang/Object;)V
     136: aload         4
     138: areturn
    Exception table:
       from    to  target type
           3    59    62   Class java/io/IOException

  public org.xml.sax.InputSource resolveEntity(java.lang.String, java.lang.String, java.lang.String);
    Code:
       0: getstatic     #3                  // Field log:Lorg/apache/commons/logging/Log;
       3: invokeinterface #4,  1            // InterfaceMethod org/apache/commons/logging/Log.isDebugEnabled:()Z
       8: ifeq          61
      11: getstatic     #3                  // Field log:Lorg/apache/commons/logging/Log;
      14: new           #5                  // class java/lang/StringBuilder
      17: dup
      18: invokespecial #6                  // Method java/lang/StringBuilder."<init>":()V
      21: ldc           #23                 // String resolveEntity: [
      23: invokevirtual #8                  // Method java/lang/StringBuilder.append:(Ljava/lang/String;)Ljava/lang/StringBuilder;
      26: aload_1
      27: invokevirtual #8                  // Method java/lang/StringBuilder.append:(Ljava/lang/String;)Ljava/lang/StringBuilder;
      30: ldc           #24                 // String ][
      32: invokevirtual #8                  // Method java/lang/StringBuilder.append:(Ljava/lang/String;)Ljava/lang/StringBuilder;
      35: aload_2
      36: invokevirtual #8                  // Method java/lang/StringBuilder.append:(Ljava/lang/String;)Ljava/lang/StringBuilder;
      39: ldc           #25                 // String ][
      41: invokevirtual #8                  // Method java/lang/StringBuilder.append:(Ljava/lang/String;)Ljava/lang/StringBuilder;
      44: aload_3
      45: invokevirtual #8                  // Method java/lang/StringBuilder.append:(Ljava/lang/String;)Ljava/lang/StringBuilder;
      48: ldc           #26                 // String ]
      50: invokevirtual #8                  // Method java/lang/StringBuilder.append:(Ljava/lang/String;)Ljava/lang/StringBuilder;
      53: invokevirtual #10                 // Method java/lang/StringBuilder.toString:()Ljava/lang/String;
      56: invokeinterface #11,  2           // InterfaceMethod org/apache/commons/logging/Log.debug:(Ljava/lang/Object;)V
      61: aconst_null
      62: astore        4
      64: aload_0
      65: getfield      #13                 // Field catalogResolver:Lorg/apache/xml/resolver/Catalog;
      68: ifnull        114
      71: getstatic     #3                  // Field log:Lorg/apache/commons/logging/Log;
      74: invokeinterface #4,  1            // InterfaceMethod org/apache/commons/logging/Log.isDebugEnabled:()Z
      79: ifeq          92
      82: getstatic     #3                  // Field log:Lorg/apache/commons/logging/Log;
      85: ldc           #27                 // String catalogResolver found, calling CatalogURIResolver.getRedirectedURI.
      87: invokeinterface #11,  2           // InterfaceMethod org/apache/commons/logging/Log.debug:(Ljava/lang/Object;)V
      92: aload_0
      93: aload_1
      94: aload_2
      95: aload_3
      96: invokevirtual #28                 // Method getRedirectedURI:(Ljava/lang/String;Ljava/lang/String;Ljava/lang/String;)Ljava/lang/String;
      99: astore        5
     101: aload         5
     103: ifnull        114
     106: aload_0
     107: aload         5
     109: invokespecial #29                 // Method getInputSourceFromRedirectedURI:(Ljava/lang/String;)Lorg/xml/sax/InputSource;
     112: astore        4
     114: aload         4
     116: ifnull        122
     119: aload         4
     121: areturn
     122: aload_0
     123: aload_1
     124: aload_2
     125: aload_3
     126: invokespecial #30                 // Method org/apache/axis2/jaxws/description/impl/URIResolverImpl.resolveEntity:(Ljava/lang/String;Ljava/lang/String;Ljava/lang/String;)Lorg/xml/sax/InputSource;
     129: areturn

  private org.xml.sax.InputSource getInputSourceFromRedirectedURI(java.lang.String);
    Code:
       0: aconst_null
       1: astore_2
       2: aconst_null
       3: astore_3
       4: aconst_null
       5: astore        4
       7: aload_0
       8: aload_1
       9: invokevirtual #31                 // Method isAbsolute:(Ljava/lang/String;)Z
      12: ifeq          27
      15: aload_0
      16: aload_1
      17: invokevirtual #32                 // Method getInputStreamForURI:(Ljava/lang/String;)Ljava/io/InputStream;
      20: astore_2
      21: aload_2
      22: ifnull        27
      25: aload_1
      26: astore_3
      27: aload_2
      28: ifnonnull     210
      31: aload_0
      32: getfield      #33                 // Field classLoader:Ljava/lang/ClassLoader;
      35: ifnull        210
      38: aload_0
      39: getfield      #33                 // Field classLoader:Ljava/lang/ClassLoader;
      42: aload_1
      43: invokevirtual #34                 // Method java/lang/ClassLoader.getResourceAsStream:(Ljava/lang/String;)Ljava/io/InputStream;
      46: astore_2
      47: aload_2
      48: ifnull        53
      51: aload_1
      52: astore_3
      53: goto          100
      56: astore        5
      58: getstatic     #3                  // Field log:Lorg/apache/commons/logging/Log;
      61: invokeinterface #4,  1            // InterfaceMethod org/apache/commons/logging/Log.isDebugEnabled:()Z
      66: ifeq          100
      69: getstatic     #3                  // Field log:Lorg/apache/commons/logging/Log;
      72: new           #5                  // class java/lang/StringBuilder
      75: dup
      76: invokespecial #6                  // Method java/lang/StringBuilder."<init>":()V
      79: ldc           #36                 // String Exception occured in validateRedirectedURI, ignoring exception continuing processing:
      81: invokevirtual #8                  // Method java/lang/StringBuilder.append:(Ljava/lang/String;)Ljava/lang/StringBuilder;
      84: aload         5
      86: invokevirtual #37                 // Method java/lang/Throwable.getMessage:()Ljava/lang/String;
      89: invokevirtual #8                  // Method java/lang/StringBuilder.append:(Ljava/lang/String;)Ljava/lang/StringBuilder;
      92: invokevirtual #10                 // Method java/lang/StringBuilder.toString:()Ljava/lang/String;
      95: invokeinterface #11,  2           // InterfaceMethod org/apache/commons/logging/Log.debug:(Ljava/lang/Object;)V
     100: aload_2
     101: ifnonnull     210
     104: aload_0
     105: aload_1
     106: invokespecial #38                 // Method stripProtocol:(Ljava/lang/String;)Ljava/lang/String;
     109: astore_1
     110: getstatic     #3                  // Field log:Lorg/apache/commons/logging/Log;
     113: invokeinterface #4,  1            // InterfaceMethod org/apache/commons/logging/Log.isDebugEnabled:()Z
     118: ifeq          148
     121: getstatic     #3                  // Field log:Lorg/apache/commons/logging/Log;
     124: new           #5                  // class java/lang/StringBuilder
     127: dup
     128: invokespecial #6                  // Method java/lang/StringBuilder."<init>":()V
     131: ldc           #39                 // String getInputSourceFromRedirectedURI: new redirected location:
     133: invokevirtual #8                  // Method java/lang/StringBuilder.append:(Ljava/lang/String;)Ljava/lang/StringBuilder;
     136: aload_1
     137: invokevirtual #8                  // Method java/lang/StringBuilder.append:(Ljava/lang/String;)Ljava/lang/StringBuilder;
     140: invokevirtual #10                 // Method java/lang/StringBuilder.toString:()Ljava/lang/String;
     143: invokeinterface #11,  2           // InterfaceMethod org/apache/commons/logging/Log.debug:(Ljava/lang/Object;)V
     148: aload_0
     149: getfield      #33                 // Field classLoader:Ljava/lang/ClassLoader;
     152: aload_1
     153: invokevirtual #34                 // Method java/lang/ClassLoader.getResourceAsStream:(Ljava/lang/String;)Ljava/io/InputStream;
     156: astore_2
     157: aload_2
     158: ifnull        163
     161: aload_1
     162: astore_3
     163: goto          210
     166: astore        5
     168: getstatic     #3                  // Field log:Lorg/apache/commons/logging/Log;
     171: invokeinterface #4,  1            // InterfaceMethod org/apache/commons/logging/Log.isDebugEnabled:()Z
     176: ifeq          210
     179: getstatic     #3                  // Field log:Lorg/apache/commons/logging/Log;
     182: new           #5                  // class java/lang/StringBuilder
     185: dup
     186: invokespecial #6                  // Method java/lang/StringBuilder."<init>":()V
     189: ldc           #36                 // String Exception occured in validateRedirectedURI, ignoring exception continuing processing:
     191: invokevirtual #8                  // Method java/lang/StringBuilder.append:(Ljava/lang/String;)Ljava/lang/StringBuilder;
     194: aload         5
     196: invokevirtual #37                 // Method java/lang/Throwable.getMessage:()Ljava/lang/String;
     199: invokevirtual #8                  // Method java/lang/StringBuilder.append:(Ljava/lang/String;)Ljava/lang/StringBuilder;
     202: invokevirtual #10                 // Method java/lang/StringBuilder.toString:()Ljava/lang/String;
     205: invokeinterface #11,  2           // InterfaceMethod org/apache/commons/logging/Log.debug:(Ljava/lang/Object;)V
     210: aload_2
     211: ifnull        318
     214: getstatic     #3                  // Field log:Lorg/apache/commons/logging/Log;
     217: invokeinterface #4,  1            // InterfaceMethod org/apache/commons/logging/Log.isDebugEnabled:()Z
     222: ifeq          252
     225: getstatic     #3                  // Field log:Lorg/apache/commons/logging/Log;
     228: new           #5                  // class java/lang/StringBuilder
     231: dup
     232: invokespecial #6                  // Method java/lang/StringBuilder."<init>":()V
     235: ldc           #40                 // String getInputSourceFromRedirectedURI: XSD input stream is not null after resolving import for:
     237: invokevirtual #8                  // Method java/lang/StringBuilder.append:(Ljava/lang/String;)Ljava/lang/StringBuilder;
     240: aload_1
     241: invokevirtual #8                  // Method java/lang/StringBuilder.append:(Ljava/lang/String;)Ljava/lang/StringBuilder;
     244: invokevirtual #10                 // Method java/lang/StringBuilder.toString:()Ljava/lang/String;
     247: invokeinterface #11,  2           // InterfaceMethod org/apache/commons/logging/Log.debug:(Ljava/lang/Object;)V
     252: new           #41                 // class org/xml/sax/InputSource
     255: dup
     256: aload_2
     257: invokespecial #42                 // Method org/xml/sax/InputSource."<init>":(Ljava/io/InputStream;)V
     260: astore        4
     262: aload         4
     264: aload_3
     265: ifnull        272
     268: aload_3
     269: goto          273
     272: aload_1
     273: invokevirtual #43                 // Method org/xml/sax/InputSource.setSystemId:(Ljava/lang/String;)V
     276: getstatic     #3                  // Field log:Lorg/apache/commons/logging/Log;
     279: invokeinterface #4,  1            // InterfaceMethod org/apache/commons/logging/Log.isDebugEnabled:()Z
     284: ifeq          318
     287: getstatic     #3                  // Field log:Lorg/apache/commons/logging/Log;
     290: new           #5                  // class java/lang/StringBuilder
     293: dup
     294: invokespecial #6                  // Method java/lang/StringBuilder."<init>":()V
     297: ldc           #44                 // String returnInputSource :
     299: invokevirtual #8                  // Method java/lang/StringBuilder.append:(Ljava/lang/String;)Ljava/lang/StringBuilder;
     302: aload         4
     304: invokevirtual #45                 // Method org/xml/sax/InputSource.getSystemId:()Ljava/lang/String;
     307: invokevirtual #8                  // Method java/lang/StringBuilder.append:(Ljava/lang/String;)Ljava/lang/StringBuilder;
     310: invokevirtual #10                 // Method java/lang/StringBuilder.toString:()Ljava/lang/String;
     313: invokeinterface #11,  2           // InterfaceMethod org/apache/commons/logging/Log.debug:(Ljava/lang/Object;)V
     318: aload         4
     320: areturn
    Exception table:
       from    to  target type
          38    53    56   Class java/lang/Throwable
         148   163   166   Class java/lang/Throwable

  private java.lang.String stripProtocol(java.lang.String);
    Code:
       0: aload_1
       1: bipush        92
       3: bipush        47
       5: invokevirtual #46                 // Method java/lang/String.replace:(CC)Ljava/lang/String;
       8: astore_2
       9: aload_2
      10: ldc           #47                 // String ://
      12: invokevirtual #48                 // Method java/lang/String.indexOf:(Ljava/lang/String;)I
      15: istore_3
      16: iload_3
      17: iconst_m1
      18: if_icmpeq     29
      21: aload_2
      22: iload_3
      23: iconst_3
      24: iadd
      25: invokevirtual #49                 // Method java/lang/String.substring:(I)Ljava/lang/String;
      28: astore_2
      29: aload_2
      30: areturn

  static {};
    Code:
       0: ldc           #50                 // class org/apache/axis2/jaxws/util/CatalogURIResolver
       2: invokestatic  #51                 // Method org/apache/commons/logging/LogFactory.getLog:(Ljava/lang/Class;)Lorg/apache/commons/logging/Log;
       5: putstatic     #3                  // Field log:Lorg/apache/commons/logging/Log;
       8: return
}
