Compiled from "ClassLoaderUtils.java"
public class org.apache.axis2.jaxws.util.ClassLoaderUtils {
  private static final org.apache.commons.logging.Log log;

  public org.apache.axis2.jaxws.util.ClassLoaderUtils();
    Code:
       0: aload_0
       1: invokespecial #1                  // Method java/lang/Object."<init>":()V
       4: return

  public static java.lang.ClassLoader getClassLoader(java.lang.Class);
    Code:
       0: aconst_null
       1: astore_1
       2: new           #2                  // class org/apache/axis2/jaxws/util/ClassLoaderUtils$1
       5: dup
       6: aload_0
       7: invokespecial #3                  // Method org/apache/axis2/jaxws/util/ClassLoaderUtils$1."<init>":(Ljava/lang/Class;)V
      10: invokestatic  #4                  // Method org/apache/axis2/java/security/AccessController.doPrivileged:(Ljava/security/PrivilegedExceptionAction;)Ljava/lang/Object;
      13: checkcast     #5                  // class java/lang/ClassLoader
      16: astore_1
      17: goto          67
      20: astore_2
      21: getstatic     #7                  // Field log:Lorg/apache/commons/logging/Log;
      24: invokeinterface #8,  1            // InterfaceMethod org/apache/commons/logging/Log.isDebugEnabled:()Z
      29: ifeq          59
      32: getstatic     #7                  // Field log:Lorg/apache/commons/logging/Log;
      35: new           #9                  // class java/lang/StringBuilder
      38: dup
      39: invokespecial #10                 // Method java/lang/StringBuilder."<init>":()V
      42: ldc           #11                 // String Exception thrown from AccessController:
      44: invokevirtual #12                 // Method java/lang/StringBuilder.append:(Ljava/lang/String;)Ljava/lang/StringBuilder;
      47: aload_2
      48: invokevirtual #13                 // Method java/lang/StringBuilder.append:(Ljava/lang/Object;)Ljava/lang/StringBuilder;
      51: invokevirtual #14                 // Method java/lang/StringBuilder.toString:()Ljava/lang/String;
      54: invokeinterface #15,  2           // InterfaceMethod org/apache/commons/logging/Log.debug:(Ljava/lang/Object;)V
      59: aload_2
      60: invokevirtual #16                 // Method java/security/PrivilegedActionException.getException:()Ljava/lang/Exception;
      63: invokestatic  #17                 // Method org/apache/axis2/jaxws/ExceptionFactory.makeWebServiceException:(Ljava/lang/Throwable;)Ljavax/xml/ws/WebServiceException;
      66: athrow
      67: aload_1
      68: areturn
    Exception table:
       from    to  target type
           2    17    20   Class java/security/PrivilegedActionException

  public static java.lang.ClassLoader getContextClassLoader(java.lang.ClassLoader);
    Code:
       0: new           #18                 // class org/apache/axis2/jaxws/util/ClassLoaderUtils$2
       3: dup
       4: aload_0
       5: invokespecial #19                 // Method org/apache/axis2/jaxws/util/ClassLoaderUtils$2."<init>":(Ljava/lang/ClassLoader;)V
       8: invokestatic  #4                  // Method org/apache/axis2/java/security/AccessController.doPrivileged:(Ljava/security/PrivilegedExceptionAction;)Ljava/lang/Object;
      11: checkcast     #5                  // class java/lang/ClassLoader
      14: astore_1
      15: goto          69
      18: astore_2
      19: getstatic     #7                  // Field log:Lorg/apache/commons/logging/Log;
      22: invokeinterface #8,  1            // InterfaceMethod org/apache/commons/logging/Log.isDebugEnabled:()Z
      27: ifeq          61
      30: getstatic     #7                  // Field log:Lorg/apache/commons/logging/Log;
      33: new           #9                  // class java/lang/StringBuilder
      36: dup
      37: invokespecial #10                 // Method java/lang/StringBuilder."<init>":()V
      40: ldc           #11                 // String Exception thrown from AccessController:
      42: invokevirtual #12                 // Method java/lang/StringBuilder.append:(Ljava/lang/String;)Ljava/lang/StringBuilder;
      45: aload_2
      46: invokevirtual #20                 // Method java/security/PrivilegedActionException.getMessage:()Ljava/lang/String;
      49: invokevirtual #12                 // Method java/lang/StringBuilder.append:(Ljava/lang/String;)Ljava/lang/StringBuilder;
      52: invokevirtual #14                 // Method java/lang/StringBuilder.toString:()Ljava/lang/String;
      55: aload_2
      56: invokeinterface #21,  3           // InterfaceMethod org/apache/commons/logging/Log.debug:(Ljava/lang/Object;Ljava/lang/Throwable;)V
      61: aload_2
      62: invokevirtual #16                 // Method java/security/PrivilegedActionException.getException:()Ljava/lang/Exception;
      65: invokestatic  #17                 // Method org/apache/axis2/jaxws/ExceptionFactory.makeWebServiceException:(Ljava/lang/Throwable;)Ljavax/xml/ws/WebServiceException;
      68: athrow
      69: aload_1
      70: areturn
    Exception table:
       from    to  target type
           0    15    18   Class java/security/PrivilegedActionException

  public static java.lang.Class forName(java.lang.String, boolean, java.lang.ClassLoader) throws java.lang.ClassNotFoundException;
    Code:
       0: aconst_null
       1: astore_3
       2: new           #22                 // class org/apache/axis2/jaxws/util/ClassLoaderUtils$3
       5: dup
       6: aload_0
       7: iload_1
       8: aload_2
       9: invokespecial #23                 // Method org/apache/axis2/jaxws/util/ClassLoaderUtils$3."<init>":(Ljava/lang/String;ZLjava/lang/ClassLoader;)V
      12: invokestatic  #4                  // Method org/apache/axis2/java/security/AccessController.doPrivileged:(Ljava/security/PrivilegedExceptionAction;)Ljava/lang/Object;
      15: checkcast     #24                 // class java/lang/Class
      18: astore_3
      19: goto          77
      22: astore        4
      24: getstatic     #7                  // Field log:Lorg/apache/commons/logging/Log;
      27: invokeinterface #8,  1            // InterfaceMethod org/apache/commons/logging/Log.isDebugEnabled:()Z
      32: ifeq          68
      35: getstatic     #7                  // Field log:Lorg/apache/commons/logging/Log;
      38: new           #9                  // class java/lang/StringBuilder
      41: dup
      42: invokespecial #10                 // Method java/lang/StringBuilder."<init>":()V
      45: ldc           #11                 // String Exception thrown from AccessController:
      47: invokevirtual #12                 // Method java/lang/StringBuilder.append:(Ljava/lang/String;)Ljava/lang/StringBuilder;
      50: aload         4
      52: invokevirtual #20                 // Method java/security/PrivilegedActionException.getMessage:()Ljava/lang/String;
      55: invokevirtual #12                 // Method java/lang/StringBuilder.append:(Ljava/lang/String;)Ljava/lang/StringBuilder;
      58: invokevirtual #14                 // Method java/lang/StringBuilder.toString:()Ljava/lang/String;
      61: aload         4
      63: invokeinterface #21,  3           // InterfaceMethod org/apache/commons/logging/Log.debug:(Ljava/lang/Object;Ljava/lang/Throwable;)V
      68: aload         4
      70: invokevirtual #16                 // Method java/security/PrivilegedActionException.getException:()Ljava/lang/Exception;
      73: checkcast     #25                 // class java/lang/ClassNotFoundException
      76: athrow
      77: aload_3
      78: areturn
    Exception table:
       from    to  target type
           2    19    22   Class java/security/PrivilegedActionException

  public static java.lang.Class forName(java.lang.String) throws java.lang.ClassNotFoundException;
    Code:
       0: aconst_null
       1: astore_1
       2: new           #26                 // class org/apache/axis2/jaxws/util/ClassLoaderUtils$4
       5: dup
       6: aload_0
       7: invokespecial #27                 // Method org/apache/axis2/jaxws/util/ClassLoaderUtils$4."<init>":(Ljava/lang/String;)V
      10: invokestatic  #4                  // Method org/apache/axis2/java/security/AccessController.doPrivileged:(Ljava/security/PrivilegedExceptionAction;)Ljava/lang/Object;
      13: checkcast     #24                 // class java/lang/Class
      16: astore_1
      17: goto          71
      20: astore_2
      21: getstatic     #7                  // Field log:Lorg/apache/commons/logging/Log;
      24: invokeinterface #8,  1            // InterfaceMethod org/apache/commons/logging/Log.isDebugEnabled:()Z
      29: ifeq          63
      32: getstatic     #7                  // Field log:Lorg/apache/commons/logging/Log;
      35: new           #9                  // class java/lang/StringBuilder
      38: dup
      39: invokespecial #10                 // Method java/lang/StringBuilder."<init>":()V
      42: ldc           #11                 // String Exception thrown from AccessController:
      44: invokevirtual #12                 // Method java/lang/StringBuilder.append:(Ljava/lang/String;)Ljava/lang/StringBuilder;
      47: aload_2
      48: invokevirtual #20                 // Method java/security/PrivilegedActionException.getMessage:()Ljava/lang/String;
      51: invokevirtual #12                 // Method java/lang/StringBuilder.append:(Ljava/lang/String;)Ljava/lang/StringBuilder;
      54: invokevirtual #14                 // Method java/lang/StringBuilder.toString:()Ljava/lang/String;
      57: aload_2
      58: invokeinterface #21,  3           // InterfaceMethod org/apache/commons/logging/Log.debug:(Ljava/lang/Object;Ljava/lang/Throwable;)V
      63: aload_2
      64: invokevirtual #16                 // Method java/security/PrivilegedActionException.getException:()Ljava/lang/Exception;
      67: checkcast     #25                 // class java/lang/ClassNotFoundException
      70: athrow
      71: aload_1
      72: areturn
    Exception table:
       from    to  target type
           2    17    20   Class java/security/PrivilegedActionException

  static {};
    Code:
       0: ldc           #28                 // class org/apache/axis2/jaxws/util/ClassLoaderUtils
       2: invokestatic  #29                 // Method org/apache/commons/logging/LogFactory.getLog:(Ljava/lang/Class;)Lorg/apache/commons/logging/Log;
       5: putstatic     #7                  // Field log:Lorg/apache/commons/logging/Log;
       8: return
}
