Compiled from "SoapUtils.java"
public class org.apache.axis2.jaxws.util.SoapUtils {
  public org.apache.axis2.jaxws.util.SoapUtils();
    Code:
       0: aload_0
       1: invokespecial #1                  // Method java/lang/Object."<init>":()V
       4: return

  public static org.apache.axiom.om.OMElement getOMElement(org.apache.axiom.soap.SOAPEnvelope);
    Code:
       0: aload_0
       1: invokeinterface #2,  1            // InterfaceMethod org/apache/axiom/soap/SOAPEnvelope.getXMLStreamReader:()Ljavax/xml/stream/XMLStreamReader;
       6: astore_1
       7: new           #3                  // class org/apache/axiom/om/impl/builder/StAXOMBuilder
      10: dup
      11: invokestatic  #4                  // Method org/apache/axiom/om/OMAbstractFactory.getOMFactory:()Lorg/apache/axiom/om/OMFactory;
      14: aload_1
      15: invokespecial #5                  // Method org/apache/axiom/om/impl/builder/StAXOMBuilder."<init>":(Lorg/apache/axiom/om/OMFactory;Ljavax/xml/stream/XMLStreamReader;)V
      18: astore_2
      19: aload_2
      20: invokevirtual #6                  // Method org/apache/axiom/om/impl/builder/StAXOMBuilder.getDocumentElement:()Lorg/apache/axiom/om/OMElement;
      23: areturn

  public static org.apache.axiom.soap.SOAPFactory getSoapFactory(java.lang.String);
    Code:
       0: ldc           #7                  // String http://www.w3.org/2003/05/soap-envelope
       2: aload_0
       3: invokevirtual #8                  // Method java/lang/String.equals:(Ljava/lang/Object;)Z
       6: ifeq          13
       9: invokestatic  #9                  // Method org/apache/axiom/om/OMAbstractFactory.getSOAP12Factory:()Lorg/apache/axiom/soap/SOAPFactory;
      12: areturn
      13: invokestatic  #10                 // Method org/apache/axiom/om/OMAbstractFactory.getSOAP11Factory:()Lorg/apache/axiom/soap/SOAPFactory;
      16: areturn
}
