Compiled from "SecurityVerificationOutInterceptor.java"
public class org.apache.cxf.ws.security.policy.interceptors.SecurityVerificationOutInterceptor extends org.apache.cxf.phase.AbstractPhaseInterceptor<org.apache.cxf.binding.soap.SoapMessage> {
  public static final org.apache.cxf.ws.security.policy.interceptors.SecurityVerificationOutInterceptor INSTANCE;

  private static final java.util.logging.Logger LOG;

  public org.apache.cxf.ws.security.policy.interceptors.SecurityVerificationOutInterceptor();
    Code:
       0: aload_0
       1: ldc           #1                  // String pre-logical
       3: invokespecial #2                  // Method org/apache/cxf/phase/AbstractPhaseInterceptor."<init>":(Ljava/lang/String;)V
       6: return

  public void handleMessage(org.apache.cxf.binding.soap.SoapMessage) throws org.apache.cxf.interceptor.Fault;
    Code:
       0: aload_1
       1: invokestatic  #3                  // Method org/apache/cxf/message/MessageUtils.isRequestor:(Lorg/apache/cxf/message/Message;)Z
       4: ifeq          112
       7: aload_1
       8: ldc_w         #4                  // class org/apache/cxf/ws/policy/AssertionInfoMap
      11: invokevirtual #5                  // Method org/apache/cxf/binding/soap/SoapMessage.get:(Ljava/lang/Class;)Ljava/lang/Object;
      14: checkcast     #4                  // class org/apache/cxf/ws/policy/AssertionInfoMap
      17: astore_2
      18: aload_2
      19: ifnull        112
      22: aload_2
      23: invokestatic  #6                  // Method org/apache/cxf/ws/security/policy/PolicyUtils.getSecurityBinding:(Lorg/apache/cxf/ws/policy/AssertionInfoMap;)Lorg/apache/wss4j/policy/model/AbstractBinding;
      26: ifnonnull     112
      29: aload_0
      30: aload_2
      31: invokespecial #7                  // Method getSecuredPart:(Lorg/apache/cxf/ws/policy/AssertionInfoMap;)Lorg/apache/cxf/ws/policy/AssertionInfo;
      34: astore_3
      35: aload_3
      36: ifnull        112
      39: ldc           #8                  // String %s assertion cannot be fulfilled without binding. At least one binding assertion (%s, %s, %s) must be specified in policy.
      41: iconst_4
      42: anewarray     #9                  // class java/lang/Object
      45: dup
      46: iconst_0
      47: aload_3
      48: invokevirtual #10                 // Method org/apache/cxf/ws/policy/AssertionInfo.getAssertion:()Lorg/apache/neethi/Assertion;
      51: invokeinterface #11,  1           // InterfaceMethod org/apache/neethi/Assertion.getName:()Ljavax/xml/namespace/QName;
      56: aastore
      57: dup
      58: iconst_1
      59: getstatic     #12                 // Field org/apache/wss4j/policy/SP12Constants.TRANSPORT_BINDING:Ljavax/xml/namespace/QName;
      62: invokevirtual #13                 // Method javax/xml/namespace/QName.getLocalPart:()Ljava/lang/String;
      65: aastore
      66: dup
      67: iconst_2
      68: getstatic     #14                 // Field org/apache/wss4j/policy/SP12Constants.ASYMMETRIC_BINDING:Ljavax/xml/namespace/QName;
      71: invokevirtual #13                 // Method javax/xml/namespace/QName.getLocalPart:()Ljava/lang/String;
      74: aastore
      75: dup
      76: iconst_3
      77: getstatic     #15                 // Field org/apache/wss4j/policy/SP12Constants.SYMMETRIC_BINDING:Ljavax/xml/namespace/QName;
      80: invokevirtual #13                 // Method javax/xml/namespace/QName.getLocalPart:()Ljava/lang/String;
      83: aastore
      84: invokestatic  #16                 // Method java/lang/String.format:(Ljava/lang/String;[Ljava/lang/Object;)Ljava/lang/String;
      87: astore        4
      89: aload_3
      90: aload         4
      92: invokevirtual #17                 // Method org/apache/cxf/ws/policy/AssertionInfo.setNotAsserted:(Ljava/lang/String;)V
      95: getstatic     #18                 // Field LOG:Ljava/util/logging/Logger;
      98: aload         4
     100: invokevirtual #19                 // Method java/util/logging/Logger.severe:(Ljava/lang/String;)V
     103: new           #20                 // class org/apache/cxf/ws/policy/PolicyException
     106: dup
     107: aload_3
     108: invokespecial #21                 // Method org/apache/cxf/ws/policy/PolicyException."<init>":(Lorg/apache/cxf/ws/policy/AssertionInfo;)V
     111: athrow
     112: return

  private org.apache.cxf.ws.policy.AssertionInfo getSecuredPart(org.apache.cxf.ws.policy.AssertionInfoMap);
    Code:
       0: aload_1
       1: ldc           #22                 // String SignedParts
       3: invokestatic  #23                 // Method org/apache/cxf/ws/security/policy/PolicyUtils.getFirstAssertionByLocalname:(Lorg/apache/cxf/ws/policy/AssertionInfoMap;Ljava/lang/String;)Lorg/apache/cxf/ws/policy/AssertionInfo;
       6: astore_2
       7: aload_2
       8: ifnull        13
      11: aload_2
      12: areturn
      13: aload_1
      14: ldc           #24                 // String SignedElements
      16: invokestatic  #23                 // Method org/apache/cxf/ws/security/policy/PolicyUtils.getFirstAssertionByLocalname:(Lorg/apache/cxf/ws/policy/AssertionInfoMap;Ljava/lang/String;)Lorg/apache/cxf/ws/policy/AssertionInfo;
      19: astore_2
      20: aload_2
      21: ifnull        26
      24: aload_2
      25: areturn
      26: aload_1
      27: ldc           #25                 // String EncryptedParts
      29: invokestatic  #23                 // Method org/apache/cxf/ws/security/policy/PolicyUtils.getFirstAssertionByLocalname:(Lorg/apache/cxf/ws/policy/AssertionInfoMap;Ljava/lang/String;)Lorg/apache/cxf/ws/policy/AssertionInfo;
      32: astore_2
      33: aload_2
      34: ifnull        39
      37: aload_2
      38: areturn
      39: aload_1
      40: ldc           #26                 // String EncryptedElements
      42: invokestatic  #23                 // Method org/apache/cxf/ws/security/policy/PolicyUtils.getFirstAssertionByLocalname:(Lorg/apache/cxf/ws/policy/AssertionInfoMap;Ljava/lang/String;)Lorg/apache/cxf/ws/policy/AssertionInfo;
      45: astore_2
      46: aload_2
      47: ifnull        52
      50: aload_2
      51: areturn
      52: aload_1
      53: ldc           #27                 // String ContentEncryptedElements
      55: invokestatic  #23                 // Method org/apache/cxf/ws/security/policy/PolicyUtils.getFirstAssertionByLocalname:(Lorg/apache/cxf/ws/policy/AssertionInfoMap;Ljava/lang/String;)Lorg/apache/cxf/ws/policy/AssertionInfo;
      58: astore_2
      59: aload_2
      60: ifnull        65
      63: aload_2
      64: areturn
      65: aconst_null
      66: areturn

  public void handleMessage(org.apache.cxf.message.Message) throws org.apache.cxf.interceptor.Fault;
    Code:
       0: aload_0
       1: aload_1
       2: checkcast     #28                 // class org/apache/cxf/binding/soap/SoapMessage
       5: invokevirtual #29                 // Method handleMessage:(Lorg/apache/cxf/binding/soap/SoapMessage;)V
       8: return

  static {};
    Code:
       0: new           #30                 // class org/apache/cxf/ws/security/policy/interceptors/SecurityVerificationOutInterceptor
       3: dup
       4: invokespecial #31                 // Method "<init>":()V
       7: putstatic     #32                 // Field INSTANCE:Lorg/apache/cxf/ws/security/policy/interceptors/SecurityVerificationOutInterceptor;
      10: ldc_w         #30                 // class org/apache/cxf/ws/security/policy/interceptors/SecurityVerificationOutInterceptor
      13: invokestatic  #33                 // Method org/apache/cxf/common/logging/LogUtils.getL7dLogger:(Ljava/lang/Class;)Ljava/util/logging/Logger;
      16: putstatic     #18                 // Field LOG:Ljava/util/logging/Logger;
      19: return
}
