Compiled from "InWhileLoopWrapper.groovy"
public class org.codehaus.groovy.transform.tailrec.InWhileLoopWrapper implements groovy.lang.GroovyObject {
  private static final java.lang.String LOOP_LABEL;

  private static final org.codehaus.groovy.transform.tailrec.GotoRecurHereException LOOP_EXCEPTION;

  private static org.codehaus.groovy.reflection.ClassInfo $staticClassInfo;

  public static transient boolean __$stMC;

  private transient groovy.lang.MetaClass metaClass;

  private static org.codehaus.groovy.reflection.ClassInfo $staticClassInfo$;

  public org.codehaus.groovy.transform.tailrec.InWhileLoopWrapper();
    Code:
       0: aload_0
       1: invokespecial #24                 // Method java/lang/Object."<init>":()V
       4: aload_0
       5: invokevirtual #28                 // Method $getStaticMetaClass:()Lgroovy/lang/MetaClass;
       8: astore_1
       9: aload_1
      10: aload_0
      11: swap
      12: putfield      #30                 // Field metaClass:Lgroovy/lang/MetaClass;
      15: aload_1
      16: pop
      17: return

  public void wrap(org.codehaus.groovy.ast.MethodNode);
    Code:
       0: aload_1
       1: invokevirtual #40                 // Method org/codehaus/groovy/ast/MethodNode.getCode:()Lorg/codehaus/groovy/ast/stmt/Statement;
       4: ldc           #42                 // class org/codehaus/groovy/ast/stmt/BlockStatement
       6: invokestatic  #48                 // Method org/codehaus/groovy/runtime/ScriptBytecodeAdapter.asType:(Ljava/lang/Object;Ljava/lang/Class;)Ljava/lang/Object;
       9: checkcast     #42                 // class org/codehaus/groovy/ast/stmt/BlockStatement
      12: astore_2
      13: aload_2
      14: pop
      15: new           #50                 // class org/codehaus/groovy/ast/stmt/TryCatchStatement
      18: dup
      19: aload_2
      20: new           #52                 // class org/codehaus/groovy/ast/stmt/EmptyStatement
      23: dup
      24: invokespecial #53                 // Method org/codehaus/groovy/ast/stmt/EmptyStatement."<init>":()V
      27: invokespecial #56                 // Method org/codehaus/groovy/ast/stmt/TryCatchStatement."<init>":(Lorg/codehaus/groovy/ast/stmt/Statement;Lorg/codehaus/groovy/ast/stmt/Statement;)V
      30: astore_3
      31: aload_3
      32: pop
      33: aload_3
      34: new           #58                 // class org/codehaus/groovy/ast/stmt/CatchStatement
      37: dup
      38: new           #60                 // class org/codehaus/groovy/ast/Parameter
      41: dup
      42: ldc           #62                 // class org/codehaus/groovy/transform/tailrec/GotoRecurHereException
      44: invokestatic  #68                 // Method org/codehaus/groovy/ast/ClassHelper.make:(Ljava/lang/Class;)Lorg/codehaus/groovy/ast/ClassNode;
      47: ldc           #70                 // String ignore
      49: invokespecial #73                 // Method org/codehaus/groovy/ast/Parameter."<init>":(Lorg/codehaus/groovy/ast/ClassNode;Ljava/lang/String;)V
      52: new           #75                 // class org/codehaus/groovy/ast/stmt/ContinueStatement
      55: dup
      56: invokestatic  #79                 // Method getLOOP_LABEL:()Ljava/lang/String;
      59: invokespecial #82                 // Method org/codehaus/groovy/ast/stmt/ContinueStatement."<init>":(Ljava/lang/String;)V
      62: invokespecial #85                 // Method org/codehaus/groovy/ast/stmt/CatchStatement."<init>":(Lorg/codehaus/groovy/ast/Parameter;Lorg/codehaus/groovy/ast/stmt/Statement;)V
      65: invokevirtual #89                 // Method org/codehaus/groovy/ast/stmt/TryCatchStatement.addCatch:(Lorg/codehaus/groovy/ast/stmt/CatchStatement;)V
      68: aconst_null
      69: pop
      70: new           #91                 // class org/codehaus/groovy/ast/stmt/WhileStatement
      73: dup
      74: new           #93                 // class org/codehaus/groovy/ast/expr/BooleanExpression
      77: dup
      78: new           #95                 // class org/codehaus/groovy/ast/expr/ConstantExpression
      81: dup
      82: iconst_1
      83: invokestatic  #101                // Method java/lang/Boolean.valueOf:(Z)Ljava/lang/Boolean;
      86: invokespecial #104                // Method org/codehaus/groovy/ast/expr/ConstantExpression."<init>":(Ljava/lang/Object;)V
      89: invokespecial #107                // Method org/codehaus/groovy/ast/expr/BooleanExpression."<init>":(Lorg/codehaus/groovy/ast/expr/Expression;)V
      92: new           #42                 // class org/codehaus/groovy/ast/stmt/BlockStatement
      95: dup
      96: iconst_1
      97: anewarray     #4                  // class java/lang/Object
     100: dup
     101: iconst_0
     102: aload_3
     103: aastore
     104: invokestatic  #111                // Method org/codehaus/groovy/runtime/ScriptBytecodeAdapter.createList:([Ljava/lang/Object;)Ljava/util/List;
     107: checkcast     #113                // class java/util/List
     110: new           #115                // class org/codehaus/groovy/ast/VariableScope
     113: dup
     114: aload_1
     115: invokevirtual #119                // Method org/codehaus/groovy/ast/MethodNode.getVariableScope:()Lorg/codehaus/groovy/ast/VariableScope;
     118: invokespecial #122                // Method org/codehaus/groovy/ast/VariableScope."<init>":(Lorg/codehaus/groovy/ast/VariableScope;)V
     121: invokespecial #125                // Method org/codehaus/groovy/ast/stmt/BlockStatement."<init>":(Ljava/util/List;Lorg/codehaus/groovy/ast/VariableScope;)V
     124: invokespecial #128                // Method org/codehaus/groovy/ast/stmt/WhileStatement."<init>":(Lorg/codehaus/groovy/ast/expr/BooleanExpression;Lorg/codehaus/groovy/ast/stmt/Statement;)V
     127: astore        4
     129: aload         4
     131: pop
     132: aload         4
     134: invokevirtual #131                // Method org/codehaus/groovy/ast/stmt/WhileStatement.getLoopBlock:()Lorg/codehaus/groovy/ast/stmt/Statement;
     137: ldc           #42                 // class org/codehaus/groovy/ast/stmt/BlockStatement
     139: invokestatic  #134                // Method org/codehaus/groovy/runtime/ScriptBytecodeAdapter.castToType:(Ljava/lang/Object;Ljava/lang/Class;)Ljava/lang/Object;
     142: checkcast     #42                 // class org/codehaus/groovy/ast/stmt/BlockStatement
     145: invokevirtual #138                // Method org/codehaus/groovy/ast/stmt/BlockStatement.getStatements:()Ljava/util/List;
     148: astore        5
     150: aload         5
     152: pop
     153: aload         5
     155: invokeinterface #142,  1          // InterfaceMethod java/util/List.size:()I
     160: iconst_0
     161: if_icmple     168
     164: iconst_1
     165: goto          169
     168: iconst_0
     169: ifeq          195
     172: getstatic     #144                // Field LOOP_LABEL:Ljava/lang/String;
     175: dup
     176: astore        6
     178: aload         5
     180: iconst_0
     181: invokestatic  #150                // Method org/codehaus/groovy/runtime/DefaultGroovyMethods.getAt:(Ljava/util/List;I)Ljava/lang/Object;
     184: checkcast     #152                // class org/codehaus/groovy/ast/stmt/Statement
     187: aload         6
     189: invokevirtual #155                // Method org/codehaus/groovy/ast/stmt/Statement.setStatementLabel:(Ljava/lang/String;)V
     192: aconst_null
     193: pop
     194: pop
     195: new           #42                 // class org/codehaus/groovy/ast/stmt/BlockStatement
     198: dup
     199: iconst_0
     200: anewarray     #4                  // class java/lang/Object
     203: invokestatic  #111                // Method org/codehaus/groovy/runtime/ScriptBytecodeAdapter.createList:([Ljava/lang/Object;)Ljava/util/List;
     206: checkcast     #113                // class java/util/List
     209: new           #115                // class org/codehaus/groovy/ast/VariableScope
     212: dup
     213: aload_1
     214: invokevirtual #119                // Method org/codehaus/groovy/ast/MethodNode.getVariableScope:()Lorg/codehaus/groovy/ast/VariableScope;
     217: invokespecial #122                // Method org/codehaus/groovy/ast/VariableScope."<init>":(Lorg/codehaus/groovy/ast/VariableScope;)V
     220: invokespecial #125                // Method org/codehaus/groovy/ast/stmt/BlockStatement."<init>":(Ljava/util/List;Lorg/codehaus/groovy/ast/VariableScope;)V
     223: astore        7
     225: aload         7
     227: pop
     228: aload         7
     230: aload         4
     232: invokevirtual #159                // Method org/codehaus/groovy/ast/stmt/BlockStatement.addStatement:(Lorg/codehaus/groovy/ast/stmt/Statement;)V
     235: aconst_null
     236: pop
     237: aload         7
     239: dup
     240: astore        8
     242: aload_1
     243: aload         8
     245: invokevirtual #162                // Method org/codehaus/groovy/ast/MethodNode.setCode:(Lorg/codehaus/groovy/ast/stmt/Statement;)V
     248: aconst_null
     249: pop
     250: pop
     251: return

  protected groovy.lang.MetaClass $getStaticMetaClass();
    Code:
       0: aload_0
       1: invokevirtual #177                // Method java/lang/Object.getClass:()Ljava/lang/Class;
       4: ldc           #2                  // class org/codehaus/groovy/transform/tailrec/InWhileLoopWrapper
       6: if_acmpeq     14
       9: aload_0
      10: invokestatic  #181                // Method org/codehaus/groovy/runtime/ScriptBytecodeAdapter.initMetaClass:(Ljava/lang/Object;)Lgroovy/lang/MetaClass;
      13: areturn
      14: getstatic     #183                // Field $staticClassInfo:Lorg/codehaus/groovy/reflection/ClassInfo;
      17: astore_1
      18: aload_1
      19: ifnonnull     34
      22: aload_0
      23: invokevirtual #177                // Method java/lang/Object.getClass:()Ljava/lang/Class;
      26: invokestatic  #189                // Method org/codehaus/groovy/reflection/ClassInfo.getClassInfo:(Ljava/lang/Class;)Lorg/codehaus/groovy/reflection/ClassInfo;
      29: dup
      30: astore_1
      31: putstatic     #183                // Field $staticClassInfo:Lorg/codehaus/groovy/reflection/ClassInfo;
      34: aload_1
      35: invokevirtual #192                // Method org/codehaus/groovy/reflection/ClassInfo.getMetaClass:()Lgroovy/lang/MetaClass;
      38: areturn

  public groovy.lang.MetaClass getMetaClass();
    Code:
       0: aload_0
       1: getfield      #30                 // Field metaClass:Lgroovy/lang/MetaClass;
       4: dup
       5: ifnull        9
       8: areturn
       9: pop
      10: aload_0
      11: dup
      12: invokevirtual #28                 // Method $getStaticMetaClass:()Lgroovy/lang/MetaClass;
      15: putfield      #30                 // Field metaClass:Lgroovy/lang/MetaClass;
      18: aload_0
      19: getfield      #30                 // Field metaClass:Lgroovy/lang/MetaClass;
      22: areturn

  public void setMetaClass(groovy.lang.MetaClass);
    Code:
       0: aload_0
       1: aload_1
       2: putfield      #30                 // Field metaClass:Lgroovy/lang/MetaClass;
       5: return

  public java.lang.Object invokeMethod(java.lang.String, java.lang.Object);
    Code:
       0: aload_0
       1: invokevirtual #197                // Method getMetaClass:()Lgroovy/lang/MetaClass;
       4: aload_0
       5: aload_1
       6: aload_2
       7: invokeinterface #202,  4          // InterfaceMethod groovy/lang/MetaClass.invokeMethod:(Ljava/lang/Object;Ljava/lang/String;Ljava/lang/Object;)Ljava/lang/Object;
      12: areturn

  public java.lang.Object getProperty(java.lang.String);
    Code:
       0: aload_0
       1: invokevirtual #197                // Method getMetaClass:()Lgroovy/lang/MetaClass;
       4: aload_0
       5: aload_1
       6: invokeinterface #207,  3          // InterfaceMethod groovy/lang/MetaClass.getProperty:(Ljava/lang/Object;Ljava/lang/String;)Ljava/lang/Object;
      11: areturn

  public void setProperty(java.lang.String, java.lang.Object);
    Code:
       0: aload_0
       1: invokevirtual #197                // Method getMetaClass:()Lgroovy/lang/MetaClass;
       4: aload_0
       5: aload_1
       6: aload_2
       7: invokeinterface #212,  4          // InterfaceMethod groovy/lang/MetaClass.setProperty:(Ljava/lang/Object;Ljava/lang/String;Ljava/lang/Object;)V
      12: return

  static {};
    Code:
       0: new           #62                 // class org/codehaus/groovy/transform/tailrec/GotoRecurHereException
       3: dup
       4: invokespecial #214                // Method org/codehaus/groovy/transform/tailrec/GotoRecurHereException."<init>":()V
       7: astore_0
       8: aload_0
       9: putstatic     #216                // Field LOOP_EXCEPTION:Lorg/codehaus/groovy/transform/tailrec/GotoRecurHereException;
      12: aload_0
      13: pop
      14: return

  public static java.lang.String getLOOP_LABEL();
    Code:
       0: getstatic     #144                // Field LOOP_LABEL:Ljava/lang/String;
       3: areturn

  public static org.codehaus.groovy.transform.tailrec.GotoRecurHereException getLOOP_EXCEPTION();
    Code:
       0: getstatic     #216                // Field LOOP_EXCEPTION:Lorg/codehaus/groovy/transform/tailrec/GotoRecurHereException;
       3: areturn
}
