Compiled from "RecursivenessTester.groovy"
public class org.codehaus.groovy.transform.tailrec.RecursivenessTester implements groovy.lang.GroovyObject {
  private static org.codehaus.groovy.reflection.ClassInfo $staticClassInfo;

  public static transient boolean __$stMC;

  private transient groovy.lang.MetaClass metaClass;

  private static org.codehaus.groovy.reflection.ClassInfo $staticClassInfo$;

  private static java.lang.ref.SoftReference $callSiteArray;

  public org.codehaus.groovy.transform.tailrec.RecursivenessTester();
    Code:
       0: invokestatic  #25                 // Method $getCallSiteArray:()[Lorg/codehaus/groovy/runtime/callsite/CallSite;
       3: astore_1
       4: aload_0
       5: invokespecial #27                 // Method java/lang/Object."<init>":()V
       8: aload_0
       9: invokevirtual #31                 // Method $getStaticMetaClass:()Lgroovy/lang/MetaClass;
      12: astore_2
      13: aload_2
      14: aload_0
      15: swap
      16: putfield      #33                 // Field metaClass:Lgroovy/lang/MetaClass;
      19: aload_2
      20: pop
      21: return

  public boolean isRecursive(java.lang.Object);
    Code:
       0: invokestatic  #25                 // Method $getCallSiteArray:()[Lorg/codehaus/groovy/runtime/callsite/CallSite;
       3: astore_2
       4: new           #39                 // class org/codehaus/groovy/runtime/powerassert/ValueRecorder
       7: dup
       8: invokespecial #40                 // Method org/codehaus/groovy/runtime/powerassert/ValueRecorder."<init>":()V
      11: astore_3
      12: aload_2
      13: ldc           #41                 // int 0
      15: aaload
      16: aload_2
      17: ldc           #42                 // int 1
      19: aaload
      20: aload_1
      21: dup
      22: aload_3
      23: swap
      24: ldc           #43                 // int 8
      26: invokevirtual #47                 // Method org/codehaus/groovy/runtime/powerassert/ValueRecorder.record:(Ljava/lang/Object;I)Ljava/lang/Object;
      29: pop
      30: invokeinterface #53,  2           // InterfaceMethod org/codehaus/groovy/runtime/callsite/CallSite.callGetProperty:(Ljava/lang/Object;)Ljava/lang/Object;
      35: dup
      36: aload_3
      37: swap
      38: ldc           #54                 // int 15
      40: invokevirtual #47                 // Method org/codehaus/groovy/runtime/powerassert/ValueRecorder.record:(Ljava/lang/Object;I)Ljava/lang/Object;
      43: pop
      44: invokeinterface #53,  2           // InterfaceMethod org/codehaus/groovy/runtime/callsite/CallSite.callGetProperty:(Ljava/lang/Object;)Ljava/lang/Object;
      49: dup
      50: aload_3
      51: swap
      52: ldc           #55                 // int 22
      54: invokevirtual #47                 // Method org/codehaus/groovy/runtime/powerassert/ValueRecorder.record:(Ljava/lang/Object;I)Ljava/lang/Object;
      57: pop
      58: ldc           #57                 // class org/codehaus/groovy/ast/MethodNode
      60: invokestatic  #63                 // Method org/codehaus/groovy/runtime/ScriptBytecodeAdapter.compareEqual:(Ljava/lang/Object;Ljava/lang/Object;)Z
      63: dup
      64: invokestatic  #69                 // Method java/lang/Boolean.valueOf:(Z)Ljava/lang/Boolean;
      67: aload_3
      68: swap
      69: ldc           #70                 // int 28
      71: invokevirtual #47                 // Method org/codehaus/groovy/runtime/powerassert/ValueRecorder.record:(Ljava/lang/Object;I)Ljava/lang/Object;
      74: pop
      75: ifeq          85
      78: aload_3
      79: invokevirtual #73                 // Method org/codehaus/groovy/runtime/powerassert/ValueRecorder.clear:()V
      82: goto          103
      85: ldc           #75                 // String assert params.method.class == MethodNode
      87: aload_3
      88: invokestatic  #81                 // Method org/codehaus/groovy/runtime/powerassert/AssertionRenderer.render:(Ljava/lang/String;Lorg/codehaus/groovy/runtime/powerassert/ValueRecorder;)Ljava/lang/String;
      91: aconst_null
      92: invokestatic  #85                 // Method org/codehaus/groovy/runtime/ScriptBytecodeAdapter.assertFailed:(Ljava/lang/Object;Ljava/lang/Object;)V
      95: goto          103
      98: aload_3
      99: invokevirtual #73                 // Method org/codehaus/groovy/runtime/powerassert/ValueRecorder.clear:()V
     102: athrow
     103: new           #39                 // class org/codehaus/groovy/runtime/powerassert/ValueRecorder
     106: dup
     107: invokespecial #40                 // Method org/codehaus/groovy/runtime/powerassert/ValueRecorder."<init>":()V
     110: astore        4
     112: aload_2
     113: ldc           #86                 // int 2
     115: aaload
     116: aload_2
     117: ldc           #87                 // int 3
     119: aaload
     120: aload_1
     121: dup
     122: aload         4
     124: swap
     125: ldc           #43                 // int 8
     127: invokevirtual #47                 // Method org/codehaus/groovy/runtime/powerassert/ValueRecorder.record:(Ljava/lang/Object;I)Ljava/lang/Object;
     130: pop
     131: invokeinterface #53,  2           // InterfaceMethod org/codehaus/groovy/runtime/callsite/CallSite.callGetProperty:(Ljava/lang/Object;)Ljava/lang/Object;
     136: dup
     137: aload         4
     139: swap
     140: ldc           #54                 // int 15
     142: invokevirtual #47                 // Method org/codehaus/groovy/runtime/powerassert/ValueRecorder.record:(Ljava/lang/Object;I)Ljava/lang/Object;
     145: pop
     146: invokeinterface #53,  2           // InterfaceMethod org/codehaus/groovy/runtime/callsite/CallSite.callGetProperty:(Ljava/lang/Object;)Ljava/lang/Object;
     151: dup
     152: aload         4
     154: swap
     155: ldc           #88                 // int 20
     157: invokevirtual #47                 // Method org/codehaus/groovy/runtime/powerassert/ValueRecorder.record:(Ljava/lang/Object;I)Ljava/lang/Object;
     160: pop
     161: ldc           #90                 // class org/codehaus/groovy/ast/expr/MethodCallExpression
     163: invokestatic  #63                 // Method org/codehaus/groovy/runtime/ScriptBytecodeAdapter.compareEqual:(Ljava/lang/Object;Ljava/lang/Object;)Z
     166: dup
     167: invokestatic  #69                 // Method java/lang/Boolean.valueOf:(Z)Ljava/lang/Boolean;
     170: aload         4
     172: swap
     173: ldc           #91                 // int 26
     175: invokevirtual #47                 // Method org/codehaus/groovy/runtime/powerassert/ValueRecorder.record:(Ljava/lang/Object;I)Ljava/lang/Object;
     178: pop
     179: ifne          190
     182: ldc           #93                 // class org/codehaus/groovy/ast/expr/StaticMethodCallExpression
     184: invokestatic  #98                 // Method org/codehaus/groovy/runtime/typehandling/DefaultTypeTransformation.booleanUnbox:(Ljava/lang/Object;)Z
     187: ifeq          194
     190: iconst_1
     191: goto          195
     194: iconst_0
     195: dup
     196: invokestatic  #69                 // Method java/lang/Boolean.valueOf:(Z)Ljava/lang/Boolean;
     199: aload         4
     201: swap
     202: ldc           #99                 // int 50
     204: invokevirtual #47                 // Method org/codehaus/groovy/runtime/powerassert/ValueRecorder.record:(Ljava/lang/Object;I)Ljava/lang/Object;
     207: pop
     208: ifeq          219
     211: aload         4
     213: invokevirtual #73                 // Method org/codehaus/groovy/runtime/powerassert/ValueRecorder.clear:()V
     216: goto          239
     219: ldc           #101                // String assert params.call.class == MethodCallExpression || StaticMethodCallExpression
     221: aload         4
     223: invokestatic  #81                 // Method org/codehaus/groovy/runtime/powerassert/AssertionRenderer.render:(Ljava/lang/String;Lorg/codehaus/groovy/runtime/powerassert/ValueRecorder;)Ljava/lang/String;
     226: aconst_null
     227: invokestatic  #85                 // Method org/codehaus/groovy/runtime/ScriptBytecodeAdapter.assertFailed:(Ljava/lang/Object;Ljava/lang/Object;)V
     230: goto          239
     233: aload         4
     235: invokevirtual #73                 // Method org/codehaus/groovy/runtime/powerassert/ValueRecorder.clear:()V
     238: athrow
     239: aload_2
     240: ldc           #102                // int 4
     242: aaload
     243: aload_0
     244: aload_2
     245: ldc           #103                // int 5
     247: aaload
     248: aload_1
     249: invokeinterface #53,  2           // InterfaceMethod org/codehaus/groovy/runtime/callsite/CallSite.callGetProperty:(Ljava/lang/Object;)Ljava/lang/Object;
     254: aload_2
     255: ldc           #104                // int 6
     257: aaload
     258: aload_1
     259: invokeinterface #53,  2           // InterfaceMethod org/codehaus/groovy/runtime/callsite/CallSite.callGetProperty:(Ljava/lang/Object;)Ljava/lang/Object;
     264: invokeinterface #108,  4          // InterfaceMethod org/codehaus/groovy/runtime/callsite/CallSite.callCurrent:(Lgroovy/lang/GroovyObject;Ljava/lang/Object;Ljava/lang/Object;)Ljava/lang/Object;
     269: invokestatic  #98                 // Method org/codehaus/groovy/runtime/typehandling/DefaultTypeTransformation.booleanUnbox:(Ljava/lang/Object;)Z
     272: ireturn
     273: ldc           #41                 // int 0
     275: invokestatic  #113                // Method java/lang/Integer.valueOf:(I)Ljava/lang/Integer;
     278: invokestatic  #98                 // Method org/codehaus/groovy/runtime/typehandling/DefaultTypeTransformation.booleanUnbox:(Ljava/lang/Object;)Z
     281: ireturn
    Exception table:
       from    to  target type
          12    95    98   any
         112   230   233   any

  public boolean isRecursive(org.codehaus.groovy.ast.MethodNode, org.codehaus.groovy.ast.expr.MethodCallExpression);
    Code:
       0: invokestatic  #25                 // Method $getCallSiteArray:()[Lorg/codehaus/groovy/runtime/callsite/CallSite;
       3: astore_3
       4: aload_3
       5: ldc           #117                // int 7
       7: aaload
       8: aload_0
       9: aload_2
      10: invokeinterface #120,  3          // InterfaceMethod org/codehaus/groovy/runtime/callsite/CallSite.callCurrent:(Lgroovy/lang/GroovyObject;Ljava/lang/Object;)Ljava/lang/Object;
      15: invokestatic  #98                 // Method org/codehaus/groovy/runtime/typehandling/DefaultTypeTransformation.booleanUnbox:(Ljava/lang/Object;)Z
      18: ifne          25
      21: iconst_1
      22: goto          26
      25: iconst_0
      26: ifeq          31
      29: iconst_0
      30: ireturn
      31: aload_3
      32: ldc           #43                 // int 8
      34: aaload
      35: aload_2
      36: invokeinterface #53,  2           // InterfaceMethod org/codehaus/groovy/runtime/callsite/CallSite.callGetProperty:(Ljava/lang/Object;)Ljava/lang/Object;
      41: instanceof    #122                // class org/codehaus/groovy/ast/expr/ConstantExpression
      44: ifne          51
      47: iconst_1
      48: goto          52
      51: iconst_0
      52: ifeq          57
      55: iconst_0
      56: ireturn
      57: aload_3
      58: ldc           #123                // int 9
      60: aaload
      61: aload_3
      62: ldc           #124                // int 10
      64: aaload
      65: aload_2
      66: invokeinterface #53,  2           // InterfaceMethod org/codehaus/groovy/runtime/callsite/CallSite.callGetProperty:(Ljava/lang/Object;)Ljava/lang/Object;
      71: invokeinterface #53,  2           // InterfaceMethod org/codehaus/groovy/runtime/callsite/CallSite.callGetProperty:(Ljava/lang/Object;)Ljava/lang/Object;
      76: aload_3
      77: ldc           #125                // int 11
      79: aaload
      80: aload_1
      81: invokeinterface #53,  2           // InterfaceMethod org/codehaus/groovy/runtime/callsite/CallSite.callGetProperty:(Ljava/lang/Object;)Ljava/lang/Object;
      86: invokestatic  #128                // Method org/codehaus/groovy/runtime/ScriptBytecodeAdapter.compareNotEqual:(Ljava/lang/Object;Ljava/lang/Object;)Z
      89: ifeq          94
      92: iconst_0
      93: ireturn
      94: aload_3
      95: ldc           #129                // int 12
      97: aaload
      98: aload_0
      99: aload_1
     100: aload_2
     101: invokeinterface #108,  4          // InterfaceMethod org/codehaus/groovy/runtime/callsite/CallSite.callCurrent:(Lgroovy/lang/GroovyObject;Ljava/lang/Object;Ljava/lang/Object;)Ljava/lang/Object;
     106: invokestatic  #98                 // Method org/codehaus/groovy/runtime/typehandling/DefaultTypeTransformation.booleanUnbox:(Ljava/lang/Object;)Z
     109: ireturn
     110: ldc           #41                 // int 0
     112: invokestatic  #113                // Method java/lang/Integer.valueOf:(I)Ljava/lang/Integer;
     115: invokestatic  #98                 // Method org/codehaus/groovy/runtime/typehandling/DefaultTypeTransformation.booleanUnbox:(Ljava/lang/Object;)Z
     118: ireturn

  public boolean isRecursive(org.codehaus.groovy.ast.MethodNode, org.codehaus.groovy.ast.expr.StaticMethodCallExpression);
    Code:
       0: invokestatic  #25                 // Method $getCallSiteArray:()[Lorg/codehaus/groovy/runtime/callsite/CallSite;
       3: astore_3
       4: aload_3
       5: ldc           #135                // int 13
       7: aaload
       8: aload_1
       9: invokeinterface #137,  2          // InterfaceMethod org/codehaus/groovy/runtime/callsite/CallSite.call:(Ljava/lang/Object;)Ljava/lang/Object;
      14: invokestatic  #98                 // Method org/codehaus/groovy/runtime/typehandling/DefaultTypeTransformation.booleanUnbox:(Ljava/lang/Object;)Z
      17: ifne          24
      20: iconst_1
      21: goto          25
      24: iconst_0
      25: ifeq          30
      28: iconst_0
      29: ireturn
      30: aload_3
      31: ldc           #138                // int 14
      33: aaload
      34: aload_1
      35: invokeinterface #53,  2           // InterfaceMethod org/codehaus/groovy/runtime/callsite/CallSite.callGetProperty:(Ljava/lang/Object;)Ljava/lang/Object;
      40: aload_3
      41: ldc           #54                 // int 15
      43: aaload
      44: aload_2
      45: invokeinterface #53,  2           // InterfaceMethod org/codehaus/groovy/runtime/callsite/CallSite.callGetProperty:(Ljava/lang/Object;)Ljava/lang/Object;
      50: invokestatic  #128                // Method org/codehaus/groovy/runtime/ScriptBytecodeAdapter.compareNotEqual:(Ljava/lang/Object;Ljava/lang/Object;)Z
      53: ifeq          58
      56: iconst_0
      57: ireturn
      58: aload_3
      59: ldc           #139                // int 16
      61: aaload
      62: aload_2
      63: invokeinterface #53,  2           // InterfaceMethod org/codehaus/groovy/runtime/callsite/CallSite.callGetProperty:(Ljava/lang/Object;)Ljava/lang/Object;
      68: aload_3
      69: ldc           #140                // int 17
      71: aaload
      72: aload_1
      73: invokeinterface #53,  2           // InterfaceMethod org/codehaus/groovy/runtime/callsite/CallSite.callGetProperty:(Ljava/lang/Object;)Ljava/lang/Object;
      78: invokestatic  #128                // Method org/codehaus/groovy/runtime/ScriptBytecodeAdapter.compareNotEqual:(Ljava/lang/Object;Ljava/lang/Object;)Z
      81: ifeq          86
      84: iconst_0
      85: ireturn
      86: aload_3
      87: ldc           #141                // int 18
      89: aaload
      90: aload_0
      91: aload_1
      92: aload_2
      93: invokeinterface #108,  4          // InterfaceMethod org/codehaus/groovy/runtime/callsite/CallSite.callCurrent:(Lgroovy/lang/GroovyObject;Ljava/lang/Object;Ljava/lang/Object;)Ljava/lang/Object;
      98: invokestatic  #98                 // Method org/codehaus/groovy/runtime/typehandling/DefaultTypeTransformation.booleanUnbox:(Ljava/lang/Object;)Z
     101: ireturn
     102: ldc           #41                 // int 0
     104: invokestatic  #113                // Method java/lang/Integer.valueOf:(I)Ljava/lang/Integer;
     107: invokestatic  #98                 // Method org/codehaus/groovy/runtime/typehandling/DefaultTypeTransformation.booleanUnbox:(Ljava/lang/Object;)Z
     110: ireturn

  private boolean isCallToThis(org.codehaus.groovy.ast.expr.MethodCallExpression);
    Code:
       0: invokestatic  #25                 // Method $getCallSiteArray:()[Lorg/codehaus/groovy/runtime/callsite/CallSite;
       3: astore_2
       4: aload_2
       5: ldc           #145                // int 19
       7: aaload
       8: aload_1
       9: invokeinterface #53,  2           // InterfaceMethod org/codehaus/groovy/runtime/callsite/CallSite.callGetProperty:(Ljava/lang/Object;)Ljava/lang/Object;
      14: aconst_null
      15: invokestatic  #63                 // Method org/codehaus/groovy/runtime/ScriptBytecodeAdapter.compareEqual:(Ljava/lang/Object;Ljava/lang/Object;)Z
      18: ifeq          35
      21: aload_2
      22: ldc           #88                 // int 20
      24: aaload
      25: aload_1
      26: invokeinterface #137,  2          // InterfaceMethod org/codehaus/groovy/runtime/callsite/CallSite.call:(Ljava/lang/Object;)Ljava/lang/Object;
      31: invokestatic  #98                 // Method org/codehaus/groovy/runtime/typehandling/DefaultTypeTransformation.booleanUnbox:(Ljava/lang/Object;)Z
      34: ireturn
      35: aload_2
      36: ldc           #146                // int 21
      38: aaload
      39: aload_1
      40: invokeinterface #53,  2           // InterfaceMethod org/codehaus/groovy/runtime/callsite/CallSite.callGetProperty:(Ljava/lang/Object;)Ljava/lang/Object;
      45: instanceof    #148                // class org/codehaus/groovy/ast/expr/VariableExpression
      48: ifne          55
      51: iconst_1
      52: goto          56
      55: iconst_0
      56: ifeq          61
      59: iconst_0
      60: ireturn
      61: aload_2
      62: ldc           #55                 // int 22
      64: aaload
      65: aload_2
      66: ldc           #149                // int 23
      68: aaload
      69: aload_1
      70: invokeinterface #53,  2           // InterfaceMethod org/codehaus/groovy/runtime/callsite/CallSite.callGetProperty:(Ljava/lang/Object;)Ljava/lang/Object;
      75: invokeinterface #137,  2          // InterfaceMethod org/codehaus/groovy/runtime/callsite/CallSite.call:(Ljava/lang/Object;)Ljava/lang/Object;
      80: invokestatic  #98                 // Method org/codehaus/groovy/runtime/typehandling/DefaultTypeTransformation.booleanUnbox:(Ljava/lang/Object;)Z
      83: ireturn
      84: ldc           #41                 // int 0
      86: invokestatic  #113                // Method java/lang/Integer.valueOf:(I)Ljava/lang/Integer;
      89: invokestatic  #98                 // Method org/codehaus/groovy/runtime/typehandling/DefaultTypeTransformation.booleanUnbox:(Ljava/lang/Object;)Z
      92: ireturn

  private boolean methodParamsMatchCallArgs(java.lang.Object, java.lang.Object);
    Code:
       0: invokestatic  #25                 // Method $getCallSiteArray:()[Lorg/codehaus/groovy/runtime/callsite/CallSite;
       3: astore_3
       4: aload_3
       5: ldc           #151                // int 24
       7: aaload
       8: aload_3
       9: ldc           #152                // int 25
      11: aaload
      12: aload_1
      13: invokeinterface #53,  2           // InterfaceMethod org/codehaus/groovy/runtime/callsite/CallSite.callGetProperty:(Ljava/lang/Object;)Ljava/lang/Object;
      18: invokeinterface #137,  2          // InterfaceMethod org/codehaus/groovy/runtime/callsite/CallSite.call:(Ljava/lang/Object;)Ljava/lang/Object;
      23: aload_3
      24: ldc           #91                 // int 26
      26: aaload
      27: aload_3
      28: ldc           #153                // int 27
      30: aaload
      31: aload_3
      32: ldc           #70                 // int 28
      34: aaload
      35: aload_2
      36: invokeinterface #53,  2           // InterfaceMethod org/codehaus/groovy/runtime/callsite/CallSite.callGetProperty:(Ljava/lang/Object;)Ljava/lang/Object;
      41: invokeinterface #53,  2           // InterfaceMethod org/codehaus/groovy/runtime/callsite/CallSite.callGetProperty:(Ljava/lang/Object;)Ljava/lang/Object;
      46: invokeinterface #137,  2          // InterfaceMethod org/codehaus/groovy/runtime/callsite/CallSite.call:(Ljava/lang/Object;)Ljava/lang/Object;
      51: invokestatic  #128                // Method org/codehaus/groovy/runtime/ScriptBytecodeAdapter.compareNotEqual:(Ljava/lang/Object;Ljava/lang/Object;)Z
      54: ifeq          59
      57: iconst_0
      58: ireturn
      59: aload_3
      60: ldc           #154                // int 29
      62: aaload
      63: iconst_2
      64: anewarray     #4                  // class java/lang/Object
      67: dup
      68: iconst_0
      69: ldc           #2                  // class org/codehaus/groovy/transform/tailrec/RecursivenessTester
      71: aload_3
      72: ldc           #155                // int 30
      74: aaload
      75: aload_1
      76: invokeinterface #53,  2           // InterfaceMethod org/codehaus/groovy/runtime/callsite/CallSite.callGetProperty:(Ljava/lang/Object;)Ljava/lang/Object;
      81: ldc           #157                // String type
      83: checkcast     #159                // class java/lang/String
      86: invokestatic  #163                // Method org/codehaus/groovy/runtime/ScriptBytecodeAdapter.getPropertySpreadSafe:(Ljava/lang/Class;Ljava/lang/Object;Ljava/lang/String;)Ljava/lang/Object;
      89: aastore
      90: dup
      91: iconst_1
      92: ldc           #2                  // class org/codehaus/groovy/transform/tailrec/RecursivenessTester
      94: aload_3
      95: ldc           #164                // int 31
      97: aaload
      98: aload_2
      99: invokeinterface #53,  2           // InterfaceMethod org/codehaus/groovy/runtime/callsite/CallSite.callGetProperty:(Ljava/lang/Object;)Ljava/lang/Object;
     104: ldc           #157                // String type
     106: checkcast     #159                // class java/lang/String
     109: invokestatic  #163                // Method org/codehaus/groovy/runtime/ScriptBytecodeAdapter.getPropertySpreadSafe:(Ljava/lang/Class;Ljava/lang/Object;Ljava/lang/String;)Ljava/lang/Object;
     112: aastore
     113: invokestatic  #168                // Method org/codehaus/groovy/runtime/ScriptBytecodeAdapter.createList:([Ljava/lang/Object;)Ljava/util/List;
     116: invokeinterface #137,  2          // InterfaceMethod org/codehaus/groovy/runtime/callsite/CallSite.call:(Ljava/lang/Object;)Ljava/lang/Object;
     121: astore        4
     123: aload         4
     125: pop
     126: aload_3
     127: ldc           #169                // int 32
     129: aaload
     130: aload         4
     132: new           #9                  // class org/codehaus/groovy/transform/tailrec/RecursivenessTester$_methodParamsMatchCallArgs_closure1
     135: dup
     136: aload_0
     137: aload_0
     138: invokespecial #171                // Method org/codehaus/groovy/transform/tailrec/RecursivenessTester$_methodParamsMatchCallArgs_closure1."<init>":(Ljava/lang/Object;Ljava/lang/Object;)V
     141: invokeinterface #174,  3          // InterfaceMethod org/codehaus/groovy/runtime/callsite/CallSite.call:(Ljava/lang/Object;Ljava/lang/Object;)Ljava/lang/Object;
     146: invokestatic  #98                 // Method org/codehaus/groovy/runtime/typehandling/DefaultTypeTransformation.booleanUnbox:(Ljava/lang/Object;)Z
     149: ireturn
     150: ldc           #41                 // int 0
     152: invokestatic  #113                // Method java/lang/Integer.valueOf:(I)Ljava/lang/Integer;
     155: invokestatic  #98                 // Method org/codehaus/groovy/runtime/typehandling/DefaultTypeTransformation.booleanUnbox:(Ljava/lang/Object;)Z
     158: ireturn

  private java.lang.Object areTypesCallCompatible(org.codehaus.groovy.ast.ClassNode, org.codehaus.groovy.ast.ClassNode);
    Code:
       0: invokestatic  #25                 // Method $getCallSiteArray:()[Lorg/codehaus/groovy/runtime/callsite/CallSite;
       3: astore_3
       4: aload_3
       5: ldc           #178                // int 33
       7: aaload
       8: ldc           #180                // class org/codehaus/groovy/ast/ClassHelper
      10: aload_1
      11: invokeinterface #174,  3          // InterfaceMethod org/codehaus/groovy/runtime/callsite/CallSite.call:(Ljava/lang/Object;Ljava/lang/Object;)Ljava/lang/Object;
      16: ldc           #182                // class org/codehaus/groovy/ast/ClassNode
      18: invokestatic  #186                // Method org/codehaus/groovy/runtime/ScriptBytecodeAdapter.castToType:(Ljava/lang/Object;Ljava/lang/Class;)Ljava/lang/Object;
      21: checkcast     #182                // class org/codehaus/groovy/ast/ClassNode
      24: astore        4
      26: aload         4
      28: pop
      29: aload_3
      30: ldc           #187                // int 34
      32: aaload
      33: ldc           #180                // class org/codehaus/groovy/ast/ClassHelper
      35: aload_2
      36: invokeinterface #174,  3          // InterfaceMethod org/codehaus/groovy/runtime/callsite/CallSite.call:(Ljava/lang/Object;Ljava/lang/Object;)Ljava/lang/Object;
      41: ldc           #182                // class org/codehaus/groovy/ast/ClassNode
      43: invokestatic  #186                // Method org/codehaus/groovy/runtime/ScriptBytecodeAdapter.castToType:(Ljava/lang/Object;Ljava/lang/Class;)Ljava/lang/Object;
      46: checkcast     #182                // class org/codehaus/groovy/ast/ClassNode
      49: astore        5
      51: aload         5
      53: pop
      54: aload_3
      55: ldc           #188                // int 35
      57: aaload
      58: aload         4
      60: aload         5
      62: invokeinterface #174,  3          // InterfaceMethod org/codehaus/groovy/runtime/callsite/CallSite.call:(Ljava/lang/Object;Ljava/lang/Object;)Ljava/lang/Object;
      67: invokestatic  #98                 // Method org/codehaus/groovy/runtime/typehandling/DefaultTypeTransformation.booleanUnbox:(Ljava/lang/Object;)Z
      70: ifne          92
      73: aload_3
      74: ldc           #189                // int 36
      76: aaload
      77: aload         5
      79: aload         4
      81: invokeinterface #174,  3          // InterfaceMethod org/codehaus/groovy/runtime/callsite/CallSite.call:(Ljava/lang/Object;Ljava/lang/Object;)Ljava/lang/Object;
      86: invokestatic  #98                 // Method org/codehaus/groovy/runtime/typehandling/DefaultTypeTransformation.booleanUnbox:(Ljava/lang/Object;)Z
      89: ifeq          96
      92: iconst_1
      93: goto          97
      96: iconst_0
      97: invokestatic  #69                 // Method java/lang/Boolean.valueOf:(Z)Ljava/lang/Boolean;
     100: areturn
     101: aconst_null
     102: areturn

  protected groovy.lang.MetaClass $getStaticMetaClass();
    Code:
       0: aload_0
       1: invokevirtual #198                // Method java/lang/Object.getClass:()Ljava/lang/Class;
       4: ldc           #2                  // class org/codehaus/groovy/transform/tailrec/RecursivenessTester
       6: if_acmpeq     14
       9: aload_0
      10: invokestatic  #202                // Method org/codehaus/groovy/runtime/ScriptBytecodeAdapter.initMetaClass:(Ljava/lang/Object;)Lgroovy/lang/MetaClass;
      13: areturn
      14: getstatic     #204                // Field $staticClassInfo:Lorg/codehaus/groovy/reflection/ClassInfo;
      17: astore_1
      18: aload_1
      19: ifnonnull     34
      22: aload_0
      23: invokevirtual #198                // Method java/lang/Object.getClass:()Ljava/lang/Class;
      26: invokestatic  #210                // Method org/codehaus/groovy/reflection/ClassInfo.getClassInfo:(Ljava/lang/Class;)Lorg/codehaus/groovy/reflection/ClassInfo;
      29: dup
      30: astore_1
      31: putstatic     #204                // Field $staticClassInfo:Lorg/codehaus/groovy/reflection/ClassInfo;
      34: aload_1
      35: invokevirtual #213                // Method org/codehaus/groovy/reflection/ClassInfo.getMetaClass:()Lgroovy/lang/MetaClass;
      38: areturn

  public groovy.lang.MetaClass getMetaClass();
    Code:
       0: aload_0
       1: getfield      #33                 // Field metaClass:Lgroovy/lang/MetaClass;
       4: dup
       5: ifnull        9
       8: areturn
       9: pop
      10: aload_0
      11: dup
      12: invokevirtual #31                 // Method $getStaticMetaClass:()Lgroovy/lang/MetaClass;
      15: putfield      #33                 // Field metaClass:Lgroovy/lang/MetaClass;
      18: aload_0
      19: getfield      #33                 // Field metaClass:Lgroovy/lang/MetaClass;
      22: areturn

  public void setMetaClass(groovy.lang.MetaClass);
    Code:
       0: aload_0
       1: aload_1
       2: putfield      #33                 // Field metaClass:Lgroovy/lang/MetaClass;
       5: return

  public java.lang.Object invokeMethod(java.lang.String, java.lang.Object);
    Code:
       0: aload_0
       1: invokevirtual #218                // Method getMetaClass:()Lgroovy/lang/MetaClass;
       4: aload_0
       5: aload_1
       6: aload_2
       7: invokeinterface #223,  4          // InterfaceMethod groovy/lang/MetaClass.invokeMethod:(Ljava/lang/Object;Ljava/lang/String;Ljava/lang/Object;)Ljava/lang/Object;
      12: areturn

  public java.lang.Object getProperty(java.lang.String);
    Code:
       0: aload_0
       1: invokevirtual #218                // Method getMetaClass:()Lgroovy/lang/MetaClass;
       4: aload_0
       5: aload_1
       6: invokeinterface #228,  3          // InterfaceMethod groovy/lang/MetaClass.getProperty:(Ljava/lang/Object;Ljava/lang/String;)Ljava/lang/Object;
      11: areturn

  public void setProperty(java.lang.String, java.lang.Object);
    Code:
       0: aload_0
       1: invokevirtual #218                // Method getMetaClass:()Lgroovy/lang/MetaClass;
       4: aload_0
       5: aload_1
       6: aload_2
       7: invokeinterface #233,  4          // InterfaceMethod groovy/lang/MetaClass.setProperty:(Ljava/lang/Object;Ljava/lang/String;Ljava/lang/Object;)V
      12: return

  private static void $createCallSiteArray_1(java.lang.String[]);
    Code:
       0: aload_0
       1: ldc           #41                 // int 0
       3: ldc           #237                // String class
       5: aastore
       6: aload_0
       7: ldc           #42                 // int 1
       9: ldc           #238                // String method
      11: aastore
      12: aload_0
      13: ldc           #86                 // int 2
      15: ldc           #237                // String class
      17: aastore
      18: aload_0
      19: ldc           #87                 // int 3
      21: ldc           #239                // String call
      23: aastore
      24: aload_0
      25: ldc           #102                // int 4
      27: ldc           #240                // String isRecursive
      29: aastore
      30: aload_0
      31: ldc           #103                // int 5
      33: ldc           #238                // String method
      35: aastore
      36: aload_0
      37: ldc           #104                // int 6
      39: ldc           #239                // String call
      41: aastore
      42: aload_0
      43: ldc           #117                // int 7
      45: ldc           #241                // String isCallToThis
      47: aastore
      48: aload_0
      49: ldc           #43                 // int 8
      51: ldc           #238                // String method
      53: aastore
      54: aload_0
      55: ldc           #123                // int 9
      57: ldc           #243                // String value
      59: aastore
      60: aload_0
      61: ldc           #124                // int 10
      63: ldc           #238                // String method
      65: aastore
      66: aload_0
      67: ldc           #125                // int 11
      69: ldc           #245                // String name
      71: aastore
      72: aload_0
      73: ldc           #129                // int 12
      75: ldc           #246                // String methodParamsMatchCallArgs
      77: aastore
      78: aload_0
      79: ldc           #135                // int 13
      81: ldc           #248                // String isStatic
      83: aastore
      84: aload_0
      85: ldc           #138                // int 14
      87: ldc           #250                // String declaringClass
      89: aastore
      90: aload_0
      91: ldc           #54                 // int 15
      93: ldc           #252                // String ownerType
      95: aastore
      96: aload_0
      97: ldc           #139                // int 16
      99: ldc           #238                // String method
     101: aastore
     102: aload_0
     103: ldc           #140                // int 17
     105: ldc           #245                // String name
     107: aastore
     108: aload_0
     109: ldc           #141                // int 18
     111: ldc           #246                // String methodParamsMatchCallArgs
     113: aastore
     114: aload_0
     115: ldc           #145                // int 19
     117: ldc           #254                // String objectExpression
     119: aastore
     120: aload_0
     121: ldc           #88                 // int 20
     123: ldc_w         #256                // String isImplicitThis
     126: aastore
     127: aload_0
     128: ldc           #146                // int 21
     130: ldc           #254                // String objectExpression
     132: aastore
     133: aload_0
     134: ldc           #55                 // int 22
     136: ldc_w         #258                // String isThisExpression
     139: aastore
     140: aload_0
     141: ldc           #149                // int 23
     143: ldc           #254                // String objectExpression
     145: aastore
     146: aload_0
     147: ldc           #151                // int 24
     149: ldc_w         #260                // String size
     152: aastore
     153: aload_0
     154: ldc           #152                // int 25
     156: ldc_w         #262                // String parameters
     159: aastore
     160: aload_0
     161: ldc           #91                 // int 26
     163: ldc_w         #260                // String size
     166: aastore
     167: aload_0
     168: ldc           #153                // int 27
     170: ldc_w         #264                // String expressions
     173: aastore
     174: aload_0
     175: ldc           #70                 // int 28
     177: ldc_w         #266                // String arguments
     180: aastore
     181: aload_0
     182: ldc           #154                // int 29
     184: ldc_w         #268                // String transpose
     187: aastore
     188: aload_0
     189: ldc           #155                // int 30
     191: ldc_w         #262                // String parameters
     194: aastore
     195: aload_0
     196: ldc           #164                // int 31
     198: ldc_w         #266                // String arguments
     201: aastore
     202: aload_0
     203: ldc           #169                // int 32
     205: ldc_w         #270                // String every
     208: aastore
     209: aload_0
     210: ldc           #178                // int 33
     212: ldc_w         #272                // String getWrapper
     215: aastore
     216: aload_0
     217: ldc           #187                // int 34
     219: ldc_w         #272                // String getWrapper
     222: aastore
     223: aload_0
     224: ldc           #188                // int 35
     226: ldc_w         #274                // String isDerivedFrom
     229: aastore
     230: aload_0
     231: ldc           #189                // int 36
     233: ldc_w         #274                // String isDerivedFrom
     236: aastore
     237: return

  private static org.codehaus.groovy.runtime.callsite.CallSiteArray $createCallSiteArray();
    Code:
       0: ldc_w         #277                // int 37
       3: anewarray     #159                // class java/lang/String
       6: astore_0
       7: aload_0
       8: invokestatic  #279                // Method $createCallSiteArray_1:([Ljava/lang/String;)V
      11: new           #281                // class org/codehaus/groovy/runtime/callsite/CallSiteArray
      14: dup
      15: ldc           #2                  // class org/codehaus/groovy/transform/tailrec/RecursivenessTester
      17: aload_0
      18: invokespecial #284                // Method org/codehaus/groovy/runtime/callsite/CallSiteArray."<init>":(Ljava/lang/Class;[Ljava/lang/String;)V
      21: areturn

  private static org.codehaus.groovy.runtime.callsite.CallSite[] $getCallSiteArray();
    Code:
       0: getstatic     #286                // Field $callSiteArray:Ljava/lang/ref/SoftReference;
       3: ifnull        20
       6: getstatic     #286                // Field $callSiteArray:Ljava/lang/ref/SoftReference;
       9: invokevirtual #292                // Method java/lang/ref/SoftReference.get:()Ljava/lang/Object;
      12: checkcast     #281                // class org/codehaus/groovy/runtime/callsite/CallSiteArray
      15: dup
      16: astore_0
      17: ifnonnull     35
      20: invokestatic  #294                // Method $createCallSiteArray:()Lorg/codehaus/groovy/runtime/callsite/CallSiteArray;
      23: astore_0
      24: new           #288                // class java/lang/ref/SoftReference
      27: dup
      28: aload_0
      29: invokespecial #297                // Method java/lang/ref/SoftReference."<init>":(Ljava/lang/Object;)V
      32: putstatic     #286                // Field $callSiteArray:Ljava/lang/ref/SoftReference;
      35: aload_0
      36: getfield      #301                // Field org/codehaus/groovy/runtime/callsite/CallSiteArray.array:[Lorg/codehaus/groovy/runtime/callsite/CallSite;
      39: areturn
}
