Compiled from "TailRecursiveASTTransformation.groovy"
public class org.codehaus.groovy.transform.tailrec.TailRecursiveASTTransformation extends org.codehaus.groovy.transform.AbstractASTTransformation implements groovy.lang.GroovyObject {
  private static final java.lang.Class MY_CLASS;

  private static final org.codehaus.groovy.ast.ClassNode MY_TYPE;

  private static final java.lang.String MY_TYPE_NAME;

  private org.codehaus.groovy.transform.tailrec.HasRecursiveCalls hasRecursiveCalls;

  private org.codehaus.groovy.transform.tailrec.TernaryToIfStatementConverter ternaryToIfStatement;

  private static org.codehaus.groovy.reflection.ClassInfo $staticClassInfo;

  public static transient boolean __$stMC;

  private transient groovy.lang.MetaClass metaClass;

  private static org.codehaus.groovy.reflection.ClassInfo $staticClassInfo$;

  public org.codehaus.groovy.transform.tailrec.TailRecursiveASTTransformation();
    Code:
       0: aload_0
       1: invokespecial #59                 // Method org/codehaus/groovy/transform/AbstractASTTransformation."<init>":()V
       4: new           #61                 // class org/codehaus/groovy/transform/tailrec/HasRecursiveCalls
       7: dup
       8: invokespecial #62                 // Method org/codehaus/groovy/transform/tailrec/HasRecursiveCalls."<init>":()V
      11: astore_1
      12: aload_1
      13: aload_0
      14: swap
      15: putfield      #64                 // Field hasRecursiveCalls:Lorg/codehaus/groovy/transform/tailrec/HasRecursiveCalls;
      18: aload_1
      19: pop
      20: new           #66                 // class org/codehaus/groovy/transform/tailrec/TernaryToIfStatementConverter
      23: dup
      24: invokespecial #67                 // Method org/codehaus/groovy/transform/tailrec/TernaryToIfStatementConverter."<init>":()V
      27: astore_2
      28: aload_2
      29: aload_0
      30: swap
      31: putfield      #69                 // Field ternaryToIfStatement:Lorg/codehaus/groovy/transform/tailrec/TernaryToIfStatementConverter;
      34: aload_2
      35: pop
      36: aload_0
      37: invokevirtual #73                 // Method $getStaticMetaClass:()Lgroovy/lang/MetaClass;
      40: astore_3
      41: aload_3
      42: aload_0
      43: swap
      44: putfield      #75                 // Field metaClass:Lgroovy/lang/MetaClass;
      47: aload_3
      48: pop
      49: return

  public void visit(org.codehaus.groovy.ast.ASTNode[], org.codehaus.groovy.control.SourceUnit);
    Code:
       0: aload_0
       1: checkcast     #2                  // class org/codehaus/groovy/transform/tailrec/TailRecursiveASTTransformation
       4: aload_1
       5: aload_2
       6: invokevirtual #82                 // Method init:([Lorg/codehaus/groovy/ast/ASTNode;Lorg/codehaus/groovy/control/SourceUnit;)V
       9: aconst_null
      10: pop
      11: aload_1
      12: iconst_1
      13: invokestatic  #88                 // Method org/codehaus/groovy/runtime/BytecodeInterface8.objectArrayGet:([Ljava/lang/Object;I)Ljava/lang/Object;
      16: ldc           #90                 // class org/codehaus/groovy/ast/MethodNode
      18: invokestatic  #96                 // Method org/codehaus/groovy/runtime/ScriptBytecodeAdapter.asType:(Ljava/lang/Object;Ljava/lang/Class;)Ljava/lang/Object;
      21: checkcast     #90                 // class org/codehaus/groovy/ast/MethodNode
      24: astore_3
      25: aload_3
      26: pop
      27: aload_3
      28: invokevirtual #100                // Method org/codehaus/groovy/ast/MethodNode.isAbstract:()Z
      31: ifeq          58
      34: aload_0
      35: checkcast     #2                  // class org/codehaus/groovy/transform/tailrec/TailRecursiveASTTransformation
      38: ldc           #102                // String Annotation
      40: getstatic     #104                // Field MY_TYPE_NAME:Ljava/lang/String;
      43: invokestatic  #110                // Method org/codehaus/groovy/runtime/StringGroovyMethods.plus:(Ljava/lang/String;Ljava/lang/CharSequence;)Ljava/lang/String;
      46: ldc           #112                // String  cannot be used for abstract methods.
      48: invokestatic  #110                // Method org/codehaus/groovy/runtime/StringGroovyMethods.plus:(Ljava/lang/String;Ljava/lang/CharSequence;)Ljava/lang/String;
      51: aload_3
      52: invokevirtual #116                // Method addError:(Ljava/lang/String;Lorg/codehaus/groovy/ast/ASTNode;)V
      55: aconst_null
      56: pop
      57: return
      58: aload_0
      59: aload_3
      60: ldc           #118                // class groovy/transform/Memoized
      62: invokestatic  #124                // Method org/codehaus/groovy/ast/ClassHelper.make:(Ljava/lang/Class;)Lorg/codehaus/groovy/ast/ClassNode;
      65: invokespecial #128                // Method hasAnnotation:(Lorg/codehaus/groovy/ast/MethodNode;Lorg/codehaus/groovy/ast/ClassNode;)Z
      68: ifeq          183
      71: ldc           #118                // class groovy/transform/Memoized
      73: invokestatic  #124                // Method org/codehaus/groovy/ast/ClassHelper.make:(Ljava/lang/Class;)Lorg/codehaus/groovy/ast/ClassNode;
      76: astore        4
      78: aload         4
      80: pop
      81: aconst_null
      82: astore        5
      84: aload_3
      85: checkcast     #90                 // class org/codehaus/groovy/ast/MethodNode
      88: invokevirtual #132                // Method org/codehaus/groovy/ast/MethodNode.getAnnotations:()Ljava/util/List;
      91: invokeinterface #138,  1          // InterfaceMethod java/util/List.iterator:()Ljava/util/Iterator;
      96: astore        6
      98: aload         6
     100: invokeinterface #143,  1          // InterfaceMethod java/util/Iterator.hasNext:()Z
     105: ifeq          183
     108: aload         6
     110: invokeinterface #147,  1          // InterfaceMethod java/util/Iterator.next:()Ljava/lang/Object;
     115: ldc           #149                // class org/codehaus/groovy/ast/AnnotationNode
     117: invokestatic  #152                // Method org/codehaus/groovy/runtime/ScriptBytecodeAdapter.castToType:(Ljava/lang/Object;Ljava/lang/Class;)Ljava/lang/Object;
     120: checkcast     #149                // class org/codehaus/groovy/ast/AnnotationNode
     123: astore        5
     125: aload         5
     127: invokevirtual #156                // Method org/codehaus/groovy/ast/AnnotationNode.getClassNode:()Lorg/codehaus/groovy/ast/ClassNode;
     130: getstatic     #158                // Field MY_TYPE:Lorg/codehaus/groovy/ast/ClassNode;
     133: invokestatic  #162                // Method org/codehaus/groovy/runtime/ScriptBytecodeAdapter.compareEqual:(Ljava/lang/Object;Ljava/lang/Object;)Z
     136: ifeq          142
     139: goto          183
     142: aload         5
     144: invokevirtual #156                // Method org/codehaus/groovy/ast/AnnotationNode.getClassNode:()Lorg/codehaus/groovy/ast/ClassNode;
     147: aload         4
     149: invokestatic  #162                // Method org/codehaus/groovy/runtime/ScriptBytecodeAdapter.compareEqual:(Ljava/lang/Object;Ljava/lang/Object;)Z
     152: ifeq          180
     155: aload_0
     156: checkcast     #2                  // class org/codehaus/groovy/transform/tailrec/TailRecursiveASTTransformation
     159: ldc           #102                // String Annotation
     161: getstatic     #104                // Field MY_TYPE_NAME:Ljava/lang/String;
     164: invokestatic  #110                // Method org/codehaus/groovy/runtime/StringGroovyMethods.plus:(Ljava/lang/String;Ljava/lang/CharSequence;)Ljava/lang/String;
     167: ldc           #164                // String  must be placed before annotation @Memoized.
     169: invokestatic  #110                // Method org/codehaus/groovy/runtime/StringGroovyMethods.plus:(Ljava/lang/String;Ljava/lang/CharSequence;)Ljava/lang/String;
     172: aload         5
     174: invokevirtual #116                // Method addError:(Ljava/lang/String;Lorg/codehaus/groovy/ast/ASTNode;)V
     177: aconst_null
     178: pop
     179: return
     180: goto          98
     183: aload_0
     184: aload_3
     185: invokespecial #168                // Method hasRecursiveMethodCalls:(Lorg/codehaus/groovy/ast/MethodNode;)Z
     188: ifne          195
     191: iconst_1
     192: goto          196
     195: iconst_0
     196: ifeq          253
     199: aload_3
     200: checkcast     #90                 // class org/codehaus/groovy/ast/MethodNode
     203: ldc           #170                // class groovy/transform/TailRecursive
     205: invokestatic  #124                // Method org/codehaus/groovy/ast/ClassHelper.make:(Ljava/lang/Class;)Lorg/codehaus/groovy/ast/ClassNode;
     208: invokevirtual #173                // Method org/codehaus/groovy/ast/MethodNode.getAnnotations:(Lorg/codehaus/groovy/ast/ClassNode;)Ljava/util/List;
     211: iconst_0
     212: invokestatic  #179                // Method org/codehaus/groovy/runtime/DefaultGroovyMethods.getAt:(Ljava/util/List;I)Ljava/lang/Object;
     215: ldc           #149                // class org/codehaus/groovy/ast/AnnotationNode
     217: invokestatic  #152                // Method org/codehaus/groovy/runtime/ScriptBytecodeAdapter.castToType:(Ljava/lang/Object;Ljava/lang/Class;)Ljava/lang/Object;
     220: checkcast     #149                // class org/codehaus/groovy/ast/AnnotationNode
     223: astore        7
     225: aload         7
     227: pop
     228: aload_0
     229: checkcast     #2                  // class org/codehaus/groovy/transform/tailrec/TailRecursiveASTTransformation
     232: ldc           #181                // String No recursive calls detected. You must remove annotation
     234: getstatic     #104                // Field MY_TYPE_NAME:Ljava/lang/String;
     237: invokestatic  #110                // Method org/codehaus/groovy/runtime/StringGroovyMethods.plus:(Ljava/lang/String;Ljava/lang/CharSequence;)Ljava/lang/String;
     240: ldc           #183                // String .
     242: invokestatic  #110                // Method org/codehaus/groovy/runtime/StringGroovyMethods.plus:(Ljava/lang/String;Ljava/lang/CharSequence;)Ljava/lang/String;
     245: aload         7
     247: invokevirtual #116                // Method addError:(Ljava/lang/String;Lorg/codehaus/groovy/ast/ASTNode;)V
     250: aconst_null
     251: pop
     252: return
     253: aload_0
     254: aload_3
     255: aload_2
     256: invokespecial #187                // Method transformToIteration:(Lorg/codehaus/groovy/ast/MethodNode;Lorg/codehaus/groovy/control/SourceUnit;)V
     259: aconst_null
     260: pop
     261: aload_0
     262: aload_3
     263: invokespecial #191                // Method ensureAllRecursiveCallsHaveBeenTransformed:(Lorg/codehaus/groovy/ast/MethodNode;)V
     266: aconst_null
     267: pop
     268: return

  private boolean hasAnnotation(org.codehaus.groovy.ast.MethodNode, org.codehaus.groovy.ast.ClassNode);
    Code:
       0: aload_1
       1: checkcast     #90                 // class org/codehaus/groovy/ast/MethodNode
       4: aload_2
       5: invokevirtual #173                // Method org/codehaus/groovy/ast/MethodNode.getAnnotations:(Lorg/codehaus/groovy/ast/ClassNode;)Ljava/util/List;
       8: astore_3
       9: aload_3
      10: pop
      11: aload_3
      12: ifnull        19
      15: iconst_1
      16: goto          20
      19: iconst_0
      20: ifeq          45
      23: aload_3
      24: invokeinterface #204,  1          // InterfaceMethod java/util/List.size:()I
      29: iconst_0
      30: if_icmple     37
      33: iconst_1
      34: goto          38
      37: iconst_0
      38: ifeq          45
      41: iconst_1
      42: goto          46
      45: iconst_0
      46: ireturn
      47: ldc           #205                // int 0
      49: invokestatic  #211                // Method java/lang/Integer.valueOf:(I)Ljava/lang/Integer;
      52: invokestatic  #217                // Method org/codehaus/groovy/runtime/typehandling/DefaultTypeTransformation.booleanUnbox:(Ljava/lang/Object;)Z
      55: ireturn

  private void transformToIteration(org.codehaus.groovy.ast.MethodNode, org.codehaus.groovy.control.SourceUnit);
    Code:
       0: aload_1
       1: invokevirtual #224                // Method org/codehaus/groovy/ast/MethodNode.isVoidMethod:()Z
       4: ifeq          18
       7: aload_0
       8: aload_1
       9: aload_2
      10: invokespecial #227                // Method transformVoidMethodToIteration:(Lorg/codehaus/groovy/ast/MethodNode;Lorg/codehaus/groovy/control/SourceUnit;)V
      13: aconst_null
      14: pop
      15: goto          26
      18: aload_0
      19: aload_1
      20: aload_2
      21: invokespecial #230                // Method transformNonVoidMethodToIteration:(Lorg/codehaus/groovy/ast/MethodNode;Lorg/codehaus/groovy/control/SourceUnit;)V
      24: aconst_null
      25: pop
      26: return

  private void transformVoidMethodToIteration(org.codehaus.groovy.ast.MethodNode, org.codehaus.groovy.control.SourceUnit);
    Code:
       0: aload_0
       1: checkcast     #2                  // class org/codehaus/groovy/transform/tailrec/TailRecursiveASTTransformation
       4: ldc           #232                // String Void methods are not supported by @TailRecursive yet.
       6: aload_1
       7: invokevirtual #116                // Method addError:(Ljava/lang/String;Lorg/codehaus/groovy/ast/ASTNode;)V
      10: aconst_null
      11: pop
      12: return

  private void transformNonVoidMethodToIteration(org.codehaus.groovy.ast.MethodNode, org.codehaus.groovy.control.SourceUnit);
    Code:
       0: aload_0
       1: aload_1
       2: invokespecial #235                // Method addMissingDefaultReturnStatement:(Lorg/codehaus/groovy/ast/MethodNode;)V
       5: aconst_null
       6: pop
       7: aload_0
       8: aload_1
       9: invokespecial #238                // Method replaceReturnsWithTernariesToIfStatements:(Lorg/codehaus/groovy/ast/MethodNode;)V
      12: aconst_null
      13: pop
      14: aload_0
      15: aload_1
      16: invokespecial #241                // Method wrapMethodBodyWithWhileLoop:(Lorg/codehaus/groovy/ast/MethodNode;)V
      19: aconst_null
      20: pop
      21: aload_0
      22: aload_1
      23: invokevirtual #245                // Method name2VariableMappingFor:(Lorg/codehaus/groovy/ast/MethodNode;)Ljava/util/Map;
      26: astore_3
      27: aload_3
      28: pop
      29: aload_0
      30: aload_1
      31: aload_3
      32: invokespecial #249                // Method replaceAllAccessToParams:(Lorg/codehaus/groovy/ast/MethodNode;Ljava/util/Map;)V
      35: aconst_null
      36: pop
      37: aload_0
      38: aload_1
      39: aload_3
      40: invokespecial #252                // Method addLocalVariablesForAllParameters:(Lorg/codehaus/groovy/ast/MethodNode;Ljava/util/Map;)V
      43: aconst_null
      44: pop
      45: aload_0
      46: aload_1
      47: invokevirtual #255                // Method position2VariableMappingFor:(Lorg/codehaus/groovy/ast/MethodNode;)Ljava/util/Map;
      50: astore        4
      52: aload         4
      54: pop
      55: aload_0
      56: aload_1
      57: aload         4
      59: invokespecial #258                // Method replaceAllRecursiveReturnsWithIteration:(Lorg/codehaus/groovy/ast/MethodNode;Ljava/util/Map;)V
      62: aconst_null
      63: pop
      64: aload_0
      65: aload_2
      66: aload_1
      67: invokespecial #262                // Method repairVariableScopes:(Lorg/codehaus/groovy/control/SourceUnit;Lorg/codehaus/groovy/ast/MethodNode;)V
      70: aconst_null
      71: pop
      72: return

  private void repairVariableScopes(org.codehaus.groovy.control.SourceUnit, org.codehaus.groovy.ast.MethodNode);
    Code:
       0: new           #267                // class org/codehaus/groovy/classgen/VariableScopeVisitor
       3: dup
       4: aload_1
       5: invokespecial #270                // Method org/codehaus/groovy/classgen/VariableScopeVisitor."<init>":(Lorg/codehaus/groovy/control/SourceUnit;)V
       8: aload_2
       9: checkcast     #90                 // class org/codehaus/groovy/ast/MethodNode
      12: invokevirtual #273                // Method org/codehaus/groovy/ast/MethodNode.getDeclaringClass:()Lorg/codehaus/groovy/ast/ClassNode;
      15: invokevirtual #277                // Method org/codehaus/groovy/classgen/VariableScopeVisitor.visitClass:(Lorg/codehaus/groovy/ast/ClassNode;)V
      18: aconst_null
      19: pop
      20: return

  private void replaceReturnsWithTernariesToIfStatements(org.codehaus.groovy.ast.MethodNode);
    Code:
       0: new           #13                 // class org/codehaus/groovy/transform/tailrec/TailRecursiveASTTransformation$_replaceReturnsWithTernariesToIfStatements_closure1
       3: dup
       4: aload_0
       5: aload_0
       6: invokespecial #280                // Method org/codehaus/groovy/transform/tailrec/TailRecursiveASTTransformation$_replaceReturnsWithTernariesToIfStatements_closure1."<init>":(Ljava/lang/Object;Ljava/lang/Object;)V
       9: astore_2
      10: aload_2
      11: pop
      12: new           #16                 // class org/codehaus/groovy/transform/tailrec/TailRecursiveASTTransformation$_replaceReturnsWithTernariesToIfStatements_closure2
      15: dup
      16: aload_0
      17: aload_0
      18: invokespecial #281                // Method org/codehaus/groovy/transform/tailrec/TailRecursiveASTTransformation$_replaceReturnsWithTernariesToIfStatements_closure2."<init>":(Ljava/lang/Object;Ljava/lang/Object;)V
      21: astore_3
      22: aload_3
      23: pop
      24: new           #283                // class org/codehaus/groovy/transform/tailrec/StatementReplacer
      27: dup
      28: invokespecial #284                // Method org/codehaus/groovy/transform/tailrec/StatementReplacer."<init>":()V
      31: astore        4
      33: aload_2
      34: dup
      35: astore        5
      37: aload         4
      39: aload         5
      41: invokevirtual #288                // Method org/codehaus/groovy/transform/tailrec/StatementReplacer.setWhen:(Lgroovy/lang/Closure;)V
      44: aconst_null
      45: pop
      46: pop
      47: aload_3
      48: dup
      49: astore        6
      51: aload         4
      53: aload         6
      55: invokevirtual #291                // Method org/codehaus/groovy/transform/tailrec/StatementReplacer.setReplaceWith:(Lgroovy/lang/Closure;)V
      58: aconst_null
      59: pop
      60: pop
      61: aload         4
      63: astore        7
      65: aload         7
      67: pop
      68: aload         7
      70: aload_1
      71: invokevirtual #295                // Method org/codehaus/groovy/ast/MethodNode.getCode:()Lorg/codehaus/groovy/ast/stmt/Statement;
      74: invokevirtual #299                // Method org/codehaus/groovy/transform/tailrec/StatementReplacer.replaceIn:(Lorg/codehaus/groovy/ast/ASTNode;)V
      77: aconst_null
      78: pop
      79: return

  private void addLocalVariablesForAllParameters(org.codehaus.groovy.ast.MethodNode, java.util.Map<java.lang.String, java.util.Map>);
    Code:
       0: aload_1
       1: invokevirtual #295                // Method org/codehaus/groovy/ast/MethodNode.getCode:()Lorg/codehaus/groovy/ast/stmt/Statement;
       4: ldc_w         #306                // class org/codehaus/groovy/ast/stmt/BlockStatement
       7: invokestatic  #96                 // Method org/codehaus/groovy/runtime/ScriptBytecodeAdapter.asType:(Ljava/lang/Object;Ljava/lang/Class;)Ljava/lang/Object;
      10: checkcast     #306                // class org/codehaus/groovy/ast/stmt/BlockStatement
      13: new           #308                // class groovy/lang/Reference
      16: dup_x1
      17: swap
      18: invokespecial #311                // Method groovy/lang/Reference."<init>":(Ljava/lang/Object;)V
      21: astore_3
      22: aload_3
      23: pop
      24: aload_2
      25: new           #19                 // class org/codehaus/groovy/transform/tailrec/TailRecursiveASTTransformation$_addLocalVariablesForAllParameters_closure3
      28: dup
      29: aload_0
      30: aload_0
      31: aload_3
      32: invokespecial #314                // Method org/codehaus/groovy/transform/tailrec/TailRecursiveASTTransformation$_addLocalVariablesForAllParameters_closure3."<init>":(Ljava/lang/Object;Ljava/lang/Object;Lgroovy/lang/Reference;)V
      35: invokestatic  #318                // Method org/codehaus/groovy/runtime/DefaultGroovyMethods.each:(Ljava/util/Map;Lgroovy/lang/Closure;)Ljava/util/Map;
      38: pop
      39: return

  private void replaceAllAccessToParams(org.codehaus.groovy.ast.MethodNode, java.util.Map<java.lang.String, java.util.Map>);
    Code:
       0: new           #322                // class org/codehaus/groovy/transform/tailrec/VariableAccessReplacer
       3: dup
       4: invokespecial #323                // Method org/codehaus/groovy/transform/tailrec/VariableAccessReplacer."<init>":()V
       7: astore_3
       8: aload_2
       9: dup
      10: astore        4
      12: aload_3
      13: aload         4
      15: invokevirtual #327                // Method org/codehaus/groovy/transform/tailrec/VariableAccessReplacer.setNameAndTypeMapping:(Ljava/util/Map;)V
      18: aconst_null
      19: pop
      20: pop
      21: aload_3
      22: aload_1
      23: invokevirtual #295                // Method org/codehaus/groovy/ast/MethodNode.getCode:()Lorg/codehaus/groovy/ast/stmt/Statement;
      26: invokevirtual #328                // Method org/codehaus/groovy/transform/tailrec/VariableAccessReplacer.replaceIn:(Lorg/codehaus/groovy/ast/ASTNode;)V
      29: aconst_null
      30: pop
      31: return

  public java.util.Map<java.lang.String, java.util.Map> name2VariableMappingFor(org.codehaus.groovy.ast.MethodNode);
    Code:
       0: iconst_0
       1: anewarray     #330                // class java/lang/Object
       4: invokestatic  #334                // Method org/codehaus/groovy/runtime/ScriptBytecodeAdapter.createMap:([Ljava/lang/Object;)Ljava/util/Map;
       7: ldc_w         #336                // class java/util/LinkedHashMap
      10: invokestatic  #152                // Method org/codehaus/groovy/runtime/ScriptBytecodeAdapter.castToType:(Ljava/lang/Object;Ljava/lang/Class;)Ljava/lang/Object;
      13: checkcast     #336                // class java/util/LinkedHashMap
      16: new           #308                // class groovy/lang/Reference
      19: dup_x1
      20: swap
      21: invokespecial #311                // Method groovy/lang/Reference."<init>":(Ljava/lang/Object;)V
      24: astore_2
      25: aload_2
      26: pop
      27: aload_1
      28: invokevirtual #340                // Method org/codehaus/groovy/ast/MethodNode.getParameters:()[Lorg/codehaus/groovy/ast/Parameter;
      31: new           #22                 // class org/codehaus/groovy/transform/tailrec/TailRecursiveASTTransformation$_name2VariableMappingFor_closure4
      34: dup
      35: aload_0
      36: aload_0
      37: aload_2
      38: invokespecial #341                // Method org/codehaus/groovy/transform/tailrec/TailRecursiveASTTransformation$_name2VariableMappingFor_closure4."<init>":(Ljava/lang/Object;Ljava/lang/Object;Lgroovy/lang/Reference;)V
      41: invokestatic  #344                // Method org/codehaus/groovy/runtime/DefaultGroovyMethods.each:(Ljava/lang/Object;Lgroovy/lang/Closure;)Ljava/lang/Object;
      44: pop
      45: aload_2
      46: invokevirtual #347                // Method groovy/lang/Reference.get:()Ljava/lang/Object;
      49: checkcast     #336                // class java/util/LinkedHashMap
      52: areturn
      53: aconst_null
      54: areturn

  public java.util.Map<java.lang.Integer, java.util.Map> position2VariableMappingFor(org.codehaus.groovy.ast.MethodNode);
    Code:
       0: iconst_0
       1: anewarray     #330                // class java/lang/Object
       4: invokestatic  #334                // Method org/codehaus/groovy/runtime/ScriptBytecodeAdapter.createMap:([Ljava/lang/Object;)Ljava/util/Map;
       7: ldc_w         #336                // class java/util/LinkedHashMap
      10: invokestatic  #152                // Method org/codehaus/groovy/runtime/ScriptBytecodeAdapter.castToType:(Ljava/lang/Object;Ljava/lang/Class;)Ljava/lang/Object;
      13: checkcast     #336                // class java/util/LinkedHashMap
      16: new           #308                // class groovy/lang/Reference
      19: dup_x1
      20: swap
      21: invokespecial #311                // Method groovy/lang/Reference."<init>":(Ljava/lang/Object;)V
      24: astore_2
      25: aload_2
      26: pop
      27: aload_1
      28: invokevirtual #340                // Method org/codehaus/groovy/ast/MethodNode.getParameters:()[Lorg/codehaus/groovy/ast/Parameter;
      31: new           #25                 // class org/codehaus/groovy/transform/tailrec/TailRecursiveASTTransformation$_position2VariableMappingFor_closure5
      34: dup
      35: aload_0
      36: aload_0
      37: aload_2
      38: invokespecial #348                // Method org/codehaus/groovy/transform/tailrec/TailRecursiveASTTransformation$_position2VariableMappingFor_closure5."<init>":(Ljava/lang/Object;Ljava/lang/Object;Lgroovy/lang/Reference;)V
      41: invokestatic  #351                // Method org/codehaus/groovy/runtime/DefaultGroovyMethods.eachWithIndex:(Ljava/lang/Object;Lgroovy/lang/Closure;)Ljava/lang/Object;
      44: pop
      45: aload_2
      46: invokevirtual #347                // Method groovy/lang/Reference.get:()Ljava/lang/Object;
      49: checkcast     #336                // class java/util/LinkedHashMap
      52: areturn
      53: aconst_null
      54: areturn

  private java.lang.String iterationVariableName(java.lang.String);
    Code:
       0: ldc_w         #355                // String _
       3: aload_1
       4: invokestatic  #110                // Method org/codehaus/groovy/runtime/StringGroovyMethods.plus:(Ljava/lang/String;Ljava/lang/CharSequence;)Ljava/lang/String;
       7: ldc_w         #355                // String _
      10: invokestatic  #110                // Method org/codehaus/groovy/runtime/StringGroovyMethods.plus:(Ljava/lang/String;Ljava/lang/CharSequence;)Ljava/lang/String;
      13: areturn
      14: aconst_null
      15: areturn

  private void replaceAllRecursiveReturnsWithIteration(org.codehaus.groovy.ast.MethodNode, java.util.Map);
    Code:
       0: aload_0
       1: aload_1
       2: aload_2
       3: invokespecial #359                // Method replaceRecursiveReturnsOutsideClosures:(Lorg/codehaus/groovy/ast/MethodNode;Ljava/util/Map;)V
       6: aconst_null
       7: pop
       8: aload_0
       9: aload_1
      10: aload_2
      11: invokespecial #362                // Method replaceRecursiveReturnsInsideClosures:(Lorg/codehaus/groovy/ast/MethodNode;Ljava/util/Map;)V
      14: aconst_null
      15: pop
      16: return

  private void replaceRecursiveReturnsOutsideClosures(org.codehaus.groovy.ast.MethodNode, java.util.Map<java.lang.Integer, java.util.Map>);
    Code:
       0: aload_1
       1: new           #308                // class groovy/lang/Reference
       4: dup_x1
       5: swap
       6: invokespecial #311                // Method groovy/lang/Reference."<init>":(Ljava/lang/Object;)V
       9: astore_3
      10: aload_2
      11: new           #308                // class groovy/lang/Reference
      14: dup_x1
      15: swap
      16: invokespecial #311                // Method groovy/lang/Reference."<init>":(Ljava/lang/Object;)V
      19: astore        4
      21: new           #28                 // class org/codehaus/groovy/transform/tailrec/TailRecursiveASTTransformation$_replaceRecursiveReturnsOutsideClosures_closure6
      24: dup
      25: aload_0
      26: aload_0
      27: aload_3
      28: invokespecial #363                // Method org/codehaus/groovy/transform/tailrec/TailRecursiveASTTransformation$_replaceRecursiveReturnsOutsideClosures_closure6."<init>":(Ljava/lang/Object;Ljava/lang/Object;Lgroovy/lang/Reference;)V
      31: astore        5
      33: aload         5
      35: pop
      36: new           #31                 // class org/codehaus/groovy/transform/tailrec/TailRecursiveASTTransformation$_replaceRecursiveReturnsOutsideClosures_closure7
      39: dup
      40: aload_0
      41: aload_0
      42: aload         4
      44: invokespecial #364                // Method org/codehaus/groovy/transform/tailrec/TailRecursiveASTTransformation$_replaceRecursiveReturnsOutsideClosures_closure7."<init>":(Ljava/lang/Object;Ljava/lang/Object;Lgroovy/lang/Reference;)V
      47: astore        6
      49: aload         6
      51: pop
      52: new           #283                // class org/codehaus/groovy/transform/tailrec/StatementReplacer
      55: dup
      56: invokespecial #284                // Method org/codehaus/groovy/transform/tailrec/StatementReplacer."<init>":()V
      59: astore        7
      61: aload         5
      63: dup
      64: astore        8
      66: aload         7
      68: aload         8
      70: invokevirtual #288                // Method org/codehaus/groovy/transform/tailrec/StatementReplacer.setWhen:(Lgroovy/lang/Closure;)V
      73: aconst_null
      74: pop
      75: pop
      76: aload         6
      78: dup
      79: astore        9
      81: aload         7
      83: aload         9
      85: invokevirtual #291                // Method org/codehaus/groovy/transform/tailrec/StatementReplacer.setReplaceWith:(Lgroovy/lang/Closure;)V
      88: aconst_null
      89: pop
      90: pop
      91: aload         7
      93: astore        10
      95: aload         10
      97: pop
      98: aload         10
     100: aload_3
     101: invokevirtual #347                // Method groovy/lang/Reference.get:()Ljava/lang/Object;
     104: checkcast     #90                 // class org/codehaus/groovy/ast/MethodNode
     107: invokevirtual #295                // Method org/codehaus/groovy/ast/MethodNode.getCode:()Lorg/codehaus/groovy/ast/stmt/Statement;
     110: invokevirtual #299                // Method org/codehaus/groovy/transform/tailrec/StatementReplacer.replaceIn:(Lorg/codehaus/groovy/ast/ASTNode;)V
     113: aconst_null
     114: pop
     115: return

  private void replaceRecursiveReturnsInsideClosures(org.codehaus.groovy.ast.MethodNode, java.util.Map<java.lang.Integer, java.util.Map>);
    Code:
       0: aload_1
       1: new           #308                // class groovy/lang/Reference
       4: dup_x1
       5: swap
       6: invokespecial #311                // Method groovy/lang/Reference."<init>":(Ljava/lang/Object;)V
       9: astore_3
      10: aload_2
      11: new           #308                // class groovy/lang/Reference
      14: dup_x1
      15: swap
      16: invokespecial #311                // Method groovy/lang/Reference."<init>":(Ljava/lang/Object;)V
      19: astore        4
      21: new           #34                 // class org/codehaus/groovy/transform/tailrec/TailRecursiveASTTransformation$_replaceRecursiveReturnsInsideClosures_closure8
      24: dup
      25: aload_0
      26: aload_0
      27: aload_3
      28: invokespecial #367                // Method org/codehaus/groovy/transform/tailrec/TailRecursiveASTTransformation$_replaceRecursiveReturnsInsideClosures_closure8."<init>":(Ljava/lang/Object;Ljava/lang/Object;Lgroovy/lang/Reference;)V
      31: astore        5
      33: aload         5
      35: pop
      36: new           #37                 // class org/codehaus/groovy/transform/tailrec/TailRecursiveASTTransformation$_replaceRecursiveReturnsInsideClosures_closure9
      39: dup
      40: aload_0
      41: aload_0
      42: aload         4
      44: invokespecial #368                // Method org/codehaus/groovy/transform/tailrec/TailRecursiveASTTransformation$_replaceRecursiveReturnsInsideClosures_closure9."<init>":(Ljava/lang/Object;Ljava/lang/Object;Lgroovy/lang/Reference;)V
      47: astore        6
      49: aload         6
      51: pop
      52: new           #283                // class org/codehaus/groovy/transform/tailrec/StatementReplacer
      55: dup
      56: invokespecial #284                // Method org/codehaus/groovy/transform/tailrec/StatementReplacer."<init>":()V
      59: astore        7
      61: aload         5
      63: dup
      64: astore        8
      66: aload         7
      68: aload         8
      70: invokevirtual #288                // Method org/codehaus/groovy/transform/tailrec/StatementReplacer.setWhen:(Lgroovy/lang/Closure;)V
      73: aconst_null
      74: pop
      75: pop
      76: aload         6
      78: dup
      79: astore        9
      81: aload         7
      83: aload         9
      85: invokevirtual #291                // Method org/codehaus/groovy/transform/tailrec/StatementReplacer.setReplaceWith:(Lgroovy/lang/Closure;)V
      88: aconst_null
      89: pop
      90: pop
      91: aload         7
      93: astore        10
      95: aload         10
      97: pop
      98: aload         10
     100: aload_3
     101: invokevirtual #347                // Method groovy/lang/Reference.get:()Ljava/lang/Object;
     104: checkcast     #90                 // class org/codehaus/groovy/ast/MethodNode
     107: invokevirtual #295                // Method org/codehaus/groovy/ast/MethodNode.getCode:()Lorg/codehaus/groovy/ast/stmt/Statement;
     110: invokevirtual #299                // Method org/codehaus/groovy/transform/tailrec/StatementReplacer.replaceIn:(Lorg/codehaus/groovy/ast/ASTNode;)V
     113: aconst_null
     114: pop
     115: return

  private void wrapMethodBodyWithWhileLoop(org.codehaus.groovy.ast.MethodNode);
    Code:
       0: new           #371                // class org/codehaus/groovy/transform/tailrec/InWhileLoopWrapper
       3: dup
       4: invokespecial #372                // Method org/codehaus/groovy/transform/tailrec/InWhileLoopWrapper."<init>":()V
       7: aload_1
       8: invokevirtual #375                // Method org/codehaus/groovy/transform/tailrec/InWhileLoopWrapper.wrap:(Lorg/codehaus/groovy/ast/MethodNode;)V
      11: aconst_null
      12: pop
      13: return

  private void addMissingDefaultReturnStatement(org.codehaus.groovy.ast.MethodNode);
    Code:
       0: new           #377                // class org/codehaus/groovy/classgen/ReturnAdder
       3: dup
       4: invokespecial #378                // Method org/codehaus/groovy/classgen/ReturnAdder."<init>":()V
       7: aload_1
       8: invokevirtual #381                // Method org/codehaus/groovy/classgen/ReturnAdder.visitMethod:(Lorg/codehaus/groovy/ast/MethodNode;)V
      11: aconst_null
      12: pop
      13: new           #383                // class org/codehaus/groovy/transform/tailrec/ReturnAdderForClosures
      16: dup
      17: invokespecial #384                // Method org/codehaus/groovy/transform/tailrec/ReturnAdderForClosures."<init>":()V
      20: aload_1
      21: invokevirtual #385                // Method org/codehaus/groovy/transform/tailrec/ReturnAdderForClosures.visitMethod:(Lorg/codehaus/groovy/ast/MethodNode;)V
      24: aconst_null
      25: pop
      26: return

  private void ensureAllRecursiveCallsHaveBeenTransformed(org.codehaus.groovy.ast.MethodNode);
    Code:
       0: new           #387                // class org/codehaus/groovy/transform/tailrec/CollectRecursiveCalls
       3: dup
       4: invokespecial #388                // Method org/codehaus/groovy/transform/tailrec/CollectRecursiveCalls."<init>":()V
       7: aload_1
       8: invokevirtual #392                // Method org/codehaus/groovy/transform/tailrec/CollectRecursiveCalls.collect:(Lorg/codehaus/groovy/ast/MethodNode;)Ljava/util/List;
      11: astore_2
      12: aload_2
      13: pop
      14: aconst_null
      15: astore_3
      16: aload_2
      17: invokeinterface #138,  1          // InterfaceMethod java/util/List.iterator:()Ljava/util/Iterator;
      22: astore        4
      24: aload         4
      26: invokeinterface #143,  1          // InterfaceMethod java/util/Iterator.hasNext:()Z
      31: ifeq          67
      34: aload         4
      36: invokeinterface #147,  1          // InterfaceMethod java/util/Iterator.next:()Ljava/lang/Object;
      41: ldc_w         #394                // class org/codehaus/groovy/ast/expr/Expression
      44: invokestatic  #152                // Method org/codehaus/groovy/runtime/ScriptBytecodeAdapter.castToType:(Ljava/lang/Object;Ljava/lang/Class;)Ljava/lang/Object;
      47: checkcast     #394                // class org/codehaus/groovy/ast/expr/Expression
      50: astore_3
      51: aload_0
      52: checkcast     #2                  // class org/codehaus/groovy/transform/tailrec/TailRecursiveASTTransformation
      55: ldc_w         #396                // String Recursive call could not be transformed by @TailRecursive. Maybe it\'s not a tail call.
      58: aload_3
      59: invokevirtual #116                // Method addError:(Ljava/lang/String;Lorg/codehaus/groovy/ast/ASTNode;)V
      62: aconst_null
      63: pop
      64: goto          24
      67: return

  private boolean hasRecursiveMethodCalls(org.codehaus.groovy.ast.MethodNode);
    Code:
       0: aload_0
       1: getfield      #64                 // Field hasRecursiveCalls:Lorg/codehaus/groovy/transform/tailrec/HasRecursiveCalls;
       4: aload_1
       5: invokevirtual #402                // Method org/codehaus/groovy/transform/tailrec/HasRecursiveCalls.test:(Lorg/codehaus/groovy/ast/MethodNode;)Z
       8: ireturn
       9: ldc           #205                // int 0
      11: invokestatic  #211                // Method java/lang/Integer.valueOf:(I)Ljava/lang/Integer;
      14: invokestatic  #217                // Method org/codehaus/groovy/runtime/typehandling/DefaultTypeTransformation.booleanUnbox:(Ljava/lang/Object;)Z
      17: ireturn

  private boolean isRecursiveIn(org.codehaus.groovy.ast.expr.Expression, org.codehaus.groovy.ast.MethodNode);
    Code:
       0: aload_1
       1: instanceof    #406                // class org/codehaus/groovy/ast/expr/MethodCallExpression
       4: ifeq          29
       7: new           #408                // class org/codehaus/groovy/transform/tailrec/RecursivenessTester
      10: dup
      11: invokespecial #409                // Method org/codehaus/groovy/transform/tailrec/RecursivenessTester."<init>":()V
      14: aload_2
      15: aload_1
      16: ldc_w         #406                // class org/codehaus/groovy/ast/expr/MethodCallExpression
      19: invokestatic  #152                // Method org/codehaus/groovy/runtime/ScriptBytecodeAdapter.castToType:(Ljava/lang/Object;Ljava/lang/Class;)Ljava/lang/Object;
      22: checkcast     #406                // class org/codehaus/groovy/ast/expr/MethodCallExpression
      25: invokevirtual #413                // Method org/codehaus/groovy/transform/tailrec/RecursivenessTester.isRecursive:(Lorg/codehaus/groovy/ast/MethodNode;Lorg/codehaus/groovy/ast/expr/MethodCallExpression;)Z
      28: ireturn
      29: aload_1
      30: instanceof    #415                // class org/codehaus/groovy/ast/expr/StaticMethodCallExpression
      33: ifeq          61
      36: new           #408                // class org/codehaus/groovy/transform/tailrec/RecursivenessTester
      39: dup
      40: invokespecial #409                // Method org/codehaus/groovy/transform/tailrec/RecursivenessTester."<init>":()V
      43: aload_2
      44: aload_1
      45: ldc_w         #415                // class org/codehaus/groovy/ast/expr/StaticMethodCallExpression
      48: invokestatic  #152                // Method org/codehaus/groovy/runtime/ScriptBytecodeAdapter.castToType:(Ljava/lang/Object;Ljava/lang/Class;)Ljava/lang/Object;
      51: checkcast     #415                // class org/codehaus/groovy/ast/expr/StaticMethodCallExpression
      54: invokevirtual #418                // Method org/codehaus/groovy/transform/tailrec/RecursivenessTester.isRecursive:(Lorg/codehaus/groovy/ast/MethodNode;Lorg/codehaus/groovy/ast/expr/StaticMethodCallExpression;)Z
      57: ireturn
      58: goto          66
      61: aconst_null
      62: invokestatic  #217                // Method org/codehaus/groovy/runtime/typehandling/DefaultTypeTransformation.booleanUnbox:(Ljava/lang/Object;)Z
      65: ireturn
      66: ldc           #205                // int 0
      68: invokestatic  #211                // Method java/lang/Integer.valueOf:(I)Ljava/lang/Integer;
      71: invokestatic  #217                // Method org/codehaus/groovy/runtime/typehandling/DefaultTypeTransformation.booleanUnbox:(Ljava/lang/Object;)Z
      74: ireturn

  protected groovy.lang.MetaClass $getStaticMetaClass();
    Code:
       0: aload_0
       1: invokevirtual #423                // Method java/lang/Object.getClass:()Ljava/lang/Class;
       4: ldc           #2                  // class org/codehaus/groovy/transform/tailrec/TailRecursiveASTTransformation
       6: if_acmpeq     14
       9: aload_0
      10: invokestatic  #427                // Method org/codehaus/groovy/runtime/ScriptBytecodeAdapter.initMetaClass:(Ljava/lang/Object;)Lgroovy/lang/MetaClass;
      13: areturn
      14: getstatic     #429                // Field $staticClassInfo:Lorg/codehaus/groovy/reflection/ClassInfo;
      17: astore_1
      18: aload_1
      19: ifnonnull     34
      22: aload_0
      23: invokevirtual #423                // Method java/lang/Object.getClass:()Ljava/lang/Class;
      26: invokestatic  #435                // Method org/codehaus/groovy/reflection/ClassInfo.getClassInfo:(Ljava/lang/Class;)Lorg/codehaus/groovy/reflection/ClassInfo;
      29: dup
      30: astore_1
      31: putstatic     #429                // Field $staticClassInfo:Lorg/codehaus/groovy/reflection/ClassInfo;
      34: aload_1
      35: invokevirtual #438                // Method org/codehaus/groovy/reflection/ClassInfo.getMetaClass:()Lgroovy/lang/MetaClass;
      38: areturn

  public static void access$0(org.codehaus.groovy.transform.tailrec.TailRecursiveASTTransformation, org.codehaus.groovy.ast.ASTNode[], org.codehaus.groovy.control.SourceUnit);
    Code:
       0: aload_0
       1: checkcast     #2                  // class org/codehaus/groovy/transform/tailrec/TailRecursiveASTTransformation
       4: aload_1
       5: aload_2
       6: invokevirtual #82                 // Method init:([Lorg/codehaus/groovy/ast/ASTNode;Lorg/codehaus/groovy/control/SourceUnit;)V
       9: aconst_null
      10: pop
      11: return

  public static java.lang.String access$1(org.codehaus.groovy.transform.tailrec.TailRecursiveASTTransformation, java.lang.String);
    Code:
       0: aload_0
       1: aload_1
       2: invokespecial #447                // Method iterationVariableName:(Ljava/lang/String;)Ljava/lang/String;
       5: areturn
       6: aconst_null
       7: areturn

  public static boolean access$2(org.codehaus.groovy.transform.tailrec.TailRecursiveASTTransformation, org.codehaus.groovy.ast.expr.Expression, org.codehaus.groovy.ast.MethodNode);
    Code:
       0: aload_0
       1: aload_1
       2: aload_2
       3: invokespecial #451                // Method isRecursiveIn:(Lorg/codehaus/groovy/ast/expr/Expression;Lorg/codehaus/groovy/ast/MethodNode;)Z
       6: ireturn
       7: ldc           #205                // int 0
       9: invokestatic  #211                // Method java/lang/Integer.valueOf:(I)Ljava/lang/Integer;
      12: invokestatic  #217                // Method org/codehaus/groovy/runtime/typehandling/DefaultTypeTransformation.booleanUnbox:(Ljava/lang/Object;)Z
      15: ireturn

  public static org.codehaus.groovy.transform.tailrec.TernaryToIfStatementConverter pfaccess$0(org.codehaus.groovy.transform.tailrec.TailRecursiveASTTransformation);
    Code:
       0: aload_0
       1: getfield      #69                 // Field ternaryToIfStatement:Lorg/codehaus/groovy/transform/tailrec/TernaryToIfStatementConverter;
       4: areturn
       5: aconst_null
       6: areturn

  public groovy.lang.MetaClass getMetaClass();
    Code:
       0: aload_0
       1: getfield      #75                 // Field metaClass:Lgroovy/lang/MetaClass;
       4: dup
       5: ifnull        9
       8: areturn
       9: pop
      10: aload_0
      11: dup
      12: invokevirtual #73                 // Method $getStaticMetaClass:()Lgroovy/lang/MetaClass;
      15: putfield      #75                 // Field metaClass:Lgroovy/lang/MetaClass;
      18: aload_0
      19: getfield      #75                 // Field metaClass:Lgroovy/lang/MetaClass;
      22: areturn

  public void setMetaClass(groovy.lang.MetaClass);
    Code:
       0: aload_0
       1: aload_1
       2: putfield      #75                 // Field metaClass:Lgroovy/lang/MetaClass;
       5: return

  public java.lang.Object invokeMethod(java.lang.String, java.lang.Object);
    Code:
       0: aload_0
       1: invokevirtual #458                // Method getMetaClass:()Lgroovy/lang/MetaClass;
       4: aload_0
       5: aload_1
       6: aload_2
       7: invokeinterface #463,  4          // InterfaceMethod groovy/lang/MetaClass.invokeMethod:(Ljava/lang/Object;Ljava/lang/String;Ljava/lang/Object;)Ljava/lang/Object;
      12: areturn

  public java.lang.Object getProperty(java.lang.String);
    Code:
       0: aload_0
       1: invokevirtual #458                // Method getMetaClass:()Lgroovy/lang/MetaClass;
       4: aload_0
       5: aload_1
       6: invokeinterface #468,  3          // InterfaceMethod groovy/lang/MetaClass.getProperty:(Ljava/lang/Object;Ljava/lang/String;)Ljava/lang/Object;
      11: areturn

  public void setProperty(java.lang.String, java.lang.Object);
    Code:
       0: aload_0
       1: invokevirtual #458                // Method getMetaClass:()Lgroovy/lang/MetaClass;
       4: aload_0
       5: aload_1
       6: aload_2
       7: invokeinterface #473,  4          // InterfaceMethod groovy/lang/MetaClass.setProperty:(Ljava/lang/Object;Ljava/lang/String;Ljava/lang/Object;)V
      12: return

  static {};
    Code:
       0: ldc           #170                // class groovy/transform/TailRecursive
       2: astore_0
       3: aload_0
       4: putstatic     #476                // Field MY_CLASS:Ljava/lang/Class;
       7: aload_0
       8: pop
       9: new           #478                // class org/codehaus/groovy/ast/ClassNode
      12: dup
      13: getstatic     #476                // Field MY_CLASS:Ljava/lang/Class;
      16: invokespecial #481                // Method org/codehaus/groovy/ast/ClassNode."<init>":(Ljava/lang/Class;)V
      19: astore_1
      20: aload_1
      21: putstatic     #158                // Field MY_TYPE:Lorg/codehaus/groovy/ast/ClassNode;
      24: aload_1
      25: pop
      26: ldc_w         #483                // String @
      29: getstatic     #158                // Field MY_TYPE:Lorg/codehaus/groovy/ast/ClassNode;
      32: invokevirtual #487                // Method org/codehaus/groovy/ast/ClassNode.getNameWithoutPackage:()Ljava/lang/String;
      35: invokestatic  #110                // Method org/codehaus/groovy/runtime/StringGroovyMethods.plus:(Ljava/lang/String;Ljava/lang/CharSequence;)Ljava/lang/String;
      38: astore_2
      39: aload_2
      40: putstatic     #104                // Field MY_TYPE_NAME:Ljava/lang/String;
      43: aload_2
      44: pop
      45: return

  public static java.lang.String getMY_TYPE_NAME();
    Code:
       0: getstatic     #104                // Field MY_TYPE_NAME:Ljava/lang/String;
       3: areturn
}
