Compiled from "Constants.java"
public final class org.apache.coyote.http11.Constants {
  public static final int DEFAULT_CONNECTION_TIMEOUT;

  public static final java.lang.String CRLF;

  public static final byte CR;

  public static final byte LF;

  public static final byte SP;

  public static final byte HT;

  public static final byte COLON;

  public static final byte SEMI_COLON;

  public static final byte A;

  public static final byte a;

  public static final byte Z;

  public static final byte QUESTION;

  public static final byte LC_OFFSET;

  public static final java.lang.String CONNECTION;

  public static final java.lang.String CLOSE;

  public static final byte[] CLOSE_BYTES;

  public static final java.lang.String KEEPALIVE;

  public static final java.lang.String KEEP_ALIVE_HEADER_VALUE_TOKEN;

  public static final byte[] KEEPALIVE_BYTES;

  public static final java.lang.String CHUNKED;

  public static final byte[] ACK_BYTES_REASON;

  public static final byte[] ACK_BYTES;

  public static final java.lang.String TRANSFERENCODING;

  public static final java.lang.String KEEP_ALIVE_HEADER_NAME;

  public static final byte[] _200_BYTES;

  public static final byte[] _400_BYTES;

  public static final byte[] _404_BYTES;

  public static final int IDENTITY_FILTER;

  public static final int CHUNKED_FILTER;

  public static final int VOID_FILTER;

  public static final int GZIP_FILTER;

  public static final int BUFFERED_FILTER;

  public static final java.lang.String HTTP_10;

  public static final java.lang.String HTTP_11;

  public static final byte[] HTTP_11_BYTES;

  public org.apache.coyote.http11.Constants();
    Code:
       0: aload_0
       1: invokespecial #1                  // Method java/lang/Object."<init>":()V
       4: return

  static {};
    Code:
       0: ldc           #2                  // String close
       2: invokestatic  #3                  // Method org/apache/tomcat/util/buf/ByteChunk.convertToBytes:(Ljava/lang/String;)[B
       5: putstatic     #4                  // Field CLOSE_BYTES:[B
       8: ldc           #5                  // String keep-alive
      10: invokestatic  #3                  // Method org/apache/tomcat/util/buf/ByteChunk.convertToBytes:(Ljava/lang/String;)[B
      13: putstatic     #6                  // Field KEEPALIVE_BYTES:[B
      16: ldc           #7                  // String HTTP/1.1 100 Continue\r\n\r\n
      18: invokestatic  #3                  // Method org/apache/tomcat/util/buf/ByteChunk.convertToBytes:(Ljava/lang/String;)[B
      21: putstatic     #8                  // Field ACK_BYTES_REASON:[B
      24: ldc           #9                  // String HTTP/1.1 100 \r\n\r\n
      26: invokestatic  #3                  // Method org/apache/tomcat/util/buf/ByteChunk.convertToBytes:(Ljava/lang/String;)[B
      29: putstatic     #10                 // Field ACK_BYTES:[B
      32: ldc           #11                 // String 200
      34: invokestatic  #3                  // Method org/apache/tomcat/util/buf/ByteChunk.convertToBytes:(Ljava/lang/String;)[B
      37: putstatic     #12                 // Field _200_BYTES:[B
      40: ldc           #13                 // String 400
      42: invokestatic  #3                  // Method org/apache/tomcat/util/buf/ByteChunk.convertToBytes:(Ljava/lang/String;)[B
      45: putstatic     #14                 // Field _400_BYTES:[B
      48: ldc           #15                 // String 404
      50: invokestatic  #3                  // Method org/apache/tomcat/util/buf/ByteChunk.convertToBytes:(Ljava/lang/String;)[B
      53: putstatic     #16                 // Field _404_BYTES:[B
      56: ldc           #17                 // String HTTP/1.1
      58: invokestatic  #3                  // Method org/apache/tomcat/util/buf/ByteChunk.convertToBytes:(Ljava/lang/String;)[B
      61: putstatic     #18                 // Field HTTP_11_BYTES:[B
      64: return
}
