Compiled from "Index.java"
class com.amazonaws.services.dynamodbv2.document.Index$1 {
  static final int[] $SwitchMap$com$amazonaws$services$dynamodbv2$model$IndexStatus;

  static {};
    Code:
       0: invokestatic  #1                  // Method com/amazonaws/services/dynamodbv2/model/IndexStatus.values:()[Lcom/amazonaws/services/dynamodbv2/model/IndexStatus;
       3: arraylength
       4: newarray       int
       6: putstatic     #2                  // Field $SwitchMap$com$amazonaws$services$dynamodbv2$model$IndexStatus:[I
       9: getstatic     #2                  // Field $SwitchMap$com$amazonaws$services$dynamodbv2$model$IndexStatus:[I
      12: getstatic     #3                  // Field com/amazonaws/services/dynamodbv2/model/IndexStatus.ACTIVE:Lcom/amazonaws/services/dynamodbv2/model/IndexStatus;
      15: invokevirtual #4                  // Method com/amazonaws/services/dynamodbv2/model/IndexStatus.ordinal:()I
      18: iconst_1
      19: iastore
      20: goto          24
      23: astore_0
      24: getstatic     #2                  // Field $SwitchMap$com$amazonaws$services$dynamodbv2$model$IndexStatus:[I
      27: getstatic     #6                  // Field com/amazonaws/services/dynamodbv2/model/IndexStatus.CREATING:Lcom/amazonaws/services/dynamodbv2/model/IndexStatus;
      30: invokevirtual #4                  // Method com/amazonaws/services/dynamodbv2/model/IndexStatus.ordinal:()I
      33: iconst_2
      34: iastore
      35: goto          39
      38: astore_0
      39: getstatic     #2                  // Field $SwitchMap$com$amazonaws$services$dynamodbv2$model$IndexStatus:[I
      42: getstatic     #7                  // Field com/amazonaws/services/dynamodbv2/model/IndexStatus.UPDATING:Lcom/amazonaws/services/dynamodbv2/model/IndexStatus;
      45: invokevirtual #4                  // Method com/amazonaws/services/dynamodbv2/model/IndexStatus.ordinal:()I
      48: iconst_3
      49: iastore
      50: goto          54
      53: astore_0
      54: return
    Exception table:
       from    to  target type
           9    20    23   Class java/lang/NoSuchFieldError
          24    35    38   Class java/lang/NoSuchFieldError
          39    50    53   Class java/lang/NoSuchFieldError
}
