Compiled from "Index.java"
public class com.amazonaws.services.dynamodbv2.document.Index implements com.amazonaws.services.dynamodbv2.document.api.QueryApi,com.amazonaws.services.dynamodbv2.document.api.ScanApi {
  private static final long SLEEP_TIME_MILLIS;

  private final com.amazonaws.services.dynamodbv2.document.Table table;

  private final java.lang.String indexName;

  private final com.amazonaws.services.dynamodbv2.document.api.QueryApi queryDelegate;

  private final com.amazonaws.services.dynamodbv2.document.internal.ScanImpl scanDelegate;

  com.amazonaws.services.dynamodbv2.document.Index(com.amazonaws.services.dynamodbv2.AmazonDynamoDB, java.lang.String, com.amazonaws.services.dynamodbv2.document.Table);
    Code:
       0: aload_0
       1: invokespecial #1                  // Method java/lang/Object."<init>":()V
       4: aload_1
       5: ifnonnull     18
       8: new           #2                  // class java/lang/IllegalArgumentException
      11: dup
      12: ldc           #3                  // String client must be specified
      14: invokespecial #4                  // Method java/lang/IllegalArgumentException."<init>":(Ljava/lang/String;)V
      17: athrow
      18: aload_2
      19: ifnull        32
      22: aload_2
      23: invokevirtual #5                  // Method java/lang/String.trim:()Ljava/lang/String;
      26: invokevirtual #6                  // Method java/lang/String.length:()I
      29: ifne          42
      32: new           #2                  // class java/lang/IllegalArgumentException
      35: dup
      36: ldc           #7                  // String index name must not be null or empty
      38: invokespecial #4                  // Method java/lang/IllegalArgumentException."<init>":(Ljava/lang/String;)V
      41: athrow
      42: aload_3
      43: ifnonnull     56
      46: new           #2                  // class java/lang/IllegalArgumentException
      49: dup
      50: ldc           #8                  // String table must be specified
      52: invokespecial #4                  // Method java/lang/IllegalArgumentException."<init>":(Ljava/lang/String;)V
      55: athrow
      56: aload_0
      57: aload_3
      58: putfield      #9                  // Field table:Lcom/amazonaws/services/dynamodbv2/document/Table;
      61: aload_0
      62: aload_2
      63: putfield      #10                 // Field indexName:Ljava/lang/String;
      66: aload_0
      67: new           #11                 // class com/amazonaws/services/dynamodbv2/document/internal/IndexQueryImpl
      70: dup
      71: aload_1
      72: aload_0
      73: invokespecial #12                 // Method com/amazonaws/services/dynamodbv2/document/internal/IndexQueryImpl."<init>":(Lcom/amazonaws/services/dynamodbv2/AmazonDynamoDB;Lcom/amazonaws/services/dynamodbv2/document/Index;)V
      76: putfield      #13                 // Field queryDelegate:Lcom/amazonaws/services/dynamodbv2/document/api/QueryApi;
      79: aload_0
      80: new           #14                 // class com/amazonaws/services/dynamodbv2/document/internal/IndexScanImpl
      83: dup
      84: aload_1
      85: aload_0
      86: invokespecial #15                 // Method com/amazonaws/services/dynamodbv2/document/internal/IndexScanImpl."<init>":(Lcom/amazonaws/services/dynamodbv2/AmazonDynamoDB;Lcom/amazonaws/services/dynamodbv2/document/Index;)V
      89: putfield      #16                 // Field scanDelegate:Lcom/amazonaws/services/dynamodbv2/document/internal/ScanImpl;
      92: return

  public final com.amazonaws.services.dynamodbv2.document.Table getTable();
    Code:
       0: aload_0
       1: getfield      #9                  // Field table:Lcom/amazonaws/services/dynamodbv2/document/Table;
       4: areturn

  public final java.lang.String getIndexName();
    Code:
       0: aload_0
       1: getfield      #10                 // Field indexName:Ljava/lang/String;
       4: areturn

  public com.amazonaws.services.dynamodbv2.document.ItemCollection<com.amazonaws.services.dynamodbv2.document.QueryOutcome> query(com.amazonaws.services.dynamodbv2.document.KeyAttribute, com.amazonaws.services.dynamodbv2.document.RangeKeyCondition);
    Code:
       0: aload_0
       1: getfield      #13                 // Field queryDelegate:Lcom/amazonaws/services/dynamodbv2/document/api/QueryApi;
       4: aload_1
       5: aload_2
       6: invokeinterface #17,  3           // InterfaceMethod com/amazonaws/services/dynamodbv2/document/api/QueryApi.query:(Lcom/amazonaws/services/dynamodbv2/document/KeyAttribute;Lcom/amazonaws/services/dynamodbv2/document/RangeKeyCondition;)Lcom/amazonaws/services/dynamodbv2/document/ItemCollection;
      11: areturn

  public com.amazonaws.services.dynamodbv2.document.ItemCollection<com.amazonaws.services.dynamodbv2.document.QueryOutcome> query(com.amazonaws.services.dynamodbv2.document.KeyAttribute, com.amazonaws.services.dynamodbv2.document.RangeKeyCondition, com.amazonaws.services.dynamodbv2.document.QueryFilter...);
    Code:
       0: aload_0
       1: getfield      #13                 // Field queryDelegate:Lcom/amazonaws/services/dynamodbv2/document/api/QueryApi;
       4: aload_1
       5: aload_2
       6: aload_3
       7: invokeinterface #18,  4           // InterfaceMethod com/amazonaws/services/dynamodbv2/document/api/QueryApi.query:(Lcom/amazonaws/services/dynamodbv2/document/KeyAttribute;Lcom/amazonaws/services/dynamodbv2/document/RangeKeyCondition;[Lcom/amazonaws/services/dynamodbv2/document/QueryFilter;)Lcom/amazonaws/services/dynamodbv2/document/ItemCollection;
      12: areturn

  public com.amazonaws.services.dynamodbv2.document.ItemCollection<com.amazonaws.services.dynamodbv2.document.QueryOutcome> query(com.amazonaws.services.dynamodbv2.document.KeyAttribute, com.amazonaws.services.dynamodbv2.document.RangeKeyCondition, java.lang.String, java.util.Map<java.lang.String, java.lang.String>, java.util.Map<java.lang.String, java.lang.Object>);
    Code:
       0: aload_0
       1: getfield      #13                 // Field queryDelegate:Lcom/amazonaws/services/dynamodbv2/document/api/QueryApi;
       4: aload_1
       5: aload_2
       6: aload_3
       7: aload         4
       9: aload         5
      11: invokeinterface #19,  6           // InterfaceMethod com/amazonaws/services/dynamodbv2/document/api/QueryApi.query:(Lcom/amazonaws/services/dynamodbv2/document/KeyAttribute;Lcom/amazonaws/services/dynamodbv2/document/RangeKeyCondition;Ljava/lang/String;Ljava/util/Map;Ljava/util/Map;)Lcom/amazonaws/services/dynamodbv2/document/ItemCollection;
      16: areturn

  public com.amazonaws.services.dynamodbv2.document.ItemCollection<com.amazonaws.services.dynamodbv2.document.QueryOutcome> query(com.amazonaws.services.dynamodbv2.document.KeyAttribute, com.amazonaws.services.dynamodbv2.document.RangeKeyCondition, java.lang.String, java.lang.String, java.util.Map<java.lang.String, java.lang.String>, java.util.Map<java.lang.String, java.lang.Object>);
    Code:
       0: aload_0
       1: getfield      #13                 // Field queryDelegate:Lcom/amazonaws/services/dynamodbv2/document/api/QueryApi;
       4: aload_1
       5: aload_2
       6: aload_3
       7: aload         4
       9: aload         5
      11: aload         6
      13: invokeinterface #20,  7           // InterfaceMethod com/amazonaws/services/dynamodbv2/document/api/QueryApi.query:(Lcom/amazonaws/services/dynamodbv2/document/KeyAttribute;Lcom/amazonaws/services/dynamodbv2/document/RangeKeyCondition;Ljava/lang/String;Ljava/lang/String;Ljava/util/Map;Ljava/util/Map;)Lcom/amazonaws/services/dynamodbv2/document/ItemCollection;
      18: areturn

  public com.amazonaws.services.dynamodbv2.document.ItemCollection<com.amazonaws.services.dynamodbv2.document.QueryOutcome> query(com.amazonaws.services.dynamodbv2.document.KeyAttribute, com.amazonaws.services.dynamodbv2.document.RangeKeyCondition, com.amazonaws.services.dynamodbv2.xspec.QueryExpressionSpec);
    Code:
       0: aload_0
       1: getfield      #13                 // Field queryDelegate:Lcom/amazonaws/services/dynamodbv2/document/api/QueryApi;
       4: aload_1
       5: aload_2
       6: aload_3
       7: invokevirtual #21                 // Method com/amazonaws/services/dynamodbv2/xspec/QueryExpressionSpec.getProjectionExpression:()Ljava/lang/String;
      10: aload_3
      11: invokevirtual #22                 // Method com/amazonaws/services/dynamodbv2/xspec/QueryExpressionSpec.getFilterExpression:()Ljava/lang/String;
      14: aload_3
      15: invokevirtual #23                 // Method com/amazonaws/services/dynamodbv2/xspec/QueryExpressionSpec.getNameMap:()Ljava/util/Map;
      18: aload_3
      19: invokevirtual #24                 // Method com/amazonaws/services/dynamodbv2/xspec/QueryExpressionSpec.getValueMap:()Ljava/util/Map;
      22: invokeinterface #20,  7           // InterfaceMethod com/amazonaws/services/dynamodbv2/document/api/QueryApi.query:(Lcom/amazonaws/services/dynamodbv2/document/KeyAttribute;Lcom/amazonaws/services/dynamodbv2/document/RangeKeyCondition;Ljava/lang/String;Ljava/lang/String;Ljava/util/Map;Ljava/util/Map;)Lcom/amazonaws/services/dynamodbv2/document/ItemCollection;
      27: areturn

  public com.amazonaws.services.dynamodbv2.document.ItemCollection<com.amazonaws.services.dynamodbv2.document.QueryOutcome> query(com.amazonaws.services.dynamodbv2.document.spec.QuerySpec);
    Code:
       0: aload_0
       1: getfield      #13                 // Field queryDelegate:Lcom/amazonaws/services/dynamodbv2/document/api/QueryApi;
       4: aload_1
       5: invokeinterface #25,  2           // InterfaceMethod com/amazonaws/services/dynamodbv2/document/api/QueryApi.query:(Lcom/amazonaws/services/dynamodbv2/document/spec/QuerySpec;)Lcom/amazonaws/services/dynamodbv2/document/ItemCollection;
      10: areturn

  public com.amazonaws.services.dynamodbv2.document.ItemCollection<com.amazonaws.services.dynamodbv2.document.QueryOutcome> query(java.lang.String, java.lang.Object);
    Code:
       0: aload_0
       1: getfield      #13                 // Field queryDelegate:Lcom/amazonaws/services/dynamodbv2/document/api/QueryApi;
       4: aload_1
       5: aload_2
       6: invokeinterface #26,  3           // InterfaceMethod com/amazonaws/services/dynamodbv2/document/api/QueryApi.query:(Ljava/lang/String;Ljava/lang/Object;)Lcom/amazonaws/services/dynamodbv2/document/ItemCollection;
      11: areturn

  public com.amazonaws.services.dynamodbv2.document.ItemCollection<com.amazonaws.services.dynamodbv2.document.QueryOutcome> query(java.lang.String, java.lang.Object, com.amazonaws.services.dynamodbv2.document.RangeKeyCondition);
    Code:
       0: aload_0
       1: getfield      #13                 // Field queryDelegate:Lcom/amazonaws/services/dynamodbv2/document/api/QueryApi;
       4: aload_1
       5: aload_2
       6: aload_3
       7: invokeinterface #27,  4           // InterfaceMethod com/amazonaws/services/dynamodbv2/document/api/QueryApi.query:(Ljava/lang/String;Ljava/lang/Object;Lcom/amazonaws/services/dynamodbv2/document/RangeKeyCondition;)Lcom/amazonaws/services/dynamodbv2/document/ItemCollection;
      12: areturn

  public com.amazonaws.services.dynamodbv2.document.ItemCollection<com.amazonaws.services.dynamodbv2.document.QueryOutcome> query(java.lang.String, java.lang.Object, com.amazonaws.services.dynamodbv2.document.RangeKeyCondition, com.amazonaws.services.dynamodbv2.document.QueryFilter...);
    Code:
       0: aload_0
       1: getfield      #13                 // Field queryDelegate:Lcom/amazonaws/services/dynamodbv2/document/api/QueryApi;
       4: aload_1
       5: aload_2
       6: aload_3
       7: aload         4
       9: invokeinterface #28,  5           // InterfaceMethod com/amazonaws/services/dynamodbv2/document/api/QueryApi.query:(Ljava/lang/String;Ljava/lang/Object;Lcom/amazonaws/services/dynamodbv2/document/RangeKeyCondition;[Lcom/amazonaws/services/dynamodbv2/document/QueryFilter;)Lcom/amazonaws/services/dynamodbv2/document/ItemCollection;
      14: areturn

  public com.amazonaws.services.dynamodbv2.document.ItemCollection<com.amazonaws.services.dynamodbv2.document.QueryOutcome> query(java.lang.String, java.lang.Object, com.amazonaws.services.dynamodbv2.document.RangeKeyCondition, java.lang.String, java.util.Map<java.lang.String, java.lang.String>, java.util.Map<java.lang.String, java.lang.Object>);
    Code:
       0: aload_0
       1: getfield      #13                 // Field queryDelegate:Lcom/amazonaws/services/dynamodbv2/document/api/QueryApi;
       4: aload_1
       5: aload_2
       6: aload_3
       7: aload         4
       9: aload         5
      11: aload         6
      13: invokeinterface #29,  7           // InterfaceMethod com/amazonaws/services/dynamodbv2/document/api/QueryApi.query:(Ljava/lang/String;Ljava/lang/Object;Lcom/amazonaws/services/dynamodbv2/document/RangeKeyCondition;Ljava/lang/String;Ljava/util/Map;Ljava/util/Map;)Lcom/amazonaws/services/dynamodbv2/document/ItemCollection;
      18: areturn

  public com.amazonaws.services.dynamodbv2.document.ItemCollection<com.amazonaws.services.dynamodbv2.document.QueryOutcome> query(java.lang.String, java.lang.Object, com.amazonaws.services.dynamodbv2.document.RangeKeyCondition, java.lang.String, java.lang.String, java.util.Map<java.lang.String, java.lang.String>, java.util.Map<java.lang.String, java.lang.Object>);
    Code:
       0: aload_0
       1: getfield      #13                 // Field queryDelegate:Lcom/amazonaws/services/dynamodbv2/document/api/QueryApi;
       4: aload_1
       5: aload_2
       6: aload_3
       7: aload         4
       9: aload         5
      11: aload         6
      13: aload         7
      15: invokeinterface #30,  8           // InterfaceMethod com/amazonaws/services/dynamodbv2/document/api/QueryApi.query:(Ljava/lang/String;Ljava/lang/Object;Lcom/amazonaws/services/dynamodbv2/document/RangeKeyCondition;Ljava/lang/String;Ljava/lang/String;Ljava/util/Map;Ljava/util/Map;)Lcom/amazonaws/services/dynamodbv2/document/ItemCollection;
      20: areturn

  public com.amazonaws.services.dynamodbv2.document.ItemCollection<com.amazonaws.services.dynamodbv2.document.QueryOutcome> query(com.amazonaws.services.dynamodbv2.document.KeyAttribute);
    Code:
       0: aload_0
       1: getfield      #13                 // Field queryDelegate:Lcom/amazonaws/services/dynamodbv2/document/api/QueryApi;
       4: aload_1
       5: invokeinterface #31,  2           // InterfaceMethod com/amazonaws/services/dynamodbv2/document/api/QueryApi.query:(Lcom/amazonaws/services/dynamodbv2/document/KeyAttribute;)Lcom/amazonaws/services/dynamodbv2/document/ItemCollection;
      10: areturn

  public com.amazonaws.services.dynamodbv2.model.TableDescription updateGSI(com.amazonaws.services.dynamodbv2.model.ProvisionedThroughput);
    Code:
       0: aload_0
       1: getfield      #9                  // Field table:Lcom/amazonaws/services/dynamodbv2/document/Table;
       4: new           #32                 // class com/amazonaws/services/dynamodbv2/document/spec/UpdateTableSpec
       7: dup
       8: invokespecial #33                 // Method com/amazonaws/services/dynamodbv2/document/spec/UpdateTableSpec."<init>":()V
      11: iconst_1
      12: anewarray     #34                 // class com/amazonaws/services/dynamodbv2/model/GlobalSecondaryIndexUpdate
      15: dup
      16: iconst_0
      17: new           #34                 // class com/amazonaws/services/dynamodbv2/model/GlobalSecondaryIndexUpdate
      20: dup
      21: invokespecial #35                 // Method com/amazonaws/services/dynamodbv2/model/GlobalSecondaryIndexUpdate."<init>":()V
      24: new           #36                 // class com/amazonaws/services/dynamodbv2/model/UpdateGlobalSecondaryIndexAction
      27: dup
      28: invokespecial #37                 // Method com/amazonaws/services/dynamodbv2/model/UpdateGlobalSecondaryIndexAction."<init>":()V
      31: aload_0
      32: getfield      #10                 // Field indexName:Ljava/lang/String;
      35: invokevirtual #38                 // Method com/amazonaws/services/dynamodbv2/model/UpdateGlobalSecondaryIndexAction.withIndexName:(Ljava/lang/String;)Lcom/amazonaws/services/dynamodbv2/model/UpdateGlobalSecondaryIndexAction;
      38: aload_1
      39: invokevirtual #39                 // Method com/amazonaws/services/dynamodbv2/model/UpdateGlobalSecondaryIndexAction.withProvisionedThroughput:(Lcom/amazonaws/services/dynamodbv2/model/ProvisionedThroughput;)Lcom/amazonaws/services/dynamodbv2/model/UpdateGlobalSecondaryIndexAction;
      42: invokevirtual #40                 // Method com/amazonaws/services/dynamodbv2/model/GlobalSecondaryIndexUpdate.withUpdate:(Lcom/amazonaws/services/dynamodbv2/model/UpdateGlobalSecondaryIndexAction;)Lcom/amazonaws/services/dynamodbv2/model/GlobalSecondaryIndexUpdate;
      45: aastore
      46: invokevirtual #41                 // Method com/amazonaws/services/dynamodbv2/document/spec/UpdateTableSpec.withGlobalSecondaryIndexUpdates:([Lcom/amazonaws/services/dynamodbv2/model/GlobalSecondaryIndexUpdate;)Lcom/amazonaws/services/dynamodbv2/document/spec/UpdateTableSpec;
      49: invokevirtual #42                 // Method com/amazonaws/services/dynamodbv2/document/Table.updateTable:(Lcom/amazonaws/services/dynamodbv2/document/spec/UpdateTableSpec;)Lcom/amazonaws/services/dynamodbv2/model/TableDescription;
      52: areturn

  public com.amazonaws.services.dynamodbv2.model.TableDescription deleteGSI();
    Code:
       0: aload_0
       1: getfield      #9                  // Field table:Lcom/amazonaws/services/dynamodbv2/document/Table;
       4: new           #32                 // class com/amazonaws/services/dynamodbv2/document/spec/UpdateTableSpec
       7: dup
       8: invokespecial #33                 // Method com/amazonaws/services/dynamodbv2/document/spec/UpdateTableSpec."<init>":()V
      11: iconst_1
      12: anewarray     #34                 // class com/amazonaws/services/dynamodbv2/model/GlobalSecondaryIndexUpdate
      15: dup
      16: iconst_0
      17: new           #34                 // class com/amazonaws/services/dynamodbv2/model/GlobalSecondaryIndexUpdate
      20: dup
      21: invokespecial #35                 // Method com/amazonaws/services/dynamodbv2/model/GlobalSecondaryIndexUpdate."<init>":()V
      24: new           #43                 // class com/amazonaws/services/dynamodbv2/model/DeleteGlobalSecondaryIndexAction
      27: dup
      28: invokespecial #44                 // Method com/amazonaws/services/dynamodbv2/model/DeleteGlobalSecondaryIndexAction."<init>":()V
      31: aload_0
      32: getfield      #10                 // Field indexName:Ljava/lang/String;
      35: invokevirtual #45                 // Method com/amazonaws/services/dynamodbv2/model/DeleteGlobalSecondaryIndexAction.withIndexName:(Ljava/lang/String;)Lcom/amazonaws/services/dynamodbv2/model/DeleteGlobalSecondaryIndexAction;
      38: invokevirtual #46                 // Method com/amazonaws/services/dynamodbv2/model/GlobalSecondaryIndexUpdate.withDelete:(Lcom/amazonaws/services/dynamodbv2/model/DeleteGlobalSecondaryIndexAction;)Lcom/amazonaws/services/dynamodbv2/model/GlobalSecondaryIndexUpdate;
      41: aastore
      42: invokevirtual #41                 // Method com/amazonaws/services/dynamodbv2/document/spec/UpdateTableSpec.withGlobalSecondaryIndexUpdates:([Lcom/amazonaws/services/dynamodbv2/model/GlobalSecondaryIndexUpdate;)Lcom/amazonaws/services/dynamodbv2/document/spec/UpdateTableSpec;
      45: invokevirtual #42                 // Method com/amazonaws/services/dynamodbv2/document/Table.updateTable:(Lcom/amazonaws/services/dynamodbv2/document/spec/UpdateTableSpec;)Lcom/amazonaws/services/dynamodbv2/model/TableDescription;
      48: areturn

  public com.amazonaws.services.dynamodbv2.model.TableDescription waitForActive() throws java.lang.InterruptedException;
    Code:
       0: aload_0
       1: invokevirtual #47                 // Method getTable:()Lcom/amazonaws/services/dynamodbv2/document/Table;
       4: astore_1
       5: aload_1
       6: invokevirtual #48                 // Method com/amazonaws/services/dynamodbv2/document/Table.getTableName:()Ljava/lang/String;
       9: astore_2
      10: aload_0
      11: invokevirtual #49                 // Method getIndexName:()Ljava/lang/String;
      14: astore_3
      15: aload_1
      16: invokevirtual #50                 // Method com/amazonaws/services/dynamodbv2/document/Table.waitForActive:()Lcom/amazonaws/services/dynamodbv2/model/TableDescription;
      19: astore        4
      21: aload         4
      23: invokevirtual #51                 // Method com/amazonaws/services/dynamodbv2/model/TableDescription.getGlobalSecondaryIndexes:()Ljava/util/List;
      26: astore        5
      28: aload         5
      30: ifnull        177
      33: aload         5
      35: invokeinterface #52,  1           // InterfaceMethod java/util/List.iterator:()Ljava/util/Iterator;
      40: astore        6
      42: aload         6
      44: invokeinterface #53,  1           // InterfaceMethod java/util/Iterator.hasNext:()Z
      49: ifeq          177
      52: aload         6
      54: invokeinterface #54,  1           // InterfaceMethod java/util/Iterator.next:()Ljava/lang/Object;
      59: checkcast     #55                 // class com/amazonaws/services/dynamodbv2/model/GlobalSecondaryIndexDescription
      62: astore        7
      64: aload         7
      66: invokevirtual #56                 // Method com/amazonaws/services/dynamodbv2/model/GlobalSecondaryIndexDescription.getIndexName:()Ljava/lang/String;
      69: aload_3
      70: invokevirtual #57                 // Method java/lang/String.equals:(Ljava/lang/Object;)Z
      73: ifeq          174
      76: aload         7
      78: invokevirtual #58                 // Method com/amazonaws/services/dynamodbv2/model/GlobalSecondaryIndexDescription.getIndexStatus:()Ljava/lang/String;
      81: astore        8
      83: getstatic     #59                 // Field com/amazonaws/services/dynamodbv2/document/Index$1.$SwitchMap$com$amazonaws$services$dynamodbv2$model$IndexStatus:[I
      86: aload         8
      88: invokestatic  #60                 // Method com/amazonaws/services/dynamodbv2/model/IndexStatus.fromValue:(Ljava/lang/String;)Lcom/amazonaws/services/dynamodbv2/model/IndexStatus;
      91: invokevirtual #61                 // Method com/amazonaws/services/dynamodbv2/model/IndexStatus.ordinal:()I
      94: iaload
      95: tableswitch   { // 1 to 3
                     1: 120
                     2: 123
                     3: 123
               default: 132
          }
     120: aload         4
     122: areturn
     123: ldc2_w        #63                 // long 5000l
     126: invokestatic  #65                 // Method java/lang/Thread.sleep:(J)V
     129: goto          15
     132: new           #2                  // class java/lang/IllegalArgumentException
     135: dup
     136: new           #66                 // class java/lang/StringBuilder
     139: dup
     140: invokespecial #67                 // Method java/lang/StringBuilder."<init>":()V
     143: ldc           #68                 // String Global Secondary Index
     145: invokevirtual #69                 // Method java/lang/StringBuilder.append:(Ljava/lang/String;)Ljava/lang/StringBuilder;
     148: aload_3
     149: invokevirtual #69                 // Method java/lang/StringBuilder.append:(Ljava/lang/String;)Ljava/lang/StringBuilder;
     152: ldc           #70                 // String  is not being created or updated (with status=
     154: invokevirtual #69                 // Method java/lang/StringBuilder.append:(Ljava/lang/String;)Ljava/lang/StringBuilder;
     157: aload         8
     159: invokevirtual #69                 // Method java/lang/StringBuilder.append:(Ljava/lang/String;)Ljava/lang/StringBuilder;
     162: ldc           #71                 // String )
     164: invokevirtual #69                 // Method java/lang/StringBuilder.append:(Ljava/lang/String;)Ljava/lang/StringBuilder;
     167: invokevirtual #72                 // Method java/lang/StringBuilder.toString:()Ljava/lang/String;
     170: invokespecial #4                  // Method java/lang/IllegalArgumentException."<init>":(Ljava/lang/String;)V
     173: athrow
     174: goto          42
     177: new           #2                  // class java/lang/IllegalArgumentException
     180: dup
     181: new           #66                 // class java/lang/StringBuilder
     184: dup
     185: invokespecial #67                 // Method java/lang/StringBuilder."<init>":()V
     188: ldc           #68                 // String Global Secondary Index
     190: invokevirtual #69                 // Method java/lang/StringBuilder.append:(Ljava/lang/String;)Ljava/lang/StringBuilder;
     193: aload_3
     194: invokevirtual #69                 // Method java/lang/StringBuilder.append:(Ljava/lang/String;)Ljava/lang/StringBuilder;
     197: ldc           #73                 // String  does not exist in Table
     199: invokevirtual #69                 // Method java/lang/StringBuilder.append:(Ljava/lang/String;)Ljava/lang/StringBuilder;
     202: aload_2
     203: invokevirtual #69                 // Method java/lang/StringBuilder.append:(Ljava/lang/String;)Ljava/lang/StringBuilder;
     206: ldc           #71                 // String )
     208: invokevirtual #69                 // Method java/lang/StringBuilder.append:(Ljava/lang/String;)Ljava/lang/StringBuilder;
     211: invokevirtual #72                 // Method java/lang/StringBuilder.toString:()Ljava/lang/String;
     214: invokespecial #4                  // Method java/lang/IllegalArgumentException."<init>":(Ljava/lang/String;)V
     217: athrow

  public com.amazonaws.services.dynamodbv2.model.TableDescription waitForDelete() throws java.lang.InterruptedException;
    Code:
       0: aload_0
       1: invokevirtual #49                 // Method getIndexName:()Ljava/lang/String;
       4: astore_1
       5: aload_0
       6: invokevirtual #47                 // Method getTable:()Lcom/amazonaws/services/dynamodbv2/document/Table;
       9: invokevirtual #50                 // Method com/amazonaws/services/dynamodbv2/document/Table.waitForActive:()Lcom/amazonaws/services/dynamodbv2/model/TableDescription;
      12: astore_2
      13: aload_2
      14: invokevirtual #51                 // Method com/amazonaws/services/dynamodbv2/model/TableDescription.getGlobalSecondaryIndexes:()Ljava/util/List;
      17: astore_3
      18: aload_3
      19: ifnull        136
      22: aload_3
      23: invokeinterface #52,  1           // InterfaceMethod java/util/List.iterator:()Ljava/util/Iterator;
      28: astore        4
      30: aload         4
      32: invokeinterface #53,  1           // InterfaceMethod java/util/Iterator.hasNext:()Z
      37: ifeq          136
      40: aload         4
      42: invokeinterface #54,  1           // InterfaceMethod java/util/Iterator.next:()Ljava/lang/Object;
      47: checkcast     #55                 // class com/amazonaws/services/dynamodbv2/model/GlobalSecondaryIndexDescription
      50: astore        5
      52: aload         5
      54: invokevirtual #56                 // Method com/amazonaws/services/dynamodbv2/model/GlobalSecondaryIndexDescription.getIndexName:()Ljava/lang/String;
      57: aload_1
      58: invokevirtual #57                 // Method java/lang/String.equals:(Ljava/lang/Object;)Z
      61: ifeq          133
      64: aload         5
      66: invokevirtual #58                 // Method com/amazonaws/services/dynamodbv2/model/GlobalSecondaryIndexDescription.getIndexStatus:()Ljava/lang/String;
      69: astore        6
      71: aload         6
      73: invokestatic  #60                 // Method com/amazonaws/services/dynamodbv2/model/IndexStatus.fromValue:(Ljava/lang/String;)Lcom/amazonaws/services/dynamodbv2/model/IndexStatus;
      76: getstatic     #74                 // Field com/amazonaws/services/dynamodbv2/model/IndexStatus.DELETING:Lcom/amazonaws/services/dynamodbv2/model/IndexStatus;
      79: if_acmpne     91
      82: ldc2_w        #63                 // long 5000l
      85: invokestatic  #65                 // Method java/lang/Thread.sleep:(J)V
      88: goto          5
      91: new           #2                  // class java/lang/IllegalArgumentException
      94: dup
      95: new           #66                 // class java/lang/StringBuilder
      98: dup
      99: invokespecial #67                 // Method java/lang/StringBuilder."<init>":()V
     102: ldc           #68                 // String Global Secondary Index
     104: invokevirtual #69                 // Method java/lang/StringBuilder.append:(Ljava/lang/String;)Ljava/lang/StringBuilder;
     107: aload_1
     108: invokevirtual #69                 // Method java/lang/StringBuilder.append:(Ljava/lang/String;)Ljava/lang/StringBuilder;
     111: ldc           #75                 // String  is not being deleted (with status=
     113: invokevirtual #69                 // Method java/lang/StringBuilder.append:(Ljava/lang/String;)Ljava/lang/StringBuilder;
     116: aload         6
     118: invokevirtual #69                 // Method java/lang/StringBuilder.append:(Ljava/lang/String;)Ljava/lang/StringBuilder;
     121: ldc           #71                 // String )
     123: invokevirtual #69                 // Method java/lang/StringBuilder.append:(Ljava/lang/String;)Ljava/lang/StringBuilder;
     126: invokevirtual #72                 // Method java/lang/StringBuilder.toString:()Ljava/lang/String;
     129: invokespecial #4                  // Method java/lang/IllegalArgumentException."<init>":(Ljava/lang/String;)V
     132: athrow
     133: goto          30
     136: aload_2
     137: areturn

  public com.amazonaws.services.dynamodbv2.model.TableDescription waitForActiveOrDelete() throws java.lang.InterruptedException;
    Code:
       0: aload_0
       1: invokevirtual #47                 // Method getTable:()Lcom/amazonaws/services/dynamodbv2/document/Table;
       4: astore_1
       5: aload_0
       6: invokevirtual #49                 // Method getIndexName:()Ljava/lang/String;
       9: astore_2
      10: aload_1
      11: invokevirtual #50                 // Method com/amazonaws/services/dynamodbv2/document/Table.waitForActive:()Lcom/amazonaws/services/dynamodbv2/model/TableDescription;
      14: astore_3
      15: aload_3
      16: invokevirtual #51                 // Method com/amazonaws/services/dynamodbv2/model/TableDescription.getGlobalSecondaryIndexes:()Ljava/util/List;
      19: astore        4
      21: aload         4
      23: ifnull        103
      26: aload_3
      27: invokevirtual #51                 // Method com/amazonaws/services/dynamodbv2/model/TableDescription.getGlobalSecondaryIndexes:()Ljava/util/List;
      30: invokeinterface #52,  1           // InterfaceMethod java/util/List.iterator:()Ljava/util/Iterator;
      35: astore        5
      37: aload         5
      39: invokeinterface #53,  1           // InterfaceMethod java/util/Iterator.hasNext:()Z
      44: ifeq          103
      47: aload         5
      49: invokeinterface #54,  1           // InterfaceMethod java/util/Iterator.next:()Ljava/lang/Object;
      54: checkcast     #55                 // class com/amazonaws/services/dynamodbv2/model/GlobalSecondaryIndexDescription
      57: astore        6
      59: aload         6
      61: invokevirtual #56                 // Method com/amazonaws/services/dynamodbv2/model/GlobalSecondaryIndexDescription.getIndexName:()Ljava/lang/String;
      64: aload_2
      65: invokevirtual #57                 // Method java/lang/String.equals:(Ljava/lang/Object;)Z
      68: ifeq          100
      71: aload         6
      73: invokevirtual #58                 // Method com/amazonaws/services/dynamodbv2/model/GlobalSecondaryIndexDescription.getIndexStatus:()Ljava/lang/String;
      76: astore        7
      78: aload         7
      80: invokestatic  #60                 // Method com/amazonaws/services/dynamodbv2/model/IndexStatus.fromValue:(Ljava/lang/String;)Lcom/amazonaws/services/dynamodbv2/model/IndexStatus;
      83: getstatic     #76                 // Field com/amazonaws/services/dynamodbv2/model/IndexStatus.ACTIVE:Lcom/amazonaws/services/dynamodbv2/model/IndexStatus;
      86: if_acmpne     91
      89: aload_3
      90: areturn
      91: ldc2_w        #63                 // long 5000l
      94: invokestatic  #65                 // Method java/lang/Thread.sleep:(J)V
      97: goto          10
     100: goto          37
     103: aload_3
     104: areturn

  public com.amazonaws.services.dynamodbv2.document.ItemCollection<com.amazonaws.services.dynamodbv2.document.ScanOutcome> scan(com.amazonaws.services.dynamodbv2.document.ScanFilter...);
    Code:
       0: aload_0
       1: getfield      #16                 // Field scanDelegate:Lcom/amazonaws/services/dynamodbv2/document/internal/ScanImpl;
       4: aload_1
       5: invokevirtual #77                 // Method com/amazonaws/services/dynamodbv2/document/internal/ScanImpl.scan:([Lcom/amazonaws/services/dynamodbv2/document/ScanFilter;)Lcom/amazonaws/services/dynamodbv2/document/ItemCollection;
       8: areturn

  public com.amazonaws.services.dynamodbv2.document.ItemCollection<com.amazonaws.services.dynamodbv2.document.ScanOutcome> scan(java.lang.String, java.util.Map<java.lang.String, java.lang.String>, java.util.Map<java.lang.String, java.lang.Object>);
    Code:
       0: aload_0
       1: getfield      #16                 // Field scanDelegate:Lcom/amazonaws/services/dynamodbv2/document/internal/ScanImpl;
       4: aload_1
       5: aload_2
       6: aload_3
       7: invokevirtual #78                 // Method com/amazonaws/services/dynamodbv2/document/internal/ScanImpl.scan:(Ljava/lang/String;Ljava/util/Map;Ljava/util/Map;)Lcom/amazonaws/services/dynamodbv2/document/ItemCollection;
      10: areturn

  public com.amazonaws.services.dynamodbv2.document.ItemCollection<com.amazonaws.services.dynamodbv2.document.ScanOutcome> scan(java.lang.String, java.lang.String, java.util.Map<java.lang.String, java.lang.String>, java.util.Map<java.lang.String, java.lang.Object>);
    Code:
       0: aload_0
       1: getfield      #16                 // Field scanDelegate:Lcom/amazonaws/services/dynamodbv2/document/internal/ScanImpl;
       4: aload_1
       5: aload_2
       6: aload_3
       7: aload         4
       9: invokevirtual #79                 // Method com/amazonaws/services/dynamodbv2/document/internal/ScanImpl.scan:(Ljava/lang/String;Ljava/lang/String;Ljava/util/Map;Ljava/util/Map;)Lcom/amazonaws/services/dynamodbv2/document/ItemCollection;
      12: areturn

  public com.amazonaws.services.dynamodbv2.document.ItemCollection<com.amazonaws.services.dynamodbv2.document.ScanOutcome> scan(com.amazonaws.services.dynamodbv2.xspec.ScanExpressionSpec);
    Code:
       0: aload_0
       1: getfield      #16                 // Field scanDelegate:Lcom/amazonaws/services/dynamodbv2/document/internal/ScanImpl;
       4: aload_1
       5: invokevirtual #80                 // Method com/amazonaws/services/dynamodbv2/xspec/ScanExpressionSpec.getFilterExpression:()Ljava/lang/String;
       8: aload_1
       9: invokevirtual #81                 // Method com/amazonaws/services/dynamodbv2/xspec/ScanExpressionSpec.getProjectionExpression:()Ljava/lang/String;
      12: aload_1
      13: invokevirtual #82                 // Method com/amazonaws/services/dynamodbv2/xspec/ScanExpressionSpec.getNameMap:()Ljava/util/Map;
      16: aload_1
      17: invokevirtual #83                 // Method com/amazonaws/services/dynamodbv2/xspec/ScanExpressionSpec.getValueMap:()Ljava/util/Map;
      20: invokevirtual #79                 // Method com/amazonaws/services/dynamodbv2/document/internal/ScanImpl.scan:(Ljava/lang/String;Ljava/lang/String;Ljava/util/Map;Ljava/util/Map;)Lcom/amazonaws/services/dynamodbv2/document/ItemCollection;
      23: areturn

  public com.amazonaws.services.dynamodbv2.document.ItemCollection<com.amazonaws.services.dynamodbv2.document.ScanOutcome> scan(com.amazonaws.services.dynamodbv2.document.spec.ScanSpec);
    Code:
       0: aload_0
       1: getfield      #16                 // Field scanDelegate:Lcom/amazonaws/services/dynamodbv2/document/internal/ScanImpl;
       4: aload_1
       5: invokevirtual #84                 // Method com/amazonaws/services/dynamodbv2/document/internal/ScanImpl.scan:(Lcom/amazonaws/services/dynamodbv2/document/spec/ScanSpec;)Lcom/amazonaws/services/dynamodbv2/document/ItemCollection;
       8: areturn
}
