Compiled from "DeploymentStrategyFluentImpl.java"
public class io.fabric8.kubernetes.api.model.apps.DeploymentStrategyFluentImpl$RollingUpdateNestedImpl<N> extends io.fabric8.kubernetes.api.model.apps.RollingUpdateDeploymentFluentImpl<io.fabric8.kubernetes.api.model.apps.DeploymentStrategyFluent$RollingUpdateNested<N>> implements io.fabric8.kubernetes.api.model.apps.DeploymentStrategyFluent$RollingUpdateNested<N>, io.fabric8.kubernetes.api.builder.Nested<N> {
  private final io.fabric8.kubernetes.api.model.apps.RollingUpdateDeploymentBuilder builder;

  final io.fabric8.kubernetes.api.model.apps.DeploymentStrategyFluentImpl this$0;

  io.fabric8.kubernetes.api.model.apps.DeploymentStrategyFluentImpl$RollingUpdateNestedImpl(io.fabric8.kubernetes.api.model.apps.DeploymentStrategyFluentImpl, io.fabric8.kubernetes.api.model.apps.RollingUpdateDeployment);
    Code:
       0: aload_0
       1: aload_1
       2: putfield      #1                  // Field this$0:Lio/fabric8/kubernetes/api/model/apps/DeploymentStrategyFluentImpl;
       5: aload_0
       6: invokespecial #2                  // Method io/fabric8/kubernetes/api/model/apps/RollingUpdateDeploymentFluentImpl."<init>":()V
       9: aload_0
      10: new           #3                  // class io/fabric8/kubernetes/api/model/apps/RollingUpdateDeploymentBuilder
      13: dup
      14: aload_0
      15: aload_2
      16: invokespecial #4                  // Method io/fabric8/kubernetes/api/model/apps/RollingUpdateDeploymentBuilder."<init>":(Lio/fabric8/kubernetes/api/model/apps/RollingUpdateDeploymentFluent;Lio/fabric8/kubernetes/api/model/apps/RollingUpdateDeployment;)V
      19: putfield      #5                  // Field builder:Lio/fabric8/kubernetes/api/model/apps/RollingUpdateDeploymentBuilder;
      22: return

  io.fabric8.kubernetes.api.model.apps.DeploymentStrategyFluentImpl$RollingUpdateNestedImpl(io.fabric8.kubernetes.api.model.apps.DeploymentStrategyFluentImpl);
    Code:
       0: aload_0
       1: aload_1
       2: putfield      #1                  // Field this$0:Lio/fabric8/kubernetes/api/model/apps/DeploymentStrategyFluentImpl;
       5: aload_0
       6: invokespecial #2                  // Method io/fabric8/kubernetes/api/model/apps/RollingUpdateDeploymentFluentImpl."<init>":()V
       9: aload_0
      10: new           #3                  // class io/fabric8/kubernetes/api/model/apps/RollingUpdateDeploymentBuilder
      13: dup
      14: aload_0
      15: invokespecial #6                  // Method io/fabric8/kubernetes/api/model/apps/RollingUpdateDeploymentBuilder."<init>":(Lio/fabric8/kubernetes/api/model/apps/RollingUpdateDeploymentFluent;)V
      18: putfield      #5                  // Field builder:Lio/fabric8/kubernetes/api/model/apps/RollingUpdateDeploymentBuilder;
      21: return

  public N and();
    Code:
       0: aload_0
       1: getfield      #1                  // Field this$0:Lio/fabric8/kubernetes/api/model/apps/DeploymentStrategyFluentImpl;
       4: aload_0
       5: getfield      #5                  // Field builder:Lio/fabric8/kubernetes/api/model/apps/RollingUpdateDeploymentBuilder;
       8: invokevirtual #7                  // Method io/fabric8/kubernetes/api/model/apps/RollingUpdateDeploymentBuilder.build:()Lio/fabric8/kubernetes/api/model/apps/RollingUpdateDeployment;
      11: invokevirtual #8                  // Method io/fabric8/kubernetes/api/model/apps/DeploymentStrategyFluentImpl.withRollingUpdate:(Lio/fabric8/kubernetes/api/model/apps/RollingUpdateDeployment;)Lio/fabric8/kubernetes/api/model/apps/DeploymentStrategyFluent;
      14: areturn

  public N endRollingUpdate();
    Code:
       0: aload_0
       1: invokevirtual #9                  // Method and:()Ljava/lang/Object;
       4: areturn
}
