Compiled from "Config.scala"
public class wvlet.airframe.config.ConfigPaths implements wvlet.log.LogSupport,scala.Product {
  private final scala.collection.Seq<java.lang.String> configPaths;

  private wvlet.log.Logger logger;

  private volatile boolean bitmap$0;

  public static scala.Option<scala.collection.Seq<java.lang.String>> unapply(wvlet.airframe.config.ConfigPaths);
    Code:
       0: getstatic     #34                 // Field wvlet/airframe/config/ConfigPaths$.MODULE$:Lwvlet/airframe/config/ConfigPaths$;
       3: aload_0
       4: invokevirtual #36                 // Method wvlet/airframe/config/ConfigPaths$.unapply:(Lwvlet/airframe/config/ConfigPaths;)Lscala/Option;
       7: areturn

  public static wvlet.airframe.config.ConfigPaths apply(scala.collection.Seq<java.lang.String>);
    Code:
       0: getstatic     #34                 // Field wvlet/airframe/config/ConfigPaths$.MODULE$:Lwvlet/airframe/config/ConfigPaths$;
       3: aload_0
       4: invokevirtual #41                 // Method wvlet/airframe/config/ConfigPaths$.apply:(Lscala/collection/Seq;)Lwvlet/airframe/config/ConfigPaths;
       7: areturn

  public static <A> scala.Function1<scala.collection.Seq<java.lang.String>, A> andThen(scala.Function1<wvlet.airframe.config.ConfigPaths, A>);
    Code:
       0: getstatic     #34                 // Field wvlet/airframe/config/ConfigPaths$.MODULE$:Lwvlet/airframe/config/ConfigPaths$;
       3: aload_0
       4: invokevirtual #47                 // Method wvlet/airframe/config/ConfigPaths$.andThen:(Lscala/Function1;)Lscala/Function1;
       7: areturn

  public static <A> scala.Function1<A, wvlet.airframe.config.ConfigPaths> compose(scala.Function1<A, scala.collection.Seq<java.lang.String>>);
    Code:
       0: getstatic     #34                 // Field wvlet/airframe/config/ConfigPaths$.MODULE$:Lwvlet/airframe/config/ConfigPaths$;
       3: aload_0
       4: invokevirtual #51                 // Method wvlet/airframe/config/ConfigPaths$.compose:(Lscala/Function1;)Lscala/Function1;
       7: areturn

  private wvlet.log.Logger logger$lzycompute();
    Code:
       0: aload_0
       1: dup
       2: astore_1
       3: monitorenter
       4: aload_0
       5: getfield      #55                 // Field bitmap$0:Z
       8: ifne          24
      11: aload_0
      12: aload_0
      13: invokestatic  #61                 // InterfaceMethod wvlet/log/LazyLogger.logger$:(Lwvlet/log/LazyLogger;)Lwvlet/log/Logger;
      16: putfield      #63                 // Field logger:Lwvlet/log/Logger;
      19: aload_0
      20: iconst_1
      21: putfield      #55                 // Field bitmap$0:Z
      24: aload_1
      25: monitorexit
      26: goto          32
      29: aload_1
      30: monitorexit
      31: athrow
      32: aload_0
      33: getfield      #63                 // Field logger:Lwvlet/log/Logger;
      36: areturn
    Exception table:
       from    to  target type
           4    24    29   any

  public wvlet.log.Logger logger();
    Code:
       0: aload_0
       1: getfield      #55                 // Field bitmap$0:Z
       4: ifne          12
       7: aload_0
       8: invokespecial #69                 // Method logger$lzycompute:()Lwvlet/log/Logger;
      11: areturn
      12: aload_0
      13: getfield      #63                 // Field logger:Lwvlet/log/Logger;
      16: areturn

  public scala.collection.Seq<java.lang.String> configPaths();
    Code:
       0: aload_0
       1: getfield      #73                 // Field configPaths:Lscala/collection/Seq;
       4: areturn

  public wvlet.airframe.config.ConfigPaths copy(scala.collection.Seq<java.lang.String>);
    Code:
       0: new           #2                  // class wvlet/airframe/config/ConfigPaths
       3: dup
       4: aload_1
       5: invokespecial #78                 // Method "<init>":(Lscala/collection/Seq;)V
       8: areturn

  public scala.collection.Seq<java.lang.String> copy$default$1();
    Code:
       0: aload_0
       1: invokevirtual #81                 // Method configPaths:()Lscala/collection/Seq;
       4: areturn

  public java.lang.String productPrefix();
    Code:
       0: ldc           #85                 // String ConfigPaths
       2: areturn

  public int productArity();
    Code:
       0: iconst_1
       1: ireturn

  public java.lang.Object productElement(int);
    Code:
       0: iload_1
       1: istore_2
       2: iload_2
       3: tableswitch   { // 0 to 0
                     0: 20
               default: 25
          }
      20: aload_0
      21: invokevirtual #81                 // Method configPaths:()Lscala/collection/Seq;
      24: areturn
      25: new           #92                 // class java/lang/IndexOutOfBoundsException
      28: dup
      29: iload_1
      30: invokestatic  #98                 // Method java/lang/Integer.toString:(I)Ljava/lang/String;
      33: invokespecial #101                // Method java/lang/IndexOutOfBoundsException."<init>":(Ljava/lang/String;)V
      36: athrow

  public scala.collection.Iterator<java.lang.Object> productIterator();
    Code:
       0: getstatic     #110                // Field scala/runtime/ScalaRunTime$.MODULE$:Lscala/runtime/ScalaRunTime$;
       3: aload_0
       4: invokevirtual #114                // Method scala/runtime/ScalaRunTime$.typedProductIterator:(Lscala/Product;)Lscala/collection/Iterator;
       7: areturn

  public boolean canEqual(java.lang.Object);
    Code:
       0: aload_1
       1: instanceof    #2                  // class wvlet/airframe/config/ConfigPaths
       4: ireturn

  public int hashCode();
    Code:
       0: getstatic     #110                // Field scala/runtime/ScalaRunTime$.MODULE$:Lscala/runtime/ScalaRunTime$;
       3: aload_0
       4: invokevirtual #122                // Method scala/runtime/ScalaRunTime$._hashCode:(Lscala/Product;)I
       7: ireturn

  public java.lang.String toString();
    Code:
       0: getstatic     #110                // Field scala/runtime/ScalaRunTime$.MODULE$:Lscala/runtime/ScalaRunTime$;
       3: aload_0
       4: invokevirtual #126                // Method scala/runtime/ScalaRunTime$._toString:(Lscala/Product;)Ljava/lang/String;
       7: areturn

  public boolean equals(java.lang.Object);
    Code:
       0: aload_0
       1: aload_1
       2: if_acmpeq     75
       5: aload_1
       6: astore_3
       7: aload_3
       8: instanceof    #2                  // class wvlet/airframe/config/ConfigPaths
      11: ifeq          18
      14: iconst_1
      15: goto          25
      18: goto          21
      21: iconst_0
      22: goto          25
      25: ifeq          79
      28: aload_1
      29: checkcast     #2                  // class wvlet/airframe/config/ConfigPaths
      32: astore        4
      34: aload_0
      35: invokevirtual #81                 // Method configPaths:()Lscala/collection/Seq;
      38: aload         4
      40: invokevirtual #81                 // Method configPaths:()Lscala/collection/Seq;
      43: astore        5
      45: dup
      46: ifnonnull     58
      49: pop
      50: aload         5
      52: ifnull        66
      55: goto          79
      58: aload         5
      60: invokevirtual #129                // Method java/lang/Object.equals:(Ljava/lang/Object;)Z
      63: ifeq          79
      66: aload         4
      68: aload_0
      69: invokevirtual #131                // Method canEqual:(Ljava/lang/Object;)Z
      72: ifeq          79
      75: iconst_1
      76: goto          80
      79: iconst_0
      80: ireturn

  public wvlet.airframe.config.ConfigPaths(scala.collection.Seq<java.lang.String>);
    Code:
       0: aload_0
       1: aload_1
       2: putfield      #73                 // Field configPaths:Lscala/collection/Seq;
       5: aload_0
       6: invokespecial #137                // Method java/lang/Object."<init>":()V
       9: aload_0
      10: invokestatic  #143                // InterfaceMethod wvlet/log/LoggingMethods.$init$:(Lwvlet/log/LoggingMethods;)V
      13: aload_0
      14: invokestatic  #146                // InterfaceMethod wvlet/log/LazyLogger.$init$:(Lwvlet/log/LazyLogger;)V
      17: aload_0
      18: invokestatic  #149                // InterfaceMethod scala/Product.$init$:(Lscala/Product;)V
      21: aload_0
      22: invokevirtual #151                // Method logger:()Lwvlet/log/Logger;
      25: getstatic     #154                // Field wvlet/log/LogLevel$INFO$.MODULE$:Lwvlet/log/LogLevel$INFO$;
      28: invokevirtual #160                // Method wvlet/log/Logger.isEnabled:(Lwvlet/log/LogLevel;)Z
      31: ifeq          98
      34: aload_0
      35: invokevirtual #151                // Method logger:()Lwvlet/log/Logger;
      38: getstatic     #154                // Field wvlet/log/LogLevel$INFO$.MODULE$:Lwvlet/log/LogLevel$INFO$;
      41: new           #162                // class wvlet/log/LogSource
      44: dup
      45: ldc           #164                // String
      47: ldc           #165                // String Config.scala
      49: bipush        31
      51: bipush        7
      53: invokespecial #168                // Method wvlet/log/LogSource."<init>":(Ljava/lang/String;Ljava/lang/String;II)V
      56: new           #170                // class java/lang/StringBuilder
      59: dup
      60: ldc           #171                // int 21
      62: invokespecial #174                // Method java/lang/StringBuilder."<init>":(I)V
      65: ldc           #176                // String Config file paths: [
      67: invokevirtual #180                // Method java/lang/StringBuilder.append:(Ljava/lang/String;)Ljava/lang/StringBuilder;
      70: aload_1
      71: ldc           #182                // String ,
      73: invokeinterface #186,  2          // InterfaceMethod scala/collection/Seq.mkString:(Ljava/lang/String;)Ljava/lang/String;
      78: invokevirtual #180                // Method java/lang/StringBuilder.append:(Ljava/lang/String;)Ljava/lang/StringBuilder;
      81: ldc           #188                // String ]
      83: invokevirtual #180                // Method java/lang/StringBuilder.append:(Ljava/lang/String;)Ljava/lang/StringBuilder;
      86: invokevirtual #190                // Method java/lang/StringBuilder.toString:()Ljava/lang/String;
      89: invokevirtual #194                // Method wvlet/log/Logger.log:(Lwvlet/log/LogLevel;Lwvlet/log/LogSource;Ljava/lang/Object;)V
      92: getstatic     #200                // Field scala/runtime/BoxedUnit.UNIT:Lscala/runtime/BoxedUnit;
      95: goto          101
      98: getstatic     #200                // Field scala/runtime/BoxedUnit.UNIT:Lscala/runtime/BoxedUnit;
     101: pop
     102: return
}
