Compiled from "PolicySetCombinerParametersType.java"
public interface org.opensaml.xacml.policy.PolicySetCombinerParametersType extends org.opensaml.xacml.policy.CombinerParametersType {
  public static final java.lang.String DEFAULT_ELEMENT_LOCAL_NAME;

  public static final javax.xml.namespace.QName DEFAULT_ELEMENT_NAME;

  public static final java.lang.String SCHEMA_TYPE_LOCAL_NAME;

  public static final javax.xml.namespace.QName SCHEMA_TYPE_NAME;

  public static final java.lang.String POLICY_SET_ID_REF_ATTRIB_NAME;

  public abstract java.lang.String getPolicySetIdRef();

  public abstract void setPolicySetIdRef(java.lang.String);

  static {};
    Code:
       0: new           #1                  // class javax/xml/namespace/QName
       3: dup
       4: ldc           #2                  // String urn:oasis:names:tc:xacml:2.0:policy:schema:os
       6: ldc           #3                  // String PolicySetCombinerParameters
       8: ldc           #4                  // String xacml
      10: invokespecial #5                  // Method javax/xml/namespace/QName."<init>":(Ljava/lang/String;Ljava/lang/String;Ljava/lang/String;)V
      13: putstatic     #6                  // Field DEFAULT_ELEMENT_NAME:Ljavax/xml/namespace/QName;
      16: new           #1                  // class javax/xml/namespace/QName
      19: dup
      20: ldc           #2                  // String urn:oasis:names:tc:xacml:2.0:policy:schema:os
      22: ldc           #7                  // String PolicySetCombinerParametersType
      24: ldc           #4                  // String xacml
      26: invokespecial #5                  // Method javax/xml/namespace/QName."<init>":(Ljava/lang/String;Ljava/lang/String;Ljava/lang/String;)V
      29: putstatic     #8                  // Field SCHEMA_TYPE_NAME:Ljavax/xml/namespace/QName;
      32: return
}
