Compiled from "NamedCacheResolver.java"
public class org.springframework.cache.interceptor.NamedCacheResolver extends org.springframework.cache.interceptor.AbstractCacheResolver {
  private java.util.Collection<java.lang.String> cacheNames;

  public org.springframework.cache.interceptor.NamedCacheResolver(org.springframework.cache.CacheManager, java.lang.String...);
    Code:
       0: aload_0
       1: aload_1
       2: invokespecial #1                  // Method org/springframework/cache/interceptor/AbstractCacheResolver."<init>":(Lorg/springframework/cache/CacheManager;)V
       5: aload_0
       6: new           #2                  // class java/util/ArrayList
       9: dup
      10: aload_2
      11: invokestatic  #3                  // Method java/util/Arrays.asList:([Ljava/lang/Object;)Ljava/util/List;
      14: invokespecial #4                  // Method java/util/ArrayList."<init>":(Ljava/util/Collection;)V
      17: putfield      #5                  // Field cacheNames:Ljava/util/Collection;
      20: return

  public org.springframework.cache.interceptor.NamedCacheResolver();
    Code:
       0: aload_0
       1: invokespecial #6                  // Method org/springframework/cache/interceptor/AbstractCacheResolver."<init>":()V
       4: return

  public void setCacheNames(java.util.Collection<java.lang.String>);
    Code:
       0: aload_0
       1: aload_1
       2: putfield      #5                  // Field cacheNames:Ljava/util/Collection;
       5: return

  protected java.util.Collection<java.lang.String> getCacheNames(org.springframework.cache.interceptor.CacheOperationInvocationContext<?>);
    Code:
       0: aload_0
       1: getfield      #5                  // Field cacheNames:Ljava/util/Collection;
       4: areturn
}
