Compiled from "KnativeSchemaFluentImpl.java"
public class io.dekorate.deps.knative.api.model.KnativeSchemaFluentImpl$V1beta1V1beta1ChanalableListNestedImpl<N> extends io.dekorate.deps.knative.duck.v1beta1.ChannelableListFluentImpl<io.dekorate.deps.knative.api.model.KnativeSchemaFluent$V1beta1V1beta1ChanalableListNested<N>> implements io.dekorate.deps.knative.api.model.KnativeSchemaFluent$V1beta1V1beta1ChanalableListNested<N>, io.dekorate.deps.kubernetes.api.builder.Nested<N> {
  private final io.dekorate.deps.knative.duck.v1beta1.ChannelableListBuilder builder;

  final io.dekorate.deps.knative.api.model.KnativeSchemaFluentImpl this$0;

  io.dekorate.deps.knative.api.model.KnativeSchemaFluentImpl$V1beta1V1beta1ChanalableListNestedImpl(io.dekorate.deps.knative.api.model.KnativeSchemaFluentImpl, io.dekorate.deps.knative.duck.v1beta1.ChannelableList);
    Code:
       0: aload_0
       1: aload_1
       2: putfield      #24                 // Field this$0:Lio/dekorate/deps/knative/api/model/KnativeSchemaFluentImpl;
       5: aload_0
       6: invokespecial #27                 // Method io/dekorate/deps/knative/duck/v1beta1/ChannelableListFluentImpl."<init>":()V
       9: aload_0
      10: new           #29                 // class io/dekorate/deps/knative/duck/v1beta1/ChannelableListBuilder
      13: dup
      14: aload_0
      15: aload_2
      16: invokespecial #32                 // Method io/dekorate/deps/knative/duck/v1beta1/ChannelableListBuilder."<init>":(Lio/dekorate/deps/knative/duck/v1beta1/ChannelableListFluent;Lio/dekorate/deps/knative/duck/v1beta1/ChannelableList;)V
      19: putfield      #34                 // Field builder:Lio/dekorate/deps/knative/duck/v1beta1/ChannelableListBuilder;
      22: return

  io.dekorate.deps.knative.api.model.KnativeSchemaFluentImpl$V1beta1V1beta1ChanalableListNestedImpl(io.dekorate.deps.knative.api.model.KnativeSchemaFluentImpl);
    Code:
       0: aload_0
       1: aload_1
       2: putfield      #24                 // Field this$0:Lio/dekorate/deps/knative/api/model/KnativeSchemaFluentImpl;
       5: aload_0
       6: invokespecial #27                 // Method io/dekorate/deps/knative/duck/v1beta1/ChannelableListFluentImpl."<init>":()V
       9: aload_0
      10: new           #29                 // class io/dekorate/deps/knative/duck/v1beta1/ChannelableListBuilder
      13: dup
      14: aload_0
      15: invokespecial #43                 // Method io/dekorate/deps/knative/duck/v1beta1/ChannelableListBuilder."<init>":(Lio/dekorate/deps/knative/duck/v1beta1/ChannelableListFluent;)V
      18: putfield      #34                 // Field builder:Lio/dekorate/deps/knative/duck/v1beta1/ChannelableListBuilder;
      21: return

  public N and();
    Code:
       0: aload_0
       1: getfield      #24                 // Field this$0:Lio/dekorate/deps/knative/api/model/KnativeSchemaFluentImpl;
       4: aload_0
       5: getfield      #34                 // Field builder:Lio/dekorate/deps/knative/duck/v1beta1/ChannelableListBuilder;
       8: invokevirtual #50                 // Method io/dekorate/deps/knative/duck/v1beta1/ChannelableListBuilder.build:()Lio/dekorate/deps/knative/duck/v1beta1/ChannelableList;
      11: invokevirtual #54                 // Method io/dekorate/deps/knative/api/model/KnativeSchemaFluentImpl.withV1beta1ChanalableList:(Lio/dekorate/deps/knative/duck/v1beta1/ChannelableList;)Lio/dekorate/deps/knative/api/model/KnativeSchemaFluent;
      14: areturn

  public N endV1beta1V1beta1ChanalableList();
    Code:
       0: aload_0
       1: invokevirtual #57                 // Method and:()Ljava/lang/Object;
       4: areturn
}
