Compiled from "KnativeSchemaFluentImpl.java"
public class io.dekorate.deps.knative.api.model.KnativeSchemaFluentImpl$ApiServerSourceListNestedImpl<N> extends io.dekorate.deps.knative.legacysources.v1alpha1.ApiServerSourceListFluentImpl<io.dekorate.deps.knative.api.model.KnativeSchemaFluent$ApiServerSourceListNested<N>> implements io.dekorate.deps.knative.api.model.KnativeSchemaFluent$ApiServerSourceListNested<N>, io.dekorate.deps.kubernetes.api.builder.Nested<N> {
  private final io.dekorate.deps.knative.legacysources.v1alpha1.ApiServerSourceListBuilder builder;

  final io.dekorate.deps.knative.api.model.KnativeSchemaFluentImpl this$0;

  io.dekorate.deps.knative.api.model.KnativeSchemaFluentImpl$ApiServerSourceListNestedImpl(io.dekorate.deps.knative.api.model.KnativeSchemaFluentImpl, io.dekorate.deps.knative.legacysources.v1alpha1.ApiServerSourceList);
    Code:
       0: aload_0
       1: aload_1
       2: putfield      #24                 // Field this$0:Lio/dekorate/deps/knative/api/model/KnativeSchemaFluentImpl;
       5: aload_0
       6: invokespecial #27                 // Method io/dekorate/deps/knative/legacysources/v1alpha1/ApiServerSourceListFluentImpl."<init>":()V
       9: aload_0
      10: new           #29                 // class io/dekorate/deps/knative/legacysources/v1alpha1/ApiServerSourceListBuilder
      13: dup
      14: aload_0
      15: aload_2
      16: invokespecial #32                 // Method io/dekorate/deps/knative/legacysources/v1alpha1/ApiServerSourceListBuilder."<init>":(Lio/dekorate/deps/knative/legacysources/v1alpha1/ApiServerSourceListFluent;Lio/dekorate/deps/knative/legacysources/v1alpha1/ApiServerSourceList;)V
      19: putfield      #34                 // Field builder:Lio/dekorate/deps/knative/legacysources/v1alpha1/ApiServerSourceListBuilder;
      22: return

  io.dekorate.deps.knative.api.model.KnativeSchemaFluentImpl$ApiServerSourceListNestedImpl(io.dekorate.deps.knative.api.model.KnativeSchemaFluentImpl);
    Code:
       0: aload_0
       1: aload_1
       2: putfield      #24                 // Field this$0:Lio/dekorate/deps/knative/api/model/KnativeSchemaFluentImpl;
       5: aload_0
       6: invokespecial #27                 // Method io/dekorate/deps/knative/legacysources/v1alpha1/ApiServerSourceListFluentImpl."<init>":()V
       9: aload_0
      10: new           #29                 // class io/dekorate/deps/knative/legacysources/v1alpha1/ApiServerSourceListBuilder
      13: dup
      14: aload_0
      15: invokespecial #43                 // Method io/dekorate/deps/knative/legacysources/v1alpha1/ApiServerSourceListBuilder."<init>":(Lio/dekorate/deps/knative/legacysources/v1alpha1/ApiServerSourceListFluent;)V
      18: putfield      #34                 // Field builder:Lio/dekorate/deps/knative/legacysources/v1alpha1/ApiServerSourceListBuilder;
      21: return

  public N and();
    Code:
       0: aload_0
       1: getfield      #24                 // Field this$0:Lio/dekorate/deps/knative/api/model/KnativeSchemaFluentImpl;
       4: aload_0
       5: getfield      #34                 // Field builder:Lio/dekorate/deps/knative/legacysources/v1alpha1/ApiServerSourceListBuilder;
       8: invokevirtual #50                 // Method io/dekorate/deps/knative/legacysources/v1alpha1/ApiServerSourceListBuilder.build:()Lio/dekorate/deps/knative/legacysources/v1alpha1/ApiServerSourceList;
      11: invokevirtual #54                 // Method io/dekorate/deps/knative/api/model/KnativeSchemaFluentImpl.withApiServerSourceList:(Lio/dekorate/deps/knative/legacysources/v1alpha1/ApiServerSourceList;)Lio/dekorate/deps/knative/api/model/KnativeSchemaFluent;
      14: areturn

  public N endApiServerSourceList();
    Code:
       0: aload_0
       1: invokevirtual #57                 // Method and:()Ljava/lang/Object;
       4: areturn
}
