Compiled from "ScopedRoutes.java"
class io.grpc.xds.shaded.io.envoyproxy.envoy.extensions.filters.network.http_connection_manager.v3.ScopedRoutes$2 {
  static final int[] $SwitchMap$io$envoyproxy$envoy$extensions$filters$network$http_connection_manager$v3$ScopedRoutes$ScopeKeyBuilder$FragmentBuilder$HeaderValueExtractor$ExtractTypeCase;

  static final int[] $SwitchMap$io$envoyproxy$envoy$extensions$filters$network$http_connection_manager$v3$ScopedRoutes$ScopeKeyBuilder$FragmentBuilder$TypeCase;

  static final int[] $SwitchMap$io$envoyproxy$envoy$extensions$filters$network$http_connection_manager$v3$ScopedRoutes$ConfigSpecifierCase;

  static {};
    Code:
       0: invokestatic  #37                 // Method io/grpc/xds/shaded/io/envoyproxy/envoy/extensions/filters/network/http_connection_manager/v3/ScopedRoutes$ConfigSpecifierCase.values:()[Lio/grpc/xds/shaded/io/envoyproxy/envoy/extensions/filters/network/http_connection_manager/v3/ScopedRoutes$ConfigSpecifierCase;
       3: arraylength
       4: newarray       int
       6: putstatic     #39                 // Field $SwitchMap$io$envoyproxy$envoy$extensions$filters$network$http_connection_manager$v3$ScopedRoutes$ConfigSpecifierCase:[I
       9: getstatic     #39                 // Field $SwitchMap$io$envoyproxy$envoy$extensions$filters$network$http_connection_manager$v3$ScopedRoutes$ConfigSpecifierCase:[I
      12: getstatic     #43                 // Field io/grpc/xds/shaded/io/envoyproxy/envoy/extensions/filters/network/http_connection_manager/v3/ScopedRoutes$ConfigSpecifierCase.SCOPED_ROUTE_CONFIGURATIONS_LIST:Lio/grpc/xds/shaded/io/envoyproxy/envoy/extensions/filters/network/http_connection_manager/v3/ScopedRoutes$ConfigSpecifierCase;
      15: invokevirtual #47                 // Method io/grpc/xds/shaded/io/envoyproxy/envoy/extensions/filters/network/http_connection_manager/v3/ScopedRoutes$ConfigSpecifierCase.ordinal:()I
      18: iconst_1
      19: iastore
      20: goto          24
      23: astore_0
      24: getstatic     #39                 // Field $SwitchMap$io$envoyproxy$envoy$extensions$filters$network$http_connection_manager$v3$ScopedRoutes$ConfigSpecifierCase:[I
      27: getstatic     #50                 // Field io/grpc/xds/shaded/io/envoyproxy/envoy/extensions/filters/network/http_connection_manager/v3/ScopedRoutes$ConfigSpecifierCase.SCOPED_RDS:Lio/grpc/xds/shaded/io/envoyproxy/envoy/extensions/filters/network/http_connection_manager/v3/ScopedRoutes$ConfigSpecifierCase;
      30: invokevirtual #47                 // Method io/grpc/xds/shaded/io/envoyproxy/envoy/extensions/filters/network/http_connection_manager/v3/ScopedRoutes$ConfigSpecifierCase.ordinal:()I
      33: iconst_2
      34: iastore
      35: goto          39
      38: astore_0
      39: getstatic     #39                 // Field $SwitchMap$io$envoyproxy$envoy$extensions$filters$network$http_connection_manager$v3$ScopedRoutes$ConfigSpecifierCase:[I
      42: getstatic     #53                 // Field io/grpc/xds/shaded/io/envoyproxy/envoy/extensions/filters/network/http_connection_manager/v3/ScopedRoutes$ConfigSpecifierCase.CONFIGSPECIFIER_NOT_SET:Lio/grpc/xds/shaded/io/envoyproxy/envoy/extensions/filters/network/http_connection_manager/v3/ScopedRoutes$ConfigSpecifierCase;
      45: invokevirtual #47                 // Method io/grpc/xds/shaded/io/envoyproxy/envoy/extensions/filters/network/http_connection_manager/v3/ScopedRoutes$ConfigSpecifierCase.ordinal:()I
      48: iconst_3
      49: iastore
      50: goto          54
      53: astore_0
      54: invokestatic  #56                 // Method io/grpc/xds/shaded/io/envoyproxy/envoy/extensions/filters/network/http_connection_manager/v3/ScopedRoutes$ScopeKeyBuilder$FragmentBuilder$TypeCase.values:()[Lio/grpc/xds/shaded/io/envoyproxy/envoy/extensions/filters/network/http_connection_manager/v3/ScopedRoutes$ScopeKeyBuilder$FragmentBuilder$TypeCase;
      57: arraylength
      58: newarray       int
      60: putstatic     #58                 // Field $SwitchMap$io$envoyproxy$envoy$extensions$filters$network$http_connection_manager$v3$ScopedRoutes$ScopeKeyBuilder$FragmentBuilder$TypeCase:[I
      63: getstatic     #58                 // Field $SwitchMap$io$envoyproxy$envoy$extensions$filters$network$http_connection_manager$v3$ScopedRoutes$ScopeKeyBuilder$FragmentBuilder$TypeCase:[I
      66: getstatic     #62                 // Field io/grpc/xds/shaded/io/envoyproxy/envoy/extensions/filters/network/http_connection_manager/v3/ScopedRoutes$ScopeKeyBuilder$FragmentBuilder$TypeCase.HEADER_VALUE_EXTRACTOR:Lio/grpc/xds/shaded/io/envoyproxy/envoy/extensions/filters/network/http_connection_manager/v3/ScopedRoutes$ScopeKeyBuilder$FragmentBuilder$TypeCase;
      69: invokevirtual #63                 // Method io/grpc/xds/shaded/io/envoyproxy/envoy/extensions/filters/network/http_connection_manager/v3/ScopedRoutes$ScopeKeyBuilder$FragmentBuilder$TypeCase.ordinal:()I
      72: iconst_1
      73: iastore
      74: goto          78
      77: astore_0
      78: getstatic     #58                 // Field $SwitchMap$io$envoyproxy$envoy$extensions$filters$network$http_connection_manager$v3$ScopedRoutes$ScopeKeyBuilder$FragmentBuilder$TypeCase:[I
      81: getstatic     #66                 // Field io/grpc/xds/shaded/io/envoyproxy/envoy/extensions/filters/network/http_connection_manager/v3/ScopedRoutes$ScopeKeyBuilder$FragmentBuilder$TypeCase.TYPE_NOT_SET:Lio/grpc/xds/shaded/io/envoyproxy/envoy/extensions/filters/network/http_connection_manager/v3/ScopedRoutes$ScopeKeyBuilder$FragmentBuilder$TypeCase;
      84: invokevirtual #63                 // Method io/grpc/xds/shaded/io/envoyproxy/envoy/extensions/filters/network/http_connection_manager/v3/ScopedRoutes$ScopeKeyBuilder$FragmentBuilder$TypeCase.ordinal:()I
      87: iconst_2
      88: iastore
      89: goto          93
      92: astore_0
      93: invokestatic  #69                 // Method io/grpc/xds/shaded/io/envoyproxy/envoy/extensions/filters/network/http_connection_manager/v3/ScopedRoutes$ScopeKeyBuilder$FragmentBuilder$HeaderValueExtractor$ExtractTypeCase.values:()[Lio/grpc/xds/shaded/io/envoyproxy/envoy/extensions/filters/network/http_connection_manager/v3/ScopedRoutes$ScopeKeyBuilder$FragmentBuilder$HeaderValueExtractor$ExtractTypeCase;
      96: arraylength
      97: newarray       int
      99: putstatic     #71                 // Field $SwitchMap$io$envoyproxy$envoy$extensions$filters$network$http_connection_manager$v3$ScopedRoutes$ScopeKeyBuilder$FragmentBuilder$HeaderValueExtractor$ExtractTypeCase:[I
     102: getstatic     #71                 // Field $SwitchMap$io$envoyproxy$envoy$extensions$filters$network$http_connection_manager$v3$ScopedRoutes$ScopeKeyBuilder$FragmentBuilder$HeaderValueExtractor$ExtractTypeCase:[I
     105: getstatic     #75                 // Field io/grpc/xds/shaded/io/envoyproxy/envoy/extensions/filters/network/http_connection_manager/v3/ScopedRoutes$ScopeKeyBuilder$FragmentBuilder$HeaderValueExtractor$ExtractTypeCase.INDEX:Lio/grpc/xds/shaded/io/envoyproxy/envoy/extensions/filters/network/http_connection_manager/v3/ScopedRoutes$ScopeKeyBuilder$FragmentBuilder$HeaderValueExtractor$ExtractTypeCase;
     108: invokevirtual #76                 // Method io/grpc/xds/shaded/io/envoyproxy/envoy/extensions/filters/network/http_connection_manager/v3/ScopedRoutes$ScopeKeyBuilder$FragmentBuilder$HeaderValueExtractor$ExtractTypeCase.ordinal:()I
     111: iconst_1
     112: iastore
     113: goto          117
     116: astore_0
     117: getstatic     #71                 // Field $SwitchMap$io$envoyproxy$envoy$extensions$filters$network$http_connection_manager$v3$ScopedRoutes$ScopeKeyBuilder$FragmentBuilder$HeaderValueExtractor$ExtractTypeCase:[I
     120: getstatic     #79                 // Field io/grpc/xds/shaded/io/envoyproxy/envoy/extensions/filters/network/http_connection_manager/v3/ScopedRoutes$ScopeKeyBuilder$FragmentBuilder$HeaderValueExtractor$ExtractTypeCase.ELEMENT:Lio/grpc/xds/shaded/io/envoyproxy/envoy/extensions/filters/network/http_connection_manager/v3/ScopedRoutes$ScopeKeyBuilder$FragmentBuilder$HeaderValueExtractor$ExtractTypeCase;
     123: invokevirtual #76                 // Method io/grpc/xds/shaded/io/envoyproxy/envoy/extensions/filters/network/http_connection_manager/v3/ScopedRoutes$ScopeKeyBuilder$FragmentBuilder$HeaderValueExtractor$ExtractTypeCase.ordinal:()I
     126: iconst_2
     127: iastore
     128: goto          132
     131: astore_0
     132: getstatic     #71                 // Field $SwitchMap$io$envoyproxy$envoy$extensions$filters$network$http_connection_manager$v3$ScopedRoutes$ScopeKeyBuilder$FragmentBuilder$HeaderValueExtractor$ExtractTypeCase:[I
     135: getstatic     #82                 // Field io/grpc/xds/shaded/io/envoyproxy/envoy/extensions/filters/network/http_connection_manager/v3/ScopedRoutes$ScopeKeyBuilder$FragmentBuilder$HeaderValueExtractor$ExtractTypeCase.EXTRACTTYPE_NOT_SET:Lio/grpc/xds/shaded/io/envoyproxy/envoy/extensions/filters/network/http_connection_manager/v3/ScopedRoutes$ScopeKeyBuilder$FragmentBuilder$HeaderValueExtractor$ExtractTypeCase;
     138: invokevirtual #76                 // Method io/grpc/xds/shaded/io/envoyproxy/envoy/extensions/filters/network/http_connection_manager/v3/ScopedRoutes$ScopeKeyBuilder$FragmentBuilder$HeaderValueExtractor$ExtractTypeCase.ordinal:()I
     141: iconst_3
     142: iastore
     143: goto          147
     146: astore_0
     147: return
    Exception table:
       from    to  target type
           9    20    23   Class java/lang/NoSuchFieldError
          24    35    38   Class java/lang/NoSuchFieldError
          39    50    53   Class java/lang/NoSuchFieldError
          63    74    77   Class java/lang/NoSuchFieldError
          78    89    92   Class java/lang/NoSuchFieldError
         102   113   116   Class java/lang/NoSuchFieldError
         117   128   131   Class java/lang/NoSuchFieldError
         132   143   146   Class java/lang/NoSuchFieldError
}
