Compiled from "ReadOnlyEhcacheEntityRegionAccessStrategy.java"
public class net.sf.ehcache.hibernate.strategy.ReadOnlyEhcacheEntityRegionAccessStrategy extends net.sf.ehcache.hibernate.strategy.AbstractEhcacheAccessStrategy<net.sf.ehcache.hibernate.regions.EhcacheEntityRegion> implements org.hibernate.cache.access.EntityRegionAccessStrategy {
  public net.sf.ehcache.hibernate.strategy.ReadOnlyEhcacheEntityRegionAccessStrategy(net.sf.ehcache.hibernate.regions.EhcacheEntityRegion, org.hibernate.cfg.Settings);
    Code:
       0: aload_0
       1: aload_1
       2: aload_2
       3: invokespecial #1                  // Method net/sf/ehcache/hibernate/strategy/AbstractEhcacheAccessStrategy."<init>":(Lnet/sf/ehcache/hibernate/regions/EhcacheTransactionalDataRegion;Lorg/hibernate/cfg/Settings;)V
       6: return

  public org.hibernate.cache.EntityRegion getRegion();
    Code:
       0: aload_0
       1: getfield      #2                  // Field region:Lnet/sf/ehcache/hibernate/regions/EhcacheTransactionalDataRegion;
       4: checkcast     #3                  // class org/hibernate/cache/EntityRegion
       7: areturn

  public java.lang.Object get(java.lang.Object, long) throws org.hibernate.cache.CacheException;
    Code:
       0: aload_0
       1: getfield      #2                  // Field region:Lnet/sf/ehcache/hibernate/regions/EhcacheTransactionalDataRegion;
       4: checkcast     #4                  // class net/sf/ehcache/hibernate/regions/EhcacheEntityRegion
       7: aload_1
       8: invokevirtual #5                  // Method net/sf/ehcache/hibernate/regions/EhcacheEntityRegion.get:(Ljava/lang/Object;)Ljava/lang/Object;
      11: areturn

  public boolean putFromLoad(java.lang.Object, java.lang.Object, long, java.lang.Object, boolean) throws org.hibernate.cache.CacheException;
    Code:
       0: iload         6
       2: ifeq          21
       5: aload_0
       6: getfield      #2                  // Field region:Lnet/sf/ehcache/hibernate/regions/EhcacheTransactionalDataRegion;
       9: checkcast     #4                  // class net/sf/ehcache/hibernate/regions/EhcacheEntityRegion
      12: aload_1
      13: invokevirtual #6                  // Method net/sf/ehcache/hibernate/regions/EhcacheEntityRegion.contains:(Ljava/lang/Object;)Z
      16: ifeq          21
      19: iconst_0
      20: ireturn
      21: aload_0
      22: getfield      #2                  // Field region:Lnet/sf/ehcache/hibernate/regions/EhcacheTransactionalDataRegion;
      25: checkcast     #4                  // class net/sf/ehcache/hibernate/regions/EhcacheEntityRegion
      28: aload_1
      29: aload_2
      30: invokevirtual #7                  // Method net/sf/ehcache/hibernate/regions/EhcacheEntityRegion.put:(Ljava/lang/Object;Ljava/lang/Object;)V
      33: iconst_1
      34: ireturn

  public org.hibernate.cache.access.SoftLock lockItem(java.lang.Object, java.lang.Object) throws java.lang.UnsupportedOperationException;
    Code:
       0: new           #8                  // class java/lang/UnsupportedOperationException
       3: dup
       4: ldc           #9                  // String Can\'t write to a readonly object
       6: invokespecial #10                 // Method java/lang/UnsupportedOperationException."<init>":(Ljava/lang/String;)V
       9: athrow

  public void unlockItem(java.lang.Object, org.hibernate.cache.access.SoftLock) throws org.hibernate.cache.CacheException;
    Code:
       0: return

  public boolean insert(java.lang.Object, java.lang.Object, java.lang.Object) throws org.hibernate.cache.CacheException;
    Code:
       0: iconst_0
       1: ireturn

  public boolean afterInsert(java.lang.Object, java.lang.Object, java.lang.Object) throws org.hibernate.cache.CacheException;
    Code:
       0: aload_0
       1: getfield      #2                  // Field region:Lnet/sf/ehcache/hibernate/regions/EhcacheTransactionalDataRegion;
       4: checkcast     #4                  // class net/sf/ehcache/hibernate/regions/EhcacheEntityRegion
       7: aload_1
       8: aload_2
       9: invokevirtual #7                  // Method net/sf/ehcache/hibernate/regions/EhcacheEntityRegion.put:(Ljava/lang/Object;Ljava/lang/Object;)V
      12: iconst_1
      13: ireturn

  public boolean update(java.lang.Object, java.lang.Object, java.lang.Object, java.lang.Object) throws java.lang.UnsupportedOperationException;
    Code:
       0: new           #8                  // class java/lang/UnsupportedOperationException
       3: dup
       4: ldc           #9                  // String Can\'t write to a readonly object
       6: invokespecial #10                 // Method java/lang/UnsupportedOperationException."<init>":(Ljava/lang/String;)V
       9: athrow

  public boolean afterUpdate(java.lang.Object, java.lang.Object, java.lang.Object, java.lang.Object, org.hibernate.cache.access.SoftLock) throws java.lang.UnsupportedOperationException;
    Code:
       0: new           #8                  // class java/lang/UnsupportedOperationException
       3: dup
       4: ldc           #9                  // String Can\'t write to a readonly object
       6: invokespecial #10                 // Method java/lang/UnsupportedOperationException."<init>":(Ljava/lang/String;)V
       9: athrow

  public void remove(java.lang.Object) throws org.hibernate.cache.CacheException;
    Code:
       0: aload_0
       1: aload_1
       2: invokespecial #11                 // Method net/sf/ehcache/hibernate/strategy/AbstractEhcacheAccessStrategy.remove:(Ljava/lang/Object;)V
       5: return
}
