Compiled from "Side.java"
public final class org.apache.commons.math3.geometry.partitioning.Side extends java.lang.Enum<org.apache.commons.math3.geometry.partitioning.Side> {
  public static final org.apache.commons.math3.geometry.partitioning.Side PLUS;

  public static final org.apache.commons.math3.geometry.partitioning.Side MINUS;

  public static final org.apache.commons.math3.geometry.partitioning.Side BOTH;

  public static final org.apache.commons.math3.geometry.partitioning.Side HYPER;

  private static final org.apache.commons.math3.geometry.partitioning.Side[] $VALUES;

  public static org.apache.commons.math3.geometry.partitioning.Side[] values();
    Code:
       0: getstatic     #1                  // Field $VALUES:[Lorg/apache/commons/math3/geometry/partitioning/Side;
       3: invokevirtual #2                  // Method "[Lorg/apache/commons/math3/geometry/partitioning/Side;".clone:()Ljava/lang/Object;
       6: checkcast     #3                  // class "[Lorg/apache/commons/math3/geometry/partitioning/Side;"
       9: areturn

  public static org.apache.commons.math3.geometry.partitioning.Side valueOf(java.lang.String);
    Code:
       0: ldc_w         #4                  // class org/apache/commons/math3/geometry/partitioning/Side
       3: aload_0
       4: invokestatic  #5                  // Method java/lang/Enum.valueOf:(Ljava/lang/Class;Ljava/lang/String;)Ljava/lang/Enum;
       7: checkcast     #4                  // class org/apache/commons/math3/geometry/partitioning/Side
      10: areturn

  private org.apache.commons.math3.geometry.partitioning.Side();
    Code:
       0: aload_0
       1: aload_1
       2: iload_2
       3: invokespecial #6                  // Method java/lang/Enum."<init>":(Ljava/lang/String;I)V
       6: return

  static {};
    Code:
       0: new           #4                  // class org/apache/commons/math3/geometry/partitioning/Side
       3: dup
       4: ldc           #7                  // String PLUS
       6: iconst_0
       7: invokespecial #8                  // Method "<init>":(Ljava/lang/String;I)V
      10: putstatic     #9                  // Field PLUS:Lorg/apache/commons/math3/geometry/partitioning/Side;
      13: new           #4                  // class org/apache/commons/math3/geometry/partitioning/Side
      16: dup
      17: ldc           #10                 // String MINUS
      19: iconst_1
      20: invokespecial #8                  // Method "<init>":(Ljava/lang/String;I)V
      23: putstatic     #11                 // Field MINUS:Lorg/apache/commons/math3/geometry/partitioning/Side;
      26: new           #4                  // class org/apache/commons/math3/geometry/partitioning/Side
      29: dup
      30: ldc           #12                 // String BOTH
      32: iconst_2
      33: invokespecial #8                  // Method "<init>":(Ljava/lang/String;I)V
      36: putstatic     #13                 // Field BOTH:Lorg/apache/commons/math3/geometry/partitioning/Side;
      39: new           #4                  // class org/apache/commons/math3/geometry/partitioning/Side
      42: dup
      43: ldc           #14                 // String HYPER
      45: iconst_3
      46: invokespecial #8                  // Method "<init>":(Ljava/lang/String;I)V
      49: putstatic     #15                 // Field HYPER:Lorg/apache/commons/math3/geometry/partitioning/Side;
      52: iconst_4
      53: anewarray     #4                  // class org/apache/commons/math3/geometry/partitioning/Side
      56: dup
      57: iconst_0
      58: getstatic     #9                  // Field PLUS:Lorg/apache/commons/math3/geometry/partitioning/Side;
      61: aastore
      62: dup
      63: iconst_1
      64: getstatic     #11                 // Field MINUS:Lorg/apache/commons/math3/geometry/partitioning/Side;
      67: aastore
      68: dup
      69: iconst_2
      70: getstatic     #13                 // Field BOTH:Lorg/apache/commons/math3/geometry/partitioning/Side;
      73: aastore
      74: dup
      75: iconst_3
      76: getstatic     #15                 // Field HYPER:Lorg/apache/commons/math3/geometry/partitioning/Side;
      79: aastore
      80: putstatic     #1                  // Field $VALUES:[Lorg/apache/commons/math3/geometry/partitioning/Side;
      83: return
}
