Compiled from "BundleDelegatingClassLoader.java"
public class org.apache.camel.core.osgi.utils.BundleDelegatingClassLoader extends java.lang.ClassLoader {
  private static final org.slf4j.Logger LOG;

  private final org.osgi.framework.Bundle bundle;

  private final java.lang.ClassLoader classLoader;

  public org.apache.camel.core.osgi.utils.BundleDelegatingClassLoader(org.osgi.framework.Bundle);
    Code:
       0: aload_0
       1: aload_1
       2: aconst_null
       3: invokespecial #1                  // Method "<init>":(Lorg/osgi/framework/Bundle;Ljava/lang/ClassLoader;)V
       6: return

  public org.apache.camel.core.osgi.utils.BundleDelegatingClassLoader(org.osgi.framework.Bundle, java.lang.ClassLoader);
    Code:
       0: aload_0
       1: invokespecial #2                  // Method java/lang/ClassLoader."<init>":()V
       4: aload_0
       5: aload_1
       6: putfield      #3                  // Field bundle:Lorg/osgi/framework/Bundle;
       9: aload_0
      10: aload_2
      11: putfield      #4                  // Field classLoader:Ljava/lang/ClassLoader;
      14: return

  protected java.lang.Class<?> findClass(java.lang.String) throws java.lang.ClassNotFoundException;
    Code:
       0: getstatic     #5                  // Field LOG:Lorg/slf4j/Logger;
       3: ldc           #6                  // String FindClass: {}
       5: aload_1
       6: invokeinterface #7,  3            // InterfaceMethod org/slf4j/Logger.trace:(Ljava/lang/String;Ljava/lang/Object;)V
      11: aload_0
      12: getfield      #3                  // Field bundle:Lorg/osgi/framework/Bundle;
      15: aload_1
      16: invokeinterface #8,  2            // InterfaceMethod org/osgi/framework/Bundle.loadClass:(Ljava/lang/String;)Ljava/lang/Class;
      21: areturn

  protected java.net.URL findResource(java.lang.String);
    Code:
       0: getstatic     #5                  // Field LOG:Lorg/slf4j/Logger;
       3: ldc           #9                  // String FindResource: {}
       5: aload_1
       6: invokeinterface #7,  3            // InterfaceMethod org/slf4j/Logger.trace:(Ljava/lang/String;Ljava/lang/Object;)V
      11: aload_0
      12: getfield      #3                  // Field bundle:Lorg/osgi/framework/Bundle;
      15: aload_1
      16: invokeinterface #10,  2           // InterfaceMethod org/osgi/framework/Bundle.getResource:(Ljava/lang/String;)Ljava/net/URL;
      21: astore_2
      22: aload_0
      23: getfield      #4                  // Field classLoader:Ljava/lang/ClassLoader;
      26: ifnull        42
      29: aload_2
      30: ifnonnull     42
      33: aload_0
      34: getfield      #4                  // Field classLoader:Ljava/lang/ClassLoader;
      37: aload_1
      38: invokevirtual #11                 // Method java/lang/ClassLoader.getResource:(Ljava/lang/String;)Ljava/net/URL;
      41: astore_2
      42: aload_2
      43: areturn

  protected java.util.Enumeration findResources(java.lang.String) throws java.io.IOException;
    Code:
       0: getstatic     #5                  // Field LOG:Lorg/slf4j/Logger;
       3: ldc           #9                  // String FindResource: {}
       5: aload_1
       6: invokeinterface #7,  3            // InterfaceMethod org/slf4j/Logger.trace:(Ljava/lang/String;Ljava/lang/Object;)V
      11: aload_0
      12: getfield      #3                  // Field bundle:Lorg/osgi/framework/Bundle;
      15: aload_1
      16: invokeinterface #12,  2           // InterfaceMethod org/osgi/framework/Bundle.getResources:(Ljava/lang/String;)Ljava/util/Enumeration;
      21: areturn

  protected java.lang.Class<?> loadClass(java.lang.String, boolean) throws java.lang.ClassNotFoundException;
    Code:
       0: getstatic     #5                  // Field LOG:Lorg/slf4j/Logger;
       3: ldc           #13                 // String LoadClass: {}, resolve: {}
       5: aload_1
       6: iload_2
       7: invokestatic  #14                 // Method java/lang/Boolean.valueOf:(Z)Ljava/lang/Boolean;
      10: invokeinterface #15,  4           // InterfaceMethod org/slf4j/Logger.trace:(Ljava/lang/String;Ljava/lang/Object;Ljava/lang/Object;)V
      15: aload_0
      16: aload_1
      17: invokevirtual #16                 // Method findClass:(Ljava/lang/String;)Ljava/lang/Class;
      20: astore_3
      21: goto          173
      24: astore        4
      26: aload_0
      27: getfield      #4                  // Field classLoader:Ljava/lang/ClassLoader;
      30: ifnull        110
      33: aload_0
      34: getfield      #4                  // Field classLoader:Ljava/lang/ClassLoader;
      37: aload_1
      38: invokevirtual #18                 // Method java/lang/ClassLoader.loadClass:(Ljava/lang/String;)Ljava/lang/Class;
      41: astore_3
      42: goto          173
      45: astore        5
      47: new           #17                 // class java/lang/ClassNotFoundException
      50: dup
      51: new           #19                 // class java/lang/StringBuilder
      54: dup
      55: invokespecial #20                 // Method java/lang/StringBuilder."<init>":()V
      58: aload_1
      59: invokevirtual #21                 // Method java/lang/StringBuilder.append:(Ljava/lang/String;)Ljava/lang/StringBuilder;
      62: ldc           #22                 // String  from bundle
      64: invokevirtual #21                 // Method java/lang/StringBuilder.append:(Ljava/lang/String;)Ljava/lang/StringBuilder;
      67: aload_0
      68: getfield      #3                  // Field bundle:Lorg/osgi/framework/Bundle;
      71: invokeinterface #23,  1           // InterfaceMethod org/osgi/framework/Bundle.getBundleId:()J
      76: invokevirtual #24                 // Method java/lang/StringBuilder.append:(J)Ljava/lang/StringBuilder;
      79: ldc           #25                 // String  (
      81: invokevirtual #21                 // Method java/lang/StringBuilder.append:(Ljava/lang/String;)Ljava/lang/StringBuilder;
      84: aload_0
      85: getfield      #3                  // Field bundle:Lorg/osgi/framework/Bundle;
      88: invokeinterface #26,  1           // InterfaceMethod org/osgi/framework/Bundle.getSymbolicName:()Ljava/lang/String;
      93: invokevirtual #21                 // Method java/lang/StringBuilder.append:(Ljava/lang/String;)Ljava/lang/StringBuilder;
      96: ldc           #27                 // String )
      98: invokevirtual #21                 // Method java/lang/StringBuilder.append:(Ljava/lang/String;)Ljava/lang/StringBuilder;
     101: invokevirtual #28                 // Method java/lang/StringBuilder.toString:()Ljava/lang/String;
     104: aload         4
     106: invokespecial #29                 // Method java/lang/ClassNotFoundException."<init>":(Ljava/lang/String;Ljava/lang/Throwable;)V
     109: athrow
     110: new           #17                 // class java/lang/ClassNotFoundException
     113: dup
     114: new           #19                 // class java/lang/StringBuilder
     117: dup
     118: invokespecial #20                 // Method java/lang/StringBuilder."<init>":()V
     121: aload_1
     122: invokevirtual #21                 // Method java/lang/StringBuilder.append:(Ljava/lang/String;)Ljava/lang/StringBuilder;
     125: ldc           #22                 // String  from bundle
     127: invokevirtual #21                 // Method java/lang/StringBuilder.append:(Ljava/lang/String;)Ljava/lang/StringBuilder;
     130: aload_0
     131: getfield      #3                  // Field bundle:Lorg/osgi/framework/Bundle;
     134: invokeinterface #23,  1           // InterfaceMethod org/osgi/framework/Bundle.getBundleId:()J
     139: invokevirtual #24                 // Method java/lang/StringBuilder.append:(J)Ljava/lang/StringBuilder;
     142: ldc           #25                 // String  (
     144: invokevirtual #21                 // Method java/lang/StringBuilder.append:(Ljava/lang/String;)Ljava/lang/StringBuilder;
     147: aload_0
     148: getfield      #3                  // Field bundle:Lorg/osgi/framework/Bundle;
     151: invokeinterface #26,  1           // InterfaceMethod org/osgi/framework/Bundle.getSymbolicName:()Ljava/lang/String;
     156: invokevirtual #21                 // Method java/lang/StringBuilder.append:(Ljava/lang/String;)Ljava/lang/StringBuilder;
     159: ldc           #27                 // String )
     161: invokevirtual #21                 // Method java/lang/StringBuilder.append:(Ljava/lang/String;)Ljava/lang/StringBuilder;
     164: invokevirtual #28                 // Method java/lang/StringBuilder.toString:()Ljava/lang/String;
     167: aload         4
     169: invokespecial #29                 // Method java/lang/ClassNotFoundException."<init>":(Ljava/lang/String;Ljava/lang/Throwable;)V
     172: athrow
     173: iload_2
     174: ifeq          182
     177: aload_0
     178: aload_3
     179: invokevirtual #30                 // Method resolveClass:(Ljava/lang/Class;)V
     182: aload_3
     183: areturn
    Exception table:
       from    to  target type
          15    21    24   Class java/lang/ClassNotFoundException
          33    42    45   Class java/lang/ClassNotFoundException

  public org.osgi.framework.Bundle getBundle();
    Code:
       0: aload_0
       1: getfield      #3                  // Field bundle:Lorg/osgi/framework/Bundle;
       4: areturn

  public java.lang.String toString();
    Code:
       0: ldc           #31                 // String BundleDelegatingClassLoader(%s)
       2: iconst_1
       3: anewarray     #32                 // class java/lang/Object
       6: dup
       7: iconst_0
       8: aload_0
       9: getfield      #3                  // Field bundle:Lorg/osgi/framework/Bundle;
      12: aastore
      13: invokestatic  #33                 // Method java/lang/String.format:(Ljava/lang/String;[Ljava/lang/Object;)Ljava/lang/String;
      16: areturn

  static {};
    Code:
       0: ldc_w         #34                 // class org/apache/camel/core/osgi/utils/BundleDelegatingClassLoader
       3: invokestatic  #35                 // Method org/slf4j/LoggerFactory.getLogger:(Ljava/lang/Class;)Lorg/slf4j/Logger;
       6: putstatic     #5                  // Field LOG:Lorg/slf4j/Logger;
       9: return
}
