Compiled from "Http2ClearClientProvider.java"
class io.undertow.client.http2.Http2ClearClientProvider$Http2ClearOpenListener$1 implements io.undertow.conduits.ByteActivityCallback {
  final io.undertow.client.http2.Http2ClearClientProvider$ClientStatisticsImpl val$clientStatistics;

  final io.undertow.client.http2.Http2ClearClientProvider$Http2ClearOpenListener this$0;

  io.undertow.client.http2.Http2ClearClientProvider$Http2ClearOpenListener$1(io.undertow.client.http2.Http2ClearClientProvider$Http2ClearOpenListener, io.undertow.client.http2.Http2ClearClientProvider$ClientStatisticsImpl);
    Code:
       0: aload_0
       1: aload_1
       2: putfield      #1                  // Field this$0:Lio/undertow/client/http2/Http2ClearClientProvider$Http2ClearOpenListener;
       5: aload_0
       6: aload_2
       7: putfield      #2                  // Field val$clientStatistics:Lio/undertow/client/http2/Http2ClearClientProvider$ClientStatisticsImpl;
      10: aload_0
      11: invokespecial #3                  // Method java/lang/Object."<init>":()V
      14: return

  public void activity(long);
    Code:
       0: aload_0
       1: getfield      #2                  // Field val$clientStatistics:Lio/undertow/client/http2/Http2ClearClientProvider$ClientStatisticsImpl;
       4: dup
       5: getfield      #4                  // Field io/undertow/client/http2/Http2ClearClientProvider$ClientStatisticsImpl.written:J
       8: lload_1
       9: ladd
      10: putfield      #4                  // Field io/undertow/client/http2/Http2ClearClientProvider$ClientStatisticsImpl.written:J
      13: return
}
