Compiled from "StubbedInvocationMatcher.java"
public class org.mockito.internal.stubbing.StubbedInvocationMatcher extends org.mockito.internal.invocation.InvocationMatcher implements org.mockito.stubbing.Answer,java.io.Serializable {
  private static final long serialVersionUID;

  private final java.util.Queue<org.mockito.stubbing.Answer> answers;

  private org.mockito.invocation.DescribedInvocation usedAt;

  public org.mockito.internal.stubbing.StubbedInvocationMatcher(org.mockito.internal.invocation.InvocationMatcher, org.mockito.stubbing.Answer);
    Code:
       0: aload_0
       1: aload_1
       2: invokevirtual #1                  // Method org/mockito/internal/invocation/InvocationMatcher.getInvocation:()Lorg/mockito/invocation/Invocation;
       5: aload_1
       6: invokevirtual #2                  // Method org/mockito/internal/invocation/InvocationMatcher.getMatchers:()Ljava/util/List;
       9: invokespecial #3                  // Method org/mockito/internal/invocation/InvocationMatcher."<init>":(Lorg/mockito/invocation/Invocation;Ljava/util/List;)V
      12: aload_0
      13: new           #4                  // class java/util/concurrent/ConcurrentLinkedQueue
      16: dup
      17: invokespecial #5                  // Method java/util/concurrent/ConcurrentLinkedQueue."<init>":()V
      20: putfield      #6                  // Field answers:Ljava/util/Queue;
      23: aload_0
      24: getfield      #6                  // Field answers:Ljava/util/Queue;
      27: aload_2
      28: invokeinterface #7,  2            // InterfaceMethod java/util/Queue.add:(Ljava/lang/Object;)Z
      33: pop
      34: return

  public java.lang.Object answer(org.mockito.invocation.InvocationOnMock) throws java.lang.Throwable;
    Code:
       0: aload_0
       1: getfield      #6                  // Field answers:Ljava/util/Queue;
       4: dup
       5: astore_3
       6: monitorenter
       7: aload_0
       8: getfield      #6                  // Field answers:Ljava/util/Queue;
      11: invokeinterface #8,  1            // InterfaceMethod java/util/Queue.size:()I
      16: iconst_1
      17: if_icmpne     35
      20: aload_0
      21: getfield      #6                  // Field answers:Ljava/util/Queue;
      24: invokeinterface #9,  1            // InterfaceMethod java/util/Queue.peek:()Ljava/lang/Object;
      29: checkcast     #10                 // class org/mockito/stubbing/Answer
      32: goto          47
      35: aload_0
      36: getfield      #6                  // Field answers:Ljava/util/Queue;
      39: invokeinterface #11,  1           // InterfaceMethod java/util/Queue.poll:()Ljava/lang/Object;
      44: checkcast     #10                 // class org/mockito/stubbing/Answer
      47: astore_2
      48: aload_3
      49: monitorexit
      50: goto          60
      53: astore        4
      55: aload_3
      56: monitorexit
      57: aload         4
      59: athrow
      60: aload_2
      61: aload_1
      62: invokeinterface #12,  2           // InterfaceMethod org/mockito/stubbing/Answer.answer:(Lorg/mockito/invocation/InvocationOnMock;)Ljava/lang/Object;
      67: areturn
    Exception table:
       from    to  target type
           7    50    53   any
          53    57    53   any

  public void addAnswer(org.mockito.stubbing.Answer);
    Code:
       0: aload_0
       1: getfield      #6                  // Field answers:Ljava/util/Queue;
       4: aload_1
       5: invokeinterface #7,  2            // InterfaceMethod java/util/Queue.add:(Ljava/lang/Object;)Z
      10: pop
      11: return

  public void markStubUsed(org.mockito.invocation.DescribedInvocation);
    Code:
       0: aload_0
       1: aload_1
       2: putfield      #13                 // Field usedAt:Lorg/mockito/invocation/DescribedInvocation;
       5: return

  public boolean wasUsed();
    Code:
       0: aload_0
       1: getfield      #13                 // Field usedAt:Lorg/mockito/invocation/DescribedInvocation;
       4: ifnull        11
       7: iconst_1
       8: goto          12
      11: iconst_0
      12: ireturn

  public java.lang.String toString();
    Code:
       0: new           #14                 // class java/lang/StringBuilder
       3: dup
       4: invokespecial #15                 // Method java/lang/StringBuilder."<init>":()V
       7: aload_0
       8: invokespecial #16                 // Method org/mockito/internal/invocation/InvocationMatcher.toString:()Ljava/lang/String;
      11: invokevirtual #17                 // Method java/lang/StringBuilder.append:(Ljava/lang/String;)Ljava/lang/StringBuilder;
      14: ldc           #18                 // String  stubbed with:
      16: invokevirtual #17                 // Method java/lang/StringBuilder.append:(Ljava/lang/String;)Ljava/lang/StringBuilder;
      19: aload_0
      20: getfield      #6                  // Field answers:Ljava/util/Queue;
      23: invokevirtual #19                 // Method java/lang/StringBuilder.append:(Ljava/lang/Object;)Ljava/lang/StringBuilder;
      26: invokevirtual #20                 // Method java/lang/StringBuilder.toString:()Ljava/lang/String;
      29: areturn
}
