Compiled from "ServerPort.java"
public class io.micronaut.function.aws.proxy.test.ServerPort {
  private boolean random;

  private java.lang.Integer port;

  public io.micronaut.function.aws.proxy.test.ServerPort();
    Code:
       0: aload_0
       1: invokespecial #1                  // Method java/lang/Object."<init>":()V
       4: return

  public io.micronaut.function.aws.proxy.test.ServerPort(boolean, java.lang.Integer);
    Code:
       0: aload_0
       1: invokespecial #1                  // Method java/lang/Object."<init>":()V
       4: aload_0
       5: iload_1
       6: putfield      #2                  // Field random:Z
       9: aload_0
      10: aload_2
      11: putfield      #3                  // Field port:Ljava/lang/Integer;
      14: return

  public boolean isRandom();
    Code:
       0: aload_0
       1: getfield      #2                  // Field random:Z
       4: ireturn

  public void setRandom(boolean);
    Code:
       0: aload_0
       1: iload_1
       2: putfield      #2                  // Field random:Z
       5: return

  public java.lang.Integer getPort();
    Code:
       0: aload_0
       1: getfield      #3                  // Field port:Ljava/lang/Integer;
       4: areturn

  public void setPort(java.lang.Integer);
    Code:
       0: aload_0
       1: aload_1
       2: putfield      #3                  // Field port:Ljava/lang/Integer;
       5: return
}
