Compiled from "MergedAnnotationCollectors.java"
public abstract class org.springframework.core.annotation.MergedAnnotationCollectors {
  private static final java.util.stream.Collector$Characteristics[] NO_CHARACTERISTICS;

  private static final java.util.stream.Collector$Characteristics[] IDENTITY_FINISH_CHARACTERISTICS;

  private org.springframework.core.annotation.MergedAnnotationCollectors();
    Code:
       0: aload_0
       1: invokespecial #1                  // Method java/lang/Object."<init>":()V
       4: return

  public static <A extends java.lang.annotation.Annotation> java.util.stream.Collector<org.springframework.core.annotation.MergedAnnotation<A>, ?, java.util.Set<A>> toAnnotationSet();
    Code:
       0: invokedynamic #2,  0              // InvokeDynamic #0:get:()Ljava/util/function/Supplier;
       5: invokedynamic #3,  0              // InvokeDynamic #1:accept:()Ljava/util/function/BiConsumer;
      10: invokedynamic #4,  0              // InvokeDynamic #2:apply:()Ljava/util/function/BinaryOperator;
      15: invokedynamic #5,  0              // InvokeDynamic #3:apply:()Ljava/util/function/Function;
      20: iconst_0
      21: anewarray     #6                  // class java/util/stream/Collector$Characteristics
      24: invokestatic  #7                  // InterfaceMethod java/util/stream/Collector.of:(Ljava/util/function/Supplier;Ljava/util/function/BiConsumer;Ljava/util/function/BinaryOperator;Ljava/util/function/Function;[Ljava/util/stream/Collector$Characteristics;)Ljava/util/stream/Collector;
      27: areturn

  public static <A extends java.lang.annotation.Annotation> java.util.stream.Collector<org.springframework.core.annotation.MergedAnnotation<A>, ?, java.lang.annotation.Annotation[]> toAnnotationArray();
    Code:
       0: invokedynamic #8,  0              // InvokeDynamic #4:apply:()Ljava/util/function/IntFunction;
       5: invokestatic  #9                  // Method toAnnotationArray:(Ljava/util/function/IntFunction;)Ljava/util/stream/Collector;
       8: areturn

  public static <R extends java.lang.annotation.Annotation, A extends R> java.util.stream.Collector<org.springframework.core.annotation.MergedAnnotation<A>, ?, R[]> toAnnotationArray(java.util.function.IntFunction<R[]>);
    Code:
       0: invokedynamic #2,  0              // InvokeDynamic #0:get:()Ljava/util/function/Supplier;
       5: invokedynamic #10,  0             // InvokeDynamic #5:accept:()Ljava/util/function/BiConsumer;
      10: invokedynamic #4,  0              // InvokeDynamic #2:apply:()Ljava/util/function/BinaryOperator;
      15: aload_0
      16: invokedynamic #11,  0             // InvokeDynamic #6:apply:(Ljava/util/function/IntFunction;)Ljava/util/function/Function;
      21: iconst_0
      22: anewarray     #6                  // class java/util/stream/Collector$Characteristics
      25: invokestatic  #7                  // InterfaceMethod java/util/stream/Collector.of:(Ljava/util/function/Supplier;Ljava/util/function/BiConsumer;Ljava/util/function/BinaryOperator;Ljava/util/function/Function;[Ljava/util/stream/Collector$Characteristics;)Ljava/util/stream/Collector;
      28: areturn

  public static <A extends java.lang.annotation.Annotation> java.util.stream.Collector<org.springframework.core.annotation.MergedAnnotation<A>, ?, org.springframework.util.MultiValueMap<java.lang.String, java.lang.Object>> toMultiValueMap(org.springframework.core.annotation.MergedAnnotation$Adapt...);
    Code:
       0: invokestatic  #12                 // InterfaceMethod java/util/function/Function.identity:()Ljava/util/function/Function;
       3: aload_0
       4: invokestatic  #13                 // Method toMultiValueMap:(Ljava/util/function/Function;[Lorg/springframework/core/annotation/MergedAnnotation$Adapt;)Ljava/util/stream/Collector;
       7: areturn

  public static <A extends java.lang.annotation.Annotation> java.util.stream.Collector<org.springframework.core.annotation.MergedAnnotation<A>, ?, org.springframework.util.MultiValueMap<java.lang.String, java.lang.Object>> toMultiValueMap(java.util.function.Function<org.springframework.util.MultiValueMap<java.lang.String, java.lang.Object>, org.springframework.util.MultiValueMap<java.lang.String, java.lang.Object>>, org.springframework.core.annotation.MergedAnnotation$Adapt...);
    Code:
       0: aload_0
       1: invokestatic  #12                 // InterfaceMethod java/util/function/Function.identity:()Ljava/util/function/Function;
       4: invokestatic  #14                 // Method isSameInstance:(Ljava/lang/Object;Ljava/lang/Object;)Z
       7: ifeq          16
      10: getstatic     #15                 // Field IDENTITY_FINISH_CHARACTERISTICS:[Ljava/util/stream/Collector$Characteristics;
      13: goto          19
      16: getstatic     #16                 // Field NO_CHARACTERISTICS:[Ljava/util/stream/Collector$Characteristics;
      19: astore_2
      20: invokedynamic #17,  0             // InvokeDynamic #7:get:()Ljava/util/function/Supplier;
      25: aload_1
      26: invokedynamic #18,  0             // InvokeDynamic #8:accept:([Lorg/springframework/core/annotation/MergedAnnotation$Adapt;)Ljava/util/function/BiConsumer;
      31: invokedynamic #19,  0             // InvokeDynamic #9:apply:()Ljava/util/function/BinaryOperator;
      36: aload_0
      37: aload_2
      38: invokestatic  #7                  // InterfaceMethod java/util/stream/Collector.of:(Ljava/util/function/Supplier;Ljava/util/function/BiConsumer;Ljava/util/function/BinaryOperator;Ljava/util/function/Function;[Ljava/util/stream/Collector$Characteristics;)Ljava/util/stream/Collector;
      41: areturn

  private static boolean isSameInstance(java.lang.Object, java.lang.Object);
    Code:
       0: aload_0
       1: aload_1
       2: if_acmpne     9
       5: iconst_1
       6: goto          10
       9: iconst_0
      10: ireturn

  private static <E, L extends java.util.List<E>> L addAll(L, L);
    Code:
       0: aload_0
       1: aload_1
       2: invokeinterface #20,  2           // InterfaceMethod java/util/List.addAll:(Ljava/util/Collection;)Z
       7: pop
       8: aload_0
       9: areturn

  private static <K, V> org.springframework.util.MultiValueMap<K, V> merge(org.springframework.util.MultiValueMap<K, V>, org.springframework.util.MultiValueMap<K, V>);
    Code:
       0: aload_0
       1: aload_1
       2: invokeinterface #21,  2           // InterfaceMethod org/springframework/util/MultiValueMap.addAll:(Lorg/springframework/util/MultiValueMap;)V
       7: aload_0
       8: areturn

  private static void lambda$toMultiValueMap$4(org.springframework.core.annotation.MergedAnnotation$Adapt[], org.springframework.util.MultiValueMap, org.springframework.core.annotation.MergedAnnotation);
    Code:
       0: aload_2
       1: aload_0
       2: invokeinterface #22,  2           // InterfaceMethod org/springframework/core/annotation/MergedAnnotation.asMap:([Lorg/springframework/core/annotation/MergedAnnotation$Adapt;)Ljava/util/Map;
       7: aload_1
       8: dup
       9: invokevirtual #23                 // Method java/lang/Object.getClass:()Ljava/lang/Class;
      12: pop
      13: invokedynamic #24,  0             // InvokeDynamic #10:accept:(Lorg/springframework/util/MultiValueMap;)Ljava/util/function/BiConsumer;
      18: invokeinterface #25,  2           // InterfaceMethod java/util/Map.forEach:(Ljava/util/function/BiConsumer;)V
      23: return

  private static java.lang.annotation.Annotation[] lambda$toAnnotationArray$3(java.util.function.IntFunction, java.util.ArrayList);
    Code:
       0: aload_1
       1: aload_0
       2: aload_1
       3: invokevirtual #26                 // Method java/util/ArrayList.size:()I
       6: invokeinterface #27,  2           // InterfaceMethod java/util/function/IntFunction.apply:(I)Ljava/lang/Object;
      11: checkcast     #28                 // class "[Ljava/lang/Object;"
      14: invokevirtual #29                 // Method java/util/ArrayList.toArray:([Ljava/lang/Object;)[Ljava/lang/Object;
      17: checkcast     #30                 // class "[Ljava/lang/annotation/Annotation;"
      20: areturn

  private static void lambda$toAnnotationArray$2(java.util.ArrayList, org.springframework.core.annotation.MergedAnnotation);
    Code:
       0: aload_0
       1: aload_1
       2: invokeinterface #31,  1           // InterfaceMethod org/springframework/core/annotation/MergedAnnotation.synthesize:()Ljava/lang/annotation/Annotation;
       7: invokevirtual #32                 // Method java/util/ArrayList.add:(Ljava/lang/Object;)Z
      10: pop
      11: return

  private static java.lang.annotation.Annotation[] lambda$toAnnotationArray$1(int);
    Code:
       0: iload_0
       1: anewarray     #33                 // class java/lang/annotation/Annotation
       4: areturn

  private static void lambda$toAnnotationSet$0(java.util.ArrayList, org.springframework.core.annotation.MergedAnnotation);
    Code:
       0: aload_0
       1: aload_1
       2: invokeinterface #31,  1           // InterfaceMethod org/springframework/core/annotation/MergedAnnotation.synthesize:()Ljava/lang/annotation/Annotation;
       7: invokevirtual #32                 // Method java/util/ArrayList.add:(Ljava/lang/Object;)Z
      10: pop
      11: return

  static {};
    Code:
       0: iconst_0
       1: anewarray     #6                  // class java/util/stream/Collector$Characteristics
       4: putstatic     #16                 // Field NO_CHARACTERISTICS:[Ljava/util/stream/Collector$Characteristics;
       7: iconst_1
       8: anewarray     #6                  // class java/util/stream/Collector$Characteristics
      11: dup
      12: iconst_0
      13: getstatic     #34                 // Field java/util/stream/Collector$Characteristics.IDENTITY_FINISH:Ljava/util/stream/Collector$Characteristics;
      16: aastore
      17: putstatic     #15                 // Field IDENTITY_FINISH_CHARACTERISTICS:[Ljava/util/stream/Collector$Characteristics;
      20: return
}
