Compiled from "NamedBuilder.java"
abstract class net.contextfw.web.application.internal.component.NamedBuilder extends net.contextfw.web.application.internal.component.PropertyBuilder {
  private final java.lang.String name;

  protected net.contextfw.web.application.internal.component.NamedBuilder(net.contextfw.web.application.internal.component.PropertyAccess<java.lang.Object>, java.lang.String, java.lang.String);
    Code:
       0: aload_0
       1: aload_1
       2: aload_3
       3: invokespecial #1                  // Method net/contextfw/web/application/internal/component/PropertyBuilder."<init>":(Lnet/contextfw/web/application/internal/component/PropertyAccess;Ljava/lang/String;)V
       6: aload_0
       7: aload_2
       8: putfield      #2                  // Field name:Ljava/lang/String;
      11: return

  final void buildValue(net.contextfw.web.application.dom.DOMBuilder, java.lang.Object);
    Code:
       0: aload_0
       1: aload_1
       2: aload_0
       3: getfield      #2                  // Field name:Ljava/lang/String;
       6: aload_2
       7: invokevirtual #3                  // Method buildNamedValue:(Lnet/contextfw/web/application/dom/DOMBuilder;Ljava/lang/String;Ljava/lang/Object;)V
      10: return

  abstract void buildNamedValue(net.contextfw.web.application.dom.DOMBuilder, java.lang.String, java.lang.Object);
}
