Compiled from "DelegatingInputStream.java"
public class org.apache.cxf.io.DelegatingInputStream extends java.io.FilterInputStream {
  protected boolean cached;

  public org.apache.cxf.io.DelegatingInputStream(java.io.InputStream);
    Code:
       0: aload_0
       1: aload_1
       2: invokespecial #1                  // Method java/io/FilterInputStream."<init>":(Ljava/io/InputStream;)V
       5: return

  public void setInputStream(java.io.InputStream);
    Code:
       0: aload_0
       1: aload_1
       2: putfield      #2                  // Field in:Ljava/io/InputStream;
       5: return

  public java.io.InputStream getInputStream();
    Code:
       0: aload_0
       1: getfield      #2                  // Field in:Ljava/io/InputStream;
       4: areturn

  public void cacheInput();
    Code:
       0: aload_0
       1: getfield      #3                  // Field cached:Z
       4: ifne          80
       7: new           #4                  // class org/apache/cxf/io/CachedOutputStream
      10: dup
      11: invokespecial #5                  // Method org/apache/cxf/io/CachedOutputStream."<init>":()V
      14: astore_1
      15: aload_0
      16: getfield      #2                  // Field in:Ljava/io/InputStream;
      19: astore_2
      20: aload_0
      21: getfield      #2                  // Field in:Ljava/io/InputStream;
      24: aload_1
      25: invokestatic  #6                  // Method org/apache/cxf/helpers/IOUtils.copy:(Ljava/io/InputStream;Ljava/io/OutputStream;)I
      28: pop
      29: aload_1
      30: invokevirtual #7                  // Method org/apache/cxf/io/CachedOutputStream.size:()J
      33: lconst_0
      34: lcmp
      35: ifle          49
      38: aload_0
      39: aload_1
      40: invokevirtual #8                  // Method org/apache/cxf/io/CachedOutputStream.getInputStream:()Ljava/io/InputStream;
      43: putfield      #2                  // Field in:Ljava/io/InputStream;
      46: goto          63
      49: aload_0
      50: new           #9                  // class java/io/ByteArrayInputStream
      53: dup
      54: iconst_0
      55: newarray       byte
      57: invokespecial #10                 // Method java/io/ByteArrayInputStream."<init>":([B)V
      60: putfield      #2                  // Field in:Ljava/io/InputStream;
      63: aload_1
      64: invokevirtual #11                 // Method org/apache/cxf/io/CachedOutputStream.close:()V
      67: aload_2
      68: invokevirtual #12                 // Method java/io/InputStream.close:()V
      71: goto          75
      74: astore_2
      75: aload_0
      76: iconst_1
      77: putfield      #3                  // Field cached:Z
      80: return
    Exception table:
       from    to  target type
          15    71    74   Class java/io/IOException
}
