Compiled from "ReflectJavaClass.kt"
final class kotlin.reflect.jvm.internal.impl.descriptors.runtime.structure.ReflectJavaClass$constructors$2 extends kotlin.jvm.internal.FunctionReference implements kotlin.jvm.functions.Function1<java.lang.reflect.Constructor<?>, kotlin.reflect.jvm.internal.impl.descriptors.runtime.structure.ReflectJavaConstructor> {
  public static final kotlin.reflect.jvm.internal.impl.descriptors.runtime.structure.ReflectJavaClass$constructors$2 INSTANCE;

  kotlin.reflect.jvm.internal.impl.descriptors.runtime.structure.ReflectJavaClass$constructors$2();
    Code:
       0: aload_0
       1: iconst_1
       2: invokespecial #14                 // Method kotlin/jvm/internal/FunctionReference."<init>":(I)V
       5: return

  public final kotlin.reflect.jvm.internal.impl.descriptors.runtime.structure.ReflectJavaConstructor invoke(java.lang.reflect.Constructor<?>);
    Code:
       0: aload_1
       1: ldc           #3                  // String p0
       3: invokestatic  #15                 // Method kotlin/jvm/internal/Intrinsics.checkNotNullParameter:(Ljava/lang/Object;Ljava/lang/String;)V
       6: new           #12                 // class kotlin/reflect/jvm/internal/impl/descriptors/runtime/structure/ReflectJavaConstructor
       9: dup
      10: aload_1
      11: invokespecial #19                 // Method kotlin/reflect/jvm/internal/impl/descriptors/runtime/structure/ReflectJavaConstructor."<init>":(Ljava/lang/reflect/Constructor;)V
      14: areturn

  public final java.lang.String getSignature();
    Code:
       0: ldc           #2                  // String <init>(Ljava/lang/reflect/Constructor;)V
       2: areturn

  public final java.lang.String getName();
    Code:
       0: ldc           #1                  // String <init>
       2: areturn

  public final kotlin.reflect.KDeclarationContainer getOwner();
    Code:
       0: ldc           #12                 // class kotlin/reflect/jvm/internal/impl/descriptors/runtime/structure/ReflectJavaConstructor
       2: invokestatic  #16                 // Method kotlin/jvm/internal/Reflection.getOrCreateKotlinClass:(Ljava/lang/Class;)Lkotlin/reflect/KClass;
       5: checkcast     #9                  // class kotlin/reflect/KDeclarationContainer
       8: areturn

  public java.lang.Object invoke(java.lang.Object);
    Code:
       0: aload_0
       1: aload_1
       2: checkcast     #4                  // class java/lang/reflect/Constructor
       5: invokevirtual #18                 // Method invoke:(Ljava/lang/reflect/Constructor;)Lkotlin/reflect/jvm/internal/impl/descriptors/runtime/structure/ReflectJavaConstructor;
       8: areturn

  static {};
    Code:
       0: new           #11                 // class kotlin/reflect/jvm/internal/impl/descriptors/runtime/structure/ReflectJavaClass$constructors$2
       3: dup
       4: invokespecial #17                 // Method "<init>":()V
       7: putstatic     #13                 // Field INSTANCE:Lkotlin/reflect/jvm/internal/impl/descriptors/runtime/structure/ReflectJavaClass$constructors$2;
      10: return
}
