Compiled from "ResourcePreconditionNotMetException.java"
final class software.amazon.awssdk.services.qldb.model.ResourcePreconditionNotMetException$BuilderImpl extends software.amazon.awssdk.services.qldb.model.QldbException$BuilderImpl implements software.amazon.awssdk.services.qldb.model.ResourcePreconditionNotMetException$Builder {
  private java.lang.String resourceType;

  private java.lang.String resourceName;

  private software.amazon.awssdk.services.qldb.model.ResourcePreconditionNotMetException$BuilderImpl();
    Code:
       0: aload_0
       1: invokespecial #5                  // Method software/amazon/awssdk/services/qldb/model/QldbException$BuilderImpl."<init>":()V
       4: return

  private software.amazon.awssdk.services.qldb.model.ResourcePreconditionNotMetException$BuilderImpl(software.amazon.awssdk.services.qldb.model.ResourcePreconditionNotMetException);
    Code:
       0: aload_0
       1: aload_1
       2: invokespecial #6                  // Method software/amazon/awssdk/services/qldb/model/QldbException$BuilderImpl."<init>":(Lsoftware/amazon/awssdk/services/qldb/model/QldbException;)V
       5: aload_0
       6: aload_1
       7: invokestatic  #7                  // Method software/amazon/awssdk/services/qldb/model/ResourcePreconditionNotMetException.access$400:(Lsoftware/amazon/awssdk/services/qldb/model/ResourcePreconditionNotMetException;)Ljava/lang/String;
      10: invokevirtual #8                  // Method resourceType:(Ljava/lang/String;)Lsoftware/amazon/awssdk/services/qldb/model/ResourcePreconditionNotMetException$Builder;
      13: pop
      14: aload_0
      15: aload_1
      16: invokestatic  #9                  // Method software/amazon/awssdk/services/qldb/model/ResourcePreconditionNotMetException.access$500:(Lsoftware/amazon/awssdk/services/qldb/model/ResourcePreconditionNotMetException;)Ljava/lang/String;
      19: invokevirtual #10                 // Method resourceName:(Ljava/lang/String;)Lsoftware/amazon/awssdk/services/qldb/model/ResourcePreconditionNotMetException$Builder;
      22: pop
      23: return

  public final java.lang.String getResourceType();
    Code:
       0: aload_0
       1: getfield      #4                  // Field resourceType:Ljava/lang/String;
       4: areturn

  public final software.amazon.awssdk.services.qldb.model.ResourcePreconditionNotMetException$Builder resourceType(java.lang.String);
    Code:
       0: aload_0
       1: aload_1
       2: putfield      #4                  // Field resourceType:Ljava/lang/String;
       5: aload_0
       6: areturn

  public final void setResourceType(java.lang.String);
    Code:
       0: aload_0
       1: aload_1
       2: putfield      #4                  // Field resourceType:Ljava/lang/String;
       5: return

  public final java.lang.String getResourceName();
    Code:
       0: aload_0
       1: getfield      #3                  // Field resourceName:Ljava/lang/String;
       4: areturn

  public final software.amazon.awssdk.services.qldb.model.ResourcePreconditionNotMetException$Builder resourceName(java.lang.String);
    Code:
       0: aload_0
       1: aload_1
       2: putfield      #3                  // Field resourceName:Ljava/lang/String;
       5: aload_0
       6: areturn

  public final void setResourceName(java.lang.String);
    Code:
       0: aload_0
       1: aload_1
       2: putfield      #3                  // Field resourceName:Ljava/lang/String;
       5: return

  public software.amazon.awssdk.services.qldb.model.ResourcePreconditionNotMetException$BuilderImpl awsErrorDetails(software.amazon.awssdk.awscore.exception.AwsErrorDetails);
    Code:
       0: aload_0
       1: aload_1
       2: putfield      #11                 // Field awsErrorDetails:Lsoftware/amazon/awssdk/awscore/exception/AwsErrorDetails;
       5: aload_0
       6: areturn

  public software.amazon.awssdk.services.qldb.model.ResourcePreconditionNotMetException$BuilderImpl message(java.lang.String);
    Code:
       0: aload_0
       1: aload_1
       2: putfield      #12                 // Field message:Ljava/lang/String;
       5: aload_0
       6: areturn

  public software.amazon.awssdk.services.qldb.model.ResourcePreconditionNotMetException$BuilderImpl requestId(java.lang.String);
    Code:
       0: aload_0
       1: aload_1
       2: putfield      #13                 // Field requestId:Ljava/lang/String;
       5: aload_0
       6: areturn

  public software.amazon.awssdk.services.qldb.model.ResourcePreconditionNotMetException$BuilderImpl statusCode(int);
    Code:
       0: aload_0
       1: iload_1
       2: putfield      #14                 // Field statusCode:I
       5: aload_0
       6: areturn

  public software.amazon.awssdk.services.qldb.model.ResourcePreconditionNotMetException$BuilderImpl cause(java.lang.Throwable);
    Code:
       0: aload_0
       1: aload_1
       2: putfield      #15                 // Field cause:Ljava/lang/Throwable;
       5: aload_0
       6: areturn

  public software.amazon.awssdk.services.qldb.model.ResourcePreconditionNotMetException build();
    Code:
       0: new           #16                 // class software/amazon/awssdk/services/qldb/model/ResourcePreconditionNotMetException
       3: dup
       4: aload_0
       5: aconst_null
       6: invokespecial #17                 // Method software/amazon/awssdk/services/qldb/model/ResourcePreconditionNotMetException."<init>":(Lsoftware/amazon/awssdk/services/qldb/model/ResourcePreconditionNotMetException$BuilderImpl;Lsoftware/amazon/awssdk/services/qldb/model/ResourcePreconditionNotMetException$1;)V
       9: areturn

  public java.util.List<software.amazon.awssdk.core.SdkField<?>> sdkFields();
    Code:
       0: invokestatic  #18                 // Method software/amazon/awssdk/services/qldb/model/ResourcePreconditionNotMetException.access$700:()Ljava/util/List;
       3: areturn

  public software.amazon.awssdk.services.qldb.model.QldbException build();
    Code:
       0: aload_0
       1: invokevirtual #19                 // Method build:()Lsoftware/amazon/awssdk/services/qldb/model/ResourcePreconditionNotMetException;
       4: areturn

  public software.amazon.awssdk.services.qldb.model.QldbException$BuilderImpl cause(java.lang.Throwable);
    Code:
       0: aload_0
       1: aload_1
       2: invokevirtual #20                 // Method cause:(Ljava/lang/Throwable;)Lsoftware/amazon/awssdk/services/qldb/model/ResourcePreconditionNotMetException$BuilderImpl;
       5: areturn

  public software.amazon.awssdk.services.qldb.model.QldbException$BuilderImpl statusCode(int);
    Code:
       0: aload_0
       1: iload_1
       2: invokevirtual #21                 // Method statusCode:(I)Lsoftware/amazon/awssdk/services/qldb/model/ResourcePreconditionNotMetException$BuilderImpl;
       5: areturn

  public software.amazon.awssdk.services.qldb.model.QldbException$BuilderImpl requestId(java.lang.String);
    Code:
       0: aload_0
       1: aload_1
       2: invokevirtual #22                 // Method requestId:(Ljava/lang/String;)Lsoftware/amazon/awssdk/services/qldb/model/ResourcePreconditionNotMetException$BuilderImpl;
       5: areturn

  public software.amazon.awssdk.services.qldb.model.QldbException$BuilderImpl message(java.lang.String);
    Code:
       0: aload_0
       1: aload_1
       2: invokevirtual #23                 // Method message:(Ljava/lang/String;)Lsoftware/amazon/awssdk/services/qldb/model/ResourcePreconditionNotMetException$BuilderImpl;
       5: areturn

  public software.amazon.awssdk.services.qldb.model.QldbException$BuilderImpl awsErrorDetails(software.amazon.awssdk.awscore.exception.AwsErrorDetails);
    Code:
       0: aload_0
       1: aload_1
       2: invokevirtual #24                 // Method awsErrorDetails:(Lsoftware/amazon/awssdk/awscore/exception/AwsErrorDetails;)Lsoftware/amazon/awssdk/services/qldb/model/ResourcePreconditionNotMetException$BuilderImpl;
       5: areturn

  public software.amazon.awssdk.services.qldb.model.QldbException$Builder cause(java.lang.Throwable);
    Code:
       0: aload_0
       1: aload_1
       2: invokevirtual #20                 // Method cause:(Ljava/lang/Throwable;)Lsoftware/amazon/awssdk/services/qldb/model/ResourcePreconditionNotMetException$BuilderImpl;
       5: areturn

  public software.amazon.awssdk.services.qldb.model.QldbException$Builder statusCode(int);
    Code:
       0: aload_0
       1: iload_1
       2: invokevirtual #21                 // Method statusCode:(I)Lsoftware/amazon/awssdk/services/qldb/model/ResourcePreconditionNotMetException$BuilderImpl;
       5: areturn

  public software.amazon.awssdk.services.qldb.model.QldbException$Builder requestId(java.lang.String);
    Code:
       0: aload_0
       1: aload_1
       2: invokevirtual #22                 // Method requestId:(Ljava/lang/String;)Lsoftware/amazon/awssdk/services/qldb/model/ResourcePreconditionNotMetException$BuilderImpl;
       5: areturn

  public software.amazon.awssdk.services.qldb.model.QldbException$Builder message(java.lang.String);
    Code:
       0: aload_0
       1: aload_1
       2: invokevirtual #23                 // Method message:(Ljava/lang/String;)Lsoftware/amazon/awssdk/services/qldb/model/ResourcePreconditionNotMetException$BuilderImpl;
       5: areturn

  public software.amazon.awssdk.services.qldb.model.QldbException$Builder awsErrorDetails(software.amazon.awssdk.awscore.exception.AwsErrorDetails);
    Code:
       0: aload_0
       1: aload_1
       2: invokevirtual #24                 // Method awsErrorDetails:(Lsoftware/amazon/awssdk/awscore/exception/AwsErrorDetails;)Lsoftware/amazon/awssdk/services/qldb/model/ResourcePreconditionNotMetException$BuilderImpl;
       5: areturn

  public software.amazon.awssdk.awscore.exception.AwsServiceException build();
    Code:
       0: aload_0
       1: invokevirtual #19                 // Method build:()Lsoftware/amazon/awssdk/services/qldb/model/ResourcePreconditionNotMetException;
       4: areturn

  public software.amazon.awssdk.awscore.exception.AwsServiceException$Builder statusCode(int);
    Code:
       0: aload_0
       1: iload_1
       2: invokevirtual #21                 // Method statusCode:(I)Lsoftware/amazon/awssdk/services/qldb/model/ResourcePreconditionNotMetException$BuilderImpl;
       5: areturn

  public software.amazon.awssdk.awscore.exception.AwsServiceException$Builder requestId(java.lang.String);
    Code:
       0: aload_0
       1: aload_1
       2: invokevirtual #22                 // Method requestId:(Ljava/lang/String;)Lsoftware/amazon/awssdk/services/qldb/model/ResourcePreconditionNotMetException$BuilderImpl;
       5: areturn

  public software.amazon.awssdk.awscore.exception.AwsServiceException$Builder cause(java.lang.Throwable);
    Code:
       0: aload_0
       1: aload_1
       2: invokevirtual #20                 // Method cause:(Ljava/lang/Throwable;)Lsoftware/amazon/awssdk/services/qldb/model/ResourcePreconditionNotMetException$BuilderImpl;
       5: areturn

  public software.amazon.awssdk.awscore.exception.AwsServiceException$Builder message(java.lang.String);
    Code:
       0: aload_0
       1: aload_1
       2: invokevirtual #23                 // Method message:(Ljava/lang/String;)Lsoftware/amazon/awssdk/services/qldb/model/ResourcePreconditionNotMetException$BuilderImpl;
       5: areturn

  public software.amazon.awssdk.awscore.exception.AwsServiceException$Builder awsErrorDetails(software.amazon.awssdk.awscore.exception.AwsErrorDetails);
    Code:
       0: aload_0
       1: aload_1
       2: invokevirtual #24                 // Method awsErrorDetails:(Lsoftware/amazon/awssdk/awscore/exception/AwsErrorDetails;)Lsoftware/amazon/awssdk/services/qldb/model/ResourcePreconditionNotMetException$BuilderImpl;
       5: areturn

  public software.amazon.awssdk.core.exception.SdkServiceException build();
    Code:
       0: aload_0
       1: invokevirtual #19                 // Method build:()Lsoftware/amazon/awssdk/services/qldb/model/ResourcePreconditionNotMetException;
       4: areturn

  public software.amazon.awssdk.core.exception.SdkServiceException$Builder statusCode(int);
    Code:
       0: aload_0
       1: iload_1
       2: invokevirtual #21                 // Method statusCode:(I)Lsoftware/amazon/awssdk/services/qldb/model/ResourcePreconditionNotMetException$BuilderImpl;
       5: areturn

  public software.amazon.awssdk.core.exception.SdkServiceException$Builder requestId(java.lang.String);
    Code:
       0: aload_0
       1: aload_1
       2: invokevirtual #22                 // Method requestId:(Ljava/lang/String;)Lsoftware/amazon/awssdk/services/qldb/model/ResourcePreconditionNotMetException$BuilderImpl;
       5: areturn

  public software.amazon.awssdk.core.exception.SdkServiceException$Builder cause(java.lang.Throwable);
    Code:
       0: aload_0
       1: aload_1
       2: invokevirtual #20                 // Method cause:(Ljava/lang/Throwable;)Lsoftware/amazon/awssdk/services/qldb/model/ResourcePreconditionNotMetException$BuilderImpl;
       5: areturn

  public software.amazon.awssdk.core.exception.SdkServiceException$Builder message(java.lang.String);
    Code:
       0: aload_0
       1: aload_1
       2: invokevirtual #23                 // Method message:(Ljava/lang/String;)Lsoftware/amazon/awssdk/services/qldb/model/ResourcePreconditionNotMetException$BuilderImpl;
       5: areturn

  public software.amazon.awssdk.core.exception.SdkException build();
    Code:
       0: aload_0
       1: invokevirtual #19                 // Method build:()Lsoftware/amazon/awssdk/services/qldb/model/ResourcePreconditionNotMetException;
       4: areturn

  public software.amazon.awssdk.core.exception.SdkException$Builder message(java.lang.String);
    Code:
       0: aload_0
       1: aload_1
       2: invokevirtual #23                 // Method message:(Ljava/lang/String;)Lsoftware/amazon/awssdk/services/qldb/model/ResourcePreconditionNotMetException$BuilderImpl;
       5: areturn

  public software.amazon.awssdk.core.exception.SdkException$Builder cause(java.lang.Throwable);
    Code:
       0: aload_0
       1: aload_1
       2: invokevirtual #20                 // Method cause:(Ljava/lang/Throwable;)Lsoftware/amazon/awssdk/services/qldb/model/ResourcePreconditionNotMetException$BuilderImpl;
       5: areturn

  public java.lang.Object build();
    Code:
       0: aload_0
       1: invokevirtual #19                 // Method build:()Lsoftware/amazon/awssdk/services/qldb/model/ResourcePreconditionNotMetException;
       4: areturn

  public software.amazon.awssdk.services.qldb.model.ResourcePreconditionNotMetException$Builder cause(java.lang.Throwable);
    Code:
       0: aload_0
       1: aload_1
       2: invokevirtual #20                 // Method cause:(Ljava/lang/Throwable;)Lsoftware/amazon/awssdk/services/qldb/model/ResourcePreconditionNotMetException$BuilderImpl;
       5: areturn

  public software.amazon.awssdk.services.qldb.model.ResourcePreconditionNotMetException$Builder statusCode(int);
    Code:
       0: aload_0
       1: iload_1
       2: invokevirtual #21                 // Method statusCode:(I)Lsoftware/amazon/awssdk/services/qldb/model/ResourcePreconditionNotMetException$BuilderImpl;
       5: areturn

  public software.amazon.awssdk.services.qldb.model.ResourcePreconditionNotMetException$Builder requestId(java.lang.String);
    Code:
       0: aload_0
       1: aload_1
       2: invokevirtual #22                 // Method requestId:(Ljava/lang/String;)Lsoftware/amazon/awssdk/services/qldb/model/ResourcePreconditionNotMetException$BuilderImpl;
       5: areturn

  public software.amazon.awssdk.services.qldb.model.ResourcePreconditionNotMetException$Builder message(java.lang.String);
    Code:
       0: aload_0
       1: aload_1
       2: invokevirtual #23                 // Method message:(Ljava/lang/String;)Lsoftware/amazon/awssdk/services/qldb/model/ResourcePreconditionNotMetException$BuilderImpl;
       5: areturn

  public software.amazon.awssdk.services.qldb.model.ResourcePreconditionNotMetException$Builder awsErrorDetails(software.amazon.awssdk.awscore.exception.AwsErrorDetails);
    Code:
       0: aload_0
       1: aload_1
       2: invokevirtual #24                 // Method awsErrorDetails:(Lsoftware/amazon/awssdk/awscore/exception/AwsErrorDetails;)Lsoftware/amazon/awssdk/services/qldb/model/ResourcePreconditionNotMetException$BuilderImpl;
       5: areturn

  static java.lang.String access$000(software.amazon.awssdk.services.qldb.model.ResourcePreconditionNotMetException$BuilderImpl);
    Code:
       0: aload_0
       1: getfield      #4                  // Field resourceType:Ljava/lang/String;
       4: areturn

  static java.lang.String access$100(software.amazon.awssdk.services.qldb.model.ResourcePreconditionNotMetException$BuilderImpl);
    Code:
       0: aload_0
       1: getfield      #3                  // Field resourceName:Ljava/lang/String;
       4: areturn

  software.amazon.awssdk.services.qldb.model.ResourcePreconditionNotMetException$BuilderImpl(software.amazon.awssdk.services.qldb.model.ResourcePreconditionNotMetException, software.amazon.awssdk.services.qldb.model.ResourcePreconditionNotMetException$1);
    Code:
       0: aload_0
       1: aload_1
       2: invokespecial #2                  // Method "<init>":(Lsoftware/amazon/awssdk/services/qldb/model/ResourcePreconditionNotMetException;)V
       5: return

  software.amazon.awssdk.services.qldb.model.ResourcePreconditionNotMetException$BuilderImpl(software.amazon.awssdk.services.qldb.model.ResourcePreconditionNotMetException$1);
    Code:
       0: aload_0
       1: invokespecial #1                  // Method "<init>":()V
       4: return
}
