Compiled from "AddToClusterNodeLabelsResponsePBImpl.java"
public class org.apache.hadoop.yarn.server.api.protocolrecords.impl.pb.AddToClusterNodeLabelsResponsePBImpl extends org.apache.hadoop.yarn.server.api.protocolrecords.AddToClusterNodeLabelsResponse {
  org.apache.hadoop.yarn.proto.YarnServerResourceManagerServiceProtos$AddToClusterNodeLabelsResponseProto proto;

  org.apache.hadoop.yarn.proto.YarnServerResourceManagerServiceProtos$AddToClusterNodeLabelsResponseProto$Builder builder;

  boolean viaProto;

  public org.apache.hadoop.yarn.server.api.protocolrecords.impl.pb.AddToClusterNodeLabelsResponsePBImpl();
    Code:
       0: aload_0
       1: invokespecial #1                  // Method org/apache/hadoop/yarn/server/api/protocolrecords/AddToClusterNodeLabelsResponse."<init>":()V
       4: aload_0
       5: invokestatic  #2                  // Method org/apache/hadoop/yarn/proto/YarnServerResourceManagerServiceProtos$AddToClusterNodeLabelsResponseProto.getDefaultInstance:()Lorg/apache/hadoop/yarn/proto/YarnServerResourceManagerServiceProtos$AddToClusterNodeLabelsResponseProto;
       8: putfield      #3                  // Field proto:Lorg/apache/hadoop/yarn/proto/YarnServerResourceManagerServiceProtos$AddToClusterNodeLabelsResponseProto;
      11: aload_0
      12: aconst_null
      13: putfield      #4                  // Field builder:Lorg/apache/hadoop/yarn/proto/YarnServerResourceManagerServiceProtos$AddToClusterNodeLabelsResponseProto$Builder;
      16: aload_0
      17: iconst_0
      18: putfield      #5                  // Field viaProto:Z
      21: aload_0
      22: invokestatic  #6                  // Method org/apache/hadoop/yarn/proto/YarnServerResourceManagerServiceProtos$AddToClusterNodeLabelsResponseProto.newBuilder:()Lorg/apache/hadoop/yarn/proto/YarnServerResourceManagerServiceProtos$AddToClusterNodeLabelsResponseProto$Builder;
      25: putfield      #4                  // Field builder:Lorg/apache/hadoop/yarn/proto/YarnServerResourceManagerServiceProtos$AddToClusterNodeLabelsResponseProto$Builder;
      28: return

  public org.apache.hadoop.yarn.server.api.protocolrecords.impl.pb.AddToClusterNodeLabelsResponsePBImpl(org.apache.hadoop.yarn.proto.YarnServerResourceManagerServiceProtos$AddToClusterNodeLabelsResponseProto);
    Code:
       0: aload_0
       1: invokespecial #1                  // Method org/apache/hadoop/yarn/server/api/protocolrecords/AddToClusterNodeLabelsResponse."<init>":()V
       4: aload_0
       5: invokestatic  #2                  // Method org/apache/hadoop/yarn/proto/YarnServerResourceManagerServiceProtos$AddToClusterNodeLabelsResponseProto.getDefaultInstance:()Lorg/apache/hadoop/yarn/proto/YarnServerResourceManagerServiceProtos$AddToClusterNodeLabelsResponseProto;
       8: putfield      #3                  // Field proto:Lorg/apache/hadoop/yarn/proto/YarnServerResourceManagerServiceProtos$AddToClusterNodeLabelsResponseProto;
      11: aload_0
      12: aconst_null
      13: putfield      #4                  // Field builder:Lorg/apache/hadoop/yarn/proto/YarnServerResourceManagerServiceProtos$AddToClusterNodeLabelsResponseProto$Builder;
      16: aload_0
      17: iconst_0
      18: putfield      #5                  // Field viaProto:Z
      21: aload_0
      22: aload_1
      23: putfield      #3                  // Field proto:Lorg/apache/hadoop/yarn/proto/YarnServerResourceManagerServiceProtos$AddToClusterNodeLabelsResponseProto;
      26: aload_0
      27: iconst_1
      28: putfield      #5                  // Field viaProto:Z
      31: return

  public org.apache.hadoop.yarn.proto.YarnServerResourceManagerServiceProtos$AddToClusterNodeLabelsResponseProto getProto();
    Code:
       0: aload_0
       1: aload_0
       2: getfield      #5                  // Field viaProto:Z
       5: ifeq          15
       8: aload_0
       9: getfield      #3                  // Field proto:Lorg/apache/hadoop/yarn/proto/YarnServerResourceManagerServiceProtos$AddToClusterNodeLabelsResponseProto;
      12: goto          22
      15: aload_0
      16: getfield      #4                  // Field builder:Lorg/apache/hadoop/yarn/proto/YarnServerResourceManagerServiceProtos$AddToClusterNodeLabelsResponseProto$Builder;
      19: invokevirtual #7                  // Method org/apache/hadoop/yarn/proto/YarnServerResourceManagerServiceProtos$AddToClusterNodeLabelsResponseProto$Builder.build:()Lorg/apache/hadoop/yarn/proto/YarnServerResourceManagerServiceProtos$AddToClusterNodeLabelsResponseProto;
      22: putfield      #3                  // Field proto:Lorg/apache/hadoop/yarn/proto/YarnServerResourceManagerServiceProtos$AddToClusterNodeLabelsResponseProto;
      25: aload_0
      26: iconst_1
      27: putfield      #5                  // Field viaProto:Z
      30: aload_0
      31: getfield      #3                  // Field proto:Lorg/apache/hadoop/yarn/proto/YarnServerResourceManagerServiceProtos$AddToClusterNodeLabelsResponseProto;
      34: areturn

  public int hashCode();
    Code:
       0: aload_0
       1: invokevirtual #8                  // Method getProto:()Lorg/apache/hadoop/yarn/proto/YarnServerResourceManagerServiceProtos$AddToClusterNodeLabelsResponseProto;
       4: invokevirtual #9                  // Method org/apache/hadoop/yarn/proto/YarnServerResourceManagerServiceProtos$AddToClusterNodeLabelsResponseProto.hashCode:()I
       7: ireturn

  public boolean equals(java.lang.Object);
    Code:
       0: aload_1
       1: ifnonnull     6
       4: iconst_0
       5: ireturn
       6: aload_1
       7: invokevirtual #10                 // Method java/lang/Object.getClass:()Ljava/lang/Class;
      10: aload_0
      11: invokevirtual #10                 // Method java/lang/Object.getClass:()Ljava/lang/Class;
      14: invokevirtual #11                 // Method java/lang/Class.isAssignableFrom:(Ljava/lang/Class;)Z
      17: ifeq          42
      20: aload_0
      21: invokevirtual #8                  // Method getProto:()Lorg/apache/hadoop/yarn/proto/YarnServerResourceManagerServiceProtos$AddToClusterNodeLabelsResponseProto;
      24: aload_0
      25: invokevirtual #10                 // Method java/lang/Object.getClass:()Ljava/lang/Class;
      28: aload_1
      29: invokevirtual #12                 // Method java/lang/Class.cast:(Ljava/lang/Object;)Ljava/lang/Object;
      32: checkcast     #13                 // class org/apache/hadoop/yarn/server/api/protocolrecords/impl/pb/AddToClusterNodeLabelsResponsePBImpl
      35: invokevirtual #8                  // Method getProto:()Lorg/apache/hadoop/yarn/proto/YarnServerResourceManagerServiceProtos$AddToClusterNodeLabelsResponseProto;
      38: invokevirtual #14                 // Method org/apache/hadoop/yarn/proto/YarnServerResourceManagerServiceProtos$AddToClusterNodeLabelsResponseProto.equals:(Ljava/lang/Object;)Z
      41: ireturn
      42: iconst_0
      43: ireturn

  public java.lang.String toString();
    Code:
       0: aload_0
       1: invokevirtual #8                  // Method getProto:()Lorg/apache/hadoop/yarn/proto/YarnServerResourceManagerServiceProtos$AddToClusterNodeLabelsResponseProto;
       4: invokestatic  #15                 // Method com/google/protobuf/TextFormat.shortDebugString:(Lcom/google/protobuf/MessageOrBuilder;)Ljava/lang/String;
       7: areturn
}
