Compiled from "AbstractResponse.java"
public class io.etcd.jetcd.AbstractResponse<R> implements io.etcd.jetcd.Response {
  private final R response;

  private final io.etcd.jetcd.api.ResponseHeader responseHeader;

  private final io.etcd.jetcd.Response$Header header;

  public io.etcd.jetcd.AbstractResponse(R, io.etcd.jetcd.api.ResponseHeader);
    Code:
       0: aload_0
       1: invokespecial #2                  // Method java/lang/Object."<init>":()V
       4: aload_0
       5: aload_1
       6: putfield      #3                  // Field response:Ljava/lang/Object;
       9: aload_0
      10: aload_2
      11: putfield      #1                  // Field responseHeader:Lio/etcd/jetcd/api/ResponseHeader;
      14: aload_0
      15: new           #4                  // class io/etcd/jetcd/AbstractResponse$HeaderImpl
      18: dup
      19: aload_0
      20: aconst_null
      21: invokespecial #5                  // Method io/etcd/jetcd/AbstractResponse$HeaderImpl."<init>":(Lio/etcd/jetcd/AbstractResponse;Lio/etcd/jetcd/AbstractResponse$1;)V
      24: putfield      #6                  // Field header:Lio/etcd/jetcd/Response$Header;
      27: return

  public io.etcd.jetcd.Response$Header getHeader();
    Code:
       0: aload_0
       1: getfield      #6                  // Field header:Lio/etcd/jetcd/Response$Header;
       4: areturn

  public java.lang.String toString();
    Code:
       0: aload_0
       1: getfield      #3                  // Field response:Ljava/lang/Object;
       4: invokevirtual #7                  // Method java/lang/Object.toString:()Ljava/lang/String;
       7: areturn

  protected final R getResponse();
    Code:
       0: aload_0
       1: getfield      #3                  // Field response:Ljava/lang/Object;
       4: areturn

  protected final io.etcd.jetcd.api.ResponseHeader getResponseHeader();
    Code:
       0: aload_0
       1: getfield      #1                  // Field responseHeader:Lio/etcd/jetcd/api/ResponseHeader;
       4: areturn

  static io.etcd.jetcd.api.ResponseHeader access$100(io.etcd.jetcd.AbstractResponse);
    Code:
       0: aload_0
       1: getfield      #1                  // Field responseHeader:Lio/etcd/jetcd/api/ResponseHeader;
       4: areturn
}
