Compiled from "ExtendedInfoSizes.kt"
public final class org.rsmod.plugins.info.player.model.ExtendedInfoSizes {
  public static final org.rsmod.plugins.info.player.model.ExtendedInfoSizes INSTANCE;

  private static final int USERNAME_MAX_BYTE_LENGTH;

  private static final int MAX_HIT_COUNT;

  private static final int PER_HIT_BYTE_LENGTH;

  private static final int APPEARANCE_LOOK_MAX_BYTE_LENGTH;

  private static final int APPEARANCE_COLORS_MAX_BYTE_LENGTH;

  private static final int APPEARANCE_BAS_MAX_BYTE_LENGTH;

  private static final int APPEARANCE_TAG_MAX_BYTE_LENGTH;

  private static final int COMPRESSED_CHAT_MAX_BYTE_LENGTH;

  public static final int TEMP_MOVE_BYTE_SIZE;

  public static final int PERM_MOVE_BYTE_SIZE;

  public static final int FACE_DIRECTION_BYTE_SIZE;

  public static final int FACE_TARGET_BYTE_SIZE;

  public static final int ANIM_BYTE_SIZE;

  public static final int GFX_BYTE_SIZE;

  public static final int TINTING_BYTE_SIZE;

  public static final int EXACT_MOVE_BYTE_SIZE;

  public static final int APPEARANCE_MAX_BYTE_SIZE;

  public static final int NAME_PREFIX_BYTE_SIZE;

  public static final int CHAT_MAX_BYTE_SIZE;

  public static final int SAY_BYTE_SIZE;

  public static final int HIT_BYTE_SIZE;

  public static final int TOTAL_BYTE_SIZE;

  private org.rsmod.plugins.info.player.model.ExtendedInfoSizes();
    Code:
       0: aload_0
       1: invokespecial #8                  // Method java/lang/Object."<init>":()V
       4: return

  static {};
    Code:
       0: new           #2                  // class org/rsmod/plugins/info/player/model/ExtendedInfoSizes
       3: dup
       4: invokespecial #12                 // Method "<init>":()V
       7: putstatic     #15                 // Field INSTANCE:Lorg/rsmod/plugins/info/player/model/ExtendedInfoSizes;
      10: return
}
