Compiled from "AbstractNestedCondition.java"
class org.springframework.boot.autoconfigure.condition.AbstractNestedCondition$MemberOutcomes {
  private final org.springframework.context.annotation.ConditionContext context;

  private final org.springframework.core.type.AnnotationMetadata metadata;

  private final java.util.List<org.springframework.boot.autoconfigure.condition.ConditionOutcome> outcomes;

  org.springframework.boot.autoconfigure.condition.AbstractNestedCondition$MemberOutcomes(org.springframework.context.annotation.ConditionContext, org.springframework.core.type.AnnotationMetadata, java.util.List<org.springframework.context.annotation.Condition>);
    Code:
       0: aload_0
       1: invokespecial #1                  // Method java/lang/Object."<init>":()V
       4: aload_0
       5: aload_1
       6: putfield      #2                  // Field context:Lorg/springframework/context/annotation/ConditionContext;
       9: aload_0
      10: aload_2
      11: putfield      #3                  // Field metadata:Lorg/springframework/core/type/AnnotationMetadata;
      14: aload_0
      15: new           #4                  // class java/util/ArrayList
      18: dup
      19: aload_3
      20: invokeinterface #5,  1            // InterfaceMethod java/util/List.size:()I
      25: invokespecial #6                  // Method java/util/ArrayList."<init>":(I)V
      28: putfield      #7                  // Field outcomes:Ljava/util/List;
      31: aload_3
      32: invokeinterface #8,  1            // InterfaceMethod java/util/List.iterator:()Ljava/util/Iterator;
      37: astore        4
      39: aload         4
      41: invokeinterface #9,  1            // InterfaceMethod java/util/Iterator.hasNext:()Z
      46: ifeq          81
      49: aload         4
      51: invokeinterface #10,  1           // InterfaceMethod java/util/Iterator.next:()Ljava/lang/Object;
      56: checkcast     #11                 // class org/springframework/context/annotation/Condition
      59: astore        5
      61: aload_0
      62: getfield      #7                  // Field outcomes:Ljava/util/List;
      65: aload_0
      66: aload_2
      67: aload         5
      69: invokespecial #12                 // Method getConditionOutcome:(Lorg/springframework/core/type/AnnotationMetadata;Lorg/springframework/context/annotation/Condition;)Lorg/springframework/boot/autoconfigure/condition/ConditionOutcome;
      72: invokeinterface #13,  2           // InterfaceMethod java/util/List.add:(Ljava/lang/Object;)Z
      77: pop
      78: goto          39
      81: return

  private org.springframework.boot.autoconfigure.condition.ConditionOutcome getConditionOutcome(org.springframework.core.type.AnnotationMetadata, org.springframework.context.annotation.Condition);
    Code:
       0: aload_2
       1: instanceof    #14                 // class org/springframework/boot/autoconfigure/condition/SpringBootCondition
       4: ifeq          20
       7: aload_2
       8: checkcast     #14                 // class org/springframework/boot/autoconfigure/condition/SpringBootCondition
      11: aload_0
      12: getfield      #2                  // Field context:Lorg/springframework/context/annotation/ConditionContext;
      15: aload_1
      16: invokevirtual #15                 // Method org/springframework/boot/autoconfigure/condition/SpringBootCondition.getMatchOutcome:(Lorg/springframework/context/annotation/ConditionContext;Lorg/springframework/core/type/AnnotatedTypeMetadata;)Lorg/springframework/boot/autoconfigure/condition/ConditionOutcome;
      19: areturn
      20: new           #16                 // class org/springframework/boot/autoconfigure/condition/ConditionOutcome
      23: dup
      24: aload_2
      25: aload_0
      26: getfield      #2                  // Field context:Lorg/springframework/context/annotation/ConditionContext;
      29: aload_1
      30: invokeinterface #17,  3           // InterfaceMethod org/springframework/context/annotation/Condition.matches:(Lorg/springframework/context/annotation/ConditionContext;Lorg/springframework/core/type/AnnotatedTypeMetadata;)Z
      35: aconst_null
      36: checkcast     #18                 // class org/springframework/boot/autoconfigure/condition/ConditionMessage
      39: invokespecial #19                 // Method org/springframework/boot/autoconfigure/condition/ConditionOutcome."<init>":(ZLorg/springframework/boot/autoconfigure/condition/ConditionMessage;)V
      42: areturn

  public org.springframework.boot.autoconfigure.condition.ConditionOutcome getUltimateOutcome();
    Code:
       0: new           #20                 // class java/lang/StringBuilder
       3: dup
       4: invokespecial #21                 // Method java/lang/StringBuilder."<init>":()V
       7: ldc           #22                 // String NestedCondition on
       9: invokevirtual #23                 // Method java/lang/StringBuilder.append:(Ljava/lang/String;)Ljava/lang/StringBuilder;
      12: aload_0
      13: getfield      #3                  // Field metadata:Lorg/springframework/core/type/AnnotationMetadata;
      16: invokeinterface #24,  1           // InterfaceMethod org/springframework/core/type/AnnotationMetadata.getClassName:()Ljava/lang/String;
      21: invokestatic  #25                 // Method org/springframework/util/ClassUtils.getShortName:(Ljava/lang/String;)Ljava/lang/String;
      24: invokevirtual #23                 // Method java/lang/StringBuilder.append:(Ljava/lang/String;)Ljava/lang/StringBuilder;
      27: invokevirtual #26                 // Method java/lang/StringBuilder.toString:()Ljava/lang/String;
      30: iconst_0
      31: anewarray     #27                 // class java/lang/Object
      34: invokestatic  #28                 // Method org/springframework/boot/autoconfigure/condition/ConditionMessage.forCondition:(Ljava/lang/String;[Ljava/lang/Object;)Lorg/springframework/boot/autoconfigure/condition/ConditionMessage$Builder;
      37: astore_1
      38: aload_0
      39: getfield      #7                  // Field outcomes:Ljava/util/List;
      42: invokeinterface #5,  1            // InterfaceMethod java/util/List.size:()I
      47: iconst_1
      48: if_icmpne     85
      51: aload_0
      52: getfield      #7                  // Field outcomes:Ljava/util/List;
      55: iconst_0
      56: invokeinterface #29,  2           // InterfaceMethod java/util/List.get:(I)Ljava/lang/Object;
      61: checkcast     #16                 // class org/springframework/boot/autoconfigure/condition/ConditionOutcome
      64: astore_2
      65: new           #16                 // class org/springframework/boot/autoconfigure/condition/ConditionOutcome
      68: dup
      69: aload_2
      70: invokevirtual #30                 // Method org/springframework/boot/autoconfigure/condition/ConditionOutcome.isMatch:()Z
      73: aload_1
      74: aload_2
      75: invokevirtual #31                 // Method org/springframework/boot/autoconfigure/condition/ConditionOutcome.getMessage:()Ljava/lang/String;
      78: invokevirtual #32                 // Method org/springframework/boot/autoconfigure/condition/ConditionMessage$Builder.because:(Ljava/lang/String;)Lorg/springframework/boot/autoconfigure/condition/ConditionMessage;
      81: invokespecial #19                 // Method org/springframework/boot/autoconfigure/condition/ConditionOutcome."<init>":(ZLorg/springframework/boot/autoconfigure/condition/ConditionMessage;)V
      84: areturn
      85: new           #4                  // class java/util/ArrayList
      88: dup
      89: invokespecial #33                 // Method java/util/ArrayList."<init>":()V
      92: astore_2
      93: new           #4                  // class java/util/ArrayList
      96: dup
      97: invokespecial #33                 // Method java/util/ArrayList."<init>":()V
     100: astore_3
     101: aload_0
     102: getfield      #7                  // Field outcomes:Ljava/util/List;
     105: invokeinterface #8,  1            // InterfaceMethod java/util/List.iterator:()Ljava/util/Iterator;
     110: astore        4
     112: aload         4
     114: invokeinterface #9,  1            // InterfaceMethod java/util/Iterator.hasNext:()Z
     119: ifeq          158
     122: aload         4
     124: invokeinterface #10,  1           // InterfaceMethod java/util/Iterator.next:()Ljava/lang/Object;
     129: checkcast     #16                 // class org/springframework/boot/autoconfigure/condition/ConditionOutcome
     132: astore        5
     134: aload         5
     136: invokevirtual #30                 // Method org/springframework/boot/autoconfigure/condition/ConditionOutcome.isMatch:()Z
     139: ifeq          146
     142: aload_2
     143: goto          147
     146: aload_3
     147: aload         5
     149: invokeinterface #13,  2           // InterfaceMethod java/util/List.add:(Ljava/lang/Object;)Z
     154: pop
     155: goto          112
     158: aload_3
     159: invokeinterface #34,  1           // InterfaceMethod java/util/List.isEmpty:()Z
     164: ifeq          181
     167: aload_1
     168: ldc           #35                 // String matching nested conditions
     170: invokevirtual #36                 // Method org/springframework/boot/autoconfigure/condition/ConditionMessage$Builder.found:(Ljava/lang/String;)Lorg/springframework/boot/autoconfigure/condition/ConditionMessage$ItemsBuilder;
     173: aload_2
     174: invokevirtual #37                 // Method org/springframework/boot/autoconfigure/condition/ConditionMessage$ItemsBuilder.items:(Ljava/util/Collection;)Lorg/springframework/boot/autoconfigure/condition/ConditionMessage;
     177: invokestatic  #38                 // Method org/springframework/boot/autoconfigure/condition/ConditionOutcome.match:(Lorg/springframework/boot/autoconfigure/condition/ConditionMessage;)Lorg/springframework/boot/autoconfigure/condition/ConditionOutcome;
     180: areturn
     181: aload_1
     182: ldc           #39                 // String non-matching nested conditions
     184: invokevirtual #36                 // Method org/springframework/boot/autoconfigure/condition/ConditionMessage$Builder.found:(Ljava/lang/String;)Lorg/springframework/boot/autoconfigure/condition/ConditionMessage$ItemsBuilder;
     187: aload_3
     188: invokevirtual #37                 // Method org/springframework/boot/autoconfigure/condition/ConditionMessage$ItemsBuilder.items:(Ljava/util/Collection;)Lorg/springframework/boot/autoconfigure/condition/ConditionMessage;
     191: invokestatic  #40                 // Method org/springframework/boot/autoconfigure/condition/ConditionOutcome.noMatch:(Lorg/springframework/boot/autoconfigure/condition/ConditionMessage;)Lorg/springframework/boot/autoconfigure/condition/ConditionOutcome;
     194: areturn
}
