Compiled from "SystemDir.java"
public class org.reflections.vfs.SystemDir implements org.reflections.vfs.Vfs$Dir {
  private final java.io.File file;

  public org.reflections.vfs.SystemDir(java.io.File);
    Code:
       0: aload_0
       1: invokespecial #3                  // Method java/lang/Object."<init>":()V
       4: aload_1
       5: ifnull        49
       8: aload_1
       9: invokevirtual #4                  // Method java/io/File.isDirectory:()Z
      12: ifeq          22
      15: aload_1
      16: invokevirtual #5                  // Method java/io/File.canRead:()Z
      19: ifne          49
      22: new           #6                  // class java/lang/RuntimeException
      25: dup
      26: new           #7                  // class java/lang/StringBuilder
      29: dup
      30: invokespecial #8                  // Method java/lang/StringBuilder."<init>":()V
      33: ldc           #9                  // String cannot use dir
      35: invokevirtual #10                 // Method java/lang/StringBuilder.append:(Ljava/lang/String;)Ljava/lang/StringBuilder;
      38: aload_1
      39: invokevirtual #11                 // Method java/lang/StringBuilder.append:(Ljava/lang/Object;)Ljava/lang/StringBuilder;
      42: invokevirtual #12                 // Method java/lang/StringBuilder.toString:()Ljava/lang/String;
      45: invokespecial #13                 // Method java/lang/RuntimeException."<init>":(Ljava/lang/String;)V
      48: athrow
      49: aload_0
      50: aload_1
      51: putfield      #2                  // Field file:Ljava/io/File;
      54: return

  public java.lang.String getPath();
    Code:
       0: aload_0
       1: getfield      #2                  // Field file:Ljava/io/File;
       4: ifnonnull     10
       7: ldc           #14                 // String /NO-SUCH-DIRECTORY/
       9: areturn
      10: aload_0
      11: getfield      #2                  // Field file:Ljava/io/File;
      14: invokevirtual #15                 // Method java/io/File.getPath:()Ljava/lang/String;
      17: ldc           #16                 // String \\
      19: ldc           #17                 // String /
      21: invokevirtual #18                 // Method java/lang/String.replace:(Ljava/lang/CharSequence;Ljava/lang/CharSequence;)Ljava/lang/String;
      24: areturn

  public java.lang.Iterable<org.reflections.vfs.Vfs$File> getFiles();
    Code:
       0: aload_0
       1: getfield      #2                  // Field file:Ljava/io/File;
       4: ifnull        17
       7: aload_0
       8: getfield      #2                  // Field file:Ljava/io/File;
      11: invokevirtual #19                 // Method java/io/File.exists:()Z
      14: ifne          21
      17: invokestatic  #20                 // Method java/util/Collections.emptyList:()Ljava/util/List;
      20: areturn
      21: new           #21                 // class org/reflections/vfs/SystemDir$1
      24: dup
      25: aload_0
      26: invokespecial #22                 // Method org/reflections/vfs/SystemDir$1."<init>":(Lorg/reflections/vfs/SystemDir;)V
      29: areturn

  private static java.util.List<java.io.File> listFiles(java.io.File);
    Code:
       0: aload_0
       1: invokevirtual #23                 // Method java/io/File.listFiles:()[Ljava/io/File;
       4: astore_1
       5: aload_1
       6: ifnull        14
       9: aload_1
      10: invokestatic  #24                 // Method com/google/common/collect/Lists.newArrayList:([Ljava/lang/Object;)Ljava/util/ArrayList;
      13: areturn
      14: invokestatic  #25                 // Method com/google/common/collect/Lists.newArrayList:()Ljava/util/ArrayList;
      17: areturn

  public void close();
    Code:
       0: return

  public java.lang.String toString();
    Code:
       0: aload_0
       1: invokevirtual #26                 // Method getPath:()Ljava/lang/String;
       4: areturn

  static java.io.File access$000(org.reflections.vfs.SystemDir);
    Code:
       0: aload_0
       1: getfield      #2                  // Field file:Ljava/io/File;
       4: areturn

  static java.util.List access$100(java.io.File);
    Code:
       0: aload_0
       1: invokestatic  #1                  // Method listFiles:(Ljava/io/File;)Ljava/util/List;
       4: areturn
}
