Compiled from "Vfs.java"
final class org.reflections.vfs.Vfs$DefaultUrlTypes$7 extends org.reflections.vfs.Vfs$DefaultUrlTypes {
  org.reflections.vfs.Vfs$DefaultUrlTypes$7(java.lang.String, int);
    Code:
       0: aload_0
       1: aload_1
       2: iload_2
       3: aconst_null
       4: invokespecial #1                  // Method org/reflections/vfs/Vfs$DefaultUrlTypes."<init>":(Ljava/lang/String;ILorg/reflections/vfs/Vfs$1;)V
       7: return

  public boolean matches(java.net.URL) throws java.lang.Exception;
    Code:
       0: aload_1
       1: invokevirtual #2                  // Method java/net/URL.toExternalForm:()Ljava/lang/String;
       4: ldc           #3                  // String .jar
       6: invokevirtual #4                  // Method java/lang/String.contains:(Ljava/lang/CharSequence;)Z
       9: ireturn

  public org.reflections.vfs.Vfs$Dir createDir(java.net.URL) throws java.lang.Exception;
    Code:
       0: new           #5                  // class org/reflections/vfs/JarInputDir
       3: dup
       4: aload_1
       5: invokespecial #6                  // Method org/reflections/vfs/JarInputDir."<init>":(Ljava/net/URL;)V
       8: areturn
}
