Compiled from "AuditMessage.java"
public class co.cask.cdap.proto.audit.AuditMessage {
  private final int version;

  private final long time;

  private final co.cask.cdap.proto.id.EntityId entityId;

  private final java.lang.String user;

  private final co.cask.cdap.proto.audit.AuditType type;

  private final co.cask.cdap.proto.audit.AuditPayload payload;

  public co.cask.cdap.proto.audit.AuditMessage(long, co.cask.cdap.proto.id.EntityId, java.lang.String, co.cask.cdap.proto.audit.AuditType, co.cask.cdap.proto.audit.AuditPayload);
    Code:
       0: aload_0
       1: invokespecial #1                  // Method java/lang/Object."<init>":()V
       4: aload_0
       5: iconst_1
       6: putfield      #2                  // Field version:I
       9: aload_0
      10: lload_1
      11: putfield      #3                  // Field time:J
      14: aload_0
      15: aload_3
      16: putfield      #4                  // Field entityId:Lco/cask/cdap/proto/id/EntityId;
      19: aload_0
      20: aload         4
      22: putfield      #5                  // Field user:Ljava/lang/String;
      25: aload_0
      26: aload         5
      28: putfield      #6                  // Field type:Lco/cask/cdap/proto/audit/AuditType;
      31: aload_0
      32: aload         6
      34: putfield      #7                  // Field payload:Lco/cask/cdap/proto/audit/AuditPayload;
      37: return

  public int getVersion();
    Code:
       0: iconst_1
       1: ireturn

  public long getTime();
    Code:
       0: aload_0
       1: getfield      #3                  // Field time:J
       4: lreturn

  public co.cask.cdap.proto.id.EntityId getEntityId();
    Code:
       0: aload_0
       1: getfield      #4                  // Field entityId:Lco/cask/cdap/proto/id/EntityId;
       4: areturn

  public java.lang.String getUser();
    Code:
       0: aload_0
       1: getfield      #5                  // Field user:Ljava/lang/String;
       4: areturn

  public co.cask.cdap.proto.audit.AuditType getType();
    Code:
       0: aload_0
       1: getfield      #6                  // Field type:Lco/cask/cdap/proto/audit/AuditType;
       4: areturn

  public co.cask.cdap.proto.audit.AuditPayload getPayload();
    Code:
       0: aload_0
       1: getfield      #7                  // Field payload:Lco/cask/cdap/proto/audit/AuditPayload;
       4: areturn

  public boolean equals(java.lang.Object);
    Code:
       0: aload_0
       1: aload_1
       2: if_acmpne     7
       5: iconst_1
       6: ireturn
       7: aload_1
       8: instanceof    #8                  // class co/cask/cdap/proto/audit/AuditMessage
      11: ifne          16
      14: iconst_0
      15: ireturn
      16: aload_1
      17: checkcast     #8                  // class co/cask/cdap/proto/audit/AuditMessage
      20: astore_2
      21: iconst_1
      22: invokestatic  #9                  // Method java/lang/Integer.valueOf:(I)Ljava/lang/Integer;
      25: aload_2
      26: invokevirtual #10                 // Method java/lang/Object.getClass:()Ljava/lang/Class;
      29: pop
      30: iconst_1
      31: invokestatic  #9                  // Method java/lang/Integer.valueOf:(I)Ljava/lang/Integer;
      34: invokestatic  #11                 // Method java/util/Objects.equals:(Ljava/lang/Object;Ljava/lang/Object;)Z
      37: ifeq          120
      40: aload_0
      41: getfield      #3                  // Field time:J
      44: invokestatic  #12                 // Method java/lang/Long.valueOf:(J)Ljava/lang/Long;
      47: aload_2
      48: getfield      #3                  // Field time:J
      51: invokestatic  #12                 // Method java/lang/Long.valueOf:(J)Ljava/lang/Long;
      54: invokestatic  #11                 // Method java/util/Objects.equals:(Ljava/lang/Object;Ljava/lang/Object;)Z
      57: ifeq          120
      60: aload_0
      61: getfield      #4                  // Field entityId:Lco/cask/cdap/proto/id/EntityId;
      64: aload_2
      65: getfield      #4                  // Field entityId:Lco/cask/cdap/proto/id/EntityId;
      68: invokestatic  #11                 // Method java/util/Objects.equals:(Ljava/lang/Object;Ljava/lang/Object;)Z
      71: ifeq          120
      74: aload_0
      75: getfield      #5                  // Field user:Ljava/lang/String;
      78: aload_2
      79: getfield      #5                  // Field user:Ljava/lang/String;
      82: invokestatic  #11                 // Method java/util/Objects.equals:(Ljava/lang/Object;Ljava/lang/Object;)Z
      85: ifeq          120
      88: aload_0
      89: getfield      #6                  // Field type:Lco/cask/cdap/proto/audit/AuditType;
      92: aload_2
      93: getfield      #6                  // Field type:Lco/cask/cdap/proto/audit/AuditType;
      96: invokestatic  #11                 // Method java/util/Objects.equals:(Ljava/lang/Object;Ljava/lang/Object;)Z
      99: ifeq          120
     102: aload_0
     103: getfield      #7                  // Field payload:Lco/cask/cdap/proto/audit/AuditPayload;
     106: aload_2
     107: getfield      #7                  // Field payload:Lco/cask/cdap/proto/audit/AuditPayload;
     110: invokestatic  #11                 // Method java/util/Objects.equals:(Ljava/lang/Object;Ljava/lang/Object;)Z
     113: ifeq          120
     116: iconst_1
     117: goto          121
     120: iconst_0
     121: ireturn

  public int hashCode();
    Code:
       0: bipush        6
       2: anewarray     #13                 // class java/lang/Object
       5: dup
       6: iconst_0
       7: iconst_1
       8: invokestatic  #9                  // Method java/lang/Integer.valueOf:(I)Ljava/lang/Integer;
      11: aastore
      12: dup
      13: iconst_1
      14: aload_0
      15: getfield      #3                  // Field time:J
      18: invokestatic  #12                 // Method java/lang/Long.valueOf:(J)Ljava/lang/Long;
      21: aastore
      22: dup
      23: iconst_2
      24: aload_0
      25: getfield      #4                  // Field entityId:Lco/cask/cdap/proto/id/EntityId;
      28: aastore
      29: dup
      30: iconst_3
      31: aload_0
      32: getfield      #5                  // Field user:Ljava/lang/String;
      35: aastore
      36: dup
      37: iconst_4
      38: aload_0
      39: getfield      #6                  // Field type:Lco/cask/cdap/proto/audit/AuditType;
      42: aastore
      43: dup
      44: iconst_5
      45: aload_0
      46: getfield      #7                  // Field payload:Lco/cask/cdap/proto/audit/AuditPayload;
      49: aastore
      50: invokestatic  #14                 // Method java/util/Objects.hash:([Ljava/lang/Object;)I
      53: ireturn

  public java.lang.String toString();
    Code:
       0: new           #15                 // class java/lang/StringBuilder
       3: dup
       4: invokespecial #16                 // Method java/lang/StringBuilder."<init>":()V
       7: ldc           #17                 // String AuditMessage{version=1, time=
       9: invokevirtual #18                 // Method java/lang/StringBuilder.append:(Ljava/lang/String;)Ljava/lang/StringBuilder;
      12: aload_0
      13: getfield      #3                  // Field time:J
      16: invokevirtual #19                 // Method java/lang/StringBuilder.append:(J)Ljava/lang/StringBuilder;
      19: ldc           #20                 // String , entityId=
      21: invokevirtual #18                 // Method java/lang/StringBuilder.append:(Ljava/lang/String;)Ljava/lang/StringBuilder;
      24: aload_0
      25: getfield      #4                  // Field entityId:Lco/cask/cdap/proto/id/EntityId;
      28: invokevirtual #21                 // Method java/lang/StringBuilder.append:(Ljava/lang/Object;)Ljava/lang/StringBuilder;
      31: ldc           #22                 // String , user=\'
      33: invokevirtual #18                 // Method java/lang/StringBuilder.append:(Ljava/lang/String;)Ljava/lang/StringBuilder;
      36: aload_0
      37: getfield      #5                  // Field user:Ljava/lang/String;
      40: invokevirtual #18                 // Method java/lang/StringBuilder.append:(Ljava/lang/String;)Ljava/lang/StringBuilder;
      43: bipush        39
      45: invokevirtual #23                 // Method java/lang/StringBuilder.append:(C)Ljava/lang/StringBuilder;
      48: ldc           #24                 // String , type=
      50: invokevirtual #18                 // Method java/lang/StringBuilder.append:(Ljava/lang/String;)Ljava/lang/StringBuilder;
      53: aload_0
      54: getfield      #6                  // Field type:Lco/cask/cdap/proto/audit/AuditType;
      57: invokevirtual #21                 // Method java/lang/StringBuilder.append:(Ljava/lang/Object;)Ljava/lang/StringBuilder;
      60: ldc           #25                 // String , payload=
      62: invokevirtual #18                 // Method java/lang/StringBuilder.append:(Ljava/lang/String;)Ljava/lang/StringBuilder;
      65: aload_0
      66: getfield      #7                  // Field payload:Lco/cask/cdap/proto/audit/AuditPayload;
      69: invokevirtual #21                 // Method java/lang/StringBuilder.append:(Ljava/lang/Object;)Ljava/lang/StringBuilder;
      72: bipush        125
      74: invokevirtual #23                 // Method java/lang/StringBuilder.append:(C)Ljava/lang/StringBuilder;
      77: invokevirtual #26                 // Method java/lang/StringBuilder.toString:()Ljava/lang/String;
      80: areturn
}
