Compiled from "DiskStorageFactory.java"
final class net.sf.ehcache.store.disk.DiskStorageFactory$Placeholder extends net.sf.ehcache.store.disk.DiskStorageFactory$DiskSubstitute {
  private final java.lang.Object key;

  private final net.sf.ehcache.Element element;

  private volatile boolean failedToFlush;

  final net.sf.ehcache.store.disk.DiskStorageFactory this$0;

  net.sf.ehcache.store.disk.DiskStorageFactory$Placeholder(net.sf.ehcache.store.disk.DiskStorageFactory, net.sf.ehcache.Element);
    Code:
       0: aload_0
       1: aload_1
       2: putfield      #3                  // Field this$0:Lnet/sf/ehcache/store/disk/DiskStorageFactory;
       5: aload_0
       6: aload_1
       7: invokespecial #4                  // Method net/sf/ehcache/store/disk/DiskStorageFactory$DiskSubstitute."<init>":(Lnet/sf/ehcache/store/disk/DiskStorageFactory;)V
      10: aload_0
      11: aload_2
      12: invokevirtual #5                  // Method net/sf/ehcache/Element.getObjectKey:()Ljava/lang/Object;
      15: putfield      #6                  // Field key:Ljava/lang/Object;
      18: aload_0
      19: aload_2
      20: putfield      #7                  // Field element:Lnet/sf/ehcache/Element;
      23: return

  boolean hasFailedToFlush();
    Code:
       0: aload_0
       1: getfield      #1                  // Field failedToFlush:Z
       4: ireturn

  private void setFailedToFlush(boolean);
    Code:
       0: aload_0
       1: iload_1
       2: putfield      #1                  // Field failedToFlush:Z
       5: return

  public void installed();
    Code:
       0: aload_0
       1: getfield      #3                  // Field this$0:Lnet/sf/ehcache/store/disk/DiskStorageFactory;
       4: new           #8                  // class net/sf/ehcache/store/disk/DiskStorageFactory$PersistentDiskWriteTask
       7: dup
       8: aload_0
       9: getfield      #3                  // Field this$0:Lnet/sf/ehcache/store/disk/DiskStorageFactory;
      12: aload_0
      13: invokespecial #9                  // Method net/sf/ehcache/store/disk/DiskStorageFactory$PersistentDiskWriteTask."<init>":(Lnet/sf/ehcache/store/disk/DiskStorageFactory;Lnet/sf/ehcache/store/disk/DiskStorageFactory$Placeholder;)V
      16: invokevirtual #10                 // Method net/sf/ehcache/store/disk/DiskStorageFactory.schedule:(Ljava/util/concurrent/Callable;)Ljava/util/concurrent/Future;
      19: pop
      20: return

  java.lang.Object getKey();
    Code:
       0: aload_0
       1: getfield      #6                  // Field key:Ljava/lang/Object;
       4: areturn

  long getHitCount();
    Code:
       0: aload_0
       1: invokevirtual #11                 // Method getElement:()Lnet/sf/ehcache/Element;
       4: invokevirtual #12                 // Method net/sf/ehcache/Element.getHitCount:()J
       7: lreturn

  long getExpirationTime();
    Code:
       0: aload_0
       1: invokevirtual #11                 // Method getElement:()Lnet/sf/ehcache/Element;
       4: invokevirtual #13                 // Method net/sf/ehcache/Element.getExpirationTime:()J
       7: lreturn

  net.sf.ehcache.Element getElement();
    Code:
       0: aload_0
       1: getfield      #7                  // Field element:Lnet/sf/ehcache/Element;
       4: areturn

  static void access$700(net.sf.ehcache.store.disk.DiskStorageFactory$Placeholder, boolean);
    Code:
       0: aload_0
       1: iload_1
       2: invokespecial #2                  // Method setFailedToFlush:(Z)V
       5: return

  static boolean access$1000(net.sf.ehcache.store.disk.DiskStorageFactory$Placeholder);
    Code:
       0: aload_0
       1: getfield      #1                  // Field failedToFlush:Z
       4: ireturn
}
