Compiled from "FixedAuthoritiesExtractor.java"
public class org.springframework.boot.autoconfigure.security.oauth2.resource.FixedAuthoritiesExtractor implements org.springframework.boot.autoconfigure.security.oauth2.resource.AuthoritiesExtractor {
  private static final java.lang.String AUTHORITIES;

  private static final java.lang.String[] AUTHORITY_KEYS;

  public org.springframework.boot.autoconfigure.security.oauth2.resource.FixedAuthoritiesExtractor();
    Code:
       0: aload_0
       1: invokespecial #1                  // Method java/lang/Object."<init>":()V
       4: return

  public java.util.List<org.springframework.security.core.GrantedAuthority> extractAuthorities(java.util.Map<java.lang.String, java.lang.Object>);
    Code:
       0: ldc           #2                  // String ROLE_USER
       2: astore_2
       3: aload_1
       4: ldc           #4                  // String authorities
       6: invokeinterface #5,  2            // InterfaceMethod java/util/Map.containsKey:(Ljava/lang/Object;)Z
      11: ifeq          27
      14: aload_0
      15: aload_1
      16: ldc           #4                  // String authorities
      18: invokeinterface #6,  2            // InterfaceMethod java/util/Map.get:(Ljava/lang/Object;)Ljava/lang/Object;
      23: invokespecial #7                  // Method asAuthorities:(Ljava/lang/Object;)Ljava/lang/String;
      26: astore_2
      27: aload_2
      28: invokestatic  #8                  // Method org/springframework/security/core/authority/AuthorityUtils.commaSeparatedStringToAuthorityList:(Ljava/lang/String;)Ljava/util/List;
      31: areturn

  private java.lang.String asAuthorities(java.lang.Object);
    Code:
       0: new           #9                  // class java/util/ArrayList
       3: dup
       4: invokespecial #10                 // Method java/util/ArrayList."<init>":()V
       7: astore_2
       8: aload_1
       9: instanceof    #11                 // class java/util/Collection
      12: ifeq          31
      15: aload_1
      16: checkcast     #11                 // class java/util/Collection
      19: astore_3
      20: aload_3
      21: iconst_0
      22: anewarray     #12                 // class java/lang/Object
      25: invokeinterface #13,  2           // InterfaceMethod java/util/Collection.toArray:([Ljava/lang/Object;)[Ljava/lang/Object;
      30: astore_1
      31: aload_1
      32: invokestatic  #14                 // Method org/springframework/util/ObjectUtils.isArray:(Ljava/lang/Object;)Z
      35: ifeq          138
      38: aload_1
      39: checkcast     #15                 // class "[Ljava/lang/Object;"
      42: checkcast     #15                 // class "[Ljava/lang/Object;"
      45: astore_3
      46: aload_3
      47: astore        4
      49: aload         4
      51: arraylength
      52: istore        5
      54: iconst_0
      55: istore        6
      57: iload         6
      59: iload         5
      61: if_icmpge     133
      64: aload         4
      66: iload         6
      68: aaload
      69: astore        7
      71: aload         7
      73: instanceof    #16                 // class java/lang/String
      76: ifeq          91
      79: aload_2
      80: aload         7
      82: invokeinterface #17,  2           // InterfaceMethod java/util/List.add:(Ljava/lang/Object;)Z
      87: pop
      88: goto          127
      91: aload         7
      93: instanceof    #18                 // class java/util/Map
      96: ifeq          118
      99: aload_2
     100: aload_0
     101: aload         7
     103: checkcast     #18                 // class java/util/Map
     106: invokespecial #19                 // Method asAuthority:(Ljava/util/Map;)Ljava/lang/Object;
     109: invokeinterface #17,  2           // InterfaceMethod java/util/List.add:(Ljava/lang/Object;)Z
     114: pop
     115: goto          127
     118: aload_2
     119: aload         7
     121: invokeinterface #17,  2           // InterfaceMethod java/util/List.add:(Ljava/lang/Object;)Z
     126: pop
     127: iinc          6, 1
     130: goto          57
     133: aload_2
     134: invokestatic  #20                 // Method org/springframework/util/StringUtils.collectionToCommaDelimitedString:(Ljava/util/Collection;)Ljava/lang/String;
     137: areturn
     138: aload_1
     139: invokevirtual #21                 // Method java/lang/Object.toString:()Ljava/lang/String;
     142: areturn

  private java.lang.Object asAuthority(java.util.Map<?, ?>);
    Code:
       0: aload_1
       1: invokeinterface #22,  1           // InterfaceMethod java/util/Map.size:()I
       6: iconst_1
       7: if_icmpne     27
      10: aload_1
      11: invokeinterface #23,  1           // InterfaceMethod java/util/Map.values:()Ljava/util/Collection;
      16: invokeinterface #24,  1           // InterfaceMethod java/util/Collection.iterator:()Ljava/util/Iterator;
      21: invokeinterface #25,  1           // InterfaceMethod java/util/Iterator.next:()Ljava/lang/Object;
      26: areturn
      27: getstatic     #26                 // Field AUTHORITY_KEYS:[Ljava/lang/String;
      30: astore_2
      31: aload_2
      32: arraylength
      33: istore_3
      34: iconst_0
      35: istore        4
      37: iload         4
      39: iload_3
      40: if_icmpge     75
      43: aload_2
      44: iload         4
      46: aaload
      47: astore        5
      49: aload_1
      50: aload         5
      52: invokeinterface #5,  2            // InterfaceMethod java/util/Map.containsKey:(Ljava/lang/Object;)Z
      57: ifeq          69
      60: aload_1
      61: aload         5
      63: invokeinterface #6,  2            // InterfaceMethod java/util/Map.get:(Ljava/lang/Object;)Ljava/lang/Object;
      68: areturn
      69: iinc          4, 1
      72: goto          37
      75: aload_1
      76: areturn

  static {};
    Code:
       0: iconst_3
       1: anewarray     #16                 // class java/lang/String
       4: dup
       5: iconst_0
       6: ldc           #27                 // String authority
       8: aastore
       9: dup
      10: iconst_1
      11: ldc           #28                 // String role
      13: aastore
      14: dup
      15: iconst_2
      16: ldc           #29                 // String value
      18: aastore
      19: putstatic     #26                 // Field AUTHORITY_KEYS:[Ljava/lang/String;
      22: return
}
