Compiled from "PersistenceManagerImpl.java"
public class org.infinispan.persistence.manager.PersistenceManagerImpl implements org.infinispan.persistence.manager.PersistenceManager {
  private static final org.infinispan.util.logging.Log log;

  private static final boolean trace;

  org.infinispan.configuration.cache.Configuration configuration;

  org.infinispan.AdvancedCache<java.lang.Object, java.lang.Object> cache;

  org.infinispan.commons.marshall.StreamingMarshaller m;

  javax.transaction.TransactionManager transactionManager;

  private org.infinispan.util.TimeService timeService;

  private final java.util.List<org.infinispan.persistence.spi.CacheLoader> loaders;

  private final java.util.List<org.infinispan.persistence.spi.CacheWriter> writers;

  private final java.util.concurrent.locks.ReadWriteLock storesMutex;

  private final java.util.Map<java.lang.Object, org.infinispan.configuration.cache.StoreConfiguration> configMap;

  private org.infinispan.persistence.factory.CacheStoreFactoryRegistry cacheStoreFactoryRegistry;

  private org.infinispan.expiration.ExpirationManager expirationManager;

  private org.infinispan.persistence.manager.PersistenceManagerImpl$AdvancedPurgeListener advanedListener;

  volatile boolean enabled;

  private java.util.concurrent.Executor persistenceExecutor;

  private org.infinispan.commons.io.ByteBufferFactory byteBufferFactory;

  private org.infinispan.marshall.core.MarshalledEntryFactory marshalledEntryFactory;

  private volatile boolean clearOnStop;

  public org.infinispan.persistence.manager.PersistenceManagerImpl();
    Code:
       0: aload_0
       1: invokespecial #2                  // Method java/lang/Object."<init>":()V
       4: aload_0
       5: new           #3                  // class java/util/ArrayList
       8: dup
       9: invokespecial #4                  // Method java/util/ArrayList."<init>":()V
      12: putfield      #5                  // Field loaders:Ljava/util/List;
      15: aload_0
      16: new           #3                  // class java/util/ArrayList
      19: dup
      20: invokespecial #4                  // Method java/util/ArrayList."<init>":()V
      23: putfield      #6                  // Field writers:Ljava/util/List;
      26: aload_0
      27: new           #7                  // class java/util/concurrent/locks/ReentrantReadWriteLock
      30: dup
      31: invokespecial #8                  // Method java/util/concurrent/locks/ReentrantReadWriteLock."<init>":()V
      34: putfield      #9                  // Field storesMutex:Ljava/util/concurrent/locks/ReadWriteLock;
      37: aload_0
      38: new           #10                 // class java/util/HashMap
      41: dup
      42: invokespecial #11                 // Method java/util/HashMap."<init>":()V
      45: putfield      #12                 // Field configMap:Ljava/util/Map;
      48: return

  public void inject(org.infinispan.AdvancedCache<java.lang.Object, java.lang.Object>, org.infinispan.commons.marshall.StreamingMarshaller, org.infinispan.configuration.cache.Configuration, javax.transaction.TransactionManager, org.infinispan.util.TimeService, java.util.concurrent.ExecutorService, org.infinispan.commons.io.ByteBufferFactory, org.infinispan.marshall.core.MarshalledEntryFactory, org.infinispan.persistence.factory.CacheStoreFactoryRegistry, org.infinispan.expiration.ExpirationManager);
    Code:
       0: aload_0
       1: aload_1
       2: putfield      #13                 // Field cache:Lorg/infinispan/AdvancedCache;
       5: aload_0
       6: aload_2
       7: putfield      #14                 // Field m:Lorg/infinispan/commons/marshall/StreamingMarshaller;
      10: aload_0
      11: aload_3
      12: putfield      #15                 // Field configuration:Lorg/infinispan/configuration/cache/Configuration;
      15: aload_0
      16: aload         4
      18: putfield      #16                 // Field transactionManager:Ljavax/transaction/TransactionManager;
      21: aload_0
      22: aload         5
      24: putfield      #17                 // Field timeService:Lorg/infinispan/util/TimeService;
      27: aload_0
      28: aload         6
      30: putfield      #18                 // Field persistenceExecutor:Ljava/util/concurrent/Executor;
      33: aload_0
      34: aload         7
      36: putfield      #19                 // Field byteBufferFactory:Lorg/infinispan/commons/io/ByteBufferFactory;
      39: aload_0
      40: aload         8
      42: putfield      #20                 // Field marshalledEntryFactory:Lorg/infinispan/marshall/core/MarshalledEntryFactory;
      45: aload_0
      46: aload         9
      48: putfield      #21                 // Field cacheStoreFactoryRegistry:Lorg/infinispan/persistence/factory/CacheStoreFactoryRegistry;
      51: aload_0
      52: aload         10
      54: putfield      #22                 // Field expirationManager:Lorg/infinispan/expiration/ExpirationManager;
      57: aload_0
      58: new           #23                 // class org/infinispan/persistence/manager/PersistenceManagerImpl$AdvancedPurgeListener
      61: dup
      62: aload         10
      64: aconst_null
      65: invokespecial #24                 // Method org/infinispan/persistence/manager/PersistenceManagerImpl$AdvancedPurgeListener."<init>":(Lorg/infinispan/expiration/ExpirationManager;Lorg/infinispan/persistence/manager/PersistenceManagerImpl$1;)V
      68: putfield      #25                 // Field advanedListener:Lorg/infinispan/persistence/manager/PersistenceManagerImpl$AdvancedPurgeListener;
      71: return

  public void start();
    Code:
       0: aload_0
       1: aload_0
       2: getfield      #15                 // Field configuration:Lorg/infinispan/configuration/cache/Configuration;
       5: invokevirtual #26                 // Method org/infinispan/configuration/cache/Configuration.persistence:()Lorg/infinispan/configuration/cache/PersistenceConfiguration;
       8: invokevirtual #27                 // Method org/infinispan/configuration/cache/PersistenceConfiguration.usingStores:()Z
      11: putfield      #28                 // Field enabled:Z
      14: aload_0
      15: getfield      #28                 // Field enabled:Z
      18: ifne          22
      21: return
      22: aload_0
      23: invokespecial #29                 // Method createLoadersAndWriters:()V
      26: aconst_null
      27: astore_1
      28: aload_0
      29: getfield      #16                 // Field transactionManager:Ljavax/transaction/TransactionManager;
      32: ifnull        45
      35: aload_0
      36: getfield      #16                 // Field transactionManager:Ljavax/transaction/TransactionManager;
      39: invokeinterface #30,  1           // InterfaceMethod javax/transaction/TransactionManager.suspend:()Ljavax/transaction/Transaction;
      44: astore_1
      45: new           #31                 // class java/util/HashSet
      48: dup
      49: invokespecial #32                 // Method java/util/HashSet."<init>":()V
      52: astore_2
      53: aload_0
      54: getfield      #6                  // Field writers:Ljava/util/List;
      57: invokeinterface #33,  1           // InterfaceMethod java/util/List.iterator:()Ljava/util/Iterator;
      62: astore_3
      63: aload_3
      64: invokeinterface #34,  1           // InterfaceMethod java/util/Iterator.hasNext:()Z
      69: ifeq          208
      72: aload_3
      73: invokeinterface #35,  1           // InterfaceMethod java/util/Iterator.next:()Ljava/lang/Object;
      78: checkcast     #36                 // class org/infinispan/persistence/spi/CacheWriter
      81: astore        4
      83: aload         4
      85: invokeinterface #37,  1           // InterfaceMethod org/infinispan/persistence/spi/CacheWriter.start:()V
      90: aload         4
      92: instanceof    #38                 // class org/infinispan/persistence/support/DelegatingCacheWriter
      95: ifeq          125
      98: aload_0
      99: aload         4
     101: invokespecial #39                 // Method undelegate:(Lorg/infinispan/persistence/spi/CacheWriter;)Lorg/infinispan/persistence/spi/CacheWriter;
     104: astore        5
     106: aload         5
     108: invokeinterface #37,  1           // InterfaceMethod org/infinispan/persistence/spi/CacheWriter.start:()V
     113: aload_2
     114: aload         5
     116: invokeinterface #40,  2           // InterfaceMethod java/util/Set.add:(Ljava/lang/Object;)Z
     121: pop
     122: goto          134
     125: aload_2
     126: aload         4
     128: invokeinterface #40,  2           // InterfaceMethod java/util/Set.add:(Ljava/lang/Object;)Z
     133: pop
     134: aload_0
     135: getfield      #12                 // Field configMap:Ljava/util/Map;
     138: aload         4
     140: invokeinterface #41,  2           // InterfaceMethod java/util/Map.get:(Ljava/lang/Object;)Ljava/lang/Object;
     145: checkcast     #42                 // class org/infinispan/configuration/cache/StoreConfiguration
     148: invokeinterface #43,  1           // InterfaceMethod org/infinispan/configuration/cache/StoreConfiguration.purgeOnStartup:()Z
     153: ifeq          205
     156: aload         4
     158: instanceof    #44                 // class org/infinispan/persistence/spi/AdvancedCacheWriter
     161: ifne          195
     164: new           #45                 // class org/infinispan/persistence/spi/PersistenceException
     167: dup
     168: new           #46                 // class java/lang/StringBuilder
     171: dup
     172: invokespecial #47                 // Method java/lang/StringBuilder."<init>":()V
     175: ldc           #48                 // String \'purgeOnStartup\' can only be set on stores implementing
     177: invokevirtual #49                 // Method java/lang/StringBuilder.append:(Ljava/lang/String;)Ljava/lang/StringBuilder;
     180: ldc           #44                 // class org/infinispan/persistence/spi/AdvancedCacheWriter
     182: invokevirtual #50                 // Method java/lang/Class.getName:()Ljava/lang/String;
     185: invokevirtual #49                 // Method java/lang/StringBuilder.append:(Ljava/lang/String;)Ljava/lang/StringBuilder;
     188: invokevirtual #51                 // Method java/lang/StringBuilder.toString:()Ljava/lang/String;
     191: invokespecial #52                 // Method org/infinispan/persistence/spi/PersistenceException."<init>":(Ljava/lang/String;)V
     194: athrow
     195: aload         4
     197: checkcast     #44                 // class org/infinispan/persistence/spi/AdvancedCacheWriter
     200: invokeinterface #53,  1           // InterfaceMethod org/infinispan/persistence/spi/AdvancedCacheWriter.clear:()V
     205: goto          63
     208: aload_0
     209: getfield      #5                  // Field loaders:Ljava/util/List;
     212: invokeinterface #33,  1           // InterfaceMethod java/util/List.iterator:()Ljava/util/Iterator;
     217: astore_3
     218: aload_3
     219: invokeinterface #34,  1           // InterfaceMethod java/util/Iterator.hasNext:()Z
     224: ifeq          293
     227: aload_3
     228: invokeinterface #35,  1           // InterfaceMethod java/util/Iterator.next:()Ljava/lang/Object;
     233: checkcast     #54                 // class org/infinispan/persistence/spi/CacheLoader
     236: astore        4
     238: aload_2
     239: aload         4
     241: invokeinterface #55,  2           // InterfaceMethod java/util/Set.contains:(Ljava/lang/Object;)Z
     246: ifne          256
     249: aload         4
     251: invokeinterface #56,  1           // InterfaceMethod org/infinispan/persistence/spi/CacheLoader.start:()V
     256: aload         4
     258: instanceof    #57                 // class org/infinispan/persistence/support/DelegatingCacheLoader
     261: ifeq          290
     264: aload_0
     265: aload         4
     267: invokespecial #58                 // Method undelegate:(Lorg/infinispan/persistence/spi/CacheLoader;)Lorg/infinispan/persistence/spi/CacheLoader;
     270: astore        5
     272: aload_2
     273: aload         5
     275: invokeinterface #55,  2           // InterfaceMethod java/util/Set.contains:(Ljava/lang/Object;)Z
     280: ifne          290
     283: aload         5
     285: invokeinterface #56,  1           // InterfaceMethod org/infinispan/persistence/spi/CacheLoader.start:()V
     290: goto          218
     293: aload_1
     294: ifnull        329
     297: aload_0
     298: getfield      #16                 // Field transactionManager:Ljavax/transaction/TransactionManager;
     301: aload_1
     302: invokeinterface #59,  2           // InterfaceMethod javax/transaction/TransactionManager.resume:(Ljavax/transaction/Transaction;)V
     307: goto          329
     310: astore        6
     312: aload_1
     313: ifnull        326
     316: aload_0
     317: getfield      #16                 // Field transactionManager:Ljavax/transaction/TransactionManager;
     320: aload_1
     321: invokeinterface #59,  2           // InterfaceMethod javax/transaction/TransactionManager.resume:(Ljavax/transaction/Transaction;)V
     326: aload         6
     328: athrow
     329: goto          344
     332: astore_1
     333: new           #61                 // class org/infinispan/commons/CacheException
     336: dup
     337: ldc           #62                 // String Unable to start cache loaders
     339: aload_1
     340: invokespecial #63                 // Method org/infinispan/commons/CacheException."<init>":(Ljava/lang/String;Ljava/lang/Throwable;)V
     343: athrow
     344: return
    Exception table:
       from    to  target type
          45   293   310   any
         310   312   310   any
          22   329   332   Class java/lang/Exception

  public void stop();
    Code:
       0: aload_0
       1: getfield      #64                 // Field clearOnStop:Z
       4: ifeq          14
       7: aload_0
       8: getstatic     #65                 // Field org/infinispan/persistence/manager/PersistenceManager$AccessMode.BOTH:Lorg/infinispan/persistence/manager/PersistenceManager$AccessMode;
      11: invokevirtual #66                 // Method clearAllStores:(Lorg/infinispan/persistence/manager/PersistenceManager$AccessMode;)V
      14: new           #31                 // class java/util/HashSet
      17: dup
      18: invokespecial #32                 // Method java/util/HashSet."<init>":()V
      21: astore_1
      22: aload_0
      23: getfield      #6                  // Field writers:Ljava/util/List;
      26: invokeinterface #33,  1           // InterfaceMethod java/util/List.iterator:()Ljava/util/Iterator;
      31: astore_2
      32: aload_2
      33: invokeinterface #34,  1           // InterfaceMethod java/util/Iterator.hasNext:()Z
      38: ifeq          101
      41: aload_2
      42: invokeinterface #35,  1           // InterfaceMethod java/util/Iterator.next:()Ljava/lang/Object;
      47: checkcast     #36                 // class org/infinispan/persistence/spi/CacheWriter
      50: astore_3
      51: aload_3
      52: invokeinterface #67,  1           // InterfaceMethod org/infinispan/persistence/spi/CacheWriter.stop:()V
      57: aload_3
      58: instanceof    #38                 // class org/infinispan/persistence/support/DelegatingCacheWriter
      61: ifeq          90
      64: aload_0
      65: aload_3
      66: invokespecial #39                 // Method undelegate:(Lorg/infinispan/persistence/spi/CacheWriter;)Lorg/infinispan/persistence/spi/CacheWriter;
      69: astore        4
      71: aload         4
      73: invokeinterface #67,  1           // InterfaceMethod org/infinispan/persistence/spi/CacheWriter.stop:()V
      78: aload_1
      79: aload         4
      81: invokeinterface #40,  2           // InterfaceMethod java/util/Set.add:(Ljava/lang/Object;)Z
      86: pop
      87: goto          98
      90: aload_1
      91: aload_3
      92: invokeinterface #40,  2           // InterfaceMethod java/util/Set.add:(Ljava/lang/Object;)Z
      97: pop
      98: goto          32
     101: aload_0
     102: getfield      #5                  // Field loaders:Ljava/util/List;
     105: invokeinterface #33,  1           // InterfaceMethod java/util/List.iterator:()Ljava/util/Iterator;
     110: astore_2
     111: aload_2
     112: invokeinterface #34,  1           // InterfaceMethod java/util/Iterator.hasNext:()Z
     117: ifeq          181
     120: aload_2
     121: invokeinterface #35,  1           // InterfaceMethod java/util/Iterator.next:()Ljava/lang/Object;
     126: checkcast     #54                 // class org/infinispan/persistence/spi/CacheLoader
     129: astore_3
     130: aload_1
     131: aload_3
     132: invokeinterface #55,  2           // InterfaceMethod java/util/Set.contains:(Ljava/lang/Object;)Z
     137: ifne          146
     140: aload_3
     141: invokeinterface #68,  1           // InterfaceMethod org/infinispan/persistence/spi/CacheLoader.stop:()V
     146: aload_3
     147: instanceof    #57                 // class org/infinispan/persistence/support/DelegatingCacheLoader
     150: ifeq          178
     153: aload_0
     154: aload_3
     155: invokespecial #58                 // Method undelegate:(Lorg/infinispan/persistence/spi/CacheLoader;)Lorg/infinispan/persistence/spi/CacheLoader;
     158: astore        4
     160: aload_1
     161: aload         4
     163: invokeinterface #55,  2           // InterfaceMethod java/util/Set.contains:(Ljava/lang/Object;)Z
     168: ifne          178
     171: aload         4
     173: invokeinterface #68,  1           // InterfaceMethod org/infinispan/persistence/spi/CacheLoader.stop:()V
     178: goto          111
     181: return

  public void preload();
    Code:
       0: aload_0
       1: getfield      #28                 // Field enabled:Z
       4: ifne          8
       7: return
       8: aconst_null
       9: astore_1
      10: aload_0
      11: getfield      #5                  // Field loaders:Ljava/util/List;
      14: invokeinterface #33,  1           // InterfaceMethod java/util/List.iterator:()Ljava/util/Iterator;
      19: astore_2
      20: aload_2
      21: invokeinterface #34,  1           // InterfaceMethod java/util/Iterator.hasNext:()Z
      26: ifeq          147
      29: aload_2
      30: invokeinterface #35,  1           // InterfaceMethod java/util/Iterator.next:()Ljava/lang/Object;
      35: checkcast     #54                 // class org/infinispan/persistence/spi/CacheLoader
      38: astore_3
      39: aload_0
      40: getfield      #12                 // Field configMap:Ljava/util/Map;
      43: aload_3
      44: invokeinterface #41,  2           // InterfaceMethod java/util/Map.get:(Ljava/lang/Object;)Ljava/lang/Object;
      49: checkcast     #42                 // class org/infinispan/configuration/cache/StoreConfiguration
      52: invokeinterface #69,  1           // InterfaceMethod org/infinispan/configuration/cache/StoreConfiguration.preload:()Z
      57: ifeq          144
      60: aload_3
      61: instanceof    #70                 // class org/infinispan/persistence/spi/AdvancedCacheLoader
      64: ifne          118
      67: new           #45                 // class org/infinispan/persistence/spi/PersistenceException
      70: dup
      71: new           #46                 // class java/lang/StringBuilder
      74: dup
      75: invokespecial #47                 // Method java/lang/StringBuilder."<init>":()V
      78: ldc           #71                 // String Cannot preload from cache loader \'
      80: invokevirtual #49                 // Method java/lang/StringBuilder.append:(Ljava/lang/String;)Ljava/lang/StringBuilder;
      83: aload_3
      84: invokevirtual #72                 // Method java/lang/Object.getClass:()Ljava/lang/Class;
      87: invokevirtual #50                 // Method java/lang/Class.getName:()Ljava/lang/String;
      90: invokevirtual #49                 // Method java/lang/StringBuilder.append:(Ljava/lang/String;)Ljava/lang/StringBuilder;
      93: ldc           #73                 // String \' as it doesn\'t implement \'
      95: invokevirtual #49                 // Method java/lang/StringBuilder.append:(Ljava/lang/String;)Ljava/lang/StringBuilder;
      98: ldc           #70                 // class org/infinispan/persistence/spi/AdvancedCacheLoader
     100: invokevirtual #50                 // Method java/lang/Class.getName:()Ljava/lang/String;
     103: invokevirtual #49                 // Method java/lang/StringBuilder.append:(Ljava/lang/String;)Ljava/lang/StringBuilder;
     106: ldc           #74                 // String \'
     108: invokevirtual #49                 // Method java/lang/StringBuilder.append:(Ljava/lang/String;)Ljava/lang/StringBuilder;
     111: invokevirtual #51                 // Method java/lang/StringBuilder.toString:()Ljava/lang/String;
     114: invokespecial #52                 // Method org/infinispan/persistence/spi/PersistenceException."<init>":(Ljava/lang/String;)V
     117: athrow
     118: aload_3
     119: checkcast     #70                 // class org/infinispan/persistence/spi/AdvancedCacheLoader
     122: astore_1
     123: aload_1
     124: instanceof    #75                 // class org/infinispan/persistence/async/AdvancedAsyncCacheLoader
     127: ifeq          147
     130: aload_1
     131: checkcast     #75                 // class org/infinispan/persistence/async/AdvancedAsyncCacheLoader
     134: invokevirtual #76                 // Method org/infinispan/persistence/async/AdvancedAsyncCacheLoader.undelegate:()Lorg/infinispan/persistence/spi/CacheLoader;
     137: checkcast     #70                 // class org/infinispan/persistence/spi/AdvancedCacheLoader
     140: astore_1
     141: goto          147
     144: goto          20
     147: aload_1
     148: ifnonnull     152
     151: return
     152: aload_0
     153: getfield      #17                 // Field timeService:Lorg/infinispan/util/TimeService;
     156: invokeinterface #77,  1           // InterfaceMethod org/infinispan/util/TimeService.time:()J
     161: lstore_2
     162: aload_0
     163: invokespecial #78                 // Method getMaxEntries:()J
     166: lstore        4
     168: new           #79                 // class java/util/concurrent/atomic/AtomicInteger
     171: dup
     172: iconst_0
     173: invokespecial #80                 // Method java/util/concurrent/atomic/AtomicInteger."<init>":(I)V
     176: astore        6
     178: aload_0
     179: invokespecial #81                 // Method getCacheForStateInsertion:()Lorg/infinispan/AdvancedCache;
     182: astore        7
     184: aload_1
     185: aconst_null
     186: new           #82                 // class org/infinispan/persistence/manager/PersistenceManagerImpl$1
     189: dup
     190: aload_0
     191: aload         6
     193: lload         4
     195: aload         7
     197: invokespecial #83                 // Method org/infinispan/persistence/manager/PersistenceManagerImpl$1."<init>":(Lorg/infinispan/persistence/manager/PersistenceManagerImpl;Ljava/util/concurrent/atomic/AtomicInteger;JLorg/infinispan/AdvancedCache;)V
     200: new           #84                 // class org/infinispan/util/concurrent/WithinThreadExecutor
     203: dup
     204: invokespecial #85                 // Method org/infinispan/util/concurrent/WithinThreadExecutor."<init>":()V
     207: iconst_1
     208: iconst_1
     209: invokeinterface #86,  6           // InterfaceMethod org/infinispan/persistence/spi/AdvancedCacheLoader.process:(Lorg/infinispan/filter/KeyFilter;Lorg/infinispan/persistence/spi/AdvancedCacheLoader$CacheLoaderTask;Ljava/util/concurrent/Executor;ZZ)V
     214: getstatic     #87                 // Field log:Lorg/infinispan/util/logging/Log;
     217: ldc           #88                 // String Preloaded %s keys in %s
     219: aload         6
     221: aload_0
     222: getfield      #17                 // Field timeService:Lorg/infinispan/util/TimeService;
     225: lload_2
     226: getstatic     #89                 // Field java/util/concurrent/TimeUnit.MILLISECONDS:Ljava/util/concurrent/TimeUnit;
     229: invokeinterface #90,  4           // InterfaceMethod org/infinispan/util/TimeService.timeDuration:(JLjava/util/concurrent/TimeUnit;)J
     234: invokestatic  #91                 // Method org/infinispan/commons/util/Util.prettyPrintTime:(J)Ljava/lang/String;
     237: invokeinterface #92,  4           // InterfaceMethod org/infinispan/util/logging/Log.debugf:(Ljava/lang/String;Ljava/lang/Object;Ljava/lang/Object;)V
     242: return

  public void disableStore(java.lang.String);
    Code:
       0: aload_0
       1: getfield      #28                 // Field enabled:Z
       4: ifeq          368
       7: aload_0
       8: getfield      #9                  // Field storesMutex:Ljava/util/concurrent/locks/ReadWriteLock;
      11: invokeinterface #93,  1           // InterfaceMethod java/util/concurrent/locks/ReadWriteLock.writeLock:()Ljava/util/concurrent/locks/Lock;
      16: invokeinterface #94,  1           // InterfaceMethod java/util/concurrent/locks/Lock.lock:()V
      21: aload_0
      22: getfield      #5                  // Field loaders:Ljava/util/List;
      25: invokeinterface #33,  1           // InterfaceMethod java/util/List.iterator:()Ljava/util/Iterator;
      30: astore_2
      31: aload_2
      32: invokeinterface #34,  1           // InterfaceMethod java/util/Iterator.hasNext:()Z
      37: ifeq          77
      40: aload_2
      41: invokeinterface #35,  1           // InterfaceMethod java/util/Iterator.next:()Ljava/lang/Object;
      46: checkcast     #54                 // class org/infinispan/persistence/spi/CacheLoader
      49: astore_3
      50: aload_0
      51: aload_3
      52: invokespecial #58                 // Method undelegate:(Lorg/infinispan/persistence/spi/CacheLoader;)Lorg/infinispan/persistence/spi/CacheLoader;
      55: invokevirtual #72                 // Method java/lang/Object.getClass:()Ljava/lang/Class;
      58: invokevirtual #50                 // Method java/lang/Class.getName:()Ljava/lang/String;
      61: aload_1
      62: invokevirtual #95                 // Method java/lang/String.equals:(Ljava/lang/Object;)Z
      65: ifeq          74
      68: aload_2
      69: invokeinterface #96,  1           // InterfaceMethod java/util/Iterator.remove:()V
      74: goto          31
      77: aload_0
      78: getfield      #6                  // Field writers:Ljava/util/List;
      81: invokeinterface #33,  1           // InterfaceMethod java/util/List.iterator:()Ljava/util/Iterator;
      86: astore_3
      87: aload_3
      88: invokeinterface #34,  1           // InterfaceMethod java/util/Iterator.hasNext:()Z
      93: ifeq          135
      96: aload_3
      97: invokeinterface #35,  1           // InterfaceMethod java/util/Iterator.next:()Ljava/lang/Object;
     102: checkcast     #36                 // class org/infinispan/persistence/spi/CacheWriter
     105: astore        4
     107: aload_0
     108: aload         4
     110: invokespecial #39                 // Method undelegate:(Lorg/infinispan/persistence/spi/CacheWriter;)Lorg/infinispan/persistence/spi/CacheWriter;
     113: invokevirtual #72                 // Method java/lang/Object.getClass:()Ljava/lang/Class;
     116: invokevirtual #50                 // Method java/lang/Class.getName:()Ljava/lang/String;
     119: aload_1
     120: invokevirtual #95                 // Method java/lang/String.equals:(Ljava/lang/Object;)Z
     123: ifeq          132
     126: aload_3
     127: invokeinterface #96,  1           // InterfaceMethod java/util/Iterator.remove:()V
     132: goto          87
     135: aload_0
     136: getfield      #9                  // Field storesMutex:Ljava/util/concurrent/locks/ReadWriteLock;
     139: invokeinterface #93,  1           // InterfaceMethod java/util/concurrent/locks/ReadWriteLock.writeLock:()Ljava/util/concurrent/locks/Lock;
     144: invokeinterface #97,  1           // InterfaceMethod java/util/concurrent/locks/Lock.unlock:()V
     149: goto          171
     152: astore        5
     154: aload_0
     155: getfield      #9                  // Field storesMutex:Ljava/util/concurrent/locks/ReadWriteLock;
     158: invokeinterface #93,  1           // InterfaceMethod java/util/concurrent/locks/ReadWriteLock.writeLock:()Ljava/util/concurrent/locks/Lock;
     163: invokeinterface #97,  1           // InterfaceMethod java/util/concurrent/locks/Lock.unlock:()V
     168: aload         5
     170: athrow
     171: aload_0
     172: getfield      #5                  // Field loaders:Ljava/util/List;
     175: invokeinterface #98,  1           // InterfaceMethod java/util/List.isEmpty:()Z
     180: ifeq          368
     183: aload_0
     184: getfield      #6                  // Field writers:Ljava/util/List;
     187: invokeinterface #98,  1           // InterfaceMethod java/util/List.isEmpty:()Z
     192: ifeq          368
     195: aload_0
     196: getfield      #13                 // Field cache:Lorg/infinispan/AdvancedCache;
     199: invokeinterface #99,  1           // InterfaceMethod org/infinispan/AdvancedCache.getComponentRegistry:()Lorg/infinispan/factories/ComponentRegistry;
     204: ldc           #100                // class org/infinispan/interceptors/InterceptorChain
     206: invokevirtual #101                // Method org/infinispan/factories/ComponentRegistry.getComponent:(Ljava/lang/Class;)Ljava/lang/Object;
     209: checkcast     #100                // class org/infinispan/interceptors/InterceptorChain
     212: astore_2
     213: aload_2
     214: ldc           #102                // class org/infinispan/interceptors/CacheLoaderInterceptor
     216: invokevirtual #103                // Method org/infinispan/interceptors/InterceptorChain.getInterceptorsWhichExtend:(Ljava/lang/Class;)Ljava/util/List;
     219: astore_3
     220: aload_3
     221: invokeinterface #98,  1           // InterfaceMethod java/util/List.isEmpty:()Z
     226: ifeq          240
     229: getstatic     #87                 // Field log:Lorg/infinispan/util/logging/Log;
     232: invokeinterface #104,  1          // InterfaceMethod org/infinispan/util/logging/Log.persistenceWithoutCacheLoaderInterceptor:()V
     237: goto          281
     240: aload_3
     241: invokeinterface #33,  1           // InterfaceMethod java/util/List.iterator:()Ljava/util/Iterator;
     246: astore        4
     248: aload         4
     250: invokeinterface #34,  1           // InterfaceMethod java/util/Iterator.hasNext:()Z
     255: ifeq          281
     258: aload         4
     260: invokeinterface #35,  1           // InterfaceMethod java/util/Iterator.next:()Ljava/lang/Object;
     265: checkcast     #105                // class org/infinispan/interceptors/base/CommandInterceptor
     268: astore        5
     270: aload         5
     272: checkcast     #102                // class org/infinispan/interceptors/CacheLoaderInterceptor
     275: invokevirtual #106                // Method org/infinispan/interceptors/CacheLoaderInterceptor.disableInterceptor:()V
     278: goto          248
     281: aload_2
     282: ldc           #107                // class org/infinispan/interceptors/CacheWriterInterceptor
     284: invokevirtual #103                // Method org/infinispan/interceptors/InterceptorChain.getInterceptorsWhichExtend:(Ljava/lang/Class;)Ljava/util/List;
     287: astore        4
     289: aload         4
     291: invokeinterface #98,  1           // InterfaceMethod java/util/List.isEmpty:()Z
     296: ifeq          310
     299: getstatic     #87                 // Field log:Lorg/infinispan/util/logging/Log;
     302: invokeinterface #108,  1          // InterfaceMethod org/infinispan/util/logging/Log.persistenceWithoutCacheWriteInterceptor:()V
     307: goto          352
     310: aload         4
     312: invokeinterface #33,  1           // InterfaceMethod java/util/List.iterator:()Ljava/util/Iterator;
     317: astore        5
     319: aload         5
     321: invokeinterface #34,  1           // InterfaceMethod java/util/Iterator.hasNext:()Z
     326: ifeq          352
     329: aload         5
     331: invokeinterface #35,  1           // InterfaceMethod java/util/Iterator.next:()Ljava/lang/Object;
     336: checkcast     #105                // class org/infinispan/interceptors/base/CommandInterceptor
     339: astore        6
     341: aload         6
     343: checkcast     #107                // class org/infinispan/interceptors/CacheWriterInterceptor
     346: invokevirtual #109                // Method org/infinispan/interceptors/CacheWriterInterceptor.disableInterceptor:()V
     349: goto          319
     352: aload_0
     353: aload_3
     354: invokespecial #110                // Method removeInterceptors:(Ljava/util/Collection;)V
     357: aload_0
     358: aload         4
     360: invokespecial #110                // Method removeInterceptors:(Ljava/util/Collection;)V
     363: aload_0
     364: iconst_0
     365: putfield      #28                 // Field enabled:Z
     368: return
    Exception table:
       from    to  target type
          21   135   152   any
         152   154   152   any

  public <T> java.util.Set<T> getStores(java.lang.Class<T>);
    Code:
       0: aload_0
       1: getfield      #9                  // Field storesMutex:Ljava/util/concurrent/locks/ReadWriteLock;
       4: invokeinterface #111,  1          // InterfaceMethod java/util/concurrent/locks/ReadWriteLock.readLock:()Ljava/util/concurrent/locks/Lock;
       9: invokeinterface #94,  1           // InterfaceMethod java/util/concurrent/locks/Lock.lock:()V
      14: new           #31                 // class java/util/HashSet
      17: dup
      18: invokespecial #32                 // Method java/util/HashSet."<init>":()V
      21: astore_2
      22: aload_0
      23: getfield      #5                  // Field loaders:Ljava/util/List;
      26: invokeinterface #33,  1           // InterfaceMethod java/util/List.iterator:()Ljava/util/Iterator;
      31: astore_3
      32: aload_3
      33: invokeinterface #34,  1           // InterfaceMethod java/util/Iterator.hasNext:()Z
      38: ifeq          81
      41: aload_3
      42: invokeinterface #35,  1           // InterfaceMethod java/util/Iterator.next:()Ljava/lang/Object;
      47: checkcast     #54                 // class org/infinispan/persistence/spi/CacheLoader
      50: astore        4
      52: aload_0
      53: aload         4
      55: invokespecial #58                 // Method undelegate:(Lorg/infinispan/persistence/spi/CacheLoader;)Lorg/infinispan/persistence/spi/CacheLoader;
      58: astore        5
      60: aload_1
      61: aload         5
      63: invokevirtual #112                // Method java/lang/Class.isInstance:(Ljava/lang/Object;)Z
      66: ifeq          78
      69: aload_2
      70: aload         5
      72: invokeinterface #40,  2           // InterfaceMethod java/util/Set.add:(Ljava/lang/Object;)Z
      77: pop
      78: goto          32
      81: aload_0
      82: getfield      #6                  // Field writers:Ljava/util/List;
      85: invokeinterface #33,  1           // InterfaceMethod java/util/List.iterator:()Ljava/util/Iterator;
      90: astore_3
      91: aload_3
      92: invokeinterface #34,  1           // InterfaceMethod java/util/Iterator.hasNext:()Z
      97: ifeq          140
     100: aload_3
     101: invokeinterface #35,  1           // InterfaceMethod java/util/Iterator.next:()Ljava/lang/Object;
     106: checkcast     #36                 // class org/infinispan/persistence/spi/CacheWriter
     109: astore        4
     111: aload_0
     112: aload         4
     114: invokespecial #39                 // Method undelegate:(Lorg/infinispan/persistence/spi/CacheWriter;)Lorg/infinispan/persistence/spi/CacheWriter;
     117: astore        5
     119: aload_1
     120: aload         5
     122: invokevirtual #112                // Method java/lang/Class.isInstance:(Ljava/lang/Object;)Z
     125: ifeq          137
     128: aload_2
     129: aload         5
     131: invokeinterface #40,  2           // InterfaceMethod java/util/Set.add:(Ljava/lang/Object;)Z
     136: pop
     137: goto          91
     140: aload_2
     141: astore_3
     142: aload_0
     143: getfield      #9                  // Field storesMutex:Ljava/util/concurrent/locks/ReadWriteLock;
     146: invokeinterface #111,  1          // InterfaceMethod java/util/concurrent/locks/ReadWriteLock.readLock:()Ljava/util/concurrent/locks/Lock;
     151: invokeinterface #97,  1           // InterfaceMethod java/util/concurrent/locks/Lock.unlock:()V
     156: aload_3
     157: areturn
     158: astore        6
     160: aload_0
     161: getfield      #9                  // Field storesMutex:Ljava/util/concurrent/locks/ReadWriteLock;
     164: invokeinterface #111,  1          // InterfaceMethod java/util/concurrent/locks/ReadWriteLock.readLock:()Ljava/util/concurrent/locks/Lock;
     169: invokeinterface #97,  1           // InterfaceMethod java/util/concurrent/locks/Lock.unlock:()V
     174: aload         6
     176: athrow
    Exception table:
       from    to  target type
          14   142   158   any
         158   160   158   any

  public java.util.Collection<java.lang.String> getStoresAsString();
    Code:
       0: aload_0
       1: getfield      #9                  // Field storesMutex:Ljava/util/concurrent/locks/ReadWriteLock;
       4: invokeinterface #111,  1          // InterfaceMethod java/util/concurrent/locks/ReadWriteLock.readLock:()Ljava/util/concurrent/locks/Lock;
       9: invokeinterface #94,  1           // InterfaceMethod java/util/concurrent/locks/Lock.lock:()V
      14: new           #31                 // class java/util/HashSet
      17: dup
      18: aload_0
      19: getfield      #5                  // Field loaders:Ljava/util/List;
      22: invokeinterface #113,  1          // InterfaceMethod java/util/List.size:()I
      27: invokespecial #114                // Method java/util/HashSet."<init>":(I)V
      30: astore_1
      31: aload_0
      32: getfield      #5                  // Field loaders:Ljava/util/List;
      35: invokeinterface #33,  1           // InterfaceMethod java/util/List.iterator:()Ljava/util/Iterator;
      40: astore_2
      41: aload_2
      42: invokeinterface #34,  1           // InterfaceMethod java/util/Iterator.hasNext:()Z
      47: ifeq          81
      50: aload_2
      51: invokeinterface #35,  1           // InterfaceMethod java/util/Iterator.next:()Ljava/lang/Object;
      56: checkcast     #54                 // class org/infinispan/persistence/spi/CacheLoader
      59: astore_3
      60: aload_1
      61: aload_0
      62: aload_3
      63: invokespecial #58                 // Method undelegate:(Lorg/infinispan/persistence/spi/CacheLoader;)Lorg/infinispan/persistence/spi/CacheLoader;
      66: invokevirtual #72                 // Method java/lang/Object.getClass:()Ljava/lang/Class;
      69: invokevirtual #50                 // Method java/lang/Class.getName:()Ljava/lang/String;
      72: invokeinterface #40,  2           // InterfaceMethod java/util/Set.add:(Ljava/lang/Object;)Z
      77: pop
      78: goto          41
      81: aload_0
      82: getfield      #6                  // Field writers:Ljava/util/List;
      85: invokeinterface #33,  1           // InterfaceMethod java/util/List.iterator:()Ljava/util/Iterator;
      90: astore_2
      91: aload_2
      92: invokeinterface #34,  1           // InterfaceMethod java/util/Iterator.hasNext:()Z
      97: ifeq          131
     100: aload_2
     101: invokeinterface #35,  1           // InterfaceMethod java/util/Iterator.next:()Ljava/lang/Object;
     106: checkcast     #36                 // class org/infinispan/persistence/spi/CacheWriter
     109: astore_3
     110: aload_1
     111: aload_0
     112: aload_3
     113: invokespecial #39                 // Method undelegate:(Lorg/infinispan/persistence/spi/CacheWriter;)Lorg/infinispan/persistence/spi/CacheWriter;
     116: invokevirtual #72                 // Method java/lang/Object.getClass:()Ljava/lang/Class;
     119: invokevirtual #50                 // Method java/lang/Class.getName:()Ljava/lang/String;
     122: invokeinterface #40,  2           // InterfaceMethod java/util/Set.add:(Ljava/lang/Object;)Z
     127: pop
     128: goto          91
     131: aload_1
     132: astore_2
     133: aload_0
     134: getfield      #9                  // Field storesMutex:Ljava/util/concurrent/locks/ReadWriteLock;
     137: invokeinterface #111,  1          // InterfaceMethod java/util/concurrent/locks/ReadWriteLock.readLock:()Ljava/util/concurrent/locks/Lock;
     142: invokeinterface #97,  1           // InterfaceMethod java/util/concurrent/locks/Lock.unlock:()V
     147: aload_2
     148: areturn
     149: astore        4
     151: aload_0
     152: getfield      #9                  // Field storesMutex:Ljava/util/concurrent/locks/ReadWriteLock;
     155: invokeinterface #111,  1          // InterfaceMethod java/util/concurrent/locks/ReadWriteLock.readLock:()Ljava/util/concurrent/locks/Lock;
     160: invokeinterface #97,  1           // InterfaceMethod java/util/concurrent/locks/Lock.unlock:()V
     165: aload         4
     167: athrow
    Exception table:
       from    to  target type
          14   133   149   any
         149   151   149   any

  public void purgeExpired();
    Code:
       0: aload_0
       1: getfield      #28                 // Field enabled:Z
       4: ifne          8
       7: return
       8: ldc2_w        #115                // long -1l
      11: lstore_1
      12: getstatic     #117                // Field trace:Z
      15: ifeq          38
      18: getstatic     #87                 // Field log:Lorg/infinispan/util/logging/Log;
      21: ldc           #118                // String Purging cache store of expired entries
      23: invokeinterface #119,  2          // InterfaceMethod org/infinispan/util/logging/Log.trace:(Ljava/lang/Object;)V
      28: aload_0
      29: getfield      #17                 // Field timeService:Lorg/infinispan/util/TimeService;
      32: invokeinterface #77,  1           // InterfaceMethod org/infinispan/util/TimeService.time:()J
      37: lstore_1
      38: aload_0
      39: getfield      #9                  // Field storesMutex:Ljava/util/concurrent/locks/ReadWriteLock;
      42: invokeinterface #111,  1          // InterfaceMethod java/util/concurrent/locks/ReadWriteLock.readLock:()Ljava/util/concurrent/locks/Lock;
      47: invokeinterface #94,  1           // InterfaceMethod java/util/concurrent/locks/Lock.lock:()V
      52: aload_0
      53: getfield      #6                  // Field writers:Ljava/util/List;
      56: invokeinterface #33,  1           // InterfaceMethod java/util/List.iterator:()Ljava/util/Iterator;
      61: astore_3
      62: aload_3
      63: invokeinterface #34,  1           // InterfaceMethod java/util/Iterator.hasNext:()Z
      68: ifeq          142
      71: aload_3
      72: invokeinterface #35,  1           // InterfaceMethod java/util/Iterator.next:()Ljava/lang/Object;
      77: checkcast     #36                 // class org/infinispan/persistence/spi/CacheWriter
      80: astore        4
      82: aload         4
      84: instanceof    #120                // class org/infinispan/persistence/spi/AdvancedCacheExpirationWriter
      87: ifeq          111
      90: aload         4
      92: checkcast     #120                // class org/infinispan/persistence/spi/AdvancedCacheExpirationWriter
      95: aload_0
      96: getfield      #18                 // Field persistenceExecutor:Ljava/util/concurrent/Executor;
      99: aload_0
     100: getfield      #25                 // Field advanedListener:Lorg/infinispan/persistence/manager/PersistenceManagerImpl$AdvancedPurgeListener;
     103: invokeinterface #121,  3          // InterfaceMethod org/infinispan/persistence/spi/AdvancedCacheExpirationWriter.purge:(Ljava/util/concurrent/Executor;Lorg/infinispan/persistence/spi/AdvancedCacheExpirationWriter$ExpirationPurgeListener;)V
     108: goto          139
     111: aload         4
     113: instanceof    #44                 // class org/infinispan/persistence/spi/AdvancedCacheWriter
     116: ifeq          139
     119: aload         4
     121: checkcast     #44                 // class org/infinispan/persistence/spi/AdvancedCacheWriter
     124: aload_0
     125: getfield      #18                 // Field persistenceExecutor:Ljava/util/concurrent/Executor;
     128: aload_0
     129: invokedynamic #122,  0            // InvokeDynamic #0:entryPurged:(Lorg/infinispan/persistence/manager/PersistenceManagerImpl;)Lorg/infinispan/persistence/spi/AdvancedCacheWriter$PurgeListener;
     134: invokeinterface #123,  3          // InterfaceMethod org/infinispan/persistence/spi/AdvancedCacheWriter.purge:(Ljava/util/concurrent/Executor;Lorg/infinispan/persistence/spi/AdvancedCacheWriter$PurgeListener;)V
     139: goto          62
     142: aload_0
     143: getfield      #9                  // Field storesMutex:Ljava/util/concurrent/locks/ReadWriteLock;
     146: invokeinterface #111,  1          // InterfaceMethod java/util/concurrent/locks/ReadWriteLock.readLock:()Ljava/util/concurrent/locks/Lock;
     151: invokeinterface #97,  1           // InterfaceMethod java/util/concurrent/locks/Lock.unlock:()V
     156: goto          178
     159: astore        5
     161: aload_0
     162: getfield      #9                  // Field storesMutex:Ljava/util/concurrent/locks/ReadWriteLock;
     165: invokeinterface #111,  1          // InterfaceMethod java/util/concurrent/locks/ReadWriteLock.readLock:()Ljava/util/concurrent/locks/Lock;
     170: invokeinterface #97,  1           // InterfaceMethod java/util/concurrent/locks/Lock.unlock:()V
     175: aload         5
     177: athrow
     178: getstatic     #117                // Field trace:Z
     181: ifeq          210
     184: getstatic     #87                 // Field log:Lorg/infinispan/util/logging/Log;
     187: ldc           #124                // String Purging cache store completed in %s
     189: aload_0
     190: getfield      #17                 // Field timeService:Lorg/infinispan/util/TimeService;
     193: lload_1
     194: getstatic     #89                 // Field java/util/concurrent/TimeUnit.MILLISECONDS:Ljava/util/concurrent/TimeUnit;
     197: invokeinterface #90,  4           // InterfaceMethod org/infinispan/util/TimeService.timeDuration:(JLjava/util/concurrent/TimeUnit;)J
     202: invokestatic  #91                 // Method org/infinispan/commons/util/Util.prettyPrintTime:(J)Ljava/lang/String;
     205: invokeinterface #125,  3          // InterfaceMethod org/infinispan/util/logging/Log.tracef:(Ljava/lang/String;Ljava/lang/Object;)V
     210: goto          223
     213: astore_3
     214: getstatic     #87                 // Field log:Lorg/infinispan/util/logging/Log;
     217: aload_3
     218: invokeinterface #126,  2          // InterfaceMethod org/infinispan/util/logging/Log.exceptionPurgingDataContainer:(Ljava/lang/Exception;)V
     223: return
    Exception table:
       from    to  target type
          52   142   159   any
         159   161   159   any
          12   210   213   Class java/lang/Exception

  public void clearAllStores(org.infinispan.persistence.manager.PersistenceManager$AccessMode);
    Code:
       0: aload_0
       1: getfield      #9                  // Field storesMutex:Ljava/util/concurrent/locks/ReadWriteLock;
       4: invokeinterface #111,  1          // InterfaceMethod java/util/concurrent/locks/ReadWriteLock.readLock:()Ljava/util/concurrent/locks/Lock;
       9: invokeinterface #94,  1           // InterfaceMethod java/util/concurrent/locks/Lock.lock:()V
      14: aload_0
      15: getfield      #6                  // Field writers:Ljava/util/List;
      18: invokeinterface #33,  1           // InterfaceMethod java/util/List.iterator:()Ljava/util/Iterator;
      23: astore_2
      24: aload_2
      25: invokeinterface #34,  1           // InterfaceMethod java/util/Iterator.hasNext:()Z
      30: ifeq          82
      33: aload_2
      34: invokeinterface #35,  1           // InterfaceMethod java/util/Iterator.next:()Ljava/lang/Object;
      39: checkcast     #36                 // class org/infinispan/persistence/spi/CacheWriter
      42: astore_3
      43: aload_3
      44: instanceof    #44                 // class org/infinispan/persistence/spi/AdvancedCacheWriter
      47: ifeq          79
      50: aload_1
      51: aload_0
      52: getfield      #12                 // Field configMap:Ljava/util/Map;
      55: aload_3
      56: invokeinterface #41,  2           // InterfaceMethod java/util/Map.get:(Ljava/lang/Object;)Ljava/lang/Object;
      61: checkcast     #42                 // class org/infinispan/configuration/cache/StoreConfiguration
      64: invokevirtual #127                // Method org/infinispan/persistence/manager/PersistenceManager$AccessMode.canPerform:(Lorg/infinispan/configuration/cache/StoreConfiguration;)Z
      67: ifeq          79
      70: aload_3
      71: checkcast     #44                 // class org/infinispan/persistence/spi/AdvancedCacheWriter
      74: invokeinterface #53,  1           // InterfaceMethod org/infinispan/persistence/spi/AdvancedCacheWriter.clear:()V
      79: goto          24
      82: aload_0
      83: getfield      #9                  // Field storesMutex:Ljava/util/concurrent/locks/ReadWriteLock;
      86: invokeinterface #111,  1          // InterfaceMethod java/util/concurrent/locks/ReadWriteLock.readLock:()Ljava/util/concurrent/locks/Lock;
      91: invokeinterface #97,  1           // InterfaceMethod java/util/concurrent/locks/Lock.unlock:()V
      96: goto          118
      99: astore        4
     101: aload_0
     102: getfield      #9                  // Field storesMutex:Ljava/util/concurrent/locks/ReadWriteLock;
     105: invokeinterface #111,  1          // InterfaceMethod java/util/concurrent/locks/ReadWriteLock.readLock:()Ljava/util/concurrent/locks/Lock;
     110: invokeinterface #97,  1           // InterfaceMethod java/util/concurrent/locks/Lock.unlock:()V
     115: aload         4
     117: athrow
     118: return
    Exception table:
       from    to  target type
          14    82    99   any
          99   101    99   any

  public boolean deleteFromAllStores(java.lang.Object, org.infinispan.persistence.manager.PersistenceManager$AccessMode);
    Code:
       0: aload_0
       1: getfield      #9                  // Field storesMutex:Ljava/util/concurrent/locks/ReadWriteLock;
       4: invokeinterface #111,  1          // InterfaceMethod java/util/concurrent/locks/ReadWriteLock.readLock:()Ljava/util/concurrent/locks/Lock;
       9: invokeinterface #94,  1           // InterfaceMethod java/util/concurrent/locks/Lock.lock:()V
      14: iconst_0
      15: istore_3
      16: aload_0
      17: getfield      #6                  // Field writers:Ljava/util/List;
      20: invokeinterface #33,  1           // InterfaceMethod java/util/List.iterator:()Ljava/util/Iterator;
      25: astore        4
      27: aload         4
      29: invokeinterface #34,  1           // InterfaceMethod java/util/Iterator.hasNext:()Z
      34: ifeq          84
      37: aload         4
      39: invokeinterface #35,  1           // InterfaceMethod java/util/Iterator.next:()Ljava/lang/Object;
      44: checkcast     #36                 // class org/infinispan/persistence/spi/CacheWriter
      47: astore        5
      49: aload_2
      50: aload_0
      51: getfield      #12                 // Field configMap:Ljava/util/Map;
      54: aload         5
      56: invokeinterface #41,  2           // InterfaceMethod java/util/Map.get:(Ljava/lang/Object;)Ljava/lang/Object;
      61: checkcast     #42                 // class org/infinispan/configuration/cache/StoreConfiguration
      64: invokevirtual #127                // Method org/infinispan/persistence/manager/PersistenceManager$AccessMode.canPerform:(Lorg/infinispan/configuration/cache/StoreConfiguration;)Z
      67: ifeq          81
      70: iload_3
      71: aload         5
      73: aload_1
      74: invokeinterface #128,  2          // InterfaceMethod org/infinispan/persistence/spi/CacheWriter.delete:(Ljava/lang/Object;)Z
      79: ior
      80: istore_3
      81: goto          27
      84: iload_3
      85: istore        4
      87: aload_0
      88: getfield      #9                  // Field storesMutex:Ljava/util/concurrent/locks/ReadWriteLock;
      91: invokeinterface #111,  1          // InterfaceMethod java/util/concurrent/locks/ReadWriteLock.readLock:()Ljava/util/concurrent/locks/Lock;
      96: invokeinterface #97,  1           // InterfaceMethod java/util/concurrent/locks/Lock.unlock:()V
     101: iload         4
     103: ireturn
     104: astore        6
     106: aload_0
     107: getfield      #9                  // Field storesMutex:Ljava/util/concurrent/locks/ReadWriteLock;
     110: invokeinterface #111,  1          // InterfaceMethod java/util/concurrent/locks/ReadWriteLock.readLock:()Ljava/util/concurrent/locks/Lock;
     115: invokeinterface #97,  1           // InterfaceMethod java/util/concurrent/locks/Lock.unlock:()V
     120: aload         6
     122: athrow
    Exception table:
       from    to  target type
          14    87   104   any
         104   106   104   any

  public void processOnAllStores(org.infinispan.filter.KeyFilter, org.infinispan.persistence.spi.AdvancedCacheLoader$CacheLoaderTask, boolean, boolean);
    Code:
       0: aload_0
       1: aload_0
       2: getfield      #18                 // Field persistenceExecutor:Ljava/util/concurrent/Executor;
       5: aload_1
       6: aload_2
       7: iload_3
       8: iload         4
      10: invokevirtual #129                // Method processOnAllStores:(Ljava/util/concurrent/Executor;Lorg/infinispan/filter/KeyFilter;Lorg/infinispan/persistence/spi/AdvancedCacheLoader$CacheLoaderTask;ZZ)V
      13: return

  public void processOnAllStores(java.util.concurrent.Executor, org.infinispan.filter.KeyFilter, org.infinispan.persistence.spi.AdvancedCacheLoader$CacheLoaderTask, boolean, boolean);
    Code:
       0: aload_0
       1: aload_1
       2: aload_2
       3: aload_3
       4: iload         4
       6: iload         5
       8: getstatic     #65                 // Field org/infinispan/persistence/manager/PersistenceManager$AccessMode.BOTH:Lorg/infinispan/persistence/manager/PersistenceManager$AccessMode;
      11: invokevirtual #130                // Method processOnAllStores:(Ljava/util/concurrent/Executor;Lorg/infinispan/filter/KeyFilter;Lorg/infinispan/persistence/spi/AdvancedCacheLoader$CacheLoaderTask;ZZLorg/infinispan/persistence/manager/PersistenceManager$AccessMode;)V
      14: return

  public void processOnAllStores(org.infinispan.filter.KeyFilter, org.infinispan.persistence.spi.AdvancedCacheLoader$CacheLoaderTask, boolean, boolean, org.infinispan.persistence.manager.PersistenceManager$AccessMode);
    Code:
       0: aload_0
       1: aload_0
       2: getfield      #18                 // Field persistenceExecutor:Ljava/util/concurrent/Executor;
       5: aload_1
       6: aload_2
       7: iload_3
       8: iload         4
      10: aload         5
      12: invokevirtual #130                // Method processOnAllStores:(Ljava/util/concurrent/Executor;Lorg/infinispan/filter/KeyFilter;Lorg/infinispan/persistence/spi/AdvancedCacheLoader$CacheLoaderTask;ZZLorg/infinispan/persistence/manager/PersistenceManager$AccessMode;)V
      15: return

  public void processOnAllStores(java.util.concurrent.Executor, org.infinispan.filter.KeyFilter, org.infinispan.persistence.spi.AdvancedCacheLoader$CacheLoaderTask, boolean, boolean, org.infinispan.persistence.manager.PersistenceManager$AccessMode);
    Code:
       0: aload_0
       1: getfield      #9                  // Field storesMutex:Ljava/util/concurrent/locks/ReadWriteLock;
       4: invokeinterface #111,  1          // InterfaceMethod java/util/concurrent/locks/ReadWriteLock.readLock:()Ljava/util/concurrent/locks/Lock;
       9: invokeinterface #94,  1           // InterfaceMethod java/util/concurrent/locks/Lock.lock:()V
      14: aload_0
      15: getfield      #5                  // Field loaders:Ljava/util/List;
      18: invokeinterface #33,  1           // InterfaceMethod java/util/List.iterator:()Ljava/util/Iterator;
      23: astore        7
      25: aload         7
      27: invokeinterface #34,  1           // InterfaceMethod java/util/Iterator.hasNext:()Z
      32: ifeq          97
      35: aload         7
      37: invokeinterface #35,  1           // InterfaceMethod java/util/Iterator.next:()Ljava/lang/Object;
      42: checkcast     #54                 // class org/infinispan/persistence/spi/CacheLoader
      45: astore        8
      47: aload         6
      49: aload_0
      50: getfield      #12                 // Field configMap:Ljava/util/Map;
      53: aload         8
      55: invokeinterface #41,  2           // InterfaceMethod java/util/Map.get:(Ljava/lang/Object;)Ljava/lang/Object;
      60: checkcast     #42                 // class org/infinispan/configuration/cache/StoreConfiguration
      63: invokevirtual #127                // Method org/infinispan/persistence/manager/PersistenceManager$AccessMode.canPerform:(Lorg/infinispan/configuration/cache/StoreConfiguration;)Z
      66: ifeq          94
      69: aload         8
      71: instanceof    #70                 // class org/infinispan/persistence/spi/AdvancedCacheLoader
      74: ifeq          94
      77: aload         8
      79: checkcast     #70                 // class org/infinispan/persistence/spi/AdvancedCacheLoader
      82: aload_2
      83: aload_3
      84: aload_1
      85: iload         4
      87: iload         5
      89: invokeinterface #86,  6           // InterfaceMethod org/infinispan/persistence/spi/AdvancedCacheLoader.process:(Lorg/infinispan/filter/KeyFilter;Lorg/infinispan/persistence/spi/AdvancedCacheLoader$CacheLoaderTask;Ljava/util/concurrent/Executor;ZZ)V
      94: goto          25
      97: aload_0
      98: getfield      #9                  // Field storesMutex:Ljava/util/concurrent/locks/ReadWriteLock;
     101: invokeinterface #111,  1          // InterfaceMethod java/util/concurrent/locks/ReadWriteLock.readLock:()Ljava/util/concurrent/locks/Lock;
     106: invokeinterface #97,  1           // InterfaceMethod java/util/concurrent/locks/Lock.unlock:()V
     111: goto          133
     114: astore        9
     116: aload_0
     117: getfield      #9                  // Field storesMutex:Ljava/util/concurrent/locks/ReadWriteLock;
     120: invokeinterface #111,  1          // InterfaceMethod java/util/concurrent/locks/ReadWriteLock.readLock:()Ljava/util/concurrent/locks/Lock;
     125: invokeinterface #97,  1           // InterfaceMethod java/util/concurrent/locks/Lock.unlock:()V
     130: aload         9
     132: athrow
     133: return
    Exception table:
       from    to  target type
          14    97   114   any
         114   116   114   any

  public org.infinispan.marshall.core.MarshalledEntry loadFromAllStores(java.lang.Object, org.infinispan.context.InvocationContext);
    Code:
       0: aload_0
       1: getfield      #9                  // Field storesMutex:Ljava/util/concurrent/locks/ReadWriteLock;
       4: invokeinterface #111,  1          // InterfaceMethod java/util/concurrent/locks/ReadWriteLock.readLock:()Ljava/util/concurrent/locks/Lock;
       9: invokeinterface #94,  1           // InterfaceMethod java/util/concurrent/locks/Lock.lock:()V
      14: aload_0
      15: getfield      #5                  // Field loaders:Ljava/util/List;
      18: invokeinterface #33,  1           // InterfaceMethod java/util/List.iterator:()Ljava/util/Iterator;
      23: astore_3
      24: aload_3
      25: invokeinterface #34,  1           // InterfaceMethod java/util/Iterator.hasNext:()Z
      30: ifeq          104
      33: aload_3
      34: invokeinterface #35,  1           // InterfaceMethod java/util/Iterator.next:()Ljava/lang/Object;
      39: checkcast     #54                 // class org/infinispan/persistence/spi/CacheLoader
      42: astore        4
      44: aload_2
      45: invokeinterface #131,  1          // InterfaceMethod org/infinispan/context/InvocationContext.isOriginLocal:()Z
      50: ifne          65
      53: aload_0
      54: aload         4
      56: invokespecial #132                // Method isLocalOnlyLoader:(Lorg/infinispan/persistence/spi/CacheLoader;)Z
      59: ifeq          65
      62: goto          24
      65: aload         4
      67: aload_1
      68: invokeinterface #133,  2          // InterfaceMethod org/infinispan/persistence/spi/CacheLoader.load:(Ljava/lang/Object;)Lorg/infinispan/marshall/core/MarshalledEntry;
      73: astore        5
      75: aload         5
      77: ifnull        101
      80: aload         5
      82: astore        6
      84: aload_0
      85: getfield      #9                  // Field storesMutex:Ljava/util/concurrent/locks/ReadWriteLock;
      88: invokeinterface #111,  1          // InterfaceMethod java/util/concurrent/locks/ReadWriteLock.readLock:()Ljava/util/concurrent/locks/Lock;
      93: invokeinterface #97,  1           // InterfaceMethod java/util/concurrent/locks/Lock.unlock:()V
      98: aload         6
     100: areturn
     101: goto          24
     104: aconst_null
     105: astore_3
     106: aload_0
     107: getfield      #9                  // Field storesMutex:Ljava/util/concurrent/locks/ReadWriteLock;
     110: invokeinterface #111,  1          // InterfaceMethod java/util/concurrent/locks/ReadWriteLock.readLock:()Ljava/util/concurrent/locks/Lock;
     115: invokeinterface #97,  1           // InterfaceMethod java/util/concurrent/locks/Lock.unlock:()V
     120: aload_3
     121: areturn
     122: astore        7
     124: aload_0
     125: getfield      #9                  // Field storesMutex:Ljava/util/concurrent/locks/ReadWriteLock;
     128: invokeinterface #111,  1          // InterfaceMethod java/util/concurrent/locks/ReadWriteLock.readLock:()Ljava/util/concurrent/locks/Lock;
     133: invokeinterface #97,  1           // InterfaceMethod java/util/concurrent/locks/Lock.unlock:()V
     138: aload         7
     140: athrow
    Exception table:
       from    to  target type
          14    84   122   any
         101   106   122   any
         122   124   122   any

  private boolean isLocalOnlyLoader(org.infinispan.persistence.spi.CacheLoader);
    Code:
       0: aload_1
       1: instanceof    #134                // class org/infinispan/persistence/spi/LocalOnlyCacheLoader
       4: ifeq          9
       7: iconst_1
       8: ireturn
       9: aload_1
      10: instanceof    #57                 // class org/infinispan/persistence/support/DelegatingCacheLoader
      13: ifeq          33
      16: aload_1
      17: checkcast     #57                 // class org/infinispan/persistence/support/DelegatingCacheLoader
      20: invokevirtual #135                // Method org/infinispan/persistence/support/DelegatingCacheLoader.undelegate:()Lorg/infinispan/persistence/spi/CacheLoader;
      23: astore_2
      24: aload_2
      25: instanceof    #134                // class org/infinispan/persistence/spi/LocalOnlyCacheLoader
      28: ifeq          33
      31: iconst_1
      32: ireturn
      33: iconst_0
      34: ireturn

  public void writeToAllStores(org.infinispan.marshall.core.MarshalledEntry, org.infinispan.persistence.manager.PersistenceManager$AccessMode);
    Code:
       0: aload_0
       1: getfield      #9                  // Field storesMutex:Ljava/util/concurrent/locks/ReadWriteLock;
       4: invokeinterface #111,  1          // InterfaceMethod java/util/concurrent/locks/ReadWriteLock.readLock:()Ljava/util/concurrent/locks/Lock;
       9: invokeinterface #94,  1           // InterfaceMethod java/util/concurrent/locks/Lock.lock:()V
      14: aload_0
      15: getfield      #6                  // Field writers:Ljava/util/List;
      18: invokeinterface #33,  1           // InterfaceMethod java/util/List.iterator:()Ljava/util/Iterator;
      23: astore_3
      24: aload_3
      25: invokeinterface #34,  1           // InterfaceMethod java/util/Iterator.hasNext:()Z
      30: ifeq          76
      33: aload_3
      34: invokeinterface #35,  1           // InterfaceMethod java/util/Iterator.next:()Ljava/lang/Object;
      39: checkcast     #36                 // class org/infinispan/persistence/spi/CacheWriter
      42: astore        4
      44: aload_2
      45: aload_0
      46: getfield      #12                 // Field configMap:Ljava/util/Map;
      49: aload         4
      51: invokeinterface #41,  2           // InterfaceMethod java/util/Map.get:(Ljava/lang/Object;)Ljava/lang/Object;
      56: checkcast     #42                 // class org/infinispan/configuration/cache/StoreConfiguration
      59: invokevirtual #127                // Method org/infinispan/persistence/manager/PersistenceManager$AccessMode.canPerform:(Lorg/infinispan/configuration/cache/StoreConfiguration;)Z
      62: ifeq          73
      65: aload         4
      67: aload_1
      68: invokeinterface #136,  2          // InterfaceMethod org/infinispan/persistence/spi/CacheWriter.write:(Lorg/infinispan/marshall/core/MarshalledEntry;)V
      73: goto          24
      76: aload_0
      77: getfield      #9                  // Field storesMutex:Ljava/util/concurrent/locks/ReadWriteLock;
      80: invokeinterface #111,  1          // InterfaceMethod java/util/concurrent/locks/ReadWriteLock.readLock:()Ljava/util/concurrent/locks/Lock;
      85: invokeinterface #97,  1           // InterfaceMethod java/util/concurrent/locks/Lock.unlock:()V
      90: goto          112
      93: astore        5
      95: aload_0
      96: getfield      #9                  // Field storesMutex:Ljava/util/concurrent/locks/ReadWriteLock;
      99: invokeinterface #111,  1          // InterfaceMethod java/util/concurrent/locks/ReadWriteLock.readLock:()Ljava/util/concurrent/locks/Lock;
     104: invokeinterface #97,  1           // InterfaceMethod java/util/concurrent/locks/Lock.unlock:()V
     109: aload         5
     111: athrow
     112: return
    Exception table:
       from    to  target type
          14    76    93   any
          93    95    93   any

  public org.infinispan.persistence.spi.AdvancedCacheLoader getStateTransferProvider();
    Code:
       0: aload_0
       1: getfield      #9                  // Field storesMutex:Ljava/util/concurrent/locks/ReadWriteLock;
       4: invokeinterface #111,  1          // InterfaceMethod java/util/concurrent/locks/ReadWriteLock.readLock:()Ljava/util/concurrent/locks/Lock;
       9: invokeinterface #94,  1           // InterfaceMethod java/util/concurrent/locks/Lock.lock:()V
      14: aload_0
      15: getfield      #5                  // Field loaders:Ljava/util/List;
      18: invokeinterface #33,  1           // InterfaceMethod java/util/List.iterator:()Ljava/util/Iterator;
      23: astore_1
      24: aload_1
      25: invokeinterface #34,  1           // InterfaceMethod java/util/Iterator.hasNext:()Z
      30: ifeq          101
      33: aload_1
      34: invokeinterface #35,  1           // InterfaceMethod java/util/Iterator.next:()Ljava/lang/Object;
      39: checkcast     #54                 // class org/infinispan/persistence/spi/CacheLoader
      42: astore_2
      43: aload_0
      44: getfield      #12                 // Field configMap:Ljava/util/Map;
      47: aload_2
      48: invokeinterface #41,  2           // InterfaceMethod java/util/Map.get:(Ljava/lang/Object;)Ljava/lang/Object;
      53: checkcast     #42                 // class org/infinispan/configuration/cache/StoreConfiguration
      56: astore_3
      57: aload_3
      58: invokeinterface #137,  1          // InterfaceMethod org/infinispan/configuration/cache/StoreConfiguration.fetchPersistentState:()Z
      63: ifeq          98
      66: aload_3
      67: invokeinterface #138,  1          // InterfaceMethod org/infinispan/configuration/cache/StoreConfiguration.shared:()Z
      72: ifne          98
      75: aload_2
      76: checkcast     #70                 // class org/infinispan/persistence/spi/AdvancedCacheLoader
      79: astore        4
      81: aload_0
      82: getfield      #9                  // Field storesMutex:Ljava/util/concurrent/locks/ReadWriteLock;
      85: invokeinterface #111,  1          // InterfaceMethod java/util/concurrent/locks/ReadWriteLock.readLock:()Ljava/util/concurrent/locks/Lock;
      90: invokeinterface #97,  1           // InterfaceMethod java/util/concurrent/locks/Lock.unlock:()V
      95: aload         4
      97: areturn
      98: goto          24
     101: aconst_null
     102: astore_1
     103: aload_0
     104: getfield      #9                  // Field storesMutex:Ljava/util/concurrent/locks/ReadWriteLock;
     107: invokeinterface #111,  1          // InterfaceMethod java/util/concurrent/locks/ReadWriteLock.readLock:()Ljava/util/concurrent/locks/Lock;
     112: invokeinterface #97,  1           // InterfaceMethod java/util/concurrent/locks/Lock.unlock:()V
     117: aload_1
     118: areturn
     119: astore        5
     121: aload_0
     122: getfield      #9                  // Field storesMutex:Ljava/util/concurrent/locks/ReadWriteLock;
     125: invokeinterface #111,  1          // InterfaceMethod java/util/concurrent/locks/ReadWriteLock.readLock:()Ljava/util/concurrent/locks/Lock;
     130: invokeinterface #97,  1           // InterfaceMethod java/util/concurrent/locks/Lock.unlock:()V
     135: aload         5
     137: athrow
    Exception table:
       from    to  target type
          14    81   119   any
          98   103   119   any
         119   121   119   any

  public int size();
    Code:
       0: aload_0
       1: getfield      #9                  // Field storesMutex:Ljava/util/concurrent/locks/ReadWriteLock;
       4: invokeinterface #111,  1          // InterfaceMethod java/util/concurrent/locks/ReadWriteLock.readLock:()Ljava/util/concurrent/locks/Lock;
       9: invokeinterface #94,  1           // InterfaceMethod java/util/concurrent/locks/Lock.lock:()V
      14: aload_0
      15: getfield      #5                  // Field loaders:Ljava/util/List;
      18: invokeinterface #33,  1           // InterfaceMethod java/util/List.iterator:()Ljava/util/Iterator;
      23: astore_1
      24: aload_1
      25: invokeinterface #34,  1           // InterfaceMethod java/util/Iterator.hasNext:()Z
      30: ifeq          79
      33: aload_1
      34: invokeinterface #35,  1           // InterfaceMethod java/util/Iterator.next:()Ljava/lang/Object;
      39: checkcast     #54                 // class org/infinispan/persistence/spi/CacheLoader
      42: astore_2
      43: aload_2
      44: instanceof    #70                 // class org/infinispan/persistence/spi/AdvancedCacheLoader
      47: ifeq          76
      50: aload_2
      51: checkcast     #70                 // class org/infinispan/persistence/spi/AdvancedCacheLoader
      54: invokeinterface #139,  1          // InterfaceMethod org/infinispan/persistence/spi/AdvancedCacheLoader.size:()I
      59: istore_3
      60: aload_0
      61: getfield      #9                  // Field storesMutex:Ljava/util/concurrent/locks/ReadWriteLock;
      64: invokeinterface #111,  1          // InterfaceMethod java/util/concurrent/locks/ReadWriteLock.readLock:()Ljava/util/concurrent/locks/Lock;
      69: invokeinterface #97,  1           // InterfaceMethod java/util/concurrent/locks/Lock.unlock:()V
      74: iload_3
      75: ireturn
      76: goto          24
      79: aload_0
      80: getfield      #9                  // Field storesMutex:Ljava/util/concurrent/locks/ReadWriteLock;
      83: invokeinterface #111,  1          // InterfaceMethod java/util/concurrent/locks/ReadWriteLock.readLock:()Ljava/util/concurrent/locks/Lock;
      88: invokeinterface #97,  1           // InterfaceMethod java/util/concurrent/locks/Lock.unlock:()V
      93: goto          115
      96: astore        4
      98: aload_0
      99: getfield      #9                  // Field storesMutex:Ljava/util/concurrent/locks/ReadWriteLock;
     102: invokeinterface #111,  1          // InterfaceMethod java/util/concurrent/locks/ReadWriteLock.readLock:()Ljava/util/concurrent/locks/Lock;
     107: invokeinterface #97,  1           // InterfaceMethod java/util/concurrent/locks/Lock.unlock:()V
     112: aload         4
     114: athrow
     115: iconst_0
     116: ireturn
    Exception table:
       from    to  target type
          14    60    96   any
          76    79    96   any
          96    98    96   any

  public void setClearOnStop(boolean);
    Code:
       0: aload_0
       1: iload_1
       2: putfield      #64                 // Field clearOnStop:Z
       5: return

  public java.util.List<org.infinispan.persistence.spi.CacheLoader> getAllLoaders();
    Code:
       0: aload_0
       1: getfield      #5                  // Field loaders:Ljava/util/List;
       4: invokestatic  #140                // Method java/util/Collections.unmodifiableList:(Ljava/util/List;)Ljava/util/List;
       7: areturn

  public java.util.List<org.infinispan.persistence.spi.CacheWriter> getAllWriters();
    Code:
       0: aload_0
       1: getfield      #6                  // Field writers:Ljava/util/List;
       4: invokestatic  #140                // Method java/util/Collections.unmodifiableList:(Ljava/util/List;)Ljava/util/List;
       7: areturn

  private void createLoadersAndWriters();
    Code:
       0: aload_0
       1: getfield      #15                 // Field configuration:Lorg/infinispan/configuration/cache/Configuration;
       4: invokevirtual #26                 // Method org/infinispan/configuration/cache/Configuration.persistence:()Lorg/infinispan/configuration/cache/PersistenceConfiguration;
       7: invokevirtual #141                // Method org/infinispan/configuration/cache/PersistenceConfiguration.stores:()Ljava/util/List;
      10: invokeinterface #33,  1           // InterfaceMethod java/util/List.iterator:()Ljava/util/Iterator;
      15: astore_1
      16: aload_1
      17: invokeinterface #34,  1           // InterfaceMethod java/util/Iterator.hasNext:()Z
      22: ifeq          151
      25: aload_1
      26: invokeinterface #35,  1           // InterfaceMethod java/util/Iterator.next:()Ljava/lang/Object;
      31: checkcast     #42                 // class org/infinispan/configuration/cache/StoreConfiguration
      34: astore_2
      35: aload_0
      36: getfield      #21                 // Field cacheStoreFactoryRegistry:Lorg/infinispan/persistence/factory/CacheStoreFactoryRegistry;
      39: aload_2
      40: invokevirtual #142                // Method org/infinispan/persistence/factory/CacheStoreFactoryRegistry.createInstance:(Lorg/infinispan/configuration/cache/StoreConfiguration;)Ljava/lang/Object;
      43: astore_3
      44: aload_0
      45: getfield      #21                 // Field cacheStoreFactoryRegistry:Lorg/infinispan/persistence/factory/CacheStoreFactoryRegistry;
      48: aload_2
      49: invokevirtual #143                // Method org/infinispan/persistence/factory/CacheStoreFactoryRegistry.processStoreConfiguration:(Lorg/infinispan/configuration/cache/StoreConfiguration;)Lorg/infinispan/configuration/cache/StoreConfiguration;
      52: astore        4
      54: aload_0
      55: aload_3
      56: invokespecial #144                // Method createCacheWriter:(Ljava/lang/Object;)Lorg/infinispan/persistence/spi/CacheWriter;
      59: astore        5
      61: aload_0
      62: aload_3
      63: invokespecial #145                // Method createCacheLoader:(Ljava/lang/Object;)Lorg/infinispan/persistence/spi/CacheLoader;
      66: astore        6
      68: aload_0
      69: aload         4
      71: aload         5
      73: invokespecial #146                // Method postProcessWriter:(Lorg/infinispan/configuration/cache/StoreConfiguration;Lorg/infinispan/persistence/spi/CacheWriter;)Lorg/infinispan/persistence/spi/CacheWriter;
      76: astore        5
      78: aload_0
      79: aload         4
      81: aload         5
      83: aload         6
      85: invokespecial #147                // Method postProcessReader:(Lorg/infinispan/configuration/cache/StoreConfiguration;Lorg/infinispan/persistence/spi/CacheWriter;Lorg/infinispan/persistence/spi/CacheLoader;)Lorg/infinispan/persistence/spi/CacheLoader;
      88: astore        6
      90: new           #148                // class org/infinispan/persistence/InitializationContextImpl
      93: dup
      94: aload         4
      96: aload_0
      97: getfield      #13                 // Field cache:Lorg/infinispan/AdvancedCache;
     100: aload_0
     101: getfield      #14                 // Field m:Lorg/infinispan/commons/marshall/StreamingMarshaller;
     104: aload_0
     105: getfield      #17                 // Field timeService:Lorg/infinispan/util/TimeService;
     108: aload_0
     109: getfield      #19                 // Field byteBufferFactory:Lorg/infinispan/commons/io/ByteBufferFactory;
     112: aload_0
     113: getfield      #20                 // Field marshalledEntryFactory:Lorg/infinispan/marshall/core/MarshalledEntryFactory;
     116: invokespecial #149                // Method org/infinispan/persistence/InitializationContextImpl."<init>":(Lorg/infinispan/configuration/cache/StoreConfiguration;Lorg/infinispan/Cache;Lorg/infinispan/commons/marshall/StreamingMarshaller;Lorg/infinispan/util/TimeService;Lorg/infinispan/commons/io/ByteBufferFactory;Lorg/infinispan/marshall/core/MarshalledEntryFactory;)V
     119: astore        7
     121: aload_0
     122: aload         4
     124: aload         6
     126: aload         7
     128: invokespecial #150                // Method initializeLoader:(Lorg/infinispan/configuration/cache/StoreConfiguration;Lorg/infinispan/persistence/spi/CacheLoader;Lorg/infinispan/persistence/InitializationContextImpl;)V
     131: aload_0
     132: aload         4
     134: aload         5
     136: aload         7
     138: invokespecial #151                // Method initializeWriter:(Lorg/infinispan/configuration/cache/StoreConfiguration;Lorg/infinispan/persistence/spi/CacheWriter;Lorg/infinispan/persistence/InitializationContextImpl;)V
     141: aload_0
     142: aload_3
     143: aload         7
     145: invokespecial #152                // Method initializeBareInstance:(Ljava/lang/Object;Lorg/infinispan/persistence/InitializationContextImpl;)V
     148: goto          16
     151: return

  private org.infinispan.persistence.spi.CacheLoader postProcessReader(org.infinispan.configuration.cache.StoreConfiguration, org.infinispan.persistence.spi.CacheWriter, org.infinispan.persistence.spi.CacheLoader);
    Code:
       0: aload_1
       1: invokeinterface #153,  1          // InterfaceMethod org/infinispan/configuration/cache/StoreConfiguration.async:()Lorg/infinispan/configuration/cache/AsyncStoreConfiguration;
       6: invokevirtual #154                // Method org/infinispan/configuration/cache/AsyncStoreConfiguration.enabled:()Z
       9: ifeq          30
      12: aload_3
      13: ifnull        30
      16: aload_2
      17: ifnull        30
      20: aload_0
      21: aload_3
      22: aload_2
      23: checkcast     #155                // class org/infinispan/persistence/async/AsyncCacheWriter
      26: invokespecial #156                // Method createAsyncLoader:(Lorg/infinispan/persistence/spi/CacheLoader;Lorg/infinispan/persistence/async/AsyncCacheWriter;)Lorg/infinispan/persistence/spi/CacheLoader;
      29: astore_3
      30: aload_3
      31: areturn

  private org.infinispan.persistence.spi.CacheWriter postProcessWriter(org.infinispan.configuration.cache.StoreConfiguration, org.infinispan.persistence.spi.CacheWriter);
    Code:
       0: aload_2
       1: ifnull        58
       4: aload_1
       5: invokeinterface #157,  1          // InterfaceMethod org/infinispan/configuration/cache/StoreConfiguration.ignoreModifications:()Z
      10: ifeq          18
      13: aconst_null
      14: astore_2
      15: goto          58
      18: aload_1
      19: invokeinterface #158,  1          // InterfaceMethod org/infinispan/configuration/cache/StoreConfiguration.singletonStore:()Lorg/infinispan/configuration/cache/SingletonStoreConfiguration;
      24: invokevirtual #159                // Method org/infinispan/configuration/cache/SingletonStoreConfiguration.enabled:()Z
      27: ifeq          40
      30: aload_0
      31: aload_1
      32: aload_2
      33: invokespecial #160                // Method createSingletonWriter:(Lorg/infinispan/configuration/cache/StoreConfiguration;Lorg/infinispan/persistence/spi/CacheWriter;)Lorg/infinispan/persistence/support/SingletonCacheWriter;
      36: astore_2
      37: goto          58
      40: aload_1
      41: invokeinterface #153,  1          // InterfaceMethod org/infinispan/configuration/cache/StoreConfiguration.async:()Lorg/infinispan/configuration/cache/AsyncStoreConfiguration;
      46: invokevirtual #154                // Method org/infinispan/configuration/cache/AsyncStoreConfiguration.enabled:()Z
      49: ifeq          58
      52: aload_0
      53: aload_2
      54: invokevirtual #161                // Method createAsyncWriter:(Lorg/infinispan/persistence/spi/CacheWriter;)Lorg/infinispan/persistence/async/AsyncCacheWriter;
      57: astore_2
      58: aload_2
      59: areturn

  private org.infinispan.persistence.spi.CacheLoader createAsyncLoader(org.infinispan.persistence.spi.CacheLoader, org.infinispan.persistence.async.AsyncCacheWriter);
    Code:
       0: aload_2
       1: invokevirtual #162                // Method org/infinispan/persistence/async/AsyncCacheWriter.getState:()Ljava/util/concurrent/atomic/AtomicReference;
       4: astore_3
       5: aload_1
       6: instanceof    #70                 // class org/infinispan/persistence/spi/AdvancedCacheLoader
       9: ifeq          24
      12: new           #75                 // class org/infinispan/persistence/async/AdvancedAsyncCacheLoader
      15: dup
      16: aload_1
      17: aload_3
      18: invokespecial #163                // Method org/infinispan/persistence/async/AdvancedAsyncCacheLoader."<init>":(Lorg/infinispan/persistence/spi/CacheLoader;Ljava/util/concurrent/atomic/AtomicReference;)V
      21: goto          33
      24: new           #164                // class org/infinispan/persistence/async/AsyncCacheLoader
      27: dup
      28: aload_1
      29: aload_3
      30: invokespecial #165                // Method org/infinispan/persistence/async/AsyncCacheLoader."<init>":(Lorg/infinispan/persistence/spi/CacheLoader;Ljava/util/concurrent/atomic/AtomicReference;)V
      33: astore_1
      34: aload_1
      35: areturn

  private org.infinispan.persistence.support.SingletonCacheWriter createSingletonWriter(org.infinispan.configuration.cache.StoreConfiguration, org.infinispan.persistence.spi.CacheWriter);
    Code:
       0: aload_2
       1: instanceof    #44                 // class org/infinispan/persistence/spi/AdvancedCacheWriter
       4: ifeq          24
       7: new           #166                // class org/infinispan/persistence/support/AdvancedSingletonCacheWriter
      10: dup
      11: aload_2
      12: aload_1
      13: invokeinterface #158,  1          // InterfaceMethod org/infinispan/configuration/cache/StoreConfiguration.singletonStore:()Lorg/infinispan/configuration/cache/SingletonStoreConfiguration;
      18: invokespecial #167                // Method org/infinispan/persistence/support/AdvancedSingletonCacheWriter."<init>":(Lorg/infinispan/persistence/spi/CacheWriter;Lorg/infinispan/configuration/cache/SingletonStoreConfiguration;)V
      21: goto          38
      24: new           #168                // class org/infinispan/persistence/support/SingletonCacheWriter
      27: dup
      28: aload_2
      29: aload_1
      30: invokeinterface #158,  1          // InterfaceMethod org/infinispan/configuration/cache/StoreConfiguration.singletonStore:()Lorg/infinispan/configuration/cache/SingletonStoreConfiguration;
      35: invokespecial #169                // Method org/infinispan/persistence/support/SingletonCacheWriter."<init>":(Lorg/infinispan/persistence/spi/CacheWriter;Lorg/infinispan/configuration/cache/SingletonStoreConfiguration;)V
      38: areturn

  private void initializeWriter(org.infinispan.configuration.cache.StoreConfiguration, org.infinispan.persistence.spi.CacheWriter, org.infinispan.persistence.InitializationContextImpl);
    Code:
       0: aload_2
       1: ifnull        41
       4: aload_2
       5: instanceof    #38                 // class org/infinispan/persistence/support/DelegatingCacheWriter
       8: ifeq          18
      11: aload_2
      12: aload_3
      13: invokeinterface #170,  2          // InterfaceMethod org/infinispan/persistence/spi/CacheWriter.init:(Lorg/infinispan/persistence/spi/InitializationContext;)V
      18: aload_0
      19: getfield      #6                  // Field writers:Ljava/util/List;
      22: aload_2
      23: invokeinterface #171,  2          // InterfaceMethod java/util/List.add:(Ljava/lang/Object;)Z
      28: pop
      29: aload_0
      30: getfield      #12                 // Field configMap:Ljava/util/Map;
      33: aload_2
      34: aload_1
      35: invokeinterface #172,  3          // InterfaceMethod java/util/Map.put:(Ljava/lang/Object;Ljava/lang/Object;)Ljava/lang/Object;
      40: pop
      41: return

  private void initializeLoader(org.infinispan.configuration.cache.StoreConfiguration, org.infinispan.persistence.spi.CacheLoader, org.infinispan.persistence.InitializationContextImpl);
    Code:
       0: aload_2
       1: ifnull        41
       4: aload_2
       5: instanceof    #57                 // class org/infinispan/persistence/support/DelegatingCacheLoader
       8: ifeq          18
      11: aload_2
      12: aload_3
      13: invokeinterface #173,  2          // InterfaceMethod org/infinispan/persistence/spi/CacheLoader.init:(Lorg/infinispan/persistence/spi/InitializationContext;)V
      18: aload_0
      19: getfield      #5                  // Field loaders:Ljava/util/List;
      22: aload_2
      23: invokeinterface #171,  2          // InterfaceMethod java/util/List.add:(Ljava/lang/Object;)Z
      28: pop
      29: aload_0
      30: getfield      #12                 // Field configMap:Ljava/util/Map;
      33: aload_2
      34: aload_1
      35: invokeinterface #172,  3          // InterfaceMethod java/util/Map.put:(Ljava/lang/Object;Ljava/lang/Object;)Ljava/lang/Object;
      40: pop
      41: return

  private void initializeBareInstance(java.lang.Object, org.infinispan.persistence.InitializationContextImpl);
    Code:
       0: aload_1
       1: instanceof    #36                 // class org/infinispan/persistence/spi/CacheWriter
       4: ifeq          20
       7: aload_1
       8: checkcast     #36                 // class org/infinispan/persistence/spi/CacheWriter
      11: aload_2
      12: invokeinterface #170,  2          // InterfaceMethod org/infinispan/persistence/spi/CacheWriter.init:(Lorg/infinispan/persistence/spi/InitializationContext;)V
      17: goto          30
      20: aload_1
      21: checkcast     #54                 // class org/infinispan/persistence/spi/CacheLoader
      24: aload_2
      25: invokeinterface #173,  2          // InterfaceMethod org/infinispan/persistence/spi/CacheLoader.init:(Lorg/infinispan/persistence/spi/InitializationContext;)V
      30: return

  private org.infinispan.persistence.spi.CacheLoader createCacheLoader(java.lang.Object);
    Code:
       0: aload_1
       1: instanceof    #54                 // class org/infinispan/persistence/spi/CacheLoader
       4: ifeq          14
       7: aload_1
       8: checkcast     #54                 // class org/infinispan/persistence/spi/CacheLoader
      11: goto          15
      14: aconst_null
      15: areturn

  private org.infinispan.persistence.spi.CacheWriter createCacheWriter(java.lang.Object);
    Code:
       0: aload_1
       1: instanceof    #36                 // class org/infinispan/persistence/spi/CacheWriter
       4: ifeq          14
       7: aload_1
       8: checkcast     #36                 // class org/infinispan/persistence/spi/CacheWriter
      11: goto          15
      14: aconst_null
      15: areturn

  protected org.infinispan.persistence.async.AsyncCacheWriter createAsyncWriter(org.infinispan.persistence.spi.CacheWriter);
    Code:
       0: aload_1
       1: instanceof    #44                 // class org/infinispan/persistence/spi/AdvancedCacheWriter
       4: ifeq          18
       7: new           #174                // class org/infinispan/persistence/async/AdvancedAsyncCacheWriter
      10: dup
      11: aload_1
      12: invokespecial #175                // Method org/infinispan/persistence/async/AdvancedAsyncCacheWriter."<init>":(Lorg/infinispan/persistence/spi/CacheWriter;)V
      15: goto          26
      18: new           #155                // class org/infinispan/persistence/async/AsyncCacheWriter
      21: dup
      22: aload_1
      23: invokespecial #176                // Method org/infinispan/persistence/async/AsyncCacheWriter."<init>":(Lorg/infinispan/persistence/spi/CacheWriter;)V
      26: areturn

  private org.infinispan.persistence.spi.CacheLoader undelegate(org.infinispan.persistence.spi.CacheLoader);
    Code:
       0: aload_1
       1: instanceof    #57                 // class org/infinispan/persistence/support/DelegatingCacheLoader
       4: ifeq          17
       7: aload_1
       8: checkcast     #57                 // class org/infinispan/persistence/support/DelegatingCacheLoader
      11: invokevirtual #135                // Method org/infinispan/persistence/support/DelegatingCacheLoader.undelegate:()Lorg/infinispan/persistence/spi/CacheLoader;
      14: goto          18
      17: aload_1
      18: areturn

  private org.infinispan.persistence.spi.CacheWriter undelegate(org.infinispan.persistence.spi.CacheWriter);
    Code:
       0: aload_1
       1: instanceof    #38                 // class org/infinispan/persistence/support/DelegatingCacheWriter
       4: ifeq          17
       7: aload_1
       8: checkcast     #38                 // class org/infinispan/persistence/support/DelegatingCacheWriter
      11: invokevirtual #177                // Method org/infinispan/persistence/support/DelegatingCacheWriter.undelegate:()Lorg/infinispan/persistence/spi/CacheWriter;
      14: goto          18
      17: aload_1
      18: areturn

  private org.infinispan.AdvancedCache<java.lang.Object, java.lang.Object> getCacheForStateInsertion();
    Code:
       0: new           #3                  // class java/util/ArrayList
       3: dup
       4: iconst_5
       5: anewarray     #178                // class org/infinispan/context/Flag
       8: dup
       9: iconst_0
      10: getstatic     #179                // Field org/infinispan/context/Flag.CACHE_MODE_LOCAL:Lorg/infinispan/context/Flag;
      13: aastore
      14: dup
      15: iconst_1
      16: getstatic     #180                // Field org/infinispan/context/Flag.SKIP_OWNERSHIP_CHECK:Lorg/infinispan/context/Flag;
      19: aastore
      20: dup
      21: iconst_2
      22: getstatic     #181                // Field org/infinispan/context/Flag.IGNORE_RETURN_VALUES:Lorg/infinispan/context/Flag;
      25: aastore
      26: dup
      27: iconst_3
      28: getstatic     #182                // Field org/infinispan/context/Flag.SKIP_CACHE_STORE:Lorg/infinispan/context/Flag;
      31: aastore
      32: dup
      33: iconst_4
      34: getstatic     #183                // Field org/infinispan/context/Flag.SKIP_LOCKING:Lorg/infinispan/context/Flag;
      37: aastore
      38: invokestatic  #184                // Method java/util/Arrays.asList:([Ljava/lang/Object;)Ljava/util/List;
      41: invokespecial #185                // Method java/util/ArrayList."<init>":(Ljava/util/Collection;)V
      44: astore_1
      45: iconst_0
      46: istore_2
      47: aload_0
      48: getfield      #6                  // Field writers:Ljava/util/List;
      51: invokeinterface #33,  1           // InterfaceMethod java/util/List.iterator:()Ljava/util/Iterator;
      56: astore_3
      57: aload_3
      58: invokeinterface #34,  1           // InterfaceMethod java/util/Iterator.hasNext:()Z
      63: ifeq          107
      66: aload_3
      67: invokeinterface #35,  1           // InterfaceMethod java/util/Iterator.next:()Ljava/lang/Object;
      72: checkcast     #36                 // class org/infinispan/persistence/spi/CacheWriter
      75: astore        4
      77: aload_0
      78: getfield      #12                 // Field configMap:Ljava/util/Map;
      81: aload         4
      83: invokeinterface #41,  2           // InterfaceMethod java/util/Map.get:(Ljava/lang/Object;)Ljava/lang/Object;
      88: checkcast     #42                 // class org/infinispan/configuration/cache/StoreConfiguration
      91: invokeinterface #138,  1          // InterfaceMethod org/infinispan/configuration/cache/StoreConfiguration.shared:()Z
      96: ifeq          104
      99: iconst_1
     100: istore_2
     101: goto          107
     104: goto          57
     107: iload_2
     108: ifeq          131
     111: aload_0
     112: invokespecial #186                // Method indexShareable:()Z
     115: ifeq          141
     118: aload_1
     119: getstatic     #187                // Field org/infinispan/context/Flag.SKIP_INDEXING:Lorg/infinispan/context/Flag;
     122: invokeinterface #171,  2          // InterfaceMethod java/util/List.add:(Ljava/lang/Object;)Z
     127: pop
     128: goto          141
     131: aload_1
     132: getstatic     #187                // Field org/infinispan/context/Flag.SKIP_INDEXING:Lorg/infinispan/context/Flag;
     135: invokeinterface #171,  2          // InterfaceMethod java/util/List.add:(Ljava/lang/Object;)Z
     140: pop
     141: aload_0
     142: getfield      #13                 // Field cache:Lorg/infinispan/AdvancedCache;
     145: invokeinterface #188,  1          // InterfaceMethod org/infinispan/AdvancedCache.getAdvancedCache:()Lorg/infinispan/AdvancedCache;
     150: aload_1
     151: aload_1
     152: invokeinterface #113,  1          // InterfaceMethod java/util/List.size:()I
     157: anewarray     #178                // class org/infinispan/context/Flag
     160: invokeinterface #189,  2          // InterfaceMethod java/util/List.toArray:([Ljava/lang/Object;)[Ljava/lang/Object;
     165: checkcast     #190                // class "[Lorg/infinispan/context/Flag;"
     168: invokeinterface #191,  2          // InterfaceMethod org/infinispan/AdvancedCache.withFlags:([Lorg/infinispan/context/Flag;)Lorg/infinispan/AdvancedCache;
     173: areturn

  private boolean localIndexingEnabled();
    Code:
       0: aload_0
       1: getfield      #15                 // Field configuration:Lorg/infinispan/configuration/cache/Configuration;
       4: invokevirtual #192                // Method org/infinispan/configuration/cache/Configuration.indexing:()Lorg/infinispan/configuration/cache/IndexingConfiguration;
       7: invokevirtual #193                // Method org/infinispan/configuration/cache/IndexingConfiguration.index:()Lorg/infinispan/configuration/cache/Index;
      10: getstatic     #194                // Field org/infinispan/configuration/cache/Index.LOCAL:Lorg/infinispan/configuration/cache/Index;
      13: if_acmpne     20
      16: iconst_1
      17: goto          21
      20: iconst_0
      21: ireturn

  private boolean indexShareable();
    Code:
       0: aload_0
       1: getfield      #15                 // Field configuration:Lorg/infinispan/configuration/cache/Configuration;
       4: invokevirtual #192                // Method org/infinispan/configuration/cache/Configuration.indexing:()Lorg/infinispan/configuration/cache/IndexingConfiguration;
       7: invokevirtual #195                // Method org/infinispan/configuration/cache/IndexingConfiguration.indexShareable:()Z
      10: ireturn

  private long getMaxEntries();
    Code:
       0: ldc2_w        #197                // long 72057594037927935l
       3: lstore_1
       4: aload_0
       5: getfield      #15                 // Field configuration:Lorg/infinispan/configuration/cache/Configuration;
       8: invokevirtual #199                // Method org/infinispan/configuration/cache/Configuration.eviction:()Lorg/infinispan/configuration/cache/EvictionConfiguration;
      11: invokevirtual #200                // Method org/infinispan/configuration/cache/EvictionConfiguration.strategy:()Lorg/infinispan/eviction/EvictionStrategy;
      14: invokevirtual #201                // Method org/infinispan/eviction/EvictionStrategy.isEnabled:()Z
      17: ifeq          47
      20: aload_0
      21: getfield      #15                 // Field configuration:Lorg/infinispan/configuration/cache/Configuration;
      24: invokevirtual #199                // Method org/infinispan/configuration/cache/Configuration.eviction:()Lorg/infinispan/configuration/cache/EvictionConfiguration;
      27: invokevirtual #202                // Method org/infinispan/configuration/cache/EvictionConfiguration.type:()Lorg/infinispan/eviction/EvictionType;
      30: getstatic     #203                // Field org/infinispan/eviction/EvictionType.COUNT:Lorg/infinispan/eviction/EvictionType;
      33: if_acmpne     47
      36: aload_0
      37: getfield      #15                 // Field configuration:Lorg/infinispan/configuration/cache/Configuration;
      40: invokevirtual #199                // Method org/infinispan/configuration/cache/Configuration.eviction:()Lorg/infinispan/configuration/cache/EvictionConfiguration;
      43: invokevirtual #204                // Method org/infinispan/configuration/cache/EvictionConfiguration.maxEntries:()J
      46: lstore_1
      47: lload_1
      48: lreturn

  private void preloadKey(org.infinispan.AdvancedCache<java.lang.Object, java.lang.Object>, java.lang.Object, java.lang.Object, org.infinispan.metadata.Metadata);
    Code:
       0: aload_0
       1: invokespecial #205                // Method suspendIfNeeded:()Ljavax/transaction/Transaction;
       4: astore        5
       6: iconst_0
       7: istore        6
       9: aload_0
      10: invokespecial #206                // Method beginIfNeeded:()V
      13: aload_1
      14: aload_2
      15: aload_3
      16: aload         4
      18: invokeinterface #207,  4          // InterfaceMethod org/infinispan/AdvancedCache.put:(Ljava/lang/Object;Ljava/lang/Object;Lorg/infinispan/metadata/Metadata;)Ljava/lang/Object;
      23: pop
      24: iconst_1
      25: istore        6
      27: aload_0
      28: iload         6
      30: invokespecial #208                // Method commitIfNeeded:(Z)V
      33: goto          61
      36: astore        7
      38: new           #45                 // class org/infinispan/persistence/spi/PersistenceException
      41: dup
      42: ldc           #209                // String Unable to preload!
      44: aload         7
      46: invokespecial #210                // Method org/infinispan/persistence/spi/PersistenceException."<init>":(Ljava/lang/String;Ljava/lang/Throwable;)V
      49: athrow
      50: astore        8
      52: aload_0
      53: iload         6
      55: invokespecial #208                // Method commitIfNeeded:(Z)V
      58: aload         8
      60: athrow
      61: aload_0
      62: aload         5
      64: invokespecial #211                // Method resumeIfNeeded:(Ljavax/transaction/Transaction;)V
      67: goto          81
      70: astore        9
      72: aload_0
      73: aload         5
      75: invokespecial #211                // Method resumeIfNeeded:(Ljavax/transaction/Transaction;)V
      78: aload         9
      80: athrow
      81: return
    Exception table:
       from    to  target type
           9    27    36   Class java/lang/Exception
           9    27    50   any
          36    52    50   any
           9    61    70   any
          70    72    70   any

  private void resumeIfNeeded(javax.transaction.Transaction);
    Code:
       0: aload_0
       1: getfield      #15                 // Field configuration:Lorg/infinispan/configuration/cache/Configuration;
       4: invokevirtual #212                // Method org/infinispan/configuration/cache/Configuration.transaction:()Lorg/infinispan/configuration/cache/TransactionConfiguration;
       7: invokevirtual #213                // Method org/infinispan/configuration/cache/TransactionConfiguration.transactionMode:()Lorg/infinispan/transaction/TransactionMode;
      10: invokevirtual #214                // Method org/infinispan/transaction/TransactionMode.isTransactional:()Z
      13: ifeq          50
      16: aload_0
      17: getfield      #16                 // Field transactionManager:Ljavax/transaction/TransactionManager;
      20: ifnull        50
      23: aload_1
      24: ifnull        50
      27: aload_0
      28: getfield      #16                 // Field transactionManager:Ljavax/transaction/TransactionManager;
      31: aload_1
      32: invokeinterface #59,  2           // InterfaceMethod javax/transaction/TransactionManager.resume:(Ljavax/transaction/Transaction;)V
      37: goto          50
      40: astore_2
      41: new           #45                 // class org/infinispan/persistence/spi/PersistenceException
      44: dup
      45: aload_2
      46: invokespecial #215                // Method org/infinispan/persistence/spi/PersistenceException."<init>":(Ljava/lang/Throwable;)V
      49: athrow
      50: return
    Exception table:
       from    to  target type
          27    37    40   Class java/lang/Exception

  private javax.transaction.Transaction suspendIfNeeded();
    Code:
       0: aload_0
       1: getfield      #15                 // Field configuration:Lorg/infinispan/configuration/cache/Configuration;
       4: invokevirtual #212                // Method org/infinispan/configuration/cache/Configuration.transaction:()Lorg/infinispan/configuration/cache/TransactionConfiguration;
       7: invokevirtual #213                // Method org/infinispan/configuration/cache/TransactionConfiguration.transactionMode:()Lorg/infinispan/transaction/TransactionMode;
      10: invokevirtual #214                // Method org/infinispan/transaction/TransactionMode.isTransactional:()Z
      13: ifeq          43
      16: aload_0
      17: getfield      #16                 // Field transactionManager:Ljavax/transaction/TransactionManager;
      20: ifnull        43
      23: aload_0
      24: getfield      #16                 // Field transactionManager:Ljavax/transaction/TransactionManager;
      27: invokeinterface #30,  1           // InterfaceMethod javax/transaction/TransactionManager.suspend:()Ljavax/transaction/Transaction;
      32: areturn
      33: astore_1
      34: new           #45                 // class org/infinispan/persistence/spi/PersistenceException
      37: dup
      38: aload_1
      39: invokespecial #215                // Method org/infinispan/persistence/spi/PersistenceException."<init>":(Ljava/lang/Throwable;)V
      42: athrow
      43: aconst_null
      44: areturn
    Exception table:
       from    to  target type
          23    32    33   Class java/lang/Exception

  private void beginIfNeeded();
    Code:
       0: aload_0
       1: getfield      #15                 // Field configuration:Lorg/infinispan/configuration/cache/Configuration;
       4: invokevirtual #212                // Method org/infinispan/configuration/cache/Configuration.transaction:()Lorg/infinispan/configuration/cache/TransactionConfiguration;
       7: invokevirtual #213                // Method org/infinispan/configuration/cache/TransactionConfiguration.transactionMode:()Lorg/infinispan/transaction/TransactionMode;
      10: invokevirtual #214                // Method org/infinispan/transaction/TransactionMode.isTransactional:()Z
      13: ifeq          45
      16: aload_0
      17: getfield      #16                 // Field transactionManager:Ljavax/transaction/TransactionManager;
      20: ifnull        45
      23: aload_0
      24: getfield      #16                 // Field transactionManager:Ljavax/transaction/TransactionManager;
      27: invokeinterface #216,  1          // InterfaceMethod javax/transaction/TransactionManager.begin:()V
      32: goto          45
      35: astore_1
      36: new           #45                 // class org/infinispan/persistence/spi/PersistenceException
      39: dup
      40: aload_1
      41: invokespecial #215                // Method org/infinispan/persistence/spi/PersistenceException."<init>":(Ljava/lang/Throwable;)V
      44: athrow
      45: return
    Exception table:
       from    to  target type
          23    32    35   Class java/lang/Exception

  private void commitIfNeeded(boolean);
    Code:
       0: aload_0
       1: getfield      #15                 // Field configuration:Lorg/infinispan/configuration/cache/Configuration;
       4: invokevirtual #212                // Method org/infinispan/configuration/cache/Configuration.transaction:()Lorg/infinispan/configuration/cache/TransactionConfiguration;
       7: invokevirtual #213                // Method org/infinispan/configuration/cache/TransactionConfiguration.transactionMode:()Lorg/infinispan/transaction/TransactionMode;
      10: invokevirtual #214                // Method org/infinispan/transaction/TransactionMode.isTransactional:()Z
      13: ifeq          61
      16: aload_0
      17: getfield      #16                 // Field transactionManager:Ljavax/transaction/TransactionManager;
      20: ifnull        61
      23: iload_1
      24: ifeq          39
      27: aload_0
      28: getfield      #16                 // Field transactionManager:Ljavax/transaction/TransactionManager;
      31: invokeinterface #217,  1          // InterfaceMethod javax/transaction/TransactionManager.commit:()V
      36: goto          48
      39: aload_0
      40: getfield      #16                 // Field transactionManager:Ljavax/transaction/TransactionManager;
      43: invokeinterface #218,  1          // InterfaceMethod javax/transaction/TransactionManager.rollback:()V
      48: goto          61
      51: astore_2
      52: new           #45                 // class org/infinispan/persistence/spi/PersistenceException
      55: dup
      56: aload_2
      57: invokespecial #215                // Method org/infinispan/persistence/spi/PersistenceException."<init>":(Ljava/lang/Throwable;)V
      60: athrow
      61: return
    Exception table:
       from    to  target type
          23    48    51   Class java/lang/Exception

  public java.util.concurrent.Executor getPersistenceExecutor();
    Code:
       0: aload_0
       1: getfield      #18                 // Field persistenceExecutor:Ljava/util/concurrent/Executor;
       4: areturn

  public org.infinispan.commons.marshall.StreamingMarshaller getMarshaller();
    Code:
       0: aload_0
       1: getfield      #14                 // Field m:Lorg/infinispan/commons/marshall/StreamingMarshaller;
       4: areturn

  private void removeInterceptors(java.util.Collection<org.infinispan.interceptors.base.CommandInterceptor>);
    Code:
       0: aload_1
       1: invokeinterface #219,  1          // InterfaceMethod java/util/Collection.isEmpty:()Z
       6: ifeq          10
       9: return
      10: aload_1
      11: invokeinterface #220,  1          // InterfaceMethod java/util/Collection.iterator:()Ljava/util/Iterator;
      16: astore_2
      17: aload_2
      18: invokeinterface #34,  1           // InterfaceMethod java/util/Iterator.hasNext:()Z
      23: ifeq          52
      26: aload_2
      27: invokeinterface #35,  1           // InterfaceMethod java/util/Iterator.next:()Ljava/lang/Object;
      32: checkcast     #105                // class org/infinispan/interceptors/base/CommandInterceptor
      35: astore_3
      36: aload_0
      37: getfield      #13                 // Field cache:Lorg/infinispan/AdvancedCache;
      40: aload_3
      41: invokevirtual #72                 // Method java/lang/Object.getClass:()Ljava/lang/Class;
      44: invokeinterface #221,  2          // InterfaceMethod org/infinispan/AdvancedCache.removeInterceptor:(Ljava/lang/Class;)V
      49: goto          17
      52: return

  private void lambda$purgeExpired$222(java.lang.Object);
    Code:
       0: aload_0
       1: getfield      #22                 // Field expirationManager:Lorg/infinispan/expiration/ExpirationManager;
       4: aload_1
       5: invokeinterface #222,  2          // InterfaceMethod org/infinispan/expiration/ExpirationManager.handleInStoreExpiration:(Ljava/lang/Object;)V
      10: return

  static void access$100(org.infinispan.persistence.manager.PersistenceManagerImpl, org.infinispan.AdvancedCache, java.lang.Object, java.lang.Object, org.infinispan.metadata.Metadata);
    Code:
       0: aload_0
       1: aload_1
       2: aload_2
       3: aload_3
       4: aload         4
       6: invokespecial #1                  // Method preloadKey:(Lorg/infinispan/AdvancedCache;Ljava/lang/Object;Ljava/lang/Object;Lorg/infinispan/metadata/Metadata;)V
       9: return

  static {};
    Code:
       0: ldc           #223                // class org/infinispan/persistence/manager/PersistenceManagerImpl
       2: invokestatic  #224                // Method org/infinispan/util/logging/LogFactory.getLog:(Ljava/lang/Class;)Lorg/infinispan/util/logging/Log;
       5: putstatic     #87                 // Field log:Lorg/infinispan/util/logging/Log;
       8: getstatic     #87                 // Field log:Lorg/infinispan/util/logging/Log;
      11: invokeinterface #225,  1          // InterfaceMethod org/infinispan/util/logging/Log.isTraceEnabled:()Z
      16: putstatic     #117                // Field trace:Z
      19: return
}
