Compiled from "KerberosLoginModule.java"
class org.jboss.security.negotiation.KerberosLoginModule$1 implements java.security.PrivilegedExceptionAction<org.ietf.jgss.GSSCredential> {
  final org.ietf.jgss.GSSManager val$manager;

  final org.jboss.security.negotiation.KerberosLoginModule this$0;

  org.jboss.security.negotiation.KerberosLoginModule$1(org.jboss.security.negotiation.KerberosLoginModule, org.ietf.jgss.GSSManager);
    Code:
       0: aload_0
       1: aload_1
       2: putfield      #1                  // Field this$0:Lorg/jboss/security/negotiation/KerberosLoginModule;
       5: aload_0
       6: aload_2
       7: putfield      #2                  // Field val$manager:Lorg/ietf/jgss/GSSManager;
      10: aload_0
      11: invokespecial #3                  // Method java/lang/Object."<init>":()V
      14: return

  public org.ietf.jgss.GSSCredential run() throws java.lang.Exception;
    Code:
       0: aload_0
       1: getfield      #1                  // Field this$0:Lorg/jboss/security/negotiation/KerberosLoginModule;
       4: invokestatic  #4                  // Method org/jboss/security/negotiation/KerberosLoginModule.access$000:(Lorg/jboss/security/negotiation/KerberosLoginModule;)Ljavax/security/auth/Subject;
       7: ldc           #5                  // class javax/security/auth/kerberos/KerberosPrincipal
       9: invokevirtual #6                  // Method javax/security/auth/Subject.getPrincipals:(Ljava/lang/Class;)Ljava/util/Set;
      12: astore_1
      13: aload_1
      14: invokeinterface #7,  1            // InterfaceMethod java/util/Set.size:()I
      19: iconst_1
      20: if_icmpge     33
      23: new           #8                  // class javax/security/auth/login/LoginException
      26: dup
      27: ldc           #9                  // String No KerberosPrincipal Found
      29: invokespecial #10                 // Method javax/security/auth/login/LoginException."<init>":(Ljava/lang/String;)V
      32: athrow
      33: aload_1
      34: invokeinterface #7,  1            // InterfaceMethod java/util/Set.size:()I
      39: iconst_1
      40: if_icmple     53
      43: new           #8                  // class javax/security/auth/login/LoginException
      46: dup
      47: ldc           #11                 // String Too Many KerberosPrincipals Found
      49: invokespecial #10                 // Method javax/security/auth/login/LoginException."<init>":(Ljava/lang/String;)V
      52: athrow
      53: aload_1
      54: invokeinterface #12,  1           // InterfaceMethod java/util/Set.iterator:()Ljava/util/Iterator;
      59: invokeinterface #13,  1           // InterfaceMethod java/util/Iterator.next:()Ljava/lang/Object;
      64: checkcast     #5                  // class javax/security/auth/kerberos/KerberosPrincipal
      67: astore_2
      68: invokestatic  #14                 // Method org/jboss/security/negotiation/KerberosLoginModule.access$100:()Lorg/jboss/logging/Logger;
      71: ldc           #15                 // String Creating GSSName for Principal \'%s\'
      73: aload_2
      74: invokevirtual #16                 // Method org/jboss/logging/Logger.tracef:(Ljava/lang/String;Ljava/lang/Object;)V
      77: aload_0
      78: getfield      #2                  // Field val$manager:Lorg/ietf/jgss/GSSManager;
      81: aload_2
      82: invokevirtual #17                 // Method javax/security/auth/kerberos/KerberosPrincipal.getName:()Ljava/lang/String;
      85: getstatic     #18                 // Field org/ietf/jgss/GSSName.NT_USER_NAME:Lorg/ietf/jgss/Oid;
      88: getstatic     #19                 // Field org/jboss/security/negotiation/Constants.KERBEROS_V5:Lorg/ietf/jgss/Oid;
      91: invokevirtual #20                 // Method org/ietf/jgss/GSSManager.createName:(Ljava/lang/String;Lorg/ietf/jgss/Oid;Lorg/ietf/jgss/Oid;)Lorg/ietf/jgss/GSSName;
      94: astore_3
      95: aload_0
      96: getfield      #2                  // Field val$manager:Lorg/ietf/jgss/GSSManager;
      99: aload_3
     100: aload_0
     101: getfield      #1                  // Field this$0:Lorg/jboss/security/negotiation/KerberosLoginModule;
     104: invokestatic  #21                 // Method org/jboss/security/negotiation/KerberosLoginModule.access$200:(Lorg/jboss/security/negotiation/KerberosLoginModule;)I
     107: getstatic     #19                 // Field org/jboss/security/negotiation/Constants.KERBEROS_V5:Lorg/ietf/jgss/Oid;
     110: iconst_1
     111: invokevirtual #23                 // Method org/ietf/jgss/GSSManager.createCredential:(Lorg/ietf/jgss/GSSName;ILorg/ietf/jgss/Oid;I)Lorg/ietf/jgss/GSSCredential;
     114: areturn

  public java.lang.Object run() throws java.lang.Exception;
    Code:
       0: aload_0
       1: invokevirtual #24                 // Method run:()Lorg/ietf/jgss/GSSCredential;
       4: areturn
}
