Compiled from "AbstractPolynomialSolver.java"
public abstract class org.apache.commons.math3.analysis.solvers.AbstractPolynomialSolver extends org.apache.commons.math3.analysis.solvers.BaseAbstractUnivariateSolver<org.apache.commons.math3.analysis.polynomials.PolynomialFunction> implements org.apache.commons.math3.analysis.solvers.PolynomialSolver {
  private org.apache.commons.math3.analysis.polynomials.PolynomialFunction polynomialFunction;

  protected org.apache.commons.math3.analysis.solvers.AbstractPolynomialSolver(double);
    Code:
       0: aload_0
       1: dload_1
       2: invokespecial #1                  // Method org/apache/commons/math3/analysis/solvers/BaseAbstractUnivariateSolver."<init>":(D)V
       5: return

  protected org.apache.commons.math3.analysis.solvers.AbstractPolynomialSolver(double, double);
    Code:
       0: aload_0
       1: dload_1
       2: dload_3
       3: invokespecial #2                  // Method org/apache/commons/math3/analysis/solvers/BaseAbstractUnivariateSolver."<init>":(DD)V
       6: return

  protected org.apache.commons.math3.analysis.solvers.AbstractPolynomialSolver(double, double, double);
    Code:
       0: aload_0
       1: dload_1
       2: dload_3
       3: dload         5
       5: invokespecial #3                  // Method org/apache/commons/math3/analysis/solvers/BaseAbstractUnivariateSolver."<init>":(DDD)V
       8: return

  protected void setup(int, org.apache.commons.math3.analysis.polynomials.PolynomialFunction, double, double, double);
    Code:
       0: aload_0
       1: iload_1
       2: aload_2
       3: dload_3
       4: dload         5
       6: dload         7
       8: invokespecial #4                  // Method org/apache/commons/math3/analysis/solvers/BaseAbstractUnivariateSolver.setup:(ILorg/apache/commons/math3/analysis/UnivariateFunction;DDD)V
      11: aload_0
      12: aload_2
      13: putfield      #5                  // Field polynomialFunction:Lorg/apache/commons/math3/analysis/polynomials/PolynomialFunction;
      16: return

  protected double[] getCoefficients();
    Code:
       0: aload_0
       1: getfield      #5                  // Field polynomialFunction:Lorg/apache/commons/math3/analysis/polynomials/PolynomialFunction;
       4: invokevirtual #6                  // Method org/apache/commons/math3/analysis/polynomials/PolynomialFunction.getCoefficients:()[D
       7: areturn

  protected void setup(int, org.apache.commons.math3.analysis.UnivariateFunction, double, double, double);
    Code:
       0: aload_0
       1: iload_1
       2: aload_2
       3: checkcast     #7                  // class org/apache/commons/math3/analysis/polynomials/PolynomialFunction
       6: dload_3
       7: dload         5
       9: dload         7
      11: invokevirtual #8                  // Method setup:(ILorg/apache/commons/math3/analysis/polynomials/PolynomialFunction;DDD)V
      14: return
}
