Compiled from "JBossAllXmlParserAdaptor.java"
public class org.jboss.as.server.deployment.module.descriptor.JBossAllXmlParserAdaptor implements org.jboss.as.server.deployment.jbossallxml.JBossAllXMLParser<org.jboss.as.server.deployment.module.descriptor.ParseResult> {
  private final org.jboss.staxmapper.XMLElementReader<org.jboss.as.server.deployment.module.descriptor.ParseResult> elementReader;

  public org.jboss.as.server.deployment.module.descriptor.JBossAllXmlParserAdaptor(org.jboss.staxmapper.XMLElementReader<org.jboss.as.server.deployment.module.descriptor.ParseResult>);
    Code:
       0: aload_0
       1: invokespecial #1                  // Method java/lang/Object."<init>":()V
       4: aload_0
       5: aload_1
       6: putfield      #2                  // Field elementReader:Lorg/jboss/staxmapper/XMLElementReader;
       9: return

  public org.jboss.as.server.deployment.module.descriptor.ParseResult parse(org.jboss.staxmapper.XMLExtendedStreamReader, org.jboss.as.server.deployment.DeploymentUnit) throws javax.xml.stream.XMLStreamException;
    Code:
       0: new           #3                  // class org/jboss/as/server/deployment/module/descriptor/ParseResult
       3: dup
       4: aload_2
       5: getstatic     #4                  // Field org/jboss/as/server/deployment/Attachments.SERVICE_MODULE_LOADER:Lorg/jboss/as/server/deployment/AttachmentKey;
       8: invokeinterface #5,  2            // InterfaceMethod org/jboss/as/server/deployment/DeploymentUnit.getAttachment:(Lorg/jboss/as/server/deployment/AttachmentKey;)Ljava/lang/Object;
      13: checkcast     #6                  // class org/jboss/modules/ModuleLoader
      16: aload_2
      17: invokespecial #7                  // Method org/jboss/as/server/deployment/module/descriptor/ParseResult."<init>":(Lorg/jboss/modules/ModuleLoader;Lorg/jboss/as/server/deployment/DeploymentUnit;)V
      20: astore_3
      21: aload_0
      22: getfield      #2                  // Field elementReader:Lorg/jboss/staxmapper/XMLElementReader;
      25: aload_1
      26: aload_3
      27: invokeinterface #8,  3            // InterfaceMethod org/jboss/staxmapper/XMLElementReader.readElement:(Lorg/jboss/staxmapper/XMLExtendedStreamReader;Ljava/lang/Object;)V
      32: aload_3
      33: areturn

  public java.lang.Object parse(org.jboss.staxmapper.XMLExtendedStreamReader, org.jboss.as.server.deployment.DeploymentUnit) throws javax.xml.stream.XMLStreamException;
    Code:
       0: aload_0
       1: aload_1
       2: aload_2
       3: invokevirtual #9                  // Method parse:(Lorg/jboss/staxmapper/XMLExtendedStreamReader;Lorg/jboss/as/server/deployment/DeploymentUnit;)Lorg/jboss/as/server/deployment/module/descriptor/ParseResult;
       6: areturn
}
