Compiled from "AudioLogSetting.java"
final class software.amazon.awssdk.services.lexmodelsv2.model.AudioLogSetting$BuilderImpl implements software.amazon.awssdk.services.lexmodelsv2.model.AudioLogSetting$Builder {
  private java.lang.Boolean enabled;

  private software.amazon.awssdk.services.lexmodelsv2.model.AudioLogDestination destination;

  private software.amazon.awssdk.services.lexmodelsv2.model.AudioLogSetting$BuilderImpl();
    Code:
       0: aload_0
       1: invokespecial #5                  // Method java/lang/Object."<init>":()V
       4: return

  private software.amazon.awssdk.services.lexmodelsv2.model.AudioLogSetting$BuilderImpl(software.amazon.awssdk.services.lexmodelsv2.model.AudioLogSetting);
    Code:
       0: aload_0
       1: invokespecial #5                  // Method java/lang/Object."<init>":()V
       4: aload_0
       5: aload_1
       6: invokestatic  #6                  // Method software/amazon/awssdk/services/lexmodelsv2/model/AudioLogSetting.access$400:(Lsoftware/amazon/awssdk/services/lexmodelsv2/model/AudioLogSetting;)Ljava/lang/Boolean;
       9: invokevirtual #7                  // Method enabled:(Ljava/lang/Boolean;)Lsoftware/amazon/awssdk/services/lexmodelsv2/model/AudioLogSetting$Builder;
      12: pop
      13: aload_0
      14: aload_1
      15: invokestatic  #8                  // Method software/amazon/awssdk/services/lexmodelsv2/model/AudioLogSetting.access$500:(Lsoftware/amazon/awssdk/services/lexmodelsv2/model/AudioLogSetting;)Lsoftware/amazon/awssdk/services/lexmodelsv2/model/AudioLogDestination;
      18: invokevirtual #9                  // Method destination:(Lsoftware/amazon/awssdk/services/lexmodelsv2/model/AudioLogDestination;)Lsoftware/amazon/awssdk/services/lexmodelsv2/model/AudioLogSetting$Builder;
      21: pop
      22: return

  public final java.lang.Boolean getEnabled();
    Code:
       0: aload_0
       1: getfield      #4                  // Field enabled:Ljava/lang/Boolean;
       4: areturn

  public final void setEnabled(java.lang.Boolean);
    Code:
       0: aload_0
       1: aload_1
       2: putfield      #4                  // Field enabled:Ljava/lang/Boolean;
       5: return

  public final software.amazon.awssdk.services.lexmodelsv2.model.AudioLogSetting$Builder enabled(java.lang.Boolean);
    Code:
       0: aload_0
       1: aload_1
       2: putfield      #4                  // Field enabled:Ljava/lang/Boolean;
       5: aload_0
       6: areturn

  public final software.amazon.awssdk.services.lexmodelsv2.model.AudioLogDestination$Builder getDestination();
    Code:
       0: aload_0
       1: getfield      #3                  // Field destination:Lsoftware/amazon/awssdk/services/lexmodelsv2/model/AudioLogDestination;
       4: ifnull        17
       7: aload_0
       8: getfield      #3                  // Field destination:Lsoftware/amazon/awssdk/services/lexmodelsv2/model/AudioLogDestination;
      11: invokevirtual #10                 // Method software/amazon/awssdk/services/lexmodelsv2/model/AudioLogDestination.toBuilder:()Lsoftware/amazon/awssdk/services/lexmodelsv2/model/AudioLogDestination$Builder;
      14: goto          18
      17: aconst_null
      18: areturn

  public final void setDestination(software.amazon.awssdk.services.lexmodelsv2.model.AudioLogDestination$BuilderImpl);
    Code:
       0: aload_0
       1: aload_1
       2: ifnull        12
       5: aload_1
       6: invokevirtual #11                 // Method software/amazon/awssdk/services/lexmodelsv2/model/AudioLogDestination$BuilderImpl.build:()Lsoftware/amazon/awssdk/services/lexmodelsv2/model/AudioLogDestination;
       9: goto          13
      12: aconst_null
      13: putfield      #3                  // Field destination:Lsoftware/amazon/awssdk/services/lexmodelsv2/model/AudioLogDestination;
      16: return

  public final software.amazon.awssdk.services.lexmodelsv2.model.AudioLogSetting$Builder destination(software.amazon.awssdk.services.lexmodelsv2.model.AudioLogDestination);
    Code:
       0: aload_0
       1: aload_1
       2: putfield      #3                  // Field destination:Lsoftware/amazon/awssdk/services/lexmodelsv2/model/AudioLogDestination;
       5: aload_0
       6: areturn

  public software.amazon.awssdk.services.lexmodelsv2.model.AudioLogSetting build();
    Code:
       0: new           #12                 // class software/amazon/awssdk/services/lexmodelsv2/model/AudioLogSetting
       3: dup
       4: aload_0
       5: aconst_null
       6: invokespecial #13                 // Method software/amazon/awssdk/services/lexmodelsv2/model/AudioLogSetting."<init>":(Lsoftware/amazon/awssdk/services/lexmodelsv2/model/AudioLogSetting$BuilderImpl;Lsoftware/amazon/awssdk/services/lexmodelsv2/model/AudioLogSetting$1;)V
       9: areturn

  public java.util.List<software.amazon.awssdk.core.SdkField<?>> sdkFields();
    Code:
       0: invokestatic  #14                 // Method software/amazon/awssdk/services/lexmodelsv2/model/AudioLogSetting.access$700:()Ljava/util/List;
       3: areturn

  public java.lang.Object build();
    Code:
       0: aload_0
       1: invokevirtual #15                 // Method build:()Lsoftware/amazon/awssdk/services/lexmodelsv2/model/AudioLogSetting;
       4: areturn

  static java.lang.Boolean access$000(software.amazon.awssdk.services.lexmodelsv2.model.AudioLogSetting$BuilderImpl);
    Code:
       0: aload_0
       1: getfield      #4                  // Field enabled:Ljava/lang/Boolean;
       4: areturn

  static software.amazon.awssdk.services.lexmodelsv2.model.AudioLogDestination access$100(software.amazon.awssdk.services.lexmodelsv2.model.AudioLogSetting$BuilderImpl);
    Code:
       0: aload_0
       1: getfield      #3                  // Field destination:Lsoftware/amazon/awssdk/services/lexmodelsv2/model/AudioLogDestination;
       4: areturn

  software.amazon.awssdk.services.lexmodelsv2.model.AudioLogSetting$BuilderImpl(software.amazon.awssdk.services.lexmodelsv2.model.AudioLogSetting, software.amazon.awssdk.services.lexmodelsv2.model.AudioLogSetting$1);
    Code:
       0: aload_0
       1: aload_1
       2: invokespecial #2                  // Method "<init>":(Lsoftware/amazon/awssdk/services/lexmodelsv2/model/AudioLogSetting;)V
       5: return

  software.amazon.awssdk.services.lexmodelsv2.model.AudioLogSetting$BuilderImpl(software.amazon.awssdk.services.lexmodelsv2.model.AudioLogSetting$1);
    Code:
       0: aload_0
       1: invokespecial #1                  // Method "<init>":()V
       4: return
}
