Compiled from "BuildBotLocaleResponse.java"
final class software.amazon.awssdk.services.lexmodelsv2.model.BuildBotLocaleResponse$BuilderImpl extends software.amazon.awssdk.services.lexmodelsv2.model.LexModelsV2Response$BuilderImpl implements software.amazon.awssdk.services.lexmodelsv2.model.BuildBotLocaleResponse$Builder {
  private java.lang.String botId;

  private java.lang.String botVersion;

  private java.lang.String localeId;

  private java.lang.String botLocaleStatus;

  private java.time.Instant lastBuildSubmittedDateTime;

  private software.amazon.awssdk.services.lexmodelsv2.model.BuildBotLocaleResponse$BuilderImpl();
    Code:
       0: aload_0
       1: invokespecial #8                  // Method software/amazon/awssdk/services/lexmodelsv2/model/LexModelsV2Response$BuilderImpl."<init>":()V
       4: return

  private software.amazon.awssdk.services.lexmodelsv2.model.BuildBotLocaleResponse$BuilderImpl(software.amazon.awssdk.services.lexmodelsv2.model.BuildBotLocaleResponse);
    Code:
       0: aload_0
       1: aload_1
       2: invokespecial #9                  // Method software/amazon/awssdk/services/lexmodelsv2/model/LexModelsV2Response$BuilderImpl."<init>":(Lsoftware/amazon/awssdk/services/lexmodelsv2/model/LexModelsV2Response;)V
       5: aload_0
       6: aload_1
       7: invokestatic  #10                 // Method software/amazon/awssdk/services/lexmodelsv2/model/BuildBotLocaleResponse.access$700:(Lsoftware/amazon/awssdk/services/lexmodelsv2/model/BuildBotLocaleResponse;)Ljava/lang/String;
      10: invokevirtual #11                 // Method botId:(Ljava/lang/String;)Lsoftware/amazon/awssdk/services/lexmodelsv2/model/BuildBotLocaleResponse$Builder;
      13: pop
      14: aload_0
      15: aload_1
      16: invokestatic  #12                 // Method software/amazon/awssdk/services/lexmodelsv2/model/BuildBotLocaleResponse.access$800:(Lsoftware/amazon/awssdk/services/lexmodelsv2/model/BuildBotLocaleResponse;)Ljava/lang/String;
      19: invokevirtual #13                 // Method botVersion:(Ljava/lang/String;)Lsoftware/amazon/awssdk/services/lexmodelsv2/model/BuildBotLocaleResponse$Builder;
      22: pop
      23: aload_0
      24: aload_1
      25: invokestatic  #14                 // Method software/amazon/awssdk/services/lexmodelsv2/model/BuildBotLocaleResponse.access$900:(Lsoftware/amazon/awssdk/services/lexmodelsv2/model/BuildBotLocaleResponse;)Ljava/lang/String;
      28: invokevirtual #15                 // Method localeId:(Ljava/lang/String;)Lsoftware/amazon/awssdk/services/lexmodelsv2/model/BuildBotLocaleResponse$Builder;
      31: pop
      32: aload_0
      33: aload_1
      34: invokestatic  #16                 // Method software/amazon/awssdk/services/lexmodelsv2/model/BuildBotLocaleResponse.access$1000:(Lsoftware/amazon/awssdk/services/lexmodelsv2/model/BuildBotLocaleResponse;)Ljava/lang/String;
      37: invokevirtual #17                 // Method botLocaleStatus:(Ljava/lang/String;)Lsoftware/amazon/awssdk/services/lexmodelsv2/model/BuildBotLocaleResponse$Builder;
      40: pop
      41: aload_0
      42: aload_1
      43: invokestatic  #18                 // Method software/amazon/awssdk/services/lexmodelsv2/model/BuildBotLocaleResponse.access$1100:(Lsoftware/amazon/awssdk/services/lexmodelsv2/model/BuildBotLocaleResponse;)Ljava/time/Instant;
      46: invokevirtual #19                 // Method lastBuildSubmittedDateTime:(Ljava/time/Instant;)Lsoftware/amazon/awssdk/services/lexmodelsv2/model/BuildBotLocaleResponse$Builder;
      49: pop
      50: return

  public final java.lang.String getBotId();
    Code:
       0: aload_0
       1: getfield      #7                  // Field botId:Ljava/lang/String;
       4: areturn

  public final void setBotId(java.lang.String);
    Code:
       0: aload_0
       1: aload_1
       2: putfield      #7                  // Field botId:Ljava/lang/String;
       5: return

  public final software.amazon.awssdk.services.lexmodelsv2.model.BuildBotLocaleResponse$Builder botId(java.lang.String);
    Code:
       0: aload_0
       1: aload_1
       2: putfield      #7                  // Field botId:Ljava/lang/String;
       5: aload_0
       6: areturn

  public final java.lang.String getBotVersion();
    Code:
       0: aload_0
       1: getfield      #6                  // Field botVersion:Ljava/lang/String;
       4: areturn

  public final void setBotVersion(java.lang.String);
    Code:
       0: aload_0
       1: aload_1
       2: putfield      #6                  // Field botVersion:Ljava/lang/String;
       5: return

  public final software.amazon.awssdk.services.lexmodelsv2.model.BuildBotLocaleResponse$Builder botVersion(java.lang.String);
    Code:
       0: aload_0
       1: aload_1
       2: putfield      #6                  // Field botVersion:Ljava/lang/String;
       5: aload_0
       6: areturn

  public final java.lang.String getLocaleId();
    Code:
       0: aload_0
       1: getfield      #5                  // Field localeId:Ljava/lang/String;
       4: areturn

  public final void setLocaleId(java.lang.String);
    Code:
       0: aload_0
       1: aload_1
       2: putfield      #5                  // Field localeId:Ljava/lang/String;
       5: return

  public final software.amazon.awssdk.services.lexmodelsv2.model.BuildBotLocaleResponse$Builder localeId(java.lang.String);
    Code:
       0: aload_0
       1: aload_1
       2: putfield      #5                  // Field localeId:Ljava/lang/String;
       5: aload_0
       6: areturn

  public final java.lang.String getBotLocaleStatus();
    Code:
       0: aload_0
       1: getfield      #4                  // Field botLocaleStatus:Ljava/lang/String;
       4: areturn

  public final void setBotLocaleStatus(java.lang.String);
    Code:
       0: aload_0
       1: aload_1
       2: putfield      #4                  // Field botLocaleStatus:Ljava/lang/String;
       5: return

  public final software.amazon.awssdk.services.lexmodelsv2.model.BuildBotLocaleResponse$Builder botLocaleStatus(java.lang.String);
    Code:
       0: aload_0
       1: aload_1
       2: putfield      #4                  // Field botLocaleStatus:Ljava/lang/String;
       5: aload_0
       6: areturn

  public final software.amazon.awssdk.services.lexmodelsv2.model.BuildBotLocaleResponse$Builder botLocaleStatus(software.amazon.awssdk.services.lexmodelsv2.model.BotLocaleStatus);
    Code:
       0: aload_0
       1: aload_1
       2: ifnonnull     9
       5: aconst_null
       6: goto          13
       9: aload_1
      10: invokevirtual #20                 // Method software/amazon/awssdk/services/lexmodelsv2/model/BotLocaleStatus.toString:()Ljava/lang/String;
      13: invokevirtual #17                 // Method botLocaleStatus:(Ljava/lang/String;)Lsoftware/amazon/awssdk/services/lexmodelsv2/model/BuildBotLocaleResponse$Builder;
      16: pop
      17: aload_0
      18: areturn

  public final java.time.Instant getLastBuildSubmittedDateTime();
    Code:
       0: aload_0
       1: getfield      #3                  // Field lastBuildSubmittedDateTime:Ljava/time/Instant;
       4: areturn

  public final void setLastBuildSubmittedDateTime(java.time.Instant);
    Code:
       0: aload_0
       1: aload_1
       2: putfield      #3                  // Field lastBuildSubmittedDateTime:Ljava/time/Instant;
       5: return

  public final software.amazon.awssdk.services.lexmodelsv2.model.BuildBotLocaleResponse$Builder lastBuildSubmittedDateTime(java.time.Instant);
    Code:
       0: aload_0
       1: aload_1
       2: putfield      #3                  // Field lastBuildSubmittedDateTime:Ljava/time/Instant;
       5: aload_0
       6: areturn

  public software.amazon.awssdk.services.lexmodelsv2.model.BuildBotLocaleResponse build();
    Code:
       0: new           #21                 // class software/amazon/awssdk/services/lexmodelsv2/model/BuildBotLocaleResponse
       3: dup
       4: aload_0
       5: aconst_null
       6: invokespecial #22                 // Method software/amazon/awssdk/services/lexmodelsv2/model/BuildBotLocaleResponse."<init>":(Lsoftware/amazon/awssdk/services/lexmodelsv2/model/BuildBotLocaleResponse$BuilderImpl;Lsoftware/amazon/awssdk/services/lexmodelsv2/model/BuildBotLocaleResponse$1;)V
       9: areturn

  public java.util.List<software.amazon.awssdk.core.SdkField<?>> sdkFields();
    Code:
       0: invokestatic  #23                 // Method software/amazon/awssdk/services/lexmodelsv2/model/BuildBotLocaleResponse.access$1300:()Ljava/util/List;
       3: areturn

  public software.amazon.awssdk.services.lexmodelsv2.model.LexModelsV2Response build();
    Code:
       0: aload_0
       1: invokevirtual #24                 // Method build:()Lsoftware/amazon/awssdk/services/lexmodelsv2/model/BuildBotLocaleResponse;
       4: areturn

  public software.amazon.awssdk.awscore.AwsResponse build();
    Code:
       0: aload_0
       1: invokevirtual #24                 // Method build:()Lsoftware/amazon/awssdk/services/lexmodelsv2/model/BuildBotLocaleResponse;
       4: areturn

  public software.amazon.awssdk.core.SdkResponse build();
    Code:
       0: aload_0
       1: invokevirtual #24                 // Method build:()Lsoftware/amazon/awssdk/services/lexmodelsv2/model/BuildBotLocaleResponse;
       4: areturn

  public java.lang.Object build();
    Code:
       0: aload_0
       1: invokevirtual #24                 // Method build:()Lsoftware/amazon/awssdk/services/lexmodelsv2/model/BuildBotLocaleResponse;
       4: areturn

  static java.lang.String access$000(software.amazon.awssdk.services.lexmodelsv2.model.BuildBotLocaleResponse$BuilderImpl);
    Code:
       0: aload_0
       1: getfield      #7                  // Field botId:Ljava/lang/String;
       4: areturn

  static java.lang.String access$100(software.amazon.awssdk.services.lexmodelsv2.model.BuildBotLocaleResponse$BuilderImpl);
    Code:
       0: aload_0
       1: getfield      #6                  // Field botVersion:Ljava/lang/String;
       4: areturn

  static java.lang.String access$200(software.amazon.awssdk.services.lexmodelsv2.model.BuildBotLocaleResponse$BuilderImpl);
    Code:
       0: aload_0
       1: getfield      #5                  // Field localeId:Ljava/lang/String;
       4: areturn

  static java.lang.String access$300(software.amazon.awssdk.services.lexmodelsv2.model.BuildBotLocaleResponse$BuilderImpl);
    Code:
       0: aload_0
       1: getfield      #4                  // Field botLocaleStatus:Ljava/lang/String;
       4: areturn

  static java.time.Instant access$400(software.amazon.awssdk.services.lexmodelsv2.model.BuildBotLocaleResponse$BuilderImpl);
    Code:
       0: aload_0
       1: getfield      #3                  // Field lastBuildSubmittedDateTime:Ljava/time/Instant;
       4: areturn

  software.amazon.awssdk.services.lexmodelsv2.model.BuildBotLocaleResponse$BuilderImpl(software.amazon.awssdk.services.lexmodelsv2.model.BuildBotLocaleResponse, software.amazon.awssdk.services.lexmodelsv2.model.BuildBotLocaleResponse$1);
    Code:
       0: aload_0
       1: aload_1
       2: invokespecial #2                  // Method "<init>":(Lsoftware/amazon/awssdk/services/lexmodelsv2/model/BuildBotLocaleResponse;)V
       5: return

  software.amazon.awssdk.services.lexmodelsv2.model.BuildBotLocaleResponse$BuilderImpl(software.amazon.awssdk.services.lexmodelsv2.model.BuildBotLocaleResponse$1);
    Code:
       0: aload_0
       1: invokespecial #1                  // Method "<init>":()V
       4: return
}
