Compiled from "CreateUploadUrlResponse.java"
final class software.amazon.awssdk.services.lexmodelsv2.model.CreateUploadUrlResponse$BuilderImpl extends software.amazon.awssdk.services.lexmodelsv2.model.LexModelsV2Response$BuilderImpl implements software.amazon.awssdk.services.lexmodelsv2.model.CreateUploadUrlResponse$Builder {
  private java.lang.String importId;

  private java.lang.String uploadUrl;

  private software.amazon.awssdk.services.lexmodelsv2.model.CreateUploadUrlResponse$BuilderImpl();
    Code:
       0: aload_0
       1: invokespecial #5                  // Method software/amazon/awssdk/services/lexmodelsv2/model/LexModelsV2Response$BuilderImpl."<init>":()V
       4: return

  private software.amazon.awssdk.services.lexmodelsv2.model.CreateUploadUrlResponse$BuilderImpl(software.amazon.awssdk.services.lexmodelsv2.model.CreateUploadUrlResponse);
    Code:
       0: aload_0
       1: aload_1
       2: invokespecial #6                  // Method software/amazon/awssdk/services/lexmodelsv2/model/LexModelsV2Response$BuilderImpl."<init>":(Lsoftware/amazon/awssdk/services/lexmodelsv2/model/LexModelsV2Response;)V
       5: aload_0
       6: aload_1
       7: invokestatic  #7                  // Method software/amazon/awssdk/services/lexmodelsv2/model/CreateUploadUrlResponse.access$400:(Lsoftware/amazon/awssdk/services/lexmodelsv2/model/CreateUploadUrlResponse;)Ljava/lang/String;
      10: invokevirtual #8                  // Method importId:(Ljava/lang/String;)Lsoftware/amazon/awssdk/services/lexmodelsv2/model/CreateUploadUrlResponse$Builder;
      13: pop
      14: aload_0
      15: aload_1
      16: invokestatic  #9                  // Method software/amazon/awssdk/services/lexmodelsv2/model/CreateUploadUrlResponse.access$500:(Lsoftware/amazon/awssdk/services/lexmodelsv2/model/CreateUploadUrlResponse;)Ljava/lang/String;
      19: invokevirtual #10                 // Method uploadUrl:(Ljava/lang/String;)Lsoftware/amazon/awssdk/services/lexmodelsv2/model/CreateUploadUrlResponse$Builder;
      22: pop
      23: return

  public final java.lang.String getImportId();
    Code:
       0: aload_0
       1: getfield      #4                  // Field importId:Ljava/lang/String;
       4: areturn

  public final void setImportId(java.lang.String);
    Code:
       0: aload_0
       1: aload_1
       2: putfield      #4                  // Field importId:Ljava/lang/String;
       5: return

  public final software.amazon.awssdk.services.lexmodelsv2.model.CreateUploadUrlResponse$Builder importId(java.lang.String);
    Code:
       0: aload_0
       1: aload_1
       2: putfield      #4                  // Field importId:Ljava/lang/String;
       5: aload_0
       6: areturn

  public final java.lang.String getUploadUrl();
    Code:
       0: aload_0
       1: getfield      #3                  // Field uploadUrl:Ljava/lang/String;
       4: areturn

  public final void setUploadUrl(java.lang.String);
    Code:
       0: aload_0
       1: aload_1
       2: putfield      #3                  // Field uploadUrl:Ljava/lang/String;
       5: return

  public final software.amazon.awssdk.services.lexmodelsv2.model.CreateUploadUrlResponse$Builder uploadUrl(java.lang.String);
    Code:
       0: aload_0
       1: aload_1
       2: putfield      #3                  // Field uploadUrl:Ljava/lang/String;
       5: aload_0
       6: areturn

  public software.amazon.awssdk.services.lexmodelsv2.model.CreateUploadUrlResponse build();
    Code:
       0: new           #11                 // class software/amazon/awssdk/services/lexmodelsv2/model/CreateUploadUrlResponse
       3: dup
       4: aload_0
       5: aconst_null
       6: invokespecial #12                 // Method software/amazon/awssdk/services/lexmodelsv2/model/CreateUploadUrlResponse."<init>":(Lsoftware/amazon/awssdk/services/lexmodelsv2/model/CreateUploadUrlResponse$BuilderImpl;Lsoftware/amazon/awssdk/services/lexmodelsv2/model/CreateUploadUrlResponse$1;)V
       9: areturn

  public java.util.List<software.amazon.awssdk.core.SdkField<?>> sdkFields();
    Code:
       0: invokestatic  #13                 // Method software/amazon/awssdk/services/lexmodelsv2/model/CreateUploadUrlResponse.access$700:()Ljava/util/List;
       3: areturn

  public software.amazon.awssdk.services.lexmodelsv2.model.LexModelsV2Response build();
    Code:
       0: aload_0
       1: invokevirtual #14                 // Method build:()Lsoftware/amazon/awssdk/services/lexmodelsv2/model/CreateUploadUrlResponse;
       4: areturn

  public software.amazon.awssdk.awscore.AwsResponse build();
    Code:
       0: aload_0
       1: invokevirtual #14                 // Method build:()Lsoftware/amazon/awssdk/services/lexmodelsv2/model/CreateUploadUrlResponse;
       4: areturn

  public software.amazon.awssdk.core.SdkResponse build();
    Code:
       0: aload_0
       1: invokevirtual #14                 // Method build:()Lsoftware/amazon/awssdk/services/lexmodelsv2/model/CreateUploadUrlResponse;
       4: areturn

  public java.lang.Object build();
    Code:
       0: aload_0
       1: invokevirtual #14                 // Method build:()Lsoftware/amazon/awssdk/services/lexmodelsv2/model/CreateUploadUrlResponse;
       4: areturn

  static java.lang.String access$000(software.amazon.awssdk.services.lexmodelsv2.model.CreateUploadUrlResponse$BuilderImpl);
    Code:
       0: aload_0
       1: getfield      #4                  // Field importId:Ljava/lang/String;
       4: areturn

  static java.lang.String access$100(software.amazon.awssdk.services.lexmodelsv2.model.CreateUploadUrlResponse$BuilderImpl);
    Code:
       0: aload_0
       1: getfield      #3                  // Field uploadUrl:Ljava/lang/String;
       4: areturn

  software.amazon.awssdk.services.lexmodelsv2.model.CreateUploadUrlResponse$BuilderImpl(software.amazon.awssdk.services.lexmodelsv2.model.CreateUploadUrlResponse, software.amazon.awssdk.services.lexmodelsv2.model.CreateUploadUrlResponse$1);
    Code:
       0: aload_0
       1: aload_1
       2: invokespecial #2                  // Method "<init>":(Lsoftware/amazon/awssdk/services/lexmodelsv2/model/CreateUploadUrlResponse;)V
       5: return

  software.amazon.awssdk.services.lexmodelsv2.model.CreateUploadUrlResponse$BuilderImpl(software.amazon.awssdk.services.lexmodelsv2.model.CreateUploadUrlResponse$1);
    Code:
       0: aload_0
       1: invokespecial #1                  // Method "<init>":()V
       4: return
}
