Compiled from "CreateExportRequest.java"
final class software.amazon.awssdk.services.lexmodelsv2.model.CreateExportRequest$BuilderImpl extends software.amazon.awssdk.services.lexmodelsv2.model.LexModelsV2Request$BuilderImpl implements software.amazon.awssdk.services.lexmodelsv2.model.CreateExportRequest$Builder {
  private software.amazon.awssdk.services.lexmodelsv2.model.ExportResourceSpecification resourceSpecification;

  private java.lang.String fileFormat;

  private java.lang.String filePassword;

  private software.amazon.awssdk.services.lexmodelsv2.model.CreateExportRequest$BuilderImpl();
    Code:
       0: aload_0
       1: invokespecial #6                  // Method software/amazon/awssdk/services/lexmodelsv2/model/LexModelsV2Request$BuilderImpl."<init>":()V
       4: return

  private software.amazon.awssdk.services.lexmodelsv2.model.CreateExportRequest$BuilderImpl(software.amazon.awssdk.services.lexmodelsv2.model.CreateExportRequest);
    Code:
       0: aload_0
       1: aload_1
       2: invokespecial #7                  // Method software/amazon/awssdk/services/lexmodelsv2/model/LexModelsV2Request$BuilderImpl."<init>":(Lsoftware/amazon/awssdk/services/lexmodelsv2/model/LexModelsV2Request;)V
       5: aload_0
       6: aload_1
       7: invokestatic  #8                  // Method software/amazon/awssdk/services/lexmodelsv2/model/CreateExportRequest.access$500:(Lsoftware/amazon/awssdk/services/lexmodelsv2/model/CreateExportRequest;)Lsoftware/amazon/awssdk/services/lexmodelsv2/model/ExportResourceSpecification;
      10: invokevirtual #9                  // Method resourceSpecification:(Lsoftware/amazon/awssdk/services/lexmodelsv2/model/ExportResourceSpecification;)Lsoftware/amazon/awssdk/services/lexmodelsv2/model/CreateExportRequest$Builder;
      13: pop
      14: aload_0
      15: aload_1
      16: invokestatic  #10                 // Method software/amazon/awssdk/services/lexmodelsv2/model/CreateExportRequest.access$600:(Lsoftware/amazon/awssdk/services/lexmodelsv2/model/CreateExportRequest;)Ljava/lang/String;
      19: invokevirtual #11                 // Method fileFormat:(Ljava/lang/String;)Lsoftware/amazon/awssdk/services/lexmodelsv2/model/CreateExportRequest$Builder;
      22: pop
      23: aload_0
      24: aload_1
      25: invokestatic  #12                 // Method software/amazon/awssdk/services/lexmodelsv2/model/CreateExportRequest.access$700:(Lsoftware/amazon/awssdk/services/lexmodelsv2/model/CreateExportRequest;)Ljava/lang/String;
      28: invokevirtual #13                 // Method filePassword:(Ljava/lang/String;)Lsoftware/amazon/awssdk/services/lexmodelsv2/model/CreateExportRequest$Builder;
      31: pop
      32: return

  public final software.amazon.awssdk.services.lexmodelsv2.model.ExportResourceSpecification$Builder getResourceSpecification();
    Code:
       0: aload_0
       1: getfield      #5                  // Field resourceSpecification:Lsoftware/amazon/awssdk/services/lexmodelsv2/model/ExportResourceSpecification;
       4: ifnull        17
       7: aload_0
       8: getfield      #5                  // Field resourceSpecification:Lsoftware/amazon/awssdk/services/lexmodelsv2/model/ExportResourceSpecification;
      11: invokevirtual #14                 // Method software/amazon/awssdk/services/lexmodelsv2/model/ExportResourceSpecification.toBuilder:()Lsoftware/amazon/awssdk/services/lexmodelsv2/model/ExportResourceSpecification$Builder;
      14: goto          18
      17: aconst_null
      18: areturn

  public final void setResourceSpecification(software.amazon.awssdk.services.lexmodelsv2.model.ExportResourceSpecification$BuilderImpl);
    Code:
       0: aload_0
       1: aload_1
       2: ifnull        12
       5: aload_1
       6: invokevirtual #15                 // Method software/amazon/awssdk/services/lexmodelsv2/model/ExportResourceSpecification$BuilderImpl.build:()Lsoftware/amazon/awssdk/services/lexmodelsv2/model/ExportResourceSpecification;
       9: goto          13
      12: aconst_null
      13: putfield      #5                  // Field resourceSpecification:Lsoftware/amazon/awssdk/services/lexmodelsv2/model/ExportResourceSpecification;
      16: return

  public final software.amazon.awssdk.services.lexmodelsv2.model.CreateExportRequest$Builder resourceSpecification(software.amazon.awssdk.services.lexmodelsv2.model.ExportResourceSpecification);
    Code:
       0: aload_0
       1: aload_1
       2: putfield      #5                  // Field resourceSpecification:Lsoftware/amazon/awssdk/services/lexmodelsv2/model/ExportResourceSpecification;
       5: aload_0
       6: areturn

  public final java.lang.String getFileFormat();
    Code:
       0: aload_0
       1: getfield      #4                  // Field fileFormat:Ljava/lang/String;
       4: areturn

  public final void setFileFormat(java.lang.String);
    Code:
       0: aload_0
       1: aload_1
       2: putfield      #4                  // Field fileFormat:Ljava/lang/String;
       5: return

  public final software.amazon.awssdk.services.lexmodelsv2.model.CreateExportRequest$Builder fileFormat(java.lang.String);
    Code:
       0: aload_0
       1: aload_1
       2: putfield      #4                  // Field fileFormat:Ljava/lang/String;
       5: aload_0
       6: areturn

  public final software.amazon.awssdk.services.lexmodelsv2.model.CreateExportRequest$Builder fileFormat(software.amazon.awssdk.services.lexmodelsv2.model.ImportExportFileFormat);
    Code:
       0: aload_0
       1: aload_1
       2: ifnonnull     9
       5: aconst_null
       6: goto          13
       9: aload_1
      10: invokevirtual #16                 // Method software/amazon/awssdk/services/lexmodelsv2/model/ImportExportFileFormat.toString:()Ljava/lang/String;
      13: invokevirtual #11                 // Method fileFormat:(Ljava/lang/String;)Lsoftware/amazon/awssdk/services/lexmodelsv2/model/CreateExportRequest$Builder;
      16: pop
      17: aload_0
      18: areturn

  public final java.lang.String getFilePassword();
    Code:
       0: aload_0
       1: getfield      #3                  // Field filePassword:Ljava/lang/String;
       4: areturn

  public final void setFilePassword(java.lang.String);
    Code:
       0: aload_0
       1: aload_1
       2: putfield      #3                  // Field filePassword:Ljava/lang/String;
       5: return

  public final software.amazon.awssdk.services.lexmodelsv2.model.CreateExportRequest$Builder filePassword(java.lang.String);
    Code:
       0: aload_0
       1: aload_1
       2: putfield      #3                  // Field filePassword:Ljava/lang/String;
       5: aload_0
       6: areturn

  public software.amazon.awssdk.services.lexmodelsv2.model.CreateExportRequest$Builder overrideConfiguration(software.amazon.awssdk.awscore.AwsRequestOverrideConfiguration);
    Code:
       0: aload_0
       1: aload_1
       2: invokespecial #17                 // Method software/amazon/awssdk/services/lexmodelsv2/model/LexModelsV2Request$BuilderImpl.overrideConfiguration:(Lsoftware/amazon/awssdk/awscore/AwsRequestOverrideConfiguration;)Lsoftware/amazon/awssdk/awscore/AwsRequest$Builder;
       5: pop
       6: aload_0
       7: areturn

  public software.amazon.awssdk.services.lexmodelsv2.model.CreateExportRequest$Builder overrideConfiguration(java.util.function.Consumer<software.amazon.awssdk.awscore.AwsRequestOverrideConfiguration$Builder>);
    Code:
       0: aload_0
       1: aload_1
       2: invokespecial #18                 // Method software/amazon/awssdk/services/lexmodelsv2/model/LexModelsV2Request$BuilderImpl.overrideConfiguration:(Ljava/util/function/Consumer;)Lsoftware/amazon/awssdk/awscore/AwsRequest$Builder;
       5: pop
       6: aload_0
       7: areturn

  public software.amazon.awssdk.services.lexmodelsv2.model.CreateExportRequest build();
    Code:
       0: new           #19                 // class software/amazon/awssdk/services/lexmodelsv2/model/CreateExportRequest
       3: dup
       4: aload_0
       5: aconst_null
       6: invokespecial #20                 // Method software/amazon/awssdk/services/lexmodelsv2/model/CreateExportRequest."<init>":(Lsoftware/amazon/awssdk/services/lexmodelsv2/model/CreateExportRequest$BuilderImpl;Lsoftware/amazon/awssdk/services/lexmodelsv2/model/CreateExportRequest$1;)V
       9: areturn

  public java.util.List<software.amazon.awssdk.core.SdkField<?>> sdkFields();
    Code:
       0: invokestatic  #21                 // Method software/amazon/awssdk/services/lexmodelsv2/model/CreateExportRequest.access$900:()Ljava/util/List;
       3: areturn

  public software.amazon.awssdk.services.lexmodelsv2.model.LexModelsV2Request build();
    Code:
       0: aload_0
       1: invokevirtual #22                 // Method build:()Lsoftware/amazon/awssdk/services/lexmodelsv2/model/CreateExportRequest;
       4: areturn

  public software.amazon.awssdk.awscore.AwsRequest build();
    Code:
       0: aload_0
       1: invokevirtual #22                 // Method build:()Lsoftware/amazon/awssdk/services/lexmodelsv2/model/CreateExportRequest;
       4: areturn

  public software.amazon.awssdk.awscore.AwsRequest$Builder overrideConfiguration(java.util.function.Consumer);
    Code:
       0: aload_0
       1: aload_1
       2: invokevirtual #23                 // Method overrideConfiguration:(Ljava/util/function/Consumer;)Lsoftware/amazon/awssdk/services/lexmodelsv2/model/CreateExportRequest$Builder;
       5: areturn

  public software.amazon.awssdk.awscore.AwsRequest$Builder overrideConfiguration(software.amazon.awssdk.awscore.AwsRequestOverrideConfiguration);
    Code:
       0: aload_0
       1: aload_1
       2: invokevirtual #24                 // Method overrideConfiguration:(Lsoftware/amazon/awssdk/awscore/AwsRequestOverrideConfiguration;)Lsoftware/amazon/awssdk/services/lexmodelsv2/model/CreateExportRequest$Builder;
       5: areturn

  public software.amazon.awssdk.core.SdkRequest build();
    Code:
       0: aload_0
       1: invokevirtual #22                 // Method build:()Lsoftware/amazon/awssdk/services/lexmodelsv2/model/CreateExportRequest;
       4: areturn

  public java.lang.Object build();
    Code:
       0: aload_0
       1: invokevirtual #22                 // Method build:()Lsoftware/amazon/awssdk/services/lexmodelsv2/model/CreateExportRequest;
       4: areturn

  static software.amazon.awssdk.services.lexmodelsv2.model.ExportResourceSpecification access$000(software.amazon.awssdk.services.lexmodelsv2.model.CreateExportRequest$BuilderImpl);
    Code:
       0: aload_0
       1: getfield      #5                  // Field resourceSpecification:Lsoftware/amazon/awssdk/services/lexmodelsv2/model/ExportResourceSpecification;
       4: areturn

  static java.lang.String access$100(software.amazon.awssdk.services.lexmodelsv2.model.CreateExportRequest$BuilderImpl);
    Code:
       0: aload_0
       1: getfield      #4                  // Field fileFormat:Ljava/lang/String;
       4: areturn

  static java.lang.String access$200(software.amazon.awssdk.services.lexmodelsv2.model.CreateExportRequest$BuilderImpl);
    Code:
       0: aload_0
       1: getfield      #3                  // Field filePassword:Ljava/lang/String;
       4: areturn

  software.amazon.awssdk.services.lexmodelsv2.model.CreateExportRequest$BuilderImpl(software.amazon.awssdk.services.lexmodelsv2.model.CreateExportRequest, software.amazon.awssdk.services.lexmodelsv2.model.CreateExportRequest$1);
    Code:
       0: aload_0
       1: aload_1
       2: invokespecial #2                  // Method "<init>":(Lsoftware/amazon/awssdk/services/lexmodelsv2/model/CreateExportRequest;)V
       5: return

  software.amazon.awssdk.services.lexmodelsv2.model.CreateExportRequest$BuilderImpl(software.amazon.awssdk.services.lexmodelsv2.model.CreateExportRequest$1);
    Code:
       0: aload_0
       1: invokespecial #1                  // Method "<init>":()V
       4: return
}
