Compiled from "DescribeBotAliasResponse.java"
public interface software.amazon.awssdk.services.lexmodelsv2.model.DescribeBotAliasResponse$Builder extends software.amazon.awssdk.services.lexmodelsv2.model.LexModelsV2Response$Builder, software.amazon.awssdk.core.SdkPojo, software.amazon.awssdk.utils.builder.CopyableBuilder<software.amazon.awssdk.services.lexmodelsv2.model.DescribeBotAliasResponse$Builder, software.amazon.awssdk.services.lexmodelsv2.model.DescribeBotAliasResponse> {
  public abstract software.amazon.awssdk.services.lexmodelsv2.model.DescribeBotAliasResponse$Builder botAliasId(java.lang.String);

  public abstract software.amazon.awssdk.services.lexmodelsv2.model.DescribeBotAliasResponse$Builder botAliasName(java.lang.String);

  public abstract software.amazon.awssdk.services.lexmodelsv2.model.DescribeBotAliasResponse$Builder description(java.lang.String);

  public abstract software.amazon.awssdk.services.lexmodelsv2.model.DescribeBotAliasResponse$Builder botVersion(java.lang.String);

  public abstract software.amazon.awssdk.services.lexmodelsv2.model.DescribeBotAliasResponse$Builder botAliasLocaleSettings(java.util.Map<java.lang.String, software.amazon.awssdk.services.lexmodelsv2.model.BotAliasLocaleSettings>);

  public abstract software.amazon.awssdk.services.lexmodelsv2.model.DescribeBotAliasResponse$Builder conversationLogSettings(software.amazon.awssdk.services.lexmodelsv2.model.ConversationLogSettings);

  public default software.amazon.awssdk.services.lexmodelsv2.model.DescribeBotAliasResponse$Builder conversationLogSettings(java.util.function.Consumer<software.amazon.awssdk.services.lexmodelsv2.model.ConversationLogSettings$Builder>);
    Code:
       0: aload_0
       1: invokestatic  #1                  // Method software/amazon/awssdk/services/lexmodelsv2/model/ConversationLogSettings.builder:()Lsoftware/amazon/awssdk/services/lexmodelsv2/model/ConversationLogSettings$Builder;
       4: aload_1
       5: invokeinterface #2,  2            // InterfaceMethod software/amazon/awssdk/services/lexmodelsv2/model/ConversationLogSettings$Builder.applyMutation:(Ljava/util/function/Consumer;)Lsoftware/amazon/awssdk/utils/builder/SdkBuilder;
      10: checkcast     #3                  // class software/amazon/awssdk/services/lexmodelsv2/model/ConversationLogSettings$Builder
      13: invokeinterface #4,  1            // InterfaceMethod software/amazon/awssdk/services/lexmodelsv2/model/ConversationLogSettings$Builder.build:()Ljava/lang/Object;
      18: checkcast     #5                  // class software/amazon/awssdk/services/lexmodelsv2/model/ConversationLogSettings
      21: invokeinterface #6,  2            // InterfaceMethod conversationLogSettings:(Lsoftware/amazon/awssdk/services/lexmodelsv2/model/ConversationLogSettings;)Lsoftware/amazon/awssdk/services/lexmodelsv2/model/DescribeBotAliasResponse$Builder;
      26: areturn

  public abstract software.amazon.awssdk.services.lexmodelsv2.model.DescribeBotAliasResponse$Builder sentimentAnalysisSettings(software.amazon.awssdk.services.lexmodelsv2.model.SentimentAnalysisSettings);

  public default software.amazon.awssdk.services.lexmodelsv2.model.DescribeBotAliasResponse$Builder sentimentAnalysisSettings(java.util.function.Consumer<software.amazon.awssdk.services.lexmodelsv2.model.SentimentAnalysisSettings$Builder>);
    Code:
       0: aload_0
       1: invokestatic  #7                  // Method software/amazon/awssdk/services/lexmodelsv2/model/SentimentAnalysisSettings.builder:()Lsoftware/amazon/awssdk/services/lexmodelsv2/model/SentimentAnalysisSettings$Builder;
       4: aload_1
       5: invokeinterface #8,  2            // InterfaceMethod software/amazon/awssdk/services/lexmodelsv2/model/SentimentAnalysisSettings$Builder.applyMutation:(Ljava/util/function/Consumer;)Lsoftware/amazon/awssdk/utils/builder/SdkBuilder;
      10: checkcast     #9                  // class software/amazon/awssdk/services/lexmodelsv2/model/SentimentAnalysisSettings$Builder
      13: invokeinterface #10,  1           // InterfaceMethod software/amazon/awssdk/services/lexmodelsv2/model/SentimentAnalysisSettings$Builder.build:()Ljava/lang/Object;
      18: checkcast     #11                 // class software/amazon/awssdk/services/lexmodelsv2/model/SentimentAnalysisSettings
      21: invokeinterface #12,  2           // InterfaceMethod sentimentAnalysisSettings:(Lsoftware/amazon/awssdk/services/lexmodelsv2/model/SentimentAnalysisSettings;)Lsoftware/amazon/awssdk/services/lexmodelsv2/model/DescribeBotAliasResponse$Builder;
      26: areturn

  public abstract software.amazon.awssdk.services.lexmodelsv2.model.DescribeBotAliasResponse$Builder botAliasHistoryEvents(java.util.Collection<software.amazon.awssdk.services.lexmodelsv2.model.BotAliasHistoryEvent>);

  public abstract software.amazon.awssdk.services.lexmodelsv2.model.DescribeBotAliasResponse$Builder botAliasHistoryEvents(software.amazon.awssdk.services.lexmodelsv2.model.BotAliasHistoryEvent...);

  public abstract software.amazon.awssdk.services.lexmodelsv2.model.DescribeBotAliasResponse$Builder botAliasHistoryEvents(java.util.function.Consumer<software.amazon.awssdk.services.lexmodelsv2.model.BotAliasHistoryEvent$Builder>...);

  public abstract software.amazon.awssdk.services.lexmodelsv2.model.DescribeBotAliasResponse$Builder botAliasStatus(java.lang.String);

  public abstract software.amazon.awssdk.services.lexmodelsv2.model.DescribeBotAliasResponse$Builder botAliasStatus(software.amazon.awssdk.services.lexmodelsv2.model.BotAliasStatus);

  public abstract software.amazon.awssdk.services.lexmodelsv2.model.DescribeBotAliasResponse$Builder botId(java.lang.String);

  public abstract software.amazon.awssdk.services.lexmodelsv2.model.DescribeBotAliasResponse$Builder creationDateTime(java.time.Instant);

  public abstract software.amazon.awssdk.services.lexmodelsv2.model.DescribeBotAliasResponse$Builder lastUpdatedDateTime(java.time.Instant);

  public abstract software.amazon.awssdk.services.lexmodelsv2.model.DescribeBotAliasResponse$Builder parentBotNetworks(java.util.Collection<software.amazon.awssdk.services.lexmodelsv2.model.ParentBotNetwork>);

  public abstract software.amazon.awssdk.services.lexmodelsv2.model.DescribeBotAliasResponse$Builder parentBotNetworks(software.amazon.awssdk.services.lexmodelsv2.model.ParentBotNetwork...);

  public abstract software.amazon.awssdk.services.lexmodelsv2.model.DescribeBotAliasResponse$Builder parentBotNetworks(java.util.function.Consumer<software.amazon.awssdk.services.lexmodelsv2.model.ParentBotNetwork$Builder>...);
}
