Compiled from "DescribeBotVersionResponse.java"
public interface software.amazon.awssdk.services.lexmodelsv2.model.DescribeBotVersionResponse$Builder extends software.amazon.awssdk.services.lexmodelsv2.model.LexModelsV2Response$Builder, software.amazon.awssdk.core.SdkPojo, software.amazon.awssdk.utils.builder.CopyableBuilder<software.amazon.awssdk.services.lexmodelsv2.model.DescribeBotVersionResponse$Builder, software.amazon.awssdk.services.lexmodelsv2.model.DescribeBotVersionResponse> {
  public abstract software.amazon.awssdk.services.lexmodelsv2.model.DescribeBotVersionResponse$Builder botId(java.lang.String);

  public abstract software.amazon.awssdk.services.lexmodelsv2.model.DescribeBotVersionResponse$Builder botName(java.lang.String);

  public abstract software.amazon.awssdk.services.lexmodelsv2.model.DescribeBotVersionResponse$Builder botVersion(java.lang.String);

  public abstract software.amazon.awssdk.services.lexmodelsv2.model.DescribeBotVersionResponse$Builder description(java.lang.String);

  public abstract software.amazon.awssdk.services.lexmodelsv2.model.DescribeBotVersionResponse$Builder roleArn(java.lang.String);

  public abstract software.amazon.awssdk.services.lexmodelsv2.model.DescribeBotVersionResponse$Builder dataPrivacy(software.amazon.awssdk.services.lexmodelsv2.model.DataPrivacy);

  public default software.amazon.awssdk.services.lexmodelsv2.model.DescribeBotVersionResponse$Builder dataPrivacy(java.util.function.Consumer<software.amazon.awssdk.services.lexmodelsv2.model.DataPrivacy$Builder>);
    Code:
       0: aload_0
       1: invokestatic  #1                  // Method software/amazon/awssdk/services/lexmodelsv2/model/DataPrivacy.builder:()Lsoftware/amazon/awssdk/services/lexmodelsv2/model/DataPrivacy$Builder;
       4: aload_1
       5: invokeinterface #2,  2            // InterfaceMethod software/amazon/awssdk/services/lexmodelsv2/model/DataPrivacy$Builder.applyMutation:(Ljava/util/function/Consumer;)Lsoftware/amazon/awssdk/utils/builder/SdkBuilder;
      10: checkcast     #3                  // class software/amazon/awssdk/services/lexmodelsv2/model/DataPrivacy$Builder
      13: invokeinterface #4,  1            // InterfaceMethod software/amazon/awssdk/services/lexmodelsv2/model/DataPrivacy$Builder.build:()Ljava/lang/Object;
      18: checkcast     #5                  // class software/amazon/awssdk/services/lexmodelsv2/model/DataPrivacy
      21: invokeinterface #6,  2            // InterfaceMethod dataPrivacy:(Lsoftware/amazon/awssdk/services/lexmodelsv2/model/DataPrivacy;)Lsoftware/amazon/awssdk/services/lexmodelsv2/model/DescribeBotVersionResponse$Builder;
      26: areturn

  public abstract software.amazon.awssdk.services.lexmodelsv2.model.DescribeBotVersionResponse$Builder idleSessionTTLInSeconds(java.lang.Integer);

  public abstract software.amazon.awssdk.services.lexmodelsv2.model.DescribeBotVersionResponse$Builder botStatus(java.lang.String);

  public abstract software.amazon.awssdk.services.lexmodelsv2.model.DescribeBotVersionResponse$Builder botStatus(software.amazon.awssdk.services.lexmodelsv2.model.BotStatus);

  public abstract software.amazon.awssdk.services.lexmodelsv2.model.DescribeBotVersionResponse$Builder failureReasons(java.util.Collection<java.lang.String>);

  public abstract software.amazon.awssdk.services.lexmodelsv2.model.DescribeBotVersionResponse$Builder failureReasons(java.lang.String...);

  public abstract software.amazon.awssdk.services.lexmodelsv2.model.DescribeBotVersionResponse$Builder creationDateTime(java.time.Instant);

  public abstract software.amazon.awssdk.services.lexmodelsv2.model.DescribeBotVersionResponse$Builder parentBotNetworks(java.util.Collection<software.amazon.awssdk.services.lexmodelsv2.model.ParentBotNetwork>);

  public abstract software.amazon.awssdk.services.lexmodelsv2.model.DescribeBotVersionResponse$Builder parentBotNetworks(software.amazon.awssdk.services.lexmodelsv2.model.ParentBotNetwork...);

  public abstract software.amazon.awssdk.services.lexmodelsv2.model.DescribeBotVersionResponse$Builder parentBotNetworks(java.util.function.Consumer<software.amazon.awssdk.services.lexmodelsv2.model.ParentBotNetwork$Builder>...);

  public abstract software.amazon.awssdk.services.lexmodelsv2.model.DescribeBotVersionResponse$Builder botType(java.lang.String);

  public abstract software.amazon.awssdk.services.lexmodelsv2.model.DescribeBotVersionResponse$Builder botType(software.amazon.awssdk.services.lexmodelsv2.model.BotType);

  public abstract software.amazon.awssdk.services.lexmodelsv2.model.DescribeBotVersionResponse$Builder botMembers(java.util.Collection<software.amazon.awssdk.services.lexmodelsv2.model.BotMember>);

  public abstract software.amazon.awssdk.services.lexmodelsv2.model.DescribeBotVersionResponse$Builder botMembers(software.amazon.awssdk.services.lexmodelsv2.model.BotMember...);

  public abstract software.amazon.awssdk.services.lexmodelsv2.model.DescribeBotVersionResponse$Builder botMembers(java.util.function.Consumer<software.amazon.awssdk.services.lexmodelsv2.model.BotMember$Builder>...);
}
