Compiled from "IntentConfirmationSetting.java"
final class software.amazon.awssdk.services.lexmodelsv2.model.IntentConfirmationSetting$BuilderImpl implements software.amazon.awssdk.services.lexmodelsv2.model.IntentConfirmationSetting$Builder {
  private software.amazon.awssdk.services.lexmodelsv2.model.PromptSpecification promptSpecification;

  private software.amazon.awssdk.services.lexmodelsv2.model.ResponseSpecification declinationResponse;

  private java.lang.Boolean active;

  private software.amazon.awssdk.services.lexmodelsv2.model.ResponseSpecification confirmationResponse;

  private software.amazon.awssdk.services.lexmodelsv2.model.DialogState confirmationNextStep;

  private software.amazon.awssdk.services.lexmodelsv2.model.ConditionalSpecification confirmationConditional;

  private software.amazon.awssdk.services.lexmodelsv2.model.DialogState declinationNextStep;

  private software.amazon.awssdk.services.lexmodelsv2.model.ConditionalSpecification declinationConditional;

  private software.amazon.awssdk.services.lexmodelsv2.model.ResponseSpecification failureResponse;

  private software.amazon.awssdk.services.lexmodelsv2.model.DialogState failureNextStep;

  private software.amazon.awssdk.services.lexmodelsv2.model.ConditionalSpecification failureConditional;

  private software.amazon.awssdk.services.lexmodelsv2.model.DialogCodeHookInvocationSetting codeHook;

  private software.amazon.awssdk.services.lexmodelsv2.model.ElicitationCodeHookInvocationSetting elicitationCodeHook;

  private software.amazon.awssdk.services.lexmodelsv2.model.IntentConfirmationSetting$BuilderImpl();
    Code:
       0: aload_0
       1: invokespecial #16                 // Method java/lang/Object."<init>":()V
       4: return

  private software.amazon.awssdk.services.lexmodelsv2.model.IntentConfirmationSetting$BuilderImpl(software.amazon.awssdk.services.lexmodelsv2.model.IntentConfirmationSetting);
    Code:
       0: aload_0
       1: invokespecial #16                 // Method java/lang/Object."<init>":()V
       4: aload_0
       5: aload_1
       6: invokestatic  #17                 // Method software/amazon/awssdk/services/lexmodelsv2/model/IntentConfirmationSetting.access$1500:(Lsoftware/amazon/awssdk/services/lexmodelsv2/model/IntentConfirmationSetting;)Lsoftware/amazon/awssdk/services/lexmodelsv2/model/PromptSpecification;
       9: invokevirtual #18                 // Method promptSpecification:(Lsoftware/amazon/awssdk/services/lexmodelsv2/model/PromptSpecification;)Lsoftware/amazon/awssdk/services/lexmodelsv2/model/IntentConfirmationSetting$Builder;
      12: pop
      13: aload_0
      14: aload_1
      15: invokestatic  #19                 // Method software/amazon/awssdk/services/lexmodelsv2/model/IntentConfirmationSetting.access$1600:(Lsoftware/amazon/awssdk/services/lexmodelsv2/model/IntentConfirmationSetting;)Lsoftware/amazon/awssdk/services/lexmodelsv2/model/ResponseSpecification;
      18: invokevirtual #20                 // Method declinationResponse:(Lsoftware/amazon/awssdk/services/lexmodelsv2/model/ResponseSpecification;)Lsoftware/amazon/awssdk/services/lexmodelsv2/model/IntentConfirmationSetting$Builder;
      21: pop
      22: aload_0
      23: aload_1
      24: invokestatic  #21                 // Method software/amazon/awssdk/services/lexmodelsv2/model/IntentConfirmationSetting.access$1700:(Lsoftware/amazon/awssdk/services/lexmodelsv2/model/IntentConfirmationSetting;)Ljava/lang/Boolean;
      27: invokevirtual #22                 // Method active:(Ljava/lang/Boolean;)Lsoftware/amazon/awssdk/services/lexmodelsv2/model/IntentConfirmationSetting$Builder;
      30: pop
      31: aload_0
      32: aload_1
      33: invokestatic  #23                 // Method software/amazon/awssdk/services/lexmodelsv2/model/IntentConfirmationSetting.access$1800:(Lsoftware/amazon/awssdk/services/lexmodelsv2/model/IntentConfirmationSetting;)Lsoftware/amazon/awssdk/services/lexmodelsv2/model/ResponseSpecification;
      36: invokevirtual #24                 // Method confirmationResponse:(Lsoftware/amazon/awssdk/services/lexmodelsv2/model/ResponseSpecification;)Lsoftware/amazon/awssdk/services/lexmodelsv2/model/IntentConfirmationSetting$Builder;
      39: pop
      40: aload_0
      41: aload_1
      42: invokestatic  #25                 // Method software/amazon/awssdk/services/lexmodelsv2/model/IntentConfirmationSetting.access$1900:(Lsoftware/amazon/awssdk/services/lexmodelsv2/model/IntentConfirmationSetting;)Lsoftware/amazon/awssdk/services/lexmodelsv2/model/DialogState;
      45: invokevirtual #26                 // Method confirmationNextStep:(Lsoftware/amazon/awssdk/services/lexmodelsv2/model/DialogState;)Lsoftware/amazon/awssdk/services/lexmodelsv2/model/IntentConfirmationSetting$Builder;
      48: pop
      49: aload_0
      50: aload_1
      51: invokestatic  #27                 // Method software/amazon/awssdk/services/lexmodelsv2/model/IntentConfirmationSetting.access$2000:(Lsoftware/amazon/awssdk/services/lexmodelsv2/model/IntentConfirmationSetting;)Lsoftware/amazon/awssdk/services/lexmodelsv2/model/ConditionalSpecification;
      54: invokevirtual #28                 // Method confirmationConditional:(Lsoftware/amazon/awssdk/services/lexmodelsv2/model/ConditionalSpecification;)Lsoftware/amazon/awssdk/services/lexmodelsv2/model/IntentConfirmationSetting$Builder;
      57: pop
      58: aload_0
      59: aload_1
      60: invokestatic  #29                 // Method software/amazon/awssdk/services/lexmodelsv2/model/IntentConfirmationSetting.access$2100:(Lsoftware/amazon/awssdk/services/lexmodelsv2/model/IntentConfirmationSetting;)Lsoftware/amazon/awssdk/services/lexmodelsv2/model/DialogState;
      63: invokevirtual #30                 // Method declinationNextStep:(Lsoftware/amazon/awssdk/services/lexmodelsv2/model/DialogState;)Lsoftware/amazon/awssdk/services/lexmodelsv2/model/IntentConfirmationSetting$Builder;
      66: pop
      67: aload_0
      68: aload_1
      69: invokestatic  #31                 // Method software/amazon/awssdk/services/lexmodelsv2/model/IntentConfirmationSetting.access$2200:(Lsoftware/amazon/awssdk/services/lexmodelsv2/model/IntentConfirmationSetting;)Lsoftware/amazon/awssdk/services/lexmodelsv2/model/ConditionalSpecification;
      72: invokevirtual #32                 // Method declinationConditional:(Lsoftware/amazon/awssdk/services/lexmodelsv2/model/ConditionalSpecification;)Lsoftware/amazon/awssdk/services/lexmodelsv2/model/IntentConfirmationSetting$Builder;
      75: pop
      76: aload_0
      77: aload_1
      78: invokestatic  #33                 // Method software/amazon/awssdk/services/lexmodelsv2/model/IntentConfirmationSetting.access$2300:(Lsoftware/amazon/awssdk/services/lexmodelsv2/model/IntentConfirmationSetting;)Lsoftware/amazon/awssdk/services/lexmodelsv2/model/ResponseSpecification;
      81: invokevirtual #34                 // Method failureResponse:(Lsoftware/amazon/awssdk/services/lexmodelsv2/model/ResponseSpecification;)Lsoftware/amazon/awssdk/services/lexmodelsv2/model/IntentConfirmationSetting$Builder;
      84: pop
      85: aload_0
      86: aload_1
      87: invokestatic  #35                 // Method software/amazon/awssdk/services/lexmodelsv2/model/IntentConfirmationSetting.access$2400:(Lsoftware/amazon/awssdk/services/lexmodelsv2/model/IntentConfirmationSetting;)Lsoftware/amazon/awssdk/services/lexmodelsv2/model/DialogState;
      90: invokevirtual #36                 // Method failureNextStep:(Lsoftware/amazon/awssdk/services/lexmodelsv2/model/DialogState;)Lsoftware/amazon/awssdk/services/lexmodelsv2/model/IntentConfirmationSetting$Builder;
      93: pop
      94: aload_0
      95: aload_1
      96: invokestatic  #37                 // Method software/amazon/awssdk/services/lexmodelsv2/model/IntentConfirmationSetting.access$2500:(Lsoftware/amazon/awssdk/services/lexmodelsv2/model/IntentConfirmationSetting;)Lsoftware/amazon/awssdk/services/lexmodelsv2/model/ConditionalSpecification;
      99: invokevirtual #38                 // Method failureConditional:(Lsoftware/amazon/awssdk/services/lexmodelsv2/model/ConditionalSpecification;)Lsoftware/amazon/awssdk/services/lexmodelsv2/model/IntentConfirmationSetting$Builder;
     102: pop
     103: aload_0
     104: aload_1
     105: invokestatic  #39                 // Method software/amazon/awssdk/services/lexmodelsv2/model/IntentConfirmationSetting.access$2600:(Lsoftware/amazon/awssdk/services/lexmodelsv2/model/IntentConfirmationSetting;)Lsoftware/amazon/awssdk/services/lexmodelsv2/model/DialogCodeHookInvocationSetting;
     108: invokevirtual #40                 // Method codeHook:(Lsoftware/amazon/awssdk/services/lexmodelsv2/model/DialogCodeHookInvocationSetting;)Lsoftware/amazon/awssdk/services/lexmodelsv2/model/IntentConfirmationSetting$Builder;
     111: pop
     112: aload_0
     113: aload_1
     114: invokestatic  #41                 // Method software/amazon/awssdk/services/lexmodelsv2/model/IntentConfirmationSetting.access$2700:(Lsoftware/amazon/awssdk/services/lexmodelsv2/model/IntentConfirmationSetting;)Lsoftware/amazon/awssdk/services/lexmodelsv2/model/ElicitationCodeHookInvocationSetting;
     117: invokevirtual #42                 // Method elicitationCodeHook:(Lsoftware/amazon/awssdk/services/lexmodelsv2/model/ElicitationCodeHookInvocationSetting;)Lsoftware/amazon/awssdk/services/lexmodelsv2/model/IntentConfirmationSetting$Builder;
     120: pop
     121: return

  public final software.amazon.awssdk.services.lexmodelsv2.model.PromptSpecification$Builder getPromptSpecification();
    Code:
       0: aload_0
       1: getfield      #15                 // Field promptSpecification:Lsoftware/amazon/awssdk/services/lexmodelsv2/model/PromptSpecification;
       4: ifnull        17
       7: aload_0
       8: getfield      #15                 // Field promptSpecification:Lsoftware/amazon/awssdk/services/lexmodelsv2/model/PromptSpecification;
      11: invokevirtual #43                 // Method software/amazon/awssdk/services/lexmodelsv2/model/PromptSpecification.toBuilder:()Lsoftware/amazon/awssdk/services/lexmodelsv2/model/PromptSpecification$Builder;
      14: goto          18
      17: aconst_null
      18: areturn

  public final void setPromptSpecification(software.amazon.awssdk.services.lexmodelsv2.model.PromptSpecification$BuilderImpl);
    Code:
       0: aload_0
       1: aload_1
       2: ifnull        12
       5: aload_1
       6: invokevirtual #44                 // Method software/amazon/awssdk/services/lexmodelsv2/model/PromptSpecification$BuilderImpl.build:()Lsoftware/amazon/awssdk/services/lexmodelsv2/model/PromptSpecification;
       9: goto          13
      12: aconst_null
      13: putfield      #15                 // Field promptSpecification:Lsoftware/amazon/awssdk/services/lexmodelsv2/model/PromptSpecification;
      16: return

  public final software.amazon.awssdk.services.lexmodelsv2.model.IntentConfirmationSetting$Builder promptSpecification(software.amazon.awssdk.services.lexmodelsv2.model.PromptSpecification);
    Code:
       0: aload_0
       1: aload_1
       2: putfield      #15                 // Field promptSpecification:Lsoftware/amazon/awssdk/services/lexmodelsv2/model/PromptSpecification;
       5: aload_0
       6: areturn

  public final software.amazon.awssdk.services.lexmodelsv2.model.ResponseSpecification$Builder getDeclinationResponse();
    Code:
       0: aload_0
       1: getfield      #14                 // Field declinationResponse:Lsoftware/amazon/awssdk/services/lexmodelsv2/model/ResponseSpecification;
       4: ifnull        17
       7: aload_0
       8: getfield      #14                 // Field declinationResponse:Lsoftware/amazon/awssdk/services/lexmodelsv2/model/ResponseSpecification;
      11: invokevirtual #45                 // Method software/amazon/awssdk/services/lexmodelsv2/model/ResponseSpecification.toBuilder:()Lsoftware/amazon/awssdk/services/lexmodelsv2/model/ResponseSpecification$Builder;
      14: goto          18
      17: aconst_null
      18: areturn

  public final void setDeclinationResponse(software.amazon.awssdk.services.lexmodelsv2.model.ResponseSpecification$BuilderImpl);
    Code:
       0: aload_0
       1: aload_1
       2: ifnull        12
       5: aload_1
       6: invokevirtual #46                 // Method software/amazon/awssdk/services/lexmodelsv2/model/ResponseSpecification$BuilderImpl.build:()Lsoftware/amazon/awssdk/services/lexmodelsv2/model/ResponseSpecification;
       9: goto          13
      12: aconst_null
      13: putfield      #14                 // Field declinationResponse:Lsoftware/amazon/awssdk/services/lexmodelsv2/model/ResponseSpecification;
      16: return

  public final software.amazon.awssdk.services.lexmodelsv2.model.IntentConfirmationSetting$Builder declinationResponse(software.amazon.awssdk.services.lexmodelsv2.model.ResponseSpecification);
    Code:
       0: aload_0
       1: aload_1
       2: putfield      #14                 // Field declinationResponse:Lsoftware/amazon/awssdk/services/lexmodelsv2/model/ResponseSpecification;
       5: aload_0
       6: areturn

  public final java.lang.Boolean getActive();
    Code:
       0: aload_0
       1: getfield      #13                 // Field active:Ljava/lang/Boolean;
       4: areturn

  public final void setActive(java.lang.Boolean);
    Code:
       0: aload_0
       1: aload_1
       2: putfield      #13                 // Field active:Ljava/lang/Boolean;
       5: return

  public final software.amazon.awssdk.services.lexmodelsv2.model.IntentConfirmationSetting$Builder active(java.lang.Boolean);
    Code:
       0: aload_0
       1: aload_1
       2: putfield      #13                 // Field active:Ljava/lang/Boolean;
       5: aload_0
       6: areturn

  public final software.amazon.awssdk.services.lexmodelsv2.model.ResponseSpecification$Builder getConfirmationResponse();
    Code:
       0: aload_0
       1: getfield      #12                 // Field confirmationResponse:Lsoftware/amazon/awssdk/services/lexmodelsv2/model/ResponseSpecification;
       4: ifnull        17
       7: aload_0
       8: getfield      #12                 // Field confirmationResponse:Lsoftware/amazon/awssdk/services/lexmodelsv2/model/ResponseSpecification;
      11: invokevirtual #45                 // Method software/amazon/awssdk/services/lexmodelsv2/model/ResponseSpecification.toBuilder:()Lsoftware/amazon/awssdk/services/lexmodelsv2/model/ResponseSpecification$Builder;
      14: goto          18
      17: aconst_null
      18: areturn

  public final void setConfirmationResponse(software.amazon.awssdk.services.lexmodelsv2.model.ResponseSpecification$BuilderImpl);
    Code:
       0: aload_0
       1: aload_1
       2: ifnull        12
       5: aload_1
       6: invokevirtual #46                 // Method software/amazon/awssdk/services/lexmodelsv2/model/ResponseSpecification$BuilderImpl.build:()Lsoftware/amazon/awssdk/services/lexmodelsv2/model/ResponseSpecification;
       9: goto          13
      12: aconst_null
      13: putfield      #12                 // Field confirmationResponse:Lsoftware/amazon/awssdk/services/lexmodelsv2/model/ResponseSpecification;
      16: return

  public final software.amazon.awssdk.services.lexmodelsv2.model.IntentConfirmationSetting$Builder confirmationResponse(software.amazon.awssdk.services.lexmodelsv2.model.ResponseSpecification);
    Code:
       0: aload_0
       1: aload_1
       2: putfield      #12                 // Field confirmationResponse:Lsoftware/amazon/awssdk/services/lexmodelsv2/model/ResponseSpecification;
       5: aload_0
       6: areturn

  public final software.amazon.awssdk.services.lexmodelsv2.model.DialogState$Builder getConfirmationNextStep();
    Code:
       0: aload_0
       1: getfield      #11                 // Field confirmationNextStep:Lsoftware/amazon/awssdk/services/lexmodelsv2/model/DialogState;
       4: ifnull        17
       7: aload_0
       8: getfield      #11                 // Field confirmationNextStep:Lsoftware/amazon/awssdk/services/lexmodelsv2/model/DialogState;
      11: invokevirtual #47                 // Method software/amazon/awssdk/services/lexmodelsv2/model/DialogState.toBuilder:()Lsoftware/amazon/awssdk/services/lexmodelsv2/model/DialogState$Builder;
      14: goto          18
      17: aconst_null
      18: areturn

  public final void setConfirmationNextStep(software.amazon.awssdk.services.lexmodelsv2.model.DialogState$BuilderImpl);
    Code:
       0: aload_0
       1: aload_1
       2: ifnull        12
       5: aload_1
       6: invokevirtual #48                 // Method software/amazon/awssdk/services/lexmodelsv2/model/DialogState$BuilderImpl.build:()Lsoftware/amazon/awssdk/services/lexmodelsv2/model/DialogState;
       9: goto          13
      12: aconst_null
      13: putfield      #11                 // Field confirmationNextStep:Lsoftware/amazon/awssdk/services/lexmodelsv2/model/DialogState;
      16: return

  public final software.amazon.awssdk.services.lexmodelsv2.model.IntentConfirmationSetting$Builder confirmationNextStep(software.amazon.awssdk.services.lexmodelsv2.model.DialogState);
    Code:
       0: aload_0
       1: aload_1
       2: putfield      #11                 // Field confirmationNextStep:Lsoftware/amazon/awssdk/services/lexmodelsv2/model/DialogState;
       5: aload_0
       6: areturn

  public final software.amazon.awssdk.services.lexmodelsv2.model.ConditionalSpecification$Builder getConfirmationConditional();
    Code:
       0: aload_0
       1: getfield      #10                 // Field confirmationConditional:Lsoftware/amazon/awssdk/services/lexmodelsv2/model/ConditionalSpecification;
       4: ifnull        17
       7: aload_0
       8: getfield      #10                 // Field confirmationConditional:Lsoftware/amazon/awssdk/services/lexmodelsv2/model/ConditionalSpecification;
      11: invokevirtual #49                 // Method software/amazon/awssdk/services/lexmodelsv2/model/ConditionalSpecification.toBuilder:()Lsoftware/amazon/awssdk/services/lexmodelsv2/model/ConditionalSpecification$Builder;
      14: goto          18
      17: aconst_null
      18: areturn

  public final void setConfirmationConditional(software.amazon.awssdk.services.lexmodelsv2.model.ConditionalSpecification$BuilderImpl);
    Code:
       0: aload_0
       1: aload_1
       2: ifnull        12
       5: aload_1
       6: invokevirtual #50                 // Method software/amazon/awssdk/services/lexmodelsv2/model/ConditionalSpecification$BuilderImpl.build:()Lsoftware/amazon/awssdk/services/lexmodelsv2/model/ConditionalSpecification;
       9: goto          13
      12: aconst_null
      13: putfield      #10                 // Field confirmationConditional:Lsoftware/amazon/awssdk/services/lexmodelsv2/model/ConditionalSpecification;
      16: return

  public final software.amazon.awssdk.services.lexmodelsv2.model.IntentConfirmationSetting$Builder confirmationConditional(software.amazon.awssdk.services.lexmodelsv2.model.ConditionalSpecification);
    Code:
       0: aload_0
       1: aload_1
       2: putfield      #10                 // Field confirmationConditional:Lsoftware/amazon/awssdk/services/lexmodelsv2/model/ConditionalSpecification;
       5: aload_0
       6: areturn

  public final software.amazon.awssdk.services.lexmodelsv2.model.DialogState$Builder getDeclinationNextStep();
    Code:
       0: aload_0
       1: getfield      #9                  // Field declinationNextStep:Lsoftware/amazon/awssdk/services/lexmodelsv2/model/DialogState;
       4: ifnull        17
       7: aload_0
       8: getfield      #9                  // Field declinationNextStep:Lsoftware/amazon/awssdk/services/lexmodelsv2/model/DialogState;
      11: invokevirtual #47                 // Method software/amazon/awssdk/services/lexmodelsv2/model/DialogState.toBuilder:()Lsoftware/amazon/awssdk/services/lexmodelsv2/model/DialogState$Builder;
      14: goto          18
      17: aconst_null
      18: areturn

  public final void setDeclinationNextStep(software.amazon.awssdk.services.lexmodelsv2.model.DialogState$BuilderImpl);
    Code:
       0: aload_0
       1: aload_1
       2: ifnull        12
       5: aload_1
       6: invokevirtual #48                 // Method software/amazon/awssdk/services/lexmodelsv2/model/DialogState$BuilderImpl.build:()Lsoftware/amazon/awssdk/services/lexmodelsv2/model/DialogState;
       9: goto          13
      12: aconst_null
      13: putfield      #9                  // Field declinationNextStep:Lsoftware/amazon/awssdk/services/lexmodelsv2/model/DialogState;
      16: return

  public final software.amazon.awssdk.services.lexmodelsv2.model.IntentConfirmationSetting$Builder declinationNextStep(software.amazon.awssdk.services.lexmodelsv2.model.DialogState);
    Code:
       0: aload_0
       1: aload_1
       2: putfield      #9                  // Field declinationNextStep:Lsoftware/amazon/awssdk/services/lexmodelsv2/model/DialogState;
       5: aload_0
       6: areturn

  public final software.amazon.awssdk.services.lexmodelsv2.model.ConditionalSpecification$Builder getDeclinationConditional();
    Code:
       0: aload_0
       1: getfield      #8                  // Field declinationConditional:Lsoftware/amazon/awssdk/services/lexmodelsv2/model/ConditionalSpecification;
       4: ifnull        17
       7: aload_0
       8: getfield      #8                  // Field declinationConditional:Lsoftware/amazon/awssdk/services/lexmodelsv2/model/ConditionalSpecification;
      11: invokevirtual #49                 // Method software/amazon/awssdk/services/lexmodelsv2/model/ConditionalSpecification.toBuilder:()Lsoftware/amazon/awssdk/services/lexmodelsv2/model/ConditionalSpecification$Builder;
      14: goto          18
      17: aconst_null
      18: areturn

  public final void setDeclinationConditional(software.amazon.awssdk.services.lexmodelsv2.model.ConditionalSpecification$BuilderImpl);
    Code:
       0: aload_0
       1: aload_1
       2: ifnull        12
       5: aload_1
       6: invokevirtual #50                 // Method software/amazon/awssdk/services/lexmodelsv2/model/ConditionalSpecification$BuilderImpl.build:()Lsoftware/amazon/awssdk/services/lexmodelsv2/model/ConditionalSpecification;
       9: goto          13
      12: aconst_null
      13: putfield      #8                  // Field declinationConditional:Lsoftware/amazon/awssdk/services/lexmodelsv2/model/ConditionalSpecification;
      16: return

  public final software.amazon.awssdk.services.lexmodelsv2.model.IntentConfirmationSetting$Builder declinationConditional(software.amazon.awssdk.services.lexmodelsv2.model.ConditionalSpecification);
    Code:
       0: aload_0
       1: aload_1
       2: putfield      #8                  // Field declinationConditional:Lsoftware/amazon/awssdk/services/lexmodelsv2/model/ConditionalSpecification;
       5: aload_0
       6: areturn

  public final software.amazon.awssdk.services.lexmodelsv2.model.ResponseSpecification$Builder getFailureResponse();
    Code:
       0: aload_0
       1: getfield      #7                  // Field failureResponse:Lsoftware/amazon/awssdk/services/lexmodelsv2/model/ResponseSpecification;
       4: ifnull        17
       7: aload_0
       8: getfield      #7                  // Field failureResponse:Lsoftware/amazon/awssdk/services/lexmodelsv2/model/ResponseSpecification;
      11: invokevirtual #45                 // Method software/amazon/awssdk/services/lexmodelsv2/model/ResponseSpecification.toBuilder:()Lsoftware/amazon/awssdk/services/lexmodelsv2/model/ResponseSpecification$Builder;
      14: goto          18
      17: aconst_null
      18: areturn

  public final void setFailureResponse(software.amazon.awssdk.services.lexmodelsv2.model.ResponseSpecification$BuilderImpl);
    Code:
       0: aload_0
       1: aload_1
       2: ifnull        12
       5: aload_1
       6: invokevirtual #46                 // Method software/amazon/awssdk/services/lexmodelsv2/model/ResponseSpecification$BuilderImpl.build:()Lsoftware/amazon/awssdk/services/lexmodelsv2/model/ResponseSpecification;
       9: goto          13
      12: aconst_null
      13: putfield      #7                  // Field failureResponse:Lsoftware/amazon/awssdk/services/lexmodelsv2/model/ResponseSpecification;
      16: return

  public final software.amazon.awssdk.services.lexmodelsv2.model.IntentConfirmationSetting$Builder failureResponse(software.amazon.awssdk.services.lexmodelsv2.model.ResponseSpecification);
    Code:
       0: aload_0
       1: aload_1
       2: putfield      #7                  // Field failureResponse:Lsoftware/amazon/awssdk/services/lexmodelsv2/model/ResponseSpecification;
       5: aload_0
       6: areturn

  public final software.amazon.awssdk.services.lexmodelsv2.model.DialogState$Builder getFailureNextStep();
    Code:
       0: aload_0
       1: getfield      #6                  // Field failureNextStep:Lsoftware/amazon/awssdk/services/lexmodelsv2/model/DialogState;
       4: ifnull        17
       7: aload_0
       8: getfield      #6                  // Field failureNextStep:Lsoftware/amazon/awssdk/services/lexmodelsv2/model/DialogState;
      11: invokevirtual #47                 // Method software/amazon/awssdk/services/lexmodelsv2/model/DialogState.toBuilder:()Lsoftware/amazon/awssdk/services/lexmodelsv2/model/DialogState$Builder;
      14: goto          18
      17: aconst_null
      18: areturn

  public final void setFailureNextStep(software.amazon.awssdk.services.lexmodelsv2.model.DialogState$BuilderImpl);
    Code:
       0: aload_0
       1: aload_1
       2: ifnull        12
       5: aload_1
       6: invokevirtual #48                 // Method software/amazon/awssdk/services/lexmodelsv2/model/DialogState$BuilderImpl.build:()Lsoftware/amazon/awssdk/services/lexmodelsv2/model/DialogState;
       9: goto          13
      12: aconst_null
      13: putfield      #6                  // Field failureNextStep:Lsoftware/amazon/awssdk/services/lexmodelsv2/model/DialogState;
      16: return

  public final software.amazon.awssdk.services.lexmodelsv2.model.IntentConfirmationSetting$Builder failureNextStep(software.amazon.awssdk.services.lexmodelsv2.model.DialogState);
    Code:
       0: aload_0
       1: aload_1
       2: putfield      #6                  // Field failureNextStep:Lsoftware/amazon/awssdk/services/lexmodelsv2/model/DialogState;
       5: aload_0
       6: areturn

  public final software.amazon.awssdk.services.lexmodelsv2.model.ConditionalSpecification$Builder getFailureConditional();
    Code:
       0: aload_0
       1: getfield      #5                  // Field failureConditional:Lsoftware/amazon/awssdk/services/lexmodelsv2/model/ConditionalSpecification;
       4: ifnull        17
       7: aload_0
       8: getfield      #5                  // Field failureConditional:Lsoftware/amazon/awssdk/services/lexmodelsv2/model/ConditionalSpecification;
      11: invokevirtual #49                 // Method software/amazon/awssdk/services/lexmodelsv2/model/ConditionalSpecification.toBuilder:()Lsoftware/amazon/awssdk/services/lexmodelsv2/model/ConditionalSpecification$Builder;
      14: goto          18
      17: aconst_null
      18: areturn

  public final void setFailureConditional(software.amazon.awssdk.services.lexmodelsv2.model.ConditionalSpecification$BuilderImpl);
    Code:
       0: aload_0
       1: aload_1
       2: ifnull        12
       5: aload_1
       6: invokevirtual #50                 // Method software/amazon/awssdk/services/lexmodelsv2/model/ConditionalSpecification$BuilderImpl.build:()Lsoftware/amazon/awssdk/services/lexmodelsv2/model/ConditionalSpecification;
       9: goto          13
      12: aconst_null
      13: putfield      #5                  // Field failureConditional:Lsoftware/amazon/awssdk/services/lexmodelsv2/model/ConditionalSpecification;
      16: return

  public final software.amazon.awssdk.services.lexmodelsv2.model.IntentConfirmationSetting$Builder failureConditional(software.amazon.awssdk.services.lexmodelsv2.model.ConditionalSpecification);
    Code:
       0: aload_0
       1: aload_1
       2: putfield      #5                  // Field failureConditional:Lsoftware/amazon/awssdk/services/lexmodelsv2/model/ConditionalSpecification;
       5: aload_0
       6: areturn

  public final software.amazon.awssdk.services.lexmodelsv2.model.DialogCodeHookInvocationSetting$Builder getCodeHook();
    Code:
       0: aload_0
       1: getfield      #4                  // Field codeHook:Lsoftware/amazon/awssdk/services/lexmodelsv2/model/DialogCodeHookInvocationSetting;
       4: ifnull        17
       7: aload_0
       8: getfield      #4                  // Field codeHook:Lsoftware/amazon/awssdk/services/lexmodelsv2/model/DialogCodeHookInvocationSetting;
      11: invokevirtual #51                 // Method software/amazon/awssdk/services/lexmodelsv2/model/DialogCodeHookInvocationSetting.toBuilder:()Lsoftware/amazon/awssdk/services/lexmodelsv2/model/DialogCodeHookInvocationSetting$Builder;
      14: goto          18
      17: aconst_null
      18: areturn

  public final void setCodeHook(software.amazon.awssdk.services.lexmodelsv2.model.DialogCodeHookInvocationSetting$BuilderImpl);
    Code:
       0: aload_0
       1: aload_1
       2: ifnull        12
       5: aload_1
       6: invokevirtual #52                 // Method software/amazon/awssdk/services/lexmodelsv2/model/DialogCodeHookInvocationSetting$BuilderImpl.build:()Lsoftware/amazon/awssdk/services/lexmodelsv2/model/DialogCodeHookInvocationSetting;
       9: goto          13
      12: aconst_null
      13: putfield      #4                  // Field codeHook:Lsoftware/amazon/awssdk/services/lexmodelsv2/model/DialogCodeHookInvocationSetting;
      16: return

  public final software.amazon.awssdk.services.lexmodelsv2.model.IntentConfirmationSetting$Builder codeHook(software.amazon.awssdk.services.lexmodelsv2.model.DialogCodeHookInvocationSetting);
    Code:
       0: aload_0
       1: aload_1
       2: putfield      #4                  // Field codeHook:Lsoftware/amazon/awssdk/services/lexmodelsv2/model/DialogCodeHookInvocationSetting;
       5: aload_0
       6: areturn

  public final software.amazon.awssdk.services.lexmodelsv2.model.ElicitationCodeHookInvocationSetting$Builder getElicitationCodeHook();
    Code:
       0: aload_0
       1: getfield      #3                  // Field elicitationCodeHook:Lsoftware/amazon/awssdk/services/lexmodelsv2/model/ElicitationCodeHookInvocationSetting;
       4: ifnull        17
       7: aload_0
       8: getfield      #3                  // Field elicitationCodeHook:Lsoftware/amazon/awssdk/services/lexmodelsv2/model/ElicitationCodeHookInvocationSetting;
      11: invokevirtual #53                 // Method software/amazon/awssdk/services/lexmodelsv2/model/ElicitationCodeHookInvocationSetting.toBuilder:()Lsoftware/amazon/awssdk/services/lexmodelsv2/model/ElicitationCodeHookInvocationSetting$Builder;
      14: goto          18
      17: aconst_null
      18: areturn

  public final void setElicitationCodeHook(software.amazon.awssdk.services.lexmodelsv2.model.ElicitationCodeHookInvocationSetting$BuilderImpl);
    Code:
       0: aload_0
       1: aload_1
       2: ifnull        12
       5: aload_1
       6: invokevirtual #54                 // Method software/amazon/awssdk/services/lexmodelsv2/model/ElicitationCodeHookInvocationSetting$BuilderImpl.build:()Lsoftware/amazon/awssdk/services/lexmodelsv2/model/ElicitationCodeHookInvocationSetting;
       9: goto          13
      12: aconst_null
      13: putfield      #3                  // Field elicitationCodeHook:Lsoftware/amazon/awssdk/services/lexmodelsv2/model/ElicitationCodeHookInvocationSetting;
      16: return

  public final software.amazon.awssdk.services.lexmodelsv2.model.IntentConfirmationSetting$Builder elicitationCodeHook(software.amazon.awssdk.services.lexmodelsv2.model.ElicitationCodeHookInvocationSetting);
    Code:
       0: aload_0
       1: aload_1
       2: putfield      #3                  // Field elicitationCodeHook:Lsoftware/amazon/awssdk/services/lexmodelsv2/model/ElicitationCodeHookInvocationSetting;
       5: aload_0
       6: areturn

  public software.amazon.awssdk.services.lexmodelsv2.model.IntentConfirmationSetting build();
    Code:
       0: new           #55                 // class software/amazon/awssdk/services/lexmodelsv2/model/IntentConfirmationSetting
       3: dup
       4: aload_0
       5: aconst_null
       6: invokespecial #56                 // Method software/amazon/awssdk/services/lexmodelsv2/model/IntentConfirmationSetting."<init>":(Lsoftware/amazon/awssdk/services/lexmodelsv2/model/IntentConfirmationSetting$BuilderImpl;Lsoftware/amazon/awssdk/services/lexmodelsv2/model/IntentConfirmationSetting$1;)V
       9: areturn

  public java.util.List<software.amazon.awssdk.core.SdkField<?>> sdkFields();
    Code:
       0: invokestatic  #57                 // Method software/amazon/awssdk/services/lexmodelsv2/model/IntentConfirmationSetting.access$2900:()Ljava/util/List;
       3: areturn

  public java.lang.Object build();
    Code:
       0: aload_0
       1: invokevirtual #58                 // Method build:()Lsoftware/amazon/awssdk/services/lexmodelsv2/model/IntentConfirmationSetting;
       4: areturn

  static software.amazon.awssdk.services.lexmodelsv2.model.PromptSpecification access$000(software.amazon.awssdk.services.lexmodelsv2.model.IntentConfirmationSetting$BuilderImpl);
    Code:
       0: aload_0
       1: getfield      #15                 // Field promptSpecification:Lsoftware/amazon/awssdk/services/lexmodelsv2/model/PromptSpecification;
       4: areturn

  static software.amazon.awssdk.services.lexmodelsv2.model.ResponseSpecification access$100(software.amazon.awssdk.services.lexmodelsv2.model.IntentConfirmationSetting$BuilderImpl);
    Code:
       0: aload_0
       1: getfield      #14                 // Field declinationResponse:Lsoftware/amazon/awssdk/services/lexmodelsv2/model/ResponseSpecification;
       4: areturn

  static java.lang.Boolean access$200(software.amazon.awssdk.services.lexmodelsv2.model.IntentConfirmationSetting$BuilderImpl);
    Code:
       0: aload_0
       1: getfield      #13                 // Field active:Ljava/lang/Boolean;
       4: areturn

  static software.amazon.awssdk.services.lexmodelsv2.model.ResponseSpecification access$300(software.amazon.awssdk.services.lexmodelsv2.model.IntentConfirmationSetting$BuilderImpl);
    Code:
       0: aload_0
       1: getfield      #12                 // Field confirmationResponse:Lsoftware/amazon/awssdk/services/lexmodelsv2/model/ResponseSpecification;
       4: areturn

  static software.amazon.awssdk.services.lexmodelsv2.model.DialogState access$400(software.amazon.awssdk.services.lexmodelsv2.model.IntentConfirmationSetting$BuilderImpl);
    Code:
       0: aload_0
       1: getfield      #11                 // Field confirmationNextStep:Lsoftware/amazon/awssdk/services/lexmodelsv2/model/DialogState;
       4: areturn

  static software.amazon.awssdk.services.lexmodelsv2.model.ConditionalSpecification access$500(software.amazon.awssdk.services.lexmodelsv2.model.IntentConfirmationSetting$BuilderImpl);
    Code:
       0: aload_0
       1: getfield      #10                 // Field confirmationConditional:Lsoftware/amazon/awssdk/services/lexmodelsv2/model/ConditionalSpecification;
       4: areturn

  static software.amazon.awssdk.services.lexmodelsv2.model.DialogState access$600(software.amazon.awssdk.services.lexmodelsv2.model.IntentConfirmationSetting$BuilderImpl);
    Code:
       0: aload_0
       1: getfield      #9                  // Field declinationNextStep:Lsoftware/amazon/awssdk/services/lexmodelsv2/model/DialogState;
       4: areturn

  static software.amazon.awssdk.services.lexmodelsv2.model.ConditionalSpecification access$700(software.amazon.awssdk.services.lexmodelsv2.model.IntentConfirmationSetting$BuilderImpl);
    Code:
       0: aload_0
       1: getfield      #8                  // Field declinationConditional:Lsoftware/amazon/awssdk/services/lexmodelsv2/model/ConditionalSpecification;
       4: areturn

  static software.amazon.awssdk.services.lexmodelsv2.model.ResponseSpecification access$800(software.amazon.awssdk.services.lexmodelsv2.model.IntentConfirmationSetting$BuilderImpl);
    Code:
       0: aload_0
       1: getfield      #7                  // Field failureResponse:Lsoftware/amazon/awssdk/services/lexmodelsv2/model/ResponseSpecification;
       4: areturn

  static software.amazon.awssdk.services.lexmodelsv2.model.DialogState access$900(software.amazon.awssdk.services.lexmodelsv2.model.IntentConfirmationSetting$BuilderImpl);
    Code:
       0: aload_0
       1: getfield      #6                  // Field failureNextStep:Lsoftware/amazon/awssdk/services/lexmodelsv2/model/DialogState;
       4: areturn

  static software.amazon.awssdk.services.lexmodelsv2.model.ConditionalSpecification access$1000(software.amazon.awssdk.services.lexmodelsv2.model.IntentConfirmationSetting$BuilderImpl);
    Code:
       0: aload_0
       1: getfield      #5                  // Field failureConditional:Lsoftware/amazon/awssdk/services/lexmodelsv2/model/ConditionalSpecification;
       4: areturn

  static software.amazon.awssdk.services.lexmodelsv2.model.DialogCodeHookInvocationSetting access$1100(software.amazon.awssdk.services.lexmodelsv2.model.IntentConfirmationSetting$BuilderImpl);
    Code:
       0: aload_0
       1: getfield      #4                  // Field codeHook:Lsoftware/amazon/awssdk/services/lexmodelsv2/model/DialogCodeHookInvocationSetting;
       4: areturn

  static software.amazon.awssdk.services.lexmodelsv2.model.ElicitationCodeHookInvocationSetting access$1200(software.amazon.awssdk.services.lexmodelsv2.model.IntentConfirmationSetting$BuilderImpl);
    Code:
       0: aload_0
       1: getfield      #3                  // Field elicitationCodeHook:Lsoftware/amazon/awssdk/services/lexmodelsv2/model/ElicitationCodeHookInvocationSetting;
       4: areturn

  software.amazon.awssdk.services.lexmodelsv2.model.IntentConfirmationSetting$BuilderImpl(software.amazon.awssdk.services.lexmodelsv2.model.IntentConfirmationSetting, software.amazon.awssdk.services.lexmodelsv2.model.IntentConfirmationSetting$1);
    Code:
       0: aload_0
       1: aload_1
       2: invokespecial #2                  // Method "<init>":(Lsoftware/amazon/awssdk/services/lexmodelsv2/model/IntentConfirmationSetting;)V
       5: return

  software.amazon.awssdk.services.lexmodelsv2.model.IntentConfirmationSetting$BuilderImpl(software.amazon.awssdk.services.lexmodelsv2.model.IntentConfirmationSetting$1);
    Code:
       0: aload_0
       1: invokespecial #1                  // Method "<init>":()V
       4: return
}
