Compiled from "KendraConfiguration.java"
final class software.amazon.awssdk.services.lexmodelsv2.model.KendraConfiguration$BuilderImpl implements software.amazon.awssdk.services.lexmodelsv2.model.KendraConfiguration$Builder {
  private java.lang.String kendraIndex;

  private java.lang.Boolean queryFilterStringEnabled;

  private java.lang.String queryFilterString;

  private software.amazon.awssdk.services.lexmodelsv2.model.KendraConfiguration$BuilderImpl();
    Code:
       0: aload_0
       1: invokespecial #6                  // Method java/lang/Object."<init>":()V
       4: return

  private software.amazon.awssdk.services.lexmodelsv2.model.KendraConfiguration$BuilderImpl(software.amazon.awssdk.services.lexmodelsv2.model.KendraConfiguration);
    Code:
       0: aload_0
       1: invokespecial #6                  // Method java/lang/Object."<init>":()V
       4: aload_0
       5: aload_1
       6: invokestatic  #7                  // Method software/amazon/awssdk/services/lexmodelsv2/model/KendraConfiguration.access$500:(Lsoftware/amazon/awssdk/services/lexmodelsv2/model/KendraConfiguration;)Ljava/lang/String;
       9: invokevirtual #8                  // Method kendraIndex:(Ljava/lang/String;)Lsoftware/amazon/awssdk/services/lexmodelsv2/model/KendraConfiguration$Builder;
      12: pop
      13: aload_0
      14: aload_1
      15: invokestatic  #9                  // Method software/amazon/awssdk/services/lexmodelsv2/model/KendraConfiguration.access$600:(Lsoftware/amazon/awssdk/services/lexmodelsv2/model/KendraConfiguration;)Ljava/lang/Boolean;
      18: invokevirtual #10                 // Method queryFilterStringEnabled:(Ljava/lang/Boolean;)Lsoftware/amazon/awssdk/services/lexmodelsv2/model/KendraConfiguration$Builder;
      21: pop
      22: aload_0
      23: aload_1
      24: invokestatic  #11                 // Method software/amazon/awssdk/services/lexmodelsv2/model/KendraConfiguration.access$700:(Lsoftware/amazon/awssdk/services/lexmodelsv2/model/KendraConfiguration;)Ljava/lang/String;
      27: invokevirtual #12                 // Method queryFilterString:(Ljava/lang/String;)Lsoftware/amazon/awssdk/services/lexmodelsv2/model/KendraConfiguration$Builder;
      30: pop
      31: return

  public final java.lang.String getKendraIndex();
    Code:
       0: aload_0
       1: getfield      #5                  // Field kendraIndex:Ljava/lang/String;
       4: areturn

  public final void setKendraIndex(java.lang.String);
    Code:
       0: aload_0
       1: aload_1
       2: putfield      #5                  // Field kendraIndex:Ljava/lang/String;
       5: return

  public final software.amazon.awssdk.services.lexmodelsv2.model.KendraConfiguration$Builder kendraIndex(java.lang.String);
    Code:
       0: aload_0
       1: aload_1
       2: putfield      #5                  // Field kendraIndex:Ljava/lang/String;
       5: aload_0
       6: areturn

  public final java.lang.Boolean getQueryFilterStringEnabled();
    Code:
       0: aload_0
       1: getfield      #4                  // Field queryFilterStringEnabled:Ljava/lang/Boolean;
       4: areturn

  public final void setQueryFilterStringEnabled(java.lang.Boolean);
    Code:
       0: aload_0
       1: aload_1
       2: putfield      #4                  // Field queryFilterStringEnabled:Ljava/lang/Boolean;
       5: return

  public final software.amazon.awssdk.services.lexmodelsv2.model.KendraConfiguration$Builder queryFilterStringEnabled(java.lang.Boolean);
    Code:
       0: aload_0
       1: aload_1
       2: putfield      #4                  // Field queryFilterStringEnabled:Ljava/lang/Boolean;
       5: aload_0
       6: areturn

  public final java.lang.String getQueryFilterString();
    Code:
       0: aload_0
       1: getfield      #3                  // Field queryFilterString:Ljava/lang/String;
       4: areturn

  public final void setQueryFilterString(java.lang.String);
    Code:
       0: aload_0
       1: aload_1
       2: putfield      #3                  // Field queryFilterString:Ljava/lang/String;
       5: return

  public final software.amazon.awssdk.services.lexmodelsv2.model.KendraConfiguration$Builder queryFilterString(java.lang.String);
    Code:
       0: aload_0
       1: aload_1
       2: putfield      #3                  // Field queryFilterString:Ljava/lang/String;
       5: aload_0
       6: areturn

  public software.amazon.awssdk.services.lexmodelsv2.model.KendraConfiguration build();
    Code:
       0: new           #13                 // class software/amazon/awssdk/services/lexmodelsv2/model/KendraConfiguration
       3: dup
       4: aload_0
       5: aconst_null
       6: invokespecial #14                 // Method software/amazon/awssdk/services/lexmodelsv2/model/KendraConfiguration."<init>":(Lsoftware/amazon/awssdk/services/lexmodelsv2/model/KendraConfiguration$BuilderImpl;Lsoftware/amazon/awssdk/services/lexmodelsv2/model/KendraConfiguration$1;)V
       9: areturn

  public java.util.List<software.amazon.awssdk.core.SdkField<?>> sdkFields();
    Code:
       0: invokestatic  #15                 // Method software/amazon/awssdk/services/lexmodelsv2/model/KendraConfiguration.access$900:()Ljava/util/List;
       3: areturn

  public java.lang.Object build();
    Code:
       0: aload_0
       1: invokevirtual #16                 // Method build:()Lsoftware/amazon/awssdk/services/lexmodelsv2/model/KendraConfiguration;
       4: areturn

  static java.lang.String access$000(software.amazon.awssdk.services.lexmodelsv2.model.KendraConfiguration$BuilderImpl);
    Code:
       0: aload_0
       1: getfield      #5                  // Field kendraIndex:Ljava/lang/String;
       4: areturn

  static java.lang.Boolean access$100(software.amazon.awssdk.services.lexmodelsv2.model.KendraConfiguration$BuilderImpl);
    Code:
       0: aload_0
       1: getfield      #4                  // Field queryFilterStringEnabled:Ljava/lang/Boolean;
       4: areturn

  static java.lang.String access$200(software.amazon.awssdk.services.lexmodelsv2.model.KendraConfiguration$BuilderImpl);
    Code:
       0: aload_0
       1: getfield      #3                  // Field queryFilterString:Ljava/lang/String;
       4: areturn

  software.amazon.awssdk.services.lexmodelsv2.model.KendraConfiguration$BuilderImpl(software.amazon.awssdk.services.lexmodelsv2.model.KendraConfiguration, software.amazon.awssdk.services.lexmodelsv2.model.KendraConfiguration$1);
    Code:
       0: aload_0
       1: aload_1
       2: invokespecial #2                  // Method "<init>":(Lsoftware/amazon/awssdk/services/lexmodelsv2/model/KendraConfiguration;)V
       5: return

  software.amazon.awssdk.services.lexmodelsv2.model.KendraConfiguration$BuilderImpl(software.amazon.awssdk.services.lexmodelsv2.model.KendraConfiguration$1);
    Code:
       0: aload_0
       1: invokespecial #1                  // Method "<init>":()V
       4: return
}
