Compiled from "ListRecommendedIntentsRequest.java"
final class software.amazon.awssdk.services.lexmodelsv2.model.ListRecommendedIntentsRequest$BuilderImpl extends software.amazon.awssdk.services.lexmodelsv2.model.LexModelsV2Request$BuilderImpl implements software.amazon.awssdk.services.lexmodelsv2.model.ListRecommendedIntentsRequest$Builder {
  private java.lang.String botId;

  private java.lang.String botVersion;

  private java.lang.String localeId;

  private java.lang.String botRecommendationId;

  private java.lang.String nextToken;

  private java.lang.Integer maxResults;

  private software.amazon.awssdk.services.lexmodelsv2.model.ListRecommendedIntentsRequest$BuilderImpl();
    Code:
       0: aload_0
       1: invokespecial #9                  // Method software/amazon/awssdk/services/lexmodelsv2/model/LexModelsV2Request$BuilderImpl."<init>":()V
       4: return

  private software.amazon.awssdk.services.lexmodelsv2.model.ListRecommendedIntentsRequest$BuilderImpl(software.amazon.awssdk.services.lexmodelsv2.model.ListRecommendedIntentsRequest);
    Code:
       0: aload_0
       1: aload_1
       2: invokespecial #10                 // Method software/amazon/awssdk/services/lexmodelsv2/model/LexModelsV2Request$BuilderImpl."<init>":(Lsoftware/amazon/awssdk/services/lexmodelsv2/model/LexModelsV2Request;)V
       5: aload_0
       6: aload_1
       7: invokestatic  #11                 // Method software/amazon/awssdk/services/lexmodelsv2/model/ListRecommendedIntentsRequest.access$800:(Lsoftware/amazon/awssdk/services/lexmodelsv2/model/ListRecommendedIntentsRequest;)Ljava/lang/String;
      10: invokevirtual #12                 // Method botId:(Ljava/lang/String;)Lsoftware/amazon/awssdk/services/lexmodelsv2/model/ListRecommendedIntentsRequest$Builder;
      13: pop
      14: aload_0
      15: aload_1
      16: invokestatic  #13                 // Method software/amazon/awssdk/services/lexmodelsv2/model/ListRecommendedIntentsRequest.access$900:(Lsoftware/amazon/awssdk/services/lexmodelsv2/model/ListRecommendedIntentsRequest;)Ljava/lang/String;
      19: invokevirtual #14                 // Method botVersion:(Ljava/lang/String;)Lsoftware/amazon/awssdk/services/lexmodelsv2/model/ListRecommendedIntentsRequest$Builder;
      22: pop
      23: aload_0
      24: aload_1
      25: invokestatic  #15                 // Method software/amazon/awssdk/services/lexmodelsv2/model/ListRecommendedIntentsRequest.access$1000:(Lsoftware/amazon/awssdk/services/lexmodelsv2/model/ListRecommendedIntentsRequest;)Ljava/lang/String;
      28: invokevirtual #16                 // Method localeId:(Ljava/lang/String;)Lsoftware/amazon/awssdk/services/lexmodelsv2/model/ListRecommendedIntentsRequest$Builder;
      31: pop
      32: aload_0
      33: aload_1
      34: invokestatic  #17                 // Method software/amazon/awssdk/services/lexmodelsv2/model/ListRecommendedIntentsRequest.access$1100:(Lsoftware/amazon/awssdk/services/lexmodelsv2/model/ListRecommendedIntentsRequest;)Ljava/lang/String;
      37: invokevirtual #18                 // Method botRecommendationId:(Ljava/lang/String;)Lsoftware/amazon/awssdk/services/lexmodelsv2/model/ListRecommendedIntentsRequest$Builder;
      40: pop
      41: aload_0
      42: aload_1
      43: invokestatic  #19                 // Method software/amazon/awssdk/services/lexmodelsv2/model/ListRecommendedIntentsRequest.access$1200:(Lsoftware/amazon/awssdk/services/lexmodelsv2/model/ListRecommendedIntentsRequest;)Ljava/lang/String;
      46: invokevirtual #20                 // Method nextToken:(Ljava/lang/String;)Lsoftware/amazon/awssdk/services/lexmodelsv2/model/ListRecommendedIntentsRequest$Builder;
      49: pop
      50: aload_0
      51: aload_1
      52: invokestatic  #21                 // Method software/amazon/awssdk/services/lexmodelsv2/model/ListRecommendedIntentsRequest.access$1300:(Lsoftware/amazon/awssdk/services/lexmodelsv2/model/ListRecommendedIntentsRequest;)Ljava/lang/Integer;
      55: invokevirtual #22                 // Method maxResults:(Ljava/lang/Integer;)Lsoftware/amazon/awssdk/services/lexmodelsv2/model/ListRecommendedIntentsRequest$Builder;
      58: pop
      59: return

  public final java.lang.String getBotId();
    Code:
       0: aload_0
       1: getfield      #8                  // Field botId:Ljava/lang/String;
       4: areturn

  public final void setBotId(java.lang.String);
    Code:
       0: aload_0
       1: aload_1
       2: putfield      #8                  // Field botId:Ljava/lang/String;
       5: return

  public final software.amazon.awssdk.services.lexmodelsv2.model.ListRecommendedIntentsRequest$Builder botId(java.lang.String);
    Code:
       0: aload_0
       1: aload_1
       2: putfield      #8                  // Field botId:Ljava/lang/String;
       5: aload_0
       6: areturn

  public final java.lang.String getBotVersion();
    Code:
       0: aload_0
       1: getfield      #7                  // Field botVersion:Ljava/lang/String;
       4: areturn

  public final void setBotVersion(java.lang.String);
    Code:
       0: aload_0
       1: aload_1
       2: putfield      #7                  // Field botVersion:Ljava/lang/String;
       5: return

  public final software.amazon.awssdk.services.lexmodelsv2.model.ListRecommendedIntentsRequest$Builder botVersion(java.lang.String);
    Code:
       0: aload_0
       1: aload_1
       2: putfield      #7                  // Field botVersion:Ljava/lang/String;
       5: aload_0
       6: areturn

  public final java.lang.String getLocaleId();
    Code:
       0: aload_0
       1: getfield      #6                  // Field localeId:Ljava/lang/String;
       4: areturn

  public final void setLocaleId(java.lang.String);
    Code:
       0: aload_0
       1: aload_1
       2: putfield      #6                  // Field localeId:Ljava/lang/String;
       5: return

  public final software.amazon.awssdk.services.lexmodelsv2.model.ListRecommendedIntentsRequest$Builder localeId(java.lang.String);
    Code:
       0: aload_0
       1: aload_1
       2: putfield      #6                  // Field localeId:Ljava/lang/String;
       5: aload_0
       6: areturn

  public final java.lang.String getBotRecommendationId();
    Code:
       0: aload_0
       1: getfield      #5                  // Field botRecommendationId:Ljava/lang/String;
       4: areturn

  public final void setBotRecommendationId(java.lang.String);
    Code:
       0: aload_0
       1: aload_1
       2: putfield      #5                  // Field botRecommendationId:Ljava/lang/String;
       5: return

  public final software.amazon.awssdk.services.lexmodelsv2.model.ListRecommendedIntentsRequest$Builder botRecommendationId(java.lang.String);
    Code:
       0: aload_0
       1: aload_1
       2: putfield      #5                  // Field botRecommendationId:Ljava/lang/String;
       5: aload_0
       6: areturn

  public final java.lang.String getNextToken();
    Code:
       0: aload_0
       1: getfield      #4                  // Field nextToken:Ljava/lang/String;
       4: areturn

  public final void setNextToken(java.lang.String);
    Code:
       0: aload_0
       1: aload_1
       2: putfield      #4                  // Field nextToken:Ljava/lang/String;
       5: return

  public final software.amazon.awssdk.services.lexmodelsv2.model.ListRecommendedIntentsRequest$Builder nextToken(java.lang.String);
    Code:
       0: aload_0
       1: aload_1
       2: putfield      #4                  // Field nextToken:Ljava/lang/String;
       5: aload_0
       6: areturn

  public final java.lang.Integer getMaxResults();
    Code:
       0: aload_0
       1: getfield      #3                  // Field maxResults:Ljava/lang/Integer;
       4: areturn

  public final void setMaxResults(java.lang.Integer);
    Code:
       0: aload_0
       1: aload_1
       2: putfield      #3                  // Field maxResults:Ljava/lang/Integer;
       5: return

  public final software.amazon.awssdk.services.lexmodelsv2.model.ListRecommendedIntentsRequest$Builder maxResults(java.lang.Integer);
    Code:
       0: aload_0
       1: aload_1
       2: putfield      #3                  // Field maxResults:Ljava/lang/Integer;
       5: aload_0
       6: areturn

  public software.amazon.awssdk.services.lexmodelsv2.model.ListRecommendedIntentsRequest$Builder overrideConfiguration(software.amazon.awssdk.awscore.AwsRequestOverrideConfiguration);
    Code:
       0: aload_0
       1: aload_1
       2: invokespecial #23                 // Method software/amazon/awssdk/services/lexmodelsv2/model/LexModelsV2Request$BuilderImpl.overrideConfiguration:(Lsoftware/amazon/awssdk/awscore/AwsRequestOverrideConfiguration;)Lsoftware/amazon/awssdk/awscore/AwsRequest$Builder;
       5: pop
       6: aload_0
       7: areturn

  public software.amazon.awssdk.services.lexmodelsv2.model.ListRecommendedIntentsRequest$Builder overrideConfiguration(java.util.function.Consumer<software.amazon.awssdk.awscore.AwsRequestOverrideConfiguration$Builder>);
    Code:
       0: aload_0
       1: aload_1
       2: invokespecial #24                 // Method software/amazon/awssdk/services/lexmodelsv2/model/LexModelsV2Request$BuilderImpl.overrideConfiguration:(Ljava/util/function/Consumer;)Lsoftware/amazon/awssdk/awscore/AwsRequest$Builder;
       5: pop
       6: aload_0
       7: areturn

  public software.amazon.awssdk.services.lexmodelsv2.model.ListRecommendedIntentsRequest build();
    Code:
       0: new           #25                 // class software/amazon/awssdk/services/lexmodelsv2/model/ListRecommendedIntentsRequest
       3: dup
       4: aload_0
       5: aconst_null
       6: invokespecial #26                 // Method software/amazon/awssdk/services/lexmodelsv2/model/ListRecommendedIntentsRequest."<init>":(Lsoftware/amazon/awssdk/services/lexmodelsv2/model/ListRecommendedIntentsRequest$BuilderImpl;Lsoftware/amazon/awssdk/services/lexmodelsv2/model/ListRecommendedIntentsRequest$1;)V
       9: areturn

  public java.util.List<software.amazon.awssdk.core.SdkField<?>> sdkFields();
    Code:
       0: invokestatic  #27                 // Method software/amazon/awssdk/services/lexmodelsv2/model/ListRecommendedIntentsRequest.access$1500:()Ljava/util/List;
       3: areturn

  public software.amazon.awssdk.services.lexmodelsv2.model.LexModelsV2Request build();
    Code:
       0: aload_0
       1: invokevirtual #28                 // Method build:()Lsoftware/amazon/awssdk/services/lexmodelsv2/model/ListRecommendedIntentsRequest;
       4: areturn

  public software.amazon.awssdk.awscore.AwsRequest build();
    Code:
       0: aload_0
       1: invokevirtual #28                 // Method build:()Lsoftware/amazon/awssdk/services/lexmodelsv2/model/ListRecommendedIntentsRequest;
       4: areturn

  public software.amazon.awssdk.awscore.AwsRequest$Builder overrideConfiguration(java.util.function.Consumer);
    Code:
       0: aload_0
       1: aload_1
       2: invokevirtual #29                 // Method overrideConfiguration:(Ljava/util/function/Consumer;)Lsoftware/amazon/awssdk/services/lexmodelsv2/model/ListRecommendedIntentsRequest$Builder;
       5: areturn

  public software.amazon.awssdk.awscore.AwsRequest$Builder overrideConfiguration(software.amazon.awssdk.awscore.AwsRequestOverrideConfiguration);
    Code:
       0: aload_0
       1: aload_1
       2: invokevirtual #30                 // Method overrideConfiguration:(Lsoftware/amazon/awssdk/awscore/AwsRequestOverrideConfiguration;)Lsoftware/amazon/awssdk/services/lexmodelsv2/model/ListRecommendedIntentsRequest$Builder;
       5: areturn

  public software.amazon.awssdk.core.SdkRequest build();
    Code:
       0: aload_0
       1: invokevirtual #28                 // Method build:()Lsoftware/amazon/awssdk/services/lexmodelsv2/model/ListRecommendedIntentsRequest;
       4: areturn

  public java.lang.Object build();
    Code:
       0: aload_0
       1: invokevirtual #28                 // Method build:()Lsoftware/amazon/awssdk/services/lexmodelsv2/model/ListRecommendedIntentsRequest;
       4: areturn

  static java.lang.String access$000(software.amazon.awssdk.services.lexmodelsv2.model.ListRecommendedIntentsRequest$BuilderImpl);
    Code:
       0: aload_0
       1: getfield      #8                  // Field botId:Ljava/lang/String;
       4: areturn

  static java.lang.String access$100(software.amazon.awssdk.services.lexmodelsv2.model.ListRecommendedIntentsRequest$BuilderImpl);
    Code:
       0: aload_0
       1: getfield      #7                  // Field botVersion:Ljava/lang/String;
       4: areturn

  static java.lang.String access$200(software.amazon.awssdk.services.lexmodelsv2.model.ListRecommendedIntentsRequest$BuilderImpl);
    Code:
       0: aload_0
       1: getfield      #6                  // Field localeId:Ljava/lang/String;
       4: areturn

  static java.lang.String access$300(software.amazon.awssdk.services.lexmodelsv2.model.ListRecommendedIntentsRequest$BuilderImpl);
    Code:
       0: aload_0
       1: getfield      #5                  // Field botRecommendationId:Ljava/lang/String;
       4: areturn

  static java.lang.String access$400(software.amazon.awssdk.services.lexmodelsv2.model.ListRecommendedIntentsRequest$BuilderImpl);
    Code:
       0: aload_0
       1: getfield      #4                  // Field nextToken:Ljava/lang/String;
       4: areturn

  static java.lang.Integer access$500(software.amazon.awssdk.services.lexmodelsv2.model.ListRecommendedIntentsRequest$BuilderImpl);
    Code:
       0: aload_0
       1: getfield      #3                  // Field maxResults:Ljava/lang/Integer;
       4: areturn

  software.amazon.awssdk.services.lexmodelsv2.model.ListRecommendedIntentsRequest$BuilderImpl(software.amazon.awssdk.services.lexmodelsv2.model.ListRecommendedIntentsRequest, software.amazon.awssdk.services.lexmodelsv2.model.ListRecommendedIntentsRequest$1);
    Code:
       0: aload_0
       1: aload_1
       2: invokespecial #2                  // Method "<init>":(Lsoftware/amazon/awssdk/services/lexmodelsv2/model/ListRecommendedIntentsRequest;)V
       5: return

  software.amazon.awssdk.services.lexmodelsv2.model.ListRecommendedIntentsRequest$BuilderImpl(software.amazon.awssdk.services.lexmodelsv2.model.ListRecommendedIntentsRequest$1);
    Code:
       0: aload_0
       1: invokespecial #1                  // Method "<init>":()V
       4: return
}
