Compiled from "ParentBotNetwork.java"
final class software.amazon.awssdk.services.lexmodelsv2.model.ParentBotNetwork$BuilderImpl implements software.amazon.awssdk.services.lexmodelsv2.model.ParentBotNetwork$Builder {
  private java.lang.String botId;

  private java.lang.String botVersion;

  private software.amazon.awssdk.services.lexmodelsv2.model.ParentBotNetwork$BuilderImpl();
    Code:
       0: aload_0
       1: invokespecial #5                  // Method java/lang/Object."<init>":()V
       4: return

  private software.amazon.awssdk.services.lexmodelsv2.model.ParentBotNetwork$BuilderImpl(software.amazon.awssdk.services.lexmodelsv2.model.ParentBotNetwork);
    Code:
       0: aload_0
       1: invokespecial #5                  // Method java/lang/Object."<init>":()V
       4: aload_0
       5: aload_1
       6: invokestatic  #6                  // Method software/amazon/awssdk/services/lexmodelsv2/model/ParentBotNetwork.access$400:(Lsoftware/amazon/awssdk/services/lexmodelsv2/model/ParentBotNetwork;)Ljava/lang/String;
       9: invokevirtual #7                  // Method botId:(Ljava/lang/String;)Lsoftware/amazon/awssdk/services/lexmodelsv2/model/ParentBotNetwork$Builder;
      12: pop
      13: aload_0
      14: aload_1
      15: invokestatic  #8                  // Method software/amazon/awssdk/services/lexmodelsv2/model/ParentBotNetwork.access$500:(Lsoftware/amazon/awssdk/services/lexmodelsv2/model/ParentBotNetwork;)Ljava/lang/String;
      18: invokevirtual #9                  // Method botVersion:(Ljava/lang/String;)Lsoftware/amazon/awssdk/services/lexmodelsv2/model/ParentBotNetwork$Builder;
      21: pop
      22: return

  public final java.lang.String getBotId();
    Code:
       0: aload_0
       1: getfield      #4                  // Field botId:Ljava/lang/String;
       4: areturn

  public final void setBotId(java.lang.String);
    Code:
       0: aload_0
       1: aload_1
       2: putfield      #4                  // Field botId:Ljava/lang/String;
       5: return

  public final software.amazon.awssdk.services.lexmodelsv2.model.ParentBotNetwork$Builder botId(java.lang.String);
    Code:
       0: aload_0
       1: aload_1
       2: putfield      #4                  // Field botId:Ljava/lang/String;
       5: aload_0
       6: areturn

  public final java.lang.String getBotVersion();
    Code:
       0: aload_0
       1: getfield      #3                  // Field botVersion:Ljava/lang/String;
       4: areturn

  public final void setBotVersion(java.lang.String);
    Code:
       0: aload_0
       1: aload_1
       2: putfield      #3                  // Field botVersion:Ljava/lang/String;
       5: return

  public final software.amazon.awssdk.services.lexmodelsv2.model.ParentBotNetwork$Builder botVersion(java.lang.String);
    Code:
       0: aload_0
       1: aload_1
       2: putfield      #3                  // Field botVersion:Ljava/lang/String;
       5: aload_0
       6: areturn

  public software.amazon.awssdk.services.lexmodelsv2.model.ParentBotNetwork build();
    Code:
       0: new           #10                 // class software/amazon/awssdk/services/lexmodelsv2/model/ParentBotNetwork
       3: dup
       4: aload_0
       5: aconst_null
       6: invokespecial #11                 // Method software/amazon/awssdk/services/lexmodelsv2/model/ParentBotNetwork."<init>":(Lsoftware/amazon/awssdk/services/lexmodelsv2/model/ParentBotNetwork$BuilderImpl;Lsoftware/amazon/awssdk/services/lexmodelsv2/model/ParentBotNetwork$1;)V
       9: areturn

  public java.util.List<software.amazon.awssdk.core.SdkField<?>> sdkFields();
    Code:
       0: invokestatic  #12                 // Method software/amazon/awssdk/services/lexmodelsv2/model/ParentBotNetwork.access$700:()Ljava/util/List;
       3: areturn

  public java.lang.Object build();
    Code:
       0: aload_0
       1: invokevirtual #13                 // Method build:()Lsoftware/amazon/awssdk/services/lexmodelsv2/model/ParentBotNetwork;
       4: areturn

  static java.lang.String access$000(software.amazon.awssdk.services.lexmodelsv2.model.ParentBotNetwork$BuilderImpl);
    Code:
       0: aload_0
       1: getfield      #4                  // Field botId:Ljava/lang/String;
       4: areturn

  static java.lang.String access$100(software.amazon.awssdk.services.lexmodelsv2.model.ParentBotNetwork$BuilderImpl);
    Code:
       0: aload_0
       1: getfield      #3                  // Field botVersion:Ljava/lang/String;
       4: areturn

  software.amazon.awssdk.services.lexmodelsv2.model.ParentBotNetwork$BuilderImpl(software.amazon.awssdk.services.lexmodelsv2.model.ParentBotNetwork, software.amazon.awssdk.services.lexmodelsv2.model.ParentBotNetwork$1);
    Code:
       0: aload_0
       1: aload_1
       2: invokespecial #2                  // Method "<init>":(Lsoftware/amazon/awssdk/services/lexmodelsv2/model/ParentBotNetwork;)V
       5: return

  software.amazon.awssdk.services.lexmodelsv2.model.ParentBotNetwork$BuilderImpl(software.amazon.awssdk.services.lexmodelsv2.model.ParentBotNetwork$1);
    Code:
       0: aload_0
       1: invokespecial #1                  // Method "<init>":()V
       4: return
}
