Compiled from "RecommendedIntentSummary.java"
final class software.amazon.awssdk.services.lexmodelsv2.model.RecommendedIntentSummary$BuilderImpl implements software.amazon.awssdk.services.lexmodelsv2.model.RecommendedIntentSummary$Builder {
  private java.lang.String intentId;

  private java.lang.String intentName;

  private java.lang.Integer sampleUtterancesCount;

  private software.amazon.awssdk.services.lexmodelsv2.model.RecommendedIntentSummary$BuilderImpl();
    Code:
       0: aload_0
       1: invokespecial #6                  // Method java/lang/Object."<init>":()V
       4: return

  private software.amazon.awssdk.services.lexmodelsv2.model.RecommendedIntentSummary$BuilderImpl(software.amazon.awssdk.services.lexmodelsv2.model.RecommendedIntentSummary);
    Code:
       0: aload_0
       1: invokespecial #6                  // Method java/lang/Object."<init>":()V
       4: aload_0
       5: aload_1
       6: invokestatic  #7                  // Method software/amazon/awssdk/services/lexmodelsv2/model/RecommendedIntentSummary.access$500:(Lsoftware/amazon/awssdk/services/lexmodelsv2/model/RecommendedIntentSummary;)Ljava/lang/String;
       9: invokevirtual #8                  // Method intentId:(Ljava/lang/String;)Lsoftware/amazon/awssdk/services/lexmodelsv2/model/RecommendedIntentSummary$Builder;
      12: pop
      13: aload_0
      14: aload_1
      15: invokestatic  #9                  // Method software/amazon/awssdk/services/lexmodelsv2/model/RecommendedIntentSummary.access$600:(Lsoftware/amazon/awssdk/services/lexmodelsv2/model/RecommendedIntentSummary;)Ljava/lang/String;
      18: invokevirtual #10                 // Method intentName:(Ljava/lang/String;)Lsoftware/amazon/awssdk/services/lexmodelsv2/model/RecommendedIntentSummary$Builder;
      21: pop
      22: aload_0
      23: aload_1
      24: invokestatic  #11                 // Method software/amazon/awssdk/services/lexmodelsv2/model/RecommendedIntentSummary.access$700:(Lsoftware/amazon/awssdk/services/lexmodelsv2/model/RecommendedIntentSummary;)Ljava/lang/Integer;
      27: invokevirtual #12                 // Method sampleUtterancesCount:(Ljava/lang/Integer;)Lsoftware/amazon/awssdk/services/lexmodelsv2/model/RecommendedIntentSummary$Builder;
      30: pop
      31: return

  public final java.lang.String getIntentId();
    Code:
       0: aload_0
       1: getfield      #5                  // Field intentId:Ljava/lang/String;
       4: areturn

  public final void setIntentId(java.lang.String);
    Code:
       0: aload_0
       1: aload_1
       2: putfield      #5                  // Field intentId:Ljava/lang/String;
       5: return

  public final software.amazon.awssdk.services.lexmodelsv2.model.RecommendedIntentSummary$Builder intentId(java.lang.String);
    Code:
       0: aload_0
       1: aload_1
       2: putfield      #5                  // Field intentId:Ljava/lang/String;
       5: aload_0
       6: areturn

  public final java.lang.String getIntentName();
    Code:
       0: aload_0
       1: getfield      #4                  // Field intentName:Ljava/lang/String;
       4: areturn

  public final void setIntentName(java.lang.String);
    Code:
       0: aload_0
       1: aload_1
       2: putfield      #4                  // Field intentName:Ljava/lang/String;
       5: return

  public final software.amazon.awssdk.services.lexmodelsv2.model.RecommendedIntentSummary$Builder intentName(java.lang.String);
    Code:
       0: aload_0
       1: aload_1
       2: putfield      #4                  // Field intentName:Ljava/lang/String;
       5: aload_0
       6: areturn

  public final java.lang.Integer getSampleUtterancesCount();
    Code:
       0: aload_0
       1: getfield      #3                  // Field sampleUtterancesCount:Ljava/lang/Integer;
       4: areturn

  public final void setSampleUtterancesCount(java.lang.Integer);
    Code:
       0: aload_0
       1: aload_1
       2: putfield      #3                  // Field sampleUtterancesCount:Ljava/lang/Integer;
       5: return

  public final software.amazon.awssdk.services.lexmodelsv2.model.RecommendedIntentSummary$Builder sampleUtterancesCount(java.lang.Integer);
    Code:
       0: aload_0
       1: aload_1
       2: putfield      #3                  // Field sampleUtterancesCount:Ljava/lang/Integer;
       5: aload_0
       6: areturn

  public software.amazon.awssdk.services.lexmodelsv2.model.RecommendedIntentSummary build();
    Code:
       0: new           #13                 // class software/amazon/awssdk/services/lexmodelsv2/model/RecommendedIntentSummary
       3: dup
       4: aload_0
       5: aconst_null
       6: invokespecial #14                 // Method software/amazon/awssdk/services/lexmodelsv2/model/RecommendedIntentSummary."<init>":(Lsoftware/amazon/awssdk/services/lexmodelsv2/model/RecommendedIntentSummary$BuilderImpl;Lsoftware/amazon/awssdk/services/lexmodelsv2/model/RecommendedIntentSummary$1;)V
       9: areturn

  public java.util.List<software.amazon.awssdk.core.SdkField<?>> sdkFields();
    Code:
       0: invokestatic  #15                 // Method software/amazon/awssdk/services/lexmodelsv2/model/RecommendedIntentSummary.access$900:()Ljava/util/List;
       3: areturn

  public java.lang.Object build();
    Code:
       0: aload_0
       1: invokevirtual #16                 // Method build:()Lsoftware/amazon/awssdk/services/lexmodelsv2/model/RecommendedIntentSummary;
       4: areturn

  static java.lang.String access$000(software.amazon.awssdk.services.lexmodelsv2.model.RecommendedIntentSummary$BuilderImpl);
    Code:
       0: aload_0
       1: getfield      #5                  // Field intentId:Ljava/lang/String;
       4: areturn

  static java.lang.String access$100(software.amazon.awssdk.services.lexmodelsv2.model.RecommendedIntentSummary$BuilderImpl);
    Code:
       0: aload_0
       1: getfield      #4                  // Field intentName:Ljava/lang/String;
       4: areturn

  static java.lang.Integer access$200(software.amazon.awssdk.services.lexmodelsv2.model.RecommendedIntentSummary$BuilderImpl);
    Code:
       0: aload_0
       1: getfield      #3                  // Field sampleUtterancesCount:Ljava/lang/Integer;
       4: areturn

  software.amazon.awssdk.services.lexmodelsv2.model.RecommendedIntentSummary$BuilderImpl(software.amazon.awssdk.services.lexmodelsv2.model.RecommendedIntentSummary, software.amazon.awssdk.services.lexmodelsv2.model.RecommendedIntentSummary$1);
    Code:
       0: aload_0
       1: aload_1
       2: invokespecial #2                  // Method "<init>":(Lsoftware/amazon/awssdk/services/lexmodelsv2/model/RecommendedIntentSummary;)V
       5: return

  software.amazon.awssdk.services.lexmodelsv2.model.RecommendedIntentSummary$BuilderImpl(software.amazon.awssdk.services.lexmodelsv2.model.RecommendedIntentSummary$1);
    Code:
       0: aload_0
       1: invokespecial #1                  // Method "<init>":()V
       4: return
}
