Compiled from "S3BucketLogDestination.java"
final class software.amazon.awssdk.services.lexmodelsv2.model.S3BucketLogDestination$BuilderImpl implements software.amazon.awssdk.services.lexmodelsv2.model.S3BucketLogDestination$Builder {
  private java.lang.String kmsKeyArn;

  private java.lang.String s3BucketArn;

  private java.lang.String logPrefix;

  private software.amazon.awssdk.services.lexmodelsv2.model.S3BucketLogDestination$BuilderImpl();
    Code:
       0: aload_0
       1: invokespecial #6                  // Method java/lang/Object."<init>":()V
       4: return

  private software.amazon.awssdk.services.lexmodelsv2.model.S3BucketLogDestination$BuilderImpl(software.amazon.awssdk.services.lexmodelsv2.model.S3BucketLogDestination);
    Code:
       0: aload_0
       1: invokespecial #6                  // Method java/lang/Object."<init>":()V
       4: aload_0
       5: aload_1
       6: invokestatic  #7                  // Method software/amazon/awssdk/services/lexmodelsv2/model/S3BucketLogDestination.access$500:(Lsoftware/amazon/awssdk/services/lexmodelsv2/model/S3BucketLogDestination;)Ljava/lang/String;
       9: invokevirtual #8                  // Method kmsKeyArn:(Ljava/lang/String;)Lsoftware/amazon/awssdk/services/lexmodelsv2/model/S3BucketLogDestination$Builder;
      12: pop
      13: aload_0
      14: aload_1
      15: invokestatic  #9                  // Method software/amazon/awssdk/services/lexmodelsv2/model/S3BucketLogDestination.access$600:(Lsoftware/amazon/awssdk/services/lexmodelsv2/model/S3BucketLogDestination;)Ljava/lang/String;
      18: invokevirtual #10                 // Method s3BucketArn:(Ljava/lang/String;)Lsoftware/amazon/awssdk/services/lexmodelsv2/model/S3BucketLogDestination$Builder;
      21: pop
      22: aload_0
      23: aload_1
      24: invokestatic  #11                 // Method software/amazon/awssdk/services/lexmodelsv2/model/S3BucketLogDestination.access$700:(Lsoftware/amazon/awssdk/services/lexmodelsv2/model/S3BucketLogDestination;)Ljava/lang/String;
      27: invokevirtual #12                 // Method logPrefix:(Ljava/lang/String;)Lsoftware/amazon/awssdk/services/lexmodelsv2/model/S3BucketLogDestination$Builder;
      30: pop
      31: return

  public final java.lang.String getKmsKeyArn();
    Code:
       0: aload_0
       1: getfield      #5                  // Field kmsKeyArn:Ljava/lang/String;
       4: areturn

  public final void setKmsKeyArn(java.lang.String);
    Code:
       0: aload_0
       1: aload_1
       2: putfield      #5                  // Field kmsKeyArn:Ljava/lang/String;
       5: return

  public final software.amazon.awssdk.services.lexmodelsv2.model.S3BucketLogDestination$Builder kmsKeyArn(java.lang.String);
    Code:
       0: aload_0
       1: aload_1
       2: putfield      #5                  // Field kmsKeyArn:Ljava/lang/String;
       5: aload_0
       6: areturn

  public final java.lang.String getS3BucketArn();
    Code:
       0: aload_0
       1: getfield      #4                  // Field s3BucketArn:Ljava/lang/String;
       4: areturn

  public final void setS3BucketArn(java.lang.String);
    Code:
       0: aload_0
       1: aload_1
       2: putfield      #4                  // Field s3BucketArn:Ljava/lang/String;
       5: return

  public final software.amazon.awssdk.services.lexmodelsv2.model.S3BucketLogDestination$Builder s3BucketArn(java.lang.String);
    Code:
       0: aload_0
       1: aload_1
       2: putfield      #4                  // Field s3BucketArn:Ljava/lang/String;
       5: aload_0
       6: areturn

  public final java.lang.String getLogPrefix();
    Code:
       0: aload_0
       1: getfield      #3                  // Field logPrefix:Ljava/lang/String;
       4: areturn

  public final void setLogPrefix(java.lang.String);
    Code:
       0: aload_0
       1: aload_1
       2: putfield      #3                  // Field logPrefix:Ljava/lang/String;
       5: return

  public final software.amazon.awssdk.services.lexmodelsv2.model.S3BucketLogDestination$Builder logPrefix(java.lang.String);
    Code:
       0: aload_0
       1: aload_1
       2: putfield      #3                  // Field logPrefix:Ljava/lang/String;
       5: aload_0
       6: areturn

  public software.amazon.awssdk.services.lexmodelsv2.model.S3BucketLogDestination build();
    Code:
       0: new           #13                 // class software/amazon/awssdk/services/lexmodelsv2/model/S3BucketLogDestination
       3: dup
       4: aload_0
       5: aconst_null
       6: invokespecial #14                 // Method software/amazon/awssdk/services/lexmodelsv2/model/S3BucketLogDestination."<init>":(Lsoftware/amazon/awssdk/services/lexmodelsv2/model/S3BucketLogDestination$BuilderImpl;Lsoftware/amazon/awssdk/services/lexmodelsv2/model/S3BucketLogDestination$1;)V
       9: areturn

  public java.util.List<software.amazon.awssdk.core.SdkField<?>> sdkFields();
    Code:
       0: invokestatic  #15                 // Method software/amazon/awssdk/services/lexmodelsv2/model/S3BucketLogDestination.access$900:()Ljava/util/List;
       3: areturn

  public java.lang.Object build();
    Code:
       0: aload_0
       1: invokevirtual #16                 // Method build:()Lsoftware/amazon/awssdk/services/lexmodelsv2/model/S3BucketLogDestination;
       4: areturn

  static java.lang.String access$000(software.amazon.awssdk.services.lexmodelsv2.model.S3BucketLogDestination$BuilderImpl);
    Code:
       0: aload_0
       1: getfield      #5                  // Field kmsKeyArn:Ljava/lang/String;
       4: areturn

  static java.lang.String access$100(software.amazon.awssdk.services.lexmodelsv2.model.S3BucketLogDestination$BuilderImpl);
    Code:
       0: aload_0
       1: getfield      #4                  // Field s3BucketArn:Ljava/lang/String;
       4: areturn

  static java.lang.String access$200(software.amazon.awssdk.services.lexmodelsv2.model.S3BucketLogDestination$BuilderImpl);
    Code:
       0: aload_0
       1: getfield      #3                  // Field logPrefix:Ljava/lang/String;
       4: areturn

  software.amazon.awssdk.services.lexmodelsv2.model.S3BucketLogDestination$BuilderImpl(software.amazon.awssdk.services.lexmodelsv2.model.S3BucketLogDestination, software.amazon.awssdk.services.lexmodelsv2.model.S3BucketLogDestination$1);
    Code:
       0: aload_0
       1: aload_1
       2: invokespecial #2                  // Method "<init>":(Lsoftware/amazon/awssdk/services/lexmodelsv2/model/S3BucketLogDestination;)V
       5: return

  software.amazon.awssdk.services.lexmodelsv2.model.S3BucketLogDestination$BuilderImpl(software.amazon.awssdk.services.lexmodelsv2.model.S3BucketLogDestination$1);
    Code:
       0: aload_0
       1: invokespecial #1                  // Method "<init>":()V
       4: return
}
