Compiled from "SlotValueElicitationSetting.java"
final class software.amazon.awssdk.services.lexmodelsv2.model.SlotValueElicitationSetting$BuilderImpl implements software.amazon.awssdk.services.lexmodelsv2.model.SlotValueElicitationSetting$Builder {
  private software.amazon.awssdk.services.lexmodelsv2.model.SlotDefaultValueSpecification defaultValueSpecification;

  private java.lang.String slotConstraint;

  private software.amazon.awssdk.services.lexmodelsv2.model.PromptSpecification promptSpecification;

  private java.util.List<software.amazon.awssdk.services.lexmodelsv2.model.SampleUtterance> sampleUtterances;

  private software.amazon.awssdk.services.lexmodelsv2.model.WaitAndContinueSpecification waitAndContinueSpecification;

  private software.amazon.awssdk.services.lexmodelsv2.model.SlotCaptureSetting slotCaptureSetting;

  private software.amazon.awssdk.services.lexmodelsv2.model.SlotValueElicitationSetting$BuilderImpl();
    Code:
       0: aload_0
       1: invokespecial #9                  // Method java/lang/Object."<init>":()V
       4: aload_0
       5: invokestatic  #10                 // Method software/amazon/awssdk/core/util/DefaultSdkAutoConstructList.getInstance:()Lsoftware/amazon/awssdk/core/util/DefaultSdkAutoConstructList;
       8: putfield      #5                  // Field sampleUtterances:Ljava/util/List;
      11: return

  private software.amazon.awssdk.services.lexmodelsv2.model.SlotValueElicitationSetting$BuilderImpl(software.amazon.awssdk.services.lexmodelsv2.model.SlotValueElicitationSetting);
    Code:
       0: aload_0
       1: invokespecial #9                  // Method java/lang/Object."<init>":()V
       4: aload_0
       5: invokestatic  #10                 // Method software/amazon/awssdk/core/util/DefaultSdkAutoConstructList.getInstance:()Lsoftware/amazon/awssdk/core/util/DefaultSdkAutoConstructList;
       8: putfield      #5                  // Field sampleUtterances:Ljava/util/List;
      11: aload_0
      12: aload_1
      13: invokestatic  #11                 // Method software/amazon/awssdk/services/lexmodelsv2/model/SlotValueElicitationSetting.access$800:(Lsoftware/amazon/awssdk/services/lexmodelsv2/model/SlotValueElicitationSetting;)Lsoftware/amazon/awssdk/services/lexmodelsv2/model/SlotDefaultValueSpecification;
      16: invokevirtual #12                 // Method defaultValueSpecification:(Lsoftware/amazon/awssdk/services/lexmodelsv2/model/SlotDefaultValueSpecification;)Lsoftware/amazon/awssdk/services/lexmodelsv2/model/SlotValueElicitationSetting$Builder;
      19: pop
      20: aload_0
      21: aload_1
      22: invokestatic  #13                 // Method software/amazon/awssdk/services/lexmodelsv2/model/SlotValueElicitationSetting.access$900:(Lsoftware/amazon/awssdk/services/lexmodelsv2/model/SlotValueElicitationSetting;)Ljava/lang/String;
      25: invokevirtual #14                 // Method slotConstraint:(Ljava/lang/String;)Lsoftware/amazon/awssdk/services/lexmodelsv2/model/SlotValueElicitationSetting$Builder;
      28: pop
      29: aload_0
      30: aload_1
      31: invokestatic  #15                 // Method software/amazon/awssdk/services/lexmodelsv2/model/SlotValueElicitationSetting.access$1000:(Lsoftware/amazon/awssdk/services/lexmodelsv2/model/SlotValueElicitationSetting;)Lsoftware/amazon/awssdk/services/lexmodelsv2/model/PromptSpecification;
      34: invokevirtual #16                 // Method promptSpecification:(Lsoftware/amazon/awssdk/services/lexmodelsv2/model/PromptSpecification;)Lsoftware/amazon/awssdk/services/lexmodelsv2/model/SlotValueElicitationSetting$Builder;
      37: pop
      38: aload_0
      39: aload_1
      40: invokestatic  #17                 // Method software/amazon/awssdk/services/lexmodelsv2/model/SlotValueElicitationSetting.access$1100:(Lsoftware/amazon/awssdk/services/lexmodelsv2/model/SlotValueElicitationSetting;)Ljava/util/List;
      43: invokevirtual #18                 // Method sampleUtterances:(Ljava/util/Collection;)Lsoftware/amazon/awssdk/services/lexmodelsv2/model/SlotValueElicitationSetting$Builder;
      46: pop
      47: aload_0
      48: aload_1
      49: invokestatic  #19                 // Method software/amazon/awssdk/services/lexmodelsv2/model/SlotValueElicitationSetting.access$1200:(Lsoftware/amazon/awssdk/services/lexmodelsv2/model/SlotValueElicitationSetting;)Lsoftware/amazon/awssdk/services/lexmodelsv2/model/WaitAndContinueSpecification;
      52: invokevirtual #20                 // Method waitAndContinueSpecification:(Lsoftware/amazon/awssdk/services/lexmodelsv2/model/WaitAndContinueSpecification;)Lsoftware/amazon/awssdk/services/lexmodelsv2/model/SlotValueElicitationSetting$Builder;
      55: pop
      56: aload_0
      57: aload_1
      58: invokestatic  #21                 // Method software/amazon/awssdk/services/lexmodelsv2/model/SlotValueElicitationSetting.access$1300:(Lsoftware/amazon/awssdk/services/lexmodelsv2/model/SlotValueElicitationSetting;)Lsoftware/amazon/awssdk/services/lexmodelsv2/model/SlotCaptureSetting;
      61: invokevirtual #22                 // Method slotCaptureSetting:(Lsoftware/amazon/awssdk/services/lexmodelsv2/model/SlotCaptureSetting;)Lsoftware/amazon/awssdk/services/lexmodelsv2/model/SlotValueElicitationSetting$Builder;
      64: pop
      65: return

  public final software.amazon.awssdk.services.lexmodelsv2.model.SlotDefaultValueSpecification$Builder getDefaultValueSpecification();
    Code:
       0: aload_0
       1: getfield      #8                  // Field defaultValueSpecification:Lsoftware/amazon/awssdk/services/lexmodelsv2/model/SlotDefaultValueSpecification;
       4: ifnull        17
       7: aload_0
       8: getfield      #8                  // Field defaultValueSpecification:Lsoftware/amazon/awssdk/services/lexmodelsv2/model/SlotDefaultValueSpecification;
      11: invokevirtual #23                 // Method software/amazon/awssdk/services/lexmodelsv2/model/SlotDefaultValueSpecification.toBuilder:()Lsoftware/amazon/awssdk/services/lexmodelsv2/model/SlotDefaultValueSpecification$Builder;
      14: goto          18
      17: aconst_null
      18: areturn

  public final void setDefaultValueSpecification(software.amazon.awssdk.services.lexmodelsv2.model.SlotDefaultValueSpecification$BuilderImpl);
    Code:
       0: aload_0
       1: aload_1
       2: ifnull        12
       5: aload_1
       6: invokevirtual #24                 // Method software/amazon/awssdk/services/lexmodelsv2/model/SlotDefaultValueSpecification$BuilderImpl.build:()Lsoftware/amazon/awssdk/services/lexmodelsv2/model/SlotDefaultValueSpecification;
       9: goto          13
      12: aconst_null
      13: putfield      #8                  // Field defaultValueSpecification:Lsoftware/amazon/awssdk/services/lexmodelsv2/model/SlotDefaultValueSpecification;
      16: return

  public final software.amazon.awssdk.services.lexmodelsv2.model.SlotValueElicitationSetting$Builder defaultValueSpecification(software.amazon.awssdk.services.lexmodelsv2.model.SlotDefaultValueSpecification);
    Code:
       0: aload_0
       1: aload_1
       2: putfield      #8                  // Field defaultValueSpecification:Lsoftware/amazon/awssdk/services/lexmodelsv2/model/SlotDefaultValueSpecification;
       5: aload_0
       6: areturn

  public final java.lang.String getSlotConstraint();
    Code:
       0: aload_0
       1: getfield      #7                  // Field slotConstraint:Ljava/lang/String;
       4: areturn

  public final void setSlotConstraint(java.lang.String);
    Code:
       0: aload_0
       1: aload_1
       2: putfield      #7                  // Field slotConstraint:Ljava/lang/String;
       5: return

  public final software.amazon.awssdk.services.lexmodelsv2.model.SlotValueElicitationSetting$Builder slotConstraint(java.lang.String);
    Code:
       0: aload_0
       1: aload_1
       2: putfield      #7                  // Field slotConstraint:Ljava/lang/String;
       5: aload_0
       6: areturn

  public final software.amazon.awssdk.services.lexmodelsv2.model.SlotValueElicitationSetting$Builder slotConstraint(software.amazon.awssdk.services.lexmodelsv2.model.SlotConstraint);
    Code:
       0: aload_0
       1: aload_1
       2: ifnonnull     9
       5: aconst_null
       6: goto          13
       9: aload_1
      10: invokevirtual #25                 // Method software/amazon/awssdk/services/lexmodelsv2/model/SlotConstraint.toString:()Ljava/lang/String;
      13: invokevirtual #14                 // Method slotConstraint:(Ljava/lang/String;)Lsoftware/amazon/awssdk/services/lexmodelsv2/model/SlotValueElicitationSetting$Builder;
      16: pop
      17: aload_0
      18: areturn

  public final software.amazon.awssdk.services.lexmodelsv2.model.PromptSpecification$Builder getPromptSpecification();
    Code:
       0: aload_0
       1: getfield      #6                  // Field promptSpecification:Lsoftware/amazon/awssdk/services/lexmodelsv2/model/PromptSpecification;
       4: ifnull        17
       7: aload_0
       8: getfield      #6                  // Field promptSpecification:Lsoftware/amazon/awssdk/services/lexmodelsv2/model/PromptSpecification;
      11: invokevirtual #26                 // Method software/amazon/awssdk/services/lexmodelsv2/model/PromptSpecification.toBuilder:()Lsoftware/amazon/awssdk/services/lexmodelsv2/model/PromptSpecification$Builder;
      14: goto          18
      17: aconst_null
      18: areturn

  public final void setPromptSpecification(software.amazon.awssdk.services.lexmodelsv2.model.PromptSpecification$BuilderImpl);
    Code:
       0: aload_0
       1: aload_1
       2: ifnull        12
       5: aload_1
       6: invokevirtual #27                 // Method software/amazon/awssdk/services/lexmodelsv2/model/PromptSpecification$BuilderImpl.build:()Lsoftware/amazon/awssdk/services/lexmodelsv2/model/PromptSpecification;
       9: goto          13
      12: aconst_null
      13: putfield      #6                  // Field promptSpecification:Lsoftware/amazon/awssdk/services/lexmodelsv2/model/PromptSpecification;
      16: return

  public final software.amazon.awssdk.services.lexmodelsv2.model.SlotValueElicitationSetting$Builder promptSpecification(software.amazon.awssdk.services.lexmodelsv2.model.PromptSpecification);
    Code:
       0: aload_0
       1: aload_1
       2: putfield      #6                  // Field promptSpecification:Lsoftware/amazon/awssdk/services/lexmodelsv2/model/PromptSpecification;
       5: aload_0
       6: areturn

  public final java.util.List<software.amazon.awssdk.services.lexmodelsv2.model.SampleUtterance$Builder> getSampleUtterances();
    Code:
       0: aload_0
       1: getfield      #5                  // Field sampleUtterances:Ljava/util/List;
       4: invokestatic  #28                 // Method software/amazon/awssdk/services/lexmodelsv2/model/SampleUtterancesListCopier.copyToBuilder:(Ljava/util/Collection;)Ljava/util/List;
       7: astore_1
       8: aload_1
       9: instanceof    #29                 // class software/amazon/awssdk/core/util/SdkAutoConstructList
      12: ifeq          17
      15: aconst_null
      16: areturn
      17: aload_1
      18: areturn

  public final void setSampleUtterances(java.util.Collection<software.amazon.awssdk.services.lexmodelsv2.model.SampleUtterance$BuilderImpl>);
    Code:
       0: aload_0
       1: aload_1
       2: invokestatic  #30                 // Method software/amazon/awssdk/services/lexmodelsv2/model/SampleUtterancesListCopier.copyFromBuilder:(Ljava/util/Collection;)Ljava/util/List;
       5: putfield      #5                  // Field sampleUtterances:Ljava/util/List;
       8: return

  public final software.amazon.awssdk.services.lexmodelsv2.model.SlotValueElicitationSetting$Builder sampleUtterances(java.util.Collection<software.amazon.awssdk.services.lexmodelsv2.model.SampleUtterance>);
    Code:
       0: aload_0
       1: aload_1
       2: invokestatic  #31                 // Method software/amazon/awssdk/services/lexmodelsv2/model/SampleUtterancesListCopier.copy:(Ljava/util/Collection;)Ljava/util/List;
       5: putfield      #5                  // Field sampleUtterances:Ljava/util/List;
       8: aload_0
       9: areturn

  public final software.amazon.awssdk.services.lexmodelsv2.model.SlotValueElicitationSetting$Builder sampleUtterances(software.amazon.awssdk.services.lexmodelsv2.model.SampleUtterance...);
    Code:
       0: aload_0
       1: aload_1
       2: invokestatic  #32                 // Method java/util/Arrays.asList:([Ljava/lang/Object;)Ljava/util/List;
       5: invokevirtual #18                 // Method sampleUtterances:(Ljava/util/Collection;)Lsoftware/amazon/awssdk/services/lexmodelsv2/model/SlotValueElicitationSetting$Builder;
       8: pop
       9: aload_0
      10: areturn

  public final software.amazon.awssdk.services.lexmodelsv2.model.SlotValueElicitationSetting$Builder sampleUtterances(java.util.function.Consumer<software.amazon.awssdk.services.lexmodelsv2.model.SampleUtterance$Builder>...);
    Code:
       0: aload_0
       1: aload_1
       2: invokestatic  #33                 // InterfaceMethod java/util/stream/Stream.of:([Ljava/lang/Object;)Ljava/util/stream/Stream;
       5: invokedynamic #34,  0             // InvokeDynamic #0:apply:()Ljava/util/function/Function;
      10: invokeinterface #35,  2           // InterfaceMethod java/util/stream/Stream.map:(Ljava/util/function/Function;)Ljava/util/stream/Stream;
      15: invokestatic  #36                 // Method java/util/stream/Collectors.toList:()Ljava/util/stream/Collector;
      18: invokeinterface #37,  2           // InterfaceMethod java/util/stream/Stream.collect:(Ljava/util/stream/Collector;)Ljava/lang/Object;
      23: checkcast     #38                 // class java/util/Collection
      26: invokevirtual #18                 // Method sampleUtterances:(Ljava/util/Collection;)Lsoftware/amazon/awssdk/services/lexmodelsv2/model/SlotValueElicitationSetting$Builder;
      29: pop
      30: aload_0
      31: areturn

  public final software.amazon.awssdk.services.lexmodelsv2.model.WaitAndContinueSpecification$Builder getWaitAndContinueSpecification();
    Code:
       0: aload_0
       1: getfield      #4                  // Field waitAndContinueSpecification:Lsoftware/amazon/awssdk/services/lexmodelsv2/model/WaitAndContinueSpecification;
       4: ifnull        17
       7: aload_0
       8: getfield      #4                  // Field waitAndContinueSpecification:Lsoftware/amazon/awssdk/services/lexmodelsv2/model/WaitAndContinueSpecification;
      11: invokevirtual #39                 // Method software/amazon/awssdk/services/lexmodelsv2/model/WaitAndContinueSpecification.toBuilder:()Lsoftware/amazon/awssdk/services/lexmodelsv2/model/WaitAndContinueSpecification$Builder;
      14: goto          18
      17: aconst_null
      18: areturn

  public final void setWaitAndContinueSpecification(software.amazon.awssdk.services.lexmodelsv2.model.WaitAndContinueSpecification$BuilderImpl);
    Code:
       0: aload_0
       1: aload_1
       2: ifnull        12
       5: aload_1
       6: invokevirtual #40                 // Method software/amazon/awssdk/services/lexmodelsv2/model/WaitAndContinueSpecification$BuilderImpl.build:()Lsoftware/amazon/awssdk/services/lexmodelsv2/model/WaitAndContinueSpecification;
       9: goto          13
      12: aconst_null
      13: putfield      #4                  // Field waitAndContinueSpecification:Lsoftware/amazon/awssdk/services/lexmodelsv2/model/WaitAndContinueSpecification;
      16: return

  public final software.amazon.awssdk.services.lexmodelsv2.model.SlotValueElicitationSetting$Builder waitAndContinueSpecification(software.amazon.awssdk.services.lexmodelsv2.model.WaitAndContinueSpecification);
    Code:
       0: aload_0
       1: aload_1
       2: putfield      #4                  // Field waitAndContinueSpecification:Lsoftware/amazon/awssdk/services/lexmodelsv2/model/WaitAndContinueSpecification;
       5: aload_0
       6: areturn

  public final software.amazon.awssdk.services.lexmodelsv2.model.SlotCaptureSetting$Builder getSlotCaptureSetting();
    Code:
       0: aload_0
       1: getfield      #3                  // Field slotCaptureSetting:Lsoftware/amazon/awssdk/services/lexmodelsv2/model/SlotCaptureSetting;
       4: ifnull        17
       7: aload_0
       8: getfield      #3                  // Field slotCaptureSetting:Lsoftware/amazon/awssdk/services/lexmodelsv2/model/SlotCaptureSetting;
      11: invokevirtual #41                 // Method software/amazon/awssdk/services/lexmodelsv2/model/SlotCaptureSetting.toBuilder:()Lsoftware/amazon/awssdk/services/lexmodelsv2/model/SlotCaptureSetting$Builder;
      14: goto          18
      17: aconst_null
      18: areturn

  public final void setSlotCaptureSetting(software.amazon.awssdk.services.lexmodelsv2.model.SlotCaptureSetting$BuilderImpl);
    Code:
       0: aload_0
       1: aload_1
       2: ifnull        12
       5: aload_1
       6: invokevirtual #42                 // Method software/amazon/awssdk/services/lexmodelsv2/model/SlotCaptureSetting$BuilderImpl.build:()Lsoftware/amazon/awssdk/services/lexmodelsv2/model/SlotCaptureSetting;
       9: goto          13
      12: aconst_null
      13: putfield      #3                  // Field slotCaptureSetting:Lsoftware/amazon/awssdk/services/lexmodelsv2/model/SlotCaptureSetting;
      16: return

  public final software.amazon.awssdk.services.lexmodelsv2.model.SlotValueElicitationSetting$Builder slotCaptureSetting(software.amazon.awssdk.services.lexmodelsv2.model.SlotCaptureSetting);
    Code:
       0: aload_0
       1: aload_1
       2: putfield      #3                  // Field slotCaptureSetting:Lsoftware/amazon/awssdk/services/lexmodelsv2/model/SlotCaptureSetting;
       5: aload_0
       6: areturn

  public software.amazon.awssdk.services.lexmodelsv2.model.SlotValueElicitationSetting build();
    Code:
       0: new           #43                 // class software/amazon/awssdk/services/lexmodelsv2/model/SlotValueElicitationSetting
       3: dup
       4: aload_0
       5: aconst_null
       6: invokespecial #44                 // Method software/amazon/awssdk/services/lexmodelsv2/model/SlotValueElicitationSetting."<init>":(Lsoftware/amazon/awssdk/services/lexmodelsv2/model/SlotValueElicitationSetting$BuilderImpl;Lsoftware/amazon/awssdk/services/lexmodelsv2/model/SlotValueElicitationSetting$1;)V
       9: areturn

  public java.util.List<software.amazon.awssdk.core.SdkField<?>> sdkFields();
    Code:
       0: invokestatic  #45                 // Method software/amazon/awssdk/services/lexmodelsv2/model/SlotValueElicitationSetting.access$1500:()Ljava/util/List;
       3: areturn

  public java.lang.Object build();
    Code:
       0: aload_0
       1: invokevirtual #46                 // Method build:()Lsoftware/amazon/awssdk/services/lexmodelsv2/model/SlotValueElicitationSetting;
       4: areturn

  private static software.amazon.awssdk.services.lexmodelsv2.model.SampleUtterance lambda$sampleUtterances$0(java.util.function.Consumer);
    Code:
       0: invokestatic  #47                 // Method software/amazon/awssdk/services/lexmodelsv2/model/SampleUtterance.builder:()Lsoftware/amazon/awssdk/services/lexmodelsv2/model/SampleUtterance$Builder;
       3: aload_0
       4: invokeinterface #48,  2           // InterfaceMethod software/amazon/awssdk/services/lexmodelsv2/model/SampleUtterance$Builder.applyMutation:(Ljava/util/function/Consumer;)Lsoftware/amazon/awssdk/utils/builder/SdkBuilder;
       9: checkcast     #49                 // class software/amazon/awssdk/services/lexmodelsv2/model/SampleUtterance$Builder
      12: invokeinterface #50,  1           // InterfaceMethod software/amazon/awssdk/services/lexmodelsv2/model/SampleUtterance$Builder.build:()Ljava/lang/Object;
      17: checkcast     #51                 // class software/amazon/awssdk/services/lexmodelsv2/model/SampleUtterance
      20: areturn

  static software.amazon.awssdk.services.lexmodelsv2.model.SlotDefaultValueSpecification access$000(software.amazon.awssdk.services.lexmodelsv2.model.SlotValueElicitationSetting$BuilderImpl);
    Code:
       0: aload_0
       1: getfield      #8                  // Field defaultValueSpecification:Lsoftware/amazon/awssdk/services/lexmodelsv2/model/SlotDefaultValueSpecification;
       4: areturn

  static java.lang.String access$100(software.amazon.awssdk.services.lexmodelsv2.model.SlotValueElicitationSetting$BuilderImpl);
    Code:
       0: aload_0
       1: getfield      #7                  // Field slotConstraint:Ljava/lang/String;
       4: areturn

  static software.amazon.awssdk.services.lexmodelsv2.model.PromptSpecification access$200(software.amazon.awssdk.services.lexmodelsv2.model.SlotValueElicitationSetting$BuilderImpl);
    Code:
       0: aload_0
       1: getfield      #6                  // Field promptSpecification:Lsoftware/amazon/awssdk/services/lexmodelsv2/model/PromptSpecification;
       4: areturn

  static java.util.List access$300(software.amazon.awssdk.services.lexmodelsv2.model.SlotValueElicitationSetting$BuilderImpl);
    Code:
       0: aload_0
       1: getfield      #5                  // Field sampleUtterances:Ljava/util/List;
       4: areturn

  static software.amazon.awssdk.services.lexmodelsv2.model.WaitAndContinueSpecification access$400(software.amazon.awssdk.services.lexmodelsv2.model.SlotValueElicitationSetting$BuilderImpl);
    Code:
       0: aload_0
       1: getfield      #4                  // Field waitAndContinueSpecification:Lsoftware/amazon/awssdk/services/lexmodelsv2/model/WaitAndContinueSpecification;
       4: areturn

  static software.amazon.awssdk.services.lexmodelsv2.model.SlotCaptureSetting access$500(software.amazon.awssdk.services.lexmodelsv2.model.SlotValueElicitationSetting$BuilderImpl);
    Code:
       0: aload_0
       1: getfield      #3                  // Field slotCaptureSetting:Lsoftware/amazon/awssdk/services/lexmodelsv2/model/SlotCaptureSetting;
       4: areturn

  software.amazon.awssdk.services.lexmodelsv2.model.SlotValueElicitationSetting$BuilderImpl(software.amazon.awssdk.services.lexmodelsv2.model.SlotValueElicitationSetting, software.amazon.awssdk.services.lexmodelsv2.model.SlotValueElicitationSetting$1);
    Code:
       0: aload_0
       1: aload_1
       2: invokespecial #2                  // Method "<init>":(Lsoftware/amazon/awssdk/services/lexmodelsv2/model/SlotValueElicitationSetting;)V
       5: return

  software.amazon.awssdk.services.lexmodelsv2.model.SlotValueElicitationSetting$BuilderImpl(software.amazon.awssdk.services.lexmodelsv2.model.SlotValueElicitationSetting$1);
    Code:
       0: aload_0
       1: invokespecial #1                  // Method "<init>":()V
       4: return
}
