Compiled from "StartImportResponse.java"
final class software.amazon.awssdk.services.lexmodelsv2.model.StartImportResponse$BuilderImpl extends software.amazon.awssdk.services.lexmodelsv2.model.LexModelsV2Response$BuilderImpl implements software.amazon.awssdk.services.lexmodelsv2.model.StartImportResponse$Builder {
  private java.lang.String importId;

  private software.amazon.awssdk.services.lexmodelsv2.model.ImportResourceSpecification resourceSpecification;

  private java.lang.String mergeStrategy;

  private java.lang.String importStatus;

  private java.time.Instant creationDateTime;

  private software.amazon.awssdk.services.lexmodelsv2.model.StartImportResponse$BuilderImpl();
    Code:
       0: aload_0
       1: invokespecial #8                  // Method software/amazon/awssdk/services/lexmodelsv2/model/LexModelsV2Response$BuilderImpl."<init>":()V
       4: return

  private software.amazon.awssdk.services.lexmodelsv2.model.StartImportResponse$BuilderImpl(software.amazon.awssdk.services.lexmodelsv2.model.StartImportResponse);
    Code:
       0: aload_0
       1: aload_1
       2: invokespecial #9                  // Method software/amazon/awssdk/services/lexmodelsv2/model/LexModelsV2Response$BuilderImpl."<init>":(Lsoftware/amazon/awssdk/services/lexmodelsv2/model/LexModelsV2Response;)V
       5: aload_0
       6: aload_1
       7: invokestatic  #10                 // Method software/amazon/awssdk/services/lexmodelsv2/model/StartImportResponse.access$700:(Lsoftware/amazon/awssdk/services/lexmodelsv2/model/StartImportResponse;)Ljava/lang/String;
      10: invokevirtual #11                 // Method importId:(Ljava/lang/String;)Lsoftware/amazon/awssdk/services/lexmodelsv2/model/StartImportResponse$Builder;
      13: pop
      14: aload_0
      15: aload_1
      16: invokestatic  #12                 // Method software/amazon/awssdk/services/lexmodelsv2/model/StartImportResponse.access$800:(Lsoftware/amazon/awssdk/services/lexmodelsv2/model/StartImportResponse;)Lsoftware/amazon/awssdk/services/lexmodelsv2/model/ImportResourceSpecification;
      19: invokevirtual #13                 // Method resourceSpecification:(Lsoftware/amazon/awssdk/services/lexmodelsv2/model/ImportResourceSpecification;)Lsoftware/amazon/awssdk/services/lexmodelsv2/model/StartImportResponse$Builder;
      22: pop
      23: aload_0
      24: aload_1
      25: invokestatic  #14                 // Method software/amazon/awssdk/services/lexmodelsv2/model/StartImportResponse.access$900:(Lsoftware/amazon/awssdk/services/lexmodelsv2/model/StartImportResponse;)Ljava/lang/String;
      28: invokevirtual #15                 // Method mergeStrategy:(Ljava/lang/String;)Lsoftware/amazon/awssdk/services/lexmodelsv2/model/StartImportResponse$Builder;
      31: pop
      32: aload_0
      33: aload_1
      34: invokestatic  #16                 // Method software/amazon/awssdk/services/lexmodelsv2/model/StartImportResponse.access$1000:(Lsoftware/amazon/awssdk/services/lexmodelsv2/model/StartImportResponse;)Ljava/lang/String;
      37: invokevirtual #17                 // Method importStatus:(Ljava/lang/String;)Lsoftware/amazon/awssdk/services/lexmodelsv2/model/StartImportResponse$Builder;
      40: pop
      41: aload_0
      42: aload_1
      43: invokestatic  #18                 // Method software/amazon/awssdk/services/lexmodelsv2/model/StartImportResponse.access$1100:(Lsoftware/amazon/awssdk/services/lexmodelsv2/model/StartImportResponse;)Ljava/time/Instant;
      46: invokevirtual #19                 // Method creationDateTime:(Ljava/time/Instant;)Lsoftware/amazon/awssdk/services/lexmodelsv2/model/StartImportResponse$Builder;
      49: pop
      50: return

  public final java.lang.String getImportId();
    Code:
       0: aload_0
       1: getfield      #7                  // Field importId:Ljava/lang/String;
       4: areturn

  public final void setImportId(java.lang.String);
    Code:
       0: aload_0
       1: aload_1
       2: putfield      #7                  // Field importId:Ljava/lang/String;
       5: return

  public final software.amazon.awssdk.services.lexmodelsv2.model.StartImportResponse$Builder importId(java.lang.String);
    Code:
       0: aload_0
       1: aload_1
       2: putfield      #7                  // Field importId:Ljava/lang/String;
       5: aload_0
       6: areturn

  public final software.amazon.awssdk.services.lexmodelsv2.model.ImportResourceSpecification$Builder getResourceSpecification();
    Code:
       0: aload_0
       1: getfield      #6                  // Field resourceSpecification:Lsoftware/amazon/awssdk/services/lexmodelsv2/model/ImportResourceSpecification;
       4: ifnull        17
       7: aload_0
       8: getfield      #6                  // Field resourceSpecification:Lsoftware/amazon/awssdk/services/lexmodelsv2/model/ImportResourceSpecification;
      11: invokevirtual #20                 // Method software/amazon/awssdk/services/lexmodelsv2/model/ImportResourceSpecification.toBuilder:()Lsoftware/amazon/awssdk/services/lexmodelsv2/model/ImportResourceSpecification$Builder;
      14: goto          18
      17: aconst_null
      18: areturn

  public final void setResourceSpecification(software.amazon.awssdk.services.lexmodelsv2.model.ImportResourceSpecification$BuilderImpl);
    Code:
       0: aload_0
       1: aload_1
       2: ifnull        12
       5: aload_1
       6: invokevirtual #21                 // Method software/amazon/awssdk/services/lexmodelsv2/model/ImportResourceSpecification$BuilderImpl.build:()Lsoftware/amazon/awssdk/services/lexmodelsv2/model/ImportResourceSpecification;
       9: goto          13
      12: aconst_null
      13: putfield      #6                  // Field resourceSpecification:Lsoftware/amazon/awssdk/services/lexmodelsv2/model/ImportResourceSpecification;
      16: return

  public final software.amazon.awssdk.services.lexmodelsv2.model.StartImportResponse$Builder resourceSpecification(software.amazon.awssdk.services.lexmodelsv2.model.ImportResourceSpecification);
    Code:
       0: aload_0
       1: aload_1
       2: putfield      #6                  // Field resourceSpecification:Lsoftware/amazon/awssdk/services/lexmodelsv2/model/ImportResourceSpecification;
       5: aload_0
       6: areturn

  public final java.lang.String getMergeStrategy();
    Code:
       0: aload_0
       1: getfield      #5                  // Field mergeStrategy:Ljava/lang/String;
       4: areturn

  public final void setMergeStrategy(java.lang.String);
    Code:
       0: aload_0
       1: aload_1
       2: putfield      #5                  // Field mergeStrategy:Ljava/lang/String;
       5: return

  public final software.amazon.awssdk.services.lexmodelsv2.model.StartImportResponse$Builder mergeStrategy(java.lang.String);
    Code:
       0: aload_0
       1: aload_1
       2: putfield      #5                  // Field mergeStrategy:Ljava/lang/String;
       5: aload_0
       6: areturn

  public final software.amazon.awssdk.services.lexmodelsv2.model.StartImportResponse$Builder mergeStrategy(software.amazon.awssdk.services.lexmodelsv2.model.MergeStrategy);
    Code:
       0: aload_0
       1: aload_1
       2: ifnonnull     9
       5: aconst_null
       6: goto          13
       9: aload_1
      10: invokevirtual #22                 // Method software/amazon/awssdk/services/lexmodelsv2/model/MergeStrategy.toString:()Ljava/lang/String;
      13: invokevirtual #15                 // Method mergeStrategy:(Ljava/lang/String;)Lsoftware/amazon/awssdk/services/lexmodelsv2/model/StartImportResponse$Builder;
      16: pop
      17: aload_0
      18: areturn

  public final java.lang.String getImportStatus();
    Code:
       0: aload_0
       1: getfield      #4                  // Field importStatus:Ljava/lang/String;
       4: areturn

  public final void setImportStatus(java.lang.String);
    Code:
       0: aload_0
       1: aload_1
       2: putfield      #4                  // Field importStatus:Ljava/lang/String;
       5: return

  public final software.amazon.awssdk.services.lexmodelsv2.model.StartImportResponse$Builder importStatus(java.lang.String);
    Code:
       0: aload_0
       1: aload_1
       2: putfield      #4                  // Field importStatus:Ljava/lang/String;
       5: aload_0
       6: areturn

  public final software.amazon.awssdk.services.lexmodelsv2.model.StartImportResponse$Builder importStatus(software.amazon.awssdk.services.lexmodelsv2.model.ImportStatus);
    Code:
       0: aload_0
       1: aload_1
       2: ifnonnull     9
       5: aconst_null
       6: goto          13
       9: aload_1
      10: invokevirtual #23                 // Method software/amazon/awssdk/services/lexmodelsv2/model/ImportStatus.toString:()Ljava/lang/String;
      13: invokevirtual #17                 // Method importStatus:(Ljava/lang/String;)Lsoftware/amazon/awssdk/services/lexmodelsv2/model/StartImportResponse$Builder;
      16: pop
      17: aload_0
      18: areturn

  public final java.time.Instant getCreationDateTime();
    Code:
       0: aload_0
       1: getfield      #3                  // Field creationDateTime:Ljava/time/Instant;
       4: areturn

  public final void setCreationDateTime(java.time.Instant);
    Code:
       0: aload_0
       1: aload_1
       2: putfield      #3                  // Field creationDateTime:Ljava/time/Instant;
       5: return

  public final software.amazon.awssdk.services.lexmodelsv2.model.StartImportResponse$Builder creationDateTime(java.time.Instant);
    Code:
       0: aload_0
       1: aload_1
       2: putfield      #3                  // Field creationDateTime:Ljava/time/Instant;
       5: aload_0
       6: areturn

  public software.amazon.awssdk.services.lexmodelsv2.model.StartImportResponse build();
    Code:
       0: new           #24                 // class software/amazon/awssdk/services/lexmodelsv2/model/StartImportResponse
       3: dup
       4: aload_0
       5: aconst_null
       6: invokespecial #25                 // Method software/amazon/awssdk/services/lexmodelsv2/model/StartImportResponse."<init>":(Lsoftware/amazon/awssdk/services/lexmodelsv2/model/StartImportResponse$BuilderImpl;Lsoftware/amazon/awssdk/services/lexmodelsv2/model/StartImportResponse$1;)V
       9: areturn

  public java.util.List<software.amazon.awssdk.core.SdkField<?>> sdkFields();
    Code:
       0: invokestatic  #26                 // Method software/amazon/awssdk/services/lexmodelsv2/model/StartImportResponse.access$1300:()Ljava/util/List;
       3: areturn

  public software.amazon.awssdk.services.lexmodelsv2.model.LexModelsV2Response build();
    Code:
       0: aload_0
       1: invokevirtual #27                 // Method build:()Lsoftware/amazon/awssdk/services/lexmodelsv2/model/StartImportResponse;
       4: areturn

  public software.amazon.awssdk.awscore.AwsResponse build();
    Code:
       0: aload_0
       1: invokevirtual #27                 // Method build:()Lsoftware/amazon/awssdk/services/lexmodelsv2/model/StartImportResponse;
       4: areturn

  public software.amazon.awssdk.core.SdkResponse build();
    Code:
       0: aload_0
       1: invokevirtual #27                 // Method build:()Lsoftware/amazon/awssdk/services/lexmodelsv2/model/StartImportResponse;
       4: areturn

  public java.lang.Object build();
    Code:
       0: aload_0
       1: invokevirtual #27                 // Method build:()Lsoftware/amazon/awssdk/services/lexmodelsv2/model/StartImportResponse;
       4: areturn

  static java.lang.String access$000(software.amazon.awssdk.services.lexmodelsv2.model.StartImportResponse$BuilderImpl);
    Code:
       0: aload_0
       1: getfield      #7                  // Field importId:Ljava/lang/String;
       4: areturn

  static software.amazon.awssdk.services.lexmodelsv2.model.ImportResourceSpecification access$100(software.amazon.awssdk.services.lexmodelsv2.model.StartImportResponse$BuilderImpl);
    Code:
       0: aload_0
       1: getfield      #6                  // Field resourceSpecification:Lsoftware/amazon/awssdk/services/lexmodelsv2/model/ImportResourceSpecification;
       4: areturn

  static java.lang.String access$200(software.amazon.awssdk.services.lexmodelsv2.model.StartImportResponse$BuilderImpl);
    Code:
       0: aload_0
       1: getfield      #5                  // Field mergeStrategy:Ljava/lang/String;
       4: areturn

  static java.lang.String access$300(software.amazon.awssdk.services.lexmodelsv2.model.StartImportResponse$BuilderImpl);
    Code:
       0: aload_0
       1: getfield      #4                  // Field importStatus:Ljava/lang/String;
       4: areturn

  static java.time.Instant access$400(software.amazon.awssdk.services.lexmodelsv2.model.StartImportResponse$BuilderImpl);
    Code:
       0: aload_0
       1: getfield      #3                  // Field creationDateTime:Ljava/time/Instant;
       4: areturn

  software.amazon.awssdk.services.lexmodelsv2.model.StartImportResponse$BuilderImpl(software.amazon.awssdk.services.lexmodelsv2.model.StartImportResponse, software.amazon.awssdk.services.lexmodelsv2.model.StartImportResponse$1);
    Code:
       0: aload_0
       1: aload_1
       2: invokespecial #2                  // Method "<init>":(Lsoftware/amazon/awssdk/services/lexmodelsv2/model/StartImportResponse;)V
       5: return

  software.amazon.awssdk.services.lexmodelsv2.model.StartImportResponse$BuilderImpl(software.amazon.awssdk.services.lexmodelsv2.model.StartImportResponse$1);
    Code:
       0: aload_0
       1: invokespecial #1                  // Method "<init>":()V
       4: return
}
