Compiled from "Filter.java"
final class com.jayway.jsonpath.Filter$SingleFilter extends com.jayway.jsonpath.Filter {
  private final com.jayway.jsonpath.Predicate predicate;

  private com.jayway.jsonpath.Filter$SingleFilter(com.jayway.jsonpath.Predicate);
    Code:
       0: aload_0
       1: invokespecial #2                  // Method com/jayway/jsonpath/Filter."<init>":()V
       4: aload_0
       5: aload_1
       6: putfield      #3                  // Field predicate:Lcom/jayway/jsonpath/Predicate;
       9: return

  public boolean apply(com.jayway.jsonpath.Predicate$PredicateContext);
    Code:
       0: aload_0
       1: getfield      #3                  // Field predicate:Lcom/jayway/jsonpath/Predicate;
       4: aload_1
       5: invokeinterface #4,  2            // InterfaceMethod com/jayway/jsonpath/Predicate.apply:(Lcom/jayway/jsonpath/Predicate$PredicateContext;)Z
      10: ireturn

  public java.lang.String toString();
    Code:
       0: aload_0
       1: getfield      #3                  // Field predicate:Lcom/jayway/jsonpath/Predicate;
       4: invokevirtual #5                  // Method java/lang/Object.toString:()Ljava/lang/String;
       7: astore_1
       8: aload_1
       9: ldc           #6                  // String (
      11: invokevirtual #7                  // Method java/lang/String.startsWith:(Ljava/lang/String;)Z
      14: ifeq          42
      17: new           #8                  // class java/lang/StringBuilder
      20: dup
      21: invokespecial #9                  // Method java/lang/StringBuilder."<init>":()V
      24: ldc           #10                 // String [?
      26: invokevirtual #11                 // Method java/lang/StringBuilder.append:(Ljava/lang/String;)Ljava/lang/StringBuilder;
      29: aload_1
      30: invokevirtual #11                 // Method java/lang/StringBuilder.append:(Ljava/lang/String;)Ljava/lang/StringBuilder;
      33: ldc           #12                 // String ]
      35: invokevirtual #11                 // Method java/lang/StringBuilder.append:(Ljava/lang/String;)Ljava/lang/StringBuilder;
      38: invokevirtual #13                 // Method java/lang/StringBuilder.toString:()Ljava/lang/String;
      41: areturn
      42: new           #8                  // class java/lang/StringBuilder
      45: dup
      46: invokespecial #9                  // Method java/lang/StringBuilder."<init>":()V
      49: ldc           #14                 // String [?(
      51: invokevirtual #11                 // Method java/lang/StringBuilder.append:(Ljava/lang/String;)Ljava/lang/StringBuilder;
      54: aload_1
      55: invokevirtual #11                 // Method java/lang/StringBuilder.append:(Ljava/lang/String;)Ljava/lang/StringBuilder;
      58: ldc           #15                 // String )]
      60: invokevirtual #11                 // Method java/lang/StringBuilder.append:(Ljava/lang/String;)Ljava/lang/StringBuilder;
      63: invokevirtual #13                 // Method java/lang/StringBuilder.toString:()Ljava/lang/String;
      66: areturn

  com.jayway.jsonpath.Filter$SingleFilter(com.jayway.jsonpath.Predicate, com.jayway.jsonpath.Filter$1);
    Code:
       0: aload_0
       1: aload_1
       2: invokespecial #1                  // Method "<init>":(Lcom/jayway/jsonpath/Predicate;)V
       5: return
}
