Compiled from "ListenableFutureTask.java"
public class org.springframework.util.concurrent.ListenableFutureTask<T> extends java.util.concurrent.FutureTask<T> implements org.springframework.util.concurrent.ListenableFuture<T> {
  private final org.springframework.util.concurrent.ListenableFutureCallbackRegistry<T> callbacks;

  public org.springframework.util.concurrent.ListenableFutureTask(java.util.concurrent.Callable<T>);
    Code:
       0: aload_0
       1: aload_1
       2: invokespecial #1                  // Method java/util/concurrent/FutureTask."<init>":(Ljava/util/concurrent/Callable;)V
       5: aload_0
       6: new           #2                  // class org/springframework/util/concurrent/ListenableFutureCallbackRegistry
       9: dup
      10: invokespecial #3                  // Method org/springframework/util/concurrent/ListenableFutureCallbackRegistry."<init>":()V
      13: putfield      #4                  // Field callbacks:Lorg/springframework/util/concurrent/ListenableFutureCallbackRegistry;
      16: return

  public org.springframework.util.concurrent.ListenableFutureTask(java.lang.Runnable, T);
    Code:
       0: aload_0
       1: aload_1
       2: aload_2
       3: invokespecial #5                  // Method java/util/concurrent/FutureTask."<init>":(Ljava/lang/Runnable;Ljava/lang/Object;)V
       6: aload_0
       7: new           #2                  // class org/springframework/util/concurrent/ListenableFutureCallbackRegistry
      10: dup
      11: invokespecial #3                  // Method org/springframework/util/concurrent/ListenableFutureCallbackRegistry."<init>":()V
      14: putfield      #4                  // Field callbacks:Lorg/springframework/util/concurrent/ListenableFutureCallbackRegistry;
      17: return

  public void addCallback(org.springframework.util.concurrent.ListenableFutureCallback<? super T>);
    Code:
       0: aload_0
       1: getfield      #4                  // Field callbacks:Lorg/springframework/util/concurrent/ListenableFutureCallbackRegistry;
       4: aload_1
       5: invokevirtual #6                  // Method org/springframework/util/concurrent/ListenableFutureCallbackRegistry.addCallback:(Lorg/springframework/util/concurrent/ListenableFutureCallback;)V
       8: return

  public void addCallback(org.springframework.util.concurrent.SuccessCallback<? super T>, org.springframework.util.concurrent.FailureCallback);
    Code:
       0: aload_0
       1: getfield      #4                  // Field callbacks:Lorg/springframework/util/concurrent/ListenableFutureCallbackRegistry;
       4: aload_1
       5: invokevirtual #7                  // Method org/springframework/util/concurrent/ListenableFutureCallbackRegistry.addSuccessCallback:(Lorg/springframework/util/concurrent/SuccessCallback;)V
       8: aload_0
       9: getfield      #4                  // Field callbacks:Lorg/springframework/util/concurrent/ListenableFutureCallbackRegistry;
      12: aload_2
      13: invokevirtual #8                  // Method org/springframework/util/concurrent/ListenableFutureCallbackRegistry.addFailureCallback:(Lorg/springframework/util/concurrent/FailureCallback;)V
      16: return

  public java.util.concurrent.CompletableFuture<T> completable();
    Code:
       0: new           #9                  // class org/springframework/util/concurrent/DelegatingCompletableFuture
       3: dup
       4: aload_0
       5: invokespecial #10                 // Method org/springframework/util/concurrent/DelegatingCompletableFuture."<init>":(Ljava/util/concurrent/Future;)V
       8: astore_1
       9: aload_0
      10: getfield      #4                  // Field callbacks:Lorg/springframework/util/concurrent/ListenableFutureCallbackRegistry;
      13: aload_1
      14: dup
      15: invokevirtual #11                 // Method java/lang/Object.getClass:()Ljava/lang/Class;
      18: pop
      19: invokedynamic #12,  0             // InvokeDynamic #0:onSuccess:(Ljava/util/concurrent/CompletableFuture;)Lorg/springframework/util/concurrent/SuccessCallback;
      24: invokevirtual #7                  // Method org/springframework/util/concurrent/ListenableFutureCallbackRegistry.addSuccessCallback:(Lorg/springframework/util/concurrent/SuccessCallback;)V
      27: aload_0
      28: getfield      #4                  // Field callbacks:Lorg/springframework/util/concurrent/ListenableFutureCallbackRegistry;
      31: aload_1
      32: dup
      33: invokevirtual #11                 // Method java/lang/Object.getClass:()Ljava/lang/Class;
      36: pop
      37: invokedynamic #13,  0             // InvokeDynamic #1:onFailure:(Ljava/util/concurrent/CompletableFuture;)Lorg/springframework/util/concurrent/FailureCallback;
      42: invokevirtual #8                  // Method org/springframework/util/concurrent/ListenableFutureCallbackRegistry.addFailureCallback:(Lorg/springframework/util/concurrent/FailureCallback;)V
      45: aload_1
      46: areturn

  protected void done();
    Code:
       0: aload_0
       1: invokevirtual #14                 // Method get:()Ljava/lang/Object;
       4: astore_2
       5: aload_0
       6: getfield      #4                  // Field callbacks:Lorg/springframework/util/concurrent/ListenableFutureCallbackRegistry;
       9: aload_2
      10: invokevirtual #15                 // Method org/springframework/util/concurrent/ListenableFutureCallbackRegistry.success:(Ljava/lang/Object;)V
      13: return
      14: astore_2
      15: invokestatic  #17                 // Method java/lang/Thread.currentThread:()Ljava/lang/Thread;
      18: invokevirtual #18                 // Method java/lang/Thread.interrupt:()V
      21: return
      22: astore_2
      23: aload_2
      24: invokevirtual #20                 // Method java/util/concurrent/ExecutionException.getCause:()Ljava/lang/Throwable;
      27: astore_1
      28: aload_1
      29: ifnonnull     34
      32: aload_2
      33: astore_1
      34: goto          40
      37: astore_2
      38: aload_2
      39: astore_1
      40: aload_0
      41: getfield      #4                  // Field callbacks:Lorg/springframework/util/concurrent/ListenableFutureCallbackRegistry;
      44: aload_1
      45: invokevirtual #22                 // Method org/springframework/util/concurrent/ListenableFutureCallbackRegistry.failure:(Ljava/lang/Throwable;)V
      48: return
    Exception table:
       from    to  target type
           0    13    14   Class java/lang/InterruptedException
           0    13    22   Class java/util/concurrent/ExecutionException
           0    13    37   Class java/lang/Throwable
}
