Compiled from "DefinitionDocumentGenerator.java"
public class org.ow2.mind.doc.DefinitionDocumentGenerator {
  public org.objectweb.fractal.adl.Loader adlLoader;

  public org.ow2.mind.idl.IDLLoader idlLoader;

  public org.ow2.mind.adl.DefinitionCompiler adlCompiler;

  public org.ow2.mind.idl.IDLVisitor idlCompiler;

  public java.util.Map<java.lang.Object, java.lang.Object> context;

  public org.ow2.mind.doc.DefinitionDocumentGenerator(java.io.File[], java.io.File, java.io.File) throws java.io.IOException;
    Code:
       0: aload_0
       1: invokespecial #1                  // Method java/lang/Object."<init>":()V
       4: new           #2                  // class org/ow2/mind/BasicInputResourceLocator
       7: dup
       8: invokespecial #3                  // Method org/ow2/mind/BasicInputResourceLocator."<init>":()V
      11: astore        4
      13: invokestatic  #4                  // Method org/ow2/mind/doc/idl/IDLLoaderChainFactory.newLocator:()Lorg/ow2/mind/idl/IDLLocator;
      16: astore        5
      18: invokestatic  #5                  // Method org/ow2/mind/doc/adl/DocumentationFrontendFactory.newLocator:()Lorg/ow2/mind/adl/ADLLocator;
      21: astore        6
      23: new           #6                  // class org/ow2/mind/st/StringTemplateComponentLoader
      26: dup
      27: invokespecial #7                  // Method org/ow2/mind/st/StringTemplateComponentLoader."<init>":()V
      30: astore        7
      32: new           #8                  // class org/ow2/mind/st/templates/parser/StringTemplateLoader
      35: dup
      36: invokespecial #9                  // Method org/ow2/mind/st/templates/parser/StringTemplateLoader."<init>":()V
      39: astore        8
      41: new           #10                 // class org/objectweb/fractal/adl/xml/XMLNodeFactoryImpl
      44: dup
      45: invokespecial #11                 // Method org/objectweb/fractal/adl/xml/XMLNodeFactoryImpl."<init>":()V
      48: astore        9
      50: aload         8
      52: aload         9
      54: putfield      #12                 // Field org/ow2/mind/st/templates/parser/StringTemplateLoader.nodeFactoryItf:Lorg/objectweb/fractal/adl/xml/XMLNodeFactory;
      57: aload         7
      59: aload         8
      61: putfield      #13                 // Field org/ow2/mind/st/StringTemplateComponentLoader.loaderItf:Lorg/objectweb/fractal/adl/Loader;
      64: new           #14                 // class org/ow2/mind/plugin/SimpleClassPluginFactory
      67: dup
      68: invokespecial #15                 // Method org/ow2/mind/plugin/SimpleClassPluginFactory."<init>":()V
      71: astore        10
      73: aload_0
      74: aload         5
      76: invokestatic  #16                 // Method org/ow2/mind/doc/idl/IDLLoaderChainFactory.newLoader:(Lorg/ow2/mind/idl/IDLLocator;)Lorg/ow2/mind/idl/IDLLoader;
      79: putfield      #17                 // Field idlLoader:Lorg/ow2/mind/idl/IDLLoader;
      82: aload_0
      83: aload         4
      85: aload         6
      87: aload         5
      89: aload_0
      90: getfield      #17                 // Field idlLoader:Lorg/ow2/mind/idl/IDLLoader;
      93: aload         10
      95: invokestatic  #18                 // Method org/ow2/mind/doc/adl/DocumentationFrontendFactory.newLoader:(Lorg/ow2/mind/BasicInputResourceLocator;Lorg/ow2/mind/adl/ADLLocator;Lorg/ow2/mind/idl/IDLLocator;Lorg/ow2/mind/idl/IDLLoader;Lorg/objectweb/fractal/adl/Factory;)Lorg/objectweb/fractal/adl/Loader;
      98: putfield      #19                 // Field adlLoader:Lorg/objectweb/fractal/adl/Loader;
     101: aload_0
     102: invokestatic  #20                 // Method org/ow2/mind/doc/adl/DocumentationBackendFactory.newDefinitionCompiler:()Lorg/ow2/mind/adl/DefinitionCompiler;
     105: putfield      #21                 // Field adlCompiler:Lorg/ow2/mind/adl/DefinitionCompiler;
     108: aload_0
     109: invokestatic  #22                 // Method org/ow2/mind/doc/idl/IDLBackendFactory.newIDLCompiler:()Lorg/ow2/mind/idl/IDLVisitor;
     112: putfield      #23                 // Field idlCompiler:Lorg/ow2/mind/idl/IDLVisitor;
     115: aload_0
     116: new           #24                 // class java/util/HashMap
     119: dup
     120: invokespecial #25                 // Method java/util/HashMap."<init>":()V
     123: putfield      #26                 // Field context:Ljava/util/Map;
     126: aload_0
     127: getfield      #26                 // Field context:Ljava/util/Map;
     130: ldc           #27                 // String outputdir
     132: aload_3
     133: invokeinterface #28,  3           // InterfaceMethod java/util/Map.put:(Ljava/lang/Object;Ljava/lang/Object;)Ljava/lang/Object;
     138: pop
     139: aload_1
     140: arraylength
     141: anewarray     #29                 // class java/net/URL
     144: astore        11
     146: iconst_0
     147: istore        12
     149: iload         12
     151: aload_1
     152: arraylength
     153: if_icmpge     181
     156: aload_1
     157: iload         12
     159: aaload
     160: astore        13
     162: aload         11
     164: iload         12
     166: aload         13
     168: invokevirtual #30                 // Method java/io/File.toURI:()Ljava/net/URI;
     171: invokevirtual #31                 // Method java/net/URI.toURL:()Ljava/net/URL;
     174: aastore
     175: iinc          12, 1
     178: goto          149
     181: ldc           #32                 // String org.ow2.mind.adl.annotation.predefined
     183: aload_0
     184: getfield      #26                 // Field context:Ljava/util/Map;
     187: invokestatic  #33                 // Method org/ow2/mind/annotation/AnnotationLocatorHelper.addDefaultAnnotationPackage:(Ljava/lang/String;Ljava/util/Map;)V
     190: new           #34                 // class java/net/URLClassLoader
     193: dup
     194: aload         11
     196: aload_0
     197: invokevirtual #35                 // Method java/lang/Object.getClass:()Ljava/lang/Class;
     200: invokevirtual #36                 // Method java/lang/Class.getClassLoader:()Ljava/lang/ClassLoader;
     203: invokespecial #37                 // Method java/net/URLClassLoader."<init>":([Ljava/net/URL;Ljava/lang/ClassLoader;)V
     206: astore        12
     208: aload_0
     209: getfield      #26                 // Field context:Ljava/util/Map;
     212: ldc           #38                 // String classloader
     214: aload         12
     216: invokeinterface #28,  3           // InterfaceMethod java/util/Map.put:(Ljava/lang/Object;Ljava/lang/Object;)Ljava/lang/Object;
     221: pop
     222: aload_0
     223: getfield      #26                 // Field context:Ljava/util/Map;
     226: ldc           #39                 // String sourceDirectory
     228: aload_2
     229: invokeinterface #28,  3           // InterfaceMethod java/util/Map.put:(Ljava/lang/Object;Ljava/lang/Object;)Ljava/lang/Object;
     234: pop
     235: return

  public org.objectweb.fractal.adl.Definition loadADL(java.lang.String) throws org.objectweb.fractal.adl.ADLException;
    Code:
       0: aload_0
       1: getfield      #19                 // Field adlLoader:Lorg/objectweb/fractal/adl/Loader;
       4: aload_1
       5: aload_0
       6: getfield      #26                 // Field context:Ljava/util/Map;
       9: invokeinterface #40,  3           // InterfaceMethod org/objectweb/fractal/adl/Loader.load:(Ljava/lang/String;Ljava/util/Map;)Lorg/objectweb/fractal/adl/Definition;
      14: areturn

  public void generateADLDocumentation(java.lang.String) throws org.objectweb.fractal.adl.ADLException, java.lang.InterruptedException;
    Code:
       0: aload_0
       1: aload_1
       2: invokevirtual #41                 // Method loadADL:(Ljava/lang/String;)Lorg/objectweb/fractal/adl/Definition;
       5: astore_2
       6: aload_0
       7: getfield      #21                 // Field adlCompiler:Lorg/ow2/mind/adl/DefinitionCompiler;
      10: aload_2
      11: aload_0
      12: getfield      #26                 // Field context:Ljava/util/Map;
      15: invokeinterface #42,  3           // InterfaceMethod org/ow2/mind/adl/DefinitionCompiler.visit:(Ljava/lang/Object;Ljava/util/Map;)Ljava/lang/Object;
      20: pop
      21: return

  public org.ow2.mind.idl.ast.IDL loadIDL(java.lang.String) throws org.objectweb.fractal.adl.ADLException;
    Code:
       0: aload_0
       1: getfield      #17                 // Field idlLoader:Lorg/ow2/mind/idl/IDLLoader;
       4: aload_1
       5: aload_0
       6: getfield      #26                 // Field context:Ljava/util/Map;
       9: invokeinterface #43,  3           // InterfaceMethod org/ow2/mind/idl/IDLLoader.load:(Ljava/lang/String;Ljava/util/Map;)Lorg/ow2/mind/idl/ast/IDL;
      14: areturn

  public void generateIDLDocumentation(java.lang.String) throws org.objectweb.fractal.adl.ADLException, java.lang.InterruptedException;
    Code:
       0: aload_0
       1: aload_1
       2: invokevirtual #44                 // Method loadIDL:(Ljava/lang/String;)Lorg/ow2/mind/idl/ast/IDL;
       5: astore_2
       6: aload_0
       7: getfield      #23                 // Field idlCompiler:Lorg/ow2/mind/idl/IDLVisitor;
      10: aload_2
      11: aload_0
      12: getfield      #26                 // Field context:Ljava/util/Map;
      15: invokeinterface #45,  3           // InterfaceMethod org/ow2/mind/idl/IDLVisitor.visit:(Ljava/lang/Object;Ljava/util/Map;)V
      20: return
}
