Compiled from "DocumentationIndexGenerator.java"
public class org.ow2.mind.doc.DocumentationIndexGenerator$IndexEntry {
  public java.lang.String name;

  public java.lang.String frameHtmlFileName;

  public java.lang.String summaryHtmlFileName;

  public org.ow2.mind.doc.DocumentationIndexGenerator$EntryKind kind;

  public java.io.File file;

  public java.util.List<org.ow2.mind.doc.DocumentationIndexGenerator$IndexEntry> adl;

  public java.util.List<org.ow2.mind.doc.DocumentationIndexGenerator$IndexEntry> itf;

  private org.ow2.mind.doc.DocumentationIndexGenerator$IndexEntry(org.ow2.mind.doc.DocumentationIndexGenerator$EntryKind, java.lang.String, java.lang.String, java.lang.String, java.io.File);
    Code:
       0: aload_0
       1: aload_1
       2: aload_2
       3: aload_3
       4: aload         4
       6: aload         5
       8: aconst_null
       9: aconst_null
      10: invokespecial #1                  // Method "<init>":(Lorg/ow2/mind/doc/DocumentationIndexGenerator$EntryKind;Ljava/lang/String;Ljava/lang/String;Ljava/lang/String;Ljava/io/File;Ljava/util/List;Ljava/util/List;)V
      13: return

  private org.ow2.mind.doc.DocumentationIndexGenerator$IndexEntry(org.ow2.mind.doc.DocumentationIndexGenerator$EntryKind, java.lang.String, java.lang.String, java.lang.String, java.io.File, java.util.List<org.ow2.mind.doc.DocumentationIndexGenerator$IndexEntry>, java.util.List<org.ow2.mind.doc.DocumentationIndexGenerator$IndexEntry>);
    Code:
       0: aload_0
       1: invokespecial #2                  // Method java/lang/Object."<init>":()V
       4: aload_0
       5: aload_2
       6: putfield      #3                  // Field name:Ljava/lang/String;
       9: aload_0
      10: aload_3
      11: putfield      #4                  // Field frameHtmlFileName:Ljava/lang/String;
      14: aload_0
      15: aload         4
      17: putfield      #5                  // Field summaryHtmlFileName:Ljava/lang/String;
      20: aload_0
      21: aload         5
      23: putfield      #6                  // Field file:Ljava/io/File;
      26: aload_0
      27: aload         6
      29: putfield      #7                  // Field adl:Ljava/util/List;
      32: aload_0
      33: aload         7
      35: putfield      #8                  // Field itf:Ljava/util/List;
      38: aload_0
      39: aload_1
      40: putfield      #9                  // Field kind:Lorg/ow2/mind/doc/DocumentationIndexGenerator$EntryKind;
      43: return

  public static org.ow2.mind.doc.DocumentationIndexGenerator$IndexEntry createADLEntry(java.io.File, java.io.File) throws java.io.IOException;
    Code:
       0: aload_0
       1: invokevirtual #10                 // Method java/io/File.getCanonicalPath:()Ljava/lang/String;
       4: aload_1
       5: invokevirtual #10                 // Method java/io/File.getCanonicalPath:()Ljava/lang/String;
       8: invokestatic  #11                 // Method org/ow2/mind/doc/HTMLDocumentationHelper.getDefinitionName:(Ljava/lang/String;Ljava/lang/String;)Ljava/lang/String;
      11: astore_2
      12: aload_2
      13: invokestatic  #12                 // Method org/ow2/mind/doc/HTMLDocumentationHelper.getPathToADL:(Ljava/lang/String;)Ljava/lang/String;
      16: astore_3
      17: aload_3
      18: getstatic     #13                 // Field java/io/File.separator:Ljava/lang/String;
      21: invokevirtual #14                 // Method java/lang/String.startsWith:(Ljava/lang/String;)Z
      24: ifeq          33
      27: aload_3
      28: iconst_1
      29: invokevirtual #15                 // Method java/lang/String.substring:(I)Ljava/lang/String;
      32: astore_3
      33: new           #16                 // class org/ow2/mind/doc/DocumentationIndexGenerator$IndexEntry
      36: dup
      37: getstatic     #17                 // Field org/ow2/mind/doc/DocumentationIndexGenerator$EntryKind.ADL:Lorg/ow2/mind/doc/DocumentationIndexGenerator$EntryKind;
      40: aload_2
      41: aconst_null
      42: aload_3
      43: aload_1
      44: invokespecial #18                 // Method "<init>":(Lorg/ow2/mind/doc/DocumentationIndexGenerator$EntryKind;Ljava/lang/String;Ljava/lang/String;Ljava/lang/String;Ljava/io/File;)V
      47: areturn

  public static org.ow2.mind.doc.DocumentationIndexGenerator$IndexEntry createITFEntry(java.io.File, java.io.File) throws java.io.IOException;
    Code:
       0: aload_0
       1: invokevirtual #10                 // Method java/io/File.getCanonicalPath:()Ljava/lang/String;
       4: aload_1
       5: invokevirtual #10                 // Method java/io/File.getCanonicalPath:()Ljava/lang/String;
       8: invokestatic  #11                 // Method org/ow2/mind/doc/HTMLDocumentationHelper.getDefinitionName:(Ljava/lang/String;Ljava/lang/String;)Ljava/lang/String;
      11: astore_2
      12: aload_2
      13: invokestatic  #19                 // Method org/ow2/mind/doc/HTMLDocumentationHelper.getPathToITF:(Ljava/lang/String;)Ljava/lang/String;
      16: astore_3
      17: aload_3
      18: getstatic     #13                 // Field java/io/File.separator:Ljava/lang/String;
      21: invokevirtual #14                 // Method java/lang/String.startsWith:(Ljava/lang/String;)Z
      24: ifeq          33
      27: aload_3
      28: iconst_1
      29: invokevirtual #15                 // Method java/lang/String.substring:(I)Ljava/lang/String;
      32: astore_3
      33: new           #16                 // class org/ow2/mind/doc/DocumentationIndexGenerator$IndexEntry
      36: dup
      37: getstatic     #20                 // Field org/ow2/mind/doc/DocumentationIndexGenerator$EntryKind.ITF:Lorg/ow2/mind/doc/DocumentationIndexGenerator$EntryKind;
      40: aload_2
      41: aconst_null
      42: aload_3
      43: aload_1
      44: invokespecial #18                 // Method "<init>":(Lorg/ow2/mind/doc/DocumentationIndexGenerator$EntryKind;Ljava/lang/String;Ljava/lang/String;Ljava/lang/String;Ljava/io/File;)V
      47: areturn

  public static org.ow2.mind.doc.DocumentationIndexGenerator$IndexEntry createPackageEntry(java.io.File, java.io.File, java.util.List<org.ow2.mind.doc.DocumentationIndexGenerator$IndexEntry>, java.util.List<org.ow2.mind.doc.DocumentationIndexGenerator$IndexEntry>) throws java.io.IOException;
    Code:
       0: aload_0
       1: invokevirtual #10                 // Method java/io/File.getCanonicalPath:()Ljava/lang/String;
       4: aload_1
       5: invokevirtual #10                 // Method java/io/File.getCanonicalPath:()Ljava/lang/String;
       8: invokestatic  #11                 // Method org/ow2/mind/doc/HTMLDocumentationHelper.getDefinitionName:(Ljava/lang/String;Ljava/lang/String;)Ljava/lang/String;
      11: astore        4
      13: new           #21                 // class java/lang/StringBuilder
      16: dup
      17: invokespecial #22                 // Method java/lang/StringBuilder."<init>":()V
      20: aload         4
      22: invokestatic  #23                 // Method org/ow2/mind/PathHelper.packageNameToDirName:(Ljava/lang/String;)Ljava/lang/String;
      25: invokevirtual #24                 // Method java/lang/StringBuilder.append:(Ljava/lang/String;)Ljava/lang/StringBuilder;
      28: getstatic     #25                 // Field java/io/File.separatorChar:C
      31: invokevirtual #26                 // Method java/lang/StringBuilder.append:(C)Ljava/lang/StringBuilder;
      34: ldc           #27                 // String package-frame.html
      36: invokevirtual #24                 // Method java/lang/StringBuilder.append:(Ljava/lang/String;)Ljava/lang/StringBuilder;
      39: invokevirtual #28                 // Method java/lang/StringBuilder.toString:()Ljava/lang/String;
      42: astore        5
      44: new           #21                 // class java/lang/StringBuilder
      47: dup
      48: invokespecial #22                 // Method java/lang/StringBuilder."<init>":()V
      51: aload         4
      53: invokestatic  #23                 // Method org/ow2/mind/PathHelper.packageNameToDirName:(Ljava/lang/String;)Ljava/lang/String;
      56: invokevirtual #24                 // Method java/lang/StringBuilder.append:(Ljava/lang/String;)Ljava/lang/StringBuilder;
      59: getstatic     #25                 // Field java/io/File.separatorChar:C
      62: invokevirtual #26                 // Method java/lang/StringBuilder.append:(C)Ljava/lang/StringBuilder;
      65: ldc           #29                 // String package-summary.html
      67: invokevirtual #24                 // Method java/lang/StringBuilder.append:(Ljava/lang/String;)Ljava/lang/StringBuilder;
      70: invokevirtual #28                 // Method java/lang/StringBuilder.toString:()Ljava/lang/String;
      73: astore        6
      75: aload         5
      77: getstatic     #13                 // Field java/io/File.separator:Ljava/lang/String;
      80: invokevirtual #14                 // Method java/lang/String.startsWith:(Ljava/lang/String;)Z
      83: ifeq          94
      86: aload         5
      88: iconst_1
      89: invokevirtual #15                 // Method java/lang/String.substring:(I)Ljava/lang/String;
      92: astore        5
      94: aload         6
      96: getstatic     #13                 // Field java/io/File.separator:Ljava/lang/String;
      99: invokevirtual #14                 // Method java/lang/String.startsWith:(Ljava/lang/String;)Z
     102: ifeq          113
     105: aload         6
     107: iconst_1
     108: invokevirtual #15                 // Method java/lang/String.substring:(I)Ljava/lang/String;
     111: astore        6
     113: new           #16                 // class org/ow2/mind/doc/DocumentationIndexGenerator$IndexEntry
     116: dup
     117: getstatic     #30                 // Field org/ow2/mind/doc/DocumentationIndexGenerator$EntryKind.PACKAGE:Lorg/ow2/mind/doc/DocumentationIndexGenerator$EntryKind;
     120: aload         4
     122: aload         5
     124: aload         6
     126: aload_1
     127: aload_2
     128: aload_3
     129: invokespecial #1                  // Method "<init>":(Lorg/ow2/mind/doc/DocumentationIndexGenerator$EntryKind;Ljava/lang/String;Ljava/lang/String;Ljava/lang/String;Ljava/io/File;Ljava/util/List;Ljava/util/List;)V
     132: areturn

  public java.lang.String toString();
    Code:
       0: ldc           #31                 // String [%s,%s]
       2: iconst_2
       3: anewarray     #32                 // class java/lang/Object
       6: dup
       7: iconst_0
       8: aload_0
       9: getfield      #3                  // Field name:Ljava/lang/String;
      12: aastore
      13: dup
      14: iconst_1
      15: aload_0
      16: getfield      #4                  // Field frameHtmlFileName:Ljava/lang/String;
      19: aastore
      20: invokestatic  #33                 // Method java/lang/String.format:(Ljava/lang/String;[Ljava/lang/Object;)Ljava/lang/String;
      23: areturn
}
