Compiled from "Digest.java"
public class org.jgroups.util.Digest implements org.jgroups.util.Streamable, java.lang.Iterable<org.jgroups.util.Digest$Entry> {
  protected org.jgroups.Address[] members;

  protected long[] seqnos;

  public org.jgroups.util.Digest();
    Code:
       0: aload_0
       1: invokespecial #1                  // Method java/lang/Object."<init>":()V
       4: return

  public org.jgroups.util.Digest(org.jgroups.Address[], long[]);
    Code:
       0: aload_0
       1: invokespecial #1                  // Method java/lang/Object."<init>":()V
       4: aload_1
       5: ifnonnull     18
       8: new           #2                  // class java/lang/IllegalArgumentException
      11: dup
      12: ldc           #3                  // String members is null
      14: invokespecial #4                  // Method java/lang/IllegalArgumentException."<init>":(Ljava/lang/String;)V
      17: athrow
      18: aload_2
      19: ifnonnull     32
      22: new           #2                  // class java/lang/IllegalArgumentException
      25: dup
      26: ldc           #5                  // String seqnos is null
      28: invokespecial #4                  // Method java/lang/IllegalArgumentException."<init>":(Ljava/lang/String;)V
      31: athrow
      32: aload_0
      33: aload_1
      34: putfield      #6                  // Field members:[Lorg/jgroups/Address;
      37: aload_0
      38: aload_2
      39: putfield      #7                  // Field seqnos:[J
      42: aload_0
      43: invokevirtual #8                  // Method checkPostcondition:()V
      46: return

  public org.jgroups.util.Digest(org.jgroups.Address[]);
    Code:
       0: aload_0
       1: invokespecial #1                  // Method java/lang/Object."<init>":()V
       4: aload_1
       5: ifnonnull     18
       8: new           #2                  // class java/lang/IllegalArgumentException
      11: dup
      12: ldc           #3                  // String members is null
      14: invokespecial #4                  // Method java/lang/IllegalArgumentException."<init>":(Ljava/lang/String;)V
      17: athrow
      18: aload_0
      19: aload_1
      20: putfield      #6                  // Field members:[Lorg/jgroups/Address;
      23: return

  public org.jgroups.util.Digest(org.jgroups.util.Digest);
    Code:
       0: aload_0
       1: invokespecial #1                  // Method java/lang/Object."<init>":()V
       4: aload_1
       5: ifnonnull     9
       8: return
       9: aload_0
      10: aload_1
      11: getfield      #6                  // Field members:[Lorg/jgroups/Address;
      14: putfield      #6                  // Field members:[Lorg/jgroups/Address;
      17: aload_0
      18: aload_1
      19: instanceof    #9                  // class org/jgroups/util/MutableDigest
      22: ifne          32
      25: aload_0
      26: instanceof    #9                  // class org/jgroups/util/MutableDigest
      29: ifeq          47
      32: aload_1
      33: getfield      #7                  // Field seqnos:[J
      36: aload_1
      37: getfield      #7                  // Field seqnos:[J
      40: arraylength
      41: invokestatic  #10                 // Method java/util/Arrays.copyOf:([JI)[J
      44: goto          51
      47: aload_1
      48: getfield      #7                  // Field seqnos:[J
      51: putfield      #7                  // Field seqnos:[J
      54: aload_0
      55: invokevirtual #8                  // Method checkPostcondition:()V
      58: return

  public org.jgroups.util.Digest(java.util.Map<org.jgroups.Address, long[]>);
    Code:
       0: aload_0
       1: invokespecial #1                  // Method java/lang/Object."<init>":()V
       4: aload_0
       5: aload_1
       6: invokevirtual #11                 // Method createArrays:(Ljava/util/Map;)V
       9: aload_0
      10: invokevirtual #8                  // Method checkPostcondition:()V
      13: return

  public org.jgroups.util.Digest(org.jgroups.Address, long, long);
    Code:
       0: aload_0
       1: invokespecial #1                  // Method java/lang/Object."<init>":()V
       4: aload_0
       5: iconst_1
       6: anewarray     #12                 // class org/jgroups/Address
       9: dup
      10: iconst_0
      11: aload_1
      12: aastore
      13: putfield      #6                  // Field members:[Lorg/jgroups/Address;
      16: aload_0
      17: iconst_2
      18: newarray       long
      20: dup
      21: iconst_0
      22: lload_2
      23: lastore
      24: dup
      25: iconst_1
      26: lload         4
      28: lastore
      29: putfield      #7                  // Field seqnos:[J
      32: return

  public org.jgroups.Address[] getMembersRaw();
    Code:
       0: aload_0
       1: getfield      #6                  // Field members:[Lorg/jgroups/Address;
       4: areturn

  public int capacity();
    Code:
       0: aload_0
       1: getfield      #6                  // Field members:[Lorg/jgroups/Address;
       4: ifnull        15
       7: aload_0
       8: getfield      #6                  // Field members:[Lorg/jgroups/Address;
      11: arraylength
      12: goto          16
      15: iconst_0
      16: ireturn

  public boolean contains(org.jgroups.Address);
    Code:
       0: aload_1
       1: ifnull        11
       4: aload_0
       5: getfield      #6                  // Field members:[Lorg/jgroups/Address;
       8: ifnonnull     13
      11: iconst_0
      12: ireturn
      13: aload_0
      14: getfield      #6                  // Field members:[Lorg/jgroups/Address;
      17: astore_2
      18: aload_2
      19: arraylength
      20: istore_3
      21: iconst_0
      22: istore        4
      24: iload         4
      26: iload_3
      27: if_icmpge     58
      30: aload_2
      31: iload         4
      33: aaload
      34: astore        5
      36: aload         5
      38: ifnull        52
      41: aload         5
      43: aload_1
      44: invokevirtual #13                 // Method java/lang/Object.equals:(Ljava/lang/Object;)Z
      47: ifeq          52
      50: iconst_1
      51: ireturn
      52: iinc          4, 1
      55: goto          24
      58: iconst_0
      59: ireturn

  public boolean containsAll(org.jgroups.Address...);
    Code:
       0: aload_1
       1: astore_2
       2: aload_2
       3: arraylength
       4: istore_3
       5: iconst_0
       6: istore        4
       8: iload         4
      10: iload_3
      11: if_icmpge     37
      14: aload_2
      15: iload         4
      17: aaload
      18: astore        5
      20: aload_0
      21: aload         5
      23: invokevirtual #14                 // Method contains:(Lorg/jgroups/Address;)Z
      26: ifne          31
      29: iconst_0
      30: ireturn
      31: iinc          4, 1
      34: goto          8
      37: iconst_1
      38: ireturn

  public boolean equals(java.lang.Object);
    Code:
       0: aload_0
       1: aload_1
       2: if_acmpne     7
       5: iconst_1
       6: ireturn
       7: aload_1
       8: checkcast     #15                 // class org/jgroups/util/Digest
      11: astore_2
      12: aload_0
      13: getfield      #6                  // Field members:[Lorg/jgroups/Address;
      16: aload_2
      17: getfield      #6                  // Field members:[Lorg/jgroups/Address;
      20: invokestatic  #16                 // Method java/util/Arrays.equals:([Ljava/lang/Object;[Ljava/lang/Object;)Z
      23: istore_3
      24: aload_0
      25: getfield      #7                  // Field seqnos:[J
      28: aload_2
      29: getfield      #7                  // Field seqnos:[J
      32: invokestatic  #17                 // Method java/util/Arrays.equals:([J[J)Z
      35: istore        4
      37: iload_3
      38: ifeq          50
      41: iload         4
      43: ifeq          50
      46: iconst_1
      47: goto          51
      50: iconst_0
      51: ireturn

  public long[] get(org.jgroups.Address);
    Code:
       0: aload_0
       1: aload_1
       2: invokevirtual #18                 // Method find:(Lorg/jgroups/Address;)I
       5: istore_2
       6: iload_2
       7: ifge          12
      10: aconst_null
      11: areturn
      12: iconst_2
      13: newarray       long
      15: dup
      16: iconst_0
      17: aload_0
      18: getfield      #7                  // Field seqnos:[J
      21: iload_2
      22: iconst_2
      23: imul
      24: laload
      25: lastore
      26: dup
      27: iconst_1
      28: aload_0
      29: getfield      #7                  // Field seqnos:[J
      32: iload_2
      33: iconst_2
      34: imul
      35: iconst_1
      36: iadd
      37: laload
      38: lastore
      39: areturn

  public java.util.Iterator<org.jgroups.util.Digest$Entry> iterator();
    Code:
       0: new           #19                 // class org/jgroups/util/Digest$MyIterator
       3: dup
       4: aload_0
       5: invokespecial #20                 // Method org/jgroups/util/Digest$MyIterator."<init>":(Lorg/jgroups/util/Digest;)V
       8: areturn

  public org.jgroups.util.Digest copy();
    Code:
       0: new           #15                 // class org/jgroups/util/Digest
       3: dup
       4: aload_0
       5: getfield      #6                  // Field members:[Lorg/jgroups/Address;
       8: aload_0
       9: getfield      #7                  // Field seqnos:[J
      12: aload_0
      13: getfield      #7                  // Field seqnos:[J
      16: arraylength
      17: invokestatic  #10                 // Method java/util/Arrays.copyOf:([JI)[J
      20: invokespecial #21                 // Method "<init>":([Lorg/jgroups/Address;[J)V
      23: areturn

  public void writeTo(java.io.DataOutput) throws java.lang.Exception;
    Code:
       0: aload_0
       1: aload_1
       2: iconst_1
       3: invokevirtual #22                 // Method writeTo:(Ljava/io/DataOutput;Z)V
       6: return

  public void writeTo(java.io.DataOutput, boolean) throws java.lang.Exception;
    Code:
       0: iload_2
       1: ifeq          15
       4: aload_0
       5: getfield      #6                  // Field members:[Lorg/jgroups/Address;
       8: aload_1
       9: invokestatic  #23                 // Method org/jgroups/util/Util.writeAddresses:([Lorg/jgroups/Address;Ljava/io/DataOutput;)V
      12: goto          26
      15: aload_1
      16: aload_0
      17: getfield      #6                  // Field members:[Lorg/jgroups/Address;
      20: arraylength
      21: invokeinterface #24,  2           // InterfaceMethod java/io/DataOutput.writeShort:(I)V
      26: iconst_0
      27: istore_3
      28: iload_3
      29: aload_0
      30: invokevirtual #25                 // Method capacity:()I
      33: if_icmpge     64
      36: aload_0
      37: getfield      #7                  // Field seqnos:[J
      40: iload_3
      41: iconst_2
      42: imul
      43: laload
      44: aload_0
      45: getfield      #7                  // Field seqnos:[J
      48: iload_3
      49: iconst_2
      50: imul
      51: iconst_1
      52: iadd
      53: laload
      54: aload_1
      55: invokestatic  #26                 // Method org/jgroups/util/Bits.writeLongSequence:(JJLjava/io/DataOutput;)V
      58: iinc          3, 1
      61: goto          28
      64: return

  public void readFrom(java.io.DataInput) throws java.lang.Exception;
    Code:
       0: aload_0
       1: aload_1
       2: iconst_1
       3: invokevirtual #27                 // Method readFrom:(Ljava/io/DataInput;Z)V
       6: return

  public void readFrom(java.io.DataInput, boolean) throws java.lang.Exception;
    Code:
       0: iload_2
       1: ifeq          27
       4: aload_0
       5: aload_1
       6: invokestatic  #28                 // Method org/jgroups/util/Util.readAddresses:(Ljava/io/DataInput;)[Lorg/jgroups/Address;
       9: putfield      #6                  // Field members:[Lorg/jgroups/Address;
      12: aload_0
      13: aload_0
      14: invokevirtual #25                 // Method capacity:()I
      17: iconst_2
      18: imul
      19: newarray       long
      21: putfield      #7                  // Field seqnos:[J
      24: goto          41
      27: aload_0
      28: aload_1
      29: invokeinterface #29,  1           // InterfaceMethod java/io/DataInput.readShort:()S
      34: iconst_2
      35: imul
      36: newarray       long
      38: putfield      #7                  // Field seqnos:[J
      41: iconst_0
      42: istore_3
      43: iload_3
      44: aload_0
      45: getfield      #7                  // Field seqnos:[J
      48: arraylength
      49: iconst_2
      50: idiv
      51: if_icmpge     92
      54: aload_1
      55: invokestatic  #30                 // Method org/jgroups/util/Bits.readLongSequence:(Ljava/io/DataInput;)[J
      58: astore        4
      60: aload_0
      61: getfield      #7                  // Field seqnos:[J
      64: iload_3
      65: iconst_2
      66: imul
      67: aload         4
      69: iconst_0
      70: laload
      71: lastore
      72: aload_0
      73: getfield      #7                  // Field seqnos:[J
      76: iload_3
      77: iconst_2
      78: imul
      79: iconst_1
      80: iadd
      81: aload         4
      83: iconst_1
      84: laload
      85: lastore
      86: iinc          3, 1
      89: goto          43
      92: return

  public long serializedSize(boolean);
    Code:
       0: iload_1
       1: ifeq          14
       4: aload_0
       5: getfield      #6                  // Field members:[Lorg/jgroups/Address;
       8: invokestatic  #31                 // Method org/jgroups/util/Util.size:([Lorg/jgroups/Address;)J
      11: goto          17
      14: ldc2_w        #32                 // long 2l
      17: lstore_2
      18: iconst_0
      19: istore        4
      21: iload         4
      23: aload_0
      24: getfield      #6                  // Field members:[Lorg/jgroups/Address;
      27: arraylength
      28: if_icmpge     64
      31: lload_2
      32: aload_0
      33: getfield      #7                  // Field seqnos:[J
      36: iload         4
      38: iconst_2
      39: imul
      40: laload
      41: aload_0
      42: getfield      #7                  // Field seqnos:[J
      45: iload         4
      47: iconst_2
      48: imul
      49: iconst_1
      50: iadd
      51: laload
      52: invokestatic  #34                 // Method org/jgroups/util/Bits.size:(JJ)B
      55: i2l
      56: ladd
      57: lstore_2
      58: iinc          4, 1
      61: goto          21
      64: lload_2
      65: lreturn

  public java.lang.String toString();
    Code:
       0: aload_0
       1: aload_0
       2: getfield      #6                  // Field members:[Lorg/jgroups/Address;
       5: iconst_1
       6: invokevirtual #35                 // Method toString:([Lorg/jgroups/Address;Z)Ljava/lang/String;
       9: areturn

  public java.lang.String toString(org.jgroups.util.Digest);
    Code:
       0: aload_1
       1: ifnull        16
       4: aload_0
       5: aload_1
       6: getfield      #6                  // Field members:[Lorg/jgroups/Address;
       9: iconst_1
      10: invokevirtual #35                 // Method toString:([Lorg/jgroups/Address;Z)Ljava/lang/String;
      13: goto          25
      16: aload_0
      17: aload_0
      18: getfield      #6                  // Field members:[Lorg/jgroups/Address;
      21: iconst_1
      22: invokevirtual #35                 // Method toString:([Lorg/jgroups/Address;Z)Ljava/lang/String;
      25: areturn

  public java.lang.String toString(org.jgroups.Address[], boolean);
    Code:
       0: new           #36                 // class java/lang/StringBuilder
       3: dup
       4: invokespecial #37                 // Method java/lang/StringBuilder."<init>":()V
       7: astore_3
       8: iconst_1
       9: istore        4
      11: aload_0
      12: invokevirtual #25                 // Method capacity:()I
      15: ifne          21
      18: ldc           #38                 // String []
      20: areturn
      21: iconst_0
      22: istore        5
      24: aload_0
      25: invokevirtual #25                 // Method capacity:()I
      28: istore        6
      30: aload_1
      31: astore        7
      33: aload         7
      35: arraylength
      36: istore        8
      38: iconst_0
      39: istore        9
      41: iload         9
      43: iload         8
      45: if_icmpge     197
      48: aload         7
      50: iload         9
      52: aaload
      53: astore        10
      55: aload         10
      57: ifnull        69
      60: aload_0
      61: aload         10
      63: invokevirtual #39                 // Method get:(Lorg/jgroups/Address;)[J
      66: goto          70
      69: aconst_null
      70: astore        11
      72: aload         10
      74: ifnull        191
      77: aload         11
      79: ifnonnull     85
      82: goto          191
      85: iload         4
      87: ifne          100
      90: aload_3
      91: ldc           #40                 // String ,
      93: invokevirtual #41                 // Method java/lang/StringBuilder.append:(Ljava/lang/String;)Ljava/lang/StringBuilder;
      96: pop
      97: goto          103
     100: iconst_0
     101: istore        4
     103: aload_3
     104: aload         10
     106: invokevirtual #42                 // Method java/lang/StringBuilder.append:(Ljava/lang/Object;)Ljava/lang/StringBuilder;
     109: ldc           #43                 // String :
     111: invokevirtual #41                 // Method java/lang/StringBuilder.append:(Ljava/lang/String;)Ljava/lang/StringBuilder;
     114: bipush        91
     116: invokevirtual #44                 // Method java/lang/StringBuilder.append:(C)Ljava/lang/StringBuilder;
     119: aload         11
     121: iconst_0
     122: laload
     123: invokevirtual #45                 // Method java/lang/StringBuilder.append:(J)Ljava/lang/StringBuilder;
     126: pop
     127: iload_2
     128: ifeq          150
     131: aload_3
     132: ldc           #46                 // String  (
     134: invokevirtual #41                 // Method java/lang/StringBuilder.append:(Ljava/lang/String;)Ljava/lang/StringBuilder;
     137: aload         11
     139: iconst_1
     140: laload
     141: invokevirtual #45                 // Method java/lang/StringBuilder.append:(J)Ljava/lang/StringBuilder;
     144: ldc           #47                 // String )
     146: invokevirtual #41                 // Method java/lang/StringBuilder.append:(Ljava/lang/String;)Ljava/lang/StringBuilder;
     149: pop
     150: aload_3
     151: ldc           #48                 // String ]
     153: invokevirtual #41                 // Method java/lang/StringBuilder.append:(Ljava/lang/String;)Ljava/lang/StringBuilder;
     156: pop
     157: getstatic     #49                 // Field org/jgroups/util/Util.MAX_LIST_PRINT_SIZE:I
     160: ifle          191
     163: iinc          5, 1
     166: iload         5
     168: getstatic     #49                 // Field org/jgroups/util/Util.MAX_LIST_PRINT_SIZE:I
     171: if_icmplt     191
     174: iload         6
     176: iload         5
     178: if_icmple     197
     181: aload_3
     182: ldc           #50                 // String , ...
     184: invokevirtual #41                 // Method java/lang/StringBuilder.append:(Ljava/lang/String;)Ljava/lang/StringBuilder;
     187: pop
     188: goto          197
     191: iinc          9, 1
     194: goto          41
     197: aload_3
     198: invokevirtual #51                 // Method java/lang/StringBuilder.toString:()Ljava/lang/String;
     201: areturn

  protected int find(org.jgroups.Address);
    Code:
       0: aload_1
       1: ifnull        11
       4: aload_0
       5: getfield      #6                  // Field members:[Lorg/jgroups/Address;
       8: ifnonnull     13
      11: iconst_m1
      12: ireturn
      13: iconst_0
      14: istore_2
      15: iload_2
      16: aload_0
      17: getfield      #6                  // Field members:[Lorg/jgroups/Address;
      20: arraylength
      21: if_icmpge     51
      24: aload_0
      25: getfield      #6                  // Field members:[Lorg/jgroups/Address;
      28: iload_2
      29: aaload
      30: astore_3
      31: aload_3
      32: ifnull        45
      35: aload_3
      36: aload_1
      37: invokevirtual #13                 // Method java/lang/Object.equals:(Ljava/lang/Object;)Z
      40: ifeq          45
      43: iload_2
      44: ireturn
      45: iinc          2, 1
      48: goto          15
      51: iconst_m1
      52: ireturn

  protected void createArrays(java.util.Map<org.jgroups.Address, long[]>);
    Code:
       0: aload_1
       1: invokeinterface #52,  1           // InterfaceMethod java/util/Map.size:()I
       6: istore_2
       7: aload_0
       8: iload_2
       9: anewarray     #12                 // class org/jgroups/Address
      12: putfield      #6                  // Field members:[Lorg/jgroups/Address;
      15: aload_0
      16: iload_2
      17: iconst_2
      18: imul
      19: newarray       long
      21: putfield      #7                  // Field seqnos:[J
      24: iconst_0
      25: istore_3
      26: aload_1
      27: invokeinterface #53,  1           // InterfaceMethod java/util/Map.entrySet:()Ljava/util/Set;
      32: invokeinterface #54,  1           // InterfaceMethod java/util/Set.iterator:()Ljava/util/Iterator;
      37: astore        4
      39: aload         4
      41: invokeinterface #55,  1           // InterfaceMethod java/util/Iterator.hasNext:()Z
      46: ifeq          125
      49: aload         4
      51: invokeinterface #56,  1           // InterfaceMethod java/util/Iterator.next:()Ljava/lang/Object;
      56: checkcast     #57                 // class java/util/Map$Entry
      59: astore        5
      61: aload_0
      62: getfield      #6                  // Field members:[Lorg/jgroups/Address;
      65: iload_3
      66: aload         5
      68: invokeinterface #58,  1           // InterfaceMethod java/util/Map$Entry.getKey:()Ljava/lang/Object;
      73: checkcast     #12                 // class org/jgroups/Address
      76: aastore
      77: aload_0
      78: getfield      #7                  // Field seqnos:[J
      81: iload_3
      82: iconst_2
      83: imul
      84: aload         5
      86: invokeinterface #59,  1           // InterfaceMethod java/util/Map$Entry.getValue:()Ljava/lang/Object;
      91: checkcast     #60                 // class "[J"
      94: iconst_0
      95: laload
      96: lastore
      97: aload_0
      98: getfield      #7                  // Field seqnos:[J
     101: iload_3
     102: iconst_2
     103: imul
     104: iconst_1
     105: iadd
     106: aload         5
     108: invokeinterface #59,  1           // InterfaceMethod java/util/Map$Entry.getValue:()Ljava/lang/Object;
     113: checkcast     #60                 // class "[J"
     116: iconst_1
     117: laload
     118: lastore
     119: iinc          3, 1
     122: goto          39
     125: return

  protected void checkPostcondition();
    Code:
       0: aload_0
       1: getfield      #6                  // Field members:[Lorg/jgroups/Address;
       4: arraylength
       5: istore_1
       6: iload_1
       7: iconst_2
       8: imul
       9: aload_0
      10: getfield      #7                  // Field seqnos:[J
      13: arraylength
      14: if_icmpeq     62
      17: new           #2                  // class java/lang/IllegalArgumentException
      20: dup
      21: new           #36                 // class java/lang/StringBuilder
      24: dup
      25: invokespecial #37                 // Method java/lang/StringBuilder."<init>":()V
      28: ldc           #61                 // String seqnos.length (
      30: invokevirtual #41                 // Method java/lang/StringBuilder.append:(Ljava/lang/String;)Ljava/lang/StringBuilder;
      33: aload_0
      34: getfield      #7                  // Field seqnos:[J
      37: arraylength
      38: invokevirtual #62                 // Method java/lang/StringBuilder.append:(I)Ljava/lang/StringBuilder;
      41: ldc           #63                 // String ) is not twice the members size (
      43: invokevirtual #41                 // Method java/lang/StringBuilder.append:(Ljava/lang/String;)Ljava/lang/StringBuilder;
      46: iload_1
      47: invokevirtual #62                 // Method java/lang/StringBuilder.append:(I)Ljava/lang/StringBuilder;
      50: ldc           #47                 // String )
      52: invokevirtual #41                 // Method java/lang/StringBuilder.append:(Ljava/lang/String;)Ljava/lang/StringBuilder;
      55: invokevirtual #51                 // Method java/lang/StringBuilder.toString:()Ljava/lang/String;
      58: invokespecial #4                  // Method java/lang/IllegalArgumentException."<init>":(Ljava/lang/String;)V
      61: athrow
      62: return
}
