Compiled from "ForwardQueue.java"
public class org.jgroups.util.ForwardQueue$Flusher extends java.lang.Thread {
  protected final org.jgroups.Address new_coord;

  final org.jgroups.util.ForwardQueue this$0;

  public org.jgroups.util.ForwardQueue$Flusher(org.jgroups.util.ForwardQueue, org.jgroups.Address);
    Code:
       0: aload_0
       1: aload_1
       2: putfield      #1                  // Field this$0:Lorg/jgroups/util/ForwardQueue;
       5: aload_0
       6: invokespecial #2                  // Method java/lang/Thread."<init>":()V
       9: aload_0
      10: aload_2
      11: putfield      #3                  // Field new_coord:Lorg/jgroups/Address;
      14: return

  public void run();
    Code:
       0: aload_0
       1: getfield      #1                  // Field this$0:Lorg/jgroups/util/ForwardQueue;
       4: aload_0
       5: getfield      #3                  // Field new_coord:Lorg/jgroups/Address;
       8: invokevirtual #4                  // Method org/jgroups/util/ForwardQueue.doFlush:(Lorg/jgroups/Address;)V
      11: goto          15
      14: astore_1
      15: return
    Exception table:
       from    to  target type
           0    11    14   Class java/lang/InterruptedException
}
