Compiled from "ImmutableReference.java"
public class org.jgroups.util.ImmutableReference<T> {
  private final T referent;

  public org.jgroups.util.ImmutableReference(T);
    Code:
       0: aload_0
       1: invokespecial #1                  // Method java/lang/Object."<init>":()V
       4: aload_0
       5: aload_1
       6: putfield      #2                  // Field referent:Ljava/lang/Object;
       9: return

  public T get();
    Code:
       0: aload_0
       1: getfield      #2                  // Field referent:Ljava/lang/Object;
       4: areturn
}
