Compiled from "SeqnoList.java"
public class org.jgroups.util.SeqnoList$SeqnoListIterator implements java.util.Iterator<java.lang.Long> {
  protected int index;

  final org.jgroups.util.SeqnoList this$0;

  protected org.jgroups.util.SeqnoList$SeqnoListIterator(org.jgroups.util.SeqnoList);
    Code:
       0: aload_0
       1: aload_1
       2: putfield      #1                  // Field this$0:Lorg/jgroups/util/SeqnoList;
       5: aload_0
       6: invokespecial #2                  // Method java/lang/Object."<init>":()V
       9: return

  public boolean hasNext();
    Code:
       0: aload_0
       1: getfield      #3                  // Field index:I
       4: aload_0
       5: getfield      #1                  // Field this$0:Lorg/jgroups/util/SeqnoList;
       8: getfield      #4                  // Field org/jgroups/util/SeqnoList.size:I
      11: if_icmpge     33
      14: aload_0
      15: getfield      #1                  // Field this$0:Lorg/jgroups/util/SeqnoList;
      18: aload_0
      19: getfield      #3                  // Field index:I
      22: invokevirtual #5                  // Method org/jgroups/util/SeqnoList.nextSetBit:(I)I
      25: iconst_m1
      26: if_icmpeq     33
      29: iconst_1
      30: goto          34
      33: iconst_0
      34: ireturn

  public java.lang.Long next();
    Code:
       0: aload_0
       1: getfield      #1                  // Field this$0:Lorg/jgroups/util/SeqnoList;
       4: aload_0
       5: getfield      #3                  // Field index:I
       8: invokevirtual #5                  // Method org/jgroups/util/SeqnoList.nextSetBit:(I)I
      11: istore_1
      12: iload_1
      13: iconst_m1
      14: if_icmpeq     28
      17: iload_1
      18: aload_0
      19: getfield      #1                  // Field this$0:Lorg/jgroups/util/SeqnoList;
      22: getfield      #4                  // Field org/jgroups/util/SeqnoList.size:I
      25: if_icmplt     55
      28: new           #6                  // class java/util/NoSuchElementException
      31: dup
      32: new           #7                  // class java/lang/StringBuilder
      35: dup
      36: invokespecial #8                  // Method java/lang/StringBuilder."<init>":()V
      39: ldc           #9                  // String index:
      41: invokevirtual #10                 // Method java/lang/StringBuilder.append:(Ljava/lang/String;)Ljava/lang/StringBuilder;
      44: iload_1
      45: invokevirtual #11                 // Method java/lang/StringBuilder.append:(I)Ljava/lang/StringBuilder;
      48: invokevirtual #12                 // Method java/lang/StringBuilder.toString:()Ljava/lang/String;
      51: invokespecial #13                 // Method java/util/NoSuchElementException."<init>":(Ljava/lang/String;)V
      54: athrow
      55: aload_0
      56: iload_1
      57: iconst_1
      58: iadd
      59: putfield      #3                  // Field index:I
      62: aload_0
      63: getfield      #1                  // Field this$0:Lorg/jgroups/util/SeqnoList;
      66: iload_1
      67: invokevirtual #14                 // Method org/jgroups/util/SeqnoList.seqno:(I)J
      70: invokestatic  #15                 // Method java/lang/Long.valueOf:(J)Ljava/lang/Long;
      73: areturn

  public void remove();
    Code:
       0: return

  public java.lang.Object next();
    Code:
       0: aload_0
       1: invokevirtual #16                 // Method next:()Ljava/lang/Long;
       4: areturn
}
