Compiled from "SuppressCache.java"
public final class org.jgroups.util.SuppressCache$Value {
  protected final long timestamp;

  protected int count;

  public org.jgroups.util.SuppressCache$Value();
    Code:
       0: aload_0
       1: invokespecial #1                  // Method java/lang/Object."<init>":()V
       4: aload_0
       5: invokestatic  #2                  // Method java/lang/System.currentTimeMillis:()J
       8: putfield      #3                  // Field timestamp:J
      11: aload_0
      12: iconst_1
      13: putfield      #4                  // Field count:I
      16: return

  public long age();
    Code:
       0: invokestatic  #2                  // Method java/lang/System.currentTimeMillis:()J
       3: aload_0
       4: getfield      #3                  // Field timestamp:J
       7: lsub
       8: lreturn

  public synchronized org.jgroups.util.SuppressCache$Value update();
    Code:
       0: aload_0
       1: dup
       2: getfield      #4                  // Field count:I
       5: iconst_1
       6: iadd
       7: putfield      #4                  // Field count:I
      10: aload_0
      11: areturn

  public int count();
    Code:
       0: aload_0
       1: getfield      #4                  // Field count:I
       4: ireturn

  public java.lang.String toString();
    Code:
       0: new           #5                  // class java/lang/StringBuilder
       3: dup
       4: invokespecial #6                  // Method java/lang/StringBuilder."<init>":()V
       7: aload_0
       8: getfield      #4                  // Field count:I
      11: invokevirtual #7                  // Method java/lang/StringBuilder.append:(I)Ljava/lang/StringBuilder;
      14: ldc           #8                  // String  update(s) in
      16: invokevirtual #9                  // Method java/lang/StringBuilder.append:(Ljava/lang/String;)Ljava/lang/StringBuilder;
      19: aload_0
      20: invokevirtual #10                 // Method age:()J
      23: invokevirtual #11                 // Method java/lang/StringBuilder.append:(J)Ljava/lang/StringBuilder;
      26: ldc           #12                 // String  ms
      28: invokevirtual #9                  // Method java/lang/StringBuilder.append:(Ljava/lang/String;)Ljava/lang/StringBuilder;
      31: invokevirtual #13                 // Method java/lang/StringBuilder.toString:()Ljava/lang/String;
      34: areturn
}
