Compiled from "Table.java"
public class org.jgroups.util.Table$Dump implements org.jgroups.util.Table$Visitor<T> {
  protected final java.lang.StringBuilder sb;

  protected boolean first;

  final org.jgroups.util.Table this$0;

  protected org.jgroups.util.Table$Dump(org.jgroups.util.Table);
    Code:
       0: aload_0
       1: aload_1
       2: putfield      #1                  // Field this$0:Lorg/jgroups/util/Table;
       5: aload_0
       6: invokespecial #2                  // Method java/lang/Object."<init>":()V
       9: aload_0
      10: new           #3                  // class java/lang/StringBuilder
      13: dup
      14: invokespecial #4                  // Method java/lang/StringBuilder."<init>":()V
      17: putfield      #5                  // Field sb:Ljava/lang/StringBuilder;
      20: aload_0
      21: iconst_1
      22: putfield      #6                  // Field first:Z
      25: return

  protected java.lang.String getResult();
    Code:
       0: aload_0
       1: getfield      #5                  // Field sb:Ljava/lang/StringBuilder;
       4: invokevirtual #7                  // Method java/lang/StringBuilder.toString:()Ljava/lang/String;
       7: areturn

  public boolean visit(long, T, int, int);
    Code:
       0: aload_3
       1: ifnull        38
       4: aload_0
       5: getfield      #6                  // Field first:Z
       8: ifeq          19
      11: aload_0
      12: iconst_0
      13: putfield      #6                  // Field first:Z
      16: goto          29
      19: aload_0
      20: getfield      #5                  // Field sb:Ljava/lang/StringBuilder;
      23: ldc           #8                  // String ,
      25: invokevirtual #9                  // Method java/lang/StringBuilder.append:(Ljava/lang/String;)Ljava/lang/StringBuilder;
      28: pop
      29: aload_0
      30: getfield      #5                  // Field sb:Ljava/lang/StringBuilder;
      33: lload_1
      34: invokevirtual #10                 // Method java/lang/StringBuilder.append:(J)Ljava/lang/StringBuilder;
      37: pop
      38: iconst_1
      39: ireturn
}
