Compiled from "TransactionalInterceptorNotSupported.java"
public class com.arjuna.ats.jta.cdi.transactional.TransactionalInterceptorNotSupported extends com.arjuna.ats.jta.cdi.transactional.TransactionalInterceptorBase {
  public com.arjuna.ats.jta.cdi.transactional.TransactionalInterceptorNotSupported();
    Code:
       0: aload_0
       1: iconst_1
       2: invokespecial #1                  // Method com/arjuna/ats/jta/cdi/transactional/TransactionalInterceptorBase."<init>":(Z)V
       5: return

  public java.lang.Object intercept(javax.interceptor.InvocationContext) throws java.lang.Exception;
    Code:
       0: aload_0
       1: aload_1
       2: invokespecial #2                  // Method com/arjuna/ats/jta/cdi/transactional/TransactionalInterceptorBase.intercept:(Ljavax/interceptor/InvocationContext;)Ljava/lang/Object;
       5: areturn

  protected java.lang.Object doIntercept(javax.transaction.TransactionManager, javax.transaction.Transaction, javax.interceptor.InvocationContext) throws java.lang.Exception;
    Code:
       0: aload_2
       1: ifnull        40
       4: aload_1
       5: invokeinterface #3,  1            // InterfaceMethod javax/transaction/TransactionManager.suspend:()Ljavax/transaction/Transaction;
      10: pop
      11: aload_0
      12: aload_3
      13: invokevirtual #4                  // Method invokeInNoTx:(Ljavax/interceptor/InvocationContext;)Ljava/lang/Object;
      16: astore        4
      18: aload_1
      19: aload_2
      20: invokeinterface #5,  2            // InterfaceMethod javax/transaction/TransactionManager.resume:(Ljavax/transaction/Transaction;)V
      25: aload         4
      27: areturn
      28: astore        5
      30: aload_1
      31: aload_2
      32: invokeinterface #5,  2            // InterfaceMethod javax/transaction/TransactionManager.resume:(Ljavax/transaction/Transaction;)V
      37: aload         5
      39: athrow
      40: aload_0
      41: aload_3
      42: invokevirtual #4                  // Method invokeInNoTx:(Ljavax/interceptor/InvocationContext;)Ljava/lang/Object;
      45: areturn
    Exception table:
       from    to  target type
          11    18    28   any
          28    30    28   any
}
