Compiled from "RSocketStrategiesAutoConfiguration.java"
public class org.springframework.boot.autoconfigure.rsocket.RSocketStrategiesAutoConfiguration$JacksonCborStrategyConfiguration {
  private static final org.springframework.http.MediaType[] SUPPORTED_TYPES;

  protected org.springframework.boot.autoconfigure.rsocket.RSocketStrategiesAutoConfiguration$JacksonCborStrategyConfiguration();
    Code:
       0: aload_0
       1: invokespecial #1                  // Method java/lang/Object."<init>":()V
       4: return

  public org.springframework.boot.rsocket.messaging.RSocketStrategiesCustomizer jacksonCborRSocketStrategyCustomizer(org.springframework.http.converter.json.Jackson2ObjectMapperBuilder);
    Code:
       0: aload_1
       1: invokedynamic #2,  0              // InvokeDynamic #0:customize:(Lorg/springframework/http/converter/json/Jackson2ObjectMapperBuilder;)Lorg/springframework/boot/rsocket/messaging/RSocketStrategiesCustomizer;
       6: areturn

  private static void lambda$jacksonCborRSocketStrategyCustomizer$0(org.springframework.http.converter.json.Jackson2ObjectMapperBuilder, org.springframework.messaging.rsocket.RSocketStrategies$Builder);
    Code:
       0: aload_0
       1: iconst_0
       2: invokevirtual #3                  // Method org/springframework/http/converter/json/Jackson2ObjectMapperBuilder.createXmlMapper:(Z)Lorg/springframework/http/converter/json/Jackson2ObjectMapperBuilder;
       5: new           #4                  // class com/fasterxml/jackson/dataformat/cbor/CBORFactory
       8: dup
       9: invokespecial #5                  // Method com/fasterxml/jackson/dataformat/cbor/CBORFactory."<init>":()V
      12: invokevirtual #6                  // Method org/springframework/http/converter/json/Jackson2ObjectMapperBuilder.factory:(Lcom/fasterxml/jackson/core/JsonFactory;)Lorg/springframework/http/converter/json/Jackson2ObjectMapperBuilder;
      15: invokevirtual #7                  // Method org/springframework/http/converter/json/Jackson2ObjectMapperBuilder.build:()Lcom/fasterxml/jackson/databind/ObjectMapper;
      18: astore_2
      19: aload_1
      20: iconst_1
      21: anewarray     #8                  // class org/springframework/core/codec/Decoder
      24: dup
      25: iconst_0
      26: new           #9                  // class org/springframework/http/codec/cbor/Jackson2CborDecoder
      29: dup
      30: aload_2
      31: getstatic     #10                 // Field SUPPORTED_TYPES:[Lorg/springframework/http/MediaType;
      34: invokespecial #11                 // Method org/springframework/http/codec/cbor/Jackson2CborDecoder."<init>":(Lcom/fasterxml/jackson/databind/ObjectMapper;[Lorg/springframework/util/MimeType;)V
      37: aastore
      38: invokeinterface #12,  2           // InterfaceMethod org/springframework/messaging/rsocket/RSocketStrategies$Builder.decoder:([Lorg/springframework/core/codec/Decoder;)Lorg/springframework/messaging/rsocket/RSocketStrategies$Builder;
      43: pop
      44: aload_1
      45: iconst_1
      46: anewarray     #13                 // class org/springframework/core/codec/Encoder
      49: dup
      50: iconst_0
      51: new           #14                 // class org/springframework/http/codec/cbor/Jackson2CborEncoder
      54: dup
      55: aload_2
      56: getstatic     #10                 // Field SUPPORTED_TYPES:[Lorg/springframework/http/MediaType;
      59: invokespecial #15                 // Method org/springframework/http/codec/cbor/Jackson2CborEncoder."<init>":(Lcom/fasterxml/jackson/databind/ObjectMapper;[Lorg/springframework/util/MimeType;)V
      62: aastore
      63: invokeinterface #16,  2           // InterfaceMethod org/springframework/messaging/rsocket/RSocketStrategies$Builder.encoder:([Lorg/springframework/core/codec/Encoder;)Lorg/springframework/messaging/rsocket/RSocketStrategies$Builder;
      68: pop
      69: return

  static {};
    Code:
       0: iconst_1
       1: anewarray     #17                 // class org/springframework/http/MediaType
       4: dup
       5: iconst_0
       6: getstatic     #18                 // Field org/springframework/http/MediaType.APPLICATION_CBOR:Lorg/springframework/http/MediaType;
       9: aastore
      10: putstatic     #10                 // Field SUPPORTED_TYPES:[Lorg/springframework/http/MediaType;
      13: return
}
