Compiled from "JoinBatch.java"
final class org.h2.table.JoinBatch$1 implements org.h2.index.Cursor {
  org.h2.table.JoinBatch$1();
    Code:
       0: aload_0
       1: invokespecial #1                  // Method java/lang/Object."<init>":()V
       4: return

  public boolean previous();
    Code:
       0: iconst_0
       1: ireturn

  public boolean next();
    Code:
       0: iconst_0
       1: ireturn

  public org.h2.result.SearchRow getSearchRow();
    Code:
       0: aconst_null
       1: areturn

  public org.h2.result.Row get();
    Code:
       0: aconst_null
       1: areturn

  public java.lang.String toString();
    Code:
       0: ldc           #2                  // String EMPTY_CURSOR
       2: areturn
}
