Compiled from "AsRequestWithPasswd.java"
public class org.apache.kerby.kerberos.kerb.client.request.AsRequestWithPasswd extends org.apache.kerby.kerberos.kerb.client.request.AsRequest {
  public org.apache.kerby.kerberos.kerb.client.request.AsRequestWithPasswd(org.apache.kerby.kerberos.kerb.client.KrbContext);
    Code:
       0: aload_0
       1: aload_1
       2: invokespecial #1                  // Method org/apache/kerby/kerberos/kerb/client/request/AsRequest."<init>":(Lorg/apache/kerby/kerberos/kerb/client/KrbContext;)V
       5: aload_0
       6: getstatic     #2                  // Field org/apache/kerby/kerberos/kerb/type/pa/PaDataType.ENC_TIMESTAMP:Lorg/apache/kerby/kerberos/kerb/type/pa/PaDataType;
       9: invokevirtual #3                  // Method setAllowedPreauth:(Lorg/apache/kerby/kerberos/kerb/type/pa/PaDataType;)V
      12: return

  public java.lang.String getPassword();
    Code:
       0: aload_0
       1: invokevirtual #4                  // Method getRequestOptions:()Lorg/apache/kerby/KOptions;
       4: getstatic     #5                  // Field org/apache/kerby/kerberos/kerb/client/KrbOption.USER_PASSWD:Lorg/apache/kerby/kerberos/kerb/client/KrbOption;
       7: invokevirtual #6                  // Method org/apache/kerby/KOptions.getStringOption:(Lorg/apache/kerby/KOption;)Ljava/lang/String;
      10: areturn

  public org.apache.kerby.kerberos.kerb.type.base.EncryptionKey getClientKey() throws org.apache.kerby.kerberos.kerb.KrbException;
    Code:
       0: aload_0
       1: invokespecial #7                  // Method org/apache/kerby/kerberos/kerb/client/request/AsRequest.getClientKey:()Lorg/apache/kerby/kerberos/kerb/type/base/EncryptionKey;
       4: ifnonnull     31
       7: aload_0
       8: invokevirtual #8                  // Method getClientPrincipal:()Lorg/apache/kerby/kerberos/kerb/type/base/PrincipalName;
      11: invokevirtual #9                  // Method org/apache/kerby/kerberos/kerb/type/base/PrincipalName.getName:()Ljava/lang/String;
      14: aload_0
      15: invokevirtual #10                 // Method getPassword:()Ljava/lang/String;
      18: aload_0
      19: invokevirtual #11                 // Method getChosenEncryptionType:()Lorg/apache/kerby/kerberos/kerb/type/base/EncryptionType;
      22: invokestatic  #12                 // Method org/apache/kerby/kerberos/kerb/crypto/EncryptionHandler.string2Key:(Ljava/lang/String;Ljava/lang/String;Lorg/apache/kerby/kerberos/kerb/type/base/EncryptionType;)Lorg/apache/kerby/kerberos/kerb/type/base/EncryptionKey;
      25: astore_1
      26: aload_0
      27: aload_1
      28: invokevirtual #13                 // Method setClientKey:(Lorg/apache/kerby/kerberos/kerb/type/base/EncryptionKey;)V
      31: aload_0
      32: invokespecial #7                  // Method org/apache/kerby/kerberos/kerb/client/request/AsRequest.getClientKey:()Lorg/apache/kerby/kerberos/kerb/type/base/EncryptionKey;
      35: areturn
}
