Compiled from "TgsRequestWithTgt.java"
public class org.apache.kerby.kerberos.kerb.client.request.TgsRequestWithTgt extends org.apache.kerby.kerberos.kerb.client.request.TgsRequest {
  private org.apache.kerby.kerberos.kerb.type.ticket.TgtTicket tgt;

  private org.apache.kerby.kerberos.kerb.type.ap.ApReq apReq;

  public org.apache.kerby.kerberos.kerb.client.request.TgsRequestWithTgt(org.apache.kerby.kerberos.kerb.client.KrbContext, org.apache.kerby.kerberos.kerb.type.ticket.TgtTicket);
    Code:
       0: aload_0
       1: aload_1
       2: invokespecial #1                  // Method org/apache/kerby/kerberos/kerb/client/request/TgsRequest."<init>":(Lorg/apache/kerby/kerberos/kerb/client/KrbContext;)V
       5: aload_0
       6: aload_2
       7: putfield      #2                  // Field tgt:Lorg/apache/kerby/kerberos/kerb/type/ticket/TgtTicket;
      10: aload_0
      11: getstatic     #3                  // Field org/apache/kerby/kerberos/kerb/type/pa/PaDataType.TGS_REQ:Lorg/apache/kerby/kerberos/kerb/type/pa/PaDataType;
      14: invokevirtual #4                  // Method setAllowedPreauth:(Lorg/apache/kerby/kerberos/kerb/type/pa/PaDataType;)V
      17: return

  public org.apache.kerby.kerberos.kerb.type.base.PrincipalName getClientPrincipal();
    Code:
       0: aload_0
       1: getfield      #2                  // Field tgt:Lorg/apache/kerby/kerberos/kerb/type/ticket/TgtTicket;
       4: invokevirtual #5                  // Method org/apache/kerby/kerberos/kerb/type/ticket/TgtTicket.getClientPrincipal:()Lorg/apache/kerby/kerberos/kerb/type/base/PrincipalName;
       7: areturn

  public org.apache.kerby.kerberos.kerb.type.base.EncryptionKey getClientKey() throws org.apache.kerby.kerberos.kerb.KrbException;
    Code:
       0: aload_0
       1: invokevirtual #6                  // Method getSessionKey:()Lorg/apache/kerby/kerberos/kerb/type/base/EncryptionKey;
       4: areturn

  public org.apache.kerby.kerberos.kerb.type.base.EncryptionKey getSessionKey();
    Code:
       0: aload_0
       1: getfield      #2                  // Field tgt:Lorg/apache/kerby/kerberos/kerb/type/ticket/TgtTicket;
       4: invokevirtual #7                  // Method org/apache/kerby/kerberos/kerb/type/ticket/TgtTicket.getSessionKey:()Lorg/apache/kerby/kerberos/kerb/type/base/EncryptionKey;
       7: areturn

  private org.apache.kerby.kerberos.kerb.type.ap.ApReq makeApReq() throws org.apache.kerby.kerberos.kerb.KrbException;
    Code:
       0: new           #8                  // class org/apache/kerby/kerberos/kerb/type/ap/ApReq
       3: dup
       4: invokespecial #9                  // Method org/apache/kerby/kerberos/kerb/type/ap/ApReq."<init>":()V
       7: astore_1
       8: aload_0
       9: invokespecial #10                 // Method makeAuthenticator:()Lorg/apache/kerby/kerberos/kerb/type/ap/Authenticator;
      12: astore_2
      13: aload_0
      14: getfield      #2                  // Field tgt:Lorg/apache/kerby/kerberos/kerb/type/ticket/TgtTicket;
      17: invokevirtual #7                  // Method org/apache/kerby/kerberos/kerb/type/ticket/TgtTicket.getSessionKey:()Lorg/apache/kerby/kerberos/kerb/type/base/EncryptionKey;
      20: astore_3
      21: aload_2
      22: aload_3
      23: getstatic     #11                 // Field org/apache/kerby/kerberos/kerb/type/base/KeyUsage.TGS_REQ_AUTH:Lorg/apache/kerby/kerberos/kerb/type/base/KeyUsage;
      26: invokestatic  #12                 // Method org/apache/kerby/kerberos/kerb/common/EncryptionUtil.seal:(Lorg/apache/kerby/asn1/type/Asn1Encodeable;Lorg/apache/kerby/kerberos/kerb/type/base/EncryptionKey;Lorg/apache/kerby/kerberos/kerb/type/base/KeyUsage;)Lorg/apache/kerby/kerberos/kerb/type/base/EncryptedData;
      29: astore        4
      31: aload_1
      32: aload         4
      34: invokevirtual #13                 // Method org/apache/kerby/kerberos/kerb/type/ap/ApReq.setEncryptedAuthenticator:(Lorg/apache/kerby/kerberos/kerb/type/base/EncryptedData;)V
      37: aload_1
      38: aload_2
      39: invokevirtual #14                 // Method org/apache/kerby/kerberos/kerb/type/ap/ApReq.setAuthenticator:(Lorg/apache/kerby/kerberos/kerb/type/ap/Authenticator;)V
      42: aload_1
      43: aload_0
      44: getfield      #2                  // Field tgt:Lorg/apache/kerby/kerberos/kerb/type/ticket/TgtTicket;
      47: invokevirtual #15                 // Method org/apache/kerby/kerberos/kerb/type/ticket/TgtTicket.getTicket:()Lorg/apache/kerby/kerberos/kerb/type/ticket/Ticket;
      50: invokevirtual #16                 // Method org/apache/kerby/kerberos/kerb/type/ap/ApReq.setTicket:(Lorg/apache/kerby/kerberos/kerb/type/ticket/Ticket;)V
      53: new           #17                 // class org/apache/kerby/kerberos/kerb/type/ap/ApOptions
      56: dup
      57: invokespecial #18                 // Method org/apache/kerby/kerberos/kerb/type/ap/ApOptions."<init>":()V
      60: astore        5
      62: aload_1
      63: aload         5
      65: invokevirtual #19                 // Method org/apache/kerby/kerberos/kerb/type/ap/ApReq.setApOptions:(Lorg/apache/kerby/kerberos/kerb/type/ap/ApOptions;)V
      68: aload_1
      69: areturn

  public org.apache.kerby.kerberos.kerb.type.ap.ApReq getApReq() throws org.apache.kerby.kerberos.kerb.KrbException;
    Code:
       0: aload_0
       1: getfield      #20                 // Field apReq:Lorg/apache/kerby/kerberos/kerb/type/ap/ApReq;
       4: ifnonnull     15
       7: aload_0
       8: aload_0
       9: invokespecial #21                 // Method makeApReq:()Lorg/apache/kerby/kerberos/kerb/type/ap/ApReq;
      12: putfield      #20                 // Field apReq:Lorg/apache/kerby/kerberos/kerb/type/ap/ApReq;
      15: aload_0
      16: getfield      #20                 // Field apReq:Lorg/apache/kerby/kerberos/kerb/type/ap/ApReq;
      19: areturn

  private org.apache.kerby.kerberos.kerb.type.ap.Authenticator makeAuthenticator() throws org.apache.kerby.kerberos.kerb.KrbException;
    Code:
       0: new           #22                 // class org/apache/kerby/kerberos/kerb/type/ap/Authenticator
       3: dup
       4: invokespecial #23                 // Method org/apache/kerby/kerberos/kerb/type/ap/Authenticator."<init>":()V
       7: astore_1
       8: aload_1
       9: iconst_5
      10: invokevirtual #24                 // Method org/apache/kerby/kerberos/kerb/type/ap/Authenticator.setAuthenticatorVno:(I)V
      13: aload_1
      14: aload_0
      15: getfield      #2                  // Field tgt:Lorg/apache/kerby/kerberos/kerb/type/ticket/TgtTicket;
      18: invokevirtual #5                  // Method org/apache/kerby/kerberos/kerb/type/ticket/TgtTicket.getClientPrincipal:()Lorg/apache/kerby/kerberos/kerb/type/base/PrincipalName;
      21: invokevirtual #25                 // Method org/apache/kerby/kerberos/kerb/type/ap/Authenticator.setCname:(Lorg/apache/kerby/kerberos/kerb/type/base/PrincipalName;)V
      24: aload_1
      25: aload_0
      26: getfield      #2                  // Field tgt:Lorg/apache/kerby/kerberos/kerb/type/ticket/TgtTicket;
      29: invokevirtual #26                 // Method org/apache/kerby/kerberos/kerb/type/ticket/TgtTicket.getRealm:()Ljava/lang/String;
      32: invokevirtual #27                 // Method org/apache/kerby/kerberos/kerb/type/ap/Authenticator.setCrealm:(Ljava/lang/String;)V
      35: aload_1
      36: invokestatic  #28                 // Method org/apache/kerby/kerberos/kerb/type/KerberosTime.now:()Lorg/apache/kerby/kerberos/kerb/type/KerberosTime;
      39: invokevirtual #29                 // Method org/apache/kerby/kerberos/kerb/type/ap/Authenticator.setCtime:(Lorg/apache/kerby/kerberos/kerb/type/KerberosTime;)V
      42: aload_1
      43: iconst_0
      44: invokevirtual #30                 // Method org/apache/kerby/kerberos/kerb/type/ap/Authenticator.setCusec:(I)V
      47: aload_1
      48: aload_0
      49: getfield      #2                  // Field tgt:Lorg/apache/kerby/kerberos/kerb/type/ticket/TgtTicket;
      52: invokevirtual #7                  // Method org/apache/kerby/kerberos/kerb/type/ticket/TgtTicket.getSessionKey:()Lorg/apache/kerby/kerberos/kerb/type/base/EncryptionKey;
      55: invokevirtual #31                 // Method org/apache/kerby/kerberos/kerb/type/ap/Authenticator.setSubKey:(Lorg/apache/kerby/kerberos/kerb/type/base/EncryptionKey;)V
      58: aconst_null
      59: astore_2
      60: aload_0
      61: invokevirtual #32                 // Method getRequestOptions:()Lorg/apache/kerby/KOptions;
      64: getstatic     #33                 // Field org/apache/kerby/kerberos/kerb/client/KrbKdcOption.RENEW:Lorg/apache/kerby/kerberos/kerb/client/KrbKdcOption;
      67: invokevirtual #34                 // Method org/apache/kerby/KOptions.contains:(Lorg/apache/kerby/KOption;)Z
      70: ifeq          84
      73: aload_0
      74: getfield      #2                  // Field tgt:Lorg/apache/kerby/kerberos/kerb/type/ticket/TgtTicket;
      77: invokevirtual #35                 // Method org/apache/kerby/kerberos/kerb/type/ticket/TgtTicket.getEncKdcRepPart:()Lorg/apache/kerby/kerberos/kerb/type/kdc/EncKdcRepPart;
      80: invokevirtual #36                 // Method org/apache/kerby/kerberos/kerb/type/kdc/EncKdcRepPart.getRenewTill:()Lorg/apache/kerby/kerberos/kerb/type/KerberosTime;
      83: astore_2
      84: aload_0
      85: aload_2
      86: invokevirtual #37                 // Method getReqBody:(Lorg/apache/kerby/kerberos/kerb/type/KerberosTime;)Lorg/apache/kerby/kerberos/kerb/type/kdc/KdcReqBody;
      89: astore_3
      90: aload_3
      91: aconst_null
      92: aload_0
      93: getfield      #2                  // Field tgt:Lorg/apache/kerby/kerberos/kerb/type/ticket/TgtTicket;
      96: invokevirtual #7                  // Method org/apache/kerby/kerberos/kerb/type/ticket/TgtTicket.getSessionKey:()Lorg/apache/kerby/kerberos/kerb/type/base/EncryptionKey;
      99: getstatic     #38                 // Field org/apache/kerby/kerberos/kerb/type/base/KeyUsage.TGS_REQ_AUTH_CKSUM:Lorg/apache/kerby/kerberos/kerb/type/base/KeyUsage;
     102: invokestatic  #39                 // Method org/apache/kerby/kerberos/kerb/common/CheckSumUtil.seal:(Lorg/apache/kerby/asn1/type/Asn1Encodeable;Lorg/apache/kerby/kerberos/kerb/type/base/CheckSumType;Lorg/apache/kerby/kerberos/kerb/type/base/EncryptionKey;Lorg/apache/kerby/kerberos/kerb/type/base/KeyUsage;)Lorg/apache/kerby/kerberos/kerb/type/base/CheckSum;
     105: astore        4
     107: aload_1
     108: aload         4
     110: invokevirtual #40                 // Method org/apache/kerby/kerberos/kerb/type/ap/Authenticator.setCksum:(Lorg/apache/kerby/kerberos/kerb/type/base/CheckSum;)V
     113: aload_1
     114: areturn
}
